Workbook

Sheet Executive Summary
B1: DISCLAIMER: This is a sample analysis for demonstration purposes only. It does not constitute investment advice.
B3: M&A Accretion / Dilution Analysis
B4: Headwaters Inc. (4011.T) x BBD Initiative Inc. (5259.T)
B6: Transaction Summary
B7: Acquirer | C7: Headwaters Inc. (4011.T)
B8: Target | C8: BBD Initiative Inc. (5259.T)
B9: Transaction Type | C9: Absorption Merger (Stock-for-Stock)
B10: Merger Ratio | C10: 0.5
B11: Deal Value (est.) | C11: ¥6,521 mn
B12: Announcement Date | C12: 2026-01-26
B13: Effective Date | C13: 2026-05-01 (planned)
B15: EPS Impact Summary (FY2026E)
C16: Scenario A (Base) | D16: Scenario B (Downside) | E16: Scenario C (Synergy 20%) | F16: Unit
B17: HW Standalone EPS | C17: 60.1 | D17: 60.1 | E17: 60.1 | F17: JPY
B18: Pro Forma EPS (Diluted) | C18: 36.5 | D18: -3.7 | E18: 39.1 | F18: JPY
B19: Accretion / (Dilution) | C19: -0.37 | D19: -1.064 | E19: -0.326 | F19: %
B20: Break-Even Synergy | C20: 131 | D20: 377 | E20: n/a | F20: JPY mn
B22: Key Observations
B23: 1. The transaction is dilutive under all scenarios due to the increase in share count.
B24: 2. Scenario B assumes BBD's FY2025 operating loss continues (¥-245.7 mn contribution).
B25: 3. 20% revenue synergy (Scenario C) reduces dilution to -32.6% but does not achieve accretion.
B26: 4. Break-even synergy of ¥131 mn (Base) represents ~2.3% of combined revenue.
B28: Analyst View
B29: This merger is structurally dilutive in the short term and represents a high-risk, high-reward transaction for HW shareholders. The critical question is whether HW can convert BBD's SaaS customer base (ARR ¥1,640mn) into an AI-driven revenue stream fast enough to offset the 58.8% share dilution.
B30: With BBD's FY2025 operating loss at ¥-351mn and goodwill amortization consuming ¥167mn/year after tax, HW needs at least ¥131mn in annual synergies just to maintain pre-merger EPS levels. Failure to reach this threshold results in persistent EPS dilution. Moreover, if BBD's business turnaround stalls and its recoverable value falls below the carrying amount including ¥4,763mn of goodwill, impairment losses could materialize — delivering a double impact on enterprise value through both ongoing operating losses and a one-time write-down.
B31: On the upside, BBD's recurring subscription base provides a stable foundation for AI integration, and the combined entity could establish a dominant position in Japan's emerging AX (AI Transformation) market. The reward is significant if execution succeeds, but the margin for error is narrow.

Sheet Transaction Overview
B1: Transaction Overview
B3: Share Calculation
C4: Shares | D4: Notes
B5: BBD Total Outstanding Shares | C5: 6120221 | D5: As of latest filing
B6: Less: HW Holdings in BBD | C6: 1599100 | D6: Acquirer's existing stake
B7: Less: BBD Treasury Shares | C7: 296 | D7: Treasury stock
B8: Shares Subject to Merger | C8: =C5-C6-C7 | D8: =Outstanding - HW Holdings - Treasury
B9: Merger Ratio (HW : BBD) | C9: 0.5 | D9: 1 BBD share = 0.50 HW share
B10: New HW Shares Issued | C10: =C8*C9 | D10: =Subject Shares x Ratio
B12: HW Pre-Merger Shares Outstanding | C12: 3844144 | D12: Before merger
B13: New HW Shares Issued (from above) | C13: =C10 | D13: Cross-ref
B14: Post-Merger Shares Outstanding | C14: =C12+C13 | D14: =Pre-Merger + New Shares
B15: Stock Options Outstanding | C15: 399200 | D15: Dilutive securities
B16: Fully Diluted Shares | C16: =C14+C15 | D16: =Post-Merger + Options
B18: Premium / (Discount) Analysis
C19: Price (JPY) | D19: Premium / (Discount)
B20: HW Share Price (Current) | C20: 2885
B21: Merger Ratio | C21: =C9
B22: Implied Consideration per BBD Share | C22: =C20*C21
B24: BBD Pre-Announcement Price | C24: 1591 | D24: Premium vs Pre-Announce
B25: Premium / (Discount) vs Pre-Announce | C25: =C22/C24-1
B27: BBD Current Price | C27: 1194
B28: Premium / (Discount) vs Current | C28: =C22/C27-1
B30: Implied Deal Value (mn JPY) | C30: =C22*C8/1000000

Sheet Pre-Deal Financials
B1: Pre-Deal Standalone Financials
B3: Headwaters Inc. (4011.T) — Acquirer
B4: (JPY mn) | C4: FY2024 | D4: FY2025 | E4: FY2026E
B5: Revenue | C5: 2905 | D5: 3900 | E5: 5764
B6: Operating Income | C6: 307 | D6: 229 | E6: 436
B7: D&A | C7: 20 | D7: 27
B8: EBITDA | C8: =C6+C7 | D8: =D6+D7
B9: Net Income | C9: 272 | D9: 58 | E9: 223
B11: Shares Outstanding | E11: 3844144
B12: EPS (JPY) | C12: 72 | D12: 15.3 | E12: =E9/E11*1000000
B14: Share Price (JPY) | D14: Current | E14: 2885
B15: Market Cap (mn JPY) | E15: =E11*E14/1000000
B17: BBD Initiative Inc. (5259.T) — Target
B18: (JPY mn) | C18: FY2024 | D18: FY2025 | E18: FY2026E
B19: Revenue | C19: 4131 | D19: 4399 | E19: 4803
B20: Operating Income | C20: 273 | D20: -351
B21: D&A | C21: 312 | D21: 342
B22: EBITDA | C22: =C20+C21 | D22: =D20+D21
B23: Net Income | C23: 156 | D23: 1750 | E23: * Includes extraordinary gain
B25: Shares Outstanding | E25: 6120221
B26: EPS (JPY) | C26: 31.2 | D26: -63.6
B28: Share Price (JPY) | D28: Current | E28: 1194
B29: Market Cap (mn JPY) | E29: =E25*E28/1000000

Sheet Pro Forma EPS
B1: Pro Forma EPS — Accretion / Dilution Analysis
B3: Key Assumptions (FY2026E)
C4: Scenario A (Base) | D4: Scenario B (Downside) | E4: Scenario C (Synergy)
B5: HW Net Income (mn JPY) | C5: ='Pre-Deal Financials'!E9 | D5: ='Pre-Deal Financials'!E9 | E5: ='Pre-Deal Financials'!E9
B6: BBD Contribution to NI (mn JPY) | C6: 0 | D6: -245.7 | E6: 0
B7: Revenue Synergy (%) | C7: 0 | D7: 0 | E7: 0.2
B8: Combined Revenue Base (mn JPY) | C8: ='Pre-Deal Financials'!E5+'Pre-Deal Financials'!E19 | D8: ='Pre-Deal Financials'!E5+'Pre-Deal Financials'!E19 | E8: ='Pre-Deal Financials'!E5+'Pre-Deal Financials'!E19
B9: Synergy Amount (mn JPY) | C9: =C5*C7 | D9: =D5*D7 | E9: =E5*E7
B10: Tax Rate on Synergies | C10: 0.3 | D10: 0.3 | E10: 0.3
B11: After-Tax Synergy (mn JPY) | C11: =C9*(1-C10) | D11: =D9*(1-D10) | E11: =E9*(1-E10)
B13: Share Count (from Transaction Overview)
B14: HW Pre-Merger Shares | C14: ='Transaction Overview'!C12
B15: Post-Merger Shares | C15: ='Transaction Overview'!C14
B16: Fully Diluted Shares | C16: ='Transaction Overview'!C16
B18: Pro Forma EPS Calculation
C19: Scenario A (Base) | D19: Scenario B (Downside) | E19: Scenario C (Synergy)
B20: Pro Forma Net Income (mn JPY) | C20: =C5+C6+C11 | D20: =D5+D6+D11 | E20: =E5+E6+E11
B21: PF EPS — Basic (JPY) | C21: =C20/$C$15*1000000 | D21: =D20/$C$15*1000000 | E21: =E20/$C$15*1000000
B22: PF EPS — Diluted (JPY) | C22: =C20/$C$16*1000000 | D22: =D20/$C$16*1000000 | E22: =E20/$C$16*1000000
B24: HW Standalone EPS (JPY) | C24: =C5/$C$14*1000000 | D24: =D5/$C$14*1000000 | E24: =E5/$C$14*1000000
B25: Accretion / (Dilution) (JPY) | C25: =C22-C24 | D25: =D22-D24 | E25: =E22-E24
B26: Accretion / (Dilution) (%) | C26: =C22/C24-1 | D26: =D22/D24-1 | E26: =E22/E24-1
B28: Break-Even Synergy Analysis
B29: Required PF NI to match Standalone EPS (mn) | C29: =C24*$C$16/1000000 | D29: =D24*$C$16/1000000
B30: Less: HW NI + BBD Contribution (mn) | C30: =C5+C6 | D30: =D5+D6
B31: Break-Even Pre-Tax Synergy (mn JPY) | C31: =(C29-C30)/(1-C10) | D31: =(D29-D30)/(1-D10) | E31: n/a (already has synergy)

Sheet Transaction Multiples
B1: Transaction Multiples
B3: Deal Value Calculation
C4: Value | D4: Unit
B5: New HW Shares Issued | C5: ='Transaction Overview'!C10 | D5: shares
B6: HW Share Price (JPY) | C6: ='Pre-Deal Financials'!E14 | D6: JPY
B7: Equity Value (Deal) | C7: =C5*C6/1000000 | D7: mn JPY
B8: BBD Total Assets | C8: 3989 | D8: mn JPY
B9: BBD Equity | C9: 1758 | D9: mn JPY
B10: BBD Net Debt | C10: =C8-C9 | D10: mn JPY
B11: Enterprise Value (Deal) | C11: =C7+C10 | D11: mn JPY
B13: Implied Multiples (FY2024)
C14: Multiple | D14: Basis
B15: BBD Revenue (FY2024) | C15: 4131 | D15: mn JPY
B16: EV / Revenue | C16: =$C$11/C15 | D16: x
B17: BBD EBITDA (FY2024) | C17: 585 | D17: mn JPY
B18: EV / EBITDA | C18: =$C$11/C17 | D18: x
B19: BBD EPS (FY2024, JPY) | C19: 31.2 | D19: JPY
B20: Implied Consideration per BBD Share | C20: =C6*'Transaction Overview'!C9 | D20: JPY
B21: PER (FY2024) | C21: =C20/C19 | D21: x
B22: BBD ARR (FY2024) | C22: 1640 | D22: mn JPY
B23: EV / ARR | C23: =$C$11/C22 | D23: x
B25: Implied Multiples (FY2025)
C26: Multiple | D26: Basis
B27: BBD Revenue (FY2025) | C27: 4399 | D27: mn JPY
B28: EV / Revenue | C28: =$C$11/C27 | D28: x
B29: EV / EBITDA | C29: N/M | D29: Negative EBITDA
B30: PER | C30: N/M | D30: Negative Earnings
B32: Merger Ratio Validation
C33: Ratio | D33: Method
B34: BBD Current Price | C34: ='Pre-Deal Financials'!E28 | D34: JPY
B35: HW Share Price | C35: ='Pre-Deal Financials'!E14 | D35: JPY
B36: Market Price Method | C36: =C34/C35 | D36: BBD Price / HW Price
B37: HW EPS (FY2024, JPY) | C37: 72
B38: PER Method | C38: =(C19*(C35/C37))/C35 | D38: (BBD EPS x HW PER) / HW Price
B39: Actual Merger Ratio | C39: ='Transaction Overview'!C9 | D39: From deal terms

Sheet Pro Forma Balance Sheet
B1: Pro Forma Balance Sheet (Simplified)
B3: (mn JPY) | C3: HW (Pre-Merger) | D3: BBD (Pre-Merger) | E3: Adjustments | F3: Pro Forma (Combined)
B4: Total Assets (excl. Goodwill)
B5: Total Assets | C5: 1800 | D5: 3989 | F5: =C5+D5
B7: Goodwill
B8: Equity Value (Deal) | E8: ='Transaction Multiples'!C7
B9: Less: BBD Book Equity | E9: =-D12
B10: Goodwill Created | E10: =E8+E9 | F10: =E10
B11: Pro Forma Total Assets | F11: =F5+F10
B12: Total Equity | C12: 1273 | D12: 1758 | E12: =E8 | F12: =C12+E8
B13: Total Debt | C13: 527 | D13: 2231 | F13: =C13+D13
B14: Check: Assets = Equity + Debt | F14: =F11-(F12+F13)
B16: Key Ratios | C16: HW Pre | D16: BBD Pre | F16: Post-Merger
B17: Debt / Equity (D/E) | C17: =C13/C12 | D17: =D13/D12 | F17: =F13/F12
B18: Goodwill % of Total Assets | F18: =F10/F11
B20: Goodwill Amortization
B21: Useful Life (years) | C21: 20
B22: Annual Amortization (mn JPY) | C22: =F10/C21
B23: Annual After-Tax Impact (30% tax) | C23: =C22*(1-0.3)

Sheet Sensitivity Analysis
B1: Sensitivity Analysis — Pro Forma EPS
B3: Key Parameters
B4: HW Net Income (mn JPY) | C4: ='Pre-Deal Financials'!E9
B5: Fully Diluted Shares | C5: ='Transaction Overview'!C16
B6: HW Pre-Merger Shares | C6: ='Transaction Overview'!C12
B7: Standalone EPS (JPY) | C7: =C4/C6*1000000
B8: Tax Rate | C8: 0.3062
B10: Table 1: Pro Forma EPS (JPY)
B11: BBD Op Profit Impr. \ Synergy % | C11: 0 | D11: 0.05 | E11: 0.1 | F11: 0.15 | G11: 0.2 | H11: 0.25 | I11: 0.3
B12: -400 | C12: =($C$4+$B12*(1-$C$8)+$C$4*C$11*(1-$C$8))/$C$5*1000000 | D12: =($C$4+$B12*(1-$C$8)+$C$4*D$11*(1-$C$8))/$C$5*1000000 | E12: =($C$4+$B12*(1-$C$8)+$C$4*E$11*(1-$C$8))/$C$5*1000000 | F12: =($C$4+$B12*(1-$C$8)+$C$4*F$11*(1-$C$8))/$C$5*1000000 | G12: =($C$4+$B12*(1-$C$8)+$C$4*G$11*(1-$C$8))/$C$5*1000000 | H12: =($C$4+$B12*(1-$C$8)+$C$4*H$11*(1-$C$8))/$C$5*1000000 | I12: =($C$4+$B12*(1-$C$8)+$C$4*I$11*(1-$C$8))/$C$5*1000000
B13: -300 | C13: =($C$4+$B13*(1-$C$8)+$C$4*C$11*(1-$C$8))/$C$5*1000000 | D13: =($C$4+$B13*(1-$C$8)+$C$4*D$11*(1-$C$8))/$C$5*1000000 | E13: =($C$4+$B13*(1-$C$8)+$C$4*E$11*(1-$C$8))/$C$5*1000000 | F13: =($C$4+$B13*(1-$C$8)+$C$4*F$11*(1-$C$8))/$C$5*1000000 | G13: =($C$4+$B13*(1-$C$8)+$C$4*G$11*(1-$C$8))/$C$5*1000000 | H13: =($C$4+$B13*(1-$C$8)+$C$4*H$11*(1-$C$8))/$C$5*1000000 | I13: =($C$4+$B13*(1-$C$8)+$C$4*I$11*(1-$C$8))/$C$5*1000000
B14: -200 | C14: =($C$4+$B14*(1-$C$8)+$C$4*C$11*(1-$C$8))/$C$5*1000000 | D14: =($C$4+$B14*(1-$C$8)+$C$4*D$11*(1-$C$8))/$C$5*1000000 | E14: =($C$4+$B14*(1-$C$8)+$C$4*E$11*(1-$C$8))/$C$5*1000000 | F14: =($C$4+$B14*(1-$C$8)+$C$4*F$11*(1-$C$8))/$C$5*1000000 | G14: =($C$4+$B14*(1-$C$8)+$C$4*G$11*(1-$C$8))/$C$5*1000000 | H14: =($C$4+$B14*(1-$C$8)+$C$4*H$11*(1-$C$8))/$C$5*1000000 | I14: =($C$4+$B14*(1-$C$8)+$C$4*I$11*(1-$C$8))/$C$5*1000000
B15: -100 | C15: =($C$4+$B15*(1-$C$8)+$C$4*C$11*(1-$C$8))/$C$5*1000000 | D15: =($C$4+$B15*(1-$C$8)+$C$4*D$11*(1-$C$8))/$C$5*1000000 | E15: =($C$4+$B15*(1-$C$8)+$C$4*E$11*(1-$C$8))/$C$5*1000000 | F15: =($C$4+$B15*(1-$C$8)+$C$4*F$11*(1-$C$8))/$C$5*1000000 | G15: =($C$4+$B15*(1-$C$8)+$C$4*G$11*(1-$C$8))/$C$5*1000000 | H15: =($C$4+$B15*(1-$C$8)+$C$4*H$11*(1-$C$8))/$C$5*1000000 | I15: =($C$4+$B15*(1-$C$8)+$C$4*I$11*(1-$C$8))/$C$5*1000000
B16: 0 | C16: =($C$4+$B16*(1-$C$8)+$C$4*C$11*(1-$C$8))/$C$5*1000000 | D16: =($C$4+$B16*(1-$C$8)+$C$4*D$11*(1-$C$8))/$C$5*1000000 | E16: =($C$4+$B16*(1-$C$8)+$C$4*E$11*(1-$C$8))/$C$5*1000000 | F16: =($C$4+$B16*(1-$C$8)+$C$4*F$11*(1-$C$8))/$C$5*1000000 | G16: =($C$4+$B16*(1-$C$8)+$C$4*G$11*(1-$C$8))/$C$5*1000000 | H16: =($C$4+$B16*(1-$C$8)+$C$4*H$11*(1-$C$8))/$C$5*1000000 | I16: =($C$4+$B16*(1-$C$8)+$C$4*I$11*(1-$C$8))/$C$5*1000000
B17: 100 | C17: =($C$4+$B17*(1-$C$8)+$C$4*C$11*(1-$C$8))/$C$5*1000000 | D17: =($C$4+$B17*(1-$C$8)+$C$4*D$11*(1-$C$8))/$C$5*1000000 | E17: =($C$4+$B17*(1-$C$8)+$C$4*E$11*(1-$C$8))/$C$5*1000000 | F17: =($C$4+$B17*(1-$C$8)+$C$4*F$11*(1-$C$8))/$C$5*1000000 | G17: =($C$4+$B17*(1-$C$8)+$C$4*G$11*(1-$C$8))/$C$5*1000000 | H17: =($C$4+$B17*(1-$C$8)+$C$4*H$11*(1-$C$8))/$C$5*1000000 | I17: =($C$4+$B17*(1-$C$8)+$C$4*I$11*(1-$C$8))/$C$5*1000000
B18: 200 | C18: =($C$4+$B18*(1-$C$8)+$C$4*C$11*(1-$C$8))/$C$5*1000000 | D18: =($C$4+$B18*(1-$C$8)+$C$4*D$11*(1-$C$8))/$C$5*1000000 | E18: =($C$4+$B18*(1-$C$8)+$C$4*E$11*(1-$C$8))/$C$5*1000000 | F18: =($C$4+$B18*(1-$C$8)+$C$4*F$11*(1-$C$8))/$C$5*1000000 | G18: =($C$4+$B18*(1-$C$8)+$C$4*G$11*(1-$C$8))/$C$5*1000000 | H18: =($C$4+$B18*(1-$C$8)+$C$4*H$11*(1-$C$8))/$C$5*1000000 | I18: =($C$4+$B18*(1-$C$8)+$C$4*I$11*(1-$C$8))/$C$5*1000000
B19: 300 | C19: =($C$4+$B19*(1-$C$8)+$C$4*C$11*(1-$C$8))/$C$5*1000000 | D19: =($C$4+$B19*(1-$C$8)+$C$4*D$11*(1-$C$8))/$C$5*1000000 | E19: =($C$4+$B19*(1-$C$8)+$C$4*E$11*(1-$C$8))/$C$5*1000000 | F19: =($C$4+$B19*(1-$C$8)+$C$4*F$11*(1-$C$8))/$C$5*1000000 | G19: =($C$4+$B19*(1-$C$8)+$C$4*G$11*(1-$C$8))/$C$5*1000000 | H19: =($C$4+$B19*(1-$C$8)+$C$4*H$11*(1-$C$8))/$C$5*1000000 | I19: =($C$4+$B19*(1-$C$8)+$C$4*I$11*(1-$C$8))/$C$5*1000000
B20: 400 | C20: =($C$4+$B20*(1-$C$8)+$C$4*C$11*(1-$C$8))/$C$5*1000000 | D20: =($C$4+$B20*(1-$C$8)+$C$4*D$11*(1-$C$8))/$C$5*1000000 | E20: =($C$4+$B20*(1-$C$8)+$C$4*E$11*(1-$C$8))/$C$5*1000000 | F20: =($C$4+$B20*(1-$C$8)+$C$4*F$11*(1-$C$8))/$C$5*1000000 | G20: =($C$4+$B20*(1-$C$8)+$C$4*G$11*(1-$C$8))/$C$5*1000000 | H20: =($C$4+$B20*(1-$C$8)+$C$4*H$11*(1-$C$8))/$C$5*1000000 | I20: =($C$4+$B20*(1-$C$8)+$C$4*I$11*(1-$C$8))/$C$5*1000000
B23: Table 2: Accretion / Dilution (%)
B24: BBD Op Profit Impr. \ Synergy % | C24: 0 | D24: 0.05 | E24: 0.1 | F24: 0.15 | G24: 0.2 | H24: 0.25 | I24: 0.3
B25: -400 | C25: =C12/$C$7-1 | D25: =D12/$C$7-1 | E25: =E12/$C$7-1 | F25: =F12/$C$7-1 | G25: =G12/$C$7-1 | H25: =H12/$C$7-1 | I25: =I12/$C$7-1
B26: -300 | C26: =C13/$C$7-1 | D26: =D13/$C$7-1 | E26: =E13/$C$7-1 | F26: =F13/$C$7-1 | G26: =G13/$C$7-1 | H26: =H13/$C$7-1 | I26: =I13/$C$7-1
B27: -200 | C27: =C14/$C$7-1 | D27: =D14/$C$7-1 | E27: =E14/$C$7-1 | F27: =F14/$C$7-1 | G27: =G14/$C$7-1 | H27: =H14/$C$7-1 | I27: =I14/$C$7-1
B28: -100 | C28: =C15/$C$7-1 | D28: =D15/$C$7-1 | E28: =E15/$C$7-1 | F28: =F15/$C$7-1 | G28: =G15/$C$7-1 | H28: =H15/$C$7-1 | I28: =I15/$C$7-1
B29: 0 | C29: =C16/$C$7-1 | D29: =D16/$C$7-1 | E29: =E16/$C$7-1 | F29: =F16/$C$7-1 | G29: =G16/$C$7-1 | H29: =H16/$C$7-1 | I29: =I16/$C$7-1
B30: 100 | C30: =C17/$C$7-1 | D30: =D17/$C$7-1 | E30: =E17/$C$7-1 | F30: =F17/$C$7-1 | G30: =G17/$C$7-1 | H30: =H17/$C$7-1 | I30: =I17/$C$7-1
B31: 200 | C31: =C18/$C$7-1 | D31: =D18/$C$7-1 | E31: =E18/$C$7-1 | F31: =F18/$C$7-1 | G31: =G18/$C$7-1 | H31: =H18/$C$7-1 | I31: =I18/$C$7-1
B32: 300 | C32: =C19/$C$7-1 | D32: =D19/$C$7-1 | E32: =E19/$C$7-1 | F32: =F19/$C$7-1 | G32: =G19/$C$7-1 | H32: =H19/$C$7-1 | I32: =I19/$C$7-1
B33: 400 | C33: =C20/$C$7-1 | D33: =D20/$C$7-1 | E33: =E20/$C$7-1 | F33: =F20/$C$7-1 | G33: =G20/$C$7-1 | H33: =H20/$C$7-1 | I33: =I20/$C$7-1
