Workbook

Sheet Executive Summary
B1: DISCLAIMER: This is a sample analysis for demonstration purposes only. It does not constitute investment advice.
B3: Besterra (1433.T)
B4: Equity Research Report
B6: Company | C6: Besterra
B7: Ticker | C7: 1433.T (TSE Prime)
B8: Sector | C8: Construction / Plant Dismantling
B9: Current Price | C9: 1269
B10: Target Price (DCF Mid) | C10: =IF(COUNT(C16:C17)=0,"N/A",ROUND(AVERAGE(C16:C17),0)) -> 1131
B11: Recommendation | C11: =IF(NOT(ISNUMBER(C12)),"N/A",IF(C12>0.15,"BUY",IF(C12>0.05,"HOLD","SELL"))) -> SELL
B12: Upside / Downside | C12: =IF(ISNUMBER(C10),(C10-C9)/C9,"N/A") -> -0.10874704
B14: Valuation Summary
B15: Methodology | C15: Implied Value (JPY) | D15: vs Current Price
B16: DCF - Perpetuity Growth | C16: =IF('DCF Model'!C53<'DCF Model'!C16,"INVALID (EV < net debt)",'DCF Model'!C55) -> 1071 | D16: =IF(ISNUMBER(C16),(C16-C9)/C9,"N/A") -> -0.15602837
B17: DCF - Exit Multiple | C17: =IF('DCF Model'!C62<'DCF Model'!C16,"INVALID (EV < net debt)",'DCF Model'!C64) -> 1191 | D17: =IF(ISNUMBER(C17),(C17-C9)/C9,"N/A") -> -0.061465721
B18: Comps - EV/EBITDA Median [参考・Target不算入] | C18: ='Comps Analysis'!C27 -> 892 | D18: =IF(ISNUMBER(C18),(C18-C9)/C9,"N/A") -> -0.29708432
B19: Comps - PER Median [参考・Target不算入] | C19: ='Comps Analysis'!C28 -> 1079 | D19: =IF(ISNUMBER(C19),(C19-C9)/C9,"N/A") -> -0.14972419
B20: Note: Target Mid は DCF 2法（PGM / Exit）の平均のみ。Comps 2法は [参考] で Target 不算入（EV<ネットデットで株式価値が負になる手法は INVALID として平均から除外）
B21: DCF Valuation Range (PGM - Exit) | C21: =IF(COUNT(C16:C17)=0,"N/A",MIN(C16:C17)&" - "&MAX(C16:C17)) -> 1071 - 1191
B23: Key Investment Thesis
B24: ="At "&TEXT(C9,"#,##0")&" the shares trade at "&TEXT('Comps Analysis'!L5,"0.0""x""")&" on reported earnings and "&TEXT('Comps Analysis'!M5,"0.00""x""")&" on book, yet order backlog grew double digits and gross margin stepped up in three straight reporting periods. The slope is in the reported numbers, not a plan: trailing twelve-month operating profit already matches full-year guidance." -> At 1,269 the shares trade at 15.3x on reported earnings and 2.10x on book, yet order backlog grew double digits and gross margin stepped up in three straight reporting periods. The slope is in the reported numbers, not a plan: trailing twelve-month operating profit already matches full-year guidance.
B25: ="Free cash flow discounts back at "&TEXT('DCF Model'!C26,"0.00%")&" and is governed almost entirely by receivable days: the business is asset-light, with capex running near zero against sales, and the 42-day fall in DSO last fiscal year turned operating cash flow from negative to strongly positive." -> Free cash flow discounts back at 12.12% and is governed almost entirely by receivable days: the business is asset-light, with capex running near zero against sales, and the 42-day fall in DSO last fiscal year turned operating cash flow from negative to strongly positive.
B26: ="Net cash and a liquid securities portfolio cover a meaningful share of market value, which cushions the downside case; the DCF mid-point of "&TEXT(C10,"#,##0")&" implies "&TEXT(C12,"+0.0%;-0.0%")&" against "&TEXT(C9,"#,##0")&"." -> Net cash and a liquid securities portfolio cover a meaningful share of market value, which cushions the downside case; the DCF mid-point of 1,131 implies -10.9% against 1,269.
B28: Key Risks
B29: Safety incidents are a live operational risk rather than a theoretical one: a prior fiscal year carried accident compensation losses, and a fatal-accident investigation has been reported in the press. A recurrence can suspend sites and trigger customer suspension, which is what the Downside 2 case models.
B30: Revenue is concentrated in a small number of large dismantling projects and a leading customer in the steel engineering chain, so a gap between projects can swing operating margin by several points within a single year.
B31: ="Reported earnings are flattered by recurring gains on securities and subsidiary disposals; on normalized earnings the multiple is materially above the headline "&TEXT('Comps Analysis'!L5,"0.0""x""")&", and the first-half result due in September can reset the slope in either direction." -> Reported earnings are flattered by recurring gains on securities and subsidiary disposals; on normalized earnings the multiple is materially above the headline 15.3x, and the first-half result due in September can reset the slope in either direction.

Sheet Financial Statements
B2: Besterra - Historical Financials (JPY mn)
C4: FY2022/1 | D4: FY2023/1 | E4: FY2024/1 | F4: FY2025/1 | G4: FY2026/1
B5: Income Statement
B6: Revenue | C6: 5966.9 | D6: 5458.7 | E6: 9394.8 | F6: 10897.5 | G6: 11140.4
B7: COGS | C7: 4609.7 | D7: 4569.1 | E7: 7875.1 | F7: 9006.8 | G7: 8902.8
B8: Gross Profit | C8: =C6-C7 -> 1357.2 | D8: =D6-D7 -> 889.6 | E8: =E6-E7 -> 1519.7 | F8: =F6-F7 -> 1890.7 | G8: =G6-G7 -> 2237.6
B9: Gross Margin | C9: =C8/C6 -> 0.22745479 | D9: =D8/D6 -> 0.16296921 | E9: =E8/E6 -> 0.1617597 | F9: =F8/F6 -> 0.17349851 | G9: =G8/G6 -> 0.20085455
B10: SGA | C10: 868.4 | D10: 1105.3 | E10: 1272.8 | F10: 1517 | G10: 1496.5
B11: Operating Income | C11: 488.8 | D11: -215.7 | E11: 246.9 | F11: 373.6 | G11: 741.1
B12: Net Income | C12: 1391.8 | D12: -64.4 | E12: 231.1 | F12: 409.8 | G12: 732.6
B13: Operating Margin | C13: =C11/C6 -> 0.081918584 | D13: =D11/D6 -> -0.039514903 | E13: =E11/E6 -> 0.026280496 | F13: =F11/F6 -> 0.034283092 | G13: =G11/G6 -> 0.066523644
B14: Net Margin | C14: =C12/C6 -> 0.23325345 | D14: =D12/D6 -> -0.011797681 | E14: =E12/E6 -> 0.024598714 | F14: =F12/F6 -> 0.037604955 | G14: =G12/G6 -> 0.065760655
B15: Revenue Growth (YoY) | C15: n/a | D15: =(D6-C6)/C6 -> -0.085169854 | E15: =(E6-D6)/D6 -> 0.72106912 | F15: =(F6-E6)/E6 -> 0.15995019 | G15: =(G6-F6)/F6 -> 0.022289516
B16: Operating Income Growth (YoY) | C16: n/a | D16: =(D11-C11)/C11 -> -1.4412848 | E16: =(E11-D11)/D11 -> -2.1446453 | F16: =(F11-E11)/E11 -> 0.51316322 | G16: =(G11-F11)/F11 -> 0.98367238
B18: Cash Flow Statement
B19: Operating Cash Flow | C19: 537.8 | D19: -354.8 | E19: -1422.3 | F19: -607.5 | G19: 1644.3
B20: Capex | C20: 37.9 | D20: 13.7 | E20: 14.8 | F20: 30.8 | G20: 4.9
B21: Free Cash Flow | C21: =C19-C20 -> 499.9 | D21: =D19-D20 -> -368.5 | E21: =E19-E20 -> -1437.1 | F21: =F19-F20 -> -638.3 | G21: =G19-G20 -> 1639.4
B22: FCF Margin | C22: =C21/C6 -> 0.083778847 | D22: =D21/D6 -> -0.067506916 | E22: =E21/E6 -> -0.1529676 | F22: =F21/F6 -> -0.058573067 | G22: =G21/G6 -> 0.14715809
B23: Capex / Revenue | C23: =C20/C6 -> 0.0063517069 | D23: =D20/D6 -> 0.0025097551 | E23: =E20/E6 -> 0.0015753395 | F23: =F20/F6 -> 0.0028263363 | G23: =G20/G6 -> 0.00043984058
B25: Balance Sheet Highlights
B26: Cash & Deposits | C26: 2122.2 | D26: 1337.6 | E26: 1444.1 | F26: 1599.5 | G26: 1434.4
B27: Total Interest-bearing Debt (short + long) | C27: 2389.4 | D27: 2426.7 | E27: 4292.4 | F27: 3752.1 | G27: 570.7
B28: Net Debt (Cash) | C28: =C27-C26 -> 267.2 | D28: =D27-D26 -> 1089.1 | E28: =E27-E26 -> 2848.3 | F28: =F27-F26 -> 2152.6 | G28: =G27-G26 -> -863.7
B30: Note: OCF / Cash / Debt coverage OCF 5/5, Cash 5/5, Debt 5/5 — blank cells are years with no year-key match in the source data (verify against 決算短信 or set hist_ocf / hist_cash / hist_debt in overrides).

Sheet DCF Model
B2: DCF Valuation Model - Besterra
B4: Assumptions
B5: Capex / Revenue | C5: 0.0045
B6: Effective Tax Rate | C6: 0.306
B7: Risk-Free Rate | C7: 0.03
B8: Beta | C8: 1
B9: Equity Risk Premium | C9: 0.065
B10: Size Premium | C10: 0.035
B11: After-tax Cost of Debt | C11: 0.0051
B12: D/E Ratio | C12: 0.0762
B13: Terminal Growth Rate | C13: 0.01
B14: Exit Multiple (EV/EBITDA) | C14: 6
B15: Fully Diluted Shares | C15: 8860910
B16: Net Debt (JPY mn) | C16: -1054
... B20: LTM Revenue (JPY mn) (override) | C20: 11882
B22: WACC Calculation
B23: Cost of Equity (Ke) | C23: =C7+C8*C9+C10 -> 0.13
B24: Weight of Equity | C24: =1/(1+C12) -> 0.92919532
B25: Weight of Debt | C25: =C12/(1+C12) -> 0.070804683
B26: WACC | C26: =C23*C24+C11*C25 -> 0.1211565
B27: Active Scenario | C27: Base | D27: =MATCH(C27,B69:B73,0) -> 1
B28: Projected Free Cash Flow
C29: FY2027(E) | D29: FY2028(E) | E29: FY2029(E) | F29: FY2030(E) | G29: FY2031(E)
B30: Revenue Growth (YoY) | C30: =CHOOSE($D$27,C69,C70,C71,C72,C73) -> 0.167 | D30: =CHOOSE($D$27,D69,D70,D71,D72,D73) -> 0.08 | E30: =CHOOSE($D$27,E69,E70,E71,E72,E73) -> 0.07 | F30: =CHOOSE($D$27,F69,F70,F71,F72,F73) -> 0.06 | G30: =CHOOSE($D$27,G69,G70,G71,G72,G73) -> 0.05
B31: COGS % of Revenue | C31: =CHOOSE($D$27,C76,C77,C78,C79,C80) -> 0.795 | D31: =CHOOSE($D$27,D76,D77,D78,D79,D80) -> 0.79 | E31: =CHOOSE($D$27,E76,E77,E78,E79,E80) -> 0.788 | F31: =CHOOSE($D$27,F76,F77,F78,F79,F80) -> 0.785 | G31: =CHOOSE($D$27,G76,G77,G78,G79,G80) -> 0.785
B32: SGA % of Revenue | C32: =CHOOSE($D$27,C83,C84,C85,C86,C87) -> 0.115 | D32: =CHOOSE($D$27,D83,D84,D85,D86,D87) -> 0.113 | E32: =CHOOSE($D$27,E83,E84,E85,E86,E87) -> 0.11 | F32: =CHOOSE($D$27,F83,F84,F85,F86,F87) -> 0.108 | G32: =CHOOSE($D$27,G83,G84,G85,G86,G87) -> 0.108
B33: Revenue | C33: =C17*(1+C30) -> 13000.847 | D33: =C33*(1+D30) -> 14040.915 | E33: =D33*(1+E30) -> 15023.779 | F33: =E33*(1+F30) -> 15925.205 | G33: =F33*(1+G30) -> 16721.466
B34: COGS | C34: =C33*C31 -> 10335.673 | D34: =D33*D31 -> 11092.322 | E34: =E33*E31 -> 11838.738 | F34: =F33*F31 -> 12501.286 | G34: =G33*G31 -> 13126.35
B35: Gross Profit | C35: =C33-C34 -> 2665.1736 | D35: =D33-D34 -> 2948.5921 | E35: =E33-E34 -> 3185.0411 | F35: =F33-F34 -> 3423.9191 | G35: =G33-G34 -> 3595.1151
B36: Gross Margin | C36: =C35/C33 -> 0.205 | D36: =D35/D33 -> 0.21 | E36: =E35/E33 -> 0.212 | F36: =F35/F33 -> 0.215 | G36: =G35/G33 -> 0.215
B37: SGA Expense | C37: =C33*C32 -> 1495.0974 | D37: =D33*D32 -> 1586.6233 | E37: =E33*E32 -> 1652.6156 | F37: =F33*F32 -> 1719.9222 | G37: =G33*G32 -> 1805.9183
B38: Implied Operating Margin | C38: =(C35-C37)/C33 -> 0.09 | D38: =(D35-D37)/D33 -> 0.097 | E38: =(E35-E37)/E33 -> 0.102 | F38: =(F35-F37)/F33 -> 0.107 | G38: =(G35-G37)/G33 -> 0.107
B39: Operating Income (EBIT) | C39: =C35-C37 -> 1170.0762 | D39: =D35-D37 -> 1361.9687 | E39: =E35-E37 -> 1532.4254 | F39: =F35-F37 -> 1703.997 | G39: =G35-G37 -> 1789.1968
B40: Less: Tax | C40: =MAX(0,C39*C6) -> 358.04332 | D40: =MAX(0,D39*C6) -> 416.76243 | E40: =MAX(0,E39*C6) -> 468.92218 | F40: =MAX(0,F39*C6) -> 521.42307 | G40: =MAX(0,G39*C6) -> 547.49422
B41: NOPAT | C41: =C39-C40 -> 812.03289 | D41: =D39-D40 -> 945.20629 | E41: =E39-E40 -> 1063.5032 | F41: =F39-F40 -> 1182.5739 | G41: =G39-G40 -> 1241.7026
B42: Plus: D&A | C42: =C33*C18 -> 54.603557 | D42: =D33*C18 -> 58.971841 | E42: =E33*C18 -> 63.09987 | F42: =F33*C18 -> 66.885862 | G42: =G33*C18 -> 70.230155
B43: Less: Capex | C43: =C33*C5 -> 58.503811 | D43: =D33*C5 -> 63.184115 | E43: =E33*C5 -> 67.607004 | F43: =F33*C5 -> 71.663424 | G43: =G33*C5 -> 75.246595
B44: Change in NWC | C44: ='NWC Schedule'!D19 -> 465.58522 | D44: ='NWC Schedule'!E19 -> 271.96703 | E44: ='NWC Schedule'!F19 -> 252.92496 | F44: ='NWC Schedule'!G19 -> 234.83401 | G44: ='NWC Schedule'!H19 -> 202.25556
B45: Unlevered Free Cash Flow | C45: =C41+C42-C43-C44 -> 342.54741 | D45: =D41+D42-D43-D44 -> 669.02698 | E45: =E41+E42-E43-E44 -> 806.07115 | F45: =F41+F42-F43-F44 -> 942.96232 | G45: =G41+G42-G43-G44 -> 1034.4306
B46: Discount Factor | C46: =1/(1+C26)^(C19+0) -> 0.95310375 | D46: =1/(1+C26)^(C19+1) -> 0.85010769 | E46: =1/(1+C26)^(C19+2) -> 0.75824177 | F46: =1/(1+C26)^(C19+3) -> 0.67630324 | G46: =1/(1+C26)^(C19+4) -> 0.6032193
B47: PV of FCF | C47: =C45*C46 -> 326.48323 | D47: =D45*D46 -> 568.74498 | E47: =E45*E46 -> 611.19681 | F47: =F45*F46 -> 637.72848 | G47: =G45*G46 -> 623.9885
B49: Valuation - Perpetuity Growth Method
B50: Sum of PV of FCFs | C50: =SUM(C47:G47) -> 2768.142
B51: Terminal Value (PGM) | C51: =G45*(1+C13)/(C26-C13) -> 9399.1349
B52: PV of Terminal Value | C52: =C51*G46 -> 5669.7396
B53: Enterprise Value | C53: =C50+C52 -> 8437.8816
B54: Equity Value | C54: =C53-C16 -> 9491.8816
B55: Implied Share Price (PGM) | C55: =ROUND(C54*1000000/C15,0) -> 1071
B57: Valuation - Exit Multiple Method
B58: Sum of PV of FCFs | C58: =C50 -> 2768.142
B59: Year 5 EBITDA | C59: =G39+G42 -> 1859.427
B60: Terminal Value (Exit Multiple) | C60: =C59*C14 -> 11156.562
B61: PV of Terminal Value | C61: =C60*G46 -> 6729.8535
B62: Enterprise Value | C62: =C58+C61 -> 9497.9954
B63: Equity Value | C63: =C62-C16 -> 10551.995
B64: Implied Share Price (Exit Multiple) | C64: =ROUND(C63*1000000/C15,0) -> 1191
B66: Scenario Input Matrix
C67: Year 1 | D67: Year 2 | E67: Year 3 | F67: Year 4 | G67: Year 5
B68: Revenue Growth (YoY)
B69: Base | C69: 0.167 | D69: 0.08 | E69: 0.07 | F69: 0.06 | G69: 0.05
B70: Upside | C70: 0.2 | D70: 0.15 | E70: 0.13 | F70: 0.11 | G70: 0.1
B71: Management | C71: 0.167 | D71: 0.114 | E71: 0.114 | F71: 0.114 | G71: 0.114
B72: Downside 1 | C72: 0.08 | D72: 0.04 | E72: 0.03 | F72: 0.03 | G72: 0.02
B73: Downside 2 | C73: 0 | D73: -0.03 | E73: 0 | F73: 0.02 | G73: 0.02
B75: COGS % of Revenue
B76: Base | C76: 0.795 | D76: 0.79 | E76: 0.788 | F76: 0.785 | G76: 0.785
B77: Upside | C77: 0.785 | D77: 0.78 | E77: 0.775 | F77: 0.77 | G77: 0.77
B78: Management | C78: 0.805 | D78: 0.798 | E78: 0.793 | F78: 0.788 | G78: 0.785
B79: Downside 1 | C79: 0.81 | D79: 0.815 | E79: 0.815 | F79: 0.815 | G79: 0.815
B80: Downside 2 | C80: 0.83 | D80: 0.84 | E80: 0.835 | F80: 0.83 | G80: 0.83
B82: SGA % of Revenue
B83: Base | C83: 0.115 | D83: 0.113 | E83: 0.11 | F83: 0.108 | G83: 0.108
B84: Upside | C84: 0.11 | D84: 0.105 | E84: 0.102 | F84: 0.1 | G84: 0.098
B85: Management | C85: 0.118 | D85: 0.115 | E85: 0.112 | F85: 0.11 | G85: 0.108
B86: Downside 1 | C86: 0.125 | D86: 0.128 | E86: 0.128 | F86: 0.127 | G86: 0.127
B87: Downside 2 | C87: 0.135 | D87: 0.14 | E87: 0.138 | F87: 0.135 | G87: 0.135

Sheet Reverse DCF
B2: Reverse DCF - Besterra (1433.T)
B3: What is the current share price already assuming? Every value below is a live formula off the other sheets.
B5: Block 0: Market-implied enterprise value (live)
B6: Current Share Price (JPY) | C6: ='Executive Summary'!C9 -> 1269
B7: Fully Diluted Shares | C7: ='DCF Model'!C15 -> 8860910
B8: Market Capitalisation (JPY mn) | C8: =C6*C7/1000000 -> 11244.495
B9: Net Debt (JPY mn) | C9: ='DCF Model'!C16 -> -1054
B10: Enterprise Value (JPY mn) | C10: =C8+C9 -> 10190.495
B11: WACC (w) | C11: ='DCF Model'!C26 -> 0.1211565
B12: Terminal Growth (g) | C12: ='DCF Model'!C13 -> 0.01
B13: Effective Tax Rate (t) | C13: ='DCF Model'!C6 -> 0.306
B14: Starting Operating Profit OP0 (LTM (2025/05-2026/04) actual) | C14: 960.1
B15: Cycle-peak Operating Profit (FY2027/1 会社予想 actual) | C15: 1000
B16: Terminal-year Revenue, active scenario (JPY mn) | C16: ='DCF Model'!G33 -> 16721.466
B17: Base-case DCF Enterprise Value, PGM (JPY mn) | C17: ='DCF Model'!C53 -> 8437.8816
B18: Cycle-peak Operating Margin (FY2027/1 会社予想 actual) | C18: 0.0769
B19: Gap: market EV less base-case DCF EV (JPY mn) | C19: =C10-C17 -> 1752.6132
B20: Gap per share (JPY) - the part of the price the base case does not explain | C20: =IFERROR(ROUND(C19*1000000/C7,0),"N/A") -> 198
B22: Block A: Required steady-state operating profit, reached IMMEDIATELY (no ramp)
B23: The lowest bar the price can clear: today's EV read as a perpetuity of one steady-state profit, capex = D&A, no NWC build.
B24: Required steady-state NOPAT (JPY mn) | C24: =C10*(C11-C12) -> 1132.7397
B25: Required steady-state Operating Profit (JPY mn) | C25: =IFERROR(C24/(1-C13),"N/A") -> 1632.1897
B26: ... as a multiple of the FY2027/1 会社予想 peak | C26: =IFERROR(C25/C15,"N/A") -> 1.6321897
B27: ... as a multiple of LTM (2025/05-2026/04) actual | C27: =IFERROR(C25/C14,"N/A") -> 1.7000206
B28: ... implied OPM on terminal-year revenue | C28: =IFERROR(C25/C16,"N/A") -> 0.097610448
B29: ... revenue needed if margins only reach the cycle peak | C29: =IFERROR(C25/C18,"N/A") -> 21224.834
B32: Block B: Required steady-state operating profit by YEARS-TO-REACH (linear ramp) x WACC
B33: Operating profit ramps linearly from OP0 (C14) to OP* over N years, then grows at g for ever. Column F is the model WACC.
B34: OP* = ( EV/(1-t) - OP0*(A-B) ) / ( B + TVF ). A longer ramp needs a HIGHER steady state, because more years are spent below it.
B36: Years to steady state (N) \ WACC | C36: N | D36: ='DCF Model'!C26-0.02 -> 0.1011565 | E36: ='DCF Model'!C26-0.01 -> 0.1111565 | F36: ='DCF Model'!C26 -> 0.1211565 | G36: ='DCF Model'!C26+0.01 -> 0.1311565 | H36: ='DCF Model'!C26+0.02 -> 0.1411565
B37: B-1 PV weight on the RAMP from OP0 (A - B)
B38: N = 3 years | C38: 3 | D38: =IFERROR((1-(1+D$36)^(-$C38))/D$36-(1+D$36)/(D$36^2*$C38)*(1-($C38+1)/(1+D$36)^$C38+$C38/(1+D$36)^($C38+1)),"N/A") -> 0.88032783 | E38: =IFERROR((1-(1+E$36)^(-$C38))/E$36-(1+E$36)/(E$36^2*$C38)*(1-($C38+1)/(1+E$36)^$C38+$C38/(1+E$36)^($C38+1)),"N/A") -> 0.86995344 | F38: =IFERROR((1-(1+F$36)^(-$C38))/F$36-(1+F$36)/(F$36^2*$C38)*(1-($C38+1)/(1+F$36)^$C38+$C38/(1+F$36)^($C38+1)),"N/A") -> 0.85980746 | G38: =IFERROR((1-(1+G$36)^(-$C38))/G$36-(1+G$36)/(G$36^2*$C38)*(1-($C38+1)/(1+G$36)^$C38+$C38/(1+G$36)^($C38+1)),"N/A") -> 0.84988269 | H38: =IFERROR((1-(1+H$36)^(-$C38))/H$36-(1+H$36)/(H$36^2*$C38)*(1-($C38+1)/(1+H$36)^$C38+$C38/(1+H$36)^($C38+1)),"N/A") -> 0.84017223
B39: N = 5 years | C39: 5 | D39: =IFERROR((1-(1+D$36)^(-$C39))/D$36-(1+D$36)/(D$36^2*$C39)*(1-($C39+1)/(1+D$36)^$C39+$C39/(1+D$36)^($C39+1)),"N/A") -> 1.6569454 | E39: =IFERROR((1-(1+E$36)^(-$C39))/E$36-(1+E$36)/(E$36^2*$C39)*(1-($C39+1)/(1+E$36)^$C39+$C39/(1+E$36)^($C39+1)),"N/A") -> 1.6286937 | F39: =IFERROR((1-(1+F$36)^(-$C39))/F$36-(1+F$36)/(F$36^2*$C39)*(1-($C39+1)/(1+F$36)^$C39+$C39/(1+F$36)^($C39+1)),"N/A") -> 1.6012909 | G39: =IFERROR((1-(1+G$36)^(-$C39))/G$36-(1+G$36)/(G$36^2*$C39)*(1-($C39+1)/(1+G$36)^$C39+$C39/(1+G$36)^($C39+1)),"N/A") -> 1.574702 | H39: =IFERROR((1-(1+H$36)^(-$C39))/H$36-(1+H$36)/(H$36^2*$C39)*(1-($C39+1)/(1+H$36)^$C39+$C39/(1+H$36)^($C39+1)),"N/A") -> 1.5488938
B40: N = 7 years | C40: 7 | D40: =IFERROR((1-(1+D$36)^(-$C40))/D$36-(1+D$36)/(D$36^2*$C40)*(1-($C40+1)/(1+D$36)^$C40+$C40/(1+D$36)^($C40+1)),"N/A") -> 2.3435543 | E40: =IFERROR((1-(1+E$36)^(-$C40))/E$36-(1+E$36)/(E$36^2*$C40)*(1-($C40+1)/(1+E$36)^$C40+$C40/(1+E$36)^($C40+1)),"N/A") -> 2.2921599 | F40: =IFERROR((1-(1+F$36)^(-$C40))/F$36-(1+F$36)/(F$36^2*$C40)*(1-($C40+1)/(1+F$36)^$C40+$C40/(1+F$36)^($C40+1)),"N/A") -> 2.2427004 | G40: =IFERROR((1-(1+G$36)^(-$C40))/G$36-(1+G$36)/(G$36^2*$C40)*(1-($C40+1)/(1+G$36)^$C40+$C40/(1+G$36)^($C40+1)),"N/A") -> 2.1950782 | H40: =IFERROR((1-(1+H$36)^(-$C40))/H$36-(1+H$36)/(H$36^2*$C40)*(1-($C40+1)/(1+H$36)^$C40+$C40/(1+H$36)^($C40+1)),"N/A") -> 2.1492018
B41: N = 10 years | C41: 10 | D41: =IFERROR((1-(1+D$36)^(-$C41))/D$36-(1+D$36)/(D$36^2*$C41)*(1-($C41+1)/(1+D$36)^$C41+$C41/(1+D$36)^($C41+1)),"N/A") -> 3.2300002 | E41: =IFERROR((1-(1+E$36)^(-$C41))/E$36-(1+E$36)/(E$36^2*$C41)*(1-($C41+1)/(1+E$36)^$C41+$C41/(1+E$36)^($C41+1)),"N/A") -> 3.1376973 | F41: =IFERROR((1-(1+F$36)^(-$C41))/F$36-(1+F$36)/(F$36^2*$C41)*(1-($C41+1)/(1+F$36)^$C41+$C41/(1+F$36)^($C41+1)),"N/A") -> 3.0498511 | G41: =IFERROR((1-(1+G$36)^(-$C41))/G$36-(1+G$36)/(G$36^2*$C41)*(1-($C41+1)/(1+G$36)^$C41+$C41/(1+G$36)^($C41+1)),"N/A") -> 2.966178 | H41: =IFERROR((1-(1+H$36)^(-$C41))/H$36-(1+H$36)/(H$36^2*$C41)*(1-($C41+1)/(1+H$36)^$C41+$C41/(1+H$36)^($C41+1)),"N/A") -> 2.8864164
B42: B-2 PV weight on the STEADY STATE OP* (B + terminal factor)
B43: N = 3 years | C43: 3 | D43: =IFERROR((1+D$36)/(D$36^2*$C43)*(1-($C43+1)/(1+D$36)^$C43+$C43/(1+D$36)^($C43+1))+(1+$C$12)/((D$36-$C$12)*(1+D$36)^$C43),"N/A") -> 9.8997216 | E43: =IFERROR((1+E$36)/(E$36^2*$C43)*(1-($C43+1)/(1+E$36)^$C43+$C43/(1+E$36)^($C43+1))+(1+$C$12)/((E$36-$C$12)*(1+E$36)^$C43),"N/A") -> 8.8466844 | F43: =IFERROR((1+F$36)/(F$36^2*$C43)*(1-($C43+1)/(1+F$36)^$C43+$C43/(1+F$36)^($C43+1))+(1+$C$12)/((F$36-$C$12)*(1+F$36)^$C43),"N/A") -> 7.9847062 | G43: =IFERROR((1+G$36)/(G$36^2*$C43)*(1-($C43+1)/(1+G$36)^$C43+$C43/(1+G$36)^($C43+1))+(1+$C$12)/((G$36-$C$12)*(1+G$36)^$C43),"N/A") -> 7.2664303 | H43: =IFERROR((1+H$36)/(H$36^2*$C43)*(1-($C43+1)/(1+H$36)^$C43+$C43/(1+H$36)^($C43+1))+(1+$C$12)/((H$36-$C$12)*(1+H$36)^$C43),"N/A") -> 6.6589445
B44: N = 5 years | C44: 5 | D44: =IFERROR((1+D$36)/(D$36^2*$C44)*(1-($C44+1)/(1+D$36)^$C44+$C44/(1+D$36)^($C44+1))+(1+$C$12)/((D$36-$C$12)*(1+D$36)^$C44),"N/A") -> 8.9663299 | E44: =IFERROR((1+E$36)/(E$36^2*$C44)*(1-($C44+1)/(1+E$36)^$C44+$C44/(1+E$36)^($C44+1))+(1+$C$12)/((E$36-$C$12)*(1+E$36)^$C44),"N/A") -> 7.9510371 | F44: =IFERROR((1+F$36)/(F$36^2*$C44)*(1-($C44+1)/(1+F$36)^$C44+$C44/(1+F$36)^($C44+1))+(1+$C$12)/((F$36-$C$12)*(1+F$36)^$C44),"N/A") -> 7.1224489 | G44: =IFERROR((1+G$36)/(G$36^2*$C44)*(1-($C44+1)/(1+G$36)^$C44+$C44/(1+G$36)^($C44+1))+(1+$C$12)/((G$36-$C$12)*(1+G$36)^$C44),"N/A") -> 6.434168 | H44: =IFERROR((1+H$36)/(H$36^2*$C44)*(1-($C44+1)/(1+H$36)^$C44+$C44/(1+H$36)^($C44+1))+(1+$C$12)/((H$36-$C$12)*(1+H$36)^$C44),"N/A") -> 5.8539559
B45: N = 7 years | C45: 7 | D45: =IFERROR((1+D$36)/(D$36^2*$C45)*(1-($C45+1)/(1+D$36)^$C45+$C45/(1+D$36)^($C45+1))+(1+$C$12)/((D$36-$C$12)*(1+D$36)^$C45),"N/A") -> 8.1504275 | E45: =IFERROR((1+E$36)/(E$36^2*$C45)*(1-($C45+1)/(1+E$36)^$C45+$C45/(1+E$36)^($C45+1))+(1+$C$12)/((E$36-$C$12)*(1+E$36)^$C45),"N/A") -> 7.1766853 | F45: =IFERROR((1+F$36)/(F$36^2*$C45)*(1-($C45+1)/(1+F$36)^$C45+$C45/(1+F$36)^($C45+1))+(1+$C$12)/((F$36-$C$12)*(1+F$36)^$C45),"N/A") -> 6.3849577 | G45: =IFERROR((1+G$36)/(G$36^2*$C45)*(1-($C45+1)/(1+G$36)^$C45+$C45/(1+G$36)^($C45+1))+(1+$C$12)/((G$36-$C$12)*(1+G$36)^$C45),"N/A") -> 5.7298202 | H45: =IFERROR((1+H$36)/(H$36^2*$C45)*(1-($C45+1)/(1+H$36)^$C45+$C45/(1+H$36)^($C45+1))+(1+$C$12)/((H$36-$C$12)*(1+H$36)^$C45),"N/A") -> 5.1797236
B46: N = 10 years | C46: 10 | D46: =IFERROR((1+D$36)/(D$36^2*$C46)*(1-($C46+1)/(1+D$36)^$C46+$C46/(1+D$36)^($C46+1))+(1+$C$12)/((D$36-$C$12)*(1+D$36)^$C46),"N/A") -> 7.1112657 | E46: =IFERROR((1+E$36)/(E$36^2*$C46)*(1-($C46+1)/(1+E$36)^$C46+$C46/(1+E$36)^($C46+1))+(1+$C$12)/((E$36-$C$12)*(1+E$36)^$C46),"N/A") -> 6.2030528 | F46: =IFERROR((1+F$36)/(F$36^2*$C46)*(1-($C46+1)/(1+F$36)^$C46+$C46/(1+F$36)^($C46+1))+(1+$C$12)/((F$36-$C$12)*(1+F$36)^$C46),"N/A") -> 5.4692276 | G46: =IFERROR((1+G$36)/(G$36^2*$C46)*(1-($C46+1)/(1+G$36)^$C46+$C46/(1+G$36)^($C46+1))+(1+$C$12)/((G$36-$C$12)*(1+G$36)^$C46),"N/A") -> 4.8658689 | H46: =IFERROR((1+H$36)/(H$36^2*$C46)*(1-($C46+1)/(1+H$36)^$C46+$C46/(1+H$36)^($C46+1))+(1+$C$12)/((H$36-$C$12)*(1+H$36)^$C46),"N/A") -> 4.362509
B47: B-3 REQUIRED steady-state Operating Profit (JPY mn)
B48: N = 3 years | C48: 3 | D48: =IFERROR(($C$10/(1-$C$13)-$C$14*D38)/D43,"N/A") -> 1397.8683 | E48: =IFERROR(($C$10/(1-$C$13)-$C$14*E38)/E43,"N/A") -> 1565.3851 | F48: =IFERROR(($C$10/(1-$C$13)-$C$14*F38)/F43,"N/A") -> 1735.5941 | G48: =IFERROR(($C$10/(1-$C$13)-$C$14*G38)/G43,"N/A") -> 1908.4664 | H48: =IFERROR(($C$10/(1-$C$13)-$C$14*H38)/H43,"N/A") -> 2083.973
B49: N = 5 years | C49: 5 | D49: =IFERROR(($C$10/(1-$C$13)-$C$14*D39)/D44,"N/A") -> 1460.227 | E49: =IFERROR(($C$10/(1-$C$13)-$C$14*E39)/E44,"N/A") -> 1650.0994 | F49: =IFERROR(($C$10/(1-$C$13)-$C$14*F39)/F44,"N/A") -> 1845.7571 | G49: =IFERROR(($C$10/(1-$C$13)-$C$14*G39)/G44,"N/A") -> 2047.1705 | H49: =IFERROR(($C$10/(1-$C$13)-$C$14*H39)/H44,"N/A") -> 2254.3076
B50: N = 7 years | C50: 7 | D50: =IFERROR(($C$10/(1-$C$13)-$C$14*D40)/D45,"N/A") -> 1525.5229 | E50: =IFERROR(($C$10/(1-$C$13)-$C$14*E40)/E45,"N/A") -> 1739.3834 | F50: =IFERROR(($C$10/(1-$C$13)-$C$14*F40)/F45,"N/A") -> 1962.5022 | G50: =IFERROR(($C$10/(1-$C$13)-$C$14*G40)/G45,"N/A") -> 2194.8709 | H50: =IFERROR(($C$10/(1-$C$13)-$C$14*H40)/H45,"N/A") -> 2436.4739
B51: N = 10 years | C51: 10 | D51: =IFERROR(($C$10/(1-$C$13)-$C$14*D41)/D46,"N/A") -> 1628.7659 | E51: =IFERROR(($C$10/(1-$C$13)-$C$14*E41)/E46,"N/A") -> 1881.5263 | F51: =IFERROR(($C$10/(1-$C$13)-$C$14*F41)/F46,"N/A") -> 2149.3982 | G51: =IFERROR(($C$10/(1-$C$13)-$C$14*G41)/G46,"N/A") -> 2432.4294 | H51: =IFERROR(($C$10/(1-$C$13)-$C$14*H41)/H46,"N/A") -> 2730.6446
B52: B-4 ... as a multiple of the FY2027/1 会社予想 peak operating profit
B53: N = 3 years | C53: 3 | D53: =IFERROR(D48/$C$15,"N/A") -> 1.3978683 | E53: =IFERROR(E48/$C$15,"N/A") -> 1.5653851 | F53: =IFERROR(F48/$C$15,"N/A") -> 1.7355941 | G53: =IFERROR(G48/$C$15,"N/A") -> 1.9084664 | H53: =IFERROR(H48/$C$15,"N/A") -> 2.083973
B54: N = 5 years | C54: 5 | D54: =IFERROR(D49/$C$15,"N/A") -> 1.460227 | E54: =IFERROR(E49/$C$15,"N/A") -> 1.6500994 | F54: =IFERROR(F49/$C$15,"N/A") -> 1.8457571 | G54: =IFERROR(G49/$C$15,"N/A") -> 2.0471705 | H54: =IFERROR(H49/$C$15,"N/A") -> 2.2543076
B55: N = 7 years | C55: 7 | D55: =IFERROR(D50/$C$15,"N/A") -> 1.5255229 | E55: =IFERROR(E50/$C$15,"N/A") -> 1.7393834 | F55: =IFERROR(F50/$C$15,"N/A") -> 1.9625022 | G55: =IFERROR(G50/$C$15,"N/A") -> 2.1948709 | H55: =IFERROR(H50/$C$15,"N/A") -> 2.4364739
B56: N = 10 years | C56: 10 | D56: =IFERROR(D51/$C$15,"N/A") -> 1.6287659 | E56: =IFERROR(E51/$C$15,"N/A") -> 1.8815263 | F56: =IFERROR(F51/$C$15,"N/A") -> 2.1493982 | G56: =IFERROR(G51/$C$15,"N/A") -> 2.4324294 | H56: =IFERROR(H51/$C$15,"N/A") -> 2.7306446
B58: Block C: Decomposing the required profit into revenue x margin (N = 5 years, model WACC)
B59: The revenue the company must run at, for a given steady-state operating margin, to earn the Block B-3 profit.
B60: Required steady-state Operating Profit (N=5, model WACC) | C60: =F49 -> 1845.7571
B62: Assumed steady-state OPM | C62: Required Revenue | D62: x base-year revenue
B63: 0.067 | C63: =IFERROR($C$60/B63,"N/A") -> 27548.614 | D63: =IFERROR(C63/'DCF Model'!C17,"N/A") -> 2.4728568
B64: 0.0832 | C64: =IFERROR($C$60/B64,"N/A") -> 22184.581 | D64: =IFERROR(C64/'DCF Model'!C17,"N/A") -> 1.991363
B65: 0.104 | C65: =IFERROR($C$60/B65,"N/A") -> 17747.665 | D65: =IFERROR(C65/'DCF Model'!C17,"N/A") -> 1.5930904
B66: 0.128 | C66: =IFERROR($C$60/B66,"N/A") -> 14419.977 | D66: =IFERROR(C66/'DCF Model'!C17,"N/A") -> 1.294386
B67: cycle-peak OPM (FY2027/1 会社予想) | C67: =IFERROR($C$60/$C$18,"N/A") -> 24002.043 | D67: =IFERROR(C67/'DCF Model'!C17,"N/A") -> 2.1545046
B69: Block D: The same question expressed as multiples
B70: Current EV / latest-FY EBITDA (actual) | C70: =IFERROR(C10/'Comps Analysis'!G5,"N/A") -> 12.488351
B71: Current EV / latest-FY Revenue (actual) | C71: =IFERROR(C10/'Comps Analysis'!F5,"N/A") -> 0.91476614
B72: EV / EBITDA if the Block A profit were already earned | C72: =IFERROR(C10/(C25+'DCF Model'!G42),"N/A") -> 5.985888
B73: EV / EBITDA if the Block B-3 (N=5) profit were already earned | C73: =IFERROR(C10/(C60+'DCF Model'!G42),"N/A") -> 5.3186652
B74: Peer median EV / EBITDA (statistics rows) | C74: =IFERROR('Comps Analysis'!D16,"N/A") -> 8.3996313
B75: Rows 3-4 answer: what multiple would today's EV be paying IF the company already earned the profit the price requires?
B77: Block E: Transaction benchmark (control price paid for the direct peer)
B78: Peer row EV / EBITDA at the announced deal terms | C78: =IFERROR('Comps Analysis'!J6,"N/A") -> 9.4216809
B79: Peer row EV / Revenue at the announced deal terms | C79: =IFERROR('Comps Analysis'!K6,"N/A") -> 0.89087898
B80: Subject share price implied by that EV / EBITDA | C80: =IFERROR(ROUND(('Comps Analysis'!G5*'Comps Analysis'!J6-C9)*1000000/C7,0),"N/A") -> 987
B81: Subject share price implied by that EV / Revenue | C81: =IFERROR(ROUND(('Comps Analysis'!F5*'Comps Analysis'!K6-C9)*1000000/C7,0),"N/A") -> 1239
B83: 注1: 上の2行は M&A の支配プレミアム付き取引条件ではなく、レイズネクスト(6379)の 2026-09-02 終値ベースの実勢売買倍率である。プラント現場工事の上場最大手として、当社が『成熟後にどの倍率で評価されるか』の代替アンカーに用いた。シート表題の 'deal terms' は汎用テンプレの文言。
B84: 注2: 上場ピア5社の実勢PER(2026-09-02終値 / 直近本決算純利益)は 1966高田工業所 10.1x / 1716第一カッター 11.6x / 1968太平電業 13.1x / 6379レイズネクスト 15.3x / 1945東京エネシス 15.9x、中央値 13.1x。プロンプト記載の『概ね10〜12倍』より上のレンジに実勢がある。
B85: 注3: ビーエイブル(604A、廃炉・原子力プラント工事、2026-07-29上場)のIPO時想定PER・公開価格は本実行環境から一次ソースで確認できなかったため【取得不可】とし、推測値は置いていない。同社の 2026-09-02 実勢は 時価総額11,225 / FY2025/7実績純利益475.6 = PER 23.6x、EV 12,430 / EBITDA 914 = 13.6x。上場から1か月・7月期決算で比較期間がずれるため comps 統計には入れていない。
B87: Block F: The one-line answer
B88: ="At "&TEXT(C6,"#,##0")&" yen the market is paying for a steady-state operating profit of "&TEXT(F49,"#,##0")&" mn JPY - "&TEXT(F54,"0.00")&"x the FY2027/1 会社予想 cycle peak of "&TEXT(C15,"#,##0")&" mn - reached in 5 years and sustained for ever, against "&TEXT(C14,"#,##0")&" mn actually earned in LTM (2025/05-2026/04)." -> At 1,269 yen the market is paying for a steady-state operating profit of 1,846 mn JPY - 1.85x the FY2027/1 会社予想 cycle peak of 1,000 mn - reached in 5 years and sustained for ever, against 960 mn actually earned in LTM (2025/05-2026/04).
B89: ="Even with no ramp at all (Block A) the price needs "&TEXT(C25,"#,##0")&" mn, or "&TEXT(C26,"0.00")&"x the peak. The base case supports an EV of only "&TEXT(C17,"#,##0")&" mn, leaving "&TEXT(C20,"#,##0")&" yen per share of the current price unexplained by mid-cycle economics." -> Even with no ramp at all (Block A) the price needs 1,632 mn, or 1.63x the peak. The base case supports an EV of only 8,438 mn, leaving 198 yen per share of the current price unexplained by mid-cycle economics.

Sheet NWC Schedule
B2: NWC Schedule - Besterra
B4: Working Capital Drivers (Days) | C4: Base Year | D4: FY2027(E) | E4: FY2028(E) | F4: FY2029(E) | G4: FY2030(E) | H4: FY2031(E)
B5: DSO (Days Sales Outstanding) | C5: =C12/C9*365 -> 130.28459 | D5: =CHOOSE('DCF Model'!$D$27,D25,D26,D27,D28,D29) -> 130 | E5: =CHOOSE('DCF Model'!$D$27,E25,E26,E27,E28,E29) -> 130 | F5: =CHOOSE('DCF Model'!$D$27,F25,F26,F27,F28,F29) -> 130 | G5: =CHOOSE('DCF Model'!$D$27,G25,G26,G27,G28,G29) -> 130 | H5: =CHOOSE('DCF Model'!$D$27,H25,H26,H27,H28,H29) -> 130
B6: DIH (Days Inventory Held) | C6: =C13/C10*365 -> 3.3823629 | D6: =CHOOSE('DCF Model'!$D$27,D32,D33,D34,D35,D36) -> 3.5 | E6: =CHOOSE('DCF Model'!$D$27,E32,E33,E34,E35,E36) -> 3.5 | F6: =CHOOSE('DCF Model'!$D$27,F32,F33,F34,F35,F36) -> 3.5 | G6: =CHOOSE('DCF Model'!$D$27,G32,G33,G34,G35,G36) -> 3.5 | H6: =CHOOSE('DCF Model'!$D$27,H32,H33,H34,H35,H36) -> 3.5
B7: DPO (Days Payable Outstanding) | C7: =C15/C10*365 -> 50.80514 | D7: =CHOOSE('DCF Model'!$D$27,D39,D40,D41,D42,D43) -> 51 | E7: =CHOOSE('DCF Model'!$D$27,E39,E40,E41,E42,E43) -> 51 | F7: =CHOOSE('DCF Model'!$D$27,F39,F40,F41,F42,F43) -> 51 | G7: =CHOOSE('DCF Model'!$D$27,G39,G40,G41,G42,G43) -> 51 | H7: =CHOOSE('DCF Model'!$D$27,H39,H40,H41,H42,H43) -> 51
B8: P&L Reference (JPY mn)
B9: Revenue | C9: 11140.4 | D9: ='DCF Model'!C33 -> 13000.847 | E9: ='DCF Model'!D33 -> 14040.915 | F9: ='DCF Model'!E33 -> 15023.779 | G9: ='DCF Model'!F33 -> 15925.205 | H9: ='DCF Model'!G33 -> 16721.466
B10: COGS | C10: 8902.8 | D10: ='DCF Model'!C34 -> 10335.673 | E10: ='DCF Model'!D34 -> 11092.322 | F10: ='DCF Model'!E34 -> 11838.738 | G10: ='DCF Model'!F34 -> 12501.286 | H10: ='DCF Model'!G34 -> 13126.35
B11: Working Capital Items (JPY mn)
B12: Accounts Receivable | C12: 3976.5 | D12: =D9*D5/365 -> 4630.4386 | E12: =E9*E5/365 -> 5000.8737 | F12: =F9*F5/365 -> 5350.9348 | G12: =G9*G5/365 -> 5671.9909 | H12: =H9*H5/365 -> 5955.5905
B13: Inventory | C13: 82.5 | D13: =D10*D6/365 -> 99.109195 | E13: =E10*E6/365 -> 106.36474 | F13: =F10*F6/365 -> 113.52214 | G13: =G10*G6/365 -> 119.87535 | H13: =H10*H6/365 -> 125.86911
B14: Current Assets (AR + Inv) | C14: =C12+C13 -> 4059 | D14: =D12+D13 -> 4729.5478 | E14: =E12+E13 -> 5107.2384 | F14: =F12+F13 -> 5464.457 | G14: =G12+G13 -> 5791.8663 | H14: =H12+H13 -> 6081.4596
B15: Accounts Payable | C15: 1239.2 | D15: =D10*D7/365 -> 1444.1626 | E15: =E10*E7/365 -> 1549.8862 | F15: =F10*F7/365 -> 1654.1798 | G15: =G10*G7/365 -> 1746.755 | H15: =H10*H7/365 -> 1834.0928
B16: Current Liabilities (AP) | C16: =C15 -> 1239.2 | D16: =D15 -> 1444.1626 | E16: =E15 -> 1549.8862 | F16: =F15 -> 1654.1798 | G16: =G15 -> 1746.755 | H16: =H15 -> 1834.0928
B17: Net Working Capital (JPY mn)
B18: Net Working Capital | C18: =C14-C16 -> 2819.8 | D18: =D14-D16 -> 3285.3852 | E18: =E14-E16 -> 3557.3523 | F18: =F14-F16 -> 3810.2772 | G18: =G14-G16 -> 4045.1112 | H18: =H14-H16 -> 4247.3668
B19: Change in NWC | C19: n/a | D19: =D18-C18 -> 465.58522 | E19: =E18-D18 -> 271.96703 | F19: =F18-E18 -> 252.92496 | G19: =G18-F18 -> 234.83401 | H19: =H18-G18 -> 202.25556
B22: Scenario Input Matrix (Working Capital Days)
D23: FY2027(E) | E23: FY2028(E) | F23: FY2029(E) | G23: FY2030(E) | H23: FY2031(E)
B24: DSO (Days)
B25: Base | D25: 130 | E25: 130 | F25: 130 | G25: 130 | H25: 130
B26: Upside | D26: 120 | E26: 120 | F26: 120 | G26: 120 | H26: 120
B27: Management | D27: 130 | E27: 130 | F27: 130 | G27: 130 | H27: 130
B28: Downside 1 | D28: 145 | E28: 145 | F28: 145 | G28: 145 | H28: 145
B29: Downside 2 | D29: 160 | E29: 160 | F29: 160 | G29: 160 | H29: 160
B31: DIH (Days)
B32: Base | D32: 3.5 | E32: 3.5 | F32: 3.5 | G32: 3.5 | H32: 3.5
B33: Upside | D33: 3.5 | E33: 3.5 | F33: 3.5 | G33: 3.5 | H33: 3.5
B34: Management | D34: 3.5 | E34: 3.5 | F34: 3.5 | G34: 3.5 | H34: 3.5
B35: Downside 1 | D35: 5 | E35: 5 | F35: 5 | G35: 5 | H35: 5
B36: Downside 2 | D36: 8 | E36: 8 | F36: 8 | G36: 8 | H36: 8
B38: DPO (Days)
B39: Base | D39: 51 | E39: 51 | F39: 51 | G39: 51 | H39: 51
B40: Upside | D40: 55 | E40: 55 | F40: 55 | G40: 55 | H40: 55
B41: Management | D41: 51 | E41: 51 | F41: 51 | G41: 51 | H41: 51
B42: Downside 1 | D42: 48 | E42: 48 | F42: 48 | G42: 48 | H42: 48
B43: Downside 2 | D43: 45 | E43: 45 | F43: 45 | G43: 45 | H43: 45

Sheet Comps Analysis
B2: Comparable Company Analysis
B3: Peer prices as of 2026-09-03 (Mkt Cap / EV of peer rows are static CSV values; the subject row is live-linked to Executive Summary)
B4: Company | C4: Ticker | D4: Mkt Cap (JPY mn) | E4: EV (JPY mn) | F4: Revenue (JPY mn) | G4: EBITDA (JPY mn) | H4: Op Income (JPY mn) | I4: Net Income (JPY mn) | J4: EV/EBITDA | K4: EV/Revenue | L4: PER | M4: PBR | N4: Op Margin | O4: ROE | P4: Book Value (JPY mn) | Q4: Note
B5: Besterra (1433) [subject] | C5: 1433.T | D5: ='Executive Summary'!C9*C23/1000000 -> 11244.495 | E5: =D5+C24 -> 10190.495 | F5: 11140 | G5: 816 | H5: 741 | I5: 733 | J5: =IFERROR(E5/G5,"") -> 12.488351 | K5: =IFERROR(E5/F5,"") -> 0.91476614 | L5: =IFERROR(D5/I5,"") -> 15.340375 | M5: =IFERROR(D5/P5,"") -> 2.0978535 | N5: =IFERROR(H5/F5,"") -> 0.066517056 | O5: =IFERROR(I5/P5,"") -> 0.13675373 | P5: 5360
B6: RAIZNEXT (6379) FY2026/3 | C6: 6379.T | D6: 160131 | E6: 155486 | F6: 174531 | G6: 16503 | H6: 14714 | I6: 10459 | J6: =IFERROR(E6/G6,"") -> 9.4216809 | K6: =IFERROR(E6/F6,"") -> 0.89087898 | L6: =IFERROR(D6/I6,"") -> 15.310355 | M6: =IFERROR(D6/P6,"") -> 1.7505439 | N6: =IFERROR(H6/F6,"") -> 0.08430594 | O6: =IFERROR(I6/P6,"") -> 0.11433725 | P6: 91475
B7: Taihei Dengyo (1968) FY2026/3 | C7: 1968.T | D7: 155363 | E7: 136704 | F7: 141657 | G7: 16275 | H7: 14840 | I7: 11902 | J7: =IFERROR(E7/G7,"") -> 8.3996313 | K7: =IFERROR(E7/F7,"") -> 0.96503526 | L7: =IFERROR(D7/I7,"") -> 13.05352 | M7: =IFERROR(D7/P7,"") -> 1.2289821 | N7: =IFERROR(H7/F7,"") -> 0.10476009 | O7: =IFERROR(I7/P7,"") -> 0.094149475 | P7: 126416
B8: Tokyo Energy & Systems (1945) FY2026/3 | C8: 1945.T | D8: 67926 | E8: 76372 | F8: 83083 | G8: 6773 | H8: 4739 | I8: 4287 | J8: =IFERROR(E8/G8,"") -> 11.275949 | K8: =IFERROR(E8/F8,"") -> 0.91922535 | L8: =IFERROR(D8/I8,"") -> 15.844647 | M8: =IFERROR(D8/P8,"") -> 0.937544 | N8: =IFERROR(H8/F8,"") -> 0.057039346 | O8: =IFERROR(I8/P8,"") -> 0.059171026 | P8: 72451
B9: Takada Corporation (1966) FY2026/3 | C9: 1966.T | D9: 12704 | E9: 20094 | F9: 53694 | G9: 2629 | H9: 1779 | I9: 1255 | J9: =IFERROR(E9/G9,"") -> 7.6432103 | K9: =IFERROR(E9/F9,"") -> 0.37423176 | L9: =IFERROR(D9/I9,"") -> 10.122709 | M9: =IFERROR(D9/P9,"") -> 0.58489871 | N9: =IFERROR(H9/F9,"") -> 0.033132194 | O9: =IFERROR(I9/P9,"") -> 0.057780847 | P9: 21720
B10: Dai-ichi Cutter Kogyo (1716) FY2025/6 | C10: 1716.T | D10: 15433 | E10: 5963 | F10: 20229 | G10: 2497 | H10: 1647 | I10: 1328 | J10: =IFERROR(E10/G10,"") -> 2.3880657 | K10: =IFERROR(E10/F10,"") -> 0.29477483 | L10: =IFERROR(D10/I10,"") -> 11.621235 | M10: =IFERROR(D10/P10,"") -> 0.8025481 | N10: =IFERROR(H10/F10,"") -> 0.081417767 | O10: =IFERROR(I10/P10,"") -> 0.069058762 | P10: 19230
B14: Statistics
B15: 25th Percentile | D15: =PERCENTILE(J6:J10,0.25) -> 7.6432103 | E15: =PERCENTILE(K6:K10,0.25) -> 0.37423176 | F15: =PERCENTILE(L6:L10,0.25) -> 11.621235 | G15: =PERCENTILE(M6:M10,0.25) -> 0.8025481 | H15: =PERCENTILE(N6:N10,0.25) -> 0.057039346 | I15: =PERCENTILE(O6:O10,0.25) -> 0.059171026
B16: Median (50th) | D16: =MEDIAN(J6:J10) -> 8.3996313 | E16: =MEDIAN(K6:K10) -> 0.89087898 | F16: =MEDIAN(L6:L10) -> 13.05352 | G16: =MEDIAN(M6:M10) -> 0.937544 | H16: =MEDIAN(N6:N10) -> 0.081417767 | I16: =MEDIAN(O6:O10) -> 0.069058762
B17: 75th Percentile | D17: =PERCENTILE(J6:J10,0.75) -> 9.4216809 | E17: =PERCENTILE(K6:K10,0.75) -> 0.91922535 | F17: =PERCENTILE(L6:L10,0.75) -> 15.310355 | G17: =PERCENTILE(M6:M10,0.75) -> 1.2289821 | H17: =PERCENTILE(N6:N10,0.75) -> 0.08430594 | I17: =PERCENTILE(O6:O10,0.75) -> 0.094149475
B19: Implied Valuation for Besterra
B20: Besterra Financials
B21: EBITDA (JPY mn) | C21: 816
B22: Net Income (JPY mn) | C22: 732.6
B23: Shares Outstanding | C23: 8860910
B24: Net Debt (JPY mn) | C24: -1054
B26: Implied Share Price (Median Multiples)
B27: Via EV/EBITDA (Median) | C27: =ROUND((C21*D16-C24)*1000000/C23,0) -> 892
B28: Via PER (Median) | C28: =ROUND(C22*F16*1000000/C23,0) -> 1079
B29: Net Income normalized (FY2026/1、特別損益の税後影響を控除) [参考・Target不算入] | C29: 567 | D29: 567 = 報告純利益 732.617 − (特別利益 252.044 − 特別損失 13.221) × (1 − 0.306)。FY2026/1 の特別利益252.0の内訳は 投資有価証券売却益 140.0 + 関係会社株式売却益 111.8 + 固定資産売却益 0.2 + その他 0.1 で、いずれも本業の稼得力ではない。ヘッドラインPERは分母が膨らんだぶん実力より低く出る(現値1,269円で 報告ベース 15.3x に対し正常化ベース 19.8x)。■もう一段厳しい正常化: 経常利益 763.546 に法定税率30.6%を掛けると 530.1(PER 21.2x)。報告純利益の実効税率が26.9%と法定より低い分も落とす分だけ保守的で、こちらの方が理論的には整合する。プロンプト指定の567を採用し、530は本ログに併記した。■同種の売却益は FY2025/1 にも 167.2 あり、投資有価証券残高は 3,403 → 2,236 → 1,919 と取り崩しが続いている。残高1,919百万に対し年140百万ペースなら、この『益』はあと十数年で尽きる性格のものである。
B30: Via PER (Median, normalized NI) [参考・Target不算入] | C30: =ROUND(C29*F16*1000000/C23,0) -> 835

Sheet Sensitivity Analysis
B2: Sensitivity Analysis
B3: Current WACC: | C3: ='DCF Model'!C26 -> 0.1211565 | E3: Terminal g: | F3: ='DCF Model'!C13 -> 0.01 | H3: Exit Multiple: | I3: ='DCF Model'!C14 -> 6
B5: Table 1: WACC vs Terminal Growth Rate (PGM - Implied Share Price, JPY)
B6: WACC \ Terminal g | C6: =$F$3-0.0075 -> 0.0025 | D6: =$F$3-0.005 -> 0.005 | E6: =$F$3-0.0025 -> 0.0075 | F6: =$F$3 -> 0.01 | G6: =$F$3+0.0025 -> 0.0125 | H6: =$F$3+0.005 -> 0.015 | I6: =$F$3+0.0075 -> 0.0175
B7: =$C$3-0.015 -> 0.1061565 | C7: =IFERROR(ROUND(('DCF Model'!C45/(1+$B7)^('DCF Model'!C19+0)+'DCF Model'!D45/(1+$B7)^('DCF Model'!C19+1)+'DCF Model'!E45/(1+$B7)^('DCF Model'!C19+2)+'DCF Model'!F45/(1+$B7)^('DCF Model'!C19+3)+'DCF Model'!G45/(1+$B7)^('DCF Model'!C19+4)+'DCF Model'!G45*(1+C$6)/($B7-C$6)/(1+$B7)^('DCF Model'!C19+4)-'DCF Model'!C16)*1000000/'DCF Model'!C15,0),"") -> 1166 | D7: =IFERROR(ROUND(('DCF Model'!C45/(1+$B7)^('DCF Model'!C19+0)+'DCF Model'!D45/(1+$B7)^('DCF Model'!C19+1)+'DCF Model'!E45/(1+$B7)^('DCF Model'!C19+2)+'DCF Model'!F45/(1+$B7)^('DCF Model'!C19+3)+'DCF Model'!G45/(1+$B7)^('DCF Model'!C19+4)+'DCF Model'!G45*(1+D$6)/($B7-D$6)/(1+$B7)^('DCF Model'!C19+4)-'DCF Model'!C16)*1000000/'DCF Model'!C15,0),"") -> 1185 | E7: =IFERROR(ROUND(('DCF Model'!C45/(1+$B7)^('DCF Model'!C19+0)+'DCF Model'!D45/(1+$B7)^('DCF Model'!C19+1)+'DCF Model'!E45/(1+$B7)^('DCF Model'!C19+2)+'DCF Model'!F45/(1+$B7)^('DCF Model'!C19+3)+'DCF Model'!G45/(1+$B7)^('DCF Model'!C19+4)+'DCF Model'!G45*(1+E$6)/($B7-E$6)/(1+$B7)^('DCF Model'!C19+4)-'DCF Model'!C16)*1000000/'DCF Model'!C15,0),"") -> 1206 | F7: =IFERROR(ROUND(('DCF Model'!C45/(1+$B7)^('DCF Model'!C19+0)+'DCF Model'!D45/(1+$B7)^('DCF Model'!C19+1)+'DCF Model'!E45/(1+$B7)^('DCF Model'!C19+2)+'DCF Model'!F45/(1+$B7)^('DCF Model'!C19+3)+'DCF Model'!G45/(1+$B7)^('DCF Model'!C19+4)+'DCF Model'!G45*(1+F$6)/($B7-F$6)/(1+$B7)^('DCF Model'!C19+4)-'DCF Model'!C16)*1000000/'DCF Model'!C15,0),"") -> 1228 | G7: =IFERROR(ROUND(('DCF Model'!C45/(1+$B7)^('DCF Model'!C19+0)+'DCF Model'!D45/(1+$B7)^('DCF Model'!C19+1)+'DCF Model'!E45/(1+$B7)^('DCF Model'!C19+2)+'DCF Model'!F45/(1+$B7)^('DCF Model'!C19+3)+'DCF Model'!G45/(1+$B7)^('DCF Model'!C19+4)+'DCF Model'!G45*(1+G$6)/($B7-G$6)/(1+$B7)^('DCF Model'!C19+4)-'DCF Model'!C16)*1000000/'DCF Model'!C15,0),"") -> 1251 | H7: =IFERROR(ROUND(('DCF Model'!C45/(1+$B7)^('DCF Model'!C19+0)+'DCF Model'!D45/(1+$B7)^('DCF Model'!C19+1)+'DCF Model'!E45/(1+$B7)^('DCF Model'!C19+2)+'DCF Model'!F45/(1+$B7)^('DCF Model'!C19+3)+'DCF Model'!G45/(1+$B7)^('DCF Model'!C19+4)+'DCF Model'!G45*(1+H$6)/($B7-H$6)/(1+$B7)^('DCF Model'!C19+4)-'DCF Model'!C16)*1000000/'DCF Model'!C15,0),"") -> 1275 | I7: =IFERROR(ROUND(('DCF Model'!C45/(1+$B7)^('DCF Model'!C19+0)+'DCF Model'!D45/(1+$B7)^('DCF Model'!C19+1)+'DCF Model'!E45/(1+$B7)^('DCF Model'!C19+2)+'DCF Model'!F45/(1+$B7)^('DCF Model'!C19+3)+'DCF Model'!G45/(1+$B7)^('DCF Model'!C19+4)+'DCF Model'!G45*(1+I$6)/($B7-I$6)/(1+$B7)^('DCF Model'!C19+4)-'DCF Model'!C16)*1000000/'DCF Model'!C15,0),"") -> 1301
B8: =$C$3-0.01 -> 0.1111565 | C8: =IFERROR(ROUND(('DCF Model'!C45/(1+$B8)^('DCF Model'!C19+0)+'DCF Model'!D45/(1+$B8)^('DCF Model'!C19+1)+'DCF Model'!E45/(1+$B8)^('DCF Model'!C19+2)+'DCF Model'!F45/(1+$B8)^('DCF Model'!C19+3)+'DCF Model'!G45/(1+$B8)^('DCF Model'!C19+4)+'DCF Model'!G45*(1+C$6)/($B8-C$6)/(1+$B8)^('DCF Model'!C19+4)-'DCF Model'!C16)*1000000/'DCF Model'!C15,0),"") -> 1115 | D8: =IFERROR(ROUND(('DCF Model'!C45/(1+$B8)^('DCF Model'!C19+0)+'DCF Model'!D45/(1+$B8)^('DCF Model'!C19+1)+'DCF Model'!E45/(1+$B8)^('DCF Model'!C19+2)+'DCF Model'!F45/(1+$B8)^('DCF Model'!C19+3)+'DCF Model'!G45/(1+$B8)^('DCF Model'!C19+4)+'DCF Model'!G45*(1+D$6)/($B8-D$6)/(1+$B8)^('DCF Model'!C19+4)-'DCF Model'!C16)*1000000/'DCF Model'!C15,0),"") -> 1133 | E8: =IFERROR(ROUND(('DCF Model'!C45/(1+$B8)^('DCF Model'!C19+0)+'DCF Model'!D45/(1+$B8)^('DCF Model'!C19+1)+'DCF Model'!E45/(1+$B8)^('DCF Model'!C19+2)+'DCF Model'!F45/(1+$B8)^('DCF Model'!C19+3)+'DCF Model'!G45/(1+$B8)^('DCF Model'!C19+4)+'DCF Model'!G45*(1+E$6)/($B8-E$6)/(1+$B8)^('DCF Model'!C19+4)-'DCF Model'!C16)*1000000/'DCF Model'!C15,0),"") -> 1151 | F8: =IFERROR(ROUND(('DCF Model'!C45/(1+$B8)^('DCF Model'!C19+0)+'DCF Model'!D45/(1+$B8)^('DCF Model'!C19+1)+'DCF Model'!E45/(1+$B8)^('DCF Model'!C19+2)+'DCF Model'!F45/(1+$B8)^('DCF Model'!C19+3)+'DCF Model'!G45/(1+$B8)^('DCF Model'!C19+4)+'DCF Model'!G45*(1+F$6)/($B8-F$6)/(1+$B8)^('DCF Model'!C19+4)-'DCF Model'!C16)*1000000/'DCF Model'!C15,0),"") -> 1170 | G8: =IFERROR(ROUND(('DCF Model'!C45/(1+$B8)^('DCF Model'!C19+0)+'DCF Model'!D45/(1+$B8)^('DCF Model'!C19+1)+'DCF Model'!E45/(1+$B8)^('DCF Model'!C19+2)+'DCF Model'!F45/(1+$B8)^('DCF Model'!C19+3)+'DCF Model'!G45/(1+$B8)^('DCF Model'!C19+4)+'DCF Model'!G45*(1+G$6)/($B8-G$6)/(1+$B8)^('DCF Model'!C19+4)-'DCF Model'!C16)*1000000/'DCF Model'!C15,0),"") -> 1191 | H8: =IFERROR(ROUND(('DCF Model'!C45/(1+$B8)^('DCF Model'!C19+0)+'DCF Model'!D45/(1+$B8)^('DCF Model'!C19+1)+'DCF Model'!E45/(1+$B8)^('DCF Model'!C19+2)+'DCF Model'!F45/(1+$B8)^('DCF Model'!C19+3)+'DCF Model'!G45/(1+$B8)^('DCF Model'!C19+4)+'DCF Model'!G45*(1+H$6)/($B8-H$6)/(1+$B8)^('DCF Model'!C19+4)-'DCF Model'!C16)*1000000/'DCF Model'!C15,0),"") -> 1212 | I8: =IFERROR(ROUND(('DCF Model'!C45/(1+$B8)^('DCF Model'!C19+0)+'DCF Model'!D45/(1+$B8)^('DCF Model'!C19+1)+'DCF Model'!E45/(1+$B8)^('DCF Model'!C19+2)+'DCF Model'!F45/(1+$B8)^('DCF Model'!C19+3)+'DCF Model'!G45/(1+$B8)^('DCF Model'!C19+4)+'DCF Model'!G45*(1+I$6)/($B8-I$6)/(1+$B8)^('DCF Model'!C19+4)-'DCF Model'!C16)*1000000/'DCF Model'!C15,0),"") -> 1235
B9: =$C$3-0.005 -> 0.1161565 | C9: =IFERROR(ROUND(('DCF Model'!C45/(1+$B9)^('DCF Model'!C19+0)+'DCF Model'!D45/(1+$B9)^('DCF Model'!C19+1)+'DCF Model'!E45/(1+$B9)^('DCF Model'!C19+2)+'DCF Model'!F45/(1+$B9)^('DCF Model'!C19+3)+'DCF Model'!G45/(1+$B9)^('DCF Model'!C19+4)+'DCF Model'!G45*(1+C$6)/($B9-C$6)/(1+$B9)^('DCF Model'!C19+4)-'DCF Model'!C16)*1000000/'DCF Model'!C15,0),"") -> 1069 | D9: =IFERROR(ROUND(('DCF Model'!C45/(1+$B9)^('DCF Model'!C19+0)+'DCF Model'!D45/(1+$B9)^('DCF Model'!C19+1)+'DCF Model'!E45/(1+$B9)^('DCF Model'!C19+2)+'DCF Model'!F45/(1+$B9)^('DCF Model'!C19+3)+'DCF Model'!G45/(1+$B9)^('DCF Model'!C19+4)+'DCF Model'!G45*(1+D$6)/($B9-D$6)/(1+$B9)^('DCF Model'!C19+4)-'DCF Model'!C16)*1000000/'DCF Model'!C15,0),"") -> 1084 | E9: =IFERROR(ROUND(('DCF Model'!C45/(1+$B9)^('DCF Model'!C19+0)+'DCF Model'!D45/(1+$B9)^('DCF Model'!C19+1)+'DCF Model'!E45/(1+$B9)^('DCF Model'!C19+2)+'DCF Model'!F45/(1+$B9)^('DCF Model'!C19+3)+'DCF Model'!G45/(1+$B9)^('DCF Model'!C19+4)+'DCF Model'!G45*(1+E$6)/($B9-E$6)/(1+$B9)^('DCF Model'!C19+4)-'DCF Model'!C16)*1000000/'DCF Model'!C15,0),"") -> 1101 | F9: =IFERROR(ROUND(('DCF Model'!C45/(1+$B9)^('DCF Model'!C19+0)+'DCF Model'!D45/(1+$B9)^('DCF Model'!C19+1)+'DCF Model'!E45/(1+$B9)^('DCF Model'!C19+2)+'DCF Model'!F45/(1+$B9)^('DCF Model'!C19+3)+'DCF Model'!G45/(1+$B9)^('DCF Model'!C19+4)+'DCF Model'!G45*(1+F$6)/($B9-F$6)/(1+$B9)^('DCF Model'!C19+4)-'DCF Model'!C16)*1000000/'DCF Model'!C15,0),"") -> 1118 | G9: =IFERROR(ROUND(('DCF Model'!C45/(1+$B9)^('DCF Model'!C19+0)+'DCF Model'!D45/(1+$B9)^('DCF Model'!C19+1)+'DCF Model'!E45/(1+$B9)^('DCF Model'!C19+2)+'DCF Model'!F45/(1+$B9)^('DCF Model'!C19+3)+'DCF Model'!G45/(1+$B9)^('DCF Model'!C19+4)+'DCF Model'!G45*(1+G$6)/($B9-G$6)/(1+$B9)^('DCF Model'!C19+4)-'DCF Model'!C16)*1000000/'DCF Model'!C15,0),"") -> 1137 | H9: =IFERROR(ROUND(('DCF Model'!C45/(1+$B9)^('DCF Model'!C19+0)+'DCF Model'!D45/(1+$B9)^('DCF Model'!C19+1)+'DCF Model'!E45/(1+$B9)^('DCF Model'!C19+2)+'DCF Model'!F45/(1+$B9)^('DCF Model'!C19+3)+'DCF Model'!G45/(1+$B9)^('DCF Model'!C19+4)+'DCF Model'!G45*(1+H$6)/($B9-H$6)/(1+$B9)^('DCF Model'!C19+4)-'DCF Model'!C16)*1000000/'DCF Model'!C15,0),"") -> 1156 | I9: =IFERROR(ROUND(('DCF Model'!C45/(1+$B9)^('DCF Model'!C19+0)+'DCF Model'!D45/(1+$B9)^('DCF Model'!C19+1)+'DCF Model'!E45/(1+$B9)^('DCF Model'!C19+2)+'DCF Model'!F45/(1+$B9)^('DCF Model'!C19+3)+'DCF Model'!G45/(1+$B9)^('DCF Model'!C19+4)+'DCF Model'!G45*(1+I$6)/($B9-I$6)/(1+$B9)^('DCF Model'!C19+4)-'DCF Model'!C16)*1000000/'DCF Model'!C15,0),"") -> 1176
B10: =$C$3 -> 0.1211565 | C10: =IFERROR(ROUND(('DCF Model'!C45/(1+$B10)^('DCF Model'!C19+0)+'DCF Model'!D45/(1+$B10)^('DCF Model'!C19+1)+'DCF Model'!E45/(1+$B10)^('DCF Model'!C19+2)+'DCF Model'!F45/(1+$B10)^('DCF Model'!C19+3)+'DCF Model'!G45/(1+$B10)^('DCF Model'!C19+4)+'DCF Model'!G45*(1+C$6)/($B10-C$6)/(1+$B10)^('DCF Model'!C19+4)-'DCF Model'!C16)*1000000/'DCF Model'!C15,0),"") -> 1026 | D10: =IFERROR(ROUND(('DCF Model'!C45/(1+$B10)^('DCF Model'!C19+0)+'DCF Model'!D45/(1+$B10)^('DCF Model'!C19+1)+'DCF Model'!E45/(1+$B10)^('DCF Model'!C19+2)+'DCF Model'!F45/(1+$B10)^('DCF Model'!C19+3)+'DCF Model'!G45/(1+$B10)^('DCF Model'!C19+4)+'DCF Model'!G45*(1+D$6)/($B10-D$6)/(1+$B10)^('DCF Model'!C19+4)-'DCF Model'!C16)*1000000/'DCF Model'!C15,0),"") -> 1041 | E10: =IFERROR(ROUND(('DCF Model'!C45/(1+$B10)^('DCF Model'!C19+0)+'DCF Model'!D45/(1+$B10)^('DCF Model'!C19+1)+'DCF Model'!E45/(1+$B10)^('DCF Model'!C19+2)+'DCF Model'!F45/(1+$B10)^('DCF Model'!C19+3)+'DCF Model'!G45/(1+$B10)^('DCF Model'!C19+4)+'DCF Model'!G45*(1+E$6)/($B10-E$6)/(1+$B10)^('DCF Model'!C19+4)-'DCF Model'!C16)*1000000/'DCF Model'!C15,0),"") -> 1056 | F10: =IFERROR(ROUND(('DCF Model'!C45/(1+$B10)^('DCF Model'!C19+0)+'DCF Model'!D45/(1+$B10)^('DCF Model'!C19+1)+'DCF Model'!E45/(1+$B10)^('DCF Model'!C19+2)+'DCF Model'!F45/(1+$B10)^('DCF Model'!C19+3)+'DCF Model'!G45/(1+$B10)^('DCF Model'!C19+4)+'DCF Model'!G45*(1+F$6)/($B10-F$6)/(1+$B10)^('DCF Model'!C19+4)-'DCF Model'!C16)*1000000/'DCF Model'!C15,0),"") -> 1071 | G10: =IFERROR(ROUND(('DCF Model'!C45/(1+$B10)^('DCF Model'!C19+0)+'DCF Model'!D45/(1+$B10)^('DCF Model'!C19+1)+'DCF Model'!E45/(1+$B10)^('DCF Model'!C19+2)+'DCF Model'!F45/(1+$B10)^('DCF Model'!C19+3)+'DCF Model'!G45/(1+$B10)^('DCF Model'!C19+4)+'DCF Model'!G45*(1+G$6)/($B10-G$6)/(1+$B10)^('DCF Model'!C19+4)-'DCF Model'!C16)*1000000/'DCF Model'!C15,0),"") -> 1088 | H10: =IFERROR(ROUND(('DCF Model'!C45/(1+$B10)^('DCF Model'!C19+0)+'DCF Model'!D45/(1+$B10)^('DCF Model'!C19+1)+'DCF Model'!E45/(1+$B10)^('DCF Model'!C19+2)+'DCF Model'!F45/(1+$B10)^('DCF Model'!C19+3)+'DCF Model'!G45/(1+$B10)^('DCF Model'!C19+4)+'DCF Model'!G45*(1+H$6)/($B10-H$6)/(1+$B10)^('DCF Model'!C19+4)-'DCF Model'!C16)*1000000/'DCF Model'!C15,0),"") -> 1105 | I10: =IFERROR(ROUND(('DCF Model'!C45/(1+$B10)^('DCF Model'!C19+0)+'DCF Model'!D45/(1+$B10)^('DCF Model'!C19+1)+'DCF Model'!E45/(1+$B10)^('DCF Model'!C19+2)+'DCF Model'!F45/(1+$B10)^('DCF Model'!C19+3)+'DCF Model'!G45/(1+$B10)^('DCF Model'!C19+4)+'DCF Model'!G45*(1+I$6)/($B10-I$6)/(1+$B10)^('DCF Model'!C19+4)-'DCF Model'!C16)*1000000/'DCF Model'!C15,0),"") -> 1123
B11: =$C$3+0.005 -> 0.1261565 | C11: =IFERROR(ROUND(('DCF Model'!C45/(1+$B11)^('DCF Model'!C19+0)+'DCF Model'!D45/(1+$B11)^('DCF Model'!C19+1)+'DCF Model'!E45/(1+$B11)^('DCF Model'!C19+2)+'DCF Model'!F45/(1+$B11)^('DCF Model'!C19+3)+'DCF Model'!G45/(1+$B11)^('DCF Model'!C19+4)+'DCF Model'!G45*(1+C$6)/($B11-C$6)/(1+$B11)^('DCF Model'!C19+4)-'DCF Model'!C16)*1000000/'DCF Model'!C15,0),"") -> 987 | D11: =IFERROR(ROUND(('DCF Model'!C45/(1+$B11)^('DCF Model'!C19+0)+'DCF Model'!D45/(1+$B11)^('DCF Model'!C19+1)+'DCF Model'!E45/(1+$B11)^('DCF Model'!C19+2)+'DCF Model'!F45/(1+$B11)^('DCF Model'!C19+3)+'DCF Model'!G45/(1+$B11)^('DCF Model'!C19+4)+'DCF Model'!G45*(1+D$6)/($B11-D$6)/(1+$B11)^('DCF Model'!C19+4)-'DCF Model'!C16)*1000000/'DCF Model'!C15,0),"") -> 1000 | E11: =IFERROR(ROUND(('DCF Model'!C45/(1+$B11)^('DCF Model'!C19+0)+'DCF Model'!D45/(1+$B11)^('DCF Model'!C19+1)+'DCF Model'!E45/(1+$B11)^('DCF Model'!C19+2)+'DCF Model'!F45/(1+$B11)^('DCF Model'!C19+3)+'DCF Model'!G45/(1+$B11)^('DCF Model'!C19+4)+'DCF Model'!G45*(1+E$6)/($B11-E$6)/(1+$B11)^('DCF Model'!C19+4)-'DCF Model'!C16)*1000000/'DCF Model'!C15,0),"") -> 1014 | F11: =IFERROR(ROUND(('DCF Model'!C45/(1+$B11)^('DCF Model'!C19+0)+'DCF Model'!D45/(1+$B11)^('DCF Model'!C19+1)+'DCF Model'!E45/(1+$B11)^('DCF Model'!C19+2)+'DCF Model'!F45/(1+$B11)^('DCF Model'!C19+3)+'DCF Model'!G45/(1+$B11)^('DCF Model'!C19+4)+'DCF Model'!G45*(1+F$6)/($B11-F$6)/(1+$B11)^('DCF Model'!C19+4)-'DCF Model'!C16)*1000000/'DCF Model'!C15,0),"") -> 1028 | G11: =IFERROR(ROUND(('DCF Model'!C45/(1+$B11)^('DCF Model'!C19+0)+'DCF Model'!D45/(1+$B11)^('DCF Model'!C19+1)+'DCF Model'!E45/(1+$B11)^('DCF Model'!C19+2)+'DCF Model'!F45/(1+$B11)^('DCF Model'!C19+3)+'DCF Model'!G45/(1+$B11)^('DCF Model'!C19+4)+'DCF Model'!G45*(1+G$6)/($B11-G$6)/(1+$B11)^('DCF Model'!C19+4)-'DCF Model'!C16)*1000000/'DCF Model'!C15,0),"") -> 1043 | H11: =IFERROR(ROUND(('DCF Model'!C45/(1+$B11)^('DCF Model'!C19+0)+'DCF Model'!D45/(1+$B11)^('DCF Model'!C19+1)+'DCF Model'!E45/(1+$B11)^('DCF Model'!C19+2)+'DCF Model'!F45/(1+$B11)^('DCF Model'!C19+3)+'DCF Model'!G45/(1+$B11)^('DCF Model'!C19+4)+'DCF Model'!G45*(1+H$6)/($B11-H$6)/(1+$B11)^('DCF Model'!C19+4)-'DCF Model'!C16)*1000000/'DCF Model'!C15,0),"") -> 1058 | I11: =IFERROR(ROUND(('DCF Model'!C45/(1+$B11)^('DCF Model'!C19+0)+'DCF Model'!D45/(1+$B11)^('DCF Model'!C19+1)+'DCF Model'!E45/(1+$B11)^('DCF Model'!C19+2)+'DCF Model'!F45/(1+$B11)^('DCF Model'!C19+3)+'DCF Model'!G45/(1+$B11)^('DCF Model'!C19+4)+'DCF Model'!G45*(1+I$6)/($B11-I$6)/(1+$B11)^('DCF Model'!C19+4)-'DCF Model'!C16)*1000000/'DCF Model'!C15,0),"") -> 1074
B12: =$C$3+0.01 -> 0.1311565 | C12: =IFERROR(ROUND(('DCF Model'!C45/(1+$B12)^('DCF Model'!C19+0)+'DCF Model'!D45/(1+$B12)^('DCF Model'!C19+1)+'DCF Model'!E45/(1+$B12)^('DCF Model'!C19+2)+'DCF Model'!F45/(1+$B12)^('DCF Model'!C19+3)+'DCF Model'!G45/(1+$B12)^('DCF Model'!C19+4)+'DCF Model'!G45*(1+C$6)/($B12-C$6)/(1+$B12)^('DCF Model'!C19+4)-'DCF Model'!C16)*1000000/'DCF Model'!C15,0),"") -> 952 | D12: =IFERROR(ROUND(('DCF Model'!C45/(1+$B12)^('DCF Model'!C19+0)+'DCF Model'!D45/(1+$B12)^('DCF Model'!C19+1)+'DCF Model'!E45/(1+$B12)^('DCF Model'!C19+2)+'DCF Model'!F45/(1+$B12)^('DCF Model'!C19+3)+'DCF Model'!G45/(1+$B12)^('DCF Model'!C19+4)+'DCF Model'!G45*(1+D$6)/($B12-D$6)/(1+$B12)^('DCF Model'!C19+4)-'DCF Model'!C16)*1000000/'DCF Model'!C15,0),"") -> 963 | E12: =IFERROR(ROUND(('DCF Model'!C45/(1+$B12)^('DCF Model'!C19+0)+'DCF Model'!D45/(1+$B12)^('DCF Model'!C19+1)+'DCF Model'!E45/(1+$B12)^('DCF Model'!C19+2)+'DCF Model'!F45/(1+$B12)^('DCF Model'!C19+3)+'DCF Model'!G45/(1+$B12)^('DCF Model'!C19+4)+'DCF Model'!G45*(1+E$6)/($B12-E$6)/(1+$B12)^('DCF Model'!C19+4)-'DCF Model'!C16)*1000000/'DCF Model'!C15,0),"") -> 976 | F12: =IFERROR(ROUND(('DCF Model'!C45/(1+$B12)^('DCF Model'!C19+0)+'DCF Model'!D45/(1+$B12)^('DCF Model'!C19+1)+'DCF Model'!E45/(1+$B12)^('DCF Model'!C19+2)+'DCF Model'!F45/(1+$B12)^('DCF Model'!C19+3)+'DCF Model'!G45/(1+$B12)^('DCF Model'!C19+4)+'DCF Model'!G45*(1+F$6)/($B12-F$6)/(1+$B12)^('DCF Model'!C19+4)-'DCF Model'!C16)*1000000/'DCF Model'!C15,0),"") -> 989 | G12: =IFERROR(ROUND(('DCF Model'!C45/(1+$B12)^('DCF Model'!C19+0)+'DCF Model'!D45/(1+$B12)^('DCF Model'!C19+1)+'DCF Model'!E45/(1+$B12)^('DCF Model'!C19+2)+'DCF Model'!F45/(1+$B12)^('DCF Model'!C19+3)+'DCF Model'!G45/(1+$B12)^('DCF Model'!C19+4)+'DCF Model'!G45*(1+G$6)/($B12-G$6)/(1+$B12)^('DCF Model'!C19+4)-'DCF Model'!C16)*1000000/'DCF Model'!C15,0),"") -> 1002 | H12: =IFERROR(ROUND(('DCF Model'!C45/(1+$B12)^('DCF Model'!C19+0)+'DCF Model'!D45/(1+$B12)^('DCF Model'!C19+1)+'DCF Model'!E45/(1+$B12)^('DCF Model'!C19+2)+'DCF Model'!F45/(1+$B12)^('DCF Model'!C19+3)+'DCF Model'!G45/(1+$B12)^('DCF Model'!C19+4)+'DCF Model'!G45*(1+H$6)/($B12-H$6)/(1+$B12)^('DCF Model'!C19+4)-'DCF Model'!C16)*1000000/'DCF Model'!C15,0),"") -> 1016 | I12: =IFERROR(ROUND(('DCF Model'!C45/(1+$B12)^('DCF Model'!C19+0)+'DCF Model'!D45/(1+$B12)^('DCF Model'!C19+1)+'DCF Model'!E45/(1+$B12)^('DCF Model'!C19+2)+'DCF Model'!F45/(1+$B12)^('DCF Model'!C19+3)+'DCF Model'!G45/(1+$B12)^('DCF Model'!C19+4)+'DCF Model'!G45*(1+I$6)/($B12-I$6)/(1+$B12)^('DCF Model'!C19+4)-'DCF Model'!C16)*1000000/'DCF Model'!C15,0),"") -> 1030
B13: =$C$3+0.015 -> 0.1361565 | C13: =IFERROR(ROUND(('DCF Model'!C45/(1+$B13)^('DCF Model'!C19+0)+'DCF Model'!D45/(1+$B13)^('DCF Model'!C19+1)+'DCF Model'!E45/(1+$B13)^('DCF Model'!C19+2)+'DCF Model'!F45/(1+$B13)^('DCF Model'!C19+3)+'DCF Model'!G45/(1+$B13)^('DCF Model'!C19+4)+'DCF Model'!G45*(1+C$6)/($B13-C$6)/(1+$B13)^('DCF Model'!C19+4)-'DCF Model'!C16)*1000000/'DCF Model'!C15,0),"") -> 919 | D13: =IFERROR(ROUND(('DCF Model'!C45/(1+$B13)^('DCF Model'!C19+0)+'DCF Model'!D45/(1+$B13)^('DCF Model'!C19+1)+'DCF Model'!E45/(1+$B13)^('DCF Model'!C19+2)+'DCF Model'!F45/(1+$B13)^('DCF Model'!C19+3)+'DCF Model'!G45/(1+$B13)^('DCF Model'!C19+4)+'DCF Model'!G45*(1+D$6)/($B13-D$6)/(1+$B13)^('DCF Model'!C19+4)-'DCF Model'!C16)*1000000/'DCF Model'!C15,0),"") -> 929 | E13: =IFERROR(ROUND(('DCF Model'!C45/(1+$B13)^('DCF Model'!C19+0)+'DCF Model'!D45/(1+$B13)^('DCF Model'!C19+1)+'DCF Model'!E45/(1+$B13)^('DCF Model'!C19+2)+'DCF Model'!F45/(1+$B13)^('DCF Model'!C19+3)+'DCF Model'!G45/(1+$B13)^('DCF Model'!C19+4)+'DCF Model'!G45*(1+E$6)/($B13-E$6)/(1+$B13)^('DCF Model'!C19+4)-'DCF Model'!C16)*1000000/'DCF Model'!C15,0),"") -> 941 | F13: =IFERROR(ROUND(('DCF Model'!C45/(1+$B13)^('DCF Model'!C19+0)+'DCF Model'!D45/(1+$B13)^('DCF Model'!C19+1)+'DCF Model'!E45/(1+$B13)^('DCF Model'!C19+2)+'DCF Model'!F45/(1+$B13)^('DCF Model'!C19+3)+'DCF Model'!G45/(1+$B13)^('DCF Model'!C19+4)+'DCF Model'!G45*(1+F$6)/($B13-F$6)/(1+$B13)^('DCF Model'!C19+4)-'DCF Model'!C16)*1000000/'DCF Model'!C15,0),"") -> 952 | G13: =IFERROR(ROUND(('DCF Model'!C45/(1+$B13)^('DCF Model'!C19+0)+'DCF Model'!D45/(1+$B13)^('DCF Model'!C19+1)+'DCF Model'!E45/(1+$B13)^('DCF Model'!C19+2)+'DCF Model'!F45/(1+$B13)^('DCF Model'!C19+3)+'DCF Model'!G45/(1+$B13)^('DCF Model'!C19+4)+'DCF Model'!G45*(1+G$6)/($B13-G$6)/(1+$B13)^('DCF Model'!C19+4)-'DCF Model'!C16)*1000000/'DCF Model'!C15,0),"") -> 964 | H13: =IFERROR(ROUND(('DCF Model'!C45/(1+$B13)^('DCF Model'!C19+0)+'DCF Model'!D45/(1+$B13)^('DCF Model'!C19+1)+'DCF Model'!E45/(1+$B13)^('DCF Model'!C19+2)+'DCF Model'!F45/(1+$B13)^('DCF Model'!C19+3)+'DCF Model'!G45/(1+$B13)^('DCF Model'!C19+4)+'DCF Model'!G45*(1+H$6)/($B13-H$6)/(1+$B13)^('DCF Model'!C19+4)-'DCF Model'!C16)*1000000/'DCF Model'!C15,0),"") -> 977 | I13: =IFERROR(ROUND(('DCF Model'!C45/(1+$B13)^('DCF Model'!C19+0)+'DCF Model'!D45/(1+$B13)^('DCF Model'!C19+1)+'DCF Model'!E45/(1+$B13)^('DCF Model'!C19+2)+'DCF Model'!F45/(1+$B13)^('DCF Model'!C19+3)+'DCF Model'!G45/(1+$B13)^('DCF Model'!C19+4)+'DCF Model'!G45*(1+I$6)/($B13-I$6)/(1+$B13)^('DCF Model'!C19+4)-'DCF Model'!C16)*1000000/'DCF Model'!C15,0),"") -> 990
B16: Table 2: WACC vs Exit Multiple (Exit Multiple - Implied Share Price, JPY)
B17: WACC \ Exit Multiple | C17: =$I$3-3 -> 3 | D17: =$I$3-2 -> 4 | E17: =$I$3-1 -> 5 | F17: =$I$3 -> 6 | G17: =$I$3+1 -> 7 | H17: =$I$3+2 -> 8 | I17: =$I$3+3 -> 9
B18: =$C$3-0.015 -> 0.1061565 | C18: =IFERROR(ROUND(('DCF Model'!C45/(1+$B18)^('DCF Model'!C19+0)+'DCF Model'!D45/(1+$B18)^('DCF Model'!C19+1)+'DCF Model'!E45/(1+$B18)^('DCF Model'!C19+2)+'DCF Model'!F45/(1+$B18)^('DCF Model'!C19+3)+'DCF Model'!G45/(1+$B18)^('DCF Model'!C19+4)+('DCF Model'!G39+'DCF Model'!G42)*C$17/(1+$B18)^('DCF Model'!C19+4)-'DCF Model'!C16)*1000000/'DCF Model'!C15,0),"") -> 846 | D18: =IFERROR(ROUND(('DCF Model'!C45/(1+$B18)^('DCF Model'!C19+0)+'DCF Model'!D45/(1+$B18)^('DCF Model'!C19+1)+'DCF Model'!E45/(1+$B18)^('DCF Model'!C19+2)+'DCF Model'!F45/(1+$B18)^('DCF Model'!C19+3)+'DCF Model'!G45/(1+$B18)^('DCF Model'!C19+4)+('DCF Model'!G39+'DCF Model'!G42)*D$17/(1+$B18)^('DCF Model'!C19+4)-'DCF Model'!C16)*1000000/'DCF Model'!C15,0),"") -> 980 | E18: =IFERROR(ROUND(('DCF Model'!C45/(1+$B18)^('DCF Model'!C19+0)+'DCF Model'!D45/(1+$B18)^('DCF Model'!C19+1)+'DCF Model'!E45/(1+$B18)^('DCF Model'!C19+2)+'DCF Model'!F45/(1+$B18)^('DCF Model'!C19+3)+'DCF Model'!G45/(1+$B18)^('DCF Model'!C19+4)+('DCF Model'!G39+'DCF Model'!G42)*E$17/(1+$B18)^('DCF Model'!C19+4)-'DCF Model'!C16)*1000000/'DCF Model'!C15,0),"") -> 1115 | F18: =IFERROR(ROUND(('DCF Model'!C45/(1+$B18)^('DCF Model'!C19+0)+'DCF Model'!D45/(1+$B18)^('DCF Model'!C19+1)+'DCF Model'!E45/(1+$B18)^('DCF Model'!C19+2)+'DCF Model'!F45/(1+$B18)^('DCF Model'!C19+3)+'DCF Model'!G45/(1+$B18)^('DCF Model'!C19+4)+('DCF Model'!G39+'DCF Model'!G42)*F$17/(1+$B18)^('DCF Model'!C19+4)-'DCF Model'!C16)*1000000/'DCF Model'!C15,0),"") -> 1249 | G18: =IFERROR(ROUND(('DCF Model'!C45/(1+$B18)^('DCF Model'!C19+0)+'DCF Model'!D45/(1+$B18)^('DCF Model'!C19+1)+'DCF Model'!E45/(1+$B18)^('DCF Model'!C19+2)+'DCF Model'!F45/(1+$B18)^('DCF Model'!C19+3)+'DCF Model'!G45/(1+$B18)^('DCF Model'!C19+4)+('DCF Model'!G39+'DCF Model'!G42)*G$17/(1+$B18)^('DCF Model'!C19+4)-'DCF Model'!C16)*1000000/'DCF Model'!C15,0),"") -> 1383 | H18: =IFERROR(ROUND(('DCF Model'!C45/(1+$B18)^('DCF Model'!C19+0)+'DCF Model'!D45/(1+$B18)^('DCF Model'!C19+1)+'DCF Model'!E45/(1+$B18)^('DCF Model'!C19+2)+'DCF Model'!F45/(1+$B18)^('DCF Model'!C19+3)+'DCF Model'!G45/(1+$B18)^('DCF Model'!C19+4)+('DCF Model'!G39+'DCF Model'!G42)*H$17/(1+$B18)^('DCF Model'!C19+4)-'DCF Model'!C16)*1000000/'DCF Model'!C15,0),"") -> 1518 | I18: =IFERROR(ROUND(('DCF Model'!C45/(1+$B18)^('DCF Model'!C19+0)+'DCF Model'!D45/(1+$B18)^('DCF Model'!C19+1)+'DCF Model'!E45/(1+$B18)^('DCF Model'!C19+2)+'DCF Model'!F45/(1+$B18)^('DCF Model'!C19+3)+'DCF Model'!G45/(1+$B18)^('DCF Model'!C19+4)+('DCF Model'!G39+'DCF Model'!G42)*I$17/(1+$B18)^('DCF Model'!C19+4)-'DCF Model'!C16)*1000000/'DCF Model'!C15,0),"") -> 1652
B19: =$C$3-0.01 -> 0.1111565 | C19: =IFERROR(ROUND(('DCF Model'!C45/(1+$B19)^('DCF Model'!C19+0)+'DCF Model'!D45/(1+$B19)^('DCF Model'!C19+1)+'DCF Model'!E45/(1+$B19)^('DCF Model'!C19+2)+'DCF Model'!F45/(1+$B19)^('DCF Model'!C19+3)+'DCF Model'!G45/(1+$B19)^('DCF Model'!C19+4)+('DCF Model'!G39+'DCF Model'!G42)*C$17/(1+$B19)^('DCF Model'!C19+4)-'DCF Model'!C16)*1000000/'DCF Model'!C15,0),"") -> 834 | D19: =IFERROR(ROUND(('DCF Model'!C45/(1+$B19)^('DCF Model'!C19+0)+'DCF Model'!D45/(1+$B19)^('DCF Model'!C19+1)+'DCF Model'!E45/(1+$B19)^('DCF Model'!C19+2)+'DCF Model'!F45/(1+$B19)^('DCF Model'!C19+3)+'DCF Model'!G45/(1+$B19)^('DCF Model'!C19+4)+('DCF Model'!G39+'DCF Model'!G42)*D$17/(1+$B19)^('DCF Model'!C19+4)-'DCF Model'!C16)*1000000/'DCF Model'!C15,0),"") -> 966 | E19: =IFERROR(ROUND(('DCF Model'!C45/(1+$B19)^('DCF Model'!C19+0)+'DCF Model'!D45/(1+$B19)^('DCF Model'!C19+1)+'DCF Model'!E45/(1+$B19)^('DCF Model'!C19+2)+'DCF Model'!F45/(1+$B19)^('DCF Model'!C19+3)+'DCF Model'!G45/(1+$B19)^('DCF Model'!C19+4)+('DCF Model'!G39+'DCF Model'!G42)*E$17/(1+$B19)^('DCF Model'!C19+4)-'DCF Model'!C16)*1000000/'DCF Model'!C15,0),"") -> 1097 | F19: =IFERROR(ROUND(('DCF Model'!C45/(1+$B19)^('DCF Model'!C19+0)+'DCF Model'!D45/(1+$B19)^('DCF Model'!C19+1)+'DCF Model'!E45/(1+$B19)^('DCF Model'!C19+2)+'DCF Model'!F45/(1+$B19)^('DCF Model'!C19+3)+'DCF Model'!G45/(1+$B19)^('DCF Model'!C19+4)+('DCF Model'!G39+'DCF Model'!G42)*F$17/(1+$B19)^('DCF Model'!C19+4)-'DCF Model'!C16)*1000000/'DCF Model'!C15,0),"") -> 1229 | G19: =IFERROR(ROUND(('DCF Model'!C45/(1+$B19)^('DCF Model'!C19+0)+'DCF Model'!D45/(1+$B19)^('DCF Model'!C19+1)+'DCF Model'!E45/(1+$B19)^('DCF Model'!C19+2)+'DCF Model'!F45/(1+$B19)^('DCF Model'!C19+3)+'DCF Model'!G45/(1+$B19)^('DCF Model'!C19+4)+('DCF Model'!G39+'DCF Model'!G42)*G$17/(1+$B19)^('DCF Model'!C19+4)-'DCF Model'!C16)*1000000/'DCF Model'!C15,0),"") -> 1361 | H19: =IFERROR(ROUND(('DCF Model'!C45/(1+$B19)^('DCF Model'!C19+0)+'DCF Model'!D45/(1+$B19)^('DCF Model'!C19+1)+'DCF Model'!E45/(1+$B19)^('DCF Model'!C19+2)+'DCF Model'!F45/(1+$B19)^('DCF Model'!C19+3)+'DCF Model'!G45/(1+$B19)^('DCF Model'!C19+4)+('DCF Model'!G39+'DCF Model'!G42)*H$17/(1+$B19)^('DCF Model'!C19+4)-'DCF Model'!C16)*1000000/'DCF Model'!C15,0),"") -> 1492 | I19: =IFERROR(ROUND(('DCF Model'!C45/(1+$B19)^('DCF Model'!C19+0)+'DCF Model'!D45/(1+$B19)^('DCF Model'!C19+1)+'DCF Model'!E45/(1+$B19)^('DCF Model'!C19+2)+'DCF Model'!F45/(1+$B19)^('DCF Model'!C19+3)+'DCF Model'!G45/(1+$B19)^('DCF Model'!C19+4)+('DCF Model'!G39+'DCF Model'!G42)*I$17/(1+$B19)^('DCF Model'!C19+4)-'DCF Model'!C16)*1000000/'DCF Model'!C15,0),"") -> 1624
B20: =$C$3-0.005 -> 0.1161565 | C20: =IFERROR(ROUND(('DCF Model'!C45/(1+$B20)^('DCF Model'!C19+0)+'DCF Model'!D45/(1+$B20)^('DCF Model'!C19+1)+'DCF Model'!E45/(1+$B20)^('DCF Model'!C19+2)+'DCF Model'!F45/(1+$B20)^('DCF Model'!C19+3)+'DCF Model'!G45/(1+$B20)^('DCF Model'!C19+4)+('DCF Model'!G39+'DCF Model'!G42)*C$17/(1+$B20)^('DCF Model'!C19+4)-'DCF Model'!C16)*1000000/'DCF Model'!C15,0),"") -> 822 | D20: =IFERROR(ROUND(('DCF Model'!C45/(1+$B20)^('DCF Model'!C19+0)+'DCF Model'!D45/(1+$B20)^('DCF Model'!C19+1)+'DCF Model'!E45/(1+$B20)^('DCF Model'!C19+2)+'DCF Model'!F45/(1+$B20)^('DCF Model'!C19+3)+'DCF Model'!G45/(1+$B20)^('DCF Model'!C19+4)+('DCF Model'!G39+'DCF Model'!G42)*D$17/(1+$B20)^('DCF Model'!C19+4)-'DCF Model'!C16)*1000000/'DCF Model'!C15,0),"") -> 952 | E20: =IFERROR(ROUND(('DCF Model'!C45/(1+$B20)^('DCF Model'!C19+0)+'DCF Model'!D45/(1+$B20)^('DCF Model'!C19+1)+'DCF Model'!E45/(1+$B20)^('DCF Model'!C19+2)+'DCF Model'!F45/(1+$B20)^('DCF Model'!C19+3)+'DCF Model'!G45/(1+$B20)^('DCF Model'!C19+4)+('DCF Model'!G39+'DCF Model'!G42)*E$17/(1+$B20)^('DCF Model'!C19+4)-'DCF Model'!C16)*1000000/'DCF Model'!C15,0),"") -> 1081 | F20: =IFERROR(ROUND(('DCF Model'!C45/(1+$B20)^('DCF Model'!C19+0)+'DCF Model'!D45/(1+$B20)^('DCF Model'!C19+1)+'DCF Model'!E45/(1+$B20)^('DCF Model'!C19+2)+'DCF Model'!F45/(1+$B20)^('DCF Model'!C19+3)+'DCF Model'!G45/(1+$B20)^('DCF Model'!C19+4)+('DCF Model'!G39+'DCF Model'!G42)*F$17/(1+$B20)^('DCF Model'!C19+4)-'DCF Model'!C16)*1000000/'DCF Model'!C15,0),"") -> 1210 | G20: =IFERROR(ROUND(('DCF Model'!C45/(1+$B20)^('DCF Model'!C19+0)+'DCF Model'!D45/(1+$B20)^('DCF Model'!C19+1)+'DCF Model'!E45/(1+$B20)^('DCF Model'!C19+2)+'DCF Model'!F45/(1+$B20)^('DCF Model'!C19+3)+'DCF Model'!G45/(1+$B20)^('DCF Model'!C19+4)+('DCF Model'!G39+'DCF Model'!G42)*G$17/(1+$B20)^('DCF Model'!C19+4)-'DCF Model'!C16)*1000000/'DCF Model'!C15,0),"") -> 1339 | H20: =IFERROR(ROUND(('DCF Model'!C45/(1+$B20)^('DCF Model'!C19+0)+'DCF Model'!D45/(1+$B20)^('DCF Model'!C19+1)+'DCF Model'!E45/(1+$B20)^('DCF Model'!C19+2)+'DCF Model'!F45/(1+$B20)^('DCF Model'!C19+3)+'DCF Model'!G45/(1+$B20)^('DCF Model'!C19+4)+('DCF Model'!G39+'DCF Model'!G42)*H$17/(1+$B20)^('DCF Model'!C19+4)-'DCF Model'!C16)*1000000/'DCF Model'!C15,0),"") -> 1468 | I20: =IFERROR(ROUND(('DCF Model'!C45/(1+$B20)^('DCF Model'!C19+0)+'DCF Model'!D45/(1+$B20)^('DCF Model'!C19+1)+'DCF Model'!E45/(1+$B20)^('DCF Model'!C19+2)+'DCF Model'!F45/(1+$B20)^('DCF Model'!C19+3)+'DCF Model'!G45/(1+$B20)^('DCF Model'!C19+4)+('DCF Model'!G39+'DCF Model'!G42)*I$17/(1+$B20)^('DCF Model'!C19+4)-'DCF Model'!C16)*1000000/'DCF Model'!C15,0),"") -> 1597
B21: =$C$3 -> 0.1211565 | C21: =IFERROR(ROUND(('DCF Model'!C45/(1+$B21)^('DCF Model'!C19+0)+'DCF Model'!D45/(1+$B21)^('DCF Model'!C19+1)+'DCF Model'!E45/(1+$B21)^('DCF Model'!C19+2)+'DCF Model'!F45/(1+$B21)^('DCF Model'!C19+3)+'DCF Model'!G45/(1+$B21)^('DCF Model'!C19+4)+('DCF Model'!G39+'DCF Model'!G42)*C$17/(1+$B21)^('DCF Model'!C19+4)-'DCF Model'!C16)*1000000/'DCF Model'!C15,0),"") -> 811 | D21: =IFERROR(ROUND(('DCF Model'!C45/(1+$B21)^('DCF Model'!C19+0)+'DCF Model'!D45/(1+$B21)^('DCF Model'!C19+1)+'DCF Model'!E45/(1+$B21)^('DCF Model'!C19+2)+'DCF Model'!F45/(1+$B21)^('DCF Model'!C19+3)+'DCF Model'!G45/(1+$B21)^('DCF Model'!C19+4)+('DCF Model'!G39+'DCF Model'!G42)*D$17/(1+$B21)^('DCF Model'!C19+4)-'DCF Model'!C16)*1000000/'DCF Model'!C15,0),"") -> 938 | E21: =IFERROR(ROUND(('DCF Model'!C45/(1+$B21)^('DCF Model'!C19+0)+'DCF Model'!D45/(1+$B21)^('DCF Model'!C19+1)+'DCF Model'!E45/(1+$B21)^('DCF Model'!C19+2)+'DCF Model'!F45/(1+$B21)^('DCF Model'!C19+3)+'DCF Model'!G45/(1+$B21)^('DCF Model'!C19+4)+('DCF Model'!G39+'DCF Model'!G42)*E$17/(1+$B21)^('DCF Model'!C19+4)-'DCF Model'!C16)*1000000/'DCF Model'!C15,0),"") -> 1064 | F21: =IFERROR(ROUND(('DCF Model'!C45/(1+$B21)^('DCF Model'!C19+0)+'DCF Model'!D45/(1+$B21)^('DCF Model'!C19+1)+'DCF Model'!E45/(1+$B21)^('DCF Model'!C19+2)+'DCF Model'!F45/(1+$B21)^('DCF Model'!C19+3)+'DCF Model'!G45/(1+$B21)^('DCF Model'!C19+4)+('DCF Model'!G39+'DCF Model'!G42)*F$17/(1+$B21)^('DCF Model'!C19+4)-'DCF Model'!C16)*1000000/'DCF Model'!C15,0),"") -> 1191 | G21: =IFERROR(ROUND(('DCF Model'!C45/(1+$B21)^('DCF Model'!C19+0)+'DCF Model'!D45/(1+$B21)^('DCF Model'!C19+1)+'DCF Model'!E45/(1+$B21)^('DCF Model'!C19+2)+'DCF Model'!F45/(1+$B21)^('DCF Model'!C19+3)+'DCF Model'!G45/(1+$B21)^('DCF Model'!C19+4)+('DCF Model'!G39+'DCF Model'!G42)*G$17/(1+$B21)^('DCF Model'!C19+4)-'DCF Model'!C16)*1000000/'DCF Model'!C15,0),"") -> 1317 | H21: =IFERROR(ROUND(('DCF Model'!C45/(1+$B21)^('DCF Model'!C19+0)+'DCF Model'!D45/(1+$B21)^('DCF Model'!C19+1)+'DCF Model'!E45/(1+$B21)^('DCF Model'!C19+2)+'DCF Model'!F45/(1+$B21)^('DCF Model'!C19+3)+'DCF Model'!G45/(1+$B21)^('DCF Model'!C19+4)+('DCF Model'!G39+'DCF Model'!G42)*H$17/(1+$B21)^('DCF Model'!C19+4)-'DCF Model'!C16)*1000000/'DCF Model'!C15,0),"") -> 1444 | I21: =IFERROR(ROUND(('DCF Model'!C45/(1+$B21)^('DCF Model'!C19+0)+'DCF Model'!D45/(1+$B21)^('DCF Model'!C19+1)+'DCF Model'!E45/(1+$B21)^('DCF Model'!C19+2)+'DCF Model'!F45/(1+$B21)^('DCF Model'!C19+3)+'DCF Model'!G45/(1+$B21)^('DCF Model'!C19+4)+('DCF Model'!G39+'DCF Model'!G42)*I$17/(1+$B21)^('DCF Model'!C19+4)-'DCF Model'!C16)*1000000/'DCF Model'!C15,0),"") -> 1571
B22: =$C$3+0.005 -> 0.1261565 | C22: =IFERROR(ROUND(('DCF Model'!C45/(1+$B22)^('DCF Model'!C19+0)+'DCF Model'!D45/(1+$B22)^('DCF Model'!C19+1)+'DCF Model'!E45/(1+$B22)^('DCF Model'!C19+2)+'DCF Model'!F45/(1+$B22)^('DCF Model'!C19+3)+'DCF Model'!G45/(1+$B22)^('DCF Model'!C19+4)+('DCF Model'!G39+'DCF Model'!G42)*C$17/(1+$B22)^('DCF Model'!C19+4)-'DCF Model'!C16)*1000000/'DCF Model'!C15,0),"") -> 800 | D22: =IFERROR(ROUND(('DCF Model'!C45/(1+$B22)^('DCF Model'!C19+0)+'DCF Model'!D45/(1+$B22)^('DCF Model'!C19+1)+'DCF Model'!E45/(1+$B22)^('DCF Model'!C19+2)+'DCF Model'!F45/(1+$B22)^('DCF Model'!C19+3)+'DCF Model'!G45/(1+$B22)^('DCF Model'!C19+4)+('DCF Model'!G39+'DCF Model'!G42)*D$17/(1+$B22)^('DCF Model'!C19+4)-'DCF Model'!C16)*1000000/'DCF Model'!C15,0),"") -> 924 | E22: =IFERROR(ROUND(('DCF Model'!C45/(1+$B22)^('DCF Model'!C19+0)+'DCF Model'!D45/(1+$B22)^('DCF Model'!C19+1)+'DCF Model'!E45/(1+$B22)^('DCF Model'!C19+2)+'DCF Model'!F45/(1+$B22)^('DCF Model'!C19+3)+'DCF Model'!G45/(1+$B22)^('DCF Model'!C19+4)+('DCF Model'!G39+'DCF Model'!G42)*E$17/(1+$B22)^('DCF Model'!C19+4)-'DCF Model'!C16)*1000000/'DCF Model'!C15,0),"") -> 1048 | F22: =IFERROR(ROUND(('DCF Model'!C45/(1+$B22)^('DCF Model'!C19+0)+'DCF Model'!D45/(1+$B22)^('DCF Model'!C19+1)+'DCF Model'!E45/(1+$B22)^('DCF Model'!C19+2)+'DCF Model'!F45/(1+$B22)^('DCF Model'!C19+3)+'DCF Model'!G45/(1+$B22)^('DCF Model'!C19+4)+('DCF Model'!G39+'DCF Model'!G42)*F$17/(1+$B22)^('DCF Model'!C19+4)-'DCF Model'!C16)*1000000/'DCF Model'!C15,0),"") -> 1172 | G22: =IFERROR(ROUND(('DCF Model'!C45/(1+$B22)^('DCF Model'!C19+0)+'DCF Model'!D45/(1+$B22)^('DCF Model'!C19+1)+'DCF Model'!E45/(1+$B22)^('DCF Model'!C19+2)+'DCF Model'!F45/(1+$B22)^('DCF Model'!C19+3)+'DCF Model'!G45/(1+$B22)^('DCF Model'!C19+4)+('DCF Model'!G39+'DCF Model'!G42)*G$17/(1+$B22)^('DCF Model'!C19+4)-'DCF Model'!C16)*1000000/'DCF Model'!C15,0),"") -> 1297 | H22: =IFERROR(ROUND(('DCF Model'!C45/(1+$B22)^('DCF Model'!C19+0)+'DCF Model'!D45/(1+$B22)^('DCF Model'!C19+1)+'DCF Model'!E45/(1+$B22)^('DCF Model'!C19+2)+'DCF Model'!F45/(1+$B22)^('DCF Model'!C19+3)+'DCF Model'!G45/(1+$B22)^('DCF Model'!C19+4)+('DCF Model'!G39+'DCF Model'!G42)*H$17/(1+$B22)^('DCF Model'!C19+4)-'DCF Model'!C16)*1000000/'DCF Model'!C15,0),"") -> 1421 | I22: =IFERROR(ROUND(('DCF Model'!C45/(1+$B22)^('DCF Model'!C19+0)+'DCF Model'!D45/(1+$B22)^('DCF Model'!C19+1)+'DCF Model'!E45/(1+$B22)^('DCF Model'!C19+2)+'DCF Model'!F45/(1+$B22)^('DCF Model'!C19+3)+'DCF Model'!G45/(1+$B22)^('DCF Model'!C19+4)+('DCF Model'!G39+'DCF Model'!G42)*I$17/(1+$B22)^('DCF Model'!C19+4)-'DCF Model'!C16)*1000000/'DCF Model'!C15,0),"") -> 1545
B23: =$C$3+0.01 -> 0.1311565 | C23: =IFERROR(ROUND(('DCF Model'!C45/(1+$B23)^('DCF Model'!C19+0)+'DCF Model'!D45/(1+$B23)^('DCF Model'!C19+1)+'DCF Model'!E45/(1+$B23)^('DCF Model'!C19+2)+'DCF Model'!F45/(1+$B23)^('DCF Model'!C19+3)+'DCF Model'!G45/(1+$B23)^('DCF Model'!C19+4)+('DCF Model'!G39+'DCF Model'!G42)*C$17/(1+$B23)^('DCF Model'!C19+4)-'DCF Model'!C16)*1000000/'DCF Model'!C15,0),"") -> 789 | D23: =IFERROR(ROUND(('DCF Model'!C45/(1+$B23)^('DCF Model'!C19+0)+'DCF Model'!D45/(1+$B23)^('DCF Model'!C19+1)+'DCF Model'!E45/(1+$B23)^('DCF Model'!C19+2)+'DCF Model'!F45/(1+$B23)^('DCF Model'!C19+3)+'DCF Model'!G45/(1+$B23)^('DCF Model'!C19+4)+('DCF Model'!G39+'DCF Model'!G42)*D$17/(1+$B23)^('DCF Model'!C19+4)-'DCF Model'!C16)*1000000/'DCF Model'!C15,0),"") -> 911 | E23: =IFERROR(ROUND(('DCF Model'!C45/(1+$B23)^('DCF Model'!C19+0)+'DCF Model'!D45/(1+$B23)^('DCF Model'!C19+1)+'DCF Model'!E45/(1+$B23)^('DCF Model'!C19+2)+'DCF Model'!F45/(1+$B23)^('DCF Model'!C19+3)+'DCF Model'!G45/(1+$B23)^('DCF Model'!C19+4)+('DCF Model'!G39+'DCF Model'!G42)*E$17/(1+$B23)^('DCF Model'!C19+4)-'DCF Model'!C16)*1000000/'DCF Model'!C15,0),"") -> 1033 | F23: =IFERROR(ROUND(('DCF Model'!C45/(1+$B23)^('DCF Model'!C19+0)+'DCF Model'!D45/(1+$B23)^('DCF Model'!C19+1)+'DCF Model'!E45/(1+$B23)^('DCF Model'!C19+2)+'DCF Model'!F45/(1+$B23)^('DCF Model'!C19+3)+'DCF Model'!G45/(1+$B23)^('DCF Model'!C19+4)+('DCF Model'!G39+'DCF Model'!G42)*F$17/(1+$B23)^('DCF Model'!C19+4)-'DCF Model'!C16)*1000000/'DCF Model'!C15,0),"") -> 1154 | G23: =IFERROR(ROUND(('DCF Model'!C45/(1+$B23)^('DCF Model'!C19+0)+'DCF Model'!D45/(1+$B23)^('DCF Model'!C19+1)+'DCF Model'!E45/(1+$B23)^('DCF Model'!C19+2)+'DCF Model'!F45/(1+$B23)^('DCF Model'!C19+3)+'DCF Model'!G45/(1+$B23)^('DCF Model'!C19+4)+('DCF Model'!G39+'DCF Model'!G42)*G$17/(1+$B23)^('DCF Model'!C19+4)-'DCF Model'!C16)*1000000/'DCF Model'!C15,0),"") -> 1276 | H23: =IFERROR(ROUND(('DCF Model'!C45/(1+$B23)^('DCF Model'!C19+0)+'DCF Model'!D45/(1+$B23)^('DCF Model'!C19+1)+'DCF Model'!E45/(1+$B23)^('DCF Model'!C19+2)+'DCF Model'!F45/(1+$B23)^('DCF Model'!C19+3)+'DCF Model'!G45/(1+$B23)^('DCF Model'!C19+4)+('DCF Model'!G39+'DCF Model'!G42)*H$17/(1+$B23)^('DCF Model'!C19+4)-'DCF Model'!C16)*1000000/'DCF Model'!C15,0),"") -> 1398 | I23: =IFERROR(ROUND(('DCF Model'!C45/(1+$B23)^('DCF Model'!C19+0)+'DCF Model'!D45/(1+$B23)^('DCF Model'!C19+1)+'DCF Model'!E45/(1+$B23)^('DCF Model'!C19+2)+'DCF Model'!F45/(1+$B23)^('DCF Model'!C19+3)+'DCF Model'!G45/(1+$B23)^('DCF Model'!C19+4)+('DCF Model'!G39+'DCF Model'!G42)*I$17/(1+$B23)^('DCF Model'!C19+4)-'DCF Model'!C16)*1000000/'DCF Model'!C15,0),"") -> 1519
B24: =$C$3+0.015 -> 0.1361565 | C24: =IFERROR(ROUND(('DCF Model'!C45/(1+$B24)^('DCF Model'!C19+0)+'DCF Model'!D45/(1+$B24)^('DCF Model'!C19+1)+'DCF Model'!E45/(1+$B24)^('DCF Model'!C19+2)+'DCF Model'!F45/(1+$B24)^('DCF Model'!C19+3)+'DCF Model'!G45/(1+$B24)^('DCF Model'!C19+4)+('DCF Model'!G39+'DCF Model'!G42)*C$17/(1+$B24)^('DCF Model'!C19+4)-'DCF Model'!C16)*1000000/'DCF Model'!C15,0),"") -> 779 | D24: =IFERROR(ROUND(('DCF Model'!C45/(1+$B24)^('DCF Model'!C19+0)+'DCF Model'!D45/(1+$B24)^('DCF Model'!C19+1)+'DCF Model'!E45/(1+$B24)^('DCF Model'!C19+2)+'DCF Model'!F45/(1+$B24)^('DCF Model'!C19+3)+'DCF Model'!G45/(1+$B24)^('DCF Model'!C19+4)+('DCF Model'!G39+'DCF Model'!G42)*D$17/(1+$B24)^('DCF Model'!C19+4)-'DCF Model'!C16)*1000000/'DCF Model'!C15,0),"") -> 898 | E24: =IFERROR(ROUND(('DCF Model'!C45/(1+$B24)^('DCF Model'!C19+0)+'DCF Model'!D45/(1+$B24)^('DCF Model'!C19+1)+'DCF Model'!E45/(1+$B24)^('DCF Model'!C19+2)+'DCF Model'!F45/(1+$B24)^('DCF Model'!C19+3)+'DCF Model'!G45/(1+$B24)^('DCF Model'!C19+4)+('DCF Model'!G39+'DCF Model'!G42)*E$17/(1+$B24)^('DCF Model'!C19+4)-'DCF Model'!C16)*1000000/'DCF Model'!C15,0),"") -> 1017 | F24: =IFERROR(ROUND(('DCF Model'!C45/(1+$B24)^('DCF Model'!C19+0)+'DCF Model'!D45/(1+$B24)^('DCF Model'!C19+1)+'DCF Model'!E45/(1+$B24)^('DCF Model'!C19+2)+'DCF Model'!F45/(1+$B24)^('DCF Model'!C19+3)+'DCF Model'!G45/(1+$B24)^('DCF Model'!C19+4)+('DCF Model'!G39+'DCF Model'!G42)*F$17/(1+$B24)^('DCF Model'!C19+4)-'DCF Model'!C16)*1000000/'DCF Model'!C15,0),"") -> 1137 | G24: =IFERROR(ROUND(('DCF Model'!C45/(1+$B24)^('DCF Model'!C19+0)+'DCF Model'!D45/(1+$B24)^('DCF Model'!C19+1)+'DCF Model'!E45/(1+$B24)^('DCF Model'!C19+2)+'DCF Model'!F45/(1+$B24)^('DCF Model'!C19+3)+'DCF Model'!G45/(1+$B24)^('DCF Model'!C19+4)+('DCF Model'!G39+'DCF Model'!G42)*G$17/(1+$B24)^('DCF Model'!C19+4)-'DCF Model'!C16)*1000000/'DCF Model'!C15,0),"") -> 1256 | H24: =IFERROR(ROUND(('DCF Model'!C45/(1+$B24)^('DCF Model'!C19+0)+'DCF Model'!D45/(1+$B24)^('DCF Model'!C19+1)+'DCF Model'!E45/(1+$B24)^('DCF Model'!C19+2)+'DCF Model'!F45/(1+$B24)^('DCF Model'!C19+3)+'DCF Model'!G45/(1+$B24)^('DCF Model'!C19+4)+('DCF Model'!G39+'DCF Model'!G42)*H$17/(1+$B24)^('DCF Model'!C19+4)-'DCF Model'!C16)*1000000/'DCF Model'!C15,0),"") -> 1375 | I24: =IFERROR(ROUND(('DCF Model'!C45/(1+$B24)^('DCF Model'!C19+0)+'DCF Model'!D45/(1+$B24)^('DCF Model'!C19+1)+'DCF Model'!E45/(1+$B24)^('DCF Model'!C19+2)+'DCF Model'!F45/(1+$B24)^('DCF Model'!C19+3)+'DCF Model'!G45/(1+$B24)^('DCF Model'!C19+4)+('DCF Model'!G39+'DCF Model'!G42)*I$17/(1+$B24)^('DCF Model'!C19+4)-'DCF Model'!C16)*1000000/'DCF Model'!C15,0),"") -> 1495
B26: All values dynamically linked to DCF Model. Headers auto-center on current WACC / Terminal g / Exit Multiple.

Sheet Adjustments Log
B2: Adjustments Log - Besterra
B4: 日付 | C4: セル | D4: 変更内容 | E4: 理由 | F4: 元の値 | G4: 状態
B5: 2026-09-03 | C5: - | D5: Generated by pipeline on 2026-09-03 10:32, template rev c9b5dd9 | E5: 初期生成（手修正なし） | F5: - | G5: generated
B6: 2026-09-02 | C6: 全シート(単位) | D6: 原典の決算短信・有価証券報告書は【千円】表記。本モデルは全て【百万円】 | E6: 桁事故の温床のため冒頭に明示する。EDINET有報のXBRLは円単位で取得し、パイプラインが百万円に換算している。相互検算: FY2026/1 売上 11,140,386,000円 = 11,140.386百万 = プロンプト転記値11,140 と一致。営業利益 741,091,000円 = 741.1 = 741 と一致。純利益 732,617,000円 = 732.6 = 733 と一致。以下このログの数値は全て百万円。 | F6: - | G6: 確定
B7: 2026-09-02 | C7: Executive Summary!C9 / DCF Model 現在株価 | D7: Current Price = 1,269円(プロンプト指定 1,433円 から変更) | E7: 【プロンプトからの変更・ユーザー確認済み】1,269円は 2026-09-02 の実測終値(yfinance 1433.T)。プロンプトが根拠として併記した参照点2つは実測と完全一致した(8/12終値 1,148円 ✓、8/28終値 1,300円 ✓)が、1,433円は 2026/07/27-09/02 の実測レンジ(安値1,097 / 高値1,336、いずれも日中値込み)の外側で一度も成立していない。銘柄コード1433と同一の数字であることから転記事故と判断し、ユーザーに提示して 1,269円 の採用を確認した。■結論への影響は大きい: 時価総額 13,323 → 11,244百万、EV 11,244 → 10,190百万。Target に対する騰落率が約13ポイント変わる。 | F7: プロンプト指定 1,433円 | G7: 確定(プロンプトからの変更・ユーザー確認済み)
B8: 2026-09-02 | C8: DCF Model!C15 / Comps Analysis 株数 | D8: Fully Diluted Shares = 8,860,910株(プロンプト暫定指定 9,297,200株 から変更) | E8: 【プロンプト §2-1 が指示した自己株控除の検算を実施した結果】検算3本が一致する: (1) EDINET FY2026/1有報(docID S100XZ7G)— 発行済株式総数 9,297,200株(NumberOfIssuedSharesAsOfFiscalYearEnd / AsOfFilingDate とも同数、提出日2026-04-16)、自己株式数 436,290株(TotalNumberOfSharesHeldTreasurySharesEtc、2026-01-31時点、うち完全議決権436,200 + 単元未満90)→ 9,297,200 − 436,290 = 8,860,910株。(2) 同報告書の1株当たり純資産 609.14円 × 8,860,910 = 5,397.5百万 = 開示純資産 5,397,535千円と一致し、BPSの分母が自己株控除後であることを確認。(3) yfinance sharesOutstanding = 8,860,910 で完全一致。よってプロンプトの9,297,200は自己株控除【前】の数字。■基準日: プロンプトは2026-04-30(Q1末)を優先指定したが、四半期報告書制度の廃止により1月期の当社はQ1のXBRLをEDINETに提出しておらず、TDnet短信PDFも本実行環境から取得できなかったため 2026-01-31 基準(プロンプトが代替として認めた基準日)を採用した。 | F8: プロンプト暫定値 9,297,200株 | G8: 確定(プロンプトからの変更)
B9: 2026-09-02 | C9: DCF Model!C15(株数の基準日) | D9: 2026/2-4 期中の自己株式異動が未確認。控除後株数はさらに減る可能性がある | E9: 純資産は 2026/1末 5,397.5 → 2026/4末 5,360 と37.5百万減っているが、同四半期に純利益260百万を計上している。差引 約298百万が配当・自己株取得・その他包括利益の変動で流出した計算になる。年間配当40円(期末25円 × 8.86百万株 ≒ 222百万)で大半は説明できるが、追加の自己株取得があれば株数は 8,860,910 を下回り、1株あたり価値はその分上振れる。9月中間決算または次回有報での確認事項。 | F9: - | G9: 要確認
B10: 2026-09-02 | C10: DCF Model!C15(希薄化) | D10: 未行使の新株予約権による希薄化要因はゼロ | E10: SubscriptionRightsToShares は FY2025/1末 7,548千円 → FY2026/1末は空欄(ゼロ)。第10回新株予約権は期中に全て行使され、株主資本等変動計算書の『新株予約権の行使』519,355千円(資本金+263,451 / 資本剰余金+263,451 / 新株予約権△7,548)として資本に振り替わっている。基本EPS 81.35 に対し潜在株式調整後EPS 81.22 の差は期中行使分によるもので、期末時点の潜在株式は存在しない。 | F10: - | G10: 確定
B11: 2026-09-02 | C11: DCF Model!C16 | D11: Net Debt = △1,054(ネットキャッシュ)。有利子負債857 − 現金及び預金1,912(2026/4/30) | E11: 内訳: 短期借入金700 + 1年内返済予定長期借入金53 + 長期借入金105 = 857(短信転記値。個別項目の合計は858で、原表の千円単位の丸め差)。■【設計判断】投資有価証券 1,919百万は net_debt に含めない。含めない理由は (a) 内訳(上場株/非上場株/匿名組合出資の別、売却制約の有無)が未確認、(b) 保守側(EV高め=Target低め)に倒すため。■非事業資産としての性格は強い: 毎期売却して特別利益化しており(FY2025/1 売却益167.2 / FY2026/1 140.0 / Q1 41)、売却収入も FY2025/1 1,414.1・FY2026/1 1,414.1 と2期連続、残高は 3,403(2025/1末)→ 2,236(2026/1末)→ 1,919(2026/4末)と一貫して取り崩されている。DCFのFCFは営業利益ベースで、これらが生む受取配当金・匿名組合損益分配額は営業外のためFCFに含まれておらず、控除しても二重計上にはならない。 | F11: テンプレ自動値(EDINET FY2026/1ベース)△863.7 | G11: 設計判断
B12: 2026-09-02 | C12: DCF Model!C16(感応度) | D12: 投資有価証券1,919を100%控除すると net_debt = △2,973、1株あたり +217円 | E12: 【要確認】有価証券報告書の『その他有価証券』明細で、上場株か非上場株か、政策保有(取引先との関係維持目的)で売却制約があるか、匿名組合出資が含まれるかを検証する必要がある。FY2026/1有報の特定投資株式の記載は2銘柄のみ(915,000株 / 120,000株、いずれも『取引先との協力関係の維持強化のため』)で、うち1銘柄は前期1,751,600株から915,000株へ減らしている。残高1,919百万の全額が即時換金可能とは限らない。控除した場合の株価インパクト +217円は現値1,269円の約17%に相当し、判断を左右しうる大きさである。 | F12: - | G12: 要確認
B13: 2026-09-02 | C13: DCF Model!C12 (D/E Ratio) | D13: de_ratio = 0.0762(プロンプト指定 0.060 から変更) | E13: 【スキーマ semantics の訂正】テンプレの de_ratio は D/(D+E) ではなく D/E である(dcf_comps_template.py calc_wacc: we = 1/(1+de_ratio)、wd = de_ratio/(1+de_ratio))。プロンプトは『D/(D+E) = 857/(857+13,323) = 6.05%』として0.060を指定していたが、そのまま入れると負債ウェイトは 0.060/1.060 = 5.66% となり意図とずれる。株価・株数訂正後のグロス有利子負債基準 D/E = 857 / 11,244 = 0.0762 を採用し、負債ウェイト wd = 7.08%(= プロンプトが意図した D/(D+E) 定義)を実現した。■ネット基準ならネットキャッシュのため de_ratio = 0 で WACC は 12.00%(+0.81pt、Target 約 -8%)。EV→株式価値ブリッジがネット控除である点との整合ではネット基準に理があるが、プロンプトの明示的意図がグロス基準であることを優先した。 | F13: プロンプト指定 0.060 | G13: 設計判断(プロンプトからの変更)
B14: 2026-09-02 | C14: DCF Model!C7 (Risk-Free Rate) | D14: Risk-Free = 3.0% | E14: プロンプト指定の新発10年国債利回り 2.99%(2026-09-01時点)を丸めた値。本実行では財務省『国債金利情報』jgbcm.csv を再取得できなかったため、プロンプト提供値をそのまま採用した。yfinance では日本国債利回りは取得できない。 | F14: テンプレ既定 2.2% | G14: 要確認(プロンプト提供値・一次ソース未再取得)
B15: 2026-09-02 | C15: DCF Model!C8 (Beta) | D15: Beta = 1.0 | E15: プロンプトのルール『yfinanceの5年月次βを取得。取得失敗、または0.6未満/1.8超なら1.0を使用』をそのまま適用した結果。実測: 1433.T vs 1306.T(TOPIX連動ETF)の5年月次 β = -0.010(n=59、相関 -0.158)、3年月次 β = -0.012(相関 -0.240)、2年週次 β = 0.524(相関 0.299)、5年週次 β = 0.562(相関 0.301)。vs 日経225では 5年月次 β = 0.437。いずれも 0.6 未満のためルール適用。■統計的信頼度は低い: 相関が全期間で0.30以下で、浮動株が薄い超小型株(日商 数万株)であることに加え、プラント解体需要は顧客の設備更新サイクルに依存し株式市場の景気循環との連動が弱い。実測βをそのまま使えば WACC は 6.5% 前後まで下がり Target が非現実的に膨らむため、1.0(=市場並み)への切り上げは保守的かつ妥当。yfinance info.beta は 1.342 だが算出基準が非開示のため採用しない。 | F15: yfinance 実測 5年月次 -0.010 | G15: 設計判断(ルール適用)
... B43: 2026-09-02 | C43: モデルの賞味期限 | D43: 2026-09-09 に FY2027/1 中間期決算が発表予定。それ以降は再計算が必要 | E43: 本モデルの基準年は FY2026/1 実績、直近の期中情報は Q1(2026/02-04)のみである。9月9日に開示される中間期(2026/02-07)実績は、(a) 粗利率の階段(17.3% → 20.1% → 21.9%)が続いたか、(b) DSO 130日が維持されたか、(c) 通期予想(売上13,000 / 営業利益1,000)が上方修正されるか、の3点を同時に確定させる。LTM営業利益960がQ1時点で既に通期予想をほぼ達成している以上、上方修正の可能性は高く、Base / Management シナリオのY1前提が入れ替わる。中間期開示後は本モデルを再生成すること。 | F43: - | G43: 未解決(期限付き)
B45: Pipeline Metadata (do not edit — read by scripts/validate_output.py)
B46: key | C46: value
B47: auto_log_entries | C47: 1
B48: capex_pct_basis | C48: assumption
B49: capex_pct_c5 | C49: 0.0045
B50: capex_pct_hist3yr | C50: 0.001614
B51: company_name | C51: Besterra
B52: comps_asof | C52: 2026-09-03
B53: comps_da_missing | C53: none
B54: comps_ev_ebitda_invalid | C54: no
B55: comps_ev_ebitda_rows | C55: 6,7,8,9,10
B56: comps_impl_mult_row | C56: 27
B57: comps_impl_per_row | C57: 28
... B85: ticker | C85: 1433.T
