Workbook

Sheet Executive Summary
B1: DISCLAIMER: This is a sample analysis for demonstration purposes only. It does not constitute investment advice.
B3: 株式会社コア (2359.T)
B4: Equity Research Report
B6: Company | C6: 株式会社コア
B7: Ticker | C7: 2359.T (TSE)
B8: Sector | C8: Information & Communication
B9: Current Price | C9: 2011
B10: Target Price (Mid) | C10: =ROUND(AVERAGE(C16:C19),0) -> 2666
B11: Recommendation | C11: =IF(C12>0.15,"BUY",IF(C12>0.05,"HOLD","SELL")) -> BUY
B12: Upside / Downside | C12: =(C10-C9)/C9 -> 0.3257086
B14: Valuation Summary
B15: Methodology | C15: Implied Value (JPY) | D15: vs Current Price
B16: DCF - Perpetuity Growth | C16: ='DCF Model'!C55 -> 2893 | D16: =(C16-C9)/C9 -> 0.43858777
B17: DCF - Exit Multiple | C17: ='DCF Model'!C64 -> 3298 | D17: =(C17-C9)/C9 -> 0.63998011
B18: Comps - EV/EBITDA Median | C18: ='Comps Analysis'!C27 -> 2450 | D18: =(C18-C9)/C9 -> 0.21829935
B19: Comps - PER Median | C19: ='Comps Analysis'!C28 -> 2021 | D19: =(C19-C9)/C9 -> 0.0049726504
B21: Integrated Valuation Range | C21: =MIN(C16:C19)&" - "&MAX(C16:C19) -> 2021 - 3298
B23: Key Investment Thesis
B24: 1. Defense Tech: GNSS anti-spoofing tech for JASDF; 4-layer moat (proprietary receiver + QZSS auth + security clearance + space tech track record)
B25: 2. AX Transformation: Layer 2 (solution) ratio rising 25.9% → 33.3%, structurally improving OPM
B26: 3. Earnings Surprise: Base case EPS >¥200 vs consensus ~¥174; Q3 OP progress rate 82.5% implies ~¥4,050M OP
B28: Key Risks
B29: 1. Defense contracts still in R&D/validation phase — mass production orders unconfirmed
B30: 2. Key person risk in specialized GNSS/space technology division
B31: 3. Revenue concentration in Japanese domestic IT services market

Sheet Financial Statements
B2: 株式会社コア - Historical Financials (JPY mn)
C4: FY2021 | D4: FY2022 | E4: FY2023 | F4: FY2024 | G4: FY2025
B5: Income Statement
B6: Revenue | C6: 20785.262 | D6: 21798.077 | E6: 22848.129 | F6: 23998.562 | G6: 24599.166
B7: COGS | C7: 15524.609 | D7: 16231.035 | E7: 16853.21 | F7: 17407.88 | G7: 17821.475
B8: Gross Profit | C8: =C6-C7 -> 5260.653 | D8: =D6-D7 -> 5567.042 | E8: =E6-E7 -> 5994.919 | F8: =F6-F7 -> 6590.682 | G8: =G6-G7 -> 6777.691
B9: Gross Margin | C9: =C8/C6 -> 0.25309534 | D9: =D8/D6 -> 0.25539143 | E9: =E8/E6 -> 0.26238118 | F9: =F8/F6 -> 0.2746282 | G9: =G8/G6 -> 0.27552524
B10: SGA | C10: 3228.568 | D10: 3199.384 | E10: 3251.051 | F10: 3450.098 | G10: 3602.229
B11: Operating Income | C11: 2032.084 | D11: 2367.658 | E11: 2743.867 | F11: 3140.583 | G11: 3175.462
B12: Net Income | C12: 1423.358 | D12: 1622.716 | E12: 1968.404 | F12: 2270.704 | G12: 2242.34
B13: Operating Margin | C13: =C11/C6 -> 0.097765619 | D13: =D11/D6 -> 0.10861775 | E13: =E11/E6 -> 0.12009154 | F13: =F11/F6 -> 0.13086547 | G13: =G11/G6 -> 0.1290882
B14: Net Margin | C14: =C12/C6 -> 0.068479195 | D14: =D12/D6 -> 0.07444308 | E14: =E12/E6 -> 0.086151649 | F14: =F12/F6 -> 0.094618336 | G14: =G12/G6 -> 0.091155123
B15: Revenue Growth (YoY) | C15: n/a | D15: =(D6-C6)/C6 -> 0.048727555 | E15: =(E6-D6)/D6 -> 0.048171772 | F15: =(F6-E6)/E6 -> 0.0503513 | G15: =(G6-F6)/F6 -> 0.025026666
B16: Operating Income Growth (YoY) | C16: n/a | D16: =(D11-C11)/C11 -> 0.16513786 | E16: =(E11-D11)/D11 -> 0.15889499 | F16: =(F11-E11)/E11 -> 0.14458281 | G16: =(G11-F11)/F11 -> 0.0111059
B18: Cash Flow Statement
B19: Operating Cash Flow | C19: 1851.105 | D19: 1799.231 | E19: 1943.795 | F19: 2190.094 | G19: 2372.799
B20: Capex | C20: 93.543 | D20: 72.084 | E20: 85.455 | F20: 93.4 | G20: 95.32
B21: Free Cash Flow | C21: =C19-C20 -> 1757.562 | D21: =D19-D20 -> 1727.147 | E21: =E19-E20 -> 1858.34 | F21: =F19-F20 -> 2096.694 | G21: =G19-G20 -> 2277.479
B22: FCF Margin | C22: =C21/C6 -> 0.084558087 | D22: =D21/D6 -> 0.079233916 | E22: =E21/E6 -> 0.08133445 | F22: =F21/F6 -> 0.087367485 | G22: =G21/G6 -> 0.092583586
B23: Capex / Revenue | C23: =C20/C6 -> 0.0045004484 | D23: =D20/D6 -> 0.0033068972 | E23: =E20/E6 -> 0.0037401312 | F23: =F20/F6 -> 0.0038918999 | G23: =G20/G6 -> 0.0038749281
B25: Balance Sheet Highlights
B26: Cash & Deposits | C26: 3636.219 | D26: 4700.235 | E26: 5586.934 | F26: 6300.075 | G26: 7586.071
B27: Short-term Debt | C27: 2109.7 | D27: 1963.6 | E27: 1812 | F27: 1734.8 | G27: 1412.4
B28: Net Debt (Cash) | C28: =C27-C26 -> -1526.519 | D28: =D27-D26 -> -2736.635 | E28: =E27-E26 -> -3774.934 | F28: =F27-F26 -> -4565.275 | G28: =G27-G26 -> -6173.671

Sheet DCF Model
B2: DCF Valuation Model - 株式会社コア
B4: Assumptions
B5: Capex / Revenue | C5: 0.0041668079
B6: Effective Tax Rate | C6: 0.305
B7: Risk-Free Rate | C7: 0.022
B8: Beta | C8: 0.88
B9: Equity Risk Premium | C9: 0.065
B10: Size Premium | C10: 0.04
B11: After-tax Cost of Debt | C11: 0.005
B12: D/E Ratio | C12: 0
B13: Terminal Growth Rate | C13: 0.02
B14: Exit Multiple (EV/EBITDA) | C14: 8
B15: Fully Diluted Shares | C15: 14368501
B16: Net Debt (JPY mn) | C16: -7296.8
... B20: LTM Revenue (JPY mn) | C20: 24599
B22: WACC Calculation
B23: Cost of Equity (Ke) | C23: =C7+C8*C9+C10 -> 0.1192
B24: Weight of Equity | C24: =1/(1+C12) -> 1
B25: Weight of Debt | C25: =C12/(1+C12) -> 0
B26: WACC | C26: =C23*C24+C11*C25 -> 0.1192
B27: Active Scenario | C27: Base | D27: =MATCH(C27,{"Base","Upside","Management","Downside 1","Downside 2"},0) -> 1
B28: Projected Free Cash Flow
C29: FY2026(E) | D29: FY2027(E) | E29: FY2028(E) | F29: FY2029(E) | G29: FY2030(E)
B30: Revenue Growth (YoY) | C30: =(C33/C17)-1 -> 0.1738837 | D30: =(D33/C33)-1 -> 0.085724203 | E30: =(E33/D33)-1 -> 0.070924591 | F30: =(F33/E33)-1 -> 0.052593291 | G30: =(G33/F33)-1 -> 0.040871093
B31: COGS % of Revenue | C31: =CHOOSE($D$27,'Segment Analysis'!F79,'Segment Analysis'!F80,'Segment Analysis'!F81,'Segment Analysis'!F82,'Segment Analysis'!F83) -> 0.7245 | D31: =CHOOSE($D$27,'Segment Analysis'!G79,'Segment Analysis'!G80,'Segment Analysis'!G81,'Segment Analysis'!G82,'Segment Analysis'!G83) -> 0.7245 | E31: =CHOOSE($D$27,'Segment Analysis'!H79,'Segment Analysis'!H80,'Segment Analysis'!H81,'Segment Analysis'!H82,'Segment Analysis'!H83) -> 0.7245 | F31: =CHOOSE($D$27,'Segment Analysis'!I79,'Segment Analysis'!I80,'Segment Analysis'!I81,'Segment Analysis'!I82,'Segment Analysis'!I83) -> 0.7245 | G31: =CHOOSE($D$27,'Segment Analysis'!J79,'Segment Analysis'!J80,'Segment Analysis'!J81,'Segment Analysis'!J82,'Segment Analysis'!J83) -> 0.7245
B32: SGA % of Revenue | C32: =CHOOSE($D$27,'Segment Analysis'!F86,'Segment Analysis'!F87,'Segment Analysis'!F88,'Segment Analysis'!F89,'Segment Analysis'!F90) -> 0.133 | D32: =CHOOSE($D$27,'Segment Analysis'!G86,'Segment Analysis'!G87,'Segment Analysis'!G88,'Segment Analysis'!G89,'Segment Analysis'!G90) -> 0.13 | E32: =CHOOSE($D$27,'Segment Analysis'!H86,'Segment Analysis'!H87,'Segment Analysis'!H88,'Segment Analysis'!H89,'Segment Analysis'!H90) -> 0.128 | F32: =CHOOSE($D$27,'Segment Analysis'!I86,'Segment Analysis'!I87,'Segment Analysis'!I88,'Segment Analysis'!I89,'Segment Analysis'!I90) -> 0.126 | G32: =CHOOSE($D$27,'Segment Analysis'!J86,'Segment Analysis'!J87,'Segment Analysis'!J88,'Segment Analysis'!J89,'Segment Analysis'!J90) -> 0.125
B33: Revenue | C33: ='Segment Analysis'!F21 -> 28876.56 | D33: ='Segment Analysis'!G21 -> 31351.98 | E33: ='Segment Analysis'!H21 -> 33575.606 | F33: ='Segment Analysis'!I21 -> 35341.458 | G33: ='Segment Analysis'!J21 -> 36785.902
B34: COGS | C34: =C33*C31 -> 20921.068 | D34: =D33*D31 -> 22714.51 | E34: =E33*E31 -> 24325.527 | F34: =F33*F31 -> 25604.886 | G34: =G33*G31 -> 26651.386
B35: Gross Profit | C35: =C33-C34 -> 7955.4923 | D35: =D33-D34 -> 8637.4705 | E35: =E33-E34 -> 9250.0796 | F35: =F33-F34 -> 9736.5717 | G35: =G33-G34 -> 10134.516
B36: Gross Margin | C36: =C35/C33 -> 0.2755 | D36: =D35/D33 -> 0.2755 | E36: =E35/E33 -> 0.2755 | F36: =F35/F33 -> 0.2755 | G36: =G35/G33 -> 0.2755
B37: SGA Expense | C37: =C33*C32 -> 3840.5825 | D37: =D33*D32 -> 4075.7574 | E37: =E33*E32 -> 4297.6776 | F37: =F33*F32 -> 4453.0237 | G37: =G33*G32 -> 4598.2378
B38: Implied Operating Margin | C38: =C39/C33 -> 0.1425 | D38: =D39/D33 -> 0.1455 | E38: =E39/E33 -> 0.1475 | F38: =F39/F33 -> 0.1495 | G38: =G39/G33 -> 0.1505
B39: Operating Income (EBIT) | C39: =C35-C37 -> 4114.9098 | D39: =D35-D37 -> 4561.7131 | E39: =E35-E37 -> 4952.402 | F39: =F35-F37 -> 5283.548 | G39: =G35-G37 -> 5536.2783
B40: Less: Tax | C40: =MAX(0,C39*C6) -> 1255.0475 | D40: =MAX(0,D39*C6) -> 1391.3225 | E40: =MAX(0,E39*C6) -> 1510.4826 | F40: =MAX(0,F39*C6) -> 1611.4821 | G40: =MAX(0,G39*C6) -> 1688.5649
B41: NOPAT | C41: =C39-C40 -> 2859.8623 | D41: =D39-D40 -> 3170.3906 | E41: =E39-E40 -> 3441.9194 | F41: =F39-F40 -> 3672.0659 | G41: =G39-G40 -> 3847.7134
B42: Plus: D&A | C42: 210 | D42: 210 | E42: 210 | F42: 215 | G42: =G33*C18 -> 315.90591
B43: Less: Capex | C43: 100 | D43: 100 | E43: 105 | F43: 105 | G43: =G33*C5 -> 153.27979
B44: Change in NWC | C44: ='NWC Schedule'!D19 -> 1026.8724 | D44: ='NWC Schedule'!E19 -> 613.76994 | E44: ='NWC Schedule'!F19 -> 570.91759 | F44: ='NWC Schedule'!G19 -> 453.38362 | G44: ='NWC Schedule'!H19 -> 370.862
B45: Unlevered Free Cash Flow | C45: =C41+C42-C43-C44 -> 1942.9899 | D45: =D41+D42-D43-D44 -> 2666.6207 | E45: =E41+E42-E43-E44 -> 2976.0018 | F45: =F41+F42-F43-F44 -> 3328.6822 | G45: =G41+G42-G43-G44 -> 3639.4775
B46: Discount Factor | C46: =1/(1+C26)^(C19+0) -> 0.97223908 | D46: =1/(1+C26)^(C19+1) -> 0.8686911 | E46: =1/(1+C26)^(C19+2) -> 0.77617146 | F46: =1/(1+C26)^(C19+3) -> 0.6935056 | G46: =1/(1+C26)^(C19+4) -> 0.61964403
B47: PV of FCF | C47: =C45*C46 -> 1889.0507 | D47: =D45*D46 -> 2316.4696 | E47: =E45*E46 -> 2309.8876 | F47: =F45*F46 -> 2308.4598 | G47: =G45*G46 -> 2255.1805
B49: Valuation - Perpetuity Growth Method
B50: Sum of PV of FCFs | C50: =SUM(C47:G47) -> 11079.048
B51: Terminal Value (PGM) | C51: =G45*(1+C13)/(C26-C13) -> 37422.047
B52: PV of Terminal Value | C52: =C51*G46 -> 23188.348
B53: Enterprise Value | C53: =C50+C52 -> 34267.396
B54: Equity Value | C54: =C53-C16 -> 41564.196
B55: Implied Share Price (PGM) | C55: =ROUND(C54*1000000/C15,0) -> 2893
B57: Valuation - Exit Multiple Method
B58: Sum of PV of FCFs | C58: =C50 -> 11079.048
B59: Year 5 EBITDA | C59: =G39+G42 -> 5852.1842
B60: Terminal Value (Exit Multiple) | C60: =C59*C14 -> 46817.473
B61: PV of Terminal Value | C61: =C60*G46 -> 29010.168
B62: Enterprise Value | C62: =C58+C61 -> 40089.216
B63: Equity Value | C63: =C62-C16 -> 47386.016
B64: Implied Share Price (Exit Multiple) | C64: =ROUND(C63*1000000/C15,0) -> 3298
B66: All scenario inputs are in Segment Analysis sheet.

Sheet NWC Schedule
B2: NWC Schedule - 株式会社コア
B4: Working Capital Drivers (Days) | C4: Base Year | D4: FY2026(E) | E4: FY2027(E) | F4: FY2028(E) | G4: FY2029(E) | H4: FY2030(E)
B5: DSO (Days Sales Outstanding) | C5: =C12/C9*365 -> 116.89299 | D5: =CHOOSE('DCF Model'!$D$27,D25,D26,D27,D28,D29) -> 115 | E5: =CHOOSE('DCF Model'!$D$27,E25,E26,E27,E28,E29) -> 114 | F5: =CHOOSE('DCF Model'!$D$27,F25,F26,F27,F28,F29) -> 114 | G5: =CHOOSE('DCF Model'!$D$27,G25,G26,G27,G28,G29) -> 114 | H5: =CHOOSE('DCF Model'!$D$27,H25,H26,H27,H28,H29) -> 114
B6: DIH (Days Inventory Held) | C6: =C13/C10*365 -> 5.5093644 | D6: =CHOOSE('DCF Model'!$D$27,D32,D33,D34,D35,D36) -> 6 | E6: =CHOOSE('DCF Model'!$D$27,E32,E33,E34,E35,E36) -> 6 | F6: =CHOOSE('DCF Model'!$D$27,F32,F33,F34,F35,F36) -> 6 | G6: =CHOOSE('DCF Model'!$D$27,G32,G33,G34,G35,G36) -> 6 | H6: =CHOOSE('DCF Model'!$D$27,H32,H33,H34,H35,H36) -> 6
B7: DPO (Days Payable Outstanding) | C7: =C15/C10*365 -> 35.595819 | D7: =CHOOSE('DCF Model'!$D$27,D39,D40,D41,D42,D43) -> 35 | E7: =CHOOSE('DCF Model'!$D$27,E39,E40,E41,E42,E43) -> 34 | F7: =CHOOSE('DCF Model'!$D$27,F39,F40,F41,F42,F43) -> 34 | G7: =CHOOSE('DCF Model'!$D$27,G39,G40,G41,G42,G43) -> 34 | H7: =CHOOSE('DCF Model'!$D$27,H39,H40,H41,H42,H43) -> 34
B8: P&L Reference (JPY mn)
B9: Revenue | C9: 24599.166 | D9: ='DCF Model'!C33 -> 28876.56 | E9: ='DCF Model'!D33 -> 31351.98 | F9: ='DCF Model'!E33 -> 33575.606 | G9: ='DCF Model'!F33 -> 35341.458 | H9: ='DCF Model'!G33 -> 36785.902
B10: COGS | C10: 17821.475 | D10: ='DCF Model'!C34 -> 20921.068 | E10: ='DCF Model'!D34 -> 22714.51 | F10: ='DCF Model'!E34 -> 24325.527 | G10: ='DCF Model'!F34 -> 25604.886 | H10: ='DCF Model'!G34 -> 26651.386
B11: Working Capital Items (JPY mn)
B12: Accounts Receivable | C12: 7878 | D12: =D9*D5/365 -> 9098.0942 | E12: =E9*E5/365 -> 9792.1253 | F12: =F9*F5/365 -> 10486.628 | G12: =G9*G5/365 -> 11038.154 | H12: =H9*H5/365 -> 11489.295
B13: Inventory | C13: 269 | D13: =D10*D6/365 -> 343.90796 | E13: =E10*E6/365 -> 373.3892 | F13: =F10*F6/365 -> 399.87167 | G13: =G10*G6/365 -> 420.90224 | H13: =H10*H6/365 -> 438.10498
B14: Current Assets (AR + Inv) | C14: =C12+C13 -> 8147 | D14: =D12+D13 -> 9442.0022 | E14: =E12+E13 -> 10165.514 | F14: =F12+F13 -> 10886.499 | G14: =G12+G13 -> 11459.056 | H14: =H12+H13 -> 11927.4
B15: Accounts Payable | C15: 1738 | D15: =D10*D7/365 -> 2006.1298 | E15: =E10*E7/365 -> 2115.8721 | F15: =F10*F7/365 -> 2265.9395 | G15: =G10*G7/365 -> 2385.1127 | H15: =H10*H7/365 -> 2482.5949
B16: Current Liabilities (AP) | C16: =C15 -> 1738 | D16: =D15 -> 2006.1298 | E16: =E15 -> 2115.8721 | F16: =F15 -> 2265.9395 | G16: =G15 -> 2385.1127 | H16: =H15 -> 2482.5949
B17: Net Working Capital (JPY mn)
B18: Net Working Capital | C18: =C14-C16 -> 6409 | D18: =D14-D16 -> 7435.8724 | E18: =E14-E16 -> 8049.6424 | F18: =F14-F16 -> 8620.56 | G18: =G14-G16 -> 9073.9436 | H18: =H14-H16 -> 9444.8056
B19: Change in NWC | C19: n/a | D19: =D18-C18 -> 1026.8724 | E19: =E18-D18 -> 613.76994 | F19: =F18-E18 -> 570.91759 | G19: =G18-F18 -> 453.38362 | H19: =H18-G18 -> 370.862
B22: Scenario Input Matrix (Working Capital Days)
D23: FY2026(E) | E23: FY2027(E) | F23: FY2028(E) | G23: FY2029(E) | H23: FY2030(E)
B24: DSO (Days)
B25: Base | D25: 115 | E25: 114 | F25: 114 | G25: 114 | H25: 114
B26: Upside | D26: 113 | E26: 111 | F26: 109 | G26: 107 | H26: 107
B27: Management | D27: 116 | E27: 115 | F27: 115 | G27: 115 | H27: 115
B28: Downside 1 | D28: 118 | E28: 119 | F28: 120 | G28: 120 | H28: 120
B29: Downside 2 | D29: 120 | E29: 122 | F29: 124 | G29: 125 | H29: 125
B31: DIH (Days)
B32: Base | D32: 6 | E32: 6 | F32: 6 | G32: 6 | H32: 6
B33: Upside | D33: 5.5 | E33: 5.5 | F33: 5.5 | G33: 5.5 | H33: 5.5
B34: Management | D34: 6 | E34: 6 | F34: 6 | G34: 6 | H34: 6
B35: Downside 1 | D35: 6.5 | E35: 6.5 | F35: 7 | G35: 7 | H35: 7
B36: Downside 2 | D36: 7 | E36: 7 | F36: 7.5 | G36: 7.5 | H36: 7.5
B38: DPO (Days)
B39: Base | D39: 35 | E39: 34 | F39: 34 | G39: 34 | H39: 34
B40: Upside | D40: 36 | E40: 37 | F40: 38 | G40: 38 | H40: 38
B41: Management | D41: 35 | E41: 35 | F41: 35 | G41: 35 | H41: 35
B42: Downside 1 | D42: 34 | E42: 33 | F42: 33 | G42: 33 | H42: 33
B43: Downside 2 | D43: 33 | E43: 32 | F43: 32 | G43: 32 | H43: 32

Sheet Comps Analysis
B2: Comparable Company Analysis
B4: Company | C4: Ticker | D4: Mkt Cap (JPY mn) | E4: EV (JPY mn) | F4: Revenue (JPY mn) | G4: EBITDA (JPY mn) | H4: Op Income (JPY mn) | I4: Net Income (JPY mn) | J4: EV/EBITDA | K4: EV/Revenue | L4: PER | M4: PBR | N4: Op Margin | O4: ROE
B5: Systena | C5: 2317.T | D5: 147986.71 | E5: 149536.71 | F5: 92410 | G5: 15820 | H5: 15360 | I5: 11250 | J5: =E5/G5 -> 9.4523837 | K5: =E5/F5 -> 1.6181875 | L5: =D5/I5 -> 13.154374 | M5: 4.4912507 | N5: =H5/F5 -> 0.16621578 | O5: 0.3414264
B6: SRA HD | C6: 3817.T | D6: 60200.481 | E6: 60270.481 | F6: 54700 | G6: 8490 | H6: 8300 | I6: 5000 | J6: =E6/G6 -> 7.0989966 | K6: =E6/F6 -> 1.1018369 | L6: =D6/I6 -> 12.040096 | M6: 1.9355201 | N6: =H6/F6 -> 0.15173675 | O6: 0.1607562
B7: CEC | C7: 9692.T | D7: 61796.721 | E7: 62146.721 | F7: 65000 | G7: 8018 | H7: 7200 | I7: 5150 | J7: =E7/G7 -> 7.7509006 | K7: =E7/F7 -> 0.95610339 | L7: =D7/I7 -> 11.999363 | M7: 1.5295839 | N7: =H7/F7 -> 0.11076923 | O7: 0.12747209
B8: Cresco | C8: 4674.T | D8: 58446.234 | E8: 55946.234 | F8: 48000 | G8: 6800 | H8: 5200 | I8: 3600 | J8: =E8/G8 -> 8.2273873 | K8: =E8/F8 -> 1.1655465 | L8: =D8/I8 -> 16.235065 | M8: 2.656647 | N8: =H8/F8 -> 0.10833333 | O8: 0.16363636
B9: DTS | C9: 9682.T | D9: 165563.47 | E9: 162563.47 | F9: 47000 | G9: 7500 | H9: 5700 | I9: 3900 | J9: =E9/G9 -> 21.675129 | K9: =E9/F9 -> 3.4587971 | L9: =D9/I9 -> 42.452171 | M9: 5.9129809 | N9: =H9/F9 -> 0.1212766 | O9: 0.13928571
B14: Statistics
B15: 25th Percentile | D15: =PERCENTILE(J5:J9,0.25) -> 7.7509006 | E15: =PERCENTILE(K5:K9,0.25) -> 1.1018369 | F15: =PERCENTILE(L5:L9,0.25) -> 12.040096 | G15: =PERCENTILE(M5:M9,0.25) -> 1.9355201 | H15: =PERCENTILE(N5:N9,0.25) -> 0.11076923 | I15: =PERCENTILE(O5:O9,0.25) -> 0.13928571
B16: Median (50th) | D16: =MEDIAN(J5:J9) -> 8.2273873 | E16: =MEDIAN(K5:K9) -> 1.1655465 | F16: =MEDIAN(L5:L9) -> 13.154374 | G16: =MEDIAN(M5:M9) -> 2.656647 | H16: =MEDIAN(N5:N9) -> 0.1212766 | I16: =MEDIAN(O5:O9) -> 0.1607562
B17: 75th Percentile | D17: =PERCENTILE(J5:J9,0.75) -> 9.4523837 | E17: =PERCENTILE(K5:K9,0.75) -> 1.6181875 | F17: =PERCENTILE(L5:L9,0.75) -> 16.235065 | G17: =PERCENTILE(M5:M9,0.75) -> 4.4912507 | H17: =PERCENTILE(N5:N9,0.75) -> 0.15173675 | I17: =PERCENTILE(O5:O9,0.75) -> 0.16363636
B19: Implied Valuation for 株式会社コア
B20: 株式会社コア Financials
B21: EBITDA (JPY mn) | C21: 3391
B22: Net Income (JPY mn) | C22: 2207
B23: Shares Outstanding | C23: 14368501
B24: Net Debt (JPY mn) | C24: -7296.8
B26: Implied Share Price (Median Multiples)
B27: Via EV/EBITDA (Median) | C27: =ROUND((C21*D16-C24)*1000000/C23,0) -> 2450
B28: Via PER (Median) | C28: =ROUND(C22*F16*1000000/C23,0) -> 2021

Sheet Sensitivity Analysis
B2: Sensitivity Analysis
B3: Current WACC: | C3: ='DCF Model'!C26 -> 0.1192 | E3: Terminal g: | F3: ='DCF Model'!C13 -> 0.02 | H3: Exit Multiple: | I3: ='DCF Model'!C14 -> 8
B5: Table 1: WACC vs Terminal Growth Rate (PGM - Implied Share Price, JPY)
B6: WACC \ Terminal g | C6: =$F$3-0.0075 -> 0.0125 | D6: =$F$3-0.005 -> 0.015 | E6: =$F$3-0.0025 -> 0.0175 | F6: =$F$3 -> 0.02 | G6: =$F$3+0.0025 -> 0.0225 | H6: =$F$3+0.005 -> 0.025 | I6: =$F$3+0.0075 -> 0.0275
B7: =$C$3-0.015 -> 0.1042 | C7: =IFERROR(ROUND(('DCF Model'!C45/(1+$B7)^('DCF Model'!C19+0)+'DCF Model'!D45/(1+$B7)^('DCF Model'!C19+1)+'DCF Model'!E45/(1+$B7)^('DCF Model'!C19+2)+'DCF Model'!F45/(1+$B7)^('DCF Model'!C19+3)+'DCF Model'!G45/(1+$B7)^('DCF Model'!C19+4)+'DCF Model'!G45*(1+C$6)/($B7-C$6)/(1+$B7)^('DCF Model'!C19+4)-'DCF Model'!C16)*1000000/'DCF Model'!C15,0),"") -> 3139 | D7: =IFERROR(ROUND(('DCF Model'!C45/(1+$B7)^('DCF Model'!C19+0)+'DCF Model'!D45/(1+$B7)^('DCF Model'!C19+1)+'DCF Model'!E45/(1+$B7)^('DCF Model'!C19+2)+'DCF Model'!F45/(1+$B7)^('DCF Model'!C19+3)+'DCF Model'!G45/(1+$B7)^('DCF Model'!C19+4)+'DCF Model'!G45*(1+D$6)/($B7-D$6)/(1+$B7)^('DCF Model'!C19+4)-'DCF Model'!C16)*1000000/'DCF Model'!C15,0),"") -> 3195 | E7: =IFERROR(ROUND(('DCF Model'!C45/(1+$B7)^('DCF Model'!C19+0)+'DCF Model'!D45/(1+$B7)^('DCF Model'!C19+1)+'DCF Model'!E45/(1+$B7)^('DCF Model'!C19+2)+'DCF Model'!F45/(1+$B7)^('DCF Model'!C19+3)+'DCF Model'!G45/(1+$B7)^('DCF Model'!C19+4)+'DCF Model'!G45*(1+E$6)/($B7-E$6)/(1+$B7)^('DCF Model'!C19+4)-'DCF Model'!C16)*1000000/'DCF Model'!C15,0),"") -> 3254 | F7: =IFERROR(ROUND(('DCF Model'!C45/(1+$B7)^('DCF Model'!C19+0)+'DCF Model'!D45/(1+$B7)^('DCF Model'!C19+1)+'DCF Model'!E45/(1+$B7)^('DCF Model'!C19+2)+'DCF Model'!F45/(1+$B7)^('DCF Model'!C19+3)+'DCF Model'!G45/(1+$B7)^('DCF Model'!C19+4)+'DCF Model'!G45*(1+F$6)/($B7-F$6)/(1+$B7)^('DCF Model'!C19+4)-'DCF Model'!C16)*1000000/'DCF Model'!C15,0),"") -> 3317 | G7: =IFERROR(ROUND(('DCF Model'!C45/(1+$B7)^('DCF Model'!C19+0)+'DCF Model'!D45/(1+$B7)^('DCF Model'!C19+1)+'DCF Model'!E45/(1+$B7)^('DCF Model'!C19+2)+'DCF Model'!F45/(1+$B7)^('DCF Model'!C19+3)+'DCF Model'!G45/(1+$B7)^('DCF Model'!C19+4)+'DCF Model'!G45*(1+G$6)/($B7-G$6)/(1+$B7)^('DCF Model'!C19+4)-'DCF Model'!C16)*1000000/'DCF Model'!C15,0),"") -> 3384 | H7: =IFERROR(ROUND(('DCF Model'!C45/(1+$B7)^('DCF Model'!C19+0)+'DCF Model'!D45/(1+$B7)^('DCF Model'!C19+1)+'DCF Model'!E45/(1+$B7)^('DCF Model'!C19+2)+'DCF Model'!F45/(1+$B7)^('DCF Model'!C19+3)+'DCF Model'!G45/(1+$B7)^('DCF Model'!C19+4)+'DCF Model'!G45*(1+H$6)/($B7-H$6)/(1+$B7)^('DCF Model'!C19+4)-'DCF Model'!C16)*1000000/'DCF Model'!C15,0),"") -> 3455 | I7: =IFERROR(ROUND(('DCF Model'!C45/(1+$B7)^('DCF Model'!C19+0)+'DCF Model'!D45/(1+$B7)^('DCF Model'!C19+1)+'DCF Model'!E45/(1+$B7)^('DCF Model'!C19+2)+'DCF Model'!F45/(1+$B7)^('DCF Model'!C19+3)+'DCF Model'!G45/(1+$B7)^('DCF Model'!C19+4)+'DCF Model'!G45*(1+I$6)/($B7-I$6)/(1+$B7)^('DCF Model'!C19+4)-'DCF Model'!C16)*1000000/'DCF Model'!C15,0),"") -> 3530
B8: =$C$3-0.01 -> 0.1092 | C8: =IFERROR(ROUND(('DCF Model'!C45/(1+$B8)^('DCF Model'!C19+0)+'DCF Model'!D45/(1+$B8)^('DCF Model'!C19+1)+'DCF Model'!E45/(1+$B8)^('DCF Model'!C19+2)+'DCF Model'!F45/(1+$B8)^('DCF Model'!C19+3)+'DCF Model'!G45/(1+$B8)^('DCF Model'!C19+4)+'DCF Model'!G45*(1+C$6)/($B8-C$6)/(1+$B8)^('DCF Model'!C19+4)-'DCF Model'!C16)*1000000/'DCF Model'!C15,0),"") -> 3002 | D8: =IFERROR(ROUND(('DCF Model'!C45/(1+$B8)^('DCF Model'!C19+0)+'DCF Model'!D45/(1+$B8)^('DCF Model'!C19+1)+'DCF Model'!E45/(1+$B8)^('DCF Model'!C19+2)+'DCF Model'!F45/(1+$B8)^('DCF Model'!C19+3)+'DCF Model'!G45/(1+$B8)^('DCF Model'!C19+4)+'DCF Model'!G45*(1+D$6)/($B8-D$6)/(1+$B8)^('DCF Model'!C19+4)-'DCF Model'!C16)*1000000/'DCF Model'!C15,0),"") -> 3052 | E8: =IFERROR(ROUND(('DCF Model'!C45/(1+$B8)^('DCF Model'!C19+0)+'DCF Model'!D45/(1+$B8)^('DCF Model'!C19+1)+'DCF Model'!E45/(1+$B8)^('DCF Model'!C19+2)+'DCF Model'!F45/(1+$B8)^('DCF Model'!C19+3)+'DCF Model'!G45/(1+$B8)^('DCF Model'!C19+4)+'DCF Model'!G45*(1+E$6)/($B8-E$6)/(1+$B8)^('DCF Model'!C19+4)-'DCF Model'!C16)*1000000/'DCF Model'!C15,0),"") -> 3104 | F8: =IFERROR(ROUND(('DCF Model'!C45/(1+$B8)^('DCF Model'!C19+0)+'DCF Model'!D45/(1+$B8)^('DCF Model'!C19+1)+'DCF Model'!E45/(1+$B8)^('DCF Model'!C19+2)+'DCF Model'!F45/(1+$B8)^('DCF Model'!C19+3)+'DCF Model'!G45/(1+$B8)^('DCF Model'!C19+4)+'DCF Model'!G45*(1+F$6)/($B8-F$6)/(1+$B8)^('DCF Model'!C19+4)-'DCF Model'!C16)*1000000/'DCF Model'!C15,0),"") -> 3160 | G8: =IFERROR(ROUND(('DCF Model'!C45/(1+$B8)^('DCF Model'!C19+0)+'DCF Model'!D45/(1+$B8)^('DCF Model'!C19+1)+'DCF Model'!E45/(1+$B8)^('DCF Model'!C19+2)+'DCF Model'!F45/(1+$B8)^('DCF Model'!C19+3)+'DCF Model'!G45/(1+$B8)^('DCF Model'!C19+4)+'DCF Model'!G45*(1+G$6)/($B8-G$6)/(1+$B8)^('DCF Model'!C19+4)-'DCF Model'!C16)*1000000/'DCF Model'!C15,0),"") -> 3218 | H8: =IFERROR(ROUND(('DCF Model'!C45/(1+$B8)^('DCF Model'!C19+0)+'DCF Model'!D45/(1+$B8)^('DCF Model'!C19+1)+'DCF Model'!E45/(1+$B8)^('DCF Model'!C19+2)+'DCF Model'!F45/(1+$B8)^('DCF Model'!C19+3)+'DCF Model'!G45/(1+$B8)^('DCF Model'!C19+4)+'DCF Model'!G45*(1+H$6)/($B8-H$6)/(1+$B8)^('DCF Model'!C19+4)-'DCF Model'!C16)*1000000/'DCF Model'!C15,0),"") -> 3280 | I8: =IFERROR(ROUND(('DCF Model'!C45/(1+$B8)^('DCF Model'!C19+0)+'DCF Model'!D45/(1+$B8)^('DCF Model'!C19+1)+'DCF Model'!E45/(1+$B8)^('DCF Model'!C19+2)+'DCF Model'!F45/(1+$B8)^('DCF Model'!C19+3)+'DCF Model'!G45/(1+$B8)^('DCF Model'!C19+4)+'DCF Model'!G45*(1+I$6)/($B8-I$6)/(1+$B8)^('DCF Model'!C19+4)-'DCF Model'!C16)*1000000/'DCF Model'!C15,0),"") -> 3346
B9: =$C$3-0.005 -> 0.1142 | C9: =IFERROR(ROUND(('DCF Model'!C45/(1+$B9)^('DCF Model'!C19+0)+'DCF Model'!D45/(1+$B9)^('DCF Model'!C19+1)+'DCF Model'!E45/(1+$B9)^('DCF Model'!C19+2)+'DCF Model'!F45/(1+$B9)^('DCF Model'!C19+3)+'DCF Model'!G45/(1+$B9)^('DCF Model'!C19+4)+'DCF Model'!G45*(1+C$6)/($B9-C$6)/(1+$B9)^('DCF Model'!C19+4)-'DCF Model'!C16)*1000000/'DCF Model'!C15,0),"") -> 2880 | D9: =IFERROR(ROUND(('DCF Model'!C45/(1+$B9)^('DCF Model'!C19+0)+'DCF Model'!D45/(1+$B9)^('DCF Model'!C19+1)+'DCF Model'!E45/(1+$B9)^('DCF Model'!C19+2)+'DCF Model'!F45/(1+$B9)^('DCF Model'!C19+3)+'DCF Model'!G45/(1+$B9)^('DCF Model'!C19+4)+'DCF Model'!G45*(1+D$6)/($B9-D$6)/(1+$B9)^('DCF Model'!C19+4)-'DCF Model'!C16)*1000000/'DCF Model'!C15,0),"") -> 2924 | E9: =IFERROR(ROUND(('DCF Model'!C45/(1+$B9)^('DCF Model'!C19+0)+'DCF Model'!D45/(1+$B9)^('DCF Model'!C19+1)+'DCF Model'!E45/(1+$B9)^('DCF Model'!C19+2)+'DCF Model'!F45/(1+$B9)^('DCF Model'!C19+3)+'DCF Model'!G45/(1+$B9)^('DCF Model'!C19+4)+'DCF Model'!G45*(1+E$6)/($B9-E$6)/(1+$B9)^('DCF Model'!C19+4)-'DCF Model'!C16)*1000000/'DCF Model'!C15,0),"") -> 2970 | F9: =IFERROR(ROUND(('DCF Model'!C45/(1+$B9)^('DCF Model'!C19+0)+'DCF Model'!D45/(1+$B9)^('DCF Model'!C19+1)+'DCF Model'!E45/(1+$B9)^('DCF Model'!C19+2)+'DCF Model'!F45/(1+$B9)^('DCF Model'!C19+3)+'DCF Model'!G45/(1+$B9)^('DCF Model'!C19+4)+'DCF Model'!G45*(1+F$6)/($B9-F$6)/(1+$B9)^('DCF Model'!C19+4)-'DCF Model'!C16)*1000000/'DCF Model'!C15,0),"") -> 3019 | G9: =IFERROR(ROUND(('DCF Model'!C45/(1+$B9)^('DCF Model'!C19+0)+'DCF Model'!D45/(1+$B9)^('DCF Model'!C19+1)+'DCF Model'!E45/(1+$B9)^('DCF Model'!C19+2)+'DCF Model'!F45/(1+$B9)^('DCF Model'!C19+3)+'DCF Model'!G45/(1+$B9)^('DCF Model'!C19+4)+'DCF Model'!G45*(1+G$6)/($B9-G$6)/(1+$B9)^('DCF Model'!C19+4)-'DCF Model'!C16)*1000000/'DCF Model'!C15,0),"") -> 3071 | H9: =IFERROR(ROUND(('DCF Model'!C45/(1+$B9)^('DCF Model'!C19+0)+'DCF Model'!D45/(1+$B9)^('DCF Model'!C19+1)+'DCF Model'!E45/(1+$B9)^('DCF Model'!C19+2)+'DCF Model'!F45/(1+$B9)^('DCF Model'!C19+3)+'DCF Model'!G45/(1+$B9)^('DCF Model'!C19+4)+'DCF Model'!G45*(1+H$6)/($B9-H$6)/(1+$B9)^('DCF Model'!C19+4)-'DCF Model'!C16)*1000000/'DCF Model'!C15,0),"") -> 3125 | I9: =IFERROR(ROUND(('DCF Model'!C45/(1+$B9)^('DCF Model'!C19+0)+'DCF Model'!D45/(1+$B9)^('DCF Model'!C19+1)+'DCF Model'!E45/(1+$B9)^('DCF Model'!C19+2)+'DCF Model'!F45/(1+$B9)^('DCF Model'!C19+3)+'DCF Model'!G45/(1+$B9)^('DCF Model'!C19+4)+'DCF Model'!G45*(1+I$6)/($B9-I$6)/(1+$B9)^('DCF Model'!C19+4)-'DCF Model'!C16)*1000000/'DCF Model'!C15,0),"") -> 3183
B10: =$C$3 -> 0.1192 | C10: =IFERROR(ROUND(('DCF Model'!C45/(1+$B10)^('DCF Model'!C19+0)+'DCF Model'!D45/(1+$B10)^('DCF Model'!C19+1)+'DCF Model'!E45/(1+$B10)^('DCF Model'!C19+2)+'DCF Model'!F45/(1+$B10)^('DCF Model'!C19+3)+'DCF Model'!G45/(1+$B10)^('DCF Model'!C19+4)+'DCF Model'!G45*(1+C$6)/($B10-C$6)/(1+$B10)^('DCF Model'!C19+4)-'DCF Model'!C16)*1000000/'DCF Model'!C15,0),"") -> 2768 | D10: =IFERROR(ROUND(('DCF Model'!C45/(1+$B10)^('DCF Model'!C19+0)+'DCF Model'!D45/(1+$B10)^('DCF Model'!C19+1)+'DCF Model'!E45/(1+$B10)^('DCF Model'!C19+2)+'DCF Model'!F45/(1+$B10)^('DCF Model'!C19+3)+'DCF Model'!G45/(1+$B10)^('DCF Model'!C19+4)+'DCF Model'!G45*(1+D$6)/($B10-D$6)/(1+$B10)^('DCF Model'!C19+4)-'DCF Model'!C16)*1000000/'DCF Model'!C15,0),"") -> 2808 | E10: =IFERROR(ROUND(('DCF Model'!C45/(1+$B10)^('DCF Model'!C19+0)+'DCF Model'!D45/(1+$B10)^('DCF Model'!C19+1)+'DCF Model'!E45/(1+$B10)^('DCF Model'!C19+2)+'DCF Model'!F45/(1+$B10)^('DCF Model'!C19+3)+'DCF Model'!G45/(1+$B10)^('DCF Model'!C19+4)+'DCF Model'!G45*(1+E$6)/($B10-E$6)/(1+$B10)^('DCF Model'!C19+4)-'DCF Model'!C16)*1000000/'DCF Model'!C15,0),"") -> 2849 | F10: =IFERROR(ROUND(('DCF Model'!C45/(1+$B10)^('DCF Model'!C19+0)+'DCF Model'!D45/(1+$B10)^('DCF Model'!C19+1)+'DCF Model'!E45/(1+$B10)^('DCF Model'!C19+2)+'DCF Model'!F45/(1+$B10)^('DCF Model'!C19+3)+'DCF Model'!G45/(1+$B10)^('DCF Model'!C19+4)+'DCF Model'!G45*(1+F$6)/($B10-F$6)/(1+$B10)^('DCF Model'!C19+4)-'DCF Model'!C16)*1000000/'DCF Model'!C15,0),"") -> 2893 | G10: =IFERROR(ROUND(('DCF Model'!C45/(1+$B10)^('DCF Model'!C19+0)+'DCF Model'!D45/(1+$B10)^('DCF Model'!C19+1)+'DCF Model'!E45/(1+$B10)^('DCF Model'!C19+2)+'DCF Model'!F45/(1+$B10)^('DCF Model'!C19+3)+'DCF Model'!G45/(1+$B10)^('DCF Model'!C19+4)+'DCF Model'!G45*(1+G$6)/($B10-G$6)/(1+$B10)^('DCF Model'!C19+4)-'DCF Model'!C16)*1000000/'DCF Model'!C15,0),"") -> 2939 | H10: =IFERROR(ROUND(('DCF Model'!C45/(1+$B10)^('DCF Model'!C19+0)+'DCF Model'!D45/(1+$B10)^('DCF Model'!C19+1)+'DCF Model'!E45/(1+$B10)^('DCF Model'!C19+2)+'DCF Model'!F45/(1+$B10)^('DCF Model'!C19+3)+'DCF Model'!G45/(1+$B10)^('DCF Model'!C19+4)+'DCF Model'!G45*(1+H$6)/($B10-H$6)/(1+$B10)^('DCF Model'!C19+4)-'DCF Model'!C16)*1000000/'DCF Model'!C15,0),"") -> 2987 | I10: =IFERROR(ROUND(('DCF Model'!C45/(1+$B10)^('DCF Model'!C19+0)+'DCF Model'!D45/(1+$B10)^('DCF Model'!C19+1)+'DCF Model'!E45/(1+$B10)^('DCF Model'!C19+2)+'DCF Model'!F45/(1+$B10)^('DCF Model'!C19+3)+'DCF Model'!G45/(1+$B10)^('DCF Model'!C19+4)+'DCF Model'!G45*(1+I$6)/($B10-I$6)/(1+$B10)^('DCF Model'!C19+4)-'DCF Model'!C16)*1000000/'DCF Model'!C15,0),"") -> 3038
B11: =$C$3+0.005 -> 0.1242 | C11: =IFERROR(ROUND(('DCF Model'!C45/(1+$B11)^('DCF Model'!C19+0)+'DCF Model'!D45/(1+$B11)^('DCF Model'!C19+1)+'DCF Model'!E45/(1+$B11)^('DCF Model'!C19+2)+'DCF Model'!F45/(1+$B11)^('DCF Model'!C19+3)+'DCF Model'!G45/(1+$B11)^('DCF Model'!C19+4)+'DCF Model'!G45*(1+C$6)/($B11-C$6)/(1+$B11)^('DCF Model'!C19+4)-'DCF Model'!C16)*1000000/'DCF Model'!C15,0),"") -> 2667 | D11: =IFERROR(ROUND(('DCF Model'!C45/(1+$B11)^('DCF Model'!C19+0)+'DCF Model'!D45/(1+$B11)^('DCF Model'!C19+1)+'DCF Model'!E45/(1+$B11)^('DCF Model'!C19+2)+'DCF Model'!F45/(1+$B11)^('DCF Model'!C19+3)+'DCF Model'!G45/(1+$B11)^('DCF Model'!C19+4)+'DCF Model'!G45*(1+D$6)/($B11-D$6)/(1+$B11)^('DCF Model'!C19+4)-'DCF Model'!C16)*1000000/'DCF Model'!C15,0),"") -> 2702 | E11: =IFERROR(ROUND(('DCF Model'!C45/(1+$B11)^('DCF Model'!C19+0)+'DCF Model'!D45/(1+$B11)^('DCF Model'!C19+1)+'DCF Model'!E45/(1+$B11)^('DCF Model'!C19+2)+'DCF Model'!F45/(1+$B11)^('DCF Model'!C19+3)+'DCF Model'!G45/(1+$B11)^('DCF Model'!C19+4)+'DCF Model'!G45*(1+E$6)/($B11-E$6)/(1+$B11)^('DCF Model'!C19+4)-'DCF Model'!C16)*1000000/'DCF Model'!C15,0),"") -> 2740 | F11: =IFERROR(ROUND(('DCF Model'!C45/(1+$B11)^('DCF Model'!C19+0)+'DCF Model'!D45/(1+$B11)^('DCF Model'!C19+1)+'DCF Model'!E45/(1+$B11)^('DCF Model'!C19+2)+'DCF Model'!F45/(1+$B11)^('DCF Model'!C19+3)+'DCF Model'!G45/(1+$B11)^('DCF Model'!C19+4)+'DCF Model'!G45*(1+F$6)/($B11-F$6)/(1+$B11)^('DCF Model'!C19+4)-'DCF Model'!C16)*1000000/'DCF Model'!C15,0),"") -> 2779 | G11: =IFERROR(ROUND(('DCF Model'!C45/(1+$B11)^('DCF Model'!C19+0)+'DCF Model'!D45/(1+$B11)^('DCF Model'!C19+1)+'DCF Model'!E45/(1+$B11)^('DCF Model'!C19+2)+'DCF Model'!F45/(1+$B11)^('DCF Model'!C19+3)+'DCF Model'!G45/(1+$B11)^('DCF Model'!C19+4)+'DCF Model'!G45*(1+G$6)/($B11-G$6)/(1+$B11)^('DCF Model'!C19+4)-'DCF Model'!C16)*1000000/'DCF Model'!C15,0),"") -> 2819 | H11: =IFERROR(ROUND(('DCF Model'!C45/(1+$B11)^('DCF Model'!C19+0)+'DCF Model'!D45/(1+$B11)^('DCF Model'!C19+1)+'DCF Model'!E45/(1+$B11)^('DCF Model'!C19+2)+'DCF Model'!F45/(1+$B11)^('DCF Model'!C19+3)+'DCF Model'!G45/(1+$B11)^('DCF Model'!C19+4)+'DCF Model'!G45*(1+H$6)/($B11-H$6)/(1+$B11)^('DCF Model'!C19+4)-'DCF Model'!C16)*1000000/'DCF Model'!C15,0),"") -> 2862 | I11: =IFERROR(ROUND(('DCF Model'!C45/(1+$B11)^('DCF Model'!C19+0)+'DCF Model'!D45/(1+$B11)^('DCF Model'!C19+1)+'DCF Model'!E45/(1+$B11)^('DCF Model'!C19+2)+'DCF Model'!F45/(1+$B11)^('DCF Model'!C19+3)+'DCF Model'!G45/(1+$B11)^('DCF Model'!C19+4)+'DCF Model'!G45*(1+I$6)/($B11-I$6)/(1+$B11)^('DCF Model'!C19+4)-'DCF Model'!C16)*1000000/'DCF Model'!C15,0),"") -> 2907
B12: =$C$3+0.01 -> 0.1292 | C12: =IFERROR(ROUND(('DCF Model'!C45/(1+$B12)^('DCF Model'!C19+0)+'DCF Model'!D45/(1+$B12)^('DCF Model'!C19+1)+'DCF Model'!E45/(1+$B12)^('DCF Model'!C19+2)+'DCF Model'!F45/(1+$B12)^('DCF Model'!C19+3)+'DCF Model'!G45/(1+$B12)^('DCF Model'!C19+4)+'DCF Model'!G45*(1+C$6)/($B12-C$6)/(1+$B12)^('DCF Model'!C19+4)-'DCF Model'!C16)*1000000/'DCF Model'!C15,0),"") -> 2574 | D12: =IFERROR(ROUND(('DCF Model'!C45/(1+$B12)^('DCF Model'!C19+0)+'DCF Model'!D45/(1+$B12)^('DCF Model'!C19+1)+'DCF Model'!E45/(1+$B12)^('DCF Model'!C19+2)+'DCF Model'!F45/(1+$B12)^('DCF Model'!C19+3)+'DCF Model'!G45/(1+$B12)^('DCF Model'!C19+4)+'DCF Model'!G45*(1+D$6)/($B12-D$6)/(1+$B12)^('DCF Model'!C19+4)-'DCF Model'!C16)*1000000/'DCF Model'!C15,0),"") -> 2606 | E12: =IFERROR(ROUND(('DCF Model'!C45/(1+$B12)^('DCF Model'!C19+0)+'DCF Model'!D45/(1+$B12)^('DCF Model'!C19+1)+'DCF Model'!E45/(1+$B12)^('DCF Model'!C19+2)+'DCF Model'!F45/(1+$B12)^('DCF Model'!C19+3)+'DCF Model'!G45/(1+$B12)^('DCF Model'!C19+4)+'DCF Model'!G45*(1+E$6)/($B12-E$6)/(1+$B12)^('DCF Model'!C19+4)-'DCF Model'!C16)*1000000/'DCF Model'!C15,0),"") -> 2640 | F12: =IFERROR(ROUND(('DCF Model'!C45/(1+$B12)^('DCF Model'!C19+0)+'DCF Model'!D45/(1+$B12)^('DCF Model'!C19+1)+'DCF Model'!E45/(1+$B12)^('DCF Model'!C19+2)+'DCF Model'!F45/(1+$B12)^('DCF Model'!C19+3)+'DCF Model'!G45/(1+$B12)^('DCF Model'!C19+4)+'DCF Model'!G45*(1+F$6)/($B12-F$6)/(1+$B12)^('DCF Model'!C19+4)-'DCF Model'!C16)*1000000/'DCF Model'!C15,0),"") -> 2675 | G12: =IFERROR(ROUND(('DCF Model'!C45/(1+$B12)^('DCF Model'!C19+0)+'DCF Model'!D45/(1+$B12)^('DCF Model'!C19+1)+'DCF Model'!E45/(1+$B12)^('DCF Model'!C19+2)+'DCF Model'!F45/(1+$B12)^('DCF Model'!C19+3)+'DCF Model'!G45/(1+$B12)^('DCF Model'!C19+4)+'DCF Model'!G45*(1+G$6)/($B12-G$6)/(1+$B12)^('DCF Model'!C19+4)-'DCF Model'!C16)*1000000/'DCF Model'!C15,0),"") -> 2712 | H12: =IFERROR(ROUND(('DCF Model'!C45/(1+$B12)^('DCF Model'!C19+0)+'DCF Model'!D45/(1+$B12)^('DCF Model'!C19+1)+'DCF Model'!E45/(1+$B12)^('DCF Model'!C19+2)+'DCF Model'!F45/(1+$B12)^('DCF Model'!C19+3)+'DCF Model'!G45/(1+$B12)^('DCF Model'!C19+4)+'DCF Model'!G45*(1+H$6)/($B12-H$6)/(1+$B12)^('DCF Model'!C19+4)-'DCF Model'!C16)*1000000/'DCF Model'!C15,0),"") -> 2750 | I12: =IFERROR(ROUND(('DCF Model'!C45/(1+$B12)^('DCF Model'!C19+0)+'DCF Model'!D45/(1+$B12)^('DCF Model'!C19+1)+'DCF Model'!E45/(1+$B12)^('DCF Model'!C19+2)+'DCF Model'!F45/(1+$B12)^('DCF Model'!C19+3)+'DCF Model'!G45/(1+$B12)^('DCF Model'!C19+4)+'DCF Model'!G45*(1+I$6)/($B12-I$6)/(1+$B12)^('DCF Model'!C19+4)-'DCF Model'!C16)*1000000/'DCF Model'!C15,0),"") -> 2790
B13: =$C$3+0.015 -> 0.1342 | C13: =IFERROR(ROUND(('DCF Model'!C45/(1+$B13)^('DCF Model'!C19+0)+'DCF Model'!D45/(1+$B13)^('DCF Model'!C19+1)+'DCF Model'!E45/(1+$B13)^('DCF Model'!C19+2)+'DCF Model'!F45/(1+$B13)^('DCF Model'!C19+3)+'DCF Model'!G45/(1+$B13)^('DCF Model'!C19+4)+'DCF Model'!G45*(1+C$6)/($B13-C$6)/(1+$B13)^('DCF Model'!C19+4)-'DCF Model'!C16)*1000000/'DCF Model'!C15,0),"") -> 2490 | D13: =IFERROR(ROUND(('DCF Model'!C45/(1+$B13)^('DCF Model'!C19+0)+'DCF Model'!D45/(1+$B13)^('DCF Model'!C19+1)+'DCF Model'!E45/(1+$B13)^('DCF Model'!C19+2)+'DCF Model'!F45/(1+$B13)^('DCF Model'!C19+3)+'DCF Model'!G45/(1+$B13)^('DCF Model'!C19+4)+'DCF Model'!G45*(1+D$6)/($B13-D$6)/(1+$B13)^('DCF Model'!C19+4)-'DCF Model'!C16)*1000000/'DCF Model'!C15,0),"") -> 2519 | E13: =IFERROR(ROUND(('DCF Model'!C45/(1+$B13)^('DCF Model'!C19+0)+'DCF Model'!D45/(1+$B13)^('DCF Model'!C19+1)+'DCF Model'!E45/(1+$B13)^('DCF Model'!C19+2)+'DCF Model'!F45/(1+$B13)^('DCF Model'!C19+3)+'DCF Model'!G45/(1+$B13)^('DCF Model'!C19+4)+'DCF Model'!G45*(1+E$6)/($B13-E$6)/(1+$B13)^('DCF Model'!C19+4)-'DCF Model'!C16)*1000000/'DCF Model'!C15,0),"") -> 2549 | F13: =IFERROR(ROUND(('DCF Model'!C45/(1+$B13)^('DCF Model'!C19+0)+'DCF Model'!D45/(1+$B13)^('DCF Model'!C19+1)+'DCF Model'!E45/(1+$B13)^('DCF Model'!C19+2)+'DCF Model'!F45/(1+$B13)^('DCF Model'!C19+3)+'DCF Model'!G45/(1+$B13)^('DCF Model'!C19+4)+'DCF Model'!G45*(1+F$6)/($B13-F$6)/(1+$B13)^('DCF Model'!C19+4)-'DCF Model'!C16)*1000000/'DCF Model'!C15,0),"") -> 2580 | G13: =IFERROR(ROUND(('DCF Model'!C45/(1+$B13)^('DCF Model'!C19+0)+'DCF Model'!D45/(1+$B13)^('DCF Model'!C19+1)+'DCF Model'!E45/(1+$B13)^('DCF Model'!C19+2)+'DCF Model'!F45/(1+$B13)^('DCF Model'!C19+3)+'DCF Model'!G45/(1+$B13)^('DCF Model'!C19+4)+'DCF Model'!G45*(1+G$6)/($B13-G$6)/(1+$B13)^('DCF Model'!C19+4)-'DCF Model'!C16)*1000000/'DCF Model'!C15,0),"") -> 2613 | H13: =IFERROR(ROUND(('DCF Model'!C45/(1+$B13)^('DCF Model'!C19+0)+'DCF Model'!D45/(1+$B13)^('DCF Model'!C19+1)+'DCF Model'!E45/(1+$B13)^('DCF Model'!C19+2)+'DCF Model'!F45/(1+$B13)^('DCF Model'!C19+3)+'DCF Model'!G45/(1+$B13)^('DCF Model'!C19+4)+'DCF Model'!G45*(1+H$6)/($B13-H$6)/(1+$B13)^('DCF Model'!C19+4)-'DCF Model'!C16)*1000000/'DCF Model'!C15,0),"") -> 2648 | I13: =IFERROR(ROUND(('DCF Model'!C45/(1+$B13)^('DCF Model'!C19+0)+'DCF Model'!D45/(1+$B13)^('DCF Model'!C19+1)+'DCF Model'!E45/(1+$B13)^('DCF Model'!C19+2)+'DCF Model'!F45/(1+$B13)^('DCF Model'!C19+3)+'DCF Model'!G45/(1+$B13)^('DCF Model'!C19+4)+'DCF Model'!G45*(1+I$6)/($B13-I$6)/(1+$B13)^('DCF Model'!C19+4)-'DCF Model'!C16)*1000000/'DCF Model'!C15,0),"") -> 2684
B16: Table 2: WACC vs Exit Multiple (Exit Multiple - Implied Share Price, JPY)
B17: WACC \ Exit Multiple | C17: =$I$3-3 -> 5 | D17: =$I$3-2 -> 6 | E17: =$I$3-1 -> 7 | F17: =$I$3 -> 8 | G17: =$I$3+1 -> 9 | H17: =$I$3+2 -> 10 | I17: =$I$3+3 -> 11
B18: =$C$3-0.015 -> 0.1042 | C18: =IFERROR(ROUND(('DCF Model'!C45/(1+$B18)^('DCF Model'!C19+0)+'DCF Model'!D45/(1+$B18)^('DCF Model'!C19+1)+'DCF Model'!E45/(1+$B18)^('DCF Model'!C19+2)+'DCF Model'!F45/(1+$B18)^('DCF Model'!C19+3)+'DCF Model'!G45/(1+$B18)^('DCF Model'!C19+4)+('DCF Model'!G39+'DCF Model'!G42)*C$17/(1+$B18)^('DCF Model'!C19+4)-'DCF Model'!C16)*1000000/'DCF Model'!C15,0),"") -> 2640 | D18: =IFERROR(ROUND(('DCF Model'!C45/(1+$B18)^('DCF Model'!C19+0)+'DCF Model'!D45/(1+$B18)^('DCF Model'!C19+1)+'DCF Model'!E45/(1+$B18)^('DCF Model'!C19+2)+'DCF Model'!F45/(1+$B18)^('DCF Model'!C19+3)+'DCF Model'!G45/(1+$B18)^('DCF Model'!C19+4)+('DCF Model'!G39+'DCF Model'!G42)*D$17/(1+$B18)^('DCF Model'!C19+4)-'DCF Model'!C16)*1000000/'DCF Model'!C15,0),"") -> 2907 | E18: =IFERROR(ROUND(('DCF Model'!C45/(1+$B18)^('DCF Model'!C19+0)+'DCF Model'!D45/(1+$B18)^('DCF Model'!C19+1)+'DCF Model'!E45/(1+$B18)^('DCF Model'!C19+2)+'DCF Model'!F45/(1+$B18)^('DCF Model'!C19+3)+'DCF Model'!G45/(1+$B18)^('DCF Model'!C19+4)+('DCF Model'!G39+'DCF Model'!G42)*E$17/(1+$B18)^('DCF Model'!C19+4)-'DCF Model'!C16)*1000000/'DCF Model'!C15,0),"") -> 3174 | F18: =IFERROR(ROUND(('DCF Model'!C45/(1+$B18)^('DCF Model'!C19+0)+'DCF Model'!D45/(1+$B18)^('DCF Model'!C19+1)+'DCF Model'!E45/(1+$B18)^('DCF Model'!C19+2)+'DCF Model'!F45/(1+$B18)^('DCF Model'!C19+3)+'DCF Model'!G45/(1+$B18)^('DCF Model'!C19+4)+('DCF Model'!G39+'DCF Model'!G42)*F$17/(1+$B18)^('DCF Model'!C19+4)-'DCF Model'!C16)*1000000/'DCF Model'!C15,0),"") -> 3442 | G18: =IFERROR(ROUND(('DCF Model'!C45/(1+$B18)^('DCF Model'!C19+0)+'DCF Model'!D45/(1+$B18)^('DCF Model'!C19+1)+'DCF Model'!E45/(1+$B18)^('DCF Model'!C19+2)+'DCF Model'!F45/(1+$B18)^('DCF Model'!C19+3)+'DCF Model'!G45/(1+$B18)^('DCF Model'!C19+4)+('DCF Model'!G39+'DCF Model'!G42)*G$17/(1+$B18)^('DCF Model'!C19+4)-'DCF Model'!C16)*1000000/'DCF Model'!C15,0),"") -> 3709 | H18: =IFERROR(ROUND(('DCF Model'!C45/(1+$B18)^('DCF Model'!C19+0)+'DCF Model'!D45/(1+$B18)^('DCF Model'!C19+1)+'DCF Model'!E45/(1+$B18)^('DCF Model'!C19+2)+'DCF Model'!F45/(1+$B18)^('DCF Model'!C19+3)+'DCF Model'!G45/(1+$B18)^('DCF Model'!C19+4)+('DCF Model'!G39+'DCF Model'!G42)*H$17/(1+$B18)^('DCF Model'!C19+4)-'DCF Model'!C16)*1000000/'DCF Model'!C15,0),"") -> 3976 | I18: =IFERROR(ROUND(('DCF Model'!C45/(1+$B18)^('DCF Model'!C19+0)+'DCF Model'!D45/(1+$B18)^('DCF Model'!C19+1)+'DCF Model'!E45/(1+$B18)^('DCF Model'!C19+2)+'DCF Model'!F45/(1+$B18)^('DCF Model'!C19+3)+'DCF Model'!G45/(1+$B18)^('DCF Model'!C19+4)+('DCF Model'!G39+'DCF Model'!G42)*I$17/(1+$B18)^('DCF Model'!C19+4)-'DCF Model'!C16)*1000000/'DCF Model'!C15,0),"") -> 4243
B19: =$C$3-0.01 -> 0.1092 | C19: =IFERROR(ROUND(('DCF Model'!C45/(1+$B19)^('DCF Model'!C19+0)+'DCF Model'!D45/(1+$B19)^('DCF Model'!C19+1)+'DCF Model'!E45/(1+$B19)^('DCF Model'!C19+2)+'DCF Model'!F45/(1+$B19)^('DCF Model'!C19+3)+'DCF Model'!G45/(1+$B19)^('DCF Model'!C19+4)+('DCF Model'!G39+'DCF Model'!G42)*C$17/(1+$B19)^('DCF Model'!C19+4)-'DCF Model'!C16)*1000000/'DCF Model'!C15,0),"") -> 2606 | D19: =IFERROR(ROUND(('DCF Model'!C45/(1+$B19)^('DCF Model'!C19+0)+'DCF Model'!D45/(1+$B19)^('DCF Model'!C19+1)+'DCF Model'!E45/(1+$B19)^('DCF Model'!C19+2)+'DCF Model'!F45/(1+$B19)^('DCF Model'!C19+3)+'DCF Model'!G45/(1+$B19)^('DCF Model'!C19+4)+('DCF Model'!G39+'DCF Model'!G42)*D$17/(1+$B19)^('DCF Model'!C19+4)-'DCF Model'!C16)*1000000/'DCF Model'!C15,0),"") -> 2868 | E19: =IFERROR(ROUND(('DCF Model'!C45/(1+$B19)^('DCF Model'!C19+0)+'DCF Model'!D45/(1+$B19)^('DCF Model'!C19+1)+'DCF Model'!E45/(1+$B19)^('DCF Model'!C19+2)+'DCF Model'!F45/(1+$B19)^('DCF Model'!C19+3)+'DCF Model'!G45/(1+$B19)^('DCF Model'!C19+4)+('DCF Model'!G39+'DCF Model'!G42)*E$17/(1+$B19)^('DCF Model'!C19+4)-'DCF Model'!C16)*1000000/'DCF Model'!C15,0),"") -> 3130 | F19: =IFERROR(ROUND(('DCF Model'!C45/(1+$B19)^('DCF Model'!C19+0)+'DCF Model'!D45/(1+$B19)^('DCF Model'!C19+1)+'DCF Model'!E45/(1+$B19)^('DCF Model'!C19+2)+'DCF Model'!F45/(1+$B19)^('DCF Model'!C19+3)+'DCF Model'!G45/(1+$B19)^('DCF Model'!C19+4)+('DCF Model'!G39+'DCF Model'!G42)*F$17/(1+$B19)^('DCF Model'!C19+4)-'DCF Model'!C16)*1000000/'DCF Model'!C15,0),"") -> 3393 | G19: =IFERROR(ROUND(('DCF Model'!C45/(1+$B19)^('DCF Model'!C19+0)+'DCF Model'!D45/(1+$B19)^('DCF Model'!C19+1)+'DCF Model'!E45/(1+$B19)^('DCF Model'!C19+2)+'DCF Model'!F45/(1+$B19)^('DCF Model'!C19+3)+'DCF Model'!G45/(1+$B19)^('DCF Model'!C19+4)+('DCF Model'!G39+'DCF Model'!G42)*G$17/(1+$B19)^('DCF Model'!C19+4)-'DCF Model'!C16)*1000000/'DCF Model'!C15,0),"") -> 3655 | H19: =IFERROR(ROUND(('DCF Model'!C45/(1+$B19)^('DCF Model'!C19+0)+'DCF Model'!D45/(1+$B19)^('DCF Model'!C19+1)+'DCF Model'!E45/(1+$B19)^('DCF Model'!C19+2)+'DCF Model'!F45/(1+$B19)^('DCF Model'!C19+3)+'DCF Model'!G45/(1+$B19)^('DCF Model'!C19+4)+('DCF Model'!G39+'DCF Model'!G42)*H$17/(1+$B19)^('DCF Model'!C19+4)-'DCF Model'!C16)*1000000/'DCF Model'!C15,0),"") -> 3917 | I19: =IFERROR(ROUND(('DCF Model'!C45/(1+$B19)^('DCF Model'!C19+0)+'DCF Model'!D45/(1+$B19)^('DCF Model'!C19+1)+'DCF Model'!E45/(1+$B19)^('DCF Model'!C19+2)+'DCF Model'!F45/(1+$B19)^('DCF Model'!C19+3)+'DCF Model'!G45/(1+$B19)^('DCF Model'!C19+4)+('DCF Model'!G39+'DCF Model'!G42)*I$17/(1+$B19)^('DCF Model'!C19+4)-'DCF Model'!C16)*1000000/'DCF Model'!C15,0),"") -> 4179
B20: =$C$3-0.005 -> 0.1142 | C20: =IFERROR(ROUND(('DCF Model'!C45/(1+$B20)^('DCF Model'!C19+0)+'DCF Model'!D45/(1+$B20)^('DCF Model'!C19+1)+'DCF Model'!E45/(1+$B20)^('DCF Model'!C19+2)+'DCF Model'!F45/(1+$B20)^('DCF Model'!C19+3)+'DCF Model'!G45/(1+$B20)^('DCF Model'!C19+4)+('DCF Model'!G39+'DCF Model'!G42)*C$17/(1+$B20)^('DCF Model'!C19+4)-'DCF Model'!C16)*1000000/'DCF Model'!C15,0),"") -> 2573 | D20: =IFERROR(ROUND(('DCF Model'!C45/(1+$B20)^('DCF Model'!C19+0)+'DCF Model'!D45/(1+$B20)^('DCF Model'!C19+1)+'DCF Model'!E45/(1+$B20)^('DCF Model'!C19+2)+'DCF Model'!F45/(1+$B20)^('DCF Model'!C19+3)+'DCF Model'!G45/(1+$B20)^('DCF Model'!C19+4)+('DCF Model'!G39+'DCF Model'!G42)*D$17/(1+$B20)^('DCF Model'!C19+4)-'DCF Model'!C16)*1000000/'DCF Model'!C15,0),"") -> 2830 | E20: =IFERROR(ROUND(('DCF Model'!C45/(1+$B20)^('DCF Model'!C19+0)+'DCF Model'!D45/(1+$B20)^('DCF Model'!C19+1)+'DCF Model'!E45/(1+$B20)^('DCF Model'!C19+2)+'DCF Model'!F45/(1+$B20)^('DCF Model'!C19+3)+'DCF Model'!G45/(1+$B20)^('DCF Model'!C19+4)+('DCF Model'!G39+'DCF Model'!G42)*E$17/(1+$B20)^('DCF Model'!C19+4)-'DCF Model'!C16)*1000000/'DCF Model'!C15,0),"") -> 3088 | F20: =IFERROR(ROUND(('DCF Model'!C45/(1+$B20)^('DCF Model'!C19+0)+'DCF Model'!D45/(1+$B20)^('DCF Model'!C19+1)+'DCF Model'!E45/(1+$B20)^('DCF Model'!C19+2)+'DCF Model'!F45/(1+$B20)^('DCF Model'!C19+3)+'DCF Model'!G45/(1+$B20)^('DCF Model'!C19+4)+('DCF Model'!G39+'DCF Model'!G42)*F$17/(1+$B20)^('DCF Model'!C19+4)-'DCF Model'!C16)*1000000/'DCF Model'!C15,0),"") -> 3345 | G20: =IFERROR(ROUND(('DCF Model'!C45/(1+$B20)^('DCF Model'!C19+0)+'DCF Model'!D45/(1+$B20)^('DCF Model'!C19+1)+'DCF Model'!E45/(1+$B20)^('DCF Model'!C19+2)+'DCF Model'!F45/(1+$B20)^('DCF Model'!C19+3)+'DCF Model'!G45/(1+$B20)^('DCF Model'!C19+4)+('DCF Model'!G39+'DCF Model'!G42)*G$17/(1+$B20)^('DCF Model'!C19+4)-'DCF Model'!C16)*1000000/'DCF Model'!C15,0),"") -> 3602 | H20: =IFERROR(ROUND(('DCF Model'!C45/(1+$B20)^('DCF Model'!C19+0)+'DCF Model'!D45/(1+$B20)^('DCF Model'!C19+1)+'DCF Model'!E45/(1+$B20)^('DCF Model'!C19+2)+'DCF Model'!F45/(1+$B20)^('DCF Model'!C19+3)+'DCF Model'!G45/(1+$B20)^('DCF Model'!C19+4)+('DCF Model'!G39+'DCF Model'!G42)*H$17/(1+$B20)^('DCF Model'!C19+4)-'DCF Model'!C16)*1000000/'DCF Model'!C15,0),"") -> 3859 | I20: =IFERROR(ROUND(('DCF Model'!C45/(1+$B20)^('DCF Model'!C19+0)+'DCF Model'!D45/(1+$B20)^('DCF Model'!C19+1)+'DCF Model'!E45/(1+$B20)^('DCF Model'!C19+2)+'DCF Model'!F45/(1+$B20)^('DCF Model'!C19+3)+'DCF Model'!G45/(1+$B20)^('DCF Model'!C19+4)+('DCF Model'!G39+'DCF Model'!G42)*I$17/(1+$B20)^('DCF Model'!C19+4)-'DCF Model'!C16)*1000000/'DCF Model'!C15,0),"") -> 4116
B21: =$C$3 -> 0.1192 | C21: =IFERROR(ROUND(('DCF Model'!C45/(1+$B21)^('DCF Model'!C19+0)+'DCF Model'!D45/(1+$B21)^('DCF Model'!C19+1)+'DCF Model'!E45/(1+$B21)^('DCF Model'!C19+2)+'DCF Model'!F45/(1+$B21)^('DCF Model'!C19+3)+'DCF Model'!G45/(1+$B21)^('DCF Model'!C19+4)+('DCF Model'!G39+'DCF Model'!G42)*C$17/(1+$B21)^('DCF Model'!C19+4)-'DCF Model'!C16)*1000000/'DCF Model'!C15,0),"") -> 2541 | D21: =IFERROR(ROUND(('DCF Model'!C45/(1+$B21)^('DCF Model'!C19+0)+'DCF Model'!D45/(1+$B21)^('DCF Model'!C19+1)+'DCF Model'!E45/(1+$B21)^('DCF Model'!C19+2)+'DCF Model'!F45/(1+$B21)^('DCF Model'!C19+3)+'DCF Model'!G45/(1+$B21)^('DCF Model'!C19+4)+('DCF Model'!G39+'DCF Model'!G42)*D$17/(1+$B21)^('DCF Model'!C19+4)-'DCF Model'!C16)*1000000/'DCF Model'!C15,0),"") -> 2793 | E21: =IFERROR(ROUND(('DCF Model'!C45/(1+$B21)^('DCF Model'!C19+0)+'DCF Model'!D45/(1+$B21)^('DCF Model'!C19+1)+'DCF Model'!E45/(1+$B21)^('DCF Model'!C19+2)+'DCF Model'!F45/(1+$B21)^('DCF Model'!C19+3)+'DCF Model'!G45/(1+$B21)^('DCF Model'!C19+4)+('DCF Model'!G39+'DCF Model'!G42)*E$17/(1+$B21)^('DCF Model'!C19+4)-'DCF Model'!C16)*1000000/'DCF Model'!C15,0),"") -> 3046 | F21: =IFERROR(ROUND(('DCF Model'!C45/(1+$B21)^('DCF Model'!C19+0)+'DCF Model'!D45/(1+$B21)^('DCF Model'!C19+1)+'DCF Model'!E45/(1+$B21)^('DCF Model'!C19+2)+'DCF Model'!F45/(1+$B21)^('DCF Model'!C19+3)+'DCF Model'!G45/(1+$B21)^('DCF Model'!C19+4)+('DCF Model'!G39+'DCF Model'!G42)*F$17/(1+$B21)^('DCF Model'!C19+4)-'DCF Model'!C16)*1000000/'DCF Model'!C15,0),"") -> 3298 | G21: =IFERROR(ROUND(('DCF Model'!C45/(1+$B21)^('DCF Model'!C19+0)+'DCF Model'!D45/(1+$B21)^('DCF Model'!C19+1)+'DCF Model'!E45/(1+$B21)^('DCF Model'!C19+2)+'DCF Model'!F45/(1+$B21)^('DCF Model'!C19+3)+'DCF Model'!G45/(1+$B21)^('DCF Model'!C19+4)+('DCF Model'!G39+'DCF Model'!G42)*G$17/(1+$B21)^('DCF Model'!C19+4)-'DCF Model'!C16)*1000000/'DCF Model'!C15,0),"") -> 3550 | H21: =IFERROR(ROUND(('DCF Model'!C45/(1+$B21)^('DCF Model'!C19+0)+'DCF Model'!D45/(1+$B21)^('DCF Model'!C19+1)+'DCF Model'!E45/(1+$B21)^('DCF Model'!C19+2)+'DCF Model'!F45/(1+$B21)^('DCF Model'!C19+3)+'DCF Model'!G45/(1+$B21)^('DCF Model'!C19+4)+('DCF Model'!G39+'DCF Model'!G42)*H$17/(1+$B21)^('DCF Model'!C19+4)-'DCF Model'!C16)*1000000/'DCF Model'!C15,0),"") -> 3803 | I21: =IFERROR(ROUND(('DCF Model'!C45/(1+$B21)^('DCF Model'!C19+0)+'DCF Model'!D45/(1+$B21)^('DCF Model'!C19+1)+'DCF Model'!E45/(1+$B21)^('DCF Model'!C19+2)+'DCF Model'!F45/(1+$B21)^('DCF Model'!C19+3)+'DCF Model'!G45/(1+$B21)^('DCF Model'!C19+4)+('DCF Model'!G39+'DCF Model'!G42)*I$17/(1+$B21)^('DCF Model'!C19+4)-'DCF Model'!C16)*1000000/'DCF Model'!C15,0),"") -> 4055
B22: =$C$3+0.005 -> 0.1242 | C22: =IFERROR(ROUND(('DCF Model'!C45/(1+$B22)^('DCF Model'!C19+0)+'DCF Model'!D45/(1+$B22)^('DCF Model'!C19+1)+'DCF Model'!E45/(1+$B22)^('DCF Model'!C19+2)+'DCF Model'!F45/(1+$B22)^('DCF Model'!C19+3)+'DCF Model'!G45/(1+$B22)^('DCF Model'!C19+4)+('DCF Model'!G39+'DCF Model'!G42)*C$17/(1+$B22)^('DCF Model'!C19+4)-'DCF Model'!C16)*1000000/'DCF Model'!C15,0),"") -> 2509 | D22: =IFERROR(ROUND(('DCF Model'!C45/(1+$B22)^('DCF Model'!C19+0)+'DCF Model'!D45/(1+$B22)^('DCF Model'!C19+1)+'DCF Model'!E45/(1+$B22)^('DCF Model'!C19+2)+'DCF Model'!F45/(1+$B22)^('DCF Model'!C19+3)+'DCF Model'!G45/(1+$B22)^('DCF Model'!C19+4)+('DCF Model'!G39+'DCF Model'!G42)*D$17/(1+$B22)^('DCF Model'!C19+4)-'DCF Model'!C16)*1000000/'DCF Model'!C15,0),"") -> 2757 | E22: =IFERROR(ROUND(('DCF Model'!C45/(1+$B22)^('DCF Model'!C19+0)+'DCF Model'!D45/(1+$B22)^('DCF Model'!C19+1)+'DCF Model'!E45/(1+$B22)^('DCF Model'!C19+2)+'DCF Model'!F45/(1+$B22)^('DCF Model'!C19+3)+'DCF Model'!G45/(1+$B22)^('DCF Model'!C19+4)+('DCF Model'!G39+'DCF Model'!G42)*E$17/(1+$B22)^('DCF Model'!C19+4)-'DCF Model'!C16)*1000000/'DCF Model'!C15,0),"") -> 3004 | F22: =IFERROR(ROUND(('DCF Model'!C45/(1+$B22)^('DCF Model'!C19+0)+'DCF Model'!D45/(1+$B22)^('DCF Model'!C19+1)+'DCF Model'!E45/(1+$B22)^('DCF Model'!C19+2)+'DCF Model'!F45/(1+$B22)^('DCF Model'!C19+3)+'DCF Model'!G45/(1+$B22)^('DCF Model'!C19+4)+('DCF Model'!G39+'DCF Model'!G42)*F$17/(1+$B22)^('DCF Model'!C19+4)-'DCF Model'!C16)*1000000/'DCF Model'!C15,0),"") -> 3252 | G22: =IFERROR(ROUND(('DCF Model'!C45/(1+$B22)^('DCF Model'!C19+0)+'DCF Model'!D45/(1+$B22)^('DCF Model'!C19+1)+'DCF Model'!E45/(1+$B22)^('DCF Model'!C19+2)+'DCF Model'!F45/(1+$B22)^('DCF Model'!C19+3)+'DCF Model'!G45/(1+$B22)^('DCF Model'!C19+4)+('DCF Model'!G39+'DCF Model'!G42)*G$17/(1+$B22)^('DCF Model'!C19+4)-'DCF Model'!C16)*1000000/'DCF Model'!C15,0),"") -> 3500 | H22: =IFERROR(ROUND(('DCF Model'!C45/(1+$B22)^('DCF Model'!C19+0)+'DCF Model'!D45/(1+$B22)^('DCF Model'!C19+1)+'DCF Model'!E45/(1+$B22)^('DCF Model'!C19+2)+'DCF Model'!F45/(1+$B22)^('DCF Model'!C19+3)+'DCF Model'!G45/(1+$B22)^('DCF Model'!C19+4)+('DCF Model'!G39+'DCF Model'!G42)*H$17/(1+$B22)^('DCF Model'!C19+4)-'DCF Model'!C16)*1000000/'DCF Model'!C15,0),"") -> 3747 | I22: =IFERROR(ROUND(('DCF Model'!C45/(1+$B22)^('DCF Model'!C19+0)+'DCF Model'!D45/(1+$B22)^('DCF Model'!C19+1)+'DCF Model'!E45/(1+$B22)^('DCF Model'!C19+2)+'DCF Model'!F45/(1+$B22)^('DCF Model'!C19+3)+'DCF Model'!G45/(1+$B22)^('DCF Model'!C19+4)+('DCF Model'!G39+'DCF Model'!G42)*I$17/(1+$B22)^('DCF Model'!C19+4)-'DCF Model'!C16)*1000000/'DCF Model'!C15,0),"") -> 3995
B23: =$C$3+0.01 -> 0.1292 | C23: =IFERROR(ROUND(('DCF Model'!C45/(1+$B23)^('DCF Model'!C19+0)+'DCF Model'!D45/(1+$B23)^('DCF Model'!C19+1)+'DCF Model'!E45/(1+$B23)^('DCF Model'!C19+2)+'DCF Model'!F45/(1+$B23)^('DCF Model'!C19+3)+'DCF Model'!G45/(1+$B23)^('DCF Model'!C19+4)+('DCF Model'!G39+'DCF Model'!G42)*C$17/(1+$B23)^('DCF Model'!C19+4)-'DCF Model'!C16)*1000000/'DCF Model'!C15,0),"") -> 2478 | D23: =IFERROR(ROUND(('DCF Model'!C45/(1+$B23)^('DCF Model'!C19+0)+'DCF Model'!D45/(1+$B23)^('DCF Model'!C19+1)+'DCF Model'!E45/(1+$B23)^('DCF Model'!C19+2)+'DCF Model'!F45/(1+$B23)^('DCF Model'!C19+3)+'DCF Model'!G45/(1+$B23)^('DCF Model'!C19+4)+('DCF Model'!G39+'DCF Model'!G42)*D$17/(1+$B23)^('DCF Model'!C19+4)-'DCF Model'!C16)*1000000/'DCF Model'!C15,0),"") -> 2721 | E23: =IFERROR(ROUND(('DCF Model'!C45/(1+$B23)^('DCF Model'!C19+0)+'DCF Model'!D45/(1+$B23)^('DCF Model'!C19+1)+'DCF Model'!E45/(1+$B23)^('DCF Model'!C19+2)+'DCF Model'!F45/(1+$B23)^('DCF Model'!C19+3)+'DCF Model'!G45/(1+$B23)^('DCF Model'!C19+4)+('DCF Model'!G39+'DCF Model'!G42)*E$17/(1+$B23)^('DCF Model'!C19+4)-'DCF Model'!C16)*1000000/'DCF Model'!C15,0),"") -> 2964 | F23: =IFERROR(ROUND(('DCF Model'!C45/(1+$B23)^('DCF Model'!C19+0)+'DCF Model'!D45/(1+$B23)^('DCF Model'!C19+1)+'DCF Model'!E45/(1+$B23)^('DCF Model'!C19+2)+'DCF Model'!F45/(1+$B23)^('DCF Model'!C19+3)+'DCF Model'!G45/(1+$B23)^('DCF Model'!C19+4)+('DCF Model'!G39+'DCF Model'!G42)*F$17/(1+$B23)^('DCF Model'!C19+4)-'DCF Model'!C16)*1000000/'DCF Model'!C15,0),"") -> 3207 | G23: =IFERROR(ROUND(('DCF Model'!C45/(1+$B23)^('DCF Model'!C19+0)+'DCF Model'!D45/(1+$B23)^('DCF Model'!C19+1)+'DCF Model'!E45/(1+$B23)^('DCF Model'!C19+2)+'DCF Model'!F45/(1+$B23)^('DCF Model'!C19+3)+'DCF Model'!G45/(1+$B23)^('DCF Model'!C19+4)+('DCF Model'!G39+'DCF Model'!G42)*G$17/(1+$B23)^('DCF Model'!C19+4)-'DCF Model'!C16)*1000000/'DCF Model'!C15,0),"") -> 3450 | H23: =IFERROR(ROUND(('DCF Model'!C45/(1+$B23)^('DCF Model'!C19+0)+'DCF Model'!D45/(1+$B23)^('DCF Model'!C19+1)+'DCF Model'!E45/(1+$B23)^('DCF Model'!C19+2)+'DCF Model'!F45/(1+$B23)^('DCF Model'!C19+3)+'DCF Model'!G45/(1+$B23)^('DCF Model'!C19+4)+('DCF Model'!G39+'DCF Model'!G42)*H$17/(1+$B23)^('DCF Model'!C19+4)-'DCF Model'!C16)*1000000/'DCF Model'!C15,0),"") -> 3693 | I23: =IFERROR(ROUND(('DCF Model'!C45/(1+$B23)^('DCF Model'!C19+0)+'DCF Model'!D45/(1+$B23)^('DCF Model'!C19+1)+'DCF Model'!E45/(1+$B23)^('DCF Model'!C19+2)+'DCF Model'!F45/(1+$B23)^('DCF Model'!C19+3)+'DCF Model'!G45/(1+$B23)^('DCF Model'!C19+4)+('DCF Model'!G39+'DCF Model'!G42)*I$17/(1+$B23)^('DCF Model'!C19+4)-'DCF Model'!C16)*1000000/'DCF Model'!C15,0),"") -> 3936
B24: =$C$3+0.015 -> 0.1342 | C24: =IFERROR(ROUND(('DCF Model'!C45/(1+$B24)^('DCF Model'!C19+0)+'DCF Model'!D45/(1+$B24)^('DCF Model'!C19+1)+'DCF Model'!E45/(1+$B24)^('DCF Model'!C19+2)+'DCF Model'!F45/(1+$B24)^('DCF Model'!C19+3)+'DCF Model'!G45/(1+$B24)^('DCF Model'!C19+4)+('DCF Model'!G39+'DCF Model'!G42)*C$17/(1+$B24)^('DCF Model'!C19+4)-'DCF Model'!C16)*1000000/'DCF Model'!C15,0),"") -> 2448 | D24: =IFERROR(ROUND(('DCF Model'!C45/(1+$B24)^('DCF Model'!C19+0)+'DCF Model'!D45/(1+$B24)^('DCF Model'!C19+1)+'DCF Model'!E45/(1+$B24)^('DCF Model'!C19+2)+'DCF Model'!F45/(1+$B24)^('DCF Model'!C19+3)+'DCF Model'!G45/(1+$B24)^('DCF Model'!C19+4)+('DCF Model'!G39+'DCF Model'!G42)*D$17/(1+$B24)^('DCF Model'!C19+4)-'DCF Model'!C16)*1000000/'DCF Model'!C15,0),"") -> 2687 | E24: =IFERROR(ROUND(('DCF Model'!C45/(1+$B24)^('DCF Model'!C19+0)+'DCF Model'!D45/(1+$B24)^('DCF Model'!C19+1)+'DCF Model'!E45/(1+$B24)^('DCF Model'!C19+2)+'DCF Model'!F45/(1+$B24)^('DCF Model'!C19+3)+'DCF Model'!G45/(1+$B24)^('DCF Model'!C19+4)+('DCF Model'!G39+'DCF Model'!G42)*E$17/(1+$B24)^('DCF Model'!C19+4)-'DCF Model'!C16)*1000000/'DCF Model'!C15,0),"") -> 2925 | F24: =IFERROR(ROUND(('DCF Model'!C45/(1+$B24)^('DCF Model'!C19+0)+'DCF Model'!D45/(1+$B24)^('DCF Model'!C19+1)+'DCF Model'!E45/(1+$B24)^('DCF Model'!C19+2)+'DCF Model'!F45/(1+$B24)^('DCF Model'!C19+3)+'DCF Model'!G45/(1+$B24)^('DCF Model'!C19+4)+('DCF Model'!G39+'DCF Model'!G42)*F$17/(1+$B24)^('DCF Model'!C19+4)-'DCF Model'!C16)*1000000/'DCF Model'!C15,0),"") -> 3164 | G24: =IFERROR(ROUND(('DCF Model'!C45/(1+$B24)^('DCF Model'!C19+0)+'DCF Model'!D45/(1+$B24)^('DCF Model'!C19+1)+'DCF Model'!E45/(1+$B24)^('DCF Model'!C19+2)+'DCF Model'!F45/(1+$B24)^('DCF Model'!C19+3)+'DCF Model'!G45/(1+$B24)^('DCF Model'!C19+4)+('DCF Model'!G39+'DCF Model'!G42)*G$17/(1+$B24)^('DCF Model'!C19+4)-'DCF Model'!C16)*1000000/'DCF Model'!C15,0),"") -> 3402 | H24: =IFERROR(ROUND(('DCF Model'!C45/(1+$B24)^('DCF Model'!C19+0)+'DCF Model'!D45/(1+$B24)^('DCF Model'!C19+1)+'DCF Model'!E45/(1+$B24)^('DCF Model'!C19+2)+'DCF Model'!F45/(1+$B24)^('DCF Model'!C19+3)+'DCF Model'!G45/(1+$B24)^('DCF Model'!C19+4)+('DCF Model'!G39+'DCF Model'!G42)*H$17/(1+$B24)^('DCF Model'!C19+4)-'DCF Model'!C16)*1000000/'DCF Model'!C15,0),"") -> 3641 | I24: =IFERROR(ROUND(('DCF Model'!C45/(1+$B24)^('DCF Model'!C19+0)+'DCF Model'!D45/(1+$B24)^('DCF Model'!C19+1)+'DCF Model'!E45/(1+$B24)^('DCF Model'!C19+2)+'DCF Model'!F45/(1+$B24)^('DCF Model'!C19+3)+'DCF Model'!G45/(1+$B24)^('DCF Model'!C19+4)+('DCF Model'!G39+'DCF Model'!G42)*I$17/(1+$B24)^('DCF Model'!C19+4)-'DCF Model'!C16)*1000000/'DCF Model'!C15,0),"") -> 3879
B26: All values dynamically linked to DCF Model. Headers auto-center on current WACC / Terminal g / Exit Multiple.

Sheet Segment Analysis
B2: Segment Analysis - 株式会社コア
C4: FY2024 | D4: FY2025 | E4: FY2026 | F4: FY2026(E) | G4: FY2027(E) | H4: FY2028(E) | I4: FY2029(E) | J4: FY2030(E)
B5: Future Society Solutions (未来社会ソリューション)
B6: Revenue | C6: — | D6: 4771 | E6: 5084 | F6: =E6*(1+CHOOSE('DCF Model'!$D$27,F34,F35,F36,F37,F38)) -> 5846.6 | G6: =F6*(1+CHOOSE('DCF Model'!$D$27,G34,G35,G36,G37,G38)) -> 6723.59 | H6: =G6*(1+CHOOSE('DCF Model'!$D$27,H34,H35,H36,H37,H38)) -> 7530.4208 | I6: =H6*(1+CHOOSE('DCF Model'!$D$27,I34,I35,I36,I37,I38)) -> 8132.8545 | J6: =I6*(1+CHOOSE('DCF Model'!$D$27,J34,J35,J36,J37,J38)) -> 8539.4972
B7: Operating Profit | C7: — | D7: 675 | E7: 741 | F7: =F6*CHOOSE('DCF Model'!$D$27,F41,F42,F43,F44,F45) -> 876.99 | G7: =G6*CHOOSE('DCF Model'!$D$27,G41,G42,G43,G44,G45) -> 1042.1564 | H7: =H6*CHOOSE('DCF Model'!$D$27,H41,H42,H43,H44,H45) -> 1204.8673 | I7: =I6*CHOOSE('DCF Model'!$D$27,I41,I42,I43,I44,I45) -> 1341.921 | J7: =J6*CHOOSE('DCF Model'!$D$27,J41,J42,J43,J44,J45) -> 1451.7145
B8: OP Margin | C8: — | D8: =D7/D6 -> 0.14147977 | E8: =E7/E6 -> 0.14575138 | F8: =CHOOSE('DCF Model'!$D$27,F41,F42,F43,F44,F45) -> 0.15 | G8: =CHOOSE('DCF Model'!$D$27,G41,G42,G43,G44,G45) -> 0.155 | H8: =CHOOSE('DCF Model'!$D$27,H41,H42,H43,H44,H45) -> 0.16 | I8: =CHOOSE('DCF Model'!$D$27,I41,I42,I43,I44,I45) -> 0.165 | J8: =CHOOSE('DCF Model'!$D$27,J41,J42,J43,J44,J45) -> 0.17
B10: Industrial Technology Solutions (産業技術ソリューション)
B11: Revenue | C11: — | D11: 10546 | E11: 13695 | F11: =E11*(1+CHOOSE('DCF Model'!$D$27,F48,F49,F50,F51,F52)) -> 15201.45 | G11: =F11*(1+CHOOSE('DCF Model'!$D$27,G48,G49,G50,G51,G52)) -> 16721.595 | H11: =G11*(1+CHOOSE('DCF Model'!$D$27,H48,H49,H50,H51,H52)) -> 18059.323 | I11: =H11*(1+CHOOSE('DCF Model'!$D$27,I48,I49,I50,I51,I52)) -> 19142.882 | J11: =I11*(1+CHOOSE('DCF Model'!$D$27,J48,J49,J50,J51,J52)) -> 20100.026
B12: Operating Profit | C12: — | D12: 1641 | E12: 2312 | F12: =F11*CHOOSE('DCF Model'!$D$27,F55,F56,F57,F58,F59) -> 2660.2537 | G12: =G11*CHOOSE('DCF Model'!$D$27,G55,G56,G57,G58,G59) -> 2976.4439 | H12: =H11*CHOOSE('DCF Model'!$D$27,H55,H56,H57,H58,H59) -> 3250.6781 | I12: =I11*CHOOSE('DCF Model'!$D$27,I55,I56,I57,I58,I59) -> 3484.0045 | J12: =J11*CHOOSE('DCF Model'!$D$27,J55,J56,J57,J58,J59) -> 3718.5048
B13: OP Margin | C13: — | D13: =D12/D11 -> 0.15560402 | E13: =E12/E11 -> 0.16882074 | F13: =CHOOSE('DCF Model'!$D$27,F55,F56,F57,F58,F59) -> 0.175 | G13: =CHOOSE('DCF Model'!$D$27,G55,G56,G57,G58,G59) -> 0.178 | H13: =CHOOSE('DCF Model'!$D$27,H55,H56,H57,H58,H59) -> 0.18 | I13: =CHOOSE('DCF Model'!$D$27,I55,I56,I57,I58,I59) -> 0.182 | J13: =CHOOSE('DCF Model'!$D$27,J55,J56,J57,J58,J59) -> 0.185
B15: Customer Business Integration (顧客業務インテグレーション)
B16: Revenue | C16: — | D16: 8680 | E16: 7751 | F16: =E16*(1+CHOOSE('DCF Model'!$D$27,F62,F63,F64,F65,F66)) -> 7828.51 | G16: =F16*(1+CHOOSE('DCF Model'!$D$27,G62,G63,G64,G65,G66)) -> 7906.7951 | H16: =G16*(1+CHOOSE('DCF Model'!$D$27,H62,H63,H64,H65,H66)) -> 7985.8631 | I16: =H16*(1+CHOOSE('DCF Model'!$D$27,I62,I63,I64,I65,I66)) -> 8065.7217 | J16: =I16*(1+CHOOSE('DCF Model'!$D$27,J62,J63,J64,J65,J66)) -> 8146.3789
B17: Operating Profit | C17: — | D17: 823 | E17: 765 | F17: =F16*CHOOSE('DCF Model'!$D$27,F69,F70,F71,F72,F73) -> 821.99355 | G17: =G16*CHOOSE('DCF Model'!$D$27,G69,G70,G71,G72,G73) -> 869.74746 | H17: =H16*CHOOSE('DCF Model'!$D$27,H69,H70,H71,H72,H73) -> 918.37425 | I17: =I16*CHOOSE('DCF Model'!$D$27,I69,I70,I71,I72,I73) -> 967.8866 | J17: =J16*CHOOSE('DCF Model'!$D$27,J69,J70,J71,J72,J73) -> 977.56547
B18: OP Margin | C18: — | D18: =D17/D16 -> 0.094815668 | E18: =E17/E16 -> 0.098696942 | F18: =CHOOSE('DCF Model'!$D$27,F69,F70,F71,F72,F73) -> 0.105 | G18: =CHOOSE('DCF Model'!$D$27,G69,G70,G71,G72,G73) -> 0.11 | H18: =CHOOSE('DCF Model'!$D$27,H69,H70,H71,H72,H73) -> 0.115 | I18: =CHOOSE('DCF Model'!$D$27,I69,I70,I71,I72,I73) -> 0.12 | J18: =CHOOSE('DCF Model'!$D$27,J69,J70,J71,J72,J73) -> 0.12
B20: Consolidated Total
B21: Total Revenue | C21: =C6+C11+C16 -> #VALUE! | D21: =D6+D11+D16 -> 23997 | E21: =E6+E11+E16 -> 26530 | F21: =F6+F11+F16 -> 28876.56 | G21: =G6+G11+G16 -> 31351.98 | H21: =H6+H11+H16 -> 33575.606 | I21: =I6+I11+I16 -> 35341.458 | J21: =J6+J11+J16 -> 36785.902
B22: Total Operating Profit | C22: =C7+C12+C17 -> #VALUE! | D22: =D7+D12+D17 -> 3139 | E22: =E7+E12+E17 -> 3818 | F22: =F7+F12+F17 -> 4359.2373 | G22: =G7+G12+G17 -> 4888.3478 | H22: =H7+H12+H17 -> 5373.9196 | I22: =I7+I12+I17 -> 5793.8121 | J22: =J7+J12+J17 -> 6147.7848
B23: Total OP Margin | C23: =IFERROR(C22/C21,"—") -> — | D23: =IFERROR(D22/D21,"—") -> 0.13080802 | E23: =IFERROR(E22/E21,"—") -> 0.14391255 | F23: =IFERROR(F22/F21,"—") -> 0.1509611 | G23: =IFERROR(G22/G21,"—") -> 0.15591831 | H23: =IFERROR(H22/H21,"—") -> 0.16005428 | I23: =IFERROR(I22/I21,"—") -> 0.16393812 | J23: =IFERROR(J22/J21,"—") -> 0.16712339
B25: Reconciliation vs DCF Model
B26: DCF Model Revenue | F26: ='DCF Model'!C33 -> 28876.56 | G26: ='DCF Model'!D33 -> 31351.98 | H26: ='DCF Model'!E33 -> 33575.606 | I26: ='DCF Model'!F33 -> 35341.458 | J26: ='DCF Model'!G33 -> 36785.902
B27: Segment Total Revenue | F27: =F21 -> 28876.56 | G27: =G21 -> 31351.98 | H27: =H21 -> 33575.606 | I27: =I21 -> 35341.458 | J27: =J21 -> 36785.902
B28: Difference | F28: =F27-F26 -> 0 | G28: =G27-G26 -> 0 | H28: =H27-H26 -> 0 | I28: =I27-I26 -> 0 | J28: =J27-J26 -> 0
B31: Segment Scenario Input Matrix
F32: FY2026(E) | G32: FY2027(E) | H32: FY2028(E) | I32: FY2029(E) | J32: FY2030(E)
B33: Future Society Solutions - Revenue Growth (YoY)
B34: Base | F34: 0.15 | G34: 0.15 | H34: 0.12 | I34: 0.08 | J34: 0.05
B35: Upside | F35: 0.25 | G35: 0.22 | H35: 0.18 | I35: 0.12 | J35: 0.08
B36: Management | F36: 0.12 | G36: 0.12 | H36: 0.1 | I36: 0.07 | J36: 0.05
B37: Downside 1 | F37: 0.08 | G37: 0.07 | H37: 0.05 | I37: 0.03 | J37: 0.02
B38: Downside 2 | F38: 0.03 | G38: 0.03 | H38: 0.02 | I38: 0.01 | J38: 0.01
B40: Future Society Solutions - OP Margin
B41: Base | F41: 0.15 | G41: 0.155 | H41: 0.16 | I41: 0.165 | J41: 0.17
B42: Upside | F42: 0.155 | G42: 0.165 | H42: 0.175 | I42: 0.18 | J42: 0.185
B43: Management | F43: 0.148 | G43: 0.15 | H43: 0.152 | I43: 0.155 | J43: 0.158
B44: Downside 1 | F44: 0.14 | G44: 0.14 | H44: 0.142 | I44: 0.145 | J44: 0.145
B45: Downside 2 | F45: 0.13 | G45: 0.125 | H45: 0.125 | I45: 0.125 | J45: 0.125
B47: Industrial Technology Solutions - Revenue Growth (YoY)
B48: Base | F48: 0.11 | G48: 0.1 | H48: 0.08 | I48: 0.06 | J48: 0.05
B49: Upside | F49: 0.12 | G49: 0.11 | H49: 0.1 | I49: 0.08 | J49: 0.06
B50: Management | F50: 0.1 | G50: 0.09 | H50: 0.08 | I50: 0.06 | J50: 0.05
B51: Downside 1 | F51: 0.08 | G51: 0.06 | H51: 0.05 | I51: 0.04 | J51: 0.03
B52: Downside 2 | F52: 0.05 | G52: 0.03 | H52: 0.02 | I52: 0.02 | J52: 0.02
B54: Industrial Technology Solutions - OP Margin
B55: Base | F55: 0.175 | G55: 0.178 | H55: 0.18 | I55: 0.182 | J55: 0.185
B56: Upside | F56: 0.18 | G56: 0.185 | H56: 0.19 | I56: 0.195 | J56: 0.198
B57: Management | F57: 0.17 | G57: 0.17 | H57: 0.172 | I57: 0.175 | J57: 0.178
B58: Downside 1 | F58: 0.16 | G58: 0.158 | H58: 0.158 | I58: 0.16 | J58: 0.16
B59: Downside 2 | F59: 0.15 | G59: 0.145 | H59: 0.145 | I59: 0.145 | J59: 0.145
B61: Customer Business Integration - Revenue Growth (YoY)
B62: Base | F62: 0.01 | G62: 0.01 | H62: 0.01 | I62: 0.01 | J62: 0.01
B63: Upside | F63: 0.02 | G63: 0.02 | H63: 0.015 | I63: 0.01 | J63: 0.01
B64: Management | F64: 0 | G64: 0.005 | H64: 0 | I64: 0 | J64: 0
B65: Downside 1 | F65: -0.02 | G65: -0.01 | H65: -0.005 | I65: -0.005 | J65: -0.005
B66: Downside 2 | F66: -0.05 | G66: -0.03 | H66: -0.02 | I66: -0.01 | J66: -0.01
B68: Customer Business Integration - OP Margin
B69: Base | F69: 0.105 | G69: 0.11 | H69: 0.115 | I69: 0.12 | J69: 0.12
B70: Upside | F70: 0.11 | G70: 0.12 | H70: 0.13 | I70: 0.135 | J70: 0.14
B71: Management | F71: 0.1 | G71: 0.105 | H71: 0.11 | I71: 0.115 | J71: 0.115
B72: Downside 1 | F72: 0.095 | G72: 0.09 | H72: 0.09 | I72: 0.09 | J72: 0.09
B73: Downside 2 | F73: 0.085 | G73: 0.08 | H73: 0.075 | I73: 0.075 | J73: 0.075
B76: Consolidated Inputs (連結レベル)
F77: FY2026(E) | G77: FY2027(E) | H77: FY2028(E) | I77: FY2029(E) | J77: FY2030(E)
B78: COGS % of Revenue
B79: Base | F79: 0.7245 | G79: 0.7245 | H79: 0.7245 | I79: 0.7245 | J79: 0.7245
B80: Upside | F80: 0.6883 | G80: 0.6883 | H80: 0.6883 | I80: 0.6883 | J80: 0.6883
B81: Management | F81: 0.7245 | G81: 0.7245 | H81: 0.7245 | I81: 0.7245 | J81: 0.7245
B82: Downside 1 | F82: 0.7607 | G82: 0.7607 | H82: 0.7607 | I82: 0.7607 | J82: 0.7607
B83: Downside 2 | F83: 0.797 | G83: 0.797 | H83: 0.797 | I83: 0.797 | J83: 0.797
B85: SGA % of Revenue
B86: Base | F86: 0.133 | G86: 0.13 | H86: 0.128 | I86: 0.126 | J86: 0.125
B87: Upside | F87: 0.13 | G87: 0.125 | H87: 0.122 | I87: 0.12 | J87: 0.118
B88: Management | F88: 0.146 | G88: 0.143 | H88: 0.14 | I88: 0.138 | J88: 0.135
B89: Downside 1 | F89: 0.14 | G89: 0.142 | H89: 0.145 | I89: 0.145 | J89: 0.145
B90: Downside 2 | F90: 0.148 | G90: 0.15 | H90: 0.155 | I90: 0.155 | J90: 0.15

Sheet Driver Analysis
B2: Driver Analysis - 株式会社コア
C4: FY2024 | D4: FY2025 | E4: FY2026 | F4: FY2026(E) | G4: FY2027(E) | H4: FY2028(E) | I4: FY2029(E) | J4: FY2030(E)
B5: Future Society Solutions (未来社会ソリューション) [manual]
B6: Revenue (Direct Input) | C6: — | D6: 4771 | E6: 4570 | F6: 5050 | G6: 5700 | H6: 6200 | I6: 6700 | J6: 7000
B7: YoY Growth | C7: — | D7: =IFERROR((D6-C6)/C6,"—") -> — | E7: =IFERROR((E6-D6)/D6,"—") -> -0.042129533 | F7: =IFERROR((F6-E6)/E6,"—") -> 0.10503282 | G7: =IFERROR((G6-F6)/F6,"—") -> 0.12871287 | H7: =IFERROR((H6-G6)/G6,"—") -> 0.087719298 | I7: =IFERROR((I6-H6)/H6,"—") -> 0.080645161 | J7: =IFERROR((J6-I6)/I6,"—") -> 0.044776119
B9: Industrial Technology Solutions (産業技術ソリューション) [manmonth]
B10: Headcount | C10: — | D10: — | E10: — | F10: 820 | G10: 850 | H10: 880 | I10: 910 | J10: 940
B11: × Utilization | C11: — | D11: — | E11: — | F11: 0.92 | G11: 0.93 | H11: 0.93 | I11: 0.94 | J11: 0.94
B12: × Unit Price (JPY mn/month) | C12: — | D12: — | E12: — | F12: 0.7 | G12: 0.72 | H12: 0.74 | I12: 0.76 | J12: 0.78
B13: Layer 1 Revenue | C13: — | D13: — | E13: — | F13: =F10*F11*F12*12 -> 6336.96 | G13: =G10*G11*G12*12 -> 6829.92 | H13: =H10*H11*H12*12 -> 7267.392 | I13: =I10*I11*I12*12 -> 7801.248 | J13: =J10*J11*J12*12 -> 8270.496
B14: + Layer 2 (Solution) Revenue | C14: — | D14: — | E14: 6058 | F14: 7400 | G14: 9238 | H14: 11000 | I14: 13000 | J14: 14500
B15: Segment Revenue | C15: — | D15: 10546 | E15: 12035 | F15: =F13+F14 -> 13736.96 | G15: =G13+G14 -> 16067.92 | H15: =H13+H14 -> 18267.392 | I15: =I13+I14 -> 20801.248 | J15: =J13+J14 -> 22770.496
B16: Layer 2 Mix % | C16: =IFERROR(C14/C15,"—") -> — | D16: =IFERROR(D14/D15,"—") -> — | E16: =IFERROR(E14/E15,"—") -> 0.50336518 | F16: =IFERROR(F14/F15,"—") -> 0.53869269 | G16: =IFERROR(G14/G15,"—") -> 0.5749344 | H16: =IFERROR(H14/H15,"—") -> 0.60216587 | I16: =IFERROR(I14/I15,"—") -> 0.6249625 | J16: =IFERROR(J14/J15,"—") -> 0.63678894
B18: Customer Business Integration (顧客業務インテグレーション) [manual]
B19: Revenue (Direct Input) | C19: — | D19: 8680 | E19: 7993 | F19: 8000 | G19: 8100 | H19: 8200 | I19: 8300 | J19: 8400
B20: YoY Growth | C20: — | D20: =IFERROR((D19-C19)/C19,"—") -> — | E20: =IFERROR((E19-D19)/D19,"—") -> -0.079147465 | F20: =IFERROR((F19-E19)/E19,"—") -> 0.0008757663 | G20: =IFERROR((G19-F19)/F19,"—") -> 0.0125 | H20: =IFERROR((H19-G19)/G19,"—") -> 0.012345679 | I20: =IFERROR((I19-H19)/H19,"—") -> 0.012195122 | J20: =IFERROR((J19-I19)/I19,"—") -> 0.012048193

Sheet Implied Growth Analysis
B2: IMPLIED GROWTH ANALYSIS - 株式会社コア (2359)
B3: 市場が織り込んでいる成長率を逆算し、自分の予想とのギャップを定量化
B5: 【BLOCK 1】Market Inputs
B6: 価格ポイント | C6: 株価 (JPY) | D6: Equity Value (JPY mn) | E6: Enterprise Value (JPY mn) | F6: Required PV(FCF+TV) (JPY mn) | G6: 想定タイミング
B7: Pre-Earnings Peak (3月高値) | C7: 2330 | D7: =C7*'DCF Model'!$C$15/1000000 -> 33478.607 | E7: =D7+'DCF Model'!$C$16 -> 26181.807 | F7: =E7 -> 26181.807 | G7: 決算前ピーク - 期待最大
B8: Current Price (現在) | C8: 1990 | D8: =C8*'DCF Model'!$C$15/1000000 -> 28593.317 | E8: =D8+'DCF Model'!$C$16 -> 21296.517 | F8: =E8 -> 21296.517 | G8: 決算後 - 失望売り後
B9: Post-Earnings Trough | C9: 1964 | D9: =C9*'DCF Model'!$C$15/1000000 -> 28219.736 | E9: =D9+'DCF Model'!$C$16 -> 20922.936 | F9: =E9 -> 20922.936 | G9: 1月安値 - サポートライン
B10: Entry Price (取得価格) | C10: 2127 | D10: =C10*'DCF Model'!$C$15/1000000 -> 30561.802 | E10: =D10+'DCF Model'!$C$16 -> 23265.002 | F10: =E10 -> 23265.002 | G10: あなたの取得価格
B11: DCF Base Target | C11: 2893 | D11: =C11*'DCF Model'!$C$15/1000000 -> 41568.073 | E11: =D11+'DCF Model'!$C$16 -> 34271.273 | F11: =E11 -> 34271.273 | G11: モデルBase評価額
B14: 【BLOCK 2】Reverse DCF - 成長プロファイル乗数α探索
B15: 理論: Baseシナリオの成長カーブ × α でスケール。α=1.0でBase完全一致、α=0.0でゼロ成長想定
B17: α (Growth Multiplier) | C17: -0.5 | D17: -0.3 | E17: -0.1 | F17: 0 | G17: 0.1 | H17: 0.2 | I17: 0.3 | J17: 0.4 | K17: 0.5 | L17: 0.6 | M17: 0.7 | N17: 0.8 | O17: 0.9 | P17: 1 | Q17: 1.1 | R17: 1.2 | S17: 1.3 | T17: 1.5
B19: 計算項目 \ α
B20: FY2027E Revenue Growth (α-scaled) | C20: =$D$57*C$17 -> -0.044224651 | D20: =$D$57*D$17 -> -0.026534791 | E20: =$D$57*E$17 -> -0.0088449303 | F20: =$D$57*F$17 -> 0 | G20: =$D$57*G$17 -> 0.0088449303 | H20: =$D$57*H$17 -> 0.017689861 | I20: =$D$57*I$17 -> 0.026534791 | J20: =$D$57*J$17 -> 0.035379721 | ... T20: =$D$57*T$17 -> 0.13267395
B21: FY2028E Revenue Growth (α-scaled) | C21: =$E$57*C$17 -> -0.042862102 | D21: =$E$57*D$17 -> -0.025717261 | E21: =$E$57*E$17 -> -0.0085724203 | F21: =$E$57*F$17 -> 0 | G21: =$E$57*G$17 -> 0.0085724203 | H21: =$E$57*H$17 -> 0.017144841 | I21: =$E$57*I$17 -> 0.025717261 | J21: =$E$57*J$17 -> 0.034289681 | ... T21: =$E$57*T$17 -> 0.1285863
B22: FY2029E Revenue Growth (α-scaled) | C22: =$F$57*C$17 -> -0.035462295 | D22: =$F$57*D$17 -> -0.021277377 | E22: =$F$57*E$17 -> -0.0070924591 | F22: =$F$57*F$17 -> 0 | G22: =$F$57*G$17 -> 0.0070924591 | H22: =$F$57*H$17 -> 0.014184918 | I22: =$F$57*I$17 -> 0.021277377 | J22: =$F$57*J$17 -> 0.028369836 | ... T22: =$F$57*T$17 -> 0.10638689
B23: FY2030E Revenue Growth (α-scaled) | C23: =$G$57*C$17 -> -0.026296646 | D23: =$G$57*D$17 -> -0.015777987 | E23: =$G$57*E$17 -> -0.0052593291 | F23: =$G$57*F$17 -> 0 | G23: =$G$57*G$17 -> 0.0052593291 | H23: =$G$57*H$17 -> 0.010518658 | I23: =$G$57*I$17 -> 0.015777987 | J23: =$G$57*J$17 -> 0.021037317 | ... T23: =$G$57*T$17 -> 0.078889937
B24: FY2031E Revenue Growth (α-scaled) | C24: =$H$57*C$17 -> -0.020435547 | D24: =$H$57*D$17 -> -0.012261328 | E24: =$H$57*E$17 -> -0.0040871093 | F24: =$H$57*F$17 -> 0 | G24: =$H$57*G$17 -> 0.0040871093 | H24: =$H$57*H$17 -> 0.0081742187 | I24: =$H$57*I$17 -> 0.012261328 | J24: =$H$57*J$17 -> 0.016348437 | ... T24: =$H$57*T$17 -> 0.06130664
B25: FY2027E Revenue | C25: =$C$48*(1+C20) -> 25356.72 | D25: =$C$48*(1+D20) -> 25826.032 | E25: =$C$48*(1+E20) -> 26295.344 | F25: =$C$48*(1+F20) -> 26530 | G25: =$C$48*(1+G20) -> 26764.656 | H25: =$C$48*(1+H20) -> 26999.312 | I25: =$C$48*(1+I20) -> 27233.968 | J25: =$C$48*(1+J20) -> 27468.624 | ... T25: =$C$48*(1+T20) -> 30049.84
B26: FY2028E Revenue | C26: =C25*(1+C21) -> 24269.878 | D26: =D25*(1+D21) -> 25161.857 | E26: =E25*(1+E21) -> 26069.929 | F26: =F25*(1+F21) -> 26530 | G26: =G25*(1+G21) -> 26994.094 | H26: =H25*(1+H21) -> 27462.211 | I26: =I25*(1+I21) -> 27934.351 | J26: =J25*(1+J21) -> 28410.514 | ... T26: =T25*(1+T21) -> 33913.838
B27: FY2029E Revenue | C27: =C26*(1+C22) -> 23409.212 | D27: =D26*(1+D22) -> 24626.479 | E27: =E26*(1+E22) -> 25885.029 | F27: =F26*(1+F22) -> 26530 | G27: =G26*(1+G22) -> 27185.548 | H27: =H26*(1+H22) -> 27851.76 | I27: =I26*(1+I22) -> 28528.721 | J27: =J26*(1+J22) -> 29216.516 | ... T27: =T26*(1+T22) -> 37521.825
B28: FY2030E Revenue | C28: =C27*(1+C23) -> 22793.628 | D28: =D27*(1+D23) -> 24237.923 | E28: =E27*(1+E23) -> 25748.891 | F28: =F27*(1+F23) -> 26530 | G28: =G27*(1+G23) -> 27328.526 | H28: =H27*(1+H23) -> 28144.723 | I28: =I27*(1+I23) -> 28978.847 | J28: =J27*(1+J23) -> 29831.153 | ... T28: =T27*(1+T23) -> 40481.92
B29: FY2031E Revenue | C29: =C28*(1+C24) -> 22327.828 | D29: =D28*(1+D24) -> 23940.733 | E29: =E28*(1+E24) -> 25643.653 | F29: =F28*(1+F24) -> 26530 | G29: =G28*(1+G24) -> 27440.221 | H29: =H28*(1+H24) -> 28374.784 | I29: =I28*(1+I24) -> 29334.166 | J29: =J28*(1+J24) -> 30318.846 | ... T29: =T28*(1+T24) -> 42963.73
B30: FY2027E EBIT (Base OPM) | C30: =C25*($C$60+($D$58-$C$60)*C$17) -> 3559.7862 | D30: =D25*($C$60+($D$58-$C$60)*D$17) -> 3662.0793 | E30: =E25*($C$60+($D$58-$C$60)*E$17) -> 3765.6957 | F30: =F25*($C$60+($D$58-$C$60)*F$17) -> 3818 | G30: =G25*($C$60+($D$58-$C$60)*G$17) -> 3870.6351 | H30: =H25*($C$60+($D$58-$C$60)*H$17) -> 3923.6011 | I30: =I25*($C$60+($D$58-$C$60)*I$17) -> 3976.8978 | J30: =J25*($C$60+($D$58-$C$60)*J$17) -> 4030.5254 | ... T30: =T25*($C$60+($D$58-$C$60)*T$17) -> 4642.2608
B31: FY2028E EBIT (Base OPM) | C31: =C26*($C$60+($E$58-$C$60)*C$17) -> 3347.0509 | D31: =D26*($C$60+($E$58-$C$60)*D$17) -> 3530.4809 | E31: =E26*($C$60+($E$58-$C$60)*E$17) -> 3720.4911 | F31: =F26*($C$60+($E$58-$C$60)*F$17) -> 3818 | G31: =G26*($C$60+($E$58-$C$60)*G$17) -> 3917.1974 | H31: =H26*($C$60+($E$58-$C$60)*H$17) -> 4018.0978 | I31: =I26*($C$60+($E$58-$C$60)*I$17) -> 4120.7157 | J31: =J26*($C$60+($E$58-$C$60)*J$17) -> 4225.0656 | ... T31: =T26*($C$60+($E$58-$C$60)*T$17) -> 5491.3691
B32: FY2029E EBIT (Base OPM) | C32: =C27*($C$60+($F$58-$C$60)*C$17) -> 3179.9468 | D32: =D27*($C$60+($F$58-$C$60)*D$17) -> 3424.8052 | E32: =E27*($C$60+($F$58-$C$60)*E$17) -> 3683.3977 | F32: =F27*($C$60+($F$58-$C$60)*F$17) -> 3818 | G32: =G27*($C$60+($F$58-$C$60)*G$17) -> 3956.2238 | H32: =H27*($C$60+($F$58-$C$60)*H$17) -> 4098.133 | I32: =I27*($C$60+($F$58-$C$60)*I$17) -> 4243.7919 | J32: =J27*($C$60+($F$58-$C$60)*J$17) -> 4393.2654 | ... T32: =T27*($C$60+($F$58-$C$60)*T$17) -> 6308.3625
B33: FY2030E EBIT (Base OPM) | C33: =C28*($C$60+($G$58-$C$60)*C$17) -> 3052.0616 | D33: =D28*($C$60+($G$58-$C$60)*D$17) -> 3342.5279 | E33: =E28*($C$60+($G$58-$C$60)*E$17) -> 3654.0251 | F33: =F28*($C$60+($G$58-$C$60)*F$17) -> 3818 | G33: =G28*($C$60+($G$58-$C$60)*G$17) -> 3987.6449 | H33: =H28*($C$60+($G$58-$C$60)*H$17) -> 4163.1017 | I33: =I28*($C$60+($G$58-$C$60)*I$17) -> 4344.5151 | J33: =J28*($C$60+($G$58-$C$60)*J$17) -> 4532.0317 | ... T33: =T28*($C$60+($G$58-$C$60)*T$17) -> 7041.8664
B34: FY2031E EBIT (Base OPM) | C34: =C29*($C$60+($H$58-$C$60)*C$17) -> 2954.1309 | D34: =D29*($C$60+($H$58-$C$60)*D$17) -> 3278.6667 | E34: =E29*($C$60+($H$58-$C$60)*E$17) -> 3630.9225 | F34: =F29*($C$60+($H$58-$C$60)*F$17) -> 3818 | G34: =G29*($C$60+($H$58-$C$60)*G$17) -> 4012.6833 | H34: =H29*($C$60+($H$58-$C$60)*H$17) -> 4215.2082 | I34: =I29*($C$60+($H$58-$C$60)*I$17) -> 4425.8159 | J34: =J29*($C$60+($H$58-$C$60)*J$17) -> 4644.7528 | ... T34: =T29*($C$60+($H$58-$C$60)*T$17) -> 7678.8566
B35: FY2027E FCF | C35: =MAX(0,C30*(1-'DCF Model'!$C$6))+$D$61-$D$62-$D$63 -> 1970.2815 | D35: =MAX(0,D30*(1-'DCF Model'!$C$6))+$D$61-$D$62-$D$63 -> 2041.3752 | E35: =MAX(0,E30*(1-'DCF Model'!$C$6))+$D$61-$D$62-$D$63 -> 2113.3885 | F35: =MAX(0,F30*(1-'DCF Model'!$C$6))+$D$61-$D$62-$D$63 -> 2149.7401 | G35: =MAX(0,G30*(1-'DCF Model'!$C$6))+$D$61-$D$62-$D$63 -> 2186.3215 | H35: =MAX(0,H30*(1-'DCF Model'!$C$6))+$D$61-$D$62-$D$63 -> 2223.1328 | I35: =MAX(0,I30*(1-'DCF Model'!$C$6))+$D$61-$D$62-$D$63 -> 2260.174 | J35: =MAX(0,J30*(1-'DCF Model'!$C$6))+$D$61-$D$62-$D$63 -> 2297.4452 | ... T35: =MAX(0,T30*(1-'DCF Model'!$C$6))+$D$61-$D$62-$D$63 -> 2722.6013
B36: FY2028E FCF | C36: =MAX(0,C31*(1-'DCF Model'!$C$6))+$E$61-$E$62-$E$63 -> 1865.2828 | D36: =MAX(0,D31*(1-'DCF Model'!$C$6))+$E$61-$E$62-$E$63 -> 1992.7666 | E36: =MAX(0,E31*(1-'DCF Model'!$C$6))+$E$61-$E$62-$E$63 -> 2124.8237 | F36: =MAX(0,F31*(1-'DCF Model'!$C$6))+$E$61-$E$62-$E$63 -> 2192.5924 | G36: =MAX(0,G31*(1-'DCF Model'!$C$6))+$E$61-$E$62-$E$63 -> 2261.5346 | H36: =MAX(0,H31*(1-'DCF Model'!$C$6))+$E$61-$E$62-$E$63 -> 2331.6604 | I36: =MAX(0,I31*(1-'DCF Model'!$C$6))+$E$61-$E$62-$E$63 -> 2402.9798 | J36: =MAX(0,J31*(1-'DCF Model'!$C$6))+$E$61-$E$62-$E$63 -> 2475.503 | ... T36: =MAX(0,T31*(1-'DCF Model'!$C$6))+$E$61-$E$62-$E$63 -> 3355.5839
B37: FY2029E FCF | C37: =MAX(0,C32*(1-'DCF Model'!$C$6))+$F$61-$F$62-$F$63 -> 1861.6794 | D37: =MAX(0,D32*(1-'DCF Model'!$C$6))+$F$61-$F$62-$F$63 -> 2031.856 | E37: =MAX(0,E32*(1-'DCF Model'!$C$6))+$F$61-$F$62-$F$63 -> 2211.5778 | F37: =MAX(0,F32*(1-'DCF Model'!$C$6))+$F$61-$F$62-$F$63 -> 2305.1264 | G37: =MAX(0,G32*(1-'DCF Model'!$C$6))+$F$61-$F$62-$F$63 -> 2401.1919 | H37: =MAX(0,H32*(1-'DCF Model'!$C$6))+$F$61-$F$62-$F$63 -> 2499.8188 | I37: =MAX(0,I32*(1-'DCF Model'!$C$6))+$F$61-$F$62-$F$63 -> 2601.0517 | J37: =MAX(0,J32*(1-'DCF Model'!$C$6))+$F$61-$F$62-$F$63 -> 2704.9359 | ... T37: =MAX(0,T32*(1-'DCF Model'!$C$6))+$F$61-$F$62-$F$63 -> 4035.9283
B38: FY2030E FCF | C38: =MAX(0,C33*(1-'DCF Model'!$C$6))+$G$61-$G$62-$G$63 -> 1860.3208 | D38: =MAX(0,D33*(1-'DCF Model'!$C$6))+$G$61-$G$62-$G$63 -> 2062.1949 | E38: =MAX(0,E33*(1-'DCF Model'!$C$6))+$G$61-$G$62-$G$63 -> 2278.6854 | F38: =MAX(0,F33*(1-'DCF Model'!$C$6))+$G$61-$G$62-$G$63 -> 2392.648 | G38: =MAX(0,G33*(1-'DCF Model'!$C$6))+$G$61-$G$62-$G$63 -> 2510.5512 | H38: =MAX(0,H33*(1-'DCF Model'!$C$6))+$G$61-$G$62-$G$63 -> 2632.4937 | I38: =MAX(0,I33*(1-'DCF Model'!$C$6))+$G$61-$G$62-$G$63 -> 2758.576 | J38: =MAX(0,J33*(1-'DCF Model'!$C$6))+$G$61-$G$62-$G$63 -> 2888.9 | ... T38: =MAX(0,T33*(1-'DCF Model'!$C$6))+$G$61-$G$62-$G$63 -> 4633.2352
B39: FY2031E FCF | C39: =MAX(0,C34*(1-'DCF Model'!$C$6))+$H$61-$H$62-0 -> 2215.7471 | D39: =MAX(0,D34*(1-'DCF Model'!$C$6))+$H$61-$H$62-0 -> 2441.2995 | E39: =MAX(0,E34*(1-'DCF Model'!$C$6))+$H$61-$H$62-0 -> 2686.1172 | F39: =MAX(0,F34*(1-'DCF Model'!$C$6))+$H$61-$H$62-0 -> 2816.1361 | G39: =MAX(0,G34*(1-'DCF Model'!$C$6))+$H$61-$H$62-0 -> 2951.441 | H39: =MAX(0,H34*(1-'DCF Model'!$C$6))+$H$61-$H$62-0 -> 3092.1958 | I39: =MAX(0,I34*(1-'DCF Model'!$C$6))+$H$61-$H$62-0 -> 3238.5681 | J39: =MAX(0,J34*(1-'DCF Model'!$C$6))+$H$61-$H$62-0 -> 3390.7293 | ... T39: =MAX(0,T34*(1-'DCF Model'!$C$6))+$H$61-$H$62-0 -> 5499.4315
B40: PV of Explicit FCFs (Sum) | C40: =C35/(1+'DCF Model'!$C$26)^('DCF Model'!$C$19+0)+C36/(1+'DCF Model'!$C$26)^('DCF Model'!$C$19+1)+C37/(1+'DCF Model'!$C$26)^('DCF Model'!$C$19+2)+C38/(1+'DCF Model'!$C$26)^('DCF Model'!$C$19+3)+C39/(1+'DCF Model'!$C$26)^('DCF Model'!$C$19+4) -> 7644.039 | D40: =D35/(1+'DCF Model'!$C$26)^('DCF Model'!$C$19+0)+D36/(1+'DCF Model'!$C$26)^('DCF Model'!$C$19+1)+D37/(1+'DCF Model'!$C$26)^('DCF Model'!$C$19+2)+D38/(1+'DCF Model'!$C$26)^('DCF Model'!$C$19+3)+D39/(1+'DCF Model'!$C$26)^('DCF Model'!$C$19+4) -> 8235.7524 | E40: =E35/(1+'DCF Model'!$C$26)^('DCF Model'!$C$19+0)+E36/(1+'DCF Model'!$C$26)^('DCF Model'!$C$19+1)+E37/(1+'DCF Model'!$C$26)^('DCF Model'!$C$19+2)+E38/(1+'DCF Model'!$C$26)^('DCF Model'!$C$19+3)+E39/(1+'DCF Model'!$C$26)^('DCF Model'!$C$19+4) -> 8861.8156 | F40: =F35/(1+'DCF Model'!$C$26)^('DCF Model'!$C$19+0)+F36/(1+'DCF Model'!$C$26)^('DCF Model'!$C$19+1)+F37/(1+'DCF Model'!$C$26)^('DCF Model'!$C$19+2)+F38/(1+'DCF Model'!$C$26)^('DCF Model'!$C$19+3)+F39/(1+'DCF Model'!$C$26)^('DCF Model'!$C$19+4) -> 9188.2368 | G40: =G35/(1+'DCF Model'!$C$26)^('DCF Model'!$C$19+0)+G36/(1+'DCF Model'!$C$26)^('DCF Model'!$C$19+1)+G37/(1+'DCF Model'!$C$26)^('DCF Model'!$C$19+2)+G38/(1+'DCF Model'!$C$26)^('DCF Model'!$C$19+3)+G39/(1+'DCF Model'!$C$26)^('DCF Model'!$C$19+4) -> 9523.8629 | H40: =H35/(1+'DCF Model'!$C$26)^('DCF Model'!$C$19+0)+H36/(1+'DCF Model'!$C$26)^('DCF Model'!$C$19+1)+H37/(1+'DCF Model'!$C$26)^('DCF Model'!$C$19+2)+H38/(1+'DCF Model'!$C$26)^('DCF Model'!$C$19+3)+H39/(1+'DCF Model'!$C$26)^('DCF Model'!$C$19+4) -> 9868.907 | I40: =I35/(1+'DCF Model'!$C$26)^('DCF Model'!$C$19+0)+I36/(1+'DCF Model'!$C$26)^('DCF Model'!$C$19+1)+I37/(1+'DCF Model'!$C$26)^('DCF Model'!$C$19+2)+I38/(1+'DCF Model'!$C$26)^('DCF Model'!$C$19+3)+I39/(1+'DCF Model'!$C$26)^('DCF Model'!$C$19+4) -> 10223.586 | J40: =J35/(1+'DCF Model'!$C$26)^('DCF Model'!$C$19+0)+J36/(1+'DCF Model'!$C$26)^('DCF Model'!$C$19+1)+J37/(1+'DCF Model'!$C$26)^('DCF Model'!$C$19+2)+J38/(1+'DCF Model'!$C$26)^('DCF Model'!$C$19+3)+J39/(1+'DCF Model'!$C$26)^('DCF Model'!$C$19+4) -> 10588.121 | ... T40: =T35/(1+'DCF Model'!$C$26)^('DCF Model'!$C$19+0)+T36/(1+'DCF Model'!$C$26)^('DCF Model'!$C$19+1)+T37/(1+'DCF Model'!$C$26)^('DCF Model'!$C$19+2)+T38/(1+'DCF Model'!$C$26)^('DCF Model'!$C$19+3)+T39/(1+'DCF Model'!$C$26)^('DCF Model'!$C$19+4) -> 15315.422
B41: Terminal Value (PGM) | C41: =C39*(1+'DCF Model'!$C$13)/('DCF Model'!$C$26-'DCF Model'!$C$13) -> 22782.883 | D41: =D39*(1+'DCF Model'!$C$13)/('DCF Model'!$C$26-'DCF Model'!$C$13) -> 25102.071 | E41: =E39*(1+'DCF Model'!$C$13)/('DCF Model'!$C$26-'DCF Model'!$C$13) -> 27619.35 | F41: =F39*(1+'DCF Model'!$C$13)/('DCF Model'!$C$26-'DCF Model'!$C$13) -> 28956.238 | G41: =G39*(1+'DCF Model'!$C$13)/('DCF Model'!$C$26-'DCF Model'!$C$13) -> 30347.478 | H41: =H39*(1+'DCF Model'!$C$13)/('DCF Model'!$C$26-'DCF Model'!$C$13) -> 31794.755 | I41: =I39*(1+'DCF Model'!$C$13)/('DCF Model'!$C$26-'DCF Model'!$C$13) -> 33299.793 | J41: =J39*(1+'DCF Model'!$C$13)/('DCF Model'!$C$26-'DCF Model'!$C$13) -> 34864.354 | ... T41: =T39*(1+'DCF Model'!$C$13)/('DCF Model'!$C$26-'DCF Model'!$C$13) -> 56546.574
B42: PV of Terminal Value | C42: =C41/(1+'DCF Model'!$C$26)^('DCF Model'!$C$19+4) -> 14117.278 | D42: =D41/(1+'DCF Model'!$C$26)^('DCF Model'!$C$19+4) -> 15554.348 | E42: =E41/(1+'DCF Model'!$C$26)^('DCF Model'!$C$19+4) -> 17114.166 | F42: =F41/(1+'DCF Model'!$C$26)^('DCF Model'!$C$19+4) -> 17942.56 | G42: =G41/(1+'DCF Model'!$C$26)^('DCF Model'!$C$19+4) -> 18804.633 | H42: =H41/(1+'DCF Model'!$C$26)^('DCF Model'!$C$19+4) -> 19701.43 | I42: =I41/(1+'DCF Model'!$C$26)^('DCF Model'!$C$19+4) -> 20634.018 | J42: =J41/(1+'DCF Model'!$C$26)^('DCF Model'!$C$19+4) -> 21603.489 | ... T42: =T41/(1+'DCF Model'!$C$26)^('DCF Model'!$C$19+4) -> 35038.747
B43: Enterprise Value | C43: =C40+C42 -> 21761.317 | D43: =D40+D42 -> 23790.101 | E43: =E40+E42 -> 25975.981 | F43: =F40+F42 -> 27130.797 | G43: =G40+G42 -> 28328.496 | H43: =H40+H42 -> 29570.337 | I43: =I40+I42 -> 30857.604 | J43: =J40+J42 -> 32191.61 | ... T43: =T40+T42 -> 50354.169
B44: Equity Value | C44: =C43-'DCF Model'!$C$16 -> 29058.117 | D44: =D43-'DCF Model'!$C$16 -> 31086.901 | E44: =E43-'DCF Model'!$C$16 -> 33272.781 | F44: =F43-'DCF Model'!$C$16 -> 34427.597 | G44: =G43-'DCF Model'!$C$16 -> 35625.296 | H44: =H43-'DCF Model'!$C$16 -> 36867.137 | I44: =I43-'DCF Model'!$C$16 -> 38154.404 | J44: =J43-'DCF Model'!$C$16 -> 39488.41 | ... T44: =T43-'DCF Model'!$C$16 -> 57650.969
B45: Implied Share Price (JPY) | C45: =ROUND(C44*1000000/'DCF Model'!$C$15,0) -> 2022 | D45: =ROUND(D44*1000000/'DCF Model'!$C$15,0) -> 2164 | E45: =ROUND(E44*1000000/'DCF Model'!$C$15,0) -> 2316 | F45: =ROUND(F44*1000000/'DCF Model'!$C$15,0) -> 2396 | G45: =ROUND(G44*1000000/'DCF Model'!$C$15,0) -> 2479 | H45: =ROUND(H44*1000000/'DCF Model'!$C$15,0) -> 2566 | I45: =ROUND(I44*1000000/'DCF Model'!$C$15,0) -> 2655 | J45: =ROUND(J44*1000000/'DCF Model'!$C$15,0) -> 2748 | ... T45: =ROUND(T44*1000000/'DCF Model'!$C$15,0) -> 4012
B47: 【参考】Base全社売上 (補助計算)
B48: FY2026A Total Revenue | C48: ='Segment Analysis'!E6+'Segment Analysis'!E11+'Segment Analysis'!E16 -> 26530
B49: FY2027E Total Revenue (Base, α=1) | C49: ='Segment Analysis'!E6*(1+'Segment Analysis'!F34)+'Segment Analysis'!E11*(1+'Segment Analysis'!F48)+'Segment Analysis'!E16*(1+'Segment Analysis'!F62) -> 28876.56
B50: FY2027E Base Growth (α=1) | C50: =C49/C48-1 -> 0.088449303
B51: Base全社成長率 各年度 (加重平均)
C52: FY2027 | D52: =('Segment Analysis'!E6*(1+'Segment Analysis'!F34)+'Segment Analysis'!E11*(1+'Segment Analysis'!F48)+'Segment Analysis'!E16*(1+'Segment Analysis'!F62))/('Segment Analysis'!E6+'Segment Analysis'!E11+'Segment Analysis'!E16)-1 -> 0.088449303
B53: 未来社会 Base Rev | C53: ='Segment Analysis'!E6 -> 5084 | D53: =C53*(1+'Segment Analysis'!F34) -> 5846.6 | E53: =D53*(1+'Segment Analysis'!G34) -> 6723.59 | F53: =E53*(1+'Segment Analysis'!H34) -> 7530.4208 | G53: =F53*(1+'Segment Analysis'!I34) -> 8132.8545 | H53: =G53*(1+'Segment Analysis'!J34) -> 8539.4972
B54: 産業技術 Base Rev | C54: ='Segment Analysis'!E11 -> 13695 | D54: =C54*(1+'Segment Analysis'!F48) -> 15201.45 | E54: =D54*(1+'Segment Analysis'!G48) -> 16721.595 | F54: =E54*(1+'Segment Analysis'!H48) -> 18059.323 | G54: =F54*(1+'Segment Analysis'!I48) -> 19142.882 | H54: =G54*(1+'Segment Analysis'!J48) -> 20100.026
B55: 顧客業務 Base Rev | C55: ='Segment Analysis'!E16 -> 7751 | D55: =C55*(1+'Segment Analysis'!F62) -> 7828.51 | E55: =D55*(1+'Segment Analysis'!G62) -> 7906.7951 | F55: =E55*(1+'Segment Analysis'!H62) -> 7985.8631 | G55: =F55*(1+'Segment Analysis'!I62) -> 8065.7217 | H55: =G55*(1+'Segment Analysis'!J62) -> 8146.3789
B56: 全社合計 Base Rev | C56: =C53+C54+C55 -> 26530 | D56: =D53+D54+D55 -> 28876.56 | E56: =E53+E54+E55 -> 31351.98 | F56: =F53+F54+F55 -> 33575.606 | G56: =G53+G54+G55 -> 35341.458 | H56: =H53+H54+H55 -> 36785.902
B57: 全社 Base 成長率 | D57: =D56/C56-1 -> 0.088449303 | E57: =E56/D56-1 -> 0.085724203 | F57: =F56/E56-1 -> 0.070924591 | G57: =G56/F56-1 -> 0.052593291 | H57: =H56/G56-1 -> 0.040871093
B58: 全社 Base OPM (加重平均) | D58: =(D53*'Segment Analysis'!F41+D54*'Segment Analysis'!F55+D55*'Segment Analysis'!F69)/D56 -> 0.1509611 | E58: =(E53*'Segment Analysis'!G41+E54*'Segment Analysis'!G55+E55*'Segment Analysis'!G69)/E56 -> 0.15591831 | F58: =(F53*'Segment Analysis'!H41+F54*'Segment Analysis'!H55+F55*'Segment Analysis'!H69)/F56 -> 0.16005428 | G58: =(G53*'Segment Analysis'!I41+G54*'Segment Analysis'!I55+G55*'Segment Analysis'!I69)/G56 -> 0.16393812 | H58: =(H53*'Segment Analysis'!J41+H54*'Segment Analysis'!J55+H55*'Segment Analysis'!J69)/H56 -> 0.16712339
B59: FY2026A Total OP (補助) | C59: ='Segment Analysis'!E7+'Segment Analysis'!E12+'Segment Analysis'!E17 -> 3818
B60: FY2026A OPM (補助) | C60: =C59/C48 -> 0.14391255
B61: Base D&A 各年度 (補助) | D61: 210 | E61: 210 | F61: 210 | G61: 215 | H61: =H56*'DCF Model'!$C$18 -> 315.90591
B62: Base Capex 各年度 (補助) | D62: 100 | E62: 100 | F62: 105 | G62: 105 | H62: =H56*'DCF Model'!$C$5 -> 153.27979
B63: Base ΔNWC 各年度 (補助、固定) | C63: 1026.8724 | D63: 613.76994 | E63: 570.91759 | F63: 453.38362 | G63: 370.862
B66: 【BLOCK 3】価格ポイント別のインプライドα
B67: 各価格ポイントが示唆するα(Base成長率乗数)を線形補間で算出
B69: 価格ポイント | C69: 株価 (JPY) | D69: Implied α | E69: 解釈 | F69: 市場の見方
B70: Pre-Earnings Peak | C70: =C7 -> 2330 | D70: =FORECAST(C70,$C$17:$T$17,$C$45:$T$45) -> -0.065946192 | E70: =IF(D70<-0.3,"Deep Pessimism",IF(D70<0,"Pessimistic",IF(D70<0.5,"Neutral",IF(D70<1,"Mild Optimism","Bullish")))) -> Pessimistic | F70: =IF(D70<-0.3,"Base成長率の半分以下で評価",IF(D70<0,"Baseより保守的、低成長織込み",IF(D70<0.5,"Base成長率の0-50%を織込み",IF(D70<1,"Base成長率の50-100%を織込み","Base以上の成長を期待")))) -> Baseより保守的、低成長織込み
B71: Current Price | C71: =C8 -> 1990 | D71: =FORECAST(C71,$C$17:$T$17,$C$45:$T$45) -> -0.40510605 | E71: =IF(D71<-0.3,"Deep Pessimism",IF(D71<0,"Pessimistic",IF(D71<0.5,"Neutral",IF(D71<1,"Mild Optimism","Bullish")))) -> Deep Pessimism | F71: =IF(D71<-0.3,"Base成長率の半分以下で評価",IF(D71<0,"Baseより保守的、低成長織込み",IF(D71<0.5,"Base成長率の0-50%を織込み",IF(D71<1,"Base成長率の50-100%を織込み","Base以上の成長を期待")))) -> Base成長率の半分以下で評価
B72: Post-Earnings Trough | C72: =C9 -> 1964 | D72: =FORECAST(C72,$C$17:$T$17,$C$45:$T$45) -> -0.4310418 | E72: =IF(D72<-0.3,"Deep Pessimism",IF(D72<0,"Pessimistic",IF(D72<0.5,"Neutral",IF(D72<1,"Mild Optimism","Bullish")))) -> Deep Pessimism | F72: =IF(D72<-0.3,"Base成長率の半分以下で評価",IF(D72<0,"Baseより保守的、低成長織込み",IF(D72<0.5,"Base成長率の0-50%を織込み",IF(D72<1,"Base成長率の50-100%を織込み","Base以上の成長を期待")))) -> Base成長率の半分以下で評価
B73: Entry Price | C73: =C10 -> 2127 | D73: =FORECAST(C73,$C$17:$T$17,$C$45:$T$45) -> -0.26844458 | E73: =IF(D73<-0.3,"Deep Pessimism",IF(D73<0,"Pessimistic",IF(D73<0.5,"Neutral",IF(D73<1,"Mild Optimism","Bullish")))) -> Pessimistic | F73: =IF(D73<-0.3,"Base成長率の半分以下で評価",IF(D73<0,"Baseより保守的、低成長織込み",IF(D73<0.5,"Base成長率の0-50%を織込み",IF(D73<1,"Base成長率の50-100%を織込み","Base以上の成長を期待")))) -> Baseより保守的、低成長織込み
B74: DCF Base Target | C74: =C11 -> 2893 | D74: =FORECAST(C74,$C$17:$T$17,$C$45:$T$45) -> 0.49566263 | E74: =IF(D74<-0.3,"Deep Pessimism",IF(D74<0,"Pessimistic",IF(D74<0.5,"Neutral",IF(D74<1,"Mild Optimism","Bullish")))) -> Neutral | F74: =IF(D74<-0.3,"Base成長率の半分以下で評価",IF(D74<0,"Baseより保守的、低成長織込み",IF(D74<0.5,"Base成長率の0-50%を織込み",IF(D74<1,"Base成長率の50-100%を織込み","Base以上の成長を期待")))) -> Base成長率の0-50%を織込み
B77: 【BLOCK 4】Comparison Matrix - 市場 vs 自分の見方
B78: 現在株価のインプライドαと、各シナリオが含意するα(Baseに対する相対倍率)を比較
B80: 比較項目 | C80: Implied α | D80: 5Y CAGR (Rev) | E80: Avg OPM | F80: Gap vs Market | G80: Verdict
B81: 市場 (Current ¥2,011) | C81: =D71 -> -0.40510605 | D81: =((1+$D$57*C81)*(1+$E$57*C81)*(1+$F$57*C81)*(1+$G$57*C81)*(1+$H$57*C81))^(1/5)-1 -> -0.027459624 | E81: =$C$60+((AVERAGE($D$58:$H$58)-$C$60)*C81) -> 0.13755786 | F81: - | G81: Reference
B82: Base | C82: 1 | D82: =((1+$D$57*C82)*(1+$E$57*C82)*(1+$F$57*C82)*(1+$G$57*C82)*(1+$H$57*C82))^(1/5)-1 -> 0.067551493 | E82: =$C$60+((AVERAGE($D$58:$H$58)-$C$60)*C82) -> 0.15959904 | F82: =C82-$C$81 -> 1.405106 | G82: =IF(F82>0.5,"BULLISH (Buy候補)",IF(F82>0.2,"Mildly Bullish",IF(F82>-0.2,"Aligned",IF(F82>-0.5,"Mildly Bearish","BEARISH (Sell候補)")))) -> BULLISH (Buy候補)
B83: Upside | C83: 1.5 | D83: =((1+$D$57*C83)*(1+$E$57*C83)*(1+$F$57*C83)*(1+$G$57*C83)*(1+$H$57*C83))^(1/5)-1 -> 0.1012171 | E83: =$C$60+((AVERAGE($D$58:$H$58)-$C$60)*C83) -> 0.16744229 | F83: =C83-$C$81 -> 1.905106 | G83: =IF(F83>0.5,"BULLISH (Buy候補)",IF(F83>0.2,"Mildly Bullish",IF(F83>-0.2,"Aligned",IF(F83>-0.5,"Mildly Bearish","BEARISH (Sell候補)")))) -> BULLISH (Buy候補)
B84: Management | C84: 0.75 | D84: =((1+$D$57*C84)*(1+$E$57*C84)*(1+$F$57*C84)*(1+$G$57*C84)*(1+$H$57*C84))^(1/5)-1 -> 0.050692418 | E84: =$C$60+((AVERAGE($D$58:$H$58)-$C$60)*C84) -> 0.15567742 | F84: =C84-$C$81 -> 1.155106 | G84: =IF(F84>0.5,"BULLISH (Buy候補)",IF(F84>0.2,"Mildly Bullish",IF(F84>-0.2,"Aligned",IF(F84>-0.5,"Mildly Bearish","BEARISH (Sell候補)")))) -> BULLISH (Buy候補)
B85: Downside 1 | C85: 0.4 | D85: =((1+$D$57*C85)*(1+$E$57*C85)*(1+$F$57*C85)*(1+$G$57*C85)*(1+$H$57*C85))^(1/5)-1 -> 0.027058268 | E85: =$C$60+((AVERAGE($D$58:$H$58)-$C$60)*C85) -> 0.15018715 | F85: =C85-$C$81 -> 0.80510605 | G85: =IF(F85>0.5,"BULLISH (Buy候補)",IF(F85>0.2,"Mildly Bullish",IF(F85>-0.2,"Aligned",IF(F85>-0.5,"Mildly Bearish","BEARISH (Sell候補)")))) -> BULLISH (Buy候補)
B86: Downside 2 | C86: 0.15 | D86: =((1+$D$57*C86)*(1+$E$57*C86)*(1+$F$57*C86)*(1+$G$57*C86)*(1+$H$57*C86))^(1/5)-1 -> 0.010153055 | E86: =$C$60+((AVERAGE($D$58:$H$58)-$C$60)*C86) -> 0.14626553 | F86: =C86-$C$81 -> 0.55510605 | G86: =IF(F86>0.5,"BULLISH (Buy候補)",IF(F86>0.2,"Mildly Bullish",IF(F86>-0.2,"Aligned",IF(F86>-0.5,"Mildly Bearish","BEARISH (Sell候補)")))) -> BULLISH (Buy候補)
B89: 【BLOCK 5】Final Verdict & Action
B91: Market View (現在株価): | C91: =D71 -> -0.40510605 | D91: =IF(C91<-0.3,"Deep Pessimism (Base成長率を半分以下で評価)",IF(C91<0,"Pessimistic (Base以下を織込み)",IF(C91<0.5,"Mildly Pessimistic",IF(C91<1,"Aligned with Base","Bullish")))) -> Deep Pessimism (Base成長率を半分以下で評価)
B92: My View (Baseシナリオ): | C92: 1 | D92: 基準値 (DCF Base想定)
B93: Gap (My View - Market): | C93: =C92-C91 -> 1.405106 | D93: =IF(C93>1,"+1.0以上 = 大きなアップサイドサプライズ余地",IF(C93>0.5,"+0.5〜1.0 = 顕著なアップサイドサプライズ余地",IF(C93>0.2,"+0.2〜0.5 = 中程度のアップサイド余地",IF(C93>-0.2,"市場とほぼ整合","自分の見方が市場以下 = 警戒")))) -> +1.0以上 = 大きなアップサイドサプライズ余地
B94: Action Recommendation: | C94: =IF(C93>0.5,"BUY (アップサイドサプライズ期待)",IF(C93>0.2,"BUY/HOLD",IF(C93>-0.2,"HOLD",IF(C93>-0.5,"HOLD/SELL","SELL (失望リスク)")))) -> BUY (アップサイドサプライズ期待)
B97: 【使い方】
B98: • C92 (My View)を変更すると、現在の市場認識との差分が即座に再計算されます
B99: • BLOCK 1 の C7-C11 (株価) を編集すると、各価格ポイントのα逆算が更新されます
B100: • 線形補間のため、テーブル範囲外(α<-0.5 または α>1.5)の株価は精度が落ちます
B101: • OPMもαで連動。α<0は売上成長低下+利益率低下の同時織込みを意味
B102: • 既存DCFモデルのD&A、Capex、ΔNWCはBaseシナリオの値を流用 (簡略化)

Sheet Market Scorecard
B2: MARKET SCORECARD - 株式会社コア (2359)
B3: 4要素・5段階・重み付き総合スコアで市場と業績の整合性を判定
B5: 【SCORECARD SUMMARY】
B6: 要素 | C6: 計測値 | D6: スコア | E6: ウェイト | F6: 寄与 | G6: 判定
B7: ① インプライド成長率 | C7: =1-'Implied Growth Analysis'!C91 -> 1.405106 | D7: =IF(C7>=1,2,IF(C7>=0.5,1,IF(C7>=-0.2,0,IF(C7>=-0.5,-1,-2)))) -> 2 | E7: 0.4 | F7: =D7*E7 -> 0.8 | G7: =IF(D7=2,"市場大幅悲観 = 強気",IF(D7=1,"市場やや悲観 = 買い候補",IF(D7=0,"市場と認識一致",IF(D7=-1,"市場やや楽観 = 警戒","市場大幅楽観 = 失望リスク")))) -> 市場大幅悲観 = 強気
B8: ② 株価モメンタム (3ヶ月) | C8: =C26 -> -0.0020366599 | D8: =IF(C8<=-0.2,2,IF(C8<=-0.1,1,IF(C8<=0.1,0,IF(C8<=0.2,-1,-2)))) -> 0 | E8: 0.25 | F8: =D8*E8 -> 0 | G8: =IF(D8=2,"過剰悲観 = リバウンド余地大",IF(D8=1,"悲観織込み = サプライズ余地",IF(D8=0,"期待ニュートラル",IF(D8=-1,"期待やや過熱","期待過熱 = 失望売りリスク")))) -> 期待ニュートラル
B9: ③ 信用残動向 | C9: =C36 -> 9.8039216 | D9: =D36 -> -2 | E9: 0.2 | F9: =D9*E9 -> -0.4 | G9: =IF(D9=2,"踏み上げ余地大",IF(D9=1,"需給良好",IF(D9=0,"ニュートラル",IF(D9=-1,"戻り売り圧力","需給最悪")))) -> 需給最悪
B10: ④ 予想ギャップ (Mine vs 会社) | C10: =C49 -> 0.00065287912 | D10: =D49 -> 0 | E10: 0.15 | F10: =D10*E10 -> 0 | G10: =IF(D10=2,"上方修正余地大",IF(D10=1,"上方修正の可能性",IF(D10=0,"認識一致",IF(D10=-1,"自分が悲観的、要確認","下方修正リスク")))) -> 認識一致
B12: 【総合スコア】 | E12: =SUM(E7:E10) -> 1 | F12: =SUM(F7:F10) -> 0.4 | G12: =IF(F12>=1,"STRONG BUY",IF(F12>=0.5,"BUY",IF(F12>=-0.5,"HOLD",IF(F12>=-1,"CAUTION","AVOID")))) -> HOLD
B14: 【判定スケール】 STRONG BUY (≥+1.0) | BUY (+0.5〜+1.0) | HOLD (-0.5〜+0.5) | CAUTION (-1.0〜-0.5) | AVOID (<-1.0)
B17: 【BLOCK 2】株価モメンタム入力
B19: 項目 | C19: 値 | D19: 備考
B20: 現在株価 (JPY) | C20: 1960 | D20: 今日の株価
B21: 3ヶ月前株価 (JPY) | C21: 1964 | D21: 2026年2月初頃の株価
B22: 1ヶ月前株価 (JPY) | C22: 2330 | D22: 4月初頃の株価 (参考)
B23: 直近高値 (JPY) | C23: 2330 | D23: 3-4月の高値
B24: 直近安値 (JPY) | C24: 1960 | D24: 直近安値
B26: 3ヶ月変化率 | C26: =C20/C21-1 -> -0.0020366599 | D26: =IF(C26<=-0.2,"過剰悲観",IF(C26<=-0.1,"悲観織込み",IF(C26<=0.1,"ニュートラル",IF(C26<=0.2,"やや過熱","過熱")))) -> ニュートラル
B27: 1ヶ月変化率 (参考) | C27: =C20/C22-1 -> -0.15879828
B28: 高値からの下落率 (参考) | C28: =C20/C23-1 -> -0.15879828
B31: 【BLOCK 3】信用残動向入力
B32: 項目 | C32: 値 | D32: 備考
B33: 信用買残 (株) | C33: 50000 | D33: 直近開示の買残
B34: 信用売残 (株) | C34: 5100 | D34: 直近開示の売残
B35: 過去6ヶ月の売残ピーク (株) | C35: 169300 | D35: 踏み上げ余地の過去最大値
B36: 信用倍率 | C36: =IF(C34=0,999,C33/C34) -> 9.8039216 | D36: =IF(AND(C36<=1,C34/C35>=0.5),2,IF(AND(C36<=3,C34/C35>=0.3),1,IF(AND(C36<=10,C34/C35>=0.1),0,IF(AND(C36<=20,C34/C35>=0.05),-1,-2)))) -> -2
B37: 売残充実度 (vs ピーク) | C37: =C34/C35 -> 0.03012404
B38: 判定 | C38: =IF(D36=2,"踏み上げ余地大",IF(D36=1,"需給良好",IF(D36=0,"ニュートラル",IF(D36=-1,"戻り売り圧力","需給最悪 (売残枯渇)")))) -> 需給最悪 (売残枯渇)
B41: 【BLOCK 4】予想ギャップ入力 (会社 vs 自分の予想)
B43: 指標 | C43: 会社予想 | D43: 自分予想 (Base) | E43: ギャップ | F43: スコア
B44: 営業利益成長率 (FY27) | C44: 0.1 | D44: ='DCF Model'!D39/'DCF Model'!C39-1 -> 0.10858155 | E44: =D44-C44 -> 0.0085815549 | F44: =IF(E44>=0.1,2,IF(E44>=0.05,1,IF(E44>=-0.05,0,IF(E44>=-0.1,-1,-2)))) -> 0
B45: 売上成長率 (FY27) | C45: 0.093 | D45: ='DCF Model'!D33/'DCF Model'!C33-1 -> 0.085724203 | E45: =D45-C45 -> -0.0072757967 | F45: =IF(E45>=0.1,2,IF(E45>=0.05,1,IF(E45>=-0.05,0,IF(E45>=-0.1,-1,-2)))) -> 0
B47: 【統合判定】
B48: 平均ギャップ (営業利益+売上 / 2) | C48: =AVERAGE(E44:E45) -> 0.00065287912
B49: 統合スコア (Block 1 ④へ送信) | C49: =AVERAGE(E44:E45) -> 0.00065287912 | D49: =ROUND(AVERAGE(F44:F45),0) -> 0
B50: 注: アナリストコンセンサスがある場合は別途上書き
B53: 【BLOCK 5】解釈ガイド
B55: STRONG BUY (+1.0以上) | C55: 4要素全てがポジティブ。市場が大幅悲観でファンダ良好。積極買い局面
B56: BUY (+0.5〜+1.0) | C56: 主要要素がポジティブ。買い候補だが、リスク管理は必要
B57: HOLD (-0.5〜+0.5) | C57: 要素混在。市場と認識ほぼ一致。様子見または既存ポジション維持
B58: CAUTION (-1.0〜-0.5) | C58: 主要要素がネガティブ。利確検討、新規買いは避ける
B59: AVOID (-1.0以下) | C59: 4要素全てがネガティブ。市場過熱でファンダ悪化リスク。売却推奨
B62: 【使い方】
B63: • Block 2-4 の黄色セル(入力欄)を最新データで更新すると、Block 1 のスコアが自動更新
B64: • 要素①(インプライド成長率)はImplied Growth Analysisシートと自動連動
B65: • 要素④はアナリストコンセンサスがあれば C44/C45 にコンセンサス値を入力
B66: • 信用残データはみんかぶ・株探等で取得 (週1回更新が現実的)
B67: • 株価モメンタムは決算発表前後の判定に最重要 (期待織込み度の代理変数)
