Workbook

Sheet Executive Summary
B1: DISCLAIMER: This is a sample analysis for demonstration purposes only. It does not constitute investment advice.
B3: キリンホールディングス (2503.T)
B4: Equity Research Report
B6: Company | C6: キリンホールディングス
B7: Ticker | C7: 2503.T (TSE Prime)
B8: Sector | C8: 食料品
B9: Current Price | C9: 2912
B10: Target Price (DCF Mid) | C10: =IF(COUNT(C16:C17)=0,"N/A",ROUND(AVERAGE(C16:C17),0)) -> 2883
B11: Recommendation | C11: =IF(NOT(ISNUMBER(C12)),"N/A",IF(C12>0.15,"BUY",IF(C12>0.05,"HOLD","SELL"))) -> SELL
B12: Upside / Downside | C12: =IF(ISNUMBER(C10),(C10-C9)/C9,"N/A") -> -0.0099587912
B14: Valuation Summary
B15: Methodology | C15: Implied Value (JPY) | D15: vs Current Price
B16: DCF - Perpetuity Growth | C16: =IF('DCF Model'!C53<'DCF Model'!C16,"INVALID (EV < net debt)",'DCF Model'!C55) -> 2397 | D16: =IF(ISNUMBER(C16),(C16-C9)/C9,"N/A") -> -0.1768544
B17: DCF - Exit Multiple | C17: =IF('DCF Model'!C62<'DCF Model'!C16,"INVALID (EV < net debt)",'DCF Model'!C64) -> 3368 | D17: =IF(ISNUMBER(C17),(C17-C9)/C9,"N/A") -> 0.15659341
B18: Comps - EV/EBITDA Median [参考・Target不算入] | C18: ='Comps Analysis'!C27 -> 3505 | D18: =IF(ISNUMBER(C18),(C18-C9)/C9,"N/A") -> 0.20364011
B19: Comps - PER Median [参考・Target不算入] | C19: ='Comps Analysis'!C28 -> 4975 | D19: =IF(ISNUMBER(C19),(C19-C9)/C9,"N/A") -> 0.7084478
B20: Note: Target Mid は DCF 2法（PGM / Exit）の平均のみ。Comps 2法は [参考] で Target 不算入（EV<ネットデットで株式価値が負になる手法は INVALID として平均から除外）
B21: DCF Valuation Range (PGM - Exit) | C21: =IF(COUNT(C16:C17)=0,"N/A",MIN(C16:C17)&" - "&MAX(C16:C17)) -> 2397 - 3368
B23: Key Investment Thesis
B24: ="Kirin combines a mature domestic beer business with health science and overseas beverage assets, and the latest year restored the operating margin to the top of its four-year range; the shares trade at "&TEXT('Comps Analysis'!L5,"0.0""x""")&" earnings and "&TEXT('Comps Analysis'!M5,"0.00""x""")&" book." -> Kirin combines a mature domestic beer business with health science and overseas beverage assets, and the latest year restored the operating margin to the top of its four-year range; the shares trade at 15.7x earnings and 1.80x book.
B25: The cost of debt in this model is the realised rate from the filings rather than an assumed spread, which matters because leverage sits between the domestic beverage peers and the more geared names.
B26: ="At "&TEXT(C9,"#,##0")&" the market is not paying for the margin recovery to hold; a base case that mean-reverts only partway supports "&TEXT(C10,"#,##0")&", or "&TEXT(C12,"+0.0%;-0.0%")&" from here." -> At 2,912 the market is not paying for the margin recovery to hold; a base case that mean-reverts only partway supports 2,883, or -1.0% from here.
B28: Key Risks
B29: ="The health-science expansion has absorbed capital without yet delivering peer-level returns, and a write-down there would take earnings back toward the trough case rather than the "&TEXT('Comps Analysis'!L5,"0.0""x""")&" implied by "&TEXT(C9,"#,##0")&"." -> The health-science expansion has absorbed capital without yet delivering peer-level returns, and a write-down there would take earnings back toward the trough case rather than the 15.7x implied by 2,912.
B30: ="Domestic beer volumes decline structurally, so modelled growth relies on overseas assets whose currencies are not hedged in the "&TEXT('DCF Model'!C26,"0.00%")&" used here." -> Domestic beer volumes decline structurally, so modelled growth relies on overseas assets whose currencies are not hedged in the 6.44% used here.
B31: ="The latest-year margin is the best in the observation window; if it proves to be a peak rather than a new level, the base case overstates the path behind "&TEXT(C10,"#,##0")&"." -> The latest-year margin is the best in the observation window; if it proves to be a peak rather than a new level, the base case overstates the path behind 2,883.

Sheet Financial Statements
B2: キリンホールディングス - Historical Financials (JPY mn)
C4: FY2022 | D4: FY2023 | E4: FY2024 | F4: FY2025
B5: Income Statement
B6: Revenue | C6: 1989468 | D6: 2134393 | E6: 2338385 | F6: 2433363
B7: COGS | C7: 1083755 | D7: 1170927 | E7: 1272430 | F7: 1275360
B8: Gross Profit | C8: =C6-C7 -> 905713 | D8: =D6-D7 -> 963466 | E8: =E6-E7 -> 1065955 | F8: =F6-F7 -> 1158003
B9: Gross Margin | C9: =C8/C6 -> 0.45525387 | D9: =D8/D6 -> 0.45140047 | E9: =E8/E6 -> 0.45585094 | F9: =F8/F6 -> 0.47588584
B10: SGA | C10: 789694 | D10: 813172 | E10: 940615 | F10: 948326
B11: Operating Income | C11: 116019 | D11: 150294 | E11: 125340 | F11: 209677
B12: Net Income | C12: 111007 | D12: 112697 | E12: 58214 | F12: 147542
B13: Operating Margin | C13: =C11/C6 -> 0.058316595 | D13: =D11/D6 -> 0.070415336 | E13: =E11/E6 -> 0.053601096 | F13: =F11/F6 -> 0.08616758
B14: Net Margin | C14: =C12/C6 -> 0.055797329 | D14: =D12/D6 -> 0.052800492 | E14: =E12/E6 -> 0.02489496 | F14: =F12/F6 -> 0.060632959
B15: Revenue Growth (YoY) | C15: n/a | D15: =(D6-C6)/C6 -> 0.072846108 | E15: =(E6-D6)/D6 -> 0.095573777 | F15: =(F6-E6)/E6 -> 0.040616922
B16: Operating Income Growth (YoY) | C16: n/a | D16: =(D11-C11)/C11 -> 0.29542575 | E16: =(E11-D11)/D11 -> -0.16603457 | F16: =(F11-E11)/E11 -> 0.67286581
B18: Cash Flow Statement
B19: Operating Cash Flow | C19: 135562 | D19: 203206 | E19: 242844 | F19: 295428
B20: Capex
B21: Free Cash Flow
B22: FCF Margin
B23: Capex / Revenue
B25: Balance Sheet Highlights
B26: Cash & Deposits | C26: 88060 | D26: 131399 | E26: 118617 | F26: 125292
B27: Total Interest-bearing Debt (short + long) | C27: 523121 | D27: 656398 | E27: 857569 | F27: 923434
B28: Net Debt (Cash) | C28: =C27-C26 -> 435061 | D28: =D27-D26 -> 524999 | E28: =E27-E26 -> 738952 | F28: =F27-F26 -> 798142
B30: Note: OCF / Cash / Debt coverage OCF 4/4, Cash 4/4, Debt 4/4 — blank cells are years with no year-key match in the source data (verify against 決算短信 or set hist_ocf / hist_cash / hist_debt in overrides).

Sheet DCF Model
B2: DCF Valuation Model - キリンホールディングス
B4: Assumptions
B5: Capex / Revenue (fallback) | C5: 0.0431
B6: Effective Tax Rate | C6: 0.25
B7: Risk-Free Rate | C7: 0.0297
B8: Beta | C8: 0.6
B9: Equity Risk Premium | C9: 0.065
B10: Size Premium | C10: 0.01
B11: After-tax Cost of Debt | C11: 0.0154
B12: D/E Ratio | C12: 0.2911
B13: Terminal Growth Rate | C13: 0.01
B14: Exit Multiple (EV/EBITDA) | C14: 11.1
B15: Fully Diluted Shares | C15: 796891219
B16: Net Debt (JPY mn) | C16: 675526
... B20: LTM Revenue (JPY mn) | C20: 2514930
B22: WACC Calculation
B23: Cost of Equity (Ke) | C23: =C7+C8*C9+C10 -> 0.0787
B24: Weight of Equity | C24: =1/(1+C12) -> 0.77453334
B25: Weight of Debt | C25: =C12/(1+C12) -> 0.22546666
B26: WACC | C26: =C23*C24+C11*C25 -> 0.064427961
B27: Active Scenario | C27: Base | D27: =MATCH(C27,B69:B73,0) -> 1
B28: Projected Free Cash Flow
C29: FY2026(E) | D29: FY2027(E) | E29: FY2028(E) | F29: FY2029(E) | G29: FY2030(E)
B30: Revenue Growth (YoY) | C30: =CHOOSE($D$27,C69,C70,C71,C72,C73) -> 0.035 | D30: =CHOOSE($D$27,D69,D70,D71,D72,D73) -> 0.03 | E30: =CHOOSE($D$27,E69,E70,E71,E72,E73) -> 0.03 | F30: =CHOOSE($D$27,F69,F70,F71,F72,F73) -> 0.025 | G30: =CHOOSE($D$27,G69,G70,G71,G72,G73) -> 0.025
B31: COGS % of Revenue | C31: =CHOOSE($D$27,C76,C77,C78,C79,C80) -> 0.545 | D31: =CHOOSE($D$27,D76,D77,D78,D79,D80) -> 0.546 | E31: =CHOOSE($D$27,E76,E77,E78,E79,E80) -> 0.548 | F31: =CHOOSE($D$27,F76,F77,F78,F79,F80) -> 0.549 | G31: =CHOOSE($D$27,G76,G77,G78,G79,G80) -> 0.5497
B32: SGA % of Revenue | C32: =CHOOSE($D$27,C83,C84,C85,C86,C87) -> 0.37 | D32: =CHOOSE($D$27,D83,D84,D85,D86,D87) -> 0.37 | E32: =CHOOSE($D$27,E83,E84,E85,E86,E87) -> 0.37 | F32: =CHOOSE($D$27,F83,F84,F85,F86,F87) -> 0.37 | G32: =CHOOSE($D$27,G83,G84,G85,G86,G87) -> 0.37
B33: Revenue | C33: =C17*(1+C30) -> 2518530.7 | D33: =C33*(1+D30) -> 2594086.6 | E33: =D33*(1+E30) -> 2671909.2 | F33: =E33*(1+F30) -> 2738707 | G33: =F33*(1+G30) -> 2807174.6
B34: COGS | C34: =C33*C31 -> 1372599.2 | D34: =D33*D31 -> 1416371.3 | E34: =E33*E31 -> 1464206.3 | F34: =F33*F31 -> 1503550.1 | G34: =G33*G31 -> 1543103.9
B35: Gross Profit | C35: =C33-C34 -> 1145931.5 | D35: =D33-D34 -> 1177715.3 | E35: =E33-E34 -> 1207703 | F35: =F33-F34 -> 1235156.8 | G35: =G33-G34 -> 1264070.7
B36: Gross Margin | C36: =C35/C33 -> 0.455 | D36: =D35/D33 -> 0.454 | E36: =E35/E33 -> 0.452 | F36: =F35/F33 -> 0.451 | G36: =G35/G33 -> 0.4503
B37: SGA Expense | C37: =C33*C32 -> 931856.36 | D37: =D33*D32 -> 959812.05 | E37: =E33*E32 -> 988606.41 | F37: =F33*F32 -> 1013321.6 | G37: =G33*G32 -> 1038654.6
B38: Implied Operating Margin | C38: =(C35-C37)/C33 -> 0.085 | D38: =(D35-D37)/D33 -> 0.084 | E38: =(E35-E37)/E33 -> 0.082 | F38: =(F35-F37)/F33 -> 0.081 | G38: =(G35-G37)/G33 -> 0.0803
B39: Operating Income (EBIT) | C39: =C35-C37 -> 214075.11 | D39: =D35-D37 -> 217903.28 | E39: =E35-E37 -> 219096.56 | F39: =F35-F37 -> 221835.26 | G39: =G35-G37 -> 225416.12
B40: Less: Tax | C40: =MAX(0,C39*C6) -> 53518.777 | D40: =MAX(0,D39*C6) -> 54475.819 | E40: =MAX(0,E39*C6) -> 54774.139 | F40: =MAX(0,F39*C6) -> 55458.816 | G40: =MAX(0,G39*C6) -> 56354.031
B41: NOPAT | C41: =C39-C40 -> 160556.33 | D41: =D39-D40 -> 163427.46 | E41: =E39-E40 -> 164322.42 | F41: =F39-F40 -> 166376.45 | G41: =G39-G40 -> 169062.09
B42: Plus: D&A | C42: =C33*C18 -> 103259.76 | D42: =D33*C18 -> 106357.55 | E42: =E33*C18 -> 109548.28 | F42: =F33*C18 -> 112286.99 | G42: =G33*C18 -> 115094.16
B43: Less: Capex | C43: 150000 | D43: 140000 | E43: 132000 | F43: 126000 | G43: 121000
B44: Change in NWC | C44: ='NWC Schedule'!D19 -> 39323.107 | D44: ='NWC Schedule'!E19 -> 16266.12 | E44: ='NWC Schedule'!F19 -> 16761.637 | F44: ='NWC Schedule'!G19 -> 14382.375 | G44: ='NWC Schedule'!H19 -> 14739.815
B45: Unlevered Free Cash Flow | C45: =C41+C42-C43-C44 -> 74492.984 | D45: =D41+D42-D43-D44 -> 113518.89 | E45: =E41+E42-E43-E44 -> 125109.06 | F45: =F41+F42-F43-F44 -> 138281.06 | G45: =G41+G42-G43-G44 -> 148416.44
B46: Discount Factor | C46: =1/(1+C26)^(C19+0) -> 0.96926351 | D46: =1/(1+C26)^(C19+1) -> 0.91059569 | E46: =1/(1+C26)^(C19+2) -> 0.85547892 | F46: =1/(1+C26)^(C19+3) -> 0.80369828 | G46: =1/(1+C26)^(C19+4) -> 0.75505183
B47: PV of FCF | C47: =C45*C46 -> 72203.331 | D47: =D45*D46 -> 103369.81 | E47: =E45*E46 -> 107028.16 | F47: =F45*F46 -> 111136.25 | G47: =G45*G46 -> 112062.1
B49: Valuation - Perpetuity Growth Method
B50: Sum of PV of FCFs | C50: =SUM(C47:G47) -> 505799.66
B51: Terminal Value (PGM) | C51: =G45*(1+C13)/(C26-C13) -> 2754110.2
B52: PV of Terminal Value | C52: =C51*G46 -> 2079496
B53: Enterprise Value | C53: =C50+C52 -> 2585295.6
B54: Equity Value | C54: =C53-C16 -> 1909769.6
B55: Implied Share Price (PGM) | C55: =ROUND(C54*1000000/C15,0) -> 2397
B57: Valuation - Exit Multiple Method
B58: Sum of PV of FCFs | C58: =C50 -> 505799.66
B59: Year 5 EBITDA | C59: =G39+G42 -> 340510.28
B60: Terminal Value (Exit Multiple) | C60: =C59*C14 -> 3779664.1
B61: PV of Terminal Value | C61: =C60*G46 -> 2853842.3
B62: Enterprise Value | C62: =C58+C61 -> 3359642
B63: Equity Value | C63: =C62-C16 -> 2684116
B64: Implied Share Price (Exit Multiple) | C64: =ROUND(C63*1000000/C15,0) -> 3368
B66: Scenario Input Matrix
C67: Year 1 | D67: Year 2 | E67: Year 3 | F67: Year 4 | G67: Year 5
B68: Revenue Growth (YoY)
B69: Base | C69: 0.035 | D69: 0.03 | E69: 0.03 | F69: 0.025 | G69: 0.025
B70: Upside | C70: 0.05 | D70: 0.045 | E70: 0.04 | F70: 0.035 | G70: 0.035
B71: Management | C71: 0.035 | D71: 0.03 | E71: 0.03 | F71: 0.025 | G71: 0.025
B72: Downside 1 | C72: 0.01 | D72: 0.005 | E72: 0.005 | F72: 0.005 | G72: 0.005
B73: Downside 2 | C73: -0.08 | D73: -0.01 | E73: 0.005 | F73: 0.01 | G73: 0.015
B75: COGS % of Revenue
B76: Base | C76: 0.545 | D76: 0.546 | E76: 0.548 | F76: 0.549 | G76: 0.5497
B77: Upside | C77: 0.544 | D77: 0.542 | E77: 0.54 | F77: 0.538 | G77: 0.5378
B78: Management | C78: 0.545 | D78: 0.546 | E78: 0.548 | F78: 0.549 | G78: 0.5497
B79: Downside 1 | C79: 0.547 | D79: 0.554 | E79: 0.56 | F79: 0.564 | G79: 0.5649
B80: Downside 2 | C80: 0.573 | D80: 0.578 | E80: 0.576 | F80: 0.573 | G80: 0.57
B82: SGA % of Revenue
B83: Base | C83: 0.37 | D83: 0.37 | E83: 0.37 | F83: 0.37 | G83: 0.37
B84: Upside | C84: 0.366 | D84: 0.366 | E84: 0.366 | F84: 0.366 | G84: 0.366
B85: Management | C85: 0.37 | D85: 0.37 | E85: 0.37 | F85: 0.37 | G85: 0.37
B86: Downside 1 | C86: 0.378 | D86: 0.378 | E86: 0.378 | F86: 0.378 | G86: 0.378
B87: Downside 2 | C87: 0.382 | D87: 0.382 | E87: 0.382 | F87: 0.382 | G87: 0.382

Sheet Reverse DCF
B2: Reverse DCF - キリンホールディングス (2503.T)
B3: What is the current share price already assuming? Every value below is a live formula off the other sheets.
B5: Block 0: Market-implied enterprise value (live)
B6: Current Share Price (JPY) | C6: ='Executive Summary'!C9 -> 2912
B7: Fully Diluted Shares | C7: ='DCF Model'!C15 -> 796891219
B8: Market Capitalisation (JPY mn) | C8: =C6*C7/1000000 -> 2320547.2
B9: Net Debt (JPY mn) | C9: ='DCF Model'!C16 -> 675526
B10: Enterprise Value (JPY mn) | C10: =C8+C9 -> 2996073.2
B11: WACC (w) | C11: ='DCF Model'!C26 -> 0.064427961
B12: Terminal Growth (g) | C12: ='DCF Model'!C13 -> 0.01
B13: Effective Tax Rate (t) | C13: ='DCF Model'!C6 -> 0.25
B14: Starting Operating Profit OP0 (FY2025 actual) | C14: 209677
B15: Cycle-peak Operating Profit (FY2025 actual) | C15: 209677
B16: Terminal-year Revenue, active scenario (JPY mn) | C16: ='DCF Model'!G33 -> 2807174.6
B17: Base-case DCF Enterprise Value, PGM (JPY mn) | C17: ='DCF Model'!C53 -> 2585295.6
B18: Cycle-peak Operating Margin (FY2025 actual) | C18: 0.08616758
B19: Gap: market EV less base-case DCF EV (JPY mn) | C19: =C10-C17 -> 410777.62
B20: Gap per share (JPY) - the part of the price the base case does not explain | C20: =IFERROR(ROUND(C19*1000000/C7,0),"N/A") -> 515
B22: Block A: Required steady-state operating profit, reached IMMEDIATELY (no ramp)
B23: The lowest bar the price can clear: today's EV read as a perpetuity of one steady-state profit, capex = D&A, no NWC build.
B24: Required steady-state NOPAT (JPY mn) | C24: =C10*(C11-C12) -> 163070.16
B25: Required steady-state Operating Profit (JPY mn) | C25: =IFERROR(C24/(1-C13),"N/A") -> 217426.87
B26: ... as a multiple of the FY2025 peak | C26: =IFERROR(C25/C15,"N/A") -> 1.036961
B27: ... as a multiple of FY2025 actual | C27: =IFERROR(C25/C14,"N/A") -> 1.036961
B28: ... implied OPM on terminal-year revenue | C28: =IFERROR(C25/C16,"N/A") -> 0.07745399
B29: ... revenue needed if margins only reach the cycle peak | C29: =IFERROR(C25/C18,"N/A") -> 2523302.6
B32: Block B: Required steady-state operating profit by YEARS-TO-REACH (linear ramp) x WACC
B33: Operating profit ramps linearly from OP0 (C14) to OP* over N years, then grows at g for ever. Column F is the model WACC.
B34: OP* = ( EV/(1-t) - OP0*(A-B) ) / ( B + TVF ). A longer ramp needs a HIGHER steady state, because more years are spent below it.
B36: Years to steady state (N) \ WACC | C36: N | D36: ='DCF Model'!C26-0.02 -> 0.044427961 | E36: ='DCF Model'!C26-0.01 -> 0.054427961 | F36: ='DCF Model'!C26 -> 0.064427961 | G36: ='DCF Model'!C26+0.01 -> 0.074427961 | H36: ='DCF Model'!C26+0.02 -> 0.084427961
B37: B-1 PV weight on the RAMP from OP0 (A - B)
B38: N = 3 years | C38: 3 | D38: =IFERROR((1-(1+D$36)^(-$C38))/D$36-(1+D$36)/(D$36^2*$C38)*(1-($C38+1)/(1+D$36)^$C38+$C38/(1+D$36)^($C38+1)),"N/A") -> 0.94388572 | E38: =IFERROR((1-(1+E$36)^(-$C38))/E$36-(1+E$36)/(E$36^2*$C38)*(1-($C38+1)/(1+E$36)^$C38+$C38/(1+E$36)^($C38+1)),"N/A") -> 0.93206353 | F38: =IFERROR((1-(1+F$36)^(-$C38))/F$36-(1+F$36)/(F$36^2*$C38)*(1-($C38+1)/(1+F$36)^$C38+$C38/(1+F$36)^($C38+1)),"N/A") -> 0.92051689 | G38: =IFERROR((1-(1+G$36)^(-$C38))/G$36-(1+G$36)/(G$36^2*$C38)*(1-($C38+1)/(1+G$36)^$C38+$C38/(1+G$36)^($C38+1)),"N/A") -> 0.90923665 | H38: =IFERROR((1-(1+H$36)^(-$C38))/H$36-(1+H$36)/(H$36^2*$C38)*(1-($C38+1)/(1+H$36)^$C38+$C38/(1+H$36)^($C38+1)),"N/A") -> 0.89821401
B39: N = 5 years | C39: 5 | D39: =IFERROR((1-(1+D$36)^(-$C39))/D$36-(1+D$36)/(D$36^2*$C39)*(1-($C39+1)/(1+D$36)^$C39+$C39/(1+D$36)^($C39+1)),"N/A") -> 1.8351844 | E39: =IFERROR((1-(1+E$36)^(-$C39))/E$36-(1+E$36)/(E$36^2*$C39)*(1-($C39+1)/(1+E$36)^$C39+$C39/(1+E$36)^($C39+1)),"N/A") -> 1.8013559 | F39: =IFERROR((1-(1+F$36)^(-$C39))/F$36-(1+F$36)/(F$36^2*$C39)*(1-($C39+1)/(1+F$36)^$C39+$C39/(1+F$36)^($C39+1)),"N/A") -> 1.7686146 | G39: =IFERROR((1-(1+G$36)^(-$C39))/G$36-(1+G$36)/(G$36^2*$C39)*(1-($C39+1)/(1+G$36)^$C39+$C39/(1+G$36)^($C39+1)),"N/A") -> 1.7369129 | H39: =IFERROR((1-(1+H$36)^(-$C39))/H$36-(1+H$36)/(H$36^2*$C39)*(1-($C39+1)/(1+H$36)^$C39+$C39/(1+H$36)^($C39+1)),"N/A") -> 1.7062058
B40: N = 7 years | C40: 7 | D40: =IFERROR((1-(1+D$36)^(-$C40))/D$36-(1+D$36)/(D$36^2*$C40)*(1-($C40+1)/(1+D$36)^$C40+$C40/(1+D$36)^($C40+1)),"N/A") -> 2.6771874 | E40: =IFERROR((1-(1+E$36)^(-$C40))/E$36-(1+E$36)/(E$36^2*$C40)*(1-($C40+1)/(1+E$36)^$C40+$C40/(1+E$36)^($C40+1)),"N/A") -> 2.6126246 | F40: =IFERROR((1-(1+F$36)^(-$C40))/F$36-(1+F$36)/(F$36^2*$C40)*(1-($C40+1)/(1+F$36)^$C40+$C40/(1+F$36)^($C40+1)),"N/A") -> 2.5506894 | G40: =IFERROR((1-(1+G$36)^(-$C40))/G$36-(1+G$36)/(G$36^2*$C40)*(1-($C40+1)/(1+G$36)^$C40+$C40/(1+G$36)^($C40+1)),"N/A") -> 2.49124 | H40: =IFERROR((1-(1+H$36)^(-$C40))/H$36-(1+H$36)/(H$36^2*$C40)*(1-($C40+1)/(1+H$36)^$C40+$C40/(1+H$36)^($C40+1)),"N/A") -> 2.4341435
B41: N = 10 years | C41: 10 | D41: =IFERROR((1-(1+D$36)^(-$C41))/D$36-(1+D$36)/(D$36^2*$C41)*(1-($C41+1)/(1+D$36)^$C41+$C41/(1+D$36)^($C41+1)),"N/A") -> 3.8544254 | E41: =IFERROR((1-(1+E$36)^(-$C41))/E$36-(1+E$36)/(E$36^2*$C41)*(1-($C41+1)/(1+E$36)^$C41+$C41/(1+E$36)^($C41+1)),"N/A") -> 3.7301847 | F41: =IFERROR((1-(1+F$36)^(-$C41))/F$36-(1+F$36)/(F$36^2*$C41)*(1-($C41+1)/(1+F$36)^$C41+$C41/(1+F$36)^($C41+1)),"N/A") -> 3.612534 | G41: =IFERROR((1-(1+G$36)^(-$C41))/G$36-(1+G$36)/(G$36^2*$C41)*(1-($C41+1)/(1+G$36)^$C41+$C41/(1+G$36)^($C41+1)),"N/A") -> 3.5010196 | H41: =IFERROR((1-(1+H$36)^(-$C41))/H$36-(1+H$36)/(H$36^2*$C41)*(1-($C41+1)/(1+H$36)^$C41+$C41/(1+H$36)^($C41+1)),"N/A") -> 3.3952251
B42: B-2 PV weight on the STEADY STATE OP* (B + terminal factor)
B43: N = 3 years | C43: 3 | D43: =IFERROR((1+D$36)/(D$36^2*$C43)*(1-($C43+1)/(1+D$36)^$C43+$C43/(1+D$36)^($C43+1))+(1+$C$12)/((D$36-$C$12)*(1+D$36)^$C43),"N/A") -> 27.557891 | E43: =IFERROR((1+E$36)/(E$36^2*$C43)*(1-($C43+1)/(1+E$36)^$C43+$C43/(1+E$36)^($C43+1))+(1+$C$12)/((E$36-$C$12)*(1+E$36)^$C43),"N/A") -> 21.160373 | F43: =IFERROR((1+F$36)/(F$36^2*$C43)*(1-($C43+1)/(1+F$36)^$C43+$C43/(1+F$36)^($C43+1))+(1+$C$12)/((F$36-$C$12)*(1+F$36)^$C43),"N/A") -> 17.117624 | G43: =IFERROR((1+G$36)/(G$36^2*$C43)*(1-($C43+1)/(1+G$36)^$C43+$C43/(1+G$36)^($C43+1))+(1+$C$12)/((G$36-$C$12)*(1+G$36)^$C43),"N/A") -> 14.333061 | H43: =IFERROR((1+H$36)/(H$36^2*$C43)*(1-($C43+1)/(1+H$36)^$C43+$C43/(1+H$36)^($C43+1))+(1+$C$12)/((H$36-$C$12)*(1+H$36)^$C43),"N/A") -> 12.299447
B44: N = 5 years | C44: 5 | D44: =IFERROR((1+D$36)/(D$36^2*$C44)*(1-($C44+1)/(1+D$36)^$C44+$C44/(1+D$36)^($C44+1))+(1+$C$12)/((D$36-$C$12)*(1+D$36)^$C44),"N/A") -> 26.167539 | E44: =IFERROR((1+E$36)/(E$36^2*$C44)*(1-($C44+1)/(1+E$36)^$C44+$C44/(1+E$36)^($C44+1))+(1+$C$12)/((E$36-$C$12)*(1+E$36)^$C44),"N/A") -> 19.916999 | F44: =IFERROR((1+F$36)/(F$36^2*$C44)*(1-($C44+1)/(1+F$36)^$C44+$C44/(1+F$36)^($C44+1))+(1+$C$12)/((F$36-$C$12)*(1+F$36)^$C44),"N/A") -> 15.974057 | G44: =IFERROR((1+G$36)/(G$36^2*$C44)*(1-($C44+1)/(1+G$36)^$C44+$C44/(1+G$36)^($C44+1))+(1+$C$12)/((G$36-$C$12)*(1+G$36)^$C44),"N/A") -> 13.263775 | H44: =IFERROR((1+H$36)/(H$36^2*$C44)*(1-($C44+1)/(1+H$36)^$C44+$C44/(1+H$36)^($C44+1))+(1+$C$12)/((H$36-$C$12)*(1+H$36)^$C44),"N/A") -> 11.288945
B45: N = 7 years | C45: 7 | D45: =IFERROR((1+D$36)/(D$36^2*$C45)*(1-($C45+1)/(1+D$36)^$C45+$C45/(1+D$36)^($C45+1))+(1+$C$12)/((D$36-$C$12)*(1+D$36)^$C45),"N/A") -> 24.868038 | E45: =IFERROR((1+E$36)/(E$36^2*$C45)*(1-($C45+1)/(1+E$36)^$C45+$C45/(1+E$36)^($C45+1))+(1+$C$12)/((E$36-$C$12)*(1+E$36)^$C45),"N/A") -> 18.76927 | F45: =IFERROR((1+F$36)/(F$36^2*$C45)*(1-($C45+1)/(1+F$36)^$C45+$C45/(1+F$36)^($C45+1))+(1+$C$12)/((F$36-$C$12)*(1+F$36)^$C45),"N/A") -> 14.931198 | G45: =IFERROR((1+G$36)/(G$36^2*$C45)*(1-($C45+1)/(1+G$36)^$C45+$C45/(1+G$36)^($C45+1))+(1+$C$12)/((G$36-$C$12)*(1+G$36)^$C45),"N/A") -> 12.300153 | H45: =IFERROR((1+H$36)/(H$36^2*$C45)*(1-($C45+1)/(1+H$36)^$C45+$C45/(1+H$36)^($C45+1))+(1+$C$12)/((H$36-$C$12)*(1+H$36)^$C45),"N/A") -> 10.388802
B46: N = 10 years | C46: 10 | D46: =IFERROR((1+D$36)/(D$36^2*$C46)*(1-($C46+1)/(1+D$36)^$C46+$C46/(1+D$36)^($C46+1))+(1+$C$12)/((D$36-$C$12)*(1+D$36)^$C46),"N/A") -> 23.074978 | E46: =IFERROR((1+E$36)/(E$36^2*$C46)*(1-($C46+1)/(1+E$36)^$C46+$C46/(1+E$36)^($C46+1))+(1+$C$12)/((E$36-$C$12)*(1+E$36)^$C46),"N/A") -> 17.209391 | F46: =IFERROR((1+F$36)/(F$36^2*$C46)*(1-($C46+1)/(1+F$36)^$C46+$C46/(1+F$36)^($C46+1))+(1+$C$12)/((F$36-$C$12)*(1+F$36)^$C46),"N/A") -> 13.53444 | G46: =IFERROR((1+G$36)/(G$36^2*$C46)*(1-($C46+1)/(1+G$36)^$C46+$C46/(1+G$36)^($C46+1))+(1+$C$12)/((G$36-$C$12)*(1+G$36)^$C46),"N/A") -> 11.027725 | H46: =IFERROR((1+H$36)/(H$36^2*$C46)*(1-($C46+1)/(1+H$36)^$C46+$C46/(1+H$36)^($C46+1))+(1+$C$12)/((H$36-$C$12)*(1+H$36)^$C46),"N/A") -> 9.2165029
B47: B-3 REQUIRED steady-state Operating Profit (JPY mn)
B48: N = 3 years | C48: 3 | D48: =IFERROR(($C$10/(1-$C$13)-$C$14*D38)/D43,"N/A") -> 137777.35 | E48: =IFERROR(($C$10/(1-$C$13)-$C$14*E38)/E43,"N/A") -> 179549.39 | F48: =IFERROR(($C$10/(1-$C$13)-$C$14*F38)/F43,"N/A") -> 222095.84 | G48: =IFERROR(($C$10/(1-$C$13)-$C$14*G38)/G43,"N/A") -> 265408.64 | H48: =IFERROR(($C$10/(1-$C$13)-$C$14*H38)/H43,"N/A") -> 309479.71
B49: N = 5 years | C49: 5 | D49: =IFERROR(($C$10/(1-$C$13)-$C$14*D39)/D44,"N/A") -> 137955.97 | E49: =IFERROR(($C$10/(1-$C$13)-$C$14*E39)/E44,"N/A") -> 181606.75 | F49: =IFERROR(($C$10/(1-$C$13)-$C$14*F39)/F44,"N/A") -> 226863.26 | G49: =IFERROR(($C$10/(1-$C$13)-$C$14*G39)/G44,"N/A") -> 273720.99 | H49: =IFERROR(($C$10/(1-$C$13)-$C$14*H39)/H44,"N/A") -> 322174.68
B50: N = 7 years | C50: 7 | D50: =IFERROR(($C$10/(1-$C$13)-$C$14*D40)/D45,"N/A") -> 138065.56 | E50: =IFERROR(($C$10/(1-$C$13)-$C$14*E40)/E45,"N/A") -> 183648.96 | F50: =IFERROR(($C$10/(1-$C$13)-$C$14*F40)/F45,"N/A") -> 231725.77 | G50: =IFERROR(($C$10/(1-$C$13)-$C$14*G40)/G45,"N/A") -> 282306.14 | H50: =IFERROR(($C$10/(1-$C$13)-$C$14*H40)/H45,"N/A") -> 335397.71
B51: N = 10 years | C51: 10 | D51: =IFERROR(($C$10/(1-$C$13)-$C$14*D41)/D46,"N/A") -> 138096.77 | E51: =IFERROR(($C$10/(1-$C$13)-$C$14*E41)/E46,"N/A") -> 186678.91 | F51: =IFERROR(($C$10/(1-$C$13)-$C$14*F41)/F46,"N/A") -> 239189.73 | G51: =IFERROR(($C$10/(1-$C$13)-$C$14*G41)/G46,"N/A") -> 295680.3 | H51: =IFERROR(($C$10/(1-$C$13)-$C$14*H41)/H46,"N/A") -> 356194.07
B52: B-4 ... as a multiple of the FY2025 peak operating profit
B53: N = 3 years | C53: 3 | D53: =IFERROR(D48/$C$15,"N/A") -> 0.65709329 | E53: =IFERROR(E48/$C$15,"N/A") -> 0.85631417 | F53: =IFERROR(F48/$C$15,"N/A") -> 1.0592284 | G53: =IFERROR(G48/$C$15,"N/A") -> 1.2657976 | H53: =IFERROR(H48/$C$15,"N/A") -> 1.4759831
B54: N = 5 years | C54: 5 | D54: =IFERROR(D49/$C$15,"N/A") -> 0.65794518 | E54: =IFERROR(E49/$C$15,"N/A") -> 0.86612623 | F54: =IFERROR(F49/$C$15,"N/A") -> 1.0819654 | G54: =IFERROR(G49/$C$15,"N/A") -> 1.3054412 | H54: =IFERROR(H49/$C$15,"N/A") -> 1.5365284
B55: N = 7 years | C55: 7 | D55: =IFERROR(D50/$C$15,"N/A") -> 0.65846785 | E55: =IFERROR(E50/$C$15,"N/A") -> 0.87586603 | F55: =IFERROR(F50/$C$15,"N/A") -> 1.1051559 | G55: =IFERROR(G50/$C$15,"N/A") -> 1.3463858 | H55: =IFERROR(H50/$C$15,"N/A") -> 1.5995923
B56: N = 10 years | C56: 10 | D56: =IFERROR(D51/$C$15,"N/A") -> 0.6586167 | E56: =IFERROR(E51/$C$15,"N/A") -> 0.8903166 | F56: =IFERROR(F51/$C$15,"N/A") -> 1.1407533 | G56: =IFERROR(G51/$C$15,"N/A") -> 1.4101704 | H56: =IFERROR(H51/$C$15,"N/A") -> 1.6987751
B58: Block C: Decomposing the required profit into revenue x margin (N = 5 years, model WACC)
B59: The revenue the company must run at, for a given steady-state operating margin, to earn the Block B-3 profit.
B60: Required steady-state Operating Profit (N=5, model WACC) | C60: =F49 -> 226863.26
B62: Assumed steady-state OPM | C62: Required Revenue | D62: x base-year revenue
B63: 0.0431 | C63: =IFERROR($C$60/B63,"N/A") -> 5263648.6 | D63: =IFERROR(C63/'DCF Model'!C17,"N/A") -> 2.1631169
B64: 0.0646 | C64: =IFERROR($C$60/B64,"N/A") -> 3511815.1 | D64: =IFERROR(C64/'DCF Model'!C17,"N/A") -> 1.4431941
B65: cycle-peak OPM (FY2025) | C65: =IFERROR($C$60/$C$18,"N/A") -> 2632814.5 | D65: =IFERROR(C65/'DCF Model'!C17,"N/A") -> 1.0819654
B66: 0.1077 | C66: =IFERROR($C$60/B66,"N/A") -> 2106436.9 | D66: =IFERROR(C66/'DCF Model'!C17,"N/A") -> 0.86564845
B67: 0.1293 | C67: =IFERROR($C$60/B67,"N/A") -> 1754549.5 | D67: =IFERROR(C67/'DCF Model'!C17,"N/A") -> 0.72103897
B69: Block D: The same question expressed as multiples
B70: Current EV / latest-FY EBITDA (actual) | C70: =IFERROR(C10/'Comps Analysis'!G5,"N/A") -> 9.617379
B71: Current EV / latest-FY Revenue (actual) | C71: =IFERROR(C10/'Comps Analysis'!F5,"N/A") -> 1.231248
B72: EV / EBITDA if the Block A profit were already earned | C72: =IFERROR(C10/(C25+'DCF Model'!G42),"N/A") -> 9.0101766
B73: EV / EBITDA if the Block B-3 (N=5) profit were already earned | C73: =IFERROR(C10/(C60+'DCF Model'!G42),"N/A") -> 8.761539
B74: Peer median EV / EBITDA (statistics rows) | C74: =IFERROR('Comps Analysis'!D16,"N/A") -> 11.133463
B75: Rows 3-4 answer: what multiple would today's EV be paying IF the company already earned the profit the price requires?
B77: Block F: The one-line answer
B78: ="At "&TEXT(C6,"#,##0")&" yen the market is paying for a steady-state operating profit of "&TEXT(F49,"#,##0")&" mn JPY - "&TEXT(F54,"0.00")&"x the FY2025 cycle peak of "&TEXT(C15,"#,##0")&" mn - reached in 5 years and sustained for ever, against "&TEXT(C14,"#,##0")&" mn actually earned in FY2025." -> At 2,912 yen the market is paying for a steady-state operating profit of 226,863 mn JPY - 1.08x the FY2025 cycle peak of 209,677 mn - reached in 5 years and sustained for ever, against 209,677 mn actually earned in FY2025.
B79: ="Even with no ramp at all (Block A) the price needs "&TEXT(C25,"#,##0")&" mn, or "&TEXT(C26,"0.00")&"x the peak. The base case supports an EV of only "&TEXT(C17,"#,##0")&" mn, leaving "&TEXT(C20,"#,##0")&" yen per share of the current price unexplained by mid-cycle economics." -> Even with no ramp at all (Block A) the price needs 217,427 mn, or 1.04x the peak. The base case supports an EV of only 2,585,296 mn, leaving 515 yen per share of the current price unexplained by mid-cycle economics.

Sheet NWC Schedule
B2: NWC Schedule - キリンホールディングス
B4: Working Capital Drivers (Days) | C4: Base Year | D4: FY2026(E) | E4: FY2027(E) | F4: FY2028(E) | G4: FY2029(E) | H4: FY2030(E)
B5: DSO (Days Sales Outstanding) | C5: =C12/C9*365 -> 80.35597 | D5: =CHOOSE('DCF Model'!$D$27,D25,D26,D27,D28,D29) -> 78 | E5: =CHOOSE('DCF Model'!$D$27,E25,E26,E27,E28,E29) -> 78 | F5: =CHOOSE('DCF Model'!$D$27,F25,F26,F27,F28,F29) -> 78 | G5: =CHOOSE('DCF Model'!$D$27,G25,G26,G27,G28,G29) -> 78 | H5: =CHOOSE('DCF Model'!$D$27,H25,H26,H27,H28,H29) -> 78
B6: DIH (Days Inventory Held) | C6: =C13/C10*365 -> 99.715037 | D6: =CHOOSE('DCF Model'!$D$27,D32,D33,D34,D35,D36) -> 101 | E6: =CHOOSE('DCF Model'!$D$27,E32,E33,E34,E35,E36) -> 101 | F6: =CHOOSE('DCF Model'!$D$27,F32,F33,F34,F35,F36) -> 101 | G6: =CHOOSE('DCF Model'!$D$27,G32,G33,G34,G35,G36) -> 101 | H6: =CHOOSE('DCF Model'!$D$27,H32,H33,H34,H35,H36) -> 101
B7: DPO (Days Payable Outstanding) | C7: =C15/C10*365 -> 109.17918 | D7: =CHOOSE('DCF Model'!$D$27,D39,D40,D41,D42,D43) -> 100 | E7: =CHOOSE('DCF Model'!$D$27,E39,E40,E41,E42,E43) -> 100 | F7: =CHOOSE('DCF Model'!$D$27,F39,F40,F41,F42,F43) -> 100 | G7: =CHOOSE('DCF Model'!$D$27,G39,G40,G41,G42,G43) -> 100 | H7: =CHOOSE('DCF Model'!$D$27,H39,H40,H41,H42,H43) -> 100
B8: P&L Reference (JPY mn)
B9: Revenue | C9: 2433363 | D9: ='DCF Model'!C33 -> 2518530.7 | E9: ='DCF Model'!D33 -> 2594086.6 | F9: ='DCF Model'!E33 -> 2671909.2 | G9: ='DCF Model'!F33 -> 2738707 | H9: ='DCF Model'!G33 -> 2807174.6
B10: COGS | C10: 1275360 | D10: ='DCF Model'!C34 -> 1372599.2 | E10: ='DCF Model'!D34 -> 1416371.3 | F10: ='DCF Model'!E34 -> 1464206.3 | G10: ='DCF Model'!F34 -> 1503550.1 | H10: ='DCF Model'!G34 -> 1543103.9
B11: Working Capital Items (JPY mn)
B12: Accounts Receivable | C12: 535713 | D12: =D9*D5/365 -> 538206.56 | E12: =E9*E5/365 -> 554352.76 | F12: =F9*F5/365 -> 570983.34 | G12: =G9*G5/365 -> 585257.92 | H12: =H9*H5/365 -> 599889.37
B13: Inventory | C13: 348418 | D13: =D10*D6/365 -> 379815.13 | E13: =E10*E6/365 -> 391927.4 | F13: =F10*F6/365 -> 405163.92 | G13: =G10*G6/365 -> 416050.85 | H13: =H10*H6/365 -> 426995.87
B14: Current Assets (AR + Inv) | C14: =C12+C13 -> 884131 | D14: =D12+D13 -> 918021.69 | E14: =E12+E13 -> 946280.16 | F14: =F12+F13 -> 976147.26 | G14: =G12+G13 -> 1001308.8 | H14: =H12+H13 -> 1026885.2
B15: Accounts Payable | C15: 381487 | D15: =D10*D7/365 -> 376054.58 | E15: =E10*E7/365 -> 388046.93 | F15: =F10*F7/365 -> 401152.4 | G15: =G10*G7/365 -> 411931.54 | H15: =H10*H7/365 -> 422768.19
B16: Current Liabilities (AP) | C16: =C15 -> 381487 | D16: =D15 -> 376054.58 | E16: =E15 -> 388046.93 | F16: =F15 -> 401152.4 | G16: =G15 -> 411931.54 | H16: =H15 -> 422768.19
B17: Net Working Capital (JPY mn)
B18: Net Working Capital | C18: =C14-C16 -> 502644 | D18: =D14-D16 -> 541967.11 | E18: =E14-E16 -> 558233.23 | F18: =F14-F16 -> 574994.87 | G18: =G14-G16 -> 589377.24 | H18: =H14-H16 -> 604117.05
B19: Change in NWC | C19: n/a | D19: =D18-C18 -> 39323.107 | E19: =E18-D18 -> 16266.12 | F19: =F18-E18 -> 16761.637 | G19: =G18-F18 -> 14382.375 | H19: =H18-G18 -> 14739.815
B22: Scenario Input Matrix (Working Capital Days)
D23: FY2026(E) | E23: FY2027(E) | F23: FY2028(E) | G23: FY2029(E) | H23: FY2030(E)
B24: DSO (Days)
B25: Base | D25: 78 | E25: 78 | F25: 78 | G25: 78 | H25: 78
B26: Upside | D26: 75 | E26: 75 | F26: 75 | G26: 75 | H26: 75
B27: Management | D27: 78 | E27: 78 | F27: 78 | G27: 78 | H27: 78
B28: Downside 1 | D28: 82 | E28: 82 | F28: 82 | G28: 82 | H28: 82
B29: Downside 2 | D29: 86 | E29: 86 | F29: 86 | G29: 86 | H29: 86
B31: DIH (Days)
B32: Base | D32: 101 | E32: 101 | F32: 101 | G32: 101 | H32: 101
B33: Upside | D33: 96 | E33: 96 | F33: 96 | G33: 96 | H33: 96
B34: Management | D34: 101 | E34: 101 | F34: 101 | G34: 101 | H34: 101
B35: Downside 1 | D35: 107 | E35: 107 | F35: 107 | G35: 107 | H35: 107
B36: Downside 2 | D36: 114 | E36: 114 | F36: 114 | G36: 114 | H36: 114
B38: DPO (Days)
B39: Base | D39: 100 | E39: 100 | F39: 100 | G39: 100 | H39: 100
B40: Upside | D40: 103 | E40: 103 | F40: 103 | G40: 103 | H40: 103
B41: Management | D41: 100 | E41: 100 | F41: 100 | G41: 100 | H41: 100
B42: Downside 1 | D42: 96 | E42: 96 | F42: 96 | G42: 96 | H42: 96
B43: Downside 2 | D43: 92 | E43: 92 | F43: 92 | G43: 92 | H43: 92

Sheet Comps Analysis
B2: Comparable Company Analysis
B3: Peer prices as of 2026-09-05 (Mkt Cap / EV of peer rows are static CSV values; the subject row is live-linked to Executive Summary)
B4: Company | C4: Ticker | D4: Mkt Cap (JPY mn) | E4: EV (JPY mn) | F4: Revenue (JPY mn) | G4: EBITDA (JPY mn) | H4: Op Income (JPY mn) | I4: Net Income (JPY mn) | J4: EV/EBITDA | K4: EV/Revenue | L4: PER | M4: PBR | N4: Op Margin | O4: ROE | P4: Book Value (JPY mn) | Q4: Note
B5: Kirin Holdings Company, Limited | C5: 2503.T | D5: ='Executive Summary'!C9*C23/1000000 -> 2320547.2 | E5: =D5+C24 -> 2996073.2 | F5: 2433363 | G5: 311527 | H5: 209677 | I5: 147542 | J5: =IFERROR(E5/G5,"") -> 9.617379 | K5: =IFERROR(E5/F5,"") -> 1.231248 | L5: =IFERROR(D5/I5,"") -> 15.728045 | M5: =IFERROR(D5/P5,"") -> 1.8030796 | N5: =IFERROR(H5/F5,"") -> 0.08616758 | O5: =IFERROR(I5/P5,"") -> 0.11464105 | P5: 1286991
B6: Asahi Group Holdings, Ltd. | C6: 2502.T | D6: 2397303 | E6: 3885100 | F6: 2894676 | G6: 348957 | H6: 185870 | I6: 121574 | J6: =IFERROR(E6/G6,"") -> 11.133463 | K6: =IFERROR(E6/F6,"") -> 1.3421537 | L6: =IFERROR(D6/I6,"") -> 19.718879 | M6: =IFERROR(D6/P6,"") -> 0.79828887 | N6: =IFERROR(H6/F6,"") -> 0.064210986 | O6: =IFERROR(I6/P6,"") -> 0.040483481 | P6: 3003052
B7: Ajinomoto Co., Inc. | C7: 2802.T | D7: 4932560 | E7: 5247222 | F7: 1583719 | G7: 277762 | H7: 191301 | I7: 134675 | J7: =IFERROR(E7/G7,"") -> 18.891072 | K7: =IFERROR(E7/F7,"") -> 3.3132279 | L7: =IFERROR(D7/I7,"") -> 36.625654 | M7: =IFERROR(D7/P7,"") -> 6.3991157 | N7: =IFERROR(H7/F7,"") -> 0.12079226 | O7: =IFERROR(I7/P7,"") -> 0.17471676 | P7: 770819
B8: Kikkoman Corporation | C8: 2801.T | D8: 1655551 | E8: 1605210 | F8: 745539 | G8: 102686 | H8: 75940 | I8: 61615 | J8: =IFERROR(E8/G8,"") -> 15.632219 | K8: =IFERROR(E8/F8,"") -> 2.1530866 | L8: =IFERROR(D8/I8,"") -> 26.869285 | M8: =IFERROR(D8/P8,"") -> 2.9514711 | N8: =IFERROR(H8/F8,"") -> 0.10185919 | O8: =IFERROR(I8/P8,"") -> 0.10984554 | P8: 560924
B9: Meiji Holdings Co., Ltd. | C9: 2269.T | D9: 1195303 | E9: 1238638 | F9: 1173688 | G9: 148261 | H9: 93307 | I9: 35076 | J9: =IFERROR(E9/G9,"") -> 8.3544425 | K9: =IFERROR(E9/F9,"") -> 1.0553384 | L9: =IFERROR(D9/I9,"") -> 34.077517 | M9: =IFERROR(D9/P9,"") -> 1.5471476 | N9: =IFERROR(H9/F9,"") -> 0.079498981 | O9: =IFERROR(I9/P9,"") -> 0.04540083 | P9: 772585
B10: Nissin Foods Holdings Co.,Ltd. | C10: 2897.T | D10: 854146 | E10: 931346 | F10: 788131 | G10: 85277 | H10: 49380 | I10: 45380 | J10: =IFERROR(E10/G10,"") -> 10.921421 | K10: =IFERROR(E10/F10,"") -> 1.1817147 | L10: =IFERROR(D10/I10,"") -> 18.82208 | M10: =IFERROR(D10/P10,"") -> 1.6515832 | N10: =IFERROR(H10/F10,"") -> 0.062654559 | O10: =IFERROR(I10/P10,"") -> 0.087747115 | P10: 517168
B14: Statistics
B15: 25th Percentile | D15: =PERCENTILE(J6:J10,0.25) -> 10.921421 | E15: =PERCENTILE(K6:K10,0.25) -> 1.1817147 | F15: =PERCENTILE(L6:L10,0.25) -> 19.718879 | G15: =PERCENTILE(M6:M10,0.25) -> 1.5471476 | H15: =PERCENTILE(N6:N10,0.25) -> 0.064210986 | I15: =PERCENTILE(O6:O10,0.25) -> 0.04540083
B16: Median (50th) | D16: =MEDIAN(J6:J10) -> 11.133463 | E16: =MEDIAN(K6:K10) -> 1.3421537 | F16: =MEDIAN(L6:L10) -> 26.869285 | G16: =MEDIAN(M6:M10) -> 1.6515832 | H16: =MEDIAN(N6:N10) -> 0.079498981 | I16: =MEDIAN(O6:O10) -> 0.087747115
B17: 75th Percentile | D17: =PERCENTILE(J6:J10,0.75) -> 15.632219 | E17: =PERCENTILE(K6:K10,0.75) -> 2.1530866 | F17: =PERCENTILE(L6:L10,0.75) -> 34.077517 | G17: =PERCENTILE(M6:M10,0.75) -> 2.9514711 | H17: =PERCENTILE(N6:N10,0.75) -> 0.10185919 | I17: =PERCENTILE(O6:O10,0.75) -> 0.10984554
B19: Implied Valuation for キリンホールディングス
B20: キリンホールディングス Financials
B21: EBITDA (JPY mn) | C21: 311527
B22: Net Income (JPY mn) | C22: 147542
B23: Shares Outstanding | C23: 796891219
B24: Net Debt (JPY mn) | C24: 675526
B26: Implied Share Price (Median Multiples)
B27: Via EV/EBITDA (Median) | C27: =ROUND((C21*D16-C24)*1000000/C23,0) -> 3505
B28: Via PER (Median) | C28: =ROUND(C22*F16*1000000/C23,0) -> 4975

Sheet Sensitivity Analysis
B2: Sensitivity Analysis
B3: Current WACC: | C3: ='DCF Model'!C26 -> 0.064427961 | E3: Terminal g: | F3: ='DCF Model'!C13 -> 0.01 | H3: Exit Multiple: | I3: ='DCF Model'!C14 -> 11.1
B5: Table 1: WACC vs Terminal Growth Rate (PGM - Implied Share Price, JPY)
B6: WACC \ Terminal g | C6: =$F$3-0.0075 -> 0.0025 | D6: =$F$3-0.005 -> 0.005 | E6: =$F$3-0.0025 -> 0.0075 | F6: =$F$3 -> 0.01 | G6: =$F$3+0.0025 -> 0.0125 | H6: =$F$3+0.005 -> 0.015 | I6: =$F$3+0.0075 -> 0.0175
B7: =$C$3-0.015 -> 0.049427961 | C7: =IFERROR(ROUND(('DCF Model'!C45/(1+$B7)^('DCF Model'!C19+0)+'DCF Model'!D45/(1+$B7)^('DCF Model'!C19+1)+'DCF Model'!E45/(1+$B7)^('DCF Model'!C19+2)+'DCF Model'!F45/(1+$B7)^('DCF Model'!C19+3)+'DCF Model'!G45/(1+$B7)^('DCF Model'!C19+4)+'DCF Model'!G45*(1+C$6)/($B7-C$6)/(1+$B7)^('DCF Model'!C19+4)-'DCF Model'!C16)*1000000/'DCF Model'!C15,0),"") -> 3014 | D7: =IFERROR(ROUND(('DCF Model'!C45/(1+$B7)^('DCF Model'!C19+0)+'DCF Model'!D45/(1+$B7)^('DCF Model'!C19+1)+'DCF Model'!E45/(1+$B7)^('DCF Model'!C19+2)+'DCF Model'!F45/(1+$B7)^('DCF Model'!C19+3)+'DCF Model'!G45/(1+$B7)^('DCF Model'!C19+4)+'DCF Model'!G45*(1+D$6)/($B7-D$6)/(1+$B7)^('DCF Model'!C19+4)-'DCF Model'!C16)*1000000/'DCF Model'!C15,0),"") -> 3203 | E7: =IFERROR(ROUND(('DCF Model'!C45/(1+$B7)^('DCF Model'!C19+0)+'DCF Model'!D45/(1+$B7)^('DCF Model'!C19+1)+'DCF Model'!E45/(1+$B7)^('DCF Model'!C19+2)+'DCF Model'!F45/(1+$B7)^('DCF Model'!C19+3)+'DCF Model'!G45/(1+$B7)^('DCF Model'!C19+4)+'DCF Model'!G45*(1+E$6)/($B7-E$6)/(1+$B7)^('DCF Model'!C19+4)-'DCF Model'!C16)*1000000/'DCF Model'!C15,0),"") -> 3414 | F7: =IFERROR(ROUND(('DCF Model'!C45/(1+$B7)^('DCF Model'!C19+0)+'DCF Model'!D45/(1+$B7)^('DCF Model'!C19+1)+'DCF Model'!E45/(1+$B7)^('DCF Model'!C19+2)+'DCF Model'!F45/(1+$B7)^('DCF Model'!C19+3)+'DCF Model'!G45/(1+$B7)^('DCF Model'!C19+4)+'DCF Model'!G45*(1+F$6)/($B7-F$6)/(1+$B7)^('DCF Model'!C19+4)-'DCF Model'!C16)*1000000/'DCF Model'!C15,0),"") -> 3652 | G7: =IFERROR(ROUND(('DCF Model'!C45/(1+$B7)^('DCF Model'!C19+0)+'DCF Model'!D45/(1+$B7)^('DCF Model'!C19+1)+'DCF Model'!E45/(1+$B7)^('DCF Model'!C19+2)+'DCF Model'!F45/(1+$B7)^('DCF Model'!C19+3)+'DCF Model'!G45/(1+$B7)^('DCF Model'!C19+4)+'DCF Model'!G45*(1+G$6)/($B7-G$6)/(1+$B7)^('DCF Model'!C19+4)-'DCF Model'!C16)*1000000/'DCF Model'!C15,0),"") -> 3922 | H7: =IFERROR(ROUND(('DCF Model'!C45/(1+$B7)^('DCF Model'!C19+0)+'DCF Model'!D45/(1+$B7)^('DCF Model'!C19+1)+'DCF Model'!E45/(1+$B7)^('DCF Model'!C19+2)+'DCF Model'!F45/(1+$B7)^('DCF Model'!C19+3)+'DCF Model'!G45/(1+$B7)^('DCF Model'!C19+4)+'DCF Model'!G45*(1+H$6)/($B7-H$6)/(1+$B7)^('DCF Model'!C19+4)-'DCF Model'!C16)*1000000/'DCF Model'!C15,0),"") -> 4231 | I7: =IFERROR(ROUND(('DCF Model'!C45/(1+$B7)^('DCF Model'!C19+0)+'DCF Model'!D45/(1+$B7)^('DCF Model'!C19+1)+'DCF Model'!E45/(1+$B7)^('DCF Model'!C19+2)+'DCF Model'!F45/(1+$B7)^('DCF Model'!C19+3)+'DCF Model'!G45/(1+$B7)^('DCF Model'!C19+4)+'DCF Model'!G45*(1+I$6)/($B7-I$6)/(1+$B7)^('DCF Model'!C19+4)-'DCF Model'!C16)*1000000/'DCF Model'!C15,0),"") -> 4589
B8: =$C$3-0.01 -> 0.054427961 | C8: =IFERROR(ROUND(('DCF Model'!C45/(1+$B8)^('DCF Model'!C19+0)+'DCF Model'!D45/(1+$B8)^('DCF Model'!C19+1)+'DCF Model'!E45/(1+$B8)^('DCF Model'!C19+2)+'DCF Model'!F45/(1+$B8)^('DCF Model'!C19+3)+'DCF Model'!G45/(1+$B8)^('DCF Model'!C19+4)+'DCF Model'!G45*(1+C$6)/($B8-C$6)/(1+$B8)^('DCF Model'!C19+4)-'DCF Model'!C16)*1000000/'DCF Model'!C15,0),"") -> 2636 | D8: =IFERROR(ROUND(('DCF Model'!C45/(1+$B8)^('DCF Model'!C19+0)+'DCF Model'!D45/(1+$B8)^('DCF Model'!C19+1)+'DCF Model'!E45/(1+$B8)^('DCF Model'!C19+2)+'DCF Model'!F45/(1+$B8)^('DCF Model'!C19+3)+'DCF Model'!G45/(1+$B8)^('DCF Model'!C19+4)+'DCF Model'!G45*(1+D$6)/($B8-D$6)/(1+$B8)^('DCF Model'!C19+4)-'DCF Model'!C16)*1000000/'DCF Model'!C15,0),"") -> 2787 | E8: =IFERROR(ROUND(('DCF Model'!C45/(1+$B8)^('DCF Model'!C19+0)+'DCF Model'!D45/(1+$B8)^('DCF Model'!C19+1)+'DCF Model'!E45/(1+$B8)^('DCF Model'!C19+2)+'DCF Model'!F45/(1+$B8)^('DCF Model'!C19+3)+'DCF Model'!G45/(1+$B8)^('DCF Model'!C19+4)+'DCF Model'!G45*(1+E$6)/($B8-E$6)/(1+$B8)^('DCF Model'!C19+4)-'DCF Model'!C16)*1000000/'DCF Model'!C15,0),"") -> 2953 | F8: =IFERROR(ROUND(('DCF Model'!C45/(1+$B8)^('DCF Model'!C19+0)+'DCF Model'!D45/(1+$B8)^('DCF Model'!C19+1)+'DCF Model'!E45/(1+$B8)^('DCF Model'!C19+2)+'DCF Model'!F45/(1+$B8)^('DCF Model'!C19+3)+'DCF Model'!G45/(1+$B8)^('DCF Model'!C19+4)+'DCF Model'!G45*(1+F$6)/($B8-F$6)/(1+$B8)^('DCF Model'!C19+4)-'DCF Model'!C16)*1000000/'DCF Model'!C15,0),"") -> 3139 | G8: =IFERROR(ROUND(('DCF Model'!C45/(1+$B8)^('DCF Model'!C19+0)+'DCF Model'!D45/(1+$B8)^('DCF Model'!C19+1)+'DCF Model'!E45/(1+$B8)^('DCF Model'!C19+2)+'DCF Model'!F45/(1+$B8)^('DCF Model'!C19+3)+'DCF Model'!G45/(1+$B8)^('DCF Model'!C19+4)+'DCF Model'!G45*(1+G$6)/($B8-G$6)/(1+$B8)^('DCF Model'!C19+4)-'DCF Model'!C16)*1000000/'DCF Model'!C15,0),"") -> 3347 | H8: =IFERROR(ROUND(('DCF Model'!C45/(1+$B8)^('DCF Model'!C19+0)+'DCF Model'!D45/(1+$B8)^('DCF Model'!C19+1)+'DCF Model'!E45/(1+$B8)^('DCF Model'!C19+2)+'DCF Model'!F45/(1+$B8)^('DCF Model'!C19+3)+'DCF Model'!G45/(1+$B8)^('DCF Model'!C19+4)+'DCF Model'!G45*(1+H$6)/($B8-H$6)/(1+$B8)^('DCF Model'!C19+4)-'DCF Model'!C16)*1000000/'DCF Model'!C15,0),"") -> 3580 | I8: =IFERROR(ROUND(('DCF Model'!C45/(1+$B8)^('DCF Model'!C19+0)+'DCF Model'!D45/(1+$B8)^('DCF Model'!C19+1)+'DCF Model'!E45/(1+$B8)^('DCF Model'!C19+2)+'DCF Model'!F45/(1+$B8)^('DCF Model'!C19+3)+'DCF Model'!G45/(1+$B8)^('DCF Model'!C19+4)+'DCF Model'!G45*(1+I$6)/($B8-I$6)/(1+$B8)^('DCF Model'!C19+4)-'DCF Model'!C16)*1000000/'DCF Model'!C15,0),"") -> 3846
B9: =$C$3-0.005 -> 0.059427961 | C9: =IFERROR(ROUND(('DCF Model'!C45/(1+$B9)^('DCF Model'!C19+0)+'DCF Model'!D45/(1+$B9)^('DCF Model'!C19+1)+'DCF Model'!E45/(1+$B9)^('DCF Model'!C19+2)+'DCF Model'!F45/(1+$B9)^('DCF Model'!C19+3)+'DCF Model'!G45/(1+$B9)^('DCF Model'!C19+4)+'DCF Model'!G45*(1+C$6)/($B9-C$6)/(1+$B9)^('DCF Model'!C19+4)-'DCF Model'!C16)*1000000/'DCF Model'!C15,0),"") -> 2324 | D9: =IFERROR(ROUND(('DCF Model'!C45/(1+$B9)^('DCF Model'!C19+0)+'DCF Model'!D45/(1+$B9)^('DCF Model'!C19+1)+'DCF Model'!E45/(1+$B9)^('DCF Model'!C19+2)+'DCF Model'!F45/(1+$B9)^('DCF Model'!C19+3)+'DCF Model'!G45/(1+$B9)^('DCF Model'!C19+4)+'DCF Model'!G45*(1+D$6)/($B9-D$6)/(1+$B9)^('DCF Model'!C19+4)-'DCF Model'!C16)*1000000/'DCF Model'!C15,0),"") -> 2447 | E9: =IFERROR(ROUND(('DCF Model'!C45/(1+$B9)^('DCF Model'!C19+0)+'DCF Model'!D45/(1+$B9)^('DCF Model'!C19+1)+'DCF Model'!E45/(1+$B9)^('DCF Model'!C19+2)+'DCF Model'!F45/(1+$B9)^('DCF Model'!C19+3)+'DCF Model'!G45/(1+$B9)^('DCF Model'!C19+4)+'DCF Model'!G45*(1+E$6)/($B9-E$6)/(1+$B9)^('DCF Model'!C19+4)-'DCF Model'!C16)*1000000/'DCF Model'!C15,0),"") -> 2582 | F9: =IFERROR(ROUND(('DCF Model'!C45/(1+$B9)^('DCF Model'!C19+0)+'DCF Model'!D45/(1+$B9)^('DCF Model'!C19+1)+'DCF Model'!E45/(1+$B9)^('DCF Model'!C19+2)+'DCF Model'!F45/(1+$B9)^('DCF Model'!C19+3)+'DCF Model'!G45/(1+$B9)^('DCF Model'!C19+4)+'DCF Model'!G45*(1+F$6)/($B9-F$6)/(1+$B9)^('DCF Model'!C19+4)-'DCF Model'!C16)*1000000/'DCF Model'!C15,0),"") -> 2730 | G9: =IFERROR(ROUND(('DCF Model'!C45/(1+$B9)^('DCF Model'!C19+0)+'DCF Model'!D45/(1+$B9)^('DCF Model'!C19+1)+'DCF Model'!E45/(1+$B9)^('DCF Model'!C19+2)+'DCF Model'!F45/(1+$B9)^('DCF Model'!C19+3)+'DCF Model'!G45/(1+$B9)^('DCF Model'!C19+4)+'DCF Model'!G45*(1+G$6)/($B9-G$6)/(1+$B9)^('DCF Model'!C19+4)-'DCF Model'!C16)*1000000/'DCF Model'!C15,0),"") -> 2894 | H9: =IFERROR(ROUND(('DCF Model'!C45/(1+$B9)^('DCF Model'!C19+0)+'DCF Model'!D45/(1+$B9)^('DCF Model'!C19+1)+'DCF Model'!E45/(1+$B9)^('DCF Model'!C19+2)+'DCF Model'!F45/(1+$B9)^('DCF Model'!C19+3)+'DCF Model'!G45/(1+$B9)^('DCF Model'!C19+4)+'DCF Model'!G45*(1+H$6)/($B9-H$6)/(1+$B9)^('DCF Model'!C19+4)-'DCF Model'!C16)*1000000/'DCF Model'!C15,0),"") -> 3077 | I9: =IFERROR(ROUND(('DCF Model'!C45/(1+$B9)^('DCF Model'!C19+0)+'DCF Model'!D45/(1+$B9)^('DCF Model'!C19+1)+'DCF Model'!E45/(1+$B9)^('DCF Model'!C19+2)+'DCF Model'!F45/(1+$B9)^('DCF Model'!C19+3)+'DCF Model'!G45/(1+$B9)^('DCF Model'!C19+4)+'DCF Model'!G45*(1+I$6)/($B9-I$6)/(1+$B9)^('DCF Model'!C19+4)-'DCF Model'!C16)*1000000/'DCF Model'!C15,0),"") -> 3281
B10: =$C$3 -> 0.064427961 | C10: =IFERROR(ROUND(('DCF Model'!C45/(1+$B10)^('DCF Model'!C19+0)+'DCF Model'!D45/(1+$B10)^('DCF Model'!C19+1)+'DCF Model'!E45/(1+$B10)^('DCF Model'!C19+2)+'DCF Model'!F45/(1+$B10)^('DCF Model'!C19+3)+'DCF Model'!G45/(1+$B10)^('DCF Model'!C19+4)+'DCF Model'!G45*(1+C$6)/($B10-C$6)/(1+$B10)^('DCF Model'!C19+4)-'DCF Model'!C16)*1000000/'DCF Model'!C15,0),"") -> 2063 | D10: =IFERROR(ROUND(('DCF Model'!C45/(1+$B10)^('DCF Model'!C19+0)+'DCF Model'!D45/(1+$B10)^('DCF Model'!C19+1)+'DCF Model'!E45/(1+$B10)^('DCF Model'!C19+2)+'DCF Model'!F45/(1+$B10)^('DCF Model'!C19+3)+'DCF Model'!G45/(1+$B10)^('DCF Model'!C19+4)+'DCF Model'!G45*(1+D$6)/($B10-D$6)/(1+$B10)^('DCF Model'!C19+4)-'DCF Model'!C16)*1000000/'DCF Model'!C15,0),"") -> 2165 | E10: =IFERROR(ROUND(('DCF Model'!C45/(1+$B10)^('DCF Model'!C19+0)+'DCF Model'!D45/(1+$B10)^('DCF Model'!C19+1)+'DCF Model'!E45/(1+$B10)^('DCF Model'!C19+2)+'DCF Model'!F45/(1+$B10)^('DCF Model'!C19+3)+'DCF Model'!G45/(1+$B10)^('DCF Model'!C19+4)+'DCF Model'!G45*(1+E$6)/($B10-E$6)/(1+$B10)^('DCF Model'!C19+4)-'DCF Model'!C16)*1000000/'DCF Model'!C15,0),"") -> 2276 | F10: =IFERROR(ROUND(('DCF Model'!C45/(1+$B10)^('DCF Model'!C19+0)+'DCF Model'!D45/(1+$B10)^('DCF Model'!C19+1)+'DCF Model'!E45/(1+$B10)^('DCF Model'!C19+2)+'DCF Model'!F45/(1+$B10)^('DCF Model'!C19+3)+'DCF Model'!G45/(1+$B10)^('DCF Model'!C19+4)+'DCF Model'!G45*(1+F$6)/($B10-F$6)/(1+$B10)^('DCF Model'!C19+4)-'DCF Model'!C16)*1000000/'DCF Model'!C15,0),"") -> 2397 | G10: =IFERROR(ROUND(('DCF Model'!C45/(1+$B10)^('DCF Model'!C19+0)+'DCF Model'!D45/(1+$B10)^('DCF Model'!C19+1)+'DCF Model'!E45/(1+$B10)^('DCF Model'!C19+2)+'DCF Model'!F45/(1+$B10)^('DCF Model'!C19+3)+'DCF Model'!G45/(1+$B10)^('DCF Model'!C19+4)+'DCF Model'!G45*(1+G$6)/($B10-G$6)/(1+$B10)^('DCF Model'!C19+4)-'DCF Model'!C16)*1000000/'DCF Model'!C15,0),"") -> 2529 | H10: =IFERROR(ROUND(('DCF Model'!C45/(1+$B10)^('DCF Model'!C19+0)+'DCF Model'!D45/(1+$B10)^('DCF Model'!C19+1)+'DCF Model'!E45/(1+$B10)^('DCF Model'!C19+2)+'DCF Model'!F45/(1+$B10)^('DCF Model'!C19+3)+'DCF Model'!G45/(1+$B10)^('DCF Model'!C19+4)+'DCF Model'!G45*(1+H$6)/($B10-H$6)/(1+$B10)^('DCF Model'!C19+4)-'DCF Model'!C16)*1000000/'DCF Model'!C15,0),"") -> 2675 | I10: =IFERROR(ROUND(('DCF Model'!C45/(1+$B10)^('DCF Model'!C19+0)+'DCF Model'!D45/(1+$B10)^('DCF Model'!C19+1)+'DCF Model'!E45/(1+$B10)^('DCF Model'!C19+2)+'DCF Model'!F45/(1+$B10)^('DCF Model'!C19+3)+'DCF Model'!G45/(1+$B10)^('DCF Model'!C19+4)+'DCF Model'!G45*(1+I$6)/($B10-I$6)/(1+$B10)^('DCF Model'!C19+4)-'DCF Model'!C16)*1000000/'DCF Model'!C15,0),"") -> 2836
B11: =$C$3+0.005 -> 0.069427961 | C11: =IFERROR(ROUND(('DCF Model'!C45/(1+$B11)^('DCF Model'!C19+0)+'DCF Model'!D45/(1+$B11)^('DCF Model'!C19+1)+'DCF Model'!E45/(1+$B11)^('DCF Model'!C19+2)+'DCF Model'!F45/(1+$B11)^('DCF Model'!C19+3)+'DCF Model'!G45/(1+$B11)^('DCF Model'!C19+4)+'DCF Model'!G45*(1+C$6)/($B11-C$6)/(1+$B11)^('DCF Model'!C19+4)-'DCF Model'!C16)*1000000/'DCF Model'!C15,0),"") -> 1842 | D11: =IFERROR(ROUND(('DCF Model'!C45/(1+$B11)^('DCF Model'!C19+0)+'DCF Model'!D45/(1+$B11)^('DCF Model'!C19+1)+'DCF Model'!E45/(1+$B11)^('DCF Model'!C19+2)+'DCF Model'!F45/(1+$B11)^('DCF Model'!C19+3)+'DCF Model'!G45/(1+$B11)^('DCF Model'!C19+4)+'DCF Model'!G45*(1+D$6)/($B11-D$6)/(1+$B11)^('DCF Model'!C19+4)-'DCF Model'!C16)*1000000/'DCF Model'!C15,0),"") -> 1927 | E11: =IFERROR(ROUND(('DCF Model'!C45/(1+$B11)^('DCF Model'!C19+0)+'DCF Model'!D45/(1+$B11)^('DCF Model'!C19+1)+'DCF Model'!E45/(1+$B11)^('DCF Model'!C19+2)+'DCF Model'!F45/(1+$B11)^('DCF Model'!C19+3)+'DCF Model'!G45/(1+$B11)^('DCF Model'!C19+4)+'DCF Model'!G45*(1+E$6)/($B11-E$6)/(1+$B11)^('DCF Model'!C19+4)-'DCF Model'!C16)*1000000/'DCF Model'!C15,0),"") -> 2019 | F11: =IFERROR(ROUND(('DCF Model'!C45/(1+$B11)^('DCF Model'!C19+0)+'DCF Model'!D45/(1+$B11)^('DCF Model'!C19+1)+'DCF Model'!E45/(1+$B11)^('DCF Model'!C19+2)+'DCF Model'!F45/(1+$B11)^('DCF Model'!C19+3)+'DCF Model'!G45/(1+$B11)^('DCF Model'!C19+4)+'DCF Model'!G45*(1+F$6)/($B11-F$6)/(1+$B11)^('DCF Model'!C19+4)-'DCF Model'!C16)*1000000/'DCF Model'!C15,0),"") -> 2119 | G11: =IFERROR(ROUND(('DCF Model'!C45/(1+$B11)^('DCF Model'!C19+0)+'DCF Model'!D45/(1+$B11)^('DCF Model'!C19+1)+'DCF Model'!E45/(1+$B11)^('DCF Model'!C19+2)+'DCF Model'!F45/(1+$B11)^('DCF Model'!C19+3)+'DCF Model'!G45/(1+$B11)^('DCF Model'!C19+4)+'DCF Model'!G45*(1+G$6)/($B11-G$6)/(1+$B11)^('DCF Model'!C19+4)-'DCF Model'!C16)*1000000/'DCF Model'!C15,0),"") -> 2228 | H11: =IFERROR(ROUND(('DCF Model'!C45/(1+$B11)^('DCF Model'!C19+0)+'DCF Model'!D45/(1+$B11)^('DCF Model'!C19+1)+'DCF Model'!E45/(1+$B11)^('DCF Model'!C19+2)+'DCF Model'!F45/(1+$B11)^('DCF Model'!C19+3)+'DCF Model'!G45/(1+$B11)^('DCF Model'!C19+4)+'DCF Model'!G45*(1+H$6)/($B11-H$6)/(1+$B11)^('DCF Model'!C19+4)-'DCF Model'!C16)*1000000/'DCF Model'!C15,0),"") -> 2347 | I11: =IFERROR(ROUND(('DCF Model'!C45/(1+$B11)^('DCF Model'!C19+0)+'DCF Model'!D45/(1+$B11)^('DCF Model'!C19+1)+'DCF Model'!E45/(1+$B11)^('DCF Model'!C19+2)+'DCF Model'!F45/(1+$B11)^('DCF Model'!C19+3)+'DCF Model'!G45/(1+$B11)^('DCF Model'!C19+4)+'DCF Model'!G45*(1+I$6)/($B11-I$6)/(1+$B11)^('DCF Model'!C19+4)-'DCF Model'!C16)*1000000/'DCF Model'!C15,0),"") -> 2477
B12: =$C$3+0.01 -> 0.074427961 | C12: =IFERROR(ROUND(('DCF Model'!C45/(1+$B12)^('DCF Model'!C19+0)+'DCF Model'!D45/(1+$B12)^('DCF Model'!C19+1)+'DCF Model'!E45/(1+$B12)^('DCF Model'!C19+2)+'DCF Model'!F45/(1+$B12)^('DCF Model'!C19+3)+'DCF Model'!G45/(1+$B12)^('DCF Model'!C19+4)+'DCF Model'!G45*(1+C$6)/($B12-C$6)/(1+$B12)^('DCF Model'!C19+4)-'DCF Model'!C16)*1000000/'DCF Model'!C15,0),"") -> 1651 | D12: =IFERROR(ROUND(('DCF Model'!C45/(1+$B12)^('DCF Model'!C19+0)+'DCF Model'!D45/(1+$B12)^('DCF Model'!C19+1)+'DCF Model'!E45/(1+$B12)^('DCF Model'!C19+2)+'DCF Model'!F45/(1+$B12)^('DCF Model'!C19+3)+'DCF Model'!G45/(1+$B12)^('DCF Model'!C19+4)+'DCF Model'!G45*(1+D$6)/($B12-D$6)/(1+$B12)^('DCF Model'!C19+4)-'DCF Model'!C16)*1000000/'DCF Model'!C15,0),"") -> 1723 | E12: =IFERROR(ROUND(('DCF Model'!C45/(1+$B12)^('DCF Model'!C19+0)+'DCF Model'!D45/(1+$B12)^('DCF Model'!C19+1)+'DCF Model'!E45/(1+$B12)^('DCF Model'!C19+2)+'DCF Model'!F45/(1+$B12)^('DCF Model'!C19+3)+'DCF Model'!G45/(1+$B12)^('DCF Model'!C19+4)+'DCF Model'!G45*(1+E$6)/($B12-E$6)/(1+$B12)^('DCF Model'!C19+4)-'DCF Model'!C16)*1000000/'DCF Model'!C15,0),"") -> 1801 | F12: =IFERROR(ROUND(('DCF Model'!C45/(1+$B12)^('DCF Model'!C19+0)+'DCF Model'!D45/(1+$B12)^('DCF Model'!C19+1)+'DCF Model'!E45/(1+$B12)^('DCF Model'!C19+2)+'DCF Model'!F45/(1+$B12)^('DCF Model'!C19+3)+'DCF Model'!G45/(1+$B12)^('DCF Model'!C19+4)+'DCF Model'!G45*(1+F$6)/($B12-F$6)/(1+$B12)^('DCF Model'!C19+4)-'DCF Model'!C16)*1000000/'DCF Model'!C15,0),"") -> 1885 | G12: =IFERROR(ROUND(('DCF Model'!C45/(1+$B12)^('DCF Model'!C19+0)+'DCF Model'!D45/(1+$B12)^('DCF Model'!C19+1)+'DCF Model'!E45/(1+$B12)^('DCF Model'!C19+2)+'DCF Model'!F45/(1+$B12)^('DCF Model'!C19+3)+'DCF Model'!G45/(1+$B12)^('DCF Model'!C19+4)+'DCF Model'!G45*(1+G$6)/($B12-G$6)/(1+$B12)^('DCF Model'!C19+4)-'DCF Model'!C16)*1000000/'DCF Model'!C15,0),"") -> 1976 | H12: =IFERROR(ROUND(('DCF Model'!C45/(1+$B12)^('DCF Model'!C19+0)+'DCF Model'!D45/(1+$B12)^('DCF Model'!C19+1)+'DCF Model'!E45/(1+$B12)^('DCF Model'!C19+2)+'DCF Model'!F45/(1+$B12)^('DCF Model'!C19+3)+'DCF Model'!G45/(1+$B12)^('DCF Model'!C19+4)+'DCF Model'!G45*(1+H$6)/($B12-H$6)/(1+$B12)^('DCF Model'!C19+4)-'DCF Model'!C16)*1000000/'DCF Model'!C15,0),"") -> 2074 | I12: =IFERROR(ROUND(('DCF Model'!C45/(1+$B12)^('DCF Model'!C19+0)+'DCF Model'!D45/(1+$B12)^('DCF Model'!C19+1)+'DCF Model'!E45/(1+$B12)^('DCF Model'!C19+2)+'DCF Model'!F45/(1+$B12)^('DCF Model'!C19+3)+'DCF Model'!G45/(1+$B12)^('DCF Model'!C19+4)+'DCF Model'!G45*(1+I$6)/($B12-I$6)/(1+$B12)^('DCF Model'!C19+4)-'DCF Model'!C16)*1000000/'DCF Model'!C15,0),"") -> 2181
B13: =$C$3+0.015 -> 0.079427961 | C13: =IFERROR(ROUND(('DCF Model'!C45/(1+$B13)^('DCF Model'!C19+0)+'DCF Model'!D45/(1+$B13)^('DCF Model'!C19+1)+'DCF Model'!E45/(1+$B13)^('DCF Model'!C19+2)+'DCF Model'!F45/(1+$B13)^('DCF Model'!C19+3)+'DCF Model'!G45/(1+$B13)^('DCF Model'!C19+4)+'DCF Model'!G45*(1+C$6)/($B13-C$6)/(1+$B13)^('DCF Model'!C19+4)-'DCF Model'!C16)*1000000/'DCF Model'!C15,0),"") -> 1485 | D13: =IFERROR(ROUND(('DCF Model'!C45/(1+$B13)^('DCF Model'!C19+0)+'DCF Model'!D45/(1+$B13)^('DCF Model'!C19+1)+'DCF Model'!E45/(1+$B13)^('DCF Model'!C19+2)+'DCF Model'!F45/(1+$B13)^('DCF Model'!C19+3)+'DCF Model'!G45/(1+$B13)^('DCF Model'!C19+4)+'DCF Model'!G45*(1+D$6)/($B13-D$6)/(1+$B13)^('DCF Model'!C19+4)-'DCF Model'!C16)*1000000/'DCF Model'!C15,0),"") -> 1547 | E13: =IFERROR(ROUND(('DCF Model'!C45/(1+$B13)^('DCF Model'!C19+0)+'DCF Model'!D45/(1+$B13)^('DCF Model'!C19+1)+'DCF Model'!E45/(1+$B13)^('DCF Model'!C19+2)+'DCF Model'!F45/(1+$B13)^('DCF Model'!C19+3)+'DCF Model'!G45/(1+$B13)^('DCF Model'!C19+4)+'DCF Model'!G45*(1+E$6)/($B13-E$6)/(1+$B13)^('DCF Model'!C19+4)-'DCF Model'!C16)*1000000/'DCF Model'!C15,0),"") -> 1613 | F13: =IFERROR(ROUND(('DCF Model'!C45/(1+$B13)^('DCF Model'!C19+0)+'DCF Model'!D45/(1+$B13)^('DCF Model'!C19+1)+'DCF Model'!E45/(1+$B13)^('DCF Model'!C19+2)+'DCF Model'!F45/(1+$B13)^('DCF Model'!C19+3)+'DCF Model'!G45/(1+$B13)^('DCF Model'!C19+4)+'DCF Model'!G45*(1+F$6)/($B13-F$6)/(1+$B13)^('DCF Model'!C19+4)-'DCF Model'!C16)*1000000/'DCF Model'!C15,0),"") -> 1685 | G13: =IFERROR(ROUND(('DCF Model'!C45/(1+$B13)^('DCF Model'!C19+0)+'DCF Model'!D45/(1+$B13)^('DCF Model'!C19+1)+'DCF Model'!E45/(1+$B13)^('DCF Model'!C19+2)+'DCF Model'!F45/(1+$B13)^('DCF Model'!C19+3)+'DCF Model'!G45/(1+$B13)^('DCF Model'!C19+4)+'DCF Model'!G45*(1+G$6)/($B13-G$6)/(1+$B13)^('DCF Model'!C19+4)-'DCF Model'!C16)*1000000/'DCF Model'!C15,0),"") -> 1761 | H13: =IFERROR(ROUND(('DCF Model'!C45/(1+$B13)^('DCF Model'!C19+0)+'DCF Model'!D45/(1+$B13)^('DCF Model'!C19+1)+'DCF Model'!E45/(1+$B13)^('DCF Model'!C19+2)+'DCF Model'!F45/(1+$B13)^('DCF Model'!C19+3)+'DCF Model'!G45/(1+$B13)^('DCF Model'!C19+4)+'DCF Model'!G45*(1+H$6)/($B13-H$6)/(1+$B13)^('DCF Model'!C19+4)-'DCF Model'!C16)*1000000/'DCF Model'!C15,0),"") -> 1844 | I13: =IFERROR(ROUND(('DCF Model'!C45/(1+$B13)^('DCF Model'!C19+0)+'DCF Model'!D45/(1+$B13)^('DCF Model'!C19+1)+'DCF Model'!E45/(1+$B13)^('DCF Model'!C19+2)+'DCF Model'!F45/(1+$B13)^('DCF Model'!C19+3)+'DCF Model'!G45/(1+$B13)^('DCF Model'!C19+4)+'DCF Model'!G45*(1+I$6)/($B13-I$6)/(1+$B13)^('DCF Model'!C19+4)-'DCF Model'!C16)*1000000/'DCF Model'!C15,0),"") -> 1933
B16: Table 2: WACC vs Exit Multiple (Exit Multiple - Implied Share Price, JPY)
B17: WACC \ Exit Multiple | C17: =$I$3-3 -> 8.1 | D17: =$I$3-2 -> 9.1 | E17: =$I$3-1 -> 10.1 | F17: =$I$3 -> 11.1 | G17: =$I$3+1 -> 12.1 | H17: =$I$3+2 -> 13.1 | I17: =$I$3+3 -> 14.1
B18: =$C$3-0.015 -> 0.049427961 | C18: =IFERROR(ROUND(('DCF Model'!C45/(1+$B18)^('DCF Model'!C19+0)+'DCF Model'!D45/(1+$B18)^('DCF Model'!C19+1)+'DCF Model'!E45/(1+$B18)^('DCF Model'!C19+2)+'DCF Model'!F45/(1+$B18)^('DCF Model'!C19+3)+'DCF Model'!G45/(1+$B18)^('DCF Model'!C19+4)+('DCF Model'!G39+'DCF Model'!G42)*C$17/(1+$B18)^('DCF Model'!C19+4)-'DCF Model'!C16)*1000000/'DCF Model'!C15,0),"") -> 2597 | D18: =IFERROR(ROUND(('DCF Model'!C45/(1+$B18)^('DCF Model'!C19+0)+'DCF Model'!D45/(1+$B18)^('DCF Model'!C19+1)+'DCF Model'!E45/(1+$B18)^('DCF Model'!C19+2)+'DCF Model'!F45/(1+$B18)^('DCF Model'!C19+3)+'DCF Model'!G45/(1+$B18)^('DCF Model'!C19+4)+('DCF Model'!G39+'DCF Model'!G42)*D$17/(1+$B18)^('DCF Model'!C19+4)-'DCF Model'!C16)*1000000/'DCF Model'!C15,0),"") -> 2941 | E18: =IFERROR(ROUND(('DCF Model'!C45/(1+$B18)^('DCF Model'!C19+0)+'DCF Model'!D45/(1+$B18)^('DCF Model'!C19+1)+'DCF Model'!E45/(1+$B18)^('DCF Model'!C19+2)+'DCF Model'!F45/(1+$B18)^('DCF Model'!C19+3)+'DCF Model'!G45/(1+$B18)^('DCF Model'!C19+4)+('DCF Model'!G39+'DCF Model'!G42)*E$17/(1+$B18)^('DCF Model'!C19+4)-'DCF Model'!C16)*1000000/'DCF Model'!C15,0),"") -> 3285 | F18: =IFERROR(ROUND(('DCF Model'!C45/(1+$B18)^('DCF Model'!C19+0)+'DCF Model'!D45/(1+$B18)^('DCF Model'!C19+1)+'DCF Model'!E45/(1+$B18)^('DCF Model'!C19+2)+'DCF Model'!F45/(1+$B18)^('DCF Model'!C19+3)+'DCF Model'!G45/(1+$B18)^('DCF Model'!C19+4)+('DCF Model'!G39+'DCF Model'!G42)*F$17/(1+$B18)^('DCF Model'!C19+4)-'DCF Model'!C16)*1000000/'DCF Model'!C15,0),"") -> 3629 | G18: =IFERROR(ROUND(('DCF Model'!C45/(1+$B18)^('DCF Model'!C19+0)+'DCF Model'!D45/(1+$B18)^('DCF Model'!C19+1)+'DCF Model'!E45/(1+$B18)^('DCF Model'!C19+2)+'DCF Model'!F45/(1+$B18)^('DCF Model'!C19+3)+'DCF Model'!G45/(1+$B18)^('DCF Model'!C19+4)+('DCF Model'!G39+'DCF Model'!G42)*G$17/(1+$B18)^('DCF Model'!C19+4)-'DCF Model'!C16)*1000000/'DCF Model'!C15,0),"") -> 3973 | H18: =IFERROR(ROUND(('DCF Model'!C45/(1+$B18)^('DCF Model'!C19+0)+'DCF Model'!D45/(1+$B18)^('DCF Model'!C19+1)+'DCF Model'!E45/(1+$B18)^('DCF Model'!C19+2)+'DCF Model'!F45/(1+$B18)^('DCF Model'!C19+3)+'DCF Model'!G45/(1+$B18)^('DCF Model'!C19+4)+('DCF Model'!G39+'DCF Model'!G42)*H$17/(1+$B18)^('DCF Model'!C19+4)-'DCF Model'!C16)*1000000/'DCF Model'!C15,0),"") -> 4317 | I18: =IFERROR(ROUND(('DCF Model'!C45/(1+$B18)^('DCF Model'!C19+0)+'DCF Model'!D45/(1+$B18)^('DCF Model'!C19+1)+'DCF Model'!E45/(1+$B18)^('DCF Model'!C19+2)+'DCF Model'!F45/(1+$B18)^('DCF Model'!C19+3)+'DCF Model'!G45/(1+$B18)^('DCF Model'!C19+4)+('DCF Model'!G39+'DCF Model'!G42)*I$17/(1+$B18)^('DCF Model'!C19+4)-'DCF Model'!C16)*1000000/'DCF Model'!C15,0),"") -> 4661
B19: =$C$3-0.01 -> 0.054427961 | C19: =IFERROR(ROUND(('DCF Model'!C45/(1+$B19)^('DCF Model'!C19+0)+'DCF Model'!D45/(1+$B19)^('DCF Model'!C19+1)+'DCF Model'!E45/(1+$B19)^('DCF Model'!C19+2)+'DCF Model'!F45/(1+$B19)^('DCF Model'!C19+3)+'DCF Model'!G45/(1+$B19)^('DCF Model'!C19+4)+('DCF Model'!G39+'DCF Model'!G42)*C$17/(1+$B19)^('DCF Model'!C19+4)-'DCF Model'!C16)*1000000/'DCF Model'!C15,0),"") -> 2530 | D19: =IFERROR(ROUND(('DCF Model'!C45/(1+$B19)^('DCF Model'!C19+0)+'DCF Model'!D45/(1+$B19)^('DCF Model'!C19+1)+'DCF Model'!E45/(1+$B19)^('DCF Model'!C19+2)+'DCF Model'!F45/(1+$B19)^('DCF Model'!C19+3)+'DCF Model'!G45/(1+$B19)^('DCF Model'!C19+4)+('DCF Model'!G39+'DCF Model'!G42)*D$17/(1+$B19)^('DCF Model'!C19+4)-'DCF Model'!C16)*1000000/'DCF Model'!C15,0),"") -> 2867 | E19: =IFERROR(ROUND(('DCF Model'!C45/(1+$B19)^('DCF Model'!C19+0)+'DCF Model'!D45/(1+$B19)^('DCF Model'!C19+1)+'DCF Model'!E45/(1+$B19)^('DCF Model'!C19+2)+'DCF Model'!F45/(1+$B19)^('DCF Model'!C19+3)+'DCF Model'!G45/(1+$B19)^('DCF Model'!C19+4)+('DCF Model'!G39+'DCF Model'!G42)*E$17/(1+$B19)^('DCF Model'!C19+4)-'DCF Model'!C16)*1000000/'DCF Model'!C15,0),"") -> 3203 | F19: =IFERROR(ROUND(('DCF Model'!C45/(1+$B19)^('DCF Model'!C19+0)+'DCF Model'!D45/(1+$B19)^('DCF Model'!C19+1)+'DCF Model'!E45/(1+$B19)^('DCF Model'!C19+2)+'DCF Model'!F45/(1+$B19)^('DCF Model'!C19+3)+'DCF Model'!G45/(1+$B19)^('DCF Model'!C19+4)+('DCF Model'!G39+'DCF Model'!G42)*F$17/(1+$B19)^('DCF Model'!C19+4)-'DCF Model'!C16)*1000000/'DCF Model'!C15,0),"") -> 3540 | G19: =IFERROR(ROUND(('DCF Model'!C45/(1+$B19)^('DCF Model'!C19+0)+'DCF Model'!D45/(1+$B19)^('DCF Model'!C19+1)+'DCF Model'!E45/(1+$B19)^('DCF Model'!C19+2)+'DCF Model'!F45/(1+$B19)^('DCF Model'!C19+3)+'DCF Model'!G45/(1+$B19)^('DCF Model'!C19+4)+('DCF Model'!G39+'DCF Model'!G42)*G$17/(1+$B19)^('DCF Model'!C19+4)-'DCF Model'!C16)*1000000/'DCF Model'!C15,0),"") -> 3877 | H19: =IFERROR(ROUND(('DCF Model'!C45/(1+$B19)^('DCF Model'!C19+0)+'DCF Model'!D45/(1+$B19)^('DCF Model'!C19+1)+'DCF Model'!E45/(1+$B19)^('DCF Model'!C19+2)+'DCF Model'!F45/(1+$B19)^('DCF Model'!C19+3)+'DCF Model'!G45/(1+$B19)^('DCF Model'!C19+4)+('DCF Model'!G39+'DCF Model'!G42)*H$17/(1+$B19)^('DCF Model'!C19+4)-'DCF Model'!C16)*1000000/'DCF Model'!C15,0),"") -> 4213 | I19: =IFERROR(ROUND(('DCF Model'!C45/(1+$B19)^('DCF Model'!C19+0)+'DCF Model'!D45/(1+$B19)^('DCF Model'!C19+1)+'DCF Model'!E45/(1+$B19)^('DCF Model'!C19+2)+'DCF Model'!F45/(1+$B19)^('DCF Model'!C19+3)+'DCF Model'!G45/(1+$B19)^('DCF Model'!C19+4)+('DCF Model'!G39+'DCF Model'!G42)*I$17/(1+$B19)^('DCF Model'!C19+4)-'DCF Model'!C16)*1000000/'DCF Model'!C15,0),"") -> 4550
B20: =$C$3-0.005 -> 0.059427961 | C20: =IFERROR(ROUND(('DCF Model'!C45/(1+$B20)^('DCF Model'!C19+0)+'DCF Model'!D45/(1+$B20)^('DCF Model'!C19+1)+'DCF Model'!E45/(1+$B20)^('DCF Model'!C19+2)+'DCF Model'!F45/(1+$B20)^('DCF Model'!C19+3)+'DCF Model'!G45/(1+$B20)^('DCF Model'!C19+4)+('DCF Model'!G39+'DCF Model'!G42)*C$17/(1+$B20)^('DCF Model'!C19+4)-'DCF Model'!C16)*1000000/'DCF Model'!C15,0),"") -> 2464 | D20: =IFERROR(ROUND(('DCF Model'!C45/(1+$B20)^('DCF Model'!C19+0)+'DCF Model'!D45/(1+$B20)^('DCF Model'!C19+1)+'DCF Model'!E45/(1+$B20)^('DCF Model'!C19+2)+'DCF Model'!F45/(1+$B20)^('DCF Model'!C19+3)+'DCF Model'!G45/(1+$B20)^('DCF Model'!C19+4)+('DCF Model'!G39+'DCF Model'!G42)*D$17/(1+$B20)^('DCF Model'!C19+4)-'DCF Model'!C16)*1000000/'DCF Model'!C15,0),"") -> 2794 | E20: =IFERROR(ROUND(('DCF Model'!C45/(1+$B20)^('DCF Model'!C19+0)+'DCF Model'!D45/(1+$B20)^('DCF Model'!C19+1)+'DCF Model'!E45/(1+$B20)^('DCF Model'!C19+2)+'DCF Model'!F45/(1+$B20)^('DCF Model'!C19+3)+'DCF Model'!G45/(1+$B20)^('DCF Model'!C19+4)+('DCF Model'!G39+'DCF Model'!G42)*E$17/(1+$B20)^('DCF Model'!C19+4)-'DCF Model'!C16)*1000000/'DCF Model'!C15,0),"") -> 3123 | F20: =IFERROR(ROUND(('DCF Model'!C45/(1+$B20)^('DCF Model'!C19+0)+'DCF Model'!D45/(1+$B20)^('DCF Model'!C19+1)+'DCF Model'!E45/(1+$B20)^('DCF Model'!C19+2)+'DCF Model'!F45/(1+$B20)^('DCF Model'!C19+3)+'DCF Model'!G45/(1+$B20)^('DCF Model'!C19+4)+('DCF Model'!G39+'DCF Model'!G42)*F$17/(1+$B20)^('DCF Model'!C19+4)-'DCF Model'!C16)*1000000/'DCF Model'!C15,0),"") -> 3453 | G20: =IFERROR(ROUND(('DCF Model'!C45/(1+$B20)^('DCF Model'!C19+0)+'DCF Model'!D45/(1+$B20)^('DCF Model'!C19+1)+'DCF Model'!E45/(1+$B20)^('DCF Model'!C19+2)+'DCF Model'!F45/(1+$B20)^('DCF Model'!C19+3)+'DCF Model'!G45/(1+$B20)^('DCF Model'!C19+4)+('DCF Model'!G39+'DCF Model'!G42)*G$17/(1+$B20)^('DCF Model'!C19+4)-'DCF Model'!C16)*1000000/'DCF Model'!C15,0),"") -> 3783 | H20: =IFERROR(ROUND(('DCF Model'!C45/(1+$B20)^('DCF Model'!C19+0)+'DCF Model'!D45/(1+$B20)^('DCF Model'!C19+1)+'DCF Model'!E45/(1+$B20)^('DCF Model'!C19+2)+'DCF Model'!F45/(1+$B20)^('DCF Model'!C19+3)+'DCF Model'!G45/(1+$B20)^('DCF Model'!C19+4)+('DCF Model'!G39+'DCF Model'!G42)*H$17/(1+$B20)^('DCF Model'!C19+4)-'DCF Model'!C16)*1000000/'DCF Model'!C15,0),"") -> 4112 | I20: =IFERROR(ROUND(('DCF Model'!C45/(1+$B20)^('DCF Model'!C19+0)+'DCF Model'!D45/(1+$B20)^('DCF Model'!C19+1)+'DCF Model'!E45/(1+$B20)^('DCF Model'!C19+2)+'DCF Model'!F45/(1+$B20)^('DCF Model'!C19+3)+'DCF Model'!G45/(1+$B20)^('DCF Model'!C19+4)+('DCF Model'!G39+'DCF Model'!G42)*I$17/(1+$B20)^('DCF Model'!C19+4)-'DCF Model'!C16)*1000000/'DCF Model'!C15,0),"") -> 4442
B21: =$C$3 -> 0.064427961 | C21: =IFERROR(ROUND(('DCF Model'!C45/(1+$B21)^('DCF Model'!C19+0)+'DCF Model'!D45/(1+$B21)^('DCF Model'!C19+1)+'DCF Model'!E45/(1+$B21)^('DCF Model'!C19+2)+'DCF Model'!F45/(1+$B21)^('DCF Model'!C19+3)+'DCF Model'!G45/(1+$B21)^('DCF Model'!C19+4)+('DCF Model'!G39+'DCF Model'!G42)*C$17/(1+$B21)^('DCF Model'!C19+4)-'DCF Model'!C16)*1000000/'DCF Model'!C15,0),"") -> 2400 | D21: =IFERROR(ROUND(('DCF Model'!C45/(1+$B21)^('DCF Model'!C19+0)+'DCF Model'!D45/(1+$B21)^('DCF Model'!C19+1)+'DCF Model'!E45/(1+$B21)^('DCF Model'!C19+2)+'DCF Model'!F45/(1+$B21)^('DCF Model'!C19+3)+'DCF Model'!G45/(1+$B21)^('DCF Model'!C19+4)+('DCF Model'!G39+'DCF Model'!G42)*D$17/(1+$B21)^('DCF Model'!C19+4)-'DCF Model'!C16)*1000000/'DCF Model'!C15,0),"") -> 2723 | E21: =IFERROR(ROUND(('DCF Model'!C45/(1+$B21)^('DCF Model'!C19+0)+'DCF Model'!D45/(1+$B21)^('DCF Model'!C19+1)+'DCF Model'!E45/(1+$B21)^('DCF Model'!C19+2)+'DCF Model'!F45/(1+$B21)^('DCF Model'!C19+3)+'DCF Model'!G45/(1+$B21)^('DCF Model'!C19+4)+('DCF Model'!G39+'DCF Model'!G42)*E$17/(1+$B21)^('DCF Model'!C19+4)-'DCF Model'!C16)*1000000/'DCF Model'!C15,0),"") -> 3046 | F21: =IFERROR(ROUND(('DCF Model'!C45/(1+$B21)^('DCF Model'!C19+0)+'DCF Model'!D45/(1+$B21)^('DCF Model'!C19+1)+'DCF Model'!E45/(1+$B21)^('DCF Model'!C19+2)+'DCF Model'!F45/(1+$B21)^('DCF Model'!C19+3)+'DCF Model'!G45/(1+$B21)^('DCF Model'!C19+4)+('DCF Model'!G39+'DCF Model'!G42)*F$17/(1+$B21)^('DCF Model'!C19+4)-'DCF Model'!C16)*1000000/'DCF Model'!C15,0),"") -> 3368 | G21: =IFERROR(ROUND(('DCF Model'!C45/(1+$B21)^('DCF Model'!C19+0)+'DCF Model'!D45/(1+$B21)^('DCF Model'!C19+1)+'DCF Model'!E45/(1+$B21)^('DCF Model'!C19+2)+'DCF Model'!F45/(1+$B21)^('DCF Model'!C19+3)+'DCF Model'!G45/(1+$B21)^('DCF Model'!C19+4)+('DCF Model'!G39+'DCF Model'!G42)*G$17/(1+$B21)^('DCF Model'!C19+4)-'DCF Model'!C16)*1000000/'DCF Model'!C15,0),"") -> 3691 | H21: =IFERROR(ROUND(('DCF Model'!C45/(1+$B21)^('DCF Model'!C19+0)+'DCF Model'!D45/(1+$B21)^('DCF Model'!C19+1)+'DCF Model'!E45/(1+$B21)^('DCF Model'!C19+2)+'DCF Model'!F45/(1+$B21)^('DCF Model'!C19+3)+'DCF Model'!G45/(1+$B21)^('DCF Model'!C19+4)+('DCF Model'!G39+'DCF Model'!G42)*H$17/(1+$B21)^('DCF Model'!C19+4)-'DCF Model'!C16)*1000000/'DCF Model'!C15,0),"") -> 4013 | I21: =IFERROR(ROUND(('DCF Model'!C45/(1+$B21)^('DCF Model'!C19+0)+'DCF Model'!D45/(1+$B21)^('DCF Model'!C19+1)+'DCF Model'!E45/(1+$B21)^('DCF Model'!C19+2)+'DCF Model'!F45/(1+$B21)^('DCF Model'!C19+3)+'DCF Model'!G45/(1+$B21)^('DCF Model'!C19+4)+('DCF Model'!G39+'DCF Model'!G42)*I$17/(1+$B21)^('DCF Model'!C19+4)-'DCF Model'!C16)*1000000/'DCF Model'!C15,0),"") -> 4336
B22: =$C$3+0.005 -> 0.069427961 | C22: =IFERROR(ROUND(('DCF Model'!C45/(1+$B22)^('DCF Model'!C19+0)+'DCF Model'!D45/(1+$B22)^('DCF Model'!C19+1)+'DCF Model'!E45/(1+$B22)^('DCF Model'!C19+2)+'DCF Model'!F45/(1+$B22)^('DCF Model'!C19+3)+'DCF Model'!G45/(1+$B22)^('DCF Model'!C19+4)+('DCF Model'!G39+'DCF Model'!G42)*C$17/(1+$B22)^('DCF Model'!C19+4)-'DCF Model'!C16)*1000000/'DCF Model'!C15,0),"") -> 2338 | D22: =IFERROR(ROUND(('DCF Model'!C45/(1+$B22)^('DCF Model'!C19+0)+'DCF Model'!D45/(1+$B22)^('DCF Model'!C19+1)+'DCF Model'!E45/(1+$B22)^('DCF Model'!C19+2)+'DCF Model'!F45/(1+$B22)^('DCF Model'!C19+3)+'DCF Model'!G45/(1+$B22)^('DCF Model'!C19+4)+('DCF Model'!G39+'DCF Model'!G42)*D$17/(1+$B22)^('DCF Model'!C19+4)-'DCF Model'!C16)*1000000/'DCF Model'!C15,0),"") -> 2654 | E22: =IFERROR(ROUND(('DCF Model'!C45/(1+$B22)^('DCF Model'!C19+0)+'DCF Model'!D45/(1+$B22)^('DCF Model'!C19+1)+'DCF Model'!E45/(1+$B22)^('DCF Model'!C19+2)+'DCF Model'!F45/(1+$B22)^('DCF Model'!C19+3)+'DCF Model'!G45/(1+$B22)^('DCF Model'!C19+4)+('DCF Model'!G39+'DCF Model'!G42)*E$17/(1+$B22)^('DCF Model'!C19+4)-'DCF Model'!C16)*1000000/'DCF Model'!C15,0),"") -> 2970 | F22: =IFERROR(ROUND(('DCF Model'!C45/(1+$B22)^('DCF Model'!C19+0)+'DCF Model'!D45/(1+$B22)^('DCF Model'!C19+1)+'DCF Model'!E45/(1+$B22)^('DCF Model'!C19+2)+'DCF Model'!F45/(1+$B22)^('DCF Model'!C19+3)+'DCF Model'!G45/(1+$B22)^('DCF Model'!C19+4)+('DCF Model'!G39+'DCF Model'!G42)*F$17/(1+$B22)^('DCF Model'!C19+4)-'DCF Model'!C16)*1000000/'DCF Model'!C15,0),"") -> 3286 | G22: =IFERROR(ROUND(('DCF Model'!C45/(1+$B22)^('DCF Model'!C19+0)+'DCF Model'!D45/(1+$B22)^('DCF Model'!C19+1)+'DCF Model'!E45/(1+$B22)^('DCF Model'!C19+2)+'DCF Model'!F45/(1+$B22)^('DCF Model'!C19+3)+'DCF Model'!G45/(1+$B22)^('DCF Model'!C19+4)+('DCF Model'!G39+'DCF Model'!G42)*G$17/(1+$B22)^('DCF Model'!C19+4)-'DCF Model'!C16)*1000000/'DCF Model'!C15,0),"") -> 3602 | H22: =IFERROR(ROUND(('DCF Model'!C45/(1+$B22)^('DCF Model'!C19+0)+'DCF Model'!D45/(1+$B22)^('DCF Model'!C19+1)+'DCF Model'!E45/(1+$B22)^('DCF Model'!C19+2)+'DCF Model'!F45/(1+$B22)^('DCF Model'!C19+3)+'DCF Model'!G45/(1+$B22)^('DCF Model'!C19+4)+('DCF Model'!G39+'DCF Model'!G42)*H$17/(1+$B22)^('DCF Model'!C19+4)-'DCF Model'!C16)*1000000/'DCF Model'!C15,0),"") -> 3917 | I22: =IFERROR(ROUND(('DCF Model'!C45/(1+$B22)^('DCF Model'!C19+0)+'DCF Model'!D45/(1+$B22)^('DCF Model'!C19+1)+'DCF Model'!E45/(1+$B22)^('DCF Model'!C19+2)+'DCF Model'!F45/(1+$B22)^('DCF Model'!C19+3)+'DCF Model'!G45/(1+$B22)^('DCF Model'!C19+4)+('DCF Model'!G39+'DCF Model'!G42)*I$17/(1+$B22)^('DCF Model'!C19+4)-'DCF Model'!C16)*1000000/'DCF Model'!C15,0),"") -> 4233
B23: =$C$3+0.01 -> 0.074427961 | C23: =IFERROR(ROUND(('DCF Model'!C45/(1+$B23)^('DCF Model'!C19+0)+'DCF Model'!D45/(1+$B23)^('DCF Model'!C19+1)+'DCF Model'!E45/(1+$B23)^('DCF Model'!C19+2)+'DCF Model'!F45/(1+$B23)^('DCF Model'!C19+3)+'DCF Model'!G45/(1+$B23)^('DCF Model'!C19+4)+('DCF Model'!G39+'DCF Model'!G42)*C$17/(1+$B23)^('DCF Model'!C19+4)-'DCF Model'!C16)*1000000/'DCF Model'!C15,0),"") -> 2277 | D23: =IFERROR(ROUND(('DCF Model'!C45/(1+$B23)^('DCF Model'!C19+0)+'DCF Model'!D45/(1+$B23)^('DCF Model'!C19+1)+'DCF Model'!E45/(1+$B23)^('DCF Model'!C19+2)+'DCF Model'!F45/(1+$B23)^('DCF Model'!C19+3)+'DCF Model'!G45/(1+$B23)^('DCF Model'!C19+4)+('DCF Model'!G39+'DCF Model'!G42)*D$17/(1+$B23)^('DCF Model'!C19+4)-'DCF Model'!C16)*1000000/'DCF Model'!C15,0),"") -> 2586 | E23: =IFERROR(ROUND(('DCF Model'!C45/(1+$B23)^('DCF Model'!C19+0)+'DCF Model'!D45/(1+$B23)^('DCF Model'!C19+1)+'DCF Model'!E45/(1+$B23)^('DCF Model'!C19+2)+'DCF Model'!F45/(1+$B23)^('DCF Model'!C19+3)+'DCF Model'!G45/(1+$B23)^('DCF Model'!C19+4)+('DCF Model'!G39+'DCF Model'!G42)*E$17/(1+$B23)^('DCF Model'!C19+4)-'DCF Model'!C16)*1000000/'DCF Model'!C15,0),"") -> 2896 | F23: =IFERROR(ROUND(('DCF Model'!C45/(1+$B23)^('DCF Model'!C19+0)+'DCF Model'!D45/(1+$B23)^('DCF Model'!C19+1)+'DCF Model'!E45/(1+$B23)^('DCF Model'!C19+2)+'DCF Model'!F45/(1+$B23)^('DCF Model'!C19+3)+'DCF Model'!G45/(1+$B23)^('DCF Model'!C19+4)+('DCF Model'!G39+'DCF Model'!G42)*F$17/(1+$B23)^('DCF Model'!C19+4)-'DCF Model'!C16)*1000000/'DCF Model'!C15,0),"") -> 3205 | G23: =IFERROR(ROUND(('DCF Model'!C45/(1+$B23)^('DCF Model'!C19+0)+'DCF Model'!D45/(1+$B23)^('DCF Model'!C19+1)+'DCF Model'!E45/(1+$B23)^('DCF Model'!C19+2)+'DCF Model'!F45/(1+$B23)^('DCF Model'!C19+3)+'DCF Model'!G45/(1+$B23)^('DCF Model'!C19+4)+('DCF Model'!G39+'DCF Model'!G42)*G$17/(1+$B23)^('DCF Model'!C19+4)-'DCF Model'!C16)*1000000/'DCF Model'!C15,0),"") -> 3514 | H23: =IFERROR(ROUND(('DCF Model'!C45/(1+$B23)^('DCF Model'!C19+0)+'DCF Model'!D45/(1+$B23)^('DCF Model'!C19+1)+'DCF Model'!E45/(1+$B23)^('DCF Model'!C19+2)+'DCF Model'!F45/(1+$B23)^('DCF Model'!C19+3)+'DCF Model'!G45/(1+$B23)^('DCF Model'!C19+4)+('DCF Model'!G39+'DCF Model'!G42)*H$17/(1+$B23)^('DCF Model'!C19+4)-'DCF Model'!C16)*1000000/'DCF Model'!C15,0),"") -> 3824 | I23: =IFERROR(ROUND(('DCF Model'!C45/(1+$B23)^('DCF Model'!C19+0)+'DCF Model'!D45/(1+$B23)^('DCF Model'!C19+1)+'DCF Model'!E45/(1+$B23)^('DCF Model'!C19+2)+'DCF Model'!F45/(1+$B23)^('DCF Model'!C19+3)+'DCF Model'!G45/(1+$B23)^('DCF Model'!C19+4)+('DCF Model'!G39+'DCF Model'!G42)*I$17/(1+$B23)^('DCF Model'!C19+4)-'DCF Model'!C16)*1000000/'DCF Model'!C15,0),"") -> 4133
B24: =$C$3+0.015 -> 0.079427961 | C24: =IFERROR(ROUND(('DCF Model'!C45/(1+$B24)^('DCF Model'!C19+0)+'DCF Model'!D45/(1+$B24)^('DCF Model'!C19+1)+'DCF Model'!E45/(1+$B24)^('DCF Model'!C19+2)+'DCF Model'!F45/(1+$B24)^('DCF Model'!C19+3)+'DCF Model'!G45/(1+$B24)^('DCF Model'!C19+4)+('DCF Model'!G39+'DCF Model'!G42)*C$17/(1+$B24)^('DCF Model'!C19+4)-'DCF Model'!C16)*1000000/'DCF Model'!C15,0),"") -> 2218 | D24: =IFERROR(ROUND(('DCF Model'!C45/(1+$B24)^('DCF Model'!C19+0)+'DCF Model'!D45/(1+$B24)^('DCF Model'!C19+1)+'DCF Model'!E45/(1+$B24)^('DCF Model'!C19+2)+'DCF Model'!F45/(1+$B24)^('DCF Model'!C19+3)+'DCF Model'!G45/(1+$B24)^('DCF Model'!C19+4)+('DCF Model'!G39+'DCF Model'!G42)*D$17/(1+$B24)^('DCF Model'!C19+4)-'DCF Model'!C16)*1000000/'DCF Model'!C15,0),"") -> 2521 | E24: =IFERROR(ROUND(('DCF Model'!C45/(1+$B24)^('DCF Model'!C19+0)+'DCF Model'!D45/(1+$B24)^('DCF Model'!C19+1)+'DCF Model'!E45/(1+$B24)^('DCF Model'!C19+2)+'DCF Model'!F45/(1+$B24)^('DCF Model'!C19+3)+'DCF Model'!G45/(1+$B24)^('DCF Model'!C19+4)+('DCF Model'!G39+'DCF Model'!G42)*E$17/(1+$B24)^('DCF Model'!C19+4)-'DCF Model'!C16)*1000000/'DCF Model'!C15,0),"") -> 2824 | F24: =IFERROR(ROUND(('DCF Model'!C45/(1+$B24)^('DCF Model'!C19+0)+'DCF Model'!D45/(1+$B24)^('DCF Model'!C19+1)+'DCF Model'!E45/(1+$B24)^('DCF Model'!C19+2)+'DCF Model'!F45/(1+$B24)^('DCF Model'!C19+3)+'DCF Model'!G45/(1+$B24)^('DCF Model'!C19+4)+('DCF Model'!G39+'DCF Model'!G42)*F$17/(1+$B24)^('DCF Model'!C19+4)-'DCF Model'!C16)*1000000/'DCF Model'!C15,0),"") -> 3126 | G24: =IFERROR(ROUND(('DCF Model'!C45/(1+$B24)^('DCF Model'!C19+0)+'DCF Model'!D45/(1+$B24)^('DCF Model'!C19+1)+'DCF Model'!E45/(1+$B24)^('DCF Model'!C19+2)+'DCF Model'!F45/(1+$B24)^('DCF Model'!C19+3)+'DCF Model'!G45/(1+$B24)^('DCF Model'!C19+4)+('DCF Model'!G39+'DCF Model'!G42)*G$17/(1+$B24)^('DCF Model'!C19+4)-'DCF Model'!C16)*1000000/'DCF Model'!C15,0),"") -> 3429 | H24: =IFERROR(ROUND(('DCF Model'!C45/(1+$B24)^('DCF Model'!C19+0)+'DCF Model'!D45/(1+$B24)^('DCF Model'!C19+1)+'DCF Model'!E45/(1+$B24)^('DCF Model'!C19+2)+'DCF Model'!F45/(1+$B24)^('DCF Model'!C19+3)+'DCF Model'!G45/(1+$B24)^('DCF Model'!C19+4)+('DCF Model'!G39+'DCF Model'!G42)*H$17/(1+$B24)^('DCF Model'!C19+4)-'DCF Model'!C16)*1000000/'DCF Model'!C15,0),"") -> 3732 | I24: =IFERROR(ROUND(('DCF Model'!C45/(1+$B24)^('DCF Model'!C19+0)+'DCF Model'!D45/(1+$B24)^('DCF Model'!C19+1)+'DCF Model'!E45/(1+$B24)^('DCF Model'!C19+2)+'DCF Model'!F45/(1+$B24)^('DCF Model'!C19+3)+'DCF Model'!G45/(1+$B24)^('DCF Model'!C19+4)+('DCF Model'!G39+'DCF Model'!G42)*I$17/(1+$B24)^('DCF Model'!C19+4)-'DCF Model'!C16)*1000000/'DCF Model'!C15,0),"") -> 4035
B26: All values dynamically linked to DCF Model. Headers auto-center on current WACC / Terminal g / Exit Multiple.

Sheet Adjustments Log
B2: Adjustments Log - キリンホールディングス
B4: 日付 | C4: セル | D4: 変更内容 | E4: 理由 | F4: 元の値 | G4: 状態
B5: 2026-09-05 | C5: - | D5: Generated by pipeline on 2026-09-05 22:39, template rev c9b5dd9 | E5: 初期生成（手修正なし） | F5: - | G5: generated
B6: 2026-09-05 | C6: DCF Model!C7 | D6: Risk-Free Rate = 2.97% | E6: 財務省 国債金利情報 jgbcm.csv 10年物 R8.9.3(2026-09-03) 2.966% を四捨五入。バッチ全銘柄共通の一次ソース。 | F6: テンプレ既定 2.2% | G6: 確定
B7: 2026-09-05 | C7: DCF Model!C9 | D7: Equity Risk Premium = 6.5% | E7: バッチ共通の固定前提(§1-3)。 | F7: テンプレ既定 6.5%(同値) | G7: 設計判断
B8: 2026-09-05 | C8: DCF Model!C10 | D8: Size Premium = 1.0% | E8: 時価総額バンドの機械決定(>3,000億円 -> 1.0%)。当社時価総額 2,320,500百万円。テンプレの自動規則(>=1兆円 -> 0.0%、>=1,000億円 -> 1.5%)とは異なる値であり、明示指定で上書きしている。当社は12月期。 | F8: テンプレ自動値 | G8: 設計判断
B9: 2026-09-05 | C9: DCF Model!C8 | D9: Beta = 0.60 | E9: yfinance実測は 0.044。テンプレは beta を [0.6, 1.75] にクランプし範囲外は【無言で 1.0 に置換】する(templates/dcf_comps_template.py:1819、生成ログでも確認)。サイレントフォールバック禁止の原則により許容域の下限 0.60 を明示指定し、当社の低ベータ性を保持した。0.60 は実測値ではなく『テンプレが受け付ける最小値』であることに注意。 | F9: yfinance実測 0.044 / テンプレ置換値 1.0 | G9: 設計判断
B10: 2026-09-05 | C10: DCF Model!C6 | D10: Effective Tax Rate = 25% | E10: バッチ共通の既定値(§1-3)。当社の実績税負担率を個別検証したものではない。 | F10: テンプレ既定 30% | G10: 推定
B11: 2026-09-05 | C11: DCF Model!C11 | D11: After-tax Cost of Debt = 1.54%(実績ベース) | E11: 支払利息 18,321百万円 ÷ 平均有利子負債 ((857,569 + 923,434)/2 = 890,502) = 2.06%(税引前)、× (1 − 25%) = 1.54%(validate チェック17 PASS)。■マージナルコスト注記: 既存借入の平均コストであり新規調達の限界コストではない。■出所は yfinance の Interest Expense で EDINET 有報の支払利息と未突合。 | F11: テンプレ既定(推定値) | G11: 推定(出所が二次ソース・要確認)
B12: 2026-09-05 | C12: DCF Model!C13 | D12: Terminal Growth = 1.0% | E12: バッチ共通の固定前提(§1-3)。 | F12: テンプレ既定 2.0% | G12: 設計判断
B13: 2026-09-05 | C13: DCF Model!C14 | D13: Exit Multiple (EV/EBITDA) = 11.1x | E13: Peer 5社の実測EV/EBITDA中央値 11.13x(2502 11.13 / 2802 18.89 / 2801 15.63 / 2269 8.35 / 2897 10.92)。 自社の現在倍率 10.21x は算式に入れていない(市場価格への循環参照回避)。■当初は Peer中央値にマージン優位分を上乗せする調整式を検討したが、EV/EBITDA は既に資本集約度を織り込んでおり営業利益率による上方調整は資本集約型銘柄で逆方向に働くため(9022 で実測 7.4x に対し調整式が 16.3x を返した)、バッチ全銘柄で素の Peer 中央値に統一した。 | F13: テンプレ既定 10.0x | G13: 設計判断
B14: 2026-09-05 | C14: DCF Model シナリオ5本 | D14: 実績OPM分布からの導出(min 5.36 / p25 5.71 / med 6.44 / p75 7.44 / max 8.62%) | E14: 直近FY2025/12 の 8.62% が実績中央値 6.44% を上回るため、Base の到達OPMは『直近実績と p75 の平均 = 8.03%』とし緩やかな平均回帰を置いた(Y1 8.5% → Y5 8.03%)。Upside は max(p75 7.44, 直近+1.0pt = 9.62) = 9.62%。Downside 1 は min(p25 5.71, 直近 8.62) = 5.71%。Downside 2 は実績トラフ 5.36% が Downside 1(5.71%)と近接し差別化できないため、売上−8%+固定費デレバレッジで 4.0-4.8% とした。SGA% は実績35.7→37.2%の直近水準37.0%を基準に調整し COGS% = 100% − OPM − SGA% で逆算。既存銘柄からの流用なし。 | F14: テンプレ自動生成シナリオ | G14: 設計判断
B15: 2026-09-05 | C15: Financial Statements / hist_* 系列 | D15: hist_years を FY2022-FY2025 の4期に置換し P/L 5系列を yfinance連結財務諸表から供給 | E15: 【リトライ1回目・§3-2 の補完】初回生成は FAIL 1(Financial Statements!D16:F16 = #DIV/0!)。原因は EDINET が hist_years を FY2017-FY2025 の9期で構築し、うち FY2018-FY2020 の営業利益を 0 で抽出していたこと。■EDINET の最新本決算は FY2025/12(docID S100XTVS)で取得できており最新期の欠落はない(2502・2802 とは異なる)。したがって fundamentals_fy ブロックは使っていない。■hist_ocf / hist_cash / hist_debt / hist_capex / hist_depreciation は【供給していない】 — Step 4.6 が会計年度キーで再マッピングするため、yfinance が未収録の FY2025/12 の D&A・capex を EDINET 実績で埋められる(生成ログの FS align は FY2022-FY2025 の4期すべてで ocf+cash+debt を確認)。■hist_sga = 売上 − COGS − 営業利益 で逆算。 | F15: EDINET自動抽出値(FY2017-FY2025、うち3期の営業利益が破損) | G15: 設計判断
... B23: 2026-09-05 | C23: 全体(納品状態) | D23: 本ファイルは DRAFT。_FINAL は付けない | E23: バッチモードでの機械生成物であり人間の検証を経ていない。FINAL化は手順書v2 §6 に従い検証後に行う。 | F23: - | G23: DRAFT
B25: Pipeline Metadata (do not edit — read by scripts/validate_output.py)
B26: key | C26: value
B27: auto_log_entries | C27: 1
B28: capex_pct_basis | C28: assumption
B29: capex_pct_c5 | C29: 0.0431
B30: capex_pct_hist3yr | C30: n/a
B31: company_name | C31: キリンホールディングス
B32: comps_asof | C32: 2026-09-05
B33: comps_da_missing | C33: none
B34: comps_ev_ebitda_invalid | C34: no
B35: comps_ev_ebitda_rows | C35: 6,7,8,9,10
B36: comps_impl_mult_row | C36: 27
B37: comps_impl_per_row | C37: 28
... B63: ticker | C63: 2503.T
