Workbook

Sheet Executive Summary
B1: DISCLAIMER: This is a sample analysis for demonstration purposes only. It does not constitute investment advice.
B3: Terra Drone (278A)
B4: Equity Research Report
B6: Company | C6: Terra Drone
B7: Ticker | C7: 278A (TSE Growth)
B8: Sector | C8: Industrial Drone Services / UTM
B9: Current Price | C9: 21620
B10: Target Price (DCF Mid) | C10: =IF(COUNT(C16:C17)=0,"N/A",ROUND(AVERAGE(C16:C17),0)) -> 529
B11: Recommendation | C11: =IF(NOT(ISNUMBER(C12)),"N/A",IF(C12>0.15,"BUY",IF(C12>0.05,"HOLD","SELL"))) -> SELL
B12: Upside / Downside | C12: =IF(ISNUMBER(C10),(C10-C9)/C9,"N/A") -> -0.97553191
B14: Valuation Summary
B15: Methodology | C15: Implied Value (JPY) | D15: vs Current Price
B16: DCF - Perpetuity Growth | C16: =IF('DCF Model'!C53<'DCF Model'!C16,"INVALID (EV < net debt)",'DCF Model'!C55) -> 59 | D16: =IF(ISNUMBER(C16),(C16-C9)/C9,"N/A") -> -0.99727105
B17: DCF - Exit Multiple | C17: =IF('DCF Model'!C62<'DCF Model'!C16,"INVALID (EV < net debt)",'DCF Model'!C64) -> 999 | D17: =IF(ISNUMBER(C17),(C17-C9)/C9,"N/A") -> -0.95379278
B18: Comps - EV/Sales Median [参考・Target不算入] | C18: ='Comps Analysis'!C27 -> 5725 | D18: =IF(ISNUMBER(C18),(C18-C9)/C9,"N/A") -> -0.73519889
B19: Comps - PER Median [参考・Target不算入] | C19: ='Comps Analysis'!C28 -> N/A | D19: =IF(ISNUMBER(C19),(C19-C9)/C9,"N/A") -> N/A
B20: Note: Target Mid は DCF 2法（PGM / Exit）の平均のみ。Comps 2法は [参考] で Target 不算入；PER法は赤字（純利益≦0）のため除外（EV<ネットデットで株式価値が負になる手法は INVALID として平均から除外）
B21: DCF Valuation Range (PGM - Exit) | C21: =IF(COUNT(C16:C17)=0,"N/A",MIN(C16:C17)&" - "&MAX(C16:C17)) -> 59 - 999
B23: Key Investment Thesis
B24: ="The August 2026 defence contract for the Terra B1 intercept drone re-rated the shares to "&TEXT(C9,"#,##0")&" from about 13,000 a month earlier. Its value, volume and schedule are all undisclosed, so this model measures two things only: what the price requires, and how far it can fall." -> The August 2026 defence contract for the Terra B1 intercept drone re-rated the shares to 21,620 from about 13,000 a month earlier. Its value, volume and schedule are all undisclosed, so this model measures two things only: what the price requires, and how far it can fall.
B25: ="At "&TEXT(C9,"#,##0")&" the enterprise value is about JPY222bn against FY1/26 revenue of JPY4,783mn. Growth is slowing as losses widen: sales rose 49.7%, then 7.8%, then 6.6%, while the operating loss went from JPY243mn to JPY627mn to JPY1,144mn." -> At 21,620 the enterprise value is about JPY222bn against FY1/26 revenue of JPY4,783mn. Growth is slowing as losses widen: sales rose 49.7%, then 7.8%, then 6.6%, while the operating loss went from JPY243mn to JPY627mn to JPY1,144mn.
B26: ="The DCF target of "&TEXT(C10,"#,##0")&" implies "&TEXT(C12,"+0.0%;-0.0%")&" at a WACC of "&TEXT('DCF Model'!C26,"0.00%")&", and the shares trade at "&TEXT('Comps Analysis'!M5,"0.00""x""")&" PBR. For a story-led name the target is not the point: the Reverse DCF sheet and the two downside scenarios are." -> The DCF target of 529 implies -97.6% at a WACC of 12.93%, and the shares trade at 50.19x PBR. For a story-led name the target is not the point: the Reverse DCF sheet and the two downside scenarios are.
B28: Key Risks
B29: Runway and dilution: FY1/26 burned JPY716mn of operating cash and JPY1,718mn of investing cash, and cash was JPY2,258mn at the end of April 2026 - roughly one year without external funding. Every prior year was funded by equity (JPY2,497mn at IPO, JPY617mn in FY1/26), so continued issuance is the base case and every per-share number in this workbook is pre-dilution and therefore flattering.
B30: The defence contract has no disclosed value, volume or schedule. Every defence assumption in this model is an estimate at JPY5.0mn per unit, and the whole re-rating rests on a programme whose economics are unknown; the second-quarter results due in mid-September 2026 and any follow-on disclosure are the near-term catalysts in both directions.
B31: Both segments were loss-making and getting worse before the contract: Drone Solutions swung from a JPY194mn to a JPY435mn segment loss and UTM from JPY433mn to JPY709mn, with a further JPY439mn of equity-method losses below the line, and the whole business carries theme-stock volatility of about 115% annualised.

Sheet Financial Statements
B2: Terra Drone - Historical Financials (JPY mn)
C4: FY2024/1 | D4: FY2025/1 | E4: FY2026/1
B5: Income Statement
B6: Revenue | C6: 2963.3 | D6: 4435.6 | E6: 4782.6
B7: COGS | C7: 1424.1 | D7: 2144 | E7: 2469.7
B8: Gross Profit | C8: =C6-C7 -> 1539.2 | D8: =D6-D7 -> 2291.6 | E8: =E6-E7 -> 2312.9
B9: Gross Margin | C9: =C8/C6 -> 0.51942092 | D9: =D8/D6 -> 0.51663811 | E9: =E8/E6 -> 0.48360724
B10: SGA | C10: 1782.3 | D10: 2918.8 | E10: 3456.7
B11: Operating Income | C11: -243.1 | D11: -627.2 | E11: -1143.8
B12: Net Income | C12: -353.9 | D12: -474.8 | E12: -2497.9
B13: Operating Margin | C13: =C11/C6 -> -0.082036918 | D13: =D11/D6 -> -0.14140139 | E13: =E11/E6 -> -0.23915862
B14: Net Margin | C14: =C12/C6 -> -0.11942767 | D14: =D12/D6 -> -0.10704302 | E14: =E12/E6 -> -0.52228913
B15: Revenue Growth (YoY) | C15: n/a | D15: =(D6-C6)/C6 -> 0.49684473 | E15: =(E6-D6)/D6 -> 0.078230679
B16: Operating Income Growth (YoY) | C16: n/a | D16: =(D11-C11)/C11 -> 1.5800082 | E16: =(E11-D11)/D11 -> 0.82366071
B18: Cash Flow Statement
B19: Operating Cash Flow | C19: -15.6 | D19: -927.9 | E19: -716.5
B20: Capex | C20: 249.9 | D20: 683.4 | E20: 875.9
B21: Free Cash Flow | C21: =C19-C20 -> -265.5 | D21: =D19-D20 -> -1611.3 | E21: =E19-E20 -> -1592.4
B22: FCF Margin | C22: =C21/C6 -> -0.089596058 | D22: =D21/D6 -> -0.3632654 | E22: =E21/E6 -> -0.33295697
B23: Capex / Revenue | C23: =C20/C6 -> 0.084331657 | D23: =D20/D6 -> 0.1540716 | E23: =E20/E6 -> 0.18314306
B25: Balance Sheet Highlights
B26: Cash & Deposits | C26: 5008.7 | D26: 4145.6 | E26: 2019
B27: Total Interest-bearing Debt (short + long) | C27: 965.1 | D27: 570.5 | E27: 0
B28: Net Debt (Cash) | C28: =C27-C26 -> -4043.6 | D28: =D27-D26 -> -3575.1 | E28: =E27-E26 -> -2019
B30: Note: OCF / Cash / Debt coverage OCF 3/3, Cash 3/3, Debt 3/3 — blank cells are years with no year-key match in the source data (verify against 決算短信 or set hist_ocf / hist_cash / hist_debt in overrides).

Sheet DCF Model
B2: DCF Valuation Model - Terra Drone
B4: Assumptions
B5: Capex / Revenue | C5: 0.075
B6: Effective Tax Rate | C6: 0.306
B7: Risk-Free Rate | C7: 0.029
B8: Beta | C8: 1.55
B9: Equity Risk Premium | C9: 0.055
B10: Size Premium | C10: 0.015
B11: After-tax Cost of Debt | C11: 0.014
B12: D/E Ratio | C12: 0
B13: Terminal Growth Rate | C13: 0.02
B14: Exit Multiple (EV/Sales) | C14: 2
B15: Fully Diluted Shares | C15: 10397100
B16: Net Debt (JPY mn) | C16: -2257
... B20: LTM Revenue (JPY mn) (override) | C20: 4845.6
B22: WACC Calculation
B23: Cost of Equity (Ke) | C23: =C7+C8*C9+C10 -> 0.12925
B24: Weight of Equity | C24: =1/(1+C12) -> 1
B25: Weight of Debt | C25: =C12/(1+C12) -> 0
B26: WACC | C26: =C23*C24+C11*C25 -> 0.12925
B27: Active Scenario | C27: Base | D27: =MATCH(C27,B69:B73,0) -> 1
B28: Projected Free Cash Flow
C29: FY2027(E) | D29: FY2028(E) | E29: FY2029(E) | F29: FY2030(E) | G29: FY2031(E) | H29: FY2032(E) | I29: FY2033(E) | J29: FY2034(E)
B30: Revenue Growth (YoY) | C30: =CHOOSE($D$27,C69,C70,C71,C72,C73) -> 0.1619 | D30: =CHOOSE($D$27,D69,D70,D71,D72,D73) -> 0.2597 | E30: =CHOOSE($D$27,E69,E70,E71,E72,E73) -> 0.2743 | F30: =CHOOSE($D$27,F69,F70,F71,F72,F73) -> 0.2099 | G30: =CHOOSE($D$27,G69,G70,G71,G72,G73) -> 0.1567 | H30: =CHOOSE($D$27,H69,H70,H71,H72,H73) -> 0.1025 | I30: =CHOOSE($D$27,I69,I70,I71,I72,I73) -> 0.0743 | J30: =CHOOSE($D$27,J69,J70,J71,J72,J73) -> 0.0511
B31: COGS % of Revenue | C31: =CHOOSE($D$27,C76,C77,C78,C79,C80) -> 0.555 | D31: =CHOOSE($D$27,D76,D77,D78,D79,D80) -> 0.56 | E31: =CHOOSE($D$27,E76,E77,E78,E79,E80) -> 0.57 | F31: =CHOOSE($D$27,F76,F77,F78,F79,F80) -> 0.57 | G31: =CHOOSE($D$27,G76,G77,G78,G79,G80) -> 0.57 | H31: =CHOOSE($D$27,H76,H77,H78,H79,H80) -> 0.57 | I31: =CHOOSE($D$27,I76,I77,I78,I79,I80) -> 0.57 | J31: =CHOOSE($D$27,J76,J77,J78,J79,J80) -> 0.57
B32: SGA % of Revenue | C32: =CHOOSE($D$27,C83,C84,C85,C86,C87) -> 0.702 | D32: =CHOOSE($D$27,D83,D84,D85,D86,D87) -> 0.604 | E32: =CHOOSE($D$27,E83,E84,E85,E86,E87) -> 0.514 | F32: =CHOOSE($D$27,F83,F84,F85,F86,F87) -> 0.456 | G32: =CHOOSE($D$27,G83,G84,G85,G86,G87) -> 0.42 | H32: =CHOOSE($D$27,H83,H84,H85,H86,H87) -> 0.376 | I32: =CHOOSE($D$27,I83,I84,I85,I86,I87) -> 0.35 | J32: =CHOOSE($D$27,J83,J84,J85,J86,J87) -> 0.33
B33: Revenue | C33: =C17*(1+C30) -> 5556.9029 | D33: =C33*(1+D30) -> 7000.0306 | E33: =D33*(1+E30) -> 8920.139 | F33: =E33*(1+F30) -> 10792.476 | G33: =F33*(1+G30) -> 12483.657 | H33: =G33*(1+H30) -> 13763.232 | I33: =H33*(1+I30) -> 14785.84 | J33: =I33*(1+J30) -> 15541.397
B34: COGS | C34: =C33*C31 -> 3084.0811 | D34: =D33*D31 -> 3920.0172 | E34: =E33*E31 -> 5084.4793 | F34: =F33*F31 -> 6151.7114 | G34: =G33*G31 -> 7115.6846 | H34: =H33*H31 -> 7845.0423 | I34: =I33*I31 -> 8427.9289 | J34: =J33*J31 -> 8858.5961
B35: Gross Profit | C35: =C33-C34 -> 2472.8218 | D35: =D33-D34 -> 3080.0135 | E35: =E33-E34 -> 3835.6598 | F35: =F33-F34 -> 4640.7648 | G35: =G33-G34 -> 5367.9726 | H35: =H33-H34 -> 5918.1898 | I35: =I33-I34 -> 6357.9113 | J35: =J33-J34 -> 6682.8006
B36: Gross Margin | C36: =C35/C33 -> 0.445 | D36: =D35/D33 -> 0.44 | E36: =E35/E33 -> 0.43 | F36: =F35/F33 -> 0.43 | G36: =G35/G33 -> 0.43 | H36: =H35/H33 -> 0.43 | I36: =I35/I33 -> 0.43 | J36: =J35/J33 -> 0.43
B37: SGA Expense | C37: =C33*C32 -> 3900.9459 | D37: =D33*D32 -> 4228.0185 | E37: =E33*E32 -> 4584.9515 | F37: =F33*F32 -> 4921.3692 | G37: =G33*G32 -> 5243.136 | H37: =H33*H32 -> 5174.9753 | I37: =I33*I32 -> 5175.0441 | J37: =J33*J32 -> 5128.6609
B38: Implied Operating Margin | C38: =(C35-C37)/C33 -> -0.257 | D38: =(D35-D37)/D33 -> -0.164 | E38: =(E35-E37)/E33 -> -0.084 | F38: =(F35-F37)/F33 -> -0.026 | G38: =(G35-G37)/G33 -> 0.01 | H38: =(H35-H37)/H33 -> 0.054 | I38: =(I35-I37)/I33 -> 0.08 | J38: =(J35-J37)/J33 -> 0.1
B39: Operating Income (EBIT) | C39: =C35-C37 -> -1428.1241 | D39: =D35-D37 -> -1148.005 | E39: =E35-E37 -> -749.29168 | F39: =F35-F37 -> -280.60438 | G39: =G35-G37 -> 124.83657 | H39: =H35-H37 -> 743.21453 | I39: =I35-I37 -> 1182.8672 | J39: =J35-J37 -> 1554.1397
B40: Less: Tax | C40: =MAX(0,C39*C6) -> 0 | D40: =MAX(0,D39*C6) -> 0 | E40: =MAX(0,E39*C6) -> 0 | F40: =MAX(0,F39*C6) -> 0 | G40: =MAX(0,G39*C6) -> 38.199991 | H40: =MAX(0,H39*C6) -> 227.42365 | I40: =MAX(0,I39*C6) -> 361.95737 | J40: =MAX(0,J39*C6) -> 475.56674
B41: NOPAT | C41: =C39-C40 -> -1428.1241 | D41: =D39-D40 -> -1148.005 | E41: =E39-E40 -> -749.29168 | F41: =F39-F40 -> -280.60438 | G41: =G39-G40 -> 86.636581 | H41: =H39-H40 -> 515.79089 | I41: =I39-I40 -> 820.90985 | J41: =J39-J40 -> 1078.5729
B42: Plus: D&A | C42: =C33*C18 -> 388.98321 | D42: =D33*C18 -> 490.00214 | E42: =E33*C18 -> 624.40973 | F42: =F33*C18 -> 755.47334 | G42: =G33*C18 -> 873.85601 | H42: =H33*C18 -> 963.42625 | I42: =I33*C18 -> 1035.0088 | J42: =J33*C18 -> 1087.8978
B43: Less: Capex | C43: =C33*C5 -> 416.76772 | D43: =D33*C5 -> 525.0023 | E43: =E33*C5 -> 669.01043 | F43: =F33*C5 -> 809.43572 | G43: =G33*C5 -> 936.27429 | H43: =H33*C5 -> 1032.2424 | I43: =I33*C5 -> 1108.938 | J43: =J33*C5 -> 1165.6048
B44: Change in NWC | C44: ='NWC Schedule'!D19 -> 281.14162 | D44: ='NWC Schedule'!E19 -> 482.74457 | E44: ='NWC Schedule'!F19 -> 627.57729 | F44: ='NWC Schedule'!G19 -> 651.98372 | G44: ='NWC Schedule'!H19 -> 520.49806 | H44: ='NWC Schedule'!I19 -> 395.57461 | I44: ='NWC Schedule'!J19 -> 225.76708 | J44: ='NWC Schedule'!K19 -> 250.38933
B45: Unlevered Free Cash Flow | C45: =C41+C42-C43-C44 -> -1737.0502 | D45: =D41+D42-D43-D44 -> -1665.7497 | E45: =E41+E42-E43-E44 -> -1421.4697 | F45: =F41+F42-F43-F44 -> -986.55048 | G45: =G41+G42-G43-G44 -> -496.27977 | H45: =H41+H42-H43-H44 -> 51.40012 | I45: =I41+I42-I43-I44 -> 521.21357 | J45: =J41+J42-J43-J44 -> 750.47661
B46: Discount Factor | C46: =1/(1+C26)^(C19+0) -> 0.95022873 | D46: =1/(1+C26)^(C19+1) -> 0.84146888 | E46: =1/(1+C26)^(C19+2) -> 0.7451573 | F46: =1/(1+C26)^(C19+3) -> 0.6598692 | G46: =1/(1+C26)^(C19+4) -> 0.58434289 | H46: =1/(1+C26)^(C19+5) -> 0.51746105 | I46: =1/(1+C26)^(C19+6) -> 0.45823427 | J46: =1/(1+C26)^(C19+7) -> 0.40578638
B47: PV of FCF | C47: =C45*C46 -> -1650.595 | D47: =D45*D46 -> -1401.6766 | E47: =E45*E46 -> -1059.2185 | F47: =F45*F46 -> -650.99428 | G47: =G45*G46 -> -289.99755 | H47: =H45*H46 -> 26.59756 | I47: =I45*I46 -> 238.83792 | J47: =J45*J46 -> 304.53319
B49: Valuation - Perpetuity Growth Method
B50: Sum of PV of FCFs | C50: =SUM(C47:J47) -> -4482.5132
B51: Terminal Value (PGM) | C51: =J45*(1+C13)/(C26-C13) -> 7006.7382
B52: PV of Terminal Value | C52: =C51*J46 -> 2843.2389
B53: Enterprise Value | C53: =C50+C52 -> -1639.2743
B54: Equity Value | C54: =C53-C16 -> 617.72566
B55: Implied Share Price (PGM) | C55: =ROUND(C54*1000000/C15,0) -> 59
B57: Valuation - Exit Multiple Method
B58: Sum of PV of FCFs | C58: =C50 -> -4482.5132
B59: Year 5 Revenue | C59: =J33 -> 15541.397
B60: Terminal Value (Exit Multiple) | C60: =C59*C14 -> 31082.793
B61: PV of Terminal Value | C61: =C60*J46 -> 12612.974
B62: Enterprise Value | C62: =C58+C61 -> 8130.4609
B63: Equity Value | C63: =C62-C16 -> 10387.461
B64: Implied Share Price (Exit Multiple) | C64: =ROUND(C63*1000000/C15,0) -> 999
B66: Scenario Input Matrix
C67: Year 1 | D67: Year 2 | E67: Year 3 | F67: Year 4 | G67: Year 5 | H67: Year 6 | I67: Year 7 | J67: Year 8
B68: Revenue Growth (YoY)
B69: Base | C69: 0.1619 | D69: 0.2597 | E69: 0.2743 | F69: 0.2099 | G69: 0.1567 | H69: 0.1025 | I69: 0.0743 | J69: 0.0511
B70: Upside | C70: 0.3047 | D70: 0.5045 | E70: 0.5195 | F70: 0.4664 | G70: 0.3578 | H70: 0.207 | I70: 0.1417 | J70: 0.0876
B71: Management | C71: 0.0607 | D71: 0.301 | E71: 0.303 | F71: 0.2674 | G71: 0.1927 | H71: 0.15 | I71: 0.1 | J71: 0.06
B72: Downside 1 | C72: 0.1019 | D72: 0.0482 | E72: 0.0313 | F72: 0.06 | G72: 0.0599 | H72: 0.06 | I72: 0.06 | J72: 0.0601
B73: Downside 2 | C73: 0.0245 | D73: -0.0102 | E73: -0.0206 | F73: -0.0105 | G73: 0 | H73: 0.0106 | I73: 0.0105 | J73: 0.0104
B75: COGS % of Revenue
B76: Base | C76: 0.555 | D76: 0.56 | E76: 0.57 | F76: 0.57 | G76: 0.57 | H76: 0.57 | I76: 0.57 | J76: 0.57
B77: Upside | C77: 0.55 | D77: 0.55 | E77: 0.56 | F77: 0.56 | G77: 0.56 | H77: 0.56 | I77: 0.56 | J77: 0.56
B78: Management | C78: 0.555 | D78: 0.56 | E78: 0.565 | F78: 0.57 | G78: 0.57 | H78: 0.57 | I78: 0.57 | J78: 0.57
B79: Downside 1 | C79: 0.56 | D79: 0.56 | E79: 0.56 | F79: 0.56 | G79: 0.56 | H79: 0.56 | I79: 0.56 | J79: 0.56
B80: Downside 2 | C80: 0.58 | D80: 0.58 | E80: 0.58 | F80: 0.58 | G80: 0.58 | H80: 0.58 | I80: 0.58 | J80: 0.58
B82: SGA % of Revenue
B83: Base | C83: 0.702 | D83: 0.604 | E83: 0.514 | F83: 0.456 | G83: 0.42 | H83: 0.376 | I83: 0.35 | J83: 0.33
B84: Upside | C84: 0.641 | D84: 0.511 | E84: 0.4 | F84: 0.325 | G84: 0.29 | H84: 0.29 | I84: 0.29 | J84: 0.29
B85: Management | C85: 0.772 | D85: 0.607 | E85: 0.482 | F85: 0.407 | G85: 0.361 | H85: 0.33 | I85: 0.31 | J85: 0.305
B86: Downside 1 | C86: 0.702 | D86: 0.68 | E86: 0.66 | F86: 0.64 | G86: 0.625 | H86: 0.61 | I86: 0.6 | J86: 0.59
B87: Downside 2 | C87: 0.714 | D87: 0.71 | E87: 0.71 | F87: 0.71 | G87: 0.71 | H87: 0.71 | I87: 0.71 | J87: 0.71

Sheet Reverse DCF
B2: Reverse DCF - Terra Drone (278A)
B3: What is the current share price already assuming? Every value below is a live formula off the other sheets.
B5: Block 0: Market-implied enterprise value (live)
B6: Current Share Price (JPY) | C6: ='Executive Summary'!C9 -> 21620
B7: Fully Diluted Shares | C7: ='DCF Model'!C15 -> 10397100
B8: Market Capitalisation (JPY mn) | C8: =C6*C7/1000000 -> 224785.3
B9: Net Debt (JPY mn) | C9: ='DCF Model'!C16 -> -2257
B10: Enterprise Value (JPY mn) | C10: =C8+C9 -> 222528.3
B11: WACC (w) | C11: ='DCF Model'!C26 -> 0.12925
B12: Terminal Growth (g) | C12: ='DCF Model'!C13 -> 0.02
B13: Effective Tax Rate (t) | C13: ='DCF Model'!C6 -> 0.306
B14: Starting Operating Profit OP0 (FY2026/1 actual) | C14: -1143.8
B15: Cycle-peak Operating Profit (Upside scenario FY2034/1 - model, not actual) | C15: 6385
B16: Terminal-year Revenue, active scenario (JPY mn) | C16: ='DCF Model'!J33 -> 15541.397
B17: Base-case DCF Enterprise Value, PGM (JPY mn) | C17: ='DCF Model'!C53 -> -1639.2743
B18: Cycle-peak Operating Margin (Upside scenario FY2034/1 - model, not actual) | C18: 0.15
B19: Gap: market EV less base-case DCF EV (JPY mn) | C19: =C10-C17 -> 224167.58
B20: Gap per share (JPY) - the part of the price the base case does not explain | C20: =IFERROR(ROUND(C19*1000000/C7,0),"N/A") -> 21561
B22: Block A: Required steady-state operating profit, reached IMMEDIATELY (no ramp)
B23: The lowest bar the price can clear: today's EV read as a perpetuity of one steady-state profit, capex = D&A, no NWC build.
B24: Required steady-state NOPAT (JPY mn) | C24: =C10*(C11-C12) -> 24311.217
B25: Required steady-state Operating Profit (JPY mn) | C25: =IFERROR(C24/(1-C13),"N/A") -> 35030.572
B26: ... as a multiple of the Upside scenario FY2034/1 - model, not peak | C26: =IFERROR(C25/C15,"N/A") -> 5.4863856
B27: ... as a multiple of FY2026/1 actual | C27: =IFERROR(C25/C14,"N/A") -> -30.626484
B28: ... implied OPM on terminal-year revenue | C28: =IFERROR(C25/C16,"N/A") -> 2.254017
B29: ... revenue needed if margins only reach the cycle peak | C29: =IFERROR(C25/C18,"N/A") -> 233537.15
B32: Block B: Required steady-state operating profit by YEARS-TO-REACH (linear ramp) x WACC
B33: Operating profit ramps linearly from OP0 (C14) to OP* over N years, then grows at g for ever. Column F is the model WACC.
B34: OP* = ( EV/(1-t) - OP0*(A-B) ) / ( B + TVF ). A longer ramp needs a HIGHER steady state, because more years are spent below it.
B36: Years to steady state (N) \ WACC | C36: N | D36: ='DCF Model'!C26-0.02 -> 0.10925 | E36: ='DCF Model'!C26-0.01 -> 0.11925 | F36: ='DCF Model'!C26 -> 0.12925 | G36: ='DCF Model'!C26+0.01 -> 0.13925 | H36: ='DCF Model'!C26+0.02 -> 0.14925
B37: B-1 PV weight on the RAMP from OP0 (A - B)
B38: N = 5 years | C38: 5 | D38: =IFERROR((1-(1+D$36)^(-$C38))/D$36-(1+D$36)/(D$36^2*$C38)*(1-($C38+1)/(1+D$36)^$C38+$C38/(1+D$36)^($C38+1)),"N/A") -> 1.6340133 | E38: =IFERROR((1-(1+E$36)^(-$C38))/E$36-(1+E$36)/(E$36^2*$C38)*(1-($C38+1)/(1+E$36)^$C38+$C38/(1+E$36)^($C38+1)),"N/A") -> 1.6064514 | F38: =IFERROR((1-(1+F$36)^(-$C38))/F$36-(1+F$36)/(F$36^2*$C38)*(1-($C38+1)/(1+F$36)^$C38+$C38/(1+F$36)^($C38+1)),"N/A") -> 1.5797099 | G38: =IFERROR((1-(1+G$36)^(-$C38))/G$36-(1+G$36)/(G$36^2*$C38)*(1-($C38+1)/(1+G$36)^$C38+$C38/(1+G$36)^($C38+1)),"N/A") -> 1.5537553 | H38: =IFERROR((1-(1+H$36)^(-$C38))/H$36-(1+H$36)/(H$36^2*$C38)*(1-($C38+1)/(1+H$36)^$C38+$C38/(1+H$36)^($C38+1)),"N/A") -> 1.5285559
B39: N = 8 years | C39: 8 | D39: =IFERROR((1-(1+D$36)^(-$C39))/D$36-(1+D$36)/(D$36^2*$C39)*(1-($C39+1)/(1+D$36)^$C39+$C39/(1+D$36)^($C39+1)),"N/A") -> 2.6045347 | E39: =IFERROR((1-(1+E$36)^(-$C39))/E$36-(1+E$36)/(E$36^2*$C39)*(1-($C39+1)/(1+E$36)^$C39+$C39/(1+E$36)^($C39+1)),"N/A") -> 2.5423159 | F39: =IFERROR((1-(1+F$36)^(-$C39))/F$36-(1+F$36)/(F$36^2*$C39)*(1-($C39+1)/(1+F$36)^$C39+$C39/(1+F$36)^($C39+1)),"N/A") -> 2.4826367 | G39: =IFERROR((1-(1+G$36)^(-$C39))/G$36-(1+G$36)/(G$36^2*$C39)*(1-($C39+1)/(1+G$36)^$C39+$C39/(1+G$36)^($C39+1)),"N/A") -> 2.4253591 | H39: =IFERROR((1-(1+H$36)^(-$C39))/H$36-(1+H$36)/(H$36^2*$C39)*(1-($C39+1)/(1+H$36)^$C39+$C39/(1+H$36)^($C39+1)),"N/A") -> 2.3703541
B40: N = 10 years | C40: 10 | D40: =IFERROR((1-(1+D$36)^(-$C40))/D$36-(1+D$36)/(D$36^2*$C40)*(1-($C40+1)/(1+D$36)^$C40+$C40/(1+D$36)^($C40+1)),"N/A") -> 3.1549419 | E40: =IFERROR((1-(1+E$36)^(-$C40))/E$36-(1+E$36)/(E$36^2*$C40)*(1-($C40+1)/(1+E$36)^$C40+$C40/(1+E$36)^($C40+1)),"N/A") -> 3.0662686 | F40: =IFERROR((1-(1+F$36)^(-$C40))/F$36-(1+F$36)/(F$36^2*$C40)*(1-($C40+1)/(1+F$36)^$C40+$C40/(1+F$36)^($C40+1)),"N/A") -> 2.9818207 | G40: =IFERROR((1-(1+G$36)^(-$C40))/G$36-(1+G$36)/(G$36^2*$C40)*(1-($C40+1)/(1+G$36)^$C40+$C40/(1+G$36)^($C40+1)),"N/A") -> 2.9013326 | H40: =IFERROR((1-(1+H$36)^(-$C40))/H$36-(1+H$36)/(H$36^2*$C40)*(1-($C40+1)/(1+H$36)^$C40+$C40/(1+H$36)^($C40+1)),"N/A") -> 2.8245588
B41: N = 15 years | C41: 15 | D41: =IFERROR((1-(1+D$36)^(-$C41))/D$36-(1+D$36)/(D$36^2*$C41)*(1-($C41+1)/(1+D$36)^$C41+$C41/(1+D$36)^($C41+1)),"N/A") -> 4.2656866 | E41: =IFERROR((1-(1+E$36)^(-$C41))/E$36-(1+E$36)/(E$36^2*$C41)*(1-($C41+1)/(1+E$36)^$C41+$C41/(1+E$36)^($C41+1)),"N/A") -> 4.1069533 | F41: =IFERROR((1-(1+F$36)^(-$C41))/F$36-(1+F$36)/(F$36^2*$C41)*(1-($C41+1)/(1+F$36)^$C41+$C41/(1+F$36)^($C41+1)),"N/A") -> 3.9582177 | G41: =IFERROR((1-(1+G$36)^(-$C41))/G$36-(1+G$36)/(G$36^2*$C41)*(1-($C41+1)/(1+G$36)^$C41+$C41/(1+G$36)^($C41+1)),"N/A") -> 3.8186559 | H41: =IFERROR((1-(1+H$36)^(-$C41))/H$36-(1+H$36)/(H$36^2*$C41)*(1-($C41+1)/(1+H$36)^$C41+$C41/(1+H$36)^($C41+1)),"N/A") -> 3.6875249
B42: B-2 PV weight on the STEADY STATE OP* (B + terminal factor)
B43: N = 5 years | C43: 5 | D43: =IFERROR((1+D$36)/(D$36^2*$C43)*(1-($C43+1)/(1+D$36)^$C43+$C43/(1+D$36)^($C43+1))+(1+$C$12)/((D$36-$C$12)*(1+D$36)^$C43),"N/A") -> 8.8741278 | E43: =IFERROR((1+E$36)/(E$36^2*$C43)*(1-($C43+1)/(1+E$36)^$C43+$C43/(1+E$36)^($C43+1))+(1+$C$12)/((E$36-$C$12)*(1+E$36)^$C43),"N/A") -> 7.856087 | F43: =IFERROR((1+F$36)/(F$36^2*$C43)*(1-($C43+1)/(1+F$36)^$C43+$C43/(1+F$36)^($C43+1))+(1+$C$12)/((F$36-$C$12)*(1+F$36)^$C43),"N/A") -> 7.0282329 | G43: =IFERROR((1+G$36)/(G$36^2*$C43)*(1-($C43+1)/(1+G$36)^$C43+$C43/(1+G$36)^($C43+1))+(1+$C$12)/((G$36-$C$12)*(1+G$36)^$C43),"N/A") -> 6.3425637 | H43: =IFERROR((1+H$36)/(H$36^2*$C43)*(1-($C43+1)/(1+H$36)^$C43+$C43/(1+H$36)^($C43+1))+(1+$C$12)/((H$36-$C$12)*(1+H$36)^$C43),"N/A") -> 5.7659408
B44: N = 8 years | C44: 8 | D44: =IFERROR((1+D$36)/(D$36^2*$C44)*(1-($C44+1)/(1+D$36)^$C44+$C44/(1+D$36)^($C44+1))+(1+$C$12)/((D$36-$C$12)*(1+D$36)^$C44),"N/A") -> 7.5414291 | E44: =IFERROR((1+E$36)/(E$36^2*$C44)*(1-($C44+1)/(1+E$36)^$C44+$C44/(1+E$36)^($C44+1))+(1+$C$12)/((E$36-$C$12)*(1+E$36)^$C44),"N/A") -> 6.611411 | F44: =IFERROR((1+F$36)/(F$36^2*$C44)*(1-($C44+1)/(1+F$36)^$C44+$C44/(1+F$36)^($C44+1))+(1+$C$12)/((F$36-$C$12)*(1+F$36)^$C44),"N/A") -> 5.8591567 | G44: =IFERROR((1+G$36)/(G$36^2*$C44)*(1-($C44+1)/(1+G$36)^$C44+$C44/(1+G$36)^($C44+1))+(1+$C$12)/((G$36-$C$12)*(1+G$36)^$C44),"N/A") -> 5.2395214 | H44: =IFERROR((1+H$36)/(H$36^2*$C44)*(1-($C44+1)/(1+H$36)^$C44+$C44/(1+H$36)^($C44+1))+(1+$C$12)/((H$36-$C$12)*(1+H$36)^$C44),"N/A") -> 4.7213601
B45: N = 10 years | C45: 10 | D45: =IFERROR((1+D$36)/(D$36^2*$C45)*(1-($C45+1)/(1+D$36)^$C45+$C45/(1+D$36)^($C45+1))+(1+$C$12)/((D$36-$C$12)*(1+D$36)^$C45),"N/A") -> 6.8051195 | E45: =IFERROR((1+E$36)/(E$36^2*$C45)*(1-($C45+1)/(1+E$36)^$C45+$C45/(1+E$36)^($C45+1))+(1+$C$12)/((E$36-$C$12)*(1+E$36)^$C45),"N/A") -> 5.9325275 | F45: =IFERROR((1+F$36)/(F$36^2*$C45)*(1-($C45+1)/(1+F$36)^$C45+$C45/(1+F$36)^($C45+1))+(1+$C$12)/((F$36-$C$12)*(1+F$36)^$C45),"N/A") -> 5.2294385 | G45: =IFERROR((1+G$36)/(G$36^2*$C45)*(1-($C45+1)/(1+G$36)^$C45+$C45/(1+G$36)^($C45+1))+(1+$C$12)/((G$36-$C$12)*(1+G$36)^$C45),"N/A") -> 4.6525635 | H45: =IFERROR((1+H$36)/(H$36^2*$C45)*(1-($C45+1)/(1+H$36)^$C45+$C45/(1+H$36)^($C45+1))+(1+$C$12)/((H$36-$C$12)*(1+H$36)^$C45),"N/A") -> 4.1720608
B46: N = 15 years | C46: 15 | D46: =IFERROR((1+D$36)/(D$36^2*$C46)*(1-($C46+1)/(1+D$36)^$C46+$C46/(1+D$36)^($C46+1))+(1+$C$12)/((D$36-$C$12)*(1+D$36)^$C46),"N/A") -> 5.3680151 | E46: =IFERROR((1+E$36)/(E$36^2*$C46)*(1-($C46+1)/(1+E$36)^$C46+$C46/(1+E$36)^($C46+1))+(1+$C$12)/((E$36-$C$12)*(1+E$36)^$C46),"N/A") -> 4.62782 | F46: =IFERROR((1+F$36)/(F$36^2*$C46)*(1-($C46+1)/(1+F$36)^$C46+$C46/(1+F$36)^($C46+1))+(1+$C$12)/((F$36-$C$12)*(1+F$36)^$C46),"N/A") -> 4.0370216 | G46: =IFERROR((1+G$36)/(G$36^2*$C46)*(1-($C46+1)/(1+G$36)^$C46+$C46/(1+G$36)^($C46+1))+(1+$C$12)/((G$36-$C$12)*(1+G$36)^$C46),"N/A") -> 3.5568104 | H46: =IFERROR((1+H$36)/(H$36^2*$C46)*(1-($C46+1)/(1+H$36)^$C46+$C46/(1+H$36)^($C46+1))+(1+$C$12)/((H$36-$C$12)*(1+H$36)^$C46),"N/A") -> 3.1605132
B47: B-3 REQUIRED steady-state Operating Profit (JPY mn)
B48: N = 5 years | C48: 5 | D48: =IFERROR(($C$10/(1-$C$13)-$C$14*D38)/D43,"N/A") -> 36343.285 | E48: =IFERROR(($C$10/(1-$C$13)-$C$14*E38)/E43,"N/A") -> 41048.862 | F48: =IFERROR(($C$10/(1-$C$13)-$C$14*F38)/F43,"N/A") -> 45879.646 | G48: =IFERROR(($C$10/(1-$C$13)-$C$14*G38)/G43,"N/A") -> 50834.831 | H48: =IFERROR(($C$10/(1-$C$13)-$C$14*H38)/H43,"N/A") -> 55913.569
B49: N = 8 years | C49: 8 | D49: =IFERROR(($C$10/(1-$C$13)-$C$14*D39)/D44,"N/A") -> 42912.959 | E49: =IFERROR(($C$10/(1-$C$13)-$C$14*E39)/E44,"N/A") -> 48938.702 | F49: =IFERROR(($C$10/(1-$C$13)-$C$14*F39)/F44,"N/A") -> 55210.267 | G49: =IFERROR(($C$10/(1-$C$13)-$C$14*G39)/G44,"N/A") -> 61727.029 | H49: =IFERROR(($C$10/(1-$C$13)-$C$14*H39)/H44,"N/A") -> 68488.142
B50: N = 10 years | C50: 10 | D50: =IFERROR(($C$10/(1-$C$13)-$C$14*D40)/D45,"N/A") -> 47648.626 | E50: =IFERROR(($C$10/(1-$C$13)-$C$14*E40)/E45,"N/A") -> 54639.977 | F50: =IFERROR(($C$10/(1-$C$13)-$C$14*F40)/F45,"N/A") -> 61967.757 | G50: =IFERROR(($C$10/(1-$C$13)-$C$14*G40)/G45,"N/A") -> 69631.401 | H50: =IFERROR(($C$10/(1-$C$13)-$C$14*H40)/H45,"N/A") -> 77629.909
B51: N = 15 years | C51: 15 | D51: =IFERROR(($C$10/(1-$C$13)-$C$14*D41)/D46,"N/A") -> 60641.606 | E51: =IFERROR(($C$10/(1-$C$13)-$C$14*E41)/E46,"N/A") -> 70301.675 | F51: =IFERROR(($C$10/(1-$C$13)-$C$14*F41)/F46,"N/A") -> 80547.842 | G51: =IFERROR(($C$10/(1-$C$13)-$C$14*G41)/G46,"N/A") -> 91377.868 | H51: =IFERROR(($C$10/(1-$C$13)-$C$14*H41)/H46,"N/A") -> 102788.29
B52: B-4 ... as a multiple of the Upside scenario FY2034/1 - model, not peak operating profit
B53: N = 5 years | C53: 5 | D53: =IFERROR(D48/$C$15,"N/A") -> 5.6919788 | E53: =IFERROR(E48/$C$15,"N/A") -> 6.4289525 | F53: =IFERROR(F48/$C$15,"N/A") -> 7.1855359 | G53: =IFERROR(G48/$C$15,"N/A") -> 7.9616024 | H53: =IFERROR(H48/$C$15,"N/A") -> 8.7570195
B54: N = 8 years | C54: 8 | D54: =IFERROR(D49/$C$15,"N/A") -> 6.7209019 | E54: =IFERROR(E49/$C$15,"N/A") -> 7.6646361 | F54: =IFERROR(F49/$C$15,"N/A") -> 8.6468704 | G54: =IFERROR(G49/$C$15,"N/A") -> 9.6675065 | H54: =IFERROR(H49/$C$15,"N/A") -> 10.726412
B55: N = 10 years | C55: 10 | D55: =IFERROR(D50/$C$15,"N/A") -> 7.4625882 | E55: =IFERROR(E50/$C$15,"N/A") -> 8.5575532 | F55: =IFERROR(F50/$C$15,"N/A") -> 9.7052087 | G55: =IFERROR(G50/$C$15,"N/A") -> 10.905466 | H55: =IFERROR(H50/$C$15,"N/A") -> 12.158169
B56: N = 15 years | C56: 15 | D56: =IFERROR(D51/$C$15,"N/A") -> 9.4975108 | E56: =IFERROR(E51/$C$15,"N/A") -> 11.010442 | F56: =IFERROR(F51/$C$15,"N/A") -> 12.615167 | G56: =IFERROR(G51/$C$15,"N/A") -> 14.311334 | H56: =IFERROR(H51/$C$15,"N/A") -> 16.098402
B58: Block C: Decomposing the required profit into revenue x margin (N = 8 years, model WACC)
B59: The revenue the company must run at, for a given steady-state operating margin, to earn the Block B-3 profit.
B60: Required steady-state Operating Profit (N=8, model WACC) | C60: =F49 -> 55210.267
B62: Assumed steady-state OPM | C62: Required Revenue | D62: x base-year revenue
B63: 0.05 | C63: =IFERROR($C$60/B63,"N/A") -> 1104205.3 | D63: =IFERROR(C63/'DCF Model'!C17,"N/A") -> 230.87972
B64: 0.1 | C64: =IFERROR($C$60/B64,"N/A") -> 552102.67 | D64: =IFERROR(C64/'DCF Model'!C17,"N/A") -> 115.43986
B65: cycle-peak OPM (Upside scenario FY2034/1 - model, not) | C65: =IFERROR($C$60/$C$18,"N/A") -> 368068.45 | D65: =IFERROR(C65/'DCF Model'!C17,"N/A") -> 76.959907
B66: 0.2 | C66: =IFERROR($C$60/B66,"N/A") -> 276051.34 | D66: =IFERROR(C66/'DCF Model'!C17,"N/A") -> 57.71993
B67: 0.25 | C67: =IFERROR($C$60/B67,"N/A") -> 220841.07 | D67: =IFERROR(C67/'DCF Model'!C17,"N/A") -> 46.175944
B69: Block D: The same question expressed as multiples
B70: Current EV / latest-FY EBITDA (actual) | C70: =IFERROR(C10/'Comps Analysis'!G5,"N/A") -> -360.66175
B71: Current EV / latest-FY Revenue (actual) | C71: =IFERROR(C10/'Comps Analysis'!F5,"N/A") -> 46.524838
B72: EV / EBITDA if the Block A profit were already earned | C72: =IFERROR(C10/(C25+'DCF Model'!J42),"N/A") -> 6.1610667
B73: EV / EBITDA if the Block B-3 (N=8) profit were already earned | C73: =IFERROR(C10/(C60+'DCF Model'!J42),"N/A") -> 3.9526742
B74: Peer median EV / EBITDA (statistics rows) | C74: =IFERROR('Comps Analysis'!D16,"N/A") -> 73.541456
B75: Rows 3-4 answer: what multiple would today's EV be paying IF the company already earned the profit the price requires?
B77: Block F: The one-line answer
B78: ="At "&TEXT(C6,"#,##0")&" yen the market is paying for a steady-state operating profit of "&TEXT(F49,"#,##0")&" mn JPY - "&TEXT(F54,"0.00")&"x the Upside scenario FY2034/1 - model, not cycle peak of "&TEXT(C15,"#,##0")&" mn - reached in 8 years and sustained for ever, against "&TEXT(C14,"#,##0")&" mn actually earned in FY2026/1." -> At 21,620 yen the market is paying for a steady-state operating profit of 55,210 mn JPY - 8.65x the Upside scenario FY2034/1 - model, not cycle peak of 6,385 mn - reached in 8 years and sustained for ever, against -1,144 mn actually earned in FY2026/1.
B79: ="Even with no ramp at all (Block A) the price needs "&TEXT(C25,"#,##0")&" mn, or "&TEXT(C26,"0.00")&"x the peak. The base case supports an EV of only "&TEXT(C17,"#,##0")&" mn, leaving "&TEXT(C20,"#,##0")&" yen per share of the current price unexplained by mid-cycle economics." -> Even with no ramp at all (Block A) the price needs 35,031 mn, or 5.49x the peak. The base case supports an EV of only -1,639 mn, leaving 21,561 yen per share of the current price unexplained by mid-cycle economics.

Sheet NWC Schedule
B2: NWC Schedule - Terra Drone
B4: Working Capital Drivers (Days) | C4: Base Year | D4: FY2027(E) | E4: FY2028(E) | F4: FY2029(E) | G4: FY2030(E) | H4: FY2031(E) | I4: FY2032(E) | J4: FY2033(E) | K4: FY2034(E)
B5: DSO (Days Sales Outstanding) | C5: =C12/C9*365 -> 115.70621 | D5: =CHOOSE('DCF Model'!$D$27,D25,D26,D27,D28,D29) -> 115 | E5: =CHOOSE('DCF Model'!$D$27,E25,E26,E27,E28,E29) -> 113 | F5: =CHOOSE('DCF Model'!$D$27,F25,F26,F27,F28,F29) -> 110 | G5: =CHOOSE('DCF Model'!$D$27,G25,G26,G27,G28,G29) -> 110 | H5: =CHOOSE('DCF Model'!$D$27,H25,H26,H27,H28,H29) -> 108 | I5: =CHOOSE('DCF Model'!$D$27,I25,I26,I27,I28,I29) -> 108 | J5: =CHOOSE('DCF Model'!$D$27,J25,J26,J27,J28,J29) -> 105 | K5: =CHOOSE('DCF Model'!$D$27,K25,K26,K27,K28,K29) -> 105
B6: DIH (Days Inventory Held) | C6: =C13/C10*365 -> 88.349597 | D6: =CHOOSE('DCF Model'!$D$27,D32,D33,D34,D35,D36) -> 88 | E6: =CHOOSE('DCF Model'!$D$27,E32,E33,E34,E35,E36) -> 88 | F6: =CHOOSE('DCF Model'!$D$27,F32,F33,F34,F35,F36) -> 90 | G6: =CHOOSE('DCF Model'!$D$27,G32,G33,G34,G35,G36) -> 90 | H6: =CHOOSE('DCF Model'!$D$27,H32,H33,H34,H35,H36) -> 90 | I6: =CHOOSE('DCF Model'!$D$27,I32,I33,I34,I35,I36) -> 88 | J6: =CHOOSE('DCF Model'!$D$27,J32,J33,J34,J35,J36) -> 88 | K6: =CHOOSE('DCF Model'!$D$27,K32,K33,K34,K35,K36) -> 88
B7: DPO (Days Payable Outstanding) | C7: =C15/C10*365 -> 58.998259 | D7: =CHOOSE('DCF Model'!$D$27,D39,D40,D41,D42,D43) -> 59 | E7: =CHOOSE('DCF Model'!$D$27,E39,E40,E41,E42,E43) -> 59 | F7: =CHOOSE('DCF Model'!$D$27,F39,F40,F41,F42,F43) -> 60 | G7: =CHOOSE('DCF Model'!$D$27,G39,G40,G41,G42,G43) -> 60 | H7: =CHOOSE('DCF Model'!$D$27,H39,H40,H41,H42,H43) -> 60 | I7: =CHOOSE('DCF Model'!$D$27,I39,I40,I41,I42,I43) -> 60 | J7: =CHOOSE('DCF Model'!$D$27,J39,J40,J41,J42,J43) -> 60 | K7: =CHOOSE('DCF Model'!$D$27,K39,K40,K41,K42,K43) -> 60
B8: P&L Reference (JPY mn)
B9: Revenue | C9: 4782.6 | D9: ='DCF Model'!C33 -> 5556.9029 | E9: ='DCF Model'!D33 -> 7000.0306 | F9: ='DCF Model'!E33 -> 8920.139 | G9: ='DCF Model'!F33 -> 10792.476 | H9: ='DCF Model'!G33 -> 12483.657 | I9: ='DCF Model'!H33 -> 13763.232 | J9: ='DCF Model'!I33 -> 14785.84 | K9: ='DCF Model'!J33 -> 15541.397
B10: COGS | C10: 2469.7 | D10: ='DCF Model'!C34 -> 3084.0811 | E10: ='DCF Model'!D34 -> 3920.0172 | F10: ='DCF Model'!E34 -> 5084.4793 | G10: ='DCF Model'!F34 -> 6151.7114 | H10: ='DCF Model'!G34 -> 7115.6846 | I10: ='DCF Model'!H34 -> 7845.0423 | J10: ='DCF Model'!I34 -> 8427.9289 | K10: ='DCF Model'!J34 -> 8858.5961
B11: Working Capital Items (JPY mn)
B12: Accounts Receivable | C12: 1516.1 | D12: =D9*D5/365 -> 1750.805 | E12: =E9*E5/365 -> 2167.1328 | F12: =F9*F5/365 -> 2688.2611 | G12: =G9*G5/365 -> 3252.5271 | H12: =H9*H5/365 -> 3693.7945 | I12: =I9*I5/365 -> 4072.4084 | J12: =J9*J5/365 -> 4253.4609 | K12: =K9*K5/365 -> 4470.8127
B13: Inventory | C13: 597.8 | D13: =D10*D6/365 -> 743.55929 | E13: =E10*E6/365 -> 945.10003 | F13: =F10*F6/365 -> 1253.7072 | G13: =G10*G6/365 -> 1516.8604 | H13: =H10*H6/365 -> 1754.5524 | I13: =I10*I6/365 -> 1891.4075 | J13: =J10*J6/365 -> 2031.939 | K13: =K10*K6/365 -> 2135.7711
B14: Current Assets (AR + Inv) | C14: =C12+C13 -> 2113.9 | D14: =D12+D13 -> 2494.3643 | E14: =E12+E13 -> 3112.2328 | F14: =F12+F13 -> 3941.9683 | G14: =G12+G13 -> 4769.3874 | H14: =H12+H13 -> 5448.3468 | I14: =I12+I13 -> 5963.8159 | J14: =J12+J13 -> 6285.3999 | K14: =K12+K13 -> 6606.5839
B15: Accounts Payable | C15: 399.2 | D15: =D10*D7/365 -> 498.5227 | E15: =E10*E7/365 -> 633.64661 | F15: =F10*F7/365 -> 835.80481 | G15: =G10*G7/365 -> 1011.2402 | H15: =H10*H7/365 -> 1169.7016 | I15: =I10*I7/365 -> 1289.596 | J15: =J10*J7/365 -> 1385.413 | K15: =K10*K7/365 -> 1456.2076
B16: Current Liabilities (AP) | C16: =C15 -> 399.2 | D16: =D15 -> 498.5227 | E16: =E15 -> 633.64661 | F16: =F15 -> 835.80481 | G16: =G15 -> 1011.2402 | H16: =H15 -> 1169.7016 | I16: =I15 -> 1289.596 | J16: =J15 -> 1385.413 | K16: =K15 -> 1456.2076
B17: Net Working Capital (JPY mn)
B18: Net Working Capital | C18: =C14-C16 -> 1714.7 | D18: =D14-D16 -> 1995.8416 | E18: =E14-E16 -> 2478.5862 | F18: =F14-F16 -> 3106.1635 | G18: =G14-G16 -> 3758.1472 | H18: =H14-H16 -> 4278.6453 | I18: =I14-I16 -> 4674.2199 | J18: =J14-J16 -> 4899.987 | K18: =K14-K16 -> 5150.3763
B19: Change in NWC | C19: n/a | D19: =D18-C18 -> 281.14162 | E19: =E18-D18 -> 482.74457 | F19: =F18-E18 -> 627.57729 | G19: =G18-F18 -> 651.98372 | H19: =H18-G18 -> 520.49806 | I19: =I18-H18 -> 395.57461 | J19: =J18-I18 -> 225.76708 | K19: =K18-J18 -> 250.38933
B22: Scenario Input Matrix (Working Capital Days)
D23: FY2027(E) | E23: FY2028(E) | F23: FY2029(E) | G23: FY2030(E) | H23: FY2031(E) | I23: FY2032(E) | J23: FY2033(E) | K23: FY2034(E)
B24: DSO (Days)
B25: Base | D25: 115 | E25: 113 | F25: 110 | G25: 110 | H25: 108 | I25: 108 | J25: 105 | K25: 105
B26: Upside | D26: 112 | E26: 110 | F26: 108 | G26: 105 | H26: 105 | I26: 103 | J26: 100 | K26: 100
B27: Management | D27: 115 | E27: 113 | F27: 110 | G27: 110 | H27: 108 | I27: 108 | J27: 105 | K27: 105
B28: Downside 1 | D28: 118 | E28: 120 | F28: 122 | G28: 122 | H28: 122 | I28: 122 | J28: 122 | K28: 122
B29: Downside 2 | D29: 122 | E29: 125 | F29: 128 | G29: 128 | H29: 128 | I29: 128 | J29: 128 | K29: 128
B31: DIH (Days)
B32: Base | D32: 88 | E32: 88 | F32: 90 | G32: 90 | H32: 90 | I32: 88 | J32: 88 | K32: 88
B33: Upside | D33: 90 | E33: 92 | F33: 95 | G33: 95 | H33: 95 | I33: 92 | J33: 90 | K33: 90
B34: Management | D34: 88 | E34: 88 | F34: 90 | G34: 90 | H34: 90 | I34: 88 | J34: 88 | K34: 88
B35: Downside 1 | D35: 90 | E35: 92 | F35: 95 | G35: 95 | H35: 95 | I35: 95 | J35: 95 | K35: 95
B36: Downside 2 | D36: 92 | E36: 95 | F36: 98 | G36: 98 | H36: 98 | I36: 98 | J36: 98 | K36: 98
B38: DPO (Days)
B39: Base | D39: 59 | E39: 59 | F39: 60 | G39: 60 | H39: 60 | I39: 60 | J39: 60 | K39: 60
B40: Upside | D40: 62 | E40: 62 | F40: 65 | G40: 65 | H40: 65 | I40: 65 | J40: 65 | K40: 65
B41: Management | D41: 59 | E41: 59 | F41: 60 | G41: 60 | H41: 60 | I41: 60 | J41: 60 | K41: 60
B42: Downside 1 | D42: 57 | E42: 56 | F42: 55 | G42: 55 | H42: 55 | I42: 55 | J42: 55 | K42: 55
B43: Downside 2 | D43: 55 | E43: 54 | F43: 52 | G43: 52 | H43: 52 | I43: 52 | J43: 52 | K43: 52

Sheet Comps Analysis
B2: Comparable Company Analysis
B3: Peer prices as of 2026-08-29 (Mkt Cap / EV of peer rows are static CSV values; the subject row is live-linked to Executive Summary)
B4: Company | C4: Ticker | D4: Mkt Cap (JPY mn) | E4: EV (JPY mn) | F4: Revenue (JPY mn) | G4: EBITDA (JPY mn) | H4: Op Income (JPY mn) | I4: Net Income (JPY mn) | J4: EV/EBITDA | K4: EV/Revenue | L4: PER | M4: PBR | N4: Op Margin | O4: ROE | P4: Book Value (JPY mn) | Q4: Note
B5: Terra Drone (278A) [subject] | C5: 278A.T | D5: ='Executive Summary'!C9*C23/1000000 -> 224785.3 | E5: =D5+C24 -> 222528.3 | F5: 4783 | G5: -617 | H5: -1144 | I5: -2498 | J5: N/A | K5: =IFERROR(E5/F5,"") -> 46.524838 | L5: N/A | M5: =IFERROR(D5/P5,"") -> 50.186493 | N5: =IFERROR(H5/F5,"") -> -0.23918043 | O5: =IFERROR(I5/P5,"") -> -0.55771378 | P5: 4479
B6: ACSL (6232) | C6: 6232.T | D6: 30278 | E6: 31123 | F6: 2599 | G6: -1768 | H6: -1840 | I6: -1364 | J6: N/A | K6: =IFERROR(E6/F6,"") -> 11.97499 | L6: N/A | M6: =IFERROR(D6/P6,"") -> 17.242597 | N6: =IFERROR(H6/F6,"") -> -0.7079646 | O6: =IFERROR(I6/P6,"") -> -0.77676538 | P6: 1756
B7: AeroVironment (AVAV) | C7: AVAV | D7: 1203277 | E7: 1235683 | F7: 316370 | G7: 31167 | H7: -11249 | I7: -42430 | J7: =IFERROR(E7/G7,"") -> 39.647159 | K7: =IFERROR(E7/F7,"") -> 3.905816 | L7: N/A | M7: =IFERROR(D7/P7,"") -> 1.7086396 | N7: =IFERROR(H7/F7,"") -> -0.035556469 | O7: =IFERROR(I7/P7,"") -> -0.060250117 | P7: 704231
B8: Kratos Defense (KTOS) | C8: KTOS | D8: 1562212 | E8: 1495828 | F8: 215539 | G8: 13923 | H8: 4433 | I8: 3521 | J8: =IFERROR(E8/G8,"") -> 107.43575 | K8: =IFERROR(E8/F8,"") -> 6.9399413 | L8: =IFERROR(D8/I8,"") -> 443.68418 | M8: =IFERROR(D8/P8,"") -> 4.8897973 | N8: =IFERROR(H8/F8,"") -> 0.020567044 | O8: =IFERROR(I8/P8,"") -> 0.011020896 | P8: 319484
B9: Red Cat Holdings (RCAT) | C9: RCAT | D9: 207496 | E9: 183582 | F9: 6518 | G9: -10296 | H9: -10658 | I9: -11535 | J9: N/A | K9: =IFERROR(E9/F9,"") -> 28.165388 | L9: N/A | M9: =IFERROR(D9/P9,"") -> 5.2741599 | N9: =IFERROR(H9/F9,"") -> -1.6351642 | O9: =IFERROR(I9/P9,"") -> -0.29319811 | P9: 39342
B10: Ondas Holdings (ONDS) | C10: ONDS | D10: 721349 | E10: 637629 | F10: 8119 | G10: -8066 | H10: -9344 | I10: -21128 | J10: N/A | K10: =IFERROR(E10/F10,"") -> 78.535411 | L10: N/A | M10: =IFERROR(D10/P10,"") -> 10.295279 | N10: =IFERROR(H10/F10,"") -> -1.1508807 | O10: =IFERROR(I10/P10,"") -> -0.30154426 | P10: 70066
B14: Statistics
B15: 25th Percentile | D15: =PERCENTILE(J7:J8,0.25) -> 56.594308 | E15: =PERCENTILE(K6:K10,0.25) -> 6.9399413 | F15: =PERCENTILE(L6:L10,0.25) -> 443.68418 | G15: =PERCENTILE(M6:M10,0.25) -> 4.8897973 | H15: =PERCENTILE(N6:N10,0.25) -> -1.1508807 | I15: =PERCENTILE(O6:O10,0.25) -> -0.30154426
B16: Median (50th) | D16: =MEDIAN(J7:J8) -> 73.541456 | E16: =MEDIAN(K6:K10) -> 11.97499 | F16: =MEDIAN(L6:L10) -> 443.68418 | G16: =MEDIAN(M6:M10) -> 5.2741599 | H16: =MEDIAN(N6:N10) -> -0.7079646 | I16: =MEDIAN(O6:O10) -> -0.29319811
B17: 75th Percentile | D17: =PERCENTILE(J7:J8,0.75) -> 90.488605 | E17: =PERCENTILE(K6:K10,0.75) -> 28.165388 | F17: =PERCENTILE(L6:L10,0.75) -> 443.68418 | G17: =PERCENTILE(M6:M10,0.75) -> 10.295279 | H17: =PERCENTILE(N6:N10,0.75) -> -0.035556469 | I17: =PERCENTILE(O6:O10,0.75) -> -0.060250117
B19: Implied Valuation for Terra Drone
B20: Terra Drone Financials
B21: Revenue (JPY mn) | C21: 4782.6
B22: Net Income (JPY mn) | C22: -2497.9
B23: Shares Outstanding | C23: 10397100
B24: Net Debt (JPY mn) | C24: -2257
B26: Implied Share Price (Median Multiples)
B27: Via EV/Sales (Median) | C27: =ROUND((C21*E16-C24)*1000000/C23,0) -> 5725
B28: Via PER (Median) | C28: N/A | D28: Net income <= 0 — PER not meaningful

Sheet Sensitivity Analysis
B2: Sensitivity Analysis
B3: Current WACC: | C3: ='DCF Model'!C26 -> 0.12925 | E3: Terminal g: | F3: ='DCF Model'!C13 -> 0.02 | H3: Exit Multiple: | I3: ='DCF Model'!C14 -> 2
B5: Table 1: WACC vs Terminal Growth Rate (PGM - Implied Share Price, JPY)
B6: WACC \ Terminal g | C6: =$F$3-0.0075 -> 0.0125 | D6: =$F$3-0.005 -> 0.015 | E6: =$F$3-0.0025 -> 0.0175 | F6: =$F$3 -> 0.02 | G6: =$F$3+0.0025 -> 0.0225 | H6: =$F$3+0.005 -> 0.025 | I6: =$F$3+0.0075 -> 0.0275
B7: =$C$3-0.015 -> 0.11425 | C7: =IFERROR(ROUND(('DCF Model'!C45/(1+$B7)^('DCF Model'!C19+0)+'DCF Model'!D45/(1+$B7)^('DCF Model'!C19+1)+'DCF Model'!E45/(1+$B7)^('DCF Model'!C19+2)+'DCF Model'!F45/(1+$B7)^('DCF Model'!C19+3)+'DCF Model'!G45/(1+$B7)^('DCF Model'!C19+4)+'DCF Model'!H45/(1+$B7)^('DCF Model'!C19+5)+'DCF Model'!I45/(1+$B7)^('DCF Model'!C19+6)+'DCF Model'!J45/(1+$B7)^('DCF Model'!C19+7)+'DCF Model'!J45*(1+C$6)/($B7-C$6)/(1+$B7)^('DCF Model'!C19+7)-'DCF Model'!C16)*1000000/'DCF Model'!C15,0),"") -> 102 | D7: =IFERROR(ROUND(('DCF Model'!C45/(1+$B7)^('DCF Model'!C19+0)+'DCF Model'!D45/(1+$B7)^('DCF Model'!C19+1)+'DCF Model'!E45/(1+$B7)^('DCF Model'!C19+2)+'DCF Model'!F45/(1+$B7)^('DCF Model'!C19+3)+'DCF Model'!G45/(1+$B7)^('DCF Model'!C19+4)+'DCF Model'!H45/(1+$B7)^('DCF Model'!C19+5)+'DCF Model'!I45/(1+$B7)^('DCF Model'!C19+6)+'DCF Model'!J45/(1+$B7)^('DCF Model'!C19+7)+'DCF Model'!J45*(1+D$6)/($B7-D$6)/(1+$B7)^('DCF Model'!C19+7)-'DCF Model'!C16)*1000000/'DCF Model'!C15,0),"") -> 111 | E7: =IFERROR(ROUND(('DCF Model'!C45/(1+$B7)^('DCF Model'!C19+0)+'DCF Model'!D45/(1+$B7)^('DCF Model'!C19+1)+'DCF Model'!E45/(1+$B7)^('DCF Model'!C19+2)+'DCF Model'!F45/(1+$B7)^('DCF Model'!C19+3)+'DCF Model'!G45/(1+$B7)^('DCF Model'!C19+4)+'DCF Model'!H45/(1+$B7)^('DCF Model'!C19+5)+'DCF Model'!I45/(1+$B7)^('DCF Model'!C19+6)+'DCF Model'!J45/(1+$B7)^('DCF Model'!C19+7)+'DCF Model'!J45*(1+E$6)/($B7-E$6)/(1+$B7)^('DCF Model'!C19+7)-'DCF Model'!C16)*1000000/'DCF Model'!C15,0),"") -> 120 | F7: =IFERROR(ROUND(('DCF Model'!C45/(1+$B7)^('DCF Model'!C19+0)+'DCF Model'!D45/(1+$B7)^('DCF Model'!C19+1)+'DCF Model'!E45/(1+$B7)^('DCF Model'!C19+2)+'DCF Model'!F45/(1+$B7)^('DCF Model'!C19+3)+'DCF Model'!G45/(1+$B7)^('DCF Model'!C19+4)+'DCF Model'!H45/(1+$B7)^('DCF Model'!C19+5)+'DCF Model'!I45/(1+$B7)^('DCF Model'!C19+6)+'DCF Model'!J45/(1+$B7)^('DCF Model'!C19+7)+'DCF Model'!J45*(1+F$6)/($B7-F$6)/(1+$B7)^('DCF Model'!C19+7)-'DCF Model'!C16)*1000000/'DCF Model'!C15,0),"") -> 130 | G7: =IFERROR(ROUND(('DCF Model'!C45/(1+$B7)^('DCF Model'!C19+0)+'DCF Model'!D45/(1+$B7)^('DCF Model'!C19+1)+'DCF Model'!E45/(1+$B7)^('DCF Model'!C19+2)+'DCF Model'!F45/(1+$B7)^('DCF Model'!C19+3)+'DCF Model'!G45/(1+$B7)^('DCF Model'!C19+4)+'DCF Model'!H45/(1+$B7)^('DCF Model'!C19+5)+'DCF Model'!I45/(1+$B7)^('DCF Model'!C19+6)+'DCF Model'!J45/(1+$B7)^('DCF Model'!C19+7)+'DCF Model'!J45*(1+G$6)/($B7-G$6)/(1+$B7)^('DCF Model'!C19+7)-'DCF Model'!C16)*1000000/'DCF Model'!C15,0),"") -> 140 | H7: =IFERROR(ROUND(('DCF Model'!C45/(1+$B7)^('DCF Model'!C19+0)+'DCF Model'!D45/(1+$B7)^('DCF Model'!C19+1)+'DCF Model'!E45/(1+$B7)^('DCF Model'!C19+2)+'DCF Model'!F45/(1+$B7)^('DCF Model'!C19+3)+'DCF Model'!G45/(1+$B7)^('DCF Model'!C19+4)+'DCF Model'!H45/(1+$B7)^('DCF Model'!C19+5)+'DCF Model'!I45/(1+$B7)^('DCF Model'!C19+6)+'DCF Model'!J45/(1+$B7)^('DCF Model'!C19+7)+'DCF Model'!J45*(1+H$6)/($B7-H$6)/(1+$B7)^('DCF Model'!C19+7)-'DCF Model'!C16)*1000000/'DCF Model'!C15,0),"") -> 151 | I7: =IFERROR(ROUND(('DCF Model'!C45/(1+$B7)^('DCF Model'!C19+0)+'DCF Model'!D45/(1+$B7)^('DCF Model'!C19+1)+'DCF Model'!E45/(1+$B7)^('DCF Model'!C19+2)+'DCF Model'!F45/(1+$B7)^('DCF Model'!C19+3)+'DCF Model'!G45/(1+$B7)^('DCF Model'!C19+4)+'DCF Model'!H45/(1+$B7)^('DCF Model'!C19+5)+'DCF Model'!I45/(1+$B7)^('DCF Model'!C19+6)+'DCF Model'!J45/(1+$B7)^('DCF Model'!C19+7)+'DCF Model'!J45*(1+I$6)/($B7-I$6)/(1+$B7)^('DCF Model'!C19+7)-'DCF Model'!C16)*1000000/'DCF Model'!C15,0),"") -> 163
B8: =$C$3-0.01 -> 0.11925 | C8: =IFERROR(ROUND(('DCF Model'!C45/(1+$B8)^('DCF Model'!C19+0)+'DCF Model'!D45/(1+$B8)^('DCF Model'!C19+1)+'DCF Model'!E45/(1+$B8)^('DCF Model'!C19+2)+'DCF Model'!F45/(1+$B8)^('DCF Model'!C19+3)+'DCF Model'!G45/(1+$B8)^('DCF Model'!C19+4)+'DCF Model'!H45/(1+$B8)^('DCF Model'!C19+5)+'DCF Model'!I45/(1+$B8)^('DCF Model'!C19+6)+'DCF Model'!J45/(1+$B8)^('DCF Model'!C19+7)+'DCF Model'!J45*(1+C$6)/($B8-C$6)/(1+$B8)^('DCF Model'!C19+7)-'DCF Model'!C16)*1000000/'DCF Model'!C15,0),"") -> 79 | D8: =IFERROR(ROUND(('DCF Model'!C45/(1+$B8)^('DCF Model'!C19+0)+'DCF Model'!D45/(1+$B8)^('DCF Model'!C19+1)+'DCF Model'!E45/(1+$B8)^('DCF Model'!C19+2)+'DCF Model'!F45/(1+$B8)^('DCF Model'!C19+3)+'DCF Model'!G45/(1+$B8)^('DCF Model'!C19+4)+'DCF Model'!H45/(1+$B8)^('DCF Model'!C19+5)+'DCF Model'!I45/(1+$B8)^('DCF Model'!C19+6)+'DCF Model'!J45/(1+$B8)^('DCF Model'!C19+7)+'DCF Model'!J45*(1+D$6)/($B8-D$6)/(1+$B8)^('DCF Model'!C19+7)-'DCF Model'!C16)*1000000/'DCF Model'!C15,0),"") -> 86 | E8: =IFERROR(ROUND(('DCF Model'!C45/(1+$B8)^('DCF Model'!C19+0)+'DCF Model'!D45/(1+$B8)^('DCF Model'!C19+1)+'DCF Model'!E45/(1+$B8)^('DCF Model'!C19+2)+'DCF Model'!F45/(1+$B8)^('DCF Model'!C19+3)+'DCF Model'!G45/(1+$B8)^('DCF Model'!C19+4)+'DCF Model'!H45/(1+$B8)^('DCF Model'!C19+5)+'DCF Model'!I45/(1+$B8)^('DCF Model'!C19+6)+'DCF Model'!J45/(1+$B8)^('DCF Model'!C19+7)+'DCF Model'!J45*(1+E$6)/($B8-E$6)/(1+$B8)^('DCF Model'!C19+7)-'DCF Model'!C16)*1000000/'DCF Model'!C15,0),"") -> 95 | F8: =IFERROR(ROUND(('DCF Model'!C45/(1+$B8)^('DCF Model'!C19+0)+'DCF Model'!D45/(1+$B8)^('DCF Model'!C19+1)+'DCF Model'!E45/(1+$B8)^('DCF Model'!C19+2)+'DCF Model'!F45/(1+$B8)^('DCF Model'!C19+3)+'DCF Model'!G45/(1+$B8)^('DCF Model'!C19+4)+'DCF Model'!H45/(1+$B8)^('DCF Model'!C19+5)+'DCF Model'!I45/(1+$B8)^('DCF Model'!C19+6)+'DCF Model'!J45/(1+$B8)^('DCF Model'!C19+7)+'DCF Model'!J45*(1+F$6)/($B8-F$6)/(1+$B8)^('DCF Model'!C19+7)-'DCF Model'!C16)*1000000/'DCF Model'!C15,0),"") -> 103 | G8: =IFERROR(ROUND(('DCF Model'!C45/(1+$B8)^('DCF Model'!C19+0)+'DCF Model'!D45/(1+$B8)^('DCF Model'!C19+1)+'DCF Model'!E45/(1+$B8)^('DCF Model'!C19+2)+'DCF Model'!F45/(1+$B8)^('DCF Model'!C19+3)+'DCF Model'!G45/(1+$B8)^('DCF Model'!C19+4)+'DCF Model'!H45/(1+$B8)^('DCF Model'!C19+5)+'DCF Model'!I45/(1+$B8)^('DCF Model'!C19+6)+'DCF Model'!J45/(1+$B8)^('DCF Model'!C19+7)+'DCF Model'!J45*(1+G$6)/($B8-G$6)/(1+$B8)^('DCF Model'!C19+7)-'DCF Model'!C16)*1000000/'DCF Model'!C15,0),"") -> 113 | H8: =IFERROR(ROUND(('DCF Model'!C45/(1+$B8)^('DCF Model'!C19+0)+'DCF Model'!D45/(1+$B8)^('DCF Model'!C19+1)+'DCF Model'!E45/(1+$B8)^('DCF Model'!C19+2)+'DCF Model'!F45/(1+$B8)^('DCF Model'!C19+3)+'DCF Model'!G45/(1+$B8)^('DCF Model'!C19+4)+'DCF Model'!H45/(1+$B8)^('DCF Model'!C19+5)+'DCF Model'!I45/(1+$B8)^('DCF Model'!C19+6)+'DCF Model'!J45/(1+$B8)^('DCF Model'!C19+7)+'DCF Model'!J45*(1+H$6)/($B8-H$6)/(1+$B8)^('DCF Model'!C19+7)-'DCF Model'!C16)*1000000/'DCF Model'!C15,0),"") -> 122 | I8: =IFERROR(ROUND(('DCF Model'!C45/(1+$B8)^('DCF Model'!C19+0)+'DCF Model'!D45/(1+$B8)^('DCF Model'!C19+1)+'DCF Model'!E45/(1+$B8)^('DCF Model'!C19+2)+'DCF Model'!F45/(1+$B8)^('DCF Model'!C19+3)+'DCF Model'!G45/(1+$B8)^('DCF Model'!C19+4)+'DCF Model'!H45/(1+$B8)^('DCF Model'!C19+5)+'DCF Model'!I45/(1+$B8)^('DCF Model'!C19+6)+'DCF Model'!J45/(1+$B8)^('DCF Model'!C19+7)+'DCF Model'!J45*(1+I$6)/($B8-I$6)/(1+$B8)^('DCF Model'!C19+7)-'DCF Model'!C16)*1000000/'DCF Model'!C15,0),"") -> 132
B9: =$C$3-0.005 -> 0.12425 | C9: =IFERROR(ROUND(('DCF Model'!C45/(1+$B9)^('DCF Model'!C19+0)+'DCF Model'!D45/(1+$B9)^('DCF Model'!C19+1)+'DCF Model'!E45/(1+$B9)^('DCF Model'!C19+2)+'DCF Model'!F45/(1+$B9)^('DCF Model'!C19+3)+'DCF Model'!G45/(1+$B9)^('DCF Model'!C19+4)+'DCF Model'!H45/(1+$B9)^('DCF Model'!C19+5)+'DCF Model'!I45/(1+$B9)^('DCF Model'!C19+6)+'DCF Model'!J45/(1+$B9)^('DCF Model'!C19+7)+'DCF Model'!J45*(1+C$6)/($B9-C$6)/(1+$B9)^('DCF Model'!C19+7)-'DCF Model'!C16)*1000000/'DCF Model'!C15,0),"") -> 58 | D9: =IFERROR(ROUND(('DCF Model'!C45/(1+$B9)^('DCF Model'!C19+0)+'DCF Model'!D45/(1+$B9)^('DCF Model'!C19+1)+'DCF Model'!E45/(1+$B9)^('DCF Model'!C19+2)+'DCF Model'!F45/(1+$B9)^('DCF Model'!C19+3)+'DCF Model'!G45/(1+$B9)^('DCF Model'!C19+4)+'DCF Model'!H45/(1+$B9)^('DCF Model'!C19+5)+'DCF Model'!I45/(1+$B9)^('DCF Model'!C19+6)+'DCF Model'!J45/(1+$B9)^('DCF Model'!C19+7)+'DCF Model'!J45*(1+D$6)/($B9-D$6)/(1+$B9)^('DCF Model'!C19+7)-'DCF Model'!C16)*1000000/'DCF Model'!C15,0),"") -> 65 | E9: =IFERROR(ROUND(('DCF Model'!C45/(1+$B9)^('DCF Model'!C19+0)+'DCF Model'!D45/(1+$B9)^('DCF Model'!C19+1)+'DCF Model'!E45/(1+$B9)^('DCF Model'!C19+2)+'DCF Model'!F45/(1+$B9)^('DCF Model'!C19+3)+'DCF Model'!G45/(1+$B9)^('DCF Model'!C19+4)+'DCF Model'!H45/(1+$B9)^('DCF Model'!C19+5)+'DCF Model'!I45/(1+$B9)^('DCF Model'!C19+6)+'DCF Model'!J45/(1+$B9)^('DCF Model'!C19+7)+'DCF Model'!J45*(1+E$6)/($B9-E$6)/(1+$B9)^('DCF Model'!C19+7)-'DCF Model'!C16)*1000000/'DCF Model'!C15,0),"") -> 72 | F9: =IFERROR(ROUND(('DCF Model'!C45/(1+$B9)^('DCF Model'!C19+0)+'DCF Model'!D45/(1+$B9)^('DCF Model'!C19+1)+'DCF Model'!E45/(1+$B9)^('DCF Model'!C19+2)+'DCF Model'!F45/(1+$B9)^('DCF Model'!C19+3)+'DCF Model'!G45/(1+$B9)^('DCF Model'!C19+4)+'DCF Model'!H45/(1+$B9)^('DCF Model'!C19+5)+'DCF Model'!I45/(1+$B9)^('DCF Model'!C19+6)+'DCF Model'!J45/(1+$B9)^('DCF Model'!C19+7)+'DCF Model'!J45*(1+F$6)/($B9-F$6)/(1+$B9)^('DCF Model'!C19+7)-'DCF Model'!C16)*1000000/'DCF Model'!C15,0),"") -> 80 | G9: =IFERROR(ROUND(('DCF Model'!C45/(1+$B9)^('DCF Model'!C19+0)+'DCF Model'!D45/(1+$B9)^('DCF Model'!C19+1)+'DCF Model'!E45/(1+$B9)^('DCF Model'!C19+2)+'DCF Model'!F45/(1+$B9)^('DCF Model'!C19+3)+'DCF Model'!G45/(1+$B9)^('DCF Model'!C19+4)+'DCF Model'!H45/(1+$B9)^('DCF Model'!C19+5)+'DCF Model'!I45/(1+$B9)^('DCF Model'!C19+6)+'DCF Model'!J45/(1+$B9)^('DCF Model'!C19+7)+'DCF Model'!J45*(1+G$6)/($B9-G$6)/(1+$B9)^('DCF Model'!C19+7)-'DCF Model'!C16)*1000000/'DCF Model'!C15,0),"") -> 88 | H9: =IFERROR(ROUND(('DCF Model'!C45/(1+$B9)^('DCF Model'!C19+0)+'DCF Model'!D45/(1+$B9)^('DCF Model'!C19+1)+'DCF Model'!E45/(1+$B9)^('DCF Model'!C19+2)+'DCF Model'!F45/(1+$B9)^('DCF Model'!C19+3)+'DCF Model'!G45/(1+$B9)^('DCF Model'!C19+4)+'DCF Model'!H45/(1+$B9)^('DCF Model'!C19+5)+'DCF Model'!I45/(1+$B9)^('DCF Model'!C19+6)+'DCF Model'!J45/(1+$B9)^('DCF Model'!C19+7)+'DCF Model'!J45*(1+H$6)/($B9-H$6)/(1+$B9)^('DCF Model'!C19+7)-'DCF Model'!C16)*1000000/'DCF Model'!C15,0),"") -> 97 | I9: =IFERROR(ROUND(('DCF Model'!C45/(1+$B9)^('DCF Model'!C19+0)+'DCF Model'!D45/(1+$B9)^('DCF Model'!C19+1)+'DCF Model'!E45/(1+$B9)^('DCF Model'!C19+2)+'DCF Model'!F45/(1+$B9)^('DCF Model'!C19+3)+'DCF Model'!G45/(1+$B9)^('DCF Model'!C19+4)+'DCF Model'!H45/(1+$B9)^('DCF Model'!C19+5)+'DCF Model'!I45/(1+$B9)^('DCF Model'!C19+6)+'DCF Model'!J45/(1+$B9)^('DCF Model'!C19+7)+'DCF Model'!J45*(1+I$6)/($B9-I$6)/(1+$B9)^('DCF Model'!C19+7)-'DCF Model'!C16)*1000000/'DCF Model'!C15,0),"") -> 105
B10: =$C$3 -> 0.12925 | C10: =IFERROR(ROUND(('DCF Model'!C45/(1+$B10)^('DCF Model'!C19+0)+'DCF Model'!D45/(1+$B10)^('DCF Model'!C19+1)+'DCF Model'!E45/(1+$B10)^('DCF Model'!C19+2)+'DCF Model'!F45/(1+$B10)^('DCF Model'!C19+3)+'DCF Model'!G45/(1+$B10)^('DCF Model'!C19+4)+'DCF Model'!H45/(1+$B10)^('DCF Model'!C19+5)+'DCF Model'!I45/(1+$B10)^('DCF Model'!C19+6)+'DCF Model'!J45/(1+$B10)^('DCF Model'!C19+7)+'DCF Model'!J45*(1+C$6)/($B10-C$6)/(1+$B10)^('DCF Model'!C19+7)-'DCF Model'!C16)*1000000/'DCF Model'!C15,0),"") -> 40 | D10: =IFERROR(ROUND(('DCF Model'!C45/(1+$B10)^('DCF Model'!C19+0)+'DCF Model'!D45/(1+$B10)^('DCF Model'!C19+1)+'DCF Model'!E45/(1+$B10)^('DCF Model'!C19+2)+'DCF Model'!F45/(1+$B10)^('DCF Model'!C19+3)+'DCF Model'!G45/(1+$B10)^('DCF Model'!C19+4)+'DCF Model'!H45/(1+$B10)^('DCF Model'!C19+5)+'DCF Model'!I45/(1+$B10)^('DCF Model'!C19+6)+'DCF Model'!J45/(1+$B10)^('DCF Model'!C19+7)+'DCF Model'!J45*(1+D$6)/($B10-D$6)/(1+$B10)^('DCF Model'!C19+7)-'DCF Model'!C16)*1000000/'DCF Model'!C15,0),"") -> 46 | E10: =IFERROR(ROUND(('DCF Model'!C45/(1+$B10)^('DCF Model'!C19+0)+'DCF Model'!D45/(1+$B10)^('DCF Model'!C19+1)+'DCF Model'!E45/(1+$B10)^('DCF Model'!C19+2)+'DCF Model'!F45/(1+$B10)^('DCF Model'!C19+3)+'DCF Model'!G45/(1+$B10)^('DCF Model'!C19+4)+'DCF Model'!H45/(1+$B10)^('DCF Model'!C19+5)+'DCF Model'!I45/(1+$B10)^('DCF Model'!C19+6)+'DCF Model'!J45/(1+$B10)^('DCF Model'!C19+7)+'DCF Model'!J45*(1+E$6)/($B10-E$6)/(1+$B10)^('DCF Model'!C19+7)-'DCF Model'!C16)*1000000/'DCF Model'!C15,0),"") -> 53 | F10: =IFERROR(ROUND(('DCF Model'!C45/(1+$B10)^('DCF Model'!C19+0)+'DCF Model'!D45/(1+$B10)^('DCF Model'!C19+1)+'DCF Model'!E45/(1+$B10)^('DCF Model'!C19+2)+'DCF Model'!F45/(1+$B10)^('DCF Model'!C19+3)+'DCF Model'!G45/(1+$B10)^('DCF Model'!C19+4)+'DCF Model'!H45/(1+$B10)^('DCF Model'!C19+5)+'DCF Model'!I45/(1+$B10)^('DCF Model'!C19+6)+'DCF Model'!J45/(1+$B10)^('DCF Model'!C19+7)+'DCF Model'!J45*(1+F$6)/($B10-F$6)/(1+$B10)^('DCF Model'!C19+7)-'DCF Model'!C16)*1000000/'DCF Model'!C15,0),"") -> 59 | G10: =IFERROR(ROUND(('DCF Model'!C45/(1+$B10)^('DCF Model'!C19+0)+'DCF Model'!D45/(1+$B10)^('DCF Model'!C19+1)+'DCF Model'!E45/(1+$B10)^('DCF Model'!C19+2)+'DCF Model'!F45/(1+$B10)^('DCF Model'!C19+3)+'DCF Model'!G45/(1+$B10)^('DCF Model'!C19+4)+'DCF Model'!H45/(1+$B10)^('DCF Model'!C19+5)+'DCF Model'!I45/(1+$B10)^('DCF Model'!C19+6)+'DCF Model'!J45/(1+$B10)^('DCF Model'!C19+7)+'DCF Model'!J45*(1+G$6)/($B10-G$6)/(1+$B10)^('DCF Model'!C19+7)-'DCF Model'!C16)*1000000/'DCF Model'!C15,0),"") -> 67 | H10: =IFERROR(ROUND(('DCF Model'!C45/(1+$B10)^('DCF Model'!C19+0)+'DCF Model'!D45/(1+$B10)^('DCF Model'!C19+1)+'DCF Model'!E45/(1+$B10)^('DCF Model'!C19+2)+'DCF Model'!F45/(1+$B10)^('DCF Model'!C19+3)+'DCF Model'!G45/(1+$B10)^('DCF Model'!C19+4)+'DCF Model'!H45/(1+$B10)^('DCF Model'!C19+5)+'DCF Model'!I45/(1+$B10)^('DCF Model'!C19+6)+'DCF Model'!J45/(1+$B10)^('DCF Model'!C19+7)+'DCF Model'!J45*(1+H$6)/($B10-H$6)/(1+$B10)^('DCF Model'!C19+7)-'DCF Model'!C16)*1000000/'DCF Model'!C15,0),"") -> 74 | I10: =IFERROR(ROUND(('DCF Model'!C45/(1+$B10)^('DCF Model'!C19+0)+'DCF Model'!D45/(1+$B10)^('DCF Model'!C19+1)+'DCF Model'!E45/(1+$B10)^('DCF Model'!C19+2)+'DCF Model'!F45/(1+$B10)^('DCF Model'!C19+3)+'DCF Model'!G45/(1+$B10)^('DCF Model'!C19+4)+'DCF Model'!H45/(1+$B10)^('DCF Model'!C19+5)+'DCF Model'!I45/(1+$B10)^('DCF Model'!C19+6)+'DCF Model'!J45/(1+$B10)^('DCF Model'!C19+7)+'DCF Model'!J45*(1+I$6)/($B10-I$6)/(1+$B10)^('DCF Model'!C19+7)-'DCF Model'!C16)*1000000/'DCF Model'!C15,0),"") -> 82
B11: =$C$3+0.005 -> 0.13425 | C11: =IFERROR(ROUND(('DCF Model'!C45/(1+$B11)^('DCF Model'!C19+0)+'DCF Model'!D45/(1+$B11)^('DCF Model'!C19+1)+'DCF Model'!E45/(1+$B11)^('DCF Model'!C19+2)+'DCF Model'!F45/(1+$B11)^('DCF Model'!C19+3)+'DCF Model'!G45/(1+$B11)^('DCF Model'!C19+4)+'DCF Model'!H45/(1+$B11)^('DCF Model'!C19+5)+'DCF Model'!I45/(1+$B11)^('DCF Model'!C19+6)+'DCF Model'!J45/(1+$B11)^('DCF Model'!C19+7)+'DCF Model'!J45*(1+C$6)/($B11-C$6)/(1+$B11)^('DCF Model'!C19+7)-'DCF Model'!C16)*1000000/'DCF Model'!C15,0),"") -> 24 | D11: =IFERROR(ROUND(('DCF Model'!C45/(1+$B11)^('DCF Model'!C19+0)+'DCF Model'!D45/(1+$B11)^('DCF Model'!C19+1)+'DCF Model'!E45/(1+$B11)^('DCF Model'!C19+2)+'DCF Model'!F45/(1+$B11)^('DCF Model'!C19+3)+'DCF Model'!G45/(1+$B11)^('DCF Model'!C19+4)+'DCF Model'!H45/(1+$B11)^('DCF Model'!C19+5)+'DCF Model'!I45/(1+$B11)^('DCF Model'!C19+6)+'DCF Model'!J45/(1+$B11)^('DCF Model'!C19+7)+'DCF Model'!J45*(1+D$6)/($B11-D$6)/(1+$B11)^('DCF Model'!C19+7)-'DCF Model'!C16)*1000000/'DCF Model'!C15,0),"") -> 29 | E11: =IFERROR(ROUND(('DCF Model'!C45/(1+$B11)^('DCF Model'!C19+0)+'DCF Model'!D45/(1+$B11)^('DCF Model'!C19+1)+'DCF Model'!E45/(1+$B11)^('DCF Model'!C19+2)+'DCF Model'!F45/(1+$B11)^('DCF Model'!C19+3)+'DCF Model'!G45/(1+$B11)^('DCF Model'!C19+4)+'DCF Model'!H45/(1+$B11)^('DCF Model'!C19+5)+'DCF Model'!I45/(1+$B11)^('DCF Model'!C19+6)+'DCF Model'!J45/(1+$B11)^('DCF Model'!C19+7)+'DCF Model'!J45*(1+E$6)/($B11-E$6)/(1+$B11)^('DCF Model'!C19+7)-'DCF Model'!C16)*1000000/'DCF Model'!C15,0),"") -> 35 | F11: =IFERROR(ROUND(('DCF Model'!C45/(1+$B11)^('DCF Model'!C19+0)+'DCF Model'!D45/(1+$B11)^('DCF Model'!C19+1)+'DCF Model'!E45/(1+$B11)^('DCF Model'!C19+2)+'DCF Model'!F45/(1+$B11)^('DCF Model'!C19+3)+'DCF Model'!G45/(1+$B11)^('DCF Model'!C19+4)+'DCF Model'!H45/(1+$B11)^('DCF Model'!C19+5)+'DCF Model'!I45/(1+$B11)^('DCF Model'!C19+6)+'DCF Model'!J45/(1+$B11)^('DCF Model'!C19+7)+'DCF Model'!J45*(1+F$6)/($B11-F$6)/(1+$B11)^('DCF Model'!C19+7)-'DCF Model'!C16)*1000000/'DCF Model'!C15,0),"") -> 41 | G11: =IFERROR(ROUND(('DCF Model'!C45/(1+$B11)^('DCF Model'!C19+0)+'DCF Model'!D45/(1+$B11)^('DCF Model'!C19+1)+'DCF Model'!E45/(1+$B11)^('DCF Model'!C19+2)+'DCF Model'!F45/(1+$B11)^('DCF Model'!C19+3)+'DCF Model'!G45/(1+$B11)^('DCF Model'!C19+4)+'DCF Model'!H45/(1+$B11)^('DCF Model'!C19+5)+'DCF Model'!I45/(1+$B11)^('DCF Model'!C19+6)+'DCF Model'!J45/(1+$B11)^('DCF Model'!C19+7)+'DCF Model'!J45*(1+G$6)/($B11-G$6)/(1+$B11)^('DCF Model'!C19+7)-'DCF Model'!C16)*1000000/'DCF Model'!C15,0),"") -> 47 | H11: =IFERROR(ROUND(('DCF Model'!C45/(1+$B11)^('DCF Model'!C19+0)+'DCF Model'!D45/(1+$B11)^('DCF Model'!C19+1)+'DCF Model'!E45/(1+$B11)^('DCF Model'!C19+2)+'DCF Model'!F45/(1+$B11)^('DCF Model'!C19+3)+'DCF Model'!G45/(1+$B11)^('DCF Model'!C19+4)+'DCF Model'!H45/(1+$B11)^('DCF Model'!C19+5)+'DCF Model'!I45/(1+$B11)^('DCF Model'!C19+6)+'DCF Model'!J45/(1+$B11)^('DCF Model'!C19+7)+'DCF Model'!J45*(1+H$6)/($B11-H$6)/(1+$B11)^('DCF Model'!C19+7)-'DCF Model'!C16)*1000000/'DCF Model'!C15,0),"") -> 54 | I11: =IFERROR(ROUND(('DCF Model'!C45/(1+$B11)^('DCF Model'!C19+0)+'DCF Model'!D45/(1+$B11)^('DCF Model'!C19+1)+'DCF Model'!E45/(1+$B11)^('DCF Model'!C19+2)+'DCF Model'!F45/(1+$B11)^('DCF Model'!C19+3)+'DCF Model'!G45/(1+$B11)^('DCF Model'!C19+4)+'DCF Model'!H45/(1+$B11)^('DCF Model'!C19+5)+'DCF Model'!I45/(1+$B11)^('DCF Model'!C19+6)+'DCF Model'!J45/(1+$B11)^('DCF Model'!C19+7)+'DCF Model'!J45*(1+I$6)/($B11-I$6)/(1+$B11)^('DCF Model'!C19+7)-'DCF Model'!C16)*1000000/'DCF Model'!C15,0),"") -> 61
B12: =$C$3+0.01 -> 0.13925 | C12: =IFERROR(ROUND(('DCF Model'!C45/(1+$B12)^('DCF Model'!C19+0)+'DCF Model'!D45/(1+$B12)^('DCF Model'!C19+1)+'DCF Model'!E45/(1+$B12)^('DCF Model'!C19+2)+'DCF Model'!F45/(1+$B12)^('DCF Model'!C19+3)+'DCF Model'!G45/(1+$B12)^('DCF Model'!C19+4)+'DCF Model'!H45/(1+$B12)^('DCF Model'!C19+5)+'DCF Model'!I45/(1+$B12)^('DCF Model'!C19+6)+'DCF Model'!J45/(1+$B12)^('DCF Model'!C19+7)+'DCF Model'!J45*(1+C$6)/($B12-C$6)/(1+$B12)^('DCF Model'!C19+7)-'DCF Model'!C16)*1000000/'DCF Model'!C15,0),"") -> 9 | D12: =IFERROR(ROUND(('DCF Model'!C45/(1+$B12)^('DCF Model'!C19+0)+'DCF Model'!D45/(1+$B12)^('DCF Model'!C19+1)+'DCF Model'!E45/(1+$B12)^('DCF Model'!C19+2)+'DCF Model'!F45/(1+$B12)^('DCF Model'!C19+3)+'DCF Model'!G45/(1+$B12)^('DCF Model'!C19+4)+'DCF Model'!H45/(1+$B12)^('DCF Model'!C19+5)+'DCF Model'!I45/(1+$B12)^('DCF Model'!C19+6)+'DCF Model'!J45/(1+$B12)^('DCF Model'!C19+7)+'DCF Model'!J45*(1+D$6)/($B12-D$6)/(1+$B12)^('DCF Model'!C19+7)-'DCF Model'!C16)*1000000/'DCF Model'!C15,0),"") -> 14 | E12: =IFERROR(ROUND(('DCF Model'!C45/(1+$B12)^('DCF Model'!C19+0)+'DCF Model'!D45/(1+$B12)^('DCF Model'!C19+1)+'DCF Model'!E45/(1+$B12)^('DCF Model'!C19+2)+'DCF Model'!F45/(1+$B12)^('DCF Model'!C19+3)+'DCF Model'!G45/(1+$B12)^('DCF Model'!C19+4)+'DCF Model'!H45/(1+$B12)^('DCF Model'!C19+5)+'DCF Model'!I45/(1+$B12)^('DCF Model'!C19+6)+'DCF Model'!J45/(1+$B12)^('DCF Model'!C19+7)+'DCF Model'!J45*(1+E$6)/($B12-E$6)/(1+$B12)^('DCF Model'!C19+7)-'DCF Model'!C16)*1000000/'DCF Model'!C15,0),"") -> 19 | F12: =IFERROR(ROUND(('DCF Model'!C45/(1+$B12)^('DCF Model'!C19+0)+'DCF Model'!D45/(1+$B12)^('DCF Model'!C19+1)+'DCF Model'!E45/(1+$B12)^('DCF Model'!C19+2)+'DCF Model'!F45/(1+$B12)^('DCF Model'!C19+3)+'DCF Model'!G45/(1+$B12)^('DCF Model'!C19+4)+'DCF Model'!H45/(1+$B12)^('DCF Model'!C19+5)+'DCF Model'!I45/(1+$B12)^('DCF Model'!C19+6)+'DCF Model'!J45/(1+$B12)^('DCF Model'!C19+7)+'DCF Model'!J45*(1+F$6)/($B12-F$6)/(1+$B12)^('DCF Model'!C19+7)-'DCF Model'!C16)*1000000/'DCF Model'!C15,0),"") -> 25 | G12: =IFERROR(ROUND(('DCF Model'!C45/(1+$B12)^('DCF Model'!C19+0)+'DCF Model'!D45/(1+$B12)^('DCF Model'!C19+1)+'DCF Model'!E45/(1+$B12)^('DCF Model'!C19+2)+'DCF Model'!F45/(1+$B12)^('DCF Model'!C19+3)+'DCF Model'!G45/(1+$B12)^('DCF Model'!C19+4)+'DCF Model'!H45/(1+$B12)^('DCF Model'!C19+5)+'DCF Model'!I45/(1+$B12)^('DCF Model'!C19+6)+'DCF Model'!J45/(1+$B12)^('DCF Model'!C19+7)+'DCF Model'!J45*(1+G$6)/($B12-G$6)/(1+$B12)^('DCF Model'!C19+7)-'DCF Model'!C16)*1000000/'DCF Model'!C15,0),"") -> 30 | H12: =IFERROR(ROUND(('DCF Model'!C45/(1+$B12)^('DCF Model'!C19+0)+'DCF Model'!D45/(1+$B12)^('DCF Model'!C19+1)+'DCF Model'!E45/(1+$B12)^('DCF Model'!C19+2)+'DCF Model'!F45/(1+$B12)^('DCF Model'!C19+3)+'DCF Model'!G45/(1+$B12)^('DCF Model'!C19+4)+'DCF Model'!H45/(1+$B12)^('DCF Model'!C19+5)+'DCF Model'!I45/(1+$B12)^('DCF Model'!C19+6)+'DCF Model'!J45/(1+$B12)^('DCF Model'!C19+7)+'DCF Model'!J45*(1+H$6)/($B12-H$6)/(1+$B12)^('DCF Model'!C19+7)-'DCF Model'!C16)*1000000/'DCF Model'!C15,0),"") -> 36 | I12: =IFERROR(ROUND(('DCF Model'!C45/(1+$B12)^('DCF Model'!C19+0)+'DCF Model'!D45/(1+$B12)^('DCF Model'!C19+1)+'DCF Model'!E45/(1+$B12)^('DCF Model'!C19+2)+'DCF Model'!F45/(1+$B12)^('DCF Model'!C19+3)+'DCF Model'!G45/(1+$B12)^('DCF Model'!C19+4)+'DCF Model'!H45/(1+$B12)^('DCF Model'!C19+5)+'DCF Model'!I45/(1+$B12)^('DCF Model'!C19+6)+'DCF Model'!J45/(1+$B12)^('DCF Model'!C19+7)+'DCF Model'!J45*(1+I$6)/($B12-I$6)/(1+$B12)^('DCF Model'!C19+7)-'DCF Model'!C16)*1000000/'DCF Model'!C15,0),"") -> 42
B13: =$C$3+0.015 -> 0.14425 | C13: =IFERROR(ROUND(('DCF Model'!C45/(1+$B13)^('DCF Model'!C19+0)+'DCF Model'!D45/(1+$B13)^('DCF Model'!C19+1)+'DCF Model'!E45/(1+$B13)^('DCF Model'!C19+2)+'DCF Model'!F45/(1+$B13)^('DCF Model'!C19+3)+'DCF Model'!G45/(1+$B13)^('DCF Model'!C19+4)+'DCF Model'!H45/(1+$B13)^('DCF Model'!C19+5)+'DCF Model'!I45/(1+$B13)^('DCF Model'!C19+6)+'DCF Model'!J45/(1+$B13)^('DCF Model'!C19+7)+'DCF Model'!J45*(1+C$6)/($B13-C$6)/(1+$B13)^('DCF Model'!C19+7)-'DCF Model'!C16)*1000000/'DCF Model'!C15,0),"") -> -4 | D13: =IFERROR(ROUND(('DCF Model'!C45/(1+$B13)^('DCF Model'!C19+0)+'DCF Model'!D45/(1+$B13)^('DCF Model'!C19+1)+'DCF Model'!E45/(1+$B13)^('DCF Model'!C19+2)+'DCF Model'!F45/(1+$B13)^('DCF Model'!C19+3)+'DCF Model'!G45/(1+$B13)^('DCF Model'!C19+4)+'DCF Model'!H45/(1+$B13)^('DCF Model'!C19+5)+'DCF Model'!I45/(1+$B13)^('DCF Model'!C19+6)+'DCF Model'!J45/(1+$B13)^('DCF Model'!C19+7)+'DCF Model'!J45*(1+D$6)/($B13-D$6)/(1+$B13)^('DCF Model'!C19+7)-'DCF Model'!C16)*1000000/'DCF Model'!C15,0),"") -> 1 | E13: =IFERROR(ROUND(('DCF Model'!C45/(1+$B13)^('DCF Model'!C19+0)+'DCF Model'!D45/(1+$B13)^('DCF Model'!C19+1)+'DCF Model'!E45/(1+$B13)^('DCF Model'!C19+2)+'DCF Model'!F45/(1+$B13)^('DCF Model'!C19+3)+'DCF Model'!G45/(1+$B13)^('DCF Model'!C19+4)+'DCF Model'!H45/(1+$B13)^('DCF Model'!C19+5)+'DCF Model'!I45/(1+$B13)^('DCF Model'!C19+6)+'DCF Model'!J45/(1+$B13)^('DCF Model'!C19+7)+'DCF Model'!J45*(1+E$6)/($B13-E$6)/(1+$B13)^('DCF Model'!C19+7)-'DCF Model'!C16)*1000000/'DCF Model'!C15,0),"") -> 5 | F13: =IFERROR(ROUND(('DCF Model'!C45/(1+$B13)^('DCF Model'!C19+0)+'DCF Model'!D45/(1+$B13)^('DCF Model'!C19+1)+'DCF Model'!E45/(1+$B13)^('DCF Model'!C19+2)+'DCF Model'!F45/(1+$B13)^('DCF Model'!C19+3)+'DCF Model'!G45/(1+$B13)^('DCF Model'!C19+4)+'DCF Model'!H45/(1+$B13)^('DCF Model'!C19+5)+'DCF Model'!I45/(1+$B13)^('DCF Model'!C19+6)+'DCF Model'!J45/(1+$B13)^('DCF Model'!C19+7)+'DCF Model'!J45*(1+F$6)/($B13-F$6)/(1+$B13)^('DCF Model'!C19+7)-'DCF Model'!C16)*1000000/'DCF Model'!C15,0),"") -> 10 | G13: =IFERROR(ROUND(('DCF Model'!C45/(1+$B13)^('DCF Model'!C19+0)+'DCF Model'!D45/(1+$B13)^('DCF Model'!C19+1)+'DCF Model'!E45/(1+$B13)^('DCF Model'!C19+2)+'DCF Model'!F45/(1+$B13)^('DCF Model'!C19+3)+'DCF Model'!G45/(1+$B13)^('DCF Model'!C19+4)+'DCF Model'!H45/(1+$B13)^('DCF Model'!C19+5)+'DCF Model'!I45/(1+$B13)^('DCF Model'!C19+6)+'DCF Model'!J45/(1+$B13)^('DCF Model'!C19+7)+'DCF Model'!J45*(1+G$6)/($B13-G$6)/(1+$B13)^('DCF Model'!C19+7)-'DCF Model'!C16)*1000000/'DCF Model'!C15,0),"") -> 15 | H13: =IFERROR(ROUND(('DCF Model'!C45/(1+$B13)^('DCF Model'!C19+0)+'DCF Model'!D45/(1+$B13)^('DCF Model'!C19+1)+'DCF Model'!E45/(1+$B13)^('DCF Model'!C19+2)+'DCF Model'!F45/(1+$B13)^('DCF Model'!C19+3)+'DCF Model'!G45/(1+$B13)^('DCF Model'!C19+4)+'DCF Model'!H45/(1+$B13)^('DCF Model'!C19+5)+'DCF Model'!I45/(1+$B13)^('DCF Model'!C19+6)+'DCF Model'!J45/(1+$B13)^('DCF Model'!C19+7)+'DCF Model'!J45*(1+H$6)/($B13-H$6)/(1+$B13)^('DCF Model'!C19+7)-'DCF Model'!C16)*1000000/'DCF Model'!C15,0),"") -> 20 | I13: =IFERROR(ROUND(('DCF Model'!C45/(1+$B13)^('DCF Model'!C19+0)+'DCF Model'!D45/(1+$B13)^('DCF Model'!C19+1)+'DCF Model'!E45/(1+$B13)^('DCF Model'!C19+2)+'DCF Model'!F45/(1+$B13)^('DCF Model'!C19+3)+'DCF Model'!G45/(1+$B13)^('DCF Model'!C19+4)+'DCF Model'!H45/(1+$B13)^('DCF Model'!C19+5)+'DCF Model'!I45/(1+$B13)^('DCF Model'!C19+6)+'DCF Model'!J45/(1+$B13)^('DCF Model'!C19+7)+'DCF Model'!J45*(1+I$6)/($B13-I$6)/(1+$B13)^('DCF Model'!C19+7)-'DCF Model'!C16)*1000000/'DCF Model'!C15,0),"") -> 26
B16: Table 2: WACC vs Exit Multiple (Exit Multiple - Implied Share Price, JPY)
B17: WACC \ Exit Multiple | C17: =$I$3-3 -> -1 | D17: =$I$3-2 -> 0 | E17: =$I$3-1 -> 1 | F17: =$I$3 -> 2 | G17: =$I$3+1 -> 3 | H17: =$I$3+2 -> 4 | I17: =$I$3+3 -> 5
B18: =$C$3-0.015 -> 0.11425 | C18: =IFERROR(ROUND(('DCF Model'!C45/(1+$B18)^('DCF Model'!C19+0)+'DCF Model'!D45/(1+$B18)^('DCF Model'!C19+1)+'DCF Model'!E45/(1+$B18)^('DCF Model'!C19+2)+'DCF Model'!F45/(1+$B18)^('DCF Model'!C19+3)+'DCF Model'!G45/(1+$B18)^('DCF Model'!C19+4)+'DCF Model'!H45/(1+$B18)^('DCF Model'!C19+5)+'DCF Model'!I45/(1+$B18)^('DCF Model'!C19+6)+'DCF Model'!J45/(1+$B18)^('DCF Model'!C19+7)+'DCF Model'!J33*C$17/(1+$B18)^('DCF Model'!C19+7)-'DCF Model'!C16)*1000000/'DCF Model'!C15,0),"") -> -890 | D18: =IFERROR(ROUND(('DCF Model'!C45/(1+$B18)^('DCF Model'!C19+0)+'DCF Model'!D45/(1+$B18)^('DCF Model'!C19+1)+'DCF Model'!E45/(1+$B18)^('DCF Model'!C19+2)+'DCF Model'!F45/(1+$B18)^('DCF Model'!C19+3)+'DCF Model'!G45/(1+$B18)^('DCF Model'!C19+4)+'DCF Model'!H45/(1+$B18)^('DCF Model'!C19+5)+'DCF Model'!I45/(1+$B18)^('DCF Model'!C19+6)+'DCF Model'!J45/(1+$B18)^('DCF Model'!C19+7)+'DCF Model'!J33*D$17/(1+$B18)^('DCF Model'!C19+7)-'DCF Model'!C16)*1000000/'DCF Model'!C15,0),"") -> -220 | E18: =IFERROR(ROUND(('DCF Model'!C45/(1+$B18)^('DCF Model'!C19+0)+'DCF Model'!D45/(1+$B18)^('DCF Model'!C19+1)+'DCF Model'!E45/(1+$B18)^('DCF Model'!C19+2)+'DCF Model'!F45/(1+$B18)^('DCF Model'!C19+3)+'DCF Model'!G45/(1+$B18)^('DCF Model'!C19+4)+'DCF Model'!H45/(1+$B18)^('DCF Model'!C19+5)+'DCF Model'!I45/(1+$B18)^('DCF Model'!C19+6)+'DCF Model'!J45/(1+$B18)^('DCF Model'!C19+7)+'DCF Model'!J33*E$17/(1+$B18)^('DCF Model'!C19+7)-'DCF Model'!C16)*1000000/'DCF Model'!C15,0),"") -> 450 | F18: =IFERROR(ROUND(('DCF Model'!C45/(1+$B18)^('DCF Model'!C19+0)+'DCF Model'!D45/(1+$B18)^('DCF Model'!C19+1)+'DCF Model'!E45/(1+$B18)^('DCF Model'!C19+2)+'DCF Model'!F45/(1+$B18)^('DCF Model'!C19+3)+'DCF Model'!G45/(1+$B18)^('DCF Model'!C19+4)+'DCF Model'!H45/(1+$B18)^('DCF Model'!C19+5)+'DCF Model'!I45/(1+$B18)^('DCF Model'!C19+6)+'DCF Model'!J45/(1+$B18)^('DCF Model'!C19+7)+'DCF Model'!J33*F$17/(1+$B18)^('DCF Model'!C19+7)-'DCF Model'!C16)*1000000/'DCF Model'!C15,0),"") -> 1119 | G18: =IFERROR(ROUND(('DCF Model'!C45/(1+$B18)^('DCF Model'!C19+0)+'DCF Model'!D45/(1+$B18)^('DCF Model'!C19+1)+'DCF Model'!E45/(1+$B18)^('DCF Model'!C19+2)+'DCF Model'!F45/(1+$B18)^('DCF Model'!C19+3)+'DCF Model'!G45/(1+$B18)^('DCF Model'!C19+4)+'DCF Model'!H45/(1+$B18)^('DCF Model'!C19+5)+'DCF Model'!I45/(1+$B18)^('DCF Model'!C19+6)+'DCF Model'!J45/(1+$B18)^('DCF Model'!C19+7)+'DCF Model'!J33*G$17/(1+$B18)^('DCF Model'!C19+7)-'DCF Model'!C16)*1000000/'DCF Model'!C15,0),"") -> 1789 | H18: =IFERROR(ROUND(('DCF Model'!C45/(1+$B18)^('DCF Model'!C19+0)+'DCF Model'!D45/(1+$B18)^('DCF Model'!C19+1)+'DCF Model'!E45/(1+$B18)^('DCF Model'!C19+2)+'DCF Model'!F45/(1+$B18)^('DCF Model'!C19+3)+'DCF Model'!G45/(1+$B18)^('DCF Model'!C19+4)+'DCF Model'!H45/(1+$B18)^('DCF Model'!C19+5)+'DCF Model'!I45/(1+$B18)^('DCF Model'!C19+6)+'DCF Model'!J45/(1+$B18)^('DCF Model'!C19+7)+'DCF Model'!J33*H$17/(1+$B18)^('DCF Model'!C19+7)-'DCF Model'!C16)*1000000/'DCF Model'!C15,0),"") -> 2459 | I18: =IFERROR(ROUND(('DCF Model'!C45/(1+$B18)^('DCF Model'!C19+0)+'DCF Model'!D45/(1+$B18)^('DCF Model'!C19+1)+'DCF Model'!E45/(1+$B18)^('DCF Model'!C19+2)+'DCF Model'!F45/(1+$B18)^('DCF Model'!C19+3)+'DCF Model'!G45/(1+$B18)^('DCF Model'!C19+4)+'DCF Model'!H45/(1+$B18)^('DCF Model'!C19+5)+'DCF Model'!I45/(1+$B18)^('DCF Model'!C19+6)+'DCF Model'!J45/(1+$B18)^('DCF Model'!C19+7)+'DCF Model'!J33*I$17/(1+$B18)^('DCF Model'!C19+7)-'DCF Model'!C16)*1000000/'DCF Model'!C15,0),"") -> 3129
B19: =$C$3-0.01 -> 0.11925 | C19: =IFERROR(ROUND(('DCF Model'!C45/(1+$B19)^('DCF Model'!C19+0)+'DCF Model'!D45/(1+$B19)^('DCF Model'!C19+1)+'DCF Model'!E45/(1+$B19)^('DCF Model'!C19+2)+'DCF Model'!F45/(1+$B19)^('DCF Model'!C19+3)+'DCF Model'!G45/(1+$B19)^('DCF Model'!C19+4)+'DCF Model'!H45/(1+$B19)^('DCF Model'!C19+5)+'DCF Model'!I45/(1+$B19)^('DCF Model'!C19+6)+'DCF Model'!J45/(1+$B19)^('DCF Model'!C19+7)+'DCF Model'!J33*C$17/(1+$B19)^('DCF Model'!C19+7)-'DCF Model'!C16)*1000000/'DCF Model'!C15,0),"") -> -866 | D19: =IFERROR(ROUND(('DCF Model'!C45/(1+$B19)^('DCF Model'!C19+0)+'DCF Model'!D45/(1+$B19)^('DCF Model'!C19+1)+'DCF Model'!E45/(1+$B19)^('DCF Model'!C19+2)+'DCF Model'!F45/(1+$B19)^('DCF Model'!C19+3)+'DCF Model'!G45/(1+$B19)^('DCF Model'!C19+4)+'DCF Model'!H45/(1+$B19)^('DCF Model'!C19+5)+'DCF Model'!I45/(1+$B19)^('DCF Model'!C19+6)+'DCF Model'!J45/(1+$B19)^('DCF Model'!C19+7)+'DCF Model'!J33*D$17/(1+$B19)^('DCF Model'!C19+7)-'DCF Model'!C16)*1000000/'DCF Model'!C15,0),"") -> -218 | E19: =IFERROR(ROUND(('DCF Model'!C45/(1+$B19)^('DCF Model'!C19+0)+'DCF Model'!D45/(1+$B19)^('DCF Model'!C19+1)+'DCF Model'!E45/(1+$B19)^('DCF Model'!C19+2)+'DCF Model'!F45/(1+$B19)^('DCF Model'!C19+3)+'DCF Model'!G45/(1+$B19)^('DCF Model'!C19+4)+'DCF Model'!H45/(1+$B19)^('DCF Model'!C19+5)+'DCF Model'!I45/(1+$B19)^('DCF Model'!C19+6)+'DCF Model'!J45/(1+$B19)^('DCF Model'!C19+7)+'DCF Model'!J33*E$17/(1+$B19)^('DCF Model'!C19+7)-'DCF Model'!C16)*1000000/'DCF Model'!C15,0),"") -> 430 | F19: =IFERROR(ROUND(('DCF Model'!C45/(1+$B19)^('DCF Model'!C19+0)+'DCF Model'!D45/(1+$B19)^('DCF Model'!C19+1)+'DCF Model'!E45/(1+$B19)^('DCF Model'!C19+2)+'DCF Model'!F45/(1+$B19)^('DCF Model'!C19+3)+'DCF Model'!G45/(1+$B19)^('DCF Model'!C19+4)+'DCF Model'!H45/(1+$B19)^('DCF Model'!C19+5)+'DCF Model'!I45/(1+$B19)^('DCF Model'!C19+6)+'DCF Model'!J45/(1+$B19)^('DCF Model'!C19+7)+'DCF Model'!J33*F$17/(1+$B19)^('DCF Model'!C19+7)-'DCF Model'!C16)*1000000/'DCF Model'!C15,0),"") -> 1078 | G19: =IFERROR(ROUND(('DCF Model'!C45/(1+$B19)^('DCF Model'!C19+0)+'DCF Model'!D45/(1+$B19)^('DCF Model'!C19+1)+'DCF Model'!E45/(1+$B19)^('DCF Model'!C19+2)+'DCF Model'!F45/(1+$B19)^('DCF Model'!C19+3)+'DCF Model'!G45/(1+$B19)^('DCF Model'!C19+4)+'DCF Model'!H45/(1+$B19)^('DCF Model'!C19+5)+'DCF Model'!I45/(1+$B19)^('DCF Model'!C19+6)+'DCF Model'!J45/(1+$B19)^('DCF Model'!C19+7)+'DCF Model'!J33*G$17/(1+$B19)^('DCF Model'!C19+7)-'DCF Model'!C16)*1000000/'DCF Model'!C15,0),"") -> 1726 | H19: =IFERROR(ROUND(('DCF Model'!C45/(1+$B19)^('DCF Model'!C19+0)+'DCF Model'!D45/(1+$B19)^('DCF Model'!C19+1)+'DCF Model'!E45/(1+$B19)^('DCF Model'!C19+2)+'DCF Model'!F45/(1+$B19)^('DCF Model'!C19+3)+'DCF Model'!G45/(1+$B19)^('DCF Model'!C19+4)+'DCF Model'!H45/(1+$B19)^('DCF Model'!C19+5)+'DCF Model'!I45/(1+$B19)^('DCF Model'!C19+6)+'DCF Model'!J45/(1+$B19)^('DCF Model'!C19+7)+'DCF Model'!J33*H$17/(1+$B19)^('DCF Model'!C19+7)-'DCF Model'!C16)*1000000/'DCF Model'!C15,0),"") -> 2374 | I19: =IFERROR(ROUND(('DCF Model'!C45/(1+$B19)^('DCF Model'!C19+0)+'DCF Model'!D45/(1+$B19)^('DCF Model'!C19+1)+'DCF Model'!E45/(1+$B19)^('DCF Model'!C19+2)+'DCF Model'!F45/(1+$B19)^('DCF Model'!C19+3)+'DCF Model'!G45/(1+$B19)^('DCF Model'!C19+4)+'DCF Model'!H45/(1+$B19)^('DCF Model'!C19+5)+'DCF Model'!I45/(1+$B19)^('DCF Model'!C19+6)+'DCF Model'!J45/(1+$B19)^('DCF Model'!C19+7)+'DCF Model'!J33*I$17/(1+$B19)^('DCF Model'!C19+7)-'DCF Model'!C16)*1000000/'DCF Model'!C15,0),"") -> 3022
B20: =$C$3-0.005 -> 0.12425 | C20: =IFERROR(ROUND(('DCF Model'!C45/(1+$B20)^('DCF Model'!C19+0)+'DCF Model'!D45/(1+$B20)^('DCF Model'!C19+1)+'DCF Model'!E45/(1+$B20)^('DCF Model'!C19+2)+'DCF Model'!F45/(1+$B20)^('DCF Model'!C19+3)+'DCF Model'!G45/(1+$B20)^('DCF Model'!C19+4)+'DCF Model'!H45/(1+$B20)^('DCF Model'!C19+5)+'DCF Model'!I45/(1+$B20)^('DCF Model'!C19+6)+'DCF Model'!J45/(1+$B20)^('DCF Model'!C19+7)+'DCF Model'!J33*C$17/(1+$B20)^('DCF Model'!C19+7)-'DCF Model'!C16)*1000000/'DCF Model'!C15,0),"") -> -843 | D20: =IFERROR(ROUND(('DCF Model'!C45/(1+$B20)^('DCF Model'!C19+0)+'DCF Model'!D45/(1+$B20)^('DCF Model'!C19+1)+'DCF Model'!E45/(1+$B20)^('DCF Model'!C19+2)+'DCF Model'!F45/(1+$B20)^('DCF Model'!C19+3)+'DCF Model'!G45/(1+$B20)^('DCF Model'!C19+4)+'DCF Model'!H45/(1+$B20)^('DCF Model'!C19+5)+'DCF Model'!I45/(1+$B20)^('DCF Model'!C19+6)+'DCF Model'!J45/(1+$B20)^('DCF Model'!C19+7)+'DCF Model'!J33*D$17/(1+$B20)^('DCF Model'!C19+7)-'DCF Model'!C16)*1000000/'DCF Model'!C15,0),"") -> -216 | E20: =IFERROR(ROUND(('DCF Model'!C45/(1+$B20)^('DCF Model'!C19+0)+'DCF Model'!D45/(1+$B20)^('DCF Model'!C19+1)+'DCF Model'!E45/(1+$B20)^('DCF Model'!C19+2)+'DCF Model'!F45/(1+$B20)^('DCF Model'!C19+3)+'DCF Model'!G45/(1+$B20)^('DCF Model'!C19+4)+'DCF Model'!H45/(1+$B20)^('DCF Model'!C19+5)+'DCF Model'!I45/(1+$B20)^('DCF Model'!C19+6)+'DCF Model'!J45/(1+$B20)^('DCF Model'!C19+7)+'DCF Model'!J33*E$17/(1+$B20)^('DCF Model'!C19+7)-'DCF Model'!C16)*1000000/'DCF Model'!C15,0),"") -> 411 | F20: =IFERROR(ROUND(('DCF Model'!C45/(1+$B20)^('DCF Model'!C19+0)+'DCF Model'!D45/(1+$B20)^('DCF Model'!C19+1)+'DCF Model'!E45/(1+$B20)^('DCF Model'!C19+2)+'DCF Model'!F45/(1+$B20)^('DCF Model'!C19+3)+'DCF Model'!G45/(1+$B20)^('DCF Model'!C19+4)+'DCF Model'!H45/(1+$B20)^('DCF Model'!C19+5)+'DCF Model'!I45/(1+$B20)^('DCF Model'!C19+6)+'DCF Model'!J45/(1+$B20)^('DCF Model'!C19+7)+'DCF Model'!J33*F$17/(1+$B20)^('DCF Model'!C19+7)-'DCF Model'!C16)*1000000/'DCF Model'!C15,0),"") -> 1038 | G20: =IFERROR(ROUND(('DCF Model'!C45/(1+$B20)^('DCF Model'!C19+0)+'DCF Model'!D45/(1+$B20)^('DCF Model'!C19+1)+'DCF Model'!E45/(1+$B20)^('DCF Model'!C19+2)+'DCF Model'!F45/(1+$B20)^('DCF Model'!C19+3)+'DCF Model'!G45/(1+$B20)^('DCF Model'!C19+4)+'DCF Model'!H45/(1+$B20)^('DCF Model'!C19+5)+'DCF Model'!I45/(1+$B20)^('DCF Model'!C19+6)+'DCF Model'!J45/(1+$B20)^('DCF Model'!C19+7)+'DCF Model'!J33*G$17/(1+$B20)^('DCF Model'!C19+7)-'DCF Model'!C16)*1000000/'DCF Model'!C15,0),"") -> 1664 | H20: =IFERROR(ROUND(('DCF Model'!C45/(1+$B20)^('DCF Model'!C19+0)+'DCF Model'!D45/(1+$B20)^('DCF Model'!C19+1)+'DCF Model'!E45/(1+$B20)^('DCF Model'!C19+2)+'DCF Model'!F45/(1+$B20)^('DCF Model'!C19+3)+'DCF Model'!G45/(1+$B20)^('DCF Model'!C19+4)+'DCF Model'!H45/(1+$B20)^('DCF Model'!C19+5)+'DCF Model'!I45/(1+$B20)^('DCF Model'!C19+6)+'DCF Model'!J45/(1+$B20)^('DCF Model'!C19+7)+'DCF Model'!J33*H$17/(1+$B20)^('DCF Model'!C19+7)-'DCF Model'!C16)*1000000/'DCF Model'!C15,0),"") -> 2291 | I20: =IFERROR(ROUND(('DCF Model'!C45/(1+$B20)^('DCF Model'!C19+0)+'DCF Model'!D45/(1+$B20)^('DCF Model'!C19+1)+'DCF Model'!E45/(1+$B20)^('DCF Model'!C19+2)+'DCF Model'!F45/(1+$B20)^('DCF Model'!C19+3)+'DCF Model'!G45/(1+$B20)^('DCF Model'!C19+4)+'DCF Model'!H45/(1+$B20)^('DCF Model'!C19+5)+'DCF Model'!I45/(1+$B20)^('DCF Model'!C19+6)+'DCF Model'!J45/(1+$B20)^('DCF Model'!C19+7)+'DCF Model'!J33*I$17/(1+$B20)^('DCF Model'!C19+7)-'DCF Model'!C16)*1000000/'DCF Model'!C15,0),"") -> 2918
B21: =$C$3 -> 0.12925 | C21: =IFERROR(ROUND(('DCF Model'!C45/(1+$B21)^('DCF Model'!C19+0)+'DCF Model'!D45/(1+$B21)^('DCF Model'!C19+1)+'DCF Model'!E45/(1+$B21)^('DCF Model'!C19+2)+'DCF Model'!F45/(1+$B21)^('DCF Model'!C19+3)+'DCF Model'!G45/(1+$B21)^('DCF Model'!C19+4)+'DCF Model'!H45/(1+$B21)^('DCF Model'!C19+5)+'DCF Model'!I45/(1+$B21)^('DCF Model'!C19+6)+'DCF Model'!J45/(1+$B21)^('DCF Model'!C19+7)+'DCF Model'!J33*C$17/(1+$B21)^('DCF Model'!C19+7)-'DCF Model'!C16)*1000000/'DCF Model'!C15,0),"") -> -821 | D21: =IFERROR(ROUND(('DCF Model'!C45/(1+$B21)^('DCF Model'!C19+0)+'DCF Model'!D45/(1+$B21)^('DCF Model'!C19+1)+'DCF Model'!E45/(1+$B21)^('DCF Model'!C19+2)+'DCF Model'!F45/(1+$B21)^('DCF Model'!C19+3)+'DCF Model'!G45/(1+$B21)^('DCF Model'!C19+4)+'DCF Model'!H45/(1+$B21)^('DCF Model'!C19+5)+'DCF Model'!I45/(1+$B21)^('DCF Model'!C19+6)+'DCF Model'!J45/(1+$B21)^('DCF Model'!C19+7)+'DCF Model'!J33*D$17/(1+$B21)^('DCF Model'!C19+7)-'DCF Model'!C16)*1000000/'DCF Model'!C15,0),"") -> -214 | E21: =IFERROR(ROUND(('DCF Model'!C45/(1+$B21)^('DCF Model'!C19+0)+'DCF Model'!D45/(1+$B21)^('DCF Model'!C19+1)+'DCF Model'!E45/(1+$B21)^('DCF Model'!C19+2)+'DCF Model'!F45/(1+$B21)^('DCF Model'!C19+3)+'DCF Model'!G45/(1+$B21)^('DCF Model'!C19+4)+'DCF Model'!H45/(1+$B21)^('DCF Model'!C19+5)+'DCF Model'!I45/(1+$B21)^('DCF Model'!C19+6)+'DCF Model'!J45/(1+$B21)^('DCF Model'!C19+7)+'DCF Model'!J33*E$17/(1+$B21)^('DCF Model'!C19+7)-'DCF Model'!C16)*1000000/'DCF Model'!C15,0),"") -> 393 | F21: =IFERROR(ROUND(('DCF Model'!C45/(1+$B21)^('DCF Model'!C19+0)+'DCF Model'!D45/(1+$B21)^('DCF Model'!C19+1)+'DCF Model'!E45/(1+$B21)^('DCF Model'!C19+2)+'DCF Model'!F45/(1+$B21)^('DCF Model'!C19+3)+'DCF Model'!G45/(1+$B21)^('DCF Model'!C19+4)+'DCF Model'!H45/(1+$B21)^('DCF Model'!C19+5)+'DCF Model'!I45/(1+$B21)^('DCF Model'!C19+6)+'DCF Model'!J45/(1+$B21)^('DCF Model'!C19+7)+'DCF Model'!J33*F$17/(1+$B21)^('DCF Model'!C19+7)-'DCF Model'!C16)*1000000/'DCF Model'!C15,0),"") -> 999 | G21: =IFERROR(ROUND(('DCF Model'!C45/(1+$B21)^('DCF Model'!C19+0)+'DCF Model'!D45/(1+$B21)^('DCF Model'!C19+1)+'DCF Model'!E45/(1+$B21)^('DCF Model'!C19+2)+'DCF Model'!F45/(1+$B21)^('DCF Model'!C19+3)+'DCF Model'!G45/(1+$B21)^('DCF Model'!C19+4)+'DCF Model'!H45/(1+$B21)^('DCF Model'!C19+5)+'DCF Model'!I45/(1+$B21)^('DCF Model'!C19+6)+'DCF Model'!J45/(1+$B21)^('DCF Model'!C19+7)+'DCF Model'!J33*G$17/(1+$B21)^('DCF Model'!C19+7)-'DCF Model'!C16)*1000000/'DCF Model'!C15,0),"") -> 1606 | H21: =IFERROR(ROUND(('DCF Model'!C45/(1+$B21)^('DCF Model'!C19+0)+'DCF Model'!D45/(1+$B21)^('DCF Model'!C19+1)+'DCF Model'!E45/(1+$B21)^('DCF Model'!C19+2)+'DCF Model'!F45/(1+$B21)^('DCF Model'!C19+3)+'DCF Model'!G45/(1+$B21)^('DCF Model'!C19+4)+'DCF Model'!H45/(1+$B21)^('DCF Model'!C19+5)+'DCF Model'!I45/(1+$B21)^('DCF Model'!C19+6)+'DCF Model'!J45/(1+$B21)^('DCF Model'!C19+7)+'DCF Model'!J33*H$17/(1+$B21)^('DCF Model'!C19+7)-'DCF Model'!C16)*1000000/'DCF Model'!C15,0),"") -> 2212 | I21: =IFERROR(ROUND(('DCF Model'!C45/(1+$B21)^('DCF Model'!C19+0)+'DCF Model'!D45/(1+$B21)^('DCF Model'!C19+1)+'DCF Model'!E45/(1+$B21)^('DCF Model'!C19+2)+'DCF Model'!F45/(1+$B21)^('DCF Model'!C19+3)+'DCF Model'!G45/(1+$B21)^('DCF Model'!C19+4)+'DCF Model'!H45/(1+$B21)^('DCF Model'!C19+5)+'DCF Model'!I45/(1+$B21)^('DCF Model'!C19+6)+'DCF Model'!J45/(1+$B21)^('DCF Model'!C19+7)+'DCF Model'!J33*I$17/(1+$B21)^('DCF Model'!C19+7)-'DCF Model'!C16)*1000000/'DCF Model'!C15,0),"") -> 2819
B22: =$C$3+0.005 -> 0.13425 | C22: =IFERROR(ROUND(('DCF Model'!C45/(1+$B22)^('DCF Model'!C19+0)+'DCF Model'!D45/(1+$B22)^('DCF Model'!C19+1)+'DCF Model'!E45/(1+$B22)^('DCF Model'!C19+2)+'DCF Model'!F45/(1+$B22)^('DCF Model'!C19+3)+'DCF Model'!G45/(1+$B22)^('DCF Model'!C19+4)+'DCF Model'!H45/(1+$B22)^('DCF Model'!C19+5)+'DCF Model'!I45/(1+$B22)^('DCF Model'!C19+6)+'DCF Model'!J45/(1+$B22)^('DCF Model'!C19+7)+'DCF Model'!J33*C$17/(1+$B22)^('DCF Model'!C19+7)-'DCF Model'!C16)*1000000/'DCF Model'!C15,0),"") -> -799 | D22: =IFERROR(ROUND(('DCF Model'!C45/(1+$B22)^('DCF Model'!C19+0)+'DCF Model'!D45/(1+$B22)^('DCF Model'!C19+1)+'DCF Model'!E45/(1+$B22)^('DCF Model'!C19+2)+'DCF Model'!F45/(1+$B22)^('DCF Model'!C19+3)+'DCF Model'!G45/(1+$B22)^('DCF Model'!C19+4)+'DCF Model'!H45/(1+$B22)^('DCF Model'!C19+5)+'DCF Model'!I45/(1+$B22)^('DCF Model'!C19+6)+'DCF Model'!J45/(1+$B22)^('DCF Model'!C19+7)+'DCF Model'!J33*D$17/(1+$B22)^('DCF Model'!C19+7)-'DCF Model'!C16)*1000000/'DCF Model'!C15,0),"") -> -212 | E22: =IFERROR(ROUND(('DCF Model'!C45/(1+$B22)^('DCF Model'!C19+0)+'DCF Model'!D45/(1+$B22)^('DCF Model'!C19+1)+'DCF Model'!E45/(1+$B22)^('DCF Model'!C19+2)+'DCF Model'!F45/(1+$B22)^('DCF Model'!C19+3)+'DCF Model'!G45/(1+$B22)^('DCF Model'!C19+4)+'DCF Model'!H45/(1+$B22)^('DCF Model'!C19+5)+'DCF Model'!I45/(1+$B22)^('DCF Model'!C19+6)+'DCF Model'!J45/(1+$B22)^('DCF Model'!C19+7)+'DCF Model'!J33*E$17/(1+$B22)^('DCF Model'!C19+7)-'DCF Model'!C16)*1000000/'DCF Model'!C15,0),"") -> 375 | F22: =IFERROR(ROUND(('DCF Model'!C45/(1+$B22)^('DCF Model'!C19+0)+'DCF Model'!D45/(1+$B22)^('DCF Model'!C19+1)+'DCF Model'!E45/(1+$B22)^('DCF Model'!C19+2)+'DCF Model'!F45/(1+$B22)^('DCF Model'!C19+3)+'DCF Model'!G45/(1+$B22)^('DCF Model'!C19+4)+'DCF Model'!H45/(1+$B22)^('DCF Model'!C19+5)+'DCF Model'!I45/(1+$B22)^('DCF Model'!C19+6)+'DCF Model'!J45/(1+$B22)^('DCF Model'!C19+7)+'DCF Model'!J33*F$17/(1+$B22)^('DCF Model'!C19+7)-'DCF Model'!C16)*1000000/'DCF Model'!C15,0),"") -> 962 | G22: =IFERROR(ROUND(('DCF Model'!C45/(1+$B22)^('DCF Model'!C19+0)+'DCF Model'!D45/(1+$B22)^('DCF Model'!C19+1)+'DCF Model'!E45/(1+$B22)^('DCF Model'!C19+2)+'DCF Model'!F45/(1+$B22)^('DCF Model'!C19+3)+'DCF Model'!G45/(1+$B22)^('DCF Model'!C19+4)+'DCF Model'!H45/(1+$B22)^('DCF Model'!C19+5)+'DCF Model'!I45/(1+$B22)^('DCF Model'!C19+6)+'DCF Model'!J45/(1+$B22)^('DCF Model'!C19+7)+'DCF Model'!J33*G$17/(1+$B22)^('DCF Model'!C19+7)-'DCF Model'!C16)*1000000/'DCF Model'!C15,0),"") -> 1549 | H22: =IFERROR(ROUND(('DCF Model'!C45/(1+$B22)^('DCF Model'!C19+0)+'DCF Model'!D45/(1+$B22)^('DCF Model'!C19+1)+'DCF Model'!E45/(1+$B22)^('DCF Model'!C19+2)+'DCF Model'!F45/(1+$B22)^('DCF Model'!C19+3)+'DCF Model'!G45/(1+$B22)^('DCF Model'!C19+4)+'DCF Model'!H45/(1+$B22)^('DCF Model'!C19+5)+'DCF Model'!I45/(1+$B22)^('DCF Model'!C19+6)+'DCF Model'!J45/(1+$B22)^('DCF Model'!C19+7)+'DCF Model'!J33*H$17/(1+$B22)^('DCF Model'!C19+7)-'DCF Model'!C16)*1000000/'DCF Model'!C15,0),"") -> 2136 | I22: =IFERROR(ROUND(('DCF Model'!C45/(1+$B22)^('DCF Model'!C19+0)+'DCF Model'!D45/(1+$B22)^('DCF Model'!C19+1)+'DCF Model'!E45/(1+$B22)^('DCF Model'!C19+2)+'DCF Model'!F45/(1+$B22)^('DCF Model'!C19+3)+'DCF Model'!G45/(1+$B22)^('DCF Model'!C19+4)+'DCF Model'!H45/(1+$B22)^('DCF Model'!C19+5)+'DCF Model'!I45/(1+$B22)^('DCF Model'!C19+6)+'DCF Model'!J45/(1+$B22)^('DCF Model'!C19+7)+'DCF Model'!J33*I$17/(1+$B22)^('DCF Model'!C19+7)-'DCF Model'!C16)*1000000/'DCF Model'!C15,0),"") -> 2723
B23: =$C$3+0.01 -> 0.13925 | C23: =IFERROR(ROUND(('DCF Model'!C45/(1+$B23)^('DCF Model'!C19+0)+'DCF Model'!D45/(1+$B23)^('DCF Model'!C19+1)+'DCF Model'!E45/(1+$B23)^('DCF Model'!C19+2)+'DCF Model'!F45/(1+$B23)^('DCF Model'!C19+3)+'DCF Model'!G45/(1+$B23)^('DCF Model'!C19+4)+'DCF Model'!H45/(1+$B23)^('DCF Model'!C19+5)+'DCF Model'!I45/(1+$B23)^('DCF Model'!C19+6)+'DCF Model'!J45/(1+$B23)^('DCF Model'!C19+7)+'DCF Model'!J33*C$17/(1+$B23)^('DCF Model'!C19+7)-'DCF Model'!C16)*1000000/'DCF Model'!C15,0),"") -> -778 | D23: =IFERROR(ROUND(('DCF Model'!C45/(1+$B23)^('DCF Model'!C19+0)+'DCF Model'!D45/(1+$B23)^('DCF Model'!C19+1)+'DCF Model'!E45/(1+$B23)^('DCF Model'!C19+2)+'DCF Model'!F45/(1+$B23)^('DCF Model'!C19+3)+'DCF Model'!G45/(1+$B23)^('DCF Model'!C19+4)+'DCF Model'!H45/(1+$B23)^('DCF Model'!C19+5)+'DCF Model'!I45/(1+$B23)^('DCF Model'!C19+6)+'DCF Model'!J45/(1+$B23)^('DCF Model'!C19+7)+'DCF Model'!J33*D$17/(1+$B23)^('DCF Model'!C19+7)-'DCF Model'!C16)*1000000/'DCF Model'!C15,0),"") -> -210 | E23: =IFERROR(ROUND(('DCF Model'!C45/(1+$B23)^('DCF Model'!C19+0)+'DCF Model'!D45/(1+$B23)^('DCF Model'!C19+1)+'DCF Model'!E45/(1+$B23)^('DCF Model'!C19+2)+'DCF Model'!F45/(1+$B23)^('DCF Model'!C19+3)+'DCF Model'!G45/(1+$B23)^('DCF Model'!C19+4)+'DCF Model'!H45/(1+$B23)^('DCF Model'!C19+5)+'DCF Model'!I45/(1+$B23)^('DCF Model'!C19+6)+'DCF Model'!J45/(1+$B23)^('DCF Model'!C19+7)+'DCF Model'!J33*E$17/(1+$B23)^('DCF Model'!C19+7)-'DCF Model'!C16)*1000000/'DCF Model'!C15,0),"") -> 358 | F23: =IFERROR(ROUND(('DCF Model'!C45/(1+$B23)^('DCF Model'!C19+0)+'DCF Model'!D45/(1+$B23)^('DCF Model'!C19+1)+'DCF Model'!E45/(1+$B23)^('DCF Model'!C19+2)+'DCF Model'!F45/(1+$B23)^('DCF Model'!C19+3)+'DCF Model'!G45/(1+$B23)^('DCF Model'!C19+4)+'DCF Model'!H45/(1+$B23)^('DCF Model'!C19+5)+'DCF Model'!I45/(1+$B23)^('DCF Model'!C19+6)+'DCF Model'!J45/(1+$B23)^('DCF Model'!C19+7)+'DCF Model'!J33*F$17/(1+$B23)^('DCF Model'!C19+7)-'DCF Model'!C16)*1000000/'DCF Model'!C15,0),"") -> 926 | G23: =IFERROR(ROUND(('DCF Model'!C45/(1+$B23)^('DCF Model'!C19+0)+'DCF Model'!D45/(1+$B23)^('DCF Model'!C19+1)+'DCF Model'!E45/(1+$B23)^('DCF Model'!C19+2)+'DCF Model'!F45/(1+$B23)^('DCF Model'!C19+3)+'DCF Model'!G45/(1+$B23)^('DCF Model'!C19+4)+'DCF Model'!H45/(1+$B23)^('DCF Model'!C19+5)+'DCF Model'!I45/(1+$B23)^('DCF Model'!C19+6)+'DCF Model'!J45/(1+$B23)^('DCF Model'!C19+7)+'DCF Model'!J33*G$17/(1+$B23)^('DCF Model'!C19+7)-'DCF Model'!C16)*1000000/'DCF Model'!C15,0),"") -> 1495 | H23: =IFERROR(ROUND(('DCF Model'!C45/(1+$B23)^('DCF Model'!C19+0)+'DCF Model'!D45/(1+$B23)^('DCF Model'!C19+1)+'DCF Model'!E45/(1+$B23)^('DCF Model'!C19+2)+'DCF Model'!F45/(1+$B23)^('DCF Model'!C19+3)+'DCF Model'!G45/(1+$B23)^('DCF Model'!C19+4)+'DCF Model'!H45/(1+$B23)^('DCF Model'!C19+5)+'DCF Model'!I45/(1+$B23)^('DCF Model'!C19+6)+'DCF Model'!J45/(1+$B23)^('DCF Model'!C19+7)+'DCF Model'!J33*H$17/(1+$B23)^('DCF Model'!C19+7)-'DCF Model'!C16)*1000000/'DCF Model'!C15,0),"") -> 2063 | I23: =IFERROR(ROUND(('DCF Model'!C45/(1+$B23)^('DCF Model'!C19+0)+'DCF Model'!D45/(1+$B23)^('DCF Model'!C19+1)+'DCF Model'!E45/(1+$B23)^('DCF Model'!C19+2)+'DCF Model'!F45/(1+$B23)^('DCF Model'!C19+3)+'DCF Model'!G45/(1+$B23)^('DCF Model'!C19+4)+'DCF Model'!H45/(1+$B23)^('DCF Model'!C19+5)+'DCF Model'!I45/(1+$B23)^('DCF Model'!C19+6)+'DCF Model'!J45/(1+$B23)^('DCF Model'!C19+7)+'DCF Model'!J33*I$17/(1+$B23)^('DCF Model'!C19+7)-'DCF Model'!C16)*1000000/'DCF Model'!C15,0),"") -> 2631
B24: =$C$3+0.015 -> 0.14425 | C24: =IFERROR(ROUND(('DCF Model'!C45/(1+$B24)^('DCF Model'!C19+0)+'DCF Model'!D45/(1+$B24)^('DCF Model'!C19+1)+'DCF Model'!E45/(1+$B24)^('DCF Model'!C19+2)+'DCF Model'!F45/(1+$B24)^('DCF Model'!C19+3)+'DCF Model'!G45/(1+$B24)^('DCF Model'!C19+4)+'DCF Model'!H45/(1+$B24)^('DCF Model'!C19+5)+'DCF Model'!I45/(1+$B24)^('DCF Model'!C19+6)+'DCF Model'!J45/(1+$B24)^('DCF Model'!C19+7)+'DCF Model'!J33*C$17/(1+$B24)^('DCF Model'!C19+7)-'DCF Model'!C16)*1000000/'DCF Model'!C15,0),"") -> -758 | D24: =IFERROR(ROUND(('DCF Model'!C45/(1+$B24)^('DCF Model'!C19+0)+'DCF Model'!D45/(1+$B24)^('DCF Model'!C19+1)+'DCF Model'!E45/(1+$B24)^('DCF Model'!C19+2)+'DCF Model'!F45/(1+$B24)^('DCF Model'!C19+3)+'DCF Model'!G45/(1+$B24)^('DCF Model'!C19+4)+'DCF Model'!H45/(1+$B24)^('DCF Model'!C19+5)+'DCF Model'!I45/(1+$B24)^('DCF Model'!C19+6)+'DCF Model'!J45/(1+$B24)^('DCF Model'!C19+7)+'DCF Model'!J33*D$17/(1+$B24)^('DCF Model'!C19+7)-'DCF Model'!C16)*1000000/'DCF Model'!C15,0),"") -> -208 | E24: =IFERROR(ROUND(('DCF Model'!C45/(1+$B24)^('DCF Model'!C19+0)+'DCF Model'!D45/(1+$B24)^('DCF Model'!C19+1)+'DCF Model'!E45/(1+$B24)^('DCF Model'!C19+2)+'DCF Model'!F45/(1+$B24)^('DCF Model'!C19+3)+'DCF Model'!G45/(1+$B24)^('DCF Model'!C19+4)+'DCF Model'!H45/(1+$B24)^('DCF Model'!C19+5)+'DCF Model'!I45/(1+$B24)^('DCF Model'!C19+6)+'DCF Model'!J45/(1+$B24)^('DCF Model'!C19+7)+'DCF Model'!J33*E$17/(1+$B24)^('DCF Model'!C19+7)-'DCF Model'!C16)*1000000/'DCF Model'!C15,0),"") -> 342 | F24: =IFERROR(ROUND(('DCF Model'!C45/(1+$B24)^('DCF Model'!C19+0)+'DCF Model'!D45/(1+$B24)^('DCF Model'!C19+1)+'DCF Model'!E45/(1+$B24)^('DCF Model'!C19+2)+'DCF Model'!F45/(1+$B24)^('DCF Model'!C19+3)+'DCF Model'!G45/(1+$B24)^('DCF Model'!C19+4)+'DCF Model'!H45/(1+$B24)^('DCF Model'!C19+5)+'DCF Model'!I45/(1+$B24)^('DCF Model'!C19+6)+'DCF Model'!J45/(1+$B24)^('DCF Model'!C19+7)+'DCF Model'!J33*F$17/(1+$B24)^('DCF Model'!C19+7)-'DCF Model'!C16)*1000000/'DCF Model'!C15,0),"") -> 892 | G24: =IFERROR(ROUND(('DCF Model'!C45/(1+$B24)^('DCF Model'!C19+0)+'DCF Model'!D45/(1+$B24)^('DCF Model'!C19+1)+'DCF Model'!E45/(1+$B24)^('DCF Model'!C19+2)+'DCF Model'!F45/(1+$B24)^('DCF Model'!C19+3)+'DCF Model'!G45/(1+$B24)^('DCF Model'!C19+4)+'DCF Model'!H45/(1+$B24)^('DCF Model'!C19+5)+'DCF Model'!I45/(1+$B24)^('DCF Model'!C19+6)+'DCF Model'!J45/(1+$B24)^('DCF Model'!C19+7)+'DCF Model'!J33*G$17/(1+$B24)^('DCF Model'!C19+7)-'DCF Model'!C16)*1000000/'DCF Model'!C15,0),"") -> 1442 | H24: =IFERROR(ROUND(('DCF Model'!C45/(1+$B24)^('DCF Model'!C19+0)+'DCF Model'!D45/(1+$B24)^('DCF Model'!C19+1)+'DCF Model'!E45/(1+$B24)^('DCF Model'!C19+2)+'DCF Model'!F45/(1+$B24)^('DCF Model'!C19+3)+'DCF Model'!G45/(1+$B24)^('DCF Model'!C19+4)+'DCF Model'!H45/(1+$B24)^('DCF Model'!C19+5)+'DCF Model'!I45/(1+$B24)^('DCF Model'!C19+6)+'DCF Model'!J45/(1+$B24)^('DCF Model'!C19+7)+'DCF Model'!J33*H$17/(1+$B24)^('DCF Model'!C19+7)-'DCF Model'!C16)*1000000/'DCF Model'!C15,0),"") -> 1992 | I24: =IFERROR(ROUND(('DCF Model'!C45/(1+$B24)^('DCF Model'!C19+0)+'DCF Model'!D45/(1+$B24)^('DCF Model'!C19+1)+'DCF Model'!E45/(1+$B24)^('DCF Model'!C19+2)+'DCF Model'!F45/(1+$B24)^('DCF Model'!C19+3)+'DCF Model'!G45/(1+$B24)^('DCF Model'!C19+4)+'DCF Model'!H45/(1+$B24)^('DCF Model'!C19+5)+'DCF Model'!I45/(1+$B24)^('DCF Model'!C19+6)+'DCF Model'!J45/(1+$B24)^('DCF Model'!C19+7)+'DCF Model'!J33*I$17/(1+$B24)^('DCF Model'!C19+7)-'DCF Model'!C16)*1000000/'DCF Model'!C15,0),"") -> 2542
B26: All values dynamically linked to DCF Model. Headers auto-center on current WACC / Terminal g / Exit Multiple.

Sheet Adjustments Log
B2: Adjustments Log - Terra Drone
B4: 日付 | C4: セル | D4: 変更内容 | E4: 理由 | F4: 元の値 | G4: 状態
B5: 2026-08-29 | C5: - | D5: Generated by pipeline on 2026-08-29 18:39, template rev 672e3c3 | E5: 初期生成（手修正なし） | F5: - | G5: generated
B6: 2026-08-29 | C6: 全シート(単位) | D6: 原典の決算短信は【千円】表記。本モデルは全て【百万円】に換算済み | E6: 桁事故の温床であるため冒頭に明示する。EDINET有報のXBRLは円単位で取得し、パイプラインが百万円に換算している。プロンプト提供の入力表も百万円換算済みのものを受領した。相互検算: EDINET FY2026/1 売上 4,782,585,000円 = 4,782.585百万円 = プロンプト転記値4,783 と一致。同 営業損失 △1,143,791,000円 = △1,143.791百万円 = △1,144 と一致。以下このログの数値は全て百万円。 | F6: - | G6: 確定
B7: 2026-08-29 | C7: 全シート(モデルの目的) | D7: 本モデルは Target を主要アウトプットとしない。逆算(Reverse DCF)と Downside 測定が目的 | E7: 銘柄タイプは【物語先行型 = 3905型の極端例】(標準メモ §4)。2026/8/25の防衛装備庁「迎撃ドローン早期取得プログラム」量産調達契約で株価が約13,000円→21,620円へ急騰したテーマ株であり、契約金額・数量・納期はいずれも未開示。DCF の Target(529円)は『現在の事業計画が生む価値』であって『株価がどこへ行くか』の予測ではない。読む順序は (1) Reverse DCF シート、(2) Downside 1 / Downside 2 のシナリオ切替、(3) Segment Bridge シートの Table 7(希薄化)、最後に Executive Summary。 | F7: - | G7: 設計判断
B8: 2026-08-29 | C8: DCF Model!C15 / Comps Analysis 株数 | D8: Fully Diluted Shares = 10,397,100株(プロンプト指定値を採用) | E8: 【要確認】EDINET FY2026/1有報(2026-04-30提出)の発行済株式総数は 期末(2026/1/31) 9,718,000株 / 提出日(2026/4/30) 9,745,300株。同報告書のBPS 497.57 × 9,718,000 = 4,835.4百万 = 純資産5,008.6 − 新株予約権38.0 − 非支配持分135.2 と完全一致し、自己株式は無い(BPSの分母 = 発行済総数)ことを確認した。yfinance の sharesOutstanding も 9,745,300 で提出日時点と一致する。差分 10,397,100 − 9,745,300 = 651,800株(+6.7%)は2026年5〜8月の新株予約権行使ないし新株発行と推定されるが、EDINET上の一次資料では確認できていない。■感応度: 実際の株数が 9,745,300 なら時価総額は 224,785 → 210,693百万(−6.3%)、EV は 222,528 → 208,436百万、1株価値は全て +6.7%(Target 529 → 564円)。逆算DCFが要求する定常営業利益は約6%減る。結論(SELL、逆算の桁)は変わらない。 | F8: EDINET提出日時点 9,745,300株 | G8: 要確認
B9: 2026-08-29 | C9: DCF Model!C15(潜在株式) | D9: 新株予約権による潜在株式数 1,142,200株(発行済+潜在の合計10,887,500株の10.49%) | E9: FY2026/1有報の【事業等のリスク】に明記。2026/4/30時点。現行株数10,397,100が既に651,800株の行使後だとすれば残存は約490,400株(現行比 +4.7%)、完全希薄化後は10,887,500株。Segment Bridge シート Table 7 の希薄化計算はこの490,400株を使っている【推定】。C15 の1株価値は全て希薄化前(=楽観側)である点に注意。 | F9: - | G9: 推定・要確認
B10: 2026-08-29 | C10: DCF Model!C15(株式分割) | D10: 株式分割は発表済み・効力発生前。モデルは全て【分割前ベース】で統一 | E10: 株価21,620円・株数10,397,100株とも分割前。株式分割はバリュエーション中立であり、1株価値・Target・逆算の結論はいずれも分割比率で機械的に割り戻せる。効力発生後にモデルを更新する場合は current_price と shares_outstanding を同じ比率で同時に変更すること(片方だけ変えると時価総額が比率倍ずれる)。 | F10: - | G10: 設計判断
B11: 2026-08-29 | C11: DCF Model!C16 | D11: Net Debt = △2,257(ネットキャッシュ2,257) | E11: 内訳: 現金及び預金 2,258 − 長期借入 0.6(いずれも2026/4/30)。FY2026/1中に長期借入560.5を完済しており実質無借金。■リース債務の扱い【設計判断】: FY2026/1末のリース債務は流動75.8 + 固定141.9 = 217.8。EVに算入すると net_debt は △2,039 になるが、(a) 2026/4/30時点のリース残高が開示されておらず現金と基準日が揃わない、(b) 差額218はEV 222,528の0.1%で結論に影響しない、の2点からプロンプト定義(借入のみ)を採用した。非支配株主持分135もEVに算入していない(時価総額の0.06%)。 | F11: プロンプト指定と同一 | G11: 設計判断
B12: 2026-08-29 | C12: Financial Statements!E列 / Comps Analysis!C22 | D12: FY2026/1 の親会社株主に帰属する当期純損失 = △2,497.9(プロンプトの△2,327から変更) | E12: EDINET有報(S100XY8O)の ProfitLossAttributableToOwnersOfParent は △2,497,915千円。検算: 利益剰余金が △1,812,673千円(FY2025/1末) → △4,310,589千円(FY2026/1末)へ 2,497,916千円 減少しており(配当なし)、親会社帰属損失と完全に一致する。非支配株主帰属分は別途 △344,778千円で、両者合計の当期純損失は △2,842.7。プロンプトの△2,327 はいずれの開示値とも一致しないため採用しなかった。 | F12: プロンプト記載 △2,327 | G12: 確定(訂正)
B13: 2026-08-29 | C13: Financial Statements!C-E列(営業CF) | D13: 営業CF = △15.6(FY2024/1) / △927.9(FY2025/1) / △716.5(FY2026/1) | E13: プロンプトは FY2026/1 を △747・前期を『△904規模(要確認)』としているが、EDINET有報の NetCashProvidedByUsedInOperatingActivities は △716.459 / △927.897。有報値を採用した。投資CFも同様に FY2026/1 △1,717.9(プロンプト△1,707)。■年間の現金燃焼は 営業CF △716.5 + 投資CF △1,717.9 = △2,434(プロンプトの『年約2,454』とほぼ一致)。2026/4/30の現金2,258に対し、外部調達なしのランウェイは約11ヶ月。 | F13: プロンプト記載 △747 / △904規模 | G13: 確定(訂正)
B14: 2026-08-29 | C14: Financial Statements!C列(FY2024/1) | D14: FY2024/1 の純損失△353.9・営業CF△15.6・capex 249.9・D&A 156.8・現金5,008.7 をEDINETから補完 | E14: 2024/11上場のため EDINET上の有報は FY2025/1期(S100VOQD)と FY2026/1期(S100XY8O)の2期のみだが、FY2025/1有報の前期比較列から FY2024/1 の実績を取得できた。プロンプトの入力表では FY2024/1 の経常・純損益が未記載(ハイフン)だった。 | F14: 空欄 | G14: 確定
B15: 2026-08-29 | C15: Financial Statements!C-E列(有利子負債) | D15: hist_debt は【借入金のみ】: 965.1 / 570.5 / 0.0。FY2026/1のゼロは欠測ではなく実質無借金という事実 | E15: FY2024/1 短期11.4 + 長期953.7 = 965.1、FY2025/1 短期139.9 + 長期430.6 = 570.5、FY2026/1 は完済でゼロ(2026/4/30時点で長期0.6のみ)。net_debt の定義と揃えている。リース債務(FY2025/1 199.8、FY2026/1 217.8)は含めていない。■現金の2系列: BSの現金及び預金(本モデルが使用、FY2026/1 2,019.0)とCF計算書の現金及び現金同等物期末残高(1,802)は3ヶ月超の定期預金等の分だけ定義が異なる。 | F15: - | G15: 確定
... B43: 2026-08-29 | C43: 全シート | D43: 納品状態 = DRAFT | E43: 手順書v2 §6-3 / 標準メモ §2 に従い DRAFT 納品。チャット側での検証 → 手修正の記録 → ユーザー承認を経て FINAL 化する。■本モデルの弱点(Target への感応度が大きい順): (1) 防衛単価5.0百万円/台という全くの推定、(2) 予測8年という期間設定、(3) Exit倍率 EV/Sales 2.0x(PGM逆算0.45xと4.4倍乖離)、(4) 株数10,397,100(EDINET未確認、±6.7%)、(5) β1.55(回帰不能・ピアアンカー)、(6) 税率30.6%(繰越欠損金未織込)。■ただし本モデルの結論(現値は Base DCF の約40倍、逆算が要求する定常営業利益は約350億で FY2026/1 実績売上の7.3倍)は、これら全てを最も楽観的に振っても桁が変わらない。 | F43: - | G43: DRAFT
B45: Pipeline Metadata (do not edit — read by scripts/validate_output.py)
B46: key | C46: value
B47: auto_log_entries | C47: 0
B48: capex_pct_basis | C48: assumption
B49: capex_pct_c5 | C49: 0.075
B50: capex_pct_hist3yr | C50: 0.140515
B51: company_name | C51: Terra Drone
B52: comps_asof | C52: 2026-08-29
B53: comps_da_missing | C53: none
B54: comps_ev_ebitda_invalid | C54: no
B55: comps_ev_ebitda_rows | C55: 7,8
B56: comps_impl_mult_row | C56: 27
B57: comps_impl_per_row | C57: 28
... B79: ticker | C79: 278A

Sheet Segment Bridge
B2: Segment Bridge, Loss Normalisation, Defence Assumptions and Dilution - Terra Drone (278A)
B3: All figures JPY mn. Two reportable segments: Drone Solutions (survey and inspection services) and UTM (unmanned traffic management, built around the Unifly equity-method holding).
B4: The point of the first table: BOTH segments were loss-making and getting worse before the August 2026 defence contract. Drone Solutions went from a JPY194mn to a JPY435mn segment loss; UTM from JPY433mn to JPY709mn on almost flat revenue of about JPY620mn. UTM also carries a further JPY439mn of equity-method losses below the operating line, so it bleeds twice.
B5: Tables 5 to 7 hold the analysis the standard eight sheets have no place for: what the FY1/26 special losses do and do not change, the explicit unit-price x volume assumptions behind the defence revenue in the Base and Upside scenarios, and how much equity has to be issued to fund the plan.
B6: Tables 5 and 7 are live formulas off 'DCF Model' and follow the scenario selector in 'DCF Model'!C27. Table 6 is a set of blue input cells: they are estimates, not disclosure.
B8: 1. Segment Revenue (JPY mn)
B9: Segment | C9: FY2025/1 | D9: FY2026/1 | E9: Note
B10: Drone Solutions ドローンソリューション | C10: 3807 | D10: 4163 | E10: External sales. 87% of FY1/26 group revenue. Segment loss more than doubled on 9.3% revenue growth. Impairment of 405 was booked in this segment in FY1/26.
B11: UTM 運航管理 | C11: 628 | D11: 620 | E11: Revenue fell 1.3% while the segment loss grew 64%. Impairment of 188 in FY1/26. Equity-method losses (Unifly and related) of 439 in FY1/26 (152 in FY1/25) sit below the operating line and are NOT in this row.
B12: Segment total セグメント計 | C12: =SUM(C10:C11) -> 4435 | D12: =SUM(D10:D11) -> 4783
B13: Adjustment 調整額 (内部売上高消去等) | C13: =4435.6-C12 -> 0.6 | D13: =4782.6-D12 -> -0.4 | E13: Derived as (consolidated - segment total). Near zero because the segment rows are external-customer sales.
B14: Consolidated revenue 連結売上高 | C14: 4435.6 | D14: 4782.6 | E14: Ties to the Financial Statements sheet (FY2024/1, FY2025/1, FY2026/1 columns) and to EDINET.
B16: 2. Segment Profit to Consolidated Operating Profit (JPY mn)
B17: Segment | C17: FY2025/1 | D17: FY2026/1 | E17: Note
B18: Drone Solutions ドローンソリューション | C18: -194 | D18: -435
B19: UTM 運航管理 | C19: -433 | D19: -709
B20: Segment profit total セグメント利益計 | C20: =SUM(C18:C19) -> -627 | D20: =SUM(D18:D19) -> -1144
B21: Adjustment 調整額 (全社費用・消去) | C21: -0.2 | D21: 0.2
B22: Bridged total 計算値 | C22: =C20+C21 -> -627.2 | D22: =D20+D21 -> -1143.8
B23: Consolidated operating profit 連結営業利益 (開示値) | C23: -627.2 | D23: -1143.8 | E23: Disclosed consolidated operating loss (EDINET: -627.159 / -1,143.791).
B24: Variance 差異 (計算値 - 開示値) | C24: =C22-C23 -> 0 | D24: =D22-D23 -> 0 | E24: Rounding of the disclosed JPY mn figures. A non-zero variance is shown rather than forced to zero.
B26: 3. Segment Operating Margin
B27: Segment | C27: FY2025/1 | D27: FY2026/1 | E27: Note
B28: Drone Solutions ドローンソリューション | C28: =IFERROR(C18/C10,"N/A") -> -0.05095876 | D28: =IFERROR(D18/D10,"N/A") -> -0.10449195
B29: UTM 運航管理 | C29: =IFERROR(C19/C11,"N/A") -> -0.68949045 | D29: =IFERROR(D19/D11,"N/A") -> -1.1435484
B30: Consolidated 連結 | C30: =IFERROR(C23/C14,"N/A") -> -0.14140139 | D30: =IFERROR(D23/D14,"N/A") -> -0.23915862
B32: 4. Depreciation & Amortisation by Segment (JPY mn)
B33: Segment | C33: FY2025/1 | D33: FY2026/1 | E33: Note
B34: Drone Solutions ドローンソリューション | D34: 414
B35: UTM 運航管理 | D35: 113
B36: Segment D&A total 計 | D36: =SUM(D34:D35) -> 527
B37: Adjustment 調整額 (D&A) | D37: 0.3
B38: Bridged total 計算値 | D38: =D36+D37 -> 527.3
B39: Consolidated D&A 連結減価償却費 (開示値) | D39: 527.3 | E39: CF-statement D&A. FY2025/1 consolidated D&A was 330.1 but is NOT disclosed by segment, so that column is left blank rather than bridged against nothing (the FY2026/1 segment total 414+113=527 ties to 527.3).
B40: Variance 差異 (計算値 - 開示値) | D40: =D38-D39 -> 0 | E40: Rounding of the disclosed JPY mn figures. A non-zero variance is shown rather than forced to zero.
B41: Consolidated EBITDA (連結営業利益 + 連結D&A) | D41: =IFERROR(D23+D39,"N/A") -> -616.5 | E41: This is the core_ebitda basis used on 'Comps Analysis'.
B43: 5. FY2026/1 Special Losses - what normalisation does and does not change
B44: Item | C44: FY2026/1 | D44: Note
B45: Operating loss as reported 営業損失 | C45: -1143.8 | D45: This is the line the DCF forecasts. None of the items below sit above it.
B46: Impairment 減損損失 | C46: 593 | D46: Drone Solutions 405 + UTM 188. Special loss, below operating.
B47: Loss on valuation of investment securities 投資有価証券評価損 | C47: 259 | D47: Special loss.
B48: Fire loss 火災損失 | C48: 342 | D48: Special loss. A related provision of 177 sits in current liabilities at 2026/4/30.
B49: Loss on business transfer 事業譲渡関連損 | C49: 157 | D49: Special loss.
B50: Total special losses 特別損失計 | C50: 1351 | D50: Sum of the four rows above (the prompt quotes 1,361; the four disclosed components sum to 1,351).
B51: Equity-method investment loss 持分法投資損失 | C51: -439 | D51: Non-operating, recurring (FY1/25: -152). Attaches to the UTM segment.
B52: Government grant income 補助金収入 | C52: 255 | D52: Non-operating, recurring (FY1/25: 107; Q1 FY1/27: 44). Flatters recurring profit, not operating profit.
B53: Profit attributable to owners of parent 親会社株主に帰属する当期純損失 | C53: -2497.9 | D53: EDINET. Cross-check: retained earnings moved -1,812.7 to -4,310.6, a fall of 2,497.9, with no dividend.
B54: Operating loss after removing every one-off 正常化後の営業損失 | C54: -1143.8 | D54: UNCHANGED. Every special item is below the operating line, so there is no reading of FY1/26 in which the operating business breaks even.
B55: This table exists to close off the 'strip out the one-offs and it is profitable' reading. The special losses are real and large, but they are all below the operating line; the operating loss of 1,143.8 stands on its own. This is why the Comps sheet shows PER as N/A and why no normalised-net-income reference row was built.
B57: 6. Defence Programme Assumptions (estimates - the contract value is not disclosed)
B58: Assumption | C58: Base | D58: Upside | E58: Unit / basis
B59: Terra B1 unit price | C59: 5 | D59: 5 | E59: JPY mn per unit. ESTIMATE. The Acquisition, Technology & Logistics Agency contract value is undisclosed.
B60: Units delivered, FY2028/1 | C60: 200 | D60: 500 | E60: units
B61: Units delivered, FY2031/1 | C61: 900 | D61: 3300 | E61: units
B62: Units delivered, FY2034/1 | C62: 1260 | D62: 4500 | E62: units
B63: Defence revenue, FY2028/1 | C63: 1000 | D63: 2500 | E63: JPY mn = unit price x units
B64: Defence revenue, FY2031/1 | C64: 4500 | D64: 16500 | E64: JPY mn
B65: Defence revenue, FY2034/1 | C65: 6300 | D65: 22500 | E65: JPY mn
B66: Cumulative units, FY2027/1 to FY2034/1 | C66: 5760 | D66: 20200 | E66: units
B67: Implied share of the 80,000-unit programme concept (%) | C67: 7 | D67: 25 | E67: % (approx). Base = a niche supplier; Upside = a quarter of the whole programme.
B68: Every cell in this table is an estimate. The unit price of JPY5.0mn is the single most important unmodelled variable: at JPY2.0mn per unit the defence revenue in both scenarios falls to 40% of the amounts above, and the Upside case loses roughly half its terminal operating profit. Nothing here is company guidance.
B70: 7. Cash Runway, Funding Requirement and Dilution (live off the active scenario)
B71: Item | C71: JPY mn / price | D71: Shares | E71: % of current shares
B72: Cumulative negative unlevered FCF over FY2027/1-FY2034/1 | C72: =-SUMIF('DCF Model'!C45:J45,"<0") -> 6307.0999 | D72: - | E72: -
B73: Net cash at 2026-04-30 | C73: =-'DCF Model'!C16 -> 2257 | D73: - | E73: -
B74: Minimum operating cash buffer (assumption) | C74: 1000 | D74: - | E74: -
B75: External equity funding required | C75: =MAX(0,C72-C73+C74) -> 5050.0999 | D75: - | E75: -
B76: Issue price at 80% of the current price | C76: =ROUND(0.8*'Executive Summary'!C9,0) -> 17296 | D76: =IFERROR(ROUND(C75*1000000/C76,0),"n/a") -> 291981 | E76: =IFERROR(D76/'DCF Model'!C15,"n/a") -> 0.028082927
B77: Issue price at 80% of the Comps EV/Sales implied value | C77: =IF('Comps Analysis'!C27<=0,"n/a",ROUND(0.8*'Comps Analysis'!C27,0)) -> 4580 | D77: =IFERROR(ROUND(C75*1000000/C77,0),"n/a") -> 1102642 | E77: =IFERROR(D77/'DCF Model'!C15,"n/a") -> 0.10605284
B78: Issue price at 80% of the DCF Exit-multiple implied value | C78: =IF('DCF Model'!C64<=0,"n/a",ROUND(0.8*'DCF Model'!C64,0)) -> 799 | D78: =IFERROR(ROUND(C75*1000000/C78,0),"n/a") -> 6320525 | E78: =IFERROR(D78/'DCF Model'!C15,"n/a") -> 0.6079123
B79: Funding required as a multiple of the DCF Exit equity value | C79: =IFERROR(ROUND(C75/'DCF Model'!C63,2),"n/a") -> 0.49 | D79: - | E79: -
B80: Outstanding stock-option shares not yet exercised | C80: - | D80: 490400 | E80: =D80/'DCF Model'!C15 -> 0.047166998
B81: Fully diluted shares if funded at 80% of the current price | C81: - | D81: =IFERROR('DCF Model'!C15+D76+D80,"n/a") -> 11179481 | E81: =IFERROR(D81/'DCF Model'!C15-1,"n/a") -> 0.075249925
B82: Fully diluted shares if funded at 80% of the DCF Exit value | C82: - | D82: =IFERROR('DCF Model'!C15+D78+D80,"n/a") -> 17208025 | E82: =IFERROR(D82/'DCF Model'!C15-1,"n/a") -> 0.6550793
B83: Equity value per share, PGM leg, pre-dilution | C83: ='DCF Model'!C55 -> 59 | D83: - | E83: -
B84: Equity value per share, PGM leg, after dilution at 80% of the DCF Exit value | C84: =IFERROR(ROUND('DCF Model'!C54*1000000/D82,0),"n/a") -> 36 | D84: - | E84: -
B85: Equity value per share, Exit leg, pre-dilution | C85: ='DCF Model'!C64 -> 999 | D85: - | E85: -
B86: Equity value per share, Exit leg, after dilution at 80% of the DCF Exit value | C86: =IFERROR(ROUND('DCF Model'!C63*1000000/D82,0),"n/a") -> 604 | D86: - | E86: -
B87: The asymmetry is the finding. At today's price the whole Base plan is funded for about 3% dilution - the theme price itself solves the funding problem. If the theme deflates towards the DCF or Comps values, the SAME cash requirement costs 40-60% of the company. Dilution risk here is a function of the share price, and it bites hardest exactly when the equity story has already failed. Switch 'DCF Model'!C27 to Downside 1 and the 'funding required as a multiple of the DCF Exit equity value' row goes above 10x: the plan is not financeable at that valuation at all, which is itself the answer. Read that ratio by scenario: Upside 0.11x, Management 0.31x, Base 0.49x, Downside 1 10.25x (not financeable), Downside 2 negative (there is no positive modelled equity value to fund against). Rows that would divide by a zero or negative modelled value show n/a rather than a spurious number. Every per-share figure on 'Executive Summary' and 'DCF Model' is PRE-dilution and therefore flattering.
B89: Notes
B90: Segment profit is the disclosed segment operating profit; the adjustment row carries corporate costs and eliminations and is close to zero in both years, so the bridge closes cleanly.
B91: Segment operating margin: Drone Solutions -5.1% (FY1/25) -> -10.4% (FY1/26); UTM -69.0% -> -114.4%. Consolidated -14.1% -> -23.9%.
B92: Segment D&A is only disclosed for FY1/26, so the D&A bridge has one usable column. The FY1/26 segment total (414 + 113 = 527) ties to consolidated D&A of 527.3.
B93: Consolidated EBITDA is negative in both years (-297.1 and -616.5). This is why the model uses EV/Sales rather than EV/EBITDA as the primary multiple.
B94: No segment data has been published for FY1/27 Q1 or for the defence contract. The mid-September 2026 second-quarter results are the first chance to see whether defence revenue lands in Drone Solutions or in a new segment, and at what margin.
B95: This sheet is informational except where noted: tables 5 and 7 contain live references INTO 'DCF Model' and 'Comps Analysis', but no cell on 'DCF Model' references this sheet.
