Workbook

Sheet Executive Summary
B1: DISCLAIMER: This is a sample analysis for demonstration purposes only. It does not constitute investment advice.
B3: SANNO (3441.T)
B4: Equity Research Report
B6: Company | C6: SANNO
B7: Ticker | C7: 3441.T (TSE Standard)
B8: Sector | C8: Precious-metal Surface Treatment / Plating
B9: Current Price | C9: 2764
B10: Target Price (DCF Mid) | C10: =IF(COUNT(C16:C17)=0,"N/A",ROUND(AVERAGE(C16:C17),0)) -> 3007
B11: Recommendation | C11: =IF(NOT(ISNUMBER(C12)),"N/A",IF(C12>0.15,"BUY",IF(C12>0.05,"HOLD","SELL"))) -> HOLD
B12: Upside / Downside | C12: =IF(ISNUMBER(C10),(C10-C9)/C9,"N/A") -> 0.087916064
B14: Valuation Summary
B15: Methodology | C15: Implied Value (JPY) | D15: vs Current Price
B16: DCF - Perpetuity Growth | C16: =IF('DCF Model'!C53<'DCF Model'!C16,"INVALID (EV < net debt)",'DCF Model'!C55) -> 2898 | D16: =IF(ISNUMBER(C16),(C16-C9)/C9,"N/A") -> 0.048480463
B17: DCF - Exit Multiple | C17: =IF('DCF Model'!C62<'DCF Model'!C16,"INVALID (EV < net debt)",'DCF Model'!C64) -> 3115 | D17: =IF(ISNUMBER(C17),(C17-C9)/C9,"N/A") -> 0.12698987
B18: Comps - EV/EBITDA Median [参考・Target不算入] | C18: ='Comps Analysis'!C27 -> 3141 | D18: =IF(ISNUMBER(C18),(C18-C9)/C9,"N/A") -> 0.13639653
B19: Comps - PER Median [参考・Target不算入] | C19: ='Comps Analysis'!C28 -> 6585 | D19: =IF(ISNUMBER(C19),(C19-C9)/C9,"N/A") -> 1.3824168
B20: Note: Target Mid は DCF 2法（PGM / Exit）の平均のみ。Comps 2法は [参考] で Target 不算入（EV<ネットデットで株式価値が負になる手法は INVALID として平均から除外）
B21: DCF Valuation Range (PGM - Exit) | C21: =IF(COUNT(C16:C17)=0,"N/A",MIN(C16:C17)&" - "&MAX(C16:C17)) -> 2898 - 3115
B23: Key Investment Thesis
B24: Gross margin has stepped up four reporting periods running - 17.5% (FY7/23), 16.4% (FY7/24), 20.3% (FY7/25), 24.2% (9M FY7/26) - and the FY7/25 step was earned in Japan, not in the Philippines: the domestic segment swung from a JPY188mn operating loss to a JPY509mn profit while the Philippine unit's profit fell from JPY348mn to JPY243mn.
B25: Nine-month operating profit of JPY1,582mn already exceeds the unrevised full-year company guidance of JPY1,400mn by 13%, so the mid-September FY7/26 results and the first FY7/27 guidance are a near-term catalyst rather than a distant one.
B26: ="At "&TEXT(C9,"#,##0")&" the reverse DCF says the market is paying for only about 84% of the annualised nine-month operating profit continuing for ever; our target of "&TEXT(C10,"#,##0")&" implies "&TEXT(C12,"+0.0%;-0.0%")&" at a WACC of "&TEXT('DCF Model'!C26,"0.00%")&", and the shares trade at "&TEXT('Comps Analysis'!M5,"0.00""x""")&" PBR." -> At 2,764 the reverse DCF says the market is paying for only about 84% of the annualised nine-month operating profit continuing for ever; our target of 3,007 implies +8.8% at a WACC of 12.19%, and the shares trade at 1.42x PBR.
B28: Key Risks
B29: The margin step may be a precious-metal spread rather than a structural gain: gold and silver pass through both revenue and cost, and the standalone third quarter already shows gross margin falling back from 25.7% in the first half to 21.9%, so a metal-price reversal would remove most of the incremental profit.
B30: Raw-material inventory rose 44% to JPY3,045mn and days inventory held went from 98 to 115, so growth consumes cash before it converts - operating cash flow was JPY462mn against JPY766mn of net profit in FY7/25, and was negative JPY222mn in the first half of FY7/26.
B31: The 8.1% effective tax rate booked in the nine months reflects Philippine incentives and deferred-tax recognition and is not sustainable; this model taxes at 25%, and the statutory 30.6% would cut the DCF value by roughly 7-8%.

Sheet Financial Statements
B2: SANNO - Historical Financials (JPY mn)
C4: FY2023/7 | D4: FY2024/7 | E4: FY2025/7 | F4: FY2026/7E
B5: Income Statement
B6: Revenue | C6: 9563.5 | D6: 8802.1 | E6: 10830.4 | F6: 14365
B7: COGS | C7: 7887.9 | D7: 7359.7 | E7: 8635.6 | F7: 10960.3
B8: Gross Profit | C8: =C6-C7 -> 1675.6 | D8: =D6-D7 -> 1442.4 | E8: =E6-E7 -> 2194.8 | F8: =F6-F7 -> 3404.7
B9: Gross Margin | C9: =C8/C6 -> 0.17520782 | D9: =D8/D6 -> 0.16386999 | E9: =E8/E6 -> 0.20265179 | F9: =F8/F6 -> 0.23701357
B10: SGA | C10: 1469.9 | D10: 1209.4 | E10: 1398.5 | F10: 1461.3
B11: Operating Income | C11: 205.6 | D11: 233 | E11: 796.2 | F11: 1943.4
B12: Net Income | C12: 154.1 | D12: 312.7 | E12: 765.7 | F12: 1750
B13: Operating Margin | C13: =C11/C6 -> 0.021498405 | D13: =D11/D6 -> 0.026470956 | E13: =E11/E6 -> 0.07351529 | F13: =F11/F6 -> 0.13528716
B14: Net Margin | C14: =C12/C6 -> 0.016113348 | D14: =D12/D6 -> 0.035525613 | E14: =E12/E6 -> 0.070699143 | F14: =F12/F6 -> 0.12182388
B15: Revenue Growth (YoY) | C15: n/a | D15: =(D6-C6)/C6 -> -0.079615204 | E15: =(E6-D6)/D6 -> 0.23043365 | F15: =(F6-E6)/E6 -> 0.32635914
B16: Operating Income Growth (YoY) | C16: n/a | D16: =(D11-C11)/C11 -> 0.13326848 | E16: =(E11-D11)/D11 -> 2.4171674 | F16: =(F11-E11)/E11 -> 1.440844
B18: Cash Flow Statement
B19: Operating Cash Flow | C19: 1185.9 | D19: 1054.8 | E19: 461.7 | F19: 940
B20: Capex | C20: 954.6 | D20: 239.3 | E20: 580 | F20: 760
B21: Free Cash Flow | C21: =C19-C20 -> 231.3 | D21: =D19-D20 -> 815.5 | E21: =E19-E20 -> -118.3 | F21: =F19-F20 -> 180
B22: FCF Margin | C22: =C21/C6 -> 0.024185706 | D22: =D21/D6 -> 0.092648345 | E22: =E21/E6 -> -0.010922958 | F22: =F21/F6 -> 0.012530456
B23: Capex / Revenue | C23: =C20/C6 -> 0.099817013 | D23: =D20/D6 -> 0.027186694 | E23: =E20/E6 -> 0.053552962 | F23: =F20/F6 -> 0.05290637
B25: Balance Sheet Highlights
B26: Cash & Deposits | C26: 2203.2 | D26: 3901.1 | E26: 3610.8 | F26: 3575
B27: Total Interest-bearing Debt (short + long) | C27: 4554.7 | D27: 4256 | E27: 4478.5 | F27: 4699
B28: Net Debt (Cash) | C28: =C27-C26 -> 2351.5 | D28: =D27-D26 -> 354.9 | E28: =E27-E26 -> 867.7 | F28: =F27-F26 -> 1124
B30: Note: OCF / Cash / Debt coverage OCF 4/4, Cash 4/4, Debt 4/4 — blank cells are years with no year-key match in the source data (verify against 決算短信 or set hist_ocf / hist_cash / hist_debt in overrides).

Sheet DCF Model
B2: DCF Valuation Model - SANNO
B4: Assumptions
B5: Capex / Revenue (hist 3yr avg, fallback) | C5: 0.0445
B6: Effective Tax Rate | C6: 0.25
B7: Risk-Free Rate | C7: 0.0289
B8: Beta | C8: 0.98
B9: Equity Risk Premium | C9: 0.065
B10: Size Premium | C10: 0.04
B11: After-tax Cost of Debt | C11: 0.01
B12: D/E Ratio | C12: 0.0959
B13: Terminal Growth Rate | C13: 0.01
B14: Exit Multiple (EV/EBITDA) | C14: 5.5
B15: Fully Diluted Shares | C15: 4241897
B16: Net Debt (JPY mn) | C16: 1124
... B20: LTM Revenue (JPY mn) (override) | C20: 14120
B22: WACC Calculation
B23: Cost of Equity (Ke) | C23: =C7+C8*C9+C10 -> 0.1326
B24: Weight of Equity | C24: =1/(1+C12) -> 0.91249202
B25: Weight of Debt | C25: =C12/(1+C12) -> 0.087507984
B26: WACC | C26: =C23*C24+C11*C25 -> 0.12187152
B27: Active Scenario | C27: Base | D27: =MATCH(C27,B69:B73,0) -> 1
B28: Projected Free Cash Flow
C29: FY2027(E) | D29: FY2028(E) | E29: FY2029(E) | F29: FY2030(E) | G29: FY2031(E)
B30: Revenue Growth (YoY) | C30: =CHOOSE($D$27,C69,C70,C71,C72,C73) -> 0.08 | D30: =CHOOSE($D$27,D69,D70,D71,D72,D73) -> 0.06 | E30: =CHOOSE($D$27,E69,E70,E71,E72,E73) -> 0.05 | F30: =CHOOSE($D$27,F69,F70,F71,F72,F73) -> 0.04 | G30: =CHOOSE($D$27,G69,G70,G71,G72,G73) -> 0.03
B31: COGS % of Revenue | C31: =CHOOSE($D$27,C76,C77,C78,C79,C80) -> 0.77 | D31: =CHOOSE($D$27,D76,D77,D78,D79,D80) -> 0.775 | E31: =CHOOSE($D$27,E76,E77,E78,E79,E80) -> 0.775 | F31: =CHOOSE($D$27,F76,F77,F78,F79,F80) -> 0.775 | G31: =CHOOSE($D$27,G76,G77,G78,G79,G80) -> 0.775
B32: SGA % of Revenue | C32: =CHOOSE($D$27,C83,C84,C85,C86,C87) -> 0.097 | D32: =CHOOSE($D$27,D83,D84,D85,D86,D87) -> 0.0943 | E32: =CHOOSE($D$27,E83,E84,E85,E86,E87) -> 0.0925 | F32: =CHOOSE($D$27,F83,F84,F85,F86,F87) -> 0.0916 | G32: =CHOOSE($D$27,G83,G84,G85,G86,G87) -> 0.0916
B33: Revenue | C33: =C17*(1+C30) -> 15514.2 | D33: =C33*(1+D30) -> 16445.052 | E33: =D33*(1+E30) -> 17267.305 | F33: =E33*(1+F30) -> 17957.997 | G33: =F33*(1+G30) -> 18496.737
B34: COGS | C34: =C33*C31 -> 11945.934 | D34: =D33*D31 -> 12744.915 | E34: =E33*E31 -> 13382.161 | F34: =F33*F31 -> 13917.448 | G34: =G33*G31 -> 14334.971
B35: Gross Profit | C35: =C33-C34 -> 3568.266 | D35: =D33-D34 -> 3700.1367 | E35: =E33-E34 -> 3885.1435 | F35: =F33-F34 -> 4040.5493 | G35: =G33-G34 -> 4161.7658
B36: Gross Margin | C36: =C35/C33 -> 0.23 | D36: =D35/D33 -> 0.225 | E36: =E35/E33 -> 0.225 | F36: =F35/F33 -> 0.225 | G36: =G35/G33 -> 0.225
B37: SGA Expense | C37: =C33*C32 -> 1504.8774 | D37: =D33*D32 -> 1550.7684 | E37: =E33*E32 -> 1597.2257 | F37: =F33*F32 -> 1644.9525 | G37: =G33*G32 -> 1694.3011
B38: Implied Operating Margin | C38: =(C35-C37)/C33 -> 0.133 | D38: =(D35-D37)/D33 -> 0.1307 | E38: =(E35-E37)/E33 -> 0.1325 | F38: =(F35-F37)/F33 -> 0.1334 | G38: =(G35-G37)/G33 -> 0.1334
B39: Operating Income (EBIT) | C39: =C35-C37 -> 2063.3886 | D39: =D35-D37 -> 2149.3683 | E39: =E35-E37 -> 2287.9179 | F39: =F35-F37 -> 2395.5968 | G39: =G35-G37 -> 2467.4647
B40: Less: Tax | C40: =MAX(0,C39*C6) -> 515.84715 | D40: =MAX(0,D39*C6) -> 537.34207 | E40: =MAX(0,E39*C6) -> 571.97946 | F40: =MAX(0,F39*C6) -> 598.89919 | G40: =MAX(0,G39*C6) -> 616.86617
B41: NOPAT | C41: =C39-C40 -> 1547.5414 | D41: =D39-D40 -> 1612.0262 | E41: =E39-E40 -> 1715.9384 | F41: =F39-F40 -> 1796.6976 | G41: =G39-G40 -> 1850.5985
B42: Plus: D&A | C42: 520 | D42: 550 | E42: 580 | F42: 600 | G42: 615
B43: Less: Capex | C43: 720 | D43: 700 | E43: 680 | F43: 660 | G43: 640
B44: Change in NWC | C44: ='NWC Schedule'!D19 -> 416.77497 | D44: ='NWC Schedule'!E19 -> 321.37772 | E44: ='NWC Schedule'!F19 -> 203.42304 | F44: ='NWC Schedule'!G19 -> 191.12304 | G44: ='NWC Schedule'!H19 -> 127.72318
B45: Unlevered Free Cash Flow | C45: =C41+C42-C43-C44 -> 930.76648 | D45: =D41+D42-D43-D44 -> 1140.6485 | E45: =E41+E42-E43-E44 -> 1412.5154 | F45: =F41+F42-F43-F44 -> 1545.5745 | G45: =G41+G42-G43-G44 -> 1697.8753
B46: Discount Factor | C46: =1/(1+C26)^(C19+0) -> 0.89960596 | D46: =1/(1+C26)^(C19+1) -> 0.80187967 | E46: =1/(1+C26)^(C19+2) -> 0.71476961 | F46: =1/(1+C26)^(C19+3) -> 0.63712252 | G46: =1/(1+C26)^(C19+4) -> 0.56791041
B47: PV of FCF | C47: =C45*C46 -> 837.32308 | D47: =D45*D46 -> 914.66285 | E47: =E45*E46 -> 1009.623 | F47: =F45*F46 -> 984.72034 | G47: =G45*G46 -> 964.24108
B49: Valuation - Perpetuity Growth Method
B50: Sum of PV of FCFs | C50: =SUM(C47:G47) -> 4710.5704
B51: Terminal Value (PGM) | C51: =G45*(1+C13)/(C26-C13) -> 15328.781
B52: PV of Terminal Value | C52: =C51*G46 -> 8705.3745
B53: Enterprise Value | C53: =C50+C52 -> 13415.945
B54: Equity Value | C54: =C53-C16 -> 12291.945
B55: Implied Share Price (PGM) | C55: =ROUND(C54*1000000/C15,0) -> 2898
B57: Valuation - Exit Multiple Method
B58: Sum of PV of FCFs | C58: =C50 -> 4710.5704
B59: Year 5 EBITDA | C59: =G39+G42 -> 3082.4647
B60: Terminal Value (Exit Multiple) | C60: =C59*C14 -> 16953.556
B61: PV of Terminal Value | C61: =C60*G46 -> 9628.1008
B62: Enterprise Value | C62: =C58+C61 -> 14338.671
B63: Equity Value | C63: =C62-C16 -> 13214.671
B64: Implied Share Price (Exit Multiple) | C64: =ROUND(C63*1000000/C15,0) -> 3115
B66: Scenario Input Matrix
C67: Year 1 | D67: Year 2 | E67: Year 3 | F67: Year 4 | G67: Year 5
B68: Revenue Growth (YoY)
B69: Base | C69: 0.08 | D69: 0.06 | E69: 0.05 | F69: 0.04 | G69: 0.03
B70: Upside | C70: 0.15 | D70: 0.12 | E70: 0.1 | F70: 0.08 | G70: 0.06
B71: Management | C71: 0.12 | D71: 0.08 | E71: 0.06 | F71: 0.05 | G71: 0.04
B72: Downside 1 | C72: 0.02 | D72: 0.01 | E72: 0.01 | F72: 0.01 | G72: 0.01
B73: Downside 2 | C73: -0.12 | D73: -0.06 | E73: 0 | F73: 0.02 | G73: 0.02
B75: COGS % of Revenue
B76: Base | C76: 0.77 | D76: 0.775 | E76: 0.775 | F76: 0.775 | G76: 0.775
B77: Upside | C77: 0.75 | D77: 0.745 | E77: 0.745 | F77: 0.745 | G77: 0.745
B78: Management | C78: 0.76 | D78: 0.76 | E78: 0.76 | F78: 0.76 | G78: 0.76
B79: Downside 1 | C79: 0.79 | D79: 0.797 | E79: 0.8 | F79: 0.8 | G79: 0.8
B80: Downside 2 | C80: 0.81 | D80: 0.825 | E80: 0.83 | F80: 0.825 | G80: 0.82
B82: SGA % of Revenue
B83: Base | C83: 0.097 | D83: 0.0943 | E83: 0.0925 | F83: 0.0916 | G83: 0.0916
B84: Upside | C84: 0.0929 | D84: 0.0871 | E84: 0.0831 | F84: 0.0808 | G84: 0.08
B85: Management | C85: 0.0945 | D85: 0.091 | E85: 0.0892 | F85: 0.0884 | G85: 0.0884
B86: Downside 1 | C86: 0.1012 | D86: 0.1017 | E86: 0.1022 | F86: 0.1027 | G86: 0.1032
B87: Downside 2 | C87: 0.1133 | D87: 0.1181 | E87: 0.1157 | F87: 0.1112 | G87: 0.1068

Sheet Reverse DCF
B2: Reverse DCF - SANNO (3441.T)
B3: What is the current share price already assuming? Every value below is a live formula off the other sheets.
B5: Block 0: Market-implied enterprise value (live)
B6: Current Share Price (JPY) | C6: ='Executive Summary'!C9 -> 2764
B7: Fully Diluted Shares | C7: ='DCF Model'!C15 -> 4241897
B8: Market Capitalisation (JPY mn) | C8: =C6*C7/1000000 -> 11724.603
B9: Net Debt (JPY mn) | C9: ='DCF Model'!C16 -> 1124
B10: Enterprise Value (JPY mn) | C10: =C8+C9 -> 12848.603
B11: WACC (w) | C11: ='DCF Model'!C26 -> 0.12187152
B12: Terminal Growth (g) | C12: ='DCF Model'!C13 -> 0.01
B13: Effective Tax Rate (t) | C13: ='DCF Model'!C6 -> 0.25
B14: Starting Operating Profit OP0 (FY2026/7E actual) | C14: 1943
B15: Cycle-peak Operating Profit (Q3 FY2026/7 annualised actual) | C15: 2109
B16: Terminal-year Revenue, active scenario (JPY mn) | C16: ='DCF Model'!G33 -> 18496.737
B17: Base-case DCF Enterprise Value, PGM (JPY mn) | C17: ='DCF Model'!C53 -> 13415.945
B18: Cycle-peak Operating Margin (Q3 FY2026/7 annualised actual) | C18: 0.1431
B19: Gap: market EV less base-case DCF EV (JPY mn) | C19: =C10-C17 -> -567.34162
B20: Gap per share (JPY) - the part of the price the base case does not explain | C20: =IFERROR(ROUND(C19*1000000/C7,0),"N/A") -> -134
B22: Block A: Required steady-state operating profit, reached IMMEDIATELY (no ramp)
B23: The lowest bar the price can clear: today's EV read as a perpetuity of one steady-state profit, capex = D&A, no NWC build.
B24: Required steady-state NOPAT (JPY mn) | C24: =C10*(C11-C12) -> 1437.3928
B25: Required steady-state Operating Profit (JPY mn) | C25: =IFERROR(C24/(1-C13),"N/A") -> 1916.5237
B26: ... as a multiple of the Q3 FY2026/7 annualised peak | C26: =IFERROR(C25/C15,"N/A") -> 0.90873577
B27: ... as a multiple of FY2026/7E actual | C27: =IFERROR(C25/C14,"N/A") -> 0.98637351
B28: ... implied OPM on terminal-year revenue | C28: =IFERROR(C25/C16,"N/A") -> 0.10361415
B29: ... revenue needed if margins only reach the cycle peak | C29: =IFERROR(C25/C18,"N/A") -> 13392.898
B32: Block B: Required steady-state operating profit by YEARS-TO-REACH (linear ramp) x WACC
B33: Operating profit ramps linearly from OP0 (C14) to OP* over N years, then grows at g for ever. Column F is the model WACC.
B34: OP* = ( EV/(1-t) - OP0*(A-B) ) / ( B + TVF ). A longer ramp needs a HIGHER steady state, because more years are spent below it.
B36: Years to steady state (N) \ WACC | C36: N | D36: ='DCF Model'!C26-0.02 -> 0.10187152 | E36: ='DCF Model'!C26-0.01 -> 0.11187152 | F36: ='DCF Model'!C26 -> 0.12187152 | G36: ='DCF Model'!C26+0.01 -> 0.13187152 | H36: ='DCF Model'!C26+0.02 -> 0.14187152
B37: B-1 PV weight on the RAMP from OP0 (A - B)
B38: N = 3 years | C38: 3 | D38: =IFERROR((1-(1+D$36)^(-$C38))/D$36-(1+D$36)/(D$36^2*$C38)*(1-($C38+1)/(1+D$36)^$C38+$C38/(1+D$36)^($C38+1)),"N/A") -> 0.8795783 | E38: =IFERROR((1-(1+E$36)^(-$C38))/E$36-(1+E$36)/(E$36^2*$C38)*(1-($C38+1)/(1+E$36)^$C38+$C38/(1+E$36)^($C38+1)),"N/A") -> 0.86922048 | F38: =IFERROR((1-(1+F$36)^(-$C38))/F$36-(1+F$36)/(F$36^2*$C38)*(1-($C38+1)/(1+F$36)^$C38+$C38/(1+F$36)^($C38+1)),"N/A") -> 0.85909055 | G38: =IFERROR((1-(1+G$36)^(-$C38))/G$36-(1+G$36)/(G$36^2*$C38)*(1-($C38+1)/(1+G$36)^$C38+$C38/(1+G$36)^($C38+1)),"N/A") -> 0.84918133 | H38: =IFERROR((1-(1+H$36)^(-$C38))/H$36-(1+H$36)/(H$36^2*$C38)*(1-($C38+1)/(1+H$36)^$C38+$C38/(1+H$36)^($C38+1)),"N/A") -> 0.83948594
B39: N = 5 years | C39: 5 | D39: =IFERROR((1-(1+D$36)^(-$C39))/D$36-(1+D$36)/(D$36^2*$C39)*(1-($C39+1)/(1+D$36)^$C39+$C39/(1+D$36)^($C39+1)),"N/A") -> 1.6548964 | E39: =IFERROR((1-(1+E$36)^(-$C39))/E$36-(1+E$36)/(E$36^2*$C39)*(1-($C39+1)/(1+E$36)^$C39+$C39/(1+E$36)^($C39+1)),"N/A") -> 1.6267066 | F39: =IFERROR((1-(1+F$36)^(-$C39))/F$36-(1+F$36)/(F$36^2*$C39)*(1-($C39+1)/(1+F$36)^$C39+$C39/(1+F$36)^($C39+1)),"N/A") -> 1.5993631 | G39: =IFERROR((1-(1+G$36)^(-$C39))/G$36-(1+G$36)/(G$36^2*$C39)*(1-($C39+1)/(1+G$36)^$C39+$C39/(1+G$36)^($C39+1)),"N/A") -> 1.5728311 | H39: =IFERROR((1-(1+H$36)^(-$C39))/H$36-(1+H$36)/(H$36^2*$C39)*(1-($C39+1)/(1+H$36)^$C39+$C39/(1+H$36)^($C39+1)),"N/A") -> 1.5470775
B40: N = 7 years | C40: 7 | D40: =IFERROR((1-(1+D$36)^(-$C40))/D$36-(1+D$36)/(D$36^2*$C40)*(1-($C40+1)/(1+D$36)^$C40+$C40/(1+D$36)^($C40+1)),"N/A") -> 2.3398131 | E40: =IFERROR((1-(1+E$36)^(-$C40))/E$36-(1+E$36)/(E$36^2*$C40)*(1-($C40+1)/(1+E$36)^$C40+$C40/(1+E$36)^($C40+1)),"N/A") -> 2.2885604 | F40: =IFERROR((1-(1+F$36)^(-$C40))/F$36-(1+F$36)/(F$36^2*$C40)*(1-($C40+1)/(1+F$36)^$C40+$C40/(1+F$36)^($C40+1)),"N/A") -> 2.2392354 | G40: =IFERROR((1-(1+G$36)^(-$C40))/G$36-(1+G$36)/(G$36^2*$C40)*(1-($C40+1)/(1+G$36)^$C40+$C40/(1+G$36)^($C40+1)),"N/A") -> 2.191741 | H40: =IFERROR((1-(1+H$36)^(-$C40))/H$36-(1+H$36)/(H$36^2*$C40)*(1-($C40+1)/(1+H$36)^$C40+$C40/(1+H$36)^($C40+1)),"N/A") -> 2.1459861
B41: N = 10 years | C41: 10 | D41: =IFERROR((1-(1+D$36)^(-$C41))/D$36-(1+D$36)/(D$36^2*$C41)*(1-($C41+1)/(1+D$36)^$C41+$C41/(1+D$36)^($C41+1)),"N/A") -> 3.2232459 | E41: =IFERROR((1-(1+E$36)^(-$C41))/E$36-(1+E$36)/(E$36^2*$C41)*(1-($C41+1)/(1+E$36)^$C41+$C41/(1+E$36)^($C41+1)),"N/A") -> 3.1312717 | F41: =IFERROR((1-(1+F$36)^(-$C41))/F$36-(1+F$36)/(F$36^2*$C41)*(1-($C41+1)/(1+F$36)^$C41+$C41/(1+F$36)^($C41+1)),"N/A") -> 3.0437329 | G41: =IFERROR((1-(1+G$36)^(-$C41))/G$36-(1+G$36)/(G$36^2*$C41)*(1-($C41+1)/(1+G$36)^$C41+$C41/(1+G$36)^($C41+1)),"N/A") -> 2.9603479 | H41: =IFERROR((1-(1+H$36)^(-$C41))/H$36-(1+H$36)/(H$36^2*$C41)*(1-($C41+1)/(1+H$36)^$C41+$C41/(1+H$36)^($C41+1)),"N/A") -> 2.8808565
B42: B-2 PV weight on the STEADY STATE OP* (B + terminal factor)
B43: N = 3 years | C43: 3 | D43: =IFERROR((1+D$36)/(D$36^2*$C43)*(1-($C43+1)/(1+D$36)^$C43+$C43/(1+D$36)^($C43+1))+(1+$C$12)/((D$36-$C$12)*(1+D$36)^$C43),"N/A") -> 9.8167518 | E43: =IFERROR((1+E$36)/(E$36^2*$C43)*(1-($C43+1)/(1+E$36)^$C43+$C43/(1+E$36)^($C43+1))+(1+$C$12)/((E$36-$C$12)*(1+E$36)^$C43),"N/A") -> 8.7793763 | F43: =IFERROR((1+F$36)/(F$36^2*$C43)*(1-($C43+1)/(1+F$36)^$C43+$C43/(1+F$36)^($C43+1))+(1+$C$12)/((F$36-$C$12)*(1+F$36)^$C43),"N/A") -> 7.9290349 | G43: =IFERROR((1+G$36)/(G$36^2*$C43)*(1-($C43+1)/(1+G$36)^$C43+$C43/(1+G$36)^($C43+1))+(1+$C$12)/((G$36-$C$12)*(1+G$36)^$C43),"N/A") -> 7.2196396 | H43: =IFERROR((1+H$36)/(H$36^2*$C43)*(1-($C43+1)/(1+H$36)^$C43+$C43/(1+H$36)^($C43+1))+(1+$C$12)/((H$36-$C$12)*(1+H$36)^$C43),"N/A") -> 6.6190841
B44: N = 5 years | C44: 5 | D44: =IFERROR((1+D$36)/(D$36^2*$C44)*(1-($C44+1)/(1+D$36)^$C44+$C44/(1+D$36)^($C44+1))+(1+$C$12)/((D$36-$C$12)*(1+D$36)^$C44),"N/A") -> 8.8862303 | E44: =IFERROR((1+E$36)/(E$36^2*$C44)*(1-($C44+1)/(1+E$36)^$C44+$C44/(1+E$36)^($C44+1))+(1+$C$12)/((E$36-$C$12)*(1+E$36)^$C44),"N/A") -> 7.8862475 | F44: =IFERROR((1+F$36)/(F$36^2*$C44)*(1-($C44+1)/(1+F$36)^$C44+$C44/(1+F$36)^($C44+1))+(1+$C$12)/((F$36-$C$12)*(1+F$36)^$C44),"N/A") -> 7.0690257 | G44: =IFERROR((1+G$36)/(G$36^2*$C44)*(1-($C44+1)/(1+G$36)^$C44+$C44/(1+G$36)^($C44+1))+(1+$C$12)/((G$36-$C$12)*(1+G$36)^$C44),"N/A") -> 6.3894112 | H44: =IFERROR((1+H$36)/(H$36^2*$C44)*(1-($C44+1)/(1+H$36)^$C44+$C44/(1+H$36)^($C44+1))+(1+$C$12)/((H$36-$C$12)*(1+H$36)^$C44),"N/A") -> 5.8159552
B45: N = 7 years | C45: 7 | D45: =IFERROR((1+D$36)/(D$36^2*$C45)*(1-($C45+1)/(1+D$36)^$C45+$C45/(1+D$36)^($C45+1))+(1+$C$12)/((D$36-$C$12)*(1+D$36)^$C45),"N/A") -> 8.0734816 | E45: =IFERROR((1+E$36)/(E$36^2*$C45)*(1-($C45+1)/(1+E$36)^$C45+$C45/(1+E$36)^($C45+1))+(1+$C$12)/((E$36-$C$12)*(1+E$36)^$C45),"N/A") -> 7.1146734 | F45: =IFERROR((1+F$36)/(F$36^2*$C45)*(1-($C45+1)/(1+F$36)^$C45+$C45/(1+F$36)^($C45+1))+(1+$C$12)/((F$36-$C$12)*(1+F$36)^$C45),"N/A") -> 6.3340183 | G45: =IFERROR((1+G$36)/(G$36^2*$C45)*(1-($C45+1)/(1+G$36)^$C45+$C45/(1+G$36)^($C45+1))+(1+$C$12)/((G$36-$C$12)*(1+G$36)^$C45),"N/A") -> 5.6873103 | H45: =IFERROR((1+H$36)/(H$36^2*$C45)*(1-($C45+1)/(1+H$36)^$C45+$C45/(1+H$36)^($C45+1))+(1+$C$12)/((H$36-$C$12)*(1+H$36)^$C45),"N/A") -> 5.1437744
B46: N = 10 years | C46: 10 | D46: =IFERROR((1+D$36)/(D$36^2*$C46)*(1-($C46+1)/(1+D$36)^$C46+$C46/(1+D$36)^($C46+1))+(1+$C$12)/((D$36-$C$12)*(1+D$36)^$C46),"N/A") -> 7.0392999 | E46: =IFERROR((1+E$36)/(E$36^2*$C46)*(1-($C46+1)/(1+E$36)^$C46+$C46/(1+E$36)^($C46+1))+(1+$C$12)/((E$36-$C$12)*(1+E$36)^$C46),"N/A") -> 6.1454133 | F46: =IFERROR((1+F$36)/(F$36^2*$C46)*(1-($C46+1)/(1+F$36)^$C46+$C46/(1+F$36)^($C46+1))+(1+$C$12)/((F$36-$C$12)*(1+F$36)^$C46),"N/A") -> 5.4221789 | G46: =IFERROR((1+G$36)/(G$36^2*$C46)*(1-($C46+1)/(1+G$36)^$C46+$C46/(1+G$36)^($C46+1))+(1+$C$12)/((G$36-$C$12)*(1+G$36)^$C46),"N/A") -> 4.8268574 | H46: =IFERROR((1+H$36)/(H$36^2*$C46)*(1-($C46+1)/(1+H$36)^$C46+$C46/(1+H$36)^($C46+1))+(1+$C$12)/((H$36-$C$12)*(1+H$36)^$C46),"N/A") -> 4.329731
B47: B-3 REQUIRED steady-state Operating Profit (JPY mn)
B48: N = 3 years | C48: 3 | D48: =IFERROR(($C$10/(1-$C$13)-$C$14*D38)/D43,"N/A") -> 1571.034 | E48: =IFERROR(($C$10/(1-$C$13)-$C$14*E38)/E43,"N/A") -> 1758.9605 | F48: =IFERROR(($C$10/(1-$C$13)-$C$14*F38)/F43,"N/A") -> 1950.0807 | G48: =IFERROR(($C$10/(1-$C$13)-$C$14*G38)/G43,"N/A") -> 2144.3607 | H48: =IFERROR(($C$10/(1-$C$13)-$C$14*H38)/H43,"N/A") -> 2341.7666
B49: N = 5 years | C49: 5 | D49: =IFERROR(($C$10/(1-$C$13)-$C$14*D39)/D44,"N/A") -> 1566.0192 | E49: =IFERROR(($C$10/(1-$C$13)-$C$14*E39)/E44,"N/A") -> 1771.5371 | F49: =IFERROR(($C$10/(1-$C$13)-$C$14*F39)/F44,"N/A") -> 1983.8531 | G49: =IFERROR(($C$10/(1-$C$13)-$C$14*G39)/G44,"N/A") -> 2202.9354 | H49: =IFERROR(($C$10/(1-$C$13)-$C$14*H39)/H44,"N/A") -> 2428.7497
B50: N = 7 years | C50: 7 | D50: =IFERROR(($C$10/(1-$C$13)-$C$14*D40)/D45,"N/A") -> 1558.8336 | E50: =IFERROR(($C$10/(1-$C$13)-$C$14*E40)/E45,"N/A") -> 1782.9066 | F50: =IFERROR(($C$10/(1-$C$13)-$C$14*F40)/F45,"N/A") -> 2017.777 | G50: =IFERROR(($C$10/(1-$C$13)-$C$14*G40)/G45,"N/A") -> 2263.4457 | H50: =IFERROR(($C$10/(1-$C$13)-$C$14*H40)/H45,"N/A") -> 2519.9045
B51: N = 10 years | C51: 10 | D51: =IFERROR(($C$10/(1-$C$13)-$C$14*D41)/D46,"N/A") -> 1544.0036 | E51: =IFERROR(($C$10/(1-$C$13)-$C$14*E41)/E46,"N/A") -> 1797.6676 | F51: =IFERROR(($C$10/(1-$C$13)-$C$14*F41)/F46,"N/A") -> 2068.8174 | G51: =IFERROR(($C$10/(1-$C$13)-$C$14*G41)/G46,"N/A") -> 2357.5412 | H51: =IFERROR(($C$10/(1-$C$13)-$C$14*H41)/H46,"N/A") -> 2663.8992
B52: B-4 ... as a multiple of the Q3 FY2026/7 annualised peak operating profit
B53: N = 3 years | C53: 3 | D53: =IFERROR(D48/$C$15,"N/A") -> 0.7449189 | E53: =IFERROR(E48/$C$15,"N/A") -> 0.83402582 | F53: =IFERROR(F48/$C$15,"N/A") -> 0.9246471 | G53: =IFERROR(G48/$C$15,"N/A") -> 1.0167666 | H53: =IFERROR(H48/$C$15,"N/A") -> 1.1103682
B54: N = 5 years | C54: 5 | D54: =IFERROR(D49/$C$15,"N/A") -> 0.74254112 | E54: =IFERROR(E49/$C$15,"N/A") -> 0.83998915 | F54: =IFERROR(F49/$C$15,"N/A") -> 0.94066055 | G54: =IFERROR(G49/$C$15,"N/A") -> 1.0445403 | H54: =IFERROR(H49/$C$15,"N/A") -> 1.151612
B55: N = 7 years | C55: 7 | D55: =IFERROR(D50/$C$15,"N/A") -> 0.73913399 | E55: =IFERROR(E50/$C$15,"N/A") -> 0.84538009 | F55: =IFERROR(F50/$C$15,"N/A") -> 0.95674587 | G55: =IFERROR(G50/$C$15,"N/A") -> 1.0732317 | H55: =IFERROR(H50/$C$15,"N/A") -> 1.1948338
B56: N = 10 years | C56: 10 | D56: =IFERROR(D51/$C$15,"N/A") -> 0.73210222 | E56: =IFERROR(E51/$C$15,"N/A") -> 0.85237912 | F56: =IFERROR(F51/$C$15,"N/A") -> 0.98094708 | G56: =IFERROR(G51/$C$15,"N/A") -> 1.1178479 | H56: =IFERROR(H51/$C$15,"N/A") -> 1.2631101
B58: Block C: Decomposing the required profit into revenue x margin (N = 5 years, model WACC)
B59: The revenue the company must run at, for a given steady-state operating margin, to earn the Block B-3 profit.
B60: Required steady-state Operating Profit (N=5, model WACC) | C60: =F49 -> 1983.8531
B62: Assumed steady-state OPM | C62: Required Revenue | D62: x base-year revenue
B63: 0.05 | C63: =IFERROR($C$60/B63,"N/A") -> 39677.062 | D63: =IFERROR(C63/'DCF Model'!C17,"N/A") -> 2.7620649
B64: 0.0735 | C64: =IFERROR($C$60/B64,"N/A") -> 26991.199 | D64: =IFERROR(C64/'DCF Model'!C17,"N/A") -> 1.8789557
B65: 0.1 | C65: =IFERROR($C$60/B65,"N/A") -> 19838.531 | D65: =IFERROR(C65/'DCF Model'!C17,"N/A") -> 1.3810324
B66: cycle-peak OPM (Q3 FY2026/7 annualised) | C66: =IFERROR($C$60/$C$18,"N/A") -> 13863.404 | D66: =IFERROR(C66/'DCF Model'!C17,"N/A") -> 0.96508207
B67: 0.17 | C67: =IFERROR($C$60/B67,"N/A") -> 11669.724 | D67: =IFERROR(C67/'DCF Model'!C17,"N/A") -> 0.81237202
B69: Block D: The same question expressed as multiples
B70: Current EV / latest-FY EBITDA (actual) | C70: =IFERROR(C10/'Comps Analysis'!G5,"N/A") -> 5.2809714
B71: Current EV / latest-FY Revenue (actual) | C71: =IFERROR(C10/'Comps Analysis'!F5,"N/A") -> 0.8944381
B72: EV / EBITDA if the Block A profit were already earned | C72: =IFERROR(C10/(C25+'DCF Model'!G42),"N/A") -> 5.0754426
B73: EV / EBITDA if the Block B-3 (N=5) profit were already earned | C73: =IFERROR(C10/(C60+'DCF Model'!G42),"N/A") -> 4.9439513
B74: Peer median EV / EBITDA (statistics rows) | C74: =IFERROR('Comps Analysis'!D16,"N/A") -> 5.9390543
B75: Rows 3-4 answer: what multiple would today's EV be paying IF the company already earned the profit the price requires?
B77: Block F: The one-line answer
B78: ="At "&TEXT(C6,"#,##0")&" yen the market is paying for a steady-state operating profit of "&TEXT(F49,"#,##0")&" mn JPY - "&TEXT(F54,"0.00")&"x the Q3 FY2026/7 annualised cycle peak of "&TEXT(C15,"#,##0")&" mn - reached in 5 years and sustained for ever, against "&TEXT(C14,"#,##0")&" mn actually earned in FY2026/7E." -> At 2,764 yen the market is paying for a steady-state operating profit of 1,984 mn JPY - 0.94x the Q3 FY2026/7 annualised cycle peak of 2,109 mn - reached in 5 years and sustained for ever, against 1,943 mn actually earned in FY2026/7E.
B79: ="Even with no ramp at all (Block A) the price needs "&TEXT(C25,"#,##0")&" mn, or "&TEXT(C26,"0.00")&"x the peak. The base case supports an EV of only "&TEXT(C17,"#,##0")&" mn, leaving "&TEXT(C20,"#,##0")&" yen per share of the current price unexplained by mid-cycle economics." -> Even with no ramp at all (Block A) the price needs 1,917 mn, or 0.91x the peak. The base case supports an EV of only 13,416 mn, leaving -134 yen per share of the current price unexplained by mid-cycle economics.

Sheet NWC Schedule
B2: NWC Schedule - SANNO
B4: Working Capital Drivers (Days) | C4: Base Year | D4: FY2027(E) | E4: FY2028(E) | F4: FY2029(E) | G4: FY2030(E) | H4: FY2031(E)
B5: DSO (Days Sales Outstanding) | C5: =C12/C9*365 -> 71.119735 | D5: =CHOOSE('DCF Model'!$D$27,D25,D26,D27,D28,D29) -> 71 | E5: =CHOOSE('DCF Model'!$D$27,E25,E26,E27,E28,E29) -> 71 | F5: =CHOOSE('DCF Model'!$D$27,F25,F26,F27,F28,F29) -> 70 | G5: =CHOOSE('DCF Model'!$D$27,G25,G26,G27,G28,G29) -> 70 | H5: =CHOOSE('DCF Model'!$D$27,H25,H26,H27,H28,H29) -> 70
B6: DIH (Days Inventory Held) | C6: =C13/C10*365 -> 114.69212 | D6: =CHOOSE('DCF Model'!$D$27,D32,D33,D34,D35,D36) -> 113 | E6: =CHOOSE('DCF Model'!$D$27,E32,E33,E34,E35,E36) -> 111 | F6: =CHOOSE('DCF Model'!$D$27,F32,F33,F34,F35,F36) -> 109 | G6: =CHOOSE('DCF Model'!$D$27,G32,G33,G34,G35,G36) -> 107 | H6: =CHOOSE('DCF Model'!$D$27,H32,H33,H34,H35,H36) -> 105
B7: DPO (Days Payable Outstanding) | C7: =C15/C10*365 -> 16.651004 | D7: =CHOOSE('DCF Model'!$D$27,D39,D40,D41,D42,D43) -> 17 | E7: =CHOOSE('DCF Model'!$D$27,E39,E40,E41,E42,E43) -> 17 | F7: =CHOOSE('DCF Model'!$D$27,F39,F40,F41,F42,F43) -> 17 | G7: =CHOOSE('DCF Model'!$D$27,G39,G40,G41,G42,G43) -> 17 | H7: =CHOOSE('DCF Model'!$D$27,H39,H40,H41,H42,H43) -> 17
B8: P&L Reference (JPY mn)
B9: Revenue | C9: 14365 | D9: ='DCF Model'!C33 -> 15514.2 | E9: ='DCF Model'!D33 -> 16445.052 | F9: ='DCF Model'!E33 -> 17267.305 | G9: ='DCF Model'!F33 -> 17957.997 | H9: ='DCF Model'!G33 -> 18496.737
B10: COGS | C10: 10960.3 | D10: ='DCF Model'!C34 -> 11945.934 | E10: ='DCF Model'!D34 -> 12744.915 | F10: ='DCF Model'!E34 -> 13382.161 | G10: ='DCF Model'!F34 -> 13917.448 | H10: ='DCF Model'!G34 -> 14334.971
B11: Working Capital Items (JPY mn)
B12: Accounts Receivable | C12: 2799 | D12: =D9*D5/365 -> 3017.8307 | E12: =E9*E5/365 -> 3198.9005 | F12: =F9*F5/365 -> 3311.5379 | G12: =G9*G5/365 -> 3443.9994 | H12: =H9*H5/365 -> 3547.3194
B13: Inventory | C13: 3444 | D13: =D10*D6/365 -> 3698.3303 | E13: =E10*E6/365 -> 3875.851 | F13: =F10*F6/365 -> 3996.3166 | G13: =G10*G6/365 -> 4079.9093 | H13: =H10*H6/365 -> 4123.7588
B14: Current Assets (AR + Inv) | C14: =C12+C13 -> 6243 | D14: =D12+D13 -> 6716.1609 | E14: =E12+E13 -> 7074.7515 | F14: =F12+F13 -> 7307.8545 | G14: =G12+G13 -> 7523.9087 | H14: =H12+H13 -> 7671.0781
B15: Accounts Payable | C15: 500 | D15: =D10*D7/365 -> 556.38597 | E15: =E10*E7/365 -> 593.59879 | F15: =F10*F7/365 -> 623.27873 | G15: =G10*G7/365 -> 648.20988 | H15: =H10*H7/365 -> 667.65618
B16: Current Liabilities (AP) | C16: =C15 -> 500 | D16: =D15 -> 556.38597 | E16: =E15 -> 593.59879 | F16: =F15 -> 623.27873 | G16: =G15 -> 648.20988 | H16: =H15 -> 667.65618
B17: Net Working Capital (JPY mn)
B18: Net Working Capital | C18: =C14-C16 -> 5743 | D18: =D14-D16 -> 6159.775 | E18: =E14-E16 -> 6481.1527 | F18: =F14-F16 -> 6684.5757 | G18: =G14-G16 -> 6875.6988 | H18: =H14-H16 -> 7003.4219
B19: Change in NWC | C19: n/a | D19: =D18-C18 -> 416.77497 | E19: =E18-D18 -> 321.37772 | F19: =F18-E18 -> 203.42304 | G19: =G18-F18 -> 191.12304 | H19: =H18-G18 -> 127.72318
B22: Scenario Input Matrix (Working Capital Days)
D23: FY2027(E) | E23: FY2028(E) | F23: FY2029(E) | G23: FY2030(E) | H23: FY2031(E)
B24: DSO (Days)
B25: Base | D25: 71 | E25: 71 | F25: 70 | G25: 70 | H25: 70
B26: Upside | D26: 69 | E26: 68 | F26: 68 | G26: 67 | H26: 67
B27: Management | D27: 71 | E27: 71 | F27: 71 | G27: 71 | H27: 71
B28: Downside 1 | D28: 74 | E28: 75 | F28: 75 | G28: 76 | H28: 76
B29: Downside 2 | D29: 77 | E29: 78 | F29: 79 | G29: 80 | H29: 80
B31: DIH (Days)
B32: Base | D32: 113 | E32: 111 | F32: 109 | G32: 107 | H32: 105
B33: Upside | D33: 115 | E33: 114 | F33: 112 | G33: 110 | H33: 108
B34: Management | D34: 115 | E34: 114 | F34: 113 | G34: 112 | H34: 111
B35: Downside 1 | D35: 118 | E35: 118 | F35: 117 | G35: 116 | H35: 115
B36: Downside 2 | D36: 122 | E36: 121 | F36: 119 | G36: 117 | H36: 115
B38: DPO (Days)
B39: Base | D39: 17 | E39: 17 | F39: 17 | G39: 17 | H39: 17
B40: Upside | D40: 19 | E40: 19 | F40: 20 | G40: 20 | H40: 20
B41: Management | D41: 17 | E41: 17 | F41: 17 | G41: 17 | H41: 17
B42: Downside 1 | D42: 15 | E42: 15 | F42: 15 | G42: 15 | H42: 15
B43: Downside 2 | D43: 14 | E43: 14 | F43: 13 | G43: 13 | H43: 13

Sheet Comps Analysis
B2: Comparable Company Analysis
B3: Peer prices as of 2026-08-29 (Mkt Cap / EV of peer rows are static CSV values; the subject row is live-linked to Executive Summary)
B4: Company | C4: Ticker | D4: Mkt Cap (JPY mn) | E4: EV (JPY mn) | F4: Revenue (JPY mn) | G4: EBITDA (JPY mn) | H4: Op Income (JPY mn) | I4: Net Income (JPY mn) | J4: EV/EBITDA | K4: EV/Revenue | L4: PER | M4: PBR | N4: Op Margin | O4: ROE | P4: Book Value (JPY mn) | Q4: Note
B5: SANNO (3441) [subject] | C5: 3441.T | D5: ='Executive Summary'!C9*C23/1000000 -> 11724.603 | E5: =D5+C24 -> 12848.603 | F5: 14365 | G5: 2433 | H5: 1943 | I5: 1750 | J5: =IFERROR(E5/G5,"") -> 5.2809714 | K5: =IFERROR(E5/F5,"") -> 0.8944381 | L5: =IFERROR(D5/I5,"") -> 6.6997733 | M5: =IFERROR(D5/P5,"") -> 1.4232342 | N5: =IFERROR(H5/F5,"") -> 0.13525931 | O5: =IFERROR(I5/P5,"") -> 0.2124302 | P5: 8238
B6: Japan Pure Chemical (4973) | C6: 4973.T | D6: 27942 | E6: 20189 | F6: 18073 | G6: 664 | H6: 576 | I6: 1804 | J6: =IFERROR(E6/G6,"") -> 30.40512 | K6: =IFERROR(E6/F6,"") -> 1.1170807 | L6: =IFERROR(D6/I6,"") -> 15.488914 | M6: =IFERROR(D6/P6,"") -> 1.5467479 | N6: =IFERROR(H6/F6,"") -> 0.031870746 | O6: =IFERROR(I6/P6,"") -> 0.099861611 | P6: 18065
B7: Enomoto (6928) | C7: 6928.T | D7: 19648 | E7: 18421 | F7: 30415 | G7: 3800 | H7: 1651 | I7: 1231 | J7: =IFERROR(E7/G7,"") -> 4.8476316 | K7: =IFERROR(E7/F7,"") -> 0.6056551 | L7: =IFERROR(D7/I7,"") -> 15.961007 | M7: =IFERROR(D7/P7,"") -> 0.84594851 | N7: =IFERROR(H7/F7,"") -> 0.054282426 | O7: =IFERROR(I7/P7,"") -> 0.053000947 | P7: 23226
B8: Nihon Parkerizing (4095) | C8: 4095.T | D8: 184047 | E8: 130873 | F8: 138155 | G8: 22036 | H8: 14818 | I8: 12940 | J8: =IFERROR(E8/G8,"") -> 5.9390543 | K8: =IFERROR(E8/F8,"") -> 0.94729109 | L8: =IFERROR(D8/I8,"") -> 14.223107 | M8: =IFERROR(D8/P8,"") -> 0.91193186 | N8: =IFERROR(H8/F8,"") -> 0.10725634 | O8: =IFERROR(I8/P8,"") -> 0.064116222 | P8: 201821
B9: KEL (6919) | C9: 6919.T | D9: 10266 | E9: 6051 | F9: 12858 | G9: 1492 | H9: 285 | I9: 210 | J9: =IFERROR(E9/G9,"") -> 4.05563 | K9: =IFERROR(E9/F9,"") -> 0.47060196 | L9: =IFERROR(D9/I9,"") -> 48.885714 | M9: =IFERROR(D9/P9,"") -> 0.67080502 | N9: =IFERROR(H9/F9,"") -> 0.022165189 | O9: =IFERROR(I9/P9,"") -> 0.013721903 | P9: 15304
B10: Yamaichi Electronics (6941) | C10: 6941.T | D10: 144887 | E10: 133238 | F10: 52699 | G10: 14831 | H10: 11557 | I10: 9074 | J10: =IFERROR(E10/G10,"") -> 8.9837503 | K10: =IFERROR(E10/F10,"") -> 2.5282833 | L10: =IFERROR(D10/I10,"") -> 15.967269 | M10: =IFERROR(D10/P10,"") -> 3.1126364 | N10: =IFERROR(H10/F10,"") -> 0.21930207 | O10: =IFERROR(I10/P10,"") -> 0.19493856 | P10: 46548
B14: Statistics
B15: 25th Percentile | D15: =PERCENTILE(J6:J10,0.25) -> 4.8476316 | E15: =PERCENTILE(K6:K10,0.25) -> 0.6056551 | F15: =PERCENTILE(L6:L10,0.25) -> 15.488914 | G15: =PERCENTILE(M6:M10,0.25) -> 0.84594851 | H15: =PERCENTILE(N6:N10,0.25) -> 0.031870746 | I15: =PERCENTILE(O6:O10,0.25) -> 0.053000947
B16: Median (50th) | D16: =MEDIAN(J6:J10) -> 5.9390543 | E16: =MEDIAN(K6:K10) -> 0.94729109 | F16: =MEDIAN(L6:L10) -> 15.961007 | G16: =MEDIAN(M6:M10) -> 0.91193186 | H16: =MEDIAN(N6:N10) -> 0.054282426 | I16: =MEDIAN(O6:O10) -> 0.064116222
B17: 75th Percentile | D17: =PERCENTILE(J6:J10,0.75) -> 8.9837503 | E17: =PERCENTILE(K6:K10,0.75) -> 1.1170807 | F17: =PERCENTILE(L6:L10,0.75) -> 15.967269 | G17: =PERCENTILE(M6:M10,0.75) -> 1.5467479 | H17: =PERCENTILE(N6:N10,0.75) -> 0.10725634 | I17: =PERCENTILE(O6:O10,0.75) -> 0.099861611
B19: Implied Valuation for SANNO
B20: SANNO Financials
B21: EBITDA (JPY mn) | C21: 2433
B22: Net Income (JPY mn) | C22: 1750
B23: Shares Outstanding | C23: 4241897
B24: Net Debt (JPY mn) | C24: 1124
B26: Implied Share Price (Median Multiples)
B27: Via EV/EBITDA (Median) | C27: =ROUND((C21*D16-C24)*1000000/C23,0) -> 3141
B28: Via PER (Median) | C28: =ROUND(C22*F16*1000000/C23,0) -> 6585
B29: Net Income normalized (FY2026/7E pretax 1,953 x normalised tax C6) [参考・Target不算入] | C29: =ROUND((1953+0)*(1-'DCF Model'!C6),0) -> 1465 | D29: Q3累計の実効税率8.1%は繰延税金資産の計上とフィリピン優遇税制による一時的な軽課で、報告ベースの純利益はPERの分母として上振れている。FY2026/7E 経常利益推定1,953(営業1,943 + 営業外純収支 +10)に DCF Model!C6 の正常化税率25%を適用した参考値。FY2025/7 実績766 も同様に法人税等調整額 -115 の押し上げを含み、正常化後は約651。
B30: Via PER (Median, normalized NI) [参考・Target不算入] | C30: =ROUND(C29*F16*1000000/C23,0) -> 5512

Sheet Sensitivity Analysis
B2: Sensitivity Analysis
B3: Current WACC: | C3: ='DCF Model'!C26 -> 0.12187152 | E3: Terminal g: | F3: ='DCF Model'!C13 -> 0.01 | H3: Exit Multiple: | I3: ='DCF Model'!C14 -> 5.5
B5: Table 1: WACC vs Terminal Growth Rate (PGM - Implied Share Price, JPY)
B6: WACC \ Terminal g | C6: =$F$3-0.0075 -> 0.0025 | D6: =$F$3-0.005 -> 0.005 | E6: =$F$3-0.0025 -> 0.0075 | F6: =$F$3 -> 0.01 | G6: =$F$3+0.0025 -> 0.0125 | H6: =$F$3+0.005 -> 0.015 | I6: =$F$3+0.0075 -> 0.0175
B7: =$C$3-0.015 -> 0.10687152 | C7: =IFERROR(ROUND(('DCF Model'!C45/(1+$B7)^('DCF Model'!C19+0)+'DCF Model'!D45/(1+$B7)^('DCF Model'!C19+1)+'DCF Model'!E45/(1+$B7)^('DCF Model'!C19+2)+'DCF Model'!F45/(1+$B7)^('DCF Model'!C19+3)+'DCF Model'!G45/(1+$B7)^('DCF Model'!C19+4)+'DCF Model'!G45*(1+C$6)/($B7-C$6)/(1+$B7)^('DCF Model'!C19+4)-'DCF Model'!C16)*1000000/'DCF Model'!C15,0),"") -> 3224 | D7: =IFERROR(ROUND(('DCF Model'!C45/(1+$B7)^('DCF Model'!C19+0)+'DCF Model'!D45/(1+$B7)^('DCF Model'!C19+1)+'DCF Model'!E45/(1+$B7)^('DCF Model'!C19+2)+'DCF Model'!F45/(1+$B7)^('DCF Model'!C19+3)+'DCF Model'!G45/(1+$B7)^('DCF Model'!C19+4)+'DCF Model'!G45*(1+D$6)/($B7-D$6)/(1+$B7)^('DCF Model'!C19+4)-'DCF Model'!C16)*1000000/'DCF Model'!C15,0),"") -> 3287 | E7: =IFERROR(ROUND(('DCF Model'!C45/(1+$B7)^('DCF Model'!C19+0)+'DCF Model'!D45/(1+$B7)^('DCF Model'!C19+1)+'DCF Model'!E45/(1+$B7)^('DCF Model'!C19+2)+'DCF Model'!F45/(1+$B7)^('DCF Model'!C19+3)+'DCF Model'!G45/(1+$B7)^('DCF Model'!C19+4)+'DCF Model'!G45*(1+E$6)/($B7-E$6)/(1+$B7)^('DCF Model'!C19+4)-'DCF Model'!C16)*1000000/'DCF Model'!C15,0),"") -> 3354 | F7: =IFERROR(ROUND(('DCF Model'!C45/(1+$B7)^('DCF Model'!C19+0)+'DCF Model'!D45/(1+$B7)^('DCF Model'!C19+1)+'DCF Model'!E45/(1+$B7)^('DCF Model'!C19+2)+'DCF Model'!F45/(1+$B7)^('DCF Model'!C19+3)+'DCF Model'!G45/(1+$B7)^('DCF Model'!C19+4)+'DCF Model'!G45*(1+F$6)/($B7-F$6)/(1+$B7)^('DCF Model'!C19+4)-'DCF Model'!C16)*1000000/'DCF Model'!C15,0),"") -> 3424 | G7: =IFERROR(ROUND(('DCF Model'!C45/(1+$B7)^('DCF Model'!C19+0)+'DCF Model'!D45/(1+$B7)^('DCF Model'!C19+1)+'DCF Model'!E45/(1+$B7)^('DCF Model'!C19+2)+'DCF Model'!F45/(1+$B7)^('DCF Model'!C19+3)+'DCF Model'!G45/(1+$B7)^('DCF Model'!C19+4)+'DCF Model'!G45*(1+G$6)/($B7-G$6)/(1+$B7)^('DCF Model'!C19+4)-'DCF Model'!C16)*1000000/'DCF Model'!C15,0),"") -> 3497 | H7: =IFERROR(ROUND(('DCF Model'!C45/(1+$B7)^('DCF Model'!C19+0)+'DCF Model'!D45/(1+$B7)^('DCF Model'!C19+1)+'DCF Model'!E45/(1+$B7)^('DCF Model'!C19+2)+'DCF Model'!F45/(1+$B7)^('DCF Model'!C19+3)+'DCF Model'!G45/(1+$B7)^('DCF Model'!C19+4)+'DCF Model'!G45*(1+H$6)/($B7-H$6)/(1+$B7)^('DCF Model'!C19+4)-'DCF Model'!C16)*1000000/'DCF Model'!C15,0),"") -> 3575 | I7: =IFERROR(ROUND(('DCF Model'!C45/(1+$B7)^('DCF Model'!C19+0)+'DCF Model'!D45/(1+$B7)^('DCF Model'!C19+1)+'DCF Model'!E45/(1+$B7)^('DCF Model'!C19+2)+'DCF Model'!F45/(1+$B7)^('DCF Model'!C19+3)+'DCF Model'!G45/(1+$B7)^('DCF Model'!C19+4)+'DCF Model'!G45*(1+I$6)/($B7-I$6)/(1+$B7)^('DCF Model'!C19+4)-'DCF Model'!C16)*1000000/'DCF Model'!C15,0),"") -> 3656
B8: =$C$3-0.01 -> 0.11187152 | C8: =IFERROR(ROUND(('DCF Model'!C45/(1+$B8)^('DCF Model'!C19+0)+'DCF Model'!D45/(1+$B8)^('DCF Model'!C19+1)+'DCF Model'!E45/(1+$B8)^('DCF Model'!C19+2)+'DCF Model'!F45/(1+$B8)^('DCF Model'!C19+3)+'DCF Model'!G45/(1+$B8)^('DCF Model'!C19+4)+'DCF Model'!G45*(1+C$6)/($B8-C$6)/(1+$B8)^('DCF Model'!C19+4)-'DCF Model'!C16)*1000000/'DCF Model'!C15,0),"") -> 3053 | D8: =IFERROR(ROUND(('DCF Model'!C45/(1+$B8)^('DCF Model'!C19+0)+'DCF Model'!D45/(1+$B8)^('DCF Model'!C19+1)+'DCF Model'!E45/(1+$B8)^('DCF Model'!C19+2)+'DCF Model'!F45/(1+$B8)^('DCF Model'!C19+3)+'DCF Model'!G45/(1+$B8)^('DCF Model'!C19+4)+'DCF Model'!G45*(1+D$6)/($B8-D$6)/(1+$B8)^('DCF Model'!C19+4)-'DCF Model'!C16)*1000000/'DCF Model'!C15,0),"") -> 3110 | E8: =IFERROR(ROUND(('DCF Model'!C45/(1+$B8)^('DCF Model'!C19+0)+'DCF Model'!D45/(1+$B8)^('DCF Model'!C19+1)+'DCF Model'!E45/(1+$B8)^('DCF Model'!C19+2)+'DCF Model'!F45/(1+$B8)^('DCF Model'!C19+3)+'DCF Model'!G45/(1+$B8)^('DCF Model'!C19+4)+'DCF Model'!G45*(1+E$6)/($B8-E$6)/(1+$B8)^('DCF Model'!C19+4)-'DCF Model'!C16)*1000000/'DCF Model'!C15,0),"") -> 3169 | F8: =IFERROR(ROUND(('DCF Model'!C45/(1+$B8)^('DCF Model'!C19+0)+'DCF Model'!D45/(1+$B8)^('DCF Model'!C19+1)+'DCF Model'!E45/(1+$B8)^('DCF Model'!C19+2)+'DCF Model'!F45/(1+$B8)^('DCF Model'!C19+3)+'DCF Model'!G45/(1+$B8)^('DCF Model'!C19+4)+'DCF Model'!G45*(1+F$6)/($B8-F$6)/(1+$B8)^('DCF Model'!C19+4)-'DCF Model'!C16)*1000000/'DCF Model'!C15,0),"") -> 3231 | G8: =IFERROR(ROUND(('DCF Model'!C45/(1+$B8)^('DCF Model'!C19+0)+'DCF Model'!D45/(1+$B8)^('DCF Model'!C19+1)+'DCF Model'!E45/(1+$B8)^('DCF Model'!C19+2)+'DCF Model'!F45/(1+$B8)^('DCF Model'!C19+3)+'DCF Model'!G45/(1+$B8)^('DCF Model'!C19+4)+'DCF Model'!G45*(1+G$6)/($B8-G$6)/(1+$B8)^('DCF Model'!C19+4)-'DCF Model'!C16)*1000000/'DCF Model'!C15,0),"") -> 3296 | H8: =IFERROR(ROUND(('DCF Model'!C45/(1+$B8)^('DCF Model'!C19+0)+'DCF Model'!D45/(1+$B8)^('DCF Model'!C19+1)+'DCF Model'!E45/(1+$B8)^('DCF Model'!C19+2)+'DCF Model'!F45/(1+$B8)^('DCF Model'!C19+3)+'DCF Model'!G45/(1+$B8)^('DCF Model'!C19+4)+'DCF Model'!G45*(1+H$6)/($B8-H$6)/(1+$B8)^('DCF Model'!C19+4)-'DCF Model'!C16)*1000000/'DCF Model'!C15,0),"") -> 3365 | I8: =IFERROR(ROUND(('DCF Model'!C45/(1+$B8)^('DCF Model'!C19+0)+'DCF Model'!D45/(1+$B8)^('DCF Model'!C19+1)+'DCF Model'!E45/(1+$B8)^('DCF Model'!C19+2)+'DCF Model'!F45/(1+$B8)^('DCF Model'!C19+3)+'DCF Model'!G45/(1+$B8)^('DCF Model'!C19+4)+'DCF Model'!G45*(1+I$6)/($B8-I$6)/(1+$B8)^('DCF Model'!C19+4)-'DCF Model'!C16)*1000000/'DCF Model'!C15,0),"") -> 3437
B9: =$C$3-0.005 -> 0.11687152 | C9: =IFERROR(ROUND(('DCF Model'!C45/(1+$B9)^('DCF Model'!C19+0)+'DCF Model'!D45/(1+$B9)^('DCF Model'!C19+1)+'DCF Model'!E45/(1+$B9)^('DCF Model'!C19+2)+'DCF Model'!F45/(1+$B9)^('DCF Model'!C19+3)+'DCF Model'!G45/(1+$B9)^('DCF Model'!C19+4)+'DCF Model'!G45*(1+C$6)/($B9-C$6)/(1+$B9)^('DCF Model'!C19+4)-'DCF Model'!C16)*1000000/'DCF Model'!C15,0),"") -> 2897 | D9: =IFERROR(ROUND(('DCF Model'!C45/(1+$B9)^('DCF Model'!C19+0)+'DCF Model'!D45/(1+$B9)^('DCF Model'!C19+1)+'DCF Model'!E45/(1+$B9)^('DCF Model'!C19+2)+'DCF Model'!F45/(1+$B9)^('DCF Model'!C19+3)+'DCF Model'!G45/(1+$B9)^('DCF Model'!C19+4)+'DCF Model'!G45*(1+D$6)/($B9-D$6)/(1+$B9)^('DCF Model'!C19+4)-'DCF Model'!C16)*1000000/'DCF Model'!C15,0),"") -> 2948 | E9: =IFERROR(ROUND(('DCF Model'!C45/(1+$B9)^('DCF Model'!C19+0)+'DCF Model'!D45/(1+$B9)^('DCF Model'!C19+1)+'DCF Model'!E45/(1+$B9)^('DCF Model'!C19+2)+'DCF Model'!F45/(1+$B9)^('DCF Model'!C19+3)+'DCF Model'!G45/(1+$B9)^('DCF Model'!C19+4)+'DCF Model'!G45*(1+E$6)/($B9-E$6)/(1+$B9)^('DCF Model'!C19+4)-'DCF Model'!C16)*1000000/'DCF Model'!C15,0),"") -> 3001 | F9: =IFERROR(ROUND(('DCF Model'!C45/(1+$B9)^('DCF Model'!C19+0)+'DCF Model'!D45/(1+$B9)^('DCF Model'!C19+1)+'DCF Model'!E45/(1+$B9)^('DCF Model'!C19+2)+'DCF Model'!F45/(1+$B9)^('DCF Model'!C19+3)+'DCF Model'!G45/(1+$B9)^('DCF Model'!C19+4)+'DCF Model'!G45*(1+F$6)/($B9-F$6)/(1+$B9)^('DCF Model'!C19+4)-'DCF Model'!C16)*1000000/'DCF Model'!C15,0),"") -> 3056 | G9: =IFERROR(ROUND(('DCF Model'!C45/(1+$B9)^('DCF Model'!C19+0)+'DCF Model'!D45/(1+$B9)^('DCF Model'!C19+1)+'DCF Model'!E45/(1+$B9)^('DCF Model'!C19+2)+'DCF Model'!F45/(1+$B9)^('DCF Model'!C19+3)+'DCF Model'!G45/(1+$B9)^('DCF Model'!C19+4)+'DCF Model'!G45*(1+G$6)/($B9-G$6)/(1+$B9)^('DCF Model'!C19+4)-'DCF Model'!C16)*1000000/'DCF Model'!C15,0),"") -> 3115 | H9: =IFERROR(ROUND(('DCF Model'!C45/(1+$B9)^('DCF Model'!C19+0)+'DCF Model'!D45/(1+$B9)^('DCF Model'!C19+1)+'DCF Model'!E45/(1+$B9)^('DCF Model'!C19+2)+'DCF Model'!F45/(1+$B9)^('DCF Model'!C19+3)+'DCF Model'!G45/(1+$B9)^('DCF Model'!C19+4)+'DCF Model'!G45*(1+H$6)/($B9-H$6)/(1+$B9)^('DCF Model'!C19+4)-'DCF Model'!C16)*1000000/'DCF Model'!C15,0),"") -> 3176 | I9: =IFERROR(ROUND(('DCF Model'!C45/(1+$B9)^('DCF Model'!C19+0)+'DCF Model'!D45/(1+$B9)^('DCF Model'!C19+1)+'DCF Model'!E45/(1+$B9)^('DCF Model'!C19+2)+'DCF Model'!F45/(1+$B9)^('DCF Model'!C19+3)+'DCF Model'!G45/(1+$B9)^('DCF Model'!C19+4)+'DCF Model'!G45*(1+I$6)/($B9-I$6)/(1+$B9)^('DCF Model'!C19+4)-'DCF Model'!C16)*1000000/'DCF Model'!C15,0),"") -> 3240
B10: =$C$3 -> 0.12187152 | C10: =IFERROR(ROUND(('DCF Model'!C45/(1+$B10)^('DCF Model'!C19+0)+'DCF Model'!D45/(1+$B10)^('DCF Model'!C19+1)+'DCF Model'!E45/(1+$B10)^('DCF Model'!C19+2)+'DCF Model'!F45/(1+$B10)^('DCF Model'!C19+3)+'DCF Model'!G45/(1+$B10)^('DCF Model'!C19+4)+'DCF Model'!G45*(1+C$6)/($B10-C$6)/(1+$B10)^('DCF Model'!C19+4)-'DCF Model'!C16)*1000000/'DCF Model'!C15,0),"") -> 2755 | D10: =IFERROR(ROUND(('DCF Model'!C45/(1+$B10)^('DCF Model'!C19+0)+'DCF Model'!D45/(1+$B10)^('DCF Model'!C19+1)+'DCF Model'!E45/(1+$B10)^('DCF Model'!C19+2)+'DCF Model'!F45/(1+$B10)^('DCF Model'!C19+3)+'DCF Model'!G45/(1+$B10)^('DCF Model'!C19+4)+'DCF Model'!G45*(1+D$6)/($B10-D$6)/(1+$B10)^('DCF Model'!C19+4)-'DCF Model'!C16)*1000000/'DCF Model'!C15,0),"") -> 2800 | E10: =IFERROR(ROUND(('DCF Model'!C45/(1+$B10)^('DCF Model'!C19+0)+'DCF Model'!D45/(1+$B10)^('DCF Model'!C19+1)+'DCF Model'!E45/(1+$B10)^('DCF Model'!C19+2)+'DCF Model'!F45/(1+$B10)^('DCF Model'!C19+3)+'DCF Model'!G45/(1+$B10)^('DCF Model'!C19+4)+'DCF Model'!G45*(1+E$6)/($B10-E$6)/(1+$B10)^('DCF Model'!C19+4)-'DCF Model'!C16)*1000000/'DCF Model'!C15,0),"") -> 2848 | F10: =IFERROR(ROUND(('DCF Model'!C45/(1+$B10)^('DCF Model'!C19+0)+'DCF Model'!D45/(1+$B10)^('DCF Model'!C19+1)+'DCF Model'!E45/(1+$B10)^('DCF Model'!C19+2)+'DCF Model'!F45/(1+$B10)^('DCF Model'!C19+3)+'DCF Model'!G45/(1+$B10)^('DCF Model'!C19+4)+'DCF Model'!G45*(1+F$6)/($B10-F$6)/(1+$B10)^('DCF Model'!C19+4)-'DCF Model'!C16)*1000000/'DCF Model'!C15,0),"") -> 2898 | G10: =IFERROR(ROUND(('DCF Model'!C45/(1+$B10)^('DCF Model'!C19+0)+'DCF Model'!D45/(1+$B10)^('DCF Model'!C19+1)+'DCF Model'!E45/(1+$B10)^('DCF Model'!C19+2)+'DCF Model'!F45/(1+$B10)^('DCF Model'!C19+3)+'DCF Model'!G45/(1+$B10)^('DCF Model'!C19+4)+'DCF Model'!G45*(1+G$6)/($B10-G$6)/(1+$B10)^('DCF Model'!C19+4)-'DCF Model'!C16)*1000000/'DCF Model'!C15,0),"") -> 2950 | H10: =IFERROR(ROUND(('DCF Model'!C45/(1+$B10)^('DCF Model'!C19+0)+'DCF Model'!D45/(1+$B10)^('DCF Model'!C19+1)+'DCF Model'!E45/(1+$B10)^('DCF Model'!C19+2)+'DCF Model'!F45/(1+$B10)^('DCF Model'!C19+3)+'DCF Model'!G45/(1+$B10)^('DCF Model'!C19+4)+'DCF Model'!G45*(1+H$6)/($B10-H$6)/(1+$B10)^('DCF Model'!C19+4)-'DCF Model'!C16)*1000000/'DCF Model'!C15,0),"") -> 3004 | I10: =IFERROR(ROUND(('DCF Model'!C45/(1+$B10)^('DCF Model'!C19+0)+'DCF Model'!D45/(1+$B10)^('DCF Model'!C19+1)+'DCF Model'!E45/(1+$B10)^('DCF Model'!C19+2)+'DCF Model'!F45/(1+$B10)^('DCF Model'!C19+3)+'DCF Model'!G45/(1+$B10)^('DCF Model'!C19+4)+'DCF Model'!G45*(1+I$6)/($B10-I$6)/(1+$B10)^('DCF Model'!C19+4)-'DCF Model'!C16)*1000000/'DCF Model'!C15,0),"") -> 3062
B11: =$C$3+0.005 -> 0.12687152 | C11: =IFERROR(ROUND(('DCF Model'!C45/(1+$B11)^('DCF Model'!C19+0)+'DCF Model'!D45/(1+$B11)^('DCF Model'!C19+1)+'DCF Model'!E45/(1+$B11)^('DCF Model'!C19+2)+'DCF Model'!F45/(1+$B11)^('DCF Model'!C19+3)+'DCF Model'!G45/(1+$B11)^('DCF Model'!C19+4)+'DCF Model'!G45*(1+C$6)/($B11-C$6)/(1+$B11)^('DCF Model'!C19+4)-'DCF Model'!C16)*1000000/'DCF Model'!C15,0),"") -> 2623 | D11: =IFERROR(ROUND(('DCF Model'!C45/(1+$B11)^('DCF Model'!C19+0)+'DCF Model'!D45/(1+$B11)^('DCF Model'!C19+1)+'DCF Model'!E45/(1+$B11)^('DCF Model'!C19+2)+'DCF Model'!F45/(1+$B11)^('DCF Model'!C19+3)+'DCF Model'!G45/(1+$B11)^('DCF Model'!C19+4)+'DCF Model'!G45*(1+D$6)/($B11-D$6)/(1+$B11)^('DCF Model'!C19+4)-'DCF Model'!C16)*1000000/'DCF Model'!C15,0),"") -> 2665 | E11: =IFERROR(ROUND(('DCF Model'!C45/(1+$B11)^('DCF Model'!C19+0)+'DCF Model'!D45/(1+$B11)^('DCF Model'!C19+1)+'DCF Model'!E45/(1+$B11)^('DCF Model'!C19+2)+'DCF Model'!F45/(1+$B11)^('DCF Model'!C19+3)+'DCF Model'!G45/(1+$B11)^('DCF Model'!C19+4)+'DCF Model'!G45*(1+E$6)/($B11-E$6)/(1+$B11)^('DCF Model'!C19+4)-'DCF Model'!C16)*1000000/'DCF Model'!C15,0),"") -> 2708 | F11: =IFERROR(ROUND(('DCF Model'!C45/(1+$B11)^('DCF Model'!C19+0)+'DCF Model'!D45/(1+$B11)^('DCF Model'!C19+1)+'DCF Model'!E45/(1+$B11)^('DCF Model'!C19+2)+'DCF Model'!F45/(1+$B11)^('DCF Model'!C19+3)+'DCF Model'!G45/(1+$B11)^('DCF Model'!C19+4)+'DCF Model'!G45*(1+F$6)/($B11-F$6)/(1+$B11)^('DCF Model'!C19+4)-'DCF Model'!C16)*1000000/'DCF Model'!C15,0),"") -> 2753 | G11: =IFERROR(ROUND(('DCF Model'!C45/(1+$B11)^('DCF Model'!C19+0)+'DCF Model'!D45/(1+$B11)^('DCF Model'!C19+1)+'DCF Model'!E45/(1+$B11)^('DCF Model'!C19+2)+'DCF Model'!F45/(1+$B11)^('DCF Model'!C19+3)+'DCF Model'!G45/(1+$B11)^('DCF Model'!C19+4)+'DCF Model'!G45*(1+G$6)/($B11-G$6)/(1+$B11)^('DCF Model'!C19+4)-'DCF Model'!C16)*1000000/'DCF Model'!C15,0),"") -> 2800 | H11: =IFERROR(ROUND(('DCF Model'!C45/(1+$B11)^('DCF Model'!C19+0)+'DCF Model'!D45/(1+$B11)^('DCF Model'!C19+1)+'DCF Model'!E45/(1+$B11)^('DCF Model'!C19+2)+'DCF Model'!F45/(1+$B11)^('DCF Model'!C19+3)+'DCF Model'!G45/(1+$B11)^('DCF Model'!C19+4)+'DCF Model'!G45*(1+H$6)/($B11-H$6)/(1+$B11)^('DCF Model'!C19+4)-'DCF Model'!C16)*1000000/'DCF Model'!C15,0),"") -> 2849 | I11: =IFERROR(ROUND(('DCF Model'!C45/(1+$B11)^('DCF Model'!C19+0)+'DCF Model'!D45/(1+$B11)^('DCF Model'!C19+1)+'DCF Model'!E45/(1+$B11)^('DCF Model'!C19+2)+'DCF Model'!F45/(1+$B11)^('DCF Model'!C19+3)+'DCF Model'!G45/(1+$B11)^('DCF Model'!C19+4)+'DCF Model'!G45*(1+I$6)/($B11-I$6)/(1+$B11)^('DCF Model'!C19+4)-'DCF Model'!C16)*1000000/'DCF Model'!C15,0),"") -> 2900
B12: =$C$3+0.01 -> 0.13187152 | C12: =IFERROR(ROUND(('DCF Model'!C45/(1+$B12)^('DCF Model'!C19+0)+'DCF Model'!D45/(1+$B12)^('DCF Model'!C19+1)+'DCF Model'!E45/(1+$B12)^('DCF Model'!C19+2)+'DCF Model'!F45/(1+$B12)^('DCF Model'!C19+3)+'DCF Model'!G45/(1+$B12)^('DCF Model'!C19+4)+'DCF Model'!G45*(1+C$6)/($B12-C$6)/(1+$B12)^('DCF Model'!C19+4)-'DCF Model'!C16)*1000000/'DCF Model'!C15,0),"") -> 2503 | D12: =IFERROR(ROUND(('DCF Model'!C45/(1+$B12)^('DCF Model'!C19+0)+'DCF Model'!D45/(1+$B12)^('DCF Model'!C19+1)+'DCF Model'!E45/(1+$B12)^('DCF Model'!C19+2)+'DCF Model'!F45/(1+$B12)^('DCF Model'!C19+3)+'DCF Model'!G45/(1+$B12)^('DCF Model'!C19+4)+'DCF Model'!G45*(1+D$6)/($B12-D$6)/(1+$B12)^('DCF Model'!C19+4)-'DCF Model'!C16)*1000000/'DCF Model'!C15,0),"") -> 2540 | E12: =IFERROR(ROUND(('DCF Model'!C45/(1+$B12)^('DCF Model'!C19+0)+'DCF Model'!D45/(1+$B12)^('DCF Model'!C19+1)+'DCF Model'!E45/(1+$B12)^('DCF Model'!C19+2)+'DCF Model'!F45/(1+$B12)^('DCF Model'!C19+3)+'DCF Model'!G45/(1+$B12)^('DCF Model'!C19+4)+'DCF Model'!G45*(1+E$6)/($B12-E$6)/(1+$B12)^('DCF Model'!C19+4)-'DCF Model'!C16)*1000000/'DCF Model'!C15,0),"") -> 2579 | F12: =IFERROR(ROUND(('DCF Model'!C45/(1+$B12)^('DCF Model'!C19+0)+'DCF Model'!D45/(1+$B12)^('DCF Model'!C19+1)+'DCF Model'!E45/(1+$B12)^('DCF Model'!C19+2)+'DCF Model'!F45/(1+$B12)^('DCF Model'!C19+3)+'DCF Model'!G45/(1+$B12)^('DCF Model'!C19+4)+'DCF Model'!G45*(1+F$6)/($B12-F$6)/(1+$B12)^('DCF Model'!C19+4)-'DCF Model'!C16)*1000000/'DCF Model'!C15,0),"") -> 2620 | G12: =IFERROR(ROUND(('DCF Model'!C45/(1+$B12)^('DCF Model'!C19+0)+'DCF Model'!D45/(1+$B12)^('DCF Model'!C19+1)+'DCF Model'!E45/(1+$B12)^('DCF Model'!C19+2)+'DCF Model'!F45/(1+$B12)^('DCF Model'!C19+3)+'DCF Model'!G45/(1+$B12)^('DCF Model'!C19+4)+'DCF Model'!G45*(1+G$6)/($B12-G$6)/(1+$B12)^('DCF Model'!C19+4)-'DCF Model'!C16)*1000000/'DCF Model'!C15,0),"") -> 2662 | H12: =IFERROR(ROUND(('DCF Model'!C45/(1+$B12)^('DCF Model'!C19+0)+'DCF Model'!D45/(1+$B12)^('DCF Model'!C19+1)+'DCF Model'!E45/(1+$B12)^('DCF Model'!C19+2)+'DCF Model'!F45/(1+$B12)^('DCF Model'!C19+3)+'DCF Model'!G45/(1+$B12)^('DCF Model'!C19+4)+'DCF Model'!G45*(1+H$6)/($B12-H$6)/(1+$B12)^('DCF Model'!C19+4)-'DCF Model'!C16)*1000000/'DCF Model'!C15,0),"") -> 2706 | I12: =IFERROR(ROUND(('DCF Model'!C45/(1+$B12)^('DCF Model'!C19+0)+'DCF Model'!D45/(1+$B12)^('DCF Model'!C19+1)+'DCF Model'!E45/(1+$B12)^('DCF Model'!C19+2)+'DCF Model'!F45/(1+$B12)^('DCF Model'!C19+3)+'DCF Model'!G45/(1+$B12)^('DCF Model'!C19+4)+'DCF Model'!G45*(1+I$6)/($B12-I$6)/(1+$B12)^('DCF Model'!C19+4)-'DCF Model'!C16)*1000000/'DCF Model'!C15,0),"") -> 2752
B13: =$C$3+0.015 -> 0.13687152 | C13: =IFERROR(ROUND(('DCF Model'!C45/(1+$B13)^('DCF Model'!C19+0)+'DCF Model'!D45/(1+$B13)^('DCF Model'!C19+1)+'DCF Model'!E45/(1+$B13)^('DCF Model'!C19+2)+'DCF Model'!F45/(1+$B13)^('DCF Model'!C19+3)+'DCF Model'!G45/(1+$B13)^('DCF Model'!C19+4)+'DCF Model'!G45*(1+C$6)/($B13-C$6)/(1+$B13)^('DCF Model'!C19+4)-'DCF Model'!C16)*1000000/'DCF Model'!C15,0),"") -> 2391 | D13: =IFERROR(ROUND(('DCF Model'!C45/(1+$B13)^('DCF Model'!C19+0)+'DCF Model'!D45/(1+$B13)^('DCF Model'!C19+1)+'DCF Model'!E45/(1+$B13)^('DCF Model'!C19+2)+'DCF Model'!F45/(1+$B13)^('DCF Model'!C19+3)+'DCF Model'!G45/(1+$B13)^('DCF Model'!C19+4)+'DCF Model'!G45*(1+D$6)/($B13-D$6)/(1+$B13)^('DCF Model'!C19+4)-'DCF Model'!C16)*1000000/'DCF Model'!C15,0),"") -> 2425 | E13: =IFERROR(ROUND(('DCF Model'!C45/(1+$B13)^('DCF Model'!C19+0)+'DCF Model'!D45/(1+$B13)^('DCF Model'!C19+1)+'DCF Model'!E45/(1+$B13)^('DCF Model'!C19+2)+'DCF Model'!F45/(1+$B13)^('DCF Model'!C19+3)+'DCF Model'!G45/(1+$B13)^('DCF Model'!C19+4)+'DCF Model'!G45*(1+E$6)/($B13-E$6)/(1+$B13)^('DCF Model'!C19+4)-'DCF Model'!C16)*1000000/'DCF Model'!C15,0),"") -> 2461 | F13: =IFERROR(ROUND(('DCF Model'!C45/(1+$B13)^('DCF Model'!C19+0)+'DCF Model'!D45/(1+$B13)^('DCF Model'!C19+1)+'DCF Model'!E45/(1+$B13)^('DCF Model'!C19+2)+'DCF Model'!F45/(1+$B13)^('DCF Model'!C19+3)+'DCF Model'!G45/(1+$B13)^('DCF Model'!C19+4)+'DCF Model'!G45*(1+F$6)/($B13-F$6)/(1+$B13)^('DCF Model'!C19+4)-'DCF Model'!C16)*1000000/'DCF Model'!C15,0),"") -> 2498 | G13: =IFERROR(ROUND(('DCF Model'!C45/(1+$B13)^('DCF Model'!C19+0)+'DCF Model'!D45/(1+$B13)^('DCF Model'!C19+1)+'DCF Model'!E45/(1+$B13)^('DCF Model'!C19+2)+'DCF Model'!F45/(1+$B13)^('DCF Model'!C19+3)+'DCF Model'!G45/(1+$B13)^('DCF Model'!C19+4)+'DCF Model'!G45*(1+G$6)/($B13-G$6)/(1+$B13)^('DCF Model'!C19+4)-'DCF Model'!C16)*1000000/'DCF Model'!C15,0),"") -> 2536 | H13: =IFERROR(ROUND(('DCF Model'!C45/(1+$B13)^('DCF Model'!C19+0)+'DCF Model'!D45/(1+$B13)^('DCF Model'!C19+1)+'DCF Model'!E45/(1+$B13)^('DCF Model'!C19+2)+'DCF Model'!F45/(1+$B13)^('DCF Model'!C19+3)+'DCF Model'!G45/(1+$B13)^('DCF Model'!C19+4)+'DCF Model'!G45*(1+H$6)/($B13-H$6)/(1+$B13)^('DCF Model'!C19+4)-'DCF Model'!C16)*1000000/'DCF Model'!C15,0),"") -> 2576 | I13: =IFERROR(ROUND(('DCF Model'!C45/(1+$B13)^('DCF Model'!C19+0)+'DCF Model'!D45/(1+$B13)^('DCF Model'!C19+1)+'DCF Model'!E45/(1+$B13)^('DCF Model'!C19+2)+'DCF Model'!F45/(1+$B13)^('DCF Model'!C19+3)+'DCF Model'!G45/(1+$B13)^('DCF Model'!C19+4)+'DCF Model'!G45*(1+I$6)/($B13-I$6)/(1+$B13)^('DCF Model'!C19+4)-'DCF Model'!C16)*1000000/'DCF Model'!C15,0),"") -> 2617
B16: Table 2: WACC vs Exit Multiple (Exit Multiple - Implied Share Price, JPY)
B17: WACC \ Exit Multiple | C17: =$I$3-3 -> 2.5 | D17: =$I$3-2 -> 3.5 | E17: =$I$3-1 -> 4.5 | F17: =$I$3 -> 5.5 | G17: =$I$3+1 -> 6.5 | H17: =$I$3+2 -> 7.5 | I17: =$I$3+3 -> 8.5
B18: =$C$3-0.015 -> 0.10687152 | C18: =IFERROR(ROUND(('DCF Model'!C45/(1+$B18)^('DCF Model'!C19+0)+'DCF Model'!D45/(1+$B18)^('DCF Model'!C19+1)+'DCF Model'!E45/(1+$B18)^('DCF Model'!C19+2)+'DCF Model'!F45/(1+$B18)^('DCF Model'!C19+3)+'DCF Model'!G45/(1+$B18)^('DCF Model'!C19+4)+('DCF Model'!G39+'DCF Model'!G42)*C$17/(1+$B18)^('DCF Model'!C19+4)-'DCF Model'!C16)*1000000/'DCF Model'!C15,0),"") -> 1994 | D18: =IFERROR(ROUND(('DCF Model'!C45/(1+$B18)^('DCF Model'!C19+0)+'DCF Model'!D45/(1+$B18)^('DCF Model'!C19+1)+'DCF Model'!E45/(1+$B18)^('DCF Model'!C19+2)+'DCF Model'!F45/(1+$B18)^('DCF Model'!C19+3)+'DCF Model'!G45/(1+$B18)^('DCF Model'!C19+4)+('DCF Model'!G39+'DCF Model'!G42)*D$17/(1+$B18)^('DCF Model'!C19+4)-'DCF Model'!C16)*1000000/'DCF Model'!C15,0),"") -> 2435 | E18: =IFERROR(ROUND(('DCF Model'!C45/(1+$B18)^('DCF Model'!C19+0)+'DCF Model'!D45/(1+$B18)^('DCF Model'!C19+1)+'DCF Model'!E45/(1+$B18)^('DCF Model'!C19+2)+'DCF Model'!F45/(1+$B18)^('DCF Model'!C19+3)+'DCF Model'!G45/(1+$B18)^('DCF Model'!C19+4)+('DCF Model'!G39+'DCF Model'!G42)*E$17/(1+$B18)^('DCF Model'!C19+4)-'DCF Model'!C16)*1000000/'DCF Model'!C15,0),"") -> 2876 | F18: =IFERROR(ROUND(('DCF Model'!C45/(1+$B18)^('DCF Model'!C19+0)+'DCF Model'!D45/(1+$B18)^('DCF Model'!C19+1)+'DCF Model'!E45/(1+$B18)^('DCF Model'!C19+2)+'DCF Model'!F45/(1+$B18)^('DCF Model'!C19+3)+'DCF Model'!G45/(1+$B18)^('DCF Model'!C19+4)+('DCF Model'!G39+'DCF Model'!G42)*F$17/(1+$B18)^('DCF Model'!C19+4)-'DCF Model'!C16)*1000000/'DCF Model'!C15,0),"") -> 3316 | G18: =IFERROR(ROUND(('DCF Model'!C45/(1+$B18)^('DCF Model'!C19+0)+'DCF Model'!D45/(1+$B18)^('DCF Model'!C19+1)+'DCF Model'!E45/(1+$B18)^('DCF Model'!C19+2)+'DCF Model'!F45/(1+$B18)^('DCF Model'!C19+3)+'DCF Model'!G45/(1+$B18)^('DCF Model'!C19+4)+('DCF Model'!G39+'DCF Model'!G42)*G$17/(1+$B18)^('DCF Model'!C19+4)-'DCF Model'!C16)*1000000/'DCF Model'!C15,0),"") -> 3757 | H18: =IFERROR(ROUND(('DCF Model'!C45/(1+$B18)^('DCF Model'!C19+0)+'DCF Model'!D45/(1+$B18)^('DCF Model'!C19+1)+'DCF Model'!E45/(1+$B18)^('DCF Model'!C19+2)+'DCF Model'!F45/(1+$B18)^('DCF Model'!C19+3)+'DCF Model'!G45/(1+$B18)^('DCF Model'!C19+4)+('DCF Model'!G39+'DCF Model'!G42)*H$17/(1+$B18)^('DCF Model'!C19+4)-'DCF Model'!C16)*1000000/'DCF Model'!C15,0),"") -> 4198 | I18: =IFERROR(ROUND(('DCF Model'!C45/(1+$B18)^('DCF Model'!C19+0)+'DCF Model'!D45/(1+$B18)^('DCF Model'!C19+1)+'DCF Model'!E45/(1+$B18)^('DCF Model'!C19+2)+'DCF Model'!F45/(1+$B18)^('DCF Model'!C19+3)+'DCF Model'!G45/(1+$B18)^('DCF Model'!C19+4)+('DCF Model'!G39+'DCF Model'!G42)*I$17/(1+$B18)^('DCF Model'!C19+4)-'DCF Model'!C16)*1000000/'DCF Model'!C15,0),"") -> 4639
B19: =$C$3-0.01 -> 0.11187152 | C19: =IFERROR(ROUND(('DCF Model'!C45/(1+$B19)^('DCF Model'!C19+0)+'DCF Model'!D45/(1+$B19)^('DCF Model'!C19+1)+'DCF Model'!E45/(1+$B19)^('DCF Model'!C19+2)+'DCF Model'!F45/(1+$B19)^('DCF Model'!C19+3)+'DCF Model'!G45/(1+$B19)^('DCF Model'!C19+4)+('DCF Model'!G39+'DCF Model'!G42)*C$17/(1+$B19)^('DCF Model'!C19+4)-'DCF Model'!C16)*1000000/'DCF Model'!C15,0),"") -> 1954 | D19: =IFERROR(ROUND(('DCF Model'!C45/(1+$B19)^('DCF Model'!C19+0)+'DCF Model'!D45/(1+$B19)^('DCF Model'!C19+1)+'DCF Model'!E45/(1+$B19)^('DCF Model'!C19+2)+'DCF Model'!F45/(1+$B19)^('DCF Model'!C19+3)+'DCF Model'!G45/(1+$B19)^('DCF Model'!C19+4)+('DCF Model'!G39+'DCF Model'!G42)*D$17/(1+$B19)^('DCF Model'!C19+4)-'DCF Model'!C16)*1000000/'DCF Model'!C15,0),"") -> 2385 | E19: =IFERROR(ROUND(('DCF Model'!C45/(1+$B19)^('DCF Model'!C19+0)+'DCF Model'!D45/(1+$B19)^('DCF Model'!C19+1)+'DCF Model'!E45/(1+$B19)^('DCF Model'!C19+2)+'DCF Model'!F45/(1+$B19)^('DCF Model'!C19+3)+'DCF Model'!G45/(1+$B19)^('DCF Model'!C19+4)+('DCF Model'!G39+'DCF Model'!G42)*E$17/(1+$B19)^('DCF Model'!C19+4)-'DCF Model'!C16)*1000000/'DCF Model'!C15,0),"") -> 2816 | F19: =IFERROR(ROUND(('DCF Model'!C45/(1+$B19)^('DCF Model'!C19+0)+'DCF Model'!D45/(1+$B19)^('DCF Model'!C19+1)+'DCF Model'!E45/(1+$B19)^('DCF Model'!C19+2)+'DCF Model'!F45/(1+$B19)^('DCF Model'!C19+3)+'DCF Model'!G45/(1+$B19)^('DCF Model'!C19+4)+('DCF Model'!G39+'DCF Model'!G42)*F$17/(1+$B19)^('DCF Model'!C19+4)-'DCF Model'!C16)*1000000/'DCF Model'!C15,0),"") -> 3248 | G19: =IFERROR(ROUND(('DCF Model'!C45/(1+$B19)^('DCF Model'!C19+0)+'DCF Model'!D45/(1+$B19)^('DCF Model'!C19+1)+'DCF Model'!E45/(1+$B19)^('DCF Model'!C19+2)+'DCF Model'!F45/(1+$B19)^('DCF Model'!C19+3)+'DCF Model'!G45/(1+$B19)^('DCF Model'!C19+4)+('DCF Model'!G39+'DCF Model'!G42)*G$17/(1+$B19)^('DCF Model'!C19+4)-'DCF Model'!C16)*1000000/'DCF Model'!C15,0),"") -> 3679 | H19: =IFERROR(ROUND(('DCF Model'!C45/(1+$B19)^('DCF Model'!C19+0)+'DCF Model'!D45/(1+$B19)^('DCF Model'!C19+1)+'DCF Model'!E45/(1+$B19)^('DCF Model'!C19+2)+'DCF Model'!F45/(1+$B19)^('DCF Model'!C19+3)+'DCF Model'!G45/(1+$B19)^('DCF Model'!C19+4)+('DCF Model'!G39+'DCF Model'!G42)*H$17/(1+$B19)^('DCF Model'!C19+4)-'DCF Model'!C16)*1000000/'DCF Model'!C15,0),"") -> 4110 | I19: =IFERROR(ROUND(('DCF Model'!C45/(1+$B19)^('DCF Model'!C19+0)+'DCF Model'!D45/(1+$B19)^('DCF Model'!C19+1)+'DCF Model'!E45/(1+$B19)^('DCF Model'!C19+2)+'DCF Model'!F45/(1+$B19)^('DCF Model'!C19+3)+'DCF Model'!G45/(1+$B19)^('DCF Model'!C19+4)+('DCF Model'!G39+'DCF Model'!G42)*I$17/(1+$B19)^('DCF Model'!C19+4)-'DCF Model'!C16)*1000000/'DCF Model'!C15,0),"") -> 4542
B20: =$C$3-0.005 -> 0.11687152 | C20: =IFERROR(ROUND(('DCF Model'!C45/(1+$B20)^('DCF Model'!C19+0)+'DCF Model'!D45/(1+$B20)^('DCF Model'!C19+1)+'DCF Model'!E45/(1+$B20)^('DCF Model'!C19+2)+'DCF Model'!F45/(1+$B20)^('DCF Model'!C19+3)+'DCF Model'!G45/(1+$B20)^('DCF Model'!C19+4)+('DCF Model'!G39+'DCF Model'!G42)*C$17/(1+$B20)^('DCF Model'!C19+4)-'DCF Model'!C16)*1000000/'DCF Model'!C15,0),"") -> 1915 | D20: =IFERROR(ROUND(('DCF Model'!C45/(1+$B20)^('DCF Model'!C19+0)+'DCF Model'!D45/(1+$B20)^('DCF Model'!C19+1)+'DCF Model'!E45/(1+$B20)^('DCF Model'!C19+2)+'DCF Model'!F45/(1+$B20)^('DCF Model'!C19+3)+'DCF Model'!G45/(1+$B20)^('DCF Model'!C19+4)+('DCF Model'!G39+'DCF Model'!G42)*D$17/(1+$B20)^('DCF Model'!C19+4)-'DCF Model'!C16)*1000000/'DCF Model'!C15,0),"") -> 2337 | E20: =IFERROR(ROUND(('DCF Model'!C45/(1+$B20)^('DCF Model'!C19+0)+'DCF Model'!D45/(1+$B20)^('DCF Model'!C19+1)+'DCF Model'!E45/(1+$B20)^('DCF Model'!C19+2)+'DCF Model'!F45/(1+$B20)^('DCF Model'!C19+3)+'DCF Model'!G45/(1+$B20)^('DCF Model'!C19+4)+('DCF Model'!G39+'DCF Model'!G42)*E$17/(1+$B20)^('DCF Model'!C19+4)-'DCF Model'!C16)*1000000/'DCF Model'!C15,0),"") -> 2759 | F20: =IFERROR(ROUND(('DCF Model'!C45/(1+$B20)^('DCF Model'!C19+0)+'DCF Model'!D45/(1+$B20)^('DCF Model'!C19+1)+'DCF Model'!E45/(1+$B20)^('DCF Model'!C19+2)+'DCF Model'!F45/(1+$B20)^('DCF Model'!C19+3)+'DCF Model'!G45/(1+$B20)^('DCF Model'!C19+4)+('DCF Model'!G39+'DCF Model'!G42)*F$17/(1+$B20)^('DCF Model'!C19+4)-'DCF Model'!C16)*1000000/'DCF Model'!C15,0),"") -> 3181 | G20: =IFERROR(ROUND(('DCF Model'!C45/(1+$B20)^('DCF Model'!C19+0)+'DCF Model'!D45/(1+$B20)^('DCF Model'!C19+1)+'DCF Model'!E45/(1+$B20)^('DCF Model'!C19+2)+'DCF Model'!F45/(1+$B20)^('DCF Model'!C19+3)+'DCF Model'!G45/(1+$B20)^('DCF Model'!C19+4)+('DCF Model'!G39+'DCF Model'!G42)*G$17/(1+$B20)^('DCF Model'!C19+4)-'DCF Model'!C16)*1000000/'DCF Model'!C15,0),"") -> 3603 | H20: =IFERROR(ROUND(('DCF Model'!C45/(1+$B20)^('DCF Model'!C19+0)+'DCF Model'!D45/(1+$B20)^('DCF Model'!C19+1)+'DCF Model'!E45/(1+$B20)^('DCF Model'!C19+2)+'DCF Model'!F45/(1+$B20)^('DCF Model'!C19+3)+'DCF Model'!G45/(1+$B20)^('DCF Model'!C19+4)+('DCF Model'!G39+'DCF Model'!G42)*H$17/(1+$B20)^('DCF Model'!C19+4)-'DCF Model'!C16)*1000000/'DCF Model'!C15,0),"") -> 4024 | I20: =IFERROR(ROUND(('DCF Model'!C45/(1+$B20)^('DCF Model'!C19+0)+'DCF Model'!D45/(1+$B20)^('DCF Model'!C19+1)+'DCF Model'!E45/(1+$B20)^('DCF Model'!C19+2)+'DCF Model'!F45/(1+$B20)^('DCF Model'!C19+3)+'DCF Model'!G45/(1+$B20)^('DCF Model'!C19+4)+('DCF Model'!G39+'DCF Model'!G42)*I$17/(1+$B20)^('DCF Model'!C19+4)-'DCF Model'!C16)*1000000/'DCF Model'!C15,0),"") -> 4446
B21: =$C$3 -> 0.12187152 | C21: =IFERROR(ROUND(('DCF Model'!C45/(1+$B21)^('DCF Model'!C19+0)+'DCF Model'!D45/(1+$B21)^('DCF Model'!C19+1)+'DCF Model'!E45/(1+$B21)^('DCF Model'!C19+2)+'DCF Model'!F45/(1+$B21)^('DCF Model'!C19+3)+'DCF Model'!G45/(1+$B21)^('DCF Model'!C19+4)+('DCF Model'!G39+'DCF Model'!G42)*C$17/(1+$B21)^('DCF Model'!C19+4)-'DCF Model'!C16)*1000000/'DCF Model'!C15,0),"") -> 1877 | D21: =IFERROR(ROUND(('DCF Model'!C45/(1+$B21)^('DCF Model'!C19+0)+'DCF Model'!D45/(1+$B21)^('DCF Model'!C19+1)+'DCF Model'!E45/(1+$B21)^('DCF Model'!C19+2)+'DCF Model'!F45/(1+$B21)^('DCF Model'!C19+3)+'DCF Model'!G45/(1+$B21)^('DCF Model'!C19+4)+('DCF Model'!G39+'DCF Model'!G42)*D$17/(1+$B21)^('DCF Model'!C19+4)-'DCF Model'!C16)*1000000/'DCF Model'!C15,0),"") -> 2290 | E21: =IFERROR(ROUND(('DCF Model'!C45/(1+$B21)^('DCF Model'!C19+0)+'DCF Model'!D45/(1+$B21)^('DCF Model'!C19+1)+'DCF Model'!E45/(1+$B21)^('DCF Model'!C19+2)+'DCF Model'!F45/(1+$B21)^('DCF Model'!C19+3)+'DCF Model'!G45/(1+$B21)^('DCF Model'!C19+4)+('DCF Model'!G39+'DCF Model'!G42)*E$17/(1+$B21)^('DCF Model'!C19+4)-'DCF Model'!C16)*1000000/'DCF Model'!C15,0),"") -> 2703 | F21: =IFERROR(ROUND(('DCF Model'!C45/(1+$B21)^('DCF Model'!C19+0)+'DCF Model'!D45/(1+$B21)^('DCF Model'!C19+1)+'DCF Model'!E45/(1+$B21)^('DCF Model'!C19+2)+'DCF Model'!F45/(1+$B21)^('DCF Model'!C19+3)+'DCF Model'!G45/(1+$B21)^('DCF Model'!C19+4)+('DCF Model'!G39+'DCF Model'!G42)*F$17/(1+$B21)^('DCF Model'!C19+4)-'DCF Model'!C16)*1000000/'DCF Model'!C15,0),"") -> 3115 | G21: =IFERROR(ROUND(('DCF Model'!C45/(1+$B21)^('DCF Model'!C19+0)+'DCF Model'!D45/(1+$B21)^('DCF Model'!C19+1)+'DCF Model'!E45/(1+$B21)^('DCF Model'!C19+2)+'DCF Model'!F45/(1+$B21)^('DCF Model'!C19+3)+'DCF Model'!G45/(1+$B21)^('DCF Model'!C19+4)+('DCF Model'!G39+'DCF Model'!G42)*G$17/(1+$B21)^('DCF Model'!C19+4)-'DCF Model'!C16)*1000000/'DCF Model'!C15,0),"") -> 3528 | H21: =IFERROR(ROUND(('DCF Model'!C45/(1+$B21)^('DCF Model'!C19+0)+'DCF Model'!D45/(1+$B21)^('DCF Model'!C19+1)+'DCF Model'!E45/(1+$B21)^('DCF Model'!C19+2)+'DCF Model'!F45/(1+$B21)^('DCF Model'!C19+3)+'DCF Model'!G45/(1+$B21)^('DCF Model'!C19+4)+('DCF Model'!G39+'DCF Model'!G42)*H$17/(1+$B21)^('DCF Model'!C19+4)-'DCF Model'!C16)*1000000/'DCF Model'!C15,0),"") -> 3941 | I21: =IFERROR(ROUND(('DCF Model'!C45/(1+$B21)^('DCF Model'!C19+0)+'DCF Model'!D45/(1+$B21)^('DCF Model'!C19+1)+'DCF Model'!E45/(1+$B21)^('DCF Model'!C19+2)+'DCF Model'!F45/(1+$B21)^('DCF Model'!C19+3)+'DCF Model'!G45/(1+$B21)^('DCF Model'!C19+4)+('DCF Model'!G39+'DCF Model'!G42)*I$17/(1+$B21)^('DCF Model'!C19+4)-'DCF Model'!C16)*1000000/'DCF Model'!C15,0),"") -> 4353
B22: =$C$3+0.005 -> 0.12687152 | C22: =IFERROR(ROUND(('DCF Model'!C45/(1+$B22)^('DCF Model'!C19+0)+'DCF Model'!D45/(1+$B22)^('DCF Model'!C19+1)+'DCF Model'!E45/(1+$B22)^('DCF Model'!C19+2)+'DCF Model'!F45/(1+$B22)^('DCF Model'!C19+3)+'DCF Model'!G45/(1+$B22)^('DCF Model'!C19+4)+('DCF Model'!G39+'DCF Model'!G42)*C$17/(1+$B22)^('DCF Model'!C19+4)-'DCF Model'!C16)*1000000/'DCF Model'!C15,0),"") -> 1840 | D22: =IFERROR(ROUND(('DCF Model'!C45/(1+$B22)^('DCF Model'!C19+0)+'DCF Model'!D45/(1+$B22)^('DCF Model'!C19+1)+'DCF Model'!E45/(1+$B22)^('DCF Model'!C19+2)+'DCF Model'!F45/(1+$B22)^('DCF Model'!C19+3)+'DCF Model'!G45/(1+$B22)^('DCF Model'!C19+4)+('DCF Model'!G39+'DCF Model'!G42)*D$17/(1+$B22)^('DCF Model'!C19+4)-'DCF Model'!C16)*1000000/'DCF Model'!C15,0),"") -> 2244 | E22: =IFERROR(ROUND(('DCF Model'!C45/(1+$B22)^('DCF Model'!C19+0)+'DCF Model'!D45/(1+$B22)^('DCF Model'!C19+1)+'DCF Model'!E45/(1+$B22)^('DCF Model'!C19+2)+'DCF Model'!F45/(1+$B22)^('DCF Model'!C19+3)+'DCF Model'!G45/(1+$B22)^('DCF Model'!C19+4)+('DCF Model'!G39+'DCF Model'!G42)*E$17/(1+$B22)^('DCF Model'!C19+4)-'DCF Model'!C16)*1000000/'DCF Model'!C15,0),"") -> 2648 | F22: =IFERROR(ROUND(('DCF Model'!C45/(1+$B22)^('DCF Model'!C19+0)+'DCF Model'!D45/(1+$B22)^('DCF Model'!C19+1)+'DCF Model'!E45/(1+$B22)^('DCF Model'!C19+2)+'DCF Model'!F45/(1+$B22)^('DCF Model'!C19+3)+'DCF Model'!G45/(1+$B22)^('DCF Model'!C19+4)+('DCF Model'!G39+'DCF Model'!G42)*F$17/(1+$B22)^('DCF Model'!C19+4)-'DCF Model'!C16)*1000000/'DCF Model'!C15,0),"") -> 3052 | G22: =IFERROR(ROUND(('DCF Model'!C45/(1+$B22)^('DCF Model'!C19+0)+'DCF Model'!D45/(1+$B22)^('DCF Model'!C19+1)+'DCF Model'!E45/(1+$B22)^('DCF Model'!C19+2)+'DCF Model'!F45/(1+$B22)^('DCF Model'!C19+3)+'DCF Model'!G45/(1+$B22)^('DCF Model'!C19+4)+('DCF Model'!G39+'DCF Model'!G42)*G$17/(1+$B22)^('DCF Model'!C19+4)-'DCF Model'!C16)*1000000/'DCF Model'!C15,0),"") -> 3455 | H22: =IFERROR(ROUND(('DCF Model'!C45/(1+$B22)^('DCF Model'!C19+0)+'DCF Model'!D45/(1+$B22)^('DCF Model'!C19+1)+'DCF Model'!E45/(1+$B22)^('DCF Model'!C19+2)+'DCF Model'!F45/(1+$B22)^('DCF Model'!C19+3)+'DCF Model'!G45/(1+$B22)^('DCF Model'!C19+4)+('DCF Model'!G39+'DCF Model'!G42)*H$17/(1+$B22)^('DCF Model'!C19+4)-'DCF Model'!C16)*1000000/'DCF Model'!C15,0),"") -> 3859 | I22: =IFERROR(ROUND(('DCF Model'!C45/(1+$B22)^('DCF Model'!C19+0)+'DCF Model'!D45/(1+$B22)^('DCF Model'!C19+1)+'DCF Model'!E45/(1+$B22)^('DCF Model'!C19+2)+'DCF Model'!F45/(1+$B22)^('DCF Model'!C19+3)+'DCF Model'!G45/(1+$B22)^('DCF Model'!C19+4)+('DCF Model'!G39+'DCF Model'!G42)*I$17/(1+$B22)^('DCF Model'!C19+4)-'DCF Model'!C16)*1000000/'DCF Model'!C15,0),"") -> 4263
B23: =$C$3+0.01 -> 0.13187152 | C23: =IFERROR(ROUND(('DCF Model'!C45/(1+$B23)^('DCF Model'!C19+0)+'DCF Model'!D45/(1+$B23)^('DCF Model'!C19+1)+'DCF Model'!E45/(1+$B23)^('DCF Model'!C19+2)+'DCF Model'!F45/(1+$B23)^('DCF Model'!C19+3)+'DCF Model'!G45/(1+$B23)^('DCF Model'!C19+4)+('DCF Model'!G39+'DCF Model'!G42)*C$17/(1+$B23)^('DCF Model'!C19+4)-'DCF Model'!C16)*1000000/'DCF Model'!C15,0),"") -> 1804 | D23: =IFERROR(ROUND(('DCF Model'!C45/(1+$B23)^('DCF Model'!C19+0)+'DCF Model'!D45/(1+$B23)^('DCF Model'!C19+1)+'DCF Model'!E45/(1+$B23)^('DCF Model'!C19+2)+'DCF Model'!F45/(1+$B23)^('DCF Model'!C19+3)+'DCF Model'!G45/(1+$B23)^('DCF Model'!C19+4)+('DCF Model'!G39+'DCF Model'!G42)*D$17/(1+$B23)^('DCF Model'!C19+4)-'DCF Model'!C16)*1000000/'DCF Model'!C15,0),"") -> 2199 | E23: =IFERROR(ROUND(('DCF Model'!C45/(1+$B23)^('DCF Model'!C19+0)+'DCF Model'!D45/(1+$B23)^('DCF Model'!C19+1)+'DCF Model'!E45/(1+$B23)^('DCF Model'!C19+2)+'DCF Model'!F45/(1+$B23)^('DCF Model'!C19+3)+'DCF Model'!G45/(1+$B23)^('DCF Model'!C19+4)+('DCF Model'!G39+'DCF Model'!G42)*E$17/(1+$B23)^('DCF Model'!C19+4)-'DCF Model'!C16)*1000000/'DCF Model'!C15,0),"") -> 2594 | F23: =IFERROR(ROUND(('DCF Model'!C45/(1+$B23)^('DCF Model'!C19+0)+'DCF Model'!D45/(1+$B23)^('DCF Model'!C19+1)+'DCF Model'!E45/(1+$B23)^('DCF Model'!C19+2)+'DCF Model'!F45/(1+$B23)^('DCF Model'!C19+3)+'DCF Model'!G45/(1+$B23)^('DCF Model'!C19+4)+('DCF Model'!G39+'DCF Model'!G42)*F$17/(1+$B23)^('DCF Model'!C19+4)-'DCF Model'!C16)*1000000/'DCF Model'!C15,0),"") -> 2989 | G23: =IFERROR(ROUND(('DCF Model'!C45/(1+$B23)^('DCF Model'!C19+0)+'DCF Model'!D45/(1+$B23)^('DCF Model'!C19+1)+'DCF Model'!E45/(1+$B23)^('DCF Model'!C19+2)+'DCF Model'!F45/(1+$B23)^('DCF Model'!C19+3)+'DCF Model'!G45/(1+$B23)^('DCF Model'!C19+4)+('DCF Model'!G39+'DCF Model'!G42)*G$17/(1+$B23)^('DCF Model'!C19+4)-'DCF Model'!C16)*1000000/'DCF Model'!C15,0),"") -> 3384 | H23: =IFERROR(ROUND(('DCF Model'!C45/(1+$B23)^('DCF Model'!C19+0)+'DCF Model'!D45/(1+$B23)^('DCF Model'!C19+1)+'DCF Model'!E45/(1+$B23)^('DCF Model'!C19+2)+'DCF Model'!F45/(1+$B23)^('DCF Model'!C19+3)+'DCF Model'!G45/(1+$B23)^('DCF Model'!C19+4)+('DCF Model'!G39+'DCF Model'!G42)*H$17/(1+$B23)^('DCF Model'!C19+4)-'DCF Model'!C16)*1000000/'DCF Model'!C15,0),"") -> 3779 | I23: =IFERROR(ROUND(('DCF Model'!C45/(1+$B23)^('DCF Model'!C19+0)+'DCF Model'!D45/(1+$B23)^('DCF Model'!C19+1)+'DCF Model'!E45/(1+$B23)^('DCF Model'!C19+2)+'DCF Model'!F45/(1+$B23)^('DCF Model'!C19+3)+'DCF Model'!G45/(1+$B23)^('DCF Model'!C19+4)+('DCF Model'!G39+'DCF Model'!G42)*I$17/(1+$B23)^('DCF Model'!C19+4)-'DCF Model'!C16)*1000000/'DCF Model'!C15,0),"") -> 4174
B24: =$C$3+0.015 -> 0.13687152 | C24: =IFERROR(ROUND(('DCF Model'!C45/(1+$B24)^('DCF Model'!C19+0)+'DCF Model'!D45/(1+$B24)^('DCF Model'!C19+1)+'DCF Model'!E45/(1+$B24)^('DCF Model'!C19+2)+'DCF Model'!F45/(1+$B24)^('DCF Model'!C19+3)+'DCF Model'!G45/(1+$B24)^('DCF Model'!C19+4)+('DCF Model'!G39+'DCF Model'!G42)*C$17/(1+$B24)^('DCF Model'!C19+4)-'DCF Model'!C16)*1000000/'DCF Model'!C15,0),"") -> 1769 | D24: =IFERROR(ROUND(('DCF Model'!C45/(1+$B24)^('DCF Model'!C19+0)+'DCF Model'!D45/(1+$B24)^('DCF Model'!C19+1)+'DCF Model'!E45/(1+$B24)^('DCF Model'!C19+2)+'DCF Model'!F45/(1+$B24)^('DCF Model'!C19+3)+'DCF Model'!G45/(1+$B24)^('DCF Model'!C19+4)+('DCF Model'!G39+'DCF Model'!G42)*D$17/(1+$B24)^('DCF Model'!C19+4)-'DCF Model'!C16)*1000000/'DCF Model'!C15,0),"") -> 2155 | E24: =IFERROR(ROUND(('DCF Model'!C45/(1+$B24)^('DCF Model'!C19+0)+'DCF Model'!D45/(1+$B24)^('DCF Model'!C19+1)+'DCF Model'!E45/(1+$B24)^('DCF Model'!C19+2)+'DCF Model'!F45/(1+$B24)^('DCF Model'!C19+3)+'DCF Model'!G45/(1+$B24)^('DCF Model'!C19+4)+('DCF Model'!G39+'DCF Model'!G42)*E$17/(1+$B24)^('DCF Model'!C19+4)-'DCF Model'!C16)*1000000/'DCF Model'!C15,0),"") -> 2542 | F24: =IFERROR(ROUND(('DCF Model'!C45/(1+$B24)^('DCF Model'!C19+0)+'DCF Model'!D45/(1+$B24)^('DCF Model'!C19+1)+'DCF Model'!E45/(1+$B24)^('DCF Model'!C19+2)+'DCF Model'!F45/(1+$B24)^('DCF Model'!C19+3)+'DCF Model'!G45/(1+$B24)^('DCF Model'!C19+4)+('DCF Model'!G39+'DCF Model'!G42)*F$17/(1+$B24)^('DCF Model'!C19+4)-'DCF Model'!C16)*1000000/'DCF Model'!C15,0),"") -> 2929 | G24: =IFERROR(ROUND(('DCF Model'!C45/(1+$B24)^('DCF Model'!C19+0)+'DCF Model'!D45/(1+$B24)^('DCF Model'!C19+1)+'DCF Model'!E45/(1+$B24)^('DCF Model'!C19+2)+'DCF Model'!F45/(1+$B24)^('DCF Model'!C19+3)+'DCF Model'!G45/(1+$B24)^('DCF Model'!C19+4)+('DCF Model'!G39+'DCF Model'!G42)*G$17/(1+$B24)^('DCF Model'!C19+4)-'DCF Model'!C16)*1000000/'DCF Model'!C15,0),"") -> 3315 | H24: =IFERROR(ROUND(('DCF Model'!C45/(1+$B24)^('DCF Model'!C19+0)+'DCF Model'!D45/(1+$B24)^('DCF Model'!C19+1)+'DCF Model'!E45/(1+$B24)^('DCF Model'!C19+2)+'DCF Model'!F45/(1+$B24)^('DCF Model'!C19+3)+'DCF Model'!G45/(1+$B24)^('DCF Model'!C19+4)+('DCF Model'!G39+'DCF Model'!G42)*H$17/(1+$B24)^('DCF Model'!C19+4)-'DCF Model'!C16)*1000000/'DCF Model'!C15,0),"") -> 3702 | I24: =IFERROR(ROUND(('DCF Model'!C45/(1+$B24)^('DCF Model'!C19+0)+'DCF Model'!D45/(1+$B24)^('DCF Model'!C19+1)+'DCF Model'!E45/(1+$B24)^('DCF Model'!C19+2)+'DCF Model'!F45/(1+$B24)^('DCF Model'!C19+3)+'DCF Model'!G45/(1+$B24)^('DCF Model'!C19+4)+('DCF Model'!G39+'DCF Model'!G42)*I$17/(1+$B24)^('DCF Model'!C19+4)-'DCF Model'!C16)*1000000/'DCF Model'!C15,0),"") -> 4088
B26: All values dynamically linked to DCF Model. Headers auto-center on current WACC / Terminal g / Exit Multiple.

Sheet Adjustments Log
B2: Adjustments Log - SANNO
B4: 日付 | C4: セル | D4: 変更内容 | E4: 理由 | F4: 元の値 | G4: 状態
B5: 2026-08-29 | C5: - | D5: Generated by pipeline on 2026-08-29 17:37, template rev 672e3c3 | E5: 初期生成（手修正なし） | F5: - | G5: generated
B6: 2026-08-29 | C6: 全シート(単位) | D6: 原典の決算短信は【千円】表記。本モデルは全て【百万円】に換算済み | E6: 桁事故の温床であるため冒頭に明示する。EDINET有報のXBRLは円単位で取得し、パイプラインが百万円に換算している。プロンプト提供の入力表も百万円換算済みのものを受領した。相互検算: EDINET FY2025/7 売上 10,830,372,000円 = 10,830.372百万円 = プロンプト転記値10,830 と一致。同 営業利益 796,224,000円 = 796.224百万円 = 796 と一致。以下このログの数値は全て百万円。 | F6: - | G6: 確定
B7: 2026-08-29 | C7: DCF Model!C15 / Comps Analysis 株数 | D7: Fully Diluted Shares = 4,241,897株(プロンプト暫定指定の5,000,000株から変更) | E7: 自己株控除後の株数を採用。検算3本が一致する: (1) EDINET FY2025/7有報(S100WWVN) — 発行済総数5,000,000株・自己株式674,400株(持株比率13.49%) → 4,325,600株。同報告書のBPS 1,561.75 × 4,325,600 = 6,755.4百万 = 開示純資産6,755,438千円と完全一致し、BPSの分母が自己株控除後であることを確認。(2) 2026/1末 半期報告書(S100XQSL) — 自己株656,800株・簿価384,926千円(FY2025/7末の674,400株・395,210千円から一部処分)。(3) 現時点 — yfinance sharesOutstanding 4,241,897・BPS 1,941.82 → 8,237.0百万 = 2026/4末純資産8,238百万と一致。したがって2026/4末の自己株は 5,000,000 − 4,241,897 = 758,103株。2026/1末656,800株からの追加取得101,303株に対し自己株簿価は385→585百万(+200百万、平均約1,975円/株)で整合する。■帰結: 時価総額は 4,241,897 × 2,764 = 11,725百万(プロンプト記載13,820百万は自己株控除前)、EV は 12,849百万(プロンプト記載14,755百万)。逆算DCFの答えが約15%変わるため、この訂正はモデルの結論に直結する。 | F7: プロンプト暫定値 5,000,000株 | G7: 確定(プロンプトからの変更)
B8: 2026-08-29 | C8: DCF Model!C16 | D8: Net Debt = 1,124(有利子負債4,699 − 現金及び預金3,575、いずれも2026/4末) | E8: 【設計判断】リース債務189をEVに算入した。内訳: 短期借入3,650 + 1年内返済長期借入346 + 長期借入514 + リース債務189 = 4,699。算入理由は (a) 契約上の有利子負債であること、(b) D&Aに使用権資産の償却が含まれる以上EBITDA基準と整合すること、(c) Comps 5社の Net_Debt も yfinance Total Debt(リース込み) − 現金 + 非支配株主持分 で統一していること。リース除外なら935で、1株価値への影響は約44円(1.4%)に留まり結論を変えない。非支配株主持分はゼロ(自己資本比率57.2% × 総資産14,398 = 8,236 ≒ 純資産8,238)。 | F8: プロンプト指定 935(リース除外) | G8: 設計判断
B9: 2026-08-29 | C9: DCF Model!C17 / C6行 基準年 | D9: Base Year Revenue = 14,365.0(FY2026/7E)。予測Y1は FY2027/7 | E9: 分析日2026-08-29 は FY2027/7期(2026/08/01-2027/07/31)の2ヶ月目であり、FY2026/7期は2026-07-31に既に終了・本決算未発表という状態。したがって基準年は FY2025/7実績(10,830)ではなく FY2026/7E とした。構成: 9ヶ月実績(Q3累計 売上11,050 / 粗利2,678 = 24.23% / 販管費1,096 / 営業利益1,582)+ Q4推定。Q4はプロンプト指定の保守前提『Q3累計÷3 × 0.9』で売上3,315.0。結果 売上14,365.0 / 売上原価10,960.3 / 粗利3,404.7(23.70%) / 販管費1,461.3 / 営業利益1,943.4(13.53%)。 | F9: テンプレ自動値 = 最新FY実績 10,830.4 | G9: 推定(3/4は実績)
B10: 2026-08-29 | C10: DCF Model!C17(Q4前提) | D10: Q4の粗利率は Q3単独実績の21.92% を採用(Q3累計平均の24.23%ではない) | E10: 【重要な発見・設計判断】EDINET半期報告書(S100XQSL)のH1実績(売上6,747.1 / 粗利1,734.8 = 25.71% / 販管費718.1 / 営業利益1,016.7 = 15.07%)をQ3累計から差し引くと、Q3単独(2026/02-04)は 売上4,302.9 / 粗利943.2 = 21.92% / 販管費377.9 / 営業利益565.3 = 13.14%。粗利率は H1 25.71% → Q3単独 21.92% と既に3.8pt低下している。本モデルの分岐軸である『粗利率の持続性』は、Q3累計24.2%という平均値ではなく既に進行中の低下として観測されており、Base の22.5%回帰はこの実測トレンドの延長線上にある。Q4販管費は9ヶ月平均365.3を使用(SGAは固定費性が強く売上に比例させない)。 | F10: Q3累計平均 24.23% を一律適用する案 | G10: 設計判断
B11: 2026-08-29 | C11: DCF Model!C17(前提の偏りの方向) | D11: 基準年の売上前提は保守側に偏っている。Q3単独ペース延長なら FY2026/7E は 売上15,353 / 営業利益2,147 | E11: Q3単独の売上4,302.9 は9ヶ月平均3,683を17%上回っており、Q4を『9ヶ月平均×0.9 = 3,315』と置くプロンプト前提は売上について保守的。Q3単独ペースをそのまま4Q目に延長すると売上15,353(+6.9%)/営業利益2,147(+10.5%)。すなわち本モデルのTargetは下方バイアスを持つ。逆に粗利率は上記のとおり既に低下しており、両者は営業利益ベースでおおむね相殺する(1,943 vs 2,147 で約10%差)。9月中旬の本決算で確定する。 | F11: - | G11: 要確認(9月中旬の本決算で解消)
B12: 2026-08-29 | C12: Financial Statements!F列 (FY2026/7E) | D12: 実績4期のうち第4列 FY2026/7E は実績ではなく推定 | E12: ラベル末尾の E がそれを示す。内訳と根拠: 売上14,365.0・売上原価10,960.3・販管費1,461.3・営業利益1,943.4 は上記の Q3累計+Q4推定。純利益1,750【推定】(Q3累計1,460 + Q4推定290。Q4は税前約371に実効税率20%を仮置き)。D&A 490 と capex 760 は半期実績(240.2 / 368.6)の単純2倍。営業CF 940【推定】はモデル内整合をとった導出値: 純利益1,750 + D&A 490 − ΔNWC 1,301(NWC は FY2025/7末 4,442.2 = 2,534.6+2,330.2−422.6 から FY2026/7E 5,743 = 2,799+3,444−500 へ)= 939。参考: H1実績の営業CFは −222.3(前年同期 +350.8)で、下期に運転資本が落ち着くことを前提にしている。現金3,575 と有利子負債4,699 は2026/4末の実績値をそのまま置いた(FS の Net Debt 行 1,124 が DCF Model!C16 と一致する)。FY2023/7〜FY2025/7 の4系列は全て EDINET有報の実績(docID S100S31C / S100UL67 / S100WWVN)。 | F12: - | G12: 推定
B13: 2026-08-29 | C13: Financial Statements!C列 純利益 | D13: FY2023/7 の当期純利益 = 154.1 をEDINETから補完 | E13: プロンプトの入力表では FY2023/7 の経常利益・当期純利益が未記載(ハイフン)だった。EDINET有報(S100S31C)の実績154,064千円を採用。同様に FY2023/7 の営業CF 1,185.9・capex 954.6・D&A 510.7・現金2,203.2 もEDINETから補完した。 | F13: 空欄 | G13: 確定
B14: 2026-08-29 | C14: DCF Model!C6 | D14: Tax Rate = 25.0% | E14: 【推定・要確認】正常化ブレンド25%。FY2026/7 Q3累計の実効税率は8.1%(法人税等128 / 税金等調整前1,589)にすぎないが、フィリピン優遇税制と繰延税金資産の計上による一時的な軽課で持続性は不明。国内法定実効税率30.6%とフィリピン子会社(FY2025/7 売上構成比29.3%)の優遇税率をブレンドして25%とした。■30.6%適用時の影響: NOPAT係数が 0.750 → 0.694(−7.5%)。予測期FCFのNOPAT部分と、それを通じたPGM/Exitのターミナル価値がほぼ比例して縮むため、Target はおおむね −7〜8%(Base Target 約3,200円 → 約2,950〜2,980円)。判定(現値2,764円に対する上値)は縮むが符号は変わらない。 | F14: テンプレ既定 30% | G14: 推定・要確認
B15: 2026-08-29 | C15: DCF Model!C7 | D15: Risk-Free Rate = 2.90% | E15: 財務省「国債金利情報」jgbcm.csv の10年債 2.897%(基準日 R8.8.27 = 2026-08-27。取得日2026-08-29、当日時点の最新掲載日)。yfinance では日本国債利回りは取得できない(^JP10YB / JP10Y-JP 等いずれも不可)。 | F15: テンプレ既定 2.2% | G15: 確定
... B41: 2026-08-29 | C41: 全シート | D41: 納品状態 = DRAFT | E41: 手順書v2 §6-3 / 標準メモ §2 に従い DRAFT 納品。チャット側での検証 → 手修正の記録 → ユーザー承認を経て FINAL 化する。FINAL 化の際はファイル名を 3441_DCF_Model_<日付>_FINAL.xlsx とし、models/ への保存確認まで行うこと。上記の【推定】【要確認】【未解決】ステータスの項目が本モデルの弱点であり、特に (1) 基準年 FY2026/7E の Q4推定、(2) 税率25%、(3) base_year_ap 500、(4) capex/D&A の予測配列 の4点が Target への感応度が大きい。 | F41: - | G41: DRAFT
B43: Pipeline Metadata (do not edit — read by scripts/validate_output.py)
B44: key | C44: value
B45: auto_log_entries | C45: 1
B46: capex_pct_basis | C46: hist_3yr_avg
B47: capex_pct_c5 | C47: 0.0445
B48: capex_pct_hist3yr | C48: 0.044549
B49: company_name | C49: SANNO
B50: comps_asof | C50: 2026-08-29
B51: comps_da_missing | C51: none
B52: comps_ev_ebitda_invalid | C52: no
B53: comps_ev_ebitda_rows | C53: 6,7,8,9,10
B54: comps_impl_mult_row | C54: 27
B55: comps_impl_per_row | C55: 28
... B83: ticker | C83: 3441.T

Sheet Segment Bridge
B2: Segment Bridge - SANNO (3441)
B3: Reportable segments are geographic: Japan (the Ohta and Chiba plants) and the Philippines (SANNO Philippines Manufacturing Corp., SPMC). All figures JPY mn, from the FY7/25 annual securities report segment note.
B4: The point of this sheet: the FY7/25 profit step-up was a JAPAN event, not a Philippine / weak-yen event. Japan swung from a JPY188mn operating loss to a JPY509mn profit (+697) while the Philippines went the other way, from JPY348mn to JPY243mn (-104). Of the three candidate drivers for the gross-margin step - (1) precious-metal price pass-through and spread, (2) semiconductor / connector volume recovery, (3) the weak yen lifting the Philippine subsidiary - driver (3) is ruled out by this table.
B5: Only two comparable fiscal years are disclosed on this basis, which is why segment data sits here rather than in a `segments` override block (that block would switch the DCF COGS line to a segment-EBIT back-solve on two data points).
B6: This sheet is informational: no cell on the DCF Model sheet references it.
B8: 1. Segment Revenue (JPY mn)
B9: Segment | C9: FY2024/7 | D9: FY2025/7 | E9: Note
B10: Japan 日本 | C10: 5892.4 | D10: 7652.9 | E10: External sales. Inter-segment sales of 6.3 (FY7/24) and 59.1 (FY7/25) are excluded here and appear in the revenue adjustment row.
B11: Philippines フィリピン (SPMC) | C11: 2909.7 | D11: 3177.5 | E11: 29.3% of FY7/25 consolidated revenue. No inter-segment sales disclosed.
B12: Segment total セグメント計 | C12: =SUM(C10:C11) -> 8802.1 | D12: =SUM(D10:D11) -> 10830.4
B13: Adjustment 調整額 (内部売上高消去等) | C13: =8802.1-C12 -> 0 | D13: =10830.4-D12 -> 0 | E13: Derived as (consolidated - segment total). Zero because the segment revenue rows above are already external-customer sales.
B14: Consolidated revenue 連結売上高 | C14: 8802.1 | D14: 10830.4 | E14: Ties to the Financial Statements sheet (FY2024/7, FY2025/7 columns).
B16: 2. Segment Profit to Consolidated Operating Profit (JPY mn)
B17: Segment | C17: FY2024/7 | D17: FY2025/7 | E17: Note
B18: Japan 日本 | C18: -188.2 | D18: 508.9
B19: Philippines フィリピン (SPMC) | C19: 347.7 | D19: 243.3
B20: Segment profit total セグメント利益計 | C20: =SUM(C18:C19) -> 159.5 | D20: =SUM(D18:D19) -> 752.2
B21: Adjustment 調整額 (全社費用・セグメント間消去) | C21: 73.5 | D21: 44
B22: Bridged total 計算値 | C22: =C20+C21 -> 233 | D22: =D20+D21 -> 796.2
B23: Consolidated operating profit 連結営業利益 (開示値) | C23: 233 | D23: 796.2 | E23: Disclosed consolidated operating profit. The adjustment row is the disclosed 調整額, so the bridge closes exactly.
B24: Variance 差異 (計算値 - 開示値) | C24: =C22-C23 -> 0 | D24: =D22-D23 -> 0 | E24: Rounding of the disclosed JPY mn figures. A non-zero variance is shown rather than forced to zero.
B26: 3. Segment Operating Margin
B27: Segment | C27: FY2024/7 | D27: FY2025/7 | E27: Note
B28: Japan 日本 | C28: =IFERROR(C18/C10,"N/A") -> -0.031939447 | D28: =IFERROR(D18/D10,"N/A") -> 0.066497668
B29: Philippines フィリピン (SPMC) | C29: =IFERROR(C19/C11,"N/A") -> 0.11949686 | D29: =IFERROR(D19/D11,"N/A") -> 0.07656963
B30: Consolidated 連結 | C30: =IFERROR(C23/C14,"N/A") -> 0.026470956 | D30: =IFERROR(D23/D14,"N/A") -> 0.07351529
B32: 4. Depreciation & Amortisation by Segment (JPY mn)
B33: Segment | C33: FY2024/7 | D33: FY2025/7 | E33: Note
B34: Japan 日本 | C34: 386.6 | D34: 378.9
B35: Philippines フィリピン (SPMC) | C35: 75.5 | D35: 69.4
B36: Segment D&A total 計 | C36: =SUM(C34:C35) -> 462.1 | D36: =SUM(D34:D35) -> 448.3
B37: Adjustment 調整額 (D&A) | C37: 0 | D37: 0 | E37: The disclosed segment D&A total equals consolidated D&A in both years, so the adjustment is nil.
B38: Bridged total 計算値 | C38: =C36+C37 -> 462.1 | D38: =D36+D37 -> 448.3
B39: Consolidated D&A 連結減価償却費 (開示値) | C39: 462.2 | D39: 448.3 | E39: CF-statement depreciation, disclosed. Equals the segment total in both years.
B40: Variance 差異 (計算値 - 開示値) | C40: =C38-C39 -> -0.1 | D40: =D38-D39 -> 0 | E40: Rounding of the disclosed JPY mn figures. A non-zero variance is shown rather than forced to zero.
B41: Consolidated EBITDA (連結営業利益 + 連結D&A) | C41: =IFERROR(C23+C39,"N/A") -> 695.2 | D41: =IFERROR(D23+D39,"N/A") -> 1244.5 | E41: This is the core_ebitda basis used on 'Comps Analysis'.
B43: 5. Capital Intensity and Headcount by Segment
B44: Item | C44: FY2024/7 | D44: FY2025/7 | E44: Note
B45: Capex 設備投資 - Japan | C45: 177.3 | D45: 629.1 | E45: Segment note 有形固定資産及び無形固定資産の増加額
B46: Capex 設備投資 - Philippines | C46: 26.7 | D46: 209.6 | E46: Philippine capex went from negligible to 209.6
B47: Capex 設備投資 - segment total | C47: 204 | D47: 838.7 | E47: Consolidated per segment note: 204.0 / 784.8; FY7/25 adjustment -53.9
B48: Segment assets 資産 - Japan | C48: 10495 | D48: 11956.1 | E48: Period end
B49: Segment assets 資産 - Philippines | C49: 3416.3 | D49: 2963.8 | E49: Period end; fell despite the weaker yen
B50: Employees 従業員数 - Japan | C50: - | D50: 320 | E50: Plus 12 average temporary workers (FY7/25)
B51: Employees 従業員数 - Philippines | C51: - | D51: 83 | E51: Plus 122 average temporary workers (FY7/25)
B52: FY7/25 capex more than quadrupled in Japan (177 -> 629) in the same year Japan swung to profit. Philippine segment assets FELL (3,416 -> 2,964) even though the cumulative translation adjustment rose from 763 (FY7/25 end) to 996 (Apr-26), which further argues that the weak yen is not what produced the earnings step.
B54: Notes
B55: Segment profit is disclosed segment operating profit; the adjustment row carries corporate costs and inter-segment eliminations and is disclosed, not derived, so the profit bridge closes to zero variance in both years.
B56: Japan segment operating margin: -3.2% (FY7/24) -> +6.6% (FY7/25). Philippine segment operating margin: +11.9% -> +7.7%. The Philippine unit is still the higher-margin business but is no longer the growth engine.
B57: No segment data is disclosed for the FY7/26 interim or third quarter, so the Japan / Philippines split of the 24.2% nine-month gross margin cannot be verified. This is the single most useful disclosure to look for in the mid-September FY7/26 results.
B58: Cumulative translation adjustment 為替換算調整勘定: 763 at FY7/25 end -> 996 at Apr-26 (+233). This flows through other comprehensive income and equity, not through operating profit, and is therefore not part of the margin story on this sheet.
