Workbook

Sheet Cover & Thesis
B2: SOTP Valuation Model
B3: Valuation Date: 2026-08-22
B5: Investment Thesis
B6: 1) The two GPU businesses are not worth the same money. Cloud rental carries a 91% gross margin and generates an estimated JPY18.0bn of FY3/27E EBITDA on JPY25bn of sales, while infrastructure build & resale turns JPY45bn of sales into JPY1.1bn of EBITDA. A single blended multiple hides the fact that roughly 96% of the sum-of-the-parts EV sits in the rental line. 2) The 10% discount applied here is not a conglomerate discount but an execution / funding-risk discount: JPY763mn of cash against JPY6,710mn of construction in progress, growth funded by warrant exercises, and a market that plainly does not believe company guidance (JPY1,840 vs a DCF perpetuity-growth value of JPY3,557). 3) Dilution is the swing factor. On 32,017k shares the SOTP fair value is about JPY4,740; on the treasury-stock-method count of 47,465k shares it falls to about JPY3,197, roughly 32% lower. Any target price on this name has to state which share count it uses.
B10: Valuation Cross-Check
B11: Method | C11: Fair Value (¥) | D11: vs SOTP Base
B12: SOTP (Base Case) | C12: ='SOTP Valuation'!C27 -> 4740.313 | D12: —
B13: DCF - Perpetuity Growth | C13: 3557 | D13: =(C13-$C$12)/$C$12 -> -0.2496276
B14: DCF - Exit Multiple | C14: 5743 | D14: =(C14-$C$12)/$C$12 -> 0.21152338
B15: Comps - EV/EBITDA Median | C15: 1417 | D15: =(C15-$C$12)/$C$12 -> -0.70107459
B16: Comps - PER Median | C16: 3626 | D16: =(C16-$C$12)/$C$12 -> -0.2350716
B18: DCF cross-check as of 2026-08-22 21:10 from 3905_DCF_Model_20260822.xlsx (static snapshot — regenerate after re-running the DCF)
B20: SOTP Scope & Method Note (本SOTPの読み方)
B21: 【本SOTPの位置づけ】開示セグメントは「国内 / 海外」(国内96%)であり、本SOTPは開示セグメントの再掲ではなく、
B22: 事業ライン別の推定分解である。GPUクラウド賃貸(粗利91%)とGPUインフラ構築・物販(粗利19%)を分けて、
B23: 市場がどちらの事業にいくら払っているかを見ることが目的。事業ラインへの売上・営業利益の分解はすべてアナリスト推定であり、
B24: 会社開示ではない。
B25: 【評価年】DCF Base シナリオ Y1 = FY2027/3E。連結 売上 73,931 百万円 / 営業利益 14,786 百万円 と一致させている
B26: (Segment Data シートの Consolidated Total で検算可)。
B27: 【全社費用の扱い】本テンプレートには corporate cost / unallocated セグメントの仕組みが無いため、全社費用 -2,614 百万円は
B28: GPUクラウド賃貸の営業利益から控除して計上している(17,000 → 14,386)。賃貸事業の単体OPMは見かけ上 約10pt 低く出る点に注意。
B29: 【株数】Base 版は期末発行済 32,017 千株。新株予約権を織り込んだ treasury stock method ベース 47,465 千株の版は
B30: 3905_SOTP_20260822_diluted.xlsx を参照(1株価値は約32%低下する)。

Sheet Segment Data
B1: Segment Financial Data
B2: (¥ millions)
B4: Segment | C4: FY2026/3 | D4: FY2027/3E
B5: GPU Cloud Rental (GPUクラウド賃貸)
B6: Revenue | C6: 3000 | D6: 25000
B7: Operating Profit | C7: 1500 | D7: 14386
B8: OPM % | C8: =IF(C6=0,0,C7/C6) -> 0.5 | D8: =IF(D6=0,0,D7/D6) -> 0.57544
B10: GPU Infrastructure Build & Resale (GPUインフラ構築・物販)
B11: Revenue | C11: 28000 | D11: 45000
B12: Operating Profit | C12: 3000 | D12: 900
B13: OPM % | C13: =IF(C11=0,0,C12/C11) -> 0.10714286 | D13: =IF(D11=0,0,D12/D11) -> 0.02
B15: Legacy AI & Data Solutions (旧来事業(AI・データソリューション))
B16: Revenue | C16: 2605 | D16: 3931
B17: Operating Profit | C17: -300 | D17: -500
B18: OPM % | C18: =IF(C16=0,0,C17/C16) -> -0.11516315 | D18: =IF(D16=0,0,D17/D16) -> -0.1271941
B20: Consolidated Total
B21: Total Revenue | C21: =C6+C11+C16 -> 33605 | D21: =D6+D11+D16 -> 73931
B22: Total Operating Profit | C22: =C7+C12+C17 -> 4200 | D22: =D7+D12+D17 -> 14786
B23: Total OPM % | C23: =IF(C21=0,0,C22/C21) -> 0.1249814 | D23: =IF(D21=0,0,D22/D21) -> 0.19999729

Sheet Peer Comps
B1: Peer Comparable Analysis
B3: GPU Cloud Rental
B4: Company | C4: Ticker | D4: EV/EBITDA | E4: OPM % | F4: Mkt Cap ($B) | G4: Note
B5: GMO internet | C5: 4784.T | D5: 13.7379 | E5: 0.10471304 | F5: 1.154 | G5: DCF Comps Analysis の値。ホスティング/クラウド。上場中(JPX)
B6: Internet Initiative Japan | C6: 3774.T | D6: 8.8392 | E6: 0.10085554 | F6: 3.772 | G6: DCF Comps Analysis の値。ネットワーク/クラウド。上場中(JPX)
B7: SAKURA Internet | C7: 3778.T | D7: 22.2664 | E7: -0.011444111 | F7: 0.899 | G7: 除外: 営業赤字(OP -404百万円 / OPM -1.1%)。EV/EBITDA が意味を持たず median を歪めるため
B8: Median | D8: =MEDIAN(D5,D6) -> 11.28855
B9: Selected Multiple | C9: Peer median(GMO 13.7x / さくら 22.3x赤字除外 / IIJ 8.8x)から、規模・資金制約・単一顧客依存で割引。DCF Exit 8.0x との整合も考慮 | D9: 9
B11: GPU Infrastructure Build & Resale
B12: Company | C12: Ticker | D12: EV/EBITDA | E12: OPM % | F12: Mkt Cap ($B) | G12: Note
B13: JBCC Holdings | C13: 9889.T | D13: 11.45 | E13: 0.0962 | F13: 0.673 | G13: yfinance 2026-08-22。FY2026/3実績 OP 7,311 + D&A 588 = EBITDA 7,899。上場中(JPX)
B14: NS Solutions | C14: 2327.T | D14: 10.77 | E14: 0.1159 | F14: 4.451 | G14: yfinance 2026-08-22。FY2026/3実績 OP 44,210 + D&A 13,889 = EBITDA 58,099。上場中(JPX)
B15: BIPROGY | C15: 8056.T | D15: 7.89 | E15: 0.0952 | F15: 2.763 | G15: yfinance 2026-08-22。FY2026/3実績 OP 41,301 + D&A 17,898 = EBITDA 59,199。上場中(JPX)
B16: TIS | C16: 3626.T | D16: 8.36 | E16: 0.1278 | F16: 5.071 | G16: yfinance 2026-08-22。FY2026/3実績 OP 76,229 + D&A 18,686 = EBITDA 94,915。上場中(JPX)
B17: Median | D17: =MEDIAN(D13,D14,D15,D16) -> 9.565
B18: Selected Multiple | C18: ITインフラ構築・再販の Peer median(9.6x)近辺から、一過性・低マージンのため賃貸より低倍率に割引 | D18: 6
B20: Legacy AI & Data Solutions
B21: Company | C21: Ticker | D21: EV/EBITDA | E21: OPM % | F21: Mkt Cap ($B) | G21: Note
B22: PKSHA Technology | C22: 3993.T | D22: 13.06 | E22: 0.2429 | F22: 0.642 | G22: yfinance 2026-08-22。FY2025/9実績 OP 5,289 + D&A 1,987 = EBITDA 7,276。上場中(JPX)
B23: HEROZ | C23: 4382.T | D23: 13.09 | E23: 0.0814 | F23: 0.073 | G23: yfinance 2026-08-22。FY2026/4実績 OP 523 + D&A 448 = EBITDA 971。黒字のため採用。上場中(JPX)
B24: Median | D24: =MEDIAN(D22,D23) -> 13.075
B25: Selected Multiple | C25: EBITDA≒0(-71百万円)のため実質的に価値ゼロ評価。倍率はAIソフト小型 Peer median 13.1x を下回る水準で形式的に置いたもので、EVへの影響は軽微 | D25: 8

Sheet SOTP Valuation
B1: SOTP Valuation
B2: (¥ millions unless noted)
B4: Segment | C4: OP (FY25E) | D4: D&A Alloc % | E4: D&A | F4: EBITDA | G4: Multiple (x) | H4: Segment EV
B5: GPU Cloud Rental | C5: ='Segment Data'!D7 -> 14386 | D5: 0.85 | E5: =B11*D5 -> 3644.8 | F5: =C5+E5 -> 18030.8 | G5: ='Peer Comps'!D9 -> 9 | H5: =F5*G5 -> 162277.2
B6: GPU Infrastructure Build & Resale | C6: ='Segment Data'!D12 -> 900 | D6: 0.05 | E6: =B11*D6 -> 214.4 | F6: =C6+E6 -> 1114.4 | G6: ='Peer Comps'!D18 -> 6 | H6: =F6*G6 -> 6686.4
B7: Legacy AI & Data Solutions | C7: ='Segment Data'!D17 -> -500 | D7: 0.1 | E7: =B11*D7 -> 428.8 | F7: =C7+E7 -> -71.2 | G7: ='Peer Comps'!D25 -> 8 | H7: =F7*G7 -> -569.6
B8: Equity Method Investments | C8: 0 | F8: =C8 -> 0 | G8: 10 | H8: =F8*G8 -> 0
B9: Total Segment EV | H9: =H5+H6+H7+H8 -> 168394
B11: 4288 | C11: ← Consolidated D&A (input)
B13: EV Composition %
B14: GPU Cloud Rental | C14: =H5/H9 -> 0.96367567
B15: GPU Infrastructure Build & Resale | C15: =H6/H9 -> 0.039706878
B16: Legacy AI & Data Solutions | C16: =H7/H9 -> -0.0033825433
B18: Equity Bridge
B19: Total Enterprise Value | C19: =H9 -> 168394
B20: Conglomerate Discount | C20: 0.1
B21: Adjusted EV | C21: =C19*(1-C20) -> 151554.6
B22: Less: Net Debt | C22: -216
B23: Less: Minority Interest | C23: 0
B24: Equity Value | C24: =C21-C22-C23 -> 151770.6
B25: Shares Outstanding (thousands) | C25: 32017
B26: Stock Split Ratio | C26: 1
B27: Fair Value Per Share (post-split) | C27: =C24*1000/C25/C26 -> 4740.313 | D27: Fair Value = Equity Value (¥M) × 1,000 ÷ Shares (千株) ÷ split. 株数は【千株】単位（dcf_comps_template は【株】単位: 桁が3つ違う）

Sheet Sensitivity
B1: Sensitivity Analysis
B3: Table 1: GPU Cloud Rental Multiple × Conglomerate Discount
B4: Fair Value (¥/share, post-split)
B5: Base Assumptions (do not edit)
B6: GPU Cloud Rental OP | C6: ='SOTP Valuation'!C5 -> 14386 | D6: ='SOTP Valuation'!E5 -> 3644.8 | E6: =C6+D6 -> 18030.8 | F6: ='SOTP Valuation'!G5 -> 9
B7: GPU Infrastructure Build & Resale OP | C7: ='SOTP Valuation'!C6 -> 900 | D7: ='SOTP Valuation'!E6 -> 214.4 | E7: =C7+D7 -> 1114.4 | F7: ='SOTP Valuation'!G6 -> 6
B8: Legacy AI & Data Solutions OP | C8: ='SOTP Valuation'!C7 -> -500 | D8: ='SOTP Valuation'!E7 -> 428.8 | E8: =C8+D8 -> -71.2 | F8: ='SOTP Valuation'!G7 -> 8
B9: Equity Method EV | C9: ='SOTP Valuation'!H8 -> 0
B10: Net Debt | C10: ='SOTP Valuation'!C22 -> -216
B11: Minority Interest | C11: ='SOTP Valuation'!C23 -> 0
B12: Shares (thousands) | C12: ='SOTP Valuation'!C25 -> 32017
B13: Split Ratio | C13: ='SOTP Valuation'!C26 -> 1
B15: GPU Cloud Rental EV/EBITDA → | C15: 6 | D15: 8 | E15: 9 | F15: 10 | G15: 12
B16: 0 | C16: =(($E$6*6+E7*F7+E8*F8+C9)*(1-$B16)-$C$10-$C$11)*1000/$C$12/$C$13 -> 3576.7748 | D16: =(($E$6*8+E7*F7+E8*F8+C9)*(1-$B16)-$C$10-$C$11)*1000/$C$12/$C$13 -> 4703.1015 | E16: =(($E$6*9+E7*F7+E8*F8+C9)*(1-$B16)-$C$10-$C$11)*1000/$C$12/$C$13 -> 5266.2648 | F16: =(($E$6*10+E7*F7+E8*F8+C9)*(1-$B16)-$C$10-$C$11)*1000/$C$12/$C$13 -> 5829.4281 | G16: =(($E$6*12+E7*F7+E8*F8+C9)*(1-$B16)-$C$10-$C$11)*1000/$C$12/$C$13 -> 6955.7548
B17: 0.05 | C17: =(($E$6*6+E7*F7+E8*F8+C9)*(1-$B17)-$C$10-$C$11)*1000/$C$12/$C$13 -> 3398.2734 | D17: =(($E$6*8+E7*F7+E8*F8+C9)*(1-$B17)-$C$10-$C$11)*1000/$C$12/$C$13 -> 4468.2837 | E17: =(($E$6*9+E7*F7+E8*F8+C9)*(1-$B17)-$C$10-$C$11)*1000/$C$12/$C$13 -> 5003.2889 | F17: =(($E$6*10+E7*F7+E8*F8+C9)*(1-$B17)-$C$10-$C$11)*1000/$C$12/$C$13 -> 5538.294 | G17: =(($E$6*12+E7*F7+E8*F8+C9)*(1-$B17)-$C$10-$C$11)*1000/$C$12/$C$13 -> 6608.3043
B18: 0.1 | C18: =(($E$6*6+E7*F7+E8*F8+C9)*(1-$B18)-$C$10-$C$11)*1000/$C$12/$C$13 -> 3219.772 | D18: =(($E$6*8+E7*F7+E8*F8+C9)*(1-$B18)-$C$10-$C$11)*1000/$C$12/$C$13 -> 4233.466 | E18: =(($E$6*9+E7*F7+E8*F8+C9)*(1-$B18)-$C$10-$C$11)*1000/$C$12/$C$13 -> 4740.313 | F18: =(($E$6*10+E7*F7+E8*F8+C9)*(1-$B18)-$C$10-$C$11)*1000/$C$12/$C$13 -> 5247.1599 | G18: =(($E$6*12+E7*F7+E8*F8+C9)*(1-$B18)-$C$10-$C$11)*1000/$C$12/$C$13 -> 6260.8539
B19: 0.15 | C19: =(($E$6*6+E7*F7+E8*F8+C9)*(1-$B19)-$C$10-$C$11)*1000/$C$12/$C$13 -> 3041.2706 | D19: =(($E$6*8+E7*F7+E8*F8+C9)*(1-$B19)-$C$10-$C$11)*1000/$C$12/$C$13 -> 3998.6482 | E19: =(($E$6*9+E7*F7+E8*F8+C9)*(1-$B19)-$C$10-$C$11)*1000/$C$12/$C$13 -> 4477.337 | F19: =(($E$6*10+E7*F7+E8*F8+C9)*(1-$B19)-$C$10-$C$11)*1000/$C$12/$C$13 -> 4956.0259 | G19: =(($E$6*12+E7*F7+E8*F8+C9)*(1-$B19)-$C$10-$C$11)*1000/$C$12/$C$13 -> 5913.4035
B20: 0.25 | C20: =(($E$6*6+E7*F7+E8*F8+C9)*(1-$B20)-$C$10-$C$11)*1000/$C$12/$C$13 -> 2684.2677 | D20: =(($E$6*8+E7*F7+E8*F8+C9)*(1-$B20)-$C$10-$C$11)*1000/$C$12/$C$13 -> 3529.0127 | E20: =(($E$6*9+E7*F7+E8*F8+C9)*(1-$B20)-$C$10-$C$11)*1000/$C$12/$C$13 -> 3951.3852 | F20: =(($E$6*10+E7*F7+E8*F8+C9)*(1-$B20)-$C$10-$C$11)*1000/$C$12/$C$13 -> 4373.7577 | G20: =(($E$6*12+E7*F7+E8*F8+C9)*(1-$B20)-$C$10-$C$11)*1000/$C$12/$C$13 -> 5218.5027
B23: Table 2: GPU Infrastructure Build & Resale × Legacy AI & Data Solutions Multiple Sensitivity
B24: Fair Value (¥/share, post-split) — Base discount, base GPU Cloud Rental multiple
B25: GPU Infrastructure Build & Resale ↓ / Legacy AI & Data Solutions → | C25: 4 | D25: 8 | E25: 12
B26: 4 | C26: =(($E$7*$B26+$E$8*C$25+$E$6*$F$6+$C$9)*(1-'SOTP Valuation'!$C$20)-$C$10-$C$11)*1000/$C$12/$C$13 -> 4685.667 | D26: =(($E$7*$B26+$E$8*D$25+$E$6*$F$6+$C$9)*(1-'SOTP Valuation'!$C$20)-$C$10-$C$11)*1000/$C$12/$C$13 -> 4677.6612 | E26: =(($E$7*$B26+$E$8*E$25+$E$6*$F$6+$C$9)*(1-'SOTP Valuation'!$C$20)-$C$10-$C$11)*1000/$C$12/$C$13 -> 4669.6555
B27: 6 | C27: =(($E$7*$B27+$E$8*C$25+$E$6*$F$6+$C$9)*(1-'SOTP Valuation'!$C$20)-$C$10-$C$11)*1000/$C$12/$C$13 -> 4748.3187 | D27: =(($E$7*$B27+$E$8*D$25+$E$6*$F$6+$C$9)*(1-'SOTP Valuation'!$C$20)-$C$10-$C$11)*1000/$C$12/$C$13 -> 4740.313 | E27: =(($E$7*$B27+$E$8*E$25+$E$6*$F$6+$C$9)*(1-'SOTP Valuation'!$C$20)-$C$10-$C$11)*1000/$C$12/$C$13 -> 4732.3072
B28: 8 | C28: =(($E$7*$B28+$E$8*C$25+$E$6*$F$6+$C$9)*(1-'SOTP Valuation'!$C$20)-$C$10-$C$11)*1000/$C$12/$C$13 -> 4810.9704 | D28: =(($E$7*$B28+$E$8*D$25+$E$6*$F$6+$C$9)*(1-'SOTP Valuation'!$C$20)-$C$10-$C$11)*1000/$C$12/$C$13 -> 4802.9647 | E28: =(($E$7*$B28+$E$8*E$25+$E$6*$F$6+$C$9)*(1-'SOTP Valuation'!$C$20)-$C$10-$C$11)*1000/$C$12/$C$13 -> 4794.9589

Sheet D&A Allocation
B1: D&A Allocation Methodology
B3: セグメント別D&Aは非開示。GPU資産(償却3〜5年)が賃貸事業に集中するため、Base Y1のD&A 4,288百万円を
B4: 賃貸85%・構築5%・旧来10%で推定配賦した。
B5: Segment-level D&A is not disclosed; the FY3/27E consolidated D&A of JPY4,288mn is allocated 85 / 5 / 10 to rental / build / legacy on estimated GPU asset concentration.
B7: Consolidated D&A (FY25E) | C7: 4288 | D7: ¥M (input)
B9: Segment | C9: Allocation % | D9: D&A (¥M) | E9: Check
B10: GPU Cloud Rental | C10: 0.85 | D10: =$C$7*C10 -> 3644.8
B11: GPU Infrastructure Build & Resale | C11: 0.05 | D11: =$C$7*C11 -> 214.4
B12: Legacy AI & Data Solutions | C12: 0.1 | D12: =$C$7*C12 -> 428.8
B13: Total | C13: =C10+C11+C12 -> 1 | D13: =D10+D11+D12 -> 4288 | E13: =IF(ABS(C13-1)<0.001,"OK","CHECK") -> OK
B15: Notes:
B16: • FY2026/3 の連結D&A 455百万円はGPU本格稼働前の水準。Y1 の 4,288 はDCF単一値(売上比5.8%)で、実態より過大の可能性(DCF Adjustments Log 未解決2件目を参照)
B17: • 構築・物販は資産を持たないため5%のみ。旧来事業はソフトウェア償却(BS ソフトウエア1,640)分
B18: • 配賦比率は推定。賃貸の配賦を下げると賃貸EBITDAが減り、SOTP Fair Value は下振れする
B19: • Allocation sums to 100% — residual is implicitly in corporate/eliminations

Sheet Adjustments Log
B1: Adjustments Log - 3905 Data Section SOTP
B2: テンプレート生成後に加えた手修正と、モデルに残る前提の記録(手順書 §6-1 / §7)
B4: Date | C4: Sheet | D4: Adjustment | E4: Reason
B5: 2026-08-22 | C5: Cover & Thesis | D5: B20 以降に SOTP のスコープ注記(開示セグメントとの関係 / 評価年 / 全社費用 / 株数)を追記 | E5: テンプレートに冒頭注記用のconfigキーが無いため。分解がアナリスト推定であることを本文に明示する必要があった
B6: 2026-08-22 | C6: Segment Data / SOTP Valuation | D6: 全社費用 -2,614 百万円を GPU Cloud Rental の FY2027/3E 営業利益に集約(17,000 → 14,386) | E6: テンプレートに corporate cost / unallocated 行が無い。3セグメント合計を連結営業利益 14,786 に一致させるため。賃貸事業の単体収益性は約10pt 過小に表示される
B7: 2026-08-22 | C7: SOTP Valuation | D7: minority_interest = 0、net_debt = -216(MI 41 込みのネットキャッシュ) | E7: DCF 'DCF Model'!C16 と同値。MI を別建てにすると二重控除になるため net_debt 側に含めた
B8: 2026-08-22 | C8: Peer Comps | D8: Mkt Cap ($B) 列の表示形式を #,##0 から #,##0.00 に変更 | E8: 小型株(HEROZ $0.07B 等)が整数書式で 0 と表示され誤読を招くため。値そのものは未変更
B9: 2026-08-22 | C9: templates/sotp_template.py | D9: generate_sotp_excel で dcf_crosscheck の 'labels' / 'source_file' を merge するよう修正 | E9: 読取済みの DCF 側ラベルと参照ファイル名が捨てられ、Cover が汎用ラベルと 'from no DCF workbook' を表示していた(テンプレート側のバグ)
B10: 2026-08-22 | C10: (全シート) | D10: Adjustments Log シートを追加 | E10: sotp_template.py は Adjustments Log を自動生成しない。手順書 §6-1 の記録要件を満たすため手動で追加
B13: Unresolved / 前提として残る論点
B14: # | C14: Item | D14: Impact
B15: 1 | C15: D&A 配賦比率 85 / 5 / 10 はアナリスト推定 | D15: セグメント別D&A非開示。賃貸配賦を下げると賃貸EBITDAが縮み Fair Value は下振れする
B16: 2 | C16: 連結D&A 4,288 百万円(売上比5.8%)そのものが過大の可能性 | D16: DCF 側 Adjustments Log 未解決2件目と同根。FY2026/3実績は 455 百万円
B17: 3 | C17: 事業ライン別の売上・営業利益の分解は会社開示ではない | D17: 会社は国内/海外の2セグメントしか開示していない。分解の誤りはそのまま各事業EVの誤りになる
