Workbook

Sheet Executive Summary
B1: DISCLAIMER: This is a sample analysis for demonstration purposes only. It does not constitute investment advice.
B3: 第一三共 (4568.T)
B4: Equity Research Report
B6: Company | C6: 第一三共
B7: Ticker | C7: 4568.T (TSE Prime)
B8: Sector | C8: 医薬品
B9: Current Price | C9: 2794
B10: Target Price (DCF Mid) | C10: =IF(COUNT(C16:C17)=0,"N/A",ROUND(AVERAGE(C16:C17),0)) -> 1618
B11: Recommendation | C11: =IF(NOT(ISNUMBER(C12)),"N/A",IF(C12>0.15,"BUY",IF(C12>0.05,"HOLD","SELL"))) -> SELL
B12: Upside / Downside | C12: =IF(ISNUMBER(C10),(C10-C9)/C9,"N/A") -> -0.42090193
B14: Valuation Summary
B15: Methodology | C15: Implied Value (JPY) | D15: vs Current Price
B16: DCF - Perpetuity Growth | C16: =IF('DCF Model'!C53<'DCF Model'!C16,"INVALID (EV < net debt)",'DCF Model'!C55) -> 1239 | D16: =IF(ISNUMBER(C16),(C16-C9)/C9,"N/A") -> -0.55654975
B17: DCF - Exit Multiple | C17: =IF('DCF Model'!C62<'DCF Model'!C16,"INVALID (EV < net debt)",'DCF Model'!C64) -> 1997 | D17: =IF(ISNUMBER(C17),(C17-C9)/C9,"N/A") -> -0.28525412
B18: Comps - EV/EBITDA Median [参考・Target不算入] | C18: ='Comps Analysis'!C27 -> 1900 | D18: =IF(ISNUMBER(C18),(C18-C9)/C9,"N/A") -> -0.31997137
B19: Comps - PER Median [参考・Target不算入] | C19: ='Comps Analysis'!C28 -> 2069 | D19: =IF(ISNUMBER(C19),(C19-C9)/C9,"N/A") -> -0.25948461
B20: Note: Target Mid は DCF 2法（PGM / Exit）の平均のみ。Comps 2法は [参考] で Target 不算入（EV<ネットデットで株式価値が負になる手法は INVALID として平均から除外）
B21: DCF Valuation Range (PGM - Exit) | C21: =IF(COUNT(C16:C17)=0,"N/A",MIN(C16:C17)&" - "&MAX(C16:C17)) -> 1239 - 1997
B23: Key Investment Thesis
B24: ="Daiichi Sankyo has built an antibody-drug-conjugate franchise around Enhertu and Datroway that has tripled revenue growth relative to the legacy business; the shares trade at "&TEXT('Comps Analysis'!L5,"0.0""x""")&" earnings and "&TEXT('Comps Analysis'!M5,"0.00""x""")&" book." -> Daiichi Sankyo has built an antibody-drug-conjugate franchise around Enhertu and Datroway that has tripled revenue growth relative to the legacy business; the shares trade at 19.6x earnings and 3.06x book.
B25: ="The balance sheet holds net cash despite the capacity build-out, so the "&TEXT('DCF Model'!C26,"0.00%")&" discount rate is the cost of equity with no leverage assumed." -> The balance sheet holds net cash despite the capacity build-out, so the 10.47% discount rate is the cost of equity with no leverage assumed.
B26: ="At "&TEXT(C9,"#,##0")&" the market pays roughly half again the peer median EV/EBITDA; this model deliberately values the terminal year on the peer median, which is why "&TEXT(C10,"#,##0")&" sits "&TEXT(C12,"+0.0%;-0.0%")&" from here." -> At 2,794 the market pays roughly half again the peer median EV/EBITDA; this model deliberately values the terminal year on the peer median, which is why 1,618 sits -42.1% from here.
B28: Key Risks
B29: ="The exit leg uses the peer median rather than the multiple the market awards this company, and that single choice accounts for most of the gap between "&TEXT(C9,"#,##0")&" and "&TEXT(C10,"#,##0")&"." -> The exit leg uses the peer median rather than the multiple the market awards this company, and that single choice accounts for most of the gap between 2,794 and 1,618.
B30: ="The discount rate uses an assumed beta of one because no measured beta is available; every listed Japanese pharmaceutical peer measures far lower, so "&TEXT('DCF Model'!C26,"0.00%")&" is probably too high." -> The discount rate uses an assumed beta of one because no measured beta is available; every listed Japanese pharmaceutical peer measures far lower, so 10.47% is probably too high.
B31: Capital expenditure has run at up to ten percent of revenue against depreciation near three and a half percent, and the base case assumes it tapers — a commitment the filings do not make.

Sheet Financial Statements
B2: 第一三共 - Historical Financials (JPY mn)
C4: FY2023 | D4: FY2024 | E4: FY2025 | F4: FY2026
B5: Income Statement
B6: Revenue | C6: 1278478 | D6: 1601688 | E6: 1886256 | F6: 2123045
B7: COGS | C7: 363525 | D7: 415322 | E7: 415797 | F7: 669045
B8: Gross Profit | C8: =C6-C7 -> 914953 | D8: =D6-D7 -> 1186366 | E8: =E6-E7 -> 1470459 | F8: =F6-F7 -> 1454000
B9: Gross Margin | C9: =C8/C6 -> 0.71565799 | D9: =D8/D6 -> 0.74069731 | E9: =E8/E6 -> 0.77956492 | F9: =F8/F6 -> 0.68486537
B10: SGA | C10: 794371 | D10: 974777 | E10: 1138534 | F10: 1224911
B11: Operating Income | C11: 120582 | D11: 211589 | E11: 331925 | F11: 229089
B12: Net Income | C12: 109188 | D12: 200731 | E12: 295756 | F12: 259874
B13: Operating Margin | C13: =C11/C6 -> 0.094316836 | D13: =D11/D6 -> 0.13210376 | E13: =E11/E6 -> 0.17597028 | F13: =F11/F6 -> 0.10790586
B14: Net Margin | C14: =C12/C6 -> 0.085404676 | D14: =D12/D6 -> 0.12532466 | E14: =E12/E6 -> 0.15679526 | F14: =F12/F6 -> 0.12240626
B15: Revenue Growth (YoY) | C15: n/a | D15: =(D6-C6)/C6 -> 0.25280842 | E15: =(E6-D6)/D6 -> 0.17766756 | F15: =(F6-E6)/E6 -> 0.12553386
B16: Operating Income Growth (YoY) | C16: n/a | D16: =(D11-C11)/C11 -> 0.75473122 | E16: =(E11-D11)/D11 -> 0.56872522 | F16: =(F11-E11)/E11 -> -0.30981698
B18: Cash Flow Statement
B19: Operating Cash Flow | C19: 114514 | D19: 599258 | E19: 53842 | F19: 77655
B20: Capex
B21: Free Cash Flow
B22: FCF Margin
B23: Capex / Revenue
B25: Balance Sheet Highlights
B26: Cash & Deposits | C26: 441921 | D26: 647180 | E26: 639838 | F26: 449807
B27: Total Interest-bearing Debt (short + long) | C27: 143088 | D27: 101713 | E27: 101332 | F27: 300481
B28: Net Debt (Cash) | C28: =C27-C26 -> -298833 | D28: =D27-D26 -> -545467 | E28: =E27-E26 -> -538506 | F28: =F27-F26 -> -149326
B30: Note: OCF / Cash / Debt coverage OCF 4/4, Cash 4/4, Debt 4/4 — blank cells are years with no year-key match in the source data (verify against 決算短信 or set hist_ocf / hist_cash / hist_debt in overrides).

Sheet DCF Model
B2: DCF Valuation Model - 第一三共
B4: Assumptions
B5: Capex / Revenue (fallback) | C5: 0.0378
B6: Effective Tax Rate | C6: 0.25
B7: Risk-Free Rate | C7: 0.0297
B8: Beta | C8: 1
B9: Equity Risk Premium | C9: 0.065
B10: Size Premium | C10: 0.01
B11: After-tax Cost of Debt | C11: 0.01
B12: D/E Ratio | C12: 0
B13: Terminal Growth Rate | C13: 0.01
B14: Exit Multiple (EV/EBITDA) | C14: 10.8
B15: Fully Diluted Shares | C15: 1819653230
B16: Net Debt (JPY mn) | C16: -149326
... B20: LTM Revenue (JPY mn) | C20: 2123045
B22: WACC Calculation
B23: Cost of Equity (Ke) | C23: =C7+C8*C9+C10 -> 0.1047
B24: Weight of Equity | C24: =1/(1+C12) -> 1
B25: Weight of Debt | C25: =C12/(1+C12) -> 0
B26: WACC | C26: =C23*C24+C11*C25 -> 0.1047
B27: Active Scenario | C27: Base | D27: =MATCH(C27,B69:B73,0) -> 1
B28: Projected Free Cash Flow
C29: FY2027(E) | D29: FY2028(E) | E29: FY2029(E) | F29: FY2030(E) | G29: FY2031(E)
B30: Revenue Growth (YoY) | C30: =CHOOSE($D$27,C69,C70,C71,C72,C73) -> 0.08 | D30: =CHOOSE($D$27,D69,D70,D71,D72,D73) -> 0.06 | E30: =CHOOSE($D$27,E69,E70,E71,E72,E73) -> 0.045 | F30: =CHOOSE($D$27,F69,F70,F71,F72,F73) -> 0.035 | G30: =CHOOSE($D$27,G69,G70,G71,G72,G73) -> 0.03
B31: COGS % of Revenue | C31: =CHOOSE($D$27,C76,C77,C78,C79,C80) -> 0.315 | D31: =CHOOSE($D$27,D76,D77,D78,D79,D80) -> 0.315 | E31: =CHOOSE($D$27,E76,E77,E78,E79,E80) -> 0.315 | F31: =CHOOSE($D$27,F76,F77,F78,F79,F80) -> 0.315 | G31: =CHOOSE($D$27,G76,G77,G78,G79,G80) -> 0.315
B32: SGA % of Revenue | C32: =CHOOSE($D$27,C83,C84,C85,C86,C87) -> 0.575 | D32: =CHOOSE($D$27,D83,D84,D85,D86,D87) -> 0.572 | E32: =CHOOSE($D$27,E83,E84,E85,E86,E87) -> 0.569 | F32: =CHOOSE($D$27,F83,F84,F85,F86,F87) -> 0.5665 | G32: =CHOOSE($D$27,G83,G84,G85,G86,G87) -> 0.565
B33: Revenue | C33: =C17*(1+C30) -> 2292888.6 | D33: =C33*(1+D30) -> 2430461.9 | E33: =D33*(1+E30) -> 2539832.7 | F33: =E33*(1+F30) -> 2628726.8 | G33: =F33*(1+G30) -> 2707588.7
B34: COGS | C34: =C33*C31 -> 722259.91 | D34: =D33*D31 -> 765595.5 | E34: =E33*E31 -> 800047.3 | F34: =F33*F31 -> 828048.96 | G34: =G33*G31 -> 852890.43
B35: Gross Profit | C35: =C33-C34 -> 1570628.7 | D35: =D33-D34 -> 1664866.4 | E35: =E33-E34 -> 1739785.4 | F35: =F33-F34 -> 1800677.9 | G35: =G33-G34 -> 1854698.2
B36: Gross Margin | C36: =C35/C33 -> 0.685 | D36: =D35/D33 -> 0.685 | E36: =E35/E33 -> 0.685 | F36: =F35/F33 -> 0.685 | G36: =G35/G33 -> 0.685
B37: SGA Expense | C37: =C33*C32 -> 1318410.9 | D37: =D33*D32 -> 1390224.2 | E37: =E33*E32 -> 1445164.8 | F37: =F33*F32 -> 1489173.8 | G37: =G33*G32 -> 1529787.6
B38: Implied Operating Margin | C38: =(C35-C37)/C33 -> 0.11 | D38: =(D35-D37)/D33 -> 0.113 | E38: =(E35-E37)/E33 -> 0.116 | F38: =(F35-F37)/F33 -> 0.1185 | G38: =(G35-G37)/G33 -> 0.12
B39: Operating Income (EBIT) | C39: =C35-C37 -> 252217.75 | D39: =D35-D37 -> 274642.2 | E39: =E35-E37 -> 294620.59 | F39: =F35-F37 -> 311504.13 | G39: =G35-G37 -> 324910.64
B40: Less: Tax | C40: =MAX(0,C39*C6) -> 63054.437 | D40: =MAX(0,D39*C6) -> 68660.549 | E40: =MAX(0,E39*C6) -> 73655.148 | F40: =MAX(0,F39*C6) -> 77876.033 | G40: =MAX(0,G39*C6) -> 81227.66
B41: NOPAT | C41: =C39-C40 -> 189163.31 | D41: =D39-D40 -> 205981.65 | E41: =E39-E40 -> 220965.45 | F41: =F39-F40 -> 233628.1 | G41: =G39-G40 -> 243682.98
B42: Plus: D&A | C42: =C33*C18 -> 82543.99 | D42: =D33*C18 -> 87496.629 | E42: =E33*C18 -> 91433.977 | F42: =F33*C18 -> 94634.166 | G42: =G33*C18 -> 97473.191
B43: Less: Capex | C43: 145000 | D43: 135000 | E43: 122000 | F43: 110000 | G43: 102400
B44: Change in NWC | C44: ='NWC Schedule'!D19 -> -139785.91 | D44: ='NWC Schedule'!E19 -> 41812.865 | E44: ='NWC Schedule'!F19 -> 33241.228 | F44: ='NWC Schedule'!G19 -> 27017.731 | G44: ='NWC Schedule'!H19 -> 23968.587
B45: Unlevered Free Cash Flow | C45: =C41+C42-C43-C44 -> 266493.21 | D45: =D41+D42-D43-D44 -> 116665.41 | E45: =E41+E42-E43-E44 -> 157158.19 | F45: =F41+F42-F43-F44 -> 191244.53 | G45: =G41+G42-G43-G44 -> 214787.58
B46: Discount Factor | C46: =1/(1+C26)^(C19+0) -> 0.90522314 | D46: =1/(1+C26)^(C19+1) -> 0.81942893 | E46: =1/(1+C26)^(C19+2) -> 0.74176603 | F46: =1/(1+C26)^(C19+3) -> 0.67146377 | G46: =1/(1+C26)^(C19+4) -> 0.60782454
B47: PV of FCF | C47: =C45*C46 -> 241235.82 | D47: =D45*D46 -> 95599.013 | E47: =E45*E46 -> 116574.61 | F47: =F45*F46 -> 128413.78 | G47: =G45*G46 -> 130553.16
B49: Valuation - Perpetuity Growth Method
B50: Sum of PV of FCFs | C50: =SUM(C47:G47) -> 712376.38
B51: Terminal Value (PGM) | C51: =G45*(1+C13)/(C26-C13) -> 2290765.1
B52: PV of Terminal Value | C52: =C51*G46 -> 1392383.3
B53: Enterprise Value | C53: =C50+C52 -> 2104759.6
B54: Equity Value | C54: =C53-C16 -> 2254085.6
B55: Implied Share Price (PGM) | C55: =ROUND(C54*1000000/C15,0) -> 1239
B57: Valuation - Exit Multiple Method
B58: Sum of PV of FCFs | C58: =C50 -> 712376.38
B59: Year 5 EBITDA | C59: =G39+G42 -> 422383.83
B60: Terminal Value (Exit Multiple) | C60: =C59*C14 -> 4561745.4
B61: PV of Terminal Value | C61: =C60*G46 -> 2772740.8
B62: Enterprise Value | C62: =C58+C61 -> 3485117.2
B63: Equity Value | C63: =C62-C16 -> 3634443.2
B64: Implied Share Price (Exit Multiple) | C64: =ROUND(C63*1000000/C15,0) -> 1997
B66: Scenario Input Matrix
C67: Year 1 | D67: Year 2 | E67: Year 3 | F67: Year 4 | G67: Year 5
B68: Revenue Growth (YoY)
B69: Base | C69: 0.08 | D69: 0.06 | E69: 0.045 | F69: 0.035 | G69: 0.03
B70: Upside | C70: 0.1 | D70: 0.08 | E70: 0.06 | F70: 0.045 | G70: 0.04
B71: Management | C71: 0.08 | D71: 0.06 | E71: 0.045 | F71: 0.035 | G71: 0.03
B72: Downside 1 | C72: 0.02 | D72: 0.015 | E72: 0.01 | F72: 0.01 | G72: 0.01
B73: Downside 2 | C73: -0.05 | D73: -0.01 | E73: 0.005 | F73: 0.01 | G73: 0.015
B75: COGS % of Revenue
B76: Base | C76: 0.315 | D76: 0.315 | E76: 0.315 | F76: 0.315 | G76: 0.315
B77: Upside | C77: 0.31 | D77: 0.31 | E77: 0.31 | F77: 0.31 | G77: 0.31
B78: Management | C78: 0.315 | D78: 0.315 | E78: 0.315 | F78: 0.315 | G78: 0.315
B79: Downside 1 | C79: 0.32 | D79: 0.32 | E79: 0.32 | F79: 0.32 | G79: 0.32
B80: Downside 2 | C80: 0.33 | D80: 0.33 | E80: 0.33 | F80: 0.33 | G80: 0.33
B82: SGA % of Revenue
B83: Base | C83: 0.575 | D83: 0.572 | E83: 0.569 | F83: 0.5665 | G83: 0.565
B84: Upside | C84: 0.572 | D84: 0.564 | E84: 0.556 | F84: 0.55 | G84: 0.5469
B85: Management | C85: 0.575 | D85: 0.572 | E85: 0.569 | F85: 0.5665 | G85: 0.565
B86: Downside 1 | C86: 0.573 | D86: 0.574 | E86: 0.575 | F86: 0.5755 | G86: 0.5755
B87: Downside 2 | C87: 0.58 | D87: 0.59 | E87: 0.585 | F87: 0.58 | G87: 0.5757

Sheet Reverse DCF
B2: Reverse DCF - 第一三共 (4568.T)
B3: What is the current share price already assuming? Every value below is a live formula off the other sheets.
B5: Block 0: Market-implied enterprise value (live)
B6: Current Share Price (JPY) | C6: ='Executive Summary'!C9 -> 2794
B7: Fully Diluted Shares | C7: ='DCF Model'!C15 -> 1819653230
B8: Market Capitalisation (JPY mn) | C8: =C6*C7/1000000 -> 5084111.1
B9: Net Debt (JPY mn) | C9: ='DCF Model'!C16 -> -149326
B10: Enterprise Value (JPY mn) | C10: =C8+C9 -> 4934785.1
B11: WACC (w) | C11: ='DCF Model'!C26 -> 0.1047
B12: Terminal Growth (g) | C12: ='DCF Model'!C13 -> 0.01
B13: Effective Tax Rate (t) | C13: ='DCF Model'!C6 -> 0.25
B14: Starting Operating Profit OP0 (FY2026 actual) | C14: 229089
B15: Cycle-peak Operating Profit (FY2025 actual) | C15: 331925
B16: Terminal-year Revenue, active scenario (JPY mn) | C16: ='DCF Model'!G33 -> 2707588.7
B17: Base-case DCF Enterprise Value, PGM (JPY mn) | C17: ='DCF Model'!C53 -> 2104759.6
B18: Cycle-peak Operating Margin (FY2025 actual) | C18: 0.17597028
B19: Gap: market EV less base-case DCF EV (JPY mn) | C19: =C10-C17 -> 2830025.5
B20: Gap per share (JPY) - the part of the price the base case does not explain | C20: =IFERROR(ROUND(C19*1000000/C7,0),"N/A") -> 1555
B22: Block A: Required steady-state operating profit, reached IMMEDIATELY (no ramp)
B23: The lowest bar the price can clear: today's EV read as a perpetuity of one steady-state profit, capex = D&A, no NWC build.
B24: Required steady-state NOPAT (JPY mn) | C24: =C10*(C11-C12) -> 467324.15
B25: Required steady-state Operating Profit (JPY mn) | C25: =IFERROR(C24/(1-C13),"N/A") -> 623098.87
B26: ... as a multiple of the FY2025 peak | C26: =IFERROR(C25/C15,"N/A") -> 1.8772279
B27: ... as a multiple of FY2026 actual | C27: =IFERROR(C25/C14,"N/A") -> 2.7198987
B28: ... implied OPM on terminal-year revenue | C28: =IFERROR(C25/C16,"N/A") -> 0.23013055
B29: ... revenue needed if margins only reach the cycle peak | C29: =IFERROR(C25/C18,"N/A") -> 3540932.4
B32: Block B: Required steady-state operating profit by YEARS-TO-REACH (linear ramp) x WACC
B33: Operating profit ramps linearly from OP0 (C14) to OP* over N years, then grows at g for ever. Column F is the model WACC.
B34: OP* = ( EV/(1-t) - OP0*(A-B) ) / ( B + TVF ). A longer ramp needs a HIGHER steady state, because more years are spent below it.
B36: Years to steady state (N) \ WACC | C36: N | D36: ='DCF Model'!C26-0.02 -> 0.0847 | E36: ='DCF Model'!C26-0.01 -> 0.0947 | F36: ='DCF Model'!C26 -> 0.1047 | G36: ='DCF Model'!C26+0.01 -> 0.1147 | H36: ='DCF Model'!C26+0.02 -> 0.1247
B37: B-1 PV weight on the RAMP from OP0 (A - B)
B38: N = 3 years | C38: 3 | D38: =IFERROR((1-(1+D$36)^(-$C38))/D$36-(1+D$36)/(D$36^2*$C38)*(1-($C38+1)/(1+D$36)^$C38+$C38/(1+D$36)^($C38+1)),"N/A") -> 0.89791767 | E38: =IFERROR((1-(1+E$36)^(-$C38))/E$36-(1+E$36)/(E$36^2*$C38)*(1-($C38+1)/(1+E$36)^$C38+$C38/(1+E$36)^($C38+1)),"N/A") -> 0.8871509 | F38: =IFERROR((1-(1+F$36)^(-$C38))/F$36-(1+F$36)/(F$36^2*$C38)*(1-($C38+1)/(1+F$36)^$C38+$C38/(1+F$36)^($C38+1)),"N/A") -> 0.87662507 | G38: =IFERROR((1-(1+G$36)^(-$C38))/G$36-(1+G$36)/(G$36^2*$C38)*(1-($C38+1)/(1+G$36)^$C38+$C38/(1+G$36)^($C38+1)),"N/A") -> 0.86633245 | H38: =IFERROR((1-(1+H$36)^(-$C38))/H$36-(1+H$36)/(H$36^2*$C38)*(1-($C38+1)/(1+H$36)^$C38+$C38/(1+H$36)^($C38+1)),"N/A") -> 0.85626567
B39: N = 5 years | C39: 5 | D39: =IFERROR((1-(1+D$36)^(-$C39))/D$36-(1+D$36)/(D$36^2*$C39)*(1-($C39+1)/(1+D$36)^$C39+$C39/(1+D$36)^($C39+1)),"N/A") -> 1.705384 | E39: =IFERROR((1-(1+E$36)^(-$C39))/E$36-(1+E$36)/(E$36^2*$C39)*(1-($C39+1)/(1+E$36)^$C39+$C39/(1+E$36)^($C39+1)),"N/A") -> 1.6756542 | F39: =IFERROR((1-(1+F$36)^(-$C39))/F$36-(1+F$36)/(F$36^2*$C39)*(1-($C39+1)/(1+F$36)^$C39+$C39/(1+F$36)^($C39+1)),"N/A") -> 1.646835 | G39: =IFERROR((1-(1+G$36)^(-$C39))/G$36-(1+G$36)/(G$36^2*$C39)*(1-($C39+1)/(1+G$36)^$C39+$C39/(1+G$36)^($C39+1)),"N/A") -> 1.6188883 | H39: =IFERROR((1-(1+H$36)^(-$C39))/H$36-(1+H$36)/(H$36^2*$C39)*(1-($C39+1)/(1+H$36)^$C39+$C39/(1+H$36)^($C39+1)),"N/A") -> 1.5917777
B40: N = 7 years | C40: 7 | D40: =IFERROR((1-(1+D$36)^(-$C40))/D$36-(1+D$36)/(D$36^2*$C40)*(1-($C40+1)/(1+D$36)^$C40+$C40/(1+D$36)^($C40+1)),"N/A") -> 2.432622 | E40: =IFERROR((1-(1+E$36)^(-$C40))/E$36-(1+E$36)/(E$36^2*$C40)*(1-($C40+1)/(1+E$36)^$C40+$C40/(1+E$36)^($C40+1)),"N/A") -> 2.3778135 | F40: =IFERROR((1-(1+F$36)^(-$C40))/F$36-(1+F$36)/(F$36^2*$C40)*(1-($C40+1)/(1+F$36)^$C40+$C40/(1+F$36)^($C40+1)),"N/A") -> 2.325115 | G40: =IFERROR((1-(1+G$36)^(-$C40))/G$36-(1+G$36)/(G$36^2*$C40)*(1-($C40+1)/(1+G$36)^$C40+$C40/(1+G$36)^($C40+1)),"N/A") -> 2.2744177 | H40: =IFERROR((1-(1+H$36)^(-$C40))/H$36-(1+H$36)/(H$36^2*$C40)*(1-($C40+1)/(1+H$36)^$C40+$C40/(1+H$36)^($C40+1)),"N/A") -> 2.2256201
B41: N = 10 years | C41: 10 | D41: =IFERROR((1-(1+D$36)^(-$C41))/D$36-(1+D$36)/(D$36^2*$C41)*(1-($C41+1)/(1+D$36)^$C41+$C41/(1+D$36)^($C41+1)),"N/A") -> 3.3924233 | E41: =IFERROR((1-(1+E$36)^(-$C41))/E$36-(1+E$36)/(E$36^2*$C41)*(1-($C41+1)/(1+E$36)^$C41+$C41/(1+E$36)^($C41+1)),"N/A") -> 3.2921059 | F41: =IFERROR((1-(1+F$36)^(-$C41))/F$36-(1+F$36)/(F$36^2*$C41)*(1-($C41+1)/(1+F$36)^$C41+$C41/(1+F$36)^($C41+1)),"N/A") -> 3.1967641 | G41: =IFERROR((1-(1+G$36)^(-$C41))/G$36-(1+G$36)/(G$36^2*$C41)*(1-($C41+1)/(1+G$36)^$C41+$C41/(1+G$36)^($C41+1)),"N/A") -> 3.1060743 | H41: =IFERROR((1-(1+H$36)^(-$C41))/H$36-(1+H$36)/(H$36^2*$C41)*(1-($C41+1)/(1+H$36)^$C41+$C41/(1+H$36)^($C41+1)),"N/A") -> 3.019738
B42: B-2 PV weight on the STEADY STATE OP* (B + terminal factor)
B43: N = 3 years | C43: 3 | D43: =IFERROR((1+D$36)/(D$36^2*$C43)*(1-($C43+1)/(1+D$36)^$C43+$C43/(1+D$36)^($C43+1))+(1+$C$12)/((D$36-$C$12)*(1+D$36)^$C43),"N/A") -> 12.251769 | E43: =IFERROR((1+E$36)/(E$36^2*$C43)*(1-($C43+1)/(1+E$36)^$C43+$C43/(1+E$36)^($C43+1))+(1+$C$12)/((E$36-$C$12)*(1+E$36)^$C43),"N/A") -> 10.712854 | F43: =IFERROR((1+F$36)/(F$36^2*$C43)*(1-($C43+1)/(1+F$36)^$C43+$C43/(1+F$36)^($C43+1))+(1+$C$12)/((F$36-$C$12)*(1+F$36)^$C43),"N/A") -> 9.5009196 | G43: =IFERROR((1+G$36)/(G$36^2*$C43)*(1-($C43+1)/(1+G$36)^$C43+$C43/(1+G$36)^($C43+1))+(1+$C$12)/((G$36-$C$12)*(1+G$36)^$C43),"N/A") -> 8.5222163 | H43: =IFERROR((1+H$36)/(H$36^2*$C43)*(1-($C43+1)/(1+H$36)^$C43+$C43/(1+H$36)^($C43+1))+(1+$C$12)/((H$36-$C$12)*(1+H$36)^$C43),"N/A") -> 7.7156898
B44: N = 5 years | C44: 5 | D44: =IFERROR((1+D$36)/(D$36^2*$C44)*(1-($C44+1)/(1+D$36)^$C44+$C44/(1+D$36)^($C44+1))+(1+$C$12)/((D$36-$C$12)*(1+D$36)^$C44),"N/A") -> 11.242706 | E44: =IFERROR((1+E$36)/(E$36^2*$C44)*(1-($C44+1)/(1+E$36)^$C44+$C44/(1+E$36)^($C44+1))+(1+$C$12)/((E$36-$C$12)*(1+E$36)^$C44),"N/A") -> 9.7521406 | F44: =IFERROR((1+F$36)/(F$36^2*$C44)*(1-($C44+1)/(1+F$36)^$C44+$C44/(1+F$36)^($C44+1))+(1+$C$12)/((F$36-$C$12)*(1+F$36)^$C44),"N/A") -> 8.5814773 | G44: =IFERROR((1+G$36)/(G$36^2*$C44)*(1-($C44+1)/(1+G$36)^$C44+$C44/(1+G$36)^($C44+1))+(1+$C$12)/((G$36-$C$12)*(1+G$36)^$C44),"N/A") -> 7.6388417 | H44: =IFERROR((1+H$36)/(H$36^2*$C44)*(1-($C44+1)/(1+H$36)^$C44+$C44/(1+H$36)^($C44+1))+(1+$C$12)/((H$36-$C$12)*(1+H$36)^$C44),"N/A") -> 6.86441
B45: N = 7 years | C45: 7 | D45: =IFERROR((1+D$36)/(D$36^2*$C45)*(1-($C45+1)/(1+D$36)^$C45+$C45/(1+D$36)^($C45+1))+(1+$C$12)/((D$36-$C$12)*(1+D$36)^$C45),"N/A") -> 10.344125 | E45: =IFERROR((1+E$36)/(E$36^2*$C45)*(1-($C45+1)/(1+E$36)^$C45+$C45/(1+E$36)^($C45+1))+(1+$C$12)/((E$36-$C$12)*(1+E$36)^$C45),"N/A") -> 8.9062777 | F45: =IFERROR((1+F$36)/(F$36^2*$C45)*(1-($C45+1)/(1+F$36)^$C45+$C45/(1+F$36)^($C45+1))+(1+$C$12)/((F$36-$C$12)*(1+F$36)^$C45),"N/A") -> 7.7809121 | G45: =IFERROR((1+G$36)/(G$36^2*$C45)*(1-($C45+1)/(1+G$36)^$C45+$C45/(1+G$36)^($C45+1))+(1+$C$12)/((G$36-$C$12)*(1+G$36)^$C45),"N/A") -> 6.8780302 | H45: =IFERROR((1+H$36)/(H$36^2*$C45)*(1-($C45+1)/(1+H$36)^$C45+$C45/(1+H$36)^($C45+1))+(1+$C$12)/((H$36-$C$12)*(1+H$36)^$C45),"N/A") -> 6.139048
B46: N = 10 years | C46: 10 | D46: =IFERROR((1+D$36)/(D$36^2*$C46)*(1-($C46+1)/(1+D$36)^$C46+$C46/(1+D$36)^($C46+1))+(1+$C$12)/((D$36-$C$12)*(1+D$36)^$C46),"N/A") -> 9.1742946 | E46: =IFERROR((1+E$36)/(E$36^2*$C46)*(1-($C46+1)/(1+E$36)^$C46+$C46/(1+E$36)^($C46+1))+(1+$C$12)/((E$36-$C$12)*(1+E$36)^$C46),"N/A") -> 7.8197742 | F46: =IFERROR((1+F$36)/(F$36^2*$C46)*(1-($C46+1)/(1+F$36)^$C46+$C46/(1+F$36)^($C46+1))+(1+$C$12)/((F$36-$C$12)*(1+F$36)^$C46),"N/A") -> 6.7659616 | G46: =IFERROR((1+G$36)/(G$36^2*$C46)*(1-($C46+1)/(1+G$36)^$C46+$C46/(1+G$36)^($C46+1))+(1+$C$12)/((G$36-$C$12)*(1+G$36)^$C46),"N/A") -> 5.9256991 | H46: =IFERROR((1+H$36)/(H$36^2*$C46)*(1-($C46+1)/(1+H$36)^$C46+$C46/(1+H$36)^($C46+1))+(1+$C$12)/((H$36-$C$12)*(1+H$36)^$C46),"N/A") -> 5.2423032
B47: B-3 REQUIRED steady-state Operating Profit (JPY mn)
B48: N = 3 years | C48: 3 | D48: =IFERROR(($C$10/(1-$C$13)-$C$14*D38)/D43,"N/A") -> 520252.25 | E48: =IFERROR(($C$10/(1-$C$13)-$C$14*E38)/E43,"N/A") -> 595217.4 | F48: =IFERROR(($C$10/(1-$C$13)-$C$14*F38)/F43,"N/A") -> 671396.94 | G48: =IFERROR(($C$10/(1-$C$13)-$C$14*G38)/G43,"N/A") -> 748777.79 | H48: =IFERROR(($C$10/(1-$C$13)-$C$14*H38)/H43,"N/A") -> 827346.96
B49: N = 5 years | C49: 5 | D49: =IFERROR(($C$10/(1-$C$13)-$C$14*D39)/D44,"N/A") -> 550492.82 | E49: =IFERROR(($C$10/(1-$C$13)-$C$14*E39)/E44,"N/A") -> 635331.24 | F49: =IFERROR(($C$10/(1-$C$13)-$C$14*F39)/F44,"N/A") -> 722770.85 | G49: =IFERROR(($C$10/(1-$C$13)-$C$14*G39)/G44,"N/A") -> 812799.15 | H49: =IFERROR(($C$10/(1-$C$13)-$C$14*H39)/H44,"N/A") -> 905402.61
B50: N = 7 years | C50: 7 | D50: =IFERROR(($C$10/(1-$C$13)-$C$14*D40)/D45,"N/A") -> 582207.43 | E50: =IFERROR(($C$10/(1-$C$13)-$C$14*E40)/E45,"N/A") -> 677609.97 | F50: =IFERROR(($C$10/(1-$C$13)-$C$14*F40)/F45,"N/A") -> 777165.34 | G50: =IFERROR(($C$10/(1-$C$13)-$C$14*G40)/G45,"N/A") -> 880872.75 | H50: =IFERROR(($C$10/(1-$C$13)-$C$14*H40)/H45,"N/A") -> 988727.96
B51: N = 10 years | C51: 10 | D51: =IFERROR(($C$10/(1-$C$13)-$C$14*D41)/D46,"N/A") -> 632478.78 | E51: =IFERROR(($C$10/(1-$C$13)-$C$14*E41)/E46,"N/A") -> 744973.97 | F51: =IFERROR(($C$10/(1-$C$13)-$C$14*F41)/F46,"N/A") -> 864233.41 | G51: =IFERROR(($C$10/(1-$C$13)-$C$14*G41)/G46,"N/A") -> 990287.55 | H51: =IFERROR(($C$10/(1-$C$13)-$C$14*H41)/H46,"N/A") -> 1123156.1
B52: B-4 ... as a multiple of the FY2025 peak operating profit
B53: N = 3 years | C53: 3 | D53: =IFERROR(D48/$C$15,"N/A") -> 1.5673789 | E53: =IFERROR(E48/$C$15,"N/A") -> 1.7932286 | F53: =IFERROR(F48/$C$15,"N/A") -> 2.0227369 | G53: =IFERROR(G48/$C$15,"N/A") -> 2.2558644 | H53: =IFERROR(H48/$C$15,"N/A") -> 2.492572
B54: N = 5 years | C54: 5 | D54: =IFERROR(D49/$C$15,"N/A") -> 1.6584856 | E54: =IFERROR(E49/$C$15,"N/A") -> 1.9140807 | F54: =IFERROR(F49/$C$15,"N/A") -> 2.1775126 | G54: =IFERROR(G49/$C$15,"N/A") -> 2.4487434 | H54: =IFERROR(H49/$C$15,"N/A") -> 2.7277325
B55: N = 7 years | C55: 7 | D55: =IFERROR(D50/$C$15,"N/A") -> 1.7540331 | E55: =IFERROR(E50/$C$15,"N/A") -> 2.0414551 | F55: =IFERROR(F50/$C$15,"N/A") -> 2.3413884 | G55: =IFERROR(G50/$C$15,"N/A") -> 2.6538307 | H55: =IFERROR(H50/$C$15,"N/A") -> 2.9787692
B56: N = 10 years | C56: 10 | D56: =IFERROR(D51/$C$15,"N/A") -> 1.905487 | E56: =IFERROR(E51/$C$15,"N/A") -> 2.2444045 | F56: =IFERROR(F51/$C$15,"N/A") -> 2.6037009 | G56: =IFERROR(G51/$C$15,"N/A") -> 2.9834678 | H56: =IFERROR(H51/$C$15,"N/A") -> 3.3837646
B58: Block C: Decomposing the required profit into revenue x margin (N = 5 years, model WACC)
B59: The revenue the company must run at, for a given steady-state operating margin, to earn the Block B-3 profit.
B60: Required steady-state Operating Profit (N=5, model WACC) | C60: =F49 -> 722770.85
B62: Assumed steady-state OPM | C62: Required Revenue | D62: x base-year revenue
B63: 0.088 | C63: =IFERROR($C$60/B63,"N/A") -> 8213305.2 | D63: =IFERROR(C63/'DCF Model'!C17,"N/A") -> 3.8686439
B64: 0.132 | C64: =IFERROR($C$60/B64,"N/A") -> 5475536.8 | D64: =IFERROR(C64/'DCF Model'!C17,"N/A") -> 2.579096
B65: cycle-peak OPM (FY2025) | C65: =IFERROR($C$60/$C$18,"N/A") -> 4107346.1 | D65: =IFERROR(C65/'DCF Model'!C17,"N/A") -> 1.9346486
B66: 0.22 | C66: =IFERROR($C$60/B66,"N/A") -> 3285322.1 | D66: =IFERROR(C66/'DCF Model'!C17,"N/A") -> 1.5474576
B67: 0.264 | C67: =IFERROR($C$60/B67,"N/A") -> 2737768.4 | D67: =IFERROR(C67/'DCF Model'!C17,"N/A") -> 1.289548
B69: Block D: The same question expressed as multiples
B70: Current EV / latest-FY EBITDA (actual) | C70: =IFERROR(C10/'Comps Analysis'!G5,"N/A") -> 16.097867
B71: Current EV / latest-FY Revenue (actual) | C71: =IFERROR(C10/'Comps Analysis'!F5,"N/A") -> 2.3243903
B72: EV / EBITDA if the Block A profit were already earned | C72: =IFERROR(C10/(C25+'DCF Model'!G42),"N/A") -> 6.848427
B73: EV / EBITDA if the Block B-3 (N=5) profit were already earned | C73: =IFERROR(C10/(C60+'DCF Model'!G42),"N/A") -> 6.0162401
B74: Peer median EV / EBITDA (statistics rows) | C74: =IFERROR('Comps Analysis'!D16,"N/A") -> 10.793408
B75: Rows 3-4 answer: what multiple would today's EV be paying IF the company already earned the profit the price requires?
B77: Block F: The one-line answer
B78: ="At "&TEXT(C6,"#,##0")&" yen the market is paying for a steady-state operating profit of "&TEXT(F49,"#,##0")&" mn JPY - "&TEXT(F54,"0.00")&"x the FY2025 cycle peak of "&TEXT(C15,"#,##0")&" mn - reached in 5 years and sustained for ever, against "&TEXT(C14,"#,##0")&" mn actually earned in FY2026." -> At 2,794 yen the market is paying for a steady-state operating profit of 722,771 mn JPY - 2.18x the FY2025 cycle peak of 331,925 mn - reached in 5 years and sustained for ever, against 229,089 mn actually earned in FY2026.
B79: ="Even with no ramp at all (Block A) the price needs "&TEXT(C25,"#,##0")&" mn, or "&TEXT(C26,"0.00")&"x the peak. The base case supports an EV of only "&TEXT(C17,"#,##0")&" mn, leaving "&TEXT(C20,"#,##0")&" yen per share of the current price unexplained by mid-cycle economics." -> Even with no ramp at all (Block A) the price needs 623,099 mn, or 1.88x the peak. The base case supports an EV of only 2,104,760 mn, leaving 1,555 yen per share of the current price unexplained by mid-cycle economics.

Sheet NWC Schedule
B2: NWC Schedule - 第一三共
B4: Working Capital Drivers (Days) | C4: Base Year | D4: FY2027(E) | E4: FY2028(E) | F4: FY2029(E) | G4: FY2030(E) | H4: FY2031(E)
B5: DSO (Days Sales Outstanding) | C5: =C12/C9*365 -> 127.41978 | D5: =CHOOSE('DCF Model'!$D$27,D25,D26,D27,D28,D29) -> 127 | E5: =CHOOSE('DCF Model'!$D$27,E25,E26,E27,E28,E29) -> 127 | F5: =CHOOSE('DCF Model'!$D$27,F25,F26,F27,F28,F29) -> 127 | G5: =CHOOSE('DCF Model'!$D$27,G25,G26,G27,G28,G29) -> 127 | H5: =CHOOSE('DCF Model'!$D$27,H25,H26,H27,H28,H29) -> 127
B6: DIH (Days Inventory Held) | C6: =C13/C10*365 -> 377.72941 | D6: =CHOOSE('DCF Model'!$D$27,D32,D33,D34,D35,D36) -> 379 | E6: =CHOOSE('DCF Model'!$D$27,E32,E33,E34,E35,E36) -> 379 | F6: =CHOOSE('DCF Model'!$D$27,F32,F33,F34,F35,F36) -> 379 | G6: =CHOOSE('DCF Model'!$D$27,G32,G33,G34,G35,G36) -> 379 | H6: =CHOOSE('DCF Model'!$D$27,H32,H33,H34,H35,H36) -> 379
B7: DPO (Days Payable Outstanding) | C7: =C15/C10*365 -> 325.61702 | D7: =CHOOSE('DCF Model'!$D$27,D39,D40,D41,D42,D43) -> 430 | E7: =CHOOSE('DCF Model'!$D$27,E39,E40,E41,E42,E43) -> 430 | F7: =CHOOSE('DCF Model'!$D$27,F39,F40,F41,F42,F43) -> 430 | G7: =CHOOSE('DCF Model'!$D$27,G39,G40,G41,G42,G43) -> 430 | H7: =CHOOSE('DCF Model'!$D$27,H39,H40,H41,H42,H43) -> 430
B8: P&L Reference (JPY mn)
B9: Revenue | C9: 2123045 | D9: ='DCF Model'!C33 -> 2292888.6 | E9: ='DCF Model'!D33 -> 2430461.9 | F9: ='DCF Model'!E33 -> 2539832.7 | G9: ='DCF Model'!F33 -> 2628726.8 | H9: ='DCF Model'!G33 -> 2707588.7
B10: COGS | C10: 669045 | D10: ='DCF Model'!C34 -> 722259.91 | E10: ='DCF Model'!D34 -> 765595.5 | F10: ='DCF Model'!E34 -> 800047.3 | G10: ='DCF Model'!F34 -> 828048.96 | H10: ='DCF Model'!G34 -> 852890.43
B11: Working Capital Items (JPY mn)
B12: Accounts Receivable | C12: 741145 | D12: =D9*D5/365 -> 797799.6 | E12: =E9*E5/365 -> 845667.57 | F12: =F9*F5/365 -> 883722.61 | G12: =G9*G5/365 -> 914652.9 | H12: =H9*H5/365 -> 942092.49
B13: Inventory | C13: 692378 | D13: =D10*D6/365 -> 749963.03 | E13: =E10*E6/365 -> 794960.81 | F13: =F10*F6/365 -> 830734.05 | G13: =G10*G6/365 -> 859809.74 | H13: =H10*H6/365 -> 885604.03
B14: Current Assets (AR + Inv) | C14: =C12+C13 -> 1433523 | D14: =D12+D13 -> 1547762.6 | E14: =E12+E13 -> 1640628.4 | F14: =F12+F13 -> 1714456.7 | G14: =G12+G13 -> 1774462.6 | H14: =H12+H13 -> 1827696.5
B15: Accounts Payable | C15: 596856 | D15: =D10*D7/365 -> 850881.54 | E15: =E10*E7/365 -> 901934.43 | F15: =F10*F7/365 -> 942521.48 | G15: =G10*G7/365 -> 975509.73 | H15: =H10*H7/365 -> 1004775
B16: Current Liabilities (AP) | C16: =C15 -> 596856 | D16: =D15 -> 850881.54 | E16: =E15 -> 901934.43 | F16: =F15 -> 942521.48 | G16: =G15 -> 975509.73 | H16: =H15 -> 1004775
B17: Net Working Capital (JPY mn)
B18: Net Working Capital | C18: =C14-C16 -> 836667 | D18: =D14-D16 -> 696881.09 | E18: =E14-E16 -> 738693.95 | F18: =F14-F16 -> 771935.18 | G18: =G14-G16 -> 798952.91 | H18: =H14-H16 -> 822921.5
B19: Change in NWC | C19: n/a | D19: =D18-C18 -> -139785.91 | E19: =E18-D18 -> 41812.865 | F19: =F18-E18 -> 33241.228 | G19: =G18-F18 -> 27017.731 | H19: =H18-G18 -> 23968.587
B22: Scenario Input Matrix (Working Capital Days)
D23: FY2027(E) | E23: FY2028(E) | F23: FY2029(E) | G23: FY2030(E) | H23: FY2031(E)
B24: DSO (Days)
B25: Base | D25: 127 | E25: 127 | F25: 127 | G25: 127 | H25: 127
B26: Upside | D26: 122 | E26: 122 | F26: 122 | G26: 122 | H26: 122
B27: Management | D27: 127 | E27: 127 | F27: 127 | G27: 127 | H27: 127
B28: Downside 1 | D28: 133 | E28: 133 | F28: 133 | G28: 133 | H28: 133
B29: Downside 2 | D29: 139 | E29: 139 | F29: 139 | G29: 139 | H29: 139
B31: DIH (Days)
B32: Base | D32: 379 | E32: 379 | F32: 379 | G32: 379 | H32: 379
B33: Upside | D33: 364 | E33: 364 | F33: 364 | G33: 364 | H33: 364
B34: Management | D34: 379 | E34: 379 | F34: 379 | G34: 379 | H34: 379
B35: Downside 1 | D35: 398 | E35: 398 | F35: 398 | G35: 398 | H35: 398
B36: Downside 2 | D36: 417 | E36: 417 | F36: 417 | G36: 417 | H36: 417
B38: DPO (Days)
B39: Base | D39: 430 | E39: 430 | F39: 430 | G39: 430 | H39: 430
B40: Upside | D40: 447 | E40: 447 | F40: 447 | G40: 447 | H40: 447
B41: Management | D41: 430 | E41: 430 | F41: 430 | G41: 430 | H41: 430
B42: Downside 1 | D42: 412 | E42: 412 | F42: 412 | G42: 412 | H42: 412
B43: Downside 2 | D43: 395 | E43: 395 | F43: 395 | G43: 395 | H43: 395

Sheet Comps Analysis
B2: Comparable Company Analysis
B3: Peer prices as of 2026-09-05 (Mkt Cap / EV of peer rows are static CSV values; the subject row is live-linked to Executive Summary)
B4: Company | C4: Ticker | D4: Mkt Cap (JPY mn) | E4: EV (JPY mn) | F4: Revenue (JPY mn) | G4: EBITDA (JPY mn) | H4: Op Income (JPY mn) | I4: Net Income (JPY mn) | J4: EV/EBITDA | K4: EV/Revenue | L4: PER | M4: PBR | N4: Op Margin | O4: ROE | P4: Book Value (JPY mn) | Q4: Note
B5: Daiichi Sankyo Company, Limited | C5: 4568.T | D5: ='Executive Summary'!C9*C23/1000000 -> 5084111.1 | E5: =D5+C24 -> 4934785.1 | F5: 2123045 | G5: 306549 | H5: 229089 | I5: 259874 | J5: =IFERROR(E5/G5,"") -> 16.097867 | K5: =IFERROR(E5/F5,"") -> 2.3243903 | L5: =IFERROR(D5/I5,"") -> 19.563754 | M5: =IFERROR(D5/P5,"") -> 3.0550266 | N5: =IFERROR(H5/F5,"") -> 0.10790586 | O5: =IFERROR(I5/P5,"") -> 0.15615748 | P5: 1664179
B6: Takeda Pharmaceutical Company Limited | C6: 4502.T | D6: 9186111 | E6: 13472895 | F6: 4505720 | G6: 1185578 | H6: 464451 | I6: -152390 | J6: =IFERROR(E6/G6,"") -> 11.363989 | K6: =IFERROR(E6/F6,"") -> 2.9901758 | L6: N/A | M6: =IFERROR(D6/P6,"") -> 1.2364471 | N6: =IFERROR(H6/F6,"") -> 0.10308031 | O6: =IFERROR(I6/P6,"") -> -0.020511637 | P6: 7429441
B7: Astellas Pharma Inc. | C7: 4503.T | D7: 4223444 | E7: 4507791 | F7: 2139245 | G7: 574653 | H7: 380059 | I7: 291535 | J7: =IFERROR(E7/G7,"") -> 7.8443704 | K7: =IFERROR(E7/F7,"") -> 2.1071878 | L7: =IFERROR(D7/I7,"") -> 14.486919 | M7: =IFERROR(D7/P7,"") -> 2.3090992 | N7: =IFERROR(H7/F7,"") -> 0.17766034 | O7: =IFERROR(I7/P7,"") -> 0.15939201 | P7: 1829044
B8: Otsuka Holdings Co., Ltd. | C8: 4578.T | D8: 6320483 | E8: 6013813 | F8: 2468892 | G8: 588273 | H8: 472106 | I8: 363150 | J8: =IFERROR(E8/G8,"") -> 10.222827 | K8: =IFERROR(E8/F8,"") -> 2.4358348 | L8: =IFERROR(D8/I8,"") -> 17.404607 | M8: =IFERROR(D8/P8,"") -> 2.0835997 | N8: =IFERROR(H8/F8,"") -> 0.19122181 | O8: =IFERROR(I8/P8,"") -> 0.11971541 | P8: 3033444
B9: Shionogi & Co., Ltd. | C9: 4507.T | D9: 2476073 | E9: 2449070 | F9: 499677 | G9: 193693 | H9: 166725 | I9: 205159 | J9: =IFERROR(E9/G9,"") -> 12.644081 | K9: =IFERROR(E9/F9,"") -> 4.9013062 | L9: =IFERROR(D9/I9,"") -> 12.069044 | M9: =IFERROR(D9/P9,"") -> 1.469292 | N9: =IFERROR(H9/F9,"") -> 0.33366555 | O9: =IFERROR(I9/P9,"") -> 0.12174055 | P9: 1685215
B14: Statistics
B15: 25th Percentile | D15: =PERCENTILE(J6:J9,0.25) -> 9.6282127 | E15: =PERCENTILE(K6:K9,0.25) -> 2.353673 | F15: =PERCENTILE(L6:L9,0.25) -> 13.277982 | G15: =PERCENTILE(M6:M9,0.25) -> 1.4110808 | H15: =PERCENTILE(N6:N9,0.25) -> 0.15901533 | I15: =PERCENTILE(O6:O9,0.25) -> 0.08465865
B16: Median (50th) | D16: =MEDIAN(J6:J9) -> 10.793408 | E16: =MEDIAN(K6:K9) -> 2.7130053 | F16: =MEDIAN(L6:L9) -> 14.486919 | G16: =MEDIAN(M6:M9) -> 1.7764459 | H16: =MEDIAN(N6:N9) -> 0.18444108 | I16: =MEDIAN(O6:O9) -> 0.12072798
B17: 75th Percentile | D17: =PERCENTILE(J6:J9,0.75) -> 11.684012 | E17: =PERCENTILE(K6:K9,0.75) -> 3.4679584 | F17: =PERCENTILE(L6:L9,0.75) -> 15.945763 | G17: =PERCENTILE(M6:M9,0.75) -> 2.1399746 | H17: =PERCENTILE(N6:N9,0.75) -> 0.22683275 | I17: =PERCENTILE(O6:O9,0.75) -> 0.13115341
B19: Implied Valuation for 第一三共
B20: 第一三共 Financials
B21: EBITDA (JPY mn) | C21: 306549
B22: Net Income (JPY mn) | C22: 259874
B23: Shares Outstanding | C23: 1819653230
B24: Net Debt (JPY mn) | C24: -149326
B26: Implied Share Price (Median Multiples)
B27: Via EV/EBITDA (Median) | C27: =ROUND((C21*D16-C24)*1000000/C23,0) -> 1900
B28: Via PER (Median) | C28: =ROUND(C22*F16*1000000/C23,0) -> 2069

Sheet Sensitivity Analysis
B2: Sensitivity Analysis
B3: Current WACC: | C3: ='DCF Model'!C26 -> 0.1047 | E3: Terminal g: | F3: ='DCF Model'!C13 -> 0.01 | H3: Exit Multiple: | I3: ='DCF Model'!C14 -> 10.8
B5: Table 1: WACC vs Terminal Growth Rate (PGM - Implied Share Price, JPY)
B6: WACC \ Terminal g | C6: =$F$3-0.0075 -> 0.0025 | D6: =$F$3-0.005 -> 0.005 | E6: =$F$3-0.0025 -> 0.0075 | F6: =$F$3 -> 0.01 | G6: =$F$3+0.0025 -> 0.0125 | H6: =$F$3+0.005 -> 0.015 | I6: =$F$3+0.0075 -> 0.0175
B7: =$C$3-0.015 -> 0.0897 | C7: =IFERROR(ROUND(('DCF Model'!C45/(1+$B7)^('DCF Model'!C19+0)+'DCF Model'!D45/(1+$B7)^('DCF Model'!C19+1)+'DCF Model'!E45/(1+$B7)^('DCF Model'!C19+2)+'DCF Model'!F45/(1+$B7)^('DCF Model'!C19+3)+'DCF Model'!G45/(1+$B7)^('DCF Model'!C19+4)+'DCF Model'!G45*(1+C$6)/($B7-C$6)/(1+$B7)^('DCF Model'!C19+4)-'DCF Model'!C16)*1000000/'DCF Model'!C15,0),"") -> 1372 | D7: =IFERROR(ROUND(('DCF Model'!C45/(1+$B7)^('DCF Model'!C19+0)+'DCF Model'!D45/(1+$B7)^('DCF Model'!C19+1)+'DCF Model'!E45/(1+$B7)^('DCF Model'!C19+2)+'DCF Model'!F45/(1+$B7)^('DCF Model'!C19+3)+'DCF Model'!G45/(1+$B7)^('DCF Model'!C19+4)+'DCF Model'!G45*(1+D$6)/($B7-D$6)/(1+$B7)^('DCF Model'!C19+4)-'DCF Model'!C16)*1000000/'DCF Model'!C15,0),"") -> 1400 | E7: =IFERROR(ROUND(('DCF Model'!C45/(1+$B7)^('DCF Model'!C19+0)+'DCF Model'!D45/(1+$B7)^('DCF Model'!C19+1)+'DCF Model'!E45/(1+$B7)^('DCF Model'!C19+2)+'DCF Model'!F45/(1+$B7)^('DCF Model'!C19+3)+'DCF Model'!G45/(1+$B7)^('DCF Model'!C19+4)+'DCF Model'!G45*(1+E$6)/($B7-E$6)/(1+$B7)^('DCF Model'!C19+4)-'DCF Model'!C16)*1000000/'DCF Model'!C15,0),"") -> 1430 | F7: =IFERROR(ROUND(('DCF Model'!C45/(1+$B7)^('DCF Model'!C19+0)+'DCF Model'!D45/(1+$B7)^('DCF Model'!C19+1)+'DCF Model'!E45/(1+$B7)^('DCF Model'!C19+2)+'DCF Model'!F45/(1+$B7)^('DCF Model'!C19+3)+'DCF Model'!G45/(1+$B7)^('DCF Model'!C19+4)+'DCF Model'!G45*(1+F$6)/($B7-F$6)/(1+$B7)^('DCF Model'!C19+4)-'DCF Model'!C16)*1000000/'DCF Model'!C15,0),"") -> 1462 | G7: =IFERROR(ROUND(('DCF Model'!C45/(1+$B7)^('DCF Model'!C19+0)+'DCF Model'!D45/(1+$B7)^('DCF Model'!C19+1)+'DCF Model'!E45/(1+$B7)^('DCF Model'!C19+2)+'DCF Model'!F45/(1+$B7)^('DCF Model'!C19+3)+'DCF Model'!G45/(1+$B7)^('DCF Model'!C19+4)+'DCF Model'!G45*(1+G$6)/($B7-G$6)/(1+$B7)^('DCF Model'!C19+4)-'DCF Model'!C16)*1000000/'DCF Model'!C15,0),"") -> 1496 | H7: =IFERROR(ROUND(('DCF Model'!C45/(1+$B7)^('DCF Model'!C19+0)+'DCF Model'!D45/(1+$B7)^('DCF Model'!C19+1)+'DCF Model'!E45/(1+$B7)^('DCF Model'!C19+2)+'DCF Model'!F45/(1+$B7)^('DCF Model'!C19+3)+'DCF Model'!G45/(1+$B7)^('DCF Model'!C19+4)+'DCF Model'!G45*(1+H$6)/($B7-H$6)/(1+$B7)^('DCF Model'!C19+4)-'DCF Model'!C16)*1000000/'DCF Model'!C15,0),"") -> 1532 | I7: =IFERROR(ROUND(('DCF Model'!C45/(1+$B7)^('DCF Model'!C19+0)+'DCF Model'!D45/(1+$B7)^('DCF Model'!C19+1)+'DCF Model'!E45/(1+$B7)^('DCF Model'!C19+2)+'DCF Model'!F45/(1+$B7)^('DCF Model'!C19+3)+'DCF Model'!G45/(1+$B7)^('DCF Model'!C19+4)+'DCF Model'!G45*(1+I$6)/($B7-I$6)/(1+$B7)^('DCF Model'!C19+4)-'DCF Model'!C16)*1000000/'DCF Model'!C15,0),"") -> 1571
B8: =$C$3-0.01 -> 0.0947 | C8: =IFERROR(ROUND(('DCF Model'!C45/(1+$B8)^('DCF Model'!C19+0)+'DCF Model'!D45/(1+$B8)^('DCF Model'!C19+1)+'DCF Model'!E45/(1+$B8)^('DCF Model'!C19+2)+'DCF Model'!F45/(1+$B8)^('DCF Model'!C19+3)+'DCF Model'!G45/(1+$B8)^('DCF Model'!C19+4)+'DCF Model'!G45*(1+C$6)/($B8-C$6)/(1+$B8)^('DCF Model'!C19+4)-'DCF Model'!C16)*1000000/'DCF Model'!C15,0),"") -> 1300 | D8: =IFERROR(ROUND(('DCF Model'!C45/(1+$B8)^('DCF Model'!C19+0)+'DCF Model'!D45/(1+$B8)^('DCF Model'!C19+1)+'DCF Model'!E45/(1+$B8)^('DCF Model'!C19+2)+'DCF Model'!F45/(1+$B8)^('DCF Model'!C19+3)+'DCF Model'!G45/(1+$B8)^('DCF Model'!C19+4)+'DCF Model'!G45*(1+D$6)/($B8-D$6)/(1+$B8)^('DCF Model'!C19+4)-'DCF Model'!C16)*1000000/'DCF Model'!C15,0),"") -> 1325 | E8: =IFERROR(ROUND(('DCF Model'!C45/(1+$B8)^('DCF Model'!C19+0)+'DCF Model'!D45/(1+$B8)^('DCF Model'!C19+1)+'DCF Model'!E45/(1+$B8)^('DCF Model'!C19+2)+'DCF Model'!F45/(1+$B8)^('DCF Model'!C19+3)+'DCF Model'!G45/(1+$B8)^('DCF Model'!C19+4)+'DCF Model'!G45*(1+E$6)/($B8-E$6)/(1+$B8)^('DCF Model'!C19+4)-'DCF Model'!C16)*1000000/'DCF Model'!C15,0),"") -> 1351 | F8: =IFERROR(ROUND(('DCF Model'!C45/(1+$B8)^('DCF Model'!C19+0)+'DCF Model'!D45/(1+$B8)^('DCF Model'!C19+1)+'DCF Model'!E45/(1+$B8)^('DCF Model'!C19+2)+'DCF Model'!F45/(1+$B8)^('DCF Model'!C19+3)+'DCF Model'!G45/(1+$B8)^('DCF Model'!C19+4)+'DCF Model'!G45*(1+F$6)/($B8-F$6)/(1+$B8)^('DCF Model'!C19+4)-'DCF Model'!C16)*1000000/'DCF Model'!C15,0),"") -> 1379 | G8: =IFERROR(ROUND(('DCF Model'!C45/(1+$B8)^('DCF Model'!C19+0)+'DCF Model'!D45/(1+$B8)^('DCF Model'!C19+1)+'DCF Model'!E45/(1+$B8)^('DCF Model'!C19+2)+'DCF Model'!F45/(1+$B8)^('DCF Model'!C19+3)+'DCF Model'!G45/(1+$B8)^('DCF Model'!C19+4)+'DCF Model'!G45*(1+G$6)/($B8-G$6)/(1+$B8)^('DCF Model'!C19+4)-'DCF Model'!C16)*1000000/'DCF Model'!C15,0),"") -> 1408 | H8: =IFERROR(ROUND(('DCF Model'!C45/(1+$B8)^('DCF Model'!C19+0)+'DCF Model'!D45/(1+$B8)^('DCF Model'!C19+1)+'DCF Model'!E45/(1+$B8)^('DCF Model'!C19+2)+'DCF Model'!F45/(1+$B8)^('DCF Model'!C19+3)+'DCF Model'!G45/(1+$B8)^('DCF Model'!C19+4)+'DCF Model'!G45*(1+H$6)/($B8-H$6)/(1+$B8)^('DCF Model'!C19+4)-'DCF Model'!C16)*1000000/'DCF Model'!C15,0),"") -> 1440 | I8: =IFERROR(ROUND(('DCF Model'!C45/(1+$B8)^('DCF Model'!C19+0)+'DCF Model'!D45/(1+$B8)^('DCF Model'!C19+1)+'DCF Model'!E45/(1+$B8)^('DCF Model'!C19+2)+'DCF Model'!F45/(1+$B8)^('DCF Model'!C19+3)+'DCF Model'!G45/(1+$B8)^('DCF Model'!C19+4)+'DCF Model'!G45*(1+I$6)/($B8-I$6)/(1+$B8)^('DCF Model'!C19+4)-'DCF Model'!C16)*1000000/'DCF Model'!C15,0),"") -> 1473
B9: =$C$3-0.005 -> 0.0997 | C9: =IFERROR(ROUND(('DCF Model'!C45/(1+$B9)^('DCF Model'!C19+0)+'DCF Model'!D45/(1+$B9)^('DCF Model'!C19+1)+'DCF Model'!E45/(1+$B9)^('DCF Model'!C19+2)+'DCF Model'!F45/(1+$B9)^('DCF Model'!C19+3)+'DCF Model'!G45/(1+$B9)^('DCF Model'!C19+4)+'DCF Model'!G45*(1+C$6)/($B9-C$6)/(1+$B9)^('DCF Model'!C19+4)-'DCF Model'!C16)*1000000/'DCF Model'!C15,0),"") -> 1235 | D9: =IFERROR(ROUND(('DCF Model'!C45/(1+$B9)^('DCF Model'!C19+0)+'DCF Model'!D45/(1+$B9)^('DCF Model'!C19+1)+'DCF Model'!E45/(1+$B9)^('DCF Model'!C19+2)+'DCF Model'!F45/(1+$B9)^('DCF Model'!C19+3)+'DCF Model'!G45/(1+$B9)^('DCF Model'!C19+4)+'DCF Model'!G45*(1+D$6)/($B9-D$6)/(1+$B9)^('DCF Model'!C19+4)-'DCF Model'!C16)*1000000/'DCF Model'!C15,0),"") -> 1257 | E9: =IFERROR(ROUND(('DCF Model'!C45/(1+$B9)^('DCF Model'!C19+0)+'DCF Model'!D45/(1+$B9)^('DCF Model'!C19+1)+'DCF Model'!E45/(1+$B9)^('DCF Model'!C19+2)+'DCF Model'!F45/(1+$B9)^('DCF Model'!C19+3)+'DCF Model'!G45/(1+$B9)^('DCF Model'!C19+4)+'DCF Model'!G45*(1+E$6)/($B9-E$6)/(1+$B9)^('DCF Model'!C19+4)-'DCF Model'!C16)*1000000/'DCF Model'!C15,0),"") -> 1280 | F9: =IFERROR(ROUND(('DCF Model'!C45/(1+$B9)^('DCF Model'!C19+0)+'DCF Model'!D45/(1+$B9)^('DCF Model'!C19+1)+'DCF Model'!E45/(1+$B9)^('DCF Model'!C19+2)+'DCF Model'!F45/(1+$B9)^('DCF Model'!C19+3)+'DCF Model'!G45/(1+$B9)^('DCF Model'!C19+4)+'DCF Model'!G45*(1+F$6)/($B9-F$6)/(1+$B9)^('DCF Model'!C19+4)-'DCF Model'!C16)*1000000/'DCF Model'!C15,0),"") -> 1305 | G9: =IFERROR(ROUND(('DCF Model'!C45/(1+$B9)^('DCF Model'!C19+0)+'DCF Model'!D45/(1+$B9)^('DCF Model'!C19+1)+'DCF Model'!E45/(1+$B9)^('DCF Model'!C19+2)+'DCF Model'!F45/(1+$B9)^('DCF Model'!C19+3)+'DCF Model'!G45/(1+$B9)^('DCF Model'!C19+4)+'DCF Model'!G45*(1+G$6)/($B9-G$6)/(1+$B9)^('DCF Model'!C19+4)-'DCF Model'!C16)*1000000/'DCF Model'!C15,0),"") -> 1331 | H9: =IFERROR(ROUND(('DCF Model'!C45/(1+$B9)^('DCF Model'!C19+0)+'DCF Model'!D45/(1+$B9)^('DCF Model'!C19+1)+'DCF Model'!E45/(1+$B9)^('DCF Model'!C19+2)+'DCF Model'!F45/(1+$B9)^('DCF Model'!C19+3)+'DCF Model'!G45/(1+$B9)^('DCF Model'!C19+4)+'DCF Model'!G45*(1+H$6)/($B9-H$6)/(1+$B9)^('DCF Model'!C19+4)-'DCF Model'!C16)*1000000/'DCF Model'!C15,0),"") -> 1358 | I9: =IFERROR(ROUND(('DCF Model'!C45/(1+$B9)^('DCF Model'!C19+0)+'DCF Model'!D45/(1+$B9)^('DCF Model'!C19+1)+'DCF Model'!E45/(1+$B9)^('DCF Model'!C19+2)+'DCF Model'!F45/(1+$B9)^('DCF Model'!C19+3)+'DCF Model'!G45/(1+$B9)^('DCF Model'!C19+4)+'DCF Model'!G45*(1+I$6)/($B9-I$6)/(1+$B9)^('DCF Model'!C19+4)-'DCF Model'!C16)*1000000/'DCF Model'!C15,0),"") -> 1387
B10: =$C$3 -> 0.1047 | C10: =IFERROR(ROUND(('DCF Model'!C45/(1+$B10)^('DCF Model'!C19+0)+'DCF Model'!D45/(1+$B10)^('DCF Model'!C19+1)+'DCF Model'!E45/(1+$B10)^('DCF Model'!C19+2)+'DCF Model'!F45/(1+$B10)^('DCF Model'!C19+3)+'DCF Model'!G45/(1+$B10)^('DCF Model'!C19+4)+'DCF Model'!G45*(1+C$6)/($B10-C$6)/(1+$B10)^('DCF Model'!C19+4)-'DCF Model'!C16)*1000000/'DCF Model'!C15,0),"") -> 1177 | D10: =IFERROR(ROUND(('DCF Model'!C45/(1+$B10)^('DCF Model'!C19+0)+'DCF Model'!D45/(1+$B10)^('DCF Model'!C19+1)+'DCF Model'!E45/(1+$B10)^('DCF Model'!C19+2)+'DCF Model'!F45/(1+$B10)^('DCF Model'!C19+3)+'DCF Model'!G45/(1+$B10)^('DCF Model'!C19+4)+'DCF Model'!G45*(1+D$6)/($B10-D$6)/(1+$B10)^('DCF Model'!C19+4)-'DCF Model'!C16)*1000000/'DCF Model'!C15,0),"") -> 1197 | E10: =IFERROR(ROUND(('DCF Model'!C45/(1+$B10)^('DCF Model'!C19+0)+'DCF Model'!D45/(1+$B10)^('DCF Model'!C19+1)+'DCF Model'!E45/(1+$B10)^('DCF Model'!C19+2)+'DCF Model'!F45/(1+$B10)^('DCF Model'!C19+3)+'DCF Model'!G45/(1+$B10)^('DCF Model'!C19+4)+'DCF Model'!G45*(1+E$6)/($B10-E$6)/(1+$B10)^('DCF Model'!C19+4)-'DCF Model'!C16)*1000000/'DCF Model'!C15,0),"") -> 1217 | F10: =IFERROR(ROUND(('DCF Model'!C45/(1+$B10)^('DCF Model'!C19+0)+'DCF Model'!D45/(1+$B10)^('DCF Model'!C19+1)+'DCF Model'!E45/(1+$B10)^('DCF Model'!C19+2)+'DCF Model'!F45/(1+$B10)^('DCF Model'!C19+3)+'DCF Model'!G45/(1+$B10)^('DCF Model'!C19+4)+'DCF Model'!G45*(1+F$6)/($B10-F$6)/(1+$B10)^('DCF Model'!C19+4)-'DCF Model'!C16)*1000000/'DCF Model'!C15,0),"") -> 1239 | G10: =IFERROR(ROUND(('DCF Model'!C45/(1+$B10)^('DCF Model'!C19+0)+'DCF Model'!D45/(1+$B10)^('DCF Model'!C19+1)+'DCF Model'!E45/(1+$B10)^('DCF Model'!C19+2)+'DCF Model'!F45/(1+$B10)^('DCF Model'!C19+3)+'DCF Model'!G45/(1+$B10)^('DCF Model'!C19+4)+'DCF Model'!G45*(1+G$6)/($B10-G$6)/(1+$B10)^('DCF Model'!C19+4)-'DCF Model'!C16)*1000000/'DCF Model'!C15,0),"") -> 1261 | H10: =IFERROR(ROUND(('DCF Model'!C45/(1+$B10)^('DCF Model'!C19+0)+'DCF Model'!D45/(1+$B10)^('DCF Model'!C19+1)+'DCF Model'!E45/(1+$B10)^('DCF Model'!C19+2)+'DCF Model'!F45/(1+$B10)^('DCF Model'!C19+3)+'DCF Model'!G45/(1+$B10)^('DCF Model'!C19+4)+'DCF Model'!G45*(1+H$6)/($B10-H$6)/(1+$B10)^('DCF Model'!C19+4)-'DCF Model'!C16)*1000000/'DCF Model'!C15,0),"") -> 1285 | I10: =IFERROR(ROUND(('DCF Model'!C45/(1+$B10)^('DCF Model'!C19+0)+'DCF Model'!D45/(1+$B10)^('DCF Model'!C19+1)+'DCF Model'!E45/(1+$B10)^('DCF Model'!C19+2)+'DCF Model'!F45/(1+$B10)^('DCF Model'!C19+3)+'DCF Model'!G45/(1+$B10)^('DCF Model'!C19+4)+'DCF Model'!G45*(1+I$6)/($B10-I$6)/(1+$B10)^('DCF Model'!C19+4)-'DCF Model'!C16)*1000000/'DCF Model'!C15,0),"") -> 1311
B11: =$C$3+0.005 -> 0.1097 | C11: =IFERROR(ROUND(('DCF Model'!C45/(1+$B11)^('DCF Model'!C19+0)+'DCF Model'!D45/(1+$B11)^('DCF Model'!C19+1)+'DCF Model'!E45/(1+$B11)^('DCF Model'!C19+2)+'DCF Model'!F45/(1+$B11)^('DCF Model'!C19+3)+'DCF Model'!G45/(1+$B11)^('DCF Model'!C19+4)+'DCF Model'!G45*(1+C$6)/($B11-C$6)/(1+$B11)^('DCF Model'!C19+4)-'DCF Model'!C16)*1000000/'DCF Model'!C15,0),"") -> 1125 | D11: =IFERROR(ROUND(('DCF Model'!C45/(1+$B11)^('DCF Model'!C19+0)+'DCF Model'!D45/(1+$B11)^('DCF Model'!C19+1)+'DCF Model'!E45/(1+$B11)^('DCF Model'!C19+2)+'DCF Model'!F45/(1+$B11)^('DCF Model'!C19+3)+'DCF Model'!G45/(1+$B11)^('DCF Model'!C19+4)+'DCF Model'!G45*(1+D$6)/($B11-D$6)/(1+$B11)^('DCF Model'!C19+4)-'DCF Model'!C16)*1000000/'DCF Model'!C15,0),"") -> 1142 | E11: =IFERROR(ROUND(('DCF Model'!C45/(1+$B11)^('DCF Model'!C19+0)+'DCF Model'!D45/(1+$B11)^('DCF Model'!C19+1)+'DCF Model'!E45/(1+$B11)^('DCF Model'!C19+2)+'DCF Model'!F45/(1+$B11)^('DCF Model'!C19+3)+'DCF Model'!G45/(1+$B11)^('DCF Model'!C19+4)+'DCF Model'!G45*(1+E$6)/($B11-E$6)/(1+$B11)^('DCF Model'!C19+4)-'DCF Model'!C16)*1000000/'DCF Model'!C15,0),"") -> 1160 | F11: =IFERROR(ROUND(('DCF Model'!C45/(1+$B11)^('DCF Model'!C19+0)+'DCF Model'!D45/(1+$B11)^('DCF Model'!C19+1)+'DCF Model'!E45/(1+$B11)^('DCF Model'!C19+2)+'DCF Model'!F45/(1+$B11)^('DCF Model'!C19+3)+'DCF Model'!G45/(1+$B11)^('DCF Model'!C19+4)+'DCF Model'!G45*(1+F$6)/($B11-F$6)/(1+$B11)^('DCF Model'!C19+4)-'DCF Model'!C16)*1000000/'DCF Model'!C15,0),"") -> 1179 | G11: =IFERROR(ROUND(('DCF Model'!C45/(1+$B11)^('DCF Model'!C19+0)+'DCF Model'!D45/(1+$B11)^('DCF Model'!C19+1)+'DCF Model'!E45/(1+$B11)^('DCF Model'!C19+2)+'DCF Model'!F45/(1+$B11)^('DCF Model'!C19+3)+'DCF Model'!G45/(1+$B11)^('DCF Model'!C19+4)+'DCF Model'!G45*(1+G$6)/($B11-G$6)/(1+$B11)^('DCF Model'!C19+4)-'DCF Model'!C16)*1000000/'DCF Model'!C15,0),"") -> 1199 | H11: =IFERROR(ROUND(('DCF Model'!C45/(1+$B11)^('DCF Model'!C19+0)+'DCF Model'!D45/(1+$B11)^('DCF Model'!C19+1)+'DCF Model'!E45/(1+$B11)^('DCF Model'!C19+2)+'DCF Model'!F45/(1+$B11)^('DCF Model'!C19+3)+'DCF Model'!G45/(1+$B11)^('DCF Model'!C19+4)+'DCF Model'!G45*(1+H$6)/($B11-H$6)/(1+$B11)^('DCF Model'!C19+4)-'DCF Model'!C16)*1000000/'DCF Model'!C15,0),"") -> 1221 | I11: =IFERROR(ROUND(('DCF Model'!C45/(1+$B11)^('DCF Model'!C19+0)+'DCF Model'!D45/(1+$B11)^('DCF Model'!C19+1)+'DCF Model'!E45/(1+$B11)^('DCF Model'!C19+2)+'DCF Model'!F45/(1+$B11)^('DCF Model'!C19+3)+'DCF Model'!G45/(1+$B11)^('DCF Model'!C19+4)+'DCF Model'!G45*(1+I$6)/($B11-I$6)/(1+$B11)^('DCF Model'!C19+4)-'DCF Model'!C16)*1000000/'DCF Model'!C15,0),"") -> 1243
B12: =$C$3+0.01 -> 0.1147 | C12: =IFERROR(ROUND(('DCF Model'!C45/(1+$B12)^('DCF Model'!C19+0)+'DCF Model'!D45/(1+$B12)^('DCF Model'!C19+1)+'DCF Model'!E45/(1+$B12)^('DCF Model'!C19+2)+'DCF Model'!F45/(1+$B12)^('DCF Model'!C19+3)+'DCF Model'!G45/(1+$B12)^('DCF Model'!C19+4)+'DCF Model'!G45*(1+C$6)/($B12-C$6)/(1+$B12)^('DCF Model'!C19+4)-'DCF Model'!C16)*1000000/'DCF Model'!C15,0),"") -> 1077 | D12: =IFERROR(ROUND(('DCF Model'!C45/(1+$B12)^('DCF Model'!C19+0)+'DCF Model'!D45/(1+$B12)^('DCF Model'!C19+1)+'DCF Model'!E45/(1+$B12)^('DCF Model'!C19+2)+'DCF Model'!F45/(1+$B12)^('DCF Model'!C19+3)+'DCF Model'!G45/(1+$B12)^('DCF Model'!C19+4)+'DCF Model'!G45*(1+D$6)/($B12-D$6)/(1+$B12)^('DCF Model'!C19+4)-'DCF Model'!C16)*1000000/'DCF Model'!C15,0),"") -> 1092 | E12: =IFERROR(ROUND(('DCF Model'!C45/(1+$B12)^('DCF Model'!C19+0)+'DCF Model'!D45/(1+$B12)^('DCF Model'!C19+1)+'DCF Model'!E45/(1+$B12)^('DCF Model'!C19+2)+'DCF Model'!F45/(1+$B12)^('DCF Model'!C19+3)+'DCF Model'!G45/(1+$B12)^('DCF Model'!C19+4)+'DCF Model'!G45*(1+E$6)/($B12-E$6)/(1+$B12)^('DCF Model'!C19+4)-'DCF Model'!C16)*1000000/'DCF Model'!C15,0),"") -> 1109 | F12: =IFERROR(ROUND(('DCF Model'!C45/(1+$B12)^('DCF Model'!C19+0)+'DCF Model'!D45/(1+$B12)^('DCF Model'!C19+1)+'DCF Model'!E45/(1+$B12)^('DCF Model'!C19+2)+'DCF Model'!F45/(1+$B12)^('DCF Model'!C19+3)+'DCF Model'!G45/(1+$B12)^('DCF Model'!C19+4)+'DCF Model'!G45*(1+F$6)/($B12-F$6)/(1+$B12)^('DCF Model'!C19+4)-'DCF Model'!C16)*1000000/'DCF Model'!C15,0),"") -> 1126 | G12: =IFERROR(ROUND(('DCF Model'!C45/(1+$B12)^('DCF Model'!C19+0)+'DCF Model'!D45/(1+$B12)^('DCF Model'!C19+1)+'DCF Model'!E45/(1+$B12)^('DCF Model'!C19+2)+'DCF Model'!F45/(1+$B12)^('DCF Model'!C19+3)+'DCF Model'!G45/(1+$B12)^('DCF Model'!C19+4)+'DCF Model'!G45*(1+G$6)/($B12-G$6)/(1+$B12)^('DCF Model'!C19+4)-'DCF Model'!C16)*1000000/'DCF Model'!C15,0),"") -> 1144 | H12: =IFERROR(ROUND(('DCF Model'!C45/(1+$B12)^('DCF Model'!C19+0)+'DCF Model'!D45/(1+$B12)^('DCF Model'!C19+1)+'DCF Model'!E45/(1+$B12)^('DCF Model'!C19+2)+'DCF Model'!F45/(1+$B12)^('DCF Model'!C19+3)+'DCF Model'!G45/(1+$B12)^('DCF Model'!C19+4)+'DCF Model'!G45*(1+H$6)/($B12-H$6)/(1+$B12)^('DCF Model'!C19+4)-'DCF Model'!C16)*1000000/'DCF Model'!C15,0),"") -> 1162 | I12: =IFERROR(ROUND(('DCF Model'!C45/(1+$B12)^('DCF Model'!C19+0)+'DCF Model'!D45/(1+$B12)^('DCF Model'!C19+1)+'DCF Model'!E45/(1+$B12)^('DCF Model'!C19+2)+'DCF Model'!F45/(1+$B12)^('DCF Model'!C19+3)+'DCF Model'!G45/(1+$B12)^('DCF Model'!C19+4)+'DCF Model'!G45*(1+I$6)/($B12-I$6)/(1+$B12)^('DCF Model'!C19+4)-'DCF Model'!C16)*1000000/'DCF Model'!C15,0),"") -> 1182
B13: =$C$3+0.015 -> 0.1197 | C13: =IFERROR(ROUND(('DCF Model'!C45/(1+$B13)^('DCF Model'!C19+0)+'DCF Model'!D45/(1+$B13)^('DCF Model'!C19+1)+'DCF Model'!E45/(1+$B13)^('DCF Model'!C19+2)+'DCF Model'!F45/(1+$B13)^('DCF Model'!C19+3)+'DCF Model'!G45/(1+$B13)^('DCF Model'!C19+4)+'DCF Model'!G45*(1+C$6)/($B13-C$6)/(1+$B13)^('DCF Model'!C19+4)-'DCF Model'!C16)*1000000/'DCF Model'!C15,0),"") -> 1033 | D13: =IFERROR(ROUND(('DCF Model'!C45/(1+$B13)^('DCF Model'!C19+0)+'DCF Model'!D45/(1+$B13)^('DCF Model'!C19+1)+'DCF Model'!E45/(1+$B13)^('DCF Model'!C19+2)+'DCF Model'!F45/(1+$B13)^('DCF Model'!C19+3)+'DCF Model'!G45/(1+$B13)^('DCF Model'!C19+4)+'DCF Model'!G45*(1+D$6)/($B13-D$6)/(1+$B13)^('DCF Model'!C19+4)-'DCF Model'!C16)*1000000/'DCF Model'!C15,0),"") -> 1047 | E13: =IFERROR(ROUND(('DCF Model'!C45/(1+$B13)^('DCF Model'!C19+0)+'DCF Model'!D45/(1+$B13)^('DCF Model'!C19+1)+'DCF Model'!E45/(1+$B13)^('DCF Model'!C19+2)+'DCF Model'!F45/(1+$B13)^('DCF Model'!C19+3)+'DCF Model'!G45/(1+$B13)^('DCF Model'!C19+4)+'DCF Model'!G45*(1+E$6)/($B13-E$6)/(1+$B13)^('DCF Model'!C19+4)-'DCF Model'!C16)*1000000/'DCF Model'!C15,0),"") -> 1062 | F13: =IFERROR(ROUND(('DCF Model'!C45/(1+$B13)^('DCF Model'!C19+0)+'DCF Model'!D45/(1+$B13)^('DCF Model'!C19+1)+'DCF Model'!E45/(1+$B13)^('DCF Model'!C19+2)+'DCF Model'!F45/(1+$B13)^('DCF Model'!C19+3)+'DCF Model'!G45/(1+$B13)^('DCF Model'!C19+4)+'DCF Model'!G45*(1+F$6)/($B13-F$6)/(1+$B13)^('DCF Model'!C19+4)-'DCF Model'!C16)*1000000/'DCF Model'!C15,0),"") -> 1077 | G13: =IFERROR(ROUND(('DCF Model'!C45/(1+$B13)^('DCF Model'!C19+0)+'DCF Model'!D45/(1+$B13)^('DCF Model'!C19+1)+'DCF Model'!E45/(1+$B13)^('DCF Model'!C19+2)+'DCF Model'!F45/(1+$B13)^('DCF Model'!C19+3)+'DCF Model'!G45/(1+$B13)^('DCF Model'!C19+4)+'DCF Model'!G45*(1+G$6)/($B13-G$6)/(1+$B13)^('DCF Model'!C19+4)-'DCF Model'!C16)*1000000/'DCF Model'!C15,0),"") -> 1093 | H13: =IFERROR(ROUND(('DCF Model'!C45/(1+$B13)^('DCF Model'!C19+0)+'DCF Model'!D45/(1+$B13)^('DCF Model'!C19+1)+'DCF Model'!E45/(1+$B13)^('DCF Model'!C19+2)+'DCF Model'!F45/(1+$B13)^('DCF Model'!C19+3)+'DCF Model'!G45/(1+$B13)^('DCF Model'!C19+4)+'DCF Model'!G45*(1+H$6)/($B13-H$6)/(1+$B13)^('DCF Model'!C19+4)-'DCF Model'!C16)*1000000/'DCF Model'!C15,0),"") -> 1110 | I13: =IFERROR(ROUND(('DCF Model'!C45/(1+$B13)^('DCF Model'!C19+0)+'DCF Model'!D45/(1+$B13)^('DCF Model'!C19+1)+'DCF Model'!E45/(1+$B13)^('DCF Model'!C19+2)+'DCF Model'!F45/(1+$B13)^('DCF Model'!C19+3)+'DCF Model'!G45/(1+$B13)^('DCF Model'!C19+4)+'DCF Model'!G45*(1+I$6)/($B13-I$6)/(1+$B13)^('DCF Model'!C19+4)-'DCF Model'!C16)*1000000/'DCF Model'!C15,0),"") -> 1127
B16: Table 2: WACC vs Exit Multiple (Exit Multiple - Implied Share Price, JPY)
B17: WACC \ Exit Multiple | C17: =$I$3-3 -> 7.8 | D17: =$I$3-2 -> 8.8 | E17: =$I$3-1 -> 9.8 | F17: =$I$3 -> 10.8 | G17: =$I$3+1 -> 11.8 | H17: =$I$3+2 -> 12.8 | I17: =$I$3+3 -> 13.8
B18: =$C$3-0.015 -> 0.0897 | C18: =IFERROR(ROUND(('DCF Model'!C45/(1+$B18)^('DCF Model'!C19+0)+'DCF Model'!D45/(1+$B18)^('DCF Model'!C19+1)+'DCF Model'!E45/(1+$B18)^('DCF Model'!C19+2)+'DCF Model'!F45/(1+$B18)^('DCF Model'!C19+3)+'DCF Model'!G45/(1+$B18)^('DCF Model'!C19+4)+('DCF Model'!G39+'DCF Model'!G42)*C$17/(1+$B18)^('DCF Model'!C19+4)-'DCF Model'!C16)*1000000/'DCF Model'!C15,0),"") -> 1667 | D18: =IFERROR(ROUND(('DCF Model'!C45/(1+$B18)^('DCF Model'!C19+0)+'DCF Model'!D45/(1+$B18)^('DCF Model'!C19+1)+'DCF Model'!E45/(1+$B18)^('DCF Model'!C19+2)+'DCF Model'!F45/(1+$B18)^('DCF Model'!C19+3)+'DCF Model'!G45/(1+$B18)^('DCF Model'!C19+4)+('DCF Model'!G39+'DCF Model'!G42)*D$17/(1+$B18)^('DCF Model'!C19+4)-'DCF Model'!C16)*1000000/'DCF Model'!C15,0),"") -> 1818 | E18: =IFERROR(ROUND(('DCF Model'!C45/(1+$B18)^('DCF Model'!C19+0)+'DCF Model'!D45/(1+$B18)^('DCF Model'!C19+1)+'DCF Model'!E45/(1+$B18)^('DCF Model'!C19+2)+'DCF Model'!F45/(1+$B18)^('DCF Model'!C19+3)+'DCF Model'!G45/(1+$B18)^('DCF Model'!C19+4)+('DCF Model'!G39+'DCF Model'!G42)*E$17/(1+$B18)^('DCF Model'!C19+4)-'DCF Model'!C16)*1000000/'DCF Model'!C15,0),"") -> 1969 | F18: =IFERROR(ROUND(('DCF Model'!C45/(1+$B18)^('DCF Model'!C19+0)+'DCF Model'!D45/(1+$B18)^('DCF Model'!C19+1)+'DCF Model'!E45/(1+$B18)^('DCF Model'!C19+2)+'DCF Model'!F45/(1+$B18)^('DCF Model'!C19+3)+'DCF Model'!G45/(1+$B18)^('DCF Model'!C19+4)+('DCF Model'!G39+'DCF Model'!G42)*F$17/(1+$B18)^('DCF Model'!C19+4)-'DCF Model'!C16)*1000000/'DCF Model'!C15,0),"") -> 2120 | G18: =IFERROR(ROUND(('DCF Model'!C45/(1+$B18)^('DCF Model'!C19+0)+'DCF Model'!D45/(1+$B18)^('DCF Model'!C19+1)+'DCF Model'!E45/(1+$B18)^('DCF Model'!C19+2)+'DCF Model'!F45/(1+$B18)^('DCF Model'!C19+3)+'DCF Model'!G45/(1+$B18)^('DCF Model'!C19+4)+('DCF Model'!G39+'DCF Model'!G42)*G$17/(1+$B18)^('DCF Model'!C19+4)-'DCF Model'!C16)*1000000/'DCF Model'!C15,0),"") -> 2271 | H18: =IFERROR(ROUND(('DCF Model'!C45/(1+$B18)^('DCF Model'!C19+0)+'DCF Model'!D45/(1+$B18)^('DCF Model'!C19+1)+'DCF Model'!E45/(1+$B18)^('DCF Model'!C19+2)+'DCF Model'!F45/(1+$B18)^('DCF Model'!C19+3)+'DCF Model'!G45/(1+$B18)^('DCF Model'!C19+4)+('DCF Model'!G39+'DCF Model'!G42)*H$17/(1+$B18)^('DCF Model'!C19+4)-'DCF Model'!C16)*1000000/'DCF Model'!C15,0),"") -> 2422 | I18: =IFERROR(ROUND(('DCF Model'!C45/(1+$B18)^('DCF Model'!C19+0)+'DCF Model'!D45/(1+$B18)^('DCF Model'!C19+1)+'DCF Model'!E45/(1+$B18)^('DCF Model'!C19+2)+'DCF Model'!F45/(1+$B18)^('DCF Model'!C19+3)+'DCF Model'!G45/(1+$B18)^('DCF Model'!C19+4)+('DCF Model'!G39+'DCF Model'!G42)*I$17/(1+$B18)^('DCF Model'!C19+4)-'DCF Model'!C16)*1000000/'DCF Model'!C15,0),"") -> 2573
B19: =$C$3-0.01 -> 0.0947 | C19: =IFERROR(ROUND(('DCF Model'!C45/(1+$B19)^('DCF Model'!C19+0)+'DCF Model'!D45/(1+$B19)^('DCF Model'!C19+1)+'DCF Model'!E45/(1+$B19)^('DCF Model'!C19+2)+'DCF Model'!F45/(1+$B19)^('DCF Model'!C19+3)+'DCF Model'!G45/(1+$B19)^('DCF Model'!C19+4)+('DCF Model'!G39+'DCF Model'!G42)*C$17/(1+$B19)^('DCF Model'!C19+4)-'DCF Model'!C16)*1000000/'DCF Model'!C15,0),"") -> 1635 | D19: =IFERROR(ROUND(('DCF Model'!C45/(1+$B19)^('DCF Model'!C19+0)+'DCF Model'!D45/(1+$B19)^('DCF Model'!C19+1)+'DCF Model'!E45/(1+$B19)^('DCF Model'!C19+2)+'DCF Model'!F45/(1+$B19)^('DCF Model'!C19+3)+'DCF Model'!G45/(1+$B19)^('DCF Model'!C19+4)+('DCF Model'!G39+'DCF Model'!G42)*D$17/(1+$B19)^('DCF Model'!C19+4)-'DCF Model'!C16)*1000000/'DCF Model'!C15,0),"") -> 1783 | E19: =IFERROR(ROUND(('DCF Model'!C45/(1+$B19)^('DCF Model'!C19+0)+'DCF Model'!D45/(1+$B19)^('DCF Model'!C19+1)+'DCF Model'!E45/(1+$B19)^('DCF Model'!C19+2)+'DCF Model'!F45/(1+$B19)^('DCF Model'!C19+3)+'DCF Model'!G45/(1+$B19)^('DCF Model'!C19+4)+('DCF Model'!G39+'DCF Model'!G42)*E$17/(1+$B19)^('DCF Model'!C19+4)-'DCF Model'!C16)*1000000/'DCF Model'!C15,0),"") -> 1930 | F19: =IFERROR(ROUND(('DCF Model'!C45/(1+$B19)^('DCF Model'!C19+0)+'DCF Model'!D45/(1+$B19)^('DCF Model'!C19+1)+'DCF Model'!E45/(1+$B19)^('DCF Model'!C19+2)+'DCF Model'!F45/(1+$B19)^('DCF Model'!C19+3)+'DCF Model'!G45/(1+$B19)^('DCF Model'!C19+4)+('DCF Model'!G39+'DCF Model'!G42)*F$17/(1+$B19)^('DCF Model'!C19+4)-'DCF Model'!C16)*1000000/'DCF Model'!C15,0),"") -> 2078 | G19: =IFERROR(ROUND(('DCF Model'!C45/(1+$B19)^('DCF Model'!C19+0)+'DCF Model'!D45/(1+$B19)^('DCF Model'!C19+1)+'DCF Model'!E45/(1+$B19)^('DCF Model'!C19+2)+'DCF Model'!F45/(1+$B19)^('DCF Model'!C19+3)+'DCF Model'!G45/(1+$B19)^('DCF Model'!C19+4)+('DCF Model'!G39+'DCF Model'!G42)*G$17/(1+$B19)^('DCF Model'!C19+4)-'DCF Model'!C16)*1000000/'DCF Model'!C15,0),"") -> 2226 | H19: =IFERROR(ROUND(('DCF Model'!C45/(1+$B19)^('DCF Model'!C19+0)+'DCF Model'!D45/(1+$B19)^('DCF Model'!C19+1)+'DCF Model'!E45/(1+$B19)^('DCF Model'!C19+2)+'DCF Model'!F45/(1+$B19)^('DCF Model'!C19+3)+'DCF Model'!G45/(1+$B19)^('DCF Model'!C19+4)+('DCF Model'!G39+'DCF Model'!G42)*H$17/(1+$B19)^('DCF Model'!C19+4)-'DCF Model'!C16)*1000000/'DCF Model'!C15,0),"") -> 2373 | I19: =IFERROR(ROUND(('DCF Model'!C45/(1+$B19)^('DCF Model'!C19+0)+'DCF Model'!D45/(1+$B19)^('DCF Model'!C19+1)+'DCF Model'!E45/(1+$B19)^('DCF Model'!C19+2)+'DCF Model'!F45/(1+$B19)^('DCF Model'!C19+3)+'DCF Model'!G45/(1+$B19)^('DCF Model'!C19+4)+('DCF Model'!G39+'DCF Model'!G42)*I$17/(1+$B19)^('DCF Model'!C19+4)-'DCF Model'!C16)*1000000/'DCF Model'!C15,0),"") -> 2521
B20: =$C$3-0.005 -> 0.0997 | C20: =IFERROR(ROUND(('DCF Model'!C45/(1+$B20)^('DCF Model'!C19+0)+'DCF Model'!D45/(1+$B20)^('DCF Model'!C19+1)+'DCF Model'!E45/(1+$B20)^('DCF Model'!C19+2)+'DCF Model'!F45/(1+$B20)^('DCF Model'!C19+3)+'DCF Model'!G45/(1+$B20)^('DCF Model'!C19+4)+('DCF Model'!G39+'DCF Model'!G42)*C$17/(1+$B20)^('DCF Model'!C19+4)-'DCF Model'!C16)*1000000/'DCF Model'!C15,0),"") -> 1604 | D20: =IFERROR(ROUND(('DCF Model'!C45/(1+$B20)^('DCF Model'!C19+0)+'DCF Model'!D45/(1+$B20)^('DCF Model'!C19+1)+'DCF Model'!E45/(1+$B20)^('DCF Model'!C19+2)+'DCF Model'!F45/(1+$B20)^('DCF Model'!C19+3)+'DCF Model'!G45/(1+$B20)^('DCF Model'!C19+4)+('DCF Model'!G39+'DCF Model'!G42)*D$17/(1+$B20)^('DCF Model'!C19+4)-'DCF Model'!C16)*1000000/'DCF Model'!C15,0),"") -> 1749 | E20: =IFERROR(ROUND(('DCF Model'!C45/(1+$B20)^('DCF Model'!C19+0)+'DCF Model'!D45/(1+$B20)^('DCF Model'!C19+1)+'DCF Model'!E45/(1+$B20)^('DCF Model'!C19+2)+'DCF Model'!F45/(1+$B20)^('DCF Model'!C19+3)+'DCF Model'!G45/(1+$B20)^('DCF Model'!C19+4)+('DCF Model'!G39+'DCF Model'!G42)*E$17/(1+$B20)^('DCF Model'!C19+4)-'DCF Model'!C16)*1000000/'DCF Model'!C15,0),"") -> 1893 | F20: =IFERROR(ROUND(('DCF Model'!C45/(1+$B20)^('DCF Model'!C19+0)+'DCF Model'!D45/(1+$B20)^('DCF Model'!C19+1)+'DCF Model'!E45/(1+$B20)^('DCF Model'!C19+2)+'DCF Model'!F45/(1+$B20)^('DCF Model'!C19+3)+'DCF Model'!G45/(1+$B20)^('DCF Model'!C19+4)+('DCF Model'!G39+'DCF Model'!G42)*F$17/(1+$B20)^('DCF Model'!C19+4)-'DCF Model'!C16)*1000000/'DCF Model'!C15,0),"") -> 2037 | G20: =IFERROR(ROUND(('DCF Model'!C45/(1+$B20)^('DCF Model'!C19+0)+'DCF Model'!D45/(1+$B20)^('DCF Model'!C19+1)+'DCF Model'!E45/(1+$B20)^('DCF Model'!C19+2)+'DCF Model'!F45/(1+$B20)^('DCF Model'!C19+3)+'DCF Model'!G45/(1+$B20)^('DCF Model'!C19+4)+('DCF Model'!G39+'DCF Model'!G42)*G$17/(1+$B20)^('DCF Model'!C19+4)-'DCF Model'!C16)*1000000/'DCF Model'!C15,0),"") -> 2182 | H20: =IFERROR(ROUND(('DCF Model'!C45/(1+$B20)^('DCF Model'!C19+0)+'DCF Model'!D45/(1+$B20)^('DCF Model'!C19+1)+'DCF Model'!E45/(1+$B20)^('DCF Model'!C19+2)+'DCF Model'!F45/(1+$B20)^('DCF Model'!C19+3)+'DCF Model'!G45/(1+$B20)^('DCF Model'!C19+4)+('DCF Model'!G39+'DCF Model'!G42)*H$17/(1+$B20)^('DCF Model'!C19+4)-'DCF Model'!C16)*1000000/'DCF Model'!C15,0),"") -> 2326 | I20: =IFERROR(ROUND(('DCF Model'!C45/(1+$B20)^('DCF Model'!C19+0)+'DCF Model'!D45/(1+$B20)^('DCF Model'!C19+1)+'DCF Model'!E45/(1+$B20)^('DCF Model'!C19+2)+'DCF Model'!F45/(1+$B20)^('DCF Model'!C19+3)+'DCF Model'!G45/(1+$B20)^('DCF Model'!C19+4)+('DCF Model'!G39+'DCF Model'!G42)*I$17/(1+$B20)^('DCF Model'!C19+4)-'DCF Model'!C16)*1000000/'DCF Model'!C15,0),"") -> 2470
B21: =$C$3 -> 0.1047 | C21: =IFERROR(ROUND(('DCF Model'!C45/(1+$B21)^('DCF Model'!C19+0)+'DCF Model'!D45/(1+$B21)^('DCF Model'!C19+1)+'DCF Model'!E45/(1+$B21)^('DCF Model'!C19+2)+'DCF Model'!F45/(1+$B21)^('DCF Model'!C19+3)+'DCF Model'!G45/(1+$B21)^('DCF Model'!C19+4)+('DCF Model'!G39+'DCF Model'!G42)*C$17/(1+$B21)^('DCF Model'!C19+4)-'DCF Model'!C16)*1000000/'DCF Model'!C15,0),"") -> 1574 | D21: =IFERROR(ROUND(('DCF Model'!C45/(1+$B21)^('DCF Model'!C19+0)+'DCF Model'!D45/(1+$B21)^('DCF Model'!C19+1)+'DCF Model'!E45/(1+$B21)^('DCF Model'!C19+2)+'DCF Model'!F45/(1+$B21)^('DCF Model'!C19+3)+'DCF Model'!G45/(1+$B21)^('DCF Model'!C19+4)+('DCF Model'!G39+'DCF Model'!G42)*D$17/(1+$B21)^('DCF Model'!C19+4)-'DCF Model'!C16)*1000000/'DCF Model'!C15,0),"") -> 1715 | E21: =IFERROR(ROUND(('DCF Model'!C45/(1+$B21)^('DCF Model'!C19+0)+'DCF Model'!D45/(1+$B21)^('DCF Model'!C19+1)+'DCF Model'!E45/(1+$B21)^('DCF Model'!C19+2)+'DCF Model'!F45/(1+$B21)^('DCF Model'!C19+3)+'DCF Model'!G45/(1+$B21)^('DCF Model'!C19+4)+('DCF Model'!G39+'DCF Model'!G42)*E$17/(1+$B21)^('DCF Model'!C19+4)-'DCF Model'!C16)*1000000/'DCF Model'!C15,0),"") -> 1856 | F21: =IFERROR(ROUND(('DCF Model'!C45/(1+$B21)^('DCF Model'!C19+0)+'DCF Model'!D45/(1+$B21)^('DCF Model'!C19+1)+'DCF Model'!E45/(1+$B21)^('DCF Model'!C19+2)+'DCF Model'!F45/(1+$B21)^('DCF Model'!C19+3)+'DCF Model'!G45/(1+$B21)^('DCF Model'!C19+4)+('DCF Model'!G39+'DCF Model'!G42)*F$17/(1+$B21)^('DCF Model'!C19+4)-'DCF Model'!C16)*1000000/'DCF Model'!C15,0),"") -> 1997 | G21: =IFERROR(ROUND(('DCF Model'!C45/(1+$B21)^('DCF Model'!C19+0)+'DCF Model'!D45/(1+$B21)^('DCF Model'!C19+1)+'DCF Model'!E45/(1+$B21)^('DCF Model'!C19+2)+'DCF Model'!F45/(1+$B21)^('DCF Model'!C19+3)+'DCF Model'!G45/(1+$B21)^('DCF Model'!C19+4)+('DCF Model'!G39+'DCF Model'!G42)*G$17/(1+$B21)^('DCF Model'!C19+4)-'DCF Model'!C16)*1000000/'DCF Model'!C15,0),"") -> 2138 | H21: =IFERROR(ROUND(('DCF Model'!C45/(1+$B21)^('DCF Model'!C19+0)+'DCF Model'!D45/(1+$B21)^('DCF Model'!C19+1)+'DCF Model'!E45/(1+$B21)^('DCF Model'!C19+2)+'DCF Model'!F45/(1+$B21)^('DCF Model'!C19+3)+'DCF Model'!G45/(1+$B21)^('DCF Model'!C19+4)+('DCF Model'!G39+'DCF Model'!G42)*H$17/(1+$B21)^('DCF Model'!C19+4)-'DCF Model'!C16)*1000000/'DCF Model'!C15,0),"") -> 2280 | I21: =IFERROR(ROUND(('DCF Model'!C45/(1+$B21)^('DCF Model'!C19+0)+'DCF Model'!D45/(1+$B21)^('DCF Model'!C19+1)+'DCF Model'!E45/(1+$B21)^('DCF Model'!C19+2)+'DCF Model'!F45/(1+$B21)^('DCF Model'!C19+3)+'DCF Model'!G45/(1+$B21)^('DCF Model'!C19+4)+('DCF Model'!G39+'DCF Model'!G42)*I$17/(1+$B21)^('DCF Model'!C19+4)-'DCF Model'!C16)*1000000/'DCF Model'!C15,0),"") -> 2421
B22: =$C$3+0.005 -> 0.1097 | C22: =IFERROR(ROUND(('DCF Model'!C45/(1+$B22)^('DCF Model'!C19+0)+'DCF Model'!D45/(1+$B22)^('DCF Model'!C19+1)+'DCF Model'!E45/(1+$B22)^('DCF Model'!C19+2)+'DCF Model'!F45/(1+$B22)^('DCF Model'!C19+3)+'DCF Model'!G45/(1+$B22)^('DCF Model'!C19+4)+('DCF Model'!G39+'DCF Model'!G42)*C$17/(1+$B22)^('DCF Model'!C19+4)-'DCF Model'!C16)*1000000/'DCF Model'!C15,0),"") -> 1545 | D22: =IFERROR(ROUND(('DCF Model'!C45/(1+$B22)^('DCF Model'!C19+0)+'DCF Model'!D45/(1+$B22)^('DCF Model'!C19+1)+'DCF Model'!E45/(1+$B22)^('DCF Model'!C19+2)+'DCF Model'!F45/(1+$B22)^('DCF Model'!C19+3)+'DCF Model'!G45/(1+$B22)^('DCF Model'!C19+4)+('DCF Model'!G39+'DCF Model'!G42)*D$17/(1+$B22)^('DCF Model'!C19+4)-'DCF Model'!C16)*1000000/'DCF Model'!C15,0),"") -> 1683 | E22: =IFERROR(ROUND(('DCF Model'!C45/(1+$B22)^('DCF Model'!C19+0)+'DCF Model'!D45/(1+$B22)^('DCF Model'!C19+1)+'DCF Model'!E45/(1+$B22)^('DCF Model'!C19+2)+'DCF Model'!F45/(1+$B22)^('DCF Model'!C19+3)+'DCF Model'!G45/(1+$B22)^('DCF Model'!C19+4)+('DCF Model'!G39+'DCF Model'!G42)*E$17/(1+$B22)^('DCF Model'!C19+4)-'DCF Model'!C16)*1000000/'DCF Model'!C15,0),"") -> 1821 | F22: =IFERROR(ROUND(('DCF Model'!C45/(1+$B22)^('DCF Model'!C19+0)+'DCF Model'!D45/(1+$B22)^('DCF Model'!C19+1)+'DCF Model'!E45/(1+$B22)^('DCF Model'!C19+2)+'DCF Model'!F45/(1+$B22)^('DCF Model'!C19+3)+'DCF Model'!G45/(1+$B22)^('DCF Model'!C19+4)+('DCF Model'!G39+'DCF Model'!G42)*F$17/(1+$B22)^('DCF Model'!C19+4)-'DCF Model'!C16)*1000000/'DCF Model'!C15,0),"") -> 1959 | G22: =IFERROR(ROUND(('DCF Model'!C45/(1+$B22)^('DCF Model'!C19+0)+'DCF Model'!D45/(1+$B22)^('DCF Model'!C19+1)+'DCF Model'!E45/(1+$B22)^('DCF Model'!C19+2)+'DCF Model'!F45/(1+$B22)^('DCF Model'!C19+3)+'DCF Model'!G45/(1+$B22)^('DCF Model'!C19+4)+('DCF Model'!G39+'DCF Model'!G42)*G$17/(1+$B22)^('DCF Model'!C19+4)-'DCF Model'!C16)*1000000/'DCF Model'!C15,0),"") -> 2096 | H22: =IFERROR(ROUND(('DCF Model'!C45/(1+$B22)^('DCF Model'!C19+0)+'DCF Model'!D45/(1+$B22)^('DCF Model'!C19+1)+'DCF Model'!E45/(1+$B22)^('DCF Model'!C19+2)+'DCF Model'!F45/(1+$B22)^('DCF Model'!C19+3)+'DCF Model'!G45/(1+$B22)^('DCF Model'!C19+4)+('DCF Model'!G39+'DCF Model'!G42)*H$17/(1+$B22)^('DCF Model'!C19+4)-'DCF Model'!C16)*1000000/'DCF Model'!C15,0),"") -> 2234 | I22: =IFERROR(ROUND(('DCF Model'!C45/(1+$B22)^('DCF Model'!C19+0)+'DCF Model'!D45/(1+$B22)^('DCF Model'!C19+1)+'DCF Model'!E45/(1+$B22)^('DCF Model'!C19+2)+'DCF Model'!F45/(1+$B22)^('DCF Model'!C19+3)+'DCF Model'!G45/(1+$B22)^('DCF Model'!C19+4)+('DCF Model'!G39+'DCF Model'!G42)*I$17/(1+$B22)^('DCF Model'!C19+4)-'DCF Model'!C16)*1000000/'DCF Model'!C15,0),"") -> 2372
B23: =$C$3+0.01 -> 0.1147 | C23: =IFERROR(ROUND(('DCF Model'!C45/(1+$B23)^('DCF Model'!C19+0)+'DCF Model'!D45/(1+$B23)^('DCF Model'!C19+1)+'DCF Model'!E45/(1+$B23)^('DCF Model'!C19+2)+'DCF Model'!F45/(1+$B23)^('DCF Model'!C19+3)+'DCF Model'!G45/(1+$B23)^('DCF Model'!C19+4)+('DCF Model'!G39+'DCF Model'!G42)*C$17/(1+$B23)^('DCF Model'!C19+4)-'DCF Model'!C16)*1000000/'DCF Model'!C15,0),"") -> 1516 | D23: =IFERROR(ROUND(('DCF Model'!C45/(1+$B23)^('DCF Model'!C19+0)+'DCF Model'!D45/(1+$B23)^('DCF Model'!C19+1)+'DCF Model'!E45/(1+$B23)^('DCF Model'!C19+2)+'DCF Model'!F45/(1+$B23)^('DCF Model'!C19+3)+'DCF Model'!G45/(1+$B23)^('DCF Model'!C19+4)+('DCF Model'!G39+'DCF Model'!G42)*D$17/(1+$B23)^('DCF Model'!C19+4)-'DCF Model'!C16)*1000000/'DCF Model'!C15,0),"") -> 1651 | E23: =IFERROR(ROUND(('DCF Model'!C45/(1+$B23)^('DCF Model'!C19+0)+'DCF Model'!D45/(1+$B23)^('DCF Model'!C19+1)+'DCF Model'!E45/(1+$B23)^('DCF Model'!C19+2)+'DCF Model'!F45/(1+$B23)^('DCF Model'!C19+3)+'DCF Model'!G45/(1+$B23)^('DCF Model'!C19+4)+('DCF Model'!G39+'DCF Model'!G42)*E$17/(1+$B23)^('DCF Model'!C19+4)-'DCF Model'!C16)*1000000/'DCF Model'!C15,0),"") -> 1786 | F23: =IFERROR(ROUND(('DCF Model'!C45/(1+$B23)^('DCF Model'!C19+0)+'DCF Model'!D45/(1+$B23)^('DCF Model'!C19+1)+'DCF Model'!E45/(1+$B23)^('DCF Model'!C19+2)+'DCF Model'!F45/(1+$B23)^('DCF Model'!C19+3)+'DCF Model'!G45/(1+$B23)^('DCF Model'!C19+4)+('DCF Model'!G39+'DCF Model'!G42)*F$17/(1+$B23)^('DCF Model'!C19+4)-'DCF Model'!C16)*1000000/'DCF Model'!C15,0),"") -> 1921 | G23: =IFERROR(ROUND(('DCF Model'!C45/(1+$B23)^('DCF Model'!C19+0)+'DCF Model'!D45/(1+$B23)^('DCF Model'!C19+1)+'DCF Model'!E45/(1+$B23)^('DCF Model'!C19+2)+'DCF Model'!F45/(1+$B23)^('DCF Model'!C19+3)+'DCF Model'!G45/(1+$B23)^('DCF Model'!C19+4)+('DCF Model'!G39+'DCF Model'!G42)*G$17/(1+$B23)^('DCF Model'!C19+4)-'DCF Model'!C16)*1000000/'DCF Model'!C15,0),"") -> 2056 | H23: =IFERROR(ROUND(('DCF Model'!C45/(1+$B23)^('DCF Model'!C19+0)+'DCF Model'!D45/(1+$B23)^('DCF Model'!C19+1)+'DCF Model'!E45/(1+$B23)^('DCF Model'!C19+2)+'DCF Model'!F45/(1+$B23)^('DCF Model'!C19+3)+'DCF Model'!G45/(1+$B23)^('DCF Model'!C19+4)+('DCF Model'!G39+'DCF Model'!G42)*H$17/(1+$B23)^('DCF Model'!C19+4)-'DCF Model'!C16)*1000000/'DCF Model'!C15,0),"") -> 2190 | I23: =IFERROR(ROUND(('DCF Model'!C45/(1+$B23)^('DCF Model'!C19+0)+'DCF Model'!D45/(1+$B23)^('DCF Model'!C19+1)+'DCF Model'!E45/(1+$B23)^('DCF Model'!C19+2)+'DCF Model'!F45/(1+$B23)^('DCF Model'!C19+3)+'DCF Model'!G45/(1+$B23)^('DCF Model'!C19+4)+('DCF Model'!G39+'DCF Model'!G42)*I$17/(1+$B23)^('DCF Model'!C19+4)-'DCF Model'!C16)*1000000/'DCF Model'!C15,0),"") -> 2325
B24: =$C$3+0.015 -> 0.1197 | C24: =IFERROR(ROUND(('DCF Model'!C45/(1+$B24)^('DCF Model'!C19+0)+'DCF Model'!D45/(1+$B24)^('DCF Model'!C19+1)+'DCF Model'!E45/(1+$B24)^('DCF Model'!C19+2)+'DCF Model'!F45/(1+$B24)^('DCF Model'!C19+3)+'DCF Model'!G45/(1+$B24)^('DCF Model'!C19+4)+('DCF Model'!G39+'DCF Model'!G42)*C$17/(1+$B24)^('DCF Model'!C19+4)-'DCF Model'!C16)*1000000/'DCF Model'!C15,0),"") -> 1488 | D24: =IFERROR(ROUND(('DCF Model'!C45/(1+$B24)^('DCF Model'!C19+0)+'DCF Model'!D45/(1+$B24)^('DCF Model'!C19+1)+'DCF Model'!E45/(1+$B24)^('DCF Model'!C19+2)+'DCF Model'!F45/(1+$B24)^('DCF Model'!C19+3)+'DCF Model'!G45/(1+$B24)^('DCF Model'!C19+4)+('DCF Model'!G39+'DCF Model'!G42)*D$17/(1+$B24)^('DCF Model'!C19+4)-'DCF Model'!C16)*1000000/'DCF Model'!C15,0),"") -> 1620 | E24: =IFERROR(ROUND(('DCF Model'!C45/(1+$B24)^('DCF Model'!C19+0)+'DCF Model'!D45/(1+$B24)^('DCF Model'!C19+1)+'DCF Model'!E45/(1+$B24)^('DCF Model'!C19+2)+'DCF Model'!F45/(1+$B24)^('DCF Model'!C19+3)+'DCF Model'!G45/(1+$B24)^('DCF Model'!C19+4)+('DCF Model'!G39+'DCF Model'!G42)*E$17/(1+$B24)^('DCF Model'!C19+4)-'DCF Model'!C16)*1000000/'DCF Model'!C15,0),"") -> 1752 | F24: =IFERROR(ROUND(('DCF Model'!C45/(1+$B24)^('DCF Model'!C19+0)+'DCF Model'!D45/(1+$B24)^('DCF Model'!C19+1)+'DCF Model'!E45/(1+$B24)^('DCF Model'!C19+2)+'DCF Model'!F45/(1+$B24)^('DCF Model'!C19+3)+'DCF Model'!G45/(1+$B24)^('DCF Model'!C19+4)+('DCF Model'!G39+'DCF Model'!G42)*F$17/(1+$B24)^('DCF Model'!C19+4)-'DCF Model'!C16)*1000000/'DCF Model'!C15,0),"") -> 1884 | G24: =IFERROR(ROUND(('DCF Model'!C45/(1+$B24)^('DCF Model'!C19+0)+'DCF Model'!D45/(1+$B24)^('DCF Model'!C19+1)+'DCF Model'!E45/(1+$B24)^('DCF Model'!C19+2)+'DCF Model'!F45/(1+$B24)^('DCF Model'!C19+3)+'DCF Model'!G45/(1+$B24)^('DCF Model'!C19+4)+('DCF Model'!G39+'DCF Model'!G42)*G$17/(1+$B24)^('DCF Model'!C19+4)-'DCF Model'!C16)*1000000/'DCF Model'!C15,0),"") -> 2016 | H24: =IFERROR(ROUND(('DCF Model'!C45/(1+$B24)^('DCF Model'!C19+0)+'DCF Model'!D45/(1+$B24)^('DCF Model'!C19+1)+'DCF Model'!E45/(1+$B24)^('DCF Model'!C19+2)+'DCF Model'!F45/(1+$B24)^('DCF Model'!C19+3)+'DCF Model'!G45/(1+$B24)^('DCF Model'!C19+4)+('DCF Model'!G39+'DCF Model'!G42)*H$17/(1+$B24)^('DCF Model'!C19+4)-'DCF Model'!C16)*1000000/'DCF Model'!C15,0),"") -> 2148 | I24: =IFERROR(ROUND(('DCF Model'!C45/(1+$B24)^('DCF Model'!C19+0)+'DCF Model'!D45/(1+$B24)^('DCF Model'!C19+1)+'DCF Model'!E45/(1+$B24)^('DCF Model'!C19+2)+'DCF Model'!F45/(1+$B24)^('DCF Model'!C19+3)+'DCF Model'!G45/(1+$B24)^('DCF Model'!C19+4)+('DCF Model'!G39+'DCF Model'!G42)*I$17/(1+$B24)^('DCF Model'!C19+4)-'DCF Model'!C16)*1000000/'DCF Model'!C15,0),"") -> 2280
B26: All values dynamically linked to DCF Model. Headers auto-center on current WACC / Terminal g / Exit Multiple.

Sheet Adjustments Log
B2: Adjustments Log - 第一三共
B4: 日付 | C4: セル | D4: 変更内容 | E4: 理由 | F4: 元の値 | G4: 状態
B5: 2026-09-05 | C5: - | D5: Generated by pipeline on 2026-09-05 16:58, template rev c9b5dd9 | E5: 初期生成（手修正なし） | F5: - | G5: generated
B6: 2026-09-05 | C6: DCF Model!C7 | D6: Risk-Free Rate = 2.97% | E6: 財務省 国債金利情報 jgbcm.csv 10年物 R8.9.3(2026-09-03) 2.966% を四捨五入。バッチ全銘柄共通の一次ソース。yfinance は日本国債利回りを返さないため使用しない。 | F6: テンプレ既定 2.2% | G6: 確定
B7: 2026-09-05 | C7: DCF Model!C9 | D7: Equity Risk Premium = 6.5% | E7: バッチ共通の固定前提(v2 §1-3)。銘柄固有の調整はしていない。 | F7: テンプレ既定 6.5%(同値) | G7: 設計判断
B8: 2026-09-05 | C8: DCF Model!C10 | D8: Size Premium = 1.0% | E8: 時価総額バンドによる機械決定(>3,000億円 -> 1.0%)。当社時価総額 5,084,111百万円。■テンプレートの自動規則(>=1兆円 -> 0.0%、>=1,000億円 -> 1.5%)とは異なる値であり、明示指定で上書きしている。 | F8: テンプレ自動値 | G8: 設計判断
B9: 2026-09-05 | C9: DCF Model!C8 | D9: Beta = 1.00 | E9: **yfinance が当社の beta を返さない（null）**。追補1 §A に従いテンプレのフォールバック値 1.0 を採用したが、**これは実測値ではなく推定である**。国内製薬同業の実測beta（4507 塩野義 0.028 / 4523 エーザイ −0.053 / 4503 アステラス 0.088 / 4578 大塚 −0.049 / 4151 協和キリン 0.138）は**いずれも大幅に低く**、Ke = WACC = 10.47% は過大である可能性が高い。クランプ下限 0.60 を使えば Ke は 7.87% となり Target は大きく上振れる。7974 任天堂と同型の未解決事項。 | F9: yfinance実測 null（取得不能） | G9: 推定(要確認)
B10: 2026-09-05 | C10: DCF Model!C6 | D10: Effective Tax Rate = 25% | E10: バッチ共通の既定値(v2 §1-3)。当社の実績税負担率を個別に検証したものではない。 | F10: テンプレ既定 30% | G10: 推定
B11: 2026-09-05 | C11: DCF Model!C11 | D11: After-tax Cost of Debt = 1.0%(テンプレ既定値のまま) | E11: net_debt がネットキャッシュ（−149,326百万円）で D/E = 0 のため、負債コストは WACC に一切寄与しない（WACC = Ke = 10.47%）。実績Kd の算出は結果に影響しないため interest_expense を指定していない。 | F11: テンプレ既定 | G11: 設計判断
B12: 2026-09-05 | C12: DCF Model!C13 | D12: Terminal Growth = 1.0% | E12: バッチ共通の固定前提(v2 §1-3)。 | F12: テンプレ既定 2.0% | G12: 設計判断
B13: 2026-09-05 | C13: DCF Model!C14 | D13: Exit Multiple (EV/EBITDA) = 10.8x | E13: Peer 4社の実測EV/EBITDA中央値 10.79x（4502 11.53 / 4503 7.84 / 4578 10.22 / 4507 12.64）。 自社の現在倍率 16.10x は算式に入れていない(市場価格への循環参照回避)。■マージン品質調整式はバッチ全体で棄却済み(EV/EBITDA が既に資本集約度を織り込むため、営業利益率による上方調整は資本集約型で逆方向に働く)。 | F13: テンプレ既定 10.0x | G13: 設計判断
B14: 2026-09-05 | C14: 全体(型判定・プレスクリーン) | D14: 型A(通常の事業会社)として処理 | E14: 追補1 §B に従い、型判定の前に batch/prescreen.py で EDINET有報XBRL の金融事業専用科目(ForFinancialBusiness / Banking / Deposits / CallLoan / InstallmentReceivable 系)を機械チェックした。検出結果: **CLEAN**（docID S100YEY0。金融事業専用科目は1件も検出されず）。銀行・captive finance なし（Debt/Revenue 0.14）。NonOp/OP +15.0%。OPMレンジ8.2pt・赤字年なしで型Bにも該当しない。 | F14: - | G14: 設計判断
B15: 2026-09-05 | C15: DCF Model!C9(株価) / C15(株数) | D15: current_price = 2,794円 / shares_outstanding = 1,819,653,230株 を明示指定 | E15: 【リトライ1回目・サイレントフォールバックの是正】初回生成では生成ログに 'Successfully fetched' 行が無く、yfinance の市場データ取得が失敗して **テンプレのプレースホルダ（株価 1,000円 / 株数 10,000,000株）にフォールバック**していた。その結果 時価総額が 10,000百万円（正しくは 5,084,111百万円）となり、**Target が 294,427円 / BUY +293% という無意味な値**になっていた。**validate は FAIL 0 のまま通過している**（構造チェックは株価・株数の妥当性を見ない）。追補2 §F の『サイレントフォールバック禁止』の原則に従い明示指定して再生成した。■検算: 2,794円 × 1,819,653,230株 = 5,084,111百万円 = yfinance の時価総額と一致。■**再発防止**: batch/check_market_data.py を新設し全生成物の株価・株数をキャッシュと機械照合する運用にした（既存23銘柄は全件 OK、当社のみが該当）。以後の全銘柄では batch/preemptive_block.py が current_price / shares_outstanding を予防的に明示供給する。■**これは _val 由来ではない新種の欠陥**であり、追補2 §I の『未知パターン』1件目として記録する。 | F15: テンプレのプレースホルダ（1,000円 / 10,000,000株） | G15: 設計判断
... B28: 2026-09-05 | C28: 全体(未解決) | D28: capex 逓減の仮定 | E28: 実績 capex は売上比 10.0% まで上昇。5年で D&A 水準（3.6%）まで下げる仮定は会社計画ではなく本モデルの設計判断。 | F28: - | G28: 未解決
B30: Pipeline Metadata (do not edit — read by scripts/validate_output.py)
B31: key | C31: value
B32: auto_log_entries | C32: 0
B33: capex_pct_basis | C33: assumption
B34: capex_pct_c5 | C34: 0.0378
B35: capex_pct_hist3yr | C35: n/a
B36: company_name | C36: 第一三共
B37: comps_asof | C37: 2026-09-05
B38: comps_da_missing | C38: none
B39: comps_ev_ebitda_invalid | C39: no
B40: comps_ev_ebitda_rows | C40: 6,7,8,9
B41: comps_impl_mult_row | C41: 27
B42: comps_impl_per_row | C42: 28
... B64: ticker | C64: 4568.T
