Workbook

Sheet Executive Summary
B1: DISCLAIMER: This is a sample analysis for demonstration purposes only. It does not constitute investment advice.
B3: Osaka Titanium Technologies (5726.T)
B4: Equity Research Report
B6: Company | C6: Osaka Titanium Technologies
B7: Ticker | C7: 5726.T (TSE Prime)
B8: Sector | C8: Sponge Titanium / Aerospace Materials
B9: Current Price | C9: 2727
B10: Target Price (DCF Mid) | C10: =IFERROR(ROUND(AVERAGE(C16:C17),0),"INVALID") -> 379
B11: Recommendation | C11: =IF(ISNUMBER(C10),IF(C12>0.15,"BUY",IF(C12>0.05,"HOLD","SELL")),"N/A") -> SELL
B12: Upside / Downside | C12: =IF(ISNUMBER(C10),(C10-C9)/C9,"N/A") -> -0.86101944
B14: Valuation Summary
B15: Methodology | C15: Implied Value (JPY) | D15: vs Current Price
B16: DCF - Perpetuity Growth | C16: =IF('DCF Model'!C53<'DCF Model'!C16,"INVALID (EV < net debt)",'DCF Model'!C55) -> 200 | D16: =IF(ISNUMBER(C16),(C16-C9)/C9,"N/A") -> -0.92665933
B17: DCF - Exit Multiple | C17: =IF('DCF Model'!C63<0,"INVALID (equity < 0)",'DCF Model'!C64) -> 558 | D17: =IF(ISNUMBER(C17),(C17-C9)/C9,"N/A") -> -0.79537954
B18: Comps - EV/EBITDA Median [参考・Target除外] | C18: ='Comps Analysis'!C27 -> 1582 | D18: =IF(ISNUMBER(C18),(C18-C9)/C9,"N/A") -> -0.41987532
B19: Comps - PER Median [参考・Target除外/分母歪み] | C19: ='Comps Analysis'!C28 -> 2247 | D19: =IF(ISNUMBER(C19),(C19-C9)/C9,"N/A") -> -0.1760176
B21: DCF Valuation Range (PGM - Exit) | C21: =MIN(C16:C17)&" - "&MAX(C16:C17) -> 200 - 558
B23: Key Investment Thesis
B24: Osaka Titanium is now the only listed pure-play sponge titanium producer in Japan: Toho Titanium, the other half of the domestic duopoly, was delisted on 28 May 2026 when JX Advanced Metals took it over in a share exchange at 0.70 JX shares per Toho share.
B25: Aerospace build rates, the replacement of Russian VSMPO-AVISMA supply and defence programmes all pull on the same narrow sponge capacity; the company is funding an expansion, with construction in progress up to JPY4.3bn at the end of Q1 FY3/27 after drawing JPY16.4bn of long-term borrowings in FY3/26.
B26: ="At "&TEXT(C9,"#,##0")&" the shares trade at "&TEXT('Comps Analysis'!L5,"0.0""x""")&" earnings and "&TEXT('Comps Analysis'!M5,"0.00""x""")&" book against a target of "&TEXT(C10,"#,##0")&" ("&TEXT(C12,"+0.0%;-0.0%")&") at a WACC of "&TEXT('DCF Model'!C26,"0.00%")&", so the case has to be argued on the reverse DCF, not on the base case." -> At 2,727 the shares trade at 39.0x earnings and 2.26x book against a target of 379 (-86.1%) at a WACC of 9.06%, so the case has to be argued on the reverse DCF, not on the base case.
B28: Key Risks
B29: Working capital is enormous and sticky: inventory was JPY36.9bn at FY3/26 against JPY35.4bn of annual cost of sales, or 380 days, so a volume recovery consumes cash long before it produces free cash flow.
B30: Net debt of JPY45.8bn sits against JPY44.3bn of book equity while capex runs at roughly 2.6x depreciation; if the aerospace build rate slips, the expanded capacity turns into fixed cost against a falling sponge price.
B31: The reverse DCF shows the price already discounts a steady-state operating profit well above the FY3/25 peak of JPY10.1bn, so a return to mid-cycle margins alone does not support it.

Sheet Financial Statements
B2: Osaka Titanium Technologies - Historical Financials (JPY mn)
C4: FY2022/3 | D4: FY2023/3 | E4: FY2024/3 | F4: FY2025/3 | G4: FY2026/3
B5: Income Statement
B6: Revenue | C6: 28549 | D6: 43074 | E6: 55322 | F6: 51914 | G6: 46952
B7: COGS | C7: 26229 | D7: 34099 | E7: 41878 | F7: 35783 | G7: 35399
B8: Gross Profit | C8: =C6-C7 -> 2320 | D8: =D6-D7 -> 8975 | E8: =E6-E7 -> 13444 | F8: =F6-F7 -> 16131 | G8: =G6-G7 -> 11553
B9: Gross Margin | C9: =C8/C6 -> 0.081263792 | D9: =D8/D6 -> 0.20836235 | E9: =E8/E6 -> 0.24301363 | F9: =F8/F6 -> 0.31072543 | G9: =G8/G6 -> 0.24605981
B10: SGA | C10: 4235 | D10: 4195 | E10: 5154 | F10: 6041 | G10: 6028
B11: Operating Income | C11: -1914 | D11: 4780 | E11: 8288 | F11: 10088 | G11: 5524
B12: Net Income | C12: -3112 | D12: 4388 | E12: 9689 | F12: 7090 | G12: 2576
B13: Operating Margin | C13: =C11/C6 -> -0.067042628 | D13: =D11/D6 -> 0.11097182 | E13: =E11/E6 -> 0.14981382 | F13: =F11/F6 -> 0.19432138 | G13: =G11/G6 -> 0.11765207
B14: Net Margin | C14: =C12/C6 -> -0.10900557 | D14: =D12/D6 -> 0.1018712 | E14: =E12/E6 -> 0.17513828 | F14: =F12/F6 -> 0.13657202 | G14: =G12/G6 -> 0.054864543
B15: Revenue Growth (YoY) | C15: n/a | D15: =(D6-C6)/C6 -> 0.50877439 | E15: =(E6-D6)/D6 -> 0.28434787 | F15: =(F6-E6)/E6 -> -0.061602979 | G15: =(G6-F6)/F6 -> -0.095581153
B16: Operating Income Growth (YoY) | C16: n/a | D16: =(D11-C11)/C11 -> -3.4973877 | E16: =(E11-D11)/D11 -> 0.73389121 | F16: =(F11-E11)/E11 -> 0.21718147 | G16: =(G11-F11)/F11 -> -0.45241872
B18: Cash Flow Statement
B19: Operating Cash Flow | C19: 6304 | D19: 741 | E19: 2098 | F19: 2859 | G19: 4169
B20: Capex | C20: 996 | D20: 2357 | E20: 2717 | F20: 2916 | G20: 8072
B21: Free Cash Flow | C21: =C19-C20 -> 5308 | D21: =D19-D20 -> -1616 | E21: =E19-E20 -> -619 | F21: =F19-F20 -> -57 | G21: =G19-G20 -> -3903
B22: FCF Margin | C22: =C21/C6 -> 0.18592595 | D22: =D21/D6 -> -0.037516831 | E22: =E21/E6 -> -0.011189039 | F22: =F21/F6 -> -0.0010979697 | G22: =G21/G6 -> -0.083127449
B23: Capex / Revenue | C23: =C20/C6 -> 0.034887387 | D23: =D20/D6 -> 0.054719785 | E23: =E20/E6 -> 0.049112469 | F23: =F20/F6 -> 0.056169819 | G23: =G20/G6 -> 0.17192026
B25: Balance Sheet Highlights
B26: Cash & Deposits | C26: 10666 | D26: 6971 | E26: 5975 | F26: 4619 | G26: 4145
B27: Total Interest-bearing Debt (short + long) | C27: 40500 | D27: 40500 | E27: 40100 | F27: 43700 | G27: 49800
B28: Net Debt (Cash) | C28: =C27-C26 -> 29834 | D28: =D27-D26 -> 33529 | E28: =E27-E26 -> 34125 | F28: =F27-F26 -> 39081 | G28: =G27-G26 -> 45655
B30: Note: OCF / Cash / Debt coverage OCF 5/5, Cash 5/5, Debt 5/5 — blank cells are years with no year-key match in the source data (verify against 決算短信 or set hist_ocf / hist_cash / hist_debt in overrides).

Sheet DCF Model
B2: DCF Valuation Model - Osaka Titanium Technologies
B4: Assumptions
B5: Capex / Revenue (hist 3yr avg, fallback) | C5: 0.0924
B6: Effective Tax Rate | C6: 0.306
B7: Risk-Free Rate | C7: 0.029
B8: Beta | C8: 1.55
B9: Equity Risk Premium | C9: 0.055
B10: Size Premium | C10: 0.015
B11: After-tax Cost of Debt | C11: 0.0059
B12: D/E Ratio | C12: 0.4568
B13: Terminal Growth Rate | C13: 0.015
B14: Exit Multiple (EV/EBITDA) | C14: 8
B15: Fully Diluted Shares | C15: 36800000
B16: Net Debt (JPY mn) | C16: 45837
... B20: LTM Revenue (JPY mn) (override) | C20: 47228
B22: WACC Calculation
B23: Cost of Equity (Ke) | C23: =C7+C8*C9+C10 -> 0.12925
B24: Weight of Equity | C24: =1/(1+C12) -> 0.68643602
B25: Weight of Debt | C25: =C12/(1+C12) -> 0.31356398
B26: WACC | C26: =C23*C24+C11*C25 -> 0.090571884
B27: Active Scenario | C27: Base | D27: =MATCH(C27,B69:B73,0) -> 1
B28: Projected Free Cash Flow
C29: FY2027(E) | D29: FY2028(E) | E29: FY2029(E) | F29: FY2030(E) | G29: FY2031(E)
B30: Revenue Growth (YoY) | C30: =CHOOSE($D$27,C69,C70,C71,C72,C73) -> 0.066 | D30: =CHOOSE($D$27,D69,D70,D71,D72,D73) -> 0.06 | E30: =CHOOSE($D$27,E69,E70,E71,E72,E73) -> 0.05 | F30: =CHOOSE($D$27,F69,F70,F71,F72,F73) -> 0.04 | G30: =CHOOSE($D$27,G69,G70,G71,G72,G73) -> 0.03
B31: COGS % of Revenue | C31: =CHOOSE($D$27,C76,C77,C78,C79,C80) -> 0.795 | D31: =CHOOSE($D$27,D76,D77,D78,D79,D80) -> 0.782 | E31: =CHOOSE($D$27,E76,E77,E78,E79,E80) -> 0.77 | F31: =CHOOSE($D$27,F76,F77,F78,F79,F80) -> 0.767 | G31: =CHOOSE($D$27,G76,G77,G78,G79,G80) -> 0.768
B32: SGA % of Revenue | C32: =CHOOSE($D$27,C83,C84,C85,C86,C87) -> 0.122 | D32: =CHOOSE($D$27,D83,D84,D85,D86,D87) -> 0.118 | E32: =CHOOSE($D$27,E83,E84,E85,E86,E87) -> 0.115 | F32: =CHOOSE($D$27,F83,F84,F85,F86,F87) -> 0.113 | G32: =CHOOSE($D$27,G83,G84,G85,G86,G87) -> 0.112
B33: Revenue | C33: =C17*(1+C30) -> 50050.832 | D33: =C33*(1+D30) -> 53053.882 | E33: =D33*(1+E30) -> 55706.576 | F33: =E33*(1+F30) -> 57934.839 | G33: =F33*(1+G30) -> 59672.884
B34: COGS | C34: =C33*C31 -> 39790.411 | D34: =D33*D31 -> 41488.136 | E34: =E33*E31 -> 42894.064 | F34: =F33*F31 -> 44436.022 | G34: =G33*G31 -> 45828.775
B35: Gross Profit | C35: =C33-C34 -> 10260.421 | D35: =D33-D34 -> 11565.746 | E35: =E33-E34 -> 12812.512 | F35: =F33-F34 -> 13498.818 | G35: =G33-G34 -> 13844.109
B36: Gross Margin | C36: =C35/C33 -> 0.205 | D36: =D35/D33 -> 0.218 | E36: =E35/E33 -> 0.23 | F36: =F35/F33 -> 0.233 | G36: =G35/G33 -> 0.232
B37: SGA Expense | C37: =C33*C32 -> 6106.2015 | D37: =D33*D32 -> 6260.3581 | E37: =E33*E32 -> 6406.2562 | F37: =F33*F32 -> 6546.6368 | G37: =G33*G32 -> 6683.363
B38: Implied Operating Margin | C38: =(C35-C37)/C33 -> 0.083 | D38: =(D35-D37)/D33 -> 0.1 | E38: =(E35-E37)/E33 -> 0.115 | F38: =(F35-F37)/F33 -> 0.12 | G38: =(G35-G37)/G33 -> 0.12
B39: Operating Income (EBIT) | C39: =C35-C37 -> 4154.2191 | D39: =D35-D37 -> 5305.3882 | E39: =E35-E37 -> 6406.2562 | F39: =F35-F37 -> 6952.1807 | G39: =G35-G37 -> 7160.7461
B40: Less: Tax | C40: =MAX(0,C39*C6) -> 1271.191 | D40: =MAX(0,D39*C6) -> 1623.4488 | E40: =MAX(0,E39*C6) -> 1960.3144 | F40: =MAX(0,F39*C6) -> 2127.3673 | G40: =MAX(0,G39*C6) -> 2191.1883
B41: NOPAT | C41: =C39-C40 -> 2883.028 | D41: =D39-D40 -> 3681.9394 | E41: =E39-E40 -> 4445.9418 | F41: =F39-F40 -> 4824.8134 | G41: =G39-G40 -> 4969.5578
B42: Plus: D&A | C42: 3400 | D42: 3700 | E42: 3900 | F42: 3950 | G42: 3950
B43: Less: Capex | C43: 7500 | D43: 6000 | E43: 4800 | F43: 4100 | G43: 3900
B44: Change in NWC | C44: ='NWC Schedule'!D19 -> 2678.0211 | D44: ='NWC Schedule'!E19 -> 238.88371 | E44: ='NWC Schedule'!F19 -> -394.27029 | F44: ='NWC Schedule'!G19 -> -373.83539 | G44: ='NWC Schedule'!H19 -> -119.3172
B45: Unlevered Free Cash Flow | C45: =C41+C42-C43-C44 -> -3894.9931 | D45: =D41+D42-D43-D44 -> 1143.0557 | E45: =E41+E42-E43-E44 -> 3940.2121 | F45: =F41+F42-F43-F44 -> 5048.6488 | G45: =G41+G42-G43-G44 -> 5138.875
B46: Discount Factor | C46: =1/(1+C26)^(C19+0) -> 0.93704248 | D46: =1/(1+C26)^(C19+1) -> 0.85922119 | E46: =1/(1+C26)^(C19+2) -> 0.78786296 | F46: =1/(1+C26)^(C19+3) -> 0.72243102 | G46: =1/(1+C26)^(C19+4) -> 0.6624332
B47: PV of FCF | C47: =C45*C46 -> -3649.7739 | D47: =D45*D46 -> 982.13768 | E47: =E45*E46 -> 3104.3472 | F47: =F45*F46 -> 3647.3005 | G47: =G45*G46 -> 3404.1614
B49: Valuation - Perpetuity Growth Method
B50: Sum of PV of FCFs | C50: =SUM(C47:G47) -> 7488.1728
B51: Terminal Value (PGM) | C51: =G45*(1+C13)/(C26-C13) -> 69019.824
B52: PV of Terminal Value | C52: =C51*G46 -> 45721.023
B53: Enterprise Value | C53: =C50+C52 -> 53209.196
B54: Equity Value | C54: =C53-C16 -> 7372.1958
B55: Implied Share Price (PGM) | C55: =ROUND(C54*1000000/C15,0) -> 200
B57: Valuation - Exit Multiple Method
B58: Sum of PV of FCFs | C58: =C50 -> 7488.1728
B59: Year 5 EBITDA | C59: =G39+G42 -> 11110.746
B60: Terminal Value (Exit Multiple) | C60: =C59*C14 -> 88885.969
B61: PV of Terminal Value | C61: =C60*G46 -> 58881.017
B62: Enterprise Value | C62: =C58+C61 -> 66369.19
B63: Equity Value | C63: =C62-C16 -> 20532.19
B64: Implied Share Price (Exit Multiple) | C64: =ROUND(C63*1000000/C15,0) -> 558
B66: Scenario Input Matrix
C67: Year 1 | D67: Year 2 | E67: Year 3 | F67: Year 4 | G67: Year 5
B68: Revenue Growth (YoY)
B69: Base | C69: 0.066 | D69: 0.06 | E69: 0.05 | F69: 0.04 | G69: 0.03
B70: Upside | C70: 0.1 | D70: 0.12 | E70: 0.1 | F70: 0.07 | G70: 0.04
B71: Management | C71: 0.0223 | D71: 0.08 | E71: 0.07 | F71: 0.05 | G71: 0.03
B72: Downside 1 | C72: 0 | D72: 0.02 | E72: 0.03 | F72: 0.03 | G72: 0.02
B73: Downside 2 | C73: -0.06 | D73: -0.05 | E73: 0 | F73: 0.02 | G73: 0.02
B75: COGS % of Revenue
B76: Base | C76: 0.795 | D76: 0.782 | E76: 0.77 | F76: 0.767 | G76: 0.768
B77: Upside | C77: 0.78 | D77: 0.748 | E77: 0.723 | F77: 0.716 | G77: 0.722
B78: Management | C78: 0.797 | D78: 0.78 | E78: 0.766 | F78: 0.758 | G78: 0.759
B79: Downside 1 | C79: 0.802 | D79: 0.794 | E79: 0.78 | F79: 0.772 | G79: 0.767
B80: Downside 2 | C80: 0.825 | D80: 0.832 | E80: 0.833 | F80: 0.829 | G80: 0.826
B82: SGA % of Revenue
B83: Base | C83: 0.122 | D83: 0.118 | E83: 0.115 | F83: 0.113 | G83: 0.112
B84: Upside | C84: 0.12 | D84: 0.112 | E84: 0.107 | F84: 0.104 | G84: 0.103
B85: Management | C85: 0.126 | D85: 0.12 | E85: 0.114 | F85: 0.112 | G85: 0.111
B86: Downside 1 | C86: 0.128 | D86: 0.126 | E86: 0.125 | F86: 0.123 | G86: 0.123
B87: Downside 2 | C87: 0.135 | D87: 0.138 | E87: 0.137 | F87: 0.136 | G87: 0.134

Sheet Reverse DCF
B2: Reverse DCF - Osaka Titanium Technologies (5726.T)
B3: What is the current share price already assuming? Every value below is a live formula off the other sheets.
B5: Block 0: Market-implied enterprise value (live)
B6: Current Share Price (JPY) | C6: ='Executive Summary'!C9 -> 2727
B7: Fully Diluted Shares | C7: ='DCF Model'!C15 -> 36800000
B8: Market Capitalisation (JPY mn) | C8: =C6*C7/1000000 -> 100353.6
B9: Net Debt (JPY mn) | C9: ='DCF Model'!C16 -> 45837
B10: Enterprise Value (JPY mn) | C10: =C8+C9 -> 146190.6
B11: WACC (w) | C11: ='DCF Model'!C26 -> 0.090571884
B12: Terminal Growth (g) | C12: ='DCF Model'!C13 -> 0.015
B13: Effective Tax Rate (t) | C13: ='DCF Model'!C6 -> 0.306
B14: Starting Operating Profit OP0 (FY2026/3 actual) | C14: 5524
B15: Cycle-peak Operating Profit (FY2025/3 actual) | C15: 10088
B16: Base-case Year 5 Revenue (JPY mn) | C16: ='DCF Model'!G33 -> 59672.884
B17: Base-case DCF Enterprise Value, PGM (JPY mn) | C17: ='DCF Model'!C53 -> 53209.196
B18: Cycle-peak Operating Margin (FY2025/3 actual) | C18: 0.194
B19: Gap: market EV less base-case DCF EV (JPY mn) | C19: =C10-C17 -> 92981.404
B20: Gap per share (JPY) - the part of the price the base case does not explain | C20: =ROUND(C19*1000000/C7,0) -> 2527
B22: Block A: Required steady-state operating profit, reached IMMEDIATELY (no ramp)
B23: The lowest bar the price can clear: today's EV read as a perpetuity of one steady-state profit, capex = D&A, no NWC build.
B24: Required steady-state NOPAT (JPY mn) | C24: =C10*(C11-C12) -> 11047.899
B25: Required steady-state Operating Profit (JPY mn) | C25: =C24/(1-C13) -> 15919.163
B26: ... as a multiple of the FY2025/3 peak | C26: =C25/C15 -> 1.5780296
B27: ... as a multiple of FY2026/3 actual | C27: =C25/C14 -> 2.881818
B28: ... implied OPM on base-case Year 5 revenue | C28: =C25/C16 -> 0.26677381
B29: ... revenue needed if margins only reach the cycle peak | C29: =C25/C18 -> 82057.54
B32: Block B: Required steady-state operating profit by YEARS-TO-REACH (linear ramp) x WACC
B33: Operating profit ramps linearly from OP0 (C14) to OP* over N years, then grows at g for ever. Column F is the model WACC.
B34: OP* = ( EV/(1-t) - OP0*(A-B) ) / ( B + TVF ). A longer ramp needs a HIGHER steady state, because more years are spent below it.
B36: Years to steady state (N) \ WACC | C36: N | D36: ='DCF Model'!C26-0.02 -> 0.070571884 | E36: ='DCF Model'!C26-0.01 -> 0.080571884 | F36: ='DCF Model'!C26 -> 0.090571884 | G36: ='DCF Model'!C26+0.01 -> 0.10057188 | H36: ='DCF Model'!C26+0.02 -> 0.11057188
B37: B-1 PV weight on the RAMP from OP0 (A - B)
B38: N = 3 years | C38: 3 | D38: =(1-(1+D$36)^(-$C38))/D$36-(1+D$36)/(D$36^2*$C38)*(1-($C38+1)/(1+D$36)^$C38+$C38/(1+D$36)^($C38+1)) -> 0.91355541 | E38: =(1-(1+E$36)^(-$C38))/E$36-(1+E$36)/(E$36^2*$C38)*(1-($C38+1)/(1+E$36)^$C38+$C38/(1+E$36)^($C38+1)) -> 0.90243445 | F38: =(1-(1+F$36)^(-$C38))/F$36-(1+F$36)/(F$36^2*$C38)*(1-($C38+1)/(1+F$36)^$C38+$C38/(1+F$36)^($C38+1)) -> 0.8915659 | G38: =(1-(1+G$36)^(-$C38))/G$36-(1+G$36)/(G$36^2*$C38)*(1-($C38+1)/(1+G$36)^$C38+$C38/(1+G$36)^($C38+1)) -> 0.88094156 | H38: =(1-(1+H$36)^(-$C38))/H$36-(1+H$36)/(H$36^2*$C38)*(1-($C38+1)/(1+H$36)^$C38+$C38/(1+H$36)^($C38+1)) -> 0.87055358
B39: N = 5 years | C39: 5 | D39: =(1-(1+D$36)^(-$C39))/D$36-(1+D$36)/(D$36^2*$C39)*(1-($C39+1)/(1+D$36)^$C39+$C39/(1+D$36)^($C39+1)) -> 1.7490171 | E39: =(1-(1+E$36)^(-$C39))/E$36-(1+E$36)/(E$36^2*$C39)*(1-($C39+1)/(1+E$36)^$C39+$C39/(1+E$36)^($C39+1)) -> 1.7179317 | F39: =(1-(1+F$36)^(-$C39))/F$36-(1+F$36)/(F$36^2*$C39)*(1-($C39+1)/(1+F$36)^$C39+$C39/(1+F$36)^($C39+1)) -> 1.6878144 | G39: =(1-(1+G$36)^(-$C39))/G$36-(1+G$36)/(G$36^2*$C39)*(1-($C39+1)/(1+G$36)^$C39+$C39/(1+G$36)^($C39+1)) -> 1.6586241 | H39: =(1-(1+H$36)^(-$C39))/H$36-(1+H$36)/(H$36^2*$C39)*(1-($C39+1)/(1+H$36)^$C39+$C39/(1+H$36)^($C39+1)) -> 1.6303216
B40: N = 7 years | C40: 7 | D40: =(1-(1+D$36)^(-$C40))/D$36-(1+D$36)/(D$36^2*$C40)*(1-($C40+1)/(1+D$36)^$C40+$C40/(1+D$36)^($C40+1)) -> 2.5138783 | E40: =(1-(1+E$36)^(-$C40))/E$36-(1+E$36)/(E$36^2*$C40)*(1-($C40+1)/(1+E$36)^$C40+$C40/(1+E$36)^($C40+1)) -> 2.4558897 | F40: =(1-(1+F$36)^(-$C40))/F$36-(1+F$36)/(F$36^2*$C40)*(1-($C40+1)/(1+F$36)^$C40+$C40/(1+F$36)^($C40+1)) -> 2.4001769 | G40: =(1-(1+G$36)^(-$C40))/G$36-(1+G$36)/(G$36^2*$C40)*(1-($C40+1)/(1+G$36)^$C40+$C40/(1+G$36)^($C40+1)) -> 2.346621 | H40: =(1-(1+H$36)^(-$C40))/H$36-(1+H$36)/(H$36^2*$C40)*(1-($C40+1)/(1+H$36)^$C40+$C40/(1+H$36)^($C40+1)) -> 2.2951103
B41: N = 10 years | C41: 10 | D41: =(1-(1+D$36)^(-$C41))/D$36-(1+D$36)/(D$36^2*$C41)*(1-($C41+1)/(1+D$36)^$C41+$C41/(1+D$36)^($C41+1)) -> 3.5433208 | E41: =(1-(1+E$36)^(-$C41))/E$36-(1+E$36)/(E$36^2*$C41)*(1-($C41+1)/(1+E$36)^$C41+$C41/(1+E$36)^($C41+1)) -> 3.4353678 | F41: =(1-(1+F$36)^(-$C41))/F$36-(1+F$36)/(F$36^2*$C41)*(1-($C41+1)/(1+F$36)^$C41+$C41/(1+F$36)^($C41+1)) -> 3.3328956 | G41: =(1-(1+G$36)^(-$C41))/G$36-(1+G$36)/(G$36^2*$C41)*(1-($C41+1)/(1+G$36)^$C41+$C41/(1+G$36)^($C41+1)) -> 3.2355406 | H41: =(1-(1+H$36)^(-$C41))/H$36-(1+H$36)/(H$36^2*$C41)*(1-($C41+1)/(1+H$36)^$C41+$C41/(1+H$36)^($C41+1)) -> 3.142968
B42: B-2 PV weight on the STEADY STATE OP* (B + terminal factor)
B43: N = 3 years | C43: 3 | D43: =(1+D$36)/(D$36^2*$C43)*(1-($C43+1)/(1+D$36)^$C43+$C43/(1+D$36)^($C43+1))+(1+$C$12)/((D$36-$C$12)*(1+D$36)^$C43) -> 16.593521 | E43: =(1+E$36)/(E$36^2*$C43)*(1-($C43+1)/(1+E$36)^$C43+$C43/(1+E$36)^($C43+1))+(1+$C$12)/((E$36-$C$12)*(1+E$36)^$C43) -> 13.94039 | F43: =(1+F$36)/(F$36^2*$C43)*(1-($C43+1)/(1+F$36)^$C43+$C43/(1+F$36)^($C43+1))+(1+$C$12)/((F$36-$C$12)*(1+F$36)^$C43) -> 11.991979 | G43: =(1+G$36)/(G$36^2*$C43)*(1-($C43+1)/(1+G$36)^$C43+$C43/(1+G$36)^($C43+1))+(1+$C$12)/((G$36-$C$12)*(1+G$36)^$C43) -> 10.501149 | H43: =(1+H$36)/(H$36^2*$C43)*(1-($C43+1)/(1+H$36)^$C43+$C43/(1+H$36)^($C43+1))+(1+$C$12)/((H$36-$C$12)*(1+H$36)^$C43) -> 9.3241983
B44: N = 5 years | C44: 5 | D44: =(1+D$36)/(D$36^2*$C44)*(1-($C44+1)/(1+D$36)^$C44+$C44/(1+D$36)^($C44+1))+(1+$C$12)/((D$36-$C$12)*(1+D$36)^$C44) -> 15.332595 | E44: =(1+E$36)/(E$36^2*$C44)*(1-($C44+1)/(1+E$36)^$C44+$C44/(1+E$36)^($C44+1))+(1+$C$12)/((E$36-$C$12)*(1+E$36)^$C44) -> 12.7758 | F44: =(1+F$36)/(F$36^2*$C44)*(1-($C44+1)/(1+F$36)^$C44+$C44/(1+F$36)^($C44+1))+(1+$C$12)/((F$36-$C$12)*(1+F$36)^$C44) -> 10.902386 | G44: =(1+G$36)/(G$36^2*$C44)*(1-($C44+1)/(1+G$36)^$C44+$C44/(1+G$36)^($C44+1))+(1+$C$12)/((G$36-$C$12)*(1+G$36)^$C44) -> 9.472495 | H44: =(1+H$36)/(H$36^2*$C44)*(1-($C44+1)/(1+H$36)^$C44+$C44/(1+H$36)^($C44+1))+(1+$C$12)/((H$36-$C$12)*(1+H$36)^$C44) -> 8.3466721
B45: N = 7 years | C45: 7 | D45: =(1+D$36)/(D$36^2*$C45)*(1-($C45+1)/(1+D$36)^$C45+$C45/(1+D$36)^($C45+1))+(1+$C$12)/((D$36-$C$12)*(1+D$36)^$C45) -> 14.196514 | E45: =(1+E$36)/(E$36^2*$C45)*(1-($C45+1)/(1+E$36)^$C45+$C45/(1+E$36)^($C45+1))+(1+$C$12)/((E$36-$C$12)*(1+E$36)^$C45) -> 11.738867 | F45: =(1+F$36)/(F$36^2*$C45)*(1-($C45+1)/(1+F$36)^$C45+$C45/(1+F$36)^($C45+1))+(1+$C$12)/((F$36-$C$12)*(1+F$36)^$C45) -> 9.9433793 | G45: =(1+G$36)/(G$36^2*$C45)*(1-($C45+1)/(1+G$36)^$C45+$C45/(1+G$36)^($C45+1))+(1+$C$12)/((G$36-$C$12)*(1+G$36)^$C45) -> 8.5772993 | H45: =(1+H$36)/(H$36^2*$C45)*(1-($C45+1)/(1+H$36)^$C45+$C45/(1+H$36)^($C45+1))+(1+$C$12)/((H$36-$C$12)*(1+H$36)^$C45) -> 7.505328
B46: N = 10 years | C46: 10 | D46: =(1+D$36)/(D$36^2*$C46)*(1-($C46+1)/(1+D$36)^$C46+$C46/(1+D$36)^($C46+1))+(1+$C$12)/((D$36-$C$12)*(1+D$36)^$C46) -> 12.697065 | E46: =(1+E$36)/(E$36^2*$C46)*(1-($C46+1)/(1+E$36)^$C46+$C46/(1+E$36)^($C46+1))+(1+$C$12)/((E$36-$C$12)*(1+E$36)^$C46) -> 10.389446 | F46: =(1+F$36)/(F$36^2*$C46)*(1-($C46+1)/(1+F$36)^$C46+$C46/(1+F$36)^($C46+1))+(1+$C$12)/((F$36-$C$12)*(1+F$36)^$C46) -> 8.7123248 | G46: =(1+G$36)/(G$36^2*$C46)*(1-($C46+1)/(1+G$36)^$C46+$C46/(1+G$36)^($C46+1))+(1+$C$12)/((G$36-$C$12)*(1+G$36)^$C46) -> 7.4433252 | H46: =(1+H$36)/(H$36^2*$C46)*(1-($C46+1)/(1+H$36)^$C46+$C46/(1+H$36)^($C46+1))+(1+$C$12)/((H$36-$C$12)*(1+H$36)^$C46) -> 6.4532496
B47: B-3 REQUIRED steady-state Operating Profit (JPY mn)
B48: N = 3 years | C48: 3 | D48: =($C$10/(1-$C$13)-$C$14*D38)/D43 -> 12390.547 | E48: =($C$10/(1-$C$13)-$C$14*E38)/E43 -> 14753.118 | F48: =($C$10/(1-$C$13)-$C$14*F38)/F43 -> 17155.155 | G48: =($C$10/(1-$C$13)-$C$14*G38)/G43 -> 19596.233 | H48: =($C$10/(1-$C$13)-$C$14*H38)/H43 -> 22075.929
B49: N = 5 years | C49: 5 | D49: =($C$10/(1-$C$13)-$C$14*D39)/D44 -> 13108.525 | E49: =($C$10/(1-$C$13)-$C$14*E39)/E44 -> 15745.349 | F49: =($C$10/(1-$C$13)-$C$14*F39)/F44 -> 18466.214 | G49: =($C$10/(1-$C$13)-$C$14*G39)/G44 -> 21270.747 | H49: =($C$10/(1-$C$13)-$C$14*H39)/H44 -> 24158.537
B50: N = 7 years | C50: 7 | D50: =($C$10/(1-$C$13)-$C$14*D40)/D45 -> 13859.925 | E50: =($C$10/(1-$C$13)-$C$14*E40)/E45 -> 16788.924 | F50: =($C$10/(1-$C$13)-$C$14*F40)/F45 -> 19851.471 | G50: =($C$10/(1-$C$13)-$C$14*G40)/G45 -> 23047.645 | H50: =($C$10/(1-$C$13)-$C$14*H40)/H45 -> 26377.407
B51: N = 10 years | C51: 10 | D51: =($C$10/(1-$C$13)-$C$14*D41)/D46 -> 15048.83 | E51: =($C$10/(1-$C$13)-$C$14*E41)/E46 -> 18448.751 | F51: =($C$10/(1-$C$13)-$C$14*F41)/F46 -> 22065.105 | G51: =($C$10/(1-$C$13)-$C$14*G41)/G46 -> 25899.198 | H51: =($C$10/(1-$C$13)-$C$14*H41)/H46 -> 29951.968
B52: B-4 ... as a multiple of the FY2025/3 peak operating profit
B53: N = 3 years | C53: 3 | D53: =D48/$C$15 -> 1.2282461 | E53: =E48/$C$15 -> 1.4624424 | F53: =F48/$C$15 -> 1.7005507 | G53: =G48/$C$15 -> 1.942529 | H53: =H48/$C$15 -> 2.1883356
B54: N = 5 years | C54: 5 | D54: =D49/$C$15 -> 1.2994177 | E54: =E49/$C$15 -> 1.5607998 | F54: =F49/$C$15 -> 1.8305129 | G54: =G49/$C$15 -> 2.1085197 | H54: =H49/$C$15 -> 2.3947796
B55: N = 7 years | C55: 7 | D55: =D50/$C$15 -> 1.3739022 | E55: =E50/$C$15 -> 1.664247 | F55: =F50/$C$15 -> 1.9678302 | G55: =G50/$C$15 -> 2.2846595 | H55: =H50/$C$15 -> 2.6147311
B56: N = 10 years | C56: 10 | D56: =D51/$C$15 -> 1.4917556 | E56: =E51/$C$15 -> 1.8287818 | F56: =F51/$C$15 -> 2.1872626 | G56: =G51/$C$15 -> 2.5673273 | H56: =H51/$C$15 -> 2.969069
B58: Block C: Decomposing the required profit into revenue x margin (N = 5 years, model WACC)
B59: The revenue the company must run at, for a given steady-state operating margin, to earn the Block B-3 profit.
B60: Required steady-state Operating Profit (N=5, model WACC) | C60: =F49 -> 18466.214
B62: Assumed steady-state OPM | C62: Required Revenue | D62: x FY base revenue
B63: 0.1 | C63: =$C$60/B63 -> 184662.14 | D63: =C63/'DCF Model'!C17 -> 3.9329985
B64: 0.12 | C64: =$C$60/B64 -> 153885.12 | D64: =C64/'DCF Model'!C17 -> 3.2774987
B65: 0.15 | C65: =$C$60/B65 -> 123108.1 | D65: =C65/'DCF Model'!C17 -> 2.621999
B66: cycle-peak OPM (FY2025/3) | C66: =$C$60/$C$18 -> 95186.672 | D66: =C66/'DCF Model'!C17 -> 2.0273188
B67: 0.25 | C67: =$C$60/B67 -> 73864.858 | D67: =C67/'DCF Model'!C17 -> 1.5731994
B69: Block D: The same question expressed as multiples
B70: Current EV / latest-FY EBITDA (actual) | C70: =C10/'Comps Analysis'!G5 -> 17.048466
B71: Current EV / latest-FY Revenue (actual) | C71: =C10/'Comps Analysis'!F5 -> 3.1136182
B72: EV / EBITDA if the Block A profit were already earned | C72: =C10/(C25+'DCF Model'!G42) -> 7.3576628
B73: EV / EBITDA if the Block B-3 (N=5) profit were already earned | C73: =C10/(C60+'DCF Model'!G42) -> 6.5216453
B74: Peer median EV / EBITDA (statistics rows) | C74: ='Comps Analysis'!D16 -> 12.13544
B75: Rows 3-4 answer: what multiple would today's EV be paying IF the company already earned the profit the price requires?
B77: Block E: Transaction benchmark (control price paid for the direct peer)
B78: Peer row EV / EBITDA at the announced exchange ratio | C78: ='Comps Analysis'!J6 -> 22.913456
B79: Peer row EV / Revenue at the announced exchange ratio | C79: ='Comps Analysis'!K6 -> 2.8956097
B80: Subject share price implied by that EV / EBITDA | C80: =ROUND(('Comps Analysis'!G5*'Comps Analysis'!J6-C9)*1000000/C7,0) -> 4094
B81: Subject share price implied by that EV / Revenue | C81: =ROUND(('Comps Analysis'!F5*'Comps Analysis'!K6-C9)*1000000/C7,0) -> 2449
B83: Direct peer Toho Titanium (5727) was delisted on 2026-05-28: JX Advanced Metals (5016) took it 100% via a share exchange at 0.70 JX shares per Toho share (effective 2026-06-01).
B84: Its market cap in the comps sheet is therefore 0.70 x JX price (3,785 yen, 2026-08-26) x 71.19m shares = 188,618 mn JPY - a live control valuation of the other half of the domestic duopoly, not a stale quote.
B85: The row is excluded from the peer statistics by the pipeline freshness check (no live quote). Read it as a transaction benchmark: it embeds a control premium and JX's own rating.
B86: CAVEAT: Toho's FY2026/3 operating margin was only 5.3%, so its 22.9x EV/EBITDA is a depressed-earnings multiple. The EV/Revenue read (2.90x -> 2,449 yen) is the more stable of the two.
B88: Block F: The one-line answer
B89: ="At "&TEXT(C6,"#,##0")&" yen the market is paying for a steady-state operating profit of "&TEXT(F49,"#,##0")&" mn JPY - "&TEXT(F54,"0.00")&"x the FY2025/3 cycle peak of "&TEXT(C15,"#,##0")&" mn - reached in 5 years and sustained for ever, against "&TEXT(C14,"#,##0")&" mn actually earned in FY2026/3." -> At 2,727 yen the market is paying for a steady-state operating profit of 18,466 mn JPY - 1.83x the FY2025/3 cycle peak of 10,088 mn - reached in 5 years and sustained for ever, against 5,524 mn actually earned in FY2026/3.
B90: ="Even with no ramp at all (Block A) the price needs "&TEXT(C25,"#,##0")&" mn, or "&TEXT(C26,"0.00")&"x the peak. The base case supports an EV of only "&TEXT(C17,"#,##0")&" mn, leaving "&TEXT(C20,"#,##0")&" yen per share of the current price unexplained by mid-cycle economics." -> Even with no ramp at all (Block A) the price needs 15,919 mn, or 1.58x the peak. The base case supports an EV of only 53,209 mn, leaving 2,527 yen per share of the current price unexplained by mid-cycle economics.

Sheet NWC Schedule
B2: NWC Schedule - Osaka Titanium Technologies
B4: Working Capital Drivers (Days) | C4: Base Year | D4: FY2027(E) | E4: FY2028(E) | F4: FY2029(E) | G4: FY2030(E) | H4: FY2031(E)
B5: DSO (Days Sales Outstanding) | C5: =C12/C9*365 -> 182.77986 | D5: =CHOOSE('DCF Model'!$D$27,D25,D26,D27,D28,D29) -> 178 | E5: =CHOOSE('DCF Model'!$D$27,E25,E26,E27,E28,E29) -> 172 | F5: =CHOOSE('DCF Model'!$D$27,F25,F26,F27,F28,F29) -> 166 | G5: =CHOOSE('DCF Model'!$D$27,G25,G26,G27,G28,G29) -> 162 | H5: =CHOOSE('DCF Model'!$D$27,H25,H26,H27,H28,H29) -> 158
B6: DIH (Days Inventory Held) | C6: =C13/C10*365 -> 380.50778 | D6: =CHOOSE('DCF Model'!$D$27,D32,D33,D34,D35,D36) -> 360 | E6: =CHOOSE('DCF Model'!$D$27,E32,E33,E34,E35,E36) -> 345 | F6: =CHOOSE('DCF Model'!$D$27,F32,F33,F34,F35,F36) -> 330 | G6: =CHOOSE('DCF Model'!$D$27,G32,G33,G34,G35,G36) -> 315 | H6: =CHOOSE('DCF Model'!$D$27,H32,H33,H34,H35,H36) -> 305
B7: DPO (Days Payable Outstanding) | C7: =C15/C10*365 -> 44.801407 | D7: =CHOOSE('DCF Model'!$D$27,D39,D40,D41,D42,D43) -> 45 | E7: =CHOOSE('DCF Model'!$D$27,E39,E40,E41,E42,E43) -> 46 | F7: =CHOOSE('DCF Model'!$D$27,F39,F40,F41,F42,F43) -> 47 | G7: =CHOOSE('DCF Model'!$D$27,G39,G40,G41,G42,G43) -> 48 | H7: =CHOOSE('DCF Model'!$D$27,H39,H40,H41,H42,H43) -> 48
B8: P&L Reference (JPY mn)
B9: Revenue | C9: 46952 | D9: ='DCF Model'!C33 -> 50050.832 | E9: ='DCF Model'!D33 -> 53053.882 | F9: ='DCF Model'!E33 -> 55706.576 | G9: ='DCF Model'!F33 -> 57934.839 | H9: ='DCF Model'!G33 -> 59672.884
B10: COGS | C10: 35399 | D10: ='DCF Model'!C34 -> 39790.411 | E10: ='DCF Model'!D34 -> 41488.136 | F10: ='DCF Model'!E34 -> 42894.064 | G10: ='DCF Model'!F34 -> 44436.022 | H10: ='DCF Model'!G34 -> 45828.775
B11: Working Capital Items (JPY mn)
B12: Accounts Receivable | C12: 23512 | D12: =D9*D5/365 -> 24408.351 | E12: =E9*E5/365 -> 25000.733 | F12: =F9*F5/365 -> 25335.046 | G12: =G9*G5/365 -> 25713.545 | H12: =H9*H5/365 -> 25831.002
B13: Inventory | C13: 36903 | D13: =D10*D6/365 -> 39245.337 | E13: =E10*E6/365 -> 39214.813 | F13: =F10*F6/365 -> 38780.934 | G13: =G10*G6/365 -> 38348.895 | H13: =H10*H6/365 -> 38295.278
B14: Current Assets (AR + Inv) | C14: =C12+C13 -> 60415 | D14: =D12+D13 -> 63653.688 | E14: =E12+E13 -> 64215.547 | F14: =F12+F13 -> 64115.98 | G14: =G12+G13 -> 64062.44 | H14: =H12+H13 -> 64126.28
B15: Accounts Payable | C15: 4345 | D15: =D10*D7/365 -> 4905.6672 | E15: =E10*E7/365 -> 5228.6418 | F15: =F10*F7/365 -> 5523.3452 | G15: =G10*G7/365 -> 5843.6412 | H15: =H10*H7/365 -> 6026.7978
B16: Current Liabilities (AP) | C16: =C15 -> 4345 | D16: =D15 -> 4905.6672 | E16: =E15 -> 5228.6418 | F16: =F15 -> 5523.3452 | G16: =G15 -> 5843.6412 | H16: =H15 -> 6026.7978
B17: Net Working Capital (JPY mn)
B18: Net Working Capital | C18: =C14-C16 -> 56070 | D18: =D14-D16 -> 58748.021 | E18: =E14-E16 -> 58986.905 | F18: =F14-F16 -> 58592.635 | G18: =G14-G16 -> 58218.799 | H18: =H14-H16 -> 58099.482
B19: Change in NWC | C19: n/a | D19: =D18-C18 -> 2678.0211 | E19: =E18-D18 -> 238.88371 | F19: =F18-E18 -> -394.27029 | G19: =G18-F18 -> -373.83539 | H19: =H18-G18 -> -119.3172
B22: Scenario Input Matrix (Working Capital Days)
D23: FY2027(E) | E23: FY2028(E) | F23: FY2029(E) | G23: FY2030(E) | H23: FY2031(E)
B24: DSO (Days)
B25: Base | D25: 178 | E25: 172 | F25: 166 | G25: 162 | H25: 158
B26: Upside | D26: 172 | E26: 164 | F26: 156 | G26: 150 | H26: 148
B27: Management | D27: 180 | E27: 175 | F27: 170 | G27: 166 | H27: 163
B28: Downside 1 | D28: 185 | E28: 184 | F28: 182 | G28: 180 | H28: 178
B29: Downside 2 | D29: 188 | E29: 190 | F29: 190 | G29: 188 | H29: 186
B31: DIH (Days)
B32: Base | D32: 360 | E32: 345 | F32: 330 | G32: 315 | H32: 305
B33: Upside | D33: 340 | E33: 310 | F33: 285 | G33: 270 | H33: 260
B34: Management | D34: 368 | E34: 355 | F34: 342 | G34: 330 | H34: 320
B35: Downside 1 | D35: 385 | E35: 382 | F35: 375 | G35: 368 | H35: 360
B36: Downside 2 | D36: 405 | E36: 420 | F36: 420 | G36: 412 | H36: 405
B38: DPO (Days)
B39: Base | D39: 45 | E39: 46 | F39: 47 | G39: 48 | H39: 48
B40: Upside | D40: 46 | E40: 48 | F40: 50 | G40: 52 | H40: 52
B41: Management | D41: 45 | E41: 46 | F41: 46 | G41: 47 | H41: 48
B42: Downside 1 | D42: 44 | E42: 44 | F42: 45 | G42: 45 | H42: 46
B43: Downside 2 | D43: 43 | E43: 42 | F43: 42 | G43: 43 | H43: 43

Sheet Comps Analysis
B2: Comparable Company Analysis
B3: Peer prices as of 2026-08-26 (Mkt Cap / EV of peer rows are static CSV values; the subject row is live-linked to Executive Summary)
B4: Company | C4: Ticker | D4: Mkt Cap (JPY mn) | E4: EV (JPY mn) | F4: Revenue (JPY mn) | G4: EBITDA (JPY mn) | H4: Op Income (JPY mn) | I4: Net Income (JPY mn) | J4: EV/EBITDA | K4: EV/Revenue | L4: PER | M4: PBR | N4: Op Margin | O4: ROE | P4: Book Value (JPY mn) | Q4: Note
B5: Osaka Titanium Technologies | C5: 5726.T | D5: ='Executive Summary'!C9*C23/1000000 -> 100353.6 | E5: =D5+C24 -> 146190.6 | F5: 46952 | G5: 8575 | H5: 5524 | I5: 2576 | J5: =IFERROR(E5/G5,"") -> 17.048466 | K5: =IFERROR(E5/F5,"") -> 3.1136182 | L5: =IFERROR(D5/I5,"") -> 38.957143 | M5: =IFERROR(D5/P5,"") -> 2.2647559 | N5: =IFERROR(H5/F5,"") -> 0.11765207 | O5: =IFERROR(I5/P5,"") -> 0.058134549 | P5: 44311
B6: Toho Titanium (delisted 2026-05-28) | C6: 5727.T | D6: 188618 | E6: 241462 | F6: 83389 | G6: 10538 | H6: 4401 | I6: 2847 | J6: =IFERROR(E6/G6,"") -> 22.913456 | K6: =IFERROR(E6/F6,"") -> 2.8956097 | L6: =IFERROR(D6/I6,"") -> 66.251493 | M6: =IFERROR(D6/P6,"") -> 3.136889 | N6: =IFERROR(H6/F6,"") -> 0.052776745 | O6: =IFERROR(I6/P6,"") -> 0.047348201 | P6: 60129 | Q6: (price unavailable — delisted or wrong ticker?)
B7: ATI Inc. | C7: ATI | D7: 4660551 | E7: 4886579 | F7: 729471 | G7: 129070 | H7: 104642 | I7: 64297 | J7: =IFERROR(E7/G7,"") -> 37.859913 | K7: =IFERROR(E7/F7,"") -> 6.6987982 | L7: =IFERROR(D7/I7,"") -> 72.484735 | M7: =IFERROR(D7/P7,"") -> 15.287462 | N7: =IFERROR(H7/F7,"") -> 0.14344916 | O7: =IFERROR(I7/P7,"") -> 0.21090595 | P7: 304861
B8: Carpenter Technology | C8: CRS | D8: 3831013 | E8: 3884161 | F8: 496810 | G8: 134032 | H8: 110637 | I8: 84222 | J8: =IFERROR(E8/G8,"") -> 28.979356 | K8: =IFERROR(E8/F8,"") -> 7.8182021 | L8: =IFERROR(D8/I8,"") -> 45.487082 | M8: =IFERROR(D8/P8,"") -> 10.812327 | N8: =IFERROR(H8/F8,"") -> 0.22269479 | O8: =IFERROR(I8/P8,"") -> 0.23770105 | P8: 354319
B9: Baoji Titanium Industry | C9: 600456.SS | D9: 304214 | E9: 350605 | F9: 144742 | G9: 28891 | H9: 18810 | I9: 9475 | J9: =IFERROR(E9/G9,"") -> 12.13544 | K9: =IFERROR(E9/F9,"") -> 2.4222755 | L9: =IFERROR(D9/I9,"") -> 32.107018 | M9: =IFERROR(D9/P9,"") -> 1.7930803 | N9: =IFERROR(H9/F9,"") -> 0.12995537 | O9: =IFERROR(I9/P9,"") -> 0.055846988 | P9: 169660
B10: Nippon Yakin Kogyo | C10: 5480.T | D10: 75919 | E10: 145174 | F10: 150866 | G10: 17508 | H10: 10974 | I10: 7215 | J10: =IFERROR(E10/G10,"") -> 8.2918666 | K10: =IFERROR(E10/F10,"") -> 0.96227115 | L10: =IFERROR(D10/I10,"") -> 10.522384 | M10: =IFERROR(D10/P10,"") -> 0.75087036 | N10: =IFERROR(H10/F10,"") -> 0.072740047 | O10: =IFERROR(I10/P10,"") -> 0.071359339 | P10: 101108
B11: Daido Steel | C11: 5471.T | D11: 455667 | E11: 574355 | F11: 578129 | G11: 73210 | H11: 42081 | I11: 32605 | J11: =IFERROR(E11/G11,"") -> 7.845308 | K11: =IFERROR(E11/F11,"") -> 0.99347205 | L11: =IFERROR(D11/I11,"") -> 13.975372 | M11: =IFERROR(D11/P11,"") -> 0.96424196 | N11: =IFERROR(H11/F11,"") -> 0.072788253 | O11: =IFERROR(I11/P11,"") -> 0.0689958 | P11: 472565
B14: Statistics
B15: 25th Percentile | D15: =PERCENTILE(J7:J11,0.25) -> 8.2918666 | E15: =PERCENTILE(K7:K11,0.25) -> 0.99347205 | F15: =PERCENTILE(L7:L11,0.25) -> 13.975372 | G15: =PERCENTILE(M7:M11,0.25) -> 0.96424196 | H15: =PERCENTILE(N7:N11,0.25) -> 0.072788253 | I15: =PERCENTILE(O7:O11,0.25) -> 0.0689958
B16: Median (50th) | D16: =MEDIAN(J7:J11) -> 12.13544 | E16: =MEDIAN(K7:K11) -> 2.4222755 | F16: =MEDIAN(L7:L11) -> 32.107018 | G16: =MEDIAN(M7:M11) -> 1.7930803 | H16: =MEDIAN(N7:N11) -> 0.12995537 | I16: =MEDIAN(O7:O11) -> 0.071359339
B17: 75th Percentile | D17: =PERCENTILE(J7:J11,0.75) -> 28.979356 | E17: =PERCENTILE(K7:K11,0.75) -> 6.6987982 | F17: =PERCENTILE(L7:L11,0.75) -> 45.487082 | G17: =PERCENTILE(M7:M11,0.75) -> 10.812327 | H17: =PERCENTILE(N7:N11,0.75) -> 0.14344916 | I17: =PERCENTILE(O7:O11,0.75) -> 0.21090595
B19: Implied Valuation for Osaka Titanium Technologies
B20: Osaka Titanium Technologies Financials
B21: EBITDA (JPY mn) | C21: 8575
B22: Net Income (JPY mn) | C22: 2576
B23: Shares Outstanding | C23: 36800000
B24: Net Debt (JPY mn) | C24: 45837
B26: Implied Share Price (Median Multiples)
B27: Via EV/EBITDA (Median) | C27: =ROUND((C21*D16-C24)*1000000/C23,0) -> 1582
B28: Via PER (Median) | C28: =ROUND(C22*F16*1000000/C23,0) -> 2247
B29: Net Income normalized (pretax 3,814 + 特損2,619, tax 30.6%) | C29: =ROUND((3814+2619)*(1-'DCF Model'!C6),0) -> 4465
B30: Via PER (Median, normalized NI) [参考・Target不算入] | C30: =ROUND(C29*F16*1000000/C23,0) -> 3896

Sheet Sensitivity Analysis
B2: Sensitivity Analysis
B3: Current WACC: | C3: ='DCF Model'!C26 -> 0.090571884 | E3: Terminal g: | F3: ='DCF Model'!C13 -> 0.015 | H3: Exit Multiple: | I3: ='DCF Model'!C14 -> 8
B5: Table 1: WACC vs Terminal Growth Rate (PGM - Implied Share Price, JPY)
B6: WACC \ Terminal g | C6: =$F$3-0.0075 -> 0.0075 | D6: =$F$3-0.005 -> 0.01 | E6: =$F$3-0.0025 -> 0.0125 | F6: =$F$3 -> 0.015 | G6: =$F$3+0.0025 -> 0.0175 | H6: =$F$3+0.005 -> 0.02 | I6: =$F$3+0.0075 -> 0.0225
B7: =$C$3-0.015 -> 0.075571884 | C7: =IFERROR(ROUND(('DCF Model'!C45/(1+$B7)^('DCF Model'!C19+0)+'DCF Model'!D45/(1+$B7)^('DCF Model'!C19+1)+'DCF Model'!E45/(1+$B7)^('DCF Model'!C19+2)+'DCF Model'!F45/(1+$B7)^('DCF Model'!C19+3)+'DCF Model'!G45/(1+$B7)^('DCF Model'!C19+4)+'DCF Model'!G45*(1+C$6)/($B7-C$6)/(1+$B7)^('DCF Model'!C19+4)-'DCF Model'!C16)*1000000/'DCF Model'!C15,0),"") -> 435 | D7: =IFERROR(ROUND(('DCF Model'!C45/(1+$B7)^('DCF Model'!C19+0)+'DCF Model'!D45/(1+$B7)^('DCF Model'!C19+1)+'DCF Model'!E45/(1+$B7)^('DCF Model'!C19+2)+'DCF Model'!F45/(1+$B7)^('DCF Model'!C19+3)+'DCF Model'!G45/(1+$B7)^('DCF Model'!C19+4)+'DCF Model'!G45*(1+D$6)/($B7-D$6)/(1+$B7)^('DCF Model'!C19+4)-'DCF Model'!C16)*1000000/'DCF Model'!C15,0),"") -> 494 | E7: =IFERROR(ROUND(('DCF Model'!C45/(1+$B7)^('DCF Model'!C19+0)+'DCF Model'!D45/(1+$B7)^('DCF Model'!C19+1)+'DCF Model'!E45/(1+$B7)^('DCF Model'!C19+2)+'DCF Model'!F45/(1+$B7)^('DCF Model'!C19+3)+'DCF Model'!G45/(1+$B7)^('DCF Model'!C19+4)+'DCF Model'!G45*(1+E$6)/($B7-E$6)/(1+$B7)^('DCF Model'!C19+4)-'DCF Model'!C16)*1000000/'DCF Model'!C15,0),"") -> 558 | F7: =IFERROR(ROUND(('DCF Model'!C45/(1+$B7)^('DCF Model'!C19+0)+'DCF Model'!D45/(1+$B7)^('DCF Model'!C19+1)+'DCF Model'!E45/(1+$B7)^('DCF Model'!C19+2)+'DCF Model'!F45/(1+$B7)^('DCF Model'!C19+3)+'DCF Model'!G45/(1+$B7)^('DCF Model'!C19+4)+'DCF Model'!G45*(1+F$6)/($B7-F$6)/(1+$B7)^('DCF Model'!C19+4)-'DCF Model'!C16)*1000000/'DCF Model'!C15,0),"") -> 628 | G7: =IFERROR(ROUND(('DCF Model'!C45/(1+$B7)^('DCF Model'!C19+0)+'DCF Model'!D45/(1+$B7)^('DCF Model'!C19+1)+'DCF Model'!E45/(1+$B7)^('DCF Model'!C19+2)+'DCF Model'!F45/(1+$B7)^('DCF Model'!C19+3)+'DCF Model'!G45/(1+$B7)^('DCF Model'!C19+4)+'DCF Model'!G45*(1+G$6)/($B7-G$6)/(1+$B7)^('DCF Model'!C19+4)-'DCF Model'!C16)*1000000/'DCF Model'!C15,0),"") -> 703 | H7: =IFERROR(ROUND(('DCF Model'!C45/(1+$B7)^('DCF Model'!C19+0)+'DCF Model'!D45/(1+$B7)^('DCF Model'!C19+1)+'DCF Model'!E45/(1+$B7)^('DCF Model'!C19+2)+'DCF Model'!F45/(1+$B7)^('DCF Model'!C19+3)+'DCF Model'!G45/(1+$B7)^('DCF Model'!C19+4)+'DCF Model'!G45*(1+H$6)/($B7-H$6)/(1+$B7)^('DCF Model'!C19+4)-'DCF Model'!C16)*1000000/'DCF Model'!C15,0),"") -> 786 | I7: =IFERROR(ROUND(('DCF Model'!C45/(1+$B7)^('DCF Model'!C19+0)+'DCF Model'!D45/(1+$B7)^('DCF Model'!C19+1)+'DCF Model'!E45/(1+$B7)^('DCF Model'!C19+2)+'DCF Model'!F45/(1+$B7)^('DCF Model'!C19+3)+'DCF Model'!G45/(1+$B7)^('DCF Model'!C19+4)+'DCF Model'!G45*(1+I$6)/($B7-I$6)/(1+$B7)^('DCF Model'!C19+4)-'DCF Model'!C16)*1000000/'DCF Model'!C15,0),"") -> 876
B8: =$C$3-0.01 -> 0.080571884 | C8: =IFERROR(ROUND(('DCF Model'!C45/(1+$B8)^('DCF Model'!C19+0)+'DCF Model'!D45/(1+$B8)^('DCF Model'!C19+1)+'DCF Model'!E45/(1+$B8)^('DCF Model'!C19+2)+'DCF Model'!F45/(1+$B8)^('DCF Model'!C19+3)+'DCF Model'!G45/(1+$B8)^('DCF Model'!C19+4)+'DCF Model'!G45*(1+C$6)/($B8-C$6)/(1+$B8)^('DCF Model'!C19+4)-'DCF Model'!C16)*1000000/'DCF Model'!C15,0),"") -> 300 | D8: =IFERROR(ROUND(('DCF Model'!C45/(1+$B8)^('DCF Model'!C19+0)+'DCF Model'!D45/(1+$B8)^('DCF Model'!C19+1)+'DCF Model'!E45/(1+$B8)^('DCF Model'!C19+2)+'DCF Model'!F45/(1+$B8)^('DCF Model'!C19+3)+'DCF Model'!G45/(1+$B8)^('DCF Model'!C19+4)+'DCF Model'!G45*(1+D$6)/($B8-D$6)/(1+$B8)^('DCF Model'!C19+4)-'DCF Model'!C16)*1000000/'DCF Model'!C15,0),"") -> 351 | E8: =IFERROR(ROUND(('DCF Model'!C45/(1+$B8)^('DCF Model'!C19+0)+'DCF Model'!D45/(1+$B8)^('DCF Model'!C19+1)+'DCF Model'!E45/(1+$B8)^('DCF Model'!C19+2)+'DCF Model'!F45/(1+$B8)^('DCF Model'!C19+3)+'DCF Model'!G45/(1+$B8)^('DCF Model'!C19+4)+'DCF Model'!G45*(1+E$6)/($B8-E$6)/(1+$B8)^('DCF Model'!C19+4)-'DCF Model'!C16)*1000000/'DCF Model'!C15,0),"") -> 405 | F8: =IFERROR(ROUND(('DCF Model'!C45/(1+$B8)^('DCF Model'!C19+0)+'DCF Model'!D45/(1+$B8)^('DCF Model'!C19+1)+'DCF Model'!E45/(1+$B8)^('DCF Model'!C19+2)+'DCF Model'!F45/(1+$B8)^('DCF Model'!C19+3)+'DCF Model'!G45/(1+$B8)^('DCF Model'!C19+4)+'DCF Model'!G45*(1+F$6)/($B8-F$6)/(1+$B8)^('DCF Model'!C19+4)-'DCF Model'!C16)*1000000/'DCF Model'!C15,0),"") -> 463 | G8: =IFERROR(ROUND(('DCF Model'!C45/(1+$B8)^('DCF Model'!C19+0)+'DCF Model'!D45/(1+$B8)^('DCF Model'!C19+1)+'DCF Model'!E45/(1+$B8)^('DCF Model'!C19+2)+'DCF Model'!F45/(1+$B8)^('DCF Model'!C19+3)+'DCF Model'!G45/(1+$B8)^('DCF Model'!C19+4)+'DCF Model'!G45*(1+G$6)/($B8-G$6)/(1+$B8)^('DCF Model'!C19+4)-'DCF Model'!C16)*1000000/'DCF Model'!C15,0),"") -> 527 | H8: =IFERROR(ROUND(('DCF Model'!C45/(1+$B8)^('DCF Model'!C19+0)+'DCF Model'!D45/(1+$B8)^('DCF Model'!C19+1)+'DCF Model'!E45/(1+$B8)^('DCF Model'!C19+2)+'DCF Model'!F45/(1+$B8)^('DCF Model'!C19+3)+'DCF Model'!G45/(1+$B8)^('DCF Model'!C19+4)+'DCF Model'!G45*(1+H$6)/($B8-H$6)/(1+$B8)^('DCF Model'!C19+4)-'DCF Model'!C16)*1000000/'DCF Model'!C15,0),"") -> 595 | I8: =IFERROR(ROUND(('DCF Model'!C45/(1+$B8)^('DCF Model'!C19+0)+'DCF Model'!D45/(1+$B8)^('DCF Model'!C19+1)+'DCF Model'!E45/(1+$B8)^('DCF Model'!C19+2)+'DCF Model'!F45/(1+$B8)^('DCF Model'!C19+3)+'DCF Model'!G45/(1+$B8)^('DCF Model'!C19+4)+'DCF Model'!G45*(1+I$6)/($B8-I$6)/(1+$B8)^('DCF Model'!C19+4)-'DCF Model'!C16)*1000000/'DCF Model'!C15,0),"") -> 669
B9: =$C$3-0.005 -> 0.085571884 | C9: =IFERROR(ROUND(('DCF Model'!C45/(1+$B9)^('DCF Model'!C19+0)+'DCF Model'!D45/(1+$B9)^('DCF Model'!C19+1)+'DCF Model'!E45/(1+$B9)^('DCF Model'!C19+2)+'DCF Model'!F45/(1+$B9)^('DCF Model'!C19+3)+'DCF Model'!G45/(1+$B9)^('DCF Model'!C19+4)+'DCF Model'!G45*(1+C$6)/($B9-C$6)/(1+$B9)^('DCF Model'!C19+4)-'DCF Model'!C16)*1000000/'DCF Model'!C15,0),"") -> 183 | D9: =IFERROR(ROUND(('DCF Model'!C45/(1+$B9)^('DCF Model'!C19+0)+'DCF Model'!D45/(1+$B9)^('DCF Model'!C19+1)+'DCF Model'!E45/(1+$B9)^('DCF Model'!C19+2)+'DCF Model'!F45/(1+$B9)^('DCF Model'!C19+3)+'DCF Model'!G45/(1+$B9)^('DCF Model'!C19+4)+'DCF Model'!G45*(1+D$6)/($B9-D$6)/(1+$B9)^('DCF Model'!C19+4)-'DCF Model'!C16)*1000000/'DCF Model'!C15,0),"") -> 226 | E9: =IFERROR(ROUND(('DCF Model'!C45/(1+$B9)^('DCF Model'!C19+0)+'DCF Model'!D45/(1+$B9)^('DCF Model'!C19+1)+'DCF Model'!E45/(1+$B9)^('DCF Model'!C19+2)+'DCF Model'!F45/(1+$B9)^('DCF Model'!C19+3)+'DCF Model'!G45/(1+$B9)^('DCF Model'!C19+4)+'DCF Model'!G45*(1+E$6)/($B9-E$6)/(1+$B9)^('DCF Model'!C19+4)-'DCF Model'!C16)*1000000/'DCF Model'!C15,0),"") -> 273 | F9: =IFERROR(ROUND(('DCF Model'!C45/(1+$B9)^('DCF Model'!C19+0)+'DCF Model'!D45/(1+$B9)^('DCF Model'!C19+1)+'DCF Model'!E45/(1+$B9)^('DCF Model'!C19+2)+'DCF Model'!F45/(1+$B9)^('DCF Model'!C19+3)+'DCF Model'!G45/(1+$B9)^('DCF Model'!C19+4)+'DCF Model'!G45*(1+F$6)/($B9-F$6)/(1+$B9)^('DCF Model'!C19+4)-'DCF Model'!C16)*1000000/'DCF Model'!C15,0),"") -> 322 | G9: =IFERROR(ROUND(('DCF Model'!C45/(1+$B9)^('DCF Model'!C19+0)+'DCF Model'!D45/(1+$B9)^('DCF Model'!C19+1)+'DCF Model'!E45/(1+$B9)^('DCF Model'!C19+2)+'DCF Model'!F45/(1+$B9)^('DCF Model'!C19+3)+'DCF Model'!G45/(1+$B9)^('DCF Model'!C19+4)+'DCF Model'!G45*(1+G$6)/($B9-G$6)/(1+$B9)^('DCF Model'!C19+4)-'DCF Model'!C16)*1000000/'DCF Model'!C15,0),"") -> 376 | H9: =IFERROR(ROUND(('DCF Model'!C45/(1+$B9)^('DCF Model'!C19+0)+'DCF Model'!D45/(1+$B9)^('DCF Model'!C19+1)+'DCF Model'!E45/(1+$B9)^('DCF Model'!C19+2)+'DCF Model'!F45/(1+$B9)^('DCF Model'!C19+3)+'DCF Model'!G45/(1+$B9)^('DCF Model'!C19+4)+'DCF Model'!G45*(1+H$6)/($B9-H$6)/(1+$B9)^('DCF Model'!C19+4)-'DCF Model'!C16)*1000000/'DCF Model'!C15,0),"") -> 433 | I9: =IFERROR(ROUND(('DCF Model'!C45/(1+$B9)^('DCF Model'!C19+0)+'DCF Model'!D45/(1+$B9)^('DCF Model'!C19+1)+'DCF Model'!E45/(1+$B9)^('DCF Model'!C19+2)+'DCF Model'!F45/(1+$B9)^('DCF Model'!C19+3)+'DCF Model'!G45/(1+$B9)^('DCF Model'!C19+4)+'DCF Model'!G45*(1+I$6)/($B9-I$6)/(1+$B9)^('DCF Model'!C19+4)-'DCF Model'!C16)*1000000/'DCF Model'!C15,0),"") -> 495
B10: =$C$3 -> 0.090571884 | C10: =IFERROR(ROUND(('DCF Model'!C45/(1+$B10)^('DCF Model'!C19+0)+'DCF Model'!D45/(1+$B10)^('DCF Model'!C19+1)+'DCF Model'!E45/(1+$B10)^('DCF Model'!C19+2)+'DCF Model'!F45/(1+$B10)^('DCF Model'!C19+3)+'DCF Model'!G45/(1+$B10)^('DCF Model'!C19+4)+'DCF Model'!G45*(1+C$6)/($B10-C$6)/(1+$B10)^('DCF Model'!C19+4)-'DCF Model'!C16)*1000000/'DCF Model'!C15,0),"") -> 80 | D10: =IFERROR(ROUND(('DCF Model'!C45/(1+$B10)^('DCF Model'!C19+0)+'DCF Model'!D45/(1+$B10)^('DCF Model'!C19+1)+'DCF Model'!E45/(1+$B10)^('DCF Model'!C19+2)+'DCF Model'!F45/(1+$B10)^('DCF Model'!C19+3)+'DCF Model'!G45/(1+$B10)^('DCF Model'!C19+4)+'DCF Model'!G45*(1+D$6)/($B10-D$6)/(1+$B10)^('DCF Model'!C19+4)-'DCF Model'!C16)*1000000/'DCF Model'!C15,0),"") -> 117 | E10: =IFERROR(ROUND(('DCF Model'!C45/(1+$B10)^('DCF Model'!C19+0)+'DCF Model'!D45/(1+$B10)^('DCF Model'!C19+1)+'DCF Model'!E45/(1+$B10)^('DCF Model'!C19+2)+'DCF Model'!F45/(1+$B10)^('DCF Model'!C19+3)+'DCF Model'!G45/(1+$B10)^('DCF Model'!C19+4)+'DCF Model'!G45*(1+E$6)/($B10-E$6)/(1+$B10)^('DCF Model'!C19+4)-'DCF Model'!C16)*1000000/'DCF Model'!C15,0),"") -> 158 | F10: =IFERROR(ROUND(('DCF Model'!C45/(1+$B10)^('DCF Model'!C19+0)+'DCF Model'!D45/(1+$B10)^('DCF Model'!C19+1)+'DCF Model'!E45/(1+$B10)^('DCF Model'!C19+2)+'DCF Model'!F45/(1+$B10)^('DCF Model'!C19+3)+'DCF Model'!G45/(1+$B10)^('DCF Model'!C19+4)+'DCF Model'!G45*(1+F$6)/($B10-F$6)/(1+$B10)^('DCF Model'!C19+4)-'DCF Model'!C16)*1000000/'DCF Model'!C15,0),"") -> 200 | G10: =IFERROR(ROUND(('DCF Model'!C45/(1+$B10)^('DCF Model'!C19+0)+'DCF Model'!D45/(1+$B10)^('DCF Model'!C19+1)+'DCF Model'!E45/(1+$B10)^('DCF Model'!C19+2)+'DCF Model'!F45/(1+$B10)^('DCF Model'!C19+3)+'DCF Model'!G45/(1+$B10)^('DCF Model'!C19+4)+'DCF Model'!G45*(1+G$6)/($B10-G$6)/(1+$B10)^('DCF Model'!C19+4)-'DCF Model'!C16)*1000000/'DCF Model'!C15,0),"") -> 246 | H10: =IFERROR(ROUND(('DCF Model'!C45/(1+$B10)^('DCF Model'!C19+0)+'DCF Model'!D45/(1+$B10)^('DCF Model'!C19+1)+'DCF Model'!E45/(1+$B10)^('DCF Model'!C19+2)+'DCF Model'!F45/(1+$B10)^('DCF Model'!C19+3)+'DCF Model'!G45/(1+$B10)^('DCF Model'!C19+4)+'DCF Model'!G45*(1+H$6)/($B10-H$6)/(1+$B10)^('DCF Model'!C19+4)-'DCF Model'!C16)*1000000/'DCF Model'!C15,0),"") -> 295 | I10: =IFERROR(ROUND(('DCF Model'!C45/(1+$B10)^('DCF Model'!C19+0)+'DCF Model'!D45/(1+$B10)^('DCF Model'!C19+1)+'DCF Model'!E45/(1+$B10)^('DCF Model'!C19+2)+'DCF Model'!F45/(1+$B10)^('DCF Model'!C19+3)+'DCF Model'!G45/(1+$B10)^('DCF Model'!C19+4)+'DCF Model'!G45*(1+I$6)/($B10-I$6)/(1+$B10)^('DCF Model'!C19+4)-'DCF Model'!C16)*1000000/'DCF Model'!C15,0),"") -> 347
B11: =$C$3+0.005 -> 0.095571884 | C11: =IFERROR(ROUND(('DCF Model'!C45/(1+$B11)^('DCF Model'!C19+0)+'DCF Model'!D45/(1+$B11)^('DCF Model'!C19+1)+'DCF Model'!E45/(1+$B11)^('DCF Model'!C19+2)+'DCF Model'!F45/(1+$B11)^('DCF Model'!C19+3)+'DCF Model'!G45/(1+$B11)^('DCF Model'!C19+4)+'DCF Model'!G45*(1+C$6)/($B11-C$6)/(1+$B11)^('DCF Model'!C19+4)-'DCF Model'!C16)*1000000/'DCF Model'!C15,0),"") -> -11 | D11: =IFERROR(ROUND(('DCF Model'!C45/(1+$B11)^('DCF Model'!C19+0)+'DCF Model'!D45/(1+$B11)^('DCF Model'!C19+1)+'DCF Model'!E45/(1+$B11)^('DCF Model'!C19+2)+'DCF Model'!F45/(1+$B11)^('DCF Model'!C19+3)+'DCF Model'!G45/(1+$B11)^('DCF Model'!C19+4)+'DCF Model'!G45*(1+D$6)/($B11-D$6)/(1+$B11)^('DCF Model'!C19+4)-'DCF Model'!C16)*1000000/'DCF Model'!C15,0),"") -> 22 | E11: =IFERROR(ROUND(('DCF Model'!C45/(1+$B11)^('DCF Model'!C19+0)+'DCF Model'!D45/(1+$B11)^('DCF Model'!C19+1)+'DCF Model'!E45/(1+$B11)^('DCF Model'!C19+2)+'DCF Model'!F45/(1+$B11)^('DCF Model'!C19+3)+'DCF Model'!G45/(1+$B11)^('DCF Model'!C19+4)+'DCF Model'!G45*(1+E$6)/($B11-E$6)/(1+$B11)^('DCF Model'!C19+4)-'DCF Model'!C16)*1000000/'DCF Model'!C15,0),"") -> 57 | F11: =IFERROR(ROUND(('DCF Model'!C45/(1+$B11)^('DCF Model'!C19+0)+'DCF Model'!D45/(1+$B11)^('DCF Model'!C19+1)+'DCF Model'!E45/(1+$B11)^('DCF Model'!C19+2)+'DCF Model'!F45/(1+$B11)^('DCF Model'!C19+3)+'DCF Model'!G45/(1+$B11)^('DCF Model'!C19+4)+'DCF Model'!G45*(1+F$6)/($B11-F$6)/(1+$B11)^('DCF Model'!C19+4)-'DCF Model'!C16)*1000000/'DCF Model'!C15,0),"") -> 94 | G11: =IFERROR(ROUND(('DCF Model'!C45/(1+$B11)^('DCF Model'!C19+0)+'DCF Model'!D45/(1+$B11)^('DCF Model'!C19+1)+'DCF Model'!E45/(1+$B11)^('DCF Model'!C19+2)+'DCF Model'!F45/(1+$B11)^('DCF Model'!C19+3)+'DCF Model'!G45/(1+$B11)^('DCF Model'!C19+4)+'DCF Model'!G45*(1+G$6)/($B11-G$6)/(1+$B11)^('DCF Model'!C19+4)-'DCF Model'!C16)*1000000/'DCF Model'!C15,0),"") -> 133 | H11: =IFERROR(ROUND(('DCF Model'!C45/(1+$B11)^('DCF Model'!C19+0)+'DCF Model'!D45/(1+$B11)^('DCF Model'!C19+1)+'DCF Model'!E45/(1+$B11)^('DCF Model'!C19+2)+'DCF Model'!F45/(1+$B11)^('DCF Model'!C19+3)+'DCF Model'!G45/(1+$B11)^('DCF Model'!C19+4)+'DCF Model'!G45*(1+H$6)/($B11-H$6)/(1+$B11)^('DCF Model'!C19+4)-'DCF Model'!C16)*1000000/'DCF Model'!C15,0),"") -> 175 | I11: =IFERROR(ROUND(('DCF Model'!C45/(1+$B11)^('DCF Model'!C19+0)+'DCF Model'!D45/(1+$B11)^('DCF Model'!C19+1)+'DCF Model'!E45/(1+$B11)^('DCF Model'!C19+2)+'DCF Model'!F45/(1+$B11)^('DCF Model'!C19+3)+'DCF Model'!G45/(1+$B11)^('DCF Model'!C19+4)+'DCF Model'!G45*(1+I$6)/($B11-I$6)/(1+$B11)^('DCF Model'!C19+4)-'DCF Model'!C16)*1000000/'DCF Model'!C15,0),"") -> 220
B12: =$C$3+0.01 -> 0.10057188 | C12: =IFERROR(ROUND(('DCF Model'!C45/(1+$B12)^('DCF Model'!C19+0)+'DCF Model'!D45/(1+$B12)^('DCF Model'!C19+1)+'DCF Model'!E45/(1+$B12)^('DCF Model'!C19+2)+'DCF Model'!F45/(1+$B12)^('DCF Model'!C19+3)+'DCF Model'!G45/(1+$B12)^('DCF Model'!C19+4)+'DCF Model'!G45*(1+C$6)/($B12-C$6)/(1+$B12)^('DCF Model'!C19+4)-'DCF Model'!C16)*1000000/'DCF Model'!C15,0),"") -> -92 | D12: =IFERROR(ROUND(('DCF Model'!C45/(1+$B12)^('DCF Model'!C19+0)+'DCF Model'!D45/(1+$B12)^('DCF Model'!C19+1)+'DCF Model'!E45/(1+$B12)^('DCF Model'!C19+2)+'DCF Model'!F45/(1+$B12)^('DCF Model'!C19+3)+'DCF Model'!G45/(1+$B12)^('DCF Model'!C19+4)+'DCF Model'!G45*(1+D$6)/($B12-D$6)/(1+$B12)^('DCF Model'!C19+4)-'DCF Model'!C16)*1000000/'DCF Model'!C15,0),"") -> -63 | E12: =IFERROR(ROUND(('DCF Model'!C45/(1+$B12)^('DCF Model'!C19+0)+'DCF Model'!D45/(1+$B12)^('DCF Model'!C19+1)+'DCF Model'!E45/(1+$B12)^('DCF Model'!C19+2)+'DCF Model'!F45/(1+$B12)^('DCF Model'!C19+3)+'DCF Model'!G45/(1+$B12)^('DCF Model'!C19+4)+'DCF Model'!G45*(1+E$6)/($B12-E$6)/(1+$B12)^('DCF Model'!C19+4)-'DCF Model'!C16)*1000000/'DCF Model'!C15,0),"") -> -33 | F12: =IFERROR(ROUND(('DCF Model'!C45/(1+$B12)^('DCF Model'!C19+0)+'DCF Model'!D45/(1+$B12)^('DCF Model'!C19+1)+'DCF Model'!E45/(1+$B12)^('DCF Model'!C19+2)+'DCF Model'!F45/(1+$B12)^('DCF Model'!C19+3)+'DCF Model'!G45/(1+$B12)^('DCF Model'!C19+4)+'DCF Model'!G45*(1+F$6)/($B12-F$6)/(1+$B12)^('DCF Model'!C19+4)-'DCF Model'!C16)*1000000/'DCF Model'!C15,0),"") -> -1 | G12: =IFERROR(ROUND(('DCF Model'!C45/(1+$B12)^('DCF Model'!C19+0)+'DCF Model'!D45/(1+$B12)^('DCF Model'!C19+1)+'DCF Model'!E45/(1+$B12)^('DCF Model'!C19+2)+'DCF Model'!F45/(1+$B12)^('DCF Model'!C19+3)+'DCF Model'!G45/(1+$B12)^('DCF Model'!C19+4)+'DCF Model'!G45*(1+G$6)/($B12-G$6)/(1+$B12)^('DCF Model'!C19+4)-'DCF Model'!C16)*1000000/'DCF Model'!C15,0),"") -> 34 | H12: =IFERROR(ROUND(('DCF Model'!C45/(1+$B12)^('DCF Model'!C19+0)+'DCF Model'!D45/(1+$B12)^('DCF Model'!C19+1)+'DCF Model'!E45/(1+$B12)^('DCF Model'!C19+2)+'DCF Model'!F45/(1+$B12)^('DCF Model'!C19+3)+'DCF Model'!G45/(1+$B12)^('DCF Model'!C19+4)+'DCF Model'!G45*(1+H$6)/($B12-H$6)/(1+$B12)^('DCF Model'!C19+4)-'DCF Model'!C16)*1000000/'DCF Model'!C15,0),"") -> 70 | I12: =IFERROR(ROUND(('DCF Model'!C45/(1+$B12)^('DCF Model'!C19+0)+'DCF Model'!D45/(1+$B12)^('DCF Model'!C19+1)+'DCF Model'!E45/(1+$B12)^('DCF Model'!C19+2)+'DCF Model'!F45/(1+$B12)^('DCF Model'!C19+3)+'DCF Model'!G45/(1+$B12)^('DCF Model'!C19+4)+'DCF Model'!G45*(1+I$6)/($B12-I$6)/(1+$B12)^('DCF Model'!C19+4)-'DCF Model'!C16)*1000000/'DCF Model'!C15,0),"") -> 109
B13: =$C$3+0.015 -> 0.10557188 | C13: =IFERROR(ROUND(('DCF Model'!C45/(1+$B13)^('DCF Model'!C19+0)+'DCF Model'!D45/(1+$B13)^('DCF Model'!C19+1)+'DCF Model'!E45/(1+$B13)^('DCF Model'!C19+2)+'DCF Model'!F45/(1+$B13)^('DCF Model'!C19+3)+'DCF Model'!G45/(1+$B13)^('DCF Model'!C19+4)+'DCF Model'!G45*(1+C$6)/($B13-C$6)/(1+$B13)^('DCF Model'!C19+4)-'DCF Model'!C16)*1000000/'DCF Model'!C15,0),"") -> -165 | D13: =IFERROR(ROUND(('DCF Model'!C45/(1+$B13)^('DCF Model'!C19+0)+'DCF Model'!D45/(1+$B13)^('DCF Model'!C19+1)+'DCF Model'!E45/(1+$B13)^('DCF Model'!C19+2)+'DCF Model'!F45/(1+$B13)^('DCF Model'!C19+3)+'DCF Model'!G45/(1+$B13)^('DCF Model'!C19+4)+'DCF Model'!G45*(1+D$6)/($B13-D$6)/(1+$B13)^('DCF Model'!C19+4)-'DCF Model'!C16)*1000000/'DCF Model'!C15,0),"") -> -139 | E13: =IFERROR(ROUND(('DCF Model'!C45/(1+$B13)^('DCF Model'!C19+0)+'DCF Model'!D45/(1+$B13)^('DCF Model'!C19+1)+'DCF Model'!E45/(1+$B13)^('DCF Model'!C19+2)+'DCF Model'!F45/(1+$B13)^('DCF Model'!C19+3)+'DCF Model'!G45/(1+$B13)^('DCF Model'!C19+4)+'DCF Model'!G45*(1+E$6)/($B13-E$6)/(1+$B13)^('DCF Model'!C19+4)-'DCF Model'!C16)*1000000/'DCF Model'!C15,0),"") -> -112 | F13: =IFERROR(ROUND(('DCF Model'!C45/(1+$B13)^('DCF Model'!C19+0)+'DCF Model'!D45/(1+$B13)^('DCF Model'!C19+1)+'DCF Model'!E45/(1+$B13)^('DCF Model'!C19+2)+'DCF Model'!F45/(1+$B13)^('DCF Model'!C19+3)+'DCF Model'!G45/(1+$B13)^('DCF Model'!C19+4)+'DCF Model'!G45*(1+F$6)/($B13-F$6)/(1+$B13)^('DCF Model'!C19+4)-'DCF Model'!C16)*1000000/'DCF Model'!C15,0),"") -> -84 | G13: =IFERROR(ROUND(('DCF Model'!C45/(1+$B13)^('DCF Model'!C19+0)+'DCF Model'!D45/(1+$B13)^('DCF Model'!C19+1)+'DCF Model'!E45/(1+$B13)^('DCF Model'!C19+2)+'DCF Model'!F45/(1+$B13)^('DCF Model'!C19+3)+'DCF Model'!G45/(1+$B13)^('DCF Model'!C19+4)+'DCF Model'!G45*(1+G$6)/($B13-G$6)/(1+$B13)^('DCF Model'!C19+4)-'DCF Model'!C16)*1000000/'DCF Model'!C15,0),"") -> -54 | H13: =IFERROR(ROUND(('DCF Model'!C45/(1+$B13)^('DCF Model'!C19+0)+'DCF Model'!D45/(1+$B13)^('DCF Model'!C19+1)+'DCF Model'!E45/(1+$B13)^('DCF Model'!C19+2)+'DCF Model'!F45/(1+$B13)^('DCF Model'!C19+3)+'DCF Model'!G45/(1+$B13)^('DCF Model'!C19+4)+'DCF Model'!G45*(1+H$6)/($B13-H$6)/(1+$B13)^('DCF Model'!C19+4)-'DCF Model'!C16)*1000000/'DCF Model'!C15,0),"") -> -22 | I13: =IFERROR(ROUND(('DCF Model'!C45/(1+$B13)^('DCF Model'!C19+0)+'DCF Model'!D45/(1+$B13)^('DCF Model'!C19+1)+'DCF Model'!E45/(1+$B13)^('DCF Model'!C19+2)+'DCF Model'!F45/(1+$B13)^('DCF Model'!C19+3)+'DCF Model'!G45/(1+$B13)^('DCF Model'!C19+4)+'DCF Model'!G45*(1+I$6)/($B13-I$6)/(1+$B13)^('DCF Model'!C19+4)-'DCF Model'!C16)*1000000/'DCF Model'!C15,0),"") -> 11
B16: Table 2: WACC vs Exit Multiple (Exit Multiple - Implied Share Price, JPY)
B17: WACC \ Exit Multiple | C17: =$I$3-3 -> 5 | D17: =$I$3-2 -> 6 | E17: =$I$3-1 -> 7 | F17: =$I$3 -> 8 | G17: =$I$3+1 -> 9 | H17: =$I$3+2 -> 10 | I17: =$I$3+3 -> 11
B18: =$C$3-0.015 -> 0.075571884 | C18: =IFERROR(ROUND(('DCF Model'!C45/(1+$B18)^('DCF Model'!C19+0)+'DCF Model'!D45/(1+$B18)^('DCF Model'!C19+1)+'DCF Model'!E45/(1+$B18)^('DCF Model'!C19+2)+'DCF Model'!F45/(1+$B18)^('DCF Model'!C19+3)+'DCF Model'!G45/(1+$B18)^('DCF Model'!C19+4)+('DCF Model'!G39+'DCF Model'!G42)*C$17/(1+$B18)^('DCF Model'!C19+4)-'DCF Model'!C16)*1000000/'DCF Model'!C15,0),"") -> 40 | D18: =IFERROR(ROUND(('DCF Model'!C45/(1+$B18)^('DCF Model'!C19+0)+'DCF Model'!D45/(1+$B18)^('DCF Model'!C19+1)+'DCF Model'!E45/(1+$B18)^('DCF Model'!C19+2)+'DCF Model'!F45/(1+$B18)^('DCF Model'!C19+3)+'DCF Model'!G45/(1+$B18)^('DCF Model'!C19+4)+('DCF Model'!G39+'DCF Model'!G42)*D$17/(1+$B18)^('DCF Model'!C19+4)-'DCF Model'!C16)*1000000/'DCF Model'!C15,0),"") -> 254 | E18: =IFERROR(ROUND(('DCF Model'!C45/(1+$B18)^('DCF Model'!C19+0)+'DCF Model'!D45/(1+$B18)^('DCF Model'!C19+1)+'DCF Model'!E45/(1+$B18)^('DCF Model'!C19+2)+'DCF Model'!F45/(1+$B18)^('DCF Model'!C19+3)+'DCF Model'!G45/(1+$B18)^('DCF Model'!C19+4)+('DCF Model'!G39+'DCF Model'!G42)*E$17/(1+$B18)^('DCF Model'!C19+4)-'DCF Model'!C16)*1000000/'DCF Model'!C15,0),"") -> 468 | F18: =IFERROR(ROUND(('DCF Model'!C45/(1+$B18)^('DCF Model'!C19+0)+'DCF Model'!D45/(1+$B18)^('DCF Model'!C19+1)+'DCF Model'!E45/(1+$B18)^('DCF Model'!C19+2)+'DCF Model'!F45/(1+$B18)^('DCF Model'!C19+3)+'DCF Model'!G45/(1+$B18)^('DCF Model'!C19+4)+('DCF Model'!G39+'DCF Model'!G42)*F$17/(1+$B18)^('DCF Model'!C19+4)-'DCF Model'!C16)*1000000/'DCF Model'!C15,0),"") -> 681 | G18: =IFERROR(ROUND(('DCF Model'!C45/(1+$B18)^('DCF Model'!C19+0)+'DCF Model'!D45/(1+$B18)^('DCF Model'!C19+1)+'DCF Model'!E45/(1+$B18)^('DCF Model'!C19+2)+'DCF Model'!F45/(1+$B18)^('DCF Model'!C19+3)+'DCF Model'!G45/(1+$B18)^('DCF Model'!C19+4)+('DCF Model'!G39+'DCF Model'!G42)*G$17/(1+$B18)^('DCF Model'!C19+4)-'DCF Model'!C16)*1000000/'DCF Model'!C15,0),"") -> 895 | H18: =IFERROR(ROUND(('DCF Model'!C45/(1+$B18)^('DCF Model'!C19+0)+'DCF Model'!D45/(1+$B18)^('DCF Model'!C19+1)+'DCF Model'!E45/(1+$B18)^('DCF Model'!C19+2)+'DCF Model'!F45/(1+$B18)^('DCF Model'!C19+3)+'DCF Model'!G45/(1+$B18)^('DCF Model'!C19+4)+('DCF Model'!G39+'DCF Model'!G42)*H$17/(1+$B18)^('DCF Model'!C19+4)-'DCF Model'!C16)*1000000/'DCF Model'!C15,0),"") -> 1108 | I18: =IFERROR(ROUND(('DCF Model'!C45/(1+$B18)^('DCF Model'!C19+0)+'DCF Model'!D45/(1+$B18)^('DCF Model'!C19+1)+'DCF Model'!E45/(1+$B18)^('DCF Model'!C19+2)+'DCF Model'!F45/(1+$B18)^('DCF Model'!C19+3)+'DCF Model'!G45/(1+$B18)^('DCF Model'!C19+4)+('DCF Model'!G39+'DCF Model'!G42)*I$17/(1+$B18)^('DCF Model'!C19+4)-'DCF Model'!C16)*1000000/'DCF Model'!C15,0),"") -> 1322
B19: =$C$3-0.01 -> 0.080571884 | C19: =IFERROR(ROUND(('DCF Model'!C45/(1+$B19)^('DCF Model'!C19+0)+'DCF Model'!D45/(1+$B19)^('DCF Model'!C19+1)+'DCF Model'!E45/(1+$B19)^('DCF Model'!C19+2)+'DCF Model'!F45/(1+$B19)^('DCF Model'!C19+3)+'DCF Model'!G45/(1+$B19)^('DCF Model'!C19+4)+('DCF Model'!G39+'DCF Model'!G42)*C$17/(1+$B19)^('DCF Model'!C19+4)-'DCF Model'!C16)*1000000/'DCF Model'!C15,0),"") -> 12 | D19: =IFERROR(ROUND(('DCF Model'!C45/(1+$B19)^('DCF Model'!C19+0)+'DCF Model'!D45/(1+$B19)^('DCF Model'!C19+1)+'DCF Model'!E45/(1+$B19)^('DCF Model'!C19+2)+'DCF Model'!F45/(1+$B19)^('DCF Model'!C19+3)+'DCF Model'!G45/(1+$B19)^('DCF Model'!C19+4)+('DCF Model'!G39+'DCF Model'!G42)*D$17/(1+$B19)^('DCF Model'!C19+4)-'DCF Model'!C16)*1000000/'DCF Model'!C15,0),"") -> 221 | E19: =IFERROR(ROUND(('DCF Model'!C45/(1+$B19)^('DCF Model'!C19+0)+'DCF Model'!D45/(1+$B19)^('DCF Model'!C19+1)+'DCF Model'!E45/(1+$B19)^('DCF Model'!C19+2)+'DCF Model'!F45/(1+$B19)^('DCF Model'!C19+3)+'DCF Model'!G45/(1+$B19)^('DCF Model'!C19+4)+('DCF Model'!G39+'DCF Model'!G42)*E$17/(1+$B19)^('DCF Model'!C19+4)-'DCF Model'!C16)*1000000/'DCF Model'!C15,0),"") -> 430 | F19: =IFERROR(ROUND(('DCF Model'!C45/(1+$B19)^('DCF Model'!C19+0)+'DCF Model'!D45/(1+$B19)^('DCF Model'!C19+1)+'DCF Model'!E45/(1+$B19)^('DCF Model'!C19+2)+'DCF Model'!F45/(1+$B19)^('DCF Model'!C19+3)+'DCF Model'!G45/(1+$B19)^('DCF Model'!C19+4)+('DCF Model'!G39+'DCF Model'!G42)*F$17/(1+$B19)^('DCF Model'!C19+4)-'DCF Model'!C16)*1000000/'DCF Model'!C15,0),"") -> 639 | G19: =IFERROR(ROUND(('DCF Model'!C45/(1+$B19)^('DCF Model'!C19+0)+'DCF Model'!D45/(1+$B19)^('DCF Model'!C19+1)+'DCF Model'!E45/(1+$B19)^('DCF Model'!C19+2)+'DCF Model'!F45/(1+$B19)^('DCF Model'!C19+3)+'DCF Model'!G45/(1+$B19)^('DCF Model'!C19+4)+('DCF Model'!G39+'DCF Model'!G42)*G$17/(1+$B19)^('DCF Model'!C19+4)-'DCF Model'!C16)*1000000/'DCF Model'!C15,0),"") -> 848 | H19: =IFERROR(ROUND(('DCF Model'!C45/(1+$B19)^('DCF Model'!C19+0)+'DCF Model'!D45/(1+$B19)^('DCF Model'!C19+1)+'DCF Model'!E45/(1+$B19)^('DCF Model'!C19+2)+'DCF Model'!F45/(1+$B19)^('DCF Model'!C19+3)+'DCF Model'!G45/(1+$B19)^('DCF Model'!C19+4)+('DCF Model'!G39+'DCF Model'!G42)*H$17/(1+$B19)^('DCF Model'!C19+4)-'DCF Model'!C16)*1000000/'DCF Model'!C15,0),"") -> 1057 | I19: =IFERROR(ROUND(('DCF Model'!C45/(1+$B19)^('DCF Model'!C19+0)+'DCF Model'!D45/(1+$B19)^('DCF Model'!C19+1)+'DCF Model'!E45/(1+$B19)^('DCF Model'!C19+2)+'DCF Model'!F45/(1+$B19)^('DCF Model'!C19+3)+'DCF Model'!G45/(1+$B19)^('DCF Model'!C19+4)+('DCF Model'!G39+'DCF Model'!G42)*I$17/(1+$B19)^('DCF Model'!C19+4)-'DCF Model'!C16)*1000000/'DCF Model'!C15,0),"") -> 1266
B20: =$C$3-0.005 -> 0.085571884 | C20: =IFERROR(ROUND(('DCF Model'!C45/(1+$B20)^('DCF Model'!C19+0)+'DCF Model'!D45/(1+$B20)^('DCF Model'!C19+1)+'DCF Model'!E45/(1+$B20)^('DCF Model'!C19+2)+'DCF Model'!F45/(1+$B20)^('DCF Model'!C19+3)+'DCF Model'!G45/(1+$B20)^('DCF Model'!C19+4)+('DCF Model'!G39+'DCF Model'!G42)*C$17/(1+$B20)^('DCF Model'!C19+4)-'DCF Model'!C16)*1000000/'DCF Model'!C15,0),"") -> -15 | D20: =IFERROR(ROUND(('DCF Model'!C45/(1+$B20)^('DCF Model'!C19+0)+'DCF Model'!D45/(1+$B20)^('DCF Model'!C19+1)+'DCF Model'!E45/(1+$B20)^('DCF Model'!C19+2)+'DCF Model'!F45/(1+$B20)^('DCF Model'!C19+3)+'DCF Model'!G45/(1+$B20)^('DCF Model'!C19+4)+('DCF Model'!G39+'DCF Model'!G42)*D$17/(1+$B20)^('DCF Model'!C19+4)-'DCF Model'!C16)*1000000/'DCF Model'!C15,0),"") -> 189 | E20: =IFERROR(ROUND(('DCF Model'!C45/(1+$B20)^('DCF Model'!C19+0)+'DCF Model'!D45/(1+$B20)^('DCF Model'!C19+1)+'DCF Model'!E45/(1+$B20)^('DCF Model'!C19+2)+'DCF Model'!F45/(1+$B20)^('DCF Model'!C19+3)+'DCF Model'!G45/(1+$B20)^('DCF Model'!C19+4)+('DCF Model'!G39+'DCF Model'!G42)*E$17/(1+$B20)^('DCF Model'!C19+4)-'DCF Model'!C16)*1000000/'DCF Model'!C15,0),"") -> 394 | F20: =IFERROR(ROUND(('DCF Model'!C45/(1+$B20)^('DCF Model'!C19+0)+'DCF Model'!D45/(1+$B20)^('DCF Model'!C19+1)+'DCF Model'!E45/(1+$B20)^('DCF Model'!C19+2)+'DCF Model'!F45/(1+$B20)^('DCF Model'!C19+3)+'DCF Model'!G45/(1+$B20)^('DCF Model'!C19+4)+('DCF Model'!G39+'DCF Model'!G42)*F$17/(1+$B20)^('DCF Model'!C19+4)-'DCF Model'!C16)*1000000/'DCF Model'!C15,0),"") -> 598 | G20: =IFERROR(ROUND(('DCF Model'!C45/(1+$B20)^('DCF Model'!C19+0)+'DCF Model'!D45/(1+$B20)^('DCF Model'!C19+1)+'DCF Model'!E45/(1+$B20)^('DCF Model'!C19+2)+'DCF Model'!F45/(1+$B20)^('DCF Model'!C19+3)+'DCF Model'!G45/(1+$B20)^('DCF Model'!C19+4)+('DCF Model'!G39+'DCF Model'!G42)*G$17/(1+$B20)^('DCF Model'!C19+4)-'DCF Model'!C16)*1000000/'DCF Model'!C15,0),"") -> 802 | H20: =IFERROR(ROUND(('DCF Model'!C45/(1+$B20)^('DCF Model'!C19+0)+'DCF Model'!D45/(1+$B20)^('DCF Model'!C19+1)+'DCF Model'!E45/(1+$B20)^('DCF Model'!C19+2)+'DCF Model'!F45/(1+$B20)^('DCF Model'!C19+3)+'DCF Model'!G45/(1+$B20)^('DCF Model'!C19+4)+('DCF Model'!G39+'DCF Model'!G42)*H$17/(1+$B20)^('DCF Model'!C19+4)-'DCF Model'!C16)*1000000/'DCF Model'!C15,0),"") -> 1007 | I20: =IFERROR(ROUND(('DCF Model'!C45/(1+$B20)^('DCF Model'!C19+0)+'DCF Model'!D45/(1+$B20)^('DCF Model'!C19+1)+'DCF Model'!E45/(1+$B20)^('DCF Model'!C19+2)+'DCF Model'!F45/(1+$B20)^('DCF Model'!C19+3)+'DCF Model'!G45/(1+$B20)^('DCF Model'!C19+4)+('DCF Model'!G39+'DCF Model'!G42)*I$17/(1+$B20)^('DCF Model'!C19+4)-'DCF Model'!C16)*1000000/'DCF Model'!C15,0),"") -> 1211
B21: =$C$3 -> 0.090571884 | C21: =IFERROR(ROUND(('DCF Model'!C45/(1+$B21)^('DCF Model'!C19+0)+'DCF Model'!D45/(1+$B21)^('DCF Model'!C19+1)+'DCF Model'!E45/(1+$B21)^('DCF Model'!C19+2)+'DCF Model'!F45/(1+$B21)^('DCF Model'!C19+3)+'DCF Model'!G45/(1+$B21)^('DCF Model'!C19+4)+('DCF Model'!G39+'DCF Model'!G42)*C$17/(1+$B21)^('DCF Model'!C19+4)-'DCF Model'!C16)*1000000/'DCF Model'!C15,0),"") -> -42 | D21: =IFERROR(ROUND(('DCF Model'!C45/(1+$B21)^('DCF Model'!C19+0)+'DCF Model'!D45/(1+$B21)^('DCF Model'!C19+1)+'DCF Model'!E45/(1+$B21)^('DCF Model'!C19+2)+'DCF Model'!F45/(1+$B21)^('DCF Model'!C19+3)+'DCF Model'!G45/(1+$B21)^('DCF Model'!C19+4)+('DCF Model'!G39+'DCF Model'!G42)*D$17/(1+$B21)^('DCF Model'!C19+4)-'DCF Model'!C16)*1000000/'DCF Model'!C15,0),"") -> 158 | E21: =IFERROR(ROUND(('DCF Model'!C45/(1+$B21)^('DCF Model'!C19+0)+'DCF Model'!D45/(1+$B21)^('DCF Model'!C19+1)+'DCF Model'!E45/(1+$B21)^('DCF Model'!C19+2)+'DCF Model'!F45/(1+$B21)^('DCF Model'!C19+3)+'DCF Model'!G45/(1+$B21)^('DCF Model'!C19+4)+('DCF Model'!G39+'DCF Model'!G42)*E$17/(1+$B21)^('DCF Model'!C19+4)-'DCF Model'!C16)*1000000/'DCF Model'!C15,0),"") -> 358 | F21: =IFERROR(ROUND(('DCF Model'!C45/(1+$B21)^('DCF Model'!C19+0)+'DCF Model'!D45/(1+$B21)^('DCF Model'!C19+1)+'DCF Model'!E45/(1+$B21)^('DCF Model'!C19+2)+'DCF Model'!F45/(1+$B21)^('DCF Model'!C19+3)+'DCF Model'!G45/(1+$B21)^('DCF Model'!C19+4)+('DCF Model'!G39+'DCF Model'!G42)*F$17/(1+$B21)^('DCF Model'!C19+4)-'DCF Model'!C16)*1000000/'DCF Model'!C15,0),"") -> 558 | G21: =IFERROR(ROUND(('DCF Model'!C45/(1+$B21)^('DCF Model'!C19+0)+'DCF Model'!D45/(1+$B21)^('DCF Model'!C19+1)+'DCF Model'!E45/(1+$B21)^('DCF Model'!C19+2)+'DCF Model'!F45/(1+$B21)^('DCF Model'!C19+3)+'DCF Model'!G45/(1+$B21)^('DCF Model'!C19+4)+('DCF Model'!G39+'DCF Model'!G42)*G$17/(1+$B21)^('DCF Model'!C19+4)-'DCF Model'!C16)*1000000/'DCF Model'!C15,0),"") -> 758 | H21: =IFERROR(ROUND(('DCF Model'!C45/(1+$B21)^('DCF Model'!C19+0)+'DCF Model'!D45/(1+$B21)^('DCF Model'!C19+1)+'DCF Model'!E45/(1+$B21)^('DCF Model'!C19+2)+'DCF Model'!F45/(1+$B21)^('DCF Model'!C19+3)+'DCF Model'!G45/(1+$B21)^('DCF Model'!C19+4)+('DCF Model'!G39+'DCF Model'!G42)*H$17/(1+$B21)^('DCF Model'!C19+4)-'DCF Model'!C16)*1000000/'DCF Model'!C15,0),"") -> 958 | I21: =IFERROR(ROUND(('DCF Model'!C45/(1+$B21)^('DCF Model'!C19+0)+'DCF Model'!D45/(1+$B21)^('DCF Model'!C19+1)+'DCF Model'!E45/(1+$B21)^('DCF Model'!C19+2)+'DCF Model'!F45/(1+$B21)^('DCF Model'!C19+3)+'DCF Model'!G45/(1+$B21)^('DCF Model'!C19+4)+('DCF Model'!G39+'DCF Model'!G42)*I$17/(1+$B21)^('DCF Model'!C19+4)-'DCF Model'!C16)*1000000/'DCF Model'!C15,0),"") -> 1158
B22: =$C$3+0.005 -> 0.095571884 | C22: =IFERROR(ROUND(('DCF Model'!C45/(1+$B22)^('DCF Model'!C19+0)+'DCF Model'!D45/(1+$B22)^('DCF Model'!C19+1)+'DCF Model'!E45/(1+$B22)^('DCF Model'!C19+2)+'DCF Model'!F45/(1+$B22)^('DCF Model'!C19+3)+'DCF Model'!G45/(1+$B22)^('DCF Model'!C19+4)+('DCF Model'!G39+'DCF Model'!G42)*C$17/(1+$B22)^('DCF Model'!C19+4)-'DCF Model'!C16)*1000000/'DCF Model'!C15,0),"") -> -68 | D22: =IFERROR(ROUND(('DCF Model'!C45/(1+$B22)^('DCF Model'!C19+0)+'DCF Model'!D45/(1+$B22)^('DCF Model'!C19+1)+'DCF Model'!E45/(1+$B22)^('DCF Model'!C19+2)+'DCF Model'!F45/(1+$B22)^('DCF Model'!C19+3)+'DCF Model'!G45/(1+$B22)^('DCF Model'!C19+4)+('DCF Model'!G39+'DCF Model'!G42)*D$17/(1+$B22)^('DCF Model'!C19+4)-'DCF Model'!C16)*1000000/'DCF Model'!C15,0),"") -> 128 | E22: =IFERROR(ROUND(('DCF Model'!C45/(1+$B22)^('DCF Model'!C19+0)+'DCF Model'!D45/(1+$B22)^('DCF Model'!C19+1)+'DCF Model'!E45/(1+$B22)^('DCF Model'!C19+2)+'DCF Model'!F45/(1+$B22)^('DCF Model'!C19+3)+'DCF Model'!G45/(1+$B22)^('DCF Model'!C19+4)+('DCF Model'!G39+'DCF Model'!G42)*E$17/(1+$B22)^('DCF Model'!C19+4)-'DCF Model'!C16)*1000000/'DCF Model'!C15,0),"") -> 323 | F22: =IFERROR(ROUND(('DCF Model'!C45/(1+$B22)^('DCF Model'!C19+0)+'DCF Model'!D45/(1+$B22)^('DCF Model'!C19+1)+'DCF Model'!E45/(1+$B22)^('DCF Model'!C19+2)+'DCF Model'!F45/(1+$B22)^('DCF Model'!C19+3)+'DCF Model'!G45/(1+$B22)^('DCF Model'!C19+4)+('DCF Model'!G39+'DCF Model'!G42)*F$17/(1+$B22)^('DCF Model'!C19+4)-'DCF Model'!C16)*1000000/'DCF Model'!C15,0),"") -> 519 | G22: =IFERROR(ROUND(('DCF Model'!C45/(1+$B22)^('DCF Model'!C19+0)+'DCF Model'!D45/(1+$B22)^('DCF Model'!C19+1)+'DCF Model'!E45/(1+$B22)^('DCF Model'!C19+2)+'DCF Model'!F45/(1+$B22)^('DCF Model'!C19+3)+'DCF Model'!G45/(1+$B22)^('DCF Model'!C19+4)+('DCF Model'!G39+'DCF Model'!G42)*G$17/(1+$B22)^('DCF Model'!C19+4)-'DCF Model'!C16)*1000000/'DCF Model'!C15,0),"") -> 715 | H22: =IFERROR(ROUND(('DCF Model'!C45/(1+$B22)^('DCF Model'!C19+0)+'DCF Model'!D45/(1+$B22)^('DCF Model'!C19+1)+'DCF Model'!E45/(1+$B22)^('DCF Model'!C19+2)+'DCF Model'!F45/(1+$B22)^('DCF Model'!C19+3)+'DCF Model'!G45/(1+$B22)^('DCF Model'!C19+4)+('DCF Model'!G39+'DCF Model'!G42)*H$17/(1+$B22)^('DCF Model'!C19+4)-'DCF Model'!C16)*1000000/'DCF Model'!C15,0),"") -> 910 | I22: =IFERROR(ROUND(('DCF Model'!C45/(1+$B22)^('DCF Model'!C19+0)+'DCF Model'!D45/(1+$B22)^('DCF Model'!C19+1)+'DCF Model'!E45/(1+$B22)^('DCF Model'!C19+2)+'DCF Model'!F45/(1+$B22)^('DCF Model'!C19+3)+'DCF Model'!G45/(1+$B22)^('DCF Model'!C19+4)+('DCF Model'!G39+'DCF Model'!G42)*I$17/(1+$B22)^('DCF Model'!C19+4)-'DCF Model'!C16)*1000000/'DCF Model'!C15,0),"") -> 1106
B23: =$C$3+0.01 -> 0.10057188 | C23: =IFERROR(ROUND(('DCF Model'!C45/(1+$B23)^('DCF Model'!C19+0)+'DCF Model'!D45/(1+$B23)^('DCF Model'!C19+1)+'DCF Model'!E45/(1+$B23)^('DCF Model'!C19+2)+'DCF Model'!F45/(1+$B23)^('DCF Model'!C19+3)+'DCF Model'!G45/(1+$B23)^('DCF Model'!C19+4)+('DCF Model'!G39+'DCF Model'!G42)*C$17/(1+$B23)^('DCF Model'!C19+4)-'DCF Model'!C16)*1000000/'DCF Model'!C15,0),"") -> -94 | D23: =IFERROR(ROUND(('DCF Model'!C45/(1+$B23)^('DCF Model'!C19+0)+'DCF Model'!D45/(1+$B23)^('DCF Model'!C19+1)+'DCF Model'!E45/(1+$B23)^('DCF Model'!C19+2)+'DCF Model'!F45/(1+$B23)^('DCF Model'!C19+3)+'DCF Model'!G45/(1+$B23)^('DCF Model'!C19+4)+('DCF Model'!G39+'DCF Model'!G42)*D$17/(1+$B23)^('DCF Model'!C19+4)-'DCF Model'!C16)*1000000/'DCF Model'!C15,0),"") -> 98 | E23: =IFERROR(ROUND(('DCF Model'!C45/(1+$B23)^('DCF Model'!C19+0)+'DCF Model'!D45/(1+$B23)^('DCF Model'!C19+1)+'DCF Model'!E45/(1+$B23)^('DCF Model'!C19+2)+'DCF Model'!F45/(1+$B23)^('DCF Model'!C19+3)+'DCF Model'!G45/(1+$B23)^('DCF Model'!C19+4)+('DCF Model'!G39+'DCF Model'!G42)*E$17/(1+$B23)^('DCF Model'!C19+4)-'DCF Model'!C16)*1000000/'DCF Model'!C15,0),"") -> 289 | F23: =IFERROR(ROUND(('DCF Model'!C45/(1+$B23)^('DCF Model'!C19+0)+'DCF Model'!D45/(1+$B23)^('DCF Model'!C19+1)+'DCF Model'!E45/(1+$B23)^('DCF Model'!C19+2)+'DCF Model'!F45/(1+$B23)^('DCF Model'!C19+3)+'DCF Model'!G45/(1+$B23)^('DCF Model'!C19+4)+('DCF Model'!G39+'DCF Model'!G42)*F$17/(1+$B23)^('DCF Model'!C19+4)-'DCF Model'!C16)*1000000/'DCF Model'!C15,0),"") -> 481 | G23: =IFERROR(ROUND(('DCF Model'!C45/(1+$B23)^('DCF Model'!C19+0)+'DCF Model'!D45/(1+$B23)^('DCF Model'!C19+1)+'DCF Model'!E45/(1+$B23)^('DCF Model'!C19+2)+'DCF Model'!F45/(1+$B23)^('DCF Model'!C19+3)+'DCF Model'!G45/(1+$B23)^('DCF Model'!C19+4)+('DCF Model'!G39+'DCF Model'!G42)*G$17/(1+$B23)^('DCF Model'!C19+4)-'DCF Model'!C16)*1000000/'DCF Model'!C15,0),"") -> 672 | H23: =IFERROR(ROUND(('DCF Model'!C45/(1+$B23)^('DCF Model'!C19+0)+'DCF Model'!D45/(1+$B23)^('DCF Model'!C19+1)+'DCF Model'!E45/(1+$B23)^('DCF Model'!C19+2)+'DCF Model'!F45/(1+$B23)^('DCF Model'!C19+3)+'DCF Model'!G45/(1+$B23)^('DCF Model'!C19+4)+('DCF Model'!G39+'DCF Model'!G42)*H$17/(1+$B23)^('DCF Model'!C19+4)-'DCF Model'!C16)*1000000/'DCF Model'!C15,0),"") -> 864 | I23: =IFERROR(ROUND(('DCF Model'!C45/(1+$B23)^('DCF Model'!C19+0)+'DCF Model'!D45/(1+$B23)^('DCF Model'!C19+1)+'DCF Model'!E45/(1+$B23)^('DCF Model'!C19+2)+'DCF Model'!F45/(1+$B23)^('DCF Model'!C19+3)+'DCF Model'!G45/(1+$B23)^('DCF Model'!C19+4)+('DCF Model'!G39+'DCF Model'!G42)*I$17/(1+$B23)^('DCF Model'!C19+4)-'DCF Model'!C16)*1000000/'DCF Model'!C15,0),"") -> 1056
B24: =$C$3+0.015 -> 0.10557188 | C24: =IFERROR(ROUND(('DCF Model'!C45/(1+$B24)^('DCF Model'!C19+0)+'DCF Model'!D45/(1+$B24)^('DCF Model'!C19+1)+'DCF Model'!E45/(1+$B24)^('DCF Model'!C19+2)+'DCF Model'!F45/(1+$B24)^('DCF Model'!C19+3)+'DCF Model'!G45/(1+$B24)^('DCF Model'!C19+4)+('DCF Model'!G39+'DCF Model'!G42)*C$17/(1+$B24)^('DCF Model'!C19+4)-'DCF Model'!C16)*1000000/'DCF Model'!C15,0),"") -> -118 | D24: =IFERROR(ROUND(('DCF Model'!C45/(1+$B24)^('DCF Model'!C19+0)+'DCF Model'!D45/(1+$B24)^('DCF Model'!C19+1)+'DCF Model'!E45/(1+$B24)^('DCF Model'!C19+2)+'DCF Model'!F45/(1+$B24)^('DCF Model'!C19+3)+'DCF Model'!G45/(1+$B24)^('DCF Model'!C19+4)+('DCF Model'!G39+'DCF Model'!G42)*D$17/(1+$B24)^('DCF Model'!C19+4)-'DCF Model'!C16)*1000000/'DCF Model'!C15,0),"") -> 69 | E24: =IFERROR(ROUND(('DCF Model'!C45/(1+$B24)^('DCF Model'!C19+0)+'DCF Model'!D45/(1+$B24)^('DCF Model'!C19+1)+'DCF Model'!E45/(1+$B24)^('DCF Model'!C19+2)+'DCF Model'!F45/(1+$B24)^('DCF Model'!C19+3)+'DCF Model'!G45/(1+$B24)^('DCF Model'!C19+4)+('DCF Model'!G39+'DCF Model'!G42)*E$17/(1+$B24)^('DCF Model'!C19+4)-'DCF Model'!C16)*1000000/'DCF Model'!C15,0),"") -> 256 | F24: =IFERROR(ROUND(('DCF Model'!C45/(1+$B24)^('DCF Model'!C19+0)+'DCF Model'!D45/(1+$B24)^('DCF Model'!C19+1)+'DCF Model'!E45/(1+$B24)^('DCF Model'!C19+2)+'DCF Model'!F45/(1+$B24)^('DCF Model'!C19+3)+'DCF Model'!G45/(1+$B24)^('DCF Model'!C19+4)+('DCF Model'!G39+'DCF Model'!G42)*F$17/(1+$B24)^('DCF Model'!C19+4)-'DCF Model'!C16)*1000000/'DCF Model'!C15,0),"") -> 444 | G24: =IFERROR(ROUND(('DCF Model'!C45/(1+$B24)^('DCF Model'!C19+0)+'DCF Model'!D45/(1+$B24)^('DCF Model'!C19+1)+'DCF Model'!E45/(1+$B24)^('DCF Model'!C19+2)+'DCF Model'!F45/(1+$B24)^('DCF Model'!C19+3)+'DCF Model'!G45/(1+$B24)^('DCF Model'!C19+4)+('DCF Model'!G39+'DCF Model'!G42)*G$17/(1+$B24)^('DCF Model'!C19+4)-'DCF Model'!C16)*1000000/'DCF Model'!C15,0),"") -> 631 | H24: =IFERROR(ROUND(('DCF Model'!C45/(1+$B24)^('DCF Model'!C19+0)+'DCF Model'!D45/(1+$B24)^('DCF Model'!C19+1)+'DCF Model'!E45/(1+$B24)^('DCF Model'!C19+2)+'DCF Model'!F45/(1+$B24)^('DCF Model'!C19+3)+'DCF Model'!G45/(1+$B24)^('DCF Model'!C19+4)+('DCF Model'!G39+'DCF Model'!G42)*H$17/(1+$B24)^('DCF Model'!C19+4)-'DCF Model'!C16)*1000000/'DCF Model'!C15,0),"") -> 819 | I24: =IFERROR(ROUND(('DCF Model'!C45/(1+$B24)^('DCF Model'!C19+0)+'DCF Model'!D45/(1+$B24)^('DCF Model'!C19+1)+'DCF Model'!E45/(1+$B24)^('DCF Model'!C19+2)+'DCF Model'!F45/(1+$B24)^('DCF Model'!C19+3)+'DCF Model'!G45/(1+$B24)^('DCF Model'!C19+4)+('DCF Model'!G39+'DCF Model'!G42)*I$17/(1+$B24)^('DCF Model'!C19+4)-'DCF Model'!C16)*1000000/'DCF Model'!C15,0),"") -> 1006
B26: All values dynamically linked to DCF Model. Headers auto-center on current WACC / Terminal g / Exit Multiple.
B28: Table 3: FX Sensitivity - FY2027(E) Operating Income (USD連動比率は推定・会社開示なし・要確認)
B29: Company FX assumption (USD/JPY, H2 guidance) | C29: 150
B30: USD-linked revenue ratio (推定) | C30: 0.6
B31: USD-linked COGS ratio (推定) | C31: 0.25
B32: FY2027(E) Revenue - active scenario | C32: ='DCF Model'!C33 -> 50050.832
B33: FY2027(E) COGS - active scenario | C33: ='DCF Model'!C34 -> 39790.411
B34: FY2027(E) Operating Income - active scenario | C34: ='DCF Model'!C39 -> 4154.2191
B35: OP sensitivity per +/-1 JPY per USD (JPY mn) | C35: =(C32*C30-C33*C31)/C29 -> 133.88598
B37: USD/JPY rate | C37: =$C$29-20 -> 130 | D37: =$C$29-10 -> 140 | E37: =$C$29-5 -> 145 | F37: =$C$29 -> 150 | G37: =$C$29+5 -> 155 | H37: =$C$29+10 -> 160 | I37: =$C$29+20 -> 170
B38: Implied FY2027(E) OP (JPY mn) | C38: =$C$34+(C37-$C$29)*$C$35 -> 1476.4995 | D38: =$C$34+(D37-$C$29)*$C$35 -> 2815.3593 | E38: =$C$34+(E37-$C$29)*$C$35 -> 3484.7892 | F38: =$C$34+(F37-$C$29)*$C$35 -> 4154.2191 | G38: =$C$34+(G37-$C$29)*$C$35 -> 4823.6489 | H38: =$C$34+(H37-$C$29)*$C$35 -> 5493.0788 | I38: =$C$34+(I37-$C$29)*$C$35 -> 6831.9386
B39: Implied OPM | C39: =C38/$C$32 -> 0.0295 | D39: =D38/$C$32 -> 0.05625 | E39: =E38/$C$32 -> 0.069625 | F39: =F38/$C$32 -> 0.083 | G39: =G38/$C$32 -> 0.096375 | H39: =H38/$C$32 -> 0.10975 | I39: =I38/$C$32 -> 0.1365
B40: 円高10円でOPは約▲1.3bn(約▲32%)。円安バフ剥落のDownsideチェックに使用。COGS側のUSD連動(原料輸入)が円高メリットとして一部相殺する構造。

Sheet Adjustments Log
B2: Adjustments Log - Osaka Titanium Technologies
B4: 日付 | C4: セル | D4: 変更内容 | E4: 理由 | F4: 元の値 | G4: 状態
B5: 2026-08-26 | C5: - | D5: Generated by pipeline on 2026-08-26 11:11, template rev e5effd6 | E5: 初期生成（手修正なし） | F5: - | G5: generated
B6: 2026-08-26 | C6: DCF Model!C7 | D6: Risk-Free Rate = 2.90% | E6: 財務省「国債金利情報」10年債 2.897%(基準日2026-08-25)を直接取得。yfinanceでは日本国債利回りが取得できない | F6: テンプレ既定 2.2% | G6: 確定
B7: 2026-08-26 | C7: DCF Model!C8 | D7: Beta = 1.55 | E7: 5726.T 週次2年リターン(105週)を TOPIX連動ETF 1306.T に回帰: 1.553。相関0.442と低く統計的信頼度は限定的 | F7: 自動値 1.0(yfinance info.beta が範囲外のため) | G7: 確定(相関低)
B8: 2026-08-26 | C8: DCF Model!C10 | D8: Size Premium = 1.5% | E8: 時価総額1,003億円でテンプレの「1,000億円以上」区分。閾値の直上0.3%しか離れておらず、株価2%下落で3.0%区分に落ちる | F8: 自動判定 1.5%(同値) | G8: 要確認
B9: 2026-08-26 | C9: DCF Model!C11 | D9: After-tax Cost of Debt = 1.94% | E9: 【推定】税引前2.8% ×(1−0.306)。10年JGB2.897%を基準に、短期借入比率45%と安定株主(神戸製鋼所・住友金属鉱山)による薄いスプレッドを勘案。実際の支払利息は本モデルの入力データに無い | F9: テンプレ既定 | G9: 推定・未解決
B10: 2026-08-26 | C10: DCF Model!C12 | D10: D/E Ratio = 0.4568 | E10: ネット有利子負債45,837 ÷ 時価総額100,346。グロス有利子負債基準なら0.5122でWACCは約0.2pt低下する。EV→株式価値ブリッジがネット控除である点と整合させ、かつ保守側になるネットを採用 | F10: 自動計算 0.4568(同値) | G10: 設計判断
B11: 2026-08-26 | C11: DCF Model!C13 | D11: Terminal Growth = 1.5% | E11: 【推定】10年JGB2.9%の名目環境では控えめ。数量成長が設備投資に律速される装置産業としてミッドサイクル定常を置いた | F11: テンプレ既定 2.5% | G11: 推定
B12: 2026-08-26 | C12: DCF Model!C14 | D12: Exit Multiple (EV/EBITDA) = 8.0x | E12: 【設計判断】国内素材ピア水準(大同特殊鋼7.8x / 日本冶金工業8.3x)。peer中央値は12.1x(宝钛股份)だが、ターミナル年は航空機ブームのピーク倍率でなく成熟ミッドサイクル倍率で評価すべきと判断。PGM逆算Exitは5.88xで乖離1.36倍(validator閾値1.8倍内) | F12: テンプレ既定 10.0x | G12: 設計判断
B13: 2026-08-26 | C13: DCF Model!C42:G42 | D13: D&A(direct) = 3,400 / 3,700 / 3,900 / 3,950 / 3,950 | E13: 【推定】FY2027/3 Q1実績823(前年714)の年換算3,292を起点に、FY2026/3の大型投資(8,072)の稼働開始で逓増させた。会社の償却計画は未開示 | F13: 売上比率方式(実績3年平均5.75%) | G13: 推定
B14: 2026-08-26 | C14: DCF Model!C43:G43 | D14: Capex(direct) = 7,500 / 6,000 / 4,800 / 4,100 / 3,900 | E14: 【推定・本モデル最大の推定領域】FY2026/3実績8,072(前期の2.8倍、長期借入収入16,400で調達)。2026/6末の建設仮勘定4,339はQ1だけで+1,484増でプログラム継続中。ターミナル年capex/D&A=0.99倍に収束させた。会社の設備投資計画・増設能力・稼働時期はいずれも未開示 | F14: 売上比率方式(実績3年平均9.24%) | G14: 推定・未解決
B15: 2026-08-26 | C15: DCF Model!C16 | D15: Net Debt = 45,837(2026/6末) | E15: 有利子負債51,400 − 現金5,563。FY2026/3末基準なら45,655。【基準混在】book_value / core_ebitda / core_net_income は peer と揃えるためFY2026/3通期末基準であり、net_debtのみQ1末基準。差182(0.4%)で結論に影響しない | F15: EDINET自動値 45,655(FY2026/3末) | G15: 確定(基準混在を注記)
... B26: 2026-08-26 | C26: (状態) | D26: 本ファイルは DRAFT。FINAL 化していない | E26: 手順書v2 §6-3 に従い、ユーザーによる検証・手修正が完了するまで _FINAL サフィックスを付けない。validate_output.py は FAIL 0 / WARN 0 | F26: n/a | G26: DRAFT
B28: Pipeline Metadata (do not edit — read by scripts/validate_output.py)
B29: key | C29: value
B30: capex_pct_basis | C30: hist_3yr_avg
B31: capex_pct_c5 | C31: 0.0924
B32: capex_pct_hist3yr | C32: 0.092401
B33: company_name | C33: Osaka Titanium Technologies
B34: comps_asof | C34: 2026-08-26
B35: comps_da_missing | C35: none
B36: comps_ev_ebitda_invalid | C36: no
B37: comps_ev_ebitda_rows | C37: 7,8,9,10,11
B38: comps_impl_mult_row | C38: 27
B39: comps_impl_per_row | C39: 28
B40: comps_peer_rows | C40: 7,8,9,10,11
... B56: ticker | C56: 5726.T
B58: 手修正記録 (2026-08-26, ユーザー委任によりClaude chatが実施。DRAFT継続)
B59: 2026-08-26 | C59: Executive Summary!C10-C12,C21 | D59: Target平均をDCF2本(PGM/Exit)のみに変更、Comps2本は[参考]に降格 | E59: プロンプト要件9(CompsはTarget平均不算入)への準拠。3905でのComps除外判断と同型 | F59: AVERAGE(C16:C19)=1,116 | G59: 確定
B60: 2026-08-26 | C60: Executive Summary!C17,D17 | D60: Downside時に負のExit株価をINVALID化するガード追加 | E60: ログB25のテンプレ課題への暫定対処。株式価値の下限は0 | F60: ガードなし | G60: 確定
B61: 2026-08-26 | C61: DCF Model!C11 | D61: 税引後負債コスト 1.94%→0.59% | E61: FY2026/3実績: 支払利息342+ローン手数料57=399 / 平均有利子負債46,750 = 税引前0.85%。注意: 新規長期借入16,400のマージナルコストはJGB2.9%環境でこれより高い可能性→差し戻し判断可。WACC 9.48%→9.06% | F61: 0.0194(推定2.8%税引前) | G61: 要確認
B62: 2026-08-26 | C62: Comps Analysis!C29,C30 | D62: 正常化純利益4,465と参考PER価格の行を追加 | E62: 特損2,619による分母歪みの補正参考値(ログB20の未解決事項への対応)。Target不算入 | F62: なし | G62: 確定
B63: 2026-08-26 | C63: Sensitivity!28-40行 | D63: Table3 為替感応度ブロック追加 | E63: プロンプト要件7。USD連動売上比率0.60/原価比率0.25は推定(会社は感応度未開示)→要確認。感応度は約134百万円/円 | F63: なし | G63: 推定・要確認
B64: 2026-08-26 | C64: Financial Statements!B27 | D64: ラベル修正: Short-term Debt→Total Interest-bearing Debt | E64: C27:G27の値は短期+長期の合計であり旧ラベルは誤り | F64: Short-term Debt | G64: 確定
B65: 2026-08-26 | C65: (未対応) | D65: セグメント分解/DIH正常化速度/前倒し四半期化は未対応のまま | E65: セグメント=短信セグメント注記の供給待ち。DIH=ユーザー判断待ち(ログB16)。前倒し=ログB22 | F65: n/a | G65: 未解決
