Workbook

Sheet Cover & Thesis
B2: SOTP Valuation Model
B3: Valuation Date: April 2026
B5: Investment Thesis
B6: DMW's consolidated valuation obscures the high-growth overseas desalination business (DeROs). SOTP separates the stable domestic public-sector pump business from the higher-margin, higher-growth overseas segment to reveal hidden value. DeROs achieves world-best energy recovery efficiency of 99.7%, positioning DMW for Middle East / India desalination TAM expansion.
B10: Valuation Cross-Check
B11: Method | C11: Fair Value (¥) | D11: vs SOTP Base
B12: SOTP (Base Case) | C12: ='SOTP Valuation'!C27 | D12: —
B13: DCF - Perpetuity Growth | C13: 5882 | D13: =(C13-$C$12)/$C$12
B14: DCF - Exit Multiple | C14: 9660 | D14: =(C14-$C$12)/$C$12
B15: Comps - EV/EBITDA Median | C15: 9772 | D15: =(C15-$C$12)/$C$12
B16: Comps - PER Median | C16: 7496 | D16: =(C16-$C$12)/$C$12
B18: DCF cross-check as of 2026-09-06 23:29 from 6365_DCF_Model_20260413.xlsx (static snapshot — regenerate after re-running the DCF)

Sheet Segment Data
B1: Segment Financial Data
B2: (¥ millions)
B4: Segment | C4: FY23 | D4: FY24 | E4: FY25E
B5: Public Sector (Pumps & Blowers) (官需部門（ポンプ・送風機）)
B6: Revenue | C6: 10000 | D6: 11000 | E6: 11500
B7: Operating Profit | C7: 900 | D7: 1000 | E7: 1100
B8: OPM % | C8: =IF(C6=0,0,C7/C6) | D8: =IF(D6=0,0,D7/D6) | E8: =IF(E6=0,0,E7/E6)
B10: Private Sector (Industrial Pumps & Blowers) (民需部門（産業用ポンプ・送風機）)
B11: Revenue | C11: 8500 | D11: 9500 | E11: 10000
B12: Operating Profit | C12: 800 | D12: 1000 | E12: 1100
B13: OPM % | C13: =IF(C11=0,0,C12/C11) | D13: =IF(D11=0,0,D12/D11) | E13: =IF(E11=0,0,E12/E11)
B15: Overseas & Desalination (DeROs + Export) (海外・淡水化部門（DeROs・輸出）)
B16: Revenue | C16: 5000 | D16: 6000 | E16: 6500
B17: Operating Profit | C17: 500 | D17: 700 | E17: 800
B18: OPM % | C18: =IF(C16=0,0,C17/C16) | D18: =IF(D16=0,0,D17/D16) | E18: =IF(E16=0,0,E17/E16)
B20: Consolidated Total
B21: Total Revenue | C21: =C6+C11+C16 | D21: =D6+D11+D16 | E21: =E6+E11+E16
B22: Total Operating Profit | C22: =C7+C12+C17 | D22: =D7+D12+D17 | E22: =E7+E12+E17
B23: Total OPM % | C23: =IF(C21=0,0,C22/C21) | D23: =IF(D21=0,0,D22/D21) | E23: =IF(E21=0,0,E22/E21)

Sheet Peer Comps
B1: Peer Comparable Analysis
B3: Public Sector (Pumps & Blowers)
B4: Company | C4: Ticker | D4: EV/EBITDA | E4: OPM % | F4: Mkt Cap ($B) | G4: Note
B5: Maezawa Industries | C5: 6489.T | D5: 7.5 | E5: 0.08 | F5: 0.25 | G5: Water/sewage equipment. Similar public-sector mix
B6: Tsurumi Manufacturing | C6: 6351.T | D6: 8 | E6: 0.13 | F6: 0.78 | G6: Water pump major. Higher margin
B7: Kubota (Water seg.) | C7: 6326.T | D7: 10 | E7: 0.1 | F7: 22 | G7: Water infrastructure. Much larger - EXCLUDED
B8: Median | D8: =MEDIAN(D5,D6)
B9: Selected Multiple | C9: Median of domestic water infrastructure peers. Stable but low-growth → discount to industrial pump median. | D9: 7
B11: Private Sector (Industrial Pumps & Blowers)
B12: Company | C12: Ticker | D12: EV/EBITDA | E12: OPM % | F12: Mkt Cap ($B) | G12: Note
B13: Torishima Pump | C13: 6363.T | D13: 9 | E13: 0.065 | F13: 0.6 | G13: Anchor comp. Large pump + power plant focus
B14: Kaji Technology | C14: 6391.T | D14: 8.5 | E14: 0.1 | F14: 0.05 | G14: High-pressure gas compressor. Backlog-driven
B15: Iwaki Co. | C15: 6237.T | D15: 8 | E15: 0.09 | F15: 0.42 | G15: Chemical pump specialist
B16: Median | D16: =MEDIAN(D13,D14,D15)
B17: Selected Multiple | C17: Median of industrial pump / machinery peers. Cyclical but improving margins. | D17: 8.5
B19: Overseas & Desalination (DeROs + Export)
B20: Company | C20: Ticker | D20: EV/EBITDA | E20: OPM % | F20: Mkt Cap ($B) | G20: Note
B21: Torishima Pump (Overseas) | C21: 6363.T | D21: 9 | E21: 0.065 | F21: 0.6 | G21: Desalination pump peer. Overseas revenue ~40%
B22: Organo Corp | C22: 6368.T | D22: 14 | E22: 0.11 | F22: 2.5 | G22: Water treatment equipment. Higher growth premium
B23: Metawater | C23: 9551.T | D23: 12 | E23: 0.09 | F23: 0.7 | G23: Water infrastructure. Reference only
B24: Median | D24: =MEDIAN(D21,D22)
B25: Selected Multiple | C25: Premium to domestic peers: (1) DeROs world-best energy recovery 99.7%, (2) India factory expansion, (3) Middle East / Africa desalination TAM growth. | D25: 12

Sheet SOTP Valuation
B1: SOTP Valuation
B2: (¥ millions unless noted)
B4: Segment | C4: OP (FY25E) | D4: D&A Alloc % | E4: D&A | F4: EBITDA | G4: Multiple (x) | H4: Segment EV
B5: Public Sector (Pumps & Blowers) | C5: ='Segment Data'!E7 | D5: 0.45 | E5: =B11*D5 | F5: =C5+E5 | G5: ='Peer Comps'!D9 | H5: =F5*G5
B6: Private Sector (Industrial Pumps & Blowers) | C6: ='Segment Data'!E12 | D6: 0.3 | E6: =B11*D6 | F6: =C6+E6 | G6: ='Peer Comps'!D17 | H6: =F6*G6
B7: Overseas & Desalination (DeROs + Export) | C7: ='Segment Data'!E17 | D7: 0.25 | E7: =B11*D7 | F7: =C7+E7 | G7: ='Peer Comps'!D25 | H7: =F7*G7
B8: Equity Method Investments | C8: 0 | F8: =C8 | G8: 10 | H8: =F8*G8
B9: Total Segment EV | H9: =H5+H6+H7+H8
B11: 650 | C11: ← Consolidated D&A (input)
B13: EV Composition %
B14: Public Sector (Pumps & Blowers) | C14: =H5/H9
B15: Private Sector (Industrial Pumps & Blowers) | C15: =H6/H9
B16: Overseas & Desalination (DeROs + Export) | C16: =H7/H9
B18: Equity Bridge
B19: Total Enterprise Value | C19: =H9
B20: Conglomerate Discount | C20: 0
B21: Adjusted EV | C21: =C19*(1-C20)
B22: Less: Net Debt | C22: -6515
B23: Less: Minority Interest | C23: 0
B24: Equity Value | C24: =C21-C22-C23
B25: Shares Outstanding (thousands) | C25: 4145
B26: Stock Split Ratio | C26: 1
B27: Fair Value Per Share (post-split) | C27: =C24*1000/C25/C26 | D27: Fair Value = Equity Value (¥M) × 1,000 ÷ Shares (千株) ÷ split. 株数は【千株】単位（dcf_comps_template は【株】単位: 桁が3つ違う）

Sheet Sensitivity
B1: Sensitivity Analysis
B3: Table 1: Overseas & Desalination (DeROs + Export) Multiple × Conglomerate Discount
B4: Fair Value (¥/share, post-split)
B5: Base Assumptions (do not edit)
B6: Public Sector (Pumps & Blowers) OP | C6: ='SOTP Valuation'!C5 | D6: ='SOTP Valuation'!E5 | E6: =C6+D6 | F6: ='SOTP Valuation'!G5
B7: Private Sector (Industrial Pumps & Blowers) OP | C7: ='SOTP Valuation'!C6 | D7: ='SOTP Valuation'!E6 | E7: =C7+D7 | F7: ='SOTP Valuation'!G6
B8: Overseas & Desalination (DeROs + Export) OP | C8: ='SOTP Valuation'!C7 | D8: ='SOTP Valuation'!E7 | E8: =C8+D8 | F8: ='SOTP Valuation'!G7
B9: Equity Method EV | C9: ='SOTP Valuation'!H8
B10: Net Debt | C10: ='SOTP Valuation'!C22
B11: Minority Interest | C11: ='SOTP Valuation'!C23
B12: Shares (thousands) | C12: ='SOTP Valuation'!C25
B13: Split Ratio | C13: ='SOTP Valuation'!C26
B15: Overseas & Desalination (DeROs + Export) EV/EBITDA → | C15: 8 | D15: 10 | E15: 12 | F15: 14 | G15: 16
B16: 0 | C16: =(($E$8*8+E6*F6+E7*F7+C9)*(1-$B16)-$C$10-$C$11)*1000/$C$12/$C$13 | D16: =(($E$8*10+E6*F6+E7*F7+C9)*(1-$B16)-$C$10-$C$11)*1000/$C$12/$C$13 | E16: =(($E$8*12+E6*F6+E7*F7+C9)*(1-$B16)-$C$10-$C$11)*1000/$C$12/$C$13 | F16: =(($E$8*14+E6*F6+E7*F7+C9)*(1-$B16)-$C$10-$C$11)*1000/$C$12/$C$13 | G16: =(($E$8*16+E6*F6+E7*F7+C9)*(1-$B16)-$C$10-$C$11)*1000/$C$12/$C$13
B17: 0.05 | C17: =(($E$8*8+E6*F6+E7*F7+C9)*(1-$B17)-$C$10-$C$11)*1000/$C$12/$C$13 | D17: =(($E$8*10+E6*F6+E7*F7+C9)*(1-$B17)-$C$10-$C$11)*1000/$C$12/$C$13 | E17: =(($E$8*12+E6*F6+E7*F7+C9)*(1-$B17)-$C$10-$C$11)*1000/$C$12/$C$13 | F17: =(($E$8*14+E6*F6+E7*F7+C9)*(1-$B17)-$C$10-$C$11)*1000/$C$12/$C$13 | G17: =(($E$8*16+E6*F6+E7*F7+C9)*(1-$B17)-$C$10-$C$11)*1000/$C$12/$C$13
B18: 0.1 | C18: =(($E$8*8+E6*F6+E7*F7+C9)*(1-$B18)-$C$10-$C$11)*1000/$C$12/$C$13 | D18: =(($E$8*10+E6*F6+E7*F7+C9)*(1-$B18)-$C$10-$C$11)*1000/$C$12/$C$13 | E18: =(($E$8*12+E6*F6+E7*F7+C9)*(1-$B18)-$C$10-$C$11)*1000/$C$12/$C$13 | F18: =(($E$8*14+E6*F6+E7*F7+C9)*(1-$B18)-$C$10-$C$11)*1000/$C$12/$C$13 | G18: =(($E$8*16+E6*F6+E7*F7+C9)*(1-$B18)-$C$10-$C$11)*1000/$C$12/$C$13
B19: 0.15 | C19: =(($E$8*8+E6*F6+E7*F7+C9)*(1-$B19)-$C$10-$C$11)*1000/$C$12/$C$13 | D19: =(($E$8*10+E6*F6+E7*F7+C9)*(1-$B19)-$C$10-$C$11)*1000/$C$12/$C$13 | E19: =(($E$8*12+E6*F6+E7*F7+C9)*(1-$B19)-$C$10-$C$11)*1000/$C$12/$C$13 | F19: =(($E$8*14+E6*F6+E7*F7+C9)*(1-$B19)-$C$10-$C$11)*1000/$C$12/$C$13 | G19: =(($E$8*16+E6*F6+E7*F7+C9)*(1-$B19)-$C$10-$C$11)*1000/$C$12/$C$13
B20: 0.2 | C20: =(($E$8*8+E6*F6+E7*F7+C9)*(1-$B20)-$C$10-$C$11)*1000/$C$12/$C$13 | D20: =(($E$8*10+E6*F6+E7*F7+C9)*(1-$B20)-$C$10-$C$11)*1000/$C$12/$C$13 | E20: =(($E$8*12+E6*F6+E7*F7+C9)*(1-$B20)-$C$10-$C$11)*1000/$C$12/$C$13 | F20: =(($E$8*14+E6*F6+E7*F7+C9)*(1-$B20)-$C$10-$C$11)*1000/$C$12/$C$13 | G20: =(($E$8*16+E6*F6+E7*F7+C9)*(1-$B20)-$C$10-$C$11)*1000/$C$12/$C$13
B23: Table 2: Public Sector (Pumps & Blowers) × Private Sector (Industrial Pumps & Blowers) Multiple Sensitivity
B24: Fair Value (¥/share, post-split) — Base discount, base Overseas & Desalination (DeROs + Export) multiple
B25: Public Sector (Pumps & Blowers) ↓ / Private Sector (Industrial Pumps & Blowers) → | C25: 6 | D25: 7 | E25: 8 | F25: 9 | G25: 10
B26: 5 | C26: =(($E$6*$B26+$E$7*C$25+$E$8*$F$8+$C$9)*(1-'SOTP Valuation'!$C$20)-$C$10-$C$11)*1000/$C$12/$C$13 | D26: =(($E$6*$B26+$E$7*D$25+$E$8*$F$8+$C$9)*(1-'SOTP Valuation'!$C$20)-$C$10-$C$11)*1000/$C$12/$C$13 | E26: =(($E$6*$B26+$E$7*E$25+$E$8*$F$8+$C$9)*(1-'SOTP Valuation'!$C$20)-$C$10-$C$11)*1000/$C$12/$C$13 | F26: =(($E$6*$B26+$E$7*F$25+$E$8*$F$8+$C$9)*(1-'SOTP Valuation'!$C$20)-$C$10-$C$11)*1000/$C$12/$C$13 | G26: =(($E$6*$B26+$E$7*G$25+$E$8*$F$8+$C$9)*(1-'SOTP Valuation'!$C$20)-$C$10-$C$11)*1000/$C$12/$C$13
B27: 6 | C27: =(($E$6*$B27+$E$7*C$25+$E$8*$F$8+$C$9)*(1-'SOTP Valuation'!$C$20)-$C$10-$C$11)*1000/$C$12/$C$13 | D27: =(($E$6*$B27+$E$7*D$25+$E$8*$F$8+$C$9)*(1-'SOTP Valuation'!$C$20)-$C$10-$C$11)*1000/$C$12/$C$13 | E27: =(($E$6*$B27+$E$7*E$25+$E$8*$F$8+$C$9)*(1-'SOTP Valuation'!$C$20)-$C$10-$C$11)*1000/$C$12/$C$13 | F27: =(($E$6*$B27+$E$7*F$25+$E$8*$F$8+$C$9)*(1-'SOTP Valuation'!$C$20)-$C$10-$C$11)*1000/$C$12/$C$13 | G27: =(($E$6*$B27+$E$7*G$25+$E$8*$F$8+$C$9)*(1-'SOTP Valuation'!$C$20)-$C$10-$C$11)*1000/$C$12/$C$13
B28: 7 | C28: =(($E$6*$B28+$E$7*C$25+$E$8*$F$8+$C$9)*(1-'SOTP Valuation'!$C$20)-$C$10-$C$11)*1000/$C$12/$C$13 | D28: =(($E$6*$B28+$E$7*D$25+$E$8*$F$8+$C$9)*(1-'SOTP Valuation'!$C$20)-$C$10-$C$11)*1000/$C$12/$C$13 | E28: =(($E$6*$B28+$E$7*E$25+$E$8*$F$8+$C$9)*(1-'SOTP Valuation'!$C$20)-$C$10-$C$11)*1000/$C$12/$C$13 | F28: =(($E$6*$B28+$E$7*F$25+$E$8*$F$8+$C$9)*(1-'SOTP Valuation'!$C$20)-$C$10-$C$11)*1000/$C$12/$C$13 | G28: =(($E$6*$B28+$E$7*G$25+$E$8*$F$8+$C$9)*(1-'SOTP Valuation'!$C$20)-$C$10-$C$11)*1000/$C$12/$C$13
B29: 8 | C29: =(($E$6*$B29+$E$7*C$25+$E$8*$F$8+$C$9)*(1-'SOTP Valuation'!$C$20)-$C$10-$C$11)*1000/$C$12/$C$13 | D29: =(($E$6*$B29+$E$7*D$25+$E$8*$F$8+$C$9)*(1-'SOTP Valuation'!$C$20)-$C$10-$C$11)*1000/$C$12/$C$13 | E29: =(($E$6*$B29+$E$7*E$25+$E$8*$F$8+$C$9)*(1-'SOTP Valuation'!$C$20)-$C$10-$C$11)*1000/$C$12/$C$13 | F29: =(($E$6*$B29+$E$7*F$25+$E$8*$F$8+$C$9)*(1-'SOTP Valuation'!$C$20)-$C$10-$C$11)*1000/$C$12/$C$13 | G29: =(($E$6*$B29+$E$7*G$25+$E$8*$F$8+$C$9)*(1-'SOTP Valuation'!$C$20)-$C$10-$C$11)*1000/$C$12/$C$13
B30: 9 | C30: =(($E$6*$B30+$E$7*C$25+$E$8*$F$8+$C$9)*(1-'SOTP Valuation'!$C$20)-$C$10-$C$11)*1000/$C$12/$C$13 | D30: =(($E$6*$B30+$E$7*D$25+$E$8*$F$8+$C$9)*(1-'SOTP Valuation'!$C$20)-$C$10-$C$11)*1000/$C$12/$C$13 | E30: =(($E$6*$B30+$E$7*E$25+$E$8*$F$8+$C$9)*(1-'SOTP Valuation'!$C$20)-$C$10-$C$11)*1000/$C$12/$C$13 | F30: =(($E$6*$B30+$E$7*F$25+$E$8*$F$8+$C$9)*(1-'SOTP Valuation'!$C$20)-$C$10-$C$11)*1000/$C$12/$C$13 | G30: =(($E$6*$B30+$E$7*G$25+$E$8*$F$8+$C$9)*(1-'SOTP Valuation'!$C$20)-$C$10-$C$11)*1000/$C$12/$C$13

Sheet D&A Allocation
B1: D&A Allocation Methodology
B3: セグメント別D&Aは非開示のため、固定資産集約度をもとに按分している。
B4: Segment-level D&A is not disclosed; allocation is estimated from fixed-asset intensity by segment.
B6: Consolidated D&A (FY25E) | C6: 650 | D6: ¥M (input)
B8: Segment | C8: Allocation % | D8: D&A (¥M) | E8: Check
B9: Public Sector (Pumps & Blowers) | C9: 0.45 | D9: =$C$6*C9
B10: Private Sector (Industrial Pumps & Blowers) | C10: 0.3 | D10: =$C$6*C10
B11: Overseas & Desalination (DeROs + Export) | C11: 0.25 | D11: =$C$6*C11
B12: Total | C12: =C9+C10+C11 | D12: =D9+D10+D11 | E12: =IF(ABS(C12-1)<0.001,"OK","CHECK")
B14: Notes:
B15: • Allocation sums to 100% — residual is implicitly in corporate/eliminations
