Workbook

Sheet Executive Summary
B1: DISCLAIMER: This is a sample analysis for demonstration purposes only. It does not constitute investment advice.
B3: パナソニックホールディングス (6752.T)
B4: Equity Research Report
B6: Company | C6: パナソニックホールディングス
B7: Ticker | C7: 6752.T (TSE Prime)
B8: Sector | C8: 電気機器
B9: Current Price | C9: 4163
B10: Target Price (DCF Mid) | C10: =IF(ISNUMBER(C17),ROUND(C17,0),"N/A") -> 2840
B11: Recommendation | C11: =IF(NOT(ISNUMBER(C12)),"N/A",IF(C12>0.15,"BUY",IF(C12>0.05,"HOLD","SELL"))) -> SELL
B12: Upside / Downside | C12: =IF(ISNUMBER(C10),(C10-C9)/C9,"N/A") -> -0.31779966
B14: Valuation Summary
B15: Methodology | C15: Implied Value (JPY) | D15: vs Current Price
B16: DCF - Perpetuity Growth [参考・Target不算入 — 追補5 §U] | C16: =IF('DCF Model'!C53<'DCF Model'!C16,"INVALID (EV < net debt)",'DCF Model'!C55) -> 448 | D16: =IF(ISNUMBER(C16),(C16-C9)/C9,"N/A") -> -0.8923853
B17: DCF - Exit Multiple | C17: =IF('DCF Model'!C62<'DCF Model'!C16,"INVALID (EV < net debt)",'DCF Model'!C64) -> 2840 | D17: =IF(ISNUMBER(C17),(C17-C9)/C9,"N/A") -> -0.31779966
B18: Comps - EV/EBITDA Median [参考・Target不算入] | C18: ='Comps Analysis'!C27 -> 3414 | D18: =IF(ISNUMBER(C18),(C18-C9)/C9,"N/A") -> -0.17991833
B19: Comps - PER Median [参考・Target不算入] | C19: ='Comps Analysis'!C28 -> 2138 | D19: =IF(ISNUMBER(C19),(C19-C9)/C9,"N/A") -> -0.48642806
B20: Note: Target Mid は DCF 2法（PGM / Exit）の平均のみ。Comps 2法は [参考] で Target 不算入（EV<ネットデットで株式価値が負になる手法は INVALID として平均から除外） ■【追補5 §U】型Bミッドサイクル正常化を適用して再生成した後もPGMとExitの乖離が 4.41倍 残ったため、§U の手順に従いどちらを正とするかを個別判断し、**PGM法を[参考]に降格して Target = Exit 単独**とした。PGM逆算のターミナルEV/EBITDAは 3.24倍 で、上場する事業会社が実際に取引される倍率の下限を大きく下回り、ターミナル価値として経験的に成立しない。一方の仮定Exit倍率 14.30倍(Peer中央値)は市場で観測される水準の内側にある。片方の脚が観測可能な範囲の外に出た場合は、内側にある脚を正とする。乖離の原因は本銘柄固有の洞察ではなく、永久成長率1.0%固定の単段階モデルが資本集約型(capex/D&A が持続的に1.5倍超)を評価しきれないという既知のモデル上の限界である(バッチ後の2段階成長モデル導入課題として登録済み)。 ■【追補8 §AF】**本銘柄の Target は「相対評価（Peer倍率準拠）」である。** Target = Exit 単独であり、これは**内在価値としての判定ではなく、当社が Peer 並みの EV/EBITDA 倍率へ再評価されることに依存した判定**である。■**Reverse DCF の Block F を併記する場合の但し書き**: **Block F は PGM脚を基準に計算される**ため、Exit脚を採用した銘柄では Block F は構造的に Target と逆を向きやすい。Block F が Target と逆を指していても、それは矛盾ではなく『どちらの脚を採ったか』の帰結である。
B21: DCF Valuation Range (PGM - Exit) | C21: =IF(COUNT(C16:C17)=0,"N/A",MIN(C16:C17)&" - "&MAX(C16:C17)) -> 448 - 2840
B23: Key Investment Thesis
B24: ="Panasonic is in the middle of a group restructuring while automotive battery capacity ramps in North America, and the operating margin fell to the bottom of its four-year range in the latest year; the shares trade at "&TEXT('Comps Analysis'!L5,"0.0""x""")&" earnings and "&TEXT('Comps Analysis'!M5,"0.00""x""")&" book." -> Panasonic is in the middle of a group restructuring while automotive battery capacity ramps in North America, and the operating margin fell to the bottom of its four-year range in the latest year; the shares trade at 51.3x earnings and 1.87x book.
B25: The realised cost of debt in this model comes from the filings rather than an assumed spread, which matters because interest-bearing debt is twenty percent of revenue.
B26: ="At "&TEXT(C9,"#,##0")&" the market capitalises the depressed margin; a base case that returns to the four-year median supports "&TEXT(C10,"#,##0")&", or "&TEXT(C12,"+0.0%;-0.0%")&" from here." -> At 4,163 the market capitalises the depressed margin; a base case that returns to the four-year median supports 2,840, or -31.8% from here.
B28: Key Risks
B29: ="Capital expenditure reached ten percent of revenue on battery capacity and the base case assumes it halves over five years; if the ramp continues, the free cash flow behind "&TEXT(C10,"#,##0")&" does not appear." -> Capital expenditure reached ten percent of revenue on battery capacity and the base case assumes it halves over five years; if the ramp continues, the free cash flow behind 2,840 does not appear.
B30: Revenue has fallen for two years while the margin also fell, so this is not a mix-shift story — the base-case recovery depends on the restructuring delivering.
B31: ="The apparent EV/EBITDA premium to peers is an artefact of a depressed earnings base rather than a quality rating, so the "&TEXT('Comps Analysis'!L5,"0.0""x""")&" comparison flatters the shares." -> The apparent EV/EBITDA premium to peers is an artefact of a depressed earnings base rather than a quality rating, so the 51.3x comparison flatters the shares.

Sheet Financial Statements
B2: パナソニックホールディングス - Historical Financials (JPY mn)
C4: FY2023 | D4: FY2024 | E4: FY2025 | F4: FY2026
B5: Income Statement
B6: Revenue | C6: 8378942 | D6: 8496420 | E6: 8458185 | F6: 8048722
B7: COGS | C7: 6117494 | D7: 6002065 | E7: 5829569 | F7: 5521854
B8: Gross Profit | C8: =C6-C7 -> 2261448 | D8: =D6-D7 -> 2494355 | E8: =E6-E7 -> 2628616 | F8: =F6-F7 -> 2526868
B9: Gross Margin | C9: =C8/C6 -> 0.26989661 | D9: =D8/D6 -> 0.29357718 | E9: =E8/E6 -> 0.31077779 | F9: =F8/F6 -> 0.31394649
B10: SGA | C10: 1974310 | D10: 2137688 | E10: 2222082 | F10: 2316905
B11: Operating Income | C11: 287138 | D11: 356667 | E11: 406534 | F11: 209963
B12: Net Income | C12: 265502 | D12: 443994 | E12: 366205 | F12: 189540
B13: Operating Margin | C13: =C11/C6 -> 0.034269004 | D13: =D11/D6 -> 0.041978504 | E13: =E11/E6 -> 0.048063976 | F13: =F11/F6 -> 0.026086502
B14: Net Margin | C14: =C12/C6 -> 0.031686817 | D14: =D12/D6 -> 0.052256597 | E14: =E12/E6 -> 0.043295932 | F14: =F12/F6 -> 0.02354908
B15: Revenue Growth (YoY) | C15: n/a | D15: =(D6-C6)/C6 -> 0.014020625 | E15: =(E6-D6)/D6 -> -0.0045001306 | F15: =(F6-E6)/E6 -> -0.048410268
B16: Operating Income Growth (YoY) | C16: n/a | D16: =(D11-C11)/C11 -> 0.24214489 | E16: =(E11-D11)/D11 -> 0.13981389 | F16: =(F11-E11)/E11 -> -0.48352905
B18: Cash Flow Statement
B19: Operating Cash Flow | D19: 866898 | E19: 796083 | F19: 624289
B20: Capex
B21: Free Cash Flow
B22: FCF Margin
B23: Capex / Revenue
B25: Balance Sheet Highlights
B26: Cash & Deposits | C26: 819499 | D26: 1119625 | E26: 847561 | F26: 770179
B27: Total Interest-bearing Debt (short + long)
B28: Net Debt (Cash)
B30: Note: OCF / Cash / Debt coverage OCF 3/4, Cash 4/4, Debt 0/4 — blank cells are years with no year-key match in the source data (verify against 決算短信 or set hist_ocf / hist_cash / hist_debt in overrides).

Sheet DCF Model
B2: DCF Valuation Model - パナソニックホールディングス
B4: Assumptions
B5: Capex / Revenue (fallback) | C5: 0.0525
B6: Effective Tax Rate | C6: 0.25
B7: Risk-Free Rate | C7: 0.0297
B8: Beta | C8: 0.85
B9: Equity Risk Premium | C9: 0.065
B10: Size Premium | C10: 0.01
B11: After-tax Cost of Debt | C11: 0.0199
B12: D/E Ratio | C12: 0.0857
B13: Terminal Growth Rate | C13: 0.01
B14: Exit Multiple (EV/EBITDA) | C14: 14.3
B15: Fully Diluted Shares | C15: 2334925020
B16: Net Debt (JPY mn) | C16: 833018
... B20: LTM Revenue (JPY mn) | C20: 8048722
B22: WACC Calculation
B23: Cost of Equity (Ke) | C23: =C7+C8*C9+C10 -> 0.09495
B24: Weight of Equity | C24: =1/(1+C12) -> 0.92106475
B25: Weight of Debt | C25: =C12/(1+C12) -> 0.078935249
B26: WACC | C26: =C23*C24+C11*C25 -> 0.08902591
B27: Active Scenario | C27: Base | D27: =MATCH(C27,B69:B73,0) -> 1
B28: Projected Free Cash Flow
C29: FY2027(E) | D29: FY2028(E) | E29: FY2029(E) | F29: FY2030(E) | G29: FY2031(E)
B30: Revenue Growth (YoY) | C30: =CHOOSE($D$27,C69,C70,C71,C72,C73) -> 0.01 | D30: =CHOOSE($D$27,D69,D70,D71,D72,D73) -> 0.02 | E30: =CHOOSE($D$27,E69,E70,E71,E72,E73) -> 0.025 | F30: =CHOOSE($D$27,F69,F70,F71,F72,F73) -> 0.025 | G30: =CHOOSE($D$27,G69,G70,G71,G72,G73) -> 0.02
B31: COGS % of Revenue | C31: =CHOOSE($D$27,C76,C77,C78,C79,C80) -> 0.686 | D31: =CHOOSE($D$27,D76,D77,D78,D79,D80) -> 0.686 | E31: =CHOOSE($D$27,E76,E77,E78,E79,E80) -> 0.686 | F31: =CHOOSE($D$27,F76,F77,F78,F79,F80) -> 0.686 | G31: =CHOOSE($D$27,G76,G77,G78,G79,G80) -> 0.686
B32: SGA % of Revenue | C32: =CHOOSE($D$27,C83,C84,C85,C86,C87) -> 0.283 | D32: =CHOOSE($D$27,D83,D84,D85,D86,D87) -> 0.28 | E32: =CHOOSE($D$27,E83,E84,E85,E86,E87) -> 0.278 | F32: =CHOOSE($D$27,F83,F84,F85,F86,F87) -> 0.277 | G32: =CHOOSE($D$27,G83,G84,G85,G86,G87) -> 0.2769
B33: Revenue | C33: =C17*(1+C30) -> 8129209.2 | D33: =C33*(1+D30) -> 8291793.4 | E33: =D33*(1+E30) -> 8499088.2 | F33: =E33*(1+F30) -> 8711565.4 | G33: =F33*(1+G30) -> 8885796.8
B34: COGS | C34: =C33*C31 -> 5576637.5 | D34: =D33*D31 -> 5688170.3 | E34: =E33*E31 -> 5830374.5 | F34: =F33*F31 -> 5976133.9 | G34: =G33*G31 -> 6095656.6
B35: Gross Profit | C35: =C33-C34 -> 2552571.7 | D35: =D33-D34 -> 2603623.1 | E35: =E33-E34 -> 2668713.7 | F35: =F33-F34 -> 2735431.5 | G35: =G33-G34 -> 2790140.2
B36: Gross Margin | C36: =C35/C33 -> 0.314 | D36: =D35/D33 -> 0.314 | E36: =E35/E33 -> 0.314 | F36: =F35/F33 -> 0.314 | G36: =G35/G33 -> 0.314
B37: SGA Expense | C37: =C33*C32 -> 2300566.2 | D37: =D33*D32 -> 2321702.2 | E37: =E33*E32 -> 2362746.5 | F37: =F33*F32 -> 2413103.6 | G37: =G33*G32 -> 2460477.1
B38: Implied Operating Margin | C38: =(C35-C37)/C33 -> 0.031 | D38: =(D35-D37)/D33 -> 0.034 | E38: =(E35-E37)/E33 -> 0.036 | F38: =(F35-F37)/F33 -> 0.037 | G38: =(G35-G37)/G33 -> 0.0371
B39: Operating Income (EBIT) | C39: =C35-C37 -> 252005.49 | D39: =D35-D37 -> 281920.98 | E39: =E35-E37 -> 305967.18 | F39: =F35-F37 -> 322327.92 | G39: =G35-G37 -> 329663.06
B40: Less: Tax | C40: =MAX(0,C39*C6) -> 63001.371 | D40: =MAX(0,D39*C6) -> 70480.244 | E40: =MAX(0,E39*C6) -> 76491.794 | F40: =MAX(0,F39*C6) -> 80581.98 | G40: =MAX(0,G39*C6) -> 82415.765
B41: NOPAT | C41: =C39-C40 -> 189004.11 | D41: =D39-D40 -> 211440.73 | E41: =E39-E40 -> 229475.38 | F41: =F39-F40 -> 241745.94 | G41: =G39-G40 -> 247247.29
B42: Plus: D&A | C42: =C33*C18 -> 406460.46 | D42: =D33*C18 -> 414589.67 | E42: =E33*C18 -> 424954.41 | F42: =F33*C18 -> 435578.27 | G42: =G33*C18 -> 444289.84
B43: Less: Capex | C43: 680000 | D43: 620000 | E43: 560000 | F43: 505000 | G43: 466000
B44: Change in NWC | C44: ='NWC Schedule'!D19 -> -68940.064 | D44: ='NWC Schedule'!E19 -> 27197.439 | E44: ='NWC Schedule'!F19 -> 34676.734 | F44: ='NWC Schedule'!G19 -> 35543.653 | G44: ='NWC Schedule'!H19 -> 29145.795
B45: Unlevered Free Cash Flow | C45: =C41+C42-C43-C44 -> -15595.36 | D45: =D41+D42-D43-D44 -> -21167.037 | E45: =E41+E42-E43-E44 -> 59753.06 | F45: =F41+F42-F43-F44 -> 136780.56 | G45: =G41+G42-G43-G44 -> 196391.34
B46: Discount Factor | C46: =1/(1+C26)^(C19+0) -> 0.9182518 | D46: =1/(1+C26)^(C19+1) -> 0.84318637 | E46: =1/(1+C26)^(C19+2) -> 0.7742574 | F46: =1/(1+C26)^(C19+3) -> 0.71096325 | G46: =1/(1+C26)^(C19+4) -> 0.65284328
B47: PV of FCF | C47: =C45*C46 -> -14320.468 | D47: =D45*D46 -> -17847.757 | E47: =E45*E46 -> 46264.249 | F47: =F45*F46 -> 97245.951 | G47: =G45*G46 -> 128212.76
B49: Valuation - Perpetuity Growth Method
B50: Sum of PV of FCFs | C50: =SUM(C47:G47) -> 239554.74
B51: Terminal Value (PGM) | C51: =G45*(1+C13)/(C26-C13) -> 2510002.8
B52: PV of Terminal Value | C52: =C51*G46 -> 1638638.4
B53: Enterprise Value | C53: =C50+C52 -> 1878193.2
B54: Equity Value | C54: =C53-C16 -> 1045175.2
B55: Implied Share Price (PGM) | C55: =ROUND(C54*1000000/C15,0) -> 448
B57: Valuation - Exit Multiple Method
B58: Sum of PV of FCFs | C58: =C50 -> 239554.74
B59: Year 5 EBITDA | C59: =G39+G42 -> 773952.9
B60: Terminal Value (Exit Multiple) | C60: =C59*C14 -> 11067526
B61: PV of Terminal Value | C61: =C60*G46 -> 7225360.3
B62: Enterprise Value | C62: =C58+C61 -> 7464915
B63: Equity Value | C63: =C62-C16 -> 6631897
B64: Implied Share Price (Exit Multiple) | C64: =ROUND(C63*1000000/C15,0) -> 2840
B66: Scenario Input Matrix
C67: Year 1 | D67: Year 2 | E67: Year 3 | F67: Year 4 | G67: Year 5
B68: Revenue Growth (YoY)
B69: Base | C69: 0.01 | D69: 0.02 | E69: 0.025 | F69: 0.025 | G69: 0.02
B70: Upside | C70: 0.025 | D70: 0.035 | E70: 0.035 | F70: 0.03 | G70: 0.03
B71: Management | C71: 0.01 | D71: 0.02 | E71: 0.025 | F71: 0.025 | G71: 0.02
B72: Downside 1 | C72: -0.01 | D72: 0 | E72: 0.005 | F72: 0.005 | G72: 0.005
B73: Downside 2 | C73: -0.08 | D73: -0.01 | E73: 0.005 | F73: 0.01 | G73: 0.015
B75: COGS % of Revenue
B76: Base | C76: 0.686 | D76: 0.686 | E76: 0.686 | F76: 0.686 | G76: 0.686
B77: Upside | C77: 0.68 | D77: 0.68 | E77: 0.68 | F77: 0.68 | G77: 0.68
B78: Management | C78: 0.686 | D78: 0.686 | E78: 0.686 | F78: 0.686 | G78: 0.686
B79: Downside 1 | C79: 0.694 | D79: 0.694 | E79: 0.694 | F79: 0.694 | G79: 0.694
B80: Downside 2 | C80: 0.71 | D80: 0.71 | E80: 0.71 | F80: 0.71 | G80: 0.71
B82: SGA % of Revenue
B83: Base | C83: 0.283 | D83: 0.28 | E83: 0.278 | F83: 0.277 | G83: 0.2769
B84: Upside | C84: 0.285 | D84: 0.281 | E84: 0.277 | F84: 0.274 | G84: 0.2719
B85: Management | C85: 0.283 | D85: 0.28 | E85: 0.278 | F85: 0.277 | G85: 0.2769
B86: Downside 1 | C86: 0.282 | D86: 0.284 | E86: 0.286 | F86: 0.287 | G86: 0.287
B87: Downside 2 | C87: 0.275 | D87: 0.278 | E87: 0.277 | F87: 0.275 | G87: 0.273

Sheet Reverse DCF
B2: Reverse DCF - パナソニックホールディングス (6752.T)
B3: What is the current share price already assuming? Every value below is a live formula off the other sheets.
B5: Block 0: Market-implied enterprise value (live)
B6: Current Share Price (JPY) | C6: ='Executive Summary'!C9 -> 4163
B7: Fully Diluted Shares | C7: ='DCF Model'!C15 -> 2334925020
B8: Market Capitalisation (JPY mn) | C8: =C6*C7/1000000 -> 9720292.9
B9: Net Debt (JPY mn) | C9: ='DCF Model'!C16 -> 833018
B10: Enterprise Value (JPY mn) | C10: =C8+C9 -> 10553311
B11: WACC (w) | C11: ='DCF Model'!C26 -> 0.08902591
B12: Terminal Growth (g) | C12: ='DCF Model'!C13 -> 0.01
B13: Effective Tax Rate (t) | C13: ='DCF Model'!C6 -> 0.25
B14: Starting Operating Profit OP0 (FY2026 actual) | C14: 209963
B15: Cycle-peak Operating Profit (FY2025 actual) | C15: 406534
B16: Terminal-year Revenue, active scenario (JPY mn) | C16: ='DCF Model'!G33 -> 8885796.8
B17: Base-case DCF Enterprise Value, PGM (JPY mn) | C17: ='DCF Model'!C53 -> 1878193.2
B18: Cycle-peak Operating Margin (FY2025 actual) | C18: 0.048063976
B19: Gap: market EV less base-case DCF EV (JPY mn) | C19: =C10-C17 -> 8675117.7
B20: Gap per share (JPY) - the part of the price the base case does not explain | C20: =IFERROR(ROUND(C19*1000000/C7,0),"N/A") -> 3715
B22: Block A: Required steady-state operating profit, reached IMMEDIATELY (no ramp)
B23: The lowest bar the price can clear: today's EV read as a perpetuity of one steady-state profit, capex = D&A, no NWC build.
B24: Required steady-state NOPAT (JPY mn) | C24: =C10*(C11-C12) -> 833984.99
B25: Required steady-state Operating Profit (JPY mn) | C25: =IFERROR(C24/(1-C13),"N/A") -> 1111980
B26: ... as a multiple of the FY2025 peak | C26: =IFERROR(C25/C15,"N/A") -> 2.7352693
B27: ... as a multiple of FY2026 actual | C27: =IFERROR(C25/C14,"N/A") -> 5.2960759
B28: ... implied OPM on terminal-year revenue | C28: =IFERROR(C25/C16,"N/A") -> 0.12514128
B29: ... revenue needed if margins only reach the cycle peak | C29: =IFERROR(C25/C18,"N/A") -> 23135414
B32: Block B: Required steady-state operating profit by YEARS-TO-REACH (linear ramp) x WACC
B33: Operating profit ramps linearly from OP0 (C14) to OP* over N years, then grows at g for ever. Column F is the model WACC.
B34: OP* = ( EV/(1-t) - OP0*(A-B) ) / ( B + TVF ). A longer ramp needs a HIGHER steady state, because more years are spent below it.
B36: Years to steady state (N) \ WACC | C36: N | D36: ='DCF Model'!C26-0.02 -> 0.06902591 | E36: ='DCF Model'!C26-0.01 -> 0.07902591 | F36: ='DCF Model'!C26 -> 0.08902591 | G36: ='DCF Model'!C26+0.01 -> 0.09902591 | H36: ='DCF Model'!C26+0.02 -> 0.10902591
B37: B-1 PV weight on the RAMP from OP0 (A - B)
B38: N = 3 years | C38: 3 | D38: =IFERROR((1-(1+D$36)^(-$C38))/D$36-(1+D$36)/(D$36^2*$C38)*(1-($C38+1)/(1+D$36)^$C38+$C38/(1+D$36)^($C38+1)),"N/A") -> 0.91529775 | E38: =IFERROR((1-(1+E$36)^(-$C38))/E$36-(1+E$36)/(E$36^2*$C38)*(1-($C38+1)/(1+E$36)^$C38+$C38/(1+E$36)^($C38+1)),"N/A") -> 0.90413702 | F38: =IFERROR((1-(1+F$36)^(-$C38))/F$36-(1+F$36)/(F$36^2*$C38)*(1-($C38+1)/(1+F$36)^$C38+$C38/(1+F$36)^($C38+1)),"N/A") -> 0.89322999 | G38: =IFERROR((1-(1+G$36)^(-$C38))/G$36-(1+G$36)/(G$36^2*$C38)*(1-($C38+1)/(1+G$36)^$C38+$C38/(1+G$36)^($C38+1)),"N/A") -> 0.88256841 | H38: =IFERROR((1-(1+H$36)^(-$C38))/H$36-(1+H$36)/(H$36^2*$C38)*(1-($C38+1)/(1+H$36)^$C38+$C38/(1+H$36)^($C38+1)),"N/A") -> 0.87214439
B39: N = 5 years | C39: 5 | D39: =IFERROR((1-(1+D$36)^(-$C39))/D$36-(1+D$36)/(D$36^2*$C39)*(1-($C39+1)/(1+D$36)^$C39+$C39/(1+D$36)^($C39+1)),"N/A") -> 1.753912 | E39: =IFERROR((1-(1+E$36)^(-$C39))/E$36-(1+E$36)/(E$36^2*$C39)*(1-($C39+1)/(1+E$36)^$C39+$C39/(1+E$36)^($C39+1)),"N/A") -> 1.7226731 | F39: =IFERROR((1-(1+F$36)^(-$C39))/F$36-(1+F$36)/(F$36^2*$C39)*(1-($C39+1)/(1+F$36)^$C39+$C39/(1+F$36)^($C39+1)),"N/A") -> 1.6924089 | G39: =IFERROR((1-(1+G$36)^(-$C39))/G$36-(1+G$36)/(G$36^2*$C39)*(1-($C39+1)/(1+G$36)^$C39+$C39/(1+G$36)^($C39+1)),"N/A") -> 1.6630778 | H39: =IFERROR((1-(1+H$36)^(-$C39))/H$36-(1+H$36)/(H$36^2*$C39)*(1-($C39+1)/(1+H$36)^$C39+$C39/(1+H$36)^($C39+1)),"N/A") -> 1.6346406
B40: N = 7 years | C40: 7 | D40: =IFERROR((1-(1+D$36)^(-$C40))/D$36-(1+D$36)/(D$36^2*$C40)*(1-($C40+1)/(1+D$36)^$C40+$C40/(1+D$36)^($C40+1)),"N/A") -> 2.5230544 | E40: =IFERROR((1-(1+E$36)^(-$C40))/E$36-(1+E$36)/(E$36^2*$C40)*(1-($C40+1)/(1+E$36)^$C40+$C40/(1+E$36)^($C40+1)),"N/A") -> 2.4647028 | F40: =IFERROR((1-(1+F$36)^(-$C40))/F$36-(1+F$36)/(F$36^2*$C40)*(1-($C40+1)/(1+F$36)^$C40+$C40/(1+F$36)^($C40+1)),"N/A") -> 2.4086461 | G40: =IFERROR((1-(1+G$36)^(-$C40))/G$36-(1+G$36)/(G$36^2*$C40)*(1-($C40+1)/(1+G$36)^$C40+$C40/(1+G$36)^($C40+1)),"N/A") -> 2.3547642 | H40: =IFERROR((1-(1+H$36)^(-$C40))/H$36-(1+H$36)/(H$36^2*$C40)*(1-($C40+1)/(1+H$36)^$C40+$C40/(1+H$36)^($C40+1)),"N/A") -> 2.3029443
B41: N = 10 years | C41: 10 | D41: =IFERROR((1-(1+D$36)^(-$C41))/D$36-(1+D$36)/(D$36^2*$C41)*(1-($C41+1)/(1+D$36)^$C41+$C41/(1+D$36)^($C41+1)),"N/A") -> 3.5605241 | E41: =IFERROR((1-(1+E$36)^(-$C41))/E$36-(1+E$36)/(E$36^2*$C41)*(1-($C41+1)/(1+E$36)^$C41+$C41/(1+E$36)^($C41+1)),"N/A") -> 3.4516893 | F41: =IFERROR((1-(1+F$36)^(-$C41))/F$36-(1+F$36)/(F$36^2*$C41)*(1-($C41+1)/(1+F$36)^$C41+$C41/(1+F$36)^($C41+1)),"N/A") -> 3.3483944 | G41: =IFERROR((1-(1+G$36)^(-$C41))/G$36-(1+G$36)/(G$36^2*$C41)*(1-($C41+1)/(1+G$36)^$C41+$C41/(1+G$36)^($C41+1)),"N/A") -> 3.2502708 | H41: =IFERROR((1-(1+H$36)^(-$C41))/H$36-(1+H$36)/(H$36^2*$C41)*(1-($C41+1)/(1+H$36)^$C41+$C41/(1+H$36)^($C41+1)),"N/A") -> 3.1569796
B42: B-2 PV weight on the STEADY STATE OP* (B + terminal factor)
B43: N = 3 years | C43: 3 | D43: =IFERROR((1+D$36)/(D$36^2*$C43)*(1-($C43+1)/(1+D$36)^$C43+$C43/(1+D$36)^($C43+1))+(1+$C$12)/((D$36-$C$12)*(1+D$36)^$C43),"N/A") -> 15.719692 | E43: =IFERROR((1+E$36)/(E$36^2*$C43)*(1-($C43+1)/(1+E$36)^$C43+$C43/(1+E$36)^($C43+1))+(1+$C$12)/((E$36-$C$12)*(1+E$36)^$C43),"N/A") -> 13.324484 | F43: =IFERROR((1+F$36)/(F$36^2*$C43)*(1-($C43+1)/(1+F$36)^$C43+$C43/(1+F$36)^($C43+1))+(1+$C$12)/((F$36-$C$12)*(1+F$36)^$C43),"N/A") -> 11.537954 | G43: =IFERROR((1+G$36)/(G$36^2*$C43)*(1-($C43+1)/(1+G$36)^$C43+$C43/(1+G$36)^($C43+1))+(1+$C$12)/((G$36-$C$12)*(1+G$36)^$C43),"N/A") -> 10.154914 | H43: =IFERROR((1+H$36)/(H$36^2*$C43)*(1-($C43+1)/(1+H$36)^$C43+$C43/(1+H$36)^($C43+1))+(1+$C$12)/((H$36-$C$12)*(1+H$36)^$C43),"N/A") -> 9.053062
B44: N = 5 years | C44: 5 | D44: =IFERROR((1+D$36)/(D$36^2*$C44)*(1-($C44+1)/(1+D$36)^$C44+$C44/(1+D$36)^($C44+1))+(1+$C$12)/((D$36-$C$12)*(1+D$36)^$C44),"N/A") -> 14.612685 | E44: =IFERROR((1+E$36)/(E$36^2*$C44)*(1-($C44+1)/(1+E$36)^$C44+$C44/(1+E$36)^($C44+1))+(1+$C$12)/((E$36-$C$12)*(1+E$36)^$C44),"N/A") -> 12.28376 | F44: =IFERROR((1+F$36)/(F$36^2*$C44)*(1-($C44+1)/(1+F$36)^$C44+$C44/(1+F$36)^($C44+1))+(1+$C$12)/((F$36-$C$12)*(1+F$36)^$C44),"N/A") -> 10.550834 | G44: =IFERROR((1+G$36)/(G$36^2*$C44)*(1-($C44+1)/(1+G$36)^$C44+$C44/(1+G$36)^($C44+1))+(1+$C$12)/((G$36-$C$12)*(1+G$36)^$C44),"N/A") -> 9.2127941 | H44: =IFERROR((1+H$36)/(H$36^2*$C44)*(1-($C44+1)/(1+H$36)^$C44+$C44/(1+H$36)^($C44+1))+(1+$C$12)/((H$36-$C$12)*(1+H$36)^$C44),"N/A") -> 8.1497776
B45: N = 7 years | C45: 7 | D45: =IFERROR((1+D$36)/(D$36^2*$C45)*(1-($C45+1)/(1+D$36)^$C45+$C45/(1+D$36)^($C45+1))+(1+$C$12)/((D$36-$C$12)*(1+D$36)^$C45),"N/A") -> 13.608691 | E45: =IFERROR((1+E$36)/(E$36^2*$C45)*(1-($C45+1)/(1+E$36)^$C45+$C45/(1+E$36)^($C45+1))+(1+$C$12)/((E$36-$C$12)*(1+E$36)^$C45),"N/A") -> 11.350896 | F45: =IFERROR((1+F$36)/(F$36^2*$C45)*(1-($C45+1)/(1+F$36)^$C45+$C45/(1+F$36)^($C45+1))+(1+$C$12)/((F$36-$C$12)*(1+F$36)^$C45),"N/A") -> 9.6761276 | G45: =IFERROR((1+G$36)/(G$36^2*$C45)*(1-($C45+1)/(1+G$36)^$C45+$C45/(1+G$36)^($C45+1))+(1+$C$12)/((G$36-$C$12)*(1+G$36)^$C45),"N/A") -> 8.3873084 | H45: =IFERROR((1+H$36)/(H$36^2*$C45)*(1-($C45+1)/(1+H$36)^$C45+$C45/(1+H$36)^($C45+1))+(1+$C$12)/((H$36-$C$12)*(1+H$36)^$C45),"N/A") -> 7.3670062
B46: N = 10 years | C46: 10 | D46: =IFERROR((1+D$36)/(D$36^2*$C46)*(1-($C46+1)/(1+D$36)^$C46+$C46/(1+D$36)^($C46+1))+(1+$C$12)/((D$36-$C$12)*(1+D$36)^$C46),"N/A") -> 12.272808 | E46: =IFERROR((1+E$36)/(E$36^2*$C46)*(1-($C46+1)/(1+E$36)^$C46+$C46/(1+E$36)^($C46+1))+(1+$C$12)/((E$36-$C$12)*(1+E$36)^$C46),"N/A") -> 10.126941 | F46: =IFERROR((1+F$36)/(F$36^2*$C46)*(1-($C46+1)/(1+F$36)^$C46+$C46/(1+F$36)^($C46+1))+(1+$C$12)/((F$36-$C$12)*(1+F$36)^$C46),"N/A") -> 8.5440266 | G46: =IFERROR((1+G$36)/(G$36^2*$C46)*(1-($C46+1)/(1+G$36)^$C46+$C46/(1+G$36)^($C46+1))+(1+$C$12)/((G$36-$C$12)*(1+G$36)^$C46),"N/A") -> 7.3330089 | H46: =IFERROR((1+H$36)/(H$36^2*$C46)*(1-($C46+1)/(1+H$36)^$C46+$C46/(1+H$36)^($C46+1))+(1+$C$12)/((H$36-$C$12)*(1+H$36)^$C46),"N/A") -> 6.3801129
B47: B-3 REQUIRED steady-state Operating Profit (JPY mn)
B48: N = 3 years | C48: 3 | D48: =IFERROR(($C$10/(1-$C$13)-$C$14*D38)/D43,"N/A") -> 882899.16 | E48: =IFERROR(($C$10/(1-$C$13)-$C$14*E38)/E43,"N/A") -> 1041784.9 | F48: =IFERROR(($C$10/(1-$C$13)-$C$14*F38)/F43,"N/A") -> 1203292.7 | G48: =IFERROR(($C$10/(1-$C$13)-$C$14*G38)/G43,"N/A") -> 1367394.6 | H48: =IFERROR(($C$10/(1-$C$13)-$C$14*H38)/H43,"N/A") -> 1534062.5
B49: N = 5 years | C49: 5 | D49: =IFERROR(($C$10/(1-$C$13)-$C$14*D39)/D44,"N/A") -> 937734.89 | E49: =IFERROR(($C$10/(1-$C$13)-$C$14*E39)/E44,"N/A") -> 1116057.6 | F49: =IFERROR(($C$10/(1-$C$13)-$C$14*F39)/F44,"N/A") -> 1299967.2 | G49: =IFERROR(($C$10/(1-$C$13)-$C$14*G39)/G44,"N/A") -> 1489439.2 | H49: =IFERROR(($C$10/(1-$C$13)-$C$14*H39)/H44,"N/A") -> 1684446.8
B50: N = 7 years | C50: 7 | D50: =IFERROR(($C$10/(1-$C$13)-$C$14*D40)/D45,"N/A") -> 995050.39 | E50: =IFERROR(($C$10/(1-$C$13)-$C$14*E40)/E45,"N/A") -> 1194054.2 | F50: =IFERROR(($C$10/(1-$C$13)-$C$14*F40)/F45,"N/A") -> 1401940.4 | G50: =IFERROR(($C$10/(1-$C$13)-$C$14*G40)/G45,"N/A") -> 1618715.7 | H50: =IFERROR(($C$10/(1-$C$13)-$C$14*H40)/H45,"N/A") -> 1844378.5
B51: N = 10 years | C51: 10 | D51: =IFERROR(($C$10/(1-$C$13)-$C$14*D41)/D46,"N/A") -> 1085611.6 | E51: =IFERROR(($C$10/(1-$C$13)-$C$14*E41)/E46,"N/A") -> 1317905.8 | F51: =IFERROR(($C$10/(1-$C$13)-$C$14*F41)/F46,"N/A") -> 1564606.8 | G51: =IFERROR(($C$10/(1-$C$13)-$C$14*G41)/G46,"N/A") -> 1825805 | H51: =IFERROR(($C$10/(1-$C$13)-$C$14*H41)/H46,"N/A") -> 2101566.6
B52: B-4 ... as a multiple of the FY2025 peak operating profit
B53: N = 3 years | C53: 3 | D53: =IFERROR(D48/$C$15,"N/A") -> 2.171772 | E53: =IFERROR(E48/$C$15,"N/A") -> 2.5626021 | F53: =IFERROR(F48/$C$15,"N/A") -> 2.9598821 | G53: =IFERROR(G48/$C$15,"N/A") -> 3.363543 | H53: =IFERROR(H48/$C$15,"N/A") -> 3.7735159
B54: N = 5 years | C54: 5 | D54: =IFERROR(D49/$C$15,"N/A") -> 2.306658 | E54: =IFERROR(E49/$C$15,"N/A") -> 2.7452995 | F54: =IFERROR(F49/$C$15,"N/A") -> 3.1976837 | G54: =IFERROR(G49/$C$15,"N/A") -> 3.6637505 | H54: =IFERROR(H49/$C$15,"N/A") -> 4.1434341
B55: N = 7 years | C55: 7 | D55: =IFERROR(D50/$C$15,"N/A") -> 2.4476437 | E55: =IFERROR(E50/$C$15,"N/A") -> 2.937157 | F55: =IFERROR(F50/$C$15,"N/A") -> 3.4485195 | G55: =IFERROR(G50/$C$15,"N/A") -> 3.9817474 | H55: =IFERROR(H50/$C$15,"N/A") -> 4.5368371
B56: N = 10 years | C56: 10 | D56: =IFERROR(D51/$C$15,"N/A") -> 2.6704079 | E56: =IFERROR(E51/$C$15,"N/A") -> 3.2418096 | F56: =IFERROR(F51/$C$15,"N/A") -> 3.8486493 | G56: =IFERROR(G51/$C$15,"N/A") -> 4.4911496 | H56: =IFERROR(H51/$C$15,"N/A") -> 5.1694732
B58: Block C: Decomposing the required profit into revenue x margin (N = 5 years, model WACC)
B59: The revenue the company must run at, for a given steady-state operating margin, to earn the Block B-3 profit.
B60: Required steady-state Operating Profit (N=5, model WACC) | C60: =F49 -> 1299967.2
B62: Assumed steady-state OPM | C62: Required Revenue | D62: x base-year revenue
B63: 0.024 | C63: =IFERROR($C$60/B63,"N/A") -> 54165299 | D63: =IFERROR(C63/'DCF Model'!C17,"N/A") -> 6.7296769
B64: 0.036 | C64: =IFERROR($C$60/B64,"N/A") -> 36110199 | D64: =IFERROR(C64/'DCF Model'!C17,"N/A") -> 4.4864513
B65: cycle-peak OPM (FY2025) | C65: =IFERROR($C$60/$C$18,"N/A") -> 27046601 | D65: =IFERROR(C65/'DCF Model'!C17,"N/A") -> 3.3603597
B66: 0.0601 | C66: =IFERROR($C$60/B66,"N/A") -> 21630069 | D66: =IFERROR(C66/'DCF Model'!C17,"N/A") -> 2.6873918
B67: 0.0721 | C67: =IFERROR($C$60/B67,"N/A") -> 18030058 | D67: =IFERROR(C67/'DCF Model'!C17,"N/A") -> 2.2401144
B69: Block D: The same question expressed as multiples
B70: Current EV / latest-FY EBITDA (actual) | C70: =IFERROR(C10/'Comps Analysis'!G5,"N/A") -> 17.179269
B71: Current EV / latest-FY Revenue (actual) | C71: =IFERROR(C10/'Comps Analysis'!F5,"N/A") -> 1.3111785
B72: EV / EBITDA if the Block A profit were already earned | C72: =IFERROR(C10/(C25+'DCF Model'!G42),"N/A") -> 6.7811575
B73: EV / EBITDA if the Block B-3 (N=5) profit were already earned | C73: =IFERROR(C10/(C60+'DCF Model'!G42),"N/A") -> 6.0503188
B74: Peer median EV / EBITDA (statistics rows) | C74: =IFERROR('Comps Analysis'!D16,"N/A") -> 14.333259
B75: Rows 3-4 answer: what multiple would today's EV be paying IF the company already earned the profit the price requires?
B77: Block F: The one-line answer
B78: ="At "&TEXT(C6,"#,##0")&" yen the market is paying for a steady-state operating profit of "&TEXT(F49,"#,##0")&" mn JPY - "&TEXT(F54,"0.00")&"x the FY2025 cycle peak of "&TEXT(C15,"#,##0")&" mn - reached in 5 years and sustained for ever, against "&TEXT(C14,"#,##0")&" mn actually earned in FY2026." -> At 4,163 yen the market is paying for a steady-state operating profit of 1,299,967 mn JPY - 3.20x the FY2025 cycle peak of 406,534 mn - reached in 5 years and sustained for ever, against 209,963 mn actually earned in FY2026.
B79: ="Even with no ramp at all (Block A) the price needs "&TEXT(C25,"#,##0")&" mn, or "&TEXT(C26,"0.00")&"x the peak. The base case supports an EV of only "&TEXT(C17,"#,##0")&" mn, leaving "&TEXT(C20,"#,##0")&" yen per share of the current price unexplained by mid-cycle economics." -> Even with no ramp at all (Block A) the price needs 1,111,980 mn, or 2.74x the peak. The base case supports an EV of only 1,878,193 mn, leaving 3,715 yen per share of the current price unexplained by mid-cycle economics.

Sheet NWC Schedule
B2: NWC Schedule - パナソニックホールディングス
B4: Working Capital Drivers (Days) | C4: Base Year | D4: FY2027(E) | E4: FY2028(E) | F4: FY2029(E) | G4: FY2030(E) | H4: FY2031(E)
B5: DSO (Days Sales Outstanding) | C5: =C12/C9*365 -> 62.570027 | D5: =CHOOSE('DCF Model'!$D$27,D25,D26,D27,D28,D29) -> 59 | E5: =CHOOSE('DCF Model'!$D$27,E25,E26,E27,E28,E29) -> 59 | F5: =CHOOSE('DCF Model'!$D$27,F25,F26,F27,F28,F29) -> 59 | G5: =CHOOSE('DCF Model'!$D$27,G25,G26,G27,G28,G29) -> 59 | H5: =CHOOSE('DCF Model'!$D$27,H25,H26,H27,H28,H29) -> 59
B6: DIH (Days Inventory Held) | C6: =C13/C10*365 -> 70.471783 | D6: =CHOOSE('DCF Model'!$D$27,D32,D33,D34,D35,D36) -> 71 | E6: =CHOOSE('DCF Model'!$D$27,E32,E33,E34,E35,E36) -> 71 | F6: =CHOOSE('DCF Model'!$D$27,F32,F33,F34,F35,F36) -> 71 | G6: =CHOOSE('DCF Model'!$D$27,G32,G33,G34,G35,G36) -> 71 | H6: =CHOOSE('DCF Model'!$D$27,H32,H33,H34,H35,H36) -> 71
B7: DPO (Days Payable Outstanding) | C7: =C15/C10*365 -> 67.228736 | D7: =CHOOSE('DCF Model'!$D$27,D39,D40,D41,D42,D43) -> 68 | E7: =CHOOSE('DCF Model'!$D$27,E39,E40,E41,E42,E43) -> 68 | F7: =CHOOSE('DCF Model'!$D$27,F39,F40,F41,F42,F43) -> 68 | G7: =CHOOSE('DCF Model'!$D$27,G39,G40,G41,G42,G43) -> 68 | H7: =CHOOSE('DCF Model'!$D$27,H39,H40,H41,H42,H43) -> 68
B8: P&L Reference (JPY mn)
B9: Revenue | C9: 8048722 | D9: ='DCF Model'!C33 -> 8129209.2 | E9: ='DCF Model'!D33 -> 8291793.4 | F9: ='DCF Model'!E33 -> 8499088.2 | G9: ='DCF Model'!F33 -> 8711565.4 | H9: ='DCF Model'!G33 -> 8885796.8
B10: COGS | C10: 5521854 | D10: ='DCF Model'!C34 -> 5576637.5 | E10: ='DCF Model'!D34 -> 5688170.3 | F10: ='DCF Model'!E34 -> 5830374.5 | G10: ='DCF Model'!F34 -> 5976133.9 | H10: ='DCF Model'!G34 -> 6095656.6
B11: Working Capital Items (JPY mn)
B12: Accounts Receivable | C12: 1379750 | D12: =D9*D5/365 -> 1314036.6 | E12: =E9*E5/365 -> 1340317.3 | F12: =F9*F5/365 -> 1373825.2 | G12: =G9*G5/365 -> 1408170.9 | H12: =H9*H5/365 -> 1436334.3
B13: Inventory | C13: 1066123 | D13: =D10*D6/365 -> 1084770.6 | E13: =E10*E6/365 -> 1106466 | F13: =F10*F6/365 -> 1134127.6 | G13: =G10*G6/365 -> 1162480.8 | H13: =H10*H6/365 -> 1185730.5
B14: Current Assets (AR + Inv) | C14: =C12+C13 -> 2445873 | D14: =D12+D13 -> 2398807.1 | E14: =E12+E13 -> 2446783.3 | F14: =F12+F13 -> 2507952.9 | G14: =G12+G13 -> 2570651.7 | H14: =H12+H13 -> 2622064.7
B15: Accounts Payable | C15: 1017061 | D15: =D10*D7/365 -> 1038935.2 | E15: =E10*E7/365 -> 1059713.9 | F15: =F10*F7/365 -> 1086206.8 | G15: =G10*G7/365 -> 1113361.9 | H15: =H10*H7/365 -> 1135629.2
B16: Current Liabilities (AP) | C16: =C15 -> 1017061 | D16: =D15 -> 1038935.2 | E16: =E15 -> 1059713.9 | F16: =F15 -> 1086206.8 | G16: =G15 -> 1113361.9 | H16: =H15 -> 1135629.2
B17: Net Working Capital (JPY mn)
B18: Net Working Capital | C18: =C14-C16 -> 1428812 | D18: =D14-D16 -> 1359871.9 | E18: =E14-E16 -> 1387069.4 | F18: =F14-F16 -> 1421746.1 | G18: =G14-G16 -> 1457289.8 | H18: =H14-H16 -> 1486435.6
B19: Change in NWC | C19: n/a | D19: =D18-C18 -> -68940.064 | E19: =E18-D18 -> 27197.439 | F19: =F18-E18 -> 34676.734 | G19: =G18-F18 -> 35543.653 | H19: =H18-G18 -> 29145.795
B22: Scenario Input Matrix (Working Capital Days)
D23: FY2027(E) | E23: FY2028(E) | F23: FY2029(E) | G23: FY2030(E) | H23: FY2031(E)
B24: DSO (Days)
B25: Base | D25: 59 | E25: 59 | F25: 59 | G25: 59 | H25: 59
B26: Upside | D26: 56 | E26: 56 | F26: 56 | G26: 56 | H26: 56
B27: Management | D27: 59 | E27: 59 | F27: 59 | G27: 59 | H27: 59
B28: Downside 1 | D28: 62 | E28: 62 | F28: 62 | G28: 62 | H28: 62
B29: Downside 2 | D29: 65 | E29: 65 | F29: 65 | G29: 65 | H29: 65
B31: DIH (Days)
B32: Base | D32: 71 | E32: 71 | F32: 71 | G32: 71 | H32: 71
B33: Upside | D33: 68 | E33: 68 | F33: 68 | G33: 68 | H33: 68
B34: Management | D34: 71 | E34: 71 | F34: 71 | G34: 71 | H34: 71
B35: Downside 1 | D35: 75 | E35: 75 | F35: 75 | G35: 75 | H35: 75
B36: Downside 2 | D36: 78 | E36: 78 | F36: 78 | G36: 78 | H36: 78
B38: DPO (Days)
B39: Base | D39: 68 | E39: 68 | F39: 68 | G39: 68 | H39: 68
B40: Upside | D40: 71 | E40: 71 | F40: 71 | G40: 71 | H40: 71
B41: Management | D41: 68 | E41: 68 | F41: 68 | G41: 68 | H41: 68
B42: Downside 1 | D42: 65 | E42: 65 | F42: 65 | G42: 65 | H42: 65
B43: Downside 2 | D43: 61 | E43: 61 | F43: 61 | G43: 61 | H43: 61

Sheet Comps Analysis
B2: Comparable Company Analysis
B3: Peer prices as of 2026-09-05 (Mkt Cap / EV of peer rows are static CSV values; the subject row is live-linked to Executive Summary)
B4: Company | C4: Ticker | D4: Mkt Cap (JPY mn) | E4: EV (JPY mn) | F4: Revenue (JPY mn) | G4: EBITDA (JPY mn) | H4: Op Income (JPY mn) | I4: Net Income (JPY mn) | J4: EV/EBITDA | K4: EV/Revenue | L4: PER | M4: PBR | N4: Op Margin | O4: ROE | P4: Book Value (JPY mn) | Q4: Note
B5: Panasonic Holdings Corporation | C5: 6752.T | D5: ='Executive Summary'!C9*C23/1000000 -> 9720292.9 | E5: =D5+C24 -> 10553311 | F5: 8048722 | G5: 614305 | H5: 209963 | I5: 189540 | J5: =IFERROR(E5/G5,"") -> 17.179269 | K5: =IFERROR(E5/F5,"") -> 1.3111785 | L5: =IFERROR(D5/I5,"") -> 51.283596 | M5: =IFERROR(D5/P5,"") -> 1.8652438 | N5: =IFERROR(H5/F5,"") -> 0.026086502 | O5: =IFERROR(I5/P5,"") -> 0.036371159 | P5: 5211272
B6: Hitachi, Ltd. | C6: 6501.T | D6: 24068208 | E6: 23753765 | F6: 10586781 | G6: 1657248 | H6: 1199275 | I6: 802368 | J6: =IFERROR(E6/G6,"") -> 14.333259 | K6: =IFERROR(E6/F6,"") -> 2.2437193 | L6: =IFERROR(D6/I6,"") -> 29.99647 | M6: =IFERROR(D6/P6,"") -> 3.6642594 | N6: =IFERROR(H6/F6,"") -> 0.11328042 | O6: =IFERROR(I6/P6,"") -> 0.12215635 | P6: 6568369
B7: Mitsubishi Electric Corporation | C7: 6503.T | D7: 10739696 | E7: 10371365 | F7: 5894747 | G7: 666879 | H7: 433095 | I7: 407758 | J7: =IFERROR(E7/G7,"") -> 15.552094 | K7: =IFERROR(E7/F7,"") -> 1.759425 | L7: =IFERROR(D7/I7,"") -> 26.338407 | M7: =IFERROR(D7/P7,"") -> 2.394973 | N7: =IFERROR(H7/F7,"") -> 0.073471347 | O7: =IFERROR(I7/P7,"") -> 0.090930823 | P7: 4484266
B8: Fujitsu Limited | C8: 6702.T | D8: 6751004 | E8: 6433732 | F8: 3502971 | G8: 489556 | H8: 348329 | I8: 449408 | J8: =IFERROR(E8/G8,"") -> 13.141974 | K8: =IFERROR(E8/F8,"") -> 1.8366501 | L8: =IFERROR(D8/I8,"") -> 15.021993 | M8: =IFERROR(D8/P8,"") -> 3.3339691 | N8: =IFERROR(H8/F8,"") -> 0.099438163 | O8: =IFERROR(I8/P8,"") -> 0.22193919 | P8: 2024915
B9: NEC Corporation | C9: 6701.T | D9: 6403589 | E9: 6233770 | F9: 3582733 | G9: 514415 | H9: 359913 | I9: 270228 | J9: =IFERROR(E9/G9,"") -> 12.118173 | K9: =IFERROR(E9/F9,"") -> 1.7399482 | L9: =IFERROR(D9/I9,"") -> 23.696986 | M9: =IFERROR(D9/P9,"") -> 2.9152568 | N9: =IFERROR(H9/F9,"") -> 0.10045767 | O9: =IFERROR(I9/P9,"") -> 0.12302226 | P9: 2196578
B10: Murata Manufacturing Co., Ltd. | C10: 6981.T | D10: 13089866 | E10: 12491933 | F10: 1830856 | G10: 460047 | H10: 281835 | I10: 233920 | J10: =IFERROR(E10/G10,"") -> 27.153602 | K10: =IFERROR(E10/F10,"") -> 6.8230014 | L10: =IFERROR(D10/I10,"") -> 55.958729 | M10: =IFERROR(D10/P10,"") -> 4.8146758 | N10: =IFERROR(H10/F10,"") -> 0.15393619 | O10: =IFERROR(I10/P10,"") -> 0.086039762 | P10: 2718743
B14: Statistics
B15: 25th Percentile | D15: =PERCENTILE(J6:J10,0.25) -> 13.141974 | E15: =PERCENTILE(K6:K10,0.25) -> 1.759425 | F15: =PERCENTILE(L6:L10,0.25) -> 23.696986 | G15: =PERCENTILE(M6:M10,0.25) -> 2.9152568 | H15: =PERCENTILE(N6:N10,0.25) -> 0.099438163 | I15: =PERCENTILE(O6:O10,0.25) -> 0.090930823
B16: Median (50th) | D16: =MEDIAN(J6:J10) -> 14.333259 | E16: =MEDIAN(K6:K10) -> 1.8366501 | F16: =MEDIAN(L6:L10) -> 26.338407 | G16: =MEDIAN(M6:M10) -> 3.3339691 | H16: =MEDIAN(N6:N10) -> 0.10045767 | I16: =MEDIAN(O6:O10) -> 0.12215635
B17: 75th Percentile | D17: =PERCENTILE(J6:J10,0.75) -> 15.552094 | E17: =PERCENTILE(K6:K10,0.75) -> 2.2437193 | F17: =PERCENTILE(L6:L10,0.75) -> 29.99647 | G17: =PERCENTILE(M6:M10,0.75) -> 3.6642594 | H17: =PERCENTILE(N6:N10,0.75) -> 0.11328042 | I17: =PERCENTILE(O6:O10,0.75) -> 0.12302226
B19: Implied Valuation for パナソニックホールディングス
B20: パナソニックホールディングス Financials
B21: EBITDA (JPY mn) | C21: 614305
B22: Net Income (JPY mn) | C22: 189540
B23: Shares Outstanding | C23: 2334925020
B24: Net Debt (JPY mn) | C24: 833018
B26: Implied Share Price (Median Multiples)
B27: Via EV/EBITDA (Median) | C27: =ROUND((C21*D16-C24)*1000000/C23,0) -> 3414
B28: Via PER (Median) | C28: =ROUND(C22*F16*1000000/C23,0) -> 2138

Sheet Sensitivity Analysis
B2: Sensitivity Analysis
B3: Current WACC: | C3: ='DCF Model'!C26 -> 0.08902591 | E3: Terminal g: | F3: ='DCF Model'!C13 -> 0.01 | H3: Exit Multiple: | I3: ='DCF Model'!C14 -> 14.3
B5: Table 1: WACC vs Terminal Growth Rate (PGM - Implied Share Price, JPY)
B6: WACC \ Terminal g | C6: =$F$3-0.0075 -> 0.0025 | D6: =$F$3-0.005 -> 0.005 | E6: =$F$3-0.0025 -> 0.0075 | F6: =$F$3 -> 0.01 | G6: =$F$3+0.0025 -> 0.0125 | H6: =$F$3+0.005 -> 0.015 | I6: =$F$3+0.0075 -> 0.0175
B7: =$C$3-0.015 -> 0.07402591 | C7: =IFERROR(ROUND(('DCF Model'!C45/(1+$B7)^('DCF Model'!C19+0)+'DCF Model'!D45/(1+$B7)^('DCF Model'!C19+1)+'DCF Model'!E45/(1+$B7)^('DCF Model'!C19+2)+'DCF Model'!F45/(1+$B7)^('DCF Model'!C19+3)+'DCF Model'!G45/(1+$B7)^('DCF Model'!C19+4)+'DCF Model'!G45*(1+C$6)/($B7-C$6)/(1+$B7)^('DCF Model'!C19+4)-'DCF Model'!C16)*1000000/'DCF Model'!C15,0),"") -> 578 | D7: =IFERROR(ROUND(('DCF Model'!C45/(1+$B7)^('DCF Model'!C19+0)+'DCF Model'!D45/(1+$B7)^('DCF Model'!C19+1)+'DCF Model'!E45/(1+$B7)^('DCF Model'!C19+2)+'DCF Model'!F45/(1+$B7)^('DCF Model'!C19+3)+'DCF Model'!G45/(1+$B7)^('DCF Model'!C19+4)+'DCF Model'!G45*(1+D$6)/($B7-D$6)/(1+$B7)^('DCF Model'!C19+4)-'DCF Model'!C16)*1000000/'DCF Model'!C15,0),"") -> 610 | E7: =IFERROR(ROUND(('DCF Model'!C45/(1+$B7)^('DCF Model'!C19+0)+'DCF Model'!D45/(1+$B7)^('DCF Model'!C19+1)+'DCF Model'!E45/(1+$B7)^('DCF Model'!C19+2)+'DCF Model'!F45/(1+$B7)^('DCF Model'!C19+3)+'DCF Model'!G45/(1+$B7)^('DCF Model'!C19+4)+'DCF Model'!G45*(1+E$6)/($B7-E$6)/(1+$B7)^('DCF Model'!C19+4)-'DCF Model'!C16)*1000000/'DCF Model'!C15,0),"") -> 644 | F7: =IFERROR(ROUND(('DCF Model'!C45/(1+$B7)^('DCF Model'!C19+0)+'DCF Model'!D45/(1+$B7)^('DCF Model'!C19+1)+'DCF Model'!E45/(1+$B7)^('DCF Model'!C19+2)+'DCF Model'!F45/(1+$B7)^('DCF Model'!C19+3)+'DCF Model'!G45/(1+$B7)^('DCF Model'!C19+4)+'DCF Model'!G45*(1+F$6)/($B7-F$6)/(1+$B7)^('DCF Model'!C19+4)-'DCF Model'!C16)*1000000/'DCF Model'!C15,0),"") -> 681 | G7: =IFERROR(ROUND(('DCF Model'!C45/(1+$B7)^('DCF Model'!C19+0)+'DCF Model'!D45/(1+$B7)^('DCF Model'!C19+1)+'DCF Model'!E45/(1+$B7)^('DCF Model'!C19+2)+'DCF Model'!F45/(1+$B7)^('DCF Model'!C19+3)+'DCF Model'!G45/(1+$B7)^('DCF Model'!C19+4)+'DCF Model'!G45*(1+G$6)/($B7-G$6)/(1+$B7)^('DCF Model'!C19+4)-'DCF Model'!C16)*1000000/'DCF Model'!C15,0),"") -> 721 | H7: =IFERROR(ROUND(('DCF Model'!C45/(1+$B7)^('DCF Model'!C19+0)+'DCF Model'!D45/(1+$B7)^('DCF Model'!C19+1)+'DCF Model'!E45/(1+$B7)^('DCF Model'!C19+2)+'DCF Model'!F45/(1+$B7)^('DCF Model'!C19+3)+'DCF Model'!G45/(1+$B7)^('DCF Model'!C19+4)+'DCF Model'!G45*(1+H$6)/($B7-H$6)/(1+$B7)^('DCF Model'!C19+4)-'DCF Model'!C16)*1000000/'DCF Model'!C15,0),"") -> 765 | I7: =IFERROR(ROUND(('DCF Model'!C45/(1+$B7)^('DCF Model'!C19+0)+'DCF Model'!D45/(1+$B7)^('DCF Model'!C19+1)+'DCF Model'!E45/(1+$B7)^('DCF Model'!C19+2)+'DCF Model'!F45/(1+$B7)^('DCF Model'!C19+3)+'DCF Model'!G45/(1+$B7)^('DCF Model'!C19+4)+'DCF Model'!G45*(1+I$6)/($B7-I$6)/(1+$B7)^('DCF Model'!C19+4)-'DCF Model'!C16)*1000000/'DCF Model'!C15,0),"") -> 812
B8: =$C$3-0.01 -> 0.07902591 | C8: =IFERROR(ROUND(('DCF Model'!C45/(1+$B8)^('DCF Model'!C19+0)+'DCF Model'!D45/(1+$B8)^('DCF Model'!C19+1)+'DCF Model'!E45/(1+$B8)^('DCF Model'!C19+2)+'DCF Model'!F45/(1+$B8)^('DCF Model'!C19+3)+'DCF Model'!G45/(1+$B8)^('DCF Model'!C19+4)+'DCF Model'!G45*(1+C$6)/($B8-C$6)/(1+$B8)^('DCF Model'!C19+4)-'DCF Model'!C16)*1000000/'DCF Model'!C15,0),"") -> 504 | D8: =IFERROR(ROUND(('DCF Model'!C45/(1+$B8)^('DCF Model'!C19+0)+'DCF Model'!D45/(1+$B8)^('DCF Model'!C19+1)+'DCF Model'!E45/(1+$B8)^('DCF Model'!C19+2)+'DCF Model'!F45/(1+$B8)^('DCF Model'!C19+3)+'DCF Model'!G45/(1+$B8)^('DCF Model'!C19+4)+'DCF Model'!G45*(1+D$6)/($B8-D$6)/(1+$B8)^('DCF Model'!C19+4)-'DCF Model'!C16)*1000000/'DCF Model'!C15,0),"") -> 531 | E8: =IFERROR(ROUND(('DCF Model'!C45/(1+$B8)^('DCF Model'!C19+0)+'DCF Model'!D45/(1+$B8)^('DCF Model'!C19+1)+'DCF Model'!E45/(1+$B8)^('DCF Model'!C19+2)+'DCF Model'!F45/(1+$B8)^('DCF Model'!C19+3)+'DCF Model'!G45/(1+$B8)^('DCF Model'!C19+4)+'DCF Model'!G45*(1+E$6)/($B8-E$6)/(1+$B8)^('DCF Model'!C19+4)-'DCF Model'!C16)*1000000/'DCF Model'!C15,0),"") -> 560 | F8: =IFERROR(ROUND(('DCF Model'!C45/(1+$B8)^('DCF Model'!C19+0)+'DCF Model'!D45/(1+$B8)^('DCF Model'!C19+1)+'DCF Model'!E45/(1+$B8)^('DCF Model'!C19+2)+'DCF Model'!F45/(1+$B8)^('DCF Model'!C19+3)+'DCF Model'!G45/(1+$B8)^('DCF Model'!C19+4)+'DCF Model'!G45*(1+F$6)/($B8-F$6)/(1+$B8)^('DCF Model'!C19+4)-'DCF Model'!C16)*1000000/'DCF Model'!C15,0),"") -> 592 | G8: =IFERROR(ROUND(('DCF Model'!C45/(1+$B8)^('DCF Model'!C19+0)+'DCF Model'!D45/(1+$B8)^('DCF Model'!C19+1)+'DCF Model'!E45/(1+$B8)^('DCF Model'!C19+2)+'DCF Model'!F45/(1+$B8)^('DCF Model'!C19+3)+'DCF Model'!G45/(1+$B8)^('DCF Model'!C19+4)+'DCF Model'!G45*(1+G$6)/($B8-G$6)/(1+$B8)^('DCF Model'!C19+4)-'DCF Model'!C16)*1000000/'DCF Model'!C15,0),"") -> 626 | H8: =IFERROR(ROUND(('DCF Model'!C45/(1+$B8)^('DCF Model'!C19+0)+'DCF Model'!D45/(1+$B8)^('DCF Model'!C19+1)+'DCF Model'!E45/(1+$B8)^('DCF Model'!C19+2)+'DCF Model'!F45/(1+$B8)^('DCF Model'!C19+3)+'DCF Model'!G45/(1+$B8)^('DCF Model'!C19+4)+'DCF Model'!G45*(1+H$6)/($B8-H$6)/(1+$B8)^('DCF Model'!C19+4)-'DCF Model'!C16)*1000000/'DCF Model'!C15,0),"") -> 662 | I8: =IFERROR(ROUND(('DCF Model'!C45/(1+$B8)^('DCF Model'!C19+0)+'DCF Model'!D45/(1+$B8)^('DCF Model'!C19+1)+'DCF Model'!E45/(1+$B8)^('DCF Model'!C19+2)+'DCF Model'!F45/(1+$B8)^('DCF Model'!C19+3)+'DCF Model'!G45/(1+$B8)^('DCF Model'!C19+4)+'DCF Model'!G45*(1+I$6)/($B8-I$6)/(1+$B8)^('DCF Model'!C19+4)-'DCF Model'!C16)*1000000/'DCF Model'!C15,0),"") -> 701
B9: =$C$3-0.005 -> 0.08402591 | C9: =IFERROR(ROUND(('DCF Model'!C45/(1+$B9)^('DCF Model'!C19+0)+'DCF Model'!D45/(1+$B9)^('DCF Model'!C19+1)+'DCF Model'!E45/(1+$B9)^('DCF Model'!C19+2)+'DCF Model'!F45/(1+$B9)^('DCF Model'!C19+3)+'DCF Model'!G45/(1+$B9)^('DCF Model'!C19+4)+'DCF Model'!G45*(1+C$6)/($B9-C$6)/(1+$B9)^('DCF Model'!C19+4)-'DCF Model'!C16)*1000000/'DCF Model'!C15,0),"") -> 439 | D9: =IFERROR(ROUND(('DCF Model'!C45/(1+$B9)^('DCF Model'!C19+0)+'DCF Model'!D45/(1+$B9)^('DCF Model'!C19+1)+'DCF Model'!E45/(1+$B9)^('DCF Model'!C19+2)+'DCF Model'!F45/(1+$B9)^('DCF Model'!C19+3)+'DCF Model'!G45/(1+$B9)^('DCF Model'!C19+4)+'DCF Model'!G45*(1+D$6)/($B9-D$6)/(1+$B9)^('DCF Model'!C19+4)-'DCF Model'!C16)*1000000/'DCF Model'!C15,0),"") -> 463 | E9: =IFERROR(ROUND(('DCF Model'!C45/(1+$B9)^('DCF Model'!C19+0)+'DCF Model'!D45/(1+$B9)^('DCF Model'!C19+1)+'DCF Model'!E45/(1+$B9)^('DCF Model'!C19+2)+'DCF Model'!F45/(1+$B9)^('DCF Model'!C19+3)+'DCF Model'!G45/(1+$B9)^('DCF Model'!C19+4)+'DCF Model'!G45*(1+E$6)/($B9-E$6)/(1+$B9)^('DCF Model'!C19+4)-'DCF Model'!C16)*1000000/'DCF Model'!C15,0),"") -> 488 | F9: =IFERROR(ROUND(('DCF Model'!C45/(1+$B9)^('DCF Model'!C19+0)+'DCF Model'!D45/(1+$B9)^('DCF Model'!C19+1)+'DCF Model'!E45/(1+$B9)^('DCF Model'!C19+2)+'DCF Model'!F45/(1+$B9)^('DCF Model'!C19+3)+'DCF Model'!G45/(1+$B9)^('DCF Model'!C19+4)+'DCF Model'!G45*(1+F$6)/($B9-F$6)/(1+$B9)^('DCF Model'!C19+4)-'DCF Model'!C16)*1000000/'DCF Model'!C15,0),"") -> 515 | G9: =IFERROR(ROUND(('DCF Model'!C45/(1+$B9)^('DCF Model'!C19+0)+'DCF Model'!D45/(1+$B9)^('DCF Model'!C19+1)+'DCF Model'!E45/(1+$B9)^('DCF Model'!C19+2)+'DCF Model'!F45/(1+$B9)^('DCF Model'!C19+3)+'DCF Model'!G45/(1+$B9)^('DCF Model'!C19+4)+'DCF Model'!G45*(1+G$6)/($B9-G$6)/(1+$B9)^('DCF Model'!C19+4)-'DCF Model'!C16)*1000000/'DCF Model'!C15,0),"") -> 543 | H9: =IFERROR(ROUND(('DCF Model'!C45/(1+$B9)^('DCF Model'!C19+0)+'DCF Model'!D45/(1+$B9)^('DCF Model'!C19+1)+'DCF Model'!E45/(1+$B9)^('DCF Model'!C19+2)+'DCF Model'!F45/(1+$B9)^('DCF Model'!C19+3)+'DCF Model'!G45/(1+$B9)^('DCF Model'!C19+4)+'DCF Model'!G45*(1+H$6)/($B9-H$6)/(1+$B9)^('DCF Model'!C19+4)-'DCF Model'!C16)*1000000/'DCF Model'!C15,0),"") -> 574 | I9: =IFERROR(ROUND(('DCF Model'!C45/(1+$B9)^('DCF Model'!C19+0)+'DCF Model'!D45/(1+$B9)^('DCF Model'!C19+1)+'DCF Model'!E45/(1+$B9)^('DCF Model'!C19+2)+'DCF Model'!F45/(1+$B9)^('DCF Model'!C19+3)+'DCF Model'!G45/(1+$B9)^('DCF Model'!C19+4)+'DCF Model'!G45*(1+I$6)/($B9-I$6)/(1+$B9)^('DCF Model'!C19+4)-'DCF Model'!C16)*1000000/'DCF Model'!C15,0),"") -> 607
B10: =$C$3 -> 0.08902591 | C10: =IFERROR(ROUND(('DCF Model'!C45/(1+$B10)^('DCF Model'!C19+0)+'DCF Model'!D45/(1+$B10)^('DCF Model'!C19+1)+'DCF Model'!E45/(1+$B10)^('DCF Model'!C19+2)+'DCF Model'!F45/(1+$B10)^('DCF Model'!C19+3)+'DCF Model'!G45/(1+$B10)^('DCF Model'!C19+4)+'DCF Model'!G45*(1+C$6)/($B10-C$6)/(1+$B10)^('DCF Model'!C19+4)-'DCF Model'!C16)*1000000/'DCF Model'!C15,0),"") -> 382 | D10: =IFERROR(ROUND(('DCF Model'!C45/(1+$B10)^('DCF Model'!C19+0)+'DCF Model'!D45/(1+$B10)^('DCF Model'!C19+1)+'DCF Model'!E45/(1+$B10)^('DCF Model'!C19+2)+'DCF Model'!F45/(1+$B10)^('DCF Model'!C19+3)+'DCF Model'!G45/(1+$B10)^('DCF Model'!C19+4)+'DCF Model'!G45*(1+D$6)/($B10-D$6)/(1+$B10)^('DCF Model'!C19+4)-'DCF Model'!C16)*1000000/'DCF Model'!C15,0),"") -> 403 | E10: =IFERROR(ROUND(('DCF Model'!C45/(1+$B10)^('DCF Model'!C19+0)+'DCF Model'!D45/(1+$B10)^('DCF Model'!C19+1)+'DCF Model'!E45/(1+$B10)^('DCF Model'!C19+2)+'DCF Model'!F45/(1+$B10)^('DCF Model'!C19+3)+'DCF Model'!G45/(1+$B10)^('DCF Model'!C19+4)+'DCF Model'!G45*(1+E$6)/($B10-E$6)/(1+$B10)^('DCF Model'!C19+4)-'DCF Model'!C16)*1000000/'DCF Model'!C15,0),"") -> 424 | F10: =IFERROR(ROUND(('DCF Model'!C45/(1+$B10)^('DCF Model'!C19+0)+'DCF Model'!D45/(1+$B10)^('DCF Model'!C19+1)+'DCF Model'!E45/(1+$B10)^('DCF Model'!C19+2)+'DCF Model'!F45/(1+$B10)^('DCF Model'!C19+3)+'DCF Model'!G45/(1+$B10)^('DCF Model'!C19+4)+'DCF Model'!G45*(1+F$6)/($B10-F$6)/(1+$B10)^('DCF Model'!C19+4)-'DCF Model'!C16)*1000000/'DCF Model'!C15,0),"") -> 448 | G10: =IFERROR(ROUND(('DCF Model'!C45/(1+$B10)^('DCF Model'!C19+0)+'DCF Model'!D45/(1+$B10)^('DCF Model'!C19+1)+'DCF Model'!E45/(1+$B10)^('DCF Model'!C19+2)+'DCF Model'!F45/(1+$B10)^('DCF Model'!C19+3)+'DCF Model'!G45/(1+$B10)^('DCF Model'!C19+4)+'DCF Model'!G45*(1+G$6)/($B10-G$6)/(1+$B10)^('DCF Model'!C19+4)-'DCF Model'!C16)*1000000/'DCF Model'!C15,0),"") -> 472 | H10: =IFERROR(ROUND(('DCF Model'!C45/(1+$B10)^('DCF Model'!C19+0)+'DCF Model'!D45/(1+$B10)^('DCF Model'!C19+1)+'DCF Model'!E45/(1+$B10)^('DCF Model'!C19+2)+'DCF Model'!F45/(1+$B10)^('DCF Model'!C19+3)+'DCF Model'!G45/(1+$B10)^('DCF Model'!C19+4)+'DCF Model'!G45*(1+H$6)/($B10-H$6)/(1+$B10)^('DCF Model'!C19+4)-'DCF Model'!C16)*1000000/'DCF Model'!C15,0),"") -> 499 | I10: =IFERROR(ROUND(('DCF Model'!C45/(1+$B10)^('DCF Model'!C19+0)+'DCF Model'!D45/(1+$B10)^('DCF Model'!C19+1)+'DCF Model'!E45/(1+$B10)^('DCF Model'!C19+2)+'DCF Model'!F45/(1+$B10)^('DCF Model'!C19+3)+'DCF Model'!G45/(1+$B10)^('DCF Model'!C19+4)+'DCF Model'!G45*(1+I$6)/($B10-I$6)/(1+$B10)^('DCF Model'!C19+4)-'DCF Model'!C16)*1000000/'DCF Model'!C15,0),"") -> 527
B11: =$C$3+0.005 -> 0.09402591 | C11: =IFERROR(ROUND(('DCF Model'!C45/(1+$B11)^('DCF Model'!C19+0)+'DCF Model'!D45/(1+$B11)^('DCF Model'!C19+1)+'DCF Model'!E45/(1+$B11)^('DCF Model'!C19+2)+'DCF Model'!F45/(1+$B11)^('DCF Model'!C19+3)+'DCF Model'!G45/(1+$B11)^('DCF Model'!C19+4)+'DCF Model'!G45*(1+C$6)/($B11-C$6)/(1+$B11)^('DCF Model'!C19+4)-'DCF Model'!C16)*1000000/'DCF Model'!C15,0),"") -> 331 | D11: =IFERROR(ROUND(('DCF Model'!C45/(1+$B11)^('DCF Model'!C19+0)+'DCF Model'!D45/(1+$B11)^('DCF Model'!C19+1)+'DCF Model'!E45/(1+$B11)^('DCF Model'!C19+2)+'DCF Model'!F45/(1+$B11)^('DCF Model'!C19+3)+'DCF Model'!G45/(1+$B11)^('DCF Model'!C19+4)+'DCF Model'!G45*(1+D$6)/($B11-D$6)/(1+$B11)^('DCF Model'!C19+4)-'DCF Model'!C16)*1000000/'DCF Model'!C15,0),"") -> 350 | E11: =IFERROR(ROUND(('DCF Model'!C45/(1+$B11)^('DCF Model'!C19+0)+'DCF Model'!D45/(1+$B11)^('DCF Model'!C19+1)+'DCF Model'!E45/(1+$B11)^('DCF Model'!C19+2)+'DCF Model'!F45/(1+$B11)^('DCF Model'!C19+3)+'DCF Model'!G45/(1+$B11)^('DCF Model'!C19+4)+'DCF Model'!G45*(1+E$6)/($B11-E$6)/(1+$B11)^('DCF Model'!C19+4)-'DCF Model'!C16)*1000000/'DCF Model'!C15,0),"") -> 369 | F11: =IFERROR(ROUND(('DCF Model'!C45/(1+$B11)^('DCF Model'!C19+0)+'DCF Model'!D45/(1+$B11)^('DCF Model'!C19+1)+'DCF Model'!E45/(1+$B11)^('DCF Model'!C19+2)+'DCF Model'!F45/(1+$B11)^('DCF Model'!C19+3)+'DCF Model'!G45/(1+$B11)^('DCF Model'!C19+4)+'DCF Model'!G45*(1+F$6)/($B11-F$6)/(1+$B11)^('DCF Model'!C19+4)-'DCF Model'!C16)*1000000/'DCF Model'!C15,0),"") -> 389 | G11: =IFERROR(ROUND(('DCF Model'!C45/(1+$B11)^('DCF Model'!C19+0)+'DCF Model'!D45/(1+$B11)^('DCF Model'!C19+1)+'DCF Model'!E45/(1+$B11)^('DCF Model'!C19+2)+'DCF Model'!F45/(1+$B11)^('DCF Model'!C19+3)+'DCF Model'!G45/(1+$B11)^('DCF Model'!C19+4)+'DCF Model'!G45*(1+G$6)/($B11-G$6)/(1+$B11)^('DCF Model'!C19+4)-'DCF Model'!C16)*1000000/'DCF Model'!C15,0),"") -> 410 | H11: =IFERROR(ROUND(('DCF Model'!C45/(1+$B11)^('DCF Model'!C19+0)+'DCF Model'!D45/(1+$B11)^('DCF Model'!C19+1)+'DCF Model'!E45/(1+$B11)^('DCF Model'!C19+2)+'DCF Model'!F45/(1+$B11)^('DCF Model'!C19+3)+'DCF Model'!G45/(1+$B11)^('DCF Model'!C19+4)+'DCF Model'!G45*(1+H$6)/($B11-H$6)/(1+$B11)^('DCF Model'!C19+4)-'DCF Model'!C16)*1000000/'DCF Model'!C15,0),"") -> 433 | I11: =IFERROR(ROUND(('DCF Model'!C45/(1+$B11)^('DCF Model'!C19+0)+'DCF Model'!D45/(1+$B11)^('DCF Model'!C19+1)+'DCF Model'!E45/(1+$B11)^('DCF Model'!C19+2)+'DCF Model'!F45/(1+$B11)^('DCF Model'!C19+3)+'DCF Model'!G45/(1+$B11)^('DCF Model'!C19+4)+'DCF Model'!G45*(1+I$6)/($B11-I$6)/(1+$B11)^('DCF Model'!C19+4)-'DCF Model'!C16)*1000000/'DCF Model'!C15,0),"") -> 457
B12: =$C$3+0.01 -> 0.09902591 | C12: =IFERROR(ROUND(('DCF Model'!C45/(1+$B12)^('DCF Model'!C19+0)+'DCF Model'!D45/(1+$B12)^('DCF Model'!C19+1)+'DCF Model'!E45/(1+$B12)^('DCF Model'!C19+2)+'DCF Model'!F45/(1+$B12)^('DCF Model'!C19+3)+'DCF Model'!G45/(1+$B12)^('DCF Model'!C19+4)+'DCF Model'!G45*(1+C$6)/($B12-C$6)/(1+$B12)^('DCF Model'!C19+4)-'DCF Model'!C16)*1000000/'DCF Model'!C15,0),"") -> 286 | D12: =IFERROR(ROUND(('DCF Model'!C45/(1+$B12)^('DCF Model'!C19+0)+'DCF Model'!D45/(1+$B12)^('DCF Model'!C19+1)+'DCF Model'!E45/(1+$B12)^('DCF Model'!C19+2)+'DCF Model'!F45/(1+$B12)^('DCF Model'!C19+3)+'DCF Model'!G45/(1+$B12)^('DCF Model'!C19+4)+'DCF Model'!G45*(1+D$6)/($B12-D$6)/(1+$B12)^('DCF Model'!C19+4)-'DCF Model'!C16)*1000000/'DCF Model'!C15,0),"") -> 302 | E12: =IFERROR(ROUND(('DCF Model'!C45/(1+$B12)^('DCF Model'!C19+0)+'DCF Model'!D45/(1+$B12)^('DCF Model'!C19+1)+'DCF Model'!E45/(1+$B12)^('DCF Model'!C19+2)+'DCF Model'!F45/(1+$B12)^('DCF Model'!C19+3)+'DCF Model'!G45/(1+$B12)^('DCF Model'!C19+4)+'DCF Model'!G45*(1+E$6)/($B12-E$6)/(1+$B12)^('DCF Model'!C19+4)-'DCF Model'!C16)*1000000/'DCF Model'!C15,0),"") -> 319 | F12: =IFERROR(ROUND(('DCF Model'!C45/(1+$B12)^('DCF Model'!C19+0)+'DCF Model'!D45/(1+$B12)^('DCF Model'!C19+1)+'DCF Model'!E45/(1+$B12)^('DCF Model'!C19+2)+'DCF Model'!F45/(1+$B12)^('DCF Model'!C19+3)+'DCF Model'!G45/(1+$B12)^('DCF Model'!C19+4)+'DCF Model'!G45*(1+F$6)/($B12-F$6)/(1+$B12)^('DCF Model'!C19+4)-'DCF Model'!C16)*1000000/'DCF Model'!C15,0),"") -> 337 | G12: =IFERROR(ROUND(('DCF Model'!C45/(1+$B12)^('DCF Model'!C19+0)+'DCF Model'!D45/(1+$B12)^('DCF Model'!C19+1)+'DCF Model'!E45/(1+$B12)^('DCF Model'!C19+2)+'DCF Model'!F45/(1+$B12)^('DCF Model'!C19+3)+'DCF Model'!G45/(1+$B12)^('DCF Model'!C19+4)+'DCF Model'!G45*(1+G$6)/($B12-G$6)/(1+$B12)^('DCF Model'!C19+4)-'DCF Model'!C16)*1000000/'DCF Model'!C15,0),"") -> 355 | H12: =IFERROR(ROUND(('DCF Model'!C45/(1+$B12)^('DCF Model'!C19+0)+'DCF Model'!D45/(1+$B12)^('DCF Model'!C19+1)+'DCF Model'!E45/(1+$B12)^('DCF Model'!C19+2)+'DCF Model'!F45/(1+$B12)^('DCF Model'!C19+3)+'DCF Model'!G45/(1+$B12)^('DCF Model'!C19+4)+'DCF Model'!G45*(1+H$6)/($B12-H$6)/(1+$B12)^('DCF Model'!C19+4)-'DCF Model'!C16)*1000000/'DCF Model'!C15,0),"") -> 375 | I12: =IFERROR(ROUND(('DCF Model'!C45/(1+$B12)^('DCF Model'!C19+0)+'DCF Model'!D45/(1+$B12)^('DCF Model'!C19+1)+'DCF Model'!E45/(1+$B12)^('DCF Model'!C19+2)+'DCF Model'!F45/(1+$B12)^('DCF Model'!C19+3)+'DCF Model'!G45/(1+$B12)^('DCF Model'!C19+4)+'DCF Model'!G45*(1+I$6)/($B12-I$6)/(1+$B12)^('DCF Model'!C19+4)-'DCF Model'!C16)*1000000/'DCF Model'!C15,0),"") -> 396
B13: =$C$3+0.015 -> 0.10402591 | C13: =IFERROR(ROUND(('DCF Model'!C45/(1+$B13)^('DCF Model'!C19+0)+'DCF Model'!D45/(1+$B13)^('DCF Model'!C19+1)+'DCF Model'!E45/(1+$B13)^('DCF Model'!C19+2)+'DCF Model'!F45/(1+$B13)^('DCF Model'!C19+3)+'DCF Model'!G45/(1+$B13)^('DCF Model'!C19+4)+'DCF Model'!G45*(1+C$6)/($B13-C$6)/(1+$B13)^('DCF Model'!C19+4)-'DCF Model'!C16)*1000000/'DCF Model'!C15,0),"") -> 246 | D13: =IFERROR(ROUND(('DCF Model'!C45/(1+$B13)^('DCF Model'!C19+0)+'DCF Model'!D45/(1+$B13)^('DCF Model'!C19+1)+'DCF Model'!E45/(1+$B13)^('DCF Model'!C19+2)+'DCF Model'!F45/(1+$B13)^('DCF Model'!C19+3)+'DCF Model'!G45/(1+$B13)^('DCF Model'!C19+4)+'DCF Model'!G45*(1+D$6)/($B13-D$6)/(1+$B13)^('DCF Model'!C19+4)-'DCF Model'!C16)*1000000/'DCF Model'!C15,0),"") -> 260 | E13: =IFERROR(ROUND(('DCF Model'!C45/(1+$B13)^('DCF Model'!C19+0)+'DCF Model'!D45/(1+$B13)^('DCF Model'!C19+1)+'DCF Model'!E45/(1+$B13)^('DCF Model'!C19+2)+'DCF Model'!F45/(1+$B13)^('DCF Model'!C19+3)+'DCF Model'!G45/(1+$B13)^('DCF Model'!C19+4)+'DCF Model'!G45*(1+E$6)/($B13-E$6)/(1+$B13)^('DCF Model'!C19+4)-'DCF Model'!C16)*1000000/'DCF Model'!C15,0),"") -> 275 | F13: =IFERROR(ROUND(('DCF Model'!C45/(1+$B13)^('DCF Model'!C19+0)+'DCF Model'!D45/(1+$B13)^('DCF Model'!C19+1)+'DCF Model'!E45/(1+$B13)^('DCF Model'!C19+2)+'DCF Model'!F45/(1+$B13)^('DCF Model'!C19+3)+'DCF Model'!G45/(1+$B13)^('DCF Model'!C19+4)+'DCF Model'!G45*(1+F$6)/($B13-F$6)/(1+$B13)^('DCF Model'!C19+4)-'DCF Model'!C16)*1000000/'DCF Model'!C15,0),"") -> 290 | G13: =IFERROR(ROUND(('DCF Model'!C45/(1+$B13)^('DCF Model'!C19+0)+'DCF Model'!D45/(1+$B13)^('DCF Model'!C19+1)+'DCF Model'!E45/(1+$B13)^('DCF Model'!C19+2)+'DCF Model'!F45/(1+$B13)^('DCF Model'!C19+3)+'DCF Model'!G45/(1+$B13)^('DCF Model'!C19+4)+'DCF Model'!G45*(1+G$6)/($B13-G$6)/(1+$B13)^('DCF Model'!C19+4)-'DCF Model'!C16)*1000000/'DCF Model'!C15,0),"") -> 307 | H13: =IFERROR(ROUND(('DCF Model'!C45/(1+$B13)^('DCF Model'!C19+0)+'DCF Model'!D45/(1+$B13)^('DCF Model'!C19+1)+'DCF Model'!E45/(1+$B13)^('DCF Model'!C19+2)+'DCF Model'!F45/(1+$B13)^('DCF Model'!C19+3)+'DCF Model'!G45/(1+$B13)^('DCF Model'!C19+4)+'DCF Model'!G45*(1+H$6)/($B13-H$6)/(1+$B13)^('DCF Model'!C19+4)-'DCF Model'!C16)*1000000/'DCF Model'!C15,0),"") -> 324 | I13: =IFERROR(ROUND(('DCF Model'!C45/(1+$B13)^('DCF Model'!C19+0)+'DCF Model'!D45/(1+$B13)^('DCF Model'!C19+1)+'DCF Model'!E45/(1+$B13)^('DCF Model'!C19+2)+'DCF Model'!F45/(1+$B13)^('DCF Model'!C19+3)+'DCF Model'!G45/(1+$B13)^('DCF Model'!C19+4)+'DCF Model'!G45*(1+I$6)/($B13-I$6)/(1+$B13)^('DCF Model'!C19+4)-'DCF Model'!C16)*1000000/'DCF Model'!C15,0),"") -> 343
B16: Table 2: WACC vs Exit Multiple (Exit Multiple - Implied Share Price, JPY)
B17: WACC \ Exit Multiple | C17: =$I$3-3 -> 11.3 | D17: =$I$3-2 -> 12.3 | E17: =$I$3-1 -> 13.3 | F17: =$I$3 -> 14.3 | G17: =$I$3+1 -> 15.3 | H17: =$I$3+2 -> 16.3 | I17: =$I$3+3 -> 17.3
B18: =$C$3-0.015 -> 0.07402591 | C18: =IFERROR(ROUND(('DCF Model'!C45/(1+$B18)^('DCF Model'!C19+0)+'DCF Model'!D45/(1+$B18)^('DCF Model'!C19+1)+'DCF Model'!E45/(1+$B18)^('DCF Model'!C19+2)+'DCF Model'!F45/(1+$B18)^('DCF Model'!C19+3)+'DCF Model'!G45/(1+$B18)^('DCF Model'!C19+4)+('DCF Model'!G39+'DCF Model'!G42)*C$17/(1+$B18)^('DCF Model'!C19+4)-'DCF Model'!C16)*1000000/'DCF Model'!C15,0),"") -> 2374 | D18: =IFERROR(ROUND(('DCF Model'!C45/(1+$B18)^('DCF Model'!C19+0)+'DCF Model'!D45/(1+$B18)^('DCF Model'!C19+1)+'DCF Model'!E45/(1+$B18)^('DCF Model'!C19+2)+'DCF Model'!F45/(1+$B18)^('DCF Model'!C19+3)+'DCF Model'!G45/(1+$B18)^('DCF Model'!C19+4)+('DCF Model'!G39+'DCF Model'!G42)*D$17/(1+$B18)^('DCF Model'!C19+4)-'DCF Model'!C16)*1000000/'DCF Model'!C15,0),"") -> 2606 | E18: =IFERROR(ROUND(('DCF Model'!C45/(1+$B18)^('DCF Model'!C19+0)+'DCF Model'!D45/(1+$B18)^('DCF Model'!C19+1)+'DCF Model'!E45/(1+$B18)^('DCF Model'!C19+2)+'DCF Model'!F45/(1+$B18)^('DCF Model'!C19+3)+'DCF Model'!G45/(1+$B18)^('DCF Model'!C19+4)+('DCF Model'!G39+'DCF Model'!G42)*E$17/(1+$B18)^('DCF Model'!C19+4)-'DCF Model'!C16)*1000000/'DCF Model'!C15,0),"") -> 2837 | F18: =IFERROR(ROUND(('DCF Model'!C45/(1+$B18)^('DCF Model'!C19+0)+'DCF Model'!D45/(1+$B18)^('DCF Model'!C19+1)+'DCF Model'!E45/(1+$B18)^('DCF Model'!C19+2)+'DCF Model'!F45/(1+$B18)^('DCF Model'!C19+3)+'DCF Model'!G45/(1+$B18)^('DCF Model'!C19+4)+('DCF Model'!G39+'DCF Model'!G42)*F$17/(1+$B18)^('DCF Model'!C19+4)-'DCF Model'!C16)*1000000/'DCF Model'!C15,0),"") -> 3069 | G18: =IFERROR(ROUND(('DCF Model'!C45/(1+$B18)^('DCF Model'!C19+0)+'DCF Model'!D45/(1+$B18)^('DCF Model'!C19+1)+'DCF Model'!E45/(1+$B18)^('DCF Model'!C19+2)+'DCF Model'!F45/(1+$B18)^('DCF Model'!C19+3)+'DCF Model'!G45/(1+$B18)^('DCF Model'!C19+4)+('DCF Model'!G39+'DCF Model'!G42)*G$17/(1+$B18)^('DCF Model'!C19+4)-'DCF Model'!C16)*1000000/'DCF Model'!C15,0),"") -> 3301 | H18: =IFERROR(ROUND(('DCF Model'!C45/(1+$B18)^('DCF Model'!C19+0)+'DCF Model'!D45/(1+$B18)^('DCF Model'!C19+1)+'DCF Model'!E45/(1+$B18)^('DCF Model'!C19+2)+'DCF Model'!F45/(1+$B18)^('DCF Model'!C19+3)+'DCF Model'!G45/(1+$B18)^('DCF Model'!C19+4)+('DCF Model'!G39+'DCF Model'!G42)*H$17/(1+$B18)^('DCF Model'!C19+4)-'DCF Model'!C16)*1000000/'DCF Model'!C15,0),"") -> 3533 | I18: =IFERROR(ROUND(('DCF Model'!C45/(1+$B18)^('DCF Model'!C19+0)+'DCF Model'!D45/(1+$B18)^('DCF Model'!C19+1)+'DCF Model'!E45/(1+$B18)^('DCF Model'!C19+2)+'DCF Model'!F45/(1+$B18)^('DCF Model'!C19+3)+'DCF Model'!G45/(1+$B18)^('DCF Model'!C19+4)+('DCF Model'!G39+'DCF Model'!G42)*I$17/(1+$B18)^('DCF Model'!C19+4)-'DCF Model'!C16)*1000000/'DCF Model'!C15,0),"") -> 3765
B19: =$C$3-0.01 -> 0.07902591 | C19: =IFERROR(ROUND(('DCF Model'!C45/(1+$B19)^('DCF Model'!C19+0)+'DCF Model'!D45/(1+$B19)^('DCF Model'!C19+1)+'DCF Model'!E45/(1+$B19)^('DCF Model'!C19+2)+'DCF Model'!F45/(1+$B19)^('DCF Model'!C19+3)+'DCF Model'!G45/(1+$B19)^('DCF Model'!C19+4)+('DCF Model'!G39+'DCF Model'!G42)*C$17/(1+$B19)^('DCF Model'!C19+4)-'DCF Model'!C16)*1000000/'DCF Model'!C15,0),"") -> 2311 | D19: =IFERROR(ROUND(('DCF Model'!C45/(1+$B19)^('DCF Model'!C19+0)+'DCF Model'!D45/(1+$B19)^('DCF Model'!C19+1)+'DCF Model'!E45/(1+$B19)^('DCF Model'!C19+2)+'DCF Model'!F45/(1+$B19)^('DCF Model'!C19+3)+'DCF Model'!G45/(1+$B19)^('DCF Model'!C19+4)+('DCF Model'!G39+'DCF Model'!G42)*D$17/(1+$B19)^('DCF Model'!C19+4)-'DCF Model'!C16)*1000000/'DCF Model'!C15,0),"") -> 2538 | E19: =IFERROR(ROUND(('DCF Model'!C45/(1+$B19)^('DCF Model'!C19+0)+'DCF Model'!D45/(1+$B19)^('DCF Model'!C19+1)+'DCF Model'!E45/(1+$B19)^('DCF Model'!C19+2)+'DCF Model'!F45/(1+$B19)^('DCF Model'!C19+3)+'DCF Model'!G45/(1+$B19)^('DCF Model'!C19+4)+('DCF Model'!G39+'DCF Model'!G42)*E$17/(1+$B19)^('DCF Model'!C19+4)-'DCF Model'!C16)*1000000/'DCF Model'!C15,0),"") -> 2764 | F19: =IFERROR(ROUND(('DCF Model'!C45/(1+$B19)^('DCF Model'!C19+0)+'DCF Model'!D45/(1+$B19)^('DCF Model'!C19+1)+'DCF Model'!E45/(1+$B19)^('DCF Model'!C19+2)+'DCF Model'!F45/(1+$B19)^('DCF Model'!C19+3)+'DCF Model'!G45/(1+$B19)^('DCF Model'!C19+4)+('DCF Model'!G39+'DCF Model'!G42)*F$17/(1+$B19)^('DCF Model'!C19+4)-'DCF Model'!C16)*1000000/'DCF Model'!C15,0),"") -> 2991 | G19: =IFERROR(ROUND(('DCF Model'!C45/(1+$B19)^('DCF Model'!C19+0)+'DCF Model'!D45/(1+$B19)^('DCF Model'!C19+1)+'DCF Model'!E45/(1+$B19)^('DCF Model'!C19+2)+'DCF Model'!F45/(1+$B19)^('DCF Model'!C19+3)+'DCF Model'!G45/(1+$B19)^('DCF Model'!C19+4)+('DCF Model'!G39+'DCF Model'!G42)*G$17/(1+$B19)^('DCF Model'!C19+4)-'DCF Model'!C16)*1000000/'DCF Model'!C15,0),"") -> 3218 | H19: =IFERROR(ROUND(('DCF Model'!C45/(1+$B19)^('DCF Model'!C19+0)+'DCF Model'!D45/(1+$B19)^('DCF Model'!C19+1)+'DCF Model'!E45/(1+$B19)^('DCF Model'!C19+2)+'DCF Model'!F45/(1+$B19)^('DCF Model'!C19+3)+'DCF Model'!G45/(1+$B19)^('DCF Model'!C19+4)+('DCF Model'!G39+'DCF Model'!G42)*H$17/(1+$B19)^('DCF Model'!C19+4)-'DCF Model'!C16)*1000000/'DCF Model'!C15,0),"") -> 3444 | I19: =IFERROR(ROUND(('DCF Model'!C45/(1+$B19)^('DCF Model'!C19+0)+'DCF Model'!D45/(1+$B19)^('DCF Model'!C19+1)+'DCF Model'!E45/(1+$B19)^('DCF Model'!C19+2)+'DCF Model'!F45/(1+$B19)^('DCF Model'!C19+3)+'DCF Model'!G45/(1+$B19)^('DCF Model'!C19+4)+('DCF Model'!G39+'DCF Model'!G42)*I$17/(1+$B19)^('DCF Model'!C19+4)-'DCF Model'!C16)*1000000/'DCF Model'!C15,0),"") -> 3671
B20: =$C$3-0.005 -> 0.08402591 | C20: =IFERROR(ROUND(('DCF Model'!C45/(1+$B20)^('DCF Model'!C19+0)+'DCF Model'!D45/(1+$B20)^('DCF Model'!C19+1)+'DCF Model'!E45/(1+$B20)^('DCF Model'!C19+2)+'DCF Model'!F45/(1+$B20)^('DCF Model'!C19+3)+'DCF Model'!G45/(1+$B20)^('DCF Model'!C19+4)+('DCF Model'!G39+'DCF Model'!G42)*C$17/(1+$B20)^('DCF Model'!C19+4)-'DCF Model'!C16)*1000000/'DCF Model'!C15,0),"") -> 2250 | D20: =IFERROR(ROUND(('DCF Model'!C45/(1+$B20)^('DCF Model'!C19+0)+'DCF Model'!D45/(1+$B20)^('DCF Model'!C19+1)+'DCF Model'!E45/(1+$B20)^('DCF Model'!C19+2)+'DCF Model'!F45/(1+$B20)^('DCF Model'!C19+3)+'DCF Model'!G45/(1+$B20)^('DCF Model'!C19+4)+('DCF Model'!G39+'DCF Model'!G42)*D$17/(1+$B20)^('DCF Model'!C19+4)-'DCF Model'!C16)*1000000/'DCF Model'!C15,0),"") -> 2472 | E20: =IFERROR(ROUND(('DCF Model'!C45/(1+$B20)^('DCF Model'!C19+0)+'DCF Model'!D45/(1+$B20)^('DCF Model'!C19+1)+'DCF Model'!E45/(1+$B20)^('DCF Model'!C19+2)+'DCF Model'!F45/(1+$B20)^('DCF Model'!C19+3)+'DCF Model'!G45/(1+$B20)^('DCF Model'!C19+4)+('DCF Model'!G39+'DCF Model'!G42)*E$17/(1+$B20)^('DCF Model'!C19+4)-'DCF Model'!C16)*1000000/'DCF Model'!C15,0),"") -> 2693 | F20: =IFERROR(ROUND(('DCF Model'!C45/(1+$B20)^('DCF Model'!C19+0)+'DCF Model'!D45/(1+$B20)^('DCF Model'!C19+1)+'DCF Model'!E45/(1+$B20)^('DCF Model'!C19+2)+'DCF Model'!F45/(1+$B20)^('DCF Model'!C19+3)+'DCF Model'!G45/(1+$B20)^('DCF Model'!C19+4)+('DCF Model'!G39+'DCF Model'!G42)*F$17/(1+$B20)^('DCF Model'!C19+4)-'DCF Model'!C16)*1000000/'DCF Model'!C15,0),"") -> 2915 | G20: =IFERROR(ROUND(('DCF Model'!C45/(1+$B20)^('DCF Model'!C19+0)+'DCF Model'!D45/(1+$B20)^('DCF Model'!C19+1)+'DCF Model'!E45/(1+$B20)^('DCF Model'!C19+2)+'DCF Model'!F45/(1+$B20)^('DCF Model'!C19+3)+'DCF Model'!G45/(1+$B20)^('DCF Model'!C19+4)+('DCF Model'!G39+'DCF Model'!G42)*G$17/(1+$B20)^('DCF Model'!C19+4)-'DCF Model'!C16)*1000000/'DCF Model'!C15,0),"") -> 3136 | H20: =IFERROR(ROUND(('DCF Model'!C45/(1+$B20)^('DCF Model'!C19+0)+'DCF Model'!D45/(1+$B20)^('DCF Model'!C19+1)+'DCF Model'!E45/(1+$B20)^('DCF Model'!C19+2)+'DCF Model'!F45/(1+$B20)^('DCF Model'!C19+3)+'DCF Model'!G45/(1+$B20)^('DCF Model'!C19+4)+('DCF Model'!G39+'DCF Model'!G42)*H$17/(1+$B20)^('DCF Model'!C19+4)-'DCF Model'!C16)*1000000/'DCF Model'!C15,0),"") -> 3357 | I20: =IFERROR(ROUND(('DCF Model'!C45/(1+$B20)^('DCF Model'!C19+0)+'DCF Model'!D45/(1+$B20)^('DCF Model'!C19+1)+'DCF Model'!E45/(1+$B20)^('DCF Model'!C19+2)+'DCF Model'!F45/(1+$B20)^('DCF Model'!C19+3)+'DCF Model'!G45/(1+$B20)^('DCF Model'!C19+4)+('DCF Model'!G39+'DCF Model'!G42)*I$17/(1+$B20)^('DCF Model'!C19+4)-'DCF Model'!C16)*1000000/'DCF Model'!C15,0),"") -> 3579
B21: =$C$3 -> 0.08902591 | C21: =IFERROR(ROUND(('DCF Model'!C45/(1+$B21)^('DCF Model'!C19+0)+'DCF Model'!D45/(1+$B21)^('DCF Model'!C19+1)+'DCF Model'!E45/(1+$B21)^('DCF Model'!C19+2)+'DCF Model'!F45/(1+$B21)^('DCF Model'!C19+3)+'DCF Model'!G45/(1+$B21)^('DCF Model'!C19+4)+('DCF Model'!G39+'DCF Model'!G42)*C$17/(1+$B21)^('DCF Model'!C19+4)-'DCF Model'!C16)*1000000/'DCF Model'!C15,0),"") -> 2191 | D21: =IFERROR(ROUND(('DCF Model'!C45/(1+$B21)^('DCF Model'!C19+0)+'DCF Model'!D45/(1+$B21)^('DCF Model'!C19+1)+'DCF Model'!E45/(1+$B21)^('DCF Model'!C19+2)+'DCF Model'!F45/(1+$B21)^('DCF Model'!C19+3)+'DCF Model'!G45/(1+$B21)^('DCF Model'!C19+4)+('DCF Model'!G39+'DCF Model'!G42)*D$17/(1+$B21)^('DCF Model'!C19+4)-'DCF Model'!C16)*1000000/'DCF Model'!C15,0),"") -> 2408 | E21: =IFERROR(ROUND(('DCF Model'!C45/(1+$B21)^('DCF Model'!C19+0)+'DCF Model'!D45/(1+$B21)^('DCF Model'!C19+1)+'DCF Model'!E45/(1+$B21)^('DCF Model'!C19+2)+'DCF Model'!F45/(1+$B21)^('DCF Model'!C19+3)+'DCF Model'!G45/(1+$B21)^('DCF Model'!C19+4)+('DCF Model'!G39+'DCF Model'!G42)*E$17/(1+$B21)^('DCF Model'!C19+4)-'DCF Model'!C16)*1000000/'DCF Model'!C15,0),"") -> 2624 | F21: =IFERROR(ROUND(('DCF Model'!C45/(1+$B21)^('DCF Model'!C19+0)+'DCF Model'!D45/(1+$B21)^('DCF Model'!C19+1)+'DCF Model'!E45/(1+$B21)^('DCF Model'!C19+2)+'DCF Model'!F45/(1+$B21)^('DCF Model'!C19+3)+'DCF Model'!G45/(1+$B21)^('DCF Model'!C19+4)+('DCF Model'!G39+'DCF Model'!G42)*F$17/(1+$B21)^('DCF Model'!C19+4)-'DCF Model'!C16)*1000000/'DCF Model'!C15,0),"") -> 2840 | G21: =IFERROR(ROUND(('DCF Model'!C45/(1+$B21)^('DCF Model'!C19+0)+'DCF Model'!D45/(1+$B21)^('DCF Model'!C19+1)+'DCF Model'!E45/(1+$B21)^('DCF Model'!C19+2)+'DCF Model'!F45/(1+$B21)^('DCF Model'!C19+3)+'DCF Model'!G45/(1+$B21)^('DCF Model'!C19+4)+('DCF Model'!G39+'DCF Model'!G42)*G$17/(1+$B21)^('DCF Model'!C19+4)-'DCF Model'!C16)*1000000/'DCF Model'!C15,0),"") -> 3057 | H21: =IFERROR(ROUND(('DCF Model'!C45/(1+$B21)^('DCF Model'!C19+0)+'DCF Model'!D45/(1+$B21)^('DCF Model'!C19+1)+'DCF Model'!E45/(1+$B21)^('DCF Model'!C19+2)+'DCF Model'!F45/(1+$B21)^('DCF Model'!C19+3)+'DCF Model'!G45/(1+$B21)^('DCF Model'!C19+4)+('DCF Model'!G39+'DCF Model'!G42)*H$17/(1+$B21)^('DCF Model'!C19+4)-'DCF Model'!C16)*1000000/'DCF Model'!C15,0),"") -> 3273 | I21: =IFERROR(ROUND(('DCF Model'!C45/(1+$B21)^('DCF Model'!C19+0)+'DCF Model'!D45/(1+$B21)^('DCF Model'!C19+1)+'DCF Model'!E45/(1+$B21)^('DCF Model'!C19+2)+'DCF Model'!F45/(1+$B21)^('DCF Model'!C19+3)+'DCF Model'!G45/(1+$B21)^('DCF Model'!C19+4)+('DCF Model'!G39+'DCF Model'!G42)*I$17/(1+$B21)^('DCF Model'!C19+4)-'DCF Model'!C16)*1000000/'DCF Model'!C15,0),"") -> 3489
B22: =$C$3+0.005 -> 0.09402591 | C22: =IFERROR(ROUND(('DCF Model'!C45/(1+$B22)^('DCF Model'!C19+0)+'DCF Model'!D45/(1+$B22)^('DCF Model'!C19+1)+'DCF Model'!E45/(1+$B22)^('DCF Model'!C19+2)+'DCF Model'!F45/(1+$B22)^('DCF Model'!C19+3)+'DCF Model'!G45/(1+$B22)^('DCF Model'!C19+4)+('DCF Model'!G39+'DCF Model'!G42)*C$17/(1+$B22)^('DCF Model'!C19+4)-'DCF Model'!C16)*1000000/'DCF Model'!C15,0),"") -> 2134 | D22: =IFERROR(ROUND(('DCF Model'!C45/(1+$B22)^('DCF Model'!C19+0)+'DCF Model'!D45/(1+$B22)^('DCF Model'!C19+1)+'DCF Model'!E45/(1+$B22)^('DCF Model'!C19+2)+'DCF Model'!F45/(1+$B22)^('DCF Model'!C19+3)+'DCF Model'!G45/(1+$B22)^('DCF Model'!C19+4)+('DCF Model'!G39+'DCF Model'!G42)*D$17/(1+$B22)^('DCF Model'!C19+4)-'DCF Model'!C16)*1000000/'DCF Model'!C15,0),"") -> 2345 | E22: =IFERROR(ROUND(('DCF Model'!C45/(1+$B22)^('DCF Model'!C19+0)+'DCF Model'!D45/(1+$B22)^('DCF Model'!C19+1)+'DCF Model'!E45/(1+$B22)^('DCF Model'!C19+2)+'DCF Model'!F45/(1+$B22)^('DCF Model'!C19+3)+'DCF Model'!G45/(1+$B22)^('DCF Model'!C19+4)+('DCF Model'!G39+'DCF Model'!G42)*E$17/(1+$B22)^('DCF Model'!C19+4)-'DCF Model'!C16)*1000000/'DCF Model'!C15,0),"") -> 2557 | F22: =IFERROR(ROUND(('DCF Model'!C45/(1+$B22)^('DCF Model'!C19+0)+'DCF Model'!D45/(1+$B22)^('DCF Model'!C19+1)+'DCF Model'!E45/(1+$B22)^('DCF Model'!C19+2)+'DCF Model'!F45/(1+$B22)^('DCF Model'!C19+3)+'DCF Model'!G45/(1+$B22)^('DCF Model'!C19+4)+('DCF Model'!G39+'DCF Model'!G42)*F$17/(1+$B22)^('DCF Model'!C19+4)-'DCF Model'!C16)*1000000/'DCF Model'!C15,0),"") -> 2768 | G22: =IFERROR(ROUND(('DCF Model'!C45/(1+$B22)^('DCF Model'!C19+0)+'DCF Model'!D45/(1+$B22)^('DCF Model'!C19+1)+'DCF Model'!E45/(1+$B22)^('DCF Model'!C19+2)+'DCF Model'!F45/(1+$B22)^('DCF Model'!C19+3)+'DCF Model'!G45/(1+$B22)^('DCF Model'!C19+4)+('DCF Model'!G39+'DCF Model'!G42)*G$17/(1+$B22)^('DCF Model'!C19+4)-'DCF Model'!C16)*1000000/'DCF Model'!C15,0),"") -> 2980 | H22: =IFERROR(ROUND(('DCF Model'!C45/(1+$B22)^('DCF Model'!C19+0)+'DCF Model'!D45/(1+$B22)^('DCF Model'!C19+1)+'DCF Model'!E45/(1+$B22)^('DCF Model'!C19+2)+'DCF Model'!F45/(1+$B22)^('DCF Model'!C19+3)+'DCF Model'!G45/(1+$B22)^('DCF Model'!C19+4)+('DCF Model'!G39+'DCF Model'!G42)*H$17/(1+$B22)^('DCF Model'!C19+4)-'DCF Model'!C16)*1000000/'DCF Model'!C15,0),"") -> 3191 | I22: =IFERROR(ROUND(('DCF Model'!C45/(1+$B22)^('DCF Model'!C19+0)+'DCF Model'!D45/(1+$B22)^('DCF Model'!C19+1)+'DCF Model'!E45/(1+$B22)^('DCF Model'!C19+2)+'DCF Model'!F45/(1+$B22)^('DCF Model'!C19+3)+'DCF Model'!G45/(1+$B22)^('DCF Model'!C19+4)+('DCF Model'!G39+'DCF Model'!G42)*I$17/(1+$B22)^('DCF Model'!C19+4)-'DCF Model'!C16)*1000000/'DCF Model'!C15,0),"") -> 3403
B23: =$C$3+0.01 -> 0.09902591 | C23: =IFERROR(ROUND(('DCF Model'!C45/(1+$B23)^('DCF Model'!C19+0)+'DCF Model'!D45/(1+$B23)^('DCF Model'!C19+1)+'DCF Model'!E45/(1+$B23)^('DCF Model'!C19+2)+'DCF Model'!F45/(1+$B23)^('DCF Model'!C19+3)+'DCF Model'!G45/(1+$B23)^('DCF Model'!C19+4)+('DCF Model'!G39+'DCF Model'!G42)*C$17/(1+$B23)^('DCF Model'!C19+4)-'DCF Model'!C16)*1000000/'DCF Model'!C15,0),"") -> 2078 | D23: =IFERROR(ROUND(('DCF Model'!C45/(1+$B23)^('DCF Model'!C19+0)+'DCF Model'!D45/(1+$B23)^('DCF Model'!C19+1)+'DCF Model'!E45/(1+$B23)^('DCF Model'!C19+2)+'DCF Model'!F45/(1+$B23)^('DCF Model'!C19+3)+'DCF Model'!G45/(1+$B23)^('DCF Model'!C19+4)+('DCF Model'!G39+'DCF Model'!G42)*D$17/(1+$B23)^('DCF Model'!C19+4)-'DCF Model'!C16)*1000000/'DCF Model'!C15,0),"") -> 2284 | E23: =IFERROR(ROUND(('DCF Model'!C45/(1+$B23)^('DCF Model'!C19+0)+'DCF Model'!D45/(1+$B23)^('DCF Model'!C19+1)+'DCF Model'!E45/(1+$B23)^('DCF Model'!C19+2)+'DCF Model'!F45/(1+$B23)^('DCF Model'!C19+3)+'DCF Model'!G45/(1+$B23)^('DCF Model'!C19+4)+('DCF Model'!G39+'DCF Model'!G42)*E$17/(1+$B23)^('DCF Model'!C19+4)-'DCF Model'!C16)*1000000/'DCF Model'!C15,0),"") -> 2491 | F23: =IFERROR(ROUND(('DCF Model'!C45/(1+$B23)^('DCF Model'!C19+0)+'DCF Model'!D45/(1+$B23)^('DCF Model'!C19+1)+'DCF Model'!E45/(1+$B23)^('DCF Model'!C19+2)+'DCF Model'!F45/(1+$B23)^('DCF Model'!C19+3)+'DCF Model'!G45/(1+$B23)^('DCF Model'!C19+4)+('DCF Model'!G39+'DCF Model'!G42)*F$17/(1+$B23)^('DCF Model'!C19+4)-'DCF Model'!C16)*1000000/'DCF Model'!C15,0),"") -> 2698 | G23: =IFERROR(ROUND(('DCF Model'!C45/(1+$B23)^('DCF Model'!C19+0)+'DCF Model'!D45/(1+$B23)^('DCF Model'!C19+1)+'DCF Model'!E45/(1+$B23)^('DCF Model'!C19+2)+'DCF Model'!F45/(1+$B23)^('DCF Model'!C19+3)+'DCF Model'!G45/(1+$B23)^('DCF Model'!C19+4)+('DCF Model'!G39+'DCF Model'!G42)*G$17/(1+$B23)^('DCF Model'!C19+4)-'DCF Model'!C16)*1000000/'DCF Model'!C15,0),"") -> 2904 | H23: =IFERROR(ROUND(('DCF Model'!C45/(1+$B23)^('DCF Model'!C19+0)+'DCF Model'!D45/(1+$B23)^('DCF Model'!C19+1)+'DCF Model'!E45/(1+$B23)^('DCF Model'!C19+2)+'DCF Model'!F45/(1+$B23)^('DCF Model'!C19+3)+'DCF Model'!G45/(1+$B23)^('DCF Model'!C19+4)+('DCF Model'!G39+'DCF Model'!G42)*H$17/(1+$B23)^('DCF Model'!C19+4)-'DCF Model'!C16)*1000000/'DCF Model'!C15,0),"") -> 3111 | I23: =IFERROR(ROUND(('DCF Model'!C45/(1+$B23)^('DCF Model'!C19+0)+'DCF Model'!D45/(1+$B23)^('DCF Model'!C19+1)+'DCF Model'!E45/(1+$B23)^('DCF Model'!C19+2)+'DCF Model'!F45/(1+$B23)^('DCF Model'!C19+3)+'DCF Model'!G45/(1+$B23)^('DCF Model'!C19+4)+('DCF Model'!G39+'DCF Model'!G42)*I$17/(1+$B23)^('DCF Model'!C19+4)-'DCF Model'!C16)*1000000/'DCF Model'!C15,0),"") -> 3318
B24: =$C$3+0.015 -> 0.10402591 | C24: =IFERROR(ROUND(('DCF Model'!C45/(1+$B24)^('DCF Model'!C19+0)+'DCF Model'!D45/(1+$B24)^('DCF Model'!C19+1)+'DCF Model'!E45/(1+$B24)^('DCF Model'!C19+2)+'DCF Model'!F45/(1+$B24)^('DCF Model'!C19+3)+'DCF Model'!G45/(1+$B24)^('DCF Model'!C19+4)+('DCF Model'!G39+'DCF Model'!G42)*C$17/(1+$B24)^('DCF Model'!C19+4)-'DCF Model'!C16)*1000000/'DCF Model'!C15,0),"") -> 2023 | D24: =IFERROR(ROUND(('DCF Model'!C45/(1+$B24)^('DCF Model'!C19+0)+'DCF Model'!D45/(1+$B24)^('DCF Model'!C19+1)+'DCF Model'!E45/(1+$B24)^('DCF Model'!C19+2)+'DCF Model'!F45/(1+$B24)^('DCF Model'!C19+3)+'DCF Model'!G45/(1+$B24)^('DCF Model'!C19+4)+('DCF Model'!G39+'DCF Model'!G42)*D$17/(1+$B24)^('DCF Model'!C19+4)-'DCF Model'!C16)*1000000/'DCF Model'!C15,0),"") -> 2225 | E24: =IFERROR(ROUND(('DCF Model'!C45/(1+$B24)^('DCF Model'!C19+0)+'DCF Model'!D45/(1+$B24)^('DCF Model'!C19+1)+'DCF Model'!E45/(1+$B24)^('DCF Model'!C19+2)+'DCF Model'!F45/(1+$B24)^('DCF Model'!C19+3)+'DCF Model'!G45/(1+$B24)^('DCF Model'!C19+4)+('DCF Model'!G39+'DCF Model'!G42)*E$17/(1+$B24)^('DCF Model'!C19+4)-'DCF Model'!C16)*1000000/'DCF Model'!C15,0),"") -> 2427 | F24: =IFERROR(ROUND(('DCF Model'!C45/(1+$B24)^('DCF Model'!C19+0)+'DCF Model'!D45/(1+$B24)^('DCF Model'!C19+1)+'DCF Model'!E45/(1+$B24)^('DCF Model'!C19+2)+'DCF Model'!F45/(1+$B24)^('DCF Model'!C19+3)+'DCF Model'!G45/(1+$B24)^('DCF Model'!C19+4)+('DCF Model'!G39+'DCF Model'!G42)*F$17/(1+$B24)^('DCF Model'!C19+4)-'DCF Model'!C16)*1000000/'DCF Model'!C15,0),"") -> 2629 | G24: =IFERROR(ROUND(('DCF Model'!C45/(1+$B24)^('DCF Model'!C19+0)+'DCF Model'!D45/(1+$B24)^('DCF Model'!C19+1)+'DCF Model'!E45/(1+$B24)^('DCF Model'!C19+2)+'DCF Model'!F45/(1+$B24)^('DCF Model'!C19+3)+'DCF Model'!G45/(1+$B24)^('DCF Model'!C19+4)+('DCF Model'!G39+'DCF Model'!G42)*G$17/(1+$B24)^('DCF Model'!C19+4)-'DCF Model'!C16)*1000000/'DCF Model'!C15,0),"") -> 2831 | H24: =IFERROR(ROUND(('DCF Model'!C45/(1+$B24)^('DCF Model'!C19+0)+'DCF Model'!D45/(1+$B24)^('DCF Model'!C19+1)+'DCF Model'!E45/(1+$B24)^('DCF Model'!C19+2)+'DCF Model'!F45/(1+$B24)^('DCF Model'!C19+3)+'DCF Model'!G45/(1+$B24)^('DCF Model'!C19+4)+('DCF Model'!G39+'DCF Model'!G42)*H$17/(1+$B24)^('DCF Model'!C19+4)-'DCF Model'!C16)*1000000/'DCF Model'!C15,0),"") -> 3034 | I24: =IFERROR(ROUND(('DCF Model'!C45/(1+$B24)^('DCF Model'!C19+0)+'DCF Model'!D45/(1+$B24)^('DCF Model'!C19+1)+'DCF Model'!E45/(1+$B24)^('DCF Model'!C19+2)+'DCF Model'!F45/(1+$B24)^('DCF Model'!C19+3)+'DCF Model'!G45/(1+$B24)^('DCF Model'!C19+4)+('DCF Model'!G39+'DCF Model'!G42)*I$17/(1+$B24)^('DCF Model'!C19+4)-'DCF Model'!C16)*1000000/'DCF Model'!C15,0),"") -> 3236
B26: All values dynamically linked to DCF Model. Headers auto-center on current WACC / Terminal g / Exit Multiple.

Sheet Adjustments Log
B2: Adjustments Log - パナソニックホールディングス
B4: 日付 | C4: セル | D4: 変更内容 | E4: 理由 | F4: 元の値 | G4: 状態
B5: 2026-09-05 | C5: - | D5: Generated by pipeline on 2026-09-05 21:25, template rev c9b5dd9 | E5: 初期生成（手修正なし） | F5: - | G5: generated
B6: 2026-09-05 | C6: DCF Model!C7 | D6: Risk-Free Rate = 2.97% | E6: 財務省 国債金利情報 jgbcm.csv 10年物 R8.9.3(2026-09-03) 2.966% を四捨五入。バッチ全銘柄共通の一次ソース。yfinance は日本国債利回りを返さないため使用しない。 | F6: テンプレ既定 2.2% | G6: 確定
B7: 2026-09-05 | C7: DCF Model!C9 | D7: Equity Risk Premium = 6.5% | E7: バッチ共通の固定前提(v2 §1-3)。銘柄固有の調整はしていない。 | F7: テンプレ既定 6.5%(同値) | G7: 設計判断
B8: 2026-09-05 | C8: DCF Model!C10 | D8: Size Premium = 1.0% | E8: 時価総額バンドによる機械決定(>3,000億円 -> 1.0%)。当社時価総額 9,720,313百万円。■テンプレートの自動規則(>=1兆円 -> 0.0%、>=1,000億円 -> 1.5%)とは異なる値であり、明示指定で上書きしている。 | F8: テンプレ自動値 | G8: 設計判断
B9: 2026-09-05 | C9: DCF Model!C8 | D9: Beta = 0.85 | E9: yfinance実測 **0.846** はテンプレのクランプ域 [0.6, 1.75] の**内側**のため素通し（置換なし）。 | F9: yfinance実測 0.846 | G9: 確定
B10: 2026-09-05 | C10: DCF Model!C6 | D10: Effective Tax Rate = 25% | E10: バッチ共通の既定値(v2 §1-3)。当社の実績税負担率を個別に検証したものではない。 | F10: テンプレ既定 30% | G10: 推定
B11: 2026-09-05 | C11: DCF Model!C11 | D11: After-tax Cost of Debt = 1.99%(実績ベース) | E11: 支払利息 41,998百万円 ÷ 平均有利子負債 ((1,568,243 + 1,603,197)/2 = 1,585,720) = 2.65%(税引前)、× (1 − 25%) = 1.99%（validate チェック17 PASS）。有利子負債が売上比20%あり Kd が WACC に一定の寄与をする。■出所は yfinance の Interest Expense で EDINET 有報の支払利息と未突合。 | F11: テンプレ既定(推定値) | G11: 推定(出所が二次ソース・要確認)
B12: 2026-09-05 | C12: DCF Model!C13 | D12: Terminal Growth = 1.0% | E12: バッチ共通の固定前提(v2 §1-3)。 | F12: テンプレ既定 2.0% | G12: 設計判断
B13: 2026-09-05 | C13: DCF Model!C14 | D13: Exit Multiple (EV/EBITDA) = 14.3x | E13: Peer 5社の実測EV/EBITDA中央値 14.33x。■**追補4 §Q の判定**: `batch/check_growth_premium.py` で機械判定した結果、**非該当**。（3条件のうち「仮定Exit倍率 > 25倍」を満たさないため。Exit法は Target に算入されたまま） 自社の現在倍率 17.18x は算式に入れていない(市場価格への循環参照回避)。■マージン品質調整式はバッチ全体で棄却済み(EV/EBITDA が既に資本集約度を織り込むため、営業利益率による上方調整は資本集約型で逆方向に働く)。 | F13: テンプレ既定 10.0x | G13: 設計判断
B14: 2026-09-05 | C14: 全体(型判定・プレスクリーン) | D14: **型B疑い(分母トラフ型)・要目視レビュー** として処理（初回生成の型A から追補5 §U により再分類） | E14: 追補1 §B に従い、型判定の前に batch/prescreen.py で EDINET有報XBRL の金融事業専用科目(ForFinancialBusiness / Banking / Deposits / CallLoan / InstallmentReceivable 系)を機械チェックした。検出結果: **CLEAN**（金融事業専用科目は1件も検出されず）。追補2 §C が『金融子会社リスクが相対的に高い』と指摘した3銘柄の1つだったが、連結BSに金融事業専用科目は存在せず CLEAN。■**初回生成では赤字年がないことを理由に型A としたが、追補5 §U により型B疑いへ再分類した。**`batch/check_trough_artifact.py` の全件スキャン（done 39銘柄）で **本銘柄のみが §U シグネチャに該当**: (1) 直近OPM **2.61%** ≤ 観測窓p25 **3.22%**（直近が観測窓の最低＝サイクルの谷）、(2) WARN11 乖離 **4.31倍** > 3.0倍、(3) 仮定Exit **14.30倍** ≤ 25倍（追補4 §Q 非該当）。■型Bの定義は『赤字年の有無』ではなく『**分母（利益）がサイクル上の異常水準にある**』ことであり、黒字でも直近が観測窓の谷にあれば型B疑いとして扱うのが §U の趣旨である。 | F14: 初回生成の型A判定 | G14: 設計判断(追補5 §U により訂正)
B15: 2026-09-05 | C15: Financial Statements / hist_* / 市場データ / net_debt / core_ebitda | D15: 追補2 §F-2 + 追補3 §L + 追補2 §G の予防的補完を生成前適用 | E15: 【追補2 §F-2 / 追補3 §L の予防的補完（生成前適用・必須）】根本原因は scripts/generate_dcf.py:66 の _val(data_dict, key, default=0) が欠損値を None ではなく 0 に落とすこと。hist_years を直近4期に置換し hist_revenue / hist_operating_income / hist_net_income / hist_cogs / hist_sga を yfinance連結財務諸表から供給（配列長は全て4で hist_years と一致、契約遵守）。CF/BS 5系列は供給せず Step 4.6 の年度キー再マッピングに委ねる。hist_sga = 売上 − COGS − 営業利益 で逆算。current_price / shares_outstanding / net_debt / core_ebitda も予防的に明示指定（追補3 §L / 追補2 §G）。■**結果として初回生成で合格（リトライ0回）**。 | F15: EDINET自動抽出値 | G15: 設計判断
... B29: 2026-09-05 | C29: Executive Summary!B16 / B20（手順書§6-4 の除外注記） | D29: PGM行のラベルに `[参考・Target不算入 — 追補5 §U]` を付し、B20 に銘柄固有の除外理由文を追記した | E29: 手順書§6-4 は『Targetから除外した手法は、その銘柄固有の理由を Exec Summary の注記に明記する』ことを求めている。テンプレート既定の総称文（Comps 2法の除外理由）だけでは PGM 降格の理由が読み取れないため、`batch/demote_dcf_leg.py` が追補5 §U の判断根拠を1文で追記した（追補2 §H で 4188 について指摘された不備の再発防止）。■手順書§5-5 に従いラベルは `=` で始まらないことをスクリプト内で assert している。 | F29: テンプレート既定の総称注記のみ | G29: 設計判断
B31: Pipeline Metadata (do not edit — read by scripts/validate_output.py)
B32: key | C32: value
B33: auto_log_entries | C33: 1
B34: capex_pct_basis | C34: assumption
B35: capex_pct_c5 | C35: 0.0525
B36: capex_pct_hist3yr | C36: n/a
B37: company_name | C37: パナソニックホールディングス
B38: comps_asof | C38: 2026-09-05
B39: comps_da_missing | C39: none
B40: comps_ev_ebitda_invalid | C40: no
B41: comps_ev_ebitda_rows | C41: 6,7,8,9,10
B42: comps_impl_mult_row | C42: 27
B43: comps_impl_per_row | C43: 28
... B69: ticker | C69: 6752.T
