Workbook

Sheet Executive Summary
B1: DISCLAIMER: This is a sample analysis for demonstration purposes only. It does not constitute investment advice.
B3: Tamagawa Holdings (6838.T)
B4: Equity Research Report
B6: Company | C6: Tamagawa Holdings
B7: Ticker | C7: 6838.T (TSE Standard)
B8: Sector | C8: Electronic & Communication Equipment / Renewable Energy
B9: Current Price | C9: 1530
B10: Target Price (DCF Mid) | C10: =IF(COUNT(C16:C17)=0,"N/A",ROUND(AVERAGE(C16:C17),0)) -> 1153
B11: Recommendation | C11: =IF(NOT(ISNUMBER(C12)),"N/A",IF(C12>0.15,"BUY",IF(C12>0.05,"HOLD","SELL"))) -> SELL
B12: Upside / Downside | C12: =IF(ISNUMBER(C10),(C10-C9)/C9,"N/A") -> -0.24640523
B14: Valuation Summary
B15: Methodology | C15: Implied Value (JPY) | D15: vs Current Price
B16: DCF - Perpetuity Growth | C16: =IF('DCF Model'!C53<'DCF Model'!C16,"INVALID (EV < net debt)",'DCF Model'!C55) -> 853 | D16: =IF(ISNUMBER(C16),(C16-C9)/C9,"N/A") -> -0.44248366
B17: DCF - Exit Multiple | C17: =IF('DCF Model'!C62<'DCF Model'!C16,"INVALID (EV < net debt)",'DCF Model'!C64) -> 1453 | D17: =IF(ISNUMBER(C17),(C17-C9)/C9,"N/A") -> -0.050326797
B18: Comps - EV/EBITDA Median [参考・Target不算入] | C18: ='Comps Analysis'!C27 -> 3650 | D18: =IF(ISNUMBER(C18),(C18-C9)/C9,"N/A") -> 1.3856209
B19: Comps - PER Median [参考・Target不算入] | C19: ='Comps Analysis'!C28 -> 2525 | D19: =IF(ISNUMBER(C19),(C19-C9)/C9,"N/A") -> 0.6503268
B20: Note: Target Mid は DCF 2法（PGM / Exit）の平均のみ。Comps 2法は [参考] で Target 不算入（EV<ネットデットで株式価値が負になる手法は INVALID として平均から除外）
B21: DCF Valuation Range (PGM - Exit) | C21: =IF(COUNT(C16:C17)=0,"N/A",MIN(C16:C17)&" - "&MAX(C16:C17)) -> 853 - 1453
B23: Key Investment Thesis
B24: The earnings slope is real: government-related revenue more than doubled to JPY2,089mn in the first half of FY10/26 as the main RF module moved from development into mass production, taking first-half operating profit to JPY752mn and already past the FY10/28 mid-term plan target of JPY761mn.
B25: Company guidance is stale rather than a ceiling: the revised full-year operating profit of JPY820mn implies only JPY68mn for the whole second half, and first-half orders of JPY4,295mn ran 15% ahead of sales with contract liabilities more than doubling.
B26: ="At "&TEXT(C9,"#,##0")&" the market is valued net of the Addvalue stake and net cash; our target of "&TEXT(C10,"#,##0")&" implies "&TEXT(C12,"+0.0%;-0.0%")&" at a WACC of "&TEXT('DCF Model'!C26,"0.00%")&", on "&TEXT('Comps Analysis'!M5,"0.00""x""")&" book, with the gain on the Singapore shares excluded from earnings and the stake counted once in the EV bridge." -> At 1,530 the market is valued net of the Addvalue stake and net cash; our target of 1,153 implies -24.6% at a WACC of 15.40%, on 1.49x book, with the gain on the Singapore shares excluded from earnings and the stake counted once in the EV bridge.
B28: Key Risks
B29: The slope is already bending: second-quarter stand-alone operating margin fell to 15.1% from 24.2% in the first quarter and quarterly revenue fell 17.5%, so the first-quarter margin may have been a mass-production launch peak rather than a steady state.
B30: Reported profit is dominated by a mark-to-market gain: about 73% of first-half net profit is the fair-value gain on 125.8mn Addvalue Technologies shares listed in Singapore, whose price moves about 9% a week; a halving of the stake would remove about JPY124 per share of value deducted in this model.
B31: Balance-sheet quality depends on a build-to-order working-capital cycle of over 200 inventory days, and the equity base was rebuilt with moving-strike warrants that added about a third to the share count in one year; further equity funding for the second factory or grid batteries would dilute again.

Sheet Financial Statements
B2: Tamagawa Holdings - Historical Financials (JPY mn)
C4: FY2023/3 | D4: FY2024/3 | E4: FY2024/10(7M) | F4: FY2025/10 | G4: FY2026/10E
B5: Income Statement
B6: Revenue | C6: 3294.5 | D6: 4154 | E6: 2356.4 | F6: 5588 | G6: 6950
B7: COGS | C7: 2404.8 | D7: 3059.3 | E7: 1644.9 | F7: 3895.1 | G7: 4093.6
B8: Gross Profit | C8: =C6-C7 -> 889.7 | D8: =D6-D7 -> 1094.7 | E8: =E6-E7 -> 711.5 | F8: =F6-F7 -> 1692.9 | G8: =G6-G7 -> 2856.4
B9: Gross Margin | C9: =C8/C6 -> 0.27005615 | D9: =D8/D6 -> 0.26352913 | E9: =E8/E6 -> 0.30194364 | F9: =F8/F6 -> 0.30295276 | G9: =G8/G6 -> 0.41099281
B10: SGA | C10: 1327 | D10: 1309.9 | E10: 759.3 | F10: 1414 | G10: 1620.4
B11: Operating Income | C11: -437.2 | D11: -215.3 | E11: -47.8 | F11: 278.9 | G11: 1236
B12: Net Income | C12: -482.8 | D12: -443.4 | E12: -113.7 | F12: 268.6 | G12: 810
B13: Operating Margin | C13: =C11/C6 -> -0.13270603 | D13: =D11/D6 -> -0.051829562 | E13: =E11/E6 -> -0.020285181 | F13: =F11/F6 -> 0.049910523 | G13: =G11/G6 -> 0.17784173
B14: Net Margin | C14: =C12/C6 -> -0.14654728 | D14: =D12/D6 -> -0.10674049 | E14: =E12/E6 -> -0.04825157 | F14: =F12/F6 -> 0.048067287 | G14: =G12/G6 -> 0.11654676
B15: Revenue Growth (YoY) | C15: n/a | D15: =(D6-C6)/C6 -> 0.26088936 | E15: =(E6-D6)/D6 -> -0.43273953 | F15: =(F6-E6)/E6 -> 1.371414 | G15: =(G6-F6)/F6 -> 0.24373658
B16: Operating Income Growth (YoY) | C16: n/a | D16: =(D11-C11)/C11 -> -0.50754803 | E16: =(E11-D11)/D11 -> -0.77798421 | F16: =(F11-E11)/E11 -> -6.834728 | G16: =(G11-F11)/F11 -> 3.4316959
B18: Cash Flow Statement
B19: Operating Cash Flow | C19: -1883.9 | D19: -1132.8 | E19: 257.8 | F19: -25.7 | G19: 1740
B20: Capex | C20: 199.8 | D20: 66.9 | E20: 188.9 | F20: 606.9 | G20: 500
B21: Free Cash Flow | C21: =C19-C20 -> -2083.7 | D21: =D19-D20 -> -1199.7 | E21: =E19-E20 -> 68.9 | F21: =F19-F20 -> -632.6 | G21: =G19-G20 -> 1240
B22: FCF Margin | C22: =C21/C6 -> -0.63247837 | D22: =D21/D6 -> -0.28880597 | E22: =E21/E6 -> 0.029239518 | F22: =F21/F6 -> -0.11320687 | G22: =G21/G6 -> 0.17841727
B23: Capex / Revenue | C23: =C20/C6 -> 0.060646532 | D23: =D20/D6 -> 0.016104959 | E23: =E20/E6 -> 0.080164658 | F23: =F20/F6 -> 0.10860773 | G23: =G20/G6 -> 0.071942446
B25: Balance Sheet Highlights
B26: Cash & Deposits | C26: 1055.1 | D26: 1210.6 | E26: 1601.8 | F26: 1221.9 | G26: 4047
B27: Total Interest-bearing Debt (short + long) | C27: 2116.2 | D27: 3210.1 | E27: 3646 | F27: 3718 | G27: 3545
B28: Net Debt (Cash) | C28: =C27-C26 -> 1061.1 | D28: =D27-D26 -> 1999.5 | E28: =E27-E26 -> 2044.2 | F28: =F27-F26 -> 2496.1 | G28: =G27-G26 -> -502
B30: Note: OCF / Cash / Debt coverage OCF 5/5, Cash 5/5, Debt 5/5 — blank cells are years with no year-key match in the source data (verify against 決算短信 or set hist_ocf / hist_cash / hist_debt in overrides).

Sheet DCF Model
B2: DCF Valuation Model - Tamagawa Holdings
B4: Assumptions
B5: Capex / Revenue (fallback) | C5: 0.06
B6: Effective Tax Rate | C6: 0.3
B7: Risk-Free Rate | C7: 0.03
B8: Beta | C8: 1.2921
B9: Equity Risk Premium | C9: 0.065
B10: Size Premium | C10: 0.04
B11: After-tax Cost of Debt | C11: 0.0111
B12: D/E Ratio | C12: 0
B13: Terminal Growth Rate | C13: 0.01
B14: Exit Multiple (EV/EBITDA) | C14: 9
B15: Fully Diluted Shares | C15: 9121192
B16: Net Debt (JPY mn) | C16: -2756.3
... B20: LTM Revenue (JPY mn) (override) | C20: 6754
B22: WACC Calculation
B23: Cost of Equity (Ke) | C23: =C7+C8*C9+C10 -> 0.1539865
B24: Weight of Equity | C24: =1/(1+C12) -> 1
B25: Weight of Debt | C25: =C12/(1+C12) -> 0
B26: WACC | C26: =C23*C24+C11*C25 -> 0.1539865
B27: Active Scenario | C27: Base | D27: =MATCH(C27,B69:B73,0) -> 1
B28: Projected Free Cash Flow
C29: FY2027(E) | D29: FY2028(E) | E29: FY2029(E) | F29: FY2030(E) | G29: FY2031(E)
B30: Revenue Growth (YoY) | C30: =CHOOSE($D$27,C69,C70,C71,C72,C73) -> 0.12 | D30: =CHOOSE($D$27,D69,D70,D71,D72,D73) -> 0.1 | E30: =CHOOSE($D$27,E69,E70,E71,E72,E73) -> 0.1 | F30: =CHOOSE($D$27,F69,F70,F71,F72,F73) -> 0.08 | G30: =CHOOSE($D$27,G69,G70,G71,G72,G73) -> 0.05
B31: COGS % of Revenue | C31: =CHOOSE($D$27,C76,C77,C78,C79,C80) -> 0.63 | D31: =CHOOSE($D$27,D76,D77,D78,D79,D80) -> 0.63 | E31: =CHOOSE($D$27,E76,E77,E78,E79,E80) -> 0.63 | F31: =CHOOSE($D$27,F76,F77,F78,F79,F80) -> 0.63 | G31: =CHOOSE($D$27,G76,G77,G78,G79,G80) -> 0.63
B32: SGA % of Revenue | C32: =CHOOSE($D$27,C83,C84,C85,C86,C87) -> 0.22 | D32: =CHOOSE($D$27,D83,D84,D85,D86,D87) -> 0.22 | E32: =CHOOSE($D$27,E83,E84,E85,E86,E87) -> 0.22 | F32: =CHOOSE($D$27,F83,F84,F85,F86,F87) -> 0.22 | G32: =CHOOSE($D$27,G83,G84,G85,G86,G87) -> 0.22
B33: Revenue | C33: =C17*(1+C30) -> 7784 | D33: =C33*(1+D30) -> 8562.4 | E33: =D33*(1+E30) -> 9418.64 | F33: =E33*(1+F30) -> 10172.131 | G33: =F33*(1+G30) -> 10680.738
B34: COGS | C34: =C33*C31 -> 4903.92 | D34: =D33*D31 -> 5394.312 | E34: =E33*E31 -> 5933.7432 | F34: =F33*F31 -> 6408.4427 | G34: =G33*G31 -> 6728.8648
B35: Gross Profit | C35: =C33-C34 -> 2880.08 | D35: =D33-D34 -> 3168.088 | E35: =E33-E34 -> 3484.8968 | F35: =F33-F34 -> 3763.6885 | G35: =G33-G34 -> 3951.873
B36: Gross Margin | C36: =C35/C33 -> 0.37 | D36: =D35/D33 -> 0.37 | E36: =E35/E33 -> 0.37 | F36: =F35/F33 -> 0.37 | G36: =G35/G33 -> 0.37
B37: SGA Expense | C37: =C33*C32 -> 1712.48 | D37: =D33*D32 -> 1883.728 | E37: =E33*E32 -> 2072.1008 | F37: =F33*F32 -> 2237.8689 | G37: =G33*G32 -> 2349.7623
B38: Implied Operating Margin | C38: =(C35-C37)/C33 -> 0.15 | D38: =(D35-D37)/D33 -> 0.15 | E38: =(E35-E37)/E33 -> 0.15 | F38: =(F35-F37)/F33 -> 0.15 | G38: =(G35-G37)/G33 -> 0.15
B39: Operating Income (EBIT) | C39: =C35-C37 -> 1167.6 | D39: =D35-D37 -> 1284.36 | E39: =E35-E37 -> 1412.796 | F39: =F35-F37 -> 1525.8197 | G39: =G35-G37 -> 1602.1107
B40: Less: Tax | C40: =MAX(0,C39*C6) -> 350.28 | D40: =MAX(0,D39*C6) -> 385.308 | E40: =MAX(0,E39*C6) -> 423.8388 | F40: =MAX(0,F39*C6) -> 457.7459 | G40: =MAX(0,G39*C6) -> 480.6332
B41: NOPAT | C41: =C39-C40 -> 817.32 | D41: =D39-D40 -> 899.052 | E41: =E39-E40 -> 988.9572 | F41: =F39-F40 -> 1068.0738 | G41: =G39-G40 -> 1121.4775
B42: Plus: D&A | C42: 400 | D42: 430 | E42: 450 | F42: 455 | G42: 440
B43: Less: Capex | C43: 700 | D43: 650 | E43: 520 | F43: 460 | G43: 430
B44: Change in NWC | C44: ='NWC Schedule'!D19 -> 402.79178 | D44: ='NWC Schedule'!E19 -> 298.24449 | E44: ='NWC Schedule'!F19 -> 320.67947 | F44: ='NWC Schedule'!G19 -> 259.43837 | G44: ='NWC Schedule'!H19 -> 137.81148
B45: Unlevered Free Cash Flow | C45: =C41+C42-C43-C44 -> 114.52822 | D45: =D41+D42-D43-D44 -> 380.80751 | E45: =E41+E42-E43-E44 -> 598.27773 | F45: =F41+F42-F43-F44 -> 803.6354 | G45: =G41+G42-G43-G44 -> 993.66599
B46: Discount Factor | C46: =1/(1+C26)^(C19+0) -> 0.8505761 | D46: =1/(1+C26)^(C19+1) -> 0.7370763 | E46: =1/(1+C26)^(C19+2) -> 0.63872177 | F46: =1/(1+C26)^(C19+3) -> 0.55349155 | G46: =1/(1+C26)^(C19+4) -> 0.47963433
B47: PV of FCF | C47: =C45*C46 -> 97.414966 | D47: =D45*D46 -> 280.68419 | E47: =E45*E46 -> 382.13301 | F47: =F45*F46 -> 444.8054 | G47: =G45*G46 -> 476.59633
B49: Valuation - Perpetuity Growth Method
B50: Sum of PV of FCFs | C50: =SUM(C47:G47) -> 1681.6339
B51: Terminal Value (PGM) | C51: =G45*(1+C13)/(C26-C13) -> 6970.1163
B52: PV of Terminal Value | C52: =C51*G46 -> 3343.1071
B53: Enterprise Value | C53: =C50+C52 -> 5024.741
B54: Equity Value | C54: =C53-C16 -> 7781.041
B55: Implied Share Price (PGM) | C55: =ROUND(C54*1000000/C15,0) -> 853
B57: Valuation - Exit Multiple Method
B58: Sum of PV of FCFs | C58: =C50 -> 1681.6339
B59: Year 5 EBITDA | C59: =G39+G42 -> 2042.1107
B60: Terminal Value (Exit Multiple) | C60: =C59*C14 -> 18378.996
B61: PV of Terminal Value | C61: =C60*G46 -> 8815.1975
B62: Enterprise Value | C62: =C58+C61 -> 10496.831
B63: Equity Value | C63: =C62-C16 -> 13253.131
B64: Implied Share Price (Exit Multiple) | C64: =ROUND(C63*1000000/C15,0) -> 1453
B66: Scenario Input Matrix
C67: Year 1 | D67: Year 2 | E67: Year 3 | F67: Year 4 | G67: Year 5
B68: Revenue Growth (YoY)
B69: Base | C69: 0.12 | D69: 0.1 | E69: 0.1 | F69: 0.08 | G69: 0.05
B70: Upside | C70: 0.18 | D70: 0.16 | E70: 0.14 | F70: 0.12 | G70: 0.1
B71: Management | C71: 0.12 | D71: 0.12 | E71: 0.11 | F71: 0.1 | G71: 0.1
B72: Downside 1 | C72: -0.08 | D72: 0 | E72: 0.02 | F72: 0.02 | G72: 0.02
B73: Downside 2 | C73: -0.2 | D73: -0.05 | E73: 0.03 | F73: 0.03 | G73: 0.03
B75: COGS % of Revenue
B76: Base | C76: 0.63 | D76: 0.63 | E76: 0.63 | F76: 0.63 | G76: 0.63
B77: Upside | C77: 0.58 | D77: 0.58 | E77: 0.58 | F77: 0.58 | G77: 0.58
B78: Management | C78: 0.63 | D78: 0.63 | E78: 0.63 | F78: 0.63 | G78: 0.63
B79: Downside 1 | C79: 0.66 | D79: 0.68 | E79: 0.69 | F79: 0.69 | G79: 0.69
B80: Downside 2 | C80: 0.7 | D80: 0.72 | E80: 0.71 | F80: 0.7 | G80: 0.7
B82: SGA % of Revenue
B83: Base | C83: 0.22 | D83: 0.22 | E83: 0.22 | F83: 0.22 | G83: 0.22
B84: Upside | C84: 0.22 | D84: 0.21 | E84: 0.21 | F84: 0.21 | G84: 0.21
B85: Management | C85: 0.24 | D85: 0.235 | E85: 0.23 | F85: 0.225 | G85: 0.22
B86: Downside 1 | C86: 0.25 | D86: 0.26 | E86: 0.26 | F86: 0.26 | G86: 0.26
B87: Downside 2 | C87: 0.29 | D87: 0.29 | E87: 0.29 | F87: 0.29 | G87: 0.28

Sheet Reverse DCF
B2: Reverse DCF - Tamagawa Holdings (6838.T)
B3: What is the current share price already assuming? Every value below is a live formula off the other sheets.
B5: Block 0: Market-implied enterprise value (live)
B6: Current Share Price (JPY) | C6: ='Executive Summary'!C9 -> 1530
B7: Fully Diluted Shares | C7: ='DCF Model'!C15 -> 9121192
B8: Market Capitalisation (JPY mn) | C8: =C6*C7/1000000 -> 13955.424
B9: Net Debt (JPY mn) | C9: ='DCF Model'!C16 -> -2756.3
B10: Enterprise Value (JPY mn) | C10: =C8+C9 -> 11199.124
B11: WACC (w) | C11: ='DCF Model'!C26 -> 0.1539865
B12: Terminal Growth (g) | C12: ='DCF Model'!C13 -> 0.01
B13: Effective Tax Rate (t) | C13: ='DCF Model'!C6 -> 0.3
B14: Starting Operating Profit OP0 (FY2026/10 guidance actual) | C14: 820
B15: Cycle-peak Operating Profit (Q2 FY26 single x4 actual) | C15: 1022.4
B16: Terminal-year Revenue, active scenario (JPY mn) | C16: ='DCF Model'!G33 -> 10680.738
B17: Base-case DCF Enterprise Value, PGM (JPY mn) | C17: ='DCF Model'!C53 -> 5024.741
B18: Cycle-peak Operating Margin (Q2 FY26 single x4 actual) | C18: 0.151
B19: Gap: market EV less base-case DCF EV (JPY mn) | C19: =C10-C17 -> 6174.3828
B20: Gap per share (JPY) - the part of the price the base case does not explain | C20: =IFERROR(ROUND(C19*1000000/C7,0),"N/A") -> 677
B22: Block A: Required steady-state operating profit, reached IMMEDIATELY (no ramp)
B23: The lowest bar the price can clear: today's EV read as a perpetuity of one steady-state profit, capex = D&A, no NWC build.
B24: Required steady-state NOPAT (JPY mn) | C24: =C10*(C11-C12) -> 1612.5226
B25: Required steady-state Operating Profit (JPY mn) | C25: =IFERROR(C24/(1-C13),"N/A") -> 2303.6038
B26: ... as a multiple of the Q2 FY26 single x4 peak | C26: =IFERROR(C25/C15,"N/A") -> 2.2531336
B27: ... as a multiple of FY2026/10 guidance actual | C27: =IFERROR(C25/C14,"N/A") -> 2.8092729
B28: ... implied OPM on terminal-year revenue | C28: =IFERROR(C25/C16,"N/A") -> 0.21567834
B29: ... revenue needed if margins only reach the cycle peak | C29: =IFERROR(C25/C18,"N/A") -> 15255.654
B32: Block B: Required steady-state operating profit by YEARS-TO-REACH (linear ramp) x WACC
B33: Operating profit ramps linearly from OP0 (C14) to OP* over N years, then grows at g for ever. Column F is the model WACC.
B34: OP* = ( EV/(1-t) - OP0*(A-B) ) / ( B + TVF ). A longer ramp needs a HIGHER steady state, because more years are spent below it.
B36: Years to steady state (N) \ WACC | C36: N | D36: ='DCF Model'!C26-0.02 -> 0.1339865 | E36: ='DCF Model'!C26-0.01 -> 0.1439865 | F36: ='DCF Model'!C26 -> 0.1539865 | G36: ='DCF Model'!C26+0.01 -> 0.1639865 | H36: ='DCF Model'!C26+0.02 -> 0.1739865
B37: B-1 PV weight on the RAMP from OP0 (A - B)
B38: N = 3 years | C38: 3 | D38: =IFERROR((1-(1+D$36)^(-$C38))/D$36-(1+D$36)/(D$36^2*$C38)*(1-($C38+1)/(1+D$36)^$C38+$C38/(1+D$36)^($C38+1)),"N/A") -> 0.84711318 | E38: =IFERROR((1-(1+E$36)^(-$C38))/E$36-(1+E$36)/(E$36^2*$C38)*(1-($C38+1)/(1+E$36)^$C38+$C38/(1+E$36)^($C38+1)),"N/A") -> 0.83746215 | F38: =IFERROR((1-(1+F$36)^(-$C38))/F$36-(1+F$36)/(F$36^2*$C38)*(1-($C38+1)/(1+F$36)^$C38+$C38/(1+F$36)^($C38+1)),"N/A") -> 0.82801698 | G38: =IFERROR((1-(1+G$36)^(-$C38))/G$36-(1+G$36)/(G$36^2*$C38)*(1-($C38+1)/(1+G$36)^$C38+$C38/(1+G$36)^($C38+1)),"N/A") -> 0.81877138 | H38: =IFERROR((1-(1+H$36)^(-$C38))/H$36-(1+H$36)/(H$36^2*$C38)*(1-($C38+1)/(1+H$36)^$C38+$C38/(1+H$36)^($C38+1)),"N/A") -> 0.80971929
B39: N = 5 years | C39: 5 | D39: =IFERROR((1-(1+D$36)^(-$C39))/D$36-(1+D$36)/(D$36^2*$C39)*(1-($C39+1)/(1+D$36)^$C39+$C39/(1+D$36)^($C39+1)),"N/A") -> 1.5673204 | E39: =IFERROR((1-(1+E$36)^(-$C39))/E$36-(1+E$36)/(E$36^2*$C39)*(1-($C39+1)/(1+E$36)^$C39+$C39/(1+E$36)^($C39+1)),"N/A") -> 1.5417274 | F39: =IFERROR((1-(1+F$36)^(-$C39))/F$36-(1+F$36)/(F$36^2*$C39)*(1-($C39+1)/(1+F$36)^$C39+$C39/(1+F$36)^($C39+1)),"N/A") -> 1.516875 | G39: =IFERROR((1-(1+G$36)^(-$C39))/G$36-(1+G$36)/(G$36^2*$C39)*(1-($C39+1)/(1+G$36)^$C39+$C39/(1+G$36)^($C39+1)),"N/A") -> 1.4927337 | H39: =IFERROR((1-(1+H$36)^(-$C39))/H$36-(1+H$36)/(H$36^2*$C39)*(1-($C39+1)/(1+H$36)^$C39+$C39/(1+H$36)^($C39+1)),"N/A") -> 1.4692756
B40: N = 7 years | C40: 7 | D40: =IFERROR((1-(1+D$36)^(-$C40))/D$36-(1+D$36)/(D$36^2*$C40)*(1-($C40+1)/(1+D$36)^$C40+$C40/(1+D$36)^($C40+1)),"N/A") -> 2.1819219 | E40: =IFERROR((1-(1+E$36)^(-$C40))/E$36-(1+E$36)/(E$36^2*$C40)*(1-($C40+1)/(1+E$36)^$C40+$C40/(1+E$36)^($C40+1)),"N/A") -> 2.1365236 | F40: =IFERROR((1-(1+F$36)^(-$C40))/F$36-(1+F$36)/(F$36^2*$C40)*(1-($C40+1)/(1+F$36)^$C40+$C40/(1+F$36)^($C40+1)),"N/A") -> 2.0927618 | G40: =IFERROR((1-(1+G$36)^(-$C40))/G$36-(1+G$36)/(G$36^2*$C40)*(1-($C40+1)/(1+G$36)^$C40+$C40/(1+G$36)^($C40+1)),"N/A") -> 2.0505568 | H40: =IFERROR((1-(1+H$36)^(-$C40))/H$36-(1+H$36)/(H$36^2*$C40)*(1-($C40+1)/(1+H$36)^$C40+$C40/(1+H$36)^($C40+1)),"N/A") -> 2.0098341
B41: N = 10 years | C41: 10 | D41: =IFERROR((1-(1+D$36)^(-$C41))/D$36-(1+D$36)/(D$36^2*$C41)*(1-($C41+1)/(1+D$36)^$C41+$C41/(1+D$36)^($C41+1)),"N/A") -> 2.9432194 | E41: =IFERROR((1-(1+E$36)^(-$C41))/E$36-(1+E$36)/(E$36^2*$C41)*(1-($C41+1)/(1+E$36)^$C41+$C41/(1+E$36)^($C41+1)),"N/A") -> 2.86452 | F41: =IFERROR((1-(1+F$36)^(-$C41))/F$36-(1+F$36)/(F$36^2*$C41)*(1-($C41+1)/(1+F$36)^$C41+$C41/(1+F$36)^($C41+1)),"N/A") -> 2.7894251 | G41: =IFERROR((1-(1+G$36)^(-$C41))/G$36-(1+G$36)/(G$36^2*$C41)*(1-($C41+1)/(1+G$36)^$C41+$C41/(1+G$36)^($C41+1)),"N/A") -> 2.7177155 | H41: =IFERROR((1-(1+H$36)^(-$C41))/H$36-(1+H$36)/(H$36^2*$C41)*(1-($C41+1)/(1+H$36)^$C41+$C41/(1+H$36)^($C41+1)),"N/A") -> 2.6491882
B42: B-2 PV weight on the STEADY STATE OP* (B + terminal factor)
B43: N = 3 years | C43: 3 | D43: =IFERROR((1+D$36)/(D$36^2*$C43)*(1-($C43+1)/(1+D$36)^$C43+$C43/(1+D$36)^($C43+1))+(1+$C$12)/((D$36-$C$12)*(1+D$36)^$C43),"N/A") -> 7.0844362 | E43: =IFERROR((1+E$36)/(E$36^2*$C43)*(1-($C43+1)/(1+E$36)^$C43+$C43/(1+E$36)^($C43+1))+(1+$C$12)/((E$36-$C$12)*(1+E$36)^$C43),"N/A") -> 6.5037065 | F43: =IFERROR((1+F$36)/(F$36^2*$C43)*(1-($C43+1)/(1+F$36)^$C43+$C43/(1+F$36)^($C43+1))+(1+$C$12)/((F$36-$C$12)*(1+F$36)^$C43),"N/A") -> 6.0047424 | G43: =IFERROR((1+G$36)/(G$36^2*$C43)*(1-($C43+1)/(1+G$36)^$C43+$C43/(1+G$36)^($C43+1))+(1+$C$12)/((G$36-$C$12)*(1+G$36)^$C43),"N/A") -> 5.5715812 | H43: =IFERROR((1+H$36)/(H$36^2*$C43)*(1-($C43+1)/(1+H$36)^$C43+$C43/(1+H$36)^($C43+1))+(1+$C$12)/((H$36-$C$12)*(1+H$36)^$C43),"N/A") -> 5.1921553
B44: N = 5 years | C44: 5 | D44: =IFERROR((1+D$36)/(D$36^2*$C44)*(1-($C44+1)/(1+D$36)^$C44+$C44/(1+D$36)^($C44+1))+(1+$C$12)/((D$36-$C$12)*(1+D$36)^$C44),"N/A") -> 6.2601446 | E44: =IFERROR((1+E$36)/(E$36^2*$C44)*(1-($C44+1)/(1+E$36)^$C44+$C44/(1+E$36)^($C44+1))+(1+$C$12)/((E$36-$C$12)*(1+E$36)^$C44),"N/A") -> 5.7060132 | F44: =IFERROR((1+F$36)/(F$36^2*$C44)*(1-($C44+1)/(1+F$36)^$C44+$C44/(1+F$36)^($C44+1))+(1+$C$12)/((F$36-$C$12)*(1+F$36)^$C44),"N/A") -> 5.2315279 | G44: =IFERROR((1+G$36)/(G$36^2*$C44)*(1-($C44+1)/(1+G$36)^$C44+$C44/(1+G$36)^($C44+1))+(1+$C$12)/((G$36-$C$12)*(1+G$36)^$C44),"N/A") -> 4.8210627 | H44: =IFERROR((1+H$36)/(H$36^2*$C44)*(1-($C44+1)/(1+H$36)^$C44+$C44/(1+H$36)^($C44+1))+(1+$C$12)/((H$36-$C$12)*(1+H$36)^$C44),"N/A") -> 4.4628084
B45: N = 7 years | C45: 7 | D45: =IFERROR((1+D$36)/(D$36^2*$C45)*(1-($C45+1)/(1+D$36)^$C45+$C45/(1+D$36)^($C45+1))+(1+$C$12)/((D$36-$C$12)*(1+D$36)^$C45),"N/A") -> 5.5646019 | E45: =IFERROR((1+E$36)/(E$36^2*$C45)*(1-($C45+1)/(1+E$36)^$C45+$C45/(1+E$36)^($C45+1))+(1+$C$12)/((E$36-$C$12)*(1+E$36)^$C45),"N/A") -> 5.0398273 | F45: =IFERROR((1+F$36)/(F$36^2*$C45)*(1-($C45+1)/(1+F$36)^$C45+$C45/(1+F$36)^($C45+1))+(1+$C$12)/((F$36-$C$12)*(1+F$36)^$C45),"N/A") -> 4.5922955 | G45: =IFERROR((1+G$36)/(G$36^2*$C45)*(1-($C45+1)/(1+G$36)^$C45+$C45/(1+G$36)^($C45+1))+(1+$C$12)/((G$36-$C$12)*(1+G$36)^$C45),"N/A") -> 4.2067349 | H45: =IFERROR((1+H$36)/(H$36^2*$C45)*(1-($C45+1)/(1+H$36)^$C45+$C45/(1+H$36)^($C45+1))+(1+$C$12)/((H$36-$C$12)*(1+H$36)^$C45),"N/A") -> 3.8716127
B46: N = 10 years | C46: 10 | D46: =IFERROR((1+D$36)/(D$36^2*$C46)*(1-($C46+1)/(1+D$36)^$C46+$C46/(1+D$36)^($C46+1))+(1+$C$12)/((D$36-$C$12)*(1+D$36)^$C46),"N/A") -> 4.7143495 | E46: =IFERROR((1+E$36)/(E$36^2*$C46)*(1-($C46+1)/(1+E$36)^$C46+$C46/(1+E$36)^($C46+1))+(1+$C$12)/((E$36-$C$12)*(1+E$36)^$C46),"N/A") -> 4.2350401 | F46: =IFERROR((1+F$36)/(F$36^2*$C46)*(1-($C46+1)/(1+F$36)^$C46+$C46/(1+F$36)^($C46+1))+(1+$C$12)/((F$36-$C$12)*(1+F$36)^$C46),"N/A") -> 3.8289272 | G46: =IFERROR((1+G$36)/(G$36^2*$C46)*(1-($C46+1)/(1+G$36)^$C46+$C46/(1+G$36)^($C46+1))+(1+$C$12)/((G$36-$C$12)*(1+G$36)^$C46),"N/A") -> 3.4813141 | H46: =IFERROR((1+H$36)/(H$36^2*$C46)*(1-($C46+1)/(1+H$36)^$C46+$C46/(1+H$36)^($C46+1))+(1+$C$12)/((H$36-$C$12)*(1+H$36)^$C46),"N/A") -> 3.1811228
B47: B-3 REQUIRED steady-state Operating Profit (JPY mn)
B48: N = 3 years | C48: 3 | D48: =IFERROR(($C$10/(1-$C$13)-$C$14*D38)/D43,"N/A") -> 2160.2446 | E48: =IFERROR(($C$10/(1-$C$13)-$C$14*E38)/E43,"N/A") -> 2354.3543 | F48: =IFERROR(($C$10/(1-$C$13)-$C$14*F38)/F43,"N/A") -> 2551.2792 | G48: =IFERROR(($C$10/(1-$C$13)-$C$14*G38)/G43,"N/A") -> 2750.9885 | H48: =IFERROR(($C$10/(1-$C$13)-$C$14*H38)/H43,"N/A") -> 2953.4514
B49: N = 5 years | C49: 5 | D49: =IFERROR(($C$10/(1-$C$13)-$C$14*D39)/D44,"N/A") -> 2350.3523 | E49: =IFERROR(($C$10/(1-$C$13)-$C$14*E39)/E44,"N/A") -> 2582.2814 | F49: =IFERROR(($C$10/(1-$C$13)-$C$14*F39)/F44,"N/A") -> 2820.3827 | G49: =IFERROR(($C$10/(1-$C$13)-$C$14*G39)/G44,"N/A") -> 3064.6162 | H49: =IFERROR(($C$10/(1-$C$13)-$C$14*H39)/H44,"N/A") -> 3314.94
B50: N = 7 years | C50: 7 | D50: =IFERROR(($C$10/(1-$C$13)-$C$14*D40)/D45,"N/A") -> 2553.565 | E50: =IFERROR(($C$10/(1-$C$13)-$C$14*E40)/E45,"N/A") -> 2826.8427 | F50: =IFERROR(($C$10/(1-$C$13)-$C$14*F40)/F45,"N/A") -> 3110.1404 | G50: =IFERROR(($C$10/(1-$C$13)-$C$14*G40)/G45,"N/A") -> 3403.4214 | H50: =IFERROR(($C$10/(1-$C$13)-$C$14*H40)/H45,"N/A") -> 3706.6425
B51: N = 10 years | C51: 10 | D51: =IFERROR(($C$10/(1-$C$13)-$C$14*D41)/D46,"N/A") -> 2881.6931 | E51: =IFERROR(($C$10/(1-$C$13)-$C$14*E41)/E46,"N/A") -> 3223.0726 | F51: =IFERROR(($C$10/(1-$C$13)-$C$14*F41)/F46,"N/A") -> 3581.0082 | G51: =IFERROR(($C$10/(1-$C$13)-$C$14*G41)/G46,"N/A") -> 3955.4666 | H51: =IFERROR(($C$10/(1-$C$13)-$C$14*H41)/H46,"N/A") -> 4346.3942
B52: B-4 ... as a multiple of the Q2 FY26 single x4 peak operating profit
B53: N = 3 years | C53: 3 | D53: =IFERROR(D48/$C$15,"N/A") -> 2.1129153 | E53: =IFERROR(E48/$C$15,"N/A") -> 2.3027722 | F53: =IFERROR(F48/$C$15,"N/A") -> 2.4953826 | G53: =IFERROR(G48/$C$15,"N/A") -> 2.6907164 | H53: =IFERROR(H48/$C$15,"N/A") -> 2.8887436
B54: N = 5 years | C54: 5 | D54: =IFERROR(D49/$C$15,"N/A") -> 2.2988579 | E54: =IFERROR(E49/$C$15,"N/A") -> 2.5257056 | F54: =IFERROR(F49/$C$15,"N/A") -> 2.7585903 | G54: =IFERROR(G49/$C$15,"N/A") -> 2.9974728 | H54: =IFERROR(H49/$C$15,"N/A") -> 3.2423122
B55: N = 7 years | C55: 7 | D55: =IFERROR(D50/$C$15,"N/A") -> 2.4976183 | E55: =IFERROR(E50/$C$15,"N/A") -> 2.7649087 | F55: =IFERROR(F50/$C$15,"N/A") -> 3.0419996 | G55: =IFERROR(G50/$C$15,"N/A") -> 3.328855 | H55: =IFERROR(H50/$C$15,"N/A") -> 3.6254328
B56: N = 10 years | C56: 10 | D56: =IFERROR(D51/$C$15,"N/A") -> 2.8185574 | E56: =IFERROR(E51/$C$15,"N/A") -> 3.1524575 | F56: =IFERROR(F51/$C$15,"N/A") -> 3.5025511 | G56: =IFERROR(G51/$C$15,"N/A") -> 3.8688054 | H56: =IFERROR(H51/$C$15,"N/A") -> 4.251168
B58: Block C: Decomposing the required profit into revenue x margin (N = 5 years, model WACC)
B59: The revenue the company must run at, for a given steady-state operating margin, to earn the Block B-3 profit.
B60: Required steady-state Operating Profit (N=5, model WACC) | C60: =F49 -> 2820.3827
B62: Assumed steady-state OPM | C62: Required Revenue | D62: x base-year revenue
B63: 0.05 | C63: =IFERROR($C$60/B63,"N/A") -> 56407.654 | D63: =IFERROR(C63/'DCF Model'!C17,"N/A") -> 8.1162091
B64: 0.1 | C64: =IFERROR($C$60/B64,"N/A") -> 28203.827 | D64: =IFERROR(C64/'DCF Model'!C17,"N/A") -> 4.0581046
B65: 0.12 | C65: =IFERROR($C$60/B65,"N/A") -> 23503.189 | D65: =IFERROR(C65/'DCF Model'!C17,"N/A") -> 3.3817538
B66: cycle-peak OPM (Q2 FY26 single x4) | C66: =IFERROR($C$60/$C$18,"N/A") -> 18678.031 | D66: =IFERROR(C66/'DCF Model'!C17,"N/A") -> 2.6874865
B67: 0.2 | C67: =IFERROR($C$60/B67,"N/A") -> 14101.913 | D67: =IFERROR(C67/'DCF Model'!C17,"N/A") -> 2.0290523
B69: Block D: The same question expressed as multiples
B70: Current EV / latest-FY EBITDA (actual) | C70: =IFERROR(C10/'Comps Analysis'!G5,"N/A") -> 6.9430401
B71: Current EV / latest-FY Revenue (actual) | C71: =IFERROR(C10/'Comps Analysis'!F5,"N/A") -> 1.6113847
B72: EV / EBITDA if the Block A profit were already earned | C72: =IFERROR(C10/(C25+'DCF Model'!G42),"N/A") -> 4.0819028
B73: EV / EBITDA if the Block B-3 (N=5) profit were already earned | C73: =IFERROR(C10/(C60+'DCF Model'!G42),"N/A") -> 3.4349108
B74: Peer median EV / EBITDA (statistics rows) | C74: =IFERROR('Comps Analysis'!D16,"N/A") -> 18.932203
B75: Rows 3-4 answer: what multiple would today's EV be paying IF the company already earned the profit the price requires?
B77: Block F: The one-line answer
B78: ="At "&TEXT(C6,"#,##0")&" yen the market is paying for a steady-state operating profit of "&TEXT(F49,"#,##0")&" mn JPY - "&TEXT(F54,"0.00")&"x the Q2 FY26 single x4 cycle peak of "&TEXT(C15,"#,##0")&" mn - reached in 5 years and sustained for ever, against "&TEXT(C14,"#,##0")&" mn actually earned in FY2026/10 guidance." -> At 1,530 yen the market is paying for a steady-state operating profit of 2,820 mn JPY - 2.76x the Q2 FY26 single x4 cycle peak of 1,022 mn - reached in 5 years and sustained for ever, against 820 mn actually earned in FY2026/10 guidance.
B79: ="Even with no ramp at all (Block A) the price needs "&TEXT(C25,"#,##0")&" mn, or "&TEXT(C26,"0.00")&"x the peak. The base case supports an EV of only "&TEXT(C17,"#,##0")&" mn, leaving "&TEXT(C20,"#,##0")&" yen per share of the current price unexplained by mid-cycle economics." -> Even with no ramp at all (Block A) the price needs 2,304 mn, or 2.25x the peak. The base case supports an EV of only 5,025 mn, leaving 677 yen per share of the current price unexplained by mid-cycle economics.

Sheet NWC Schedule
B2: NWC Schedule - Tamagawa Holdings
B4: Working Capital Drivers (Days) | C4: Base Year | D4: FY2027(E) | E4: FY2028(E) | F4: FY2029(E) | G4: FY2030(E) | H4: FY2031(E)
B5: DSO (Days Sales Outstanding) | C5: =C12/C9*365 -> 80.762158 | D5: =CHOOSE('DCF Model'!$D$27,D25,D26,D27,D28,D29) -> 80 | E5: =CHOOSE('DCF Model'!$D$27,E25,E26,E27,E28,E29) -> 80 | F5: =CHOOSE('DCF Model'!$D$27,F25,F26,F27,F28,F29) -> 80 | G5: =CHOOSE('DCF Model'!$D$27,G25,G26,G27,G28,G29) -> 80 | H5: =CHOOSE('DCF Model'!$D$27,H25,H26,H27,H28,H29) -> 80
B6: DIH (Days Inventory Held) | C6: =C13/C10*365 -> 229.46245 | D6: =CHOOSE('DCF Model'!$D$27,D32,D33,D34,D35,D36) -> 220 | E6: =CHOOSE('DCF Model'!$D$27,E32,E33,E34,E35,E36) -> 215 | F6: =CHOOSE('DCF Model'!$D$27,F32,F33,F34,F35,F36) -> 210 | G6: =CHOOSE('DCF Model'!$D$27,G32,G33,G34,G35,G36) -> 205 | H6: =CHOOSE('DCF Model'!$D$27,H32,H33,H34,H35,H36) -> 200
B7: DPO (Days Payable Outstanding) | C7: =C15/C10*365 -> 70.679964 | D7: =CHOOSE('DCF Model'!$D$27,D39,D40,D41,D42,D43) -> 70 | E7: =CHOOSE('DCF Model'!$D$27,E39,E40,E41,E42,E43) -> 70 | F7: =CHOOSE('DCF Model'!$D$27,F39,F40,F41,F42,F43) -> 70 | G7: =CHOOSE('DCF Model'!$D$27,G39,G40,G41,G42,G43) -> 70 | H7: =CHOOSE('DCF Model'!$D$27,H39,H40,H41,H42,H43) -> 70
B8: P&L Reference (JPY mn)
B9: Revenue | C9: 6950 | D9: ='DCF Model'!C33 -> 7784 | E9: ='DCF Model'!D33 -> 8562.4 | F9: ='DCF Model'!E33 -> 9418.64 | G9: ='DCF Model'!F33 -> 10172.131 | H9: ='DCF Model'!G33 -> 10680.738
B10: COGS | C10: 4093.6 | D10: ='DCF Model'!C34 -> 4903.92 | E10: ='DCF Model'!D34 -> 5394.312 | F10: ='DCF Model'!E34 -> 5933.7432 | G10: ='DCF Model'!F34 -> 6408.4427 | H10: ='DCF Model'!G34 -> 6728.8648
B11: Working Capital Items (JPY mn)
B12: Accounts Receivable | C12: 1537.8 | D12: =D9*D5/365 -> 1706.0822 | E12: =E9*E5/365 -> 1876.6904 | F12: =F9*F5/365 -> 2064.3595 | G12: =G9*G5/365 -> 2229.5082 | H12: =H9*H5/365 -> 2340.9836
B13: Inventory | C13: 2573.5 | D13: =D10*D6/365 -> 2955.7874 | E13: =E10*E6/365 -> 3177.4715 | F13: =F10*F6/365 -> 3413.9344 | G13: =G10*G6/365 -> 3599.2623 | H13: =H10*H6/365 -> 3687.0492
B14: Current Assets (AR + Inv) | C14: =C12+C13 -> 4111.3 | D14: =D12+D13 -> 4661.8696 | E14: =E12+E13 -> 5054.1619 | F14: =F12+F13 -> 5478.2939 | G14: =G12+G13 -> 5828.7705 | H14: =H12+H13 -> 6028.0328
B15: Accounts Payable | C15: 792.7 | D15: =D10*D7/365 -> 940.47781 | E15: =E10*E7/365 -> 1034.5256 | F15: =F10*F7/365 -> 1137.9781 | G15: =G10*G7/365 -> 1229.0164 | H15: =H10*H7/365 -> 1290.4672
B16: Current Liabilities (AP) | C16: =C15 -> 792.7 | D16: =D15 -> 940.47781 | E16: =E15 -> 1034.5256 | F16: =F15 -> 1137.9781 | G16: =G15 -> 1229.0164 | H16: =H15 -> 1290.4672
B17: Net Working Capital (JPY mn)
B18: Net Working Capital | C18: =C14-C16 -> 3318.6 | D18: =D14-D16 -> 3721.3918 | E18: =E14-E16 -> 4019.6363 | F18: =F14-F16 -> 4340.3157 | G18: =G14-G16 -> 4599.7541 | H18: =H14-H16 -> 4737.5656
B19: Change in NWC | C19: n/a | D19: =D18-C18 -> 402.79178 | E19: =E18-D18 -> 298.24449 | F19: =F18-E18 -> 320.67947 | G19: =G18-F18 -> 259.43837 | H19: =H18-G18 -> 137.81148
B22: Scenario Input Matrix (Working Capital Days)
D23: FY2027(E) | E23: FY2028(E) | F23: FY2029(E) | G23: FY2030(E) | H23: FY2031(E)
B24: DSO (Days)
B25: Base | D25: 80 | E25: 80 | F25: 80 | G25: 80 | H25: 80
B26: Upside | D26: 78 | E26: 76 | F26: 75 | G26: 75 | H26: 75
B27: Management | D27: 80 | E27: 80 | F27: 80 | G27: 80 | H27: 80
B28: Downside 1 | D28: 85 | E28: 85 | F28: 85 | G28: 85 | H28: 85
B29: Downside 2 | D29: 95 | E29: 95 | F29: 95 | G29: 95 | H29: 95
B31: DIH (Days)
B32: Base | D32: 220 | E32: 215 | F32: 210 | G32: 205 | H32: 200
B33: Upside | D33: 210 | E33: 200 | F33: 190 | G33: 185 | H33: 180
B34: Management | D34: 220 | E34: 215 | F34: 210 | G34: 205 | H34: 200
B35: Downside 1 | D35: 240 | E35: 240 | F35: 240 | G35: 240 | H35: 240
B36: Downside 2 | D36: 260 | E36: 260 | F36: 260 | G36: 260 | H36: 260
B38: DPO (Days)
B39: Base | D39: 70 | E39: 70 | F39: 70 | G39: 70 | H39: 70
B40: Upside | D40: 72 | E40: 72 | F40: 72 | G40: 72 | H40: 72
B41: Management | D41: 70 | E41: 70 | F41: 70 | G41: 70 | H41: 70
B42: Downside 1 | D42: 65 | E42: 65 | F42: 65 | G42: 65 | H42: 65
B43: Downside 2 | D43: 60 | E43: 60 | F43: 60 | G43: 60 | H43: 60

Sheet Comps Analysis
B2: Comparable Company Analysis
B3: Peer prices as of 2026-09-14 (Mkt Cap / EV of peer rows are static CSV values; the subject row is live-linked to Executive Summary)
B4: Company | C4: Ticker | D4: Mkt Cap (JPY mn) | E4: EV (JPY mn) | F4: Revenue (JPY mn) | G4: EBITDA (JPY mn) | H4: Op Income (JPY mn) | I4: Net Income (JPY mn) | J4: EV/EBITDA | K4: EV/Revenue | L4: PER | M4: PBR | N4: Op Margin | O4: ROE | P4: Book Value (JPY mn) | Q4: Note
B5: Tamagawa HD (6838) [subject] | C5: 6838.T | D5: ='Executive Summary'!C9*C23/1000000 -> 13955.424 | E5: =D5+C24 -> 11199.124 | F5: 6950 | G5: 1613 | H5: 1236 | I5: 810 | J5: =IFERROR(E5/G5,"") -> 6.9430401 | K5: =IFERROR(E5/F5,"") -> 1.6113847 | L5: =IFERROR(D5/I5,"") -> 17.228918 | M5: =IFERROR(D5/P5,"") -> 1.489055 | N5: =IFERROR(H5/F5,"") -> 0.17784173 | O5: =IFERROR(I5/P5,"") -> 0.086427657 | P5: 9372
B6: Tokyo Keiki (7721) | C6: 7721.T | D6: 115949 | E6: 134348 | F6: 61186 | G6: 7093 | H6: 5362 | I6: 4005 | J6: =IFERROR(E6/G6,"") -> 18.940928 | K6: =IFERROR(E6/F6,"") -> 2.195731 | L6: =IFERROR(D6/I6,"") -> 28.951061 | M6: =IFERROR(D6/P6,"") -> 2.54721 | N6: =IFERROR(H6/F6,"") -> 0.087634426 | O6: =IFERROR(I6/P6,"") -> 0.087983304 | P6: 45520
B7: Nippon Avionics (6946) | C7: 6946.T | D7: 108636 | E7: 118102 | F7: 29194 | G7: 5994 | H7: 5515 | I7: 3820 | J7: =IFERROR(E7/G7,"") -> 19.70337 | K7: =IFERROR(E7/F7,"") -> 4.0454203 | L7: =IFERROR(D7/I7,"") -> 28.438743 | M7: =IFERROR(D7/P7,"") -> 6.7459016 | N7: =IFERROR(H7/F7,"") -> 0.18890868 | O7: =IFERROR(I7/P7,"") -> 0.23720815 | P7: 16104
B8: RION (6823) | C8: 6823.T | D8: 39353 | E8: 30790 | F8: 28502 | G8: 5693 | H8: 4362 | I8: 3346 | J8: =IFERROR(E8/G8,"") -> 5.4083963 | K8: =IFERROR(E8/F8,"") -> 1.0802751 | L8: =IFERROR(D8/I8,"") -> 11.761207 | M8: =IFERROR(D8/P8,"") -> 1.1307359 | N8: =IFERROR(H8/F8,"") -> 0.15304189 | O8: =IFERROR(I8/P8,"") -> 0.096141137 | P8: 34803
B9: Ikegami Tsushinki (6771) | C9: 6771.T | D9: 4809 | E9: 10187 | F9: 21329 | G9: 868 | H9: 407 | I9: 376 | J9: =IFERROR(E9/G9,"") -> 11.736175 | K9: =IFERROR(E9/F9,"") -> 0.47761264 | L9: =IFERROR(D9/I9,"") -> 12.789894 | M9: =IFERROR(D9/P9,"") -> 0.33624668 | N9: =IFERROR(H9/F9,"") -> 0.019082001 | O9: =IFERROR(I9/P9,"") -> 0.026290029 | P9: 14302
B10: Artiza Networks (6778) | C10: 6778.T | D10: 5900 | E10: 4468 | F10: 2681 | G10: 236 | H10: 116 | I10: 133 | J10: =IFERROR(E10/G10,"") -> 18.932203 | K10: =IFERROR(E10/F10,"") -> 1.6665423 | L10: =IFERROR(D10/I10,"") -> 44.360902 | M10: =IFERROR(D10/P10,"") -> 0.89925316 | N10: =IFERROR(H10/F10,"") -> 0.043267438 | O10: =IFERROR(I10/P10,"") -> 0.0202713 | P10: 6561
B14: Statistics
B15: 25th Percentile | D15: =PERCENTILE(J6:J10,0.25) -> 11.736175 | E15: =PERCENTILE(K6:K10,0.25) -> 1.0802751 | F15: =PERCENTILE(L6:L10,0.25) -> 12.789894 | G15: =PERCENTILE(M6:M10,0.25) -> 0.89925316 | H15: =PERCENTILE(N6:N10,0.25) -> 0.043267438 | I15: =PERCENTILE(O6:O10,0.25) -> 0.026290029
B16: Median (50th) | D16: =MEDIAN(J6:J10) -> 18.932203 | E16: =MEDIAN(K6:K10) -> 1.6665423 | F16: =MEDIAN(L6:L10) -> 28.438743 | G16: =MEDIAN(M6:M10) -> 1.1307359 | H16: =MEDIAN(N6:N10) -> 0.087634426 | I16: =MEDIAN(O6:O10) -> 0.087983304
B17: 75th Percentile | D17: =PERCENTILE(J6:J10,0.75) -> 18.940928 | E17: =PERCENTILE(K6:K10,0.75) -> 2.195731 | F17: =PERCENTILE(L6:L10,0.75) -> 28.951061 | G17: =PERCENTILE(M6:M10,0.75) -> 2.54721 | H17: =PERCENTILE(N6:N10,0.75) -> 0.15304189 | I17: =PERCENTILE(O6:O10,0.75) -> 0.096141137
B19: Implied Valuation for Tamagawa Holdings
B20: Tamagawa Holdings Financials
B21: EBITDA (JPY mn) | C21: 1613
B22: Net Income (JPY mn) | C22: 810
B23: Shares Outstanding | C23: 9121192
B24: Net Debt (JPY mn) | C24: -2756.3
B26: Implied Share Price (Median Multiples)
B27: Via EV/EBITDA (Median) | C27: =ROUND((C21*D16-C24)*1000000/C23,0) -> 3650
B28: Via PER (Median) | C28: =ROUND(C22*F16*1000000/C23,0) -> 2525
B29: Net Income normalised (FY2026/10E pretax 1,158 ex Addvalue FV gain x normalised tax C6) [参考・Target不算入] | C29: =ROUND((1157.6+0)*(1-'DCF Model'!C6),0) -> 810 | D29: 会社予想の親会社帰属当期利益1,835は Addvalue株の評価益(税効果控除後)を含み PER の分母として不適。FY2026/10E 推定営業利益1,236 − 金融費用純額78.4 = 1,157.6 に DCF Model!C6 の正常化税率30%を適用。H1実績でも中間利益1,832.4の約73%が評価益由来(正常化純利益499、Segment Bridge 表4)。FY2025/10(J-GAAP)の特別利益132.1(投資有価証券売却益124.4・固定資産売却益7.7)も正常化で除外。
B30: Via PER (Median, normalized NI) [参考・Target不算入] | C30: =ROUND(C29*F16*1000000/C23,0) -> 2525

Sheet Sensitivity Analysis
B2: Sensitivity Analysis
B3: Current WACC: | C3: ='DCF Model'!C26 -> 0.1539865 | E3: Terminal g: | F3: ='DCF Model'!C13 -> 0.01 | H3: Exit Multiple: | I3: ='DCF Model'!C14 -> 9
B5: Table 1: WACC vs Terminal Growth Rate (PGM - Implied Share Price, JPY)
B6: WACC \ Terminal g | C6: =$F$3-0.0075 -> 0.0025 | D6: =$F$3-0.005 -> 0.005 | E6: =$F$3-0.0025 -> 0.0075 | F6: =$F$3 -> 0.01 | G6: =$F$3+0.0025 -> 0.0125 | H6: =$F$3+0.005 -> 0.015 | I6: =$F$3+0.0075 -> 0.0175
B7: =$C$3-0.015 -> 0.1389865 | C7: =IFERROR(ROUND(('DCF Model'!C45/(1+$B7)^('DCF Model'!C19+0)+'DCF Model'!D45/(1+$B7)^('DCF Model'!C19+1)+'DCF Model'!E45/(1+$B7)^('DCF Model'!C19+2)+'DCF Model'!F45/(1+$B7)^('DCF Model'!C19+3)+'DCF Model'!G45/(1+$B7)^('DCF Model'!C19+4)+'DCF Model'!G45*(1+C$6)/($B7-C$6)/(1+$B7)^('DCF Model'!C19+4)-'DCF Model'!C16)*1000000/'DCF Model'!C15,0),"") -> 906 | D7: =IFERROR(ROUND(('DCF Model'!C45/(1+$B7)^('DCF Model'!C19+0)+'DCF Model'!D45/(1+$B7)^('DCF Model'!C19+1)+'DCF Model'!E45/(1+$B7)^('DCF Model'!C19+2)+'DCF Model'!F45/(1+$B7)^('DCF Model'!C19+3)+'DCF Model'!G45/(1+$B7)^('DCF Model'!C19+4)+'DCF Model'!G45*(1+D$6)/($B7-D$6)/(1+$B7)^('DCF Model'!C19+4)-'DCF Model'!C16)*1000000/'DCF Model'!C15,0),"") -> 915 | E7: =IFERROR(ROUND(('DCF Model'!C45/(1+$B7)^('DCF Model'!C19+0)+'DCF Model'!D45/(1+$B7)^('DCF Model'!C19+1)+'DCF Model'!E45/(1+$B7)^('DCF Model'!C19+2)+'DCF Model'!F45/(1+$B7)^('DCF Model'!C19+3)+'DCF Model'!G45/(1+$B7)^('DCF Model'!C19+4)+'DCF Model'!G45*(1+E$6)/($B7-E$6)/(1+$B7)^('DCF Model'!C19+4)-'DCF Model'!C16)*1000000/'DCF Model'!C15,0),"") -> 924 | F7: =IFERROR(ROUND(('DCF Model'!C45/(1+$B7)^('DCF Model'!C19+0)+'DCF Model'!D45/(1+$B7)^('DCF Model'!C19+1)+'DCF Model'!E45/(1+$B7)^('DCF Model'!C19+2)+'DCF Model'!F45/(1+$B7)^('DCF Model'!C19+3)+'DCF Model'!G45/(1+$B7)^('DCF Model'!C19+4)+'DCF Model'!G45*(1+F$6)/($B7-F$6)/(1+$B7)^('DCF Model'!C19+4)-'DCF Model'!C16)*1000000/'DCF Model'!C15,0),"") -> 933 | G7: =IFERROR(ROUND(('DCF Model'!C45/(1+$B7)^('DCF Model'!C19+0)+'DCF Model'!D45/(1+$B7)^('DCF Model'!C19+1)+'DCF Model'!E45/(1+$B7)^('DCF Model'!C19+2)+'DCF Model'!F45/(1+$B7)^('DCF Model'!C19+3)+'DCF Model'!G45/(1+$B7)^('DCF Model'!C19+4)+'DCF Model'!G45*(1+G$6)/($B7-G$6)/(1+$B7)^('DCF Model'!C19+4)-'DCF Model'!C16)*1000000/'DCF Model'!C15,0),"") -> 943 | H7: =IFERROR(ROUND(('DCF Model'!C45/(1+$B7)^('DCF Model'!C19+0)+'DCF Model'!D45/(1+$B7)^('DCF Model'!C19+1)+'DCF Model'!E45/(1+$B7)^('DCF Model'!C19+2)+'DCF Model'!F45/(1+$B7)^('DCF Model'!C19+3)+'DCF Model'!G45/(1+$B7)^('DCF Model'!C19+4)+'DCF Model'!G45*(1+H$6)/($B7-H$6)/(1+$B7)^('DCF Model'!C19+4)-'DCF Model'!C16)*1000000/'DCF Model'!C15,0),"") -> 953 | I7: =IFERROR(ROUND(('DCF Model'!C45/(1+$B7)^('DCF Model'!C19+0)+'DCF Model'!D45/(1+$B7)^('DCF Model'!C19+1)+'DCF Model'!E45/(1+$B7)^('DCF Model'!C19+2)+'DCF Model'!F45/(1+$B7)^('DCF Model'!C19+3)+'DCF Model'!G45/(1+$B7)^('DCF Model'!C19+4)+'DCF Model'!G45*(1+I$6)/($B7-I$6)/(1+$B7)^('DCF Model'!C19+4)-'DCF Model'!C16)*1000000/'DCF Model'!C15,0),"") -> 964
B8: =$C$3-0.01 -> 0.1439865 | C8: =IFERROR(ROUND(('DCF Model'!C45/(1+$B8)^('DCF Model'!C19+0)+'DCF Model'!D45/(1+$B8)^('DCF Model'!C19+1)+'DCF Model'!E45/(1+$B8)^('DCF Model'!C19+2)+'DCF Model'!F45/(1+$B8)^('DCF Model'!C19+3)+'DCF Model'!G45/(1+$B8)^('DCF Model'!C19+4)+'DCF Model'!G45*(1+C$6)/($B8-C$6)/(1+$B8)^('DCF Model'!C19+4)-'DCF Model'!C16)*1000000/'DCF Model'!C15,0),"") -> 880 | D8: =IFERROR(ROUND(('DCF Model'!C45/(1+$B8)^('DCF Model'!C19+0)+'DCF Model'!D45/(1+$B8)^('DCF Model'!C19+1)+'DCF Model'!E45/(1+$B8)^('DCF Model'!C19+2)+'DCF Model'!F45/(1+$B8)^('DCF Model'!C19+3)+'DCF Model'!G45/(1+$B8)^('DCF Model'!C19+4)+'DCF Model'!G45*(1+D$6)/($B8-D$6)/(1+$B8)^('DCF Model'!C19+4)-'DCF Model'!C16)*1000000/'DCF Model'!C15,0),"") -> 888 | E8: =IFERROR(ROUND(('DCF Model'!C45/(1+$B8)^('DCF Model'!C19+0)+'DCF Model'!D45/(1+$B8)^('DCF Model'!C19+1)+'DCF Model'!E45/(1+$B8)^('DCF Model'!C19+2)+'DCF Model'!F45/(1+$B8)^('DCF Model'!C19+3)+'DCF Model'!G45/(1+$B8)^('DCF Model'!C19+4)+'DCF Model'!G45*(1+E$6)/($B8-E$6)/(1+$B8)^('DCF Model'!C19+4)-'DCF Model'!C16)*1000000/'DCF Model'!C15,0),"") -> 896 | F8: =IFERROR(ROUND(('DCF Model'!C45/(1+$B8)^('DCF Model'!C19+0)+'DCF Model'!D45/(1+$B8)^('DCF Model'!C19+1)+'DCF Model'!E45/(1+$B8)^('DCF Model'!C19+2)+'DCF Model'!F45/(1+$B8)^('DCF Model'!C19+3)+'DCF Model'!G45/(1+$B8)^('DCF Model'!C19+4)+'DCF Model'!G45*(1+F$6)/($B8-F$6)/(1+$B8)^('DCF Model'!C19+4)-'DCF Model'!C16)*1000000/'DCF Model'!C15,0),"") -> 904 | G8: =IFERROR(ROUND(('DCF Model'!C45/(1+$B8)^('DCF Model'!C19+0)+'DCF Model'!D45/(1+$B8)^('DCF Model'!C19+1)+'DCF Model'!E45/(1+$B8)^('DCF Model'!C19+2)+'DCF Model'!F45/(1+$B8)^('DCF Model'!C19+3)+'DCF Model'!G45/(1+$B8)^('DCF Model'!C19+4)+'DCF Model'!G45*(1+G$6)/($B8-G$6)/(1+$B8)^('DCF Model'!C19+4)-'DCF Model'!C16)*1000000/'DCF Model'!C15,0),"") -> 913 | H8: =IFERROR(ROUND(('DCF Model'!C45/(1+$B8)^('DCF Model'!C19+0)+'DCF Model'!D45/(1+$B8)^('DCF Model'!C19+1)+'DCF Model'!E45/(1+$B8)^('DCF Model'!C19+2)+'DCF Model'!F45/(1+$B8)^('DCF Model'!C19+3)+'DCF Model'!G45/(1+$B8)^('DCF Model'!C19+4)+'DCF Model'!G45*(1+H$6)/($B8-H$6)/(1+$B8)^('DCF Model'!C19+4)-'DCF Model'!C16)*1000000/'DCF Model'!C15,0),"") -> 923 | I8: =IFERROR(ROUND(('DCF Model'!C45/(1+$B8)^('DCF Model'!C19+0)+'DCF Model'!D45/(1+$B8)^('DCF Model'!C19+1)+'DCF Model'!E45/(1+$B8)^('DCF Model'!C19+2)+'DCF Model'!F45/(1+$B8)^('DCF Model'!C19+3)+'DCF Model'!G45/(1+$B8)^('DCF Model'!C19+4)+'DCF Model'!G45*(1+I$6)/($B8-I$6)/(1+$B8)^('DCF Model'!C19+4)-'DCF Model'!C16)*1000000/'DCF Model'!C15,0),"") -> 932
B9: =$C$3-0.005 -> 0.1489865 | C9: =IFERROR(ROUND(('DCF Model'!C45/(1+$B9)^('DCF Model'!C19+0)+'DCF Model'!D45/(1+$B9)^('DCF Model'!C19+1)+'DCF Model'!E45/(1+$B9)^('DCF Model'!C19+2)+'DCF Model'!F45/(1+$B9)^('DCF Model'!C19+3)+'DCF Model'!G45/(1+$B9)^('DCF Model'!C19+4)+'DCF Model'!G45*(1+C$6)/($B9-C$6)/(1+$B9)^('DCF Model'!C19+4)-'DCF Model'!C16)*1000000/'DCF Model'!C15,0),"") -> 855 | D9: =IFERROR(ROUND(('DCF Model'!C45/(1+$B9)^('DCF Model'!C19+0)+'DCF Model'!D45/(1+$B9)^('DCF Model'!C19+1)+'DCF Model'!E45/(1+$B9)^('DCF Model'!C19+2)+'DCF Model'!F45/(1+$B9)^('DCF Model'!C19+3)+'DCF Model'!G45/(1+$B9)^('DCF Model'!C19+4)+'DCF Model'!G45*(1+D$6)/($B9-D$6)/(1+$B9)^('DCF Model'!C19+4)-'DCF Model'!C16)*1000000/'DCF Model'!C15,0),"") -> 862 | E9: =IFERROR(ROUND(('DCF Model'!C45/(1+$B9)^('DCF Model'!C19+0)+'DCF Model'!D45/(1+$B9)^('DCF Model'!C19+1)+'DCF Model'!E45/(1+$B9)^('DCF Model'!C19+2)+'DCF Model'!F45/(1+$B9)^('DCF Model'!C19+3)+'DCF Model'!G45/(1+$B9)^('DCF Model'!C19+4)+'DCF Model'!G45*(1+E$6)/($B9-E$6)/(1+$B9)^('DCF Model'!C19+4)-'DCF Model'!C16)*1000000/'DCF Model'!C15,0),"") -> 870 | F9: =IFERROR(ROUND(('DCF Model'!C45/(1+$B9)^('DCF Model'!C19+0)+'DCF Model'!D45/(1+$B9)^('DCF Model'!C19+1)+'DCF Model'!E45/(1+$B9)^('DCF Model'!C19+2)+'DCF Model'!F45/(1+$B9)^('DCF Model'!C19+3)+'DCF Model'!G45/(1+$B9)^('DCF Model'!C19+4)+'DCF Model'!G45*(1+F$6)/($B9-F$6)/(1+$B9)^('DCF Model'!C19+4)-'DCF Model'!C16)*1000000/'DCF Model'!C15,0),"") -> 878 | G9: =IFERROR(ROUND(('DCF Model'!C45/(1+$B9)^('DCF Model'!C19+0)+'DCF Model'!D45/(1+$B9)^('DCF Model'!C19+1)+'DCF Model'!E45/(1+$B9)^('DCF Model'!C19+2)+'DCF Model'!F45/(1+$B9)^('DCF Model'!C19+3)+'DCF Model'!G45/(1+$B9)^('DCF Model'!C19+4)+'DCF Model'!G45*(1+G$6)/($B9-G$6)/(1+$B9)^('DCF Model'!C19+4)-'DCF Model'!C16)*1000000/'DCF Model'!C15,0),"") -> 886 | H9: =IFERROR(ROUND(('DCF Model'!C45/(1+$B9)^('DCF Model'!C19+0)+'DCF Model'!D45/(1+$B9)^('DCF Model'!C19+1)+'DCF Model'!E45/(1+$B9)^('DCF Model'!C19+2)+'DCF Model'!F45/(1+$B9)^('DCF Model'!C19+3)+'DCF Model'!G45/(1+$B9)^('DCF Model'!C19+4)+'DCF Model'!G45*(1+H$6)/($B9-H$6)/(1+$B9)^('DCF Model'!C19+4)-'DCF Model'!C16)*1000000/'DCF Model'!C15,0),"") -> 894 | I9: =IFERROR(ROUND(('DCF Model'!C45/(1+$B9)^('DCF Model'!C19+0)+'DCF Model'!D45/(1+$B9)^('DCF Model'!C19+1)+'DCF Model'!E45/(1+$B9)^('DCF Model'!C19+2)+'DCF Model'!F45/(1+$B9)^('DCF Model'!C19+3)+'DCF Model'!G45/(1+$B9)^('DCF Model'!C19+4)+'DCF Model'!G45*(1+I$6)/($B9-I$6)/(1+$B9)^('DCF Model'!C19+4)-'DCF Model'!C16)*1000000/'DCF Model'!C15,0),"") -> 903
B10: =$C$3 -> 0.1539865 | C10: =IFERROR(ROUND(('DCF Model'!C45/(1+$B10)^('DCF Model'!C19+0)+'DCF Model'!D45/(1+$B10)^('DCF Model'!C19+1)+'DCF Model'!E45/(1+$B10)^('DCF Model'!C19+2)+'DCF Model'!F45/(1+$B10)^('DCF Model'!C19+3)+'DCF Model'!G45/(1+$B10)^('DCF Model'!C19+4)+'DCF Model'!G45*(1+C$6)/($B10-C$6)/(1+$B10)^('DCF Model'!C19+4)-'DCF Model'!C16)*1000000/'DCF Model'!C15,0),"") -> 832 | D10: =IFERROR(ROUND(('DCF Model'!C45/(1+$B10)^('DCF Model'!C19+0)+'DCF Model'!D45/(1+$B10)^('DCF Model'!C19+1)+'DCF Model'!E45/(1+$B10)^('DCF Model'!C19+2)+'DCF Model'!F45/(1+$B10)^('DCF Model'!C19+3)+'DCF Model'!G45/(1+$B10)^('DCF Model'!C19+4)+'DCF Model'!G45*(1+D$6)/($B10-D$6)/(1+$B10)^('DCF Model'!C19+4)-'DCF Model'!C16)*1000000/'DCF Model'!C15,0),"") -> 839 | E10: =IFERROR(ROUND(('DCF Model'!C45/(1+$B10)^('DCF Model'!C19+0)+'DCF Model'!D45/(1+$B10)^('DCF Model'!C19+1)+'DCF Model'!E45/(1+$B10)^('DCF Model'!C19+2)+'DCF Model'!F45/(1+$B10)^('DCF Model'!C19+3)+'DCF Model'!G45/(1+$B10)^('DCF Model'!C19+4)+'DCF Model'!G45*(1+E$6)/($B10-E$6)/(1+$B10)^('DCF Model'!C19+4)-'DCF Model'!C16)*1000000/'DCF Model'!C15,0),"") -> 846 | F10: =IFERROR(ROUND(('DCF Model'!C45/(1+$B10)^('DCF Model'!C19+0)+'DCF Model'!D45/(1+$B10)^('DCF Model'!C19+1)+'DCF Model'!E45/(1+$B10)^('DCF Model'!C19+2)+'DCF Model'!F45/(1+$B10)^('DCF Model'!C19+3)+'DCF Model'!G45/(1+$B10)^('DCF Model'!C19+4)+'DCF Model'!G45*(1+F$6)/($B10-F$6)/(1+$B10)^('DCF Model'!C19+4)-'DCF Model'!C16)*1000000/'DCF Model'!C15,0),"") -> 853 | G10: =IFERROR(ROUND(('DCF Model'!C45/(1+$B10)^('DCF Model'!C19+0)+'DCF Model'!D45/(1+$B10)^('DCF Model'!C19+1)+'DCF Model'!E45/(1+$B10)^('DCF Model'!C19+2)+'DCF Model'!F45/(1+$B10)^('DCF Model'!C19+3)+'DCF Model'!G45/(1+$B10)^('DCF Model'!C19+4)+'DCF Model'!G45*(1+G$6)/($B10-G$6)/(1+$B10)^('DCF Model'!C19+4)-'DCF Model'!C16)*1000000/'DCF Model'!C15,0),"") -> 860 | H10: =IFERROR(ROUND(('DCF Model'!C45/(1+$B10)^('DCF Model'!C19+0)+'DCF Model'!D45/(1+$B10)^('DCF Model'!C19+1)+'DCF Model'!E45/(1+$B10)^('DCF Model'!C19+2)+'DCF Model'!F45/(1+$B10)^('DCF Model'!C19+3)+'DCF Model'!G45/(1+$B10)^('DCF Model'!C19+4)+'DCF Model'!G45*(1+H$6)/($B10-H$6)/(1+$B10)^('DCF Model'!C19+4)-'DCF Model'!C16)*1000000/'DCF Model'!C15,0),"") -> 868 | I10: =IFERROR(ROUND(('DCF Model'!C45/(1+$B10)^('DCF Model'!C19+0)+'DCF Model'!D45/(1+$B10)^('DCF Model'!C19+1)+'DCF Model'!E45/(1+$B10)^('DCF Model'!C19+2)+'DCF Model'!F45/(1+$B10)^('DCF Model'!C19+3)+'DCF Model'!G45/(1+$B10)^('DCF Model'!C19+4)+'DCF Model'!G45*(1+I$6)/($B10-I$6)/(1+$B10)^('DCF Model'!C19+4)-'DCF Model'!C16)*1000000/'DCF Model'!C15,0),"") -> 876
B11: =$C$3+0.005 -> 0.1589865 | C11: =IFERROR(ROUND(('DCF Model'!C45/(1+$B11)^('DCF Model'!C19+0)+'DCF Model'!D45/(1+$B11)^('DCF Model'!C19+1)+'DCF Model'!E45/(1+$B11)^('DCF Model'!C19+2)+'DCF Model'!F45/(1+$B11)^('DCF Model'!C19+3)+'DCF Model'!G45/(1+$B11)^('DCF Model'!C19+4)+'DCF Model'!G45*(1+C$6)/($B11-C$6)/(1+$B11)^('DCF Model'!C19+4)-'DCF Model'!C16)*1000000/'DCF Model'!C15,0),"") -> 811 | D11: =IFERROR(ROUND(('DCF Model'!C45/(1+$B11)^('DCF Model'!C19+0)+'DCF Model'!D45/(1+$B11)^('DCF Model'!C19+1)+'DCF Model'!E45/(1+$B11)^('DCF Model'!C19+2)+'DCF Model'!F45/(1+$B11)^('DCF Model'!C19+3)+'DCF Model'!G45/(1+$B11)^('DCF Model'!C19+4)+'DCF Model'!G45*(1+D$6)/($B11-D$6)/(1+$B11)^('DCF Model'!C19+4)-'DCF Model'!C16)*1000000/'DCF Model'!C15,0),"") -> 817 | E11: =IFERROR(ROUND(('DCF Model'!C45/(1+$B11)^('DCF Model'!C19+0)+'DCF Model'!D45/(1+$B11)^('DCF Model'!C19+1)+'DCF Model'!E45/(1+$B11)^('DCF Model'!C19+2)+'DCF Model'!F45/(1+$B11)^('DCF Model'!C19+3)+'DCF Model'!G45/(1+$B11)^('DCF Model'!C19+4)+'DCF Model'!G45*(1+E$6)/($B11-E$6)/(1+$B11)^('DCF Model'!C19+4)-'DCF Model'!C16)*1000000/'DCF Model'!C15,0),"") -> 824 | F11: =IFERROR(ROUND(('DCF Model'!C45/(1+$B11)^('DCF Model'!C19+0)+'DCF Model'!D45/(1+$B11)^('DCF Model'!C19+1)+'DCF Model'!E45/(1+$B11)^('DCF Model'!C19+2)+'DCF Model'!F45/(1+$B11)^('DCF Model'!C19+3)+'DCF Model'!G45/(1+$B11)^('DCF Model'!C19+4)+'DCF Model'!G45*(1+F$6)/($B11-F$6)/(1+$B11)^('DCF Model'!C19+4)-'DCF Model'!C16)*1000000/'DCF Model'!C15,0),"") -> 830 | G11: =IFERROR(ROUND(('DCF Model'!C45/(1+$B11)^('DCF Model'!C19+0)+'DCF Model'!D45/(1+$B11)^('DCF Model'!C19+1)+'DCF Model'!E45/(1+$B11)^('DCF Model'!C19+2)+'DCF Model'!F45/(1+$B11)^('DCF Model'!C19+3)+'DCF Model'!G45/(1+$B11)^('DCF Model'!C19+4)+'DCF Model'!G45*(1+G$6)/($B11-G$6)/(1+$B11)^('DCF Model'!C19+4)-'DCF Model'!C16)*1000000/'DCF Model'!C15,0),"") -> 837 | H11: =IFERROR(ROUND(('DCF Model'!C45/(1+$B11)^('DCF Model'!C19+0)+'DCF Model'!D45/(1+$B11)^('DCF Model'!C19+1)+'DCF Model'!E45/(1+$B11)^('DCF Model'!C19+2)+'DCF Model'!F45/(1+$B11)^('DCF Model'!C19+3)+'DCF Model'!G45/(1+$B11)^('DCF Model'!C19+4)+'DCF Model'!G45*(1+H$6)/($B11-H$6)/(1+$B11)^('DCF Model'!C19+4)-'DCF Model'!C16)*1000000/'DCF Model'!C15,0),"") -> 844 | I11: =IFERROR(ROUND(('DCF Model'!C45/(1+$B11)^('DCF Model'!C19+0)+'DCF Model'!D45/(1+$B11)^('DCF Model'!C19+1)+'DCF Model'!E45/(1+$B11)^('DCF Model'!C19+2)+'DCF Model'!F45/(1+$B11)^('DCF Model'!C19+3)+'DCF Model'!G45/(1+$B11)^('DCF Model'!C19+4)+'DCF Model'!G45*(1+I$6)/($B11-I$6)/(1+$B11)^('DCF Model'!C19+4)-'DCF Model'!C16)*1000000/'DCF Model'!C15,0),"") -> 851
B12: =$C$3+0.01 -> 0.1639865 | C12: =IFERROR(ROUND(('DCF Model'!C45/(1+$B12)^('DCF Model'!C19+0)+'DCF Model'!D45/(1+$B12)^('DCF Model'!C19+1)+'DCF Model'!E45/(1+$B12)^('DCF Model'!C19+2)+'DCF Model'!F45/(1+$B12)^('DCF Model'!C19+3)+'DCF Model'!G45/(1+$B12)^('DCF Model'!C19+4)+'DCF Model'!G45*(1+C$6)/($B12-C$6)/(1+$B12)^('DCF Model'!C19+4)-'DCF Model'!C16)*1000000/'DCF Model'!C15,0),"") -> 791 | D12: =IFERROR(ROUND(('DCF Model'!C45/(1+$B12)^('DCF Model'!C19+0)+'DCF Model'!D45/(1+$B12)^('DCF Model'!C19+1)+'DCF Model'!E45/(1+$B12)^('DCF Model'!C19+2)+'DCF Model'!F45/(1+$B12)^('DCF Model'!C19+3)+'DCF Model'!G45/(1+$B12)^('DCF Model'!C19+4)+'DCF Model'!G45*(1+D$6)/($B12-D$6)/(1+$B12)^('DCF Model'!C19+4)-'DCF Model'!C16)*1000000/'DCF Model'!C15,0),"") -> 797 | E12: =IFERROR(ROUND(('DCF Model'!C45/(1+$B12)^('DCF Model'!C19+0)+'DCF Model'!D45/(1+$B12)^('DCF Model'!C19+1)+'DCF Model'!E45/(1+$B12)^('DCF Model'!C19+2)+'DCF Model'!F45/(1+$B12)^('DCF Model'!C19+3)+'DCF Model'!G45/(1+$B12)^('DCF Model'!C19+4)+'DCF Model'!G45*(1+E$6)/($B12-E$6)/(1+$B12)^('DCF Model'!C19+4)-'DCF Model'!C16)*1000000/'DCF Model'!C15,0),"") -> 803 | F12: =IFERROR(ROUND(('DCF Model'!C45/(1+$B12)^('DCF Model'!C19+0)+'DCF Model'!D45/(1+$B12)^('DCF Model'!C19+1)+'DCF Model'!E45/(1+$B12)^('DCF Model'!C19+2)+'DCF Model'!F45/(1+$B12)^('DCF Model'!C19+3)+'DCF Model'!G45/(1+$B12)^('DCF Model'!C19+4)+'DCF Model'!G45*(1+F$6)/($B12-F$6)/(1+$B12)^('DCF Model'!C19+4)-'DCF Model'!C16)*1000000/'DCF Model'!C15,0),"") -> 809 | G12: =IFERROR(ROUND(('DCF Model'!C45/(1+$B12)^('DCF Model'!C19+0)+'DCF Model'!D45/(1+$B12)^('DCF Model'!C19+1)+'DCF Model'!E45/(1+$B12)^('DCF Model'!C19+2)+'DCF Model'!F45/(1+$B12)^('DCF Model'!C19+3)+'DCF Model'!G45/(1+$B12)^('DCF Model'!C19+4)+'DCF Model'!G45*(1+G$6)/($B12-G$6)/(1+$B12)^('DCF Model'!C19+4)-'DCF Model'!C16)*1000000/'DCF Model'!C15,0),"") -> 815 | H12: =IFERROR(ROUND(('DCF Model'!C45/(1+$B12)^('DCF Model'!C19+0)+'DCF Model'!D45/(1+$B12)^('DCF Model'!C19+1)+'DCF Model'!E45/(1+$B12)^('DCF Model'!C19+2)+'DCF Model'!F45/(1+$B12)^('DCF Model'!C19+3)+'DCF Model'!G45/(1+$B12)^('DCF Model'!C19+4)+'DCF Model'!G45*(1+H$6)/($B12-H$6)/(1+$B12)^('DCF Model'!C19+4)-'DCF Model'!C16)*1000000/'DCF Model'!C15,0),"") -> 821 | I12: =IFERROR(ROUND(('DCF Model'!C45/(1+$B12)^('DCF Model'!C19+0)+'DCF Model'!D45/(1+$B12)^('DCF Model'!C19+1)+'DCF Model'!E45/(1+$B12)^('DCF Model'!C19+2)+'DCF Model'!F45/(1+$B12)^('DCF Model'!C19+3)+'DCF Model'!G45/(1+$B12)^('DCF Model'!C19+4)+'DCF Model'!G45*(1+I$6)/($B12-I$6)/(1+$B12)^('DCF Model'!C19+4)-'DCF Model'!C16)*1000000/'DCF Model'!C15,0),"") -> 828
B13: =$C$3+0.015 -> 0.1689865 | C13: =IFERROR(ROUND(('DCF Model'!C45/(1+$B13)^('DCF Model'!C19+0)+'DCF Model'!D45/(1+$B13)^('DCF Model'!C19+1)+'DCF Model'!E45/(1+$B13)^('DCF Model'!C19+2)+'DCF Model'!F45/(1+$B13)^('DCF Model'!C19+3)+'DCF Model'!G45/(1+$B13)^('DCF Model'!C19+4)+'DCF Model'!G45*(1+C$6)/($B13-C$6)/(1+$B13)^('DCF Model'!C19+4)-'DCF Model'!C16)*1000000/'DCF Model'!C15,0),"") -> 772 | D13: =IFERROR(ROUND(('DCF Model'!C45/(1+$B13)^('DCF Model'!C19+0)+'DCF Model'!D45/(1+$B13)^('DCF Model'!C19+1)+'DCF Model'!E45/(1+$B13)^('DCF Model'!C19+2)+'DCF Model'!F45/(1+$B13)^('DCF Model'!C19+3)+'DCF Model'!G45/(1+$B13)^('DCF Model'!C19+4)+'DCF Model'!G45*(1+D$6)/($B13-D$6)/(1+$B13)^('DCF Model'!C19+4)-'DCF Model'!C16)*1000000/'DCF Model'!C15,0),"") -> 778 | E13: =IFERROR(ROUND(('DCF Model'!C45/(1+$B13)^('DCF Model'!C19+0)+'DCF Model'!D45/(1+$B13)^('DCF Model'!C19+1)+'DCF Model'!E45/(1+$B13)^('DCF Model'!C19+2)+'DCF Model'!F45/(1+$B13)^('DCF Model'!C19+3)+'DCF Model'!G45/(1+$B13)^('DCF Model'!C19+4)+'DCF Model'!G45*(1+E$6)/($B13-E$6)/(1+$B13)^('DCF Model'!C19+4)-'DCF Model'!C16)*1000000/'DCF Model'!C15,0),"") -> 783 | F13: =IFERROR(ROUND(('DCF Model'!C45/(1+$B13)^('DCF Model'!C19+0)+'DCF Model'!D45/(1+$B13)^('DCF Model'!C19+1)+'DCF Model'!E45/(1+$B13)^('DCF Model'!C19+2)+'DCF Model'!F45/(1+$B13)^('DCF Model'!C19+3)+'DCF Model'!G45/(1+$B13)^('DCF Model'!C19+4)+'DCF Model'!G45*(1+F$6)/($B13-F$6)/(1+$B13)^('DCF Model'!C19+4)-'DCF Model'!C16)*1000000/'DCF Model'!C15,0),"") -> 789 | G13: =IFERROR(ROUND(('DCF Model'!C45/(1+$B13)^('DCF Model'!C19+0)+'DCF Model'!D45/(1+$B13)^('DCF Model'!C19+1)+'DCF Model'!E45/(1+$B13)^('DCF Model'!C19+2)+'DCF Model'!F45/(1+$B13)^('DCF Model'!C19+3)+'DCF Model'!G45/(1+$B13)^('DCF Model'!C19+4)+'DCF Model'!G45*(1+G$6)/($B13-G$6)/(1+$B13)^('DCF Model'!C19+4)-'DCF Model'!C16)*1000000/'DCF Model'!C15,0),"") -> 794 | H13: =IFERROR(ROUND(('DCF Model'!C45/(1+$B13)^('DCF Model'!C19+0)+'DCF Model'!D45/(1+$B13)^('DCF Model'!C19+1)+'DCF Model'!E45/(1+$B13)^('DCF Model'!C19+2)+'DCF Model'!F45/(1+$B13)^('DCF Model'!C19+3)+'DCF Model'!G45/(1+$B13)^('DCF Model'!C19+4)+'DCF Model'!G45*(1+H$6)/($B13-H$6)/(1+$B13)^('DCF Model'!C19+4)-'DCF Model'!C16)*1000000/'DCF Model'!C15,0),"") -> 800 | I13: =IFERROR(ROUND(('DCF Model'!C45/(1+$B13)^('DCF Model'!C19+0)+'DCF Model'!D45/(1+$B13)^('DCF Model'!C19+1)+'DCF Model'!E45/(1+$B13)^('DCF Model'!C19+2)+'DCF Model'!F45/(1+$B13)^('DCF Model'!C19+3)+'DCF Model'!G45/(1+$B13)^('DCF Model'!C19+4)+'DCF Model'!G45*(1+I$6)/($B13-I$6)/(1+$B13)^('DCF Model'!C19+4)-'DCF Model'!C16)*1000000/'DCF Model'!C15,0),"") -> 806
B16: Table 2: WACC vs Exit Multiple (Exit Multiple - Implied Share Price, JPY)
B17: WACC \ Exit Multiple | C17: =$I$3-3 -> 6 | D17: =$I$3-2 -> 7 | E17: =$I$3-1 -> 8 | F17: =$I$3 -> 9 | G17: =$I$3+1 -> 10 | H17: =$I$3+2 -> 11 | I17: =$I$3+3 -> 12
B18: =$C$3-0.015 -> 0.1389865 | C18: =IFERROR(ROUND(('DCF Model'!C45/(1+$B18)^('DCF Model'!C19+0)+'DCF Model'!D45/(1+$B18)^('DCF Model'!C19+1)+'DCF Model'!E45/(1+$B18)^('DCF Model'!C19+2)+'DCF Model'!F45/(1+$B18)^('DCF Model'!C19+3)+'DCF Model'!G45/(1+$B18)^('DCF Model'!C19+4)+('DCF Model'!G39+'DCF Model'!G42)*C$17/(1+$B18)^('DCF Model'!C19+4)-'DCF Model'!C16)*1000000/'DCF Model'!C15,0),"") -> 1185 | D18: =IFERROR(ROUND(('DCF Model'!C45/(1+$B18)^('DCF Model'!C19+0)+'DCF Model'!D45/(1+$B18)^('DCF Model'!C19+1)+'DCF Model'!E45/(1+$B18)^('DCF Model'!C19+2)+'DCF Model'!F45/(1+$B18)^('DCF Model'!C19+3)+'DCF Model'!G45/(1+$B18)^('DCF Model'!C19+4)+('DCF Model'!G39+'DCF Model'!G42)*D$17/(1+$B18)^('DCF Model'!C19+4)-'DCF Model'!C16)*1000000/'DCF Model'!C15,0),"") -> 1300 | E18: =IFERROR(ROUND(('DCF Model'!C45/(1+$B18)^('DCF Model'!C19+0)+'DCF Model'!D45/(1+$B18)^('DCF Model'!C19+1)+'DCF Model'!E45/(1+$B18)^('DCF Model'!C19+2)+'DCF Model'!F45/(1+$B18)^('DCF Model'!C19+3)+'DCF Model'!G45/(1+$B18)^('DCF Model'!C19+4)+('DCF Model'!G39+'DCF Model'!G42)*E$17/(1+$B18)^('DCF Model'!C19+4)-'DCF Model'!C16)*1000000/'DCF Model'!C15,0),"") -> 1414 | F18: =IFERROR(ROUND(('DCF Model'!C45/(1+$B18)^('DCF Model'!C19+0)+'DCF Model'!D45/(1+$B18)^('DCF Model'!C19+1)+'DCF Model'!E45/(1+$B18)^('DCF Model'!C19+2)+'DCF Model'!F45/(1+$B18)^('DCF Model'!C19+3)+'DCF Model'!G45/(1+$B18)^('DCF Model'!C19+4)+('DCF Model'!G39+'DCF Model'!G42)*F$17/(1+$B18)^('DCF Model'!C19+4)-'DCF Model'!C16)*1000000/'DCF Model'!C15,0),"") -> 1529 | G18: =IFERROR(ROUND(('DCF Model'!C45/(1+$B18)^('DCF Model'!C19+0)+'DCF Model'!D45/(1+$B18)^('DCF Model'!C19+1)+'DCF Model'!E45/(1+$B18)^('DCF Model'!C19+2)+'DCF Model'!F45/(1+$B18)^('DCF Model'!C19+3)+'DCF Model'!G45/(1+$B18)^('DCF Model'!C19+4)+('DCF Model'!G39+'DCF Model'!G42)*G$17/(1+$B18)^('DCF Model'!C19+4)-'DCF Model'!C16)*1000000/'DCF Model'!C15,0),"") -> 1644 | H18: =IFERROR(ROUND(('DCF Model'!C45/(1+$B18)^('DCF Model'!C19+0)+'DCF Model'!D45/(1+$B18)^('DCF Model'!C19+1)+'DCF Model'!E45/(1+$B18)^('DCF Model'!C19+2)+'DCF Model'!F45/(1+$B18)^('DCF Model'!C19+3)+'DCF Model'!G45/(1+$B18)^('DCF Model'!C19+4)+('DCF Model'!G39+'DCF Model'!G42)*H$17/(1+$B18)^('DCF Model'!C19+4)-'DCF Model'!C16)*1000000/'DCF Model'!C15,0),"") -> 1759 | I18: =IFERROR(ROUND(('DCF Model'!C45/(1+$B18)^('DCF Model'!C19+0)+'DCF Model'!D45/(1+$B18)^('DCF Model'!C19+1)+'DCF Model'!E45/(1+$B18)^('DCF Model'!C19+2)+'DCF Model'!F45/(1+$B18)^('DCF Model'!C19+3)+'DCF Model'!G45/(1+$B18)^('DCF Model'!C19+4)+('DCF Model'!G39+'DCF Model'!G42)*I$17/(1+$B18)^('DCF Model'!C19+4)-'DCF Model'!C16)*1000000/'DCF Model'!C15,0),"") -> 1874
B19: =$C$3-0.01 -> 0.1439865 | C19: =IFERROR(ROUND(('DCF Model'!C45/(1+$B19)^('DCF Model'!C19+0)+'DCF Model'!D45/(1+$B19)^('DCF Model'!C19+1)+'DCF Model'!E45/(1+$B19)^('DCF Model'!C19+2)+'DCF Model'!F45/(1+$B19)^('DCF Model'!C19+3)+'DCF Model'!G45/(1+$B19)^('DCF Model'!C19+4)+('DCF Model'!G39+'DCF Model'!G42)*C$17/(1+$B19)^('DCF Model'!C19+4)-'DCF Model'!C16)*1000000/'DCF Model'!C15,0),"") -> 1166 | D19: =IFERROR(ROUND(('DCF Model'!C45/(1+$B19)^('DCF Model'!C19+0)+'DCF Model'!D45/(1+$B19)^('DCF Model'!C19+1)+'DCF Model'!E45/(1+$B19)^('DCF Model'!C19+2)+'DCF Model'!F45/(1+$B19)^('DCF Model'!C19+3)+'DCF Model'!G45/(1+$B19)^('DCF Model'!C19+4)+('DCF Model'!G39+'DCF Model'!G42)*D$17/(1+$B19)^('DCF Model'!C19+4)-'DCF Model'!C16)*1000000/'DCF Model'!C15,0),"") -> 1279 | E19: =IFERROR(ROUND(('DCF Model'!C45/(1+$B19)^('DCF Model'!C19+0)+'DCF Model'!D45/(1+$B19)^('DCF Model'!C19+1)+'DCF Model'!E45/(1+$B19)^('DCF Model'!C19+2)+'DCF Model'!F45/(1+$B19)^('DCF Model'!C19+3)+'DCF Model'!G45/(1+$B19)^('DCF Model'!C19+4)+('DCF Model'!G39+'DCF Model'!G42)*E$17/(1+$B19)^('DCF Model'!C19+4)-'DCF Model'!C16)*1000000/'DCF Model'!C15,0),"") -> 1391 | F19: =IFERROR(ROUND(('DCF Model'!C45/(1+$B19)^('DCF Model'!C19+0)+'DCF Model'!D45/(1+$B19)^('DCF Model'!C19+1)+'DCF Model'!E45/(1+$B19)^('DCF Model'!C19+2)+'DCF Model'!F45/(1+$B19)^('DCF Model'!C19+3)+'DCF Model'!G45/(1+$B19)^('DCF Model'!C19+4)+('DCF Model'!G39+'DCF Model'!G42)*F$17/(1+$B19)^('DCF Model'!C19+4)-'DCF Model'!C16)*1000000/'DCF Model'!C15,0),"") -> 1503 | G19: =IFERROR(ROUND(('DCF Model'!C45/(1+$B19)^('DCF Model'!C19+0)+'DCF Model'!D45/(1+$B19)^('DCF Model'!C19+1)+'DCF Model'!E45/(1+$B19)^('DCF Model'!C19+2)+'DCF Model'!F45/(1+$B19)^('DCF Model'!C19+3)+'DCF Model'!G45/(1+$B19)^('DCF Model'!C19+4)+('DCF Model'!G39+'DCF Model'!G42)*G$17/(1+$B19)^('DCF Model'!C19+4)-'DCF Model'!C16)*1000000/'DCF Model'!C15,0),"") -> 1615 | H19: =IFERROR(ROUND(('DCF Model'!C45/(1+$B19)^('DCF Model'!C19+0)+'DCF Model'!D45/(1+$B19)^('DCF Model'!C19+1)+'DCF Model'!E45/(1+$B19)^('DCF Model'!C19+2)+'DCF Model'!F45/(1+$B19)^('DCF Model'!C19+3)+'DCF Model'!G45/(1+$B19)^('DCF Model'!C19+4)+('DCF Model'!G39+'DCF Model'!G42)*H$17/(1+$B19)^('DCF Model'!C19+4)-'DCF Model'!C16)*1000000/'DCF Model'!C15,0),"") -> 1728 | I19: =IFERROR(ROUND(('DCF Model'!C45/(1+$B19)^('DCF Model'!C19+0)+'DCF Model'!D45/(1+$B19)^('DCF Model'!C19+1)+'DCF Model'!E45/(1+$B19)^('DCF Model'!C19+2)+'DCF Model'!F45/(1+$B19)^('DCF Model'!C19+3)+'DCF Model'!G45/(1+$B19)^('DCF Model'!C19+4)+('DCF Model'!G39+'DCF Model'!G42)*I$17/(1+$B19)^('DCF Model'!C19+4)-'DCF Model'!C16)*1000000/'DCF Model'!C15,0),"") -> 1840
B20: =$C$3-0.005 -> 0.1489865 | C20: =IFERROR(ROUND(('DCF Model'!C45/(1+$B20)^('DCF Model'!C19+0)+'DCF Model'!D45/(1+$B20)^('DCF Model'!C19+1)+'DCF Model'!E45/(1+$B20)^('DCF Model'!C19+2)+'DCF Model'!F45/(1+$B20)^('DCF Model'!C19+3)+'DCF Model'!G45/(1+$B20)^('DCF Model'!C19+4)+('DCF Model'!G39+'DCF Model'!G42)*C$17/(1+$B20)^('DCF Model'!C19+4)-'DCF Model'!C16)*1000000/'DCF Model'!C15,0),"") -> 1148 | D20: =IFERROR(ROUND(('DCF Model'!C45/(1+$B20)^('DCF Model'!C19+0)+'DCF Model'!D45/(1+$B20)^('DCF Model'!C19+1)+'DCF Model'!E45/(1+$B20)^('DCF Model'!C19+2)+'DCF Model'!F45/(1+$B20)^('DCF Model'!C19+3)+'DCF Model'!G45/(1+$B20)^('DCF Model'!C19+4)+('DCF Model'!G39+'DCF Model'!G42)*D$17/(1+$B20)^('DCF Model'!C19+4)-'DCF Model'!C16)*1000000/'DCF Model'!C15,0),"") -> 1258 | E20: =IFERROR(ROUND(('DCF Model'!C45/(1+$B20)^('DCF Model'!C19+0)+'DCF Model'!D45/(1+$B20)^('DCF Model'!C19+1)+'DCF Model'!E45/(1+$B20)^('DCF Model'!C19+2)+'DCF Model'!F45/(1+$B20)^('DCF Model'!C19+3)+'DCF Model'!G45/(1+$B20)^('DCF Model'!C19+4)+('DCF Model'!G39+'DCF Model'!G42)*E$17/(1+$B20)^('DCF Model'!C19+4)-'DCF Model'!C16)*1000000/'DCF Model'!C15,0),"") -> 1368 | F20: =IFERROR(ROUND(('DCF Model'!C45/(1+$B20)^('DCF Model'!C19+0)+'DCF Model'!D45/(1+$B20)^('DCF Model'!C19+1)+'DCF Model'!E45/(1+$B20)^('DCF Model'!C19+2)+'DCF Model'!F45/(1+$B20)^('DCF Model'!C19+3)+'DCF Model'!G45/(1+$B20)^('DCF Model'!C19+4)+('DCF Model'!G39+'DCF Model'!G42)*F$17/(1+$B20)^('DCF Model'!C19+4)-'DCF Model'!C16)*1000000/'DCF Model'!C15,0),"") -> 1478 | G20: =IFERROR(ROUND(('DCF Model'!C45/(1+$B20)^('DCF Model'!C19+0)+'DCF Model'!D45/(1+$B20)^('DCF Model'!C19+1)+'DCF Model'!E45/(1+$B20)^('DCF Model'!C19+2)+'DCF Model'!F45/(1+$B20)^('DCF Model'!C19+3)+'DCF Model'!G45/(1+$B20)^('DCF Model'!C19+4)+('DCF Model'!G39+'DCF Model'!G42)*G$17/(1+$B20)^('DCF Model'!C19+4)-'DCF Model'!C16)*1000000/'DCF Model'!C15,0),"") -> 1588 | H20: =IFERROR(ROUND(('DCF Model'!C45/(1+$B20)^('DCF Model'!C19+0)+'DCF Model'!D45/(1+$B20)^('DCF Model'!C19+1)+'DCF Model'!E45/(1+$B20)^('DCF Model'!C19+2)+'DCF Model'!F45/(1+$B20)^('DCF Model'!C19+3)+'DCF Model'!G45/(1+$B20)^('DCF Model'!C19+4)+('DCF Model'!G39+'DCF Model'!G42)*H$17/(1+$B20)^('DCF Model'!C19+4)-'DCF Model'!C16)*1000000/'DCF Model'!C15,0),"") -> 1697 | I20: =IFERROR(ROUND(('DCF Model'!C45/(1+$B20)^('DCF Model'!C19+0)+'DCF Model'!D45/(1+$B20)^('DCF Model'!C19+1)+'DCF Model'!E45/(1+$B20)^('DCF Model'!C19+2)+'DCF Model'!F45/(1+$B20)^('DCF Model'!C19+3)+'DCF Model'!G45/(1+$B20)^('DCF Model'!C19+4)+('DCF Model'!G39+'DCF Model'!G42)*I$17/(1+$B20)^('DCF Model'!C19+4)-'DCF Model'!C16)*1000000/'DCF Model'!C15,0),"") -> 1807
B21: =$C$3 -> 0.1539865 | C21: =IFERROR(ROUND(('DCF Model'!C45/(1+$B21)^('DCF Model'!C19+0)+'DCF Model'!D45/(1+$B21)^('DCF Model'!C19+1)+'DCF Model'!E45/(1+$B21)^('DCF Model'!C19+2)+'DCF Model'!F45/(1+$B21)^('DCF Model'!C19+3)+'DCF Model'!G45/(1+$B21)^('DCF Model'!C19+4)+('DCF Model'!G39+'DCF Model'!G42)*C$17/(1+$B21)^('DCF Model'!C19+4)-'DCF Model'!C16)*1000000/'DCF Model'!C15,0),"") -> 1131 | D21: =IFERROR(ROUND(('DCF Model'!C45/(1+$B21)^('DCF Model'!C19+0)+'DCF Model'!D45/(1+$B21)^('DCF Model'!C19+1)+'DCF Model'!E45/(1+$B21)^('DCF Model'!C19+2)+'DCF Model'!F45/(1+$B21)^('DCF Model'!C19+3)+'DCF Model'!G45/(1+$B21)^('DCF Model'!C19+4)+('DCF Model'!G39+'DCF Model'!G42)*D$17/(1+$B21)^('DCF Model'!C19+4)-'DCF Model'!C16)*1000000/'DCF Model'!C15,0),"") -> 1238 | E21: =IFERROR(ROUND(('DCF Model'!C45/(1+$B21)^('DCF Model'!C19+0)+'DCF Model'!D45/(1+$B21)^('DCF Model'!C19+1)+'DCF Model'!E45/(1+$B21)^('DCF Model'!C19+2)+'DCF Model'!F45/(1+$B21)^('DCF Model'!C19+3)+'DCF Model'!G45/(1+$B21)^('DCF Model'!C19+4)+('DCF Model'!G39+'DCF Model'!G42)*E$17/(1+$B21)^('DCF Model'!C19+4)-'DCF Model'!C16)*1000000/'DCF Model'!C15,0),"") -> 1346 | F21: =IFERROR(ROUND(('DCF Model'!C45/(1+$B21)^('DCF Model'!C19+0)+'DCF Model'!D45/(1+$B21)^('DCF Model'!C19+1)+'DCF Model'!E45/(1+$B21)^('DCF Model'!C19+2)+'DCF Model'!F45/(1+$B21)^('DCF Model'!C19+3)+'DCF Model'!G45/(1+$B21)^('DCF Model'!C19+4)+('DCF Model'!G39+'DCF Model'!G42)*F$17/(1+$B21)^('DCF Model'!C19+4)-'DCF Model'!C16)*1000000/'DCF Model'!C15,0),"") -> 1453 | G21: =IFERROR(ROUND(('DCF Model'!C45/(1+$B21)^('DCF Model'!C19+0)+'DCF Model'!D45/(1+$B21)^('DCF Model'!C19+1)+'DCF Model'!E45/(1+$B21)^('DCF Model'!C19+2)+'DCF Model'!F45/(1+$B21)^('DCF Model'!C19+3)+'DCF Model'!G45/(1+$B21)^('DCF Model'!C19+4)+('DCF Model'!G39+'DCF Model'!G42)*G$17/(1+$B21)^('DCF Model'!C19+4)-'DCF Model'!C16)*1000000/'DCF Model'!C15,0),"") -> 1560 | H21: =IFERROR(ROUND(('DCF Model'!C45/(1+$B21)^('DCF Model'!C19+0)+'DCF Model'!D45/(1+$B21)^('DCF Model'!C19+1)+'DCF Model'!E45/(1+$B21)^('DCF Model'!C19+2)+'DCF Model'!F45/(1+$B21)^('DCF Model'!C19+3)+'DCF Model'!G45/(1+$B21)^('DCF Model'!C19+4)+('DCF Model'!G39+'DCF Model'!G42)*H$17/(1+$B21)^('DCF Model'!C19+4)-'DCF Model'!C16)*1000000/'DCF Model'!C15,0),"") -> 1668 | I21: =IFERROR(ROUND(('DCF Model'!C45/(1+$B21)^('DCF Model'!C19+0)+'DCF Model'!D45/(1+$B21)^('DCF Model'!C19+1)+'DCF Model'!E45/(1+$B21)^('DCF Model'!C19+2)+'DCF Model'!F45/(1+$B21)^('DCF Model'!C19+3)+'DCF Model'!G45/(1+$B21)^('DCF Model'!C19+4)+('DCF Model'!G39+'DCF Model'!G42)*I$17/(1+$B21)^('DCF Model'!C19+4)-'DCF Model'!C16)*1000000/'DCF Model'!C15,0),"") -> 1775
B22: =$C$3+0.005 -> 0.1589865 | C22: =IFERROR(ROUND(('DCF Model'!C45/(1+$B22)^('DCF Model'!C19+0)+'DCF Model'!D45/(1+$B22)^('DCF Model'!C19+1)+'DCF Model'!E45/(1+$B22)^('DCF Model'!C19+2)+'DCF Model'!F45/(1+$B22)^('DCF Model'!C19+3)+'DCF Model'!G45/(1+$B22)^('DCF Model'!C19+4)+('DCF Model'!G39+'DCF Model'!G42)*C$17/(1+$B22)^('DCF Model'!C19+4)-'DCF Model'!C16)*1000000/'DCF Model'!C15,0),"") -> 1114 | D22: =IFERROR(ROUND(('DCF Model'!C45/(1+$B22)^('DCF Model'!C19+0)+'DCF Model'!D45/(1+$B22)^('DCF Model'!C19+1)+'DCF Model'!E45/(1+$B22)^('DCF Model'!C19+2)+'DCF Model'!F45/(1+$B22)^('DCF Model'!C19+3)+'DCF Model'!G45/(1+$B22)^('DCF Model'!C19+4)+('DCF Model'!G39+'DCF Model'!G42)*D$17/(1+$B22)^('DCF Model'!C19+4)-'DCF Model'!C16)*1000000/'DCF Model'!C15,0),"") -> 1219 | E22: =IFERROR(ROUND(('DCF Model'!C45/(1+$B22)^('DCF Model'!C19+0)+'DCF Model'!D45/(1+$B22)^('DCF Model'!C19+1)+'DCF Model'!E45/(1+$B22)^('DCF Model'!C19+2)+'DCF Model'!F45/(1+$B22)^('DCF Model'!C19+3)+'DCF Model'!G45/(1+$B22)^('DCF Model'!C19+4)+('DCF Model'!G39+'DCF Model'!G42)*E$17/(1+$B22)^('DCF Model'!C19+4)-'DCF Model'!C16)*1000000/'DCF Model'!C15,0),"") -> 1324 | F22: =IFERROR(ROUND(('DCF Model'!C45/(1+$B22)^('DCF Model'!C19+0)+'DCF Model'!D45/(1+$B22)^('DCF Model'!C19+1)+'DCF Model'!E45/(1+$B22)^('DCF Model'!C19+2)+'DCF Model'!F45/(1+$B22)^('DCF Model'!C19+3)+'DCF Model'!G45/(1+$B22)^('DCF Model'!C19+4)+('DCF Model'!G39+'DCF Model'!G42)*F$17/(1+$B22)^('DCF Model'!C19+4)-'DCF Model'!C16)*1000000/'DCF Model'!C15,0),"") -> 1429 | G22: =IFERROR(ROUND(('DCF Model'!C45/(1+$B22)^('DCF Model'!C19+0)+'DCF Model'!D45/(1+$B22)^('DCF Model'!C19+1)+'DCF Model'!E45/(1+$B22)^('DCF Model'!C19+2)+'DCF Model'!F45/(1+$B22)^('DCF Model'!C19+3)+'DCF Model'!G45/(1+$B22)^('DCF Model'!C19+4)+('DCF Model'!G39+'DCF Model'!G42)*G$17/(1+$B22)^('DCF Model'!C19+4)-'DCF Model'!C16)*1000000/'DCF Model'!C15,0),"") -> 1534 | H22: =IFERROR(ROUND(('DCF Model'!C45/(1+$B22)^('DCF Model'!C19+0)+'DCF Model'!D45/(1+$B22)^('DCF Model'!C19+1)+'DCF Model'!E45/(1+$B22)^('DCF Model'!C19+2)+'DCF Model'!F45/(1+$B22)^('DCF Model'!C19+3)+'DCF Model'!G45/(1+$B22)^('DCF Model'!C19+4)+('DCF Model'!G39+'DCF Model'!G42)*H$17/(1+$B22)^('DCF Model'!C19+4)-'DCF Model'!C16)*1000000/'DCF Model'!C15,0),"") -> 1639 | I22: =IFERROR(ROUND(('DCF Model'!C45/(1+$B22)^('DCF Model'!C19+0)+'DCF Model'!D45/(1+$B22)^('DCF Model'!C19+1)+'DCF Model'!E45/(1+$B22)^('DCF Model'!C19+2)+'DCF Model'!F45/(1+$B22)^('DCF Model'!C19+3)+'DCF Model'!G45/(1+$B22)^('DCF Model'!C19+4)+('DCF Model'!G39+'DCF Model'!G42)*I$17/(1+$B22)^('DCF Model'!C19+4)-'DCF Model'!C16)*1000000/'DCF Model'!C15,0),"") -> 1744
B23: =$C$3+0.01 -> 0.1639865 | C23: =IFERROR(ROUND(('DCF Model'!C45/(1+$B23)^('DCF Model'!C19+0)+'DCF Model'!D45/(1+$B23)^('DCF Model'!C19+1)+'DCF Model'!E45/(1+$B23)^('DCF Model'!C19+2)+'DCF Model'!F45/(1+$B23)^('DCF Model'!C19+3)+'DCF Model'!G45/(1+$B23)^('DCF Model'!C19+4)+('DCF Model'!G39+'DCF Model'!G42)*C$17/(1+$B23)^('DCF Model'!C19+4)-'DCF Model'!C16)*1000000/'DCF Model'!C15,0),"") -> 1097 | D23: =IFERROR(ROUND(('DCF Model'!C45/(1+$B23)^('DCF Model'!C19+0)+'DCF Model'!D45/(1+$B23)^('DCF Model'!C19+1)+'DCF Model'!E45/(1+$B23)^('DCF Model'!C19+2)+'DCF Model'!F45/(1+$B23)^('DCF Model'!C19+3)+'DCF Model'!G45/(1+$B23)^('DCF Model'!C19+4)+('DCF Model'!G39+'DCF Model'!G42)*D$17/(1+$B23)^('DCF Model'!C19+4)-'DCF Model'!C16)*1000000/'DCF Model'!C15,0),"") -> 1200 | E23: =IFERROR(ROUND(('DCF Model'!C45/(1+$B23)^('DCF Model'!C19+0)+'DCF Model'!D45/(1+$B23)^('DCF Model'!C19+1)+'DCF Model'!E45/(1+$B23)^('DCF Model'!C19+2)+'DCF Model'!F45/(1+$B23)^('DCF Model'!C19+3)+'DCF Model'!G45/(1+$B23)^('DCF Model'!C19+4)+('DCF Model'!G39+'DCF Model'!G42)*E$17/(1+$B23)^('DCF Model'!C19+4)-'DCF Model'!C16)*1000000/'DCF Model'!C15,0),"") -> 1303 | F23: =IFERROR(ROUND(('DCF Model'!C45/(1+$B23)^('DCF Model'!C19+0)+'DCF Model'!D45/(1+$B23)^('DCF Model'!C19+1)+'DCF Model'!E45/(1+$B23)^('DCF Model'!C19+2)+'DCF Model'!F45/(1+$B23)^('DCF Model'!C19+3)+'DCF Model'!G45/(1+$B23)^('DCF Model'!C19+4)+('DCF Model'!G39+'DCF Model'!G42)*F$17/(1+$B23)^('DCF Model'!C19+4)-'DCF Model'!C16)*1000000/'DCF Model'!C15,0),"") -> 1405 | G23: =IFERROR(ROUND(('DCF Model'!C45/(1+$B23)^('DCF Model'!C19+0)+'DCF Model'!D45/(1+$B23)^('DCF Model'!C19+1)+'DCF Model'!E45/(1+$B23)^('DCF Model'!C19+2)+'DCF Model'!F45/(1+$B23)^('DCF Model'!C19+3)+'DCF Model'!G45/(1+$B23)^('DCF Model'!C19+4)+('DCF Model'!G39+'DCF Model'!G42)*G$17/(1+$B23)^('DCF Model'!C19+4)-'DCF Model'!C16)*1000000/'DCF Model'!C15,0),"") -> 1508 | H23: =IFERROR(ROUND(('DCF Model'!C45/(1+$B23)^('DCF Model'!C19+0)+'DCF Model'!D45/(1+$B23)^('DCF Model'!C19+1)+'DCF Model'!E45/(1+$B23)^('DCF Model'!C19+2)+'DCF Model'!F45/(1+$B23)^('DCF Model'!C19+3)+'DCF Model'!G45/(1+$B23)^('DCF Model'!C19+4)+('DCF Model'!G39+'DCF Model'!G42)*H$17/(1+$B23)^('DCF Model'!C19+4)-'DCF Model'!C16)*1000000/'DCF Model'!C15,0),"") -> 1611 | I23: =IFERROR(ROUND(('DCF Model'!C45/(1+$B23)^('DCF Model'!C19+0)+'DCF Model'!D45/(1+$B23)^('DCF Model'!C19+1)+'DCF Model'!E45/(1+$B23)^('DCF Model'!C19+2)+'DCF Model'!F45/(1+$B23)^('DCF Model'!C19+3)+'DCF Model'!G45/(1+$B23)^('DCF Model'!C19+4)+('DCF Model'!G39+'DCF Model'!G42)*I$17/(1+$B23)^('DCF Model'!C19+4)-'DCF Model'!C16)*1000000/'DCF Model'!C15,0),"") -> 1714
B24: =$C$3+0.015 -> 0.1689865 | C24: =IFERROR(ROUND(('DCF Model'!C45/(1+$B24)^('DCF Model'!C19+0)+'DCF Model'!D45/(1+$B24)^('DCF Model'!C19+1)+'DCF Model'!E45/(1+$B24)^('DCF Model'!C19+2)+'DCF Model'!F45/(1+$B24)^('DCF Model'!C19+3)+'DCF Model'!G45/(1+$B24)^('DCF Model'!C19+4)+('DCF Model'!G39+'DCF Model'!G42)*C$17/(1+$B24)^('DCF Model'!C19+4)-'DCF Model'!C16)*1000000/'DCF Model'!C15,0),"") -> 1081 | D24: =IFERROR(ROUND(('DCF Model'!C45/(1+$B24)^('DCF Model'!C19+0)+'DCF Model'!D45/(1+$B24)^('DCF Model'!C19+1)+'DCF Model'!E45/(1+$B24)^('DCF Model'!C19+2)+'DCF Model'!F45/(1+$B24)^('DCF Model'!C19+3)+'DCF Model'!G45/(1+$B24)^('DCF Model'!C19+4)+('DCF Model'!G39+'DCF Model'!G42)*D$17/(1+$B24)^('DCF Model'!C19+4)-'DCF Model'!C16)*1000000/'DCF Model'!C15,0),"") -> 1182 | E24: =IFERROR(ROUND(('DCF Model'!C45/(1+$B24)^('DCF Model'!C19+0)+'DCF Model'!D45/(1+$B24)^('DCF Model'!C19+1)+'DCF Model'!E45/(1+$B24)^('DCF Model'!C19+2)+'DCF Model'!F45/(1+$B24)^('DCF Model'!C19+3)+'DCF Model'!G45/(1+$B24)^('DCF Model'!C19+4)+('DCF Model'!G39+'DCF Model'!G42)*E$17/(1+$B24)^('DCF Model'!C19+4)-'DCF Model'!C16)*1000000/'DCF Model'!C15,0),"") -> 1282 | F24: =IFERROR(ROUND(('DCF Model'!C45/(1+$B24)^('DCF Model'!C19+0)+'DCF Model'!D45/(1+$B24)^('DCF Model'!C19+1)+'DCF Model'!E45/(1+$B24)^('DCF Model'!C19+2)+'DCF Model'!F45/(1+$B24)^('DCF Model'!C19+3)+'DCF Model'!G45/(1+$B24)^('DCF Model'!C19+4)+('DCF Model'!G39+'DCF Model'!G42)*F$17/(1+$B24)^('DCF Model'!C19+4)-'DCF Model'!C16)*1000000/'DCF Model'!C15,0),"") -> 1383 | G24: =IFERROR(ROUND(('DCF Model'!C45/(1+$B24)^('DCF Model'!C19+0)+'DCF Model'!D45/(1+$B24)^('DCF Model'!C19+1)+'DCF Model'!E45/(1+$B24)^('DCF Model'!C19+2)+'DCF Model'!F45/(1+$B24)^('DCF Model'!C19+3)+'DCF Model'!G45/(1+$B24)^('DCF Model'!C19+4)+('DCF Model'!G39+'DCF Model'!G42)*G$17/(1+$B24)^('DCF Model'!C19+4)-'DCF Model'!C16)*1000000/'DCF Model'!C15,0),"") -> 1483 | H24: =IFERROR(ROUND(('DCF Model'!C45/(1+$B24)^('DCF Model'!C19+0)+'DCF Model'!D45/(1+$B24)^('DCF Model'!C19+1)+'DCF Model'!E45/(1+$B24)^('DCF Model'!C19+2)+'DCF Model'!F45/(1+$B24)^('DCF Model'!C19+3)+'DCF Model'!G45/(1+$B24)^('DCF Model'!C19+4)+('DCF Model'!G39+'DCF Model'!G42)*H$17/(1+$B24)^('DCF Model'!C19+4)-'DCF Model'!C16)*1000000/'DCF Model'!C15,0),"") -> 1584 | I24: =IFERROR(ROUND(('DCF Model'!C45/(1+$B24)^('DCF Model'!C19+0)+'DCF Model'!D45/(1+$B24)^('DCF Model'!C19+1)+'DCF Model'!E45/(1+$B24)^('DCF Model'!C19+2)+'DCF Model'!F45/(1+$B24)^('DCF Model'!C19+3)+'DCF Model'!G45/(1+$B24)^('DCF Model'!C19+4)+('DCF Model'!G39+'DCF Model'!G42)*I$17/(1+$B24)^('DCF Model'!C19+4)-'DCF Model'!C16)*1000000/'DCF Model'!C15,0),"") -> 1684
B26: All values dynamically linked to DCF Model. Headers auto-center on current WACC / Terminal g / Exit Multiple.

Sheet Adjustments Log
B2: Adjustments Log - Tamagawa Holdings
B4: 日付 | C4: セル | D4: 変更内容 | E4: 理由 | F4: 元の値 | G4: 状態
B5: 2026-09-14 | C5: - | D5: Generated by pipeline on 2026-09-14 10:51, template rev 5c8a57d | E5: 初期生成（手修正なし） | F5: - | G5: generated
B6: 2026-09-14 | C6: 全シート(単位) | D6: 原典の決算短信・有報・半期報告書は【千円】表記。本モデルは全て【百万円】に換算済み | E6: 桁事故の温床のため冒頭に明示。相互検算: 半期報告書 売上収益3,742,889千円 = 3,742.9百万円、営業利益751,607千円 = 751.6、有報FY2025/10 支払利息58,405千円 = 58.4。プロンプト入力表(百万円換算済み)と一致。 | F6: - | G6: 確定
B7: 2026-09-14 | C7: 全シート(比較可能性の制約) | D7: 時系列は二重に断絶: (1) IFRS任意適用(移行日2024-11-01、FY2026/10 Q1から) (2) 決算期変更(FY2024/10 = 2024-04-01〜10-31 の7ヶ月変則決算) | E7: Financial Statements の FY2023/3・FY2024/3・FY2024/10(7M)・FY2025/10 は J-GAAP、FY2026/10E は IFRS 推定。7ヶ月と12ヶ月、J-GAAP と IFRS を並べた前年比は無意味であり、成長率行を指標として読まないこと。hist_years のラベルに (7M) と E を付して区別。Segment Bridge の4列(7M J-GAAP / 12M J-GAAP / H1 IFRS x2)も時系列ではない旨を冒頭注記。LTM 6,754 も GAAP 混在の近似。 | F7: - | G7: 設計判断
B8: 2026-09-14 | C8: DCF Model!C15 / Executive Summary | D8: 株価・株数の基準日整合チェック(プロンプト要確認事項): 株式分割なし。株数9,121,192株を採用(プロンプト指定9,182,700株から変更、ユーザー承認済み) | E8: (1) 2026-06-04の2,372円→1,530円は実際の値下がり: Yahoo 年初来安値696円(1/5)・高値2,496円(6/3)・9/11終値1,526円、同期間の株数は8,912,700→9,182,700(+3%)で分割の痕跡なし。社長名『投資家の皆さまへ』(2026-07-21)は業績予想・事業計画に重大な変更なしと表明。(2) 株数増はMSワラント(Cantor Fitzgerald Europe 宛 第15〜17回、計1,626,700株)の行使で、第16回は2026-05-12、第17回は05-18に全行使完了(残0)。(3) 不整合A: 9,182,700株は自己株61,508株を含む → 控除。不整合B: 6/15株数に含まれる5月行使265,100株の払込金251.7百万円が4/30 BSのネットキャッシュに未計上 → net debt に加算。以上をユーザーに報告し『流通株+現金補正』の承認を得てからモデル化した。 | F8: 9,182,700株 | G8: 確定(ユーザー承認)
B9: 2026-09-14 | C9: DCF Model!C15(残差4,900株) | D9: 4/30発行済8,912,700 + 第16回104,300 + 第17回160,800 = 9,177,800 と 6/15提出日 9,182,700 の差4,900株の出所が未特定 | E9: 第13回(行使期間2026-03-31終了)・第14回新株予約権の行使と推定。払込金は未特定のため現金に加算していない(影響は1株あたり1円未満)。第14回の未行使残(潜在株式)も未確認 — H1の希薄化性潜在株式245,102株は期中平均ベースで、MSワラント完了後の残存数は不明。 | F9: - | G9: 要確認
B10: 2026-09-14 | C10: DCF Model!C16 | D10: Net Debt = -2,756(有利子負債3,545.0 − 現金3,795.3 − 5月払込251.7 − Addvalue株2,254.3) | E10: 【Addvalue二重計上回避ロジック】海外現地法人保有のSGX上場 Addvalue Technologies 株125,802,352株(2026-04-30公正価値2,254.3、レベル1、FVTPL)を非事業資産として現金同等に EV から控除する。同時に、H1金融収益1,595.5(評価益)は正常化EBIT・正常化純利益・core_net_income・Comps自社行から全額除外する。評価益を利益に残したまま資産も控除すると同じ価値を二度数えるため、『利益から除外・資産で一度だけ控除』に統一。素のEV(非控除)と50%評価ケースは Segment Bridge 表2に生きた数式で併記し、表2の検算行(Reverse DCF!C10 との差=0)で DCF Model!C16 との整合を監視する。 | F10: プロンプト: 素のEV 13,799.2 / 控除後EV 11,545.2(株数9,182,700・4/30現金ベース) | G10: 設計判断
B11: 2026-09-14 | C11: DCF Model!C16(Addvalue 時価) | D11: Addvalue株の控除額は2026-04-30の開示公正価値2,254.3を主値とした(ユーザー承認)。2026-09-14時点の時価は未確定 | E11: Web検索では直近株価 SGD 0.14(日付未確認)。4/30評価額の1株あたりは約17.9円。SGD/JPY と日付付き株価を確認のうえ、Q3短信(7/31時点の評価額が開示される見込み)で差し替える。週次約9%動く銘柄で、50%評価ケースのEVと必要利益を Segment Bridge 表2に併記。 | F11: - | G11: 要確認
B12: 2026-09-14 | C12: DCF Model!C16(Addvalue 税効果) | D12: Addvalue控除は税効果控除前(グロス)の2,254.3 | E12: H1に繰延税金負債が97.3→376.0(+278.7)増加しており評価益への繰延税金と解される。売却時の税流出を控除すると控除額は約1,976(1株あたり約-30円)。プロンプト指示(2,254控除)に従いグロスを主値とし、差額を未解決として残す。 | F12: - | G12: 要確認
B13: 2026-09-14 | C13: DCF Model!C6 | D13: Tax Rate = 30.0%(正常化税率) | E13: H1実効税率20.6%(475.4/2,307.9)は評価益の繰延税金を含み正常値として使えない。国内法定実効税率約30.6%を丸めた。海外子会社(ベトナム工場等)の軽課は未反映。 | F13: H1実効税率 20.6% | G13: 推定・要確認
B14: 2026-09-14 | C14: DCF Model!C7 | D14: Risk-Free Rate = 3.00% | E14: 財務省 jgbcm.csv 10年債 2.987%(2026-09-11)を丸め。 | F14: テンプレ既定 2.2% | G14: 確定
B15: 2026-09-14 | C15: DCF Model!C8 | D15: Beta raw = 1.436(Blume調整後 1.292) | E15: 6838 週次リターン104週(〜2026-08-31、screener.db prices)を TOPIX に回帰、相関0.379。1年1.775 / 3年1.267。yfinance は venv の numpy DLL がアプリケーション制御ポリシーでブロックされ使用不可のため自前回帰。MSワラント行使期の需給が β を押し上げている可能性あり。 | F15: yfinance 取得不能 | G15: 推定
... B37: 2026-09-14 | C37: Executive Summary(DRAFT) | D37: 本モデルは DRAFT。chat側検証 → 手修正 → ユーザー承認後に FINAL 化 | E37: 手順書v2 §6-3 / 標準メモ§2。 | F37: - | G37: DRAFT
B39: Pipeline Metadata (do not edit — read by scripts/validate_output.py)
B40: key | C40: value
B41: annual_doc_ids | C41: 2025-10-31=S100XHR9, 2024-10-31=S100V5E9, 2023-10-31=S100TV0O, 2022-10-31=S100R5MN, 2021-10-31=S100OBOM
B42: auto_log_entries | C42: 2
B43: beta_adopted_c8 | C43: 1.2921
B44: beta_basis | C44: Blume: 0.67 x 1.436 + 0.33 x 1.00 = 1.292
B45: beta_blume_adjusted | C45: 1.2921
B46: beta_clamped | C46: no
B47: beta_raw | C47: 1.436
B48: capex_pct_basis | C48: explicit_override
B49: capex_pct_c5 | C49: 0.06
B50: capex_pct_hist3yr | C50: 0.086905
B51: company_name | C51: Tamagawa Holdings
... B96: ticker | C96: 6838.T

Sheet Segment Bridge
B2: Segment Bridge - Tamagawa HD (6838)
B3: Two reportable segments: Electronic & Communication Equipment (radio, measurement, information and industrial equipment; government and 5G/mobile infrastructure) and Renewable Energy (small wind / solar plant sales and power sales). All figures JPY mn; the source filings are in JPY thousands.
B4: COMPARABILITY WARNING: the four columns are NOT a time series. FY2024/10 is a 7-month transition period (Apr-Oct 2024) under J-GAAP; FY2025/10 is 12 months under J-GAAP; the two H1 columns are 6 months under IFRS (transition date 2024-11-01). No growth rate is computed across these columns on purpose. Margins within a column are comparable; growth between columns is not.
B5: Segment profit is operating-profit based. The adjustment row is disclosed group overhead (plus unrealised-profit eliminations), so the profit bridge closes to the disclosed consolidated operating profit.
B6: Informational sheet: no cell on the DCF Model sheet references it. Tables 2-5 below reference 'Reverse DCF' and hold the Q3 replacement cells, the Addvalue EV bridge, the NWC decomposition and the normalisation bridge.
B8: 1. Segment Revenue (JPY mn)
B9: Segment | C9: FY2024/10 (7M) J-GAAP | D9: FY2025/10 J-GAAP | E9: H1 FY2025/10 IFRS | F9: H1 FY2026/10 IFRS | G9: Note
B10: Electronic & Communication Equipment 電子・通信用機器 | C10: 2096.22 | D10: 5029.48 | E10: 2254.5 | F10: 3449.48 | G10: Main customers FY2025/10: NEC 1,331.6 / Toshiba 857.6. H1 FY2026 revenue split: government 2,089.1, mobile infrastructure 769.0, public projects 386.5, FA/measurement/other 204.9.
B11: Renewable Energy 再生可能エネルギー | C11: 260.2 | D11: 558.49 | E11: 322.27 | F11: 293.41 | G11: Power sales plus plant sales. Flores (Indonesia) small-hydro and the Miyama grid battery (grid-connected Jul-2026, handed over 2026-08-31) are not yet in these columns.
B12: Segment total セグメント計 | C12: =SUM(C10:C11) -> 2356.42 | D12: =SUM(D10:D11) -> 5587.97 | E12: =SUM(E10:E11) -> 2576.77 | F12: =SUM(F10:F11) -> 3742.89
B13: Adjustment 調整額 (内部売上高消去等) | C13: =2356.42-C12 -> 0 | D13: =5587.97-D12 -> 0 | E13: =2576.77-E12 -> 0 | F13: =3742.89-F12 -> 0 | G13: No inter-segment revenue is disclosed in any period, so the derived adjustment is zero.
B14: Consolidated revenue 連結売上高 | C14: 2356.42 | D14: 5587.97 | E14: 2576.77 | F14: 3742.89 | G14: Disclosed consolidated revenue (J-GAAP 売上高 / IFRS 売上収益).
B16: 2. Segment Profit to Consolidated Operating Profit (JPY mn)
B17: Segment | C17: FY2024/10 (7M) J-GAAP | D17: FY2025/10 J-GAAP | E17: H1 FY2025/10 IFRS | F17: H1 FY2026/10 IFRS | G17: Note
B18: Electronic & Communication Equipment 電子・通信用機器 | C18: 202 | D18: 574.04 | E18: 313.33 | F18: 900.28
B19: Renewable Energy 再生可能エネルギー | C19: -30.21 | D19: 74.99 | E19: 79.53 | F19: 83.35
B20: Segment profit total セグメント利益計 | C20: =SUM(C18:C19) -> 171.79 | D20: =SUM(D18:D19) -> 649.03 | E20: =SUM(E18:E19) -> 392.86 | F20: =SUM(F18:F19) -> 983.63
B21: Adjustment 調整額 (全社費用・未実現利益消去) | C21: -219.56 | D21: -370.13 | E21: -192.56 | F21: -232.02
B22: Bridged total 計算値 | C22: =C20+C21 -> -47.77 | D22: =D20+D21 -> 278.9 | E22: =E20+E21 -> 200.3 | F22: =F20+F21 -> 751.61
B23: Consolidated operating profit 連結営業利益 (開示値) | C23: -47.77 | D23: 278.9 | E23: 200.31 | F23: 751.61 | G23: Disclosed consolidated operating profit. IFRS operating profit = 事業利益 at present (company note: no equity-method or non-recurring items).
B24: Variance 差異 (計算値 - 開示値) | C24: =C22-C23 -> 0 | D24: =D22-D23 -> 0 | E24: =E22-E23 -> -0.01 | F24: =F22-F23 -> 0 | G24: Rounding of the disclosed JPY mn figures. A non-zero variance is shown rather than forced to zero.
B26: 3. Segment Operating Margin
B27: Segment | C27: FY2024/10 (7M) J-GAAP | D27: FY2025/10 J-GAAP | E27: H1 FY2025/10 IFRS | F27: H1 FY2026/10 IFRS | G27: Note
B28: Electronic & Communication Equipment 電子・通信用機器 | C28: =IFERROR(C18/C10,"N/A") -> 0.096363931 | D28: =IFERROR(D18/D10,"N/A") -> 0.11413506 | E28: =IFERROR(E18/E10,"N/A") -> 0.13897982 | F28: =IFERROR(F18/F10,"N/A") -> 0.26099006
B29: Renewable Energy 再生可能エネルギー | C29: =IFERROR(C19/C11,"N/A") -> -0.116103 | D29: =IFERROR(D19/D11,"N/A") -> 0.13427277 | E29: =IFERROR(E19/E11,"N/A") -> 0.24678065 | F29: =IFERROR(F19/F11,"N/A") -> 0.28407348
B30: Consolidated 連結 | C30: =IFERROR(C23/C14,"N/A") -> -0.020272277 | D30: =IFERROR(D23/D14,"N/A") -> 0.049910791 | E30: =IFERROR(E23/E14,"N/A") -> 0.077736857 | F30: =IFERROR(F23/F14,"N/A") -> 0.20081007
B32: 4. Depreciation & Amortisation by Segment (JPY mn)
B33: Segment | C33: FY2024/10 (7M) J-GAAP | D33: FY2025/10 J-GAAP | E33: H1 FY2025/10 IFRS | F33: H1 FY2026/10 IFRS | G33: Note
B34: Electronic & Communication Equipment 電子・通信用機器 | C34: 72.1 | D34: 181.98
B35: Renewable Energy 再生可能エネルギー | C35: 95.25 | D35: 161.75
B36: Segment D&A total 計 | C36: =SUM(C34:C35) -> 167.35 | D36: =SUM(D34:D35) -> 343.73
B37: Adjustment 調整額 (D&A) | C37: 3.51 | D37: 4.03 | G37: Segment D&A is not disclosed in the IFRS interim note; the H1 consolidated D&A (CF statement) is shown on the consolidated row only, so the H1 D&A bridge is intentionally open.
B38: Bridged total 計算値 | C38: =C36+C37 -> 170.86 | D38: =D36+D37 -> 347.76
B39: Consolidated D&A 連結減価償却費 (開示値) | C39: 170.86 | D39: 347.77 | E39: 197.4 | F39: 188.6 | G39: CF-statement depreciation and amortisation.
B40: Variance 差異 (計算値 - 開示値) | C40: =C38-C39 -> 0 | D40: =D38-D39 -> -0.01 | E40: =E38-E39 -> -197.4 | F40: =F38-F39 -> -188.6 | G40: Rounding of the disclosed JPY mn figures. A non-zero variance is shown rather than forced to zero.
B41: Consolidated EBITDA (連結営業利益 + 連結D&A) | C41: =IFERROR(C23+C39,"N/A") -> 123.09 | D41: =IFERROR(D23+D39,"N/A") -> 626.67 | E41: =IFERROR(E23+E39,"N/A") -> 397.71 | F41: =IFERROR(F23+F39,"N/A") -> 940.21 | G41: This is the core_ebitda basis used on 'Comps Analysis'.
B43: 5. Single-quarter decomposition and Q3 replacement cells (Q3 results due 2026-09-14 - NOT yet loaded)
B44: Item | C44: Q1 FY26 (Nov-Jan) | D44: H1 FY26 cumulative | E44: Q2 single (derived) | F44: 9M FY26 cumulative - INPUT | G44: Q3 single (derived) | H44: Note
B45: Revenue 売上収益 | C45: 2051 | D45: 3742.89 | E45: =D45-C45 -> 1691.89 | F45: - | G45: =IF(ISNUMBER(F45),F45-D45,"未入力") -> 未入力 | H45: Q2 single 1,691.9 = H1 - Q1 (-17.5% vs Q1). Type the 9M cumulative figure into column F over the dash when the Q3 短信 is released.
B46: Operating profit 営業利益 | C46: 496 | D46: 751.61 | E46: =D46-C46 -> 255.61 | F46: - | G46: =IF(ISNUMBER(F46),F46-D46,"未入力") -> 未入力 | H46: Q2 single 255.6. Do not annualise the H1 cumulative figure (3441 lesson).
B47: Operating margin | C47: =C46/C45 -> 0.24183325 | D47: =D46/D45 -> 0.20081007 | E47: =E46/E45 -> 0.15107956 | F47: =IF(ISNUMBER(F45),F46/F45,"未入力") -> 未入力 | G47: =IF(ISNUMBER(G45),G46/G45,"未入力") -> 未入力 | H47: Q1 24.2% -> Q2 single 15.1% (about -9pt). Base scenario anchors the steady-state margin on the Q2 single figure.
B48: Government revenue 官公庁向け売上 | C48: 1240 | D48: 2089.08 | E48: =D48-C48 -> 849.08 | F48: - | G48: =IF(ISNUMBER(F48),F48-D48,"未入力") -> 未入力 | H48: Q1 1,240 (about 5.1x YoY). Q2 single derived 849.1. The 9M figure is in the Q3 revenue-disaggregation note.
B49: E&C segment profit 電子・通信セグメント利益 | C49: 555 | D49: 900.28 | E49: =D49-C49 -> 345.28 | F49: - | G49: =IF(ISNUMBER(F49),F49-D49,"未入力") -> 未入力 | H49: Q1 555 (3.7x YoY). Q2 single derived 345.3.
B50: Q2 single operating profit x4 (annualised run-rate) | C50: - | D50: - | E50: =E46*4 -> 1022.44 | F50: - | G50: =IF(ISNUMBER(G46),G46*4,"未入力") -> 未入力 | H50: 1,022.4 = the Reverse DCF peak_op input. Replace the Reverse DCF C15 input with the Q3 single x4 figure once column G is populated.
B51: Implied H2 operating profit if FY guidance 820 holds | C51: - | D51: =820-D46 -> 68.39 | E51: - | F51: =IF(ISNUMBER(F46),820-F46,"未入力") -> 未入力 | G51: - | H51: 68.4 for the whole of H2 = guidance is stale (S5 type). H1 progress 91.7% of 820.
B52: H1 progress vs FY guidance (OP 820 / revenue 6,950) | C52: =C46/820 -> 0.60487805 | D52: =D46/820 -> 0.91659756 | E52: =D45/6950 -> 0.53854532 | F52: =IF(ISNUMBER(F46),F46/820,"未入力") -> 未入力 | G52: - | H52: Column E of this row is H1 REVENUE progress (53.9%), the others are operating-profit progress.
B53: Blue cells are inputs. Column F shows '-' until the Q3 figures are typed in; every derived cell reads 未入力 until then. Adjustments Log records that the Q3 results were NOT loaded in this DRAFT (built 2026-09-14 10:15 JST, TDnet list had no 6838 entry).
B55: 6. EV bridge - Addvalue deduction (double-count guard) and alternative EVs, live off 'Reverse DCF' (Block E substitute)
B56: Item | C56: JPY mn | D56: Note
B57: Market capitalisation (live) | C57: ='Reverse DCF'!C8 -> 13955.424 | D57: Price x 9,121,192 shares (issued 9,182,700 at 2026-06-15 less 61,508 treasury).
B58: Interest-bearing debt 2026-04-30 (borrowings 3,338.9 + leases 206.1) | C58: 3545 | D58: IFRS BS. Leases included, consistent with IFRS EBITDA.
B59: Cash and cash equivalents 2026-04-30 | C59: -3795.3 | D59: IFRS BS.
B60: May-2026 warrant proceeds not yet in the 04-30 BS | C60: -251.7 | D60: 16th series 104,300 sh x 764 = 79.7; 17th series 160,800 sh x 1,070 = 172.1. Pro forma so that cash and share count share one basis date.
B61: BARE EV - Addvalue NOT deducted | C61: =SUM(C57:C60) -> 13453.424 | D61: Reference only. Mixing this EV with normalised (gain-excluded) earnings would undercount the stake.
B62: Addvalue Technologies stake, FV 2026-04-30 (Level 1) | C62: 2254.3 | D62: 125,802,352 SGX shares, FVTPL. H1 FV gain 1,595.5 booked in finance income.
B63: PRIMARY EV - Addvalue deducted (= model) | C63: =C61-C62 -> 11199.124 | D63: Gain removed from earnings AND stake deducted from EV, once each. Never add the gain back to EBIT and deduct the stake at the same time as well.
B64: Check: primary EV less 'Reverse DCF'!C10 (must be 0) | C64: ='Reverse DCF'!C10-C63 -> 0 | D64: Non-zero means DCF Model!C16 net debt and this bridge have drifted apart.
B65: EV if Addvalue is marked at 50% | C65: =C61-0.5*C62 -> 12326.274 | D65: SGX small cap, weekly moves of about 9%. 4/30 value per share about JPY 17.9.
B66: Block A required steady OP (immediate) - BARE EV | C66: =C61*('Reverse DCF'!C11-'Reverse DCF'!C12)/(1-'Reverse DCF'!C13) -> 2767.302 | D66: EV x (WACC - g) / (1 - t).
B67: Block A required steady OP (immediate) - PRIMARY EV | C67: ='Reverse DCF'!C25 -> 2303.6038 | D67: Live link.
B68: Block A required steady OP (immediate) - Addvalue 50% | C68: =C65*('Reverse DCF'!C11-'Reverse DCF'!C12)/(1-'Reverse DCF'!C13) -> 2535.4529 | D68: Same formula on the 50% EV.
B69: Block B-3 required steady OP, N=5, model WACC - BARE EV | C69: =(C61/(1-'Reverse DCF'!C13)-'Reverse DCF'!C14*'Reverse DCF'!F39)/'Reverse DCF'!F44 -> 3435.9636 | D69: OP* = (EV/(1-t) - OP0 x (A-B)) / (B+TVF), factors from Reverse DCF F39 / F44.
B70: Block B-3 required steady OP, N=5, model WACC - PRIMARY EV | C70: ='Reverse DCF'!F49 -> 2820.3827 | D70: Live link.
B71: Block B-3 required steady OP, N=5, model WACC - Addvalue 50% | C71: =(C65/(1-'Reverse DCF'!C13)-'Reverse DCF'!C14*'Reverse DCF'!F39)/'Reverse DCF'!F44 -> 3128.1731 | D71: Same formula on the 50% EV.
B72: Primary B-3 (N=5) as % of FY guidance OP 820 | C72: =C70/820 -> 3.4394911 | D72: The headline multiple asked in the prompt.
B73: Primary B-3 (N=5) as % of Q2 single x4 (1,022.4) | C73: =C70/1022.4 -> 2.7585903 | D73: Against the Q2 single-quarter run-rate.
B74: Bare-EV B-3 (N=5) as % of FY guidance OP 820 | C74: =C69/820 -> 4.1901995 | D74: Reference.
B75: Addvalue-50% B-3 (N=5) as % of FY guidance OP 820 | C75: =C71/820 -> 3.8148453 | D75: Reference.
B76: Primary Block A as % of FY guidance OP 820 | C76: =C67/820 -> 2.8092729 | D76: No-ramp floor.
B77: Gross deduction is the primary case per instruction. A deferred tax liability sits against the unrealised gain (DTL 97.3 -> 376.0 in H1, +278.7); deducting the stake net of that DTL would cut the deduction to about 1,976 (about JPY -30 per share). Recorded as 要確認 in the Adjustments Log.
B79: 7. NWC - work-in-process build: activity (COGS scale) vs days, plus order intake vs sales (J-GAAP)
B80: Item | C80: FY2024/10 end (7M) | D80: FY2025/10 end | E80: Change / derived | F80: Note
B81: Work in process 仕掛品 | C81: 1042.1 | D81: 1569.5 | E81: =D81/C81-1 -> 0.50609347 | F81: +50.6%.
B82: COGS run-rate (FY2024/10 = 7M x 12/7) | C82: =1644.9*12/7 -> 2819.8286 | D82: 3895.1 | E82: =D82/C82-1 -> 0.38132511 | F82: Annualising a 7-month period is an approximation (seasonality not removed) - 推定.
B83: WIP days (balance / COGS x 365) | C83: =C81/C82*365 -> 134.88994 | D83: =D81/D82*365 -> 147.07389 | E83: =D83/C83-1 -> 0.090325122 | F83: Days lengthened about 9%.
B84: Check: (1+COGS growth) x (1+days growth) - 1 | C84: - | D84: - | E84: =(1+E82)*(1+E83)-1 -> 0.50609347 | F84: Must equal the WIP growth in row 1.
B85: WIP increase explained by activity (COGS scale) | C85: - | D85: =C81*E82 -> 397.37889 | E85: =D85/(D81-C81) -> 0.75346775 | F85: Price and volume are inseparable here: COGS growth carries both material-price inflation and unit volume.
B86: WIP increase explained by longer days (build-up) | C86: - | D86: =(D81-C81)-D85 -> 130.02111 | E86: =D86/(D81-C81) -> 0.24653225 | F86: Ambiguous: for a build-to-order maker a longer WIP cycle can lead orders (mass-production ramp) or signal slippage (customer-supplied parts delayed one H1 FY26 project).
B87: Orders vs sales FY2025/10 (consolidated) | C87: 5588 | D87: 5787 | E87: =D87/C87-1 -> 0.035612026 | F87: Orders exceeded sales by 199 -> backlog build.
B88: Orders vs sales H1 FY2026 (consolidated) | C88: 3742.9 | D88: 4295 | E88: =D88/C88-1 -> 0.14750594 | F88: Book-to-bill 1.15. E&C segment: orders 3,881 vs sales 3,449.5 (prior-year H1 orders 2,460).
B89: Contract liabilities 契約負債 | C89: 30.1 | D89: 71.2 | E89: =D89/C89-1 -> 1.3654485 | F89: Advances up 2.4x - supports the order-led reading.
B90: Trade receivables incl. contract assets | C90: 1325.1 | D90: 2065.6 | E90: =D90/C90-1 -> 0.55882575 | F90: Unwound in H1 FY26 (IFRS receivables 2,021.2 -> 1,537.8), releasing +489.9 of operating CF.
B91: Verdict (両義判定): activity explains about three quarters of the WIP build and is order-backed (book-to-bill above 1, contract liabilities up). The days component is the part to watch; H1 FY26 inventories already fell 2,752.7 -> 2,573.5 (IFRS), so the build has started to convert.
B93: 8. Normalisation bridge - valuation gain and special items removed
B94: Item | C94: H1 FY2026 IFRS | D94: FY2026/10E | E94: Note
B95: Profit before tax (reported / company-implied) | C95: 2307.9 | D95: - | E95: H1 reported.
B96: Operating profit | C96: 751.61 | D96: 1236 | E96: FY = model estimate 1,236 (H1 actual 751.6 + H2 revenue 3,207.1 x Q2 single OPM 15.1%). Company guidance 事業利益 820 is stale.
B97: Less: Addvalue FV gain in finance income | C97: -1595.5 | D97: - | E97: Non-cash; H1 CF adds back 1,594.0.
B98: Finance income ex-gain less finance costs | C98: =C95+C97-C96 -> -39.21 | D98: -78.4 | E98: H1 derived. FY = 2 x H1 finance costs 39.2 (推定).
B99: Normalised profit before tax | C99: =C96+C98 -> 712.4 | D99: =D96+D98 -> 1157.6 | E99: Gain excluded in every period (FY2025/10 J-GAAP special gain 124.4 on securities also excluded).
B100: Normalised tax at 30% (推定・要確認) | C100: =-C99*0.3 -> -213.72 | D100: =-D99*0.3 -> -347.28 | E100: Reported H1 effective rate 20.6% (475.4 / 2,307.9) is distorted by the deferred tax on the gain.
B101: Normalised net profit | C101: =C99+C100 -> 498.68 | D101: =D99+D100 -> 810.32 | E101: FY2026/10E 810 is the Comps subject Net_Income, core_net_income and the normalized_net_income reference row.
B102: Reported profit attributable to owners | C102: 1832.4 | D102: 1835 | E102: FY = company forecast incl. the after-tax gain.
B103: Share of reported profit that is NOT operating | C103: =1-C101/C102 -> 0.72785418 | D103: =1-D101/D102 -> 0.55840872 | E103: About 73% of H1 profit is the Addvalue mark (normalised 499 vs reported 1,832).
B104: Normalised EPS on 9,121,192 shares (JPY) | C104: =C101*1000000/9121192 -> 54.672679 | D104: =D101*1000000/9121192 -> 88.839266 | E104: Reported basic EPS 253.57 used 7,226,437 weighted-average shares - never mix the two share counts.
B105: The EV deducts the Addvalue stake (table 2) and this bridge removes its gain from earnings, so the stake is counted exactly once.
B107: 9. Share count reconciliation (price / share basis-date gate, 2026-09-14)
B108: Item | C108: Shares | D108: Note
B109: Issued shares 2026-04-30 | C109: 8912700 | D109: Half-year report S100YBBW.
B110: 16th series MS warrant, May exercises (completed 2026-05-12) | C110: 104300 | D110: At JPY 764. Series fully exercised, 0 remaining.
...
