Workbook

Sheet Cover & Thesis
B2: SOTP Valuation Model
B3: Valuation Date: April 2026
B5: Investment Thesis
B6: IHI's consolidated valuation obscures value concentration in Aero segment. 76% of EV from Aerospace & Defense.
B10: Valuation Cross-Check
B11: Method | C11: Fair Value (¥) | D11: vs SOTP Base
B12: SOTP (Base Case) | C12: ='SOTP Valuation'!C29 | D12: —
B13: DCF — Perpetuity Growth | C13: 1982 | D13: =(C13-$C$12)/$C$12
B14: DCF — Exit Multiple | C14: 3463 | D14: =(C14-$C$12)/$C$12
B15: Comps — EV/EBITDA | C15: 3794 | D15: =(C15-$C$12)/$C$12
B16: Comps — PER | C16: 4973 | D16: =(C16-$C$12)/$C$12

Sheet Segment Data
B1: Segment Financial Data
B2: (¥ millions)
B4: Segment | C4: FY23 | D4: FY24 | E4: FY25E
B5: Aero, Space & Defense (航空・宇宙・防衛)
B6: Revenue | C6: 270400 | D6: 555700 | E6: 620000
B7: Operating Profit | C7: -102800 | D7: 122700 | E7: 130000
B8: OPM % | C8: =IF(C6=0,0,C7/C6) | D8: =IF(D6=0,0,D7/D6) | E8: =IF(E6=0,0,E7/E6)
B10: Resources, Energy & Environment (資源・エネルギー・環境)
B11: Revenue | C11: 404900 | D11: 411400 | E11: 370000
B12: Operating Profit | C12: 17700 | D12: 16100 | E12: 24000
B13: OPM % | C13: =IF(C11=0,0,C12/C11) | D13: =IF(D11=0,0,D12/D11) | E13: =IF(E11=0,0,E12/E11)
B15: Industrial Systems & General Machinery (産業システム・汎用機械)
B16: Revenue | C16: 466100 | D16: 484800 | E16: 440000
B17: Operating Profit | C17: 12700 | D17: 10800 | E17: 25000
B18: OPM % | C18: =IF(C16=0,0,C17/C16) | D18: =IF(D16=0,0,D17/D16) | E18: =IF(E16=0,0,E17/E16)
B20: Social Infrastructure (社会基盤)
B21: Revenue | C21: 154300 | D21: 146000 | E21: 140000
B22: Operating Profit | C22: 4900 | D22: -4200 | E22: 0
B23: OPM % | C23: =IF(C21=0,0,C22/C21) | D23: =IF(D21=0,0,D22/D21) | E23: =IF(E21=0,0,E22/E21)
B25: Consolidated Total
B26: Total Revenue | C26: =C6+C11+C16+C21 | D26: =D6+D11+D16+D21 | E26: =E6+E11+E16+E21
B27: Total Operating Profit | C27: =C7+C12+C17+C22 | D27: =D7+D12+D17+D22 | E27: =E7+E12+E17+E22
B28: Total OPM % | C28: =IF(C26=0,0,C27/C26) | D28: =IF(D26=0,0,D27/D26) | E28: =IF(E26=0,0,E27/E26)

Sheet Peer Comps
B1: Peer Comparable Analysis
B3: Aero, Space & Defense
B4: Company | C4: Ticker | D4: EV/EBITDA | E4: OPM % | F4: Mkt Cap ($B) | G4: Note
B5: Safran | C5: SAF.PA | D5: 20.5 | E5: 0.166 | F5: 130 | G5: CFM LEAP, MRO, Defense
B6: MTU Aero Engines | C6: MTX.DE | D6: 11.9 | E6: 0.199 | F6: 24 | G6: V2500/PW1100G partner
B7: Rolls-Royce | C7: RR.L | D7: 18 | E7: 0.15 | F7: 65 | G7: Large engine, V-shape recovery
B8: TransDigm | C8: TDG | D8: 25 | E8: 0.54 | F8: 75 | G8: Aftermarket monopoly — EXCLUDED
B9: Median | D9: =MEDIAN(D5,D6,D7)
B10: Selected Multiple | C10: Median of Safran/MTU/Rolls-Royce (excl. TransDigm) | D10: 18
B12: Resources, Energy & Environment
B13: Company | C13: Ticker | D13: EV/EBITDA | E13: OPM % | F13: Mkt Cap ($B) | G13: Note
B14: Siemens Energy | C14: ENR.DE | D14: 12 | E14: 0.06 | F14: 50 | G14: Gas turbine, grid
B15: MHI (Energy seg.) | C15: 7011.T | D15: 8 | E15: 0.05 | F15: 0 | G15: Comparable segment estimate
B16: Median | D16: =MEDIAN(D14,D15)
B17: Selected Multiple | C17: Energy equipment peers | D17: 8
B19: Industrial Systems & General Machinery
B20: Company | C20: Ticker | D20: EV/EBITDA | E20: OPM % | F20: Mkt Cap ($B) | G20: Note
B21: BorgWarner | C21: BWA | D21: 6.5 | E21: 0.1 | F21: 7 | G21: Turbocharger OEM
B22: Garrett Motion | C22: GTX | D22: 7 | E22: 0.15 | F22: 3 | G22: Turbocharger pure-play
B23: Median | D23: =MEDIAN(D21,D22)
B24: Selected Multiple | C24: Turbocharger/machinery blend | D24: 10
B26: Social Infrastructure
B27: Company | C27: Ticker | D27: EV/EBITDA | E27: OPM % | F27: Mkt Cap ($B) | G27: Note
B28: Yokogawa Bridge | C28: 5911.T | D28: 5.5 | E28: 0.04 | F28: 0 | G28: Bridge construction — low margin
B29: Median | D29: =MEDIAN(D28)
B30: Selected Multiple | C30: Infrastructure floor | D30: 6

Sheet SOTP Valuation
B1: SOTP Valuation
B2: (¥ millions unless noted)
B4: Segment | C4: OP (FY25E) | D4: D&A Alloc % | E4: D&A | F4: EBITDA | G4: Multiple (x) | H4: Segment EV
B5: Aero, Space & Defense | C5: ='Segment Data'!E7 | D5: 0.31 | E5: =B12*D5 | F5: =C5+E5 | G5: ='Peer Comps'!D10 | H5: =F5*G5
B6: Resources, Energy & Environment | C6: ='Segment Data'!E12 | D6: 0.3 | E6: =B12*D6 | F6: =C6+E6 | G6: ='Peer Comps'!D17 | H6: =F6*G6
B7: Industrial Systems & General Machinery | C7: ='Segment Data'!E17 | D7: 0.27 | E7: =B12*D7 | F7: =C7+E7 | G7: ='Peer Comps'!D24 | H7: =F7*G7
B8: Social Infrastructure | C8: ='Segment Data'!E22 | D8: 0.12 | E8: =B12*D8 | F8: =C8+E8 | G8: ='Peer Comps'!D30 | H8: =F8*G8
B9: Equity Method Investments | C9: 6200 | F9: =C9 | G9: 10 | H9: =F9*G9
B10: Total Segment EV | H10: =H5+H6+H7+H8+H9
B12: 70000 | C12: ← Consolidated D&A (input)
B14: EV Composition %
B15: Aero, Space & Defense | C15: =H5/H10
B16: Resources, Energy & Environment | C16: =H6/H10
B17: Industrial Systems & General Machinery | C17: =H7/H10
B18: Social Infrastructure | C18: =H8/H10
B20: Equity Bridge
B21: Total Enterprise Value | C21: =H10
B22: Conglomerate Discount | C22: 0
B23: Adjusted EV | C23: =C21*(1-C22)
B24: Less: Net Debt | C24: 360000
B25: Less: Minority Interest | C25: 27000
B26: Equity Value | C26: =C23-C24-C25
B27: Shares Outstanding (thousands) | C27: 151364
B28: Stock Split Ratio | C28: 7
B29: Fair Value Per Share (post-split) | C29: =C26*1000/C27/C28

Sheet Sensitivity
B1: Sensitivity Analysis
B3: Table 1: Aero, Space & Defense Multiple × Conglomerate Discount
B4: Fair Value (¥/share, post-split)
B5: Base Assumptions (do not edit)
B6: Aero, Space & Defense OP | C6: ='SOTP Valuation'!C5 | D6: ='SOTP Valuation'!E5 | E6: =C6+D6 | F6: ='SOTP Valuation'!G5
B7: Resources, Energy & Environment OP | C7: ='SOTP Valuation'!C6 | D7: ='SOTP Valuation'!E6 | E7: =C7+D7 | F7: ='SOTP Valuation'!G6
B8: Industrial Systems & General Machinery OP | C8: ='SOTP Valuation'!C7 | D8: ='SOTP Valuation'!E7 | E8: =C8+D8 | F8: ='SOTP Valuation'!G7
B9: Social Infrastructure OP | C9: ='SOTP Valuation'!C8 | D9: ='SOTP Valuation'!E8 | E9: =C9+D9 | F9: ='SOTP Valuation'!G8
B10: Equity Method EV | C10: ='SOTP Valuation'!H9
B11: Net Debt | C11: ='SOTP Valuation'!C24
B12: Minority Interest | C12: ='SOTP Valuation'!C25
B13: Shares (thousands) | C13: ='SOTP Valuation'!C27
B14: Split Ratio | C14: ='SOTP Valuation'!C28
B16: Aero, Space & Defense EV/EBITDA → | C16: 14 | D16: 16 | E16: 18 | F16: 20 | G16: 22 | H16: 25
B17: 0 | C17: =(($E$6*14+E7*F7+E8*F8+E9*F9+C10)*(1-$B17)-$C$11-$C$12)*1000/$C$13/$C$14 | D17: =(($E$6*16+E7*F7+E8*F8+E9*F9+C10)*(1-$B17)-$C$11-$C$12)*1000/$C$13/$C$14 | E17: =(($E$6*18+E7*F7+E8*F8+E9*F9+C10)*(1-$B17)-$C$11-$C$12)*1000/$C$13/$C$14 | F17: =(($E$6*20+E7*F7+E8*F8+E9*F9+C10)*(1-$B17)-$C$11-$C$12)*1000/$C$13/$C$14 | G17: =(($E$6*22+E7*F7+E8*F8+E9*F9+C10)*(1-$B17)-$C$11-$C$12)*1000/$C$13/$C$14 | H17: =(($E$6*25+E7*F7+E8*F8+E9*F9+C10)*(1-$B17)-$C$11-$C$12)*1000/$C$13/$C$14
B18: 0.05 | C18: =(($E$6*14+E7*F7+E8*F8+E9*F9+C10)*(1-$B18)-$C$11-$C$12)*1000/$C$13/$C$14 | D18: =(($E$6*16+E7*F7+E8*F8+E9*F9+C10)*(1-$B18)-$C$11-$C$12)*1000/$C$13/$C$14 | E18: =(($E$6*18+E7*F7+E8*F8+E9*F9+C10)*(1-$B18)-$C$11-$C$12)*1000/$C$13/$C$14 | F18: =(($E$6*20+E7*F7+E8*F8+E9*F9+C10)*(1-$B18)-$C$11-$C$12)*1000/$C$13/$C$14 | G18: =(($E$6*22+E7*F7+E8*F8+E9*F9+C10)*(1-$B18)-$C$11-$C$12)*1000/$C$13/$C$14 | H18: =(($E$6*25+E7*F7+E8*F8+E9*F9+C10)*(1-$B18)-$C$11-$C$12)*1000/$C$13/$C$14
B19: 0.1 | C19: =(($E$6*14+E7*F7+E8*F8+E9*F9+C10)*(1-$B19)-$C$11-$C$12)*1000/$C$13/$C$14 | D19: =(($E$6*16+E7*F7+E8*F8+E9*F9+C10)*(1-$B19)-$C$11-$C$12)*1000/$C$13/$C$14 | E19: =(($E$6*18+E7*F7+E8*F8+E9*F9+C10)*(1-$B19)-$C$11-$C$12)*1000/$C$13/$C$14 | F19: =(($E$6*20+E7*F7+E8*F8+E9*F9+C10)*(1-$B19)-$C$11-$C$12)*1000/$C$13/$C$14 | G19: =(($E$6*22+E7*F7+E8*F8+E9*F9+C10)*(1-$B19)-$C$11-$C$12)*1000/$C$13/$C$14 | H19: =(($E$6*25+E7*F7+E8*F8+E9*F9+C10)*(1-$B19)-$C$11-$C$12)*1000/$C$13/$C$14
B20: 0.15 | C20: =(($E$6*14+E7*F7+E8*F8+E9*F9+C10)*(1-$B20)-$C$11-$C$12)*1000/$C$13/$C$14 | D20: =(($E$6*16+E7*F7+E8*F8+E9*F9+C10)*(1-$B20)-$C$11-$C$12)*1000/$C$13/$C$14 | E20: =(($E$6*18+E7*F7+E8*F8+E9*F9+C10)*(1-$B20)-$C$11-$C$12)*1000/$C$13/$C$14 | F20: =(($E$6*20+E7*F7+E8*F8+E9*F9+C10)*(1-$B20)-$C$11-$C$12)*1000/$C$13/$C$14 | G20: =(($E$6*22+E7*F7+E8*F8+E9*F9+C10)*(1-$B20)-$C$11-$C$12)*1000/$C$13/$C$14 | H20: =(($E$6*25+E7*F7+E8*F8+E9*F9+C10)*(1-$B20)-$C$11-$C$12)*1000/$C$13/$C$14
B21: 0.2 | C21: =(($E$6*14+E7*F7+E8*F8+E9*F9+C10)*(1-$B21)-$C$11-$C$12)*1000/$C$13/$C$14 | D21: =(($E$6*16+E7*F7+E8*F8+E9*F9+C10)*(1-$B21)-$C$11-$C$12)*1000/$C$13/$C$14 | E21: =(($E$6*18+E7*F7+E8*F8+E9*F9+C10)*(1-$B21)-$C$11-$C$12)*1000/$C$13/$C$14 | F21: =(($E$6*20+E7*F7+E8*F8+E9*F9+C10)*(1-$B21)-$C$11-$C$12)*1000/$C$13/$C$14 | G21: =(($E$6*22+E7*F7+E8*F8+E9*F9+C10)*(1-$B21)-$C$11-$C$12)*1000/$C$13/$C$14 | H21: =(($E$6*25+E7*F7+E8*F8+E9*F9+C10)*(1-$B21)-$C$11-$C$12)*1000/$C$13/$C$14
B24: Table 2: Industrial Systems & General Machinery × Resources, Energy & Environment Multiple Sensitivity
B25: Fair Value (¥/share, post-split) — Base discount, base Aero multiple
B26: Industrial Systems & General Machinery ↓ / Resources, Energy & Environment → | C26: 6 | D26: 8 | E26: 10 | F26: 12
B27: 7 | C27: =(($E$8*$B27+$E$7*C$26+$E$6*$F$6+$E$9*$F$9+$C$10)*(1-0.0)-$C$11-$C$12)*1000/$C$13/$C$14 | D27: =(($E$8*$B27+$E$7*D$26+$E$6*$F$6+$E$9*$F$9+$C$10)*(1-0.0)-$C$11-$C$12)*1000/$C$13/$C$14 | E27: =(($E$8*$B27+$E$7*E$26+$E$6*$F$6+$E$9*$F$9+$C$10)*(1-0.0)-$C$11-$C$12)*1000/$C$13/$C$14 | F27: =(($E$8*$B27+$E$7*F$26+$E$6*$F$6+$E$9*$F$9+$C$10)*(1-0.0)-$C$11-$C$12)*1000/$C$13/$C$14
B28: 8 | C28: =(($E$8*$B28+$E$7*C$26+$E$6*$F$6+$E$9*$F$9+$C$10)*(1-0.0)-$C$11-$C$12)*1000/$C$13/$C$14 | D28: =(($E$8*$B28+$E$7*D$26+$E$6*$F$6+$E$9*$F$9+$C$10)*(1-0.0)-$C$11-$C$12)*1000/$C$13/$C$14 | E28: =(($E$8*$B28+$E$7*E$26+$E$6*$F$6+$E$9*$F$9+$C$10)*(1-0.0)-$C$11-$C$12)*1000/$C$13/$C$14 | F28: =(($E$8*$B28+$E$7*F$26+$E$6*$F$6+$E$9*$F$9+$C$10)*(1-0.0)-$C$11-$C$12)*1000/$C$13/$C$14
B29: 10 | C29: =(($E$8*$B29+$E$7*C$26+$E$6*$F$6+$E$9*$F$9+$C$10)*(1-0.0)-$C$11-$C$12)*1000/$C$13/$C$14 | D29: =(($E$8*$B29+$E$7*D$26+$E$6*$F$6+$E$9*$F$9+$C$10)*(1-0.0)-$C$11-$C$12)*1000/$C$13/$C$14 | E29: =(($E$8*$B29+$E$7*E$26+$E$6*$F$6+$E$9*$F$9+$C$10)*(1-0.0)-$C$11-$C$12)*1000/$C$13/$C$14 | F29: =(($E$8*$B29+$E$7*F$26+$E$6*$F$6+$E$9*$F$9+$C$10)*(1-0.0)-$C$11-$C$12)*1000/$C$13/$C$14
B30: 12 | C30: =(($E$8*$B30+$E$7*C$26+$E$6*$F$6+$E$9*$F$9+$C$10)*(1-0.0)-$C$11-$C$12)*1000/$C$13/$C$14 | D30: =(($E$8*$B30+$E$7*D$26+$E$6*$F$6+$E$9*$F$9+$C$10)*(1-0.0)-$C$11-$C$12)*1000/$C$13/$C$14 | E30: =(($E$8*$B30+$E$7*E$26+$E$6*$F$6+$E$9*$F$9+$C$10)*(1-0.0)-$C$11-$C$12)*1000/$C$13/$C$14 | F30: =(($E$8*$B30+$E$7*F$26+$E$6*$F$6+$E$9*$F$9+$C$10)*(1-0.0)-$C$11-$C$12)*1000/$C$13/$C$14
B31: 14 | C31: =(($E$8*$B31+$E$7*C$26+$E$6*$F$6+$E$9*$F$9+$C$10)*(1-0.0)-$C$11-$C$12)*1000/$C$13/$C$14 | D31: =(($E$8*$B31+$E$7*D$26+$E$6*$F$6+$E$9*$F$9+$C$10)*(1-0.0)-$C$11-$C$12)*1000/$C$13/$C$14 | E31: =(($E$8*$B31+$E$7*E$26+$E$6*$F$6+$E$9*$F$9+$C$10)*(1-0.0)-$C$11-$C$12)*1000/$C$13/$C$14 | F31: =(($E$8*$B31+$E$7*F$26+$E$6*$F$6+$E$9*$F$9+$C$10)*(1-0.0)-$C$11-$C$12)*1000/$C$13/$C$14

Sheet D&A Allocation
B1: D&A Allocation Methodology
B3: IHI does not disclose segment-level D&A.
B4: Allocation is estimated based on fixed asset intensity by segment.
B6: Consolidated D&A (FY25E) | C6: 70000 | D6: ¥M (input)
B8: Segment | C8: Allocation % | D8: D&A (¥M) | E8: Check
B9: Aero, Space & Defense | C9: 0.31 | D9: =$C$6*C9
B10: Resources, Energy & Environment | C10: 0.3 | D10: =$C$6*C10
B11: Industrial Systems & General Machinery | C11: 0.27 | D11: =$C$6*C11
B12: Social Infrastructure | C12: 0.12 | D12: =$C$6*C12
B13: Total | C13: =C9+C10+C11+C12 | D13: =D9+D10+D11+D12 | E13: =IF(ABS(C13-1)<0.001,"OK","CHECK")
B15: Notes:
B16: • Aero segment has highest capital intensity (engine test facilities, MRO hangars)
B17: • Energy segment includes boiler/turbine manufacturing → moderate fixed assets
B18: • Industrial includes turbocharger plants (Niigata, overseas) → moderate
B19: • Social Infrastructure: project-based, lower owned fixed assets
B20: • Allocation sums to 100% — residual is implicitly in corporate/eliminations
