Workbook

Sheet Executive Summary
B1: DISCLAIMER: This is a sample analysis for demonstration purposes only. It does not constitute investment advice.
B3: Ricoh Company, Ltd. (7752.T)
B4: Equity Research Report
B6: Company | C6: Ricoh Company, Ltd.
B7: Ticker | C7: 7752.T (TSE Prime)
B8: Sector | C8: Office Imaging / Digital Services
B9: Current Price | C9: 1690
B10: Target Price (DCF Mid) | C10: =IF(COUNT(C16:C17)=0,"N/A",ROUND(AVERAGE(C16:C17),0)) -> 1627
B11: Recommendation | C11: =IF(NOT(ISNUMBER(C12)),"N/A",IF(C12>0.15,"BUY",IF(C12>0.05,"HOLD","SELL"))) -> SELL
B12: Upside / Downside | C12: =IF(ISNUMBER(C10),(C10-C9)/C9,"N/A") -> -0.037278107
B14: Valuation Summary
B15: Methodology | C15: Implied Value (JPY) | D15: vs Current Price
B16: DCF - Perpetuity Growth | C16: =IF('DCF Model'!C53<'DCF Model'!C16,"INVALID (EV < net debt)",'DCF Model'!C55) -> 984 | D16: =IF(ISNUMBER(C16),(C16-C9)/C9,"N/A") -> -0.41775148
B17: DCF - Exit Multiple | C17: =IF('DCF Model'!C62<'DCF Model'!C16,"INVALID (EV < net debt)",'DCF Model'!C64) -> 2269 | D17: =IF(ISNUMBER(C17),(C17-C9)/C9,"N/A") -> 0.34260355
B18: Comps - EV/EBITDA Median [参考・Target不算入] | C18: ='Comps Analysis'!C27 -> 2550 | D18: =IF(ISNUMBER(C18),(C18-C9)/C9,"N/A") -> 0.50887574
B19: Comps - PER Median [参考・Target不算入] | C19: ='Comps Analysis'!C28 -> 1420 | D19: =IF(ISNUMBER(C19),(C19-C9)/C9,"N/A") -> -0.15976331
B20: Note: Target Mid は DCF 2法（PGM / Exit）の平均のみ。Comps 2法は [参考] で Target 不算入（EV<ネットデットで株式価値が負になる手法は INVALID として平均から除外）
B21: DCF Valuation Range (PGM - Exit) | C21: =IF(COUNT(C16:C17)=0,"N/A",MIN(C16:C17)&" - "&MAX(C16:C17)) -> 984 - 2269
B23: Key Investment Thesis
B24: ="1. Ricoh trades at "&TEXT('Comps Analysis'!L5,"0.0""x""")&" earnings and "&TEXT('Comps Analysis'!M5,"0.00""x""")&" book against a peer set whose EV/EBITDA median is 7.7x, and the printing business it is named after is no longer the whole company: digital services now carry the margin recovery visible in FY3/26 (operating margin 3.75%, up from a 2.58% trough)." -> 1. Ricoh trades at 17.1x earnings and 0.82x book against a peer set whose EV/EBITDA median is 7.7x, and the printing business it is named after is no longer the whole company: digital services now carry the margin recovery visible in FY3/26 (operating margin 3.75%, up from a 2.58% trough).
B25: 2. Company guidance for FY3/27 is JPY 2,700bn of revenue and JPY 95bn of operating profit - a 3.5% top line and a 3.52% margin - which the Management scenario models directly rather than as a copy of Base.
B26: 3. The balance sheet carries the optionality: net debt is a live question (see the Adjustments Log), and a resolution in favour of the EDINET figure is worth roughly JPY 157 per share against the yfinance read.
B28: Key Risks
B29: 1. The office printing market is structurally shrinking; the last three years of top-line growth (+10.1%, +7.6%, +3.2%) came substantially from currency and acquisitions and has already decelerated to guidance-level 3.5%.
B30: 2. Operating margin has been below 4% for the whole observation window and the 2.58% trough is two years old, not ten - the Downside 1 case of 2.64% is an observed level, not a stress assumption.
B31: ="3. Net debt differs by JPY 88.2bn between the EDINET filing and yfinance, and the cause is not yet verified. At "&TEXT(C9,"#,##0")&" per share that difference is material to the equity value." -> 3. Net debt differs by JPY 88.2bn between the EDINET filing and yfinance, and the cause is not yet verified. At 1,690 per share that difference is material to the equity value.

Sheet Financial Statements
B2: Ricoh Company, Ltd. - Historical Financials (JPY mn)
C4: FY2023 | D4: FY2024 | E4: FY2025 | F4: FY2026
B5: Income Statement
B6: Revenue | C6: 2134180 | D6: 2348987 | E6: 2527876 | F6: 2608314
B7: COGS | C7: 1388758 | D7: 1528889 | E7: 1659268 | F7: 1719166
B8: Gross Profit | C8: =C6-C7 -> 745422 | D8: =D6-D7 -> 820098 | E8: =E6-E7 -> 868608 | F8: =F6-F7 -> 889148
B9: Gross Margin | C9: =C8/C6 -> 0.34927794 | D9: =D8/D6 -> 0.34912837 | E9: =E8/E6 -> 0.34361179 | F9: =F8/F6 -> 0.34088994
B10: SGA | C10: 688156 | D10: 769810 | E10: 818945 | F10: 815166
B11: Operating Income | C11: 78810 | D11: 62642 | E11: 65140 | F11: 97724
B12: Net Income | C12: 54367 | D12: 44176 | E12: 45709 | F12: 55669
B13: Operating Margin | C13: =C11/C6 -> 0.036927532 | D13: =D11/D6 -> 0.026667666 | E13: =E11/E6 -> 0.025768669 | F13: =F11/F6 -> 0.037466348
B14: Net Margin | C14: =C12/C6 -> 0.025474421 | D14: =D12/D6 -> 0.018806405 | E14: =E12/E6 -> 0.018081979 | F14: =F12/F6 -> 0.021342906
B15: Revenue Growth (YoY) | C15: n/a | D15: =(D6-C6)/C6 -> 0.10065084 | E15: =(E6-D6)/D6 -> 0.076155807 | F15: =(F6-E6)/E6 -> 0.03182039
B16: Operating Income Growth (YoY) | C16: n/a | D16: =(D11-C11)/C11 -> -0.20515163 | E16: =(E11-D11)/D11 -> 0.039877399 | F16: =(F11-E11)/E11 -> 0.50021492
B18: Cash Flow Statement
B19: Operating Cash Flow | C19: 66708 | D19: 125617 | E19: 136877 | F19: 158120
B20: Capex
B21: Free Cash Flow
B22: FCF Margin
B23: Capex / Revenue
B25: Balance Sheet Highlights
B26: Cash & Deposits | C26: 221890 | D26: 177050 | E26: 190657 | F26: 204855
B27: Total Interest-bearing Debt (short + long) | C27: 362938 | D27: 349566 | E27: 440646 | F27: 432126
B28: Net Debt (Cash) | C28: =C27-C26 -> 141048 | D28: =D27-D26 -> 172516 | E28: =E27-E26 -> 249989 | F28: =F27-F26 -> 227271
B30: Note: OCF / Cash / Debt coverage OCF 4/4, Cash 4/4, Debt 4/4 — blank cells are years with no year-key match in the source data (verify against 決算短信 or set hist_ocf / hist_cash / hist_debt in overrides).

Sheet DCF Model
B2: DCF Valuation Model - Ricoh Company, Ltd.
B4: Assumptions
B5: Capex / Revenue | C5: 0.0518
B6: Effective Tax Rate | C6: 0.25
B7: Risk-Free Rate | C7: 0.0297
B8: Beta | C8: 1.0296
B9: Equity Risk Premium | C9: 0.065
B10: Size Premium | C10: 0.01
B11: After-tax Cost of Debt | C11: 0.01
B12: D/E Ratio | C12: 0.2393
B13: Terminal Growth Rate | C13: 0.01
B14: Exit Multiple (EV/EBITDA) | C14: 7.7
B15: Fully Diluted Shares | C15: 562049730
B16: Net Debt (JPY mn) | C16: 227271
... B20: LTM Revenue (JPY mn) | C20: 2608314
B22: WACC Calculation
B23: Cost of Equity (Ke) | C23: =C7+C8*C9+C10 -> 0.106624
B24: Weight of Equity | C24: =1/(1+C12) -> 0.80690712
B25: Weight of Debt | C25: =C12/(1+C12) -> 0.19309288
B26: WACC | C26: =C23*C24+C11*C25 -> 0.087966594
B27: Active Scenario | C27: Base | D27: =MATCH(C27,B69:B73,0) -> 1
B28: Projected Free Cash Flow
C29: FY2027(E) | D29: FY2028(E) | E29: FY2029(E) | F29: FY2030(E) | G29: FY2031(E)
B30: Revenue Growth (YoY) | C30: =CHOOSE($D$27,C69,C70,C71,C72,C73) -> 0.035 | D30: =CHOOSE($D$27,D69,D70,D71,D72,D73) -> 0.025 | E30: =CHOOSE($D$27,E69,E70,E71,E72,E73) -> 0.02 | F30: =CHOOSE($D$27,F69,F70,F71,F72,F73) -> 0.015 | G30: =CHOOSE($D$27,G69,G70,G71,G72,G73) -> 0.015
B31: COGS % of Revenue | C31: =CHOOSE($D$27,C76,C77,C78,C79,C80) -> 0.6591 | D31: =CHOOSE($D$27,D76,D77,D78,D79,D80) -> 0.6591 | E31: =CHOOSE($D$27,E76,E77,E78,E79,E80) -> 0.6591 | F31: =CHOOSE($D$27,F76,F77,F78,F79,F80) -> 0.6591 | G31: =CHOOSE($D$27,G76,G77,G78,G79,G80) -> 0.6591
B32: SGA % of Revenue | C32: =CHOOSE($D$27,C83,C84,C85,C86,C87) -> 0.3036 | D32: =CHOOSE($D$27,D83,D84,D85,D86,D87) -> 0.3036 | E32: =CHOOSE($D$27,E83,E84,E85,E86,E87) -> 0.3036 | F32: =CHOOSE($D$27,F83,F84,F85,F86,F87) -> 0.3036 | G32: =CHOOSE($D$27,G83,G84,G85,G86,G87) -> 0.3036
B33: Revenue | C33: =C17*(1+C30) -> 2699605 | D33: =C33*(1+D30) -> 2767095.1 | E33: =D33*(1+E30) -> 2822437 | F33: =E33*(1+F30) -> 2864773.6 | G33: =F33*(1+G30) -> 2907745.2
B34: COGS | C34: =C33*C31 -> 1779309.6 | D34: =D33*D31 -> 1823792.4 | E34: =E33*E31 -> 1860268.2 | F34: =F33*F31 -> 1888172.3 | G34: =G33*G31 -> 1916494.8
B35: Gross Profit | C35: =C33-C34 -> 920295.34 | D35: =D33-D34 -> 943302.72 | E35: =E33-E34 -> 962168.78 | F35: =F33-F34 -> 976601.31 | G35: =G33-G34 -> 991250.33
B36: Gross Margin | C36: =C35/C33 -> 0.3409 | D36: =D35/D33 -> 0.3409 | E36: =E35/E33 -> 0.3409 | F36: =F35/F33 -> 0.3409 | G36: =G35/G33 -> 0.3409
B37: SGA Expense | C37: =C33*C32 -> 819600.07 | D37: =D33*D32 -> 840090.08 | E37: =E33*E32 -> 856891.88 | F37: =F33*F32 -> 869745.26 | G37: =G33*G32 -> 882791.44
B38: Implied Operating Margin | C38: =(C35-C37)/C33 -> 0.0373 | D38: =(D35-D37)/D33 -> 0.0373 | E38: =(E35-E37)/E33 -> 0.0373 | F38: =(F35-F37)/F33 -> 0.0373 | G38: =(G35-G37)/G33 -> 0.0373
B39: Operating Income (EBIT) | C39: =C35-C37 -> 100695.27 | D39: =D35-D37 -> 103212.65 | E39: =E35-E37 -> 105276.9 | F39: =F35-F37 -> 106856.05 | G39: =G35-G37 -> 108458.9
B40: Less: Tax | C40: =MAX(0,C39*C6) -> 25173.817 | D40: =MAX(0,D39*C6) -> 25803.162 | E40: =MAX(0,E39*C6) -> 26319.225 | F40: =MAX(0,F39*C6) -> 26714.014 | G40: =MAX(0,G39*C6) -> 27114.724
B41: NOPAT | C41: =C39-C40 -> 75521.45 | D41: =D39-D40 -> 77409.486 | E41: =E39-E40 -> 78957.676 | F41: =F39-F40 -> 80142.041 | G41: =G39-G40 -> 81344.171
B42: Plus: D&A | C42: =C33*C18 -> 133090.53 | D42: =D33*C18 -> 136417.79 | E42: =E33*C18 -> 139146.14 | F42: =F33*C18 -> 141233.34 | G42: =G33*C18 -> 143351.84
B43: Less: Capex | C43: =C33*C5 -> 139839.54 | D43: =D33*C5 -> 143335.53 | E43: =E33*C5 -> 146202.24 | F43: =F33*C5 -> 148395.27 | G43: =G33*C5 -> 150621.2
B44: Change in NWC | C44: ='NWC Schedule'!D19 -> 15116.781 | D44: ='NWC Schedule'!E19 -> 14733.52 | E44: ='NWC Schedule'!F19 -> 12081.486 | F44: ='NWC Schedule'!G19 -> 9242.3368 | G44: ='NWC Schedule'!H19 -> 9380.9718
B45: Unlevered Free Cash Flow | C45: =C41+C42-C43-C44 -> 53655.657 | D45: =D41+D42-D43-D44 -> 55758.229 | E45: =E41+E42-E43-E44 -> 59820.097 | F45: =F41+F42-F43-F44 -> 63737.77 | G45: =G41+G42-G43-G44 -> 64693.837
B46: Discount Factor | C46: =1/(1+C26)^(C19+0) -> 0.91914587 | D46: =1/(1+C26)^(C19+1) -> 0.84482913 | E46: =1/(1+C26)^(C19+2) -> 0.7765212 | F46: =1/(1+C26)^(C19+3) -> 0.71373625 | G46: =1/(1+C26)^(C19+4) -> 0.65602773
B47: PV of FCF | C47: =C45*C46 -> 49317.375 | D47: =D45*D46 -> 47106.176 | E47: =E45*E46 -> 46451.574 | F47: =F45*F46 -> 45491.957 | G47: =G45*G46 -> 42440.951
B49: Valuation - Perpetuity Growth Method
B50: Sum of PV of FCFs | C50: =SUM(C47:G47) -> 230808.03
B51: Terminal Value (PGM) | C51: =G45*(1+C13)/(C26-C13) -> 838061.17
B52: PV of Terminal Value | C52: =C51*G46 -> 549791.37
B53: Enterprise Value | C53: =C50+C52 -> 780599.4
B54: Equity Value | C54: =C53-C16 -> 553328.4
B55: Implied Share Price (PGM) | C55: =ROUND(C54*1000000/C15,0) -> 984
B57: Valuation - Exit Multiple Method
B58: Sum of PV of FCFs | C58: =C50 -> 230808.03
B59: Year 5 EBITDA | C59: =G39+G42 -> 251810.73
B60: Terminal Value (Exit Multiple) | C60: =C59*C14 -> 1938942.6
B61: PV of Terminal Value | C61: =C60*G46 -> 1272000.1
B62: Enterprise Value | C62: =C58+C61 -> 1502808.2
B63: Equity Value | C63: =C62-C16 -> 1275537.2
B64: Implied Share Price (Exit Multiple) | C64: =ROUND(C63*1000000/C15,0) -> 2269
B66: Scenario Input Matrix
C67: Year 1 | D67: Year 2 | E67: Year 3 | F67: Year 4 | G67: Year 5
B68: Revenue Growth (YoY)
B69: Base | C69: 0.035 | D69: 0.025 | E69: 0.02 | F69: 0.015 | G69: 0.015
B70: Upside | C70: 0.05 | D70: 0.04 | E70: 0.03 | F70: 0.025 | G70: 0.02
B71: Management | C71: 0.0352 | D71: 0.0353 | E71: 0.0353 | F71: 0.0354 | G71: 0.0354
B72: Downside 1 | C72: 0.01 | D72: 0.01 | E72: 0.01 | F72: 0.01 | G72: 0.01
B73: Downside 2 | C73: -0.05 | D73: 0 | E73: 0.01 | F73: 0.01 | G73: 0.01
B75: COGS % of Revenue
B76: Base | C76: 0.6591 | D76: 0.6591 | E76: 0.6591 | F76: 0.6591 | G76: 0.6591
B77: Upside | C77: 0.6591 | D77: 0.6591 | E77: 0.6591 | F77: 0.6591 | G77: 0.6591
B78: Management | C78: 0.6591 | D78: 0.6591 | E78: 0.6591 | F78: 0.6591 | G78: 0.6591
B79: Downside 1 | C79: 0.6591 | D79: 0.6591 | E79: 0.6591 | F79: 0.6591 | G79: 0.6591
B80: Downside 2 | C80: 0.6591 | D80: 0.6591 | E80: 0.6591 | F80: 0.6591 | G80: 0.6591
B82: SGA % of Revenue
B83: Base | C83: 0.3036 | D83: 0.3036 | E83: 0.3036 | F83: 0.3036 | G83: 0.3036
B84: Upside | C84: 0.2934 | D84: 0.2934 | E84: 0.2934 | F84: 0.2934 | G84: 0.2934
B85: Management | C85: 0.3057 | D85: 0.3057 | E85: 0.3057 | F85: 0.3057 | G85: 0.3057
B86: Downside 1 | C86: 0.3145 | D86: 0.3145 | E86: 0.3145 | F86: 0.3145 | G86: 0.3145
B87: Downside 2 | C87: 0.3222 | D87: 0.3222 | E87: 0.3222 | F87: 0.3222 | G87: 0.3222

Sheet Reverse DCF
B2: Reverse DCF - Ricoh Company, Ltd. (7752.T)
B3: What is the current share price already assuming? Every value below is a live formula off the other sheets.
B5: Block 0: Market-implied enterprise value (live)
B6: Current Share Price (JPY) | C6: ='Executive Summary'!C9 -> 1690
B7: Fully Diluted Shares | C7: ='DCF Model'!C15 -> 562049730
B8: Market Capitalisation (JPY mn) | C8: =C6*C7/1000000 -> 949864.04
B9: Net Debt (JPY mn) | C9: ='DCF Model'!C16 -> 227271
B10: Enterprise Value (JPY mn) | C10: =C8+C9 -> 1177135
B11: WACC (w) | C11: ='DCF Model'!C26 -> 0.087966594
B12: Terminal Growth (g) | C12: ='DCF Model'!C13 -> 0.01
B13: Effective Tax Rate (t) | C13: ='DCF Model'!C6 -> 0.25
B14: Starting Operating Profit OP0 (FY2026 actual) | C14: 97724
B15: Cycle-peak Operating Profit (FY2026 actual) | C15: 97724
B16: Terminal-year Revenue, active scenario (JPY mn) | C16: ='DCF Model'!G33 -> 2907745.2
B17: Base-case DCF Enterprise Value, PGM (JPY mn) | C17: ='DCF Model'!C53 -> 780599.4
B18: Cycle-peak Operating Margin (FY2026 actual) | C18: 0.037466348
B19: Gap: market EV less base-case DCF EV (JPY mn) | C19: =C10-C17 -> 396535.65
B20: Gap per share (JPY) - the part of the price the base case does not explain | C20: =IFERROR(ROUND(C19*1000000/C7,0),"N/A") -> 706
B22: Block A: Required steady-state operating profit, reached IMMEDIATELY (no ramp)
B23: The lowest bar the price can clear: today's EV read as a perpetuity of one steady-state profit, capex = D&A, no NWC build.
B24: Required steady-state NOPAT (JPY mn) | C24: =C10*(C11-C12) -> 91777.21
B25: Required steady-state Operating Profit (JPY mn) | C25: =IFERROR(C24/(1-C13),"N/A") -> 122369.61
B26: ... as a multiple of the FY2026 peak | C26: =IFERROR(C25/C15,"N/A") -> 1.2521961
B27: ... as a multiple of FY2026 actual | C27: =IFERROR(C25/C14,"N/A") -> 1.2521961
B28: ... implied OPM on terminal-year revenue | C28: =IFERROR(C25/C16,"N/A") -> 0.042084023
B29: ... revenue needed if margins only reach the cycle peak | C29: =IFERROR(C25/C18,"N/A") -> 3266120.7
B32: Block B: Required steady-state operating profit by YEARS-TO-REACH (linear ramp) x WACC
B33: Operating profit ramps linearly from OP0 (C14) to OP* over N years, then grows at g for ever. Column F is the model WACC.
B34: OP* = ( EV/(1-t) - OP0*(A-B) ) / ( B + TVF ). A longer ramp needs a HIGHER steady state, because more years are spent below it.
B36: Years to steady state (N) \ WACC | C36: N | D36: ='DCF Model'!C26-0.02 -> 0.067966594 | E36: ='DCF Model'!C26-0.01 -> 0.077966594 | F36: ='DCF Model'!C26 -> 0.087966594 | G36: ='DCF Model'!C26+0.01 -> 0.097966594 | H36: ='DCF Model'!C26+0.02 -> 0.10796659
B37: B-1 PV weight on the RAMP from OP0 (A - B)
B38: N = 3 years | C38: 3 | D38: =IFERROR((1-(1+D$36)^(-$C38))/D$36-(1+D$36)/(D$36^2*$C38)*(1-($C38+1)/(1+D$36)^$C38+$C38/(1+D$36)^($C38+1)),"N/A") -> 0.91649523 | E38: =IFERROR((1-(1+E$36)^(-$C38))/E$36-(1+E$36)/(E$36^2*$C38)*(1-($C38+1)/(1+E$36)^$C38+$C38/(1+E$36)^($C38+1)),"N/A") -> 0.90530713 | F38: =IFERROR((1-(1+F$36)^(-$C38))/F$36-(1+F$36)/(F$36^2*$C38)*(1-($C38+1)/(1+F$36)^$C38+$C38/(1+F$36)^($C38+1)),"N/A") -> 0.89437362 | G38: =IFERROR((1-(1+G$36)^(-$C38))/G$36-(1+G$36)/(G$36^2*$C38)*(1-($C38+1)/(1+G$36)^$C38+$C38/(1+G$36)^($C38+1)),"N/A") -> 0.88368642 | H38: =IFERROR((1-(1+H$36)^(-$C38))/H$36-(1+H$36)/(H$36^2*$C38)*(1-($C38+1)/(1+H$36)^$C38+$C38/(1+H$36)^($C38+1)),"N/A") -> 0.87323761
B39: N = 5 years | C39: 5 | D39: =IFERROR((1-(1+D$36)^(-$C39))/D$36-(1+D$36)/(D$36^2*$C39)*(1-($C39+1)/(1+D$36)^$C39+$C39/(1+D$36)^($C39+1)),"N/A") -> 1.7572801 | E39: =IFERROR((1-(1+E$36)^(-$C39))/E$36-(1+E$36)/(E$36^2*$C39)*(1-($C39+1)/(1+E$36)^$C39+$C39/(1+E$36)^($C39+1)),"N/A") -> 1.7259354 | F39: =IFERROR((1-(1+F$36)^(-$C39))/F$36-(1+F$36)/(F$36^2*$C39)*(1-($C39+1)/(1+F$36)^$C39+$C39/(1+F$36)^($C39+1)),"N/A") -> 1.6955699 | G39: =IFERROR((1-(1+G$36)^(-$C39))/G$36-(1+G$36)/(G$36^2*$C39)*(1-($C39+1)/(1+G$36)^$C39+$C39/(1+G$36)^($C39+1)),"N/A") -> 1.6661419 | H39: =IFERROR((1-(1+H$36)^(-$C39))/H$36-(1+H$36)/(H$36^2*$C39)*(1-($C39+1)/(1+H$36)^$C39+$C39/(1+H$36)^($C39+1)),"N/A") -> 1.6376118
B40: N = 7 years | C40: 7 | D40: =IFERROR((1-(1+D$36)^(-$C40))/D$36-(1+D$36)/(D$36^2*$C40)*(1-($C40+1)/(1+D$36)^$C40+$C40/(1+D$36)^($C40+1)),"N/A") -> 2.5293753 | E40: =IFERROR((1-(1+E$36)^(-$C40))/E$36-(1+E$36)/(E$36^2*$C40)*(1-($C40+1)/(1+E$36)^$C40+$C40/(1+E$36)^($C40+1)),"N/A") -> 2.4707732 | F40: =IFERROR((1-(1+F$36)^(-$C40))/F$36-(1+F$36)/(F$36^2*$C40)*(1-($C40+1)/(1+F$36)^$C40+$C40/(1+F$36)^($C40+1)),"N/A") -> 2.4144793 | G40: =IFERROR((1-(1+G$36)^(-$C40))/G$36-(1+G$36)/(G$36^2*$C40)*(1-($C40+1)/(1+G$36)^$C40+$C40/(1+G$36)^($C40+1)),"N/A") -> 2.3603724 | H40: =IFERROR((1-(1+H$36)^(-$C40))/H$36-(1+H$36)/(H$36^2*$C40)*(1-($C40+1)/(1+H$36)^$C40+$C40/(1+H$36)^($C40+1)),"N/A") -> 2.3083392
B41: N = 10 years | C41: 10 | D41: =IFERROR((1-(1+D$36)^(-$C41))/D$36-(1+D$36)/(D$36^2*$C41)*(1-($C41+1)/(1+D$36)^$C41+$C41/(1+D$36)^($C41+1)),"N/A") -> 3.5723938 | E41: =IFERROR((1-(1+E$36)^(-$C41))/E$36-(1+E$36)/(E$36^2*$C41)*(1-($C41+1)/(1+E$36)^$C41+$C41/(1+E$36)^($C41+1)),"N/A") -> 3.4629493 | F41: =IFERROR((1-(1+F$36)^(-$C41))/F$36-(1+F$36)/(F$36^2*$C41)*(1-($C41+1)/(1+F$36)^$C41+$C41/(1+F$36)^($C41+1)),"N/A") -> 3.3590855 | G41: =IFERROR((1-(1+G$36)^(-$C41))/G$36-(1+G$36)/(G$36^2*$C41)*(1-($C41+1)/(1+G$36)^$C41+$C41/(1+G$36)^($C41+1)),"N/A") -> 3.2604307 | H41: =IFERROR((1-(1+H$36)^(-$C41))/H$36-(1+H$36)/(H$36^2*$C41)*(1-($C41+1)/(1+H$36)^$C41+$C41/(1+H$36)^($C41+1)),"N/A") -> 3.1666428
B42: B-2 PV weight on the STEADY STATE OP* (B + terminal factor)
B43: N = 3 years | C43: 3 | D43: =IFERROR((1+D$36)/(D$36^2*$C43)*(1-($C43+1)/(1+D$36)^$C43+$C43/(1+D$36)^($C43+1))+(1+$C$12)/((D$36-$C$12)*(1+D$36)^$C43),"N/A") -> 16.022032 | E43: =IFERROR((1+E$36)/(E$36^2*$C43)*(1-($C43+1)/(1+E$36)^$C43+$C43/(1+E$36)^($C43+1))+(1+$C$12)/((E$36-$C$12)*(1+E$36)^$C43),"N/A") -> 13.544696 | F43: =IFERROR((1+F$36)/(F$36^2*$C43)*(1-($C43+1)/(1+F$36)^$C43+$C43/(1+F$36)^($C43+1))+(1+$C$12)/((F$36-$C$12)*(1+F$36)^$C43),"N/A") -> 11.705385 | G43: =IFERROR((1+G$36)/(G$36^2*$C43)*(1-($C43+1)/(1+G$36)^$C43+$C43/(1+G$36)^($C43+1))+(1+$C$12)/((G$36-$C$12)*(1+G$36)^$C43),"N/A") -> 10.286431 | H43: =IFERROR((1+H$36)/(H$36^2*$C43)*(1-($C43+1)/(1+H$36)^$C43+$C43/(1+H$36)^($C43+1))+(1+$C$12)/((H$36-$C$12)*(1+H$36)^$C43),"N/A") -> 9.1590435
B44: N = 5 years | C44: 5 | D44: =IFERROR((1+D$36)/(D$36^2*$C44)*(1-($C44+1)/(1+D$36)^$C44+$C44/(1+D$36)^($C44+1))+(1+$C$12)/((D$36-$C$12)*(1+D$36)^$C44),"N/A") -> 14.907004 | E44: =IFERROR((1+E$36)/(E$36^2*$C44)*(1-($C44+1)/(1+E$36)^$C44+$C44/(1+E$36)^($C44+1))+(1+$C$12)/((E$36-$C$12)*(1+E$36)^$C44),"N/A") -> 12.497644 | F44: =IFERROR((1+F$36)/(F$36^2*$C44)*(1-($C44+1)/(1+F$36)^$C44+$C44/(1+F$36)^($C44+1))+(1+$C$12)/((F$36-$C$12)*(1+F$36)^$C44),"N/A") -> 10.713048 | G44: =IFERROR((1+G$36)/(G$36^2*$C44)*(1-($C44+1)/(1+G$36)^$C44+$C44/(1+G$36)^($C44+1))+(1+$C$12)/((G$36-$C$12)*(1+G$36)^$C44),"N/A") -> 9.3398692 | H44: =IFERROR((1+H$36)/(H$36^2*$C44)*(1-($C44+1)/(1+H$36)^$C44+$C44/(1+H$36)^($C44+1))+(1+$C$12)/((H$36-$C$12)*(1+H$36)^$C44),"N/A") -> 8.2518855
B45: N = 7 years | C45: 7 | D45: =IFERROR((1+D$36)/(D$36^2*$C45)*(1-($C45+1)/(1+D$36)^$C45+$C45/(1+D$36)^($C45+1))+(1+$C$12)/((D$36-$C$12)*(1+D$36)^$C45),"N/A") -> 13.894462 | E45: =IFERROR((1+E$36)/(E$36^2*$C45)*(1-($C45+1)/(1+E$36)^$C45+$C45/(1+E$36)^($C45+1))+(1+$C$12)/((E$36-$C$12)*(1+E$36)^$C45),"N/A") -> 11.557952 | F45: =IFERROR((1+F$36)/(F$36^2*$C45)*(1-($C45+1)/(1+F$36)^$C45+$C45/(1+F$36)^($C45+1))+(1+$C$12)/((F$36-$C$12)*(1+F$36)^$C45),"N/A") -> 9.8326575 | G45: =IFERROR((1+G$36)/(G$36^2*$C45)*(1-($C45+1)/(1+G$36)^$C45+$C45/(1+G$36)^($C45+1))+(1+$C$12)/((G$36-$C$12)*(1+G$36)^$C45),"N/A") -> 8.5095111 | H45: =IFERROR((1+H$36)/(H$36^2*$C45)*(1-($C45+1)/(1+H$36)^$C45+$C45/(1+H$36)^($C45+1))+(1+$C$12)/((H$36-$C$12)*(1+H$36)^$C45),"N/A") -> 7.4648458
B46: N = 10 years | C46: 10 | D46: =IFERROR((1+D$36)/(D$36^2*$C46)*(1-($C46+1)/(1+D$36)^$C46+$C46/(1+D$36)^($C46+1))+(1+$C$12)/((D$36-$C$12)*(1+D$36)^$C46),"N/A") -> 12.545171 | E46: =IFERROR((1+E$36)/(E$36^2*$C46)*(1-($C46+1)/(1+E$36)^$C46+$C46/(1+E$36)^($C46+1))+(1+$C$12)/((E$36-$C$12)*(1+E$36)^$C46),"N/A") -> 10.323227 | F46: =IFERROR((1+F$36)/(F$36^2*$C46)*(1-($C46+1)/(1+F$36)^$C46+$C46/(1+F$36)^($C46+1))+(1+$C$12)/((F$36-$C$12)*(1+F$36)^$C46),"N/A") -> 8.6915721 | G46: =IFERROR((1+G$36)/(G$36^2*$C46)*(1-($C46+1)/(1+G$36)^$C46+$C46/(1+G$36)^($C46+1))+(1+$C$12)/((G$36-$C$12)*(1+G$36)^$C46),"N/A") -> 7.447513 | H46: =IFERROR((1+H$36)/(H$36^2*$C46)*(1-($C46+1)/(1+H$36)^$C46+$C46/(1+H$36)^($C46+1))+(1+$C$12)/((H$36-$C$12)*(1+H$36)^$C46),"N/A") -> 6.4712258
B47: B-3 REQUIRED steady-state Operating Profit (JPY mn)
B48: N = 3 years | C48: 3 | D48: =IFERROR(($C$10/(1-$C$13)-$C$14*D38)/D43,"N/A") -> 92369.67 | E48: =IFERROR(($C$10/(1-$C$13)-$C$14*E38)/E43,"N/A") -> 109344.88 | F48: =IFERROR(($C$10/(1-$C$13)-$C$14*F38)/F43,"N/A") -> 126617.93 | G48: =IFERROR(($C$10/(1-$C$13)-$C$14*G38)/G43,"N/A") -> 144185.68 | H48: =IFERROR(($C$10/(1-$C$13)-$C$14*H38)/H43,"N/A") -> 162044.99
B49: N = 5 years | C49: 5 | D49: =IFERROR(($C$10/(1-$C$13)-$C$14*D39)/D44,"N/A") -> 93766.991 | E49: =IFERROR(($C$10/(1-$C$13)-$C$14*E39)/E44,"N/A") -> 112088.97 | F49: =IFERROR(($C$10/(1-$C$13)-$C$14*F39)/F44,"N/A") -> 131037.92 | G49: =IFERROR(($C$10/(1-$C$13)-$C$14*G39)/G44,"N/A") -> 150611.46 | H49: =IFERROR(($C$10/(1-$C$13)-$C$14*H39)/H44,"N/A") -> 170806.95
B50: N = 7 years | C50: 7 | D50: =IFERROR(($C$10/(1-$C$13)-$C$14*D40)/D45,"N/A") -> 95169.767 | E50: =IFERROR(($C$10/(1-$C$13)-$C$14*E40)/E45,"N/A") -> 114904.4 | F50: =IFERROR(($C$10/(1-$C$13)-$C$14*F40)/F45,"N/A") -> 135625.68 | G50: =IFERROR(($C$10/(1-$C$13)-$C$14*G40)/G45,"N/A") -> 157335.52 | H50: =IFERROR(($C$10/(1-$C$13)-$C$14*H40)/H45,"N/A") -> 180034.97
B51: N = 10 years | C51: 10 | D51: =IFERROR(($C$10/(1-$C$13)-$C$14*D41)/D46,"N/A") -> 97280.839 | E51: =IFERROR(($C$10/(1-$C$13)-$C$14*E41)/E46,"N/A") -> 119255.36 | F51: =IFERROR(($C$10/(1-$C$13)-$C$14*F41)/F46,"N/A") -> 142810.77 | G51: =IFERROR(($C$10/(1-$C$13)-$C$14*G41)/G46,"N/A") -> 167960.91 | H51: =IFERROR(($C$10/(1-$C$13)-$C$14*H41)/H46,"N/A") -> 194716.8
B52: B-4 ... as a multiple of the FY2026 peak operating profit
B53: N = 3 years | C53: 3 | D53: =IFERROR(D48/$C$15,"N/A") -> 0.94520967 | E53: =IFERROR(E48/$C$15,"N/A") -> 1.1189153 | F53: =IFERROR(F48/$C$15,"N/A") -> 1.2956687 | G53: =IFERROR(G48/$C$15,"N/A") -> 1.4754378 | H53: =IFERROR(H48/$C$15,"N/A") -> 1.6581903
B54: N = 5 years | C54: 5 | D54: =IFERROR(D49/$C$15,"N/A") -> 0.95950832 | E54: =IFERROR(E49/$C$15,"N/A") -> 1.1469953 | F54: =IFERROR(F49/$C$15,"N/A") -> 1.340898 | G54: =IFERROR(G49/$C$15,"N/A") -> 1.5411921 | H54: =IFERROR(H49/$C$15,"N/A") -> 1.7478506
B55: N = 7 years | C55: 7 | D55: =IFERROR(D50/$C$15,"N/A") -> 0.97386279 | E55: =IFERROR(E50/$C$15,"N/A") -> 1.1758054 | F55: =IFERROR(F50/$C$15,"N/A") -> 1.3878441 | G55: =IFERROR(G50/$C$15,"N/A") -> 1.6099988 | H55: =IFERROR(H50/$C$15,"N/A") -> 1.8422799
B56: N = 10 years | C56: 10 | D56: =IFERROR(D51/$C$15,"N/A") -> 0.99546518 | E56: =IFERROR(E51/$C$15,"N/A") -> 1.2203283 | F56: =IFERROR(F51/$C$15,"N/A") -> 1.4613685 | G56: =IFERROR(G51/$C$15,"N/A") -> 1.7187274 | H56: =IFERROR(H51/$C$15,"N/A") -> 1.9925177
B58: Block C: Decomposing the required profit into revenue x margin (N = 5 years, model WACC)
B59: The revenue the company must run at, for a given steady-state operating margin, to earn the Block B-3 profit.
B60: Required steady-state Operating Profit (N=5, model WACC) | C60: =F49 -> 131037.92
B62: Assumed steady-state OPM | C62: Required Revenue | D62: x base-year revenue
B63: 0.0187 | C63: =IFERROR($C$60/B63,"N/A") -> 7007375.4 | D63: =IFERROR(C63/'DCF Model'!C17,"N/A") -> 2.6865536
B64: 0.0281 | C64: =IFERROR($C$60/B64,"N/A") -> 4663271.1 | D64: =IFERROR(C64/'DCF Model'!C17,"N/A") -> 1.7878488
B65: cycle-peak OPM (FY2026) | C65: =IFERROR($C$60/$C$18,"N/A") -> 3497483.1 | D65: =IFERROR(C65/'DCF Model'!C17,"N/A") -> 1.340898
B66: 0.0468 | C66: =IFERROR($C$60/B66,"N/A") -> 2799955.5 | D66: =IFERROR(C66/'DCF Model'!C17,"N/A") -> 1.0734733
B67: 0.0562 | C67: =IFERROR($C$60/B67,"N/A") -> 2331635.6 | D67: =IFERROR(C67/'DCF Model'!C17,"N/A") -> 0.89392442
B69: Block D: The same question expressed as multiples
B70: Current EV / latest-FY EBITDA (actual) | C70: =IFERROR(C10/'Comps Analysis'!G5,"N/A") -> 5.4717891
B71: Current EV / latest-FY Revenue (actual) | C71: =IFERROR(C10/'Comps Analysis'!F5,"N/A") -> 0.45130113
B72: EV / EBITDA if the Block A profit were already earned | C72: =IFERROR(C10/(C25+'DCF Model'!G42),"N/A") -> 4.4299587
B73: EV / EBITDA if the Block B-3 (N=5) profit were already earned | C73: =IFERROR(C10/(C60+'DCF Model'!G42),"N/A") -> 4.2900109
B74: Peer median EV / EBITDA (statistics rows) | C74: =IFERROR('Comps Analysis'!D16,"N/A") -> 7.7188502
B75: Rows 3-4 answer: what multiple would today's EV be paying IF the company already earned the profit the price requires?
B77: Block F: The one-line answer
B78: ="At "&TEXT(C6,"#,##0")&" yen the market is paying for a steady-state operating profit of "&TEXT(F49,"#,##0")&" mn JPY - "&TEXT(F54,"0.00")&"x the FY2026 cycle peak of "&TEXT(C15,"#,##0")&" mn - reached in 5 years and sustained for ever, against "&TEXT(C14,"#,##0")&" mn actually earned in FY2026." -> At 1,690 yen the market is paying for a steady-state operating profit of 131,038 mn JPY - 1.34x the FY2026 cycle peak of 97,724 mn - reached in 5 years and sustained for ever, against 97,724 mn actually earned in FY2026.
B79: ="Even with no ramp at all (Block A) the price needs "&TEXT(C25,"#,##0")&" mn, or "&TEXT(C26,"0.00")&"x the peak. The base case supports an EV of only "&TEXT(C17,"#,##0")&" mn, leaving "&TEXT(C20,"#,##0")&" yen per share of the current price unexplained by mid-cycle economics." -> Even with no ramp at all (Block A) the price needs 122,370 mn, or 1.25x the peak. The base case supports an EV of only 780,599 mn, leaving 706 yen per share of the current price unexplained by mid-cycle economics.

Sheet NWC Schedule
B2: NWC Schedule - Ricoh Company, Ltd.
B4: Working Capital Drivers (Days) | C4: Base Year | D4: FY2027(E) | E4: FY2028(E) | F4: FY2029(E) | G4: FY2030(E) | H4: FY2031(E)
B5: DSO (Days Sales Outstanding) | C5: =C12/C9*365 -> 82.339293 | D5: =CHOOSE('DCF Model'!$D$27,D25,D26,D27,D28,D29) -> 81 | E5: =CHOOSE('DCF Model'!$D$27,E25,E26,E27,E28,E29) -> 81 | F5: =CHOOSE('DCF Model'!$D$27,F25,F26,F27,F28,F29) -> 81 | G5: =CHOOSE('DCF Model'!$D$27,G25,G26,G27,G28,G29) -> 81 | H5: =CHOOSE('DCF Model'!$D$27,H25,H26,H27,H28,H29) -> 81
B6: DIH (Days Inventory Held) | C6: =C13/C10*365 -> 70.26113 | D6: =CHOOSE('DCF Model'!$D$27,D32,D33,D34,D35,D36) -> 73 | E6: =CHOOSE('DCF Model'!$D$27,E32,E33,E34,E35,E36) -> 73 | F6: =CHOOSE('DCF Model'!$D$27,F32,F33,F34,F35,F36) -> 73 | G6: =CHOOSE('DCF Model'!$D$27,G32,G33,G34,G35,G36) -> 73 | H6: =CHOOSE('DCF Model'!$D$27,H32,H33,H34,H35,H36) -> 73
B7: DPO (Days Payable Outstanding) | C7: =C15/C10*365 -> 73.271293 | D7: =CHOOSE('DCF Model'!$D$27,D39,D40,D41,D42,D43) -> 75 | E7: =CHOOSE('DCF Model'!$D$27,E39,E40,E41,E42,E43) -> 75 | F7: =CHOOSE('DCF Model'!$D$27,F39,F40,F41,F42,F43) -> 75 | G7: =CHOOSE('DCF Model'!$D$27,G39,G40,G41,G42,G43) -> 75 | H7: =CHOOSE('DCF Model'!$D$27,H39,H40,H41,H42,H43) -> 75
B8: P&L Reference (JPY mn)
B9: Revenue | C9: 2608314 | D9: ='DCF Model'!C33 -> 2699605 | E9: ='DCF Model'!D33 -> 2767095.1 | F9: ='DCF Model'!E33 -> 2822437 | G9: ='DCF Model'!F33 -> 2864773.6 | H9: ='DCF Model'!G33 -> 2907745.2
B10: COGS | C10: 1719166 | D10: ='DCF Model'!C34 -> 1779309.6 | E10: ='DCF Model'!D34 -> 1823792.4 | F10: ='DCF Model'!E34 -> 1860268.2 | G10: ='DCF Model'!F34 -> 1888172.3 | H10: ='DCF Model'!G34 -> 1916494.8
B11: Working Capital Items (JPY mn)
B12: Accounts Receivable | C12: 588402 | D12: =D9*D5/365 -> 599090.42 | E12: =E9*E5/365 -> 614067.68 | F12: =F9*F5/365 -> 626349.04 | G12: =G9*G5/365 -> 635744.27 | H12: =H9*H5/365 -> 645280.44
B13: Inventory | C13: 330933 | D13: =D10*D6/365 -> 355861.93 | E13: =E10*E6/365 -> 364758.48 | F13: =F10*F6/365 -> 372053.65 | G13: =G10*G6/365 -> 377634.45 | H13: =H10*H6/365 -> 383298.97
B14: Current Assets (AR + Inv) | C14: =C12+C13 -> 919335 | D14: =D12+D13 -> 954952.35 | E14: =E12+E13 -> 978826.16 | F14: =F12+F13 -> 998402.68 | G14: =G12+G13 -> 1013378.7 | H14: =H12+H13 -> 1028579.4
B15: Accounts Payable | C15: 345111 | D15: =D10*D7/365 -> 365611.57 | E15: =E10*E7/365 -> 374751.86 | F15: =F10*F7/365 -> 382246.9 | G15: =G10*G7/365 -> 387980.6 | H15: =H10*H7/365 -> 393800.31
B16: Current Liabilities (AP) | C16: =C15 -> 345111 | D16: =D15 -> 365611.57 | E16: =E15 -> 374751.86 | F16: =F15 -> 382246.9 | G16: =G15 -> 387980.6 | H16: =H15 -> 393800.31
B17: Net Working Capital (JPY mn)
B18: Net Working Capital | C18: =C14-C16 -> 574224 | D18: =D14-D16 -> 589340.78 | E18: =E14-E16 -> 604074.3 | F18: =F14-F16 -> 616155.79 | G18: =G14-G16 -> 625398.12 | H18: =H14-H16 -> 634779.09
B19: Change in NWC | C19: n/a | D19: =D18-C18 -> 15116.781 | E19: =E18-D18 -> 14733.52 | F19: =F18-E18 -> 12081.486 | G19: =G18-F18 -> 9242.3368 | H19: =H18-G18 -> 9380.9718
B22: Scenario Input Matrix (Working Capital Days)
D23: FY2027(E) | E23: FY2028(E) | F23: FY2029(E) | G23: FY2030(E) | H23: FY2031(E)
B24: DSO (Days)
B25: Base | D25: 81 | E25: 81 | F25: 81 | G25: 81 | H25: 81
B26: Upside | D26: 78 | E26: 78 | F26: 78 | G26: 78 | H26: 78
B27: Management | D27: 81 | E27: 81 | F27: 81 | G27: 81 | H27: 81
B28: Downside 1 | D28: 85 | E28: 85 | F28: 85 | G28: 85 | H28: 85
B29: Downside 2 | D29: 89 | E29: 89 | F29: 89 | G29: 89 | H29: 89
B31: DIH (Days)
B32: Base | D32: 73 | E32: 73 | F32: 73 | G32: 73 | H32: 73
B33: Upside | D33: 69 | E33: 69 | F33: 69 | G33: 69 | H33: 69
B34: Management | D34: 73 | E34: 73 | F34: 73 | G34: 73 | H34: 73
B35: Downside 1 | D35: 77 | E35: 77 | F35: 77 | G35: 77 | H35: 77
B36: Downside 2 | D36: 81 | E36: 81 | F36: 81 | G36: 81 | H36: 81
B38: DPO (Days)
B39: Base | D39: 75 | E39: 75 | F39: 75 | G39: 75 | H39: 75
B40: Upside | D40: 78 | E40: 78 | F40: 78 | G40: 78 | H40: 78
B41: Management | D41: 75 | E41: 75 | F41: 75 | G41: 75 | H41: 75
B42: Downside 1 | D42: 72 | E42: 72 | F42: 72 | G42: 72 | H42: 72
B43: Downside 2 | D43: 69 | E43: 69 | F43: 69 | G43: 69 | H43: 69

Sheet Comps Analysis
B2: Comparable Company Analysis
B3: Peer prices as of 2026-09-06 (Mkt Cap / EV of peer rows are static CSV values; the subject row is live-linked to Executive Summary)
B4: Company | C4: Ticker | D4: Mkt Cap (JPY mn) | E4: EV (JPY mn) | F4: Revenue (JPY mn) | G4: EBITDA (JPY mn) | H4: Op Income (JPY mn) | I4: Net Income (JPY mn) | J4: EV/EBITDA | K4: EV/Revenue | L4: PER | M4: PBR | N4: Op Margin | O4: ROE | P4: Book Value (JPY mn) | Q4: Note
B5: Ricoh Company, Ltd. | C5: 7752.T | D5: ='Executive Summary'!C9*C23/1000000 -> 949864.04 | E5: =D5+C24 -> 1177135 | F5: 2608314 | G5: 215128 | H5: 97724 | I5: 55669 | J5: =IFERROR(E5/G5,"") -> 5.4717891 | K5: =IFERROR(E5/F5,"") -> 0.45130113 | L5: =IFERROR(D5/I5,"") -> 17.062711 | M5: =IFERROR(D5/P5,"") -> 0.82158149 | N5: =IFERROR(H5/F5,"") -> 0.037466348 | O5: =IFERROR(I5/P5,"") -> 0.048150701 | P5: 1156141
B6: Canon Inc. | C6: 7751.T | D6: 3894844 | E6: 4255022 | F6: 4624727 | G6: 694626 | H6: 455390 | I6: 332053 | J6: =IFERROR(E6/G6,"") -> 6.1256302 | K6: =IFERROR(E6/F6,"") -> 0.92005907 | L6: =IFERROR(D6/I6,"") -> 11.729585 | M6: =IFERROR(D6/P6,"") -> 1.1154233 | N6: =IFERROR(H6/F6,"") -> 0.098468515 | O6: =IFERROR(I6/P6,"") -> 0.095094862 | P6: 3491808
B7: FUJIFILM Holdings Corporation | C7: 4901.T | D7: 3962306 | E7: 4818766 | F7: 3356969 | G7: 522581 | H7: 350210 | I7: 276415 | J7: =IFERROR(E7/G7,"") -> 9.2210892 | K7: =IFERROR(E7/F7,"") -> 1.4354514 | L7: =IFERROR(D7/I7,"") -> 14.334627 | M7: =IFERROR(D7/P7,"") -> 1.0319715 | N7: =IFERROR(H7/F7,"") -> 0.10432327 | O7: =IFERROR(I7/P7,"") -> 0.071991509 | P7: 3839550
B8: Konica Minolta, Inc. | C8: 4902.T | D8: 325420 | E8: 612968 | F8: 1087738 | G8: 108552 | H8: 49869 | I8: 30268 | J8: =IFERROR(E8/G8,"") -> 5.6467684 | K8: =IFERROR(E8/F8,"") -> 0.56352541 | L8: =IFERROR(D8/I8,"") -> 10.751288 | M8: =IFERROR(D8/P8,"") -> 0.60655539 | N8: =IFERROR(H8/F8,"") -> 0.045846518 | O8: =IFERROR(I8/P8,"") -> 0.056416995 | P8: 536505
B9: Seiko Epson Corporation | C9: 6724.T | D9: 1037225 | E9: 980101 | F9: 1413251 | G9: 126975 | H9: 49558 | I9: 18201 | J9: =IFERROR(E9/G9,"") -> 7.7188502 | K9: =IFERROR(E9/F9,"") -> 0.69350809 | L9: =IFERROR(D9/I9,"") -> 56.987253 | M9: =IFERROR(D9/P9,"") -> 1.2152564 | N9: =IFERROR(H9/F9,"") -> 0.035066665 | O9: =IFERROR(I9/P9,"") -> 0.021325057 | P9: 853503
B10: Brother Industries, Ltd. | C10: 6448.T | D10: 1207757 | E10: 1011074 | F10: 893464 | G10: 129297 | H10: 77868 | I10: 67624 | J10: =IFERROR(E10/G10,"") -> 7.8197793 | K10: =IFERROR(E10/F10,"") -> 1.1316337 | L10: =IFERROR(D10/I10,"") -> 17.859887 | M10: =IFERROR(D10/P10,"") -> 1.5823312 | N10: =IFERROR(H10/F10,"") -> 0.087152924 | O10: =IFERROR(I10/P10,"") -> 0.088596931 | P10: 763277
B14: Statistics
B15: 25th Percentile | D15: =PERCENTILE(J6:J10,0.25) -> 6.1256302 | E15: =PERCENTILE(K6:K10,0.25) -> 0.69350809 | F15: =PERCENTILE(L6:L10,0.25) -> 11.729585 | G15: =PERCENTILE(M6:M10,0.25) -> 1.0319715 | H15: =PERCENTILE(N6:N10,0.25) -> 0.045846518 | I15: =PERCENTILE(O6:O10,0.25) -> 0.056416995
B16: Median (50th) | D16: =MEDIAN(J6:J10) -> 7.7188502 | E16: =MEDIAN(K6:K10) -> 0.92005907 | F16: =MEDIAN(L6:L10) -> 14.334627 | G16: =MEDIAN(M6:M10) -> 1.1154233 | H16: =MEDIAN(N6:N10) -> 0.087152924 | I16: =MEDIAN(O6:O10) -> 0.071991509
B17: 75th Percentile | D17: =PERCENTILE(J6:J10,0.75) -> 7.8197793 | E17: =PERCENTILE(K6:K10,0.75) -> 1.1316337 | F17: =PERCENTILE(L6:L10,0.75) -> 17.859887 | G17: =PERCENTILE(M6:M10,0.75) -> 1.2152564 | H17: =PERCENTILE(N6:N10,0.75) -> 0.098468515 | I17: =PERCENTILE(O6:O10,0.75) -> 0.088596931
B19: Implied Valuation for Ricoh Company, Ltd.
B20: Ricoh Company, Ltd. Financials
B21: EBITDA (JPY mn) | C21: 215128
B22: Net Income (JPY mn) | C22: 55669
B23: Shares Outstanding | C23: 562049730
B24: Net Debt (JPY mn) | C24: 227271
B26: Implied Share Price (Median Multiples)
B27: Via EV/EBITDA (Median) | C27: =ROUND((C21*D16-C24)*1000000/C23,0) -> 2550
B28: Via PER (Median) | C28: =ROUND(C22*F16*1000000/C23,0) -> 1420

Sheet Sensitivity Analysis
B2: Sensitivity Analysis
B3: Current WACC: | C3: ='DCF Model'!C26 -> 0.087966594 | E3: Terminal g: | F3: ='DCF Model'!C13 -> 0.01 | H3: Exit Multiple: | I3: ='DCF Model'!C14 -> 7.7
B5: Table 1: WACC vs Terminal Growth Rate (PGM - Implied Share Price, JPY)
B6: WACC \ Terminal g | C6: =$F$3-0.0075 -> 0.0025 | D6: =$F$3-0.005 -> 0.005 | E6: =$F$3-0.0025 -> 0.0075 | F6: =$F$3 -> 0.01 | G6: =$F$3+0.0025 -> 0.0125 | H6: =$F$3+0.005 -> 0.015 | I6: =$F$3+0.0075 -> 0.0175
B7: =$C$3-0.015 -> 0.072966594 | C7: =IFERROR(ROUND(('DCF Model'!C45/(1+$B7)^('DCF Model'!C19+0)+'DCF Model'!D45/(1+$B7)^('DCF Model'!C19+1)+'DCF Model'!E45/(1+$B7)^('DCF Model'!C19+2)+'DCF Model'!F45/(1+$B7)^('DCF Model'!C19+3)+'DCF Model'!G45/(1+$B7)^('DCF Model'!C19+4)+'DCF Model'!G45*(1+C$6)/($B7-C$6)/(1+$B7)^('DCF Model'!C19+4)-'DCF Model'!C16)*1000000/'DCF Model'!C15,0),"") -> 1175 | D7: =IFERROR(ROUND(('DCF Model'!C45/(1+$B7)^('DCF Model'!C19+0)+'DCF Model'!D45/(1+$B7)^('DCF Model'!C19+1)+'DCF Model'!E45/(1+$B7)^('DCF Model'!C19+2)+'DCF Model'!F45/(1+$B7)^('DCF Model'!C19+3)+'DCF Model'!G45/(1+$B7)^('DCF Model'!C19+4)+'DCF Model'!G45*(1+D$6)/($B7-D$6)/(1+$B7)^('DCF Model'!C19+4)-'DCF Model'!C16)*1000000/'DCF Model'!C15,0),"") -> 1220 | E7: =IFERROR(ROUND(('DCF Model'!C45/(1+$B7)^('DCF Model'!C19+0)+'DCF Model'!D45/(1+$B7)^('DCF Model'!C19+1)+'DCF Model'!E45/(1+$B7)^('DCF Model'!C19+2)+'DCF Model'!F45/(1+$B7)^('DCF Model'!C19+3)+'DCF Model'!G45/(1+$B7)^('DCF Model'!C19+4)+'DCF Model'!G45*(1+E$6)/($B7-E$6)/(1+$B7)^('DCF Model'!C19+4)-'DCF Model'!C16)*1000000/'DCF Model'!C15,0),"") -> 1269 | F7: =IFERROR(ROUND(('DCF Model'!C45/(1+$B7)^('DCF Model'!C19+0)+'DCF Model'!D45/(1+$B7)^('DCF Model'!C19+1)+'DCF Model'!E45/(1+$B7)^('DCF Model'!C19+2)+'DCF Model'!F45/(1+$B7)^('DCF Model'!C19+3)+'DCF Model'!G45/(1+$B7)^('DCF Model'!C19+4)+'DCF Model'!G45*(1+F$6)/($B7-F$6)/(1+$B7)^('DCF Model'!C19+4)-'DCF Model'!C16)*1000000/'DCF Model'!C15,0),"") -> 1322 | G7: =IFERROR(ROUND(('DCF Model'!C45/(1+$B7)^('DCF Model'!C19+0)+'DCF Model'!D45/(1+$B7)^('DCF Model'!C19+1)+'DCF Model'!E45/(1+$B7)^('DCF Model'!C19+2)+'DCF Model'!F45/(1+$B7)^('DCF Model'!C19+3)+'DCF Model'!G45/(1+$B7)^('DCF Model'!C19+4)+'DCF Model'!G45*(1+G$6)/($B7-G$6)/(1+$B7)^('DCF Model'!C19+4)-'DCF Model'!C16)*1000000/'DCF Model'!C15,0),"") -> 1379 | H7: =IFERROR(ROUND(('DCF Model'!C45/(1+$B7)^('DCF Model'!C19+0)+'DCF Model'!D45/(1+$B7)^('DCF Model'!C19+1)+'DCF Model'!E45/(1+$B7)^('DCF Model'!C19+2)+'DCF Model'!F45/(1+$B7)^('DCF Model'!C19+3)+'DCF Model'!G45/(1+$B7)^('DCF Model'!C19+4)+'DCF Model'!G45*(1+H$6)/($B7-H$6)/(1+$B7)^('DCF Model'!C19+4)-'DCF Model'!C16)*1000000/'DCF Model'!C15,0),"") -> 1441 | I7: =IFERROR(ROUND(('DCF Model'!C45/(1+$B7)^('DCF Model'!C19+0)+'DCF Model'!D45/(1+$B7)^('DCF Model'!C19+1)+'DCF Model'!E45/(1+$B7)^('DCF Model'!C19+2)+'DCF Model'!F45/(1+$B7)^('DCF Model'!C19+3)+'DCF Model'!G45/(1+$B7)^('DCF Model'!C19+4)+'DCF Model'!G45*(1+I$6)/($B7-I$6)/(1+$B7)^('DCF Model'!C19+4)-'DCF Model'!C16)*1000000/'DCF Model'!C15,0),"") -> 1508
B8: =$C$3-0.01 -> 0.077966594 | C8: =IFERROR(ROUND(('DCF Model'!C45/(1+$B8)^('DCF Model'!C19+0)+'DCF Model'!D45/(1+$B8)^('DCF Model'!C19+1)+'DCF Model'!E45/(1+$B8)^('DCF Model'!C19+2)+'DCF Model'!F45/(1+$B8)^('DCF Model'!C19+3)+'DCF Model'!G45/(1+$B8)^('DCF Model'!C19+4)+'DCF Model'!G45*(1+C$6)/($B8-C$6)/(1+$B8)^('DCF Model'!C19+4)-'DCF Model'!C16)*1000000/'DCF Model'!C15,0),"") -> 1068 | D8: =IFERROR(ROUND(('DCF Model'!C45/(1+$B8)^('DCF Model'!C19+0)+'DCF Model'!D45/(1+$B8)^('DCF Model'!C19+1)+'DCF Model'!E45/(1+$B8)^('DCF Model'!C19+2)+'DCF Model'!F45/(1+$B8)^('DCF Model'!C19+3)+'DCF Model'!G45/(1+$B8)^('DCF Model'!C19+4)+'DCF Model'!G45*(1+D$6)/($B8-D$6)/(1+$B8)^('DCF Model'!C19+4)-'DCF Model'!C16)*1000000/'DCF Model'!C15,0),"") -> 1107 | E8: =IFERROR(ROUND(('DCF Model'!C45/(1+$B8)^('DCF Model'!C19+0)+'DCF Model'!D45/(1+$B8)^('DCF Model'!C19+1)+'DCF Model'!E45/(1+$B8)^('DCF Model'!C19+2)+'DCF Model'!F45/(1+$B8)^('DCF Model'!C19+3)+'DCF Model'!G45/(1+$B8)^('DCF Model'!C19+4)+'DCF Model'!G45*(1+E$6)/($B8-E$6)/(1+$B8)^('DCF Model'!C19+4)-'DCF Model'!C16)*1000000/'DCF Model'!C15,0),"") -> 1148 | F8: =IFERROR(ROUND(('DCF Model'!C45/(1+$B8)^('DCF Model'!C19+0)+'DCF Model'!D45/(1+$B8)^('DCF Model'!C19+1)+'DCF Model'!E45/(1+$B8)^('DCF Model'!C19+2)+'DCF Model'!F45/(1+$B8)^('DCF Model'!C19+3)+'DCF Model'!G45/(1+$B8)^('DCF Model'!C19+4)+'DCF Model'!G45*(1+F$6)/($B8-F$6)/(1+$B8)^('DCF Model'!C19+4)-'DCF Model'!C16)*1000000/'DCF Model'!C15,0),"") -> 1193 | G8: =IFERROR(ROUND(('DCF Model'!C45/(1+$B8)^('DCF Model'!C19+0)+'DCF Model'!D45/(1+$B8)^('DCF Model'!C19+1)+'DCF Model'!E45/(1+$B8)^('DCF Model'!C19+2)+'DCF Model'!F45/(1+$B8)^('DCF Model'!C19+3)+'DCF Model'!G45/(1+$B8)^('DCF Model'!C19+4)+'DCF Model'!G45*(1+G$6)/($B8-G$6)/(1+$B8)^('DCF Model'!C19+4)-'DCF Model'!C16)*1000000/'DCF Model'!C15,0),"") -> 1241 | H8: =IFERROR(ROUND(('DCF Model'!C45/(1+$B8)^('DCF Model'!C19+0)+'DCF Model'!D45/(1+$B8)^('DCF Model'!C19+1)+'DCF Model'!E45/(1+$B8)^('DCF Model'!C19+2)+'DCF Model'!F45/(1+$B8)^('DCF Model'!C19+3)+'DCF Model'!G45/(1+$B8)^('DCF Model'!C19+4)+'DCF Model'!G45*(1+H$6)/($B8-H$6)/(1+$B8)^('DCF Model'!C19+4)-'DCF Model'!C16)*1000000/'DCF Model'!C15,0),"") -> 1292 | I8: =IFERROR(ROUND(('DCF Model'!C45/(1+$B8)^('DCF Model'!C19+0)+'DCF Model'!D45/(1+$B8)^('DCF Model'!C19+1)+'DCF Model'!E45/(1+$B8)^('DCF Model'!C19+2)+'DCF Model'!F45/(1+$B8)^('DCF Model'!C19+3)+'DCF Model'!G45/(1+$B8)^('DCF Model'!C19+4)+'DCF Model'!G45*(1+I$6)/($B8-I$6)/(1+$B8)^('DCF Model'!C19+4)-'DCF Model'!C16)*1000000/'DCF Model'!C15,0),"") -> 1348
B9: =$C$3-0.005 -> 0.082966594 | C9: =IFERROR(ROUND(('DCF Model'!C45/(1+$B9)^('DCF Model'!C19+0)+'DCF Model'!D45/(1+$B9)^('DCF Model'!C19+1)+'DCF Model'!E45/(1+$B9)^('DCF Model'!C19+2)+'DCF Model'!F45/(1+$B9)^('DCF Model'!C19+3)+'DCF Model'!G45/(1+$B9)^('DCF Model'!C19+4)+'DCF Model'!G45*(1+C$6)/($B9-C$6)/(1+$B9)^('DCF Model'!C19+4)-'DCF Model'!C16)*1000000/'DCF Model'!C15,0),"") -> 975 | D9: =IFERROR(ROUND(('DCF Model'!C45/(1+$B9)^('DCF Model'!C19+0)+'DCF Model'!D45/(1+$B9)^('DCF Model'!C19+1)+'DCF Model'!E45/(1+$B9)^('DCF Model'!C19+2)+'DCF Model'!F45/(1+$B9)^('DCF Model'!C19+3)+'DCF Model'!G45/(1+$B9)^('DCF Model'!C19+4)+'DCF Model'!G45*(1+D$6)/($B9-D$6)/(1+$B9)^('DCF Model'!C19+4)-'DCF Model'!C16)*1000000/'DCF Model'!C15,0),"") -> 1008 | E9: =IFERROR(ROUND(('DCF Model'!C45/(1+$B9)^('DCF Model'!C19+0)+'DCF Model'!D45/(1+$B9)^('DCF Model'!C19+1)+'DCF Model'!E45/(1+$B9)^('DCF Model'!C19+2)+'DCF Model'!F45/(1+$B9)^('DCF Model'!C19+3)+'DCF Model'!G45/(1+$B9)^('DCF Model'!C19+4)+'DCF Model'!G45*(1+E$6)/($B9-E$6)/(1+$B9)^('DCF Model'!C19+4)-'DCF Model'!C16)*1000000/'DCF Model'!C15,0),"") -> 1043 | F9: =IFERROR(ROUND(('DCF Model'!C45/(1+$B9)^('DCF Model'!C19+0)+'DCF Model'!D45/(1+$B9)^('DCF Model'!C19+1)+'DCF Model'!E45/(1+$B9)^('DCF Model'!C19+2)+'DCF Model'!F45/(1+$B9)^('DCF Model'!C19+3)+'DCF Model'!G45/(1+$B9)^('DCF Model'!C19+4)+'DCF Model'!G45*(1+F$6)/($B9-F$6)/(1+$B9)^('DCF Model'!C19+4)-'DCF Model'!C16)*1000000/'DCF Model'!C15,0),"") -> 1081 | G9: =IFERROR(ROUND(('DCF Model'!C45/(1+$B9)^('DCF Model'!C19+0)+'DCF Model'!D45/(1+$B9)^('DCF Model'!C19+1)+'DCF Model'!E45/(1+$B9)^('DCF Model'!C19+2)+'DCF Model'!F45/(1+$B9)^('DCF Model'!C19+3)+'DCF Model'!G45/(1+$B9)^('DCF Model'!C19+4)+'DCF Model'!G45*(1+G$6)/($B9-G$6)/(1+$B9)^('DCF Model'!C19+4)-'DCF Model'!C16)*1000000/'DCF Model'!C15,0),"") -> 1122 | H9: =IFERROR(ROUND(('DCF Model'!C45/(1+$B9)^('DCF Model'!C19+0)+'DCF Model'!D45/(1+$B9)^('DCF Model'!C19+1)+'DCF Model'!E45/(1+$B9)^('DCF Model'!C19+2)+'DCF Model'!F45/(1+$B9)^('DCF Model'!C19+3)+'DCF Model'!G45/(1+$B9)^('DCF Model'!C19+4)+'DCF Model'!G45*(1+H$6)/($B9-H$6)/(1+$B9)^('DCF Model'!C19+4)-'DCF Model'!C16)*1000000/'DCF Model'!C15,0),"") -> 1166 | I9: =IFERROR(ROUND(('DCF Model'!C45/(1+$B9)^('DCF Model'!C19+0)+'DCF Model'!D45/(1+$B9)^('DCF Model'!C19+1)+'DCF Model'!E45/(1+$B9)^('DCF Model'!C19+2)+'DCF Model'!F45/(1+$B9)^('DCF Model'!C19+3)+'DCF Model'!G45/(1+$B9)^('DCF Model'!C19+4)+'DCF Model'!G45*(1+I$6)/($B9-I$6)/(1+$B9)^('DCF Model'!C19+4)-'DCF Model'!C16)*1000000/'DCF Model'!C15,0),"") -> 1213
B10: =$C$3 -> 0.087966594 | C10: =IFERROR(ROUND(('DCF Model'!C45/(1+$B10)^('DCF Model'!C19+0)+'DCF Model'!D45/(1+$B10)^('DCF Model'!C19+1)+'DCF Model'!E45/(1+$B10)^('DCF Model'!C19+2)+'DCF Model'!F45/(1+$B10)^('DCF Model'!C19+3)+'DCF Model'!G45/(1+$B10)^('DCF Model'!C19+4)+'DCF Model'!G45*(1+C$6)/($B10-C$6)/(1+$B10)^('DCF Model'!C19+4)-'DCF Model'!C16)*1000000/'DCF Model'!C15,0),"") -> 892 | D10: =IFERROR(ROUND(('DCF Model'!C45/(1+$B10)^('DCF Model'!C19+0)+'DCF Model'!D45/(1+$B10)^('DCF Model'!C19+1)+'DCF Model'!E45/(1+$B10)^('DCF Model'!C19+2)+'DCF Model'!F45/(1+$B10)^('DCF Model'!C19+3)+'DCF Model'!G45/(1+$B10)^('DCF Model'!C19+4)+'DCF Model'!G45*(1+D$6)/($B10-D$6)/(1+$B10)^('DCF Model'!C19+4)-'DCF Model'!C16)*1000000/'DCF Model'!C15,0),"") -> 921 | E10: =IFERROR(ROUND(('DCF Model'!C45/(1+$B10)^('DCF Model'!C19+0)+'DCF Model'!D45/(1+$B10)^('DCF Model'!C19+1)+'DCF Model'!E45/(1+$B10)^('DCF Model'!C19+2)+'DCF Model'!F45/(1+$B10)^('DCF Model'!C19+3)+'DCF Model'!G45/(1+$B10)^('DCF Model'!C19+4)+'DCF Model'!G45*(1+E$6)/($B10-E$6)/(1+$B10)^('DCF Model'!C19+4)-'DCF Model'!C16)*1000000/'DCF Model'!C15,0),"") -> 952 | F10: =IFERROR(ROUND(('DCF Model'!C45/(1+$B10)^('DCF Model'!C19+0)+'DCF Model'!D45/(1+$B10)^('DCF Model'!C19+1)+'DCF Model'!E45/(1+$B10)^('DCF Model'!C19+2)+'DCF Model'!F45/(1+$B10)^('DCF Model'!C19+3)+'DCF Model'!G45/(1+$B10)^('DCF Model'!C19+4)+'DCF Model'!G45*(1+F$6)/($B10-F$6)/(1+$B10)^('DCF Model'!C19+4)-'DCF Model'!C16)*1000000/'DCF Model'!C15,0),"") -> 984 | G10: =IFERROR(ROUND(('DCF Model'!C45/(1+$B10)^('DCF Model'!C19+0)+'DCF Model'!D45/(1+$B10)^('DCF Model'!C19+1)+'DCF Model'!E45/(1+$B10)^('DCF Model'!C19+2)+'DCF Model'!F45/(1+$B10)^('DCF Model'!C19+3)+'DCF Model'!G45/(1+$B10)^('DCF Model'!C19+4)+'DCF Model'!G45*(1+G$6)/($B10-G$6)/(1+$B10)^('DCF Model'!C19+4)-'DCF Model'!C16)*1000000/'DCF Model'!C15,0),"") -> 1019 | H10: =IFERROR(ROUND(('DCF Model'!C45/(1+$B10)^('DCF Model'!C19+0)+'DCF Model'!D45/(1+$B10)^('DCF Model'!C19+1)+'DCF Model'!E45/(1+$B10)^('DCF Model'!C19+2)+'DCF Model'!F45/(1+$B10)^('DCF Model'!C19+3)+'DCF Model'!G45/(1+$B10)^('DCF Model'!C19+4)+'DCF Model'!G45*(1+H$6)/($B10-H$6)/(1+$B10)^('DCF Model'!C19+4)-'DCF Model'!C16)*1000000/'DCF Model'!C15,0),"") -> 1057 | I10: =IFERROR(ROUND(('DCF Model'!C45/(1+$B10)^('DCF Model'!C19+0)+'DCF Model'!D45/(1+$B10)^('DCF Model'!C19+1)+'DCF Model'!E45/(1+$B10)^('DCF Model'!C19+2)+'DCF Model'!F45/(1+$B10)^('DCF Model'!C19+3)+'DCF Model'!G45/(1+$B10)^('DCF Model'!C19+4)+'DCF Model'!G45*(1+I$6)/($B10-I$6)/(1+$B10)^('DCF Model'!C19+4)-'DCF Model'!C16)*1000000/'DCF Model'!C15,0),"") -> 1097
B11: =$C$3+0.005 -> 0.092966594 | C11: =IFERROR(ROUND(('DCF Model'!C45/(1+$B11)^('DCF Model'!C19+0)+'DCF Model'!D45/(1+$B11)^('DCF Model'!C19+1)+'DCF Model'!E45/(1+$B11)^('DCF Model'!C19+2)+'DCF Model'!F45/(1+$B11)^('DCF Model'!C19+3)+'DCF Model'!G45/(1+$B11)^('DCF Model'!C19+4)+'DCF Model'!G45*(1+C$6)/($B11-C$6)/(1+$B11)^('DCF Model'!C19+4)-'DCF Model'!C16)*1000000/'DCF Model'!C15,0),"") -> 819 | D11: =IFERROR(ROUND(('DCF Model'!C45/(1+$B11)^('DCF Model'!C19+0)+'DCF Model'!D45/(1+$B11)^('DCF Model'!C19+1)+'DCF Model'!E45/(1+$B11)^('DCF Model'!C19+2)+'DCF Model'!F45/(1+$B11)^('DCF Model'!C19+3)+'DCF Model'!G45/(1+$B11)^('DCF Model'!C19+4)+'DCF Model'!G45*(1+D$6)/($B11-D$6)/(1+$B11)^('DCF Model'!C19+4)-'DCF Model'!C16)*1000000/'DCF Model'!C15,0),"") -> 844 | E11: =IFERROR(ROUND(('DCF Model'!C45/(1+$B11)^('DCF Model'!C19+0)+'DCF Model'!D45/(1+$B11)^('DCF Model'!C19+1)+'DCF Model'!E45/(1+$B11)^('DCF Model'!C19+2)+'DCF Model'!F45/(1+$B11)^('DCF Model'!C19+3)+'DCF Model'!G45/(1+$B11)^('DCF Model'!C19+4)+'DCF Model'!G45*(1+E$6)/($B11-E$6)/(1+$B11)^('DCF Model'!C19+4)-'DCF Model'!C16)*1000000/'DCF Model'!C15,0),"") -> 871 | F11: =IFERROR(ROUND(('DCF Model'!C45/(1+$B11)^('DCF Model'!C19+0)+'DCF Model'!D45/(1+$B11)^('DCF Model'!C19+1)+'DCF Model'!E45/(1+$B11)^('DCF Model'!C19+2)+'DCF Model'!F45/(1+$B11)^('DCF Model'!C19+3)+'DCF Model'!G45/(1+$B11)^('DCF Model'!C19+4)+'DCF Model'!G45*(1+F$6)/($B11-F$6)/(1+$B11)^('DCF Model'!C19+4)-'DCF Model'!C16)*1000000/'DCF Model'!C15,0),"") -> 899 | G11: =IFERROR(ROUND(('DCF Model'!C45/(1+$B11)^('DCF Model'!C19+0)+'DCF Model'!D45/(1+$B11)^('DCF Model'!C19+1)+'DCF Model'!E45/(1+$B11)^('DCF Model'!C19+2)+'DCF Model'!F45/(1+$B11)^('DCF Model'!C19+3)+'DCF Model'!G45/(1+$B11)^('DCF Model'!C19+4)+'DCF Model'!G45*(1+G$6)/($B11-G$6)/(1+$B11)^('DCF Model'!C19+4)-'DCF Model'!C16)*1000000/'DCF Model'!C15,0),"") -> 929 | H11: =IFERROR(ROUND(('DCF Model'!C45/(1+$B11)^('DCF Model'!C19+0)+'DCF Model'!D45/(1+$B11)^('DCF Model'!C19+1)+'DCF Model'!E45/(1+$B11)^('DCF Model'!C19+2)+'DCF Model'!F45/(1+$B11)^('DCF Model'!C19+3)+'DCF Model'!G45/(1+$B11)^('DCF Model'!C19+4)+'DCF Model'!G45*(1+H$6)/($B11-H$6)/(1+$B11)^('DCF Model'!C19+4)-'DCF Model'!C16)*1000000/'DCF Model'!C15,0),"") -> 962 | I11: =IFERROR(ROUND(('DCF Model'!C45/(1+$B11)^('DCF Model'!C19+0)+'DCF Model'!D45/(1+$B11)^('DCF Model'!C19+1)+'DCF Model'!E45/(1+$B11)^('DCF Model'!C19+2)+'DCF Model'!F45/(1+$B11)^('DCF Model'!C19+3)+'DCF Model'!G45/(1+$B11)^('DCF Model'!C19+4)+'DCF Model'!G45*(1+I$6)/($B11-I$6)/(1+$B11)^('DCF Model'!C19+4)-'DCF Model'!C16)*1000000/'DCF Model'!C15,0),"") -> 996
B12: =$C$3+0.01 -> 0.097966594 | C12: =IFERROR(ROUND(('DCF Model'!C45/(1+$B12)^('DCF Model'!C19+0)+'DCF Model'!D45/(1+$B12)^('DCF Model'!C19+1)+'DCF Model'!E45/(1+$B12)^('DCF Model'!C19+2)+'DCF Model'!F45/(1+$B12)^('DCF Model'!C19+3)+'DCF Model'!G45/(1+$B12)^('DCF Model'!C19+4)+'DCF Model'!G45*(1+C$6)/($B12-C$6)/(1+$B12)^('DCF Model'!C19+4)-'DCF Model'!C16)*1000000/'DCF Model'!C15,0),"") -> 753 | D12: =IFERROR(ROUND(('DCF Model'!C45/(1+$B12)^('DCF Model'!C19+0)+'DCF Model'!D45/(1+$B12)^('DCF Model'!C19+1)+'DCF Model'!E45/(1+$B12)^('DCF Model'!C19+2)+'DCF Model'!F45/(1+$B12)^('DCF Model'!C19+3)+'DCF Model'!G45/(1+$B12)^('DCF Model'!C19+4)+'DCF Model'!G45*(1+D$6)/($B12-D$6)/(1+$B12)^('DCF Model'!C19+4)-'DCF Model'!C16)*1000000/'DCF Model'!C15,0),"") -> 775 | E12: =IFERROR(ROUND(('DCF Model'!C45/(1+$B12)^('DCF Model'!C19+0)+'DCF Model'!D45/(1+$B12)^('DCF Model'!C19+1)+'DCF Model'!E45/(1+$B12)^('DCF Model'!C19+2)+'DCF Model'!F45/(1+$B12)^('DCF Model'!C19+3)+'DCF Model'!G45/(1+$B12)^('DCF Model'!C19+4)+'DCF Model'!G45*(1+E$6)/($B12-E$6)/(1+$B12)^('DCF Model'!C19+4)-'DCF Model'!C16)*1000000/'DCF Model'!C15,0),"") -> 799 | F12: =IFERROR(ROUND(('DCF Model'!C45/(1+$B12)^('DCF Model'!C19+0)+'DCF Model'!D45/(1+$B12)^('DCF Model'!C19+1)+'DCF Model'!E45/(1+$B12)^('DCF Model'!C19+2)+'DCF Model'!F45/(1+$B12)^('DCF Model'!C19+3)+'DCF Model'!G45/(1+$B12)^('DCF Model'!C19+4)+'DCF Model'!G45*(1+F$6)/($B12-F$6)/(1+$B12)^('DCF Model'!C19+4)-'DCF Model'!C16)*1000000/'DCF Model'!C15,0),"") -> 824 | G12: =IFERROR(ROUND(('DCF Model'!C45/(1+$B12)^('DCF Model'!C19+0)+'DCF Model'!D45/(1+$B12)^('DCF Model'!C19+1)+'DCF Model'!E45/(1+$B12)^('DCF Model'!C19+2)+'DCF Model'!F45/(1+$B12)^('DCF Model'!C19+3)+'DCF Model'!G45/(1+$B12)^('DCF Model'!C19+4)+'DCF Model'!G45*(1+G$6)/($B12-G$6)/(1+$B12)^('DCF Model'!C19+4)-'DCF Model'!C16)*1000000/'DCF Model'!C15,0),"") -> 850 | H12: =IFERROR(ROUND(('DCF Model'!C45/(1+$B12)^('DCF Model'!C19+0)+'DCF Model'!D45/(1+$B12)^('DCF Model'!C19+1)+'DCF Model'!E45/(1+$B12)^('DCF Model'!C19+2)+'DCF Model'!F45/(1+$B12)^('DCF Model'!C19+3)+'DCF Model'!G45/(1+$B12)^('DCF Model'!C19+4)+'DCF Model'!G45*(1+H$6)/($B12-H$6)/(1+$B12)^('DCF Model'!C19+4)-'DCF Model'!C16)*1000000/'DCF Model'!C15,0),"") -> 878 | I12: =IFERROR(ROUND(('DCF Model'!C45/(1+$B12)^('DCF Model'!C19+0)+'DCF Model'!D45/(1+$B12)^('DCF Model'!C19+1)+'DCF Model'!E45/(1+$B12)^('DCF Model'!C19+2)+'DCF Model'!F45/(1+$B12)^('DCF Model'!C19+3)+'DCF Model'!G45/(1+$B12)^('DCF Model'!C19+4)+'DCF Model'!G45*(1+I$6)/($B12-I$6)/(1+$B12)^('DCF Model'!C19+4)-'DCF Model'!C16)*1000000/'DCF Model'!C15,0),"") -> 908
B13: =$C$3+0.015 -> 0.10296659 | C13: =IFERROR(ROUND(('DCF Model'!C45/(1+$B13)^('DCF Model'!C19+0)+'DCF Model'!D45/(1+$B13)^('DCF Model'!C19+1)+'DCF Model'!E45/(1+$B13)^('DCF Model'!C19+2)+'DCF Model'!F45/(1+$B13)^('DCF Model'!C19+3)+'DCF Model'!G45/(1+$B13)^('DCF Model'!C19+4)+'DCF Model'!G45*(1+C$6)/($B13-C$6)/(1+$B13)^('DCF Model'!C19+4)-'DCF Model'!C16)*1000000/'DCF Model'!C15,0),"") -> 694 | D13: =IFERROR(ROUND(('DCF Model'!C45/(1+$B13)^('DCF Model'!C19+0)+'DCF Model'!D45/(1+$B13)^('DCF Model'!C19+1)+'DCF Model'!E45/(1+$B13)^('DCF Model'!C19+2)+'DCF Model'!F45/(1+$B13)^('DCF Model'!C19+3)+'DCF Model'!G45/(1+$B13)^('DCF Model'!C19+4)+'DCF Model'!G45*(1+D$6)/($B13-D$6)/(1+$B13)^('DCF Model'!C19+4)-'DCF Model'!C16)*1000000/'DCF Model'!C15,0),"") -> 714 | E13: =IFERROR(ROUND(('DCF Model'!C45/(1+$B13)^('DCF Model'!C19+0)+'DCF Model'!D45/(1+$B13)^('DCF Model'!C19+1)+'DCF Model'!E45/(1+$B13)^('DCF Model'!C19+2)+'DCF Model'!F45/(1+$B13)^('DCF Model'!C19+3)+'DCF Model'!G45/(1+$B13)^('DCF Model'!C19+4)+'DCF Model'!G45*(1+E$6)/($B13-E$6)/(1+$B13)^('DCF Model'!C19+4)-'DCF Model'!C16)*1000000/'DCF Model'!C15,0),"") -> 734 | F13: =IFERROR(ROUND(('DCF Model'!C45/(1+$B13)^('DCF Model'!C19+0)+'DCF Model'!D45/(1+$B13)^('DCF Model'!C19+1)+'DCF Model'!E45/(1+$B13)^('DCF Model'!C19+2)+'DCF Model'!F45/(1+$B13)^('DCF Model'!C19+3)+'DCF Model'!G45/(1+$B13)^('DCF Model'!C19+4)+'DCF Model'!G45*(1+F$6)/($B13-F$6)/(1+$B13)^('DCF Model'!C19+4)-'DCF Model'!C16)*1000000/'DCF Model'!C15,0),"") -> 756 | G13: =IFERROR(ROUND(('DCF Model'!C45/(1+$B13)^('DCF Model'!C19+0)+'DCF Model'!D45/(1+$B13)^('DCF Model'!C19+1)+'DCF Model'!E45/(1+$B13)^('DCF Model'!C19+2)+'DCF Model'!F45/(1+$B13)^('DCF Model'!C19+3)+'DCF Model'!G45/(1+$B13)^('DCF Model'!C19+4)+'DCF Model'!G45*(1+G$6)/($B13-G$6)/(1+$B13)^('DCF Model'!C19+4)-'DCF Model'!C16)*1000000/'DCF Model'!C15,0),"") -> 779 | H13: =IFERROR(ROUND(('DCF Model'!C45/(1+$B13)^('DCF Model'!C19+0)+'DCF Model'!D45/(1+$B13)^('DCF Model'!C19+1)+'DCF Model'!E45/(1+$B13)^('DCF Model'!C19+2)+'DCF Model'!F45/(1+$B13)^('DCF Model'!C19+3)+'DCF Model'!G45/(1+$B13)^('DCF Model'!C19+4)+'DCF Model'!G45*(1+H$6)/($B13-H$6)/(1+$B13)^('DCF Model'!C19+4)-'DCF Model'!C16)*1000000/'DCF Model'!C15,0),"") -> 804 | I13: =IFERROR(ROUND(('DCF Model'!C45/(1+$B13)^('DCF Model'!C19+0)+'DCF Model'!D45/(1+$B13)^('DCF Model'!C19+1)+'DCF Model'!E45/(1+$B13)^('DCF Model'!C19+2)+'DCF Model'!F45/(1+$B13)^('DCF Model'!C19+3)+'DCF Model'!G45/(1+$B13)^('DCF Model'!C19+4)+'DCF Model'!G45*(1+I$6)/($B13-I$6)/(1+$B13)^('DCF Model'!C19+4)-'DCF Model'!C16)*1000000/'DCF Model'!C15,0),"") -> 830
B16: Table 2: WACC vs Exit Multiple (Exit Multiple - Implied Share Price, JPY)
B17: WACC \ Exit Multiple | C17: =$I$3-3 -> 4.7 | D17: =$I$3-2 -> 5.7 | E17: =$I$3-1 -> 6.7 | F17: =$I$3 -> 7.7 | G17: =$I$3+1 -> 8.7 | H17: =$I$3+2 -> 9.7 | I17: =$I$3+3 -> 10.7
B18: =$C$3-0.015 -> 0.072966594 | C18: =IFERROR(ROUND(('DCF Model'!C45/(1+$B18)^('DCF Model'!C19+0)+'DCF Model'!D45/(1+$B18)^('DCF Model'!C19+1)+'DCF Model'!E45/(1+$B18)^('DCF Model'!C19+2)+'DCF Model'!F45/(1+$B18)^('DCF Model'!C19+3)+'DCF Model'!G45/(1+$B18)^('DCF Model'!C19+4)+('DCF Model'!G39+'DCF Model'!G42)*C$17/(1+$B18)^('DCF Model'!C19+4)-'DCF Model'!C16)*1000000/'DCF Model'!C15,0),"") -> 1504 | D18: =IFERROR(ROUND(('DCF Model'!C45/(1+$B18)^('DCF Model'!C19+0)+'DCF Model'!D45/(1+$B18)^('DCF Model'!C19+1)+'DCF Model'!E45/(1+$B18)^('DCF Model'!C19+2)+'DCF Model'!F45/(1+$B18)^('DCF Model'!C19+3)+'DCF Model'!G45/(1+$B18)^('DCF Model'!C19+4)+('DCF Model'!G39+'DCF Model'!G42)*D$17/(1+$B18)^('DCF Model'!C19+4)-'DCF Model'!C16)*1000000/'DCF Model'!C15,0),"") -> 1819 | E18: =IFERROR(ROUND(('DCF Model'!C45/(1+$B18)^('DCF Model'!C19+0)+'DCF Model'!D45/(1+$B18)^('DCF Model'!C19+1)+'DCF Model'!E45/(1+$B18)^('DCF Model'!C19+2)+'DCF Model'!F45/(1+$B18)^('DCF Model'!C19+3)+'DCF Model'!G45/(1+$B18)^('DCF Model'!C19+4)+('DCF Model'!G39+'DCF Model'!G42)*E$17/(1+$B18)^('DCF Model'!C19+4)-'DCF Model'!C16)*1000000/'DCF Model'!C15,0),"") -> 2134 | F18: =IFERROR(ROUND(('DCF Model'!C45/(1+$B18)^('DCF Model'!C19+0)+'DCF Model'!D45/(1+$B18)^('DCF Model'!C19+1)+'DCF Model'!E45/(1+$B18)^('DCF Model'!C19+2)+'DCF Model'!F45/(1+$B18)^('DCF Model'!C19+3)+'DCF Model'!G45/(1+$B18)^('DCF Model'!C19+4)+('DCF Model'!G39+'DCF Model'!G42)*F$17/(1+$B18)^('DCF Model'!C19+4)-'DCF Model'!C16)*1000000/'DCF Model'!C15,0),"") -> 2449 | G18: =IFERROR(ROUND(('DCF Model'!C45/(1+$B18)^('DCF Model'!C19+0)+'DCF Model'!D45/(1+$B18)^('DCF Model'!C19+1)+'DCF Model'!E45/(1+$B18)^('DCF Model'!C19+2)+'DCF Model'!F45/(1+$B18)^('DCF Model'!C19+3)+'DCF Model'!G45/(1+$B18)^('DCF Model'!C19+4)+('DCF Model'!G39+'DCF Model'!G42)*G$17/(1+$B18)^('DCF Model'!C19+4)-'DCF Model'!C16)*1000000/'DCF Model'!C15,0),"") -> 2764 | H18: =IFERROR(ROUND(('DCF Model'!C45/(1+$B18)^('DCF Model'!C19+0)+'DCF Model'!D45/(1+$B18)^('DCF Model'!C19+1)+'DCF Model'!E45/(1+$B18)^('DCF Model'!C19+2)+'DCF Model'!F45/(1+$B18)^('DCF Model'!C19+3)+'DCF Model'!G45/(1+$B18)^('DCF Model'!C19+4)+('DCF Model'!G39+'DCF Model'!G42)*H$17/(1+$B18)^('DCF Model'!C19+4)-'DCF Model'!C16)*1000000/'DCF Model'!C15,0),"") -> 3079 | I18: =IFERROR(ROUND(('DCF Model'!C45/(1+$B18)^('DCF Model'!C19+0)+'DCF Model'!D45/(1+$B18)^('DCF Model'!C19+1)+'DCF Model'!E45/(1+$B18)^('DCF Model'!C19+2)+'DCF Model'!F45/(1+$B18)^('DCF Model'!C19+3)+'DCF Model'!G45/(1+$B18)^('DCF Model'!C19+4)+('DCF Model'!G39+'DCF Model'!G42)*I$17/(1+$B18)^('DCF Model'!C19+4)-'DCF Model'!C16)*1000000/'DCF Model'!C15,0),"") -> 3394
B19: =$C$3-0.01 -> 0.077966594 | C19: =IFERROR(ROUND(('DCF Model'!C45/(1+$B19)^('DCF Model'!C19+0)+'DCF Model'!D45/(1+$B19)^('DCF Model'!C19+1)+'DCF Model'!E45/(1+$B19)^('DCF Model'!C19+2)+'DCF Model'!F45/(1+$B19)^('DCF Model'!C19+3)+'DCF Model'!G45/(1+$B19)^('DCF Model'!C19+4)+('DCF Model'!G39+'DCF Model'!G42)*C$17/(1+$B19)^('DCF Model'!C19+4)-'DCF Model'!C16)*1000000/'DCF Model'!C15,0),"") -> 1464 | D19: =IFERROR(ROUND(('DCF Model'!C45/(1+$B19)^('DCF Model'!C19+0)+'DCF Model'!D45/(1+$B19)^('DCF Model'!C19+1)+'DCF Model'!E45/(1+$B19)^('DCF Model'!C19+2)+'DCF Model'!F45/(1+$B19)^('DCF Model'!C19+3)+'DCF Model'!G45/(1+$B19)^('DCF Model'!C19+4)+('DCF Model'!G39+'DCF Model'!G42)*D$17/(1+$B19)^('DCF Model'!C19+4)-'DCF Model'!C16)*1000000/'DCF Model'!C15,0),"") -> 1772 | E19: =IFERROR(ROUND(('DCF Model'!C45/(1+$B19)^('DCF Model'!C19+0)+'DCF Model'!D45/(1+$B19)^('DCF Model'!C19+1)+'DCF Model'!E45/(1+$B19)^('DCF Model'!C19+2)+'DCF Model'!F45/(1+$B19)^('DCF Model'!C19+3)+'DCF Model'!G45/(1+$B19)^('DCF Model'!C19+4)+('DCF Model'!G39+'DCF Model'!G42)*E$17/(1+$B19)^('DCF Model'!C19+4)-'DCF Model'!C16)*1000000/'DCF Model'!C15,0),"") -> 2080 | F19: =IFERROR(ROUND(('DCF Model'!C45/(1+$B19)^('DCF Model'!C19+0)+'DCF Model'!D45/(1+$B19)^('DCF Model'!C19+1)+'DCF Model'!E45/(1+$B19)^('DCF Model'!C19+2)+'DCF Model'!F45/(1+$B19)^('DCF Model'!C19+3)+'DCF Model'!G45/(1+$B19)^('DCF Model'!C19+4)+('DCF Model'!G39+'DCF Model'!G42)*F$17/(1+$B19)^('DCF Model'!C19+4)-'DCF Model'!C16)*1000000/'DCF Model'!C15,0),"") -> 2388 | G19: =IFERROR(ROUND(('DCF Model'!C45/(1+$B19)^('DCF Model'!C19+0)+'DCF Model'!D45/(1+$B19)^('DCF Model'!C19+1)+'DCF Model'!E45/(1+$B19)^('DCF Model'!C19+2)+'DCF Model'!F45/(1+$B19)^('DCF Model'!C19+3)+'DCF Model'!G45/(1+$B19)^('DCF Model'!C19+4)+('DCF Model'!G39+'DCF Model'!G42)*G$17/(1+$B19)^('DCF Model'!C19+4)-'DCF Model'!C16)*1000000/'DCF Model'!C15,0),"") -> 2695 | H19: =IFERROR(ROUND(('DCF Model'!C45/(1+$B19)^('DCF Model'!C19+0)+'DCF Model'!D45/(1+$B19)^('DCF Model'!C19+1)+'DCF Model'!E45/(1+$B19)^('DCF Model'!C19+2)+'DCF Model'!F45/(1+$B19)^('DCF Model'!C19+3)+'DCF Model'!G45/(1+$B19)^('DCF Model'!C19+4)+('DCF Model'!G39+'DCF Model'!G42)*H$17/(1+$B19)^('DCF Model'!C19+4)-'DCF Model'!C16)*1000000/'DCF Model'!C15,0),"") -> 3003 | I19: =IFERROR(ROUND(('DCF Model'!C45/(1+$B19)^('DCF Model'!C19+0)+'DCF Model'!D45/(1+$B19)^('DCF Model'!C19+1)+'DCF Model'!E45/(1+$B19)^('DCF Model'!C19+2)+'DCF Model'!F45/(1+$B19)^('DCF Model'!C19+3)+'DCF Model'!G45/(1+$B19)^('DCF Model'!C19+4)+('DCF Model'!G39+'DCF Model'!G42)*I$17/(1+$B19)^('DCF Model'!C19+4)-'DCF Model'!C16)*1000000/'DCF Model'!C15,0),"") -> 3311
B20: =$C$3-0.005 -> 0.082966594 | C20: =IFERROR(ROUND(('DCF Model'!C45/(1+$B20)^('DCF Model'!C19+0)+'DCF Model'!D45/(1+$B20)^('DCF Model'!C19+1)+'DCF Model'!E45/(1+$B20)^('DCF Model'!C19+2)+'DCF Model'!F45/(1+$B20)^('DCF Model'!C19+3)+'DCF Model'!G45/(1+$B20)^('DCF Model'!C19+4)+('DCF Model'!G39+'DCF Model'!G42)*C$17/(1+$B20)^('DCF Model'!C19+4)-'DCF Model'!C16)*1000000/'DCF Model'!C15,0),"") -> 1425 | D20: =IFERROR(ROUND(('DCF Model'!C45/(1+$B20)^('DCF Model'!C19+0)+'DCF Model'!D45/(1+$B20)^('DCF Model'!C19+1)+'DCF Model'!E45/(1+$B20)^('DCF Model'!C19+2)+'DCF Model'!F45/(1+$B20)^('DCF Model'!C19+3)+'DCF Model'!G45/(1+$B20)^('DCF Model'!C19+4)+('DCF Model'!G39+'DCF Model'!G42)*D$17/(1+$B20)^('DCF Model'!C19+4)-'DCF Model'!C16)*1000000/'DCF Model'!C15,0),"") -> 1726 | E20: =IFERROR(ROUND(('DCF Model'!C45/(1+$B20)^('DCF Model'!C19+0)+'DCF Model'!D45/(1+$B20)^('DCF Model'!C19+1)+'DCF Model'!E45/(1+$B20)^('DCF Model'!C19+2)+'DCF Model'!F45/(1+$B20)^('DCF Model'!C19+3)+'DCF Model'!G45/(1+$B20)^('DCF Model'!C19+4)+('DCF Model'!G39+'DCF Model'!G42)*E$17/(1+$B20)^('DCF Model'!C19+4)-'DCF Model'!C16)*1000000/'DCF Model'!C15,0),"") -> 2027 | F20: =IFERROR(ROUND(('DCF Model'!C45/(1+$B20)^('DCF Model'!C19+0)+'DCF Model'!D45/(1+$B20)^('DCF Model'!C19+1)+'DCF Model'!E45/(1+$B20)^('DCF Model'!C19+2)+'DCF Model'!F45/(1+$B20)^('DCF Model'!C19+3)+'DCF Model'!G45/(1+$B20)^('DCF Model'!C19+4)+('DCF Model'!G39+'DCF Model'!G42)*F$17/(1+$B20)^('DCF Model'!C19+4)-'DCF Model'!C16)*1000000/'DCF Model'!C15,0),"") -> 2328 | G20: =IFERROR(ROUND(('DCF Model'!C45/(1+$B20)^('DCF Model'!C19+0)+'DCF Model'!D45/(1+$B20)^('DCF Model'!C19+1)+'DCF Model'!E45/(1+$B20)^('DCF Model'!C19+2)+'DCF Model'!F45/(1+$B20)^('DCF Model'!C19+3)+'DCF Model'!G45/(1+$B20)^('DCF Model'!C19+4)+('DCF Model'!G39+'DCF Model'!G42)*G$17/(1+$B20)^('DCF Model'!C19+4)-'DCF Model'!C16)*1000000/'DCF Model'!C15,0),"") -> 2629 | H20: =IFERROR(ROUND(('DCF Model'!C45/(1+$B20)^('DCF Model'!C19+0)+'DCF Model'!D45/(1+$B20)^('DCF Model'!C19+1)+'DCF Model'!E45/(1+$B20)^('DCF Model'!C19+2)+'DCF Model'!F45/(1+$B20)^('DCF Model'!C19+3)+'DCF Model'!G45/(1+$B20)^('DCF Model'!C19+4)+('DCF Model'!G39+'DCF Model'!G42)*H$17/(1+$B20)^('DCF Model'!C19+4)-'DCF Model'!C16)*1000000/'DCF Model'!C15,0),"") -> 2929 | I20: =IFERROR(ROUND(('DCF Model'!C45/(1+$B20)^('DCF Model'!C19+0)+'DCF Model'!D45/(1+$B20)^('DCF Model'!C19+1)+'DCF Model'!E45/(1+$B20)^('DCF Model'!C19+2)+'DCF Model'!F45/(1+$B20)^('DCF Model'!C19+3)+'DCF Model'!G45/(1+$B20)^('DCF Model'!C19+4)+('DCF Model'!G39+'DCF Model'!G42)*I$17/(1+$B20)^('DCF Model'!C19+4)-'DCF Model'!C16)*1000000/'DCF Model'!C15,0),"") -> 3230
B21: =$C$3 -> 0.087966594 | C21: =IFERROR(ROUND(('DCF Model'!C45/(1+$B21)^('DCF Model'!C19+0)+'DCF Model'!D45/(1+$B21)^('DCF Model'!C19+1)+'DCF Model'!E45/(1+$B21)^('DCF Model'!C19+2)+'DCF Model'!F45/(1+$B21)^('DCF Model'!C19+3)+'DCF Model'!G45/(1+$B21)^('DCF Model'!C19+4)+('DCF Model'!G39+'DCF Model'!G42)*C$17/(1+$B21)^('DCF Model'!C19+4)-'DCF Model'!C16)*1000000/'DCF Model'!C15,0),"") -> 1388 | D21: =IFERROR(ROUND(('DCF Model'!C45/(1+$B21)^('DCF Model'!C19+0)+'DCF Model'!D45/(1+$B21)^('DCF Model'!C19+1)+'DCF Model'!E45/(1+$B21)^('DCF Model'!C19+2)+'DCF Model'!F45/(1+$B21)^('DCF Model'!C19+3)+'DCF Model'!G45/(1+$B21)^('DCF Model'!C19+4)+('DCF Model'!G39+'DCF Model'!G42)*D$17/(1+$B21)^('DCF Model'!C19+4)-'DCF Model'!C16)*1000000/'DCF Model'!C15,0),"") -> 1682 | E21: =IFERROR(ROUND(('DCF Model'!C45/(1+$B21)^('DCF Model'!C19+0)+'DCF Model'!D45/(1+$B21)^('DCF Model'!C19+1)+'DCF Model'!E45/(1+$B21)^('DCF Model'!C19+2)+'DCF Model'!F45/(1+$B21)^('DCF Model'!C19+3)+'DCF Model'!G45/(1+$B21)^('DCF Model'!C19+4)+('DCF Model'!G39+'DCF Model'!G42)*E$17/(1+$B21)^('DCF Model'!C19+4)-'DCF Model'!C16)*1000000/'DCF Model'!C15,0),"") -> 1976 | F21: =IFERROR(ROUND(('DCF Model'!C45/(1+$B21)^('DCF Model'!C19+0)+'DCF Model'!D45/(1+$B21)^('DCF Model'!C19+1)+'DCF Model'!E45/(1+$B21)^('DCF Model'!C19+2)+'DCF Model'!F45/(1+$B21)^('DCF Model'!C19+3)+'DCF Model'!G45/(1+$B21)^('DCF Model'!C19+4)+('DCF Model'!G39+'DCF Model'!G42)*F$17/(1+$B21)^('DCF Model'!C19+4)-'DCF Model'!C16)*1000000/'DCF Model'!C15,0),"") -> 2269 | G21: =IFERROR(ROUND(('DCF Model'!C45/(1+$B21)^('DCF Model'!C19+0)+'DCF Model'!D45/(1+$B21)^('DCF Model'!C19+1)+'DCF Model'!E45/(1+$B21)^('DCF Model'!C19+2)+'DCF Model'!F45/(1+$B21)^('DCF Model'!C19+3)+'DCF Model'!G45/(1+$B21)^('DCF Model'!C19+4)+('DCF Model'!G39+'DCF Model'!G42)*G$17/(1+$B21)^('DCF Model'!C19+4)-'DCF Model'!C16)*1000000/'DCF Model'!C15,0),"") -> 2563 | H21: =IFERROR(ROUND(('DCF Model'!C45/(1+$B21)^('DCF Model'!C19+0)+'DCF Model'!D45/(1+$B21)^('DCF Model'!C19+1)+'DCF Model'!E45/(1+$B21)^('DCF Model'!C19+2)+'DCF Model'!F45/(1+$B21)^('DCF Model'!C19+3)+'DCF Model'!G45/(1+$B21)^('DCF Model'!C19+4)+('DCF Model'!G39+'DCF Model'!G42)*H$17/(1+$B21)^('DCF Model'!C19+4)-'DCF Model'!C16)*1000000/'DCF Model'!C15,0),"") -> 2857 | I21: =IFERROR(ROUND(('DCF Model'!C45/(1+$B21)^('DCF Model'!C19+0)+'DCF Model'!D45/(1+$B21)^('DCF Model'!C19+1)+'DCF Model'!E45/(1+$B21)^('DCF Model'!C19+2)+'DCF Model'!F45/(1+$B21)^('DCF Model'!C19+3)+'DCF Model'!G45/(1+$B21)^('DCF Model'!C19+4)+('DCF Model'!G39+'DCF Model'!G42)*I$17/(1+$B21)^('DCF Model'!C19+4)-'DCF Model'!C16)*1000000/'DCF Model'!C15,0),"") -> 3151
B22: =$C$3+0.005 -> 0.092966594 | C22: =IFERROR(ROUND(('DCF Model'!C45/(1+$B22)^('DCF Model'!C19+0)+'DCF Model'!D45/(1+$B22)^('DCF Model'!C19+1)+'DCF Model'!E45/(1+$B22)^('DCF Model'!C19+2)+'DCF Model'!F45/(1+$B22)^('DCF Model'!C19+3)+'DCF Model'!G45/(1+$B22)^('DCF Model'!C19+4)+('DCF Model'!G39+'DCF Model'!G42)*C$17/(1+$B22)^('DCF Model'!C19+4)-'DCF Model'!C16)*1000000/'DCF Model'!C15,0),"") -> 1351 | D22: =IFERROR(ROUND(('DCF Model'!C45/(1+$B22)^('DCF Model'!C19+0)+'DCF Model'!D45/(1+$B22)^('DCF Model'!C19+1)+'DCF Model'!E45/(1+$B22)^('DCF Model'!C19+2)+'DCF Model'!F45/(1+$B22)^('DCF Model'!C19+3)+'DCF Model'!G45/(1+$B22)^('DCF Model'!C19+4)+('DCF Model'!G39+'DCF Model'!G42)*D$17/(1+$B22)^('DCF Model'!C19+4)-'DCF Model'!C16)*1000000/'DCF Model'!C15,0),"") -> 1638 | E22: =IFERROR(ROUND(('DCF Model'!C45/(1+$B22)^('DCF Model'!C19+0)+'DCF Model'!D45/(1+$B22)^('DCF Model'!C19+1)+'DCF Model'!E45/(1+$B22)^('DCF Model'!C19+2)+'DCF Model'!F45/(1+$B22)^('DCF Model'!C19+3)+'DCF Model'!G45/(1+$B22)^('DCF Model'!C19+4)+('DCF Model'!G39+'DCF Model'!G42)*E$17/(1+$B22)^('DCF Model'!C19+4)-'DCF Model'!C16)*1000000/'DCF Model'!C15,0),"") -> 1925 | F22: =IFERROR(ROUND(('DCF Model'!C45/(1+$B22)^('DCF Model'!C19+0)+'DCF Model'!D45/(1+$B22)^('DCF Model'!C19+1)+'DCF Model'!E45/(1+$B22)^('DCF Model'!C19+2)+'DCF Model'!F45/(1+$B22)^('DCF Model'!C19+3)+'DCF Model'!G45/(1+$B22)^('DCF Model'!C19+4)+('DCF Model'!G39+'DCF Model'!G42)*F$17/(1+$B22)^('DCF Model'!C19+4)-'DCF Model'!C16)*1000000/'DCF Model'!C15,0),"") -> 2213 | G22: =IFERROR(ROUND(('DCF Model'!C45/(1+$B22)^('DCF Model'!C19+0)+'DCF Model'!D45/(1+$B22)^('DCF Model'!C19+1)+'DCF Model'!E45/(1+$B22)^('DCF Model'!C19+2)+'DCF Model'!F45/(1+$B22)^('DCF Model'!C19+3)+'DCF Model'!G45/(1+$B22)^('DCF Model'!C19+4)+('DCF Model'!G39+'DCF Model'!G42)*G$17/(1+$B22)^('DCF Model'!C19+4)-'DCF Model'!C16)*1000000/'DCF Model'!C15,0),"") -> 2500 | H22: =IFERROR(ROUND(('DCF Model'!C45/(1+$B22)^('DCF Model'!C19+0)+'DCF Model'!D45/(1+$B22)^('DCF Model'!C19+1)+'DCF Model'!E45/(1+$B22)^('DCF Model'!C19+2)+'DCF Model'!F45/(1+$B22)^('DCF Model'!C19+3)+'DCF Model'!G45/(1+$B22)^('DCF Model'!C19+4)+('DCF Model'!G39+'DCF Model'!G42)*H$17/(1+$B22)^('DCF Model'!C19+4)-'DCF Model'!C16)*1000000/'DCF Model'!C15,0),"") -> 2787 | I22: =IFERROR(ROUND(('DCF Model'!C45/(1+$B22)^('DCF Model'!C19+0)+'DCF Model'!D45/(1+$B22)^('DCF Model'!C19+1)+'DCF Model'!E45/(1+$B22)^('DCF Model'!C19+2)+'DCF Model'!F45/(1+$B22)^('DCF Model'!C19+3)+'DCF Model'!G45/(1+$B22)^('DCF Model'!C19+4)+('DCF Model'!G39+'DCF Model'!G42)*I$17/(1+$B22)^('DCF Model'!C19+4)-'DCF Model'!C16)*1000000/'DCF Model'!C15,0),"") -> 3074
B23: =$C$3+0.01 -> 0.097966594 | C23: =IFERROR(ROUND(('DCF Model'!C45/(1+$B23)^('DCF Model'!C19+0)+'DCF Model'!D45/(1+$B23)^('DCF Model'!C19+1)+'DCF Model'!E45/(1+$B23)^('DCF Model'!C19+2)+'DCF Model'!F45/(1+$B23)^('DCF Model'!C19+3)+'DCF Model'!G45/(1+$B23)^('DCF Model'!C19+4)+('DCF Model'!G39+'DCF Model'!G42)*C$17/(1+$B23)^('DCF Model'!C19+4)-'DCF Model'!C16)*1000000/'DCF Model'!C15,0),"") -> 1315 | D23: =IFERROR(ROUND(('DCF Model'!C45/(1+$B23)^('DCF Model'!C19+0)+'DCF Model'!D45/(1+$B23)^('DCF Model'!C19+1)+'DCF Model'!E45/(1+$B23)^('DCF Model'!C19+2)+'DCF Model'!F45/(1+$B23)^('DCF Model'!C19+3)+'DCF Model'!G45/(1+$B23)^('DCF Model'!C19+4)+('DCF Model'!G39+'DCF Model'!G42)*D$17/(1+$B23)^('DCF Model'!C19+4)-'DCF Model'!C16)*1000000/'DCF Model'!C15,0),"") -> 1596 | E23: =IFERROR(ROUND(('DCF Model'!C45/(1+$B23)^('DCF Model'!C19+0)+'DCF Model'!D45/(1+$B23)^('DCF Model'!C19+1)+'DCF Model'!E45/(1+$B23)^('DCF Model'!C19+2)+'DCF Model'!F45/(1+$B23)^('DCF Model'!C19+3)+'DCF Model'!G45/(1+$B23)^('DCF Model'!C19+4)+('DCF Model'!G39+'DCF Model'!G42)*E$17/(1+$B23)^('DCF Model'!C19+4)-'DCF Model'!C16)*1000000/'DCF Model'!C15,0),"") -> 1877 | F23: =IFERROR(ROUND(('DCF Model'!C45/(1+$B23)^('DCF Model'!C19+0)+'DCF Model'!D45/(1+$B23)^('DCF Model'!C19+1)+'DCF Model'!E45/(1+$B23)^('DCF Model'!C19+2)+'DCF Model'!F45/(1+$B23)^('DCF Model'!C19+3)+'DCF Model'!G45/(1+$B23)^('DCF Model'!C19+4)+('DCF Model'!G39+'DCF Model'!G42)*F$17/(1+$B23)^('DCF Model'!C19+4)-'DCF Model'!C16)*1000000/'DCF Model'!C15,0),"") -> 2157 | G23: =IFERROR(ROUND(('DCF Model'!C45/(1+$B23)^('DCF Model'!C19+0)+'DCF Model'!D45/(1+$B23)^('DCF Model'!C19+1)+'DCF Model'!E45/(1+$B23)^('DCF Model'!C19+2)+'DCF Model'!F45/(1+$B23)^('DCF Model'!C19+3)+'DCF Model'!G45/(1+$B23)^('DCF Model'!C19+4)+('DCF Model'!G39+'DCF Model'!G42)*G$17/(1+$B23)^('DCF Model'!C19+4)-'DCF Model'!C16)*1000000/'DCF Model'!C15,0),"") -> 2438 | H23: =IFERROR(ROUND(('DCF Model'!C45/(1+$B23)^('DCF Model'!C19+0)+'DCF Model'!D45/(1+$B23)^('DCF Model'!C19+1)+'DCF Model'!E45/(1+$B23)^('DCF Model'!C19+2)+'DCF Model'!F45/(1+$B23)^('DCF Model'!C19+3)+'DCF Model'!G45/(1+$B23)^('DCF Model'!C19+4)+('DCF Model'!G39+'DCF Model'!G42)*H$17/(1+$B23)^('DCF Model'!C19+4)-'DCF Model'!C16)*1000000/'DCF Model'!C15,0),"") -> 2719 | I23: =IFERROR(ROUND(('DCF Model'!C45/(1+$B23)^('DCF Model'!C19+0)+'DCF Model'!D45/(1+$B23)^('DCF Model'!C19+1)+'DCF Model'!E45/(1+$B23)^('DCF Model'!C19+2)+'DCF Model'!F45/(1+$B23)^('DCF Model'!C19+3)+'DCF Model'!G45/(1+$B23)^('DCF Model'!C19+4)+('DCF Model'!G39+'DCF Model'!G42)*I$17/(1+$B23)^('DCF Model'!C19+4)-'DCF Model'!C16)*1000000/'DCF Model'!C15,0),"") -> 3000
B24: =$C$3+0.015 -> 0.10296659 | C24: =IFERROR(ROUND(('DCF Model'!C45/(1+$B24)^('DCF Model'!C19+0)+'DCF Model'!D45/(1+$B24)^('DCF Model'!C19+1)+'DCF Model'!E45/(1+$B24)^('DCF Model'!C19+2)+'DCF Model'!F45/(1+$B24)^('DCF Model'!C19+3)+'DCF Model'!G45/(1+$B24)^('DCF Model'!C19+4)+('DCF Model'!G39+'DCF Model'!G42)*C$17/(1+$B24)^('DCF Model'!C19+4)-'DCF Model'!C16)*1000000/'DCF Model'!C15,0),"") -> 1280 | D24: =IFERROR(ROUND(('DCF Model'!C45/(1+$B24)^('DCF Model'!C19+0)+'DCF Model'!D45/(1+$B24)^('DCF Model'!C19+1)+'DCF Model'!E45/(1+$B24)^('DCF Model'!C19+2)+'DCF Model'!F45/(1+$B24)^('DCF Model'!C19+3)+'DCF Model'!G45/(1+$B24)^('DCF Model'!C19+4)+('DCF Model'!G39+'DCF Model'!G42)*D$17/(1+$B24)^('DCF Model'!C19+4)-'DCF Model'!C16)*1000000/'DCF Model'!C15,0),"") -> 1555 | E24: =IFERROR(ROUND(('DCF Model'!C45/(1+$B24)^('DCF Model'!C19+0)+'DCF Model'!D45/(1+$B24)^('DCF Model'!C19+1)+'DCF Model'!E45/(1+$B24)^('DCF Model'!C19+2)+'DCF Model'!F45/(1+$B24)^('DCF Model'!C19+3)+'DCF Model'!G45/(1+$B24)^('DCF Model'!C19+4)+('DCF Model'!G39+'DCF Model'!G42)*E$17/(1+$B24)^('DCF Model'!C19+4)-'DCF Model'!C16)*1000000/'DCF Model'!C15,0),"") -> 1829 | F24: =IFERROR(ROUND(('DCF Model'!C45/(1+$B24)^('DCF Model'!C19+0)+'DCF Model'!D45/(1+$B24)^('DCF Model'!C19+1)+'DCF Model'!E45/(1+$B24)^('DCF Model'!C19+2)+'DCF Model'!F45/(1+$B24)^('DCF Model'!C19+3)+'DCF Model'!G45/(1+$B24)^('DCF Model'!C19+4)+('DCF Model'!G39+'DCF Model'!G42)*F$17/(1+$B24)^('DCF Model'!C19+4)-'DCF Model'!C16)*1000000/'DCF Model'!C15,0),"") -> 2104 | G24: =IFERROR(ROUND(('DCF Model'!C45/(1+$B24)^('DCF Model'!C19+0)+'DCF Model'!D45/(1+$B24)^('DCF Model'!C19+1)+'DCF Model'!E45/(1+$B24)^('DCF Model'!C19+2)+'DCF Model'!F45/(1+$B24)^('DCF Model'!C19+3)+'DCF Model'!G45/(1+$B24)^('DCF Model'!C19+4)+('DCF Model'!G39+'DCF Model'!G42)*G$17/(1+$B24)^('DCF Model'!C19+4)-'DCF Model'!C16)*1000000/'DCF Model'!C15,0),"") -> 2378 | H24: =IFERROR(ROUND(('DCF Model'!C45/(1+$B24)^('DCF Model'!C19+0)+'DCF Model'!D45/(1+$B24)^('DCF Model'!C19+1)+'DCF Model'!E45/(1+$B24)^('DCF Model'!C19+2)+'DCF Model'!F45/(1+$B24)^('DCF Model'!C19+3)+'DCF Model'!G45/(1+$B24)^('DCF Model'!C19+4)+('DCF Model'!G39+'DCF Model'!G42)*H$17/(1+$B24)^('DCF Model'!C19+4)-'DCF Model'!C16)*1000000/'DCF Model'!C15,0),"") -> 2653 | I24: =IFERROR(ROUND(('DCF Model'!C45/(1+$B24)^('DCF Model'!C19+0)+'DCF Model'!D45/(1+$B24)^('DCF Model'!C19+1)+'DCF Model'!E45/(1+$B24)^('DCF Model'!C19+2)+'DCF Model'!F45/(1+$B24)^('DCF Model'!C19+3)+'DCF Model'!G45/(1+$B24)^('DCF Model'!C19+4)+('DCF Model'!G39+'DCF Model'!G42)*I$17/(1+$B24)^('DCF Model'!C19+4)-'DCF Model'!C16)*1000000/'DCF Model'!C15,0),"") -> 2927
B26: All values dynamically linked to DCF Model. Headers auto-center on current WACC / Terminal g / Exit Multiple.

Sheet Adjustments Log
B2: Adjustments Log - Ricoh Company, Ltd.
B4: 日付 | C4: セル | D4: 変更内容 | E4: 理由 | F4: 元の値 | G4: 状態
B5: 2026-09-06 | C5: - | D5: Generated by pipeline on 2026-09-06 21:22, template rev b2810d8 | E5: 初期生成（手修正なし） | F5: - | G5: generated
B6: 2026-09-06 | C6: DCF Model!C8 | D6: Beta = 1.030（採用値） | E6: 実測β(raw) = 1.044 → Blume調整 0.67×raw + 0.33×1.00 = 1.030 → 採用 1.030。クランプ域 [0.3, 2.0] の内側。置換なし。回帰βは平均回帰するため Blume 調整を既定とする（2026-09-05 バッチで85件中57件が旧下限 0.60 に張り付き、両裾の歪みが実証された）。 | F6: 実測 1.044 | G6: 確定
B12: Pipeline Metadata (do not edit — read by scripts/validate_output.py)
B13: key | C13: value
B14: auto_log_entries | C14: 1
B15: beta_adopted_c8 | C15: 1.0296
B16: beta_basis | C16: Blume: 0.67 x 1.044 + 0.33 x 1.00 = 1.030
B17: beta_blume_adjusted | C17: 1.0296
B18: beta_clamped | C18: no
B19: beta_raw | C19: 1.0442
B20: capex_pct_basis | C20: explicit_override
B21: capex_pct_c5 | C21: 0.0518
B22: capex_pct_hist3yr | C22: n/a
B23: company_name | C23: Ricoh Company, Ltd.
B24: comps_asof | C24: 2026-09-06
... B60: ticker | C60: 7752.T
