Workbook

Sheet Executive Summary
B1: DISCLAIMER: This is a sample analysis for demonstration purposes only. It does not constitute investment advice.
B3: 任天堂 (7974.T)
B4: Equity Research Report
B6: Company | C6: 任天堂
B7: Ticker | C7: 7974.T (TSE Prime)
B8: Sector | C8: その他製品
B9: Current Price | C9: 8839
B10: Target Price (DCF Mid) | C10: =IF(COUNT(C16:C17)=0,"N/A",ROUND(AVERAGE(C16:C17),0)) -> 7917
B11: Recommendation | C11: =IF(NOT(ISNUMBER(C12)),"N/A",IF(C12>0.15,"BUY",IF(C12>0.05,"HOLD","SELL"))) -> SELL
B12: Upside / Downside | C12: =IF(ISNUMBER(C10),(C10-C9)/C9,"N/A") -> -0.10431044
B14: Valuation Summary
B15: Methodology | C15: Implied Value (JPY) | D15: vs Current Price
B16: DCF - Perpetuity Growth | C16: =IF('DCF Model'!C53<'DCF Model'!C16,"INVALID (EV < net debt)",'DCF Model'!C55) -> 6669 | D16: =IF(ISNUMBER(C16),(C16-C9)/C9,"N/A") -> -0.24550288
B17: DCF - Exit Multiple | C17: =IF('DCF Model'!C62<'DCF Model'!C16,"INVALID (EV < net debt)",'DCF Model'!C64) -> 9164 | D17: =IF(ISNUMBER(C17),(C17-C9)/C9,"N/A") -> 0.036768865
B18: Comps - EV/EBITDA Median [参考・Target不算入] | C18: ='Comps Analysis'!C27 -> 5848 | D18: =IF(ISNUMBER(C18),(C18-C9)/C9,"N/A") -> -0.3383867
B19: Comps - PER Median [参考・Target不算入] | C19: ='Comps Analysis'!C28 -> 11346 | D19: =IF(ISNUMBER(C19),(C19-C9)/C9,"N/A") -> 0.28362937
B20: Note: Target Mid は DCF 2法（PGM / Exit）の平均のみ。Comps 2法は [参考] で Target 不算入（EV<ネットデットで株式価値が負になる手法は INVALID として平均から除外）
B21: DCF Valuation Range (PGM - Exit) | C21: =IF(COUNT(C16:C17)=0,"N/A",MIN(C16:C17)&" - "&MAX(C16:C17)) -> 6669 - 9164
B23: Key Investment Thesis
B24: ="The Switch 2 launch year carries hardware-heavy economics, which is why the operating margin sits at the bottom of its four-year range; as the software attach rate builds, the mix normalises and the "&TEXT('Comps Analysis'!L5,"0.0""x""")&" the market pays looks different against mid-cycle earnings." -> The Switch 2 launch year carries hardware-heavy economics, which is why the operating margin sits at the bottom of its four-year range; as the software attach rate builds, the mix normalises and the 24.0x the market pays looks different against mid-cycle earnings.
B25: ="A large net cash position means enterprise value is well below market capitalisation, so the "&TEXT('DCF Model'!C26,"0.00%")&" discount rate applies to a business with no financial leverage and the equity absorbs none of the balance-sheet risk." -> A large net cash position means enterprise value is well below market capitalisation, so the 10.47% discount rate applies to a business with no financial leverage and the equity absorbs none of the balance-sheet risk.
B26: ="At "&TEXT(C9,"#,##0")&" the shares are held at a clear premium to the listed Japanese game peer group on "&TEXT('Comps Analysis'!M5,"0.00""x""")&" book; the base case mid-cycle normalisation supports "&TEXT(C10,"#,##0")&", or "&TEXT(C12,"+0.0%;-0.0%")&" from here." -> At 8,839 the shares are held at a clear premium to the listed Japanese game peer group on 3.45x book; the base case mid-cycle normalisation supports 7,917, or -10.4% from here.
B28: Key Risks
B29: ="Console cycles are hit-driven and the projected margin recovery depends on a software line-up that is not yet on the market, so a soft attach rate would leave earnings near the launch-year trough rather than the "&TEXT('Comps Analysis'!L5,"0.0""x""")&" implied by "&TEXT(C9,"#,##0")&"." -> Console cycles are hit-driven and the projected margin recovery depends on a software line-up that is not yet on the market, so a soft attach rate would leave earnings near the launch-year trough rather than the 24.0x implied by 8,839.
B30: The hardware bill of materials is dollar-denominated while a large share of revenue is not, so yen weakness or component inflation compresses the very margin recovery the base case assumes.
B31: ="The model discounts a smoothed cycle rather than an actual one: real console transitions produce a revenue cliff between generations, which the "&TEXT('DCF Model'!C26,"0.00%")&" single-path discounting does not represent." -> The model discounts a smoothed cycle rather than an actual one: real console transitions produce a revenue cliff between generations, which the 10.47% single-path discounting does not represent.

Sheet Financial Statements
B2: 任天堂 - Historical Financials (JPY mn)
C4: FY2021 | D4: FY2022 | E4: FY2023 | F4: FY2024 | G4: FY2025 | H4: FY2026
B5: Income Statement
B6: Revenue | C6: 1758910 | D6: 1695344 | E6: 1601677 | F6: 1671865 | G6: 1164922 | H6: 2313051
B7: COGS | C7: 788437 | D7: 749299 | E7: 716237 | F7: 717530 | G7: 454754 | H7: 1404094
B8: Gross Profit | C8: =C6-C7 -> 970473 | D8: =D6-D7 -> 946045 | E8: =E6-E7 -> 885440 | F8: =F6-F7 -> 954335 | G8: =G6-G7 -> 710168 | H8: =H6-H7 -> 908957
B9: Gross Margin | C9: =C8/C6 -> 0.55174682 | D9: =D8/D6 -> 0.55802539 | E9: =E8/E6 -> 0.55282057 | F9: =F8/F6 -> 0.57082061 | G9: =G8/G6 -> 0.60962708 | H9: =H8/H6 -> 0.39296885
B10: SGA | C10: 329838 | D10: 353283 | E10: 381065 | F10: 425393 | G10: 427614 | H10: 548839
B11: Operating Income | C11: 640634 | D11: 592760 | E11: 504375 | F11: 528941 | G11: 282553 | H11: 360117
B12: Net Income | C12: 480376 | D12: 477691 | E12: 432768 | F12: 490602 | G12: 278806 | H12: 424056
B13: Operating Margin | C13: =C11/C6 -> 0.36422216 | D13: =D11/D6 -> 0.34963996 | E13: =E11/E6 -> 0.31490432 | F13: =F11/F6 -> 0.31637782 | G13: =G11/G6 -> 0.242551 | H13: =H11/H6 -> 0.15568917
B14: Net Margin | C14: =C12/C6 -> 0.27311005 | D14: =D12/D6 -> 0.28176641 | E14: =E12/E6 -> 0.2701968 | F14: =F12/F6 -> 0.29344594 | G14: =G12/G6 -> 0.23933448 | H14: =H12/H6 -> 0.18333189
B15: Revenue Growth (YoY) | C15: n/a | D15: =(D6-C6)/C6 -> -0.036139427 | E15: =(E6-D6)/D6 -> -0.055249554 | F15: =(F6-E6)/E6 -> 0.04382157 | G15: =(G6-F6)/F6 -> -0.30322006 | H15: =(H6-G6)/G6 -> 0.98558444
B16: Operating Income Growth (YoY) | C16: n/a | D16: =(D11-C11)/C11 -> -0.074729096 | E16: =(E11-D11)/D11 -> -0.14910756 | F16: =(F11-E11)/E11 -> 0.048705824 | G16: =(G11-F11)/F11 -> -0.46581377 | H16: =(H11-G11)/G11 -> 0.27451133
B18: Cash Flow Statement
B19: Operating Cash Flow | C19: 612106 | D19: 289661 | E19: 322843 | F19: 462097 | G19: 12069 | H19: 289789
B20: Capex
B21: Free Cash Flow
B22: FCF Margin
B23: Capex / Revenue
B25: Balance Sheet Highlights
B26: Cash & Deposits | C26: 932079 | D26: 1022718 | E26: 1194569 | F26: 853432 | G26: 1586275 | H26: 1791802
B27: Total Interest-bearing Debt (short + long)
B28: Net Debt (Cash)
B30: Note: OCF / Cash / Debt coverage OCF 6/6, Cash 6/6, Debt 0/6 — blank cells are years with no year-key match in the source data (verify against 決算短信 or set hist_ocf / hist_cash / hist_debt in overrides).

Sheet DCF Model
B2: DCF Valuation Model - 任天堂
B4: Assumptions
B5: Capex / Revenue | C5: 0.0095
B6: Effective Tax Rate | C6: 0.25
B7: Risk-Free Rate | C7: 0.0297
B8: Beta | C8: 1
B9: Equity Risk Premium | C9: 0.065
B10: Size Premium | C10: 0.01
B11: After-tax Cost of Debt | C11: 0.01
B12: D/E Ratio | C12: 0
B13: Terminal Growth Rate | C13: 0.01
B14: Exit Multiple (EV/EBITDA) | C14: 13.2
B15: Fully Diluted Shares | C15: 1152873205
B16: Net Debt (JPY mn) | C16: -1791802
... B20: LTM Revenue (JPY mn) | C20: 2313051
B22: WACC Calculation
B23: Cost of Equity (Ke) | C23: =C7+C8*C9+C10 -> 0.1047
B24: Weight of Equity | C24: =1/(1+C12) -> 1
B25: Weight of Debt | C25: =C12/(1+C12) -> 0
B26: WACC | C26: =C23*C24+C11*C25 -> 0.1047
B27: Active Scenario | C27: Base | D27: =MATCH(C27,B69:B73,0) -> 1
B28: Projected Free Cash Flow
C29: FY2027(E) | D29: FY2028(E) | E29: FY2029(E) | F29: FY2030(E) | G29: FY2031(E)
B30: Revenue Growth (YoY) | C30: =CHOOSE($D$27,C69,C70,C71,C72,C73) -> 0.12 | D30: =CHOOSE($D$27,D69,D70,D71,D72,D73) -> 0.06 | E30: =CHOOSE($D$27,E69,E70,E71,E72,E73) -> 0.03 | F30: =CHOOSE($D$27,F69,F70,F71,F72,F73) -> 0.02 | G30: =CHOOSE($D$27,G69,G70,G71,G72,G73) -> 0.02
B31: COGS % of Revenue | C31: =CHOOSE($D$27,C76,C77,C78,C79,C80) -> 0.56 | D31: =CHOOSE($D$27,D76,D77,D78,D79,D80) -> 0.52 | E31: =CHOOSE($D$27,E76,E77,E78,E79,E80) -> 0.49 | F31: =CHOOSE($D$27,F76,F77,F78,F79,F80) -> 0.48 | G31: =CHOOSE($D$27,G76,G77,G78,G79,G80) -> 0.481
B32: SGA % of Revenue | C32: =CHOOSE($D$27,C83,C84,C85,C86,C87) -> 0.24 | D32: =CHOOSE($D$27,D83,D84,D85,D86,D87) -> 0.24 | E32: =CHOOSE($D$27,E83,E84,E85,E86,E87) -> 0.24 | F32: =CHOOSE($D$27,F83,F84,F85,F86,F87) -> 0.24 | G32: =CHOOSE($D$27,G83,G84,G85,G86,G87) -> 0.24
B33: Revenue | C33: =C17*(1+C30) -> 2590617.1 | D33: =C33*(1+D30) -> 2746054.1 | E33: =D33*(1+E30) -> 2828435.8 | F33: =E33*(1+F30) -> 2885004.5 | G33: =F33*(1+G30) -> 2942704.6
B34: COGS | C34: =C33*C31 -> 1450745.6 | D34: =D33*D31 -> 1427948.2 | E34: =E33*E31 -> 1385933.5 | F34: =F33*F31 -> 1384802.2 | G34: =G33*G31 -> 1415440.9
B35: Gross Profit | C35: =C33-C34 -> 1139871.5 | D35: =D33-D34 -> 1318106 | E35: =E33-E34 -> 1442502.2 | F35: =F33-F34 -> 1500202.3 | G35: =G33-G34 -> 1527263.7
B36: Gross Margin | C36: =C35/C33 -> 0.44 | D36: =D35/D33 -> 0.48 | E36: =E35/E33 -> 0.51 | F36: =F35/F33 -> 0.52 | G36: =G35/G33 -> 0.519
B37: SGA Expense | C37: =C33*C32 -> 621748.11 | D37: =D33*D32 -> 659053 | E37: =E33*E32 -> 678824.59 | F37: =F33*F32 -> 692401.08 | G37: =G33*G32 -> 706249.1
B38: Implied Operating Margin | C38: =(C35-C37)/C33 -> 0.2 | D38: =(D35-D37)/D33 -> 0.24 | E38: =(E35-E37)/E33 -> 0.27 | F38: =(F35-F37)/F33 -> 0.28 | G38: =(G35-G37)/G33 -> 0.279
B39: Operating Income (EBIT) | C39: =C35-C37 -> 518123.42 | D39: =D35-D37 -> 659053 | E39: =E35-E37 -> 763677.66 | F39: =F35-F37 -> 807801.26 | G39: =G35-G37 -> 821014.58
B40: Less: Tax | C40: =MAX(0,C39*C6) -> 129530.86 | D40: =MAX(0,D39*C6) -> 164763.25 | E40: =MAX(0,E39*C6) -> 190919.41 | F40: =MAX(0,F39*C6) -> 201950.31 | G40: =MAX(0,G39*C6) -> 205253.64
B41: NOPAT | C41: =C39-C40 -> 388592.57 | D41: =D39-D40 -> 494289.75 | E41: =E39-E40 -> 572758.24 | F41: =F39-F40 -> 605850.94 | G41: =G39-G40 -> 615760.93
B42: Plus: D&A | C42: =C33*C18 -> 23315.554 | D42: =D33*C18 -> 24714.487 | E42: =E33*C18 -> 25455.922 | F42: =F33*C18 -> 25965.04 | G42: =G33*C18 -> 26484.341
B43: Less: Capex | C43: =C33*C5 -> 24610.863 | D43: =D33*C5 -> 26087.514 | E43: =E33*C5 -> 26870.14 | F43: =F33*C5 -> 27407.543 | G43: =G33*C5 -> 27955.693
B44: Change in NWC | C44: ='NWC Schedule'!D19 -> -28758.97 | D44: ='NWC Schedule'!E19 -> 5184.0733 | E44: ='NWC Schedule'!F19 -> -2746.8065 | F44: ='NWC Schedule'!G19 -> 3201.9443 | G44: ='NWC Schedule'!H19 -> 9101.9125
B45: Unlevered Free Cash Flow | C45: =C41+C42-C43-C44 -> 416056.23 | D45: =D41+D42-D43-D44 -> 487732.65 | E45: =E41+E42-E43-E44 -> 574090.83 | F45: =F41+F42-F43-F44 -> 601206.5 | G45: =G41+G42-G43-G44 -> 605187.67
B46: Discount Factor | C46: =1/(1+C26)^(C19+0) -> 0.90522314 | D46: =1/(1+C26)^(C19+1) -> 0.81942893 | E46: =1/(1+C26)^(C19+2) -> 0.74176603 | F46: =1/(1+C26)^(C19+3) -> 0.67146377 | G46: =1/(1+C26)^(C19+4) -> 0.60782454
B47: PV of FCF | C47: =C45*C46 -> 376623.73 | D47: =D45*D46 -> 399662.24 | E47: =E45*E46 -> 425841.08 | F47: =F45*F46 -> 403688.38 | G47: =G45*G46 -> 367847.92
B49: Valuation - Perpetuity Growth Method
B50: Sum of PV of FCFs | C50: =SUM(C47:G47) -> 1973663.3
B51: Terminal Value (PGM) | C51: =G45*(1+C13)/(C26-C13) -> 6454483
B52: PV of Terminal Value | C52: =C51*G46 -> 3923193.2
B53: Enterprise Value | C53: =C50+C52 -> 5896856.5
B54: Equity Value | C54: =C53-C16 -> 7688658.5
B55: Implied Share Price (PGM) | C55: =ROUND(C54*1000000/C15,0) -> 6669
B57: Valuation - Exit Multiple Method
B58: Sum of PV of FCFs | C58: =C50 -> 1973663.3
B59: Year 5 EBITDA | C59: =G39+G42 -> 847498.92
B60: Terminal Value (Exit Multiple) | C60: =C59*C14 -> 11186986
B61: PV of Terminal Value | C61: =C60*G46 -> 6799724.4
B62: Enterprise Value | C62: =C58+C61 -> 8773387.8
B63: Equity Value | C63: =C62-C16 -> 10565190
B64: Implied Share Price (Exit Multiple) | C64: =ROUND(C63*1000000/C15,0) -> 9164
B66: Scenario Input Matrix
C67: Year 1 | D67: Year 2 | E67: Year 3 | F67: Year 4 | G67: Year 5
B68: Revenue Growth (YoY)
B69: Base | C69: 0.12 | D69: 0.06 | E69: 0.03 | F69: 0.02 | G69: 0.02
B70: Upside | C70: 0.16 | D70: 0.09 | E70: 0.05 | F70: 0.03 | G70: 0.03
B71: Management | C71: 0.12 | D71: 0.06 | E71: 0.03 | F71: 0.02 | G71: 0.02
B72: Downside 1 | C72: 0.05 | D72: 0.02 | E72: 0 | F72: 0 | G72: 0
B73: Downside 2 | C73: -0.15 | D73: -0.05 | E73: 0 | F73: 0.01 | G73: 0.02
B75: COGS % of Revenue
B76: Base | C76: 0.56 | D76: 0.52 | E76: 0.49 | F76: 0.48 | G76: 0.481
B77: Upside | C77: 0.545 | D77: 0.495 | E77: 0.465 | F77: 0.45 | G77: 0.45
B78: Management | C78: 0.56 | D78: 0.52 | E78: 0.49 | F78: 0.48 | G78: 0.481
B79: Downside 1 | C79: 0.58 | D79: 0.56 | E79: 0.54 | F79: 0.53 | G79: 0.529
B80: Downside 2 | C80: 0.64 | D80: 0.65 | E80: 0.64 | F80: 0.63 | G80: 0.62
B82: SGA % of Revenue
B83: Base | C83: 0.24 | D83: 0.24 | E83: 0.24 | F83: 0.24 | G83: 0.24
B84: Upside | C84: 0.235 | D84: 0.235 | E84: 0.235 | F84: 0.235 | G84: 0.235
B85: Management | C85: 0.24 | D85: 0.24 | E85: 0.24 | F85: 0.24 | G85: 0.24
B86: Downside 1 | C86: 0.25 | D86: 0.25 | E86: 0.25 | F86: 0.25 | G86: 0.25
B87: Downside 2 | C87: 0.27 | D87: 0.27 | E87: 0.27 | F87: 0.27 | G87: 0.27

Sheet Reverse DCF
B2: Reverse DCF - 任天堂 (7974.T)
B3: What is the current share price already assuming? Every value below is a live formula off the other sheets.
B5: Block 0: Market-implied enterprise value (live)
B6: Current Share Price (JPY) | C6: ='Executive Summary'!C9 -> 8839
B7: Fully Diluted Shares | C7: ='DCF Model'!C15 -> 1152873205
B8: Market Capitalisation (JPY mn) | C8: =C6*C7/1000000 -> 10190246
B9: Net Debt (JPY mn) | C9: ='DCF Model'!C16 -> -1791802
B10: Enterprise Value (JPY mn) | C10: =C8+C9 -> 8398444.3
B11: WACC (w) | C11: ='DCF Model'!C26 -> 0.1047
B12: Terminal Growth (g) | C12: ='DCF Model'!C13 -> 0.01
B13: Effective Tax Rate (t) | C13: ='DCF Model'!C6 -> 0.25
B14: Starting Operating Profit OP0 (FY2026 actual) | C14: 360117
B15: Cycle-peak Operating Profit (FY2021 actual) | C15: 640634
B16: Terminal-year Revenue, active scenario (JPY mn) | C16: ='DCF Model'!G33 -> 2942704.6
B17: Base-case DCF Enterprise Value, PGM (JPY mn) | C17: ='DCF Model'!C53 -> 5896856.5
B18: Cycle-peak Operating Margin (FY2021 actual) | C18: 0.36422216
B19: Gap: market EV less base-case DCF EV (JPY mn) | C19: =C10-C17 -> 2501587.7
B20: Gap per share (JPY) - the part of the price the base case does not explain | C20: =IFERROR(ROUND(C19*1000000/C7,0),"N/A") -> 2170
B22: Block A: Required steady-state operating profit, reached IMMEDIATELY (no ramp)
B23: The lowest bar the price can clear: today's EV read as a perpetuity of one steady-state profit, capex = D&A, no NWC build.
B24: Required steady-state NOPAT (JPY mn) | C24: =C10*(C11-C12) -> 795332.67
B25: Required steady-state Operating Profit (JPY mn) | C25: =IFERROR(C24/(1-C13),"N/A") -> 1060443.6
B26: ... as a multiple of the FY2021 peak | C26: =IFERROR(C25/C15,"N/A") -> 1.6553033
B27: ... as a multiple of FY2026 actual | C27: =IFERROR(C25/C14,"N/A") -> 2.9447195
B28: ... implied OPM on terminal-year revenue | C28: =IFERROR(C25/C16,"N/A") -> 0.36036358
B29: ... revenue needed if margins only reach the cycle peak | C29: =IFERROR(C25/C18,"N/A") -> 2911529.5
B32: Block B: Required steady-state operating profit by YEARS-TO-REACH (linear ramp) x WACC
B33: Operating profit ramps linearly from OP0 (C14) to OP* over N years, then grows at g for ever. Column F is the model WACC.
B34: OP* = ( EV/(1-t) - OP0*(A-B) ) / ( B + TVF ). A longer ramp needs a HIGHER steady state, because more years are spent below it.
B36: Years to steady state (N) \ WACC | C36: N | D36: ='DCF Model'!C26-0.02 -> 0.0847 | E36: ='DCF Model'!C26-0.01 -> 0.0947 | F36: ='DCF Model'!C26 -> 0.1047 | G36: ='DCF Model'!C26+0.01 -> 0.1147 | H36: ='DCF Model'!C26+0.02 -> 0.1247
B37: B-1 PV weight on the RAMP from OP0 (A - B)
B38: N = 3 years | C38: 3 | D38: =IFERROR((1-(1+D$36)^(-$C38))/D$36-(1+D$36)/(D$36^2*$C38)*(1-($C38+1)/(1+D$36)^$C38+$C38/(1+D$36)^($C38+1)),"N/A") -> 0.89791767 | E38: =IFERROR((1-(1+E$36)^(-$C38))/E$36-(1+E$36)/(E$36^2*$C38)*(1-($C38+1)/(1+E$36)^$C38+$C38/(1+E$36)^($C38+1)),"N/A") -> 0.8871509 | F38: =IFERROR((1-(1+F$36)^(-$C38))/F$36-(1+F$36)/(F$36^2*$C38)*(1-($C38+1)/(1+F$36)^$C38+$C38/(1+F$36)^($C38+1)),"N/A") -> 0.87662507 | G38: =IFERROR((1-(1+G$36)^(-$C38))/G$36-(1+G$36)/(G$36^2*$C38)*(1-($C38+1)/(1+G$36)^$C38+$C38/(1+G$36)^($C38+1)),"N/A") -> 0.86633245 | H38: =IFERROR((1-(1+H$36)^(-$C38))/H$36-(1+H$36)/(H$36^2*$C38)*(1-($C38+1)/(1+H$36)^$C38+$C38/(1+H$36)^($C38+1)),"N/A") -> 0.85626567
B39: N = 5 years | C39: 5 | D39: =IFERROR((1-(1+D$36)^(-$C39))/D$36-(1+D$36)/(D$36^2*$C39)*(1-($C39+1)/(1+D$36)^$C39+$C39/(1+D$36)^($C39+1)),"N/A") -> 1.705384 | E39: =IFERROR((1-(1+E$36)^(-$C39))/E$36-(1+E$36)/(E$36^2*$C39)*(1-($C39+1)/(1+E$36)^$C39+$C39/(1+E$36)^($C39+1)),"N/A") -> 1.6756542 | F39: =IFERROR((1-(1+F$36)^(-$C39))/F$36-(1+F$36)/(F$36^2*$C39)*(1-($C39+1)/(1+F$36)^$C39+$C39/(1+F$36)^($C39+1)),"N/A") -> 1.646835 | G39: =IFERROR((1-(1+G$36)^(-$C39))/G$36-(1+G$36)/(G$36^2*$C39)*(1-($C39+1)/(1+G$36)^$C39+$C39/(1+G$36)^($C39+1)),"N/A") -> 1.6188883 | H39: =IFERROR((1-(1+H$36)^(-$C39))/H$36-(1+H$36)/(H$36^2*$C39)*(1-($C39+1)/(1+H$36)^$C39+$C39/(1+H$36)^($C39+1)),"N/A") -> 1.5917777
B40: N = 7 years | C40: 7 | D40: =IFERROR((1-(1+D$36)^(-$C40))/D$36-(1+D$36)/(D$36^2*$C40)*(1-($C40+1)/(1+D$36)^$C40+$C40/(1+D$36)^($C40+1)),"N/A") -> 2.432622 | E40: =IFERROR((1-(1+E$36)^(-$C40))/E$36-(1+E$36)/(E$36^2*$C40)*(1-($C40+1)/(1+E$36)^$C40+$C40/(1+E$36)^($C40+1)),"N/A") -> 2.3778135 | F40: =IFERROR((1-(1+F$36)^(-$C40))/F$36-(1+F$36)/(F$36^2*$C40)*(1-($C40+1)/(1+F$36)^$C40+$C40/(1+F$36)^($C40+1)),"N/A") -> 2.325115 | G40: =IFERROR((1-(1+G$36)^(-$C40))/G$36-(1+G$36)/(G$36^2*$C40)*(1-($C40+1)/(1+G$36)^$C40+$C40/(1+G$36)^($C40+1)),"N/A") -> 2.2744177 | H40: =IFERROR((1-(1+H$36)^(-$C40))/H$36-(1+H$36)/(H$36^2*$C40)*(1-($C40+1)/(1+H$36)^$C40+$C40/(1+H$36)^($C40+1)),"N/A") -> 2.2256201
B41: N = 10 years | C41: 10 | D41: =IFERROR((1-(1+D$36)^(-$C41))/D$36-(1+D$36)/(D$36^2*$C41)*(1-($C41+1)/(1+D$36)^$C41+$C41/(1+D$36)^($C41+1)),"N/A") -> 3.3924233 | E41: =IFERROR((1-(1+E$36)^(-$C41))/E$36-(1+E$36)/(E$36^2*$C41)*(1-($C41+1)/(1+E$36)^$C41+$C41/(1+E$36)^($C41+1)),"N/A") -> 3.2921059 | F41: =IFERROR((1-(1+F$36)^(-$C41))/F$36-(1+F$36)/(F$36^2*$C41)*(1-($C41+1)/(1+F$36)^$C41+$C41/(1+F$36)^($C41+1)),"N/A") -> 3.1967641 | G41: =IFERROR((1-(1+G$36)^(-$C41))/G$36-(1+G$36)/(G$36^2*$C41)*(1-($C41+1)/(1+G$36)^$C41+$C41/(1+G$36)^($C41+1)),"N/A") -> 3.1060743 | H41: =IFERROR((1-(1+H$36)^(-$C41))/H$36-(1+H$36)/(H$36^2*$C41)*(1-($C41+1)/(1+H$36)^$C41+$C41/(1+H$36)^($C41+1)),"N/A") -> 3.019738
B42: B-2 PV weight on the STEADY STATE OP* (B + terminal factor)
B43: N = 3 years | C43: 3 | D43: =IFERROR((1+D$36)/(D$36^2*$C43)*(1-($C43+1)/(1+D$36)^$C43+$C43/(1+D$36)^($C43+1))+(1+$C$12)/((D$36-$C$12)*(1+D$36)^$C43),"N/A") -> 12.251769 | E43: =IFERROR((1+E$36)/(E$36^2*$C43)*(1-($C43+1)/(1+E$36)^$C43+$C43/(1+E$36)^($C43+1))+(1+$C$12)/((E$36-$C$12)*(1+E$36)^$C43),"N/A") -> 10.712854 | F43: =IFERROR((1+F$36)/(F$36^2*$C43)*(1-($C43+1)/(1+F$36)^$C43+$C43/(1+F$36)^($C43+1))+(1+$C$12)/((F$36-$C$12)*(1+F$36)^$C43),"N/A") -> 9.5009196 | G43: =IFERROR((1+G$36)/(G$36^2*$C43)*(1-($C43+1)/(1+G$36)^$C43+$C43/(1+G$36)^($C43+1))+(1+$C$12)/((G$36-$C$12)*(1+G$36)^$C43),"N/A") -> 8.5222163 | H43: =IFERROR((1+H$36)/(H$36^2*$C43)*(1-($C43+1)/(1+H$36)^$C43+$C43/(1+H$36)^($C43+1))+(1+$C$12)/((H$36-$C$12)*(1+H$36)^$C43),"N/A") -> 7.7156898
B44: N = 5 years | C44: 5 | D44: =IFERROR((1+D$36)/(D$36^2*$C44)*(1-($C44+1)/(1+D$36)^$C44+$C44/(1+D$36)^($C44+1))+(1+$C$12)/((D$36-$C$12)*(1+D$36)^$C44),"N/A") -> 11.242706 | E44: =IFERROR((1+E$36)/(E$36^2*$C44)*(1-($C44+1)/(1+E$36)^$C44+$C44/(1+E$36)^($C44+1))+(1+$C$12)/((E$36-$C$12)*(1+E$36)^$C44),"N/A") -> 9.7521406 | F44: =IFERROR((1+F$36)/(F$36^2*$C44)*(1-($C44+1)/(1+F$36)^$C44+$C44/(1+F$36)^($C44+1))+(1+$C$12)/((F$36-$C$12)*(1+F$36)^$C44),"N/A") -> 8.5814773 | G44: =IFERROR((1+G$36)/(G$36^2*$C44)*(1-($C44+1)/(1+G$36)^$C44+$C44/(1+G$36)^($C44+1))+(1+$C$12)/((G$36-$C$12)*(1+G$36)^$C44),"N/A") -> 7.6388417 | H44: =IFERROR((1+H$36)/(H$36^2*$C44)*(1-($C44+1)/(1+H$36)^$C44+$C44/(1+H$36)^($C44+1))+(1+$C$12)/((H$36-$C$12)*(1+H$36)^$C44),"N/A") -> 6.86441
B45: N = 7 years | C45: 7 | D45: =IFERROR((1+D$36)/(D$36^2*$C45)*(1-($C45+1)/(1+D$36)^$C45+$C45/(1+D$36)^($C45+1))+(1+$C$12)/((D$36-$C$12)*(1+D$36)^$C45),"N/A") -> 10.344125 | E45: =IFERROR((1+E$36)/(E$36^2*$C45)*(1-($C45+1)/(1+E$36)^$C45+$C45/(1+E$36)^($C45+1))+(1+$C$12)/((E$36-$C$12)*(1+E$36)^$C45),"N/A") -> 8.9062777 | F45: =IFERROR((1+F$36)/(F$36^2*$C45)*(1-($C45+1)/(1+F$36)^$C45+$C45/(1+F$36)^($C45+1))+(1+$C$12)/((F$36-$C$12)*(1+F$36)^$C45),"N/A") -> 7.7809121 | G45: =IFERROR((1+G$36)/(G$36^2*$C45)*(1-($C45+1)/(1+G$36)^$C45+$C45/(1+G$36)^($C45+1))+(1+$C$12)/((G$36-$C$12)*(1+G$36)^$C45),"N/A") -> 6.8780302 | H45: =IFERROR((1+H$36)/(H$36^2*$C45)*(1-($C45+1)/(1+H$36)^$C45+$C45/(1+H$36)^($C45+1))+(1+$C$12)/((H$36-$C$12)*(1+H$36)^$C45),"N/A") -> 6.139048
B46: N = 10 years | C46: 10 | D46: =IFERROR((1+D$36)/(D$36^2*$C46)*(1-($C46+1)/(1+D$36)^$C46+$C46/(1+D$36)^($C46+1))+(1+$C$12)/((D$36-$C$12)*(1+D$36)^$C46),"N/A") -> 9.1742946 | E46: =IFERROR((1+E$36)/(E$36^2*$C46)*(1-($C46+1)/(1+E$36)^$C46+$C46/(1+E$36)^($C46+1))+(1+$C$12)/((E$36-$C$12)*(1+E$36)^$C46),"N/A") -> 7.8197742 | F46: =IFERROR((1+F$36)/(F$36^2*$C46)*(1-($C46+1)/(1+F$36)^$C46+$C46/(1+F$36)^($C46+1))+(1+$C$12)/((F$36-$C$12)*(1+F$36)^$C46),"N/A") -> 6.7659616 | G46: =IFERROR((1+G$36)/(G$36^2*$C46)*(1-($C46+1)/(1+G$36)^$C46+$C46/(1+G$36)^($C46+1))+(1+$C$12)/((G$36-$C$12)*(1+G$36)^$C46),"N/A") -> 5.9256991 | H46: =IFERROR((1+H$36)/(H$36^2*$C46)*(1-($C46+1)/(1+H$36)^$C46+$C46/(1+H$36)^($C46+1))+(1+$C$12)/((H$36-$C$12)*(1+H$36)^$C46),"N/A") -> 5.2423032
B47: B-3 REQUIRED steady-state Operating Profit (JPY mn)
B48: N = 3 years | C48: 3 | D48: =IFERROR(($C$10/(1-$C$13)-$C$14*D38)/D43,"N/A") -> 887591.83 | E48: =IFERROR(($C$10/(1-$C$13)-$C$14*E38)/E43,"N/A") -> 1015457.5 | F48: =IFERROR(($C$10/(1-$C$13)-$C$14*F38)/F43,"N/A") -> 1145387.9 | G48: =IFERROR(($C$10/(1-$C$13)-$C$14*G38)/G43,"N/A") -> 1277360.8 | H48: =IFERROR(($C$10/(1-$C$13)-$C$14*H38)/H43,"N/A") -> 1411354
B49: N = 5 years | C49: 5 | D49: =IFERROR(($C$10/(1-$C$13)-$C$14*D39)/D44,"N/A") -> 941391.53 | E49: =IFERROR(($C$10/(1-$C$13)-$C$14*E39)/E44,"N/A") -> 1086376.3 | F49: =IFERROR(($C$10/(1-$C$13)-$C$14*F39)/F44,"N/A") -> 1235786.3 | G49: =IFERROR(($C$10/(1-$C$13)-$C$14*G39)/G44,"N/A") -> 1389600.3 | H49: =IFERROR(($C$10/(1-$C$13)-$C$14*H39)/H44,"N/A") -> 1547795
B50: N = 7 years | C50: 7 | D50: =IFERROR(($C$10/(1-$C$13)-$C$14*D40)/D45,"N/A") -> 997851.14 | E50: =IFERROR(($C$10/(1-$C$13)-$C$14*E40)/E45,"N/A") -> 1161162.4 | F50: =IFERROR(($C$10/(1-$C$13)-$C$14*F40)/F45,"N/A") -> 1331542.1 | G50: =IFERROR(($C$10/(1-$C$13)-$C$14*G40)/G45,"N/A") -> 1508988.6 | H50: =IFERROR(($C$10/(1-$C$13)-$C$14*H40)/H45,"N/A") -> 1693494.2
B51: N = 10 years | C51: 10 | D51: =IFERROR(($C$10/(1-$C$13)-$C$14*D41)/D46,"N/A") -> 1087414 | E51: =IFERROR(($C$10/(1-$C$13)-$C$14*E41)/E46,"N/A") -> 1280392.8 | F51: =IFERROR(($C$10/(1-$C$13)-$C$14*F41)/F46,"N/A") -> 1484891.2 | G51: =IFERROR(($C$10/(1-$C$13)-$C$14*G41)/G46,"N/A") -> 1700959.7 | H51: =IFERROR(($C$10/(1-$C$13)-$C$14*H41)/H46,"N/A") -> 1928630.6
B52: B-4 ... as a multiple of the FY2021 peak operating profit
B53: N = 3 years | C53: 3 | D53: =IFERROR(D48/$C$15,"N/A") -> 1.3854897 | E53: =IFERROR(E48/$C$15,"N/A") -> 1.5850821 | F53: =IFERROR(F48/$C$15,"N/A") -> 1.7878974 | G53: =IFERROR(G48/$C$15,"N/A") -> 1.993901 | H53: =IFERROR(H48/$C$15,"N/A") -> 2.2030583
B54: N = 5 years | C54: 5 | D54: =IFERROR(D49/$C$15,"N/A") -> 1.4694686 | E54: =IFERROR(E49/$C$15,"N/A") -> 1.695783 | F54: =IFERROR(F49/$C$15,"N/A") -> 1.9290052 | G54: =IFERROR(G49/$C$15,"N/A") -> 2.1691017 | H54: =IFERROR(H49/$C$15,"N/A") -> 2.4160363
B55: N = 7 years | C55: 7 | D55: =IFERROR(D50/$C$15,"N/A") -> 1.5575994 | E55: =IFERROR(E50/$C$15,"N/A") -> 1.8125207 | F55: =IFERROR(F50/$C$15,"N/A") -> 2.0784756 | G55: =IFERROR(G50/$C$15,"N/A") -> 2.3554613 | H55: =IFERROR(H50/$C$15,"N/A") -> 2.643466
B56: N = 10 years | C56: 10 | D56: =IFERROR(D51/$C$15,"N/A") -> 1.6974029 | E56: =IFERROR(E51/$C$15,"N/A") -> 1.9986338 | F56: =IFERROR(F51/$C$15,"N/A") -> 2.3178463 | G56: =IFERROR(G51/$C$15,"N/A") -> 2.6551194 | H56: =IFERROR(H51/$C$15,"N/A") -> 3.0105031
B58: Block C: Decomposing the required profit into revenue x margin (N = 5 years, model WACC)
B59: The revenue the company must run at, for a given steady-state operating margin, to earn the Block B-3 profit.
B60: Required steady-state Operating Profit (N=5, model WACC) | C60: =F49 -> 1235786.3
B62: Assumed steady-state OPM | C62: Required Revenue | D62: x base-year revenue
B63: 0.1821 | C63: =IFERROR($C$60/B63,"N/A") -> 6786306 | D63: =IFERROR(C63/'DCF Model'!C17,"N/A") -> 2.9339198
B64: 0.2732 | C64: =IFERROR($C$60/B64,"N/A") -> 4523376 | D64: =IFERROR(C64/'DCF Model'!C17,"N/A") -> 1.9555885
B65: cycle-peak OPM (FY2021) | C65: =IFERROR($C$60/$C$18,"N/A") -> 3392946.6 | D65: =IFERROR(C65/'DCF Model'!C17,"N/A") -> 1.4668706
B66: 0.4553 | C66: =IFERROR($C$60/B66,"N/A") -> 2714224.3 | D66: =IFERROR(C66/'DCF Model'!C17,"N/A") -> 1.173439
B67: 0.5463 | C67: =IFERROR($C$60/B67,"N/A") -> 2262102 | D67: =IFERROR(C67/'DCF Model'!C17,"N/A") -> 0.97797325
B69: Block D: The same question expressed as multiples
B70: Current EV / latest-FY EBITDA (actual) | C70: =IFERROR(C10/'Comps Analysis'!G5,"N/A") -> 22.338011
B71: Current EV / latest-FY Revenue (actual) | C71: =IFERROR(C10/'Comps Analysis'!F5,"N/A") -> 3.6308945
B72: EV / EBITDA if the Block A profit were already earned | C72: =IFERROR(C10/(C25+'DCF Model'!G42),"N/A") -> 7.7267722
B73: EV / EBITDA if the Block B-3 (N=5) profit were already earned | C73: =IFERROR(C10/(C60+'DCF Model'!G42),"N/A") -> 6.6534417
B74: Peer median EV / EBITDA (statistics rows) | C74: =IFERROR('Comps Analysis'!D16,"N/A") -> 13.167574
B75: Rows 3-4 answer: what multiple would today's EV be paying IF the company already earned the profit the price requires?
B77: Block F: The one-line answer
B78: ="At "&TEXT(C6,"#,##0")&" yen the market is paying for a steady-state operating profit of "&TEXT(F49,"#,##0")&" mn JPY - "&TEXT(F54,"0.00")&"x the FY2021 cycle peak of "&TEXT(C15,"#,##0")&" mn - reached in 5 years and sustained for ever, against "&TEXT(C14,"#,##0")&" mn actually earned in FY2026." -> At 8,839 yen the market is paying for a steady-state operating profit of 1,235,786 mn JPY - 1.93x the FY2021 cycle peak of 640,634 mn - reached in 5 years and sustained for ever, against 360,117 mn actually earned in FY2026.
B79: ="Even with no ramp at all (Block A) the price needs "&TEXT(C25,"#,##0")&" mn, or "&TEXT(C26,"0.00")&"x the peak. The base case supports an EV of only "&TEXT(C17,"#,##0")&" mn, leaving "&TEXT(C20,"#,##0")&" yen per share of the current price unexplained by mid-cycle economics." -> Even with no ramp at all (Block A) the price needs 1,060,444 mn, or 1.66x the peak. The base case supports an EV of only 5,896,857 mn, leaving 2,170 yen per share of the current price unexplained by mid-cycle economics.

Sheet NWC Schedule
B2: NWC Schedule - 任天堂
B4: Working Capital Drivers (Days) | C4: Base Year | D4: FY2027(E) | E4: FY2028(E) | F4: FY2029(E) | G4: FY2030(E) | H4: FY2031(E)
B5: DSO (Days Sales Outstanding) | C5: =C12/C9*365 -> 23.273168 | D5: =CHOOSE('DCF Model'!$D$27,D25,D26,D27,D28,D29) -> 22 | E5: =CHOOSE('DCF Model'!$D$27,E25,E26,E27,E28,E29) -> 22 | F5: =CHOOSE('DCF Model'!$D$27,F25,F26,F27,F28,F29) -> 22 | G5: =CHOOSE('DCF Model'!$D$27,G25,G26,G27,G28,G29) -> 22 | H5: =CHOOSE('DCF Model'!$D$27,H25,H26,H27,H28,H29) -> 22
B6: DIH (Days Inventory Held) | C6: =C13/C10*365 -> 140.32427 | D6: =CHOOSE('DCF Model'!$D$27,D32,D33,D34,D35,D36) -> 136 | E6: =CHOOSE('DCF Model'!$D$27,E32,E33,E34,E35,E36) -> 136 | F6: =CHOOSE('DCF Model'!$D$27,F32,F33,F34,F35,F36) -> 136 | G6: =CHOOSE('DCF Model'!$D$27,G32,G33,G34,G35,G36) -> 136 | H6: =CHOOSE('DCF Model'!$D$27,H32,H33,H34,H35,H36) -> 136
B7: DPO (Days Payable Outstanding) | C7: =C15/C10*365 -> 61.370485 | D7: =CHOOSE('DCF Model'!$D$27,D39,D40,D41,D42,D43) -> 69 | E7: =CHOOSE('DCF Model'!$D$27,E39,E40,E41,E42,E43) -> 69 | F7: =CHOOSE('DCF Model'!$D$27,F39,F40,F41,F42,F43) -> 69 | G7: =CHOOSE('DCF Model'!$D$27,G39,G40,G41,G42,G43) -> 69 | H7: =CHOOSE('DCF Model'!$D$27,H39,H40,H41,H42,H43) -> 69
B8: P&L Reference (JPY mn)
B9: Revenue | C9: 2313051 | D9: ='DCF Model'!C33 -> 2590617.1 | E9: ='DCF Model'!D33 -> 2746054.1 | F9: ='DCF Model'!E33 -> 2828435.8 | G9: ='DCF Model'!F33 -> 2885004.5 | H9: ='DCF Model'!G33 -> 2942704.6
B10: COGS | C10: 1404094 | D10: ='DCF Model'!C34 -> 1450745.6 | E10: ='DCF Model'!D34 -> 1427948.2 | F10: ='DCF Model'!E34 -> 1385933.5 | G10: ='DCF Model'!F34 -> 1384802.2 | H10: ='DCF Model'!G34 -> 1415440.9
B11: Working Capital Items (JPY mn)
B12: Accounts Receivable | C12: 147485 | D12: =D9*D5/365 -> 156146.79 | E12: =E9*E5/365 -> 165515.59 | F12: =F9*F5/365 -> 170481.06 | G12: =G9*G5/365 -> 173890.68 | H12: =H9*H5/365 -> 177368.5
B13: Inventory | C13: 539804 | D13: =D10*D6/365 -> 540551.78 | E13: =E10*E6/365 -> 532057.4 | F13: =F10*F6/365 -> 516402.63 | G13: =G10*G6/365 -> 515981.08 | H13: =H10*H6/365 -> 527397.16
B14: Current Assets (AR + Inv) | C14: =C12+C13 -> 687289 | D14: =D12+D13 -> 696698.57 | E14: =E12+E13 -> 697572.99 | F14: =F12+F13 -> 686883.69 | G14: =G12+G13 -> 689871.76 | H14: =H12+H13 -> 704765.65
B15: Accounts Payable | C15: 236082 | D15: =D10*D7/365 -> 274250.54 | E15: =E10*E7/365 -> 269940.88 | F15: =F10*F7/365 -> 261998.39 | G15: =G10*G7/365 -> 261784.52 | H15: =H10*H7/365 -> 267576.5
B16: Current Liabilities (AP) | C16: =C15 -> 236082 | D16: =D15 -> 274250.54 | E16: =E15 -> 269940.88 | F16: =F15 -> 261998.39 | G16: =G15 -> 261784.52 | H16: =H15 -> 267576.5
B17: Net Working Capital (JPY mn)
B18: Net Working Capital | C18: =C14-C16 -> 451207 | D18: =D14-D16 -> 422448.03 | E18: =E14-E16 -> 427632.1 | F18: =F14-F16 -> 424885.3 | G18: =G14-G16 -> 428087.24 | H18: =H14-H16 -> 437189.15
B19: Change in NWC | C19: n/a | D19: =D18-C18 -> -28758.97 | E19: =E18-D18 -> 5184.0733 | F19: =F18-E18 -> -2746.8065 | G19: =G18-F18 -> 3201.9443 | H19: =H18-G18 -> 9101.9125
B22: Scenario Input Matrix (Working Capital Days)
D23: FY2027(E) | E23: FY2028(E) | F23: FY2029(E) | G23: FY2030(E) | H23: FY2031(E)
B24: DSO (Days)
B25: Base | D25: 22 | E25: 22 | F25: 22 | G25: 22 | H25: 22
B26: Upside | D26: 21 | E26: 21 | F26: 21 | G26: 21 | H26: 21
B27: Management | D27: 22 | E27: 22 | F27: 22 | G27: 22 | H27: 22
B28: Downside 1 | D28: 24 | E28: 24 | F28: 24 | G28: 24 | H28: 24
B29: Downside 2 | D29: 26 | E29: 26 | F29: 26 | G29: 26 | H29: 26
B31: DIH (Days)
B32: Base | D32: 136 | E32: 136 | F32: 136 | G32: 136 | H32: 136
B33: Upside | D33: 120 | E33: 118 | F33: 115 | G33: 115 | H33: 115
B34: Management | D34: 136 | E34: 136 | F34: 136 | G34: 136 | H34: 136
B35: Downside 1 | D35: 150 | E35: 152 | F35: 155 | G35: 155 | H35: 155
B36: Downside 2 | D36: 175 | E36: 180 | F36: 175 | G36: 170 | H36: 165
B38: DPO (Days)
B39: Base | D39: 69 | E39: 69 | F39: 69 | G39: 69 | H39: 69
B40: Upside | D40: 72 | E40: 72 | F40: 72 | G40: 72 | H40: 72
B41: Management | D41: 69 | E41: 69 | F41: 69 | G41: 69 | H41: 69
B42: Downside 1 | D42: 65 | E42: 65 | F42: 65 | G42: 65 | H42: 65
B43: Downside 2 | D43: 60 | E43: 60 | F43: 60 | G43: 60 | H43: 60

Sheet Comps Analysis
B2: Comparable Company Analysis
B3: Peer prices as of 2026-09-06 (Mkt Cap / EV of peer rows are static CSV values; the subject row is live-linked to Executive Summary)
B4: Company | C4: Ticker | D4: Mkt Cap (JPY mn) | E4: EV (JPY mn) | F4: Revenue (JPY mn) | G4: EBITDA (JPY mn) | H4: Op Income (JPY mn) | I4: Net Income (JPY mn) | J4: EV/EBITDA | K4: EV/Revenue | L4: PER | M4: PBR | N4: Op Margin | O4: ROE | P4: Book Value (JPY mn) | Q4: Note
B5: Nintendo Co., Ltd. | C5: 7974.T | D5: ='Executive Summary'!C9*C23/1000000 -> 10190246 | E5: =D5+C24 -> 8398444.3 | F5: 2313051 | G5: 375971 | H5: 360117 | I5: 424056 | J5: =IFERROR(E5/G5,"") -> 22.338011 | K5: =IFERROR(E5/F5,"") -> 3.6308945 | L5: =IFERROR(D5/I5,"") -> 24.030426 | M5: =IFERROR(D5/P5,"") -> 3.4496164 | N5: =IFERROR(H5/F5,"") -> 0.15568917 | O5: =IFERROR(I5/P5,"") -> 0.14355203 | P5: 2954023
B6: BANDAI NAMCO Holdings Inc. | C6: 7832.T | D6: 3569201 | E6: 3148064 | F6: 1348246 | G6: 239077 | H6: 189518 | I6: 140651 | J6: =IFERROR(E6/G6,"") -> 13.167574 | K6: =IFERROR(E6/F6,"") -> 2.3349329 | L6: =IFERROR(D6/I6,"") -> 25.376293 | M6: =IFERROR(D6/P6,"") -> 4.1464778 | N6: =IFERROR(H6/F6,"") -> 0.14056634 | O6: =IFERROR(I6/P6,"") -> 0.16339966 | P6: 860779
B7: Konami Group Corporation | C7: 9766.T | D7: 2914464 | E7: 2626836 | F7: 493677 | G7: 170081 | H7: 135891 | I7: 100013 | J7: =IFERROR(E7/G7,"") -> 15.444618 | K7: =IFERROR(E7/F7,"") -> 5.3209609 | L7: =IFERROR(D7/I7,"") -> 29.140852 | M7: =IFERROR(D7/P7,"") -> 5.1625739 | N7: =IFERROR(H7/F7,"") -> 0.27526298 | O7: =IFERROR(I7/P7,"") -> 0.17715934 | P7: 564537
B8: Capcom Co., Ltd. | C8: 9697.T | D8: 1776976 | E8: 1634071 | F8: 195365 | G8: 80496 | H8: 75296 | I8: 54587 | J8: =IFERROR(E8/G8,"") -> 20.300027 | K8: =IFERROR(E8/F8,"") -> 8.3641952 | L8: =IFERROR(D8/I8,"") -> 32.553099 | M8: =IFERROR(D8/P8,"") -> 6.637938 | N8: =IFERROR(H8/F8,"") -> 0.38541192 | O8: =IFERROR(I8/P8,"") -> 0.20391109 | P8: 267700
B9: Square Enix Holdings Co., Ltd. | C9: 9684.T | D9: 1042352 | E9: 766298 | F9: 297661 | G9: 63428 | H9: 54742 | I9: 29616 | J9: =IFERROR(E9/G9,"") -> 12.081384 | K9: =IFERROR(E9/F9,"") -> 2.5743984 | L9: =IFERROR(D9/I9,"") -> 35.19557 | M9: =IFERROR(D9/P9,"") -> 2.9877435 | N9: =IFERROR(H9/F9,"") -> 0.1839072 | O9: =IFERROR(I9/P9,"") -> 0.08488976 | P9: 348876
B10: Sony Group Corporation | C10: 6758.T | D10: 22696920 | E10: 22157710 | F10: 12479620 | G10: 2734345 | H10: 1553690 | I10: -326865 | J10: =IFERROR(E10/G10,"") -> 8.10348 | K10: =IFERROR(E10/F10,"") -> 1.7755116 | L10: N/A | M10: =IFERROR(D10/P10,"") -> 2.7955277 | N10: =IFERROR(H10/F10,"") -> 0.12449818 | O10: =IFERROR(I10/P10,"") -> -0.040259214 | P10: 8119011
B14: Statistics
B15: 25th Percentile | D15: =PERCENTILE(J6:J10,0.25) -> 12.081384 | E15: =PERCENTILE(K6:K10,0.25) -> 2.3349329 | F15: =PERCENTILE(L6:L10,0.25) -> 28.199712 | G15: =PERCENTILE(M6:M10,0.25) -> 2.9877435 | H15: =PERCENTILE(N6:N10,0.25) -> 0.14056634 | I15: =PERCENTILE(O6:O10,0.25) -> 0.08488976
B16: Median (50th) | D16: =MEDIAN(J6:J10) -> 13.167574 | E16: =MEDIAN(K6:K10) -> 2.5743984 | F16: =MEDIAN(L6:L10) -> 30.846975 | G16: =MEDIAN(M6:M10) -> 4.1464778 | H16: =MEDIAN(N6:N10) -> 0.1839072 | I16: =MEDIAN(O6:O10) -> 0.16339966
B17: 75th Percentile | D17: =PERCENTILE(J6:J10,0.75) -> 15.444618 | E17: =PERCENTILE(K6:K10,0.75) -> 5.3209609 | F17: =PERCENTILE(L6:L10,0.75) -> 33.213717 | G17: =PERCENTILE(M6:M10,0.75) -> 5.1625739 | H17: =PERCENTILE(N6:N10,0.75) -> 0.27526298 | I17: =PERCENTILE(O6:O10,0.75) -> 0.17715934
B19: Implied Valuation for 任天堂
B20: 任天堂 Financials
B21: EBITDA (JPY mn) | C21: 375971
B22: Net Income (JPY mn) | C22: 424056
B23: Shares Outstanding | C23: 1152873205
B24: Net Debt (JPY mn) | C24: -1791802
B26: Implied Share Price (Median Multiples)
B27: Via EV/EBITDA (Median) | C27: =ROUND((C21*D16-C24)*1000000/C23,0) -> 5848
B28: Via PER (Median) | C28: =ROUND(C22*F16*1000000/C23,0) -> 11346

Sheet Sensitivity Analysis
B2: Sensitivity Analysis
B3: Current WACC: | C3: ='DCF Model'!C26 -> 0.1047 | E3: Terminal g: | F3: ='DCF Model'!C13 -> 0.01 | H3: Exit Multiple: | I3: ='DCF Model'!C14 -> 13.2
B5: Table 1: WACC vs Terminal Growth Rate (PGM - Implied Share Price, JPY)
B6: WACC \ Terminal g | C6: =$F$3-0.0075 -> 0.0025 | D6: =$F$3-0.005 -> 0.005 | E6: =$F$3-0.0025 -> 0.0075 | F6: =$F$3 -> 0.01 | G6: =$F$3+0.0025 -> 0.0125 | H6: =$F$3+0.005 -> 0.015 | I6: =$F$3+0.0075 -> 0.0175
B7: =$C$3-0.015 -> 0.0897 | C7: =IFERROR(ROUND(('DCF Model'!C45/(1+$B7)^('DCF Model'!C19+0)+'DCF Model'!D45/(1+$B7)^('DCF Model'!C19+1)+'DCF Model'!E45/(1+$B7)^('DCF Model'!C19+2)+'DCF Model'!F45/(1+$B7)^('DCF Model'!C19+3)+'DCF Model'!G45/(1+$B7)^('DCF Model'!C19+4)+'DCF Model'!G45*(1+C$6)/($B7-C$6)/(1+$B7)^('DCF Model'!C19+4)-'DCF Model'!C16)*1000000/'DCF Model'!C15,0),"") -> 7266 | D7: =IFERROR(ROUND(('DCF Model'!C45/(1+$B7)^('DCF Model'!C19+0)+'DCF Model'!D45/(1+$B7)^('DCF Model'!C19+1)+'DCF Model'!E45/(1+$B7)^('DCF Model'!C19+2)+'DCF Model'!F45/(1+$B7)^('DCF Model'!C19+3)+'DCF Model'!G45/(1+$B7)^('DCF Model'!C19+4)+'DCF Model'!G45*(1+D$6)/($B7-D$6)/(1+$B7)^('DCF Model'!C19+4)-'DCF Model'!C16)*1000000/'DCF Model'!C15,0),"") -> 7392 | E7: =IFERROR(ROUND(('DCF Model'!C45/(1+$B7)^('DCF Model'!C19+0)+'DCF Model'!D45/(1+$B7)^('DCF Model'!C19+1)+'DCF Model'!E45/(1+$B7)^('DCF Model'!C19+2)+'DCF Model'!F45/(1+$B7)^('DCF Model'!C19+3)+'DCF Model'!G45/(1+$B7)^('DCF Model'!C19+4)+'DCF Model'!G45*(1+E$6)/($B7-E$6)/(1+$B7)^('DCF Model'!C19+4)-'DCF Model'!C16)*1000000/'DCF Model'!C15,0),"") -> 7525 | F7: =IFERROR(ROUND(('DCF Model'!C45/(1+$B7)^('DCF Model'!C19+0)+'DCF Model'!D45/(1+$B7)^('DCF Model'!C19+1)+'DCF Model'!E45/(1+$B7)^('DCF Model'!C19+2)+'DCF Model'!F45/(1+$B7)^('DCF Model'!C19+3)+'DCF Model'!G45/(1+$B7)^('DCF Model'!C19+4)+'DCF Model'!G45*(1+F$6)/($B7-F$6)/(1+$B7)^('DCF Model'!C19+4)-'DCF Model'!C16)*1000000/'DCF Model'!C15,0),"") -> 7667 | G7: =IFERROR(ROUND(('DCF Model'!C45/(1+$B7)^('DCF Model'!C19+0)+'DCF Model'!D45/(1+$B7)^('DCF Model'!C19+1)+'DCF Model'!E45/(1+$B7)^('DCF Model'!C19+2)+'DCF Model'!F45/(1+$B7)^('DCF Model'!C19+3)+'DCF Model'!G45/(1+$B7)^('DCF Model'!C19+4)+'DCF Model'!G45*(1+G$6)/($B7-G$6)/(1+$B7)^('DCF Model'!C19+4)-'DCF Model'!C16)*1000000/'DCF Model'!C15,0),"") -> 7819 | H7: =IFERROR(ROUND(('DCF Model'!C45/(1+$B7)^('DCF Model'!C19+0)+'DCF Model'!D45/(1+$B7)^('DCF Model'!C19+1)+'DCF Model'!E45/(1+$B7)^('DCF Model'!C19+2)+'DCF Model'!F45/(1+$B7)^('DCF Model'!C19+3)+'DCF Model'!G45/(1+$B7)^('DCF Model'!C19+4)+'DCF Model'!G45*(1+H$6)/($B7-H$6)/(1+$B7)^('DCF Model'!C19+4)-'DCF Model'!C16)*1000000/'DCF Model'!C15,0),"") -> 7980 | I7: =IFERROR(ROUND(('DCF Model'!C45/(1+$B7)^('DCF Model'!C19+0)+'DCF Model'!D45/(1+$B7)^('DCF Model'!C19+1)+'DCF Model'!E45/(1+$B7)^('DCF Model'!C19+2)+'DCF Model'!F45/(1+$B7)^('DCF Model'!C19+3)+'DCF Model'!G45/(1+$B7)^('DCF Model'!C19+4)+'DCF Model'!G45*(1+I$6)/($B7-I$6)/(1+$B7)^('DCF Model'!C19+4)-'DCF Model'!C16)*1000000/'DCF Model'!C15,0),"") -> 8153
B8: =$C$3-0.01 -> 0.0947 | C8: =IFERROR(ROUND(('DCF Model'!C45/(1+$B8)^('DCF Model'!C19+0)+'DCF Model'!D45/(1+$B8)^('DCF Model'!C19+1)+'DCF Model'!E45/(1+$B8)^('DCF Model'!C19+2)+'DCF Model'!F45/(1+$B8)^('DCF Model'!C19+3)+'DCF Model'!G45/(1+$B8)^('DCF Model'!C19+4)+'DCF Model'!G45*(1+C$6)/($B8-C$6)/(1+$B8)^('DCF Model'!C19+4)-'DCF Model'!C16)*1000000/'DCF Model'!C15,0),"") -> 6944 | D8: =IFERROR(ROUND(('DCF Model'!C45/(1+$B8)^('DCF Model'!C19+0)+'DCF Model'!D45/(1+$B8)^('DCF Model'!C19+1)+'DCF Model'!E45/(1+$B8)^('DCF Model'!C19+2)+'DCF Model'!F45/(1+$B8)^('DCF Model'!C19+3)+'DCF Model'!G45/(1+$B8)^('DCF Model'!C19+4)+'DCF Model'!G45*(1+D$6)/($B8-D$6)/(1+$B8)^('DCF Model'!C19+4)-'DCF Model'!C16)*1000000/'DCF Model'!C15,0),"") -> 7055 | E8: =IFERROR(ROUND(('DCF Model'!C45/(1+$B8)^('DCF Model'!C19+0)+'DCF Model'!D45/(1+$B8)^('DCF Model'!C19+1)+'DCF Model'!E45/(1+$B8)^('DCF Model'!C19+2)+'DCF Model'!F45/(1+$B8)^('DCF Model'!C19+3)+'DCF Model'!G45/(1+$B8)^('DCF Model'!C19+4)+'DCF Model'!G45*(1+E$6)/($B8-E$6)/(1+$B8)^('DCF Model'!C19+4)-'DCF Model'!C16)*1000000/'DCF Model'!C15,0),"") -> 7172 | F8: =IFERROR(ROUND(('DCF Model'!C45/(1+$B8)^('DCF Model'!C19+0)+'DCF Model'!D45/(1+$B8)^('DCF Model'!C19+1)+'DCF Model'!E45/(1+$B8)^('DCF Model'!C19+2)+'DCF Model'!F45/(1+$B8)^('DCF Model'!C19+3)+'DCF Model'!G45/(1+$B8)^('DCF Model'!C19+4)+'DCF Model'!G45*(1+F$6)/($B8-F$6)/(1+$B8)^('DCF Model'!C19+4)-'DCF Model'!C16)*1000000/'DCF Model'!C15,0),"") -> 7295 | G8: =IFERROR(ROUND(('DCF Model'!C45/(1+$B8)^('DCF Model'!C19+0)+'DCF Model'!D45/(1+$B8)^('DCF Model'!C19+1)+'DCF Model'!E45/(1+$B8)^('DCF Model'!C19+2)+'DCF Model'!F45/(1+$B8)^('DCF Model'!C19+3)+'DCF Model'!G45/(1+$B8)^('DCF Model'!C19+4)+'DCF Model'!G45*(1+G$6)/($B8-G$6)/(1+$B8)^('DCF Model'!C19+4)-'DCF Model'!C16)*1000000/'DCF Model'!C15,0),"") -> 7427 | H8: =IFERROR(ROUND(('DCF Model'!C45/(1+$B8)^('DCF Model'!C19+0)+'DCF Model'!D45/(1+$B8)^('DCF Model'!C19+1)+'DCF Model'!E45/(1+$B8)^('DCF Model'!C19+2)+'DCF Model'!F45/(1+$B8)^('DCF Model'!C19+3)+'DCF Model'!G45/(1+$B8)^('DCF Model'!C19+4)+'DCF Model'!G45*(1+H$6)/($B8-H$6)/(1+$B8)^('DCF Model'!C19+4)-'DCF Model'!C16)*1000000/'DCF Model'!C15,0),"") -> 7566 | I8: =IFERROR(ROUND(('DCF Model'!C45/(1+$B8)^('DCF Model'!C19+0)+'DCF Model'!D45/(1+$B8)^('DCF Model'!C19+1)+'DCF Model'!E45/(1+$B8)^('DCF Model'!C19+2)+'DCF Model'!F45/(1+$B8)^('DCF Model'!C19+3)+'DCF Model'!G45/(1+$B8)^('DCF Model'!C19+4)+'DCF Model'!G45*(1+I$6)/($B8-I$6)/(1+$B8)^('DCF Model'!C19+4)-'DCF Model'!C16)*1000000/'DCF Model'!C15,0),"") -> 7715
B9: =$C$3-0.005 -> 0.0997 | C9: =IFERROR(ROUND(('DCF Model'!C45/(1+$B9)^('DCF Model'!C19+0)+'DCF Model'!D45/(1+$B9)^('DCF Model'!C19+1)+'DCF Model'!E45/(1+$B9)^('DCF Model'!C19+2)+'DCF Model'!F45/(1+$B9)^('DCF Model'!C19+3)+'DCF Model'!G45/(1+$B9)^('DCF Model'!C19+4)+'DCF Model'!G45*(1+C$6)/($B9-C$6)/(1+$B9)^('DCF Model'!C19+4)-'DCF Model'!C16)*1000000/'DCF Model'!C15,0),"") -> 6656 | D9: =IFERROR(ROUND(('DCF Model'!C45/(1+$B9)^('DCF Model'!C19+0)+'DCF Model'!D45/(1+$B9)^('DCF Model'!C19+1)+'DCF Model'!E45/(1+$B9)^('DCF Model'!C19+2)+'DCF Model'!F45/(1+$B9)^('DCF Model'!C19+3)+'DCF Model'!G45/(1+$B9)^('DCF Model'!C19+4)+'DCF Model'!G45*(1+D$6)/($B9-D$6)/(1+$B9)^('DCF Model'!C19+4)-'DCF Model'!C16)*1000000/'DCF Model'!C15,0),"") -> 6753 | E9: =IFERROR(ROUND(('DCF Model'!C45/(1+$B9)^('DCF Model'!C19+0)+'DCF Model'!D45/(1+$B9)^('DCF Model'!C19+1)+'DCF Model'!E45/(1+$B9)^('DCF Model'!C19+2)+'DCF Model'!F45/(1+$B9)^('DCF Model'!C19+3)+'DCF Model'!G45/(1+$B9)^('DCF Model'!C19+4)+'DCF Model'!G45*(1+E$6)/($B9-E$6)/(1+$B9)^('DCF Model'!C19+4)-'DCF Model'!C16)*1000000/'DCF Model'!C15,0),"") -> 6856 | F9: =IFERROR(ROUND(('DCF Model'!C45/(1+$B9)^('DCF Model'!C19+0)+'DCF Model'!D45/(1+$B9)^('DCF Model'!C19+1)+'DCF Model'!E45/(1+$B9)^('DCF Model'!C19+2)+'DCF Model'!F45/(1+$B9)^('DCF Model'!C19+3)+'DCF Model'!G45/(1+$B9)^('DCF Model'!C19+4)+'DCF Model'!G45*(1+F$6)/($B9-F$6)/(1+$B9)^('DCF Model'!C19+4)-'DCF Model'!C16)*1000000/'DCF Model'!C15,0),"") -> 6965 | G9: =IFERROR(ROUND(('DCF Model'!C45/(1+$B9)^('DCF Model'!C19+0)+'DCF Model'!D45/(1+$B9)^('DCF Model'!C19+1)+'DCF Model'!E45/(1+$B9)^('DCF Model'!C19+2)+'DCF Model'!F45/(1+$B9)^('DCF Model'!C19+3)+'DCF Model'!G45/(1+$B9)^('DCF Model'!C19+4)+'DCF Model'!G45*(1+G$6)/($B9-G$6)/(1+$B9)^('DCF Model'!C19+4)-'DCF Model'!C16)*1000000/'DCF Model'!C15,0),"") -> 7079 | H9: =IFERROR(ROUND(('DCF Model'!C45/(1+$B9)^('DCF Model'!C19+0)+'DCF Model'!D45/(1+$B9)^('DCF Model'!C19+1)+'DCF Model'!E45/(1+$B9)^('DCF Model'!C19+2)+'DCF Model'!F45/(1+$B9)^('DCF Model'!C19+3)+'DCF Model'!G45/(1+$B9)^('DCF Model'!C19+4)+'DCF Model'!G45*(1+H$6)/($B9-H$6)/(1+$B9)^('DCF Model'!C19+4)-'DCF Model'!C16)*1000000/'DCF Model'!C15,0),"") -> 7201 | I9: =IFERROR(ROUND(('DCF Model'!C45/(1+$B9)^('DCF Model'!C19+0)+'DCF Model'!D45/(1+$B9)^('DCF Model'!C19+1)+'DCF Model'!E45/(1+$B9)^('DCF Model'!C19+2)+'DCF Model'!F45/(1+$B9)^('DCF Model'!C19+3)+'DCF Model'!G45/(1+$B9)^('DCF Model'!C19+4)+'DCF Model'!G45*(1+I$6)/($B9-I$6)/(1+$B9)^('DCF Model'!C19+4)-'DCF Model'!C16)*1000000/'DCF Model'!C15,0),"") -> 7330
B10: =$C$3 -> 0.1047 | C10: =IFERROR(ROUND(('DCF Model'!C45/(1+$B10)^('DCF Model'!C19+0)+'DCF Model'!D45/(1+$B10)^('DCF Model'!C19+1)+'DCF Model'!E45/(1+$B10)^('DCF Model'!C19+2)+'DCF Model'!F45/(1+$B10)^('DCF Model'!C19+3)+'DCF Model'!G45/(1+$B10)^('DCF Model'!C19+4)+'DCF Model'!G45*(1+C$6)/($B10-C$6)/(1+$B10)^('DCF Model'!C19+4)-'DCF Model'!C16)*1000000/'DCF Model'!C15,0),"") -> 6396 | D10: =IFERROR(ROUND(('DCF Model'!C45/(1+$B10)^('DCF Model'!C19+0)+'DCF Model'!D45/(1+$B10)^('DCF Model'!C19+1)+'DCF Model'!E45/(1+$B10)^('DCF Model'!C19+2)+'DCF Model'!F45/(1+$B10)^('DCF Model'!C19+3)+'DCF Model'!G45/(1+$B10)^('DCF Model'!C19+4)+'DCF Model'!G45*(1+D$6)/($B10-D$6)/(1+$B10)^('DCF Model'!C19+4)-'DCF Model'!C16)*1000000/'DCF Model'!C15,0),"") -> 6482 | E10: =IFERROR(ROUND(('DCF Model'!C45/(1+$B10)^('DCF Model'!C19+0)+'DCF Model'!D45/(1+$B10)^('DCF Model'!C19+1)+'DCF Model'!E45/(1+$B10)^('DCF Model'!C19+2)+'DCF Model'!F45/(1+$B10)^('DCF Model'!C19+3)+'DCF Model'!G45/(1+$B10)^('DCF Model'!C19+4)+'DCF Model'!G45*(1+E$6)/($B10-E$6)/(1+$B10)^('DCF Model'!C19+4)-'DCF Model'!C16)*1000000/'DCF Model'!C15,0),"") -> 6573 | F10: =IFERROR(ROUND(('DCF Model'!C45/(1+$B10)^('DCF Model'!C19+0)+'DCF Model'!D45/(1+$B10)^('DCF Model'!C19+1)+'DCF Model'!E45/(1+$B10)^('DCF Model'!C19+2)+'DCF Model'!F45/(1+$B10)^('DCF Model'!C19+3)+'DCF Model'!G45/(1+$B10)^('DCF Model'!C19+4)+'DCF Model'!G45*(1+F$6)/($B10-F$6)/(1+$B10)^('DCF Model'!C19+4)-'DCF Model'!C16)*1000000/'DCF Model'!C15,0),"") -> 6669 | G10: =IFERROR(ROUND(('DCF Model'!C45/(1+$B10)^('DCF Model'!C19+0)+'DCF Model'!D45/(1+$B10)^('DCF Model'!C19+1)+'DCF Model'!E45/(1+$B10)^('DCF Model'!C19+2)+'DCF Model'!F45/(1+$B10)^('DCF Model'!C19+3)+'DCF Model'!G45/(1+$B10)^('DCF Model'!C19+4)+'DCF Model'!G45*(1+G$6)/($B10-G$6)/(1+$B10)^('DCF Model'!C19+4)-'DCF Model'!C16)*1000000/'DCF Model'!C15,0),"") -> 6770 | H10: =IFERROR(ROUND(('DCF Model'!C45/(1+$B10)^('DCF Model'!C19+0)+'DCF Model'!D45/(1+$B10)^('DCF Model'!C19+1)+'DCF Model'!E45/(1+$B10)^('DCF Model'!C19+2)+'DCF Model'!F45/(1+$B10)^('DCF Model'!C19+3)+'DCF Model'!G45/(1+$B10)^('DCF Model'!C19+4)+'DCF Model'!G45*(1+H$6)/($B10-H$6)/(1+$B10)^('DCF Model'!C19+4)-'DCF Model'!C16)*1000000/'DCF Model'!C15,0),"") -> 6877 | I10: =IFERROR(ROUND(('DCF Model'!C45/(1+$B10)^('DCF Model'!C19+0)+'DCF Model'!D45/(1+$B10)^('DCF Model'!C19+1)+'DCF Model'!E45/(1+$B10)^('DCF Model'!C19+2)+'DCF Model'!F45/(1+$B10)^('DCF Model'!C19+3)+'DCF Model'!G45/(1+$B10)^('DCF Model'!C19+4)+'DCF Model'!G45*(1+I$6)/($B10-I$6)/(1+$B10)^('DCF Model'!C19+4)-'DCF Model'!C16)*1000000/'DCF Model'!C15,0),"") -> 6989
B11: =$C$3+0.005 -> 0.1097 | C11: =IFERROR(ROUND(('DCF Model'!C45/(1+$B11)^('DCF Model'!C19+0)+'DCF Model'!D45/(1+$B11)^('DCF Model'!C19+1)+'DCF Model'!E45/(1+$B11)^('DCF Model'!C19+2)+'DCF Model'!F45/(1+$B11)^('DCF Model'!C19+3)+'DCF Model'!G45/(1+$B11)^('DCF Model'!C19+4)+'DCF Model'!G45*(1+C$6)/($B11-C$6)/(1+$B11)^('DCF Model'!C19+4)-'DCF Model'!C16)*1000000/'DCF Model'!C15,0),"") -> 6160 | D11: =IFERROR(ROUND(('DCF Model'!C45/(1+$B11)^('DCF Model'!C19+0)+'DCF Model'!D45/(1+$B11)^('DCF Model'!C19+1)+'DCF Model'!E45/(1+$B11)^('DCF Model'!C19+2)+'DCF Model'!F45/(1+$B11)^('DCF Model'!C19+3)+'DCF Model'!G45/(1+$B11)^('DCF Model'!C19+4)+'DCF Model'!G45*(1+D$6)/($B11-D$6)/(1+$B11)^('DCF Model'!C19+4)-'DCF Model'!C16)*1000000/'DCF Model'!C15,0),"") -> 6238 | E11: =IFERROR(ROUND(('DCF Model'!C45/(1+$B11)^('DCF Model'!C19+0)+'DCF Model'!D45/(1+$B11)^('DCF Model'!C19+1)+'DCF Model'!E45/(1+$B11)^('DCF Model'!C19+2)+'DCF Model'!F45/(1+$B11)^('DCF Model'!C19+3)+'DCF Model'!G45/(1+$B11)^('DCF Model'!C19+4)+'DCF Model'!G45*(1+E$6)/($B11-E$6)/(1+$B11)^('DCF Model'!C19+4)-'DCF Model'!C16)*1000000/'DCF Model'!C15,0),"") -> 6318 | F11: =IFERROR(ROUND(('DCF Model'!C45/(1+$B11)^('DCF Model'!C19+0)+'DCF Model'!D45/(1+$B11)^('DCF Model'!C19+1)+'DCF Model'!E45/(1+$B11)^('DCF Model'!C19+2)+'DCF Model'!F45/(1+$B11)^('DCF Model'!C19+3)+'DCF Model'!G45/(1+$B11)^('DCF Model'!C19+4)+'DCF Model'!G45*(1+F$6)/($B11-F$6)/(1+$B11)^('DCF Model'!C19+4)-'DCF Model'!C16)*1000000/'DCF Model'!C15,0),"") -> 6403 | G11: =IFERROR(ROUND(('DCF Model'!C45/(1+$B11)^('DCF Model'!C19+0)+'DCF Model'!D45/(1+$B11)^('DCF Model'!C19+1)+'DCF Model'!E45/(1+$B11)^('DCF Model'!C19+2)+'DCF Model'!F45/(1+$B11)^('DCF Model'!C19+3)+'DCF Model'!G45/(1+$B11)^('DCF Model'!C19+4)+'DCF Model'!G45*(1+G$6)/($B11-G$6)/(1+$B11)^('DCF Model'!C19+4)-'DCF Model'!C16)*1000000/'DCF Model'!C15,0),"") -> 6493 | H11: =IFERROR(ROUND(('DCF Model'!C45/(1+$B11)^('DCF Model'!C19+0)+'DCF Model'!D45/(1+$B11)^('DCF Model'!C19+1)+'DCF Model'!E45/(1+$B11)^('DCF Model'!C19+2)+'DCF Model'!F45/(1+$B11)^('DCF Model'!C19+3)+'DCF Model'!G45/(1+$B11)^('DCF Model'!C19+4)+'DCF Model'!G45*(1+H$6)/($B11-H$6)/(1+$B11)^('DCF Model'!C19+4)-'DCF Model'!C16)*1000000/'DCF Model'!C15,0),"") -> 6587 | I11: =IFERROR(ROUND(('DCF Model'!C45/(1+$B11)^('DCF Model'!C19+0)+'DCF Model'!D45/(1+$B11)^('DCF Model'!C19+1)+'DCF Model'!E45/(1+$B11)^('DCF Model'!C19+2)+'DCF Model'!F45/(1+$B11)^('DCF Model'!C19+3)+'DCF Model'!G45/(1+$B11)^('DCF Model'!C19+4)+'DCF Model'!G45*(1+I$6)/($B11-I$6)/(1+$B11)^('DCF Model'!C19+4)-'DCF Model'!C16)*1000000/'DCF Model'!C15,0),"") -> 6686
B12: =$C$3+0.01 -> 0.1147 | C12: =IFERROR(ROUND(('DCF Model'!C45/(1+$B12)^('DCF Model'!C19+0)+'DCF Model'!D45/(1+$B12)^('DCF Model'!C19+1)+'DCF Model'!E45/(1+$B12)^('DCF Model'!C19+2)+'DCF Model'!F45/(1+$B12)^('DCF Model'!C19+3)+'DCF Model'!G45/(1+$B12)^('DCF Model'!C19+4)+'DCF Model'!G45*(1+C$6)/($B12-C$6)/(1+$B12)^('DCF Model'!C19+4)-'DCF Model'!C16)*1000000/'DCF Model'!C15,0),"") -> 5946 | D12: =IFERROR(ROUND(('DCF Model'!C45/(1+$B12)^('DCF Model'!C19+0)+'DCF Model'!D45/(1+$B12)^('DCF Model'!C19+1)+'DCF Model'!E45/(1+$B12)^('DCF Model'!C19+2)+'DCF Model'!F45/(1+$B12)^('DCF Model'!C19+3)+'DCF Model'!G45/(1+$B12)^('DCF Model'!C19+4)+'DCF Model'!G45*(1+D$6)/($B12-D$6)/(1+$B12)^('DCF Model'!C19+4)-'DCF Model'!C16)*1000000/'DCF Model'!C15,0),"") -> 6015 | E12: =IFERROR(ROUND(('DCF Model'!C45/(1+$B12)^('DCF Model'!C19+0)+'DCF Model'!D45/(1+$B12)^('DCF Model'!C19+1)+'DCF Model'!E45/(1+$B12)^('DCF Model'!C19+2)+'DCF Model'!F45/(1+$B12)^('DCF Model'!C19+3)+'DCF Model'!G45/(1+$B12)^('DCF Model'!C19+4)+'DCF Model'!G45*(1+E$6)/($B12-E$6)/(1+$B12)^('DCF Model'!C19+4)-'DCF Model'!C16)*1000000/'DCF Model'!C15,0),"") -> 6087 | F12: =IFERROR(ROUND(('DCF Model'!C45/(1+$B12)^('DCF Model'!C19+0)+'DCF Model'!D45/(1+$B12)^('DCF Model'!C19+1)+'DCF Model'!E45/(1+$B12)^('DCF Model'!C19+2)+'DCF Model'!F45/(1+$B12)^('DCF Model'!C19+3)+'DCF Model'!G45/(1+$B12)^('DCF Model'!C19+4)+'DCF Model'!G45*(1+F$6)/($B12-F$6)/(1+$B12)^('DCF Model'!C19+4)-'DCF Model'!C16)*1000000/'DCF Model'!C15,0),"") -> 6163 | G12: =IFERROR(ROUND(('DCF Model'!C45/(1+$B12)^('DCF Model'!C19+0)+'DCF Model'!D45/(1+$B12)^('DCF Model'!C19+1)+'DCF Model'!E45/(1+$B12)^('DCF Model'!C19+2)+'DCF Model'!F45/(1+$B12)^('DCF Model'!C19+3)+'DCF Model'!G45/(1+$B12)^('DCF Model'!C19+4)+'DCF Model'!G45*(1+G$6)/($B12-G$6)/(1+$B12)^('DCF Model'!C19+4)-'DCF Model'!C16)*1000000/'DCF Model'!C15,0),"") -> 6243 | H12: =IFERROR(ROUND(('DCF Model'!C45/(1+$B12)^('DCF Model'!C19+0)+'DCF Model'!D45/(1+$B12)^('DCF Model'!C19+1)+'DCF Model'!E45/(1+$B12)^('DCF Model'!C19+2)+'DCF Model'!F45/(1+$B12)^('DCF Model'!C19+3)+'DCF Model'!G45/(1+$B12)^('DCF Model'!C19+4)+'DCF Model'!G45*(1+H$6)/($B12-H$6)/(1+$B12)^('DCF Model'!C19+4)-'DCF Model'!C16)*1000000/'DCF Model'!C15,0),"") -> 6326 | I12: =IFERROR(ROUND(('DCF Model'!C45/(1+$B12)^('DCF Model'!C19+0)+'DCF Model'!D45/(1+$B12)^('DCF Model'!C19+1)+'DCF Model'!E45/(1+$B12)^('DCF Model'!C19+2)+'DCF Model'!F45/(1+$B12)^('DCF Model'!C19+3)+'DCF Model'!G45/(1+$B12)^('DCF Model'!C19+4)+'DCF Model'!G45*(1+I$6)/($B12-I$6)/(1+$B12)^('DCF Model'!C19+4)-'DCF Model'!C16)*1000000/'DCF Model'!C15,0),"") -> 6414
B13: =$C$3+0.015 -> 0.1197 | C13: =IFERROR(ROUND(('DCF Model'!C45/(1+$B13)^('DCF Model'!C19+0)+'DCF Model'!D45/(1+$B13)^('DCF Model'!C19+1)+'DCF Model'!E45/(1+$B13)^('DCF Model'!C19+2)+'DCF Model'!F45/(1+$B13)^('DCF Model'!C19+3)+'DCF Model'!G45/(1+$B13)^('DCF Model'!C19+4)+'DCF Model'!G45*(1+C$6)/($B13-C$6)/(1+$B13)^('DCF Model'!C19+4)-'DCF Model'!C16)*1000000/'DCF Model'!C15,0),"") -> 5750 | D13: =IFERROR(ROUND(('DCF Model'!C45/(1+$B13)^('DCF Model'!C19+0)+'DCF Model'!D45/(1+$B13)^('DCF Model'!C19+1)+'DCF Model'!E45/(1+$B13)^('DCF Model'!C19+2)+'DCF Model'!F45/(1+$B13)^('DCF Model'!C19+3)+'DCF Model'!G45/(1+$B13)^('DCF Model'!C19+4)+'DCF Model'!G45*(1+D$6)/($B13-D$6)/(1+$B13)^('DCF Model'!C19+4)-'DCF Model'!C16)*1000000/'DCF Model'!C15,0),"") -> 5812 | E13: =IFERROR(ROUND(('DCF Model'!C45/(1+$B13)^('DCF Model'!C19+0)+'DCF Model'!D45/(1+$B13)^('DCF Model'!C19+1)+'DCF Model'!E45/(1+$B13)^('DCF Model'!C19+2)+'DCF Model'!F45/(1+$B13)^('DCF Model'!C19+3)+'DCF Model'!G45/(1+$B13)^('DCF Model'!C19+4)+'DCF Model'!G45*(1+E$6)/($B13-E$6)/(1+$B13)^('DCF Model'!C19+4)-'DCF Model'!C16)*1000000/'DCF Model'!C15,0),"") -> 5877 | F13: =IFERROR(ROUND(('DCF Model'!C45/(1+$B13)^('DCF Model'!C19+0)+'DCF Model'!D45/(1+$B13)^('DCF Model'!C19+1)+'DCF Model'!E45/(1+$B13)^('DCF Model'!C19+2)+'DCF Model'!F45/(1+$B13)^('DCF Model'!C19+3)+'DCF Model'!G45/(1+$B13)^('DCF Model'!C19+4)+'DCF Model'!G45*(1+F$6)/($B13-F$6)/(1+$B13)^('DCF Model'!C19+4)-'DCF Model'!C16)*1000000/'DCF Model'!C15,0),"") -> 5945 | G13: =IFERROR(ROUND(('DCF Model'!C45/(1+$B13)^('DCF Model'!C19+0)+'DCF Model'!D45/(1+$B13)^('DCF Model'!C19+1)+'DCF Model'!E45/(1+$B13)^('DCF Model'!C19+2)+'DCF Model'!F45/(1+$B13)^('DCF Model'!C19+3)+'DCF Model'!G45/(1+$B13)^('DCF Model'!C19+4)+'DCF Model'!G45*(1+G$6)/($B13-G$6)/(1+$B13)^('DCF Model'!C19+4)-'DCF Model'!C16)*1000000/'DCF Model'!C15,0),"") -> 6016 | H13: =IFERROR(ROUND(('DCF Model'!C45/(1+$B13)^('DCF Model'!C19+0)+'DCF Model'!D45/(1+$B13)^('DCF Model'!C19+1)+'DCF Model'!E45/(1+$B13)^('DCF Model'!C19+2)+'DCF Model'!F45/(1+$B13)^('DCF Model'!C19+3)+'DCF Model'!G45/(1+$B13)^('DCF Model'!C19+4)+'DCF Model'!G45*(1+H$6)/($B13-H$6)/(1+$B13)^('DCF Model'!C19+4)-'DCF Model'!C16)*1000000/'DCF Model'!C15,0),"") -> 6090 | I13: =IFERROR(ROUND(('DCF Model'!C45/(1+$B13)^('DCF Model'!C19+0)+'DCF Model'!D45/(1+$B13)^('DCF Model'!C19+1)+'DCF Model'!E45/(1+$B13)^('DCF Model'!C19+2)+'DCF Model'!F45/(1+$B13)^('DCF Model'!C19+3)+'DCF Model'!G45/(1+$B13)^('DCF Model'!C19+4)+'DCF Model'!G45*(1+I$6)/($B13-I$6)/(1+$B13)^('DCF Model'!C19+4)-'DCF Model'!C16)*1000000/'DCF Model'!C15,0),"") -> 6168
B16: Table 2: WACC vs Exit Multiple (Exit Multiple - Implied Share Price, JPY)
B17: WACC \ Exit Multiple | C17: =$I$3-3 -> 10.2 | D17: =$I$3-2 -> 11.2 | E17: =$I$3-1 -> 12.2 | F17: =$I$3 -> 13.2 | G17: =$I$3+1 -> 14.2 | H17: =$I$3+2 -> 15.2 | I17: =$I$3+3 -> 16.2
B18: =$C$3-0.015 -> 0.0897 | C18: =IFERROR(ROUND(('DCF Model'!C45/(1+$B18)^('DCF Model'!C19+0)+'DCF Model'!D45/(1+$B18)^('DCF Model'!C19+1)+'DCF Model'!E45/(1+$B18)^('DCF Model'!C19+2)+'DCF Model'!F45/(1+$B18)^('DCF Model'!C19+3)+'DCF Model'!G45/(1+$B18)^('DCF Model'!C19+4)+('DCF Model'!G39+'DCF Model'!G42)*C$17/(1+$B18)^('DCF Model'!C19+4)-'DCF Model'!C16)*1000000/'DCF Model'!C15,0),"") -> 8218 | D18: =IFERROR(ROUND(('DCF Model'!C45/(1+$B18)^('DCF Model'!C19+0)+'DCF Model'!D45/(1+$B18)^('DCF Model'!C19+1)+'DCF Model'!E45/(1+$B18)^('DCF Model'!C19+2)+'DCF Model'!F45/(1+$B18)^('DCF Model'!C19+3)+'DCF Model'!G45/(1+$B18)^('DCF Model'!C19+4)+('DCF Model'!G39+'DCF Model'!G42)*D$17/(1+$B18)^('DCF Model'!C19+4)-'DCF Model'!C16)*1000000/'DCF Model'!C15,0),"") -> 8696 | E18: =IFERROR(ROUND(('DCF Model'!C45/(1+$B18)^('DCF Model'!C19+0)+'DCF Model'!D45/(1+$B18)^('DCF Model'!C19+1)+'DCF Model'!E45/(1+$B18)^('DCF Model'!C19+2)+'DCF Model'!F45/(1+$B18)^('DCF Model'!C19+3)+'DCF Model'!G45/(1+$B18)^('DCF Model'!C19+4)+('DCF Model'!G39+'DCF Model'!G42)*E$17/(1+$B18)^('DCF Model'!C19+4)-'DCF Model'!C16)*1000000/'DCF Model'!C15,0),"") -> 9175 | F18: =IFERROR(ROUND(('DCF Model'!C45/(1+$B18)^('DCF Model'!C19+0)+'DCF Model'!D45/(1+$B18)^('DCF Model'!C19+1)+'DCF Model'!E45/(1+$B18)^('DCF Model'!C19+2)+'DCF Model'!F45/(1+$B18)^('DCF Model'!C19+3)+'DCF Model'!G45/(1+$B18)^('DCF Model'!C19+4)+('DCF Model'!G39+'DCF Model'!G42)*F$17/(1+$B18)^('DCF Model'!C19+4)-'DCF Model'!C16)*1000000/'DCF Model'!C15,0),"") -> 9653 | G18: =IFERROR(ROUND(('DCF Model'!C45/(1+$B18)^('DCF Model'!C19+0)+'DCF Model'!D45/(1+$B18)^('DCF Model'!C19+1)+'DCF Model'!E45/(1+$B18)^('DCF Model'!C19+2)+'DCF Model'!F45/(1+$B18)^('DCF Model'!C19+3)+'DCF Model'!G45/(1+$B18)^('DCF Model'!C19+4)+('DCF Model'!G39+'DCF Model'!G42)*G$17/(1+$B18)^('DCF Model'!C19+4)-'DCF Model'!C16)*1000000/'DCF Model'!C15,0),"") -> 10132 | H18: =IFERROR(ROUND(('DCF Model'!C45/(1+$B18)^('DCF Model'!C19+0)+'DCF Model'!D45/(1+$B18)^('DCF Model'!C19+1)+'DCF Model'!E45/(1+$B18)^('DCF Model'!C19+2)+'DCF Model'!F45/(1+$B18)^('DCF Model'!C19+3)+'DCF Model'!G45/(1+$B18)^('DCF Model'!C19+4)+('DCF Model'!G39+'DCF Model'!G42)*H$17/(1+$B18)^('DCF Model'!C19+4)-'DCF Model'!C16)*1000000/'DCF Model'!C15,0),"") -> 10610 | I18: =IFERROR(ROUND(('DCF Model'!C45/(1+$B18)^('DCF Model'!C19+0)+'DCF Model'!D45/(1+$B18)^('DCF Model'!C19+1)+'DCF Model'!E45/(1+$B18)^('DCF Model'!C19+2)+'DCF Model'!F45/(1+$B18)^('DCF Model'!C19+3)+'DCF Model'!G45/(1+$B18)^('DCF Model'!C19+4)+('DCF Model'!G39+'DCF Model'!G42)*I$17/(1+$B18)^('DCF Model'!C19+4)-'DCF Model'!C16)*1000000/'DCF Model'!C15,0),"") -> 11089
B19: =$C$3-0.01 -> 0.0947 | C19: =IFERROR(ROUND(('DCF Model'!C45/(1+$B19)^('DCF Model'!C19+0)+'DCF Model'!D45/(1+$B19)^('DCF Model'!C19+1)+'DCF Model'!E45/(1+$B19)^('DCF Model'!C19+2)+'DCF Model'!F45/(1+$B19)^('DCF Model'!C19+3)+'DCF Model'!G45/(1+$B19)^('DCF Model'!C19+4)+('DCF Model'!G39+'DCF Model'!G42)*C$17/(1+$B19)^('DCF Model'!C19+4)-'DCF Model'!C16)*1000000/'DCF Model'!C15,0),"") -> 8083 | D19: =IFERROR(ROUND(('DCF Model'!C45/(1+$B19)^('DCF Model'!C19+0)+'DCF Model'!D45/(1+$B19)^('DCF Model'!C19+1)+'DCF Model'!E45/(1+$B19)^('DCF Model'!C19+2)+'DCF Model'!F45/(1+$B19)^('DCF Model'!C19+3)+'DCF Model'!G45/(1+$B19)^('DCF Model'!C19+4)+('DCF Model'!G39+'DCF Model'!G42)*D$17/(1+$B19)^('DCF Model'!C19+4)-'DCF Model'!C16)*1000000/'DCF Model'!C15,0),"") -> 8551 | E19: =IFERROR(ROUND(('DCF Model'!C45/(1+$B19)^('DCF Model'!C19+0)+'DCF Model'!D45/(1+$B19)^('DCF Model'!C19+1)+'DCF Model'!E45/(1+$B19)^('DCF Model'!C19+2)+'DCF Model'!F45/(1+$B19)^('DCF Model'!C19+3)+'DCF Model'!G45/(1+$B19)^('DCF Model'!C19+4)+('DCF Model'!G39+'DCF Model'!G42)*E$17/(1+$B19)^('DCF Model'!C19+4)-'DCF Model'!C16)*1000000/'DCF Model'!C15,0),"") -> 9018 | F19: =IFERROR(ROUND(('DCF Model'!C45/(1+$B19)^('DCF Model'!C19+0)+'DCF Model'!D45/(1+$B19)^('DCF Model'!C19+1)+'DCF Model'!E45/(1+$B19)^('DCF Model'!C19+2)+'DCF Model'!F45/(1+$B19)^('DCF Model'!C19+3)+'DCF Model'!G45/(1+$B19)^('DCF Model'!C19+4)+('DCF Model'!G39+'DCF Model'!G42)*F$17/(1+$B19)^('DCF Model'!C19+4)-'DCF Model'!C16)*1000000/'DCF Model'!C15,0),"") -> 9486 | G19: =IFERROR(ROUND(('DCF Model'!C45/(1+$B19)^('DCF Model'!C19+0)+'DCF Model'!D45/(1+$B19)^('DCF Model'!C19+1)+'DCF Model'!E45/(1+$B19)^('DCF Model'!C19+2)+'DCF Model'!F45/(1+$B19)^('DCF Model'!C19+3)+'DCF Model'!G45/(1+$B19)^('DCF Model'!C19+4)+('DCF Model'!G39+'DCF Model'!G42)*G$17/(1+$B19)^('DCF Model'!C19+4)-'DCF Model'!C16)*1000000/'DCF Model'!C15,0),"") -> 9954 | H19: =IFERROR(ROUND(('DCF Model'!C45/(1+$B19)^('DCF Model'!C19+0)+'DCF Model'!D45/(1+$B19)^('DCF Model'!C19+1)+'DCF Model'!E45/(1+$B19)^('DCF Model'!C19+2)+'DCF Model'!F45/(1+$B19)^('DCF Model'!C19+3)+'DCF Model'!G45/(1+$B19)^('DCF Model'!C19+4)+('DCF Model'!G39+'DCF Model'!G42)*H$17/(1+$B19)^('DCF Model'!C19+4)-'DCF Model'!C16)*1000000/'DCF Model'!C15,0),"") -> 10421 | I19: =IFERROR(ROUND(('DCF Model'!C45/(1+$B19)^('DCF Model'!C19+0)+'DCF Model'!D45/(1+$B19)^('DCF Model'!C19+1)+'DCF Model'!E45/(1+$B19)^('DCF Model'!C19+2)+'DCF Model'!F45/(1+$B19)^('DCF Model'!C19+3)+'DCF Model'!G45/(1+$B19)^('DCF Model'!C19+4)+('DCF Model'!G39+'DCF Model'!G42)*I$17/(1+$B19)^('DCF Model'!C19+4)-'DCF Model'!C16)*1000000/'DCF Model'!C15,0),"") -> 10889
B20: =$C$3-0.005 -> 0.0997 | C20: =IFERROR(ROUND(('DCF Model'!C45/(1+$B20)^('DCF Model'!C19+0)+'DCF Model'!D45/(1+$B20)^('DCF Model'!C19+1)+'DCF Model'!E45/(1+$B20)^('DCF Model'!C19+2)+'DCF Model'!F45/(1+$B20)^('DCF Model'!C19+3)+'DCF Model'!G45/(1+$B20)^('DCF Model'!C19+4)+('DCF Model'!G39+'DCF Model'!G42)*C$17/(1+$B20)^('DCF Model'!C19+4)-'DCF Model'!C16)*1000000/'DCF Model'!C15,0),"") -> 7952 | D20: =IFERROR(ROUND(('DCF Model'!C45/(1+$B20)^('DCF Model'!C19+0)+'DCF Model'!D45/(1+$B20)^('DCF Model'!C19+1)+'DCF Model'!E45/(1+$B20)^('DCF Model'!C19+2)+'DCF Model'!F45/(1+$B20)^('DCF Model'!C19+3)+'DCF Model'!G45/(1+$B20)^('DCF Model'!C19+4)+('DCF Model'!G39+'DCF Model'!G42)*D$17/(1+$B20)^('DCF Model'!C19+4)-'DCF Model'!C16)*1000000/'DCF Model'!C15,0),"") -> 8409 | E20: =IFERROR(ROUND(('DCF Model'!C45/(1+$B20)^('DCF Model'!C19+0)+'DCF Model'!D45/(1+$B20)^('DCF Model'!C19+1)+'DCF Model'!E45/(1+$B20)^('DCF Model'!C19+2)+'DCF Model'!F45/(1+$B20)^('DCF Model'!C19+3)+'DCF Model'!G45/(1+$B20)^('DCF Model'!C19+4)+('DCF Model'!G39+'DCF Model'!G42)*E$17/(1+$B20)^('DCF Model'!C19+4)-'DCF Model'!C16)*1000000/'DCF Model'!C15,0),"") -> 8866 | F20: =IFERROR(ROUND(('DCF Model'!C45/(1+$B20)^('DCF Model'!C19+0)+'DCF Model'!D45/(1+$B20)^('DCF Model'!C19+1)+'DCF Model'!E45/(1+$B20)^('DCF Model'!C19+2)+'DCF Model'!F45/(1+$B20)^('DCF Model'!C19+3)+'DCF Model'!G45/(1+$B20)^('DCF Model'!C19+4)+('DCF Model'!G39+'DCF Model'!G42)*F$17/(1+$B20)^('DCF Model'!C19+4)-'DCF Model'!C16)*1000000/'DCF Model'!C15,0),"") -> 9323 | G20: =IFERROR(ROUND(('DCF Model'!C45/(1+$B20)^('DCF Model'!C19+0)+'DCF Model'!D45/(1+$B20)^('DCF Model'!C19+1)+'DCF Model'!E45/(1+$B20)^('DCF Model'!C19+2)+'DCF Model'!F45/(1+$B20)^('DCF Model'!C19+3)+'DCF Model'!G45/(1+$B20)^('DCF Model'!C19+4)+('DCF Model'!G39+'DCF Model'!G42)*G$17/(1+$B20)^('DCF Model'!C19+4)-'DCF Model'!C16)*1000000/'DCF Model'!C15,0),"") -> 9780 | H20: =IFERROR(ROUND(('DCF Model'!C45/(1+$B20)^('DCF Model'!C19+0)+'DCF Model'!D45/(1+$B20)^('DCF Model'!C19+1)+'DCF Model'!E45/(1+$B20)^('DCF Model'!C19+2)+'DCF Model'!F45/(1+$B20)^('DCF Model'!C19+3)+'DCF Model'!G45/(1+$B20)^('DCF Model'!C19+4)+('DCF Model'!G39+'DCF Model'!G42)*H$17/(1+$B20)^('DCF Model'!C19+4)-'DCF Model'!C16)*1000000/'DCF Model'!C15,0),"") -> 10237 | I20: =IFERROR(ROUND(('DCF Model'!C45/(1+$B20)^('DCF Model'!C19+0)+'DCF Model'!D45/(1+$B20)^('DCF Model'!C19+1)+'DCF Model'!E45/(1+$B20)^('DCF Model'!C19+2)+'DCF Model'!F45/(1+$B20)^('DCF Model'!C19+3)+'DCF Model'!G45/(1+$B20)^('DCF Model'!C19+4)+('DCF Model'!G39+'DCF Model'!G42)*I$17/(1+$B20)^('DCF Model'!C19+4)-'DCF Model'!C16)*1000000/'DCF Model'!C15,0),"") -> 10694
B21: =$C$3 -> 0.1047 | C21: =IFERROR(ROUND(('DCF Model'!C45/(1+$B21)^('DCF Model'!C19+0)+'DCF Model'!D45/(1+$B21)^('DCF Model'!C19+1)+'DCF Model'!E45/(1+$B21)^('DCF Model'!C19+2)+'DCF Model'!F45/(1+$B21)^('DCF Model'!C19+3)+'DCF Model'!G45/(1+$B21)^('DCF Model'!C19+4)+('DCF Model'!G39+'DCF Model'!G42)*C$17/(1+$B21)^('DCF Model'!C19+4)-'DCF Model'!C16)*1000000/'DCF Model'!C15,0),"") -> 7824 | D21: =IFERROR(ROUND(('DCF Model'!C45/(1+$B21)^('DCF Model'!C19+0)+'DCF Model'!D45/(1+$B21)^('DCF Model'!C19+1)+'DCF Model'!E45/(1+$B21)^('DCF Model'!C19+2)+'DCF Model'!F45/(1+$B21)^('DCF Model'!C19+3)+'DCF Model'!G45/(1+$B21)^('DCF Model'!C19+4)+('DCF Model'!G39+'DCF Model'!G42)*D$17/(1+$B21)^('DCF Model'!C19+4)-'DCF Model'!C16)*1000000/'DCF Model'!C15,0),"") -> 8271 | E21: =IFERROR(ROUND(('DCF Model'!C45/(1+$B21)^('DCF Model'!C19+0)+'DCF Model'!D45/(1+$B21)^('DCF Model'!C19+1)+'DCF Model'!E45/(1+$B21)^('DCF Model'!C19+2)+'DCF Model'!F45/(1+$B21)^('DCF Model'!C19+3)+'DCF Model'!G45/(1+$B21)^('DCF Model'!C19+4)+('DCF Model'!G39+'DCF Model'!G42)*E$17/(1+$B21)^('DCF Model'!C19+4)-'DCF Model'!C16)*1000000/'DCF Model'!C15,0),"") -> 8717 | F21: =IFERROR(ROUND(('DCF Model'!C45/(1+$B21)^('DCF Model'!C19+0)+'DCF Model'!D45/(1+$B21)^('DCF Model'!C19+1)+'DCF Model'!E45/(1+$B21)^('DCF Model'!C19+2)+'DCF Model'!F45/(1+$B21)^('DCF Model'!C19+3)+'DCF Model'!G45/(1+$B21)^('DCF Model'!C19+4)+('DCF Model'!G39+'DCF Model'!G42)*F$17/(1+$B21)^('DCF Model'!C19+4)-'DCF Model'!C16)*1000000/'DCF Model'!C15,0),"") -> 9164 | G21: =IFERROR(ROUND(('DCF Model'!C45/(1+$B21)^('DCF Model'!C19+0)+'DCF Model'!D45/(1+$B21)^('DCF Model'!C19+1)+'DCF Model'!E45/(1+$B21)^('DCF Model'!C19+2)+'DCF Model'!F45/(1+$B21)^('DCF Model'!C19+3)+'DCF Model'!G45/(1+$B21)^('DCF Model'!C19+4)+('DCF Model'!G39+'DCF Model'!G42)*G$17/(1+$B21)^('DCF Model'!C19+4)-'DCF Model'!C16)*1000000/'DCF Model'!C15,0),"") -> 9611 | H21: =IFERROR(ROUND(('DCF Model'!C45/(1+$B21)^('DCF Model'!C19+0)+'DCF Model'!D45/(1+$B21)^('DCF Model'!C19+1)+'DCF Model'!E45/(1+$B21)^('DCF Model'!C19+2)+'DCF Model'!F45/(1+$B21)^('DCF Model'!C19+3)+'DCF Model'!G45/(1+$B21)^('DCF Model'!C19+4)+('DCF Model'!G39+'DCF Model'!G42)*H$17/(1+$B21)^('DCF Model'!C19+4)-'DCF Model'!C16)*1000000/'DCF Model'!C15,0),"") -> 10058 | I21: =IFERROR(ROUND(('DCF Model'!C45/(1+$B21)^('DCF Model'!C19+0)+'DCF Model'!D45/(1+$B21)^('DCF Model'!C19+1)+'DCF Model'!E45/(1+$B21)^('DCF Model'!C19+2)+'DCF Model'!F45/(1+$B21)^('DCF Model'!C19+3)+'DCF Model'!G45/(1+$B21)^('DCF Model'!C19+4)+('DCF Model'!G39+'DCF Model'!G42)*I$17/(1+$B21)^('DCF Model'!C19+4)-'DCF Model'!C16)*1000000/'DCF Model'!C15,0),"") -> 10505
B22: =$C$3+0.005 -> 0.1097 | C22: =IFERROR(ROUND(('DCF Model'!C45/(1+$B22)^('DCF Model'!C19+0)+'DCF Model'!D45/(1+$B22)^('DCF Model'!C19+1)+'DCF Model'!E45/(1+$B22)^('DCF Model'!C19+2)+'DCF Model'!F45/(1+$B22)^('DCF Model'!C19+3)+'DCF Model'!G45/(1+$B22)^('DCF Model'!C19+4)+('DCF Model'!G39+'DCF Model'!G42)*C$17/(1+$B22)^('DCF Model'!C19+4)-'DCF Model'!C16)*1000000/'DCF Model'!C15,0),"") -> 7699 | D22: =IFERROR(ROUND(('DCF Model'!C45/(1+$B22)^('DCF Model'!C19+0)+'DCF Model'!D45/(1+$B22)^('DCF Model'!C19+1)+'DCF Model'!E45/(1+$B22)^('DCF Model'!C19+2)+'DCF Model'!F45/(1+$B22)^('DCF Model'!C19+3)+'DCF Model'!G45/(1+$B22)^('DCF Model'!C19+4)+('DCF Model'!G39+'DCF Model'!G42)*D$17/(1+$B22)^('DCF Model'!C19+4)-'DCF Model'!C16)*1000000/'DCF Model'!C15,0),"") -> 8136 | E22: =IFERROR(ROUND(('DCF Model'!C45/(1+$B22)^('DCF Model'!C19+0)+'DCF Model'!D45/(1+$B22)^('DCF Model'!C19+1)+'DCF Model'!E45/(1+$B22)^('DCF Model'!C19+2)+'DCF Model'!F45/(1+$B22)^('DCF Model'!C19+3)+'DCF Model'!G45/(1+$B22)^('DCF Model'!C19+4)+('DCF Model'!G39+'DCF Model'!G42)*E$17/(1+$B22)^('DCF Model'!C19+4)-'DCF Model'!C16)*1000000/'DCF Model'!C15,0),"") -> 8573 | F22: =IFERROR(ROUND(('DCF Model'!C45/(1+$B22)^('DCF Model'!C19+0)+'DCF Model'!D45/(1+$B22)^('DCF Model'!C19+1)+'DCF Model'!E45/(1+$B22)^('DCF Model'!C19+2)+'DCF Model'!F45/(1+$B22)^('DCF Model'!C19+3)+'DCF Model'!G45/(1+$B22)^('DCF Model'!C19+4)+('DCF Model'!G39+'DCF Model'!G42)*F$17/(1+$B22)^('DCF Model'!C19+4)-'DCF Model'!C16)*1000000/'DCF Model'!C15,0),"") -> 9010 | G22: =IFERROR(ROUND(('DCF Model'!C45/(1+$B22)^('DCF Model'!C19+0)+'DCF Model'!D45/(1+$B22)^('DCF Model'!C19+1)+'DCF Model'!E45/(1+$B22)^('DCF Model'!C19+2)+'DCF Model'!F45/(1+$B22)^('DCF Model'!C19+3)+'DCF Model'!G45/(1+$B22)^('DCF Model'!C19+4)+('DCF Model'!G39+'DCF Model'!G42)*G$17/(1+$B22)^('DCF Model'!C19+4)-'DCF Model'!C16)*1000000/'DCF Model'!C15,0),"") -> 9446 | H22: =IFERROR(ROUND(('DCF Model'!C45/(1+$B22)^('DCF Model'!C19+0)+'DCF Model'!D45/(1+$B22)^('DCF Model'!C19+1)+'DCF Model'!E45/(1+$B22)^('DCF Model'!C19+2)+'DCF Model'!F45/(1+$B22)^('DCF Model'!C19+3)+'DCF Model'!G45/(1+$B22)^('DCF Model'!C19+4)+('DCF Model'!G39+'DCF Model'!G42)*H$17/(1+$B22)^('DCF Model'!C19+4)-'DCF Model'!C16)*1000000/'DCF Model'!C15,0),"") -> 9883 | I22: =IFERROR(ROUND(('DCF Model'!C45/(1+$B22)^('DCF Model'!C19+0)+'DCF Model'!D45/(1+$B22)^('DCF Model'!C19+1)+'DCF Model'!E45/(1+$B22)^('DCF Model'!C19+2)+'DCF Model'!F45/(1+$B22)^('DCF Model'!C19+3)+'DCF Model'!G45/(1+$B22)^('DCF Model'!C19+4)+('DCF Model'!G39+'DCF Model'!G42)*I$17/(1+$B22)^('DCF Model'!C19+4)-'DCF Model'!C16)*1000000/'DCF Model'!C15,0),"") -> 10320
B23: =$C$3+0.01 -> 0.1147 | C23: =IFERROR(ROUND(('DCF Model'!C45/(1+$B23)^('DCF Model'!C19+0)+'DCF Model'!D45/(1+$B23)^('DCF Model'!C19+1)+'DCF Model'!E45/(1+$B23)^('DCF Model'!C19+2)+'DCF Model'!F45/(1+$B23)^('DCF Model'!C19+3)+'DCF Model'!G45/(1+$B23)^('DCF Model'!C19+4)+('DCF Model'!G39+'DCF Model'!G42)*C$17/(1+$B23)^('DCF Model'!C19+4)-'DCF Model'!C16)*1000000/'DCF Model'!C15,0),"") -> 7578 | D23: =IFERROR(ROUND(('DCF Model'!C45/(1+$B23)^('DCF Model'!C19+0)+'DCF Model'!D45/(1+$B23)^('DCF Model'!C19+1)+'DCF Model'!E45/(1+$B23)^('DCF Model'!C19+2)+'DCF Model'!F45/(1+$B23)^('DCF Model'!C19+3)+'DCF Model'!G45/(1+$B23)^('DCF Model'!C19+4)+('DCF Model'!G39+'DCF Model'!G42)*D$17/(1+$B23)^('DCF Model'!C19+4)-'DCF Model'!C16)*1000000/'DCF Model'!C15,0),"") -> 8005 | E23: =IFERROR(ROUND(('DCF Model'!C45/(1+$B23)^('DCF Model'!C19+0)+'DCF Model'!D45/(1+$B23)^('DCF Model'!C19+1)+'DCF Model'!E45/(1+$B23)^('DCF Model'!C19+2)+'DCF Model'!F45/(1+$B23)^('DCF Model'!C19+3)+'DCF Model'!G45/(1+$B23)^('DCF Model'!C19+4)+('DCF Model'!G39+'DCF Model'!G42)*E$17/(1+$B23)^('DCF Model'!C19+4)-'DCF Model'!C16)*1000000/'DCF Model'!C15,0),"") -> 8432 | F23: =IFERROR(ROUND(('DCF Model'!C45/(1+$B23)^('DCF Model'!C19+0)+'DCF Model'!D45/(1+$B23)^('DCF Model'!C19+1)+'DCF Model'!E45/(1+$B23)^('DCF Model'!C19+2)+'DCF Model'!F45/(1+$B23)^('DCF Model'!C19+3)+'DCF Model'!G45/(1+$B23)^('DCF Model'!C19+4)+('DCF Model'!G39+'DCF Model'!G42)*F$17/(1+$B23)^('DCF Model'!C19+4)-'DCF Model'!C16)*1000000/'DCF Model'!C15,0),"") -> 8859 | G23: =IFERROR(ROUND(('DCF Model'!C45/(1+$B23)^('DCF Model'!C19+0)+'DCF Model'!D45/(1+$B23)^('DCF Model'!C19+1)+'DCF Model'!E45/(1+$B23)^('DCF Model'!C19+2)+'DCF Model'!F45/(1+$B23)^('DCF Model'!C19+3)+'DCF Model'!G45/(1+$B23)^('DCF Model'!C19+4)+('DCF Model'!G39+'DCF Model'!G42)*G$17/(1+$B23)^('DCF Model'!C19+4)-'DCF Model'!C16)*1000000/'DCF Model'!C15,0),"") -> 9286 | H23: =IFERROR(ROUND(('DCF Model'!C45/(1+$B23)^('DCF Model'!C19+0)+'DCF Model'!D45/(1+$B23)^('DCF Model'!C19+1)+'DCF Model'!E45/(1+$B23)^('DCF Model'!C19+2)+'DCF Model'!F45/(1+$B23)^('DCF Model'!C19+3)+'DCF Model'!G45/(1+$B23)^('DCF Model'!C19+4)+('DCF Model'!G39+'DCF Model'!G42)*H$17/(1+$B23)^('DCF Model'!C19+4)-'DCF Model'!C16)*1000000/'DCF Model'!C15,0),"") -> 9713 | I23: =IFERROR(ROUND(('DCF Model'!C45/(1+$B23)^('DCF Model'!C19+0)+'DCF Model'!D45/(1+$B23)^('DCF Model'!C19+1)+'DCF Model'!E45/(1+$B23)^('DCF Model'!C19+2)+'DCF Model'!F45/(1+$B23)^('DCF Model'!C19+3)+'DCF Model'!G45/(1+$B23)^('DCF Model'!C19+4)+('DCF Model'!G39+'DCF Model'!G42)*I$17/(1+$B23)^('DCF Model'!C19+4)-'DCF Model'!C16)*1000000/'DCF Model'!C15,0),"") -> 10140
B24: =$C$3+0.015 -> 0.1197 | C24: =IFERROR(ROUND(('DCF Model'!C45/(1+$B24)^('DCF Model'!C19+0)+'DCF Model'!D45/(1+$B24)^('DCF Model'!C19+1)+'DCF Model'!E45/(1+$B24)^('DCF Model'!C19+2)+'DCF Model'!F45/(1+$B24)^('DCF Model'!C19+3)+'DCF Model'!G45/(1+$B24)^('DCF Model'!C19+4)+('DCF Model'!G39+'DCF Model'!G42)*C$17/(1+$B24)^('DCF Model'!C19+4)-'DCF Model'!C16)*1000000/'DCF Model'!C15,0),"") -> 7459 | D24: =IFERROR(ROUND(('DCF Model'!C45/(1+$B24)^('DCF Model'!C19+0)+'DCF Model'!D45/(1+$B24)^('DCF Model'!C19+1)+'DCF Model'!E45/(1+$B24)^('DCF Model'!C19+2)+'DCF Model'!F45/(1+$B24)^('DCF Model'!C19+3)+'DCF Model'!G45/(1+$B24)^('DCF Model'!C19+4)+('DCF Model'!G39+'DCF Model'!G42)*D$17/(1+$B24)^('DCF Model'!C19+4)-'DCF Model'!C16)*1000000/'DCF Model'!C15,0),"") -> 7877 | E24: =IFERROR(ROUND(('DCF Model'!C45/(1+$B24)^('DCF Model'!C19+0)+'DCF Model'!D45/(1+$B24)^('DCF Model'!C19+1)+'DCF Model'!E45/(1+$B24)^('DCF Model'!C19+2)+'DCF Model'!F45/(1+$B24)^('DCF Model'!C19+3)+'DCF Model'!G45/(1+$B24)^('DCF Model'!C19+4)+('DCF Model'!G39+'DCF Model'!G42)*E$17/(1+$B24)^('DCF Model'!C19+4)-'DCF Model'!C16)*1000000/'DCF Model'!C15,0),"") -> 8294 | F24: =IFERROR(ROUND(('DCF Model'!C45/(1+$B24)^('DCF Model'!C19+0)+'DCF Model'!D45/(1+$B24)^('DCF Model'!C19+1)+'DCF Model'!E45/(1+$B24)^('DCF Model'!C19+2)+'DCF Model'!F45/(1+$B24)^('DCF Model'!C19+3)+'DCF Model'!G45/(1+$B24)^('DCF Model'!C19+4)+('DCF Model'!G39+'DCF Model'!G42)*F$17/(1+$B24)^('DCF Model'!C19+4)-'DCF Model'!C16)*1000000/'DCF Model'!C15,0),"") -> 8712 | G24: =IFERROR(ROUND(('DCF Model'!C45/(1+$B24)^('DCF Model'!C19+0)+'DCF Model'!D45/(1+$B24)^('DCF Model'!C19+1)+'DCF Model'!E45/(1+$B24)^('DCF Model'!C19+2)+'DCF Model'!F45/(1+$B24)^('DCF Model'!C19+3)+'DCF Model'!G45/(1+$B24)^('DCF Model'!C19+4)+('DCF Model'!G39+'DCF Model'!G42)*G$17/(1+$B24)^('DCF Model'!C19+4)-'DCF Model'!C16)*1000000/'DCF Model'!C15,0),"") -> 9130 | H24: =IFERROR(ROUND(('DCF Model'!C45/(1+$B24)^('DCF Model'!C19+0)+'DCF Model'!D45/(1+$B24)^('DCF Model'!C19+1)+'DCF Model'!E45/(1+$B24)^('DCF Model'!C19+2)+'DCF Model'!F45/(1+$B24)^('DCF Model'!C19+3)+'DCF Model'!G45/(1+$B24)^('DCF Model'!C19+4)+('DCF Model'!G39+'DCF Model'!G42)*H$17/(1+$B24)^('DCF Model'!C19+4)-'DCF Model'!C16)*1000000/'DCF Model'!C15,0),"") -> 9548 | I24: =IFERROR(ROUND(('DCF Model'!C45/(1+$B24)^('DCF Model'!C19+0)+'DCF Model'!D45/(1+$B24)^('DCF Model'!C19+1)+'DCF Model'!E45/(1+$B24)^('DCF Model'!C19+2)+'DCF Model'!F45/(1+$B24)^('DCF Model'!C19+3)+'DCF Model'!G45/(1+$B24)^('DCF Model'!C19+4)+('DCF Model'!G39+'DCF Model'!G42)*I$17/(1+$B24)^('DCF Model'!C19+4)-'DCF Model'!C16)*1000000/'DCF Model'!C15,0),"") -> 9965
B26: All values dynamically linked to DCF Model. Headers auto-center on current WACC / Terminal g / Exit Multiple.

Sheet Adjustments Log
B2: Adjustments Log - 任天堂
B4: 日付 | C4: セル | D4: 変更内容 | E4: 理由 | F4: 元の値 | G4: 状態
B5: 2026-09-06 | C5: - | D5: Generated by pipeline on 2026-09-06 01:34, template rev c9b5dd9 | E5: 初期生成（手修正なし） | F5: - | G5: generated
B6: 2026-09-05 | C6: DCF Model!C7 | D6: Risk-Free Rate = 2.97% | E6: 財務省 国債金利情報 jgbcm.csv の10年物 R8.9.3(2026-09-03) 2.966% を四捨五入。バッチ全銘柄共通の一次ソース。yfinanceは日本国債利回りを返さないため使用しない。 | F6: テンプレ既定 2.2% | G6: 確定
B7: 2026-09-05 | C7: DCF Model!C9 | D7: Equity Risk Premium = 6.5% | E7: バッチ共通の固定前提(§1-3)。銘柄固有の調整なし。 | F7: テンプレ既定 6.5%(同値) | G7: 設計判断
B8: 2026-09-05 | C8: DCF Model!C10 | D8: Size Premium = 1.0% | E8: 時価総額バンドによる機械決定(>3,000億円 -> 1.0%)。当社時価総額 10,190,200百万円。■テンプレートの自動規則(>=1兆円 -> 0.0%)とは異なる値で、明示指定により上書きしている。WACCを1.0pt押し上げる。 | F8: テンプレ自動値 0.0% | G8: 設計判断
B9: 2026-09-05 | C9: DCF Model!C8 | D9: Beta = 1.00 | E9: yfinance が当社の beta を返さない(null)。テンプレのフォールバック値 1.0 を明示的に採用した。実測値ではなく推定である。■低ベータの同業(9697 カプコン 0.49 / 7832 バンダイナムコ 0.11)と比べると保守的(WACCを高く見積もる方向)。 | F9: - | G9: 推定(要確認)
B10: 2026-09-05 | C10: DCF Model!C6 | D10: Effective Tax Rate = 25% | E10: バッチ共通の既定値(§1-3)。当社の実績税負担率を個別検証したものではない。 | F10: テンプレ既定 30% | G10: 推定
B11: 2026-09-05 | C11: DCF Model!C11 | D11: After-tax Cost of Debt = 1.0%(テンプレ既定値のまま) | E11: 当社は有利子負債ゼロ・ネットキャッシュ(net_debt −1,791,802百万円)で D/E=0 のため、負債コストはWACCに一切寄与しない(WACC = Ke = 10.47%)。実績Kdの算出は無意味なので interest_expense を指定していない。 | F11: テンプレ既定 | G11: 設計判断
B12: 2026-09-05 | C12: DCF Model!C13 | D12: Terminal Growth = 1.0% | E12: バッチ共通の固定前提(§1-3)。 | F12: テンプレ既定 2.0% | G12: 設計判断
B13: 2026-09-05 | C13: DCF Model!C14 | D13: Exit Multiple (EV/EBITDA) = 13.2x | E13: Peer 5社の実測EV/EBITDA中央値 13.17x(7832 13.17 / 9766 15.44 / 9697 20.30 / 9684 12.08 / 6758 8.10)。型Bのため §4-4 により Peer中央値が上限だが、本ルールは中央値そのものを採るため上限は binding しない。自社の現在倍率 22.34x は算式に入れていない(市場価格への循環参照回避)。 | F13: テンプレ既定 10.0x | G13: 設計判断
B14: 2026-09-05 | C14: DCF Model!C16 | D14: Net Debt = −1,791,802百万円(ネットキャッシュ) | E14: 型A定義: 有利子負債 0 − 現金及び現金同等物 1,791,802。■有利子負債ゼロは抽出漏れではなく事実(EDINET側 Debt 0/6、yfinance にも Total Debt 行が存在しない)。■保守的な定義: 短期有価証券(定期預金等)は現金及び現金同等物に含まれないためネットキャッシュから除外している。含めればネットキャッシュは拡大し株式価値は上振れる。 | F14: - | G14: 設計判断
B15: 2026-09-05 | C15: DCF Model!C15 | D15: Fully Diluted Shares = 1,152,873,205株 | E15: yfinance sharesOutstanding(自己株控除後)。時価総額 10,190,200百万円 ÷ 株価 8,839円 = 1,152,873,205 と整合。■EDINET有報(docID S100Y9NX)による発行済−自己株の独立検算は本バッチでは未実施。 | F15: - | G15: 要確認(EDINET側の自己株控除検算 未実施)
... B26: 2026-09-05 | C26: 全体(未解決) | D26: 逆算DCF(Block F)が示すギャップ | E26: 現値 8,839円は定常営業利益 1,235,786百万円(FY2021サイクルピーク 640,634百万の1.93倍)を5年で達成し永続することを織り込んだ水準。実績FY2026 は 360,117百万。ミッドサイクル前提の Base が支える EV は 5,896,857百万円にとどまり、1株2,170円が説明できない。Switch 2 サイクルのピーク利益をどこに置くか(Base の Y5 OPM 27.9% が保守的すぎないか)は人間の判断を要する。 | F26: - | G26: 未解決
B28: Pipeline Metadata (do not edit — read by scripts/validate_output.py)
B29: key | C29: value
B30: auto_log_entries | C30: 0
B31: capex_pct_basis | C31: assumption
B32: capex_pct_c5 | C32: 0.0095
B33: capex_pct_hist3yr | C33: n/a
B34: company_name | C34: 任天堂
B35: comps_asof | C35: 2026-09-06
B36: comps_da_missing | C36: none
B37: comps_ev_ebitda_invalid | C37: no
B38: comps_ev_ebitda_rows | C38: 6,7,8,9,10
B39: comps_impl_mult_row | C39: 27
B40: comps_impl_per_row | C40: 28
... B62: ticker | C62: 7974.T
