Workbook

Sheet Executive Summary
B1: DISCLAIMER: This is a sample analysis for demonstration purposes only. It does not constitute investment advice.
B3: イオン株式会社 (8267.T)
B4: Equity Research Report
B6: Company | C6: イオン株式会社
B7: Ticker | C7: 8267.T (TSE)
B8: Sector | C8: Retail holding company (GMS/SM/drugstore/mall/finance/services)
B9: Current Price | C9: 1424
B10: Target Price (Mid) - excl. invalid PGM | C10: =ROUND(AVERAGE(C17:C19),0) -> 652
B11: Recommendation | C11: =IF(C12>0.15,"BUY",IF(C12>0.05,"HOLD","SELL")) -> SELL
B12: Upside / Downside | C12: =(C10-C9)/C9 -> -0.54213483
B13: NOTE: the Perpetuity Growth method returns a negative equity value and is EXCLUDED from the Target Price and the range. Cause: Year-5 capex of 545,000 is 1.22x Year-5 D&A of 445,000, so terminal free cash flow is only 157,320 and the resulting enterprise value (3,618,133) sits below net debt plus minority interests (4,083,263). Terminal capex must converge toward D&A when perpetual growth is 0.5%. Normalising Year-5 capex gives: 500,000 -> 182/share, 470,000 -> 416/share, 445,000 (= D&A) -> 611/share, the last of which is consistent with the Exit method at 657. The capex projections in rows 43 of the DCF sheet have NOT been changed - that is a forecast decision.
B14: Valuation Summary
B15: Methodology | C15: Implied Value (JPY) | D15: vs Current Price
B16: DCF - Perpetuity Growth (INVALID - see note) | C16: ='DCF Model'!C55 -> -168 | D16: =(C16-C9)/C9 -> -1.1179775
B17: DCF - Exit Multiple | C17: ='DCF Model'!C64 -> 657 | D17: =(C17-C9)/C9 -> -0.5386236
B18: Comps - EV/EBITDA Median | C18: ='Comps Analysis'!C27 -> 772 | D18: =IF(ISNUMBER(C18),(C18-C9)/C9,"N/A") -> -0.45786517
B19: Comps - PER Median | C19: ='Comps Analysis'!C28 -> 527 | D19: =IF(ISNUMBER(C19),(C19-C9)/C9,"N/A") -> -0.62991573
B21: Integrated Valuation Range | C21: =MIN(C17:C19)&" - "&MAX(C17:C19) -> 527 - 772
B23: Key Investment Thesis
B24: 1. Operating profit is compounding but almost none of it reaches the parent. Operating income rose from 209,783 (FY2023/2) to 270,459 (FY2026/2) and is guided to 340,000 in FY2027/2 (+25.7%), yet guided parent net income is 73,000, up just 0.4%. Non-controlling interests took 51,858 of the 124,536 consolidated net income in FY2026/2. The investment case is entirely about whether Aeon can convert consolidated growth into parent-level value.
B25: 2. Drug-store consolidation is reshaping the group. The Tsuruha integration drove a 69,086 step-acquisition gain in FY2026/2 and underpins the guided 12.0% revenue jump to 12,000,000. Health & Wellness is now the growth engine alongside the developer business.
B26: 3. Low cost of capital supports a long-duration asset base. Interest expense of 51,376 on average interest-bearing debt of 4,140,937 is a 1.24% pre-tax cost, giving a WACC near 4.4%. For a business with 3,941,556 of property and 1,138,073 of land, cheap long-term funding is a genuine structural advantage.
B28: Key Risks
B29: 1. Minority interests are 984,094 at book, or 356 per share against a 1,424 price. Because the listed subsidiaries trade above book, the true economic deduction is larger than the balance sheet figure. Any consolidated valuation that omits this overstates the equity by more than a quarter.
B30: 2. Valuation already prices in the improvement. At 1,424 the shares trade at 3.23x book, 54.2x parent earnings and 12.29x consolidated EBITDA on a 2.52% operating margin. A retailer at 12.3x EBITDA leaves no room for the margin recovery to disappoint.
B31: 3. Impairment and leverage. FY2026/2 booked 97,486 of impairment losses with 270,803 of goodwill still on the balance sheet, and the effective tax rate has run 40-57% because much of that charge is not deductible. Interest-bearing debt of 4,449,206 against 1,218,421 of owners' equity means a small move in funding costs moves the WACC and the terminal value materially.

Sheet Financial Statements
B2: イオン株式会社 - Historical Financials (JPY mn)
C4: FY2023/2 | D4: FY2024/2 | E4: FY2025/2 | F4: FY2026/2
B5: Income Statement
B6: Revenue | C6: 9116823 | D6: 9553557 | E6: 10134877 | F6: 10715342
B7: COGS | C7: 5778894 | D7: 6007745 | E7: 6380141 | F7: 6804966
B8: Gross Profit | C8: =C6-C7 -> 3337929 | D8: =D6-D7 -> 3545812 | E8: =E6-E7 -> 3754736 | F8: =F6-F7 -> 3910376
B9: Gross Margin | C9: =C8/C6 -> 0.36612853 | D9: =D8/D6 -> 0.37115098 | E9: =E8/E6 -> 0.37047672 | F9: =F8/F6 -> 0.36493245
B10: SGA | C10: 3128145 | D10: 3294989 | E10: 3516989 | F10: 3639916
B11: Operating Income | C11: 209783 | D11: 250822 | E11: 237747 | F11: 270459
B12: Net Income | C12: 21381 | D12: 44692 | E12: 27168 | F12: 72677
B13: Operating Margin | C13: =C11/C6 -> 0.023010538 | D13: =D11/D6 -> 0.026254305 | E13: =E11/E6 -> 0.023458301 | F13: =F11/F6 -> 0.025240352
B14: Net Margin | C14: =C12/C6 -> 0.0023452249 | D14: =D12/D6 -> 0.0046780482 | E14: =E12/E6 -> 0.0026806443 | F14: =F12/F6 -> 0.006782518
B15: Revenue Growth (YoY) | C15: n/a | D15: =(D6-C6)/C6 -> 0.047904188 | E15: =(E6-D6)/D6 -> 0.06084854 | F15: =(F6-E6)/E6 -> 0.057274005
B16: Operating Income Growth (YoY) | C16: n/a | D16: =(D11-C11)/C11 -> 0.19562596 | E16: =(E11-D11)/D11 -> -0.052128601 | F16: =(F11-E11)/E11 -> 0.13759164
B18: Cash Flow Statement
B19: Operating Cash Flow (incl. bank flows) | C19: 433710 | D19: 368487 | E19: 566218 | F19: 1126589
B20: Capex (固定資産の取得) | C20: 370848 | D20: 396236 | E20: 465958 | F20: 528536
B21: Free Cash Flow (incl. bank flows) | C21: =C19-C20 -> 62862 | D21: =D19-D20 -> -27749 | E21: =E19-E20 -> 100260 | F21: =F19-F20 -> 598053
B22: FCF Margin (incl. bank flows) | C22: =C21/C6 -> 0.0068951651 | D22: =D21/D6 -> -0.0029045726 | E22: =E21/E6 -> 0.009892572 | F22: =F21/F6 -> 0.055812778
B23: Capex / Revenue | C23: =C20/C6 -> 0.040677328 | D23: =D20/D6 -> 0.041475233 | E23: =E20/E6 -> 0.045975694 | F23: =F20/F6 -> 0.049325164
B25: Balance Sheet Highlights
B26: Cash & Deposits (現金及び預金) | C26: 1309725 | D26: 1165536 | E26: 1258383 | F26: 1350037
B27: Interest-Bearing Debt (excl. bank deposits) | C27: 3465146 | D27: 3700013 | E27: 3832668 | F27: 4449206
B28: Net Debt - financial only (excl. MI) | C28: =C27-C26 -> 2155421 | D28: =D27-D26 -> 2534477 | E28: =E27-E26 -> 2574285 | F28: =F27-F26 -> 3099169
B30: Source: 決算短信 FY2024/2 and FY2026/2. Operating Cash Flow and Capex (固定資産の取得による支出) from the 連結キャッシュ・フロー計算書; Cash & Deposits and Interest-Bearing Debt from the 連結貸借対照表. Interest-bearing debt = 短期借入金 + 1年内返済予定の長期借入金 + 1年内償還予定の社債 + コマーシャル・ペーパー + リース債務(流動) + 社債 + 長期借入金 + リース債務(固定).
B31: WARNING - Operating Cash Flow INCLUDES AEON Bank balance-sheet flows and is therefore not an operating cash flow in the economic sense. FY2026/2 absorbed 銀行業における預金の増減額 of +277,144 and 銀行業における貸出金の増減額 of -174,561. Excluding both, ex-bank operating cash flow was 1,024,006 and ex-bank free cash flow 495,470, versus the 598,053 shown in row 21.
B32: Row 27 EXCLUDES 銀行業における預金 (5,474,093 at 2026/2/28). Deposits fund AEON Bank's loan book (銀行業における貸出金 3,197,412) and are the raw material of a banking business, not corporate debt. Including them would make net debt meaningless.
B33: Row 28 (3,099,169 at FY2026/2) is the FINANCIAL-DEBT component of 'DCF Model'!C16 = 4,083,263. The 984,094 difference is non-controlling interests, folded into net debt in the DCF because the template computes Equity = EV - net_debt and has no separate minority-interest deduction. de_ratio is overridden to 0.8403 (financial debt / market cap) so that the MI addback does not distort the WACC - verify it reads 0.8403 and not 1.1071.
B34: Income Statement rows: Revenue = 営業収益合計 (売上高 + 総合金融事業における営業収益 + その他の営業収益), COGS = 営業原価合計, SGA = 販売費及び一般管理費, Operating Income = 営業利益, Net Income = 親会社株主に帰属する当期純利益. Reconciles to the 短信 within 1 for all four years. FY2026/2 net income of 72,677 includes a 段階取得に係る差益 of 69,086 from the Tsuruha consolidation.

Sheet DCF Model
B2: DCF Valuation Model - イオン株式会社
B4: Assumptions
B5: Capex / Revenue | C5: 0.049325164
B6: Effective Tax Rate | C6: 0.3062
B7: Risk-Free Rate | C7: 0.023
B8: Beta | C8: 0.8
B9: Equity Risk Premium | C9: 0.06
B10: Size Premium | C10: 0
B11: After-tax Cost of Debt | C11: 0.012
B12: D/E Ratio | C12: 0.8403
B13: Terminal Growth Rate | C13: 0.005
B14: Exit Multiple (EV/EBITDA) | C14: 8
B15: Fully Diluted Shares | C15: 2765768421
B16: Net Debt (JPY mn) | C16: 4083263
... B20: LTM Revenue (JPY mn) | C20: 10715342
B22: WACC Calculation
B23: Cost of Equity (Ke) | C23: =C7+C8*C9+C10 -> 0.071
B24: Weight of Equity | C24: =1/(1+C12) -> 0.54338966
B25: Weight of Debt | C25: =C12/(1+C12) -> 0.45661034
B26: WACC | C26: =C23*C24+C11*C25 -> 0.04405999
B27: Active Scenario | C27: Base | D27: 1
B28: Projected Free Cash Flow
C29: FY2027(E) | D29: FY2028(E) | E29: FY2029(E) | F29: FY2030(E) | G29: FY2031(E)
B30: Revenue Growth (YoY) | C30: =CHOOSE($D$27,C69,C70,C71,C72,C73) -> 0.08 | D30: =CHOOSE($D$27,D69,D70,D71,D72,D73) -> 0.04 | E30: =CHOOSE($D$27,E69,E70,E71,E72,E73) -> 0.03 | F30: =CHOOSE($D$27,F69,F70,F71,F72,F73) -> 0.025 | G30: =CHOOSE($D$27,G69,G70,G71,G72,G73) -> 0.02
B31: COGS % of Revenue | C31: =CHOOSE($D$27,C76,C77,C78,C79,C80) -> 0.634 | D31: =CHOOSE($D$27,D76,D77,D78,D79,D80) -> 0.633 | E31: =CHOOSE($D$27,E76,E77,E78,E79,E80) -> 0.632 | F31: =CHOOSE($D$27,F76,F77,F78,F79,F80) -> 0.631 | G31: =CHOOSE($D$27,G76,G77,G78,G79,G80) -> 0.63
B32: SGA % of Revenue | C32: =CHOOSE($D$27,C83,C84,C85,C86,C87) -> 0.339 | D32: =CHOOSE($D$27,D83,D84,D85,D86,D87) -> 0.338 | E32: =CHOOSE($D$27,E83,E84,E85,E86,E87) -> 0.3375 | F32: =CHOOSE($D$27,F83,F84,F85,F86,F87) -> 0.3375 | G32: =CHOOSE($D$27,G83,G84,G85,G86,G87) -> 0.338
B33: Revenue | C33: =C17*(1+C30) -> 11572569 | D33: =C33*(1+D30) -> 12035472 | E33: =D33*(1+E30) -> 12396536 | F33: =E33*(1+F30) -> 12706450 | G33: =F33*(1+G30) -> 12960579
B34: COGS | C34: =C33*C31 -> 7337009 | D34: =D33*D31 -> 7618453.9 | E34: =E33*E31 -> 7834610.9 | F34: =F33*F31 -> 8017769.8 | G34: =G33*G31 -> 8165164.6
B35: Gross Profit | C35: =C33-C34 -> 4235560.4 | D35: =D33-D34 -> 4417018.3 | E35: =E33-E34 -> 4561925.4 | F35: =F33-F34 -> 4688679.9 | G35: =G33-G34 -> 4795414.1
B36: Gross Margin | C36: =C35/C33 -> 0.366 | D36: =D35/D33 -> 0.367 | E36: =E35/E33 -> 0.368 | F36: =F35/F33 -> 0.369 | G36: =G35/G33 -> 0.37
B37: SGA Expense | C37: =C33*C32 -> 3923101 | D37: =D33*D32 -> 4067989.6 | E37: =E33*E32 -> 4183831 | F37: =F33*F32 -> 4288426.8 | G37: =G33*G32 -> 4380675.6
B38: Implied Operating Margin | C38: =(C35-C37)/C33 -> 0.027 | D38: =(D35-D37)/D33 -> 0.029 | E38: =(E35-E37)/E33 -> 0.0305 | F38: =(F35-F37)/F33 -> 0.0315 | G38: =(G35-G37)/G33 -> 0.032
B39: Operating Income (EBIT) | C39: =C35-C37 -> 312459.37 | D39: =D35-D37 -> 349028.69 | E39: =E35-E37 -> 378094.36 | F39: =F35-F37 -> 400253.17 | G39: =G35-G37 -> 414738.52
B40: Less: Tax | C40: =MAX(0,C39*C6) -> 95675.06 | D40: =MAX(0,D39*C6) -> 106872.59 | E40: =MAX(0,E39*C6) -> 115772.49 | F40: =MAX(0,F39*C6) -> 122557.52 | G40: =MAX(0,G39*C6) -> 126992.93
B41: NOPAT | C41: =C39-C40 -> 216784.31 | D41: =D39-D40 -> 242156.11 | E41: =E39-E40 -> 262321.86 | F41: =F39-F40 -> 277695.65 | G41: =G39-G40 -> 287745.58
B42: Plus: D&A | C42: 400000 | D42: 415000 | E42: 425000 | F42: 435000 | G42: 445000
B43: Less: Capex | C43: 560000 | D43: 550000 | E43: 540000 | F43: 540000 | G43: 545000
B44: Change in NWC | C44: ='NWC Schedule'!D19 -> 84442.041 | D44: ='NWC Schedule'!E19 -> 54178.648 | E44: ='NWC Schedule'!F19 -> 42582.49 | F44: ='NWC Schedule'!G19 -> 36777.806 | G44: ='NWC Schedule'!H19 -> 30425.855
B45: Unlevered Free Cash Flow | C45: =C41+C42-C43-C44 -> -27657.728 | D45: =D41+D42-D43-D44 -> 52977.458 | E45: =E41+E42-E43-E44 -> 104739.38 | F45: =F41+F42-F43-F44 -> 135917.84 | G45: =G41+G42-G43-G44 -> 157319.73
B46: Discount Factor | C46: =1/(1+C26)^(C19+0) -> 0.95779937 | D46: =1/(1+C26)^(C19+1) -> 0.91737963 | E46: =1/(1+C26)^(C19+2) -> 0.87866563 | F46: =1/(1+C26)^(C19+3) -> 0.84158539 | G46: =1/(1+C26)^(C19+4) -> 0.80606995
B47: PV of FCF | C47: =C45*C46 -> -26490.555 | D47: =D45*D46 -> 48600.441 | E47: =E45*E46 -> 92030.889 | F47: =F45*F46 -> 114386.47 | G47: =G45*G46 -> 126810.71
B49: Valuation - Perpetuity Growth Method
B50: Sum of PV of FCFs | C50: =SUM(C47:G47) -> 355337.95
B51: Terminal Value (PGM) | C51: =G45*(1+C13)/(C26-C13) -> 4047782.1
B52: PV of Terminal Value | C52: =C51*G46 -> 3262795.5
B53: Enterprise Value | C53: =C50+C52 -> 3618133.5
B54: Equity Value | C54: =C53-C16 -> -465129.55
B55: Implied Share Price (PGM) | C55: =ROUND(C54*1000000/C15,0) -> -168
B57: Valuation - Exit Multiple Method
B58: Sum of PV of FCFs | C58: =C50 -> 355337.95
B59: Year 5 EBITDA | C59: =G39+G42 -> 859738.52
B60: Terminal Value (Exit Multiple) | C60: =C59*C14 -> 6877908.1
B61: PV of Terminal Value | C61: =C60*G46 -> 5544075.1
B62: Enterprise Value | C62: =C58+C61 -> 5899413.1
B63: Equity Value | C63: =C62-C16 -> 1816150.1
B64: Implied Share Price (Exit Multiple) | C64: =ROUND(C63*1000000/C15,0) -> 657
B66: Scenario Input Matrix
C67: Year 1 | D67: Year 2 | E67: Year 3 | F67: Year 4 | G67: Year 5
B68: Revenue Growth (YoY)
B69: Base | C69: 0.08 | D69: 0.04 | E69: 0.03 | F69: 0.025 | G69: 0.02
B70: Upside | C70: 0.11 | D70: 0.06 | E70: 0.05 | F70: 0.04 | G70: 0.035
B71: Management | C71: 0.12 | D71: 0.03 | E71: 0.025 | F71: 0.02 | G71: 0.02
B72: Downside 1 | C72: 0.05 | D72: 0.01 | E72: 0.005 | F72: 0.005 | G72: 0.005
B73: Downside 2 | C73: 0.02 | D73: -0.01 | E73: -0.01 | F73: -0.005 | G73: -0.005
B75: COGS % of Revenue
B76: Base | C76: 0.634 | D76: 0.633 | E76: 0.632 | F76: 0.631 | G76: 0.63
B77: Upside | C77: 0.632 | D77: 0.63 | E77: 0.628 | F77: 0.627 | G77: 0.626
B78: Management | C78: 0.634 | D78: 0.633 | E78: 0.633 | F78: 0.633 | G78: 0.633
B79: Downside 1 | C79: 0.638 | D79: 0.64 | E79: 0.64 | F79: 0.639 | G79: 0.639
B80: Downside 2 | C80: 0.643 | D80: 0.648 | E80: 0.648 | F80: 0.646 | G80: 0.646
B82: SGA % of Revenue
B83: Base | C83: 0.339 | D83: 0.338 | E83: 0.3375 | F83: 0.3375 | G83: 0.338
B84: Upside | C84: 0.338 | D84: 0.336 | E84: 0.335 | F84: 0.334 | G84: 0.334
B85: Management | C85: 0.3377 | D85: 0.3375 | E85: 0.337 | F85: 0.3365 | G85: 0.3365
B86: Downside 1 | C86: 0.34 | D86: 0.341 | E86: 0.341 | F86: 0.341 | G86: 0.341
B87: Downside 2 | C87: 0.342 | D87: 0.344 | E87: 0.344 | F87: 0.344 | G87: 0.344

Sheet NWC Schedule
B2: NWC Schedule - イオン株式会社
B4: Working Capital Drivers (Days) | C4: Base Year | D4: FY2027(E) | E4: FY2028(E) | F4: FY2029(E) | G4: FY2030(E) | H4: FY2031(E)
B5: DSO (Days Sales Outstanding) | C5: =C12/C9*365 -> 64.298276 | D5: =CHOOSE('DCF Model'!$D$27,D25,D26,D27,D28,D29) -> 64 | E5: =CHOOSE('DCF Model'!$D$27,E25,E26,E27,E28,E29) -> 64 | F5: =CHOOSE('DCF Model'!$D$27,F25,F26,F27,F28,F29) -> 64 | G5: =CHOOSE('DCF Model'!$D$27,G25,G26,G27,G28,G29) -> 64 | H5: =CHOOSE('DCF Model'!$D$27,H25,H26,H27,H28,H29) -> 64
B6: DIH (Days Inventory Held) | C6: =C13/C10*365 -> 44.493427 | D6: =CHOOSE('DCF Model'!$D$27,D32,D33,D34,D35,D36) -> 44 | E6: =CHOOSE('DCF Model'!$D$27,E32,E33,E34,E35,E36) -> 44 | F6: =CHOOSE('DCF Model'!$D$27,F32,F33,F34,F35,F36) -> 44 | G6: =CHOOSE('DCF Model'!$D$27,G32,G33,G34,G35,G36) -> 44 | H6: =CHOOSE('DCF Model'!$D$27,H32,H33,H34,H35,H36) -> 44
B7: DPO (Days Payable Outstanding) | C7: =C15/C10*365 -> 79.16667 | D7: =CHOOSE('DCF Model'!$D$27,D39,D40,D41,D42,D43) -> 79 | E7: =CHOOSE('DCF Model'!$D$27,E39,E40,E41,E42,E43) -> 79 | F7: =CHOOSE('DCF Model'!$D$27,F39,F40,F41,F42,F43) -> 79 | G7: =CHOOSE('DCF Model'!$D$27,G39,G40,G41,G42,G43) -> 79 | H7: =CHOOSE('DCF Model'!$D$27,H39,H40,H41,H42,H43) -> 79
B8: P&L Reference (JPY mn)
B9: Revenue | C9: 10715342 | D9: ='DCF Model'!C33 -> 11572569 | E9: ='DCF Model'!D33 -> 12035472 | F9: ='DCF Model'!E33 -> 12396536 | G9: ='DCF Model'!F33 -> 12706450 | H9: ='DCF Model'!G33 -> 12960579
B10: COGS | C10: 6804966 | D10: ='DCF Model'!C34 -> 7337009 | E10: ='DCF Model'!D34 -> 7618453.9 | F10: ='DCF Model'!E34 -> 7834610.9 | G10: ='DCF Model'!F34 -> 8017769.8 | H10: ='DCF Model'!G34 -> 8165164.6
B11: Working Capital Items (JPY mn)
B12: Accounts Receivable | C12: 1887611 | D12: =D9*D5/365 -> 2029162.8 | E12: =E9*E5/365 -> 2110329.4 | F12: =F9*F5/365 -> 2173639.2 | G12: =G9*G5/365 -> 2227980.2 | H12: =H9*H5/365 -> 2272539.8
B13: Inventory | C13: 829524 | D13: =D10*D6/365 -> 884461.36 | E13: =E10*E6/365 -> 918388.96 | F13: =F10*F6/365 -> 944446.25 | G13: =G10*G6/365 -> 966525.67 | H13: =H10*H6/365 -> 984293.81
B14: Current Assets (AR + Inv) | C14: =C12+C13 -> 2717135 | D14: =D12+D13 -> 2913624.2 | E14: =E12+E13 -> 3028718.3 | F14: =F12+F13 -> 3118085.5 | G14: =G12+G13 -> 3194505.9 | H14: =H12+H13 -> 3256833.6
B15: Accounts Payable | C15: 1475963 | D15: =D10*D7/365 -> 1588010.2 | E15: =E10*E7/365 -> 1648925.6 | F15: =F10*F7/365 -> 1695710.3 | G15: =G10*G7/365 -> 1735352.9 | H15: =H10*H7/365 -> 1767254.8
B16: Current Liabilities (AP) | C16: =C15 -> 1475963 | D16: =D15 -> 1588010.2 | E16: =E15 -> 1648925.6 | F16: =F15 -> 1695710.3 | G16: =G15 -> 1735352.9 | H16: =H15 -> 1767254.8
B17: Net Working Capital (JPY mn)
B18: Net Working Capital | C18: =C14-C16 -> 1241172 | D18: =D14-D16 -> 1325614 | E18: =E14-E16 -> 1379792.7 | F18: =F14-F16 -> 1422375.2 | G18: =G14-G16 -> 1459153 | H18: =H14-H16 -> 1489578.8
B19: Change in NWC | C19: n/a | D19: =D18-C18 -> 84442.041 | E19: =E18-D18 -> 54178.648 | F19: =F18-E18 -> 42582.49 | G19: =G18-F18 -> 36777.806 | H19: =H18-G18 -> 30425.855
B22: Scenario Input Matrix (Working Capital Days)
D23: FY2027(E) | E23: FY2028(E) | F23: FY2029(E) | G23: FY2030(E) | H23: FY2031(E)
B24: DSO (Days)
B25: Base | D25: 64 | E25: 64 | F25: 64 | G25: 64 | H25: 64
B26: Upside | D26: 63 | E26: 63 | F26: 62 | G26: 62 | H26: 62
B27: Management | D27: 64 | E27: 64 | F27: 64 | G27: 64 | H27: 64
B28: Downside 1 | D28: 65 | E28: 66 | F28: 66 | G28: 66 | H28: 66
B29: Downside 2 | D29: 67 | E29: 68 | F29: 68 | G29: 68 | H29: 68
B31: DIH (Days)
B32: Base | D32: 44 | E32: 44 | F32: 44 | G32: 44 | H32: 44
B33: Upside | D33: 43 | E33: 43 | F33: 42 | G33: 42 | H33: 42
B34: Management | D34: 44 | E34: 44 | F34: 44 | G34: 44 | H34: 44
B35: Downside 1 | D35: 46 | E35: 47 | F35: 47 | G35: 46 | H35: 46
B36: Downside 2 | D36: 48 | E36: 50 | F36: 50 | G36: 49 | H36: 49
B38: DPO (Days)
B39: Base | D39: 79 | E39: 79 | F39: 79 | G39: 79 | H39: 79
B40: Upside | D40: 80 | E40: 80 | F40: 80 | G40: 80 | H40: 80
B41: Management | D41: 79 | E41: 79 | F41: 79 | G41: 79 | H41: 79
B42: Downside 1 | D42: 78 | E42: 78 | F42: 78 | G42: 78 | H42: 78
B43: Downside 2 | D43: 76 | E43: 75 | F43: 75 | G43: 76 | H43: 76

Sheet Comps Analysis
B2: Comparable Company Analysis
B4: Company | C4: Ticker | D4: Mkt Cap (JPY mn) | E4: EV (JPY mn) | F4: Revenue (JPY mn) | G4: EBITDA (JPY mn) | H4: Op Income (JPY mn) | I4: Net Income (JPY mn) | J4: EV/EBITDA | K4: EV/Revenue | L4: PER | M4: PBR | N4: Op Margin | O4: ROE
B5: AEON | C5: 8267.T | D5: 3938454 | E5: 8021717 | F5: 10715342 | G5: 652959 | H5: 270459 | I5: 72677 | J5: =E5/G5 -> 12.285177 | K5: =E5/F5 -> 0.74861978 | L5: =D5/I5 -> 54.191202 | M5: 3.2324246 | N5: =H5/F5 -> 0.025240352 | O5: 0.059648512
B6: Seven & I Holdings | C6: 3382.T | D6: 5875800 | E6: 7667166 | F6: 10430200 | G6: 805002 | H6: 422993 | I6: 292760 | J6: =E6/G6 -> 9.5244062 | K6: =E6/F6 -> 0.7350929 | L6: =D6/I6 -> 20.070365 | M6: 2.2305823 | N6: =H6/F6 -> 0.040554639 | O6: 0.11113811
B7: Pan Pacific International Holdings | C7: 7532.T | D7: 3060000 | E7: 3288542 | F7: 2246758 | G7: 210185 | H7: 162296 | I7: 90512 | J7: =E7/G7 -> 15.64594 | K7: =E7/F7 -> 1.4636832 | L7: =D7/I7 -> 33.807672 | M7: 5.0515556 | N7: =H7/F7 -> 0.072235639 | O7: 0.14942039
B8: Nitori Holdings | C8: 9843.T | D8: 1562700 | E8: 1577690 | F8: 912248 | G8: 195035 | H8: 125526 | I8: 89270 | J8: =E8/G8 -> 8.089266 | K8: =E8/F8 -> 1.729453 | L8: =D8/I8 -> 17.505321 | M8: 1.5807858 | N8: =H8/F8 -> 0.13760074 | O8: 0.090303158
B14: Statistics
B15: 25th Percentile | D15: =PERCENTILE(J6:J8,0.25) -> 8.8068361 | E15: =PERCENTILE(K6:K8,0.25) -> 1.0993881 | F15: =PERCENTILE(L6:L8,0.25) -> 18.787843 | G15: =PERCENTILE(M6:M8,0.25) -> 1.9056841 | H15: =PERCENTILE(N6:N8,0.25) -> 0.056395139 | I15: =PERCENTILE(O6:O8,0.25) -> 0.10072063
B16: Median (50th) | D16: =MEDIAN(J6:J8) -> 9.5244062 | E16: =MEDIAN(K6:K8) -> 1.4636832 | F16: =MEDIAN(L6:L8) -> 20.070365 | G16: =MEDIAN(M6:M8) -> 2.2305823 | H16: =MEDIAN(N6:N8) -> 0.072235639 | I16: =MEDIAN(O6:O8) -> 0.11113811
B17: 75th Percentile | D17: =PERCENTILE(J6:J8,0.75) -> 12.585173 | E17: =PERCENTILE(K6:K8,0.75) -> 1.5965681 | F17: =PERCENTILE(L6:L8,0.75) -> 26.939018 | G17: =PERCENTILE(M6:M8,0.75) -> 3.641069 | H17: =PERCENTILE(N6:N8,0.75) -> 0.10491819 | I17: =PERCENTILE(O6:O8,0.75) -> 0.13027925
B19: Implied Valuation for イオン株式会社
B20: イオン株式会社 Financials
B21: EBITDA (JPY mn) | C21: 652959
B22: Net Income (JPY mn) | C22: 72677
B23: Shares Outstanding | C23: 2765768421
B24: Net Debt (JPY mn) | C24: 4083263
B26: Implied Share Price (Median Multiples)
B27: Via EV/EBITDA (Median) | C27: =ROUND((C21*D16-C24)*1000000/C23,0) -> 772
B28: Via PER (Median) | C28: =ROUND(C22*F16*1000000/C23,0) -> 527

Sheet Sensitivity Analysis
B2: Sensitivity Analysis
B3: Current WACC: | C3: ='DCF Model'!C26 -> 0.04405999 | E3: Terminal g: | F3: ='DCF Model'!C13 -> 0.005 | H3: Exit Multiple: | I3: ='DCF Model'!C14 -> 8
B5: Table 1: WACC vs Terminal Growth Rate (PGM - Implied Share Price, JPY)
B6: WACC \ Terminal g | C6: =$F$3-0.0075 -> -0.0025 | D6: =$F$3-0.005 -> 0 | E6: =$F$3-0.0025 -> 0.0025 | F6: =$F$3 -> 0.005 | G6: =$F$3+0.0025 -> 0.0075 | H6: =$F$3+0.005 -> 0.01 | I6: =$F$3+0.0075 -> 0.0125
B7: =$C$3-0.015 -> 0.02905999 | C7: =IFERROR(ROUND(('DCF Model'!C45/(1+$B7)^('DCF Model'!C19+0)+'DCF Model'!D45/(1+$B7)^('DCF Model'!C19+1)+'DCF Model'!E45/(1+$B7)^('DCF Model'!C19+2)+'DCF Model'!F45/(1+$B7)^('DCF Model'!C19+3)+'DCF Model'!G45/(1+$B7)^('DCF Model'!C19+4)+'DCF Model'!G45*(1+C$6)/($B7-C$6)/(1+$B7)^('DCF Model'!C19+4)-'DCF Model'!C16)*1000000/'DCF Model'!C15,0),"") -> 218 | D7: =IFERROR(ROUND(('DCF Model'!C45/(1+$B7)^('DCF Model'!C19+0)+'DCF Model'!D45/(1+$B7)^('DCF Model'!C19+1)+'DCF Model'!E45/(1+$B7)^('DCF Model'!C19+2)+'DCF Model'!F45/(1+$B7)^('DCF Model'!C19+3)+'DCF Model'!G45/(1+$B7)^('DCF Model'!C19+4)+'DCF Model'!G45*(1+D$6)/($B7-D$6)/(1+$B7)^('DCF Model'!C19+4)-'DCF Model'!C16)*1000000/'DCF Model'!C15,0),"") -> 356 | E7: =IFERROR(ROUND(('DCF Model'!C45/(1+$B7)^('DCF Model'!C19+0)+'DCF Model'!D45/(1+$B7)^('DCF Model'!C19+1)+'DCF Model'!E45/(1+$B7)^('DCF Model'!C19+2)+'DCF Model'!F45/(1+$B7)^('DCF Model'!C19+3)+'DCF Model'!G45/(1+$B7)^('DCF Model'!C19+4)+'DCF Model'!G45*(1+E$6)/($B7-E$6)/(1+$B7)^('DCF Model'!C19+4)-'DCF Model'!C16)*1000000/'DCF Model'!C15,0),"") -> 520 | F7: =IFERROR(ROUND(('DCF Model'!C45/(1+$B7)^('DCF Model'!C19+0)+'DCF Model'!D45/(1+$B7)^('DCF Model'!C19+1)+'DCF Model'!E45/(1+$B7)^('DCF Model'!C19+2)+'DCF Model'!F45/(1+$B7)^('DCF Model'!C19+3)+'DCF Model'!G45/(1+$B7)^('DCF Model'!C19+4)+'DCF Model'!G45*(1+F$6)/($B7-F$6)/(1+$B7)^('DCF Model'!C19+4)-'DCF Model'!C16)*1000000/'DCF Model'!C15,0),"") -> 719 | G7: =IFERROR(ROUND(('DCF Model'!C45/(1+$B7)^('DCF Model'!C19+0)+'DCF Model'!D45/(1+$B7)^('DCF Model'!C19+1)+'DCF Model'!E45/(1+$B7)^('DCF Model'!C19+2)+'DCF Model'!F45/(1+$B7)^('DCF Model'!C19+3)+'DCF Model'!G45/(1+$B7)^('DCF Model'!C19+4)+'DCF Model'!G45*(1+G$6)/($B7-G$6)/(1+$B7)^('DCF Model'!C19+4)-'DCF Model'!C16)*1000000/'DCF Model'!C15,0),"") -> 963 | H7: =IFERROR(ROUND(('DCF Model'!C45/(1+$B7)^('DCF Model'!C19+0)+'DCF Model'!D45/(1+$B7)^('DCF Model'!C19+1)+'DCF Model'!E45/(1+$B7)^('DCF Model'!C19+2)+'DCF Model'!F45/(1+$B7)^('DCF Model'!C19+3)+'DCF Model'!G45/(1+$B7)^('DCF Model'!C19+4)+'DCF Model'!G45*(1+H$6)/($B7-H$6)/(1+$B7)^('DCF Model'!C19+4)-'DCF Model'!C16)*1000000/'DCF Model'!C15,0),"") -> 1272 | I7: =IFERROR(ROUND(('DCF Model'!C45/(1+$B7)^('DCF Model'!C19+0)+'DCF Model'!D45/(1+$B7)^('DCF Model'!C19+1)+'DCF Model'!E45/(1+$B7)^('DCF Model'!C19+2)+'DCF Model'!F45/(1+$B7)^('DCF Model'!C19+3)+'DCF Model'!G45/(1+$B7)^('DCF Model'!C19+4)+'DCF Model'!G45*(1+I$6)/($B7-I$6)/(1+$B7)^('DCF Model'!C19+4)-'DCF Model'!C16)*1000000/'DCF Model'!C15,0),"") -> 1674
B8: =$C$3-0.01 -> 0.03405999 | C8: =IFERROR(ROUND(('DCF Model'!C45/(1+$B8)^('DCF Model'!C19+0)+'DCF Model'!D45/(1+$B8)^('DCF Model'!C19+1)+'DCF Model'!E45/(1+$B8)^('DCF Model'!C19+2)+'DCF Model'!F45/(1+$B8)^('DCF Model'!C19+3)+'DCF Model'!G45/(1+$B8)^('DCF Model'!C19+4)+'DCF Model'!G45*(1+C$6)/($B8-C$6)/(1+$B8)^('DCF Model'!C19+4)-'DCF Model'!C16)*1000000/'DCF Model'!C15,0),"") -> -30 | D8: =IFERROR(ROUND(('DCF Model'!C45/(1+$B8)^('DCF Model'!C19+0)+'DCF Model'!D45/(1+$B8)^('DCF Model'!C19+1)+'DCF Model'!E45/(1+$B8)^('DCF Model'!C19+2)+'DCF Model'!F45/(1+$B8)^('DCF Model'!C19+3)+'DCF Model'!G45/(1+$B8)^('DCF Model'!C19+4)+'DCF Model'!G45*(1+D$6)/($B8-D$6)/(1+$B8)^('DCF Model'!C19+4)-'DCF Model'!C16)*1000000/'DCF Model'!C15,0),"") -> 70 | E8: =IFERROR(ROUND(('DCF Model'!C45/(1+$B8)^('DCF Model'!C19+0)+'DCF Model'!D45/(1+$B8)^('DCF Model'!C19+1)+'DCF Model'!E45/(1+$B8)^('DCF Model'!C19+2)+'DCF Model'!F45/(1+$B8)^('DCF Model'!C19+3)+'DCF Model'!G45/(1+$B8)^('DCF Model'!C19+4)+'DCF Model'!G45*(1+E$6)/($B8-E$6)/(1+$B8)^('DCF Model'!C19+4)-'DCF Model'!C16)*1000000/'DCF Model'!C15,0),"") -> 185 | F8: =IFERROR(ROUND(('DCF Model'!C45/(1+$B8)^('DCF Model'!C19+0)+'DCF Model'!D45/(1+$B8)^('DCF Model'!C19+1)+'DCF Model'!E45/(1+$B8)^('DCF Model'!C19+2)+'DCF Model'!F45/(1+$B8)^('DCF Model'!C19+3)+'DCF Model'!G45/(1+$B8)^('DCF Model'!C19+4)+'DCF Model'!G45*(1+F$6)/($B8-F$6)/(1+$B8)^('DCF Model'!C19+4)-'DCF Model'!C16)*1000000/'DCF Model'!C15,0),"") -> 321 | G8: =IFERROR(ROUND(('DCF Model'!C45/(1+$B8)^('DCF Model'!C19+0)+'DCF Model'!D45/(1+$B8)^('DCF Model'!C19+1)+'DCF Model'!E45/(1+$B8)^('DCF Model'!C19+2)+'DCF Model'!F45/(1+$B8)^('DCF Model'!C19+3)+'DCF Model'!G45/(1+$B8)^('DCF Model'!C19+4)+'DCF Model'!G45*(1+G$6)/($B8-G$6)/(1+$B8)^('DCF Model'!C19+4)-'DCF Model'!C16)*1000000/'DCF Model'!C15,0),"") -> 482 | H8: =IFERROR(ROUND(('DCF Model'!C45/(1+$B8)^('DCF Model'!C19+0)+'DCF Model'!D45/(1+$B8)^('DCF Model'!C19+1)+'DCF Model'!E45/(1+$B8)^('DCF Model'!C19+2)+'DCF Model'!F45/(1+$B8)^('DCF Model'!C19+3)+'DCF Model'!G45/(1+$B8)^('DCF Model'!C19+4)+'DCF Model'!G45*(1+H$6)/($B8-H$6)/(1+$B8)^('DCF Model'!C19+4)-'DCF Model'!C16)*1000000/'DCF Model'!C15,0),"") -> 677 | I8: =IFERROR(ROUND(('DCF Model'!C45/(1+$B8)^('DCF Model'!C19+0)+'DCF Model'!D45/(1+$B8)^('DCF Model'!C19+1)+'DCF Model'!E45/(1+$B8)^('DCF Model'!C19+2)+'DCF Model'!F45/(1+$B8)^('DCF Model'!C19+3)+'DCF Model'!G45/(1+$B8)^('DCF Model'!C19+4)+'DCF Model'!G45*(1+I$6)/($B8-I$6)/(1+$B8)^('DCF Model'!C19+4)-'DCF Model'!C16)*1000000/'DCF Model'!C15,0),"") -> 917
B9: =$C$3-0.005 -> 0.03905999 | C9: =IFERROR(ROUND(('DCF Model'!C45/(1+$B9)^('DCF Model'!C19+0)+'DCF Model'!D45/(1+$B9)^('DCF Model'!C19+1)+'DCF Model'!E45/(1+$B9)^('DCF Model'!C19+2)+'DCF Model'!F45/(1+$B9)^('DCF Model'!C19+3)+'DCF Model'!G45/(1+$B9)^('DCF Model'!C19+4)+'DCF Model'!G45*(1+C$6)/($B9-C$6)/(1+$B9)^('DCF Model'!C19+4)-'DCF Model'!C16)*1000000/'DCF Model'!C15,0),"") -> -218 | D9: =IFERROR(ROUND(('DCF Model'!C45/(1+$B9)^('DCF Model'!C19+0)+'DCF Model'!D45/(1+$B9)^('DCF Model'!C19+1)+'DCF Model'!E45/(1+$B9)^('DCF Model'!C19+2)+'DCF Model'!F45/(1+$B9)^('DCF Model'!C19+3)+'DCF Model'!G45/(1+$B9)^('DCF Model'!C19+4)+'DCF Model'!G45*(1+D$6)/($B9-D$6)/(1+$B9)^('DCF Model'!C19+4)-'DCF Model'!C16)*1000000/'DCF Model'!C15,0),"") -> -143 | E9: =IFERROR(ROUND(('DCF Model'!C45/(1+$B9)^('DCF Model'!C19+0)+'DCF Model'!D45/(1+$B9)^('DCF Model'!C19+1)+'DCF Model'!E45/(1+$B9)^('DCF Model'!C19+2)+'DCF Model'!F45/(1+$B9)^('DCF Model'!C19+3)+'DCF Model'!G45/(1+$B9)^('DCF Model'!C19+4)+'DCF Model'!G45*(1+E$6)/($B9-E$6)/(1+$B9)^('DCF Model'!C19+4)-'DCF Model'!C16)*1000000/'DCF Model'!C15,0),"") -> -58 | F9: =IFERROR(ROUND(('DCF Model'!C45/(1+$B9)^('DCF Model'!C19+0)+'DCF Model'!D45/(1+$B9)^('DCF Model'!C19+1)+'DCF Model'!E45/(1+$B9)^('DCF Model'!C19+2)+'DCF Model'!F45/(1+$B9)^('DCF Model'!C19+3)+'DCF Model'!G45/(1+$B9)^('DCF Model'!C19+4)+'DCF Model'!G45*(1+F$6)/($B9-F$6)/(1+$B9)^('DCF Model'!C19+4)-'DCF Model'!C16)*1000000/'DCF Model'!C15,0),"") -> 40 | G9: =IFERROR(ROUND(('DCF Model'!C45/(1+$B9)^('DCF Model'!C19+0)+'DCF Model'!D45/(1+$B9)^('DCF Model'!C19+1)+'DCF Model'!E45/(1+$B9)^('DCF Model'!C19+2)+'DCF Model'!F45/(1+$B9)^('DCF Model'!C19+3)+'DCF Model'!G45/(1+$B9)^('DCF Model'!C19+4)+'DCF Model'!G45*(1+G$6)/($B9-G$6)/(1+$B9)^('DCF Model'!C19+4)-'DCF Model'!C16)*1000000/'DCF Model'!C15,0),"") -> 154 | H9: =IFERROR(ROUND(('DCF Model'!C45/(1+$B9)^('DCF Model'!C19+0)+'DCF Model'!D45/(1+$B9)^('DCF Model'!C19+1)+'DCF Model'!E45/(1+$B9)^('DCF Model'!C19+2)+'DCF Model'!F45/(1+$B9)^('DCF Model'!C19+3)+'DCF Model'!G45/(1+$B9)^('DCF Model'!C19+4)+'DCF Model'!G45*(1+H$6)/($B9-H$6)/(1+$B9)^('DCF Model'!C19+4)-'DCF Model'!C16)*1000000/'DCF Model'!C15,0),"") -> 287 | I9: =IFERROR(ROUND(('DCF Model'!C45/(1+$B9)^('DCF Model'!C19+0)+'DCF Model'!D45/(1+$B9)^('DCF Model'!C19+1)+'DCF Model'!E45/(1+$B9)^('DCF Model'!C19+2)+'DCF Model'!F45/(1+$B9)^('DCF Model'!C19+3)+'DCF Model'!G45/(1+$B9)^('DCF Model'!C19+4)+'DCF Model'!G45*(1+I$6)/($B9-I$6)/(1+$B9)^('DCF Model'!C19+4)-'DCF Model'!C16)*1000000/'DCF Model'!C15,0),"") -> 445
B10: =$C$3 -> 0.04405999 | C10: =IFERROR(ROUND(('DCF Model'!C45/(1+$B10)^('DCF Model'!C19+0)+'DCF Model'!D45/(1+$B10)^('DCF Model'!C19+1)+'DCF Model'!E45/(1+$B10)^('DCF Model'!C19+2)+'DCF Model'!F45/(1+$B10)^('DCF Model'!C19+3)+'DCF Model'!G45/(1+$B10)^('DCF Model'!C19+4)+'DCF Model'!G45*(1+C$6)/($B10-C$6)/(1+$B10)^('DCF Model'!C19+4)-'DCF Model'!C16)*1000000/'DCF Model'!C15,0),"") -> -366 | D10: =IFERROR(ROUND(('DCF Model'!C45/(1+$B10)^('DCF Model'!C19+0)+'DCF Model'!D45/(1+$B10)^('DCF Model'!C19+1)+'DCF Model'!E45/(1+$B10)^('DCF Model'!C19+2)+'DCF Model'!F45/(1+$B10)^('DCF Model'!C19+3)+'DCF Model'!G45/(1+$B10)^('DCF Model'!C19+4)+'DCF Model'!G45*(1+D$6)/($B10-D$6)/(1+$B10)^('DCF Model'!C19+4)-'DCF Model'!C16)*1000000/'DCF Model'!C15,0),"") -> -307 | E10: =IFERROR(ROUND(('DCF Model'!C45/(1+$B10)^('DCF Model'!C19+0)+'DCF Model'!D45/(1+$B10)^('DCF Model'!C19+1)+'DCF Model'!E45/(1+$B10)^('DCF Model'!C19+2)+'DCF Model'!F45/(1+$B10)^('DCF Model'!C19+3)+'DCF Model'!G45/(1+$B10)^('DCF Model'!C19+4)+'DCF Model'!G45*(1+E$6)/($B10-E$6)/(1+$B10)^('DCF Model'!C19+4)-'DCF Model'!C16)*1000000/'DCF Model'!C15,0),"") -> -242 | F10: =IFERROR(ROUND(('DCF Model'!C45/(1+$B10)^('DCF Model'!C19+0)+'DCF Model'!D45/(1+$B10)^('DCF Model'!C19+1)+'DCF Model'!E45/(1+$B10)^('DCF Model'!C19+2)+'DCF Model'!F45/(1+$B10)^('DCF Model'!C19+3)+'DCF Model'!G45/(1+$B10)^('DCF Model'!C19+4)+'DCF Model'!G45*(1+F$6)/($B10-F$6)/(1+$B10)^('DCF Model'!C19+4)-'DCF Model'!C16)*1000000/'DCF Model'!C15,0),"") -> -168 | G10: =IFERROR(ROUND(('DCF Model'!C45/(1+$B10)^('DCF Model'!C19+0)+'DCF Model'!D45/(1+$B10)^('DCF Model'!C19+1)+'DCF Model'!E45/(1+$B10)^('DCF Model'!C19+2)+'DCF Model'!F45/(1+$B10)^('DCF Model'!C19+3)+'DCF Model'!G45/(1+$B10)^('DCF Model'!C19+4)+'DCF Model'!G45*(1+G$6)/($B10-G$6)/(1+$B10)^('DCF Model'!C19+4)-'DCF Model'!C16)*1000000/'DCF Model'!C15,0),"") -> -84 | H10: =IFERROR(ROUND(('DCF Model'!C45/(1+$B10)^('DCF Model'!C19+0)+'DCF Model'!D45/(1+$B10)^('DCF Model'!C19+1)+'DCF Model'!E45/(1+$B10)^('DCF Model'!C19+2)+'DCF Model'!F45/(1+$B10)^('DCF Model'!C19+3)+'DCF Model'!G45/(1+$B10)^('DCF Model'!C19+4)+'DCF Model'!G45*(1+H$6)/($B10-H$6)/(1+$B10)^('DCF Model'!C19+4)-'DCF Model'!C16)*1000000/'DCF Model'!C15,0),"") -> 12 | I10: =IFERROR(ROUND(('DCF Model'!C45/(1+$B10)^('DCF Model'!C19+0)+'DCF Model'!D45/(1+$B10)^('DCF Model'!C19+1)+'DCF Model'!E45/(1+$B10)^('DCF Model'!C19+2)+'DCF Model'!F45/(1+$B10)^('DCF Model'!C19+3)+'DCF Model'!G45/(1+$B10)^('DCF Model'!C19+4)+'DCF Model'!G45*(1+I$6)/($B10-I$6)/(1+$B10)^('DCF Model'!C19+4)-'DCF Model'!C16)*1000000/'DCF Model'!C15,0),"") -> 123
B11: =$C$3+0.005 -> 0.04905999 | C11: =IFERROR(ROUND(('DCF Model'!C45/(1+$B11)^('DCF Model'!C19+0)+'DCF Model'!D45/(1+$B11)^('DCF Model'!C19+1)+'DCF Model'!E45/(1+$B11)^('DCF Model'!C19+2)+'DCF Model'!F45/(1+$B11)^('DCF Model'!C19+3)+'DCF Model'!G45/(1+$B11)^('DCF Model'!C19+4)+'DCF Model'!G45*(1+C$6)/($B11-C$6)/(1+$B11)^('DCF Model'!C19+4)-'DCF Model'!C16)*1000000/'DCF Model'!C15,0),"") -> -484 | D11: =IFERROR(ROUND(('DCF Model'!C45/(1+$B11)^('DCF Model'!C19+0)+'DCF Model'!D45/(1+$B11)^('DCF Model'!C19+1)+'DCF Model'!E45/(1+$B11)^('DCF Model'!C19+2)+'DCF Model'!F45/(1+$B11)^('DCF Model'!C19+3)+'DCF Model'!G45/(1+$B11)^('DCF Model'!C19+4)+'DCF Model'!G45*(1+D$6)/($B11-D$6)/(1+$B11)^('DCF Model'!C19+4)-'DCF Model'!C16)*1000000/'DCF Model'!C15,0),"") -> -438 | E11: =IFERROR(ROUND(('DCF Model'!C45/(1+$B11)^('DCF Model'!C19+0)+'DCF Model'!D45/(1+$B11)^('DCF Model'!C19+1)+'DCF Model'!E45/(1+$B11)^('DCF Model'!C19+2)+'DCF Model'!F45/(1+$B11)^('DCF Model'!C19+3)+'DCF Model'!G45/(1+$B11)^('DCF Model'!C19+4)+'DCF Model'!G45*(1+E$6)/($B11-E$6)/(1+$B11)^('DCF Model'!C19+4)-'DCF Model'!C16)*1000000/'DCF Model'!C15,0),"") -> -386 | F11: =IFERROR(ROUND(('DCF Model'!C45/(1+$B11)^('DCF Model'!C19+0)+'DCF Model'!D45/(1+$B11)^('DCF Model'!C19+1)+'DCF Model'!E45/(1+$B11)^('DCF Model'!C19+2)+'DCF Model'!F45/(1+$B11)^('DCF Model'!C19+3)+'DCF Model'!G45/(1+$B11)^('DCF Model'!C19+4)+'DCF Model'!G45*(1+F$6)/($B11-F$6)/(1+$B11)^('DCF Model'!C19+4)-'DCF Model'!C16)*1000000/'DCF Model'!C15,0),"") -> -329 | G11: =IFERROR(ROUND(('DCF Model'!C45/(1+$B11)^('DCF Model'!C19+0)+'DCF Model'!D45/(1+$B11)^('DCF Model'!C19+1)+'DCF Model'!E45/(1+$B11)^('DCF Model'!C19+2)+'DCF Model'!F45/(1+$B11)^('DCF Model'!C19+3)+'DCF Model'!G45/(1+$B11)^('DCF Model'!C19+4)+'DCF Model'!G45*(1+G$6)/($B11-G$6)/(1+$B11)^('DCF Model'!C19+4)-'DCF Model'!C16)*1000000/'DCF Model'!C15,0),"") -> -265 | H11: =IFERROR(ROUND(('DCF Model'!C45/(1+$B11)^('DCF Model'!C19+0)+'DCF Model'!D45/(1+$B11)^('DCF Model'!C19+1)+'DCF Model'!E45/(1+$B11)^('DCF Model'!C19+2)+'DCF Model'!F45/(1+$B11)^('DCF Model'!C19+3)+'DCF Model'!G45/(1+$B11)^('DCF Model'!C19+4)+'DCF Model'!G45*(1+H$6)/($B11-H$6)/(1+$B11)^('DCF Model'!C19+4)-'DCF Model'!C16)*1000000/'DCF Model'!C15,0),"") -> -193 | I11: =IFERROR(ROUND(('DCF Model'!C45/(1+$B11)^('DCF Model'!C19+0)+'DCF Model'!D45/(1+$B11)^('DCF Model'!C19+1)+'DCF Model'!E45/(1+$B11)^('DCF Model'!C19+2)+'DCF Model'!F45/(1+$B11)^('DCF Model'!C19+3)+'DCF Model'!G45/(1+$B11)^('DCF Model'!C19+4)+'DCF Model'!G45*(1+I$6)/($B11-I$6)/(1+$B11)^('DCF Model'!C19+4)-'DCF Model'!C16)*1000000/'DCF Model'!C15,0),"") -> -111
B12: =$C$3+0.01 -> 0.05405999 | C12: =IFERROR(ROUND(('DCF Model'!C45/(1+$B12)^('DCF Model'!C19+0)+'DCF Model'!D45/(1+$B12)^('DCF Model'!C19+1)+'DCF Model'!E45/(1+$B12)^('DCF Model'!C19+2)+'DCF Model'!F45/(1+$B12)^('DCF Model'!C19+3)+'DCF Model'!G45/(1+$B12)^('DCF Model'!C19+4)+'DCF Model'!G45*(1+C$6)/($B12-C$6)/(1+$B12)^('DCF Model'!C19+4)-'DCF Model'!C16)*1000000/'DCF Model'!C15,0),"") -> -582 | D12: =IFERROR(ROUND(('DCF Model'!C45/(1+$B12)^('DCF Model'!C19+0)+'DCF Model'!D45/(1+$B12)^('DCF Model'!C19+1)+'DCF Model'!E45/(1+$B12)^('DCF Model'!C19+2)+'DCF Model'!F45/(1+$B12)^('DCF Model'!C19+3)+'DCF Model'!G45/(1+$B12)^('DCF Model'!C19+4)+'DCF Model'!G45*(1+D$6)/($B12-D$6)/(1+$B12)^('DCF Model'!C19+4)-'DCF Model'!C16)*1000000/'DCF Model'!C15,0),"") -> -544 | E12: =IFERROR(ROUND(('DCF Model'!C45/(1+$B12)^('DCF Model'!C19+0)+'DCF Model'!D45/(1+$B12)^('DCF Model'!C19+1)+'DCF Model'!E45/(1+$B12)^('DCF Model'!C19+2)+'DCF Model'!F45/(1+$B12)^('DCF Model'!C19+3)+'DCF Model'!G45/(1+$B12)^('DCF Model'!C19+4)+'DCF Model'!G45*(1+E$6)/($B12-E$6)/(1+$B12)^('DCF Model'!C19+4)-'DCF Model'!C16)*1000000/'DCF Model'!C15,0),"") -> -503 | F12: =IFERROR(ROUND(('DCF Model'!C45/(1+$B12)^('DCF Model'!C19+0)+'DCF Model'!D45/(1+$B12)^('DCF Model'!C19+1)+'DCF Model'!E45/(1+$B12)^('DCF Model'!C19+2)+'DCF Model'!F45/(1+$B12)^('DCF Model'!C19+3)+'DCF Model'!G45/(1+$B12)^('DCF Model'!C19+4)+'DCF Model'!G45*(1+F$6)/($B12-F$6)/(1+$B12)^('DCF Model'!C19+4)-'DCF Model'!C16)*1000000/'DCF Model'!C15,0),"") -> -457 | G12: =IFERROR(ROUND(('DCF Model'!C45/(1+$B12)^('DCF Model'!C19+0)+'DCF Model'!D45/(1+$B12)^('DCF Model'!C19+1)+'DCF Model'!E45/(1+$B12)^('DCF Model'!C19+2)+'DCF Model'!F45/(1+$B12)^('DCF Model'!C19+3)+'DCF Model'!G45/(1+$B12)^('DCF Model'!C19+4)+'DCF Model'!G45*(1+G$6)/($B12-G$6)/(1+$B12)^('DCF Model'!C19+4)-'DCF Model'!C16)*1000000/'DCF Model'!C15,0),"") -> -407 | H12: =IFERROR(ROUND(('DCF Model'!C45/(1+$B12)^('DCF Model'!C19+0)+'DCF Model'!D45/(1+$B12)^('DCF Model'!C19+1)+'DCF Model'!E45/(1+$B12)^('DCF Model'!C19+2)+'DCF Model'!F45/(1+$B12)^('DCF Model'!C19+3)+'DCF Model'!G45/(1+$B12)^('DCF Model'!C19+4)+'DCF Model'!G45*(1+H$6)/($B12-H$6)/(1+$B12)^('DCF Model'!C19+4)-'DCF Model'!C16)*1000000/'DCF Model'!C15,0),"") -> -351 | I12: =IFERROR(ROUND(('DCF Model'!C45/(1+$B12)^('DCF Model'!C19+0)+'DCF Model'!D45/(1+$B12)^('DCF Model'!C19+1)+'DCF Model'!E45/(1+$B12)^('DCF Model'!C19+2)+'DCF Model'!F45/(1+$B12)^('DCF Model'!C19+3)+'DCF Model'!G45/(1+$B12)^('DCF Model'!C19+4)+'DCF Model'!G45*(1+I$6)/($B12-I$6)/(1+$B12)^('DCF Model'!C19+4)-'DCF Model'!C16)*1000000/'DCF Model'!C15,0),"") -> -288
B13: =$C$3+0.015 -> 0.05905999 | C13: =IFERROR(ROUND(('DCF Model'!C45/(1+$B13)^('DCF Model'!C19+0)+'DCF Model'!D45/(1+$B13)^('DCF Model'!C19+1)+'DCF Model'!E45/(1+$B13)^('DCF Model'!C19+2)+'DCF Model'!F45/(1+$B13)^('DCF Model'!C19+3)+'DCF Model'!G45/(1+$B13)^('DCF Model'!C19+4)+'DCF Model'!G45*(1+C$6)/($B13-C$6)/(1+$B13)^('DCF Model'!C19+4)-'DCF Model'!C16)*1000000/'DCF Model'!C15,0),"") -> -663 | D13: =IFERROR(ROUND(('DCF Model'!C45/(1+$B13)^('DCF Model'!C19+0)+'DCF Model'!D45/(1+$B13)^('DCF Model'!C19+1)+'DCF Model'!E45/(1+$B13)^('DCF Model'!C19+2)+'DCF Model'!F45/(1+$B13)^('DCF Model'!C19+3)+'DCF Model'!G45/(1+$B13)^('DCF Model'!C19+4)+'DCF Model'!G45*(1+D$6)/($B13-D$6)/(1+$B13)^('DCF Model'!C19+4)-'DCF Model'!C16)*1000000/'DCF Model'!C15,0),"") -> -632 | E13: =IFERROR(ROUND(('DCF Model'!C45/(1+$B13)^('DCF Model'!C19+0)+'DCF Model'!D45/(1+$B13)^('DCF Model'!C19+1)+'DCF Model'!E45/(1+$B13)^('DCF Model'!C19+2)+'DCF Model'!F45/(1+$B13)^('DCF Model'!C19+3)+'DCF Model'!G45/(1+$B13)^('DCF Model'!C19+4)+'DCF Model'!G45*(1+E$6)/($B13-E$6)/(1+$B13)^('DCF Model'!C19+4)-'DCF Model'!C16)*1000000/'DCF Model'!C15,0),"") -> -598 | F13: =IFERROR(ROUND(('DCF Model'!C45/(1+$B13)^('DCF Model'!C19+0)+'DCF Model'!D45/(1+$B13)^('DCF Model'!C19+1)+'DCF Model'!E45/(1+$B13)^('DCF Model'!C19+2)+'DCF Model'!F45/(1+$B13)^('DCF Model'!C19+3)+'DCF Model'!G45/(1+$B13)^('DCF Model'!C19+4)+'DCF Model'!G45*(1+F$6)/($B13-F$6)/(1+$B13)^('DCF Model'!C19+4)-'DCF Model'!C16)*1000000/'DCF Model'!C15,0),"") -> -561 | G13: =IFERROR(ROUND(('DCF Model'!C45/(1+$B13)^('DCF Model'!C19+0)+'DCF Model'!D45/(1+$B13)^('DCF Model'!C19+1)+'DCF Model'!E45/(1+$B13)^('DCF Model'!C19+2)+'DCF Model'!F45/(1+$B13)^('DCF Model'!C19+3)+'DCF Model'!G45/(1+$B13)^('DCF Model'!C19+4)+'DCF Model'!G45*(1+G$6)/($B13-G$6)/(1+$B13)^('DCF Model'!C19+4)-'DCF Model'!C16)*1000000/'DCF Model'!C15,0),"") -> -521 | H13: =IFERROR(ROUND(('DCF Model'!C45/(1+$B13)^('DCF Model'!C19+0)+'DCF Model'!D45/(1+$B13)^('DCF Model'!C19+1)+'DCF Model'!E45/(1+$B13)^('DCF Model'!C19+2)+'DCF Model'!F45/(1+$B13)^('DCF Model'!C19+3)+'DCF Model'!G45/(1+$B13)^('DCF Model'!C19+4)+'DCF Model'!G45*(1+H$6)/($B13-H$6)/(1+$B13)^('DCF Model'!C19+4)-'DCF Model'!C16)*1000000/'DCF Model'!C15,0),"") -> -476 | I13: =IFERROR(ROUND(('DCF Model'!C45/(1+$B13)^('DCF Model'!C19+0)+'DCF Model'!D45/(1+$B13)^('DCF Model'!C19+1)+'DCF Model'!E45/(1+$B13)^('DCF Model'!C19+2)+'DCF Model'!F45/(1+$B13)^('DCF Model'!C19+3)+'DCF Model'!G45/(1+$B13)^('DCF Model'!C19+4)+'DCF Model'!G45*(1+I$6)/($B13-I$6)/(1+$B13)^('DCF Model'!C19+4)-'DCF Model'!C16)*1000000/'DCF Model'!C15,0),"") -> -427
B16: Table 2: WACC vs Exit Multiple (Exit Multiple - Implied Share Price, JPY)
B17: WACC \ Exit Multiple | C17: =$I$3-3 -> 5 | D17: =$I$3-2 -> 6 | E17: =$I$3-1 -> 7 | F17: =$I$3 -> 8 | G17: =$I$3+1 -> 9 | H17: =$I$3+2 -> 10 | I17: =$I$3+3 -> 11
B18: =$C$3-0.015 -> 0.02905999 | C18: =IFERROR(ROUND(('DCF Model'!C45/(1+$B18)^('DCF Model'!C19+0)+'DCF Model'!D45/(1+$B18)^('DCF Model'!C19+1)+'DCF Model'!E45/(1+$B18)^('DCF Model'!C19+2)+'DCF Model'!F45/(1+$B18)^('DCF Model'!C19+3)+'DCF Model'!G45/(1+$B18)^('DCF Model'!C19+4)+('DCF Model'!G39+'DCF Model'!G42)*C$17/(1+$B18)^('DCF Model'!C19+4)-'DCF Model'!C16)*1000000/'DCF Model'!C15,0),"") -> 7 | D18: =IFERROR(ROUND(('DCF Model'!C45/(1+$B18)^('DCF Model'!C19+0)+'DCF Model'!D45/(1+$B18)^('DCF Model'!C19+1)+'DCF Model'!E45/(1+$B18)^('DCF Model'!C19+2)+'DCF Model'!F45/(1+$B18)^('DCF Model'!C19+3)+'DCF Model'!G45/(1+$B18)^('DCF Model'!C19+4)+('DCF Model'!G39+'DCF Model'!G42)*D$17/(1+$B18)^('DCF Model'!C19+4)-'DCF Model'!C16)*1000000/'DCF Model'!C15,0),"") -> 276 | E18: =IFERROR(ROUND(('DCF Model'!C45/(1+$B18)^('DCF Model'!C19+0)+'DCF Model'!D45/(1+$B18)^('DCF Model'!C19+1)+'DCF Model'!E45/(1+$B18)^('DCF Model'!C19+2)+'DCF Model'!F45/(1+$B18)^('DCF Model'!C19+3)+'DCF Model'!G45/(1+$B18)^('DCF Model'!C19+4)+('DCF Model'!G39+'DCF Model'!G42)*E$17/(1+$B18)^('DCF Model'!C19+4)-'DCF Model'!C16)*1000000/'DCF Model'!C15,0),"") -> 545 | F18: =IFERROR(ROUND(('DCF Model'!C45/(1+$B18)^('DCF Model'!C19+0)+'DCF Model'!D45/(1+$B18)^('DCF Model'!C19+1)+'DCF Model'!E45/(1+$B18)^('DCF Model'!C19+2)+'DCF Model'!F45/(1+$B18)^('DCF Model'!C19+3)+'DCF Model'!G45/(1+$B18)^('DCF Model'!C19+4)+('DCF Model'!G39+'DCF Model'!G42)*F$17/(1+$B18)^('DCF Model'!C19+4)-'DCF Model'!C16)*1000000/'DCF Model'!C15,0),"") -> 815 | G18: =IFERROR(ROUND(('DCF Model'!C45/(1+$B18)^('DCF Model'!C19+0)+'DCF Model'!D45/(1+$B18)^('DCF Model'!C19+1)+'DCF Model'!E45/(1+$B18)^('DCF Model'!C19+2)+'DCF Model'!F45/(1+$B18)^('DCF Model'!C19+3)+'DCF Model'!G45/(1+$B18)^('DCF Model'!C19+4)+('DCF Model'!G39+'DCF Model'!G42)*G$17/(1+$B18)^('DCF Model'!C19+4)-'DCF Model'!C16)*1000000/'DCF Model'!C15,0),"") -> 1084 | H18: =IFERROR(ROUND(('DCF Model'!C45/(1+$B18)^('DCF Model'!C19+0)+'DCF Model'!D45/(1+$B18)^('DCF Model'!C19+1)+'DCF Model'!E45/(1+$B18)^('DCF Model'!C19+2)+'DCF Model'!F45/(1+$B18)^('DCF Model'!C19+3)+'DCF Model'!G45/(1+$B18)^('DCF Model'!C19+4)+('DCF Model'!G39+'DCF Model'!G42)*H$17/(1+$B18)^('DCF Model'!C19+4)-'DCF Model'!C16)*1000000/'DCF Model'!C15,0),"") -> 1354 | I18: =IFERROR(ROUND(('DCF Model'!C45/(1+$B18)^('DCF Model'!C19+0)+'DCF Model'!D45/(1+$B18)^('DCF Model'!C19+1)+'DCF Model'!E45/(1+$B18)^('DCF Model'!C19+2)+'DCF Model'!F45/(1+$B18)^('DCF Model'!C19+3)+'DCF Model'!G45/(1+$B18)^('DCF Model'!C19+4)+('DCF Model'!G39+'DCF Model'!G42)*I$17/(1+$B18)^('DCF Model'!C19+4)-'DCF Model'!C16)*1000000/'DCF Model'!C15,0),"") -> 1623
B19: =$C$3-0.01 -> 0.03405999 | C19: =IFERROR(ROUND(('DCF Model'!C45/(1+$B19)^('DCF Model'!C19+0)+'DCF Model'!D45/(1+$B19)^('DCF Model'!C19+1)+'DCF Model'!E45/(1+$B19)^('DCF Model'!C19+2)+'DCF Model'!F45/(1+$B19)^('DCF Model'!C19+3)+'DCF Model'!G45/(1+$B19)^('DCF Model'!C19+4)+('DCF Model'!G39+'DCF Model'!G42)*C$17/(1+$B19)^('DCF Model'!C19+4)-'DCF Model'!C16)*1000000/'DCF Model'!C15,0),"") -> -28 | D19: =IFERROR(ROUND(('DCF Model'!C45/(1+$B19)^('DCF Model'!C19+0)+'DCF Model'!D45/(1+$B19)^('DCF Model'!C19+1)+'DCF Model'!E45/(1+$B19)^('DCF Model'!C19+2)+'DCF Model'!F45/(1+$B19)^('DCF Model'!C19+3)+'DCF Model'!G45/(1+$B19)^('DCF Model'!C19+4)+('DCF Model'!G39+'DCF Model'!G42)*D$17/(1+$B19)^('DCF Model'!C19+4)-'DCF Model'!C16)*1000000/'DCF Model'!C15,0),"") -> 235 | E19: =IFERROR(ROUND(('DCF Model'!C45/(1+$B19)^('DCF Model'!C19+0)+'DCF Model'!D45/(1+$B19)^('DCF Model'!C19+1)+'DCF Model'!E45/(1+$B19)^('DCF Model'!C19+2)+'DCF Model'!F45/(1+$B19)^('DCF Model'!C19+3)+'DCF Model'!G45/(1+$B19)^('DCF Model'!C19+4)+('DCF Model'!G39+'DCF Model'!G42)*E$17/(1+$B19)^('DCF Model'!C19+4)-'DCF Model'!C16)*1000000/'DCF Model'!C15,0),"") -> 498 | F19: =IFERROR(ROUND(('DCF Model'!C45/(1+$B19)^('DCF Model'!C19+0)+'DCF Model'!D45/(1+$B19)^('DCF Model'!C19+1)+'DCF Model'!E45/(1+$B19)^('DCF Model'!C19+2)+'DCF Model'!F45/(1+$B19)^('DCF Model'!C19+3)+'DCF Model'!G45/(1+$B19)^('DCF Model'!C19+4)+('DCF Model'!G39+'DCF Model'!G42)*F$17/(1+$B19)^('DCF Model'!C19+4)-'DCF Model'!C16)*1000000/'DCF Model'!C15,0),"") -> 761 | G19: =IFERROR(ROUND(('DCF Model'!C45/(1+$B19)^('DCF Model'!C19+0)+'DCF Model'!D45/(1+$B19)^('DCF Model'!C19+1)+'DCF Model'!E45/(1+$B19)^('DCF Model'!C19+2)+'DCF Model'!F45/(1+$B19)^('DCF Model'!C19+3)+'DCF Model'!G45/(1+$B19)^('DCF Model'!C19+4)+('DCF Model'!G39+'DCF Model'!G42)*G$17/(1+$B19)^('DCF Model'!C19+4)-'DCF Model'!C16)*1000000/'DCF Model'!C15,0),"") -> 1023 | H19: =IFERROR(ROUND(('DCF Model'!C45/(1+$B19)^('DCF Model'!C19+0)+'DCF Model'!D45/(1+$B19)^('DCF Model'!C19+1)+'DCF Model'!E45/(1+$B19)^('DCF Model'!C19+2)+'DCF Model'!F45/(1+$B19)^('DCF Model'!C19+3)+'DCF Model'!G45/(1+$B19)^('DCF Model'!C19+4)+('DCF Model'!G39+'DCF Model'!G42)*H$17/(1+$B19)^('DCF Model'!C19+4)-'DCF Model'!C16)*1000000/'DCF Model'!C15,0),"") -> 1286 | I19: =IFERROR(ROUND(('DCF Model'!C45/(1+$B19)^('DCF Model'!C19+0)+'DCF Model'!D45/(1+$B19)^('DCF Model'!C19+1)+'DCF Model'!E45/(1+$B19)^('DCF Model'!C19+2)+'DCF Model'!F45/(1+$B19)^('DCF Model'!C19+3)+'DCF Model'!G45/(1+$B19)^('DCF Model'!C19+4)+('DCF Model'!G39+'DCF Model'!G42)*I$17/(1+$B19)^('DCF Model'!C19+4)-'DCF Model'!C16)*1000000/'DCF Model'!C15,0),"") -> 1549
B20: =$C$3-0.005 -> 0.03905999 | C20: =IFERROR(ROUND(('DCF Model'!C45/(1+$B20)^('DCF Model'!C19+0)+'DCF Model'!D45/(1+$B20)^('DCF Model'!C19+1)+'DCF Model'!E45/(1+$B20)^('DCF Model'!C19+2)+'DCF Model'!F45/(1+$B20)^('DCF Model'!C19+3)+'DCF Model'!G45/(1+$B20)^('DCF Model'!C19+4)+('DCF Model'!G39+'DCF Model'!G42)*C$17/(1+$B20)^('DCF Model'!C19+4)-'DCF Model'!C16)*1000000/'DCF Model'!C15,0),"") -> -62 | D20: =IFERROR(ROUND(('DCF Model'!C45/(1+$B20)^('DCF Model'!C19+0)+'DCF Model'!D45/(1+$B20)^('DCF Model'!C19+1)+'DCF Model'!E45/(1+$B20)^('DCF Model'!C19+2)+'DCF Model'!F45/(1+$B20)^('DCF Model'!C19+3)+'DCF Model'!G45/(1+$B20)^('DCF Model'!C19+4)+('DCF Model'!G39+'DCF Model'!G42)*D$17/(1+$B20)^('DCF Model'!C19+4)-'DCF Model'!C16)*1000000/'DCF Model'!C15,0),"") -> 195 | E20: =IFERROR(ROUND(('DCF Model'!C45/(1+$B20)^('DCF Model'!C19+0)+'DCF Model'!D45/(1+$B20)^('DCF Model'!C19+1)+'DCF Model'!E45/(1+$B20)^('DCF Model'!C19+2)+'DCF Model'!F45/(1+$B20)^('DCF Model'!C19+3)+'DCF Model'!G45/(1+$B20)^('DCF Model'!C19+4)+('DCF Model'!G39+'DCF Model'!G42)*E$17/(1+$B20)^('DCF Model'!C19+4)-'DCF Model'!C16)*1000000/'DCF Model'!C15,0),"") -> 451 | F20: =IFERROR(ROUND(('DCF Model'!C45/(1+$B20)^('DCF Model'!C19+0)+'DCF Model'!D45/(1+$B20)^('DCF Model'!C19+1)+'DCF Model'!E45/(1+$B20)^('DCF Model'!C19+2)+'DCF Model'!F45/(1+$B20)^('DCF Model'!C19+3)+'DCF Model'!G45/(1+$B20)^('DCF Model'!C19+4)+('DCF Model'!G39+'DCF Model'!G42)*F$17/(1+$B20)^('DCF Model'!C19+4)-'DCF Model'!C16)*1000000/'DCF Model'!C15,0),"") -> 708 | G20: =IFERROR(ROUND(('DCF Model'!C45/(1+$B20)^('DCF Model'!C19+0)+'DCF Model'!D45/(1+$B20)^('DCF Model'!C19+1)+'DCF Model'!E45/(1+$B20)^('DCF Model'!C19+2)+'DCF Model'!F45/(1+$B20)^('DCF Model'!C19+3)+'DCF Model'!G45/(1+$B20)^('DCF Model'!C19+4)+('DCF Model'!G39+'DCF Model'!G42)*G$17/(1+$B20)^('DCF Model'!C19+4)-'DCF Model'!C16)*1000000/'DCF Model'!C15,0),"") -> 965 | H20: =IFERROR(ROUND(('DCF Model'!C45/(1+$B20)^('DCF Model'!C19+0)+'DCF Model'!D45/(1+$B20)^('DCF Model'!C19+1)+'DCF Model'!E45/(1+$B20)^('DCF Model'!C19+2)+'DCF Model'!F45/(1+$B20)^('DCF Model'!C19+3)+'DCF Model'!G45/(1+$B20)^('DCF Model'!C19+4)+('DCF Model'!G39+'DCF Model'!G42)*H$17/(1+$B20)^('DCF Model'!C19+4)-'DCF Model'!C16)*1000000/'DCF Model'!C15,0),"") -> 1221 | I20: =IFERROR(ROUND(('DCF Model'!C45/(1+$B20)^('DCF Model'!C19+0)+'DCF Model'!D45/(1+$B20)^('DCF Model'!C19+1)+'DCF Model'!E45/(1+$B20)^('DCF Model'!C19+2)+'DCF Model'!F45/(1+$B20)^('DCF Model'!C19+3)+'DCF Model'!G45/(1+$B20)^('DCF Model'!C19+4)+('DCF Model'!G39+'DCF Model'!G42)*I$17/(1+$B20)^('DCF Model'!C19+4)-'DCF Model'!C16)*1000000/'DCF Model'!C15,0),"") -> 1478
B21: =$C$3 -> 0.04405999 | C21: =IFERROR(ROUND(('DCF Model'!C45/(1+$B21)^('DCF Model'!C19+0)+'DCF Model'!D45/(1+$B21)^('DCF Model'!C19+1)+'DCF Model'!E45/(1+$B21)^('DCF Model'!C19+2)+'DCF Model'!F45/(1+$B21)^('DCF Model'!C19+3)+'DCF Model'!G45/(1+$B21)^('DCF Model'!C19+4)+('DCF Model'!G39+'DCF Model'!G42)*C$17/(1+$B21)^('DCF Model'!C19+4)-'DCF Model'!C16)*1000000/'DCF Model'!C15,0),"") -> -95 | D21: =IFERROR(ROUND(('DCF Model'!C45/(1+$B21)^('DCF Model'!C19+0)+'DCF Model'!D45/(1+$B21)^('DCF Model'!C19+1)+'DCF Model'!E45/(1+$B21)^('DCF Model'!C19+2)+'DCF Model'!F45/(1+$B21)^('DCF Model'!C19+3)+'DCF Model'!G45/(1+$B21)^('DCF Model'!C19+4)+('DCF Model'!G39+'DCF Model'!G42)*D$17/(1+$B21)^('DCF Model'!C19+4)-'DCF Model'!C16)*1000000/'DCF Model'!C15,0),"") -> 156 | E21: =IFERROR(ROUND(('DCF Model'!C45/(1+$B21)^('DCF Model'!C19+0)+'DCF Model'!D45/(1+$B21)^('DCF Model'!C19+1)+'DCF Model'!E45/(1+$B21)^('DCF Model'!C19+2)+'DCF Model'!F45/(1+$B21)^('DCF Model'!C19+3)+'DCF Model'!G45/(1+$B21)^('DCF Model'!C19+4)+('DCF Model'!G39+'DCF Model'!G42)*E$17/(1+$B21)^('DCF Model'!C19+4)-'DCF Model'!C16)*1000000/'DCF Model'!C15,0),"") -> 406 | F21: =IFERROR(ROUND(('DCF Model'!C45/(1+$B21)^('DCF Model'!C19+0)+'DCF Model'!D45/(1+$B21)^('DCF Model'!C19+1)+'DCF Model'!E45/(1+$B21)^('DCF Model'!C19+2)+'DCF Model'!F45/(1+$B21)^('DCF Model'!C19+3)+'DCF Model'!G45/(1+$B21)^('DCF Model'!C19+4)+('DCF Model'!G39+'DCF Model'!G42)*F$17/(1+$B21)^('DCF Model'!C19+4)-'DCF Model'!C16)*1000000/'DCF Model'!C15,0),"") -> 657 | G21: =IFERROR(ROUND(('DCF Model'!C45/(1+$B21)^('DCF Model'!C19+0)+'DCF Model'!D45/(1+$B21)^('DCF Model'!C19+1)+'DCF Model'!E45/(1+$B21)^('DCF Model'!C19+2)+'DCF Model'!F45/(1+$B21)^('DCF Model'!C19+3)+'DCF Model'!G45/(1+$B21)^('DCF Model'!C19+4)+('DCF Model'!G39+'DCF Model'!G42)*G$17/(1+$B21)^('DCF Model'!C19+4)-'DCF Model'!C16)*1000000/'DCF Model'!C15,0),"") -> 907 | H21: =IFERROR(ROUND(('DCF Model'!C45/(1+$B21)^('DCF Model'!C19+0)+'DCF Model'!D45/(1+$B21)^('DCF Model'!C19+1)+'DCF Model'!E45/(1+$B21)^('DCF Model'!C19+2)+'DCF Model'!F45/(1+$B21)^('DCF Model'!C19+3)+'DCF Model'!G45/(1+$B21)^('DCF Model'!C19+4)+('DCF Model'!G39+'DCF Model'!G42)*H$17/(1+$B21)^('DCF Model'!C19+4)-'DCF Model'!C16)*1000000/'DCF Model'!C15,0),"") -> 1158 | I21: =IFERROR(ROUND(('DCF Model'!C45/(1+$B21)^('DCF Model'!C19+0)+'DCF Model'!D45/(1+$B21)^('DCF Model'!C19+1)+'DCF Model'!E45/(1+$B21)^('DCF Model'!C19+2)+'DCF Model'!F45/(1+$B21)^('DCF Model'!C19+3)+'DCF Model'!G45/(1+$B21)^('DCF Model'!C19+4)+('DCF Model'!G39+'DCF Model'!G42)*I$17/(1+$B21)^('DCF Model'!C19+4)-'DCF Model'!C16)*1000000/'DCF Model'!C15,0),"") -> 1408
B22: =$C$3+0.005 -> 0.04905999 | C22: =IFERROR(ROUND(('DCF Model'!C45/(1+$B22)^('DCF Model'!C19+0)+'DCF Model'!D45/(1+$B22)^('DCF Model'!C19+1)+'DCF Model'!E45/(1+$B22)^('DCF Model'!C19+2)+'DCF Model'!F45/(1+$B22)^('DCF Model'!C19+3)+'DCF Model'!G45/(1+$B22)^('DCF Model'!C19+4)+('DCF Model'!G39+'DCF Model'!G42)*C$17/(1+$B22)^('DCF Model'!C19+4)-'DCF Model'!C16)*1000000/'DCF Model'!C15,0),"") -> -127 | D22: =IFERROR(ROUND(('DCF Model'!C45/(1+$B22)^('DCF Model'!C19+0)+'DCF Model'!D45/(1+$B22)^('DCF Model'!C19+1)+'DCF Model'!E45/(1+$B22)^('DCF Model'!C19+2)+'DCF Model'!F45/(1+$B22)^('DCF Model'!C19+3)+'DCF Model'!G45/(1+$B22)^('DCF Model'!C19+4)+('DCF Model'!G39+'DCF Model'!G42)*D$17/(1+$B22)^('DCF Model'!C19+4)-'DCF Model'!C16)*1000000/'DCF Model'!C15,0),"") -> 118 | E22: =IFERROR(ROUND(('DCF Model'!C45/(1+$B22)^('DCF Model'!C19+0)+'DCF Model'!D45/(1+$B22)^('DCF Model'!C19+1)+'DCF Model'!E45/(1+$B22)^('DCF Model'!C19+2)+'DCF Model'!F45/(1+$B22)^('DCF Model'!C19+3)+'DCF Model'!G45/(1+$B22)^('DCF Model'!C19+4)+('DCF Model'!G39+'DCF Model'!G42)*E$17/(1+$B22)^('DCF Model'!C19+4)-'DCF Model'!C16)*1000000/'DCF Model'!C15,0),"") -> 362 | F22: =IFERROR(ROUND(('DCF Model'!C45/(1+$B22)^('DCF Model'!C19+0)+'DCF Model'!D45/(1+$B22)^('DCF Model'!C19+1)+'DCF Model'!E45/(1+$B22)^('DCF Model'!C19+2)+'DCF Model'!F45/(1+$B22)^('DCF Model'!C19+3)+'DCF Model'!G45/(1+$B22)^('DCF Model'!C19+4)+('DCF Model'!G39+'DCF Model'!G42)*F$17/(1+$B22)^('DCF Model'!C19+4)-'DCF Model'!C16)*1000000/'DCF Model'!C15,0),"") -> 607 | G22: =IFERROR(ROUND(('DCF Model'!C45/(1+$B22)^('DCF Model'!C19+0)+'DCF Model'!D45/(1+$B22)^('DCF Model'!C19+1)+'DCF Model'!E45/(1+$B22)^('DCF Model'!C19+2)+'DCF Model'!F45/(1+$B22)^('DCF Model'!C19+3)+'DCF Model'!G45/(1+$B22)^('DCF Model'!C19+4)+('DCF Model'!G39+'DCF Model'!G42)*G$17/(1+$B22)^('DCF Model'!C19+4)-'DCF Model'!C16)*1000000/'DCF Model'!C15,0),"") -> 852 | H22: =IFERROR(ROUND(('DCF Model'!C45/(1+$B22)^('DCF Model'!C19+0)+'DCF Model'!D45/(1+$B22)^('DCF Model'!C19+1)+'DCF Model'!E45/(1+$B22)^('DCF Model'!C19+2)+'DCF Model'!F45/(1+$B22)^('DCF Model'!C19+3)+'DCF Model'!G45/(1+$B22)^('DCF Model'!C19+4)+('DCF Model'!G39+'DCF Model'!G42)*H$17/(1+$B22)^('DCF Model'!C19+4)-'DCF Model'!C16)*1000000/'DCF Model'!C15,0),"") -> 1096 | I22: =IFERROR(ROUND(('DCF Model'!C45/(1+$B22)^('DCF Model'!C19+0)+'DCF Model'!D45/(1+$B22)^('DCF Model'!C19+1)+'DCF Model'!E45/(1+$B22)^('DCF Model'!C19+2)+'DCF Model'!F45/(1+$B22)^('DCF Model'!C19+3)+'DCF Model'!G45/(1+$B22)^('DCF Model'!C19+4)+('DCF Model'!G39+'DCF Model'!G42)*I$17/(1+$B22)^('DCF Model'!C19+4)-'DCF Model'!C16)*1000000/'DCF Model'!C15,0),"") -> 1341
B23: =$C$3+0.01 -> 0.05405999 | C23: =IFERROR(ROUND(('DCF Model'!C45/(1+$B23)^('DCF Model'!C19+0)+'DCF Model'!D45/(1+$B23)^('DCF Model'!C19+1)+'DCF Model'!E45/(1+$B23)^('DCF Model'!C19+2)+'DCF Model'!F45/(1+$B23)^('DCF Model'!C19+3)+'DCF Model'!G45/(1+$B23)^('DCF Model'!C19+4)+('DCF Model'!G39+'DCF Model'!G42)*C$17/(1+$B23)^('DCF Model'!C19+4)-'DCF Model'!C16)*1000000/'DCF Model'!C15,0),"") -> -158 | D23: =IFERROR(ROUND(('DCF Model'!C45/(1+$B23)^('DCF Model'!C19+0)+'DCF Model'!D45/(1+$B23)^('DCF Model'!C19+1)+'DCF Model'!E45/(1+$B23)^('DCF Model'!C19+2)+'DCF Model'!F45/(1+$B23)^('DCF Model'!C19+3)+'DCF Model'!G45/(1+$B23)^('DCF Model'!C19+4)+('DCF Model'!G39+'DCF Model'!G42)*D$17/(1+$B23)^('DCF Model'!C19+4)-'DCF Model'!C16)*1000000/'DCF Model'!C15,0),"") -> 81 | E23: =IFERROR(ROUND(('DCF Model'!C45/(1+$B23)^('DCF Model'!C19+0)+'DCF Model'!D45/(1+$B23)^('DCF Model'!C19+1)+'DCF Model'!E45/(1+$B23)^('DCF Model'!C19+2)+'DCF Model'!F45/(1+$B23)^('DCF Model'!C19+3)+'DCF Model'!G45/(1+$B23)^('DCF Model'!C19+4)+('DCF Model'!G39+'DCF Model'!G42)*E$17/(1+$B23)^('DCF Model'!C19+4)-'DCF Model'!C16)*1000000/'DCF Model'!C15,0),"") -> 320 | F23: =IFERROR(ROUND(('DCF Model'!C45/(1+$B23)^('DCF Model'!C19+0)+'DCF Model'!D45/(1+$B23)^('DCF Model'!C19+1)+'DCF Model'!E45/(1+$B23)^('DCF Model'!C19+2)+'DCF Model'!F45/(1+$B23)^('DCF Model'!C19+3)+'DCF Model'!G45/(1+$B23)^('DCF Model'!C19+4)+('DCF Model'!G39+'DCF Model'!G42)*F$17/(1+$B23)^('DCF Model'!C19+4)-'DCF Model'!C16)*1000000/'DCF Model'!C15,0),"") -> 558 | G23: =IFERROR(ROUND(('DCF Model'!C45/(1+$B23)^('DCF Model'!C19+0)+'DCF Model'!D45/(1+$B23)^('DCF Model'!C19+1)+'DCF Model'!E45/(1+$B23)^('DCF Model'!C19+2)+'DCF Model'!F45/(1+$B23)^('DCF Model'!C19+3)+'DCF Model'!G45/(1+$B23)^('DCF Model'!C19+4)+('DCF Model'!G39+'DCF Model'!G42)*G$17/(1+$B23)^('DCF Model'!C19+4)-'DCF Model'!C16)*1000000/'DCF Model'!C15,0),"") -> 797 | H23: =IFERROR(ROUND(('DCF Model'!C45/(1+$B23)^('DCF Model'!C19+0)+'DCF Model'!D45/(1+$B23)^('DCF Model'!C19+1)+'DCF Model'!E45/(1+$B23)^('DCF Model'!C19+2)+'DCF Model'!F45/(1+$B23)^('DCF Model'!C19+3)+'DCF Model'!G45/(1+$B23)^('DCF Model'!C19+4)+('DCF Model'!G39+'DCF Model'!G42)*H$17/(1+$B23)^('DCF Model'!C19+4)-'DCF Model'!C16)*1000000/'DCF Model'!C15,0),"") -> 1036 | I23: =IFERROR(ROUND(('DCF Model'!C45/(1+$B23)^('DCF Model'!C19+0)+'DCF Model'!D45/(1+$B23)^('DCF Model'!C19+1)+'DCF Model'!E45/(1+$B23)^('DCF Model'!C19+2)+'DCF Model'!F45/(1+$B23)^('DCF Model'!C19+3)+'DCF Model'!G45/(1+$B23)^('DCF Model'!C19+4)+('DCF Model'!G39+'DCF Model'!G42)*I$17/(1+$B23)^('DCF Model'!C19+4)-'DCF Model'!C16)*1000000/'DCF Model'!C15,0),"") -> 1275
B24: =$C$3+0.015 -> 0.05905999 | C24: =IFERROR(ROUND(('DCF Model'!C45/(1+$B24)^('DCF Model'!C19+0)+'DCF Model'!D45/(1+$B24)^('DCF Model'!C19+1)+'DCF Model'!E45/(1+$B24)^('DCF Model'!C19+2)+'DCF Model'!F45/(1+$B24)^('DCF Model'!C19+3)+'DCF Model'!G45/(1+$B24)^('DCF Model'!C19+4)+('DCF Model'!G39+'DCF Model'!G42)*C$17/(1+$B24)^('DCF Model'!C19+4)-'DCF Model'!C16)*1000000/'DCF Model'!C15,0),"") -> -188 | D24: =IFERROR(ROUND(('DCF Model'!C45/(1+$B24)^('DCF Model'!C19+0)+'DCF Model'!D45/(1+$B24)^('DCF Model'!C19+1)+'DCF Model'!E45/(1+$B24)^('DCF Model'!C19+2)+'DCF Model'!F45/(1+$B24)^('DCF Model'!C19+3)+'DCF Model'!G45/(1+$B24)^('DCF Model'!C19+4)+('DCF Model'!G39+'DCF Model'!G42)*D$17/(1+$B24)^('DCF Model'!C19+4)-'DCF Model'!C16)*1000000/'DCF Model'!C15,0),"") -> 45 | E24: =IFERROR(ROUND(('DCF Model'!C45/(1+$B24)^('DCF Model'!C19+0)+'DCF Model'!D45/(1+$B24)^('DCF Model'!C19+1)+'DCF Model'!E45/(1+$B24)^('DCF Model'!C19+2)+'DCF Model'!F45/(1+$B24)^('DCF Model'!C19+3)+'DCF Model'!G45/(1+$B24)^('DCF Model'!C19+4)+('DCF Model'!G39+'DCF Model'!G42)*E$17/(1+$B24)^('DCF Model'!C19+4)-'DCF Model'!C16)*1000000/'DCF Model'!C15,0),"") -> 278 | F24: =IFERROR(ROUND(('DCF Model'!C45/(1+$B24)^('DCF Model'!C19+0)+'DCF Model'!D45/(1+$B24)^('DCF Model'!C19+1)+'DCF Model'!E45/(1+$B24)^('DCF Model'!C19+2)+'DCF Model'!F45/(1+$B24)^('DCF Model'!C19+3)+'DCF Model'!G45/(1+$B24)^('DCF Model'!C19+4)+('DCF Model'!G39+'DCF Model'!G42)*F$17/(1+$B24)^('DCF Model'!C19+4)-'DCF Model'!C16)*1000000/'DCF Model'!C15,0),"") -> 511 | G24: =IFERROR(ROUND(('DCF Model'!C45/(1+$B24)^('DCF Model'!C19+0)+'DCF Model'!D45/(1+$B24)^('DCF Model'!C19+1)+'DCF Model'!E45/(1+$B24)^('DCF Model'!C19+2)+'DCF Model'!F45/(1+$B24)^('DCF Model'!C19+3)+'DCF Model'!G45/(1+$B24)^('DCF Model'!C19+4)+('DCF Model'!G39+'DCF Model'!G42)*G$17/(1+$B24)^('DCF Model'!C19+4)-'DCF Model'!C16)*1000000/'DCF Model'!C15,0),"") -> 745 | H24: =IFERROR(ROUND(('DCF Model'!C45/(1+$B24)^('DCF Model'!C19+0)+'DCF Model'!D45/(1+$B24)^('DCF Model'!C19+1)+'DCF Model'!E45/(1+$B24)^('DCF Model'!C19+2)+'DCF Model'!F45/(1+$B24)^('DCF Model'!C19+3)+'DCF Model'!G45/(1+$B24)^('DCF Model'!C19+4)+('DCF Model'!G39+'DCF Model'!G42)*H$17/(1+$B24)^('DCF Model'!C19+4)-'DCF Model'!C16)*1000000/'DCF Model'!C15,0),"") -> 978 | I24: =IFERROR(ROUND(('DCF Model'!C45/(1+$B24)^('DCF Model'!C19+0)+'DCF Model'!D45/(1+$B24)^('DCF Model'!C19+1)+'DCF Model'!E45/(1+$B24)^('DCF Model'!C19+2)+'DCF Model'!F45/(1+$B24)^('DCF Model'!C19+3)+'DCF Model'!G45/(1+$B24)^('DCF Model'!C19+4)+('DCF Model'!G39+'DCF Model'!G42)*I$17/(1+$B24)^('DCF Model'!C19+4)-'DCF Model'!C16)*1000000/'DCF Model'!C15,0),"") -> 1211
B26: All values dynamically linked to DCF Model. Headers auto-center on current WACC / Terminal g / Exit Multiple.

Sheet SOTP Cross-Check
B2: SOTP Cross-Check (intended PRIMARY framework -- see note)
B3: AEON is a holding company for many listed/unlisted subsidiaries; a consolidated DCF ('DCF Model' sheet) is an approximation. SOTP is the theoretically correct lens, but see the critical finding below before using this sheet's totals.
B5: CRITICAL FINDING: 3 of 9 originally-in-scope subsidiaries went private in 2025
B6: AEON Mall (8905) | C6: Delisted 2025-06-27 (share exchange -> 100% AEON-owned)
B7: AEON Delight (9787) | C7: Delisted 2025-07-17 (TOB + squeeze-out -> 100% AEON-owned)
B8: Welcia Holdings (3141) | C8: Delisted 2025-11-27 (merged into Tsuruha Holdings as wholly-owned sub)
B10: Only 6 of the 9 remain listed with a market price. Per the source prompt's own fallback instruction, this sheet presents the sum of the 6 remaining listed stakes as an explicit FLOOR value -- it does NOT attempt to price the now-wholly-owned AEON Mall / AEON Delight, the Welcia business now inside Tsuruha, or the GMS/SM retail core (no reliable, non-guessed EBITDA breakdown by segment is available for AEON). The floor will therefore sit far below AEON's actual market cap by construction -- that gap IS the (unquantified) value of the wholly-owned businesses.
B13: Listed Subsidiary / Affiliate Stakes
B14: Company | C14: Ticker | D14: Market Cap (JPY mn) | E14: AEON Ownership % | F14: Implied Stake Value (JPY mn)
B15: AEON Financial Service | C15: 8570.T | D15: 325500 | E15: 0.4817 | F15: =D15*E15 -> 156793.35
B16: Tsuruha Holdings | C16: 3391.T | D16: 1175800 | E16: 0.5033 | F16: =D16*E16 -> 591780.14
B17: AEON Kyushu | C17: 2653.T | D17: 99171 | E17: 0.699 | F17: =D17*E17 -> 69320.529
B18: AEON Hokkaido | C18: 7512.T | D18: 121016 | E18: 0.6562 | F18: =D18*E18 -> 79410.699
B19: Maxvalu Tokai | C19: 8198.T | D19: 107751 | E19: 0.6386 | F19: =D19*E19 -> 68809.789
B20: Ministop | C20: 9946.T | D20: 52871 | E20: 0.4871 | F20: =D20*E20 -> 25753.464
B21: Sum of Listed Stakes (JPY mn) | F21: =SUM(F15:F20) -> 991867.97
B22: Market cap data as of late Jul 2026; ownership % from FY2026/2 yuho 'related companies' disclosures (Tsuruha stake reflects the Jan-2026 TOB result, 50.11%->50.33% via subsequent market purchases).
B24: Non-listed / wholly-owned businesses (AEON Mall, AEON Delight, GMS/SM core, Welcia-in-Tsuruha)
B25: NOT PRICED -- no reliable per-segment EBITDA breakdown available; not guessed (per instruction).
B27: Market Capitalisation Attribution (replaces the negative floor bridge - see Adjustments Log)
B28: AEON market capitalisation | C28: ='Executive Summary'!C9*C32/1000000 -> 3938454.2 | D28: =ROUND(C28/$C$32*1000000,0) -> 1424
B29: Less: AEON share of the 6 remaining listed subsidiaries, at market | C29: =F21 -> 991867.97 | D29: =ROUND(C29/$C$32*1000000,0) -> 359
B30: Implied market value of wholly-owned businesses, net of parent debt | C30: =C28-C29 -> 2946586.3 | D30: =ROUND(C30/$C$32*1000000,0) -> 1065
B31: Share of market cap represented by the 6 listed stakes | C31: =C29/C28 -> 0.25184194
B32: Shares Outstanding | C32: ='DCF Model'!C15 -> 2765768421
B34: Column D is JPY per share. No group-level debt is deducted here: the listed subsidiaries' own borrowings are already inside their market capitalisations, and AEON parent-only net debt is inside the residual on row 30. The earlier construction deducted consolidated net debt of 3,099,169 against only 991,868 of stake value, which was negative by construction and double-counted subsidiary leverage.
B37: Reconciliation against the consolidated DCF
B38: DCF - Exit Multiple: total group equity per share | C38: ='Executive Summary'!C17 -> 657
B39: Comps - EV/EBITDA median: total group equity per share | C39: ='Executive Summary'!C18 -> 772
B40: Market value of the 6 listed stakes alone, per share | C40: =D29 -> 359
B41: Residual left for the wholly-owned core by DCF Exit (row 38 less row 40) | C41: =C38-C40 -> 298
B42: Residual the MARKET pays for the wholly-owned core (price less row 40) | C42: ='Executive Summary'!C9-C40 -> 1065
B44: THE CRUX: the market pays roughly 1,065 per share for the wholly-owned businesses (GMS/SM core, the now-100%-owned AEON Mall and AEON Delight, and the Welcia business inside Tsuruha), while the consolidated DCF Exit method leaves only about 298 per share for them - a gap of roughly 3.6x. Either the DCF materially undervalues the wholly-owned core, or the market does the opposite. Resolving that requires a per-segment EBITDA breakdown, which AEON does not disclose in a form usable here. This is the single most important open question in the model.
B49: Cross-check: Sum of Listed Stakes vs Non-Controlling Interests (book)
B50: Sum of Listed Stakes (JPY mn, AEON's share) | C50: =F21 -> 991867.97
B51: Non-Controlling Interests, book value (JPY mn) | C51: 984094
B52: Difference (JPY mn) | C52: =C50-C51 -> 7773.9709
B53: Difference per share (JPY) | C53: =ROUND(C52/C32*1000000,0) -> 3
B55: NOT a clean apples-to-apples comparison: NCI book value (984,094) covers ALL consolidated subsidiaries (including the now-wholly-owned AEON Mall/AEON Delight, where NCI has since gone to zero post-buyout, and many unlisted subs), while the listed-stakes sum above covers only the 6 companies still listed today. The rough numerical proximity between the two figures is not strong evidence that book-value MI is fairly stated; it is a coincidence of a mixed, shifting subsidiary base, not a controlled comparison.

Sheet Adjustments Log
B2: Manual Adjustments Log — 8267 AEON (finalised 2026-07-30, price 1,424)
B4: # | C4: Sheet / Cell | D4: Was | E4: Now | F4: Why
B5: 1 | C5: Exec Summary!B10, C10, C21, B16, B13 | D5: Target = AVERAGE(C16:C19) = 447 | E5: AVERAGE(C17:C19) = 652 | F5: The Perpetuity Growth method returns a NEGATIVE equity value of -465,130, or -168 per share, and that negative number was being averaged into the Target Price and shown as the bottom of the valuation range. Cause: Year-5 capex of 545,000 is 1.22x Year-5 D&A of 445,000, so terminal FCF is only 157,320; the terminal value of 4,047,782 gives an EV of 3,618,133, below net debt plus MI of 4,083,263. Terminal capex must converge toward D&A when perpetual growth is 0.5%. PGM row kept and labelled INVALID; excluded from Target and range (now 527 - 772). Normalisation sensitivity added at B13: Y5 capex 500,000 -> 182/share, 470,000 -> 416, 445,000 (= D&A) -> 611, which lines up with the Exit method at 657. Capex projections NOT changed.
B6: 2 | C6: Exec Summary!B29, B30 | D6: 380/share, 3.03x, 50.7x, 11.90x | E6: 356/share, 3.23x, 54.2x, 12.29x | F6: Thesis and risk text was written against the earlier 2,590,000,000 share-count assumption. At 2,765,768,421 shares and 1,424 the market cap is 3,938,454, so P/B is 3.232x, P/E 54.19x and EV/EBITDA 12.285x, and minority interests of 984,094 are 356 per share rather than 380. The Comps sheet already carried the correct multiples; only the prose was stale.
B7: 3 | C7: FS!C19:F19, C26:F27, labels B19-B28, notes B30:B34 | D7: see col C | E7: 短信 actuals | F7: EDINET residuals shifted two fiscal years: the FY2026/2 column carried FY2024/2 figures (OCF 368,487 where the actual is 1,126,589; cash 1,064,093 where 現金及び預金 is 1,350,037), so Free Cash Flow read -160,049 for a year that actually generated 598,053. Replaced with 短信 actuals: OCF 433,710 / 368,487 / 566,218 / 1,126,589; cash 1,309,725 / 1,165,536 / 1,258,383 / 1,350,037; interest-bearing debt 3,465,146 / 3,700,013 / 3,832,668 / 4,449,206. Row 28 now reads 3,099,169 for FY2026/2, which is exactly the financial-debt component of 'DCF Model'!C16 = 4,083,263 (the 984,094 balance being MI). Five notes added, including the warning that OCF contains bank deposit and loan flows (ex-bank FY2026/2 FCF was 495,470, not 598,053).
B8: 4 | C8: DCF!C20 | D8: 9,355,439 | E8: 10,715,342 | F8: LTM Revenue held 売上高 only, excluding 総合金融事業における営業収益 (486,237) and その他の営業収益 (873,665), so it did not match base_year_revenue. Reference cell only; stub fraction is 1.0 so there is no valuation effect.
B9: 5 | C9: DCF!C5, C18 | D9: 5.105% / 3.957% | E9: 4.933% / 3.570% | F9: Both had been back-solved from the AVERAGE of the five-year direct projections (547,000 and 424,000 over base revenue) rather than from actuals. They are revenue_pct fallbacks and unused because capex/D&A run on the direct method (rows 42-43 hold absolute values). Rebased on FY2026/2 actuals: capex 528,536 and D&A 382,500 over 10,715,342.
B10: 6 | C10: SOTP!B27:E46 | D10: negative "floor" + discount table | E10: market-cap attribution | F10: The floor bridge deducted CONSOLIDATED net debt of 3,099,169 against only the 991,868 of remaining minority-held listed stakes, producing -762 per share, and the holding-company discount table ran from -762 to -457 with a "vs current price" column reading -153% to -132%. That construction is negative by definition and double-counts the subsidiaries' leverage, which is already inside their market caps. Replaced with an attribution that needs no invented data: market cap 3,938,454 (1,424/share), of which the 6 listed stakes are 991,868 (359/share, 25.2%), leaving 2,946,586 (1,065/share, 74.8%) as the market's valuation of the wholly-owned businesses net of parent debt. A reconciliation against the DCF was added at rows 37-44. The delisting findings and the stake table (rows 5-22) and the NCI cross-check (rows 49-55) were kept unchanged - they are the best work on the sheet.
C11: CONFIRMED CORRECT - not changed | F11: de_ratio = 0.8403 (the explicit override held; had it defaulted to net_debt / market cap it would read 1.1071 and would have treated minority interests as debt, understating the WACC); size_premium = 0.0%; WACC = 4.406%; net_debt = 4,083,263 including the 984,094 MI addback; NWC base days DSO 64.30 / DIH 44.49 / DPO 79.17, matching the 短信 exactly; hist_revenue through hist_operating_income reconcile to the 短信 within 1 for all four years; Comps statistics correctly exclude AEON (ranges are J6:J8) and Net_Debt is defined consistently across all rows including the MI addback; capex history (370,848 / 396,236 / 465,958 / 528,536) was extracted from source rather than left at the estimates in the specification.
C12: OPEN ITEM - share count | D12: DCF!C15 = 2,765,768,421 | F12: The specification carried a fallback of 2,590,000,000; the workbook uses 2,765,768,421 and is internally consistent at that figure throughout (Comps D5, SOTP C32). The higher count is most likely correct because AEON issued new shares in the June 2025 AEON Mall share exchange, which the fallback predated. Worth one confirmation against the 短信 期末発行済株式数 less 期末自己株式数, because every per-share output scales with it: a 2% error moves the target price 2%.
C13: OPEN ITEM - terminal capex | D13: DCF!C43:G43 | F13: Capex is projected at 560,000 / 550,000 / 540,000 / 540,000 / 545,000 against D&A of 400,000 / 415,000 / 425,000 / 435,000 / 445,000. Holding capex at 1.22x D&A in the terminal year is inconsistent with 0.5% perpetual growth and is what makes the PGM method fail. Historically capex has run 4.07% -> 4.15% -> 4.60% -> 4.93% of revenue while D&A ran 3.57%, so the growth-phase gap is real; the issue is only the terminal year. Changing it is a forecast decision and has been left to the analyst.
C14: OPEN ITEM - tax rate | D14: DCF!C6 = 30.62% | F14: The specification proposed 0.40 based on effective rates of 49.9% / 42.2% / 57.4% / 39.9% over FY2023/2 to FY2026/2, which run above statutory because much of the impairment charge (97,486 in FY2026/2) is not deductible and loss-making subsidiaries cannot offset. The workbook uses the statutory 30.62%. That is defensible for a going-concern DCF but is roughly 9 points below realised experience and lifts NOPAT by about 13%. Worth a stated sensitivity.
C15: OPEN ITEM - comps depth | D15: Comps rows 6-8 | F15: Only Seven & i (3382), Pan Pacific (7532) and Nitori (9843) remain in the statistics, so each median is the middle of three. AEON Mall (8905) and Welcia (3141) were correctly dropped from the specification's list because both delisted in 2025. AEON's 2.52% operating margin sits far below Pan Pacific (7.22%) and Nitori (13.76%), so the peer medians describe better businesses; the EV/EBITDA implied value of 772 should be read with that in mind.
