Workbook

Sheet Executive Summary
B1: DISCLAIMER: This is a sample analysis for demonstration purposes only. It does not constitute investment advice.
B3: 株式会社セブン銀行 (8410.T)
B4: Equity Research Report
B6: Company | C6: 株式会社セブン銀行
B7: Ticker | C7: 8410.T (TSE)
B8: Sector | C8: Banking (ATM network / fee-based financial infrastructure)
B9: Current Price | C9: 327
B10: Target Price (Mid) | C10: =ROUND(AVERAGE(C16:C19),0) -> 380
B11: Recommendation | C11: =IF(C12>0.15,"BUY",IF(C12>0.05,"HOLD","SELL")) -> BUY
B12: Upside / Downside | C12: =(C10-C9)/C9 -> 0.16207951
B14: Valuation Summary
B15: Methodology | C15: Implied Value (JPY) | D15: vs Current Price
B16: DCF - Perpetuity Growth | C16: ='DCF Model'!C55 -> 389 | D16: =(C16-C9)/C9 -> 0.18960245
B17: DCF - Exit Multiple | C17: ='DCF Model'!C64 -> 431 | D17: =(C17-C9)/C9 -> 0.31804281
B18: Comps - EV/EBITDA Median | C18: ='Comps Analysis'!C27 -> 505 | D18: =IF(ISNUMBER(C18),(C18-C9)/C9,"N/A") -> 0.54434251
B19: Comps - PER Median | C19: ='Comps Analysis'!C28 -> 196 | D19: =IF(ISNUMBER(C19),(C19-C9)/C9,"N/A") -> -0.40061162
B21: Integrated Valuation Range | C21: =MIN(C16:C19)&" - "&MAX(C16:C19) -> 196 - 505
B23: Key Investment Thesis
B24: 1. The reported 26% net income decline is misleading -- ordinary profit was essentially flat at 30,165 (-0.4%). The drop came from an 8,456 impairment on the credit card business and new-ATM replacement costs, both below the ordinary line. The franchise did not deteriorate; the accounting did.
B25: 2. Cashless payment adoption is currently a TAILWIND, not a headwind. ATM transaction volume rose because consumers load cash onto cashless wallets at Seven Bank ATMs. ATM units reached 28,536 (+1.9%) with 109.2 daily transactions per unit. The bear case requires this to reverse, which it has not yet.
B26: 3. Fee-based infrastructure economics inside a banking licence. 91.3% of ordinary income is fee income (ATM fees alone 169,240, or 76.9%); interest income is only 7.2%. This is an ATM network operator, and should be valued on franchise durability and ROE, not on net interest margin.
B28: Key Risks
B29: 1. ROE sits almost exactly at the cost of equity. FY2026/3 ROE was 4.8% (6.1% on FY2027/3 guidance) against an estimated 6.2% cost of equity. When ROE equals Ke, intrinsic value collapses to book value, and the shares already trade at 1.065x book. There is little valuation cushion.
B30: 2. Capex exceeds depreciation during the ATM replacement cycle. Depreciation is roughly 30,586 while the fourth-generation ATM rollout keeps capex elevated. 28,536 units must be refreshed on a recurring cycle regardless of demand.
B31: 3. Payout ratio near 90% leaves almost no retained growth. Sustainable growth = ROE x (1 - payout) is well under 1%, so the dividend is the return. Any ROE shortfall hits both the dividend and the terminal value simultaneously.

Sheet Financial Statements
B2: 株式会社セブン銀行 - Historical Financials (JPY mn)
C4: FY2024/3 | D4: FY2025/3 | E4: FY2026/3
B5: Income Statement
B6: Revenue | C6: 197877 | D6: 214408 | E6: 220025
B7: COGS | C7: 54594 | D7: 57759 | E7: 58729
B8: Gross Profit | C8: =C6-C7 -> 143283 | D8: =D6-D7 -> 156649 | E8: =E6-E7 -> 161296
B9: Gross Margin | C9: =C8/C6 -> 0.72410134 | D9: =D8/D6 -> 0.73061173 | E9: =E8/E6 -> 0.73308033
B10: SGA | C10: 112757 | D10: 126357 | E10: 131129
B11: Operating Income | C11: 30526 | D11: 30289 | E11: 30165
B12: Net Income | C12: 31970 | D12: 18221 | E12: 13476
B13: Operating Margin | C13: =C11/C6 -> 0.15426755 | D13: =D11/D6 -> 0.14126805 | E13: =E11/E6 -> 0.13709806
B14: Net Margin | C14: =C12/C6 -> 0.16156501 | D14: =D12/D6 -> 0.084982836 | E14: =E12/E6 -> 0.061247586
B15: Revenue Growth (YoY) | C15: n/a | D15: =(D6-C6)/C6 -> 0.083541796 | E15: =(E6-D6)/D6 -> 0.026197717
B16: Operating Income Growth (YoY) | C16: n/a | D16: =(D11-C11)/C11 -> -0.0077638734 | E16: =(E11-D11)/D11 -> -0.0040938955
B18: Cash Flow Statement
B19: Operating Cash Flow | C19: 136039 | D19: 41311 | E19: 66577
B20: Capex | C20: 17739 | D20: 23206 | E20: 9947
B21: Free Cash Flow | C21: =C19-C20 -> 118300 | D21: =D19-D20 -> 18105 | E21: =E19-E20 -> 56630
B22: FCF Margin | C22: =C21/C6 -> 0.59784614 | D22: =D21/D6 -> 0.084441812 | E22: =E21/E6 -> 0.25737984
B23: Capex / Revenue | C23: =C20/C6 -> 0.089646599 | D23: =D20/D6 -> 0.1082329 | E23: =E20/E6 -> 0.045208499
B25: Balance Sheet Highlights
B26: Cash & Deposits | C26: 937945 | D26: 931404 | E26: 950256
B27: Short-term Debt | C27: 105000 | D27: 105000 | E27: 85000
B28: Net Debt (Cash) | C28: =C27-C26 -> -832945 | D28: =D27-D26 -> -826404 | E28: =E27-E26 -> -865256

Sheet DCF Model
B2: DCF Valuation Model - 株式会社セブン銀行
B4: Assumptions
B5: Capex / Revenue | C5: 0.15998182
B6: Effective Tax Rate | C6: 0.35
B7: Risk-Free Rate | C7: 0.023
B8: Beta | C8: 0.65
B9: Equity Risk Premium | C9: 0.06
B10: Size Premium | C10: 0
B11: After-tax Cost of Debt | C11: 0.01
B12: D/E Ratio | C12: 0
B13: Terminal Growth Rate | C13: 0.005
B14: Exit Multiple (EV/EBITDA) | C14: 7
B15: Fully Diluted Shares | C15: 1110000000
B16: Net Debt (JPY mn) | C16: 0
... B20: LTM Revenue (JPY mn) | C20: 221294
B22: WACC Calculation
B23: Cost of Equity (Ke) | C23: =C7+C8*C9+C10 -> 0.062
B24: Weight of Equity | C24: =1/(1+C12) -> 1
B25: Weight of Debt | C25: =C12/(1+C12) -> 0
B26: WACC | C26: =C23*C24+C11*C25 -> 0.062
B27: Active Scenario | C27: Base | D27: =MATCH(C27,B69:B73,0) -> 1
B28: Projected Free Cash Flow
C29: FY2027(E) | D29: FY2028(E) | E29: FY2029(E) | F29: FY2030(E) | G29: FY2031(E)
B30: Revenue Growth (YoY) | C30: =CHOOSE($D$27,C69,C70,C71,C72,C73) -> 0.05 | D30: =CHOOSE($D$27,D69,D70,D71,D72,D73) -> 0.035 | E30: =CHOOSE($D$27,E69,E70,E71,E72,E73) -> 0.03 | F30: =CHOOSE($D$27,F69,F70,F71,F72,F73) -> 0.025 | G30: =CHOOSE($D$27,G69,G70,G71,G72,G73) -> 0.02
B31: COGS % of Revenue | C31: =CHOOSE($D$27,C76,C77,C78,C79,C80) -> 0.265 | D31: =CHOOSE($D$27,D76,D77,D78,D79,D80) -> 0.265 | E31: =CHOOSE($D$27,E76,E77,E78,E79,E80) -> 0.265 | F31: =CHOOSE($D$27,F76,F77,F78,F79,F80) -> 0.265 | G31: =CHOOSE($D$27,G76,G77,G78,G79,G80) -> 0.265
B32: SGA % of Revenue | C32: =CHOOSE($D$27,C83,C84,C85,C86,C87) -> 0.61 | D32: =CHOOSE($D$27,D83,D84,D85,D86,D87) -> 0.6 | E32: =CHOOSE($D$27,E83,E84,E85,E86,E87) -> 0.59 | F32: =CHOOSE($D$27,F83,F84,F85,F86,F87) -> 0.585 | G32: =CHOOSE($D$27,G83,G84,G85,G86,G87) -> 0.585
B33: Revenue | C33: =C17*(1+C30) -> 231026.25 | D33: =C33*(1+D30) -> 239112.17 | E33: =D33*(1+E30) -> 246285.53 | F33: =E33*(1+F30) -> 252442.67 | G33: =F33*(1+G30) -> 257491.53
B34: COGS | C34: =C33*C31 -> 61221.956 | D34: =D33*D31 -> 63364.725 | E34: =E33*E31 -> 65265.666 | F34: =F33*F31 -> 66897.308 | G34: =G33*G31 -> 68235.254
B35: Gross Profit | C35: =C33-C34 -> 169804.29 | D35: =D33-D34 -> 175747.44 | E35: =E33-E34 -> 181019.87 | F35: =F33-F34 -> 185545.36 | G35: =G33-G34 -> 189256.27
B36: Gross Margin | C36: =C35/C33 -> 0.735 | D36: =D35/D33 -> 0.735 | E36: =E35/E33 -> 0.735 | F36: =F35/F33 -> 0.735 | G36: =G35/G33 -> 0.735
B37: SGA Expense | C37: =C33*C32 -> 140926.01 | D37: =D33*D32 -> 143467.3 | E37: =E33*E32 -> 145308.46 | F37: =F33*F32 -> 147678.96 | G37: =G33*G32 -> 150632.54
B38: Implied Operating Margin | C38: =(C35-C37)/C33 -> 0.125 | D38: =(D35-D37)/D33 -> 0.135 | E38: =(E35-E37)/E33 -> 0.145 | F38: =(F35-F37)/F33 -> 0.15 | G38: =(G35-G37)/G33 -> 0.15
B39: Operating Income (EBIT) | C39: =C35-C37 -> 28878.281 | D39: =D35-D37 -> 32280.143 | E39: =E35-E37 -> 35711.402 | F39: =F35-F37 -> 37866.401 | G39: =G35-G37 -> 38623.729
B40: Less: Tax | C40: =MAX(0,C39*C6) -> 10107.398 | D40: =MAX(0,D39*C6) -> 11298.05 | E40: =MAX(0,E39*C6) -> 12498.991 | F40: =MAX(0,F39*C6) -> 13253.24 | G40: =MAX(0,G39*C6) -> 13518.305
B41: NOPAT | C41: =C39-C40 -> 18770.883 | D41: =D39-D40 -> 20982.093 | E41: =E39-E40 -> 23212.412 | F41: =F39-F40 -> 24613.161 | G41: =G39-G40 -> 25105.424
B42: Plus: D&A | C42: 32000 | D42: 33000 | E42: 33500 | F42: 34000 | G42: 34500
B43: Less: Capex | C43: 38000 | D43: 36000 | E43: 34000 | F43: 34000 | G43: 34000
B44: Change in NWC | C44: ='NWC Schedule'!D19 -> 0 | D44: ='NWC Schedule'!E19 -> 0 | E44: ='NWC Schedule'!F19 -> 0 | F44: ='NWC Schedule'!G19 -> 0 | G44: ='NWC Schedule'!H19 -> 0
B45: Unlevered Free Cash Flow | C45: =C41+C42-C43-C44 -> 12770.883 | D45: =D41+D42-D43-D44 -> 17982.093 | E45: =E41+E42-E43-E44 -> 22712.412 | F45: =F41+F42-F43-F44 -> 24613.161 | G45: =G41+G42-G43-G44 -> 25605.424
B46: Discount Factor | C46: =1/(1+C26)^(C19+0) -> 0.97037085 | D46: =1/(1+C26)^(C19+1) -> 0.9137202 | E46: =1/(1+C26)^(C19+2) -> 0.86037683 | F46: =1/(1+C26)^(C19+3) -> 0.81014768 | G46: =1/(1+C26)^(C19+4) -> 0.76285092
B47: PV of FCF | C47: =C45*C46 -> 12392.492 | D47: =D45*D46 -> 16430.601 | E47: =E45*E46 -> 19541.233 | F47: =F45*F46 -> 19940.295 | G47: =G45*G46 -> 19533.121
B49: Valuation - Perpetuity Growth Method
B50: Sum of PV of FCFs | C50: =SUM(C47:G47) -> 87837.742
B51: Terminal Value (PGM) | C51: =G45*(1+C13)/(C26-C13) -> 451464.05
B52: PV of Terminal Value | C52: =C51*G46 -> 344399.77
B53: Enterprise Value | C53: =C50+C52 -> 432237.51
B54: Equity Value | C54: =C53-C16 -> 432237.51
B55: Implied Share Price (PGM) | C55: =ROUND(C54*1000000/C15,0) -> 389
B57: Valuation - Exit Multiple Method
B58: Sum of PV of FCFs | C58: =C50 -> 87837.742
B59: Year 5 EBITDA | C59: =G39+G42 -> 73123.729
B60: Terminal Value (Exit Multiple) | C60: =C59*C14 -> 511866.1
B61: PV of Terminal Value | C61: =C60*G46 -> 390477.53
B62: Enterprise Value | C62: =C58+C61 -> 478315.27
B63: Equity Value | C63: =C62-C16 -> 478315.27
B64: Implied Share Price (Exit Multiple) | C64: =ROUND(C63*1000000/C15,0) -> 431
B66: Scenario Input Matrix
C67: Year 1 | D67: Year 2 | E67: Year 3 | F67: Year 4 | G67: Year 5
B68: Revenue Growth (YoY)
B69: Base | C69: 0.05 | D69: 0.035 | E69: 0.03 | F69: 0.025 | G69: 0.02
B70: Upside | C70: 0.09 | D70: 0.07 | E70: 0.06 | F70: 0.05 | G70: 0.045
B71: Management | C71: 0.07 | D71: 0.04 | E71: 0.03 | F71: 0.025 | G71: 0.02
B72: Downside 1 | C72: 0.02 | D72: 0 | E72: -0.01 | F72: -0.01 | G72: -0.01
B73: Downside 2 | C73: -0.02 | D73: -0.04 | E73: -0.04 | F73: -0.03 | G73: -0.03
B75: COGS % of Revenue
B76: Base | C76: 0.265 | D76: 0.265 | E76: 0.265 | F76: 0.265 | G76: 0.265
B77: Upside | C77: 0.26 | D77: 0.26 | E77: 0.26 | F77: 0.26 | G77: 0.26
B78: Management | C78: 0.265 | D78: 0.265 | E78: 0.265 | F78: 0.265 | G78: 0.265
B79: Downside 1 | C79: 0.275 | D79: 0.275 | E79: 0.275 | F79: 0.275 | G79: 0.275
B80: Downside 2 | C80: 0.285 | D80: 0.285 | E80: 0.285 | F80: 0.285 | G80: 0.285
B82: SGA % of Revenue
B83: Base | C83: 0.61 | D83: 0.6 | E83: 0.59 | F83: 0.585 | G83: 0.585
B84: Upside | C84: 0.605 | D84: 0.59 | E84: 0.575 | F84: 0.57 | G84: 0.565
B85: Management | C85: 0.61 | D85: 0.605 | E85: 0.6 | F85: 0.595 | G85: 0.595
B86: Downside 1 | C86: 0.615 | D86: 0.625 | E86: 0.625 | F86: 0.62 | G86: 0.62
B87: Downside 2 | C87: 0.625 | D87: 0.65 | E87: 0.655 | F87: 0.65 | G87: 0.65

Sheet NWC Schedule
B2: NWC Schedule - 株式会社セブン銀行
B4: Working Capital Drivers (% of Revenue) | C4: Base Year | D4: FY2027(E) | E4: FY2028(E) | F4: FY2029(E) | G4: FY2030(E) | H4: FY2031(E)
B5: NWC % of Revenue | C5: =C18/C9 -> 0 | D5: =CHOOSE('DCF Model'!$D$27,D25,D26,D27,D28,D29) -> 0 | E5: =CHOOSE('DCF Model'!$D$27,E25,E26,E27,E28,E29) -> 0 | F5: =CHOOSE('DCF Model'!$D$27,F25,F26,F27,F28,F29) -> 0 | G5: =CHOOSE('DCF Model'!$D$27,G25,G26,G27,G28,G29) -> 0 | H5: =CHOOSE('DCF Model'!$D$27,H25,H26,H27,H28,H29) -> 0
B6: — | C6: — | D6: — | E6: — | F6: — | G6: — | H6: —
B7: — | C7: — | D7: — | E7: — | F7: — | G7: — | H7: —
B8: P&L Reference (JPY mn)
B9: Revenue | C9: 220025 | D9: ='DCF Model'!C33 -> 231026.25 | E9: ='DCF Model'!D33 -> 239112.17 | F9: ='DCF Model'!E33 -> 246285.53 | G9: ='DCF Model'!F33 -> 252442.67 | H9: ='DCF Model'!G33 -> 257491.53
B10: — | C10: — | D10: — | E10: — | F10: — | G10: — | H10: —
B11: Working Capital Items (JPY mn)
B12: — | C12: — | D12: — | E12: — | F12: — | G12: — | H12: —
B13: — | C13: — | D13: — | E13: — | F13: — | G13: — | H13: —
B14: — | C14: — | D14: — | E14: — | F14: — | G14: — | H14: —
B15: — | C15: — | D15: — | E15: — | F15: — | G15: — | H15: —
B16: — | C16: — | D16: — | E16: — | F16: — | G16: — | H16: —
B17: Net Working Capital (JPY mn)
B18: Net Working Capital | C18: 0 | D18: =D9*D5 -> 0 | E18: =E9*E5 -> 0 | F18: =F9*F5 -> 0 | G18: =G9*G5 -> 0 | H18: =H9*H5 -> 0
B19: Change in NWC | C19: n/a | D19: =D18-C18 -> 0 | E19: =E18-D18 -> 0 | F19: =F18-E18 -> 0 | G19: =G18-F18 -> 0 | H19: =H18-G18 -> 0
B22: Scenario Input Matrix (NWC % of Revenue)
D23: FY2027(E) | E23: FY2028(E) | F23: FY2029(E) | G23: FY2030(E) | H23: FY2031(E)
B24: NWC % of Revenue
B25: Base | D25: 0 | E25: 0 | F25: 0 | G25: 0 | H25: 0
B26: Upside | D26: 0 | E26: 0 | F26: 0 | G26: 0 | H26: 0
B27: Management | D27: 0 | E27: 0 | F27: 0 | G27: 0 | H27: 0
B28: Downside 1 | D28: 0 | E28: 0 | F28: 0 | G28: 0 | H28: 0
B29: Downside 2 | D29: 0 | E29: 0 | F29: 0 | G29: 0 | H29: 0

Sheet Comps Analysis
B2: Comparable Company Analysis
B4: Company | C4: Ticker | D4: Mkt Cap (JPY mn) | E4: EV (JPY mn) | F4: Revenue (JPY mn) | G4: EBITDA (JPY mn) | H4: Op Income (JPY mn) | I4: Net Income (JPY mn) | J4: EV/EBITDA | K4: EV/Revenue | L4: PER | M4: PBR | N4: Op Margin | O4: ROE
B5: Seven Bank | C5: 8410.T | D5: 298590 | E5: 298590 | F5: 220025 | G5: 60751 | H5: 30165 | I5: 13476 | J5: =E5/G5 -> 4.9149808 | K5: =E5/F5 -> 1.3570731 | L5: =D5/I5 -> 22.157168 | M5: 1.0645261 | N5: =H5/F5 -> 0.13709806 | O5: 0.048044322
B6: Rakuten Bank | C6: 5838.T | D6: 950497 | E6: 950497 | F6: 255579 | G6: 103091 | H6: 103091 | I6: 73072 | J6: =E6/G6 -> 9.2199804 | K6: =E6/F6 -> 3.7189949 | L6: =D6/I6 -> 13.007677 | M6: 2.4483652 | N6: =H6/F6 -> 0.40336256 | O6: 0.18822463
B7: Japan Post Bank | C7: 7182.T | D7: 11500000 | E7: 11500000 | F7: 2852200 | G7: 759100 | H7: 759100 | I7: 525500 | J7: =E7/G7 -> 15.149519 | K7: =E7/F7 -> 4.0319753 | L7: =D7/I7 -> 21.88392 | M7: 1.2419006 | N7: =H7/F7 -> 0.26614543 | O7: 0.05674946
B8: AEON Financial Service | C8: 8570.T | D8: 340000 | E8: 340000 | F8: 569370 | G8: 60693 | H8: 60693 | I8: 21092 | J8: =E8/G8 -> 5.601964 | K8: =E8/F8 -> 0.59715124 | L8: =D8/I8 -> 16.119856 | M8: 0.7328913 | N8: =H8/F8 -> 0.10659676 | O8: 0.045465127
B14: Statistics
B15: 25th Percentile | D15: =PERCENTILE(J6:J8,0.25) -> 7.4109722 | E15: =PERCENTILE(K6:K8,0.25) -> 2.1580731 | F15: =PERCENTILE(L6:L8,0.25) -> 14.563767 | G15: =PERCENTILE(M6:M8,0.25) -> 0.98739597 | H15: =PERCENTILE(N6:N8,0.25) -> 0.1863711 | I15: =PERCENTILE(O6:O8,0.25) -> 0.051107294
B16: Median (50th) | D16: =MEDIAN(J6:J8) -> 9.2199804 | E16: =MEDIAN(K6:K8) -> 3.7189949 | F16: =MEDIAN(L6:L8) -> 16.119856 | G16: =MEDIAN(M6:M8) -> 1.2419006 | H16: =MEDIAN(N6:N8) -> 0.26614543 | I16: =MEDIAN(O6:O8) -> 0.05674946
B17: 75th Percentile | D17: =PERCENTILE(J6:J8,0.75) -> 12.18475 | E17: =PERCENTILE(K6:K8,0.75) -> 3.8754851 | F17: =PERCENTILE(L6:L8,0.75) -> 19.001888 | G17: =PERCENTILE(M6:M8,0.75) -> 1.8451329 | H17: =PERCENTILE(N6:N8,0.75) -> 0.334754 | I17: =PERCENTILE(O6:O8,0.75) -> 0.12248704
B19: Implied Valuation for 株式会社セブン銀行
B20: 株式会社セブン銀行 Financials
B21: EBITDA (JPY mn) | C21: 60751
B22: Net Income (JPY mn) | C22: 13476
B23: Shares Outstanding | C23: 1110000000
B24: Net Debt (JPY mn) | C24: 0
B26: Implied Share Price (Median Multiples)
B27: Via EV/EBITDA (Median) | C27: =ROUND((C21*D16-C24)*1000000/C23,0) -> 505
B28: Via PER (Median) | C28: =ROUND(C22*F16*1000000/C23,0) -> 196

Sheet Sensitivity Analysis
B2: Sensitivity Analysis
B3: Current WACC: | C3: ='DCF Model'!C26 -> 0.062 | E3: Terminal g: | F3: ='DCF Model'!C13 -> 0.005 | H3: Exit Multiple: | I3: ='DCF Model'!C14 -> 7
B5: Table 1: WACC vs Terminal Growth Rate (PGM - Implied Share Price, JPY)
B6: WACC \ Terminal g | C6: =$F$3-0.0075 -> -0.0025 | D6: =$F$3-0.005 -> 0 | E6: =$F$3-0.0025 -> 0.0025 | F6: =$F$3 -> 0.005 | G6: =$F$3+0.0025 -> 0.0075 | H6: =$F$3+0.005 -> 0.01 | I6: =$F$3+0.0075 -> 0.0125
B7: =$C$3-0.015 -> 0.047 | C7: =IFERROR(ROUND(('DCF Model'!C45/(1+$B7)^('DCF Model'!C19+0)+'DCF Model'!D45/(1+$B7)^('DCF Model'!C19+1)+'DCF Model'!E45/(1+$B7)^('DCF Model'!C19+2)+'DCF Model'!F45/(1+$B7)^('DCF Model'!C19+3)+'DCF Model'!G45/(1+$B7)^('DCF Model'!C19+4)+'DCF Model'!G45*(1+C$6)/($B7-C$6)/(1+$B7)^('DCF Model'!C19+4)-'DCF Model'!C16)*1000000/'DCF Model'!C15,0),"") -> 460 | D7: =IFERROR(ROUND(('DCF Model'!C45/(1+$B7)^('DCF Model'!C19+0)+'DCF Model'!D45/(1+$B7)^('DCF Model'!C19+1)+'DCF Model'!E45/(1+$B7)^('DCF Model'!C19+2)+'DCF Model'!F45/(1+$B7)^('DCF Model'!C19+3)+'DCF Model'!G45/(1+$B7)^('DCF Model'!C19+4)+'DCF Model'!G45*(1+D$6)/($B7-D$6)/(1+$B7)^('DCF Model'!C19+4)-'DCF Model'!C16)*1000000/'DCF Model'!C15,0),"") -> 481 | E7: =IFERROR(ROUND(('DCF Model'!C45/(1+$B7)^('DCF Model'!C19+0)+'DCF Model'!D45/(1+$B7)^('DCF Model'!C19+1)+'DCF Model'!E45/(1+$B7)^('DCF Model'!C19+2)+'DCF Model'!F45/(1+$B7)^('DCF Model'!C19+3)+'DCF Model'!G45/(1+$B7)^('DCF Model'!C19+4)+'DCF Model'!G45*(1+E$6)/($B7-E$6)/(1+$B7)^('DCF Model'!C19+4)-'DCF Model'!C16)*1000000/'DCF Model'!C15,0),"") -> 505 | F7: =IFERROR(ROUND(('DCF Model'!C45/(1+$B7)^('DCF Model'!C19+0)+'DCF Model'!D45/(1+$B7)^('DCF Model'!C19+1)+'DCF Model'!E45/(1+$B7)^('DCF Model'!C19+2)+'DCF Model'!F45/(1+$B7)^('DCF Model'!C19+3)+'DCF Model'!G45/(1+$B7)^('DCF Model'!C19+4)+'DCF Model'!G45*(1+F$6)/($B7-F$6)/(1+$B7)^('DCF Model'!C19+4)-'DCF Model'!C16)*1000000/'DCF Model'!C15,0),"") -> 531 | G7: =IFERROR(ROUND(('DCF Model'!C45/(1+$B7)^('DCF Model'!C19+0)+'DCF Model'!D45/(1+$B7)^('DCF Model'!C19+1)+'DCF Model'!E45/(1+$B7)^('DCF Model'!C19+2)+'DCF Model'!F45/(1+$B7)^('DCF Model'!C19+3)+'DCF Model'!G45/(1+$B7)^('DCF Model'!C19+4)+'DCF Model'!G45*(1+G$6)/($B7-G$6)/(1+$B7)^('DCF Model'!C19+4)-'DCF Model'!C16)*1000000/'DCF Model'!C15,0),"") -> 561 | H7: =IFERROR(ROUND(('DCF Model'!C45/(1+$B7)^('DCF Model'!C19+0)+'DCF Model'!D45/(1+$B7)^('DCF Model'!C19+1)+'DCF Model'!E45/(1+$B7)^('DCF Model'!C19+2)+'DCF Model'!F45/(1+$B7)^('DCF Model'!C19+3)+'DCF Model'!G45/(1+$B7)^('DCF Model'!C19+4)+'DCF Model'!G45*(1+H$6)/($B7-H$6)/(1+$B7)^('DCF Model'!C19+4)-'DCF Model'!C16)*1000000/'DCF Model'!C15,0),"") -> 594 | I7: =IFERROR(ROUND(('DCF Model'!C45/(1+$B7)^('DCF Model'!C19+0)+'DCF Model'!D45/(1+$B7)^('DCF Model'!C19+1)+'DCF Model'!E45/(1+$B7)^('DCF Model'!C19+2)+'DCF Model'!F45/(1+$B7)^('DCF Model'!C19+3)+'DCF Model'!G45/(1+$B7)^('DCF Model'!C19+4)+'DCF Model'!G45*(1+I$6)/($B7-I$6)/(1+$B7)^('DCF Model'!C19+4)-'DCF Model'!C16)*1000000/'DCF Model'!C15,0),"") -> 633
B8: =$C$3-0.01 -> 0.052 | C8: =IFERROR(ROUND(('DCF Model'!C45/(1+$B8)^('DCF Model'!C19+0)+'DCF Model'!D45/(1+$B8)^('DCF Model'!C19+1)+'DCF Model'!E45/(1+$B8)^('DCF Model'!C19+2)+'DCF Model'!F45/(1+$B8)^('DCF Model'!C19+3)+'DCF Model'!G45/(1+$B8)^('DCF Model'!C19+4)+'DCF Model'!G45*(1+C$6)/($B8-C$6)/(1+$B8)^('DCF Model'!C19+4)-'DCF Model'!C16)*1000000/'DCF Model'!C15,0),"") -> 417 | D8: =IFERROR(ROUND(('DCF Model'!C45/(1+$B8)^('DCF Model'!C19+0)+'DCF Model'!D45/(1+$B8)^('DCF Model'!C19+1)+'DCF Model'!E45/(1+$B8)^('DCF Model'!C19+2)+'DCF Model'!F45/(1+$B8)^('DCF Model'!C19+3)+'DCF Model'!G45/(1+$B8)^('DCF Model'!C19+4)+'DCF Model'!G45*(1+D$6)/($B8-D$6)/(1+$B8)^('DCF Model'!C19+4)-'DCF Model'!C16)*1000000/'DCF Model'!C15,0),"") -> 434 | E8: =IFERROR(ROUND(('DCF Model'!C45/(1+$B8)^('DCF Model'!C19+0)+'DCF Model'!D45/(1+$B8)^('DCF Model'!C19+1)+'DCF Model'!E45/(1+$B8)^('DCF Model'!C19+2)+'DCF Model'!F45/(1+$B8)^('DCF Model'!C19+3)+'DCF Model'!G45/(1+$B8)^('DCF Model'!C19+4)+'DCF Model'!G45*(1+E$6)/($B8-E$6)/(1+$B8)^('DCF Model'!C19+4)-'DCF Model'!C16)*1000000/'DCF Model'!C15,0),"") -> 453 | F8: =IFERROR(ROUND(('DCF Model'!C45/(1+$B8)^('DCF Model'!C19+0)+'DCF Model'!D45/(1+$B8)^('DCF Model'!C19+1)+'DCF Model'!E45/(1+$B8)^('DCF Model'!C19+2)+'DCF Model'!F45/(1+$B8)^('DCF Model'!C19+3)+'DCF Model'!G45/(1+$B8)^('DCF Model'!C19+4)+'DCF Model'!G45*(1+F$6)/($B8-F$6)/(1+$B8)^('DCF Model'!C19+4)-'DCF Model'!C16)*1000000/'DCF Model'!C15,0),"") -> 474 | G8: =IFERROR(ROUND(('DCF Model'!C45/(1+$B8)^('DCF Model'!C19+0)+'DCF Model'!D45/(1+$B8)^('DCF Model'!C19+1)+'DCF Model'!E45/(1+$B8)^('DCF Model'!C19+2)+'DCF Model'!F45/(1+$B8)^('DCF Model'!C19+3)+'DCF Model'!G45/(1+$B8)^('DCF Model'!C19+4)+'DCF Model'!G45*(1+G$6)/($B8-G$6)/(1+$B8)^('DCF Model'!C19+4)-'DCF Model'!C16)*1000000/'DCF Model'!C15,0),"") -> 497 | H8: =IFERROR(ROUND(('DCF Model'!C45/(1+$B8)^('DCF Model'!C19+0)+'DCF Model'!D45/(1+$B8)^('DCF Model'!C19+1)+'DCF Model'!E45/(1+$B8)^('DCF Model'!C19+2)+'DCF Model'!F45/(1+$B8)^('DCF Model'!C19+3)+'DCF Model'!G45/(1+$B8)^('DCF Model'!C19+4)+'DCF Model'!G45*(1+H$6)/($B8-H$6)/(1+$B8)^('DCF Model'!C19+4)-'DCF Model'!C16)*1000000/'DCF Model'!C15,0),"") -> 523 | I8: =IFERROR(ROUND(('DCF Model'!C45/(1+$B8)^('DCF Model'!C19+0)+'DCF Model'!D45/(1+$B8)^('DCF Model'!C19+1)+'DCF Model'!E45/(1+$B8)^('DCF Model'!C19+2)+'DCF Model'!F45/(1+$B8)^('DCF Model'!C19+3)+'DCF Model'!G45/(1+$B8)^('DCF Model'!C19+4)+'DCF Model'!G45*(1+I$6)/($B8-I$6)/(1+$B8)^('DCF Model'!C19+4)-'DCF Model'!C16)*1000000/'DCF Model'!C15,0),"") -> 552
B9: =$C$3-0.005 -> 0.057 | C9: =IFERROR(ROUND(('DCF Model'!C45/(1+$B9)^('DCF Model'!C19+0)+'DCF Model'!D45/(1+$B9)^('DCF Model'!C19+1)+'DCF Model'!E45/(1+$B9)^('DCF Model'!C19+2)+'DCF Model'!F45/(1+$B9)^('DCF Model'!C19+3)+'DCF Model'!G45/(1+$B9)^('DCF Model'!C19+4)+'DCF Model'!G45*(1+C$6)/($B9-C$6)/(1+$B9)^('DCF Model'!C19+4)-'DCF Model'!C16)*1000000/'DCF Model'!C15,0),"") -> 381 | D9: =IFERROR(ROUND(('DCF Model'!C45/(1+$B9)^('DCF Model'!C19+0)+'DCF Model'!D45/(1+$B9)^('DCF Model'!C19+1)+'DCF Model'!E45/(1+$B9)^('DCF Model'!C19+2)+'DCF Model'!F45/(1+$B9)^('DCF Model'!C19+3)+'DCF Model'!G45/(1+$B9)^('DCF Model'!C19+4)+'DCF Model'!G45*(1+D$6)/($B9-D$6)/(1+$B9)^('DCF Model'!C19+4)-'DCF Model'!C16)*1000000/'DCF Model'!C15,0),"") -> 396 | E9: =IFERROR(ROUND(('DCF Model'!C45/(1+$B9)^('DCF Model'!C19+0)+'DCF Model'!D45/(1+$B9)^('DCF Model'!C19+1)+'DCF Model'!E45/(1+$B9)^('DCF Model'!C19+2)+'DCF Model'!F45/(1+$B9)^('DCF Model'!C19+3)+'DCF Model'!G45/(1+$B9)^('DCF Model'!C19+4)+'DCF Model'!G45*(1+E$6)/($B9-E$6)/(1+$B9)^('DCF Model'!C19+4)-'DCF Model'!C16)*1000000/'DCF Model'!C15,0),"") -> 411 | F9: =IFERROR(ROUND(('DCF Model'!C45/(1+$B9)^('DCF Model'!C19+0)+'DCF Model'!D45/(1+$B9)^('DCF Model'!C19+1)+'DCF Model'!E45/(1+$B9)^('DCF Model'!C19+2)+'DCF Model'!F45/(1+$B9)^('DCF Model'!C19+3)+'DCF Model'!G45/(1+$B9)^('DCF Model'!C19+4)+'DCF Model'!G45*(1+F$6)/($B9-F$6)/(1+$B9)^('DCF Model'!C19+4)-'DCF Model'!C16)*1000000/'DCF Model'!C15,0),"") -> 428 | G9: =IFERROR(ROUND(('DCF Model'!C45/(1+$B9)^('DCF Model'!C19+0)+'DCF Model'!D45/(1+$B9)^('DCF Model'!C19+1)+'DCF Model'!E45/(1+$B9)^('DCF Model'!C19+2)+'DCF Model'!F45/(1+$B9)^('DCF Model'!C19+3)+'DCF Model'!G45/(1+$B9)^('DCF Model'!C19+4)+'DCF Model'!G45*(1+G$6)/($B9-G$6)/(1+$B9)^('DCF Model'!C19+4)-'DCF Model'!C16)*1000000/'DCF Model'!C15,0),"") -> 446 | H9: =IFERROR(ROUND(('DCF Model'!C45/(1+$B9)^('DCF Model'!C19+0)+'DCF Model'!D45/(1+$B9)^('DCF Model'!C19+1)+'DCF Model'!E45/(1+$B9)^('DCF Model'!C19+2)+'DCF Model'!F45/(1+$B9)^('DCF Model'!C19+3)+'DCF Model'!G45/(1+$B9)^('DCF Model'!C19+4)+'DCF Model'!G45*(1+H$6)/($B9-H$6)/(1+$B9)^('DCF Model'!C19+4)-'DCF Model'!C16)*1000000/'DCF Model'!C15,0),"") -> 466 | I9: =IFERROR(ROUND(('DCF Model'!C45/(1+$B9)^('DCF Model'!C19+0)+'DCF Model'!D45/(1+$B9)^('DCF Model'!C19+1)+'DCF Model'!E45/(1+$B9)^('DCF Model'!C19+2)+'DCF Model'!F45/(1+$B9)^('DCF Model'!C19+3)+'DCF Model'!G45/(1+$B9)^('DCF Model'!C19+4)+'DCF Model'!G45*(1+I$6)/($B9-I$6)/(1+$B9)^('DCF Model'!C19+4)-'DCF Model'!C16)*1000000/'DCF Model'!C15,0),"") -> 489
B10: =$C$3 -> 0.062 | C10: =IFERROR(ROUND(('DCF Model'!C45/(1+$B10)^('DCF Model'!C19+0)+'DCF Model'!D45/(1+$B10)^('DCF Model'!C19+1)+'DCF Model'!E45/(1+$B10)^('DCF Model'!C19+2)+'DCF Model'!F45/(1+$B10)^('DCF Model'!C19+3)+'DCF Model'!G45/(1+$B10)^('DCF Model'!C19+4)+'DCF Model'!G45*(1+C$6)/($B10-C$6)/(1+$B10)^('DCF Model'!C19+4)-'DCF Model'!C16)*1000000/'DCF Model'!C15,0),"") -> 351 | D10: =IFERROR(ROUND(('DCF Model'!C45/(1+$B10)^('DCF Model'!C19+0)+'DCF Model'!D45/(1+$B10)^('DCF Model'!C19+1)+'DCF Model'!E45/(1+$B10)^('DCF Model'!C19+2)+'DCF Model'!F45/(1+$B10)^('DCF Model'!C19+3)+'DCF Model'!G45/(1+$B10)^('DCF Model'!C19+4)+'DCF Model'!G45*(1+D$6)/($B10-D$6)/(1+$B10)^('DCF Model'!C19+4)-'DCF Model'!C16)*1000000/'DCF Model'!C15,0),"") -> 363 | E10: =IFERROR(ROUND(('DCF Model'!C45/(1+$B10)^('DCF Model'!C19+0)+'DCF Model'!D45/(1+$B10)^('DCF Model'!C19+1)+'DCF Model'!E45/(1+$B10)^('DCF Model'!C19+2)+'DCF Model'!F45/(1+$B10)^('DCF Model'!C19+3)+'DCF Model'!G45/(1+$B10)^('DCF Model'!C19+4)+'DCF Model'!G45*(1+E$6)/($B10-E$6)/(1+$B10)^('DCF Model'!C19+4)-'DCF Model'!C16)*1000000/'DCF Model'!C15,0),"") -> 376 | F10: =IFERROR(ROUND(('DCF Model'!C45/(1+$B10)^('DCF Model'!C19+0)+'DCF Model'!D45/(1+$B10)^('DCF Model'!C19+1)+'DCF Model'!E45/(1+$B10)^('DCF Model'!C19+2)+'DCF Model'!F45/(1+$B10)^('DCF Model'!C19+3)+'DCF Model'!G45/(1+$B10)^('DCF Model'!C19+4)+'DCF Model'!G45*(1+F$6)/($B10-F$6)/(1+$B10)^('DCF Model'!C19+4)-'DCF Model'!C16)*1000000/'DCF Model'!C15,0),"") -> 389 | G10: =IFERROR(ROUND(('DCF Model'!C45/(1+$B10)^('DCF Model'!C19+0)+'DCF Model'!D45/(1+$B10)^('DCF Model'!C19+1)+'DCF Model'!E45/(1+$B10)^('DCF Model'!C19+2)+'DCF Model'!F45/(1+$B10)^('DCF Model'!C19+3)+'DCF Model'!G45/(1+$B10)^('DCF Model'!C19+4)+'DCF Model'!G45*(1+G$6)/($B10-G$6)/(1+$B10)^('DCF Model'!C19+4)-'DCF Model'!C16)*1000000/'DCF Model'!C15,0),"") -> 404 | H10: =IFERROR(ROUND(('DCF Model'!C45/(1+$B10)^('DCF Model'!C19+0)+'DCF Model'!D45/(1+$B10)^('DCF Model'!C19+1)+'DCF Model'!E45/(1+$B10)^('DCF Model'!C19+2)+'DCF Model'!F45/(1+$B10)^('DCF Model'!C19+3)+'DCF Model'!G45/(1+$B10)^('DCF Model'!C19+4)+'DCF Model'!G45*(1+H$6)/($B10-H$6)/(1+$B10)^('DCF Model'!C19+4)-'DCF Model'!C16)*1000000/'DCF Model'!C15,0),"") -> 421 | I10: =IFERROR(ROUND(('DCF Model'!C45/(1+$B10)^('DCF Model'!C19+0)+'DCF Model'!D45/(1+$B10)^('DCF Model'!C19+1)+'DCF Model'!E45/(1+$B10)^('DCF Model'!C19+2)+'DCF Model'!F45/(1+$B10)^('DCF Model'!C19+3)+'DCF Model'!G45/(1+$B10)^('DCF Model'!C19+4)+'DCF Model'!G45*(1+I$6)/($B10-I$6)/(1+$B10)^('DCF Model'!C19+4)-'DCF Model'!C16)*1000000/'DCF Model'!C15,0),"") -> 439
B11: =$C$3+0.005 -> 0.067 | C11: =IFERROR(ROUND(('DCF Model'!C45/(1+$B11)^('DCF Model'!C19+0)+'DCF Model'!D45/(1+$B11)^('DCF Model'!C19+1)+'DCF Model'!E45/(1+$B11)^('DCF Model'!C19+2)+'DCF Model'!F45/(1+$B11)^('DCF Model'!C19+3)+'DCF Model'!G45/(1+$B11)^('DCF Model'!C19+4)+'DCF Model'!G45*(1+C$6)/($B11-C$6)/(1+$B11)^('DCF Model'!C19+4)-'DCF Model'!C16)*1000000/'DCF Model'!C15,0),"") -> 325 | D11: =IFERROR(ROUND(('DCF Model'!C45/(1+$B11)^('DCF Model'!C19+0)+'DCF Model'!D45/(1+$B11)^('DCF Model'!C19+1)+'DCF Model'!E45/(1+$B11)^('DCF Model'!C19+2)+'DCF Model'!F45/(1+$B11)^('DCF Model'!C19+3)+'DCF Model'!G45/(1+$B11)^('DCF Model'!C19+4)+'DCF Model'!G45*(1+D$6)/($B11-D$6)/(1+$B11)^('DCF Model'!C19+4)-'DCF Model'!C16)*1000000/'DCF Model'!C15,0),"") -> 335 | E11: =IFERROR(ROUND(('DCF Model'!C45/(1+$B11)^('DCF Model'!C19+0)+'DCF Model'!D45/(1+$B11)^('DCF Model'!C19+1)+'DCF Model'!E45/(1+$B11)^('DCF Model'!C19+2)+'DCF Model'!F45/(1+$B11)^('DCF Model'!C19+3)+'DCF Model'!G45/(1+$B11)^('DCF Model'!C19+4)+'DCF Model'!G45*(1+E$6)/($B11-E$6)/(1+$B11)^('DCF Model'!C19+4)-'DCF Model'!C16)*1000000/'DCF Model'!C15,0),"") -> 346 | F11: =IFERROR(ROUND(('DCF Model'!C45/(1+$B11)^('DCF Model'!C19+0)+'DCF Model'!D45/(1+$B11)^('DCF Model'!C19+1)+'DCF Model'!E45/(1+$B11)^('DCF Model'!C19+2)+'DCF Model'!F45/(1+$B11)^('DCF Model'!C19+3)+'DCF Model'!G45/(1+$B11)^('DCF Model'!C19+4)+'DCF Model'!G45*(1+F$6)/($B11-F$6)/(1+$B11)^('DCF Model'!C19+4)-'DCF Model'!C16)*1000000/'DCF Model'!C15,0),"") -> 357 | G11: =IFERROR(ROUND(('DCF Model'!C45/(1+$B11)^('DCF Model'!C19+0)+'DCF Model'!D45/(1+$B11)^('DCF Model'!C19+1)+'DCF Model'!E45/(1+$B11)^('DCF Model'!C19+2)+'DCF Model'!F45/(1+$B11)^('DCF Model'!C19+3)+'DCF Model'!G45/(1+$B11)^('DCF Model'!C19+4)+'DCF Model'!G45*(1+G$6)/($B11-G$6)/(1+$B11)^('DCF Model'!C19+4)-'DCF Model'!C16)*1000000/'DCF Model'!C15,0),"") -> 370 | H11: =IFERROR(ROUND(('DCF Model'!C45/(1+$B11)^('DCF Model'!C19+0)+'DCF Model'!D45/(1+$B11)^('DCF Model'!C19+1)+'DCF Model'!E45/(1+$B11)^('DCF Model'!C19+2)+'DCF Model'!F45/(1+$B11)^('DCF Model'!C19+3)+'DCF Model'!G45/(1+$B11)^('DCF Model'!C19+4)+'DCF Model'!G45*(1+H$6)/($B11-H$6)/(1+$B11)^('DCF Model'!C19+4)-'DCF Model'!C16)*1000000/'DCF Model'!C15,0),"") -> 383 | I11: =IFERROR(ROUND(('DCF Model'!C45/(1+$B11)^('DCF Model'!C19+0)+'DCF Model'!D45/(1+$B11)^('DCF Model'!C19+1)+'DCF Model'!E45/(1+$B11)^('DCF Model'!C19+2)+'DCF Model'!F45/(1+$B11)^('DCF Model'!C19+3)+'DCF Model'!G45/(1+$B11)^('DCF Model'!C19+4)+'DCF Model'!G45*(1+I$6)/($B11-I$6)/(1+$B11)^('DCF Model'!C19+4)-'DCF Model'!C16)*1000000/'DCF Model'!C15,0),"") -> 398
B12: =$C$3+0.01 -> 0.072 | C12: =IFERROR(ROUND(('DCF Model'!C45/(1+$B12)^('DCF Model'!C19+0)+'DCF Model'!D45/(1+$B12)^('DCF Model'!C19+1)+'DCF Model'!E45/(1+$B12)^('DCF Model'!C19+2)+'DCF Model'!F45/(1+$B12)^('DCF Model'!C19+3)+'DCF Model'!G45/(1+$B12)^('DCF Model'!C19+4)+'DCF Model'!G45*(1+C$6)/($B12-C$6)/(1+$B12)^('DCF Model'!C19+4)-'DCF Model'!C16)*1000000/'DCF Model'!C15,0),"") -> 303 | D12: =IFERROR(ROUND(('DCF Model'!C45/(1+$B12)^('DCF Model'!C19+0)+'DCF Model'!D45/(1+$B12)^('DCF Model'!C19+1)+'DCF Model'!E45/(1+$B12)^('DCF Model'!C19+2)+'DCF Model'!F45/(1+$B12)^('DCF Model'!C19+3)+'DCF Model'!G45/(1+$B12)^('DCF Model'!C19+4)+'DCF Model'!G45*(1+D$6)/($B12-D$6)/(1+$B12)^('DCF Model'!C19+4)-'DCF Model'!C16)*1000000/'DCF Model'!C15,0),"") -> 311 | E12: =IFERROR(ROUND(('DCF Model'!C45/(1+$B12)^('DCF Model'!C19+0)+'DCF Model'!D45/(1+$B12)^('DCF Model'!C19+1)+'DCF Model'!E45/(1+$B12)^('DCF Model'!C19+2)+'DCF Model'!F45/(1+$B12)^('DCF Model'!C19+3)+'DCF Model'!G45/(1+$B12)^('DCF Model'!C19+4)+'DCF Model'!G45*(1+E$6)/($B12-E$6)/(1+$B12)^('DCF Model'!C19+4)-'DCF Model'!C16)*1000000/'DCF Model'!C15,0),"") -> 321 | F12: =IFERROR(ROUND(('DCF Model'!C45/(1+$B12)^('DCF Model'!C19+0)+'DCF Model'!D45/(1+$B12)^('DCF Model'!C19+1)+'DCF Model'!E45/(1+$B12)^('DCF Model'!C19+2)+'DCF Model'!F45/(1+$B12)^('DCF Model'!C19+3)+'DCF Model'!G45/(1+$B12)^('DCF Model'!C19+4)+'DCF Model'!G45*(1+F$6)/($B12-F$6)/(1+$B12)^('DCF Model'!C19+4)-'DCF Model'!C16)*1000000/'DCF Model'!C15,0),"") -> 330 | G12: =IFERROR(ROUND(('DCF Model'!C45/(1+$B12)^('DCF Model'!C19+0)+'DCF Model'!D45/(1+$B12)^('DCF Model'!C19+1)+'DCF Model'!E45/(1+$B12)^('DCF Model'!C19+2)+'DCF Model'!F45/(1+$B12)^('DCF Model'!C19+3)+'DCF Model'!G45/(1+$B12)^('DCF Model'!C19+4)+'DCF Model'!G45*(1+G$6)/($B12-G$6)/(1+$B12)^('DCF Model'!C19+4)-'DCF Model'!C16)*1000000/'DCF Model'!C15,0),"") -> 341 | H12: =IFERROR(ROUND(('DCF Model'!C45/(1+$B12)^('DCF Model'!C19+0)+'DCF Model'!D45/(1+$B12)^('DCF Model'!C19+1)+'DCF Model'!E45/(1+$B12)^('DCF Model'!C19+2)+'DCF Model'!F45/(1+$B12)^('DCF Model'!C19+3)+'DCF Model'!G45/(1+$B12)^('DCF Model'!C19+4)+'DCF Model'!G45*(1+H$6)/($B12-H$6)/(1+$B12)^('DCF Model'!C19+4)-'DCF Model'!C16)*1000000/'DCF Model'!C15,0),"") -> 352 | I12: =IFERROR(ROUND(('DCF Model'!C45/(1+$B12)^('DCF Model'!C19+0)+'DCF Model'!D45/(1+$B12)^('DCF Model'!C19+1)+'DCF Model'!E45/(1+$B12)^('DCF Model'!C19+2)+'DCF Model'!F45/(1+$B12)^('DCF Model'!C19+3)+'DCF Model'!G45/(1+$B12)^('DCF Model'!C19+4)+'DCF Model'!G45*(1+I$6)/($B12-I$6)/(1+$B12)^('DCF Model'!C19+4)-'DCF Model'!C16)*1000000/'DCF Model'!C15,0),"") -> 364
B13: =$C$3+0.015 -> 0.077 | C13: =IFERROR(ROUND(('DCF Model'!C45/(1+$B13)^('DCF Model'!C19+0)+'DCF Model'!D45/(1+$B13)^('DCF Model'!C19+1)+'DCF Model'!E45/(1+$B13)^('DCF Model'!C19+2)+'DCF Model'!F45/(1+$B13)^('DCF Model'!C19+3)+'DCF Model'!G45/(1+$B13)^('DCF Model'!C19+4)+'DCF Model'!G45*(1+C$6)/($B13-C$6)/(1+$B13)^('DCF Model'!C19+4)-'DCF Model'!C16)*1000000/'DCF Model'!C15,0),"") -> 283 | D13: =IFERROR(ROUND(('DCF Model'!C45/(1+$B13)^('DCF Model'!C19+0)+'DCF Model'!D45/(1+$B13)^('DCF Model'!C19+1)+'DCF Model'!E45/(1+$B13)^('DCF Model'!C19+2)+'DCF Model'!F45/(1+$B13)^('DCF Model'!C19+3)+'DCF Model'!G45/(1+$B13)^('DCF Model'!C19+4)+'DCF Model'!G45*(1+D$6)/($B13-D$6)/(1+$B13)^('DCF Model'!C19+4)-'DCF Model'!C16)*1000000/'DCF Model'!C15,0),"") -> 291 | E13: =IFERROR(ROUND(('DCF Model'!C45/(1+$B13)^('DCF Model'!C19+0)+'DCF Model'!D45/(1+$B13)^('DCF Model'!C19+1)+'DCF Model'!E45/(1+$B13)^('DCF Model'!C19+2)+'DCF Model'!F45/(1+$B13)^('DCF Model'!C19+3)+'DCF Model'!G45/(1+$B13)^('DCF Model'!C19+4)+'DCF Model'!G45*(1+E$6)/($B13-E$6)/(1+$B13)^('DCF Model'!C19+4)-'DCF Model'!C16)*1000000/'DCF Model'!C15,0),"") -> 299 | F13: =IFERROR(ROUND(('DCF Model'!C45/(1+$B13)^('DCF Model'!C19+0)+'DCF Model'!D45/(1+$B13)^('DCF Model'!C19+1)+'DCF Model'!E45/(1+$B13)^('DCF Model'!C19+2)+'DCF Model'!F45/(1+$B13)^('DCF Model'!C19+3)+'DCF Model'!G45/(1+$B13)^('DCF Model'!C19+4)+'DCF Model'!G45*(1+F$6)/($B13-F$6)/(1+$B13)^('DCF Model'!C19+4)-'DCF Model'!C16)*1000000/'DCF Model'!C15,0),"") -> 307 | G13: =IFERROR(ROUND(('DCF Model'!C45/(1+$B13)^('DCF Model'!C19+0)+'DCF Model'!D45/(1+$B13)^('DCF Model'!C19+1)+'DCF Model'!E45/(1+$B13)^('DCF Model'!C19+2)+'DCF Model'!F45/(1+$B13)^('DCF Model'!C19+3)+'DCF Model'!G45/(1+$B13)^('DCF Model'!C19+4)+'DCF Model'!G45*(1+G$6)/($B13-G$6)/(1+$B13)^('DCF Model'!C19+4)-'DCF Model'!C16)*1000000/'DCF Model'!C15,0),"") -> 316 | H13: =IFERROR(ROUND(('DCF Model'!C45/(1+$B13)^('DCF Model'!C19+0)+'DCF Model'!D45/(1+$B13)^('DCF Model'!C19+1)+'DCF Model'!E45/(1+$B13)^('DCF Model'!C19+2)+'DCF Model'!F45/(1+$B13)^('DCF Model'!C19+3)+'DCF Model'!G45/(1+$B13)^('DCF Model'!C19+4)+'DCF Model'!G45*(1+H$6)/($B13-H$6)/(1+$B13)^('DCF Model'!C19+4)-'DCF Model'!C16)*1000000/'DCF Model'!C15,0),"") -> 325 | I13: =IFERROR(ROUND(('DCF Model'!C45/(1+$B13)^('DCF Model'!C19+0)+'DCF Model'!D45/(1+$B13)^('DCF Model'!C19+1)+'DCF Model'!E45/(1+$B13)^('DCF Model'!C19+2)+'DCF Model'!F45/(1+$B13)^('DCF Model'!C19+3)+'DCF Model'!G45/(1+$B13)^('DCF Model'!C19+4)+'DCF Model'!G45*(1+I$6)/($B13-I$6)/(1+$B13)^('DCF Model'!C19+4)-'DCF Model'!C16)*1000000/'DCF Model'!C15,0),"") -> 336
B16: Table 2: WACC vs Exit Multiple (Exit Multiple - Implied Share Price, JPY)
B17: WACC \ Exit Multiple | C17: =$I$3-3 -> 4 | D17: =$I$3-2 -> 5 | E17: =$I$3-1 -> 6 | F17: =$I$3 -> 7 | G17: =$I$3+1 -> 8 | H17: =$I$3+2 -> 9 | I17: =$I$3+3 -> 10
B18: =$C$3-0.015 -> 0.047 | C18: =IFERROR(ROUND(('DCF Model'!C45/(1+$B18)^('DCF Model'!C19+0)+'DCF Model'!D45/(1+$B18)^('DCF Model'!C19+1)+'DCF Model'!E45/(1+$B18)^('DCF Model'!C19+2)+'DCF Model'!F45/(1+$B18)^('DCF Model'!C19+3)+'DCF Model'!G45/(1+$B18)^('DCF Model'!C19+4)+('DCF Model'!G39+'DCF Model'!G42)*C$17/(1+$B18)^('DCF Model'!C19+4)-'DCF Model'!C16)*1000000/'DCF Model'!C15,0),"") -> 297 | D18: =IFERROR(ROUND(('DCF Model'!C45/(1+$B18)^('DCF Model'!C19+0)+'DCF Model'!D45/(1+$B18)^('DCF Model'!C19+1)+'DCF Model'!E45/(1+$B18)^('DCF Model'!C19+2)+'DCF Model'!F45/(1+$B18)^('DCF Model'!C19+3)+'DCF Model'!G45/(1+$B18)^('DCF Model'!C19+4)+('DCF Model'!G39+'DCF Model'!G42)*D$17/(1+$B18)^('DCF Model'!C19+4)-'DCF Model'!C16)*1000000/'DCF Model'!C15,0),"") -> 350 | E18: =IFERROR(ROUND(('DCF Model'!C45/(1+$B18)^('DCF Model'!C19+0)+'DCF Model'!D45/(1+$B18)^('DCF Model'!C19+1)+'DCF Model'!E45/(1+$B18)^('DCF Model'!C19+2)+'DCF Model'!F45/(1+$B18)^('DCF Model'!C19+3)+'DCF Model'!G45/(1+$B18)^('DCF Model'!C19+4)+('DCF Model'!G39+'DCF Model'!G42)*E$17/(1+$B18)^('DCF Model'!C19+4)-'DCF Model'!C16)*1000000/'DCF Model'!C15,0),"") -> 404 | F18: =IFERROR(ROUND(('DCF Model'!C45/(1+$B18)^('DCF Model'!C19+0)+'DCF Model'!D45/(1+$B18)^('DCF Model'!C19+1)+'DCF Model'!E45/(1+$B18)^('DCF Model'!C19+2)+'DCF Model'!F45/(1+$B18)^('DCF Model'!C19+3)+'DCF Model'!G45/(1+$B18)^('DCF Model'!C19+4)+('DCF Model'!G39+'DCF Model'!G42)*F$17/(1+$B18)^('DCF Model'!C19+4)-'DCF Model'!C16)*1000000/'DCF Model'!C15,0),"") -> 457 | G18: =IFERROR(ROUND(('DCF Model'!C45/(1+$B18)^('DCF Model'!C19+0)+'DCF Model'!D45/(1+$B18)^('DCF Model'!C19+1)+'DCF Model'!E45/(1+$B18)^('DCF Model'!C19+2)+'DCF Model'!F45/(1+$B18)^('DCF Model'!C19+3)+'DCF Model'!G45/(1+$B18)^('DCF Model'!C19+4)+('DCF Model'!G39+'DCF Model'!G42)*G$17/(1+$B18)^('DCF Model'!C19+4)-'DCF Model'!C16)*1000000/'DCF Model'!C15,0),"") -> 511 | H18: =IFERROR(ROUND(('DCF Model'!C45/(1+$B18)^('DCF Model'!C19+0)+'DCF Model'!D45/(1+$B18)^('DCF Model'!C19+1)+'DCF Model'!E45/(1+$B18)^('DCF Model'!C19+2)+'DCF Model'!F45/(1+$B18)^('DCF Model'!C19+3)+'DCF Model'!G45/(1+$B18)^('DCF Model'!C19+4)+('DCF Model'!G39+'DCF Model'!G42)*H$17/(1+$B18)^('DCF Model'!C19+4)-'DCF Model'!C16)*1000000/'DCF Model'!C15,0),"") -> 564 | I18: =IFERROR(ROUND(('DCF Model'!C45/(1+$B18)^('DCF Model'!C19+0)+'DCF Model'!D45/(1+$B18)^('DCF Model'!C19+1)+'DCF Model'!E45/(1+$B18)^('DCF Model'!C19+2)+'DCF Model'!F45/(1+$B18)^('DCF Model'!C19+3)+'DCF Model'!G45/(1+$B18)^('DCF Model'!C19+4)+('DCF Model'!G39+'DCF Model'!G42)*I$17/(1+$B18)^('DCF Model'!C19+4)-'DCF Model'!C16)*1000000/'DCF Model'!C15,0),"") -> 618
B19: =$C$3-0.01 -> 0.052 | C19: =IFERROR(ROUND(('DCF Model'!C45/(1+$B19)^('DCF Model'!C19+0)+'DCF Model'!D45/(1+$B19)^('DCF Model'!C19+1)+'DCF Model'!E45/(1+$B19)^('DCF Model'!C19+2)+'DCF Model'!F45/(1+$B19)^('DCF Model'!C19+3)+'DCF Model'!G45/(1+$B19)^('DCF Model'!C19+4)+('DCF Model'!G39+'DCF Model'!G42)*C$17/(1+$B19)^('DCF Model'!C19+4)-'DCF Model'!C16)*1000000/'DCF Model'!C15,0),"") -> 291 | D19: =IFERROR(ROUND(('DCF Model'!C45/(1+$B19)^('DCF Model'!C19+0)+'DCF Model'!D45/(1+$B19)^('DCF Model'!C19+1)+'DCF Model'!E45/(1+$B19)^('DCF Model'!C19+2)+'DCF Model'!F45/(1+$B19)^('DCF Model'!C19+3)+'DCF Model'!G45/(1+$B19)^('DCF Model'!C19+4)+('DCF Model'!G39+'DCF Model'!G42)*D$17/(1+$B19)^('DCF Model'!C19+4)-'DCF Model'!C16)*1000000/'DCF Model'!C15,0),"") -> 343 | E19: =IFERROR(ROUND(('DCF Model'!C45/(1+$B19)^('DCF Model'!C19+0)+'DCF Model'!D45/(1+$B19)^('DCF Model'!C19+1)+'DCF Model'!E45/(1+$B19)^('DCF Model'!C19+2)+'DCF Model'!F45/(1+$B19)^('DCF Model'!C19+3)+'DCF Model'!G45/(1+$B19)^('DCF Model'!C19+4)+('DCF Model'!G39+'DCF Model'!G42)*E$17/(1+$B19)^('DCF Model'!C19+4)-'DCF Model'!C16)*1000000/'DCF Model'!C15,0),"") -> 396 | F19: =IFERROR(ROUND(('DCF Model'!C45/(1+$B19)^('DCF Model'!C19+0)+'DCF Model'!D45/(1+$B19)^('DCF Model'!C19+1)+'DCF Model'!E45/(1+$B19)^('DCF Model'!C19+2)+'DCF Model'!F45/(1+$B19)^('DCF Model'!C19+3)+'DCF Model'!G45/(1+$B19)^('DCF Model'!C19+4)+('DCF Model'!G39+'DCF Model'!G42)*F$17/(1+$B19)^('DCF Model'!C19+4)-'DCF Model'!C16)*1000000/'DCF Model'!C15,0),"") -> 448 | G19: =IFERROR(ROUND(('DCF Model'!C45/(1+$B19)^('DCF Model'!C19+0)+'DCF Model'!D45/(1+$B19)^('DCF Model'!C19+1)+'DCF Model'!E45/(1+$B19)^('DCF Model'!C19+2)+'DCF Model'!F45/(1+$B19)^('DCF Model'!C19+3)+'DCF Model'!G45/(1+$B19)^('DCF Model'!C19+4)+('DCF Model'!G39+'DCF Model'!G42)*G$17/(1+$B19)^('DCF Model'!C19+4)-'DCF Model'!C16)*1000000/'DCF Model'!C15,0),"") -> 501 | H19: =IFERROR(ROUND(('DCF Model'!C45/(1+$B19)^('DCF Model'!C19+0)+'DCF Model'!D45/(1+$B19)^('DCF Model'!C19+1)+'DCF Model'!E45/(1+$B19)^('DCF Model'!C19+2)+'DCF Model'!F45/(1+$B19)^('DCF Model'!C19+3)+'DCF Model'!G45/(1+$B19)^('DCF Model'!C19+4)+('DCF Model'!G39+'DCF Model'!G42)*H$17/(1+$B19)^('DCF Model'!C19+4)-'DCF Model'!C16)*1000000/'DCF Model'!C15,0),"") -> 553 | I19: =IFERROR(ROUND(('DCF Model'!C45/(1+$B19)^('DCF Model'!C19+0)+'DCF Model'!D45/(1+$B19)^('DCF Model'!C19+1)+'DCF Model'!E45/(1+$B19)^('DCF Model'!C19+2)+'DCF Model'!F45/(1+$B19)^('DCF Model'!C19+3)+'DCF Model'!G45/(1+$B19)^('DCF Model'!C19+4)+('DCF Model'!G39+'DCF Model'!G42)*I$17/(1+$B19)^('DCF Model'!C19+4)-'DCF Model'!C16)*1000000/'DCF Model'!C15,0),"") -> 606
B20: =$C$3-0.005 -> 0.057 | C20: =IFERROR(ROUND(('DCF Model'!C45/(1+$B20)^('DCF Model'!C19+0)+'DCF Model'!D45/(1+$B20)^('DCF Model'!C19+1)+'DCF Model'!E45/(1+$B20)^('DCF Model'!C19+2)+'DCF Model'!F45/(1+$B20)^('DCF Model'!C19+3)+'DCF Model'!G45/(1+$B20)^('DCF Model'!C19+4)+('DCF Model'!G39+'DCF Model'!G42)*C$17/(1+$B20)^('DCF Model'!C19+4)-'DCF Model'!C16)*1000000/'DCF Model'!C15,0),"") -> 285 | D20: =IFERROR(ROUND(('DCF Model'!C45/(1+$B20)^('DCF Model'!C19+0)+'DCF Model'!D45/(1+$B20)^('DCF Model'!C19+1)+'DCF Model'!E45/(1+$B20)^('DCF Model'!C19+2)+'DCF Model'!F45/(1+$B20)^('DCF Model'!C19+3)+'DCF Model'!G45/(1+$B20)^('DCF Model'!C19+4)+('DCF Model'!G39+'DCF Model'!G42)*D$17/(1+$B20)^('DCF Model'!C19+4)-'DCF Model'!C16)*1000000/'DCF Model'!C15,0),"") -> 337 | E20: =IFERROR(ROUND(('DCF Model'!C45/(1+$B20)^('DCF Model'!C19+0)+'DCF Model'!D45/(1+$B20)^('DCF Model'!C19+1)+'DCF Model'!E45/(1+$B20)^('DCF Model'!C19+2)+'DCF Model'!F45/(1+$B20)^('DCF Model'!C19+3)+'DCF Model'!G45/(1+$B20)^('DCF Model'!C19+4)+('DCF Model'!G39+'DCF Model'!G42)*E$17/(1+$B20)^('DCF Model'!C19+4)-'DCF Model'!C16)*1000000/'DCF Model'!C15,0),"") -> 388 | F20: =IFERROR(ROUND(('DCF Model'!C45/(1+$B20)^('DCF Model'!C19+0)+'DCF Model'!D45/(1+$B20)^('DCF Model'!C19+1)+'DCF Model'!E45/(1+$B20)^('DCF Model'!C19+2)+'DCF Model'!F45/(1+$B20)^('DCF Model'!C19+3)+'DCF Model'!G45/(1+$B20)^('DCF Model'!C19+4)+('DCF Model'!G39+'DCF Model'!G42)*F$17/(1+$B20)^('DCF Model'!C19+4)-'DCF Model'!C16)*1000000/'DCF Model'!C15,0),"") -> 439 | G20: =IFERROR(ROUND(('DCF Model'!C45/(1+$B20)^('DCF Model'!C19+0)+'DCF Model'!D45/(1+$B20)^('DCF Model'!C19+1)+'DCF Model'!E45/(1+$B20)^('DCF Model'!C19+2)+'DCF Model'!F45/(1+$B20)^('DCF Model'!C19+3)+'DCF Model'!G45/(1+$B20)^('DCF Model'!C19+4)+('DCF Model'!G39+'DCF Model'!G42)*G$17/(1+$B20)^('DCF Model'!C19+4)-'DCF Model'!C16)*1000000/'DCF Model'!C15,0),"") -> 491 | H20: =IFERROR(ROUND(('DCF Model'!C45/(1+$B20)^('DCF Model'!C19+0)+'DCF Model'!D45/(1+$B20)^('DCF Model'!C19+1)+'DCF Model'!E45/(1+$B20)^('DCF Model'!C19+2)+'DCF Model'!F45/(1+$B20)^('DCF Model'!C19+3)+'DCF Model'!G45/(1+$B20)^('DCF Model'!C19+4)+('DCF Model'!G39+'DCF Model'!G42)*H$17/(1+$B20)^('DCF Model'!C19+4)-'DCF Model'!C16)*1000000/'DCF Model'!C15,0),"") -> 542 | I20: =IFERROR(ROUND(('DCF Model'!C45/(1+$B20)^('DCF Model'!C19+0)+'DCF Model'!D45/(1+$B20)^('DCF Model'!C19+1)+'DCF Model'!E45/(1+$B20)^('DCF Model'!C19+2)+'DCF Model'!F45/(1+$B20)^('DCF Model'!C19+3)+'DCF Model'!G45/(1+$B20)^('DCF Model'!C19+4)+('DCF Model'!G39+'DCF Model'!G42)*I$17/(1+$B20)^('DCF Model'!C19+4)-'DCF Model'!C16)*1000000/'DCF Model'!C15,0),"") -> 593
B21: =$C$3 -> 0.062 | C21: =IFERROR(ROUND(('DCF Model'!C45/(1+$B21)^('DCF Model'!C19+0)+'DCF Model'!D45/(1+$B21)^('DCF Model'!C19+1)+'DCF Model'!E45/(1+$B21)^('DCF Model'!C19+2)+'DCF Model'!F45/(1+$B21)^('DCF Model'!C19+3)+'DCF Model'!G45/(1+$B21)^('DCF Model'!C19+4)+('DCF Model'!G39+'DCF Model'!G42)*C$17/(1+$B21)^('DCF Model'!C19+4)-'DCF Model'!C16)*1000000/'DCF Model'!C15,0),"") -> 280 | D21: =IFERROR(ROUND(('DCF Model'!C45/(1+$B21)^('DCF Model'!C19+0)+'DCF Model'!D45/(1+$B21)^('DCF Model'!C19+1)+'DCF Model'!E45/(1+$B21)^('DCF Model'!C19+2)+'DCF Model'!F45/(1+$B21)^('DCF Model'!C19+3)+'DCF Model'!G45/(1+$B21)^('DCF Model'!C19+4)+('DCF Model'!G39+'DCF Model'!G42)*D$17/(1+$B21)^('DCF Model'!C19+4)-'DCF Model'!C16)*1000000/'DCF Model'!C15,0),"") -> 330 | E21: =IFERROR(ROUND(('DCF Model'!C45/(1+$B21)^('DCF Model'!C19+0)+'DCF Model'!D45/(1+$B21)^('DCF Model'!C19+1)+'DCF Model'!E45/(1+$B21)^('DCF Model'!C19+2)+'DCF Model'!F45/(1+$B21)^('DCF Model'!C19+3)+'DCF Model'!G45/(1+$B21)^('DCF Model'!C19+4)+('DCF Model'!G39+'DCF Model'!G42)*E$17/(1+$B21)^('DCF Model'!C19+4)-'DCF Model'!C16)*1000000/'DCF Model'!C15,0),"") -> 381 | F21: =IFERROR(ROUND(('DCF Model'!C45/(1+$B21)^('DCF Model'!C19+0)+'DCF Model'!D45/(1+$B21)^('DCF Model'!C19+1)+'DCF Model'!E45/(1+$B21)^('DCF Model'!C19+2)+'DCF Model'!F45/(1+$B21)^('DCF Model'!C19+3)+'DCF Model'!G45/(1+$B21)^('DCF Model'!C19+4)+('DCF Model'!G39+'DCF Model'!G42)*F$17/(1+$B21)^('DCF Model'!C19+4)-'DCF Model'!C16)*1000000/'DCF Model'!C15,0),"") -> 431 | G21: =IFERROR(ROUND(('DCF Model'!C45/(1+$B21)^('DCF Model'!C19+0)+'DCF Model'!D45/(1+$B21)^('DCF Model'!C19+1)+'DCF Model'!E45/(1+$B21)^('DCF Model'!C19+2)+'DCF Model'!F45/(1+$B21)^('DCF Model'!C19+3)+'DCF Model'!G45/(1+$B21)^('DCF Model'!C19+4)+('DCF Model'!G39+'DCF Model'!G42)*G$17/(1+$B21)^('DCF Model'!C19+4)-'DCF Model'!C16)*1000000/'DCF Model'!C15,0),"") -> 481 | H21: =IFERROR(ROUND(('DCF Model'!C45/(1+$B21)^('DCF Model'!C19+0)+'DCF Model'!D45/(1+$B21)^('DCF Model'!C19+1)+'DCF Model'!E45/(1+$B21)^('DCF Model'!C19+2)+'DCF Model'!F45/(1+$B21)^('DCF Model'!C19+3)+'DCF Model'!G45/(1+$B21)^('DCF Model'!C19+4)+('DCF Model'!G39+'DCF Model'!G42)*H$17/(1+$B21)^('DCF Model'!C19+4)-'DCF Model'!C16)*1000000/'DCF Model'!C15,0),"") -> 531 | I21: =IFERROR(ROUND(('DCF Model'!C45/(1+$B21)^('DCF Model'!C19+0)+'DCF Model'!D45/(1+$B21)^('DCF Model'!C19+1)+'DCF Model'!E45/(1+$B21)^('DCF Model'!C19+2)+'DCF Model'!F45/(1+$B21)^('DCF Model'!C19+3)+'DCF Model'!G45/(1+$B21)^('DCF Model'!C19+4)+('DCF Model'!G39+'DCF Model'!G42)*I$17/(1+$B21)^('DCF Model'!C19+4)-'DCF Model'!C16)*1000000/'DCF Model'!C15,0),"") -> 582
B22: =$C$3+0.005 -> 0.067 | C22: =IFERROR(ROUND(('DCF Model'!C45/(1+$B22)^('DCF Model'!C19+0)+'DCF Model'!D45/(1+$B22)^('DCF Model'!C19+1)+'DCF Model'!E45/(1+$B22)^('DCF Model'!C19+2)+'DCF Model'!F45/(1+$B22)^('DCF Model'!C19+3)+'DCF Model'!G45/(1+$B22)^('DCF Model'!C19+4)+('DCF Model'!G39+'DCF Model'!G42)*C$17/(1+$B22)^('DCF Model'!C19+4)-'DCF Model'!C16)*1000000/'DCF Model'!C15,0),"") -> 275 | D22: =IFERROR(ROUND(('DCF Model'!C45/(1+$B22)^('DCF Model'!C19+0)+'DCF Model'!D45/(1+$B22)^('DCF Model'!C19+1)+'DCF Model'!E45/(1+$B22)^('DCF Model'!C19+2)+'DCF Model'!F45/(1+$B22)^('DCF Model'!C19+3)+'DCF Model'!G45/(1+$B22)^('DCF Model'!C19+4)+('DCF Model'!G39+'DCF Model'!G42)*D$17/(1+$B22)^('DCF Model'!C19+4)-'DCF Model'!C16)*1000000/'DCF Model'!C15,0),"") -> 324 | E22: =IFERROR(ROUND(('DCF Model'!C45/(1+$B22)^('DCF Model'!C19+0)+'DCF Model'!D45/(1+$B22)^('DCF Model'!C19+1)+'DCF Model'!E45/(1+$B22)^('DCF Model'!C19+2)+'DCF Model'!F45/(1+$B22)^('DCF Model'!C19+3)+'DCF Model'!G45/(1+$B22)^('DCF Model'!C19+4)+('DCF Model'!G39+'DCF Model'!G42)*E$17/(1+$B22)^('DCF Model'!C19+4)-'DCF Model'!C16)*1000000/'DCF Model'!C15,0),"") -> 373 | F22: =IFERROR(ROUND(('DCF Model'!C45/(1+$B22)^('DCF Model'!C19+0)+'DCF Model'!D45/(1+$B22)^('DCF Model'!C19+1)+'DCF Model'!E45/(1+$B22)^('DCF Model'!C19+2)+'DCF Model'!F45/(1+$B22)^('DCF Model'!C19+3)+'DCF Model'!G45/(1+$B22)^('DCF Model'!C19+4)+('DCF Model'!G39+'DCF Model'!G42)*F$17/(1+$B22)^('DCF Model'!C19+4)-'DCF Model'!C16)*1000000/'DCF Model'!C15,0),"") -> 423 | G22: =IFERROR(ROUND(('DCF Model'!C45/(1+$B22)^('DCF Model'!C19+0)+'DCF Model'!D45/(1+$B22)^('DCF Model'!C19+1)+'DCF Model'!E45/(1+$B22)^('DCF Model'!C19+2)+'DCF Model'!F45/(1+$B22)^('DCF Model'!C19+3)+'DCF Model'!G45/(1+$B22)^('DCF Model'!C19+4)+('DCF Model'!G39+'DCF Model'!G42)*G$17/(1+$B22)^('DCF Model'!C19+4)-'DCF Model'!C16)*1000000/'DCF Model'!C15,0),"") -> 472 | H22: =IFERROR(ROUND(('DCF Model'!C45/(1+$B22)^('DCF Model'!C19+0)+'DCF Model'!D45/(1+$B22)^('DCF Model'!C19+1)+'DCF Model'!E45/(1+$B22)^('DCF Model'!C19+2)+'DCF Model'!F45/(1+$B22)^('DCF Model'!C19+3)+'DCF Model'!G45/(1+$B22)^('DCF Model'!C19+4)+('DCF Model'!G39+'DCF Model'!G42)*H$17/(1+$B22)^('DCF Model'!C19+4)-'DCF Model'!C16)*1000000/'DCF Model'!C15,0),"") -> 521 | I22: =IFERROR(ROUND(('DCF Model'!C45/(1+$B22)^('DCF Model'!C19+0)+'DCF Model'!D45/(1+$B22)^('DCF Model'!C19+1)+'DCF Model'!E45/(1+$B22)^('DCF Model'!C19+2)+'DCF Model'!F45/(1+$B22)^('DCF Model'!C19+3)+'DCF Model'!G45/(1+$B22)^('DCF Model'!C19+4)+('DCF Model'!G39+'DCF Model'!G42)*I$17/(1+$B22)^('DCF Model'!C19+4)-'DCF Model'!C16)*1000000/'DCF Model'!C15,0),"") -> 570
B23: =$C$3+0.01 -> 0.072 | C23: =IFERROR(ROUND(('DCF Model'!C45/(1+$B23)^('DCF Model'!C19+0)+'DCF Model'!D45/(1+$B23)^('DCF Model'!C19+1)+'DCF Model'!E45/(1+$B23)^('DCF Model'!C19+2)+'DCF Model'!F45/(1+$B23)^('DCF Model'!C19+3)+'DCF Model'!G45/(1+$B23)^('DCF Model'!C19+4)+('DCF Model'!G39+'DCF Model'!G42)*C$17/(1+$B23)^('DCF Model'!C19+4)-'DCF Model'!C16)*1000000/'DCF Model'!C15,0),"") -> 270 | D23: =IFERROR(ROUND(('DCF Model'!C45/(1+$B23)^('DCF Model'!C19+0)+'DCF Model'!D45/(1+$B23)^('DCF Model'!C19+1)+'DCF Model'!E45/(1+$B23)^('DCF Model'!C19+2)+'DCF Model'!F45/(1+$B23)^('DCF Model'!C19+3)+'DCF Model'!G45/(1+$B23)^('DCF Model'!C19+4)+('DCF Model'!G39+'DCF Model'!G42)*D$17/(1+$B23)^('DCF Model'!C19+4)-'DCF Model'!C16)*1000000/'DCF Model'!C15,0),"") -> 318 | E23: =IFERROR(ROUND(('DCF Model'!C45/(1+$B23)^('DCF Model'!C19+0)+'DCF Model'!D45/(1+$B23)^('DCF Model'!C19+1)+'DCF Model'!E45/(1+$B23)^('DCF Model'!C19+2)+'DCF Model'!F45/(1+$B23)^('DCF Model'!C19+3)+'DCF Model'!G45/(1+$B23)^('DCF Model'!C19+4)+('DCF Model'!G39+'DCF Model'!G42)*E$17/(1+$B23)^('DCF Model'!C19+4)-'DCF Model'!C16)*1000000/'DCF Model'!C15,0),"") -> 366 | F23: =IFERROR(ROUND(('DCF Model'!C45/(1+$B23)^('DCF Model'!C19+0)+'DCF Model'!D45/(1+$B23)^('DCF Model'!C19+1)+'DCF Model'!E45/(1+$B23)^('DCF Model'!C19+2)+'DCF Model'!F45/(1+$B23)^('DCF Model'!C19+3)+'DCF Model'!G45/(1+$B23)^('DCF Model'!C19+4)+('DCF Model'!G39+'DCF Model'!G42)*F$17/(1+$B23)^('DCF Model'!C19+4)-'DCF Model'!C16)*1000000/'DCF Model'!C15,0),"") -> 414 | G23: =IFERROR(ROUND(('DCF Model'!C45/(1+$B23)^('DCF Model'!C19+0)+'DCF Model'!D45/(1+$B23)^('DCF Model'!C19+1)+'DCF Model'!E45/(1+$B23)^('DCF Model'!C19+2)+'DCF Model'!F45/(1+$B23)^('DCF Model'!C19+3)+'DCF Model'!G45/(1+$B23)^('DCF Model'!C19+4)+('DCF Model'!G39+'DCF Model'!G42)*G$17/(1+$B23)^('DCF Model'!C19+4)-'DCF Model'!C16)*1000000/'DCF Model'!C15,0),"") -> 463 | H23: =IFERROR(ROUND(('DCF Model'!C45/(1+$B23)^('DCF Model'!C19+0)+'DCF Model'!D45/(1+$B23)^('DCF Model'!C19+1)+'DCF Model'!E45/(1+$B23)^('DCF Model'!C19+2)+'DCF Model'!F45/(1+$B23)^('DCF Model'!C19+3)+'DCF Model'!G45/(1+$B23)^('DCF Model'!C19+4)+('DCF Model'!G39+'DCF Model'!G42)*H$17/(1+$B23)^('DCF Model'!C19+4)-'DCF Model'!C16)*1000000/'DCF Model'!C15,0),"") -> 511 | I23: =IFERROR(ROUND(('DCF Model'!C45/(1+$B23)^('DCF Model'!C19+0)+'DCF Model'!D45/(1+$B23)^('DCF Model'!C19+1)+'DCF Model'!E45/(1+$B23)^('DCF Model'!C19+2)+'DCF Model'!F45/(1+$B23)^('DCF Model'!C19+3)+'DCF Model'!G45/(1+$B23)^('DCF Model'!C19+4)+('DCF Model'!G39+'DCF Model'!G42)*I$17/(1+$B23)^('DCF Model'!C19+4)-'DCF Model'!C16)*1000000/'DCF Model'!C15,0),"") -> 559
B24: =$C$3+0.015 -> 0.077 | C24: =IFERROR(ROUND(('DCF Model'!C45/(1+$B24)^('DCF Model'!C19+0)+'DCF Model'!D45/(1+$B24)^('DCF Model'!C19+1)+'DCF Model'!E45/(1+$B24)^('DCF Model'!C19+2)+'DCF Model'!F45/(1+$B24)^('DCF Model'!C19+3)+'DCF Model'!G45/(1+$B24)^('DCF Model'!C19+4)+('DCF Model'!G39+'DCF Model'!G42)*C$17/(1+$B24)^('DCF Model'!C19+4)-'DCF Model'!C16)*1000000/'DCF Model'!C15,0),"") -> 265 | D24: =IFERROR(ROUND(('DCF Model'!C45/(1+$B24)^('DCF Model'!C19+0)+'DCF Model'!D45/(1+$B24)^('DCF Model'!C19+1)+'DCF Model'!E45/(1+$B24)^('DCF Model'!C19+2)+'DCF Model'!F45/(1+$B24)^('DCF Model'!C19+3)+'DCF Model'!G45/(1+$B24)^('DCF Model'!C19+4)+('DCF Model'!G39+'DCF Model'!G42)*D$17/(1+$B24)^('DCF Model'!C19+4)-'DCF Model'!C16)*1000000/'DCF Model'!C15,0),"") -> 312 | E24: =IFERROR(ROUND(('DCF Model'!C45/(1+$B24)^('DCF Model'!C19+0)+'DCF Model'!D45/(1+$B24)^('DCF Model'!C19+1)+'DCF Model'!E45/(1+$B24)^('DCF Model'!C19+2)+'DCF Model'!F45/(1+$B24)^('DCF Model'!C19+3)+'DCF Model'!G45/(1+$B24)^('DCF Model'!C19+4)+('DCF Model'!G39+'DCF Model'!G42)*E$17/(1+$B24)^('DCF Model'!C19+4)-'DCF Model'!C16)*1000000/'DCF Model'!C15,0),"") -> 359 | F24: =IFERROR(ROUND(('DCF Model'!C45/(1+$B24)^('DCF Model'!C19+0)+'DCF Model'!D45/(1+$B24)^('DCF Model'!C19+1)+'DCF Model'!E45/(1+$B24)^('DCF Model'!C19+2)+'DCF Model'!F45/(1+$B24)^('DCF Model'!C19+3)+'DCF Model'!G45/(1+$B24)^('DCF Model'!C19+4)+('DCF Model'!G39+'DCF Model'!G42)*F$17/(1+$B24)^('DCF Model'!C19+4)-'DCF Model'!C16)*1000000/'DCF Model'!C15,0),"") -> 406 | G24: =IFERROR(ROUND(('DCF Model'!C45/(1+$B24)^('DCF Model'!C19+0)+'DCF Model'!D45/(1+$B24)^('DCF Model'!C19+1)+'DCF Model'!E45/(1+$B24)^('DCF Model'!C19+2)+'DCF Model'!F45/(1+$B24)^('DCF Model'!C19+3)+'DCF Model'!G45/(1+$B24)^('DCF Model'!C19+4)+('DCF Model'!G39+'DCF Model'!G42)*G$17/(1+$B24)^('DCF Model'!C19+4)-'DCF Model'!C16)*1000000/'DCF Model'!C15,0),"") -> 454 | H24: =IFERROR(ROUND(('DCF Model'!C45/(1+$B24)^('DCF Model'!C19+0)+'DCF Model'!D45/(1+$B24)^('DCF Model'!C19+1)+'DCF Model'!E45/(1+$B24)^('DCF Model'!C19+2)+'DCF Model'!F45/(1+$B24)^('DCF Model'!C19+3)+'DCF Model'!G45/(1+$B24)^('DCF Model'!C19+4)+('DCF Model'!G39+'DCF Model'!G42)*H$17/(1+$B24)^('DCF Model'!C19+4)-'DCF Model'!C16)*1000000/'DCF Model'!C15,0),"") -> 501 | I24: =IFERROR(ROUND(('DCF Model'!C45/(1+$B24)^('DCF Model'!C19+0)+'DCF Model'!D45/(1+$B24)^('DCF Model'!C19+1)+'DCF Model'!E45/(1+$B24)^('DCF Model'!C19+2)+'DCF Model'!F45/(1+$B24)^('DCF Model'!C19+3)+'DCF Model'!G45/(1+$B24)^('DCF Model'!C19+4)+('DCF Model'!G39+'DCF Model'!G42)*I$17/(1+$B24)^('DCF Model'!C19+4)-'DCF Model'!C16)*1000000/'DCF Model'!C15,0),"") -> 548
B26: All values dynamically linked to DCF Model. Headers auto-center on current WACC / Terminal g / Exit Multiple.

Sheet DDM
B2: DDM - 2-Stage Dividend Discount Model (PRIMARY METHOD - bank)
B3: Standard UFCF DCF does not apply to a bank (see 'DCF Model' sheet, used only as an auxiliary ATM-fee-franchise cross-check).
B5: Inputs
B6: Risk-Free Rate | C6: ='DCF Model'!C7 -> 0.023
B7: Beta | C7: ='DCF Model'!C8 -> 0.65
B8: Equity Risk Premium | C8: ='DCF Model'!C9 -> 0.06
B9: Cost of Equity (Ke) | C9: ='DCF Model'!C23 -> 0.062
B10: Shares Outstanding | C10: ='DCF Model'!C15 -> 1110000000
B11: Current Price (JPY) | C11: ='Executive Summary'!C9 -> 327
B12: Terminal Growth (g) | C12: 0.015
B14: Guard (Ke must exceed g) | C14: =IF($C$9<=$C$12,"ERROR: Ke <= g, model invalid","OK") -> OK
B16: Dividend per Share Forecast (Base scenario)
C17: FY2027(E) | D17: FY2028(E) | E17: FY2029(E) | F17: FY2030(E) | G17: FY2031(E)
B18: DPS (JPY) | C18: 11 | D18: 11.5 | E18: 12 | F18: 12.5 | G18: 13 | H18: FY2027(E)=11.00 matches company guidance (dividend forecast, flat vs FY2026/3 actual)
B19: Discount Factor | C19: =1/(1+$C$9)^1 -> 0.94161959 | D19: =1/(1+$C$9)^2 -> 0.88664744 | E19: =1/(1+$C$9)^3 -> 0.8348846 | F19: =1/(1+$C$9)^4 -> 0.78614369 | G19: =1/(1+$C$9)^5 -> 0.7402483
B20: PV of DPS | C20: =C18*C19 -> 10.357815 | D20: =D18*D19 -> 10.196446 | E20: =E18*E19 -> 10.018615 | F20: =F18*F19 -> 9.8267961 | G20: =G18*G19 -> 9.6232278
B22: Valuation
B23: Sum of PV of DPS (Yr 1-5) | C23: =SUM(C20:G20) -> 50.0229
B24: Terminal Value (Yr 5) | C24: =G18*(1+$C$12)/($C$9-$C$12) -> 280.74468
B25: PV of Terminal Value | C25: =C24*G19 -> 207.82077
B26: Implied Value per Share (JPY) | C26: =ROUND(C23+C25,0) -> 258
B27: Upside / (Downside) vs Current Price | C27: =C26/$C$11-1 -> -0.21100917
B29: Sensitivity: Ke (rows) x Terminal g (cols)
B30: Ke \ g | C30: 0.005 | D30: 0.0075 | E30: 0.01 | F30: 0.0125 | G30: 0.015 | H30: 0.0175 | I30: 0.02 | J30: 0.0225 | K30: 0.025
B31: 0.052 | C31: =IF($B31<=C$30,"",ROUND(SUMPRODUCT($C$18:$G$18,1/(1+$B31)^{1,2,3,4,5})+G18*(1+C$30)/($B31-C$30)/(1+$B31)^5,0)) -> 267 | D31: =IF($B31<=D$30,"",ROUND(SUMPRODUCT($C$18:$G$18,1/(1+$B31)^{1,2,3,4,5})+G18*(1+D$30)/($B31-D$30)/(1+$B31)^5,0)) -> 280 | E31: =IF($B31<=E$30,"",ROUND(SUMPRODUCT($C$18:$G$18,1/(1+$B31)^{1,2,3,4,5})+G18*(1+E$30)/($B31-E$30)/(1+$B31)^5,0)) -> 294 | F31: =IF($B31<=F$30,"",ROUND(SUMPRODUCT($C$18:$G$18,1/(1+$B31)^{1,2,3,4,5})+G18*(1+F$30)/($B31-F$30)/(1+$B31)^5,0)) -> 310 | G31: =IF($B31<=G$30,"",ROUND(SUMPRODUCT($C$18:$G$18,1/(1+$B31)^{1,2,3,4,5})+G18*(1+G$30)/($B31-G$30)/(1+$B31)^5,0)) -> 328 | H31: =IF($B31<=H$30,"",ROUND(SUMPRODUCT($C$18:$G$18,1/(1+$B31)^{1,2,3,4,5})+G18*(1+H$30)/($B31-H$30)/(1+$B31)^5,0)) -> 349 | I31: =IF($B31<=I$30,"",ROUND(SUMPRODUCT($C$18:$G$18,1/(1+$B31)^{1,2,3,4,5})+G18*(1+I$30)/($B31-I$30)/(1+$B31)^5,0)) -> 373 | J31: =IF($B31<=J$30,"",ROUND(SUMPRODUCT($C$18:$G$18,1/(1+$B31)^{1,2,3,4,5})+G18*(1+J$30)/($B31-J$30)/(1+$B31)^5,0)) -> 401 | K31: =IF($B31<=K$30,"",ROUND(SUMPRODUCT($C$18:$G$18,1/(1+$B31)^{1,2,3,4,5})+G18*(1+K$30)/($B31-K$30)/(1+$B31)^5,0)) -> 434
B32: 0.0545 | C32: =IF($B32<=C$30,"",ROUND(SUMPRODUCT($C$18:$G$18,1/(1+$B32)^{1,2,3,4,5})+G18*(1+C$30)/($B32-C$30)/(1+$B32)^5,0)) -> 254 | D32: =IF($B32<=D$30,"",ROUND(SUMPRODUCT($C$18:$G$18,1/(1+$B32)^{1,2,3,4,5})+G18*(1+D$30)/($B32-D$30)/(1+$B32)^5,0)) -> 265 | E32: =IF($B32<=E$30,"",ROUND(SUMPRODUCT($C$18:$G$18,1/(1+$B32)^{1,2,3,4,5})+G18*(1+E$30)/($B32-E$30)/(1+$B32)^5,0)) -> 277 | F32: =IF($B32<=F$30,"",ROUND(SUMPRODUCT($C$18:$G$18,1/(1+$B32)^{1,2,3,4,5})+G18*(1+F$30)/($B32-F$30)/(1+$B32)^5,0)) -> 291 | G32: =IF($B32<=G$30,"",ROUND(SUMPRODUCT($C$18:$G$18,1/(1+$B32)^{1,2,3,4,5})+G18*(1+G$30)/($B32-G$30)/(1+$B32)^5,0)) -> 307 | H32: =IF($B32<=H$30,"",ROUND(SUMPRODUCT($C$18:$G$18,1/(1+$B32)^{1,2,3,4,5})+G18*(1+H$30)/($B32-H$30)/(1+$B32)^5,0)) -> 325 | I32: =IF($B32<=I$30,"",ROUND(SUMPRODUCT($C$18:$G$18,1/(1+$B32)^{1,2,3,4,5})+G18*(1+I$30)/($B32-I$30)/(1+$B32)^5,0)) -> 346 | J32: =IF($B32<=J$30,"",ROUND(SUMPRODUCT($C$18:$G$18,1/(1+$B32)^{1,2,3,4,5})+G18*(1+J$30)/($B32-J$30)/(1+$B32)^5,0)) -> 370 | K32: =IF($B32<=K$30,"",ROUND(SUMPRODUCT($C$18:$G$18,1/(1+$B32)^{1,2,3,4,5})+G18*(1+K$30)/($B32-K$30)/(1+$B32)^5,0)) -> 398
B33: 0.057 | C33: =IF($B33<=C$30,"",ROUND(SUMPRODUCT($C$18:$G$18,1/(1+$B33)^{1,2,3,4,5})+G18*(1+C$30)/($B33-C$30)/(1+$B33)^5,0)) -> 241 | D33: =IF($B33<=D$30,"",ROUND(SUMPRODUCT($C$18:$G$18,1/(1+$B33)^{1,2,3,4,5})+G18*(1+D$30)/($B33-D$30)/(1+$B33)^5,0)) -> 251 | E33: =IF($B33<=E$30,"",ROUND(SUMPRODUCT($C$18:$G$18,1/(1+$B33)^{1,2,3,4,5})+G18*(1+E$30)/($B33-E$30)/(1+$B33)^5,0)) -> 262 | F33: =IF($B33<=F$30,"",ROUND(SUMPRODUCT($C$18:$G$18,1/(1+$B33)^{1,2,3,4,5})+G18*(1+F$30)/($B33-F$30)/(1+$B33)^5,0)) -> 275 | G33: =IF($B33<=G$30,"",ROUND(SUMPRODUCT($C$18:$G$18,1/(1+$B33)^{1,2,3,4,5})+G18*(1+G$30)/($B33-G$30)/(1+$B33)^5,0)) -> 289 | H33: =IF($B33<=H$30,"",ROUND(SUMPRODUCT($C$18:$G$18,1/(1+$B33)^{1,2,3,4,5})+G18*(1+H$30)/($B33-H$30)/(1+$B33)^5,0)) -> 305 | I33: =IF($B33<=I$30,"",ROUND(SUMPRODUCT($C$18:$G$18,1/(1+$B33)^{1,2,3,4,5})+G18*(1+I$30)/($B33-I$30)/(1+$B33)^5,0)) -> 322 | J33: =IF($B33<=J$30,"",ROUND(SUMPRODUCT($C$18:$G$18,1/(1+$B33)^{1,2,3,4,5})+G18*(1+J$30)/($B33-J$30)/(1+$B33)^5,0)) -> 343 | K33: =IF($B33<=K$30,"",ROUND(SUMPRODUCT($C$18:$G$18,1/(1+$B33)^{1,2,3,4,5})+G18*(1+K$30)/($B33-K$30)/(1+$B33)^5,0)) -> 366
B34: 0.0595 | C34: =IF($B34<=C$30,"",ROUND(SUMPRODUCT($C$18:$G$18,1/(1+$B34)^{1,2,3,4,5})+G18*(1+C$30)/($B34-C$30)/(1+$B34)^5,0)) -> 230 | D34: =IF($B34<=D$30,"",ROUND(SUMPRODUCT($C$18:$G$18,1/(1+$B34)^{1,2,3,4,5})+G18*(1+D$30)/($B34-D$30)/(1+$B34)^5,0)) -> 239 | E34: =IF($B34<=E$30,"",ROUND(SUMPRODUCT($C$18:$G$18,1/(1+$B34)^{1,2,3,4,5})+G18*(1+E$30)/($B34-E$30)/(1+$B34)^5,0)) -> 249 | F34: =IF($B34<=F$30,"",ROUND(SUMPRODUCT($C$18:$G$18,1/(1+$B34)^{1,2,3,4,5})+G18*(1+F$30)/($B34-F$30)/(1+$B34)^5,0)) -> 260 | G34: =IF($B34<=G$30,"",ROUND(SUMPRODUCT($C$18:$G$18,1/(1+$B34)^{1,2,3,4,5})+G18*(1+G$30)/($B34-G$30)/(1+$B34)^5,0)) -> 272 | H34: =IF($B34<=H$30,"",ROUND(SUMPRODUCT($C$18:$G$18,1/(1+$B34)^{1,2,3,4,5})+G18*(1+H$30)/($B34-H$30)/(1+$B34)^5,0)) -> 286 | I34: =IF($B34<=I$30,"",ROUND(SUMPRODUCT($C$18:$G$18,1/(1+$B34)^{1,2,3,4,5})+G18*(1+I$30)/($B34-I$30)/(1+$B34)^5,0)) -> 302 | J34: =IF($B34<=J$30,"",ROUND(SUMPRODUCT($C$18:$G$18,1/(1+$B34)^{1,2,3,4,5})+G18*(1+J$30)/($B34-J$30)/(1+$B34)^5,0)) -> 319 | K34: =IF($B34<=K$30,"",ROUND(SUMPRODUCT($C$18:$G$18,1/(1+$B34)^{1,2,3,4,5})+G18*(1+K$30)/($B34-K$30)/(1+$B34)^5,0)) -> 340
B35: 0.062 | C35: =IF($B35<=C$30,"",ROUND(SUMPRODUCT($C$18:$G$18,1/(1+$B35)^{1,2,3,4,5})+G18*(1+C$30)/($B35-C$30)/(1+$B35)^5,0)) -> 220 | D35: =IF($B35<=D$30,"",ROUND(SUMPRODUCT($C$18:$G$18,1/(1+$B35)^{1,2,3,4,5})+G18*(1+D$30)/($B35-D$30)/(1+$B35)^5,0)) -> 228 | E35: =IF($B35<=E$30,"",ROUND(SUMPRODUCT($C$18:$G$18,1/(1+$B35)^{1,2,3,4,5})+G18*(1+E$30)/($B35-E$30)/(1+$B35)^5,0)) -> 237 | F35: =IF($B35<=F$30,"",ROUND(SUMPRODUCT($C$18:$G$18,1/(1+$B35)^{1,2,3,4,5})+G18*(1+F$30)/($B35-F$30)/(1+$B35)^5,0)) -> 247 | G35: =IF($B35<=G$30,"",ROUND(SUMPRODUCT($C$18:$G$18,1/(1+$B35)^{1,2,3,4,5})+G18*(1+G$30)/($B35-G$30)/(1+$B35)^5,0)) -> 258 | H35: =IF($B35<=H$30,"",ROUND(SUMPRODUCT($C$18:$G$18,1/(1+$B35)^{1,2,3,4,5})+G18*(1+H$30)/($B35-H$30)/(1+$B35)^5,0)) -> 270 | I35: =IF($B35<=I$30,"",ROUND(SUMPRODUCT($C$18:$G$18,1/(1+$B35)^{1,2,3,4,5})+G18*(1+I$30)/($B35-I$30)/(1+$B35)^5,0)) -> 284 | J35: =IF($B35<=J$30,"",ROUND(SUMPRODUCT($C$18:$G$18,1/(1+$B35)^{1,2,3,4,5})+G18*(1+J$30)/($B35-J$30)/(1+$B35)^5,0)) -> 299 | K35: =IF($B35<=K$30,"",ROUND(SUMPRODUCT($C$18:$G$18,1/(1+$B35)^{1,2,3,4,5})+G18*(1+K$30)/($B35-K$30)/(1+$B35)^5,0)) -> 317
B36: 0.0645 | C36: =IF($B36<=C$30,"",ROUND(SUMPRODUCT($C$18:$G$18,1/(1+$B36)^{1,2,3,4,5})+G18*(1+C$30)/($B36-C$30)/(1+$B36)^5,0)) -> 210 | D36: =IF($B36<=D$30,"",ROUND(SUMPRODUCT($C$18:$G$18,1/(1+$B36)^{1,2,3,4,5})+G18*(1+D$30)/($B36-D$30)/(1+$B36)^5,0)) -> 218 | E36: =IF($B36<=E$30,"",ROUND(SUMPRODUCT($C$18:$G$18,1/(1+$B36)^{1,2,3,4,5})+G18*(1+E$30)/($B36-E$30)/(1+$B36)^5,0)) -> 226 | F36: =IF($B36<=F$30,"",ROUND(SUMPRODUCT($C$18:$G$18,1/(1+$B36)^{1,2,3,4,5})+G18*(1+F$30)/($B36-F$30)/(1+$B36)^5,0)) -> 235 | G36: =IF($B36<=G$30,"",ROUND(SUMPRODUCT($C$18:$G$18,1/(1+$B36)^{1,2,3,4,5})+G18*(1+G$30)/($B36-G$30)/(1+$B36)^5,0)) -> 245 | H36: =IF($B36<=H$30,"",ROUND(SUMPRODUCT($C$18:$G$18,1/(1+$B36)^{1,2,3,4,5})+G18*(1+H$30)/($B36-H$30)/(1+$B36)^5,0)) -> 256 | I36: =IF($B36<=I$30,"",ROUND(SUMPRODUCT($C$18:$G$18,1/(1+$B36)^{1,2,3,4,5})+G18*(1+I$30)/($B36-I$30)/(1+$B36)^5,0)) -> 268 | J36: =IF($B36<=J$30,"",ROUND(SUMPRODUCT($C$18:$G$18,1/(1+$B36)^{1,2,3,4,5})+G18*(1+J$30)/($B36-J$30)/(1+$B36)^5,0)) -> 281 | K36: =IF($B36<=K$30,"",ROUND(SUMPRODUCT($C$18:$G$18,1/(1+$B36)^{1,2,3,4,5})+G18*(1+K$30)/($B36-K$30)/(1+$B36)^5,0)) -> 296
B37: 0.067 | C37: =IF($B37<=C$30,"",ROUND(SUMPRODUCT($C$18:$G$18,1/(1+$B37)^{1,2,3,4,5})+G18*(1+C$30)/($B37-C$30)/(1+$B37)^5,0)) -> 202 | D37: =IF($B37<=D$30,"",ROUND(SUMPRODUCT($C$18:$G$18,1/(1+$B37)^{1,2,3,4,5})+G18*(1+D$30)/($B37-D$30)/(1+$B37)^5,0)) -> 208 | E37: =IF($B37<=E$30,"",ROUND(SUMPRODUCT($C$18:$G$18,1/(1+$B37)^{1,2,3,4,5})+G18*(1+E$30)/($B37-E$30)/(1+$B37)^5,0)) -> 216 | F37: =IF($B37<=F$30,"",ROUND(SUMPRODUCT($C$18:$G$18,1/(1+$B37)^{1,2,3,4,5})+G18*(1+F$30)/($B37-F$30)/(1+$B37)^5,0)) -> 224 | G37: =IF($B37<=G$30,"",ROUND(SUMPRODUCT($C$18:$G$18,1/(1+$B37)^{1,2,3,4,5})+G18*(1+G$30)/($B37-G$30)/(1+$B37)^5,0)) -> 233 | H37: =IF($B37<=H$30,"",ROUND(SUMPRODUCT($C$18:$G$18,1/(1+$B37)^{1,2,3,4,5})+G18*(1+H$30)/($B37-H$30)/(1+$B37)^5,0)) -> 243 | I37: =IF($B37<=I$30,"",ROUND(SUMPRODUCT($C$18:$G$18,1/(1+$B37)^{1,2,3,4,5})+G18*(1+I$30)/($B37-I$30)/(1+$B37)^5,0)) -> 253 | J37: =IF($B37<=J$30,"",ROUND(SUMPRODUCT($C$18:$G$18,1/(1+$B37)^{1,2,3,4,5})+G18*(1+J$30)/($B37-J$30)/(1+$B37)^5,0)) -> 265 | K37: =IF($B37<=K$30,"",ROUND(SUMPRODUCT($C$18:$G$18,1/(1+$B37)^{1,2,3,4,5})+G18*(1+K$30)/($B37-K$30)/(1+$B37)^5,0)) -> 279
B38: 0.0695 | C38: =IF($B38<=C$30,"",ROUND(SUMPRODUCT($C$18:$G$18,1/(1+$B38)^{1,2,3,4,5})+G18*(1+C$30)/($B38-C$30)/(1+$B38)^5,0)) -> 194 | D38: =IF($B38<=D$30,"",ROUND(SUMPRODUCT($C$18:$G$18,1/(1+$B38)^{1,2,3,4,5})+G18*(1+D$30)/($B38-D$30)/(1+$B38)^5,0)) -> 200 | E38: =IF($B38<=E$30,"",ROUND(SUMPRODUCT($C$18:$G$18,1/(1+$B38)^{1,2,3,4,5})+G18*(1+E$30)/($B38-E$30)/(1+$B38)^5,0)) -> 207 | F38: =IF($B38<=F$30,"",ROUND(SUMPRODUCT($C$18:$G$18,1/(1+$B38)^{1,2,3,4,5})+G18*(1+F$30)/($B38-F$30)/(1+$B38)^5,0)) -> 214 | G38: =IF($B38<=G$30,"",ROUND(SUMPRODUCT($C$18:$G$18,1/(1+$B38)^{1,2,3,4,5})+G18*(1+G$30)/($B38-G$30)/(1+$B38)^5,0)) -> 222 | H38: =IF($B38<=H$30,"",ROUND(SUMPRODUCT($C$18:$G$18,1/(1+$B38)^{1,2,3,4,5})+G18*(1+H$30)/($B38-H$30)/(1+$B38)^5,0)) -> 231 | I38: =IF($B38<=I$30,"",ROUND(SUMPRODUCT($C$18:$G$18,1/(1+$B38)^{1,2,3,4,5})+G18*(1+I$30)/($B38-I$30)/(1+$B38)^5,0)) -> 240 | J38: =IF($B38<=J$30,"",ROUND(SUMPRODUCT($C$18:$G$18,1/(1+$B38)^{1,2,3,4,5})+G18*(1+J$30)/($B38-J$30)/(1+$B38)^5,0)) -> 251 | K38: =IF($B38<=K$30,"",ROUND(SUMPRODUCT($C$18:$G$18,1/(1+$B38)^{1,2,3,4,5})+G18*(1+K$30)/($B38-K$30)/(1+$B38)^5,0)) -> 263
B39: 0.072 | C39: =IF($B39<=C$30,"",ROUND(SUMPRODUCT($C$18:$G$18,1/(1+$B39)^{1,2,3,4,5})+G18*(1+C$30)/($B39-C$30)/(1+$B39)^5,0)) -> 186 | D39: =IF($B39<=D$30,"",ROUND(SUMPRODUCT($C$18:$G$18,1/(1+$B39)^{1,2,3,4,5})+G18*(1+D$30)/($B39-D$30)/(1+$B39)^5,0)) -> 192 | E39: =IF($B39<=E$30,"",ROUND(SUMPRODUCT($C$18:$G$18,1/(1+$B39)^{1,2,3,4,5})+G18*(1+E$30)/($B39-E$30)/(1+$B39)^5,0)) -> 198 | F39: =IF($B39<=F$30,"",ROUND(SUMPRODUCT($C$18:$G$18,1/(1+$B39)^{1,2,3,4,5})+G18*(1+F$30)/($B39-F$30)/(1+$B39)^5,0)) -> 205 | G39: =IF($B39<=G$30,"",ROUND(SUMPRODUCT($C$18:$G$18,1/(1+$B39)^{1,2,3,4,5})+G18*(1+G$30)/($B39-G$30)/(1+$B39)^5,0)) -> 212 | H39: =IF($B39<=H$30,"",ROUND(SUMPRODUCT($C$18:$G$18,1/(1+$B39)^{1,2,3,4,5})+G18*(1+H$30)/($B39-H$30)/(1+$B39)^5,0)) -> 220 | I39: =IF($B39<=I$30,"",ROUND(SUMPRODUCT($C$18:$G$18,1/(1+$B39)^{1,2,3,4,5})+G18*(1+I$30)/($B39-I$30)/(1+$B39)^5,0)) -> 229 | J39: =IF($B39<=J$30,"",ROUND(SUMPRODUCT($C$18:$G$18,1/(1+$B39)^{1,2,3,4,5})+G18*(1+J$30)/($B39-J$30)/(1+$B39)^5,0)) -> 238 | K39: =IF($B39<=K$30,"",ROUND(SUMPRODUCT($C$18:$G$18,1/(1+$B39)^{1,2,3,4,5})+G18*(1+K$30)/($B39-K$30)/(1+$B39)^5,0)) -> 249

Sheet Residual Income
B2: Residual Income Model (PRIMARY METHOD - bank)
B3: Value = Book Value + PV(Residual Income). When ROE approaches Ke, value converges to book value.
B5: Inputs
B6: Beginning Book Value (JPY mn) | C6: 280491
B7: Shares Outstanding | C7: =DDM!C$10 -> 1110000000
B8: BPS_0 (JPY) | C8: =C6/C7*1000000 -> 252.69459
B9: Cost of Equity (Ke) | C9: =DDM!C$9 -> 0.062
B10: Terminal Growth (g) | C10: =DDM!C$12 -> 0.015
B12: ROE Forecast (Base scenario)
C13: FY2027(E) | D13: FY2028(E) | E13: FY2029(E) | F13: FY2030(E) | G13: FY2031(E)
B14: ROE | C14: 0.061 | D14: 0.065 | E14: 0.068 | F14: 0.07 | G14: 0.07 | H14: FY2027(E)=6.1% = company net income guidance 17,000 / beginning equity 280,491
B16: Book Value Rollforward (JPY mn)
C17: FY2027(E) | D17: FY2028(E) | E17: FY2029(E) | F17: FY2030(E) | G17: FY2031(E)
B18: Net Income_t = ROE_t x BV_(t-1) | C18: =C14*$C$6 -> 17109.951 | D18: =D14*C20 -> 18550.412 | E18: =E14*D20 -> 19799.993 | F18: =F14*E20 -> 20835.945 | G18: =G14*F20 -> 21323.211
B19: Dividends_t (from DDM) | C19: =DDM!C18*C7/1000000 -> 12210 | D19: =DDM!D18*C7/1000000 -> 12765 | E19: =DDM!E18*C7/1000000 -> 13320 | F19: =DDM!F18*C7/1000000 -> 13875 | G19: =DDM!G18*C7/1000000 -> 14430
B20: Ending Book Value | C20: =$C$6+C18-C19 -> 285390.95 | D20: =C20+D18-D19 -> 291176.36 | E20: =D20+E18-E19 -> 297656.36 | F20: =E20+F18-F19 -> 304617.3 | G20: =F20+G18-G19 -> 311510.51
B21: Residual Income_t = (ROE_t - Ke) x BV_(t-1) | C21: =(C14-$C$9)*$C$6 -> -280.491 | D21: =(D14-$C$9)*C20 -> 856.17285 | E21: =(E14-$C$9)*D20 -> 1747.0582 | F21: =(F14-$C$9)*E20 -> 2381.2508 | G21: =(G14-$C$9)*F20 -> 2436.9384
B22: PV of Residual Income | C22: =C21/(1+$C$9)^1 -> -264.11582 | D22: =D21/(1+$C$9)^2 -> 759.12347 | E22: =E21/(1+$C$9)^3 -> 1458.592 | F22: =F21/(1+$C$9)^4 -> 1872.0053 | G22: =G21/(1+$C$9)^5 -> 1803.9395
B24: Valuation
B25: Sum of PV of Residual Income | C25: =SUM(C22:G22) -> 5629.5444
B26: Terminal Residual Income | C26: =G21*(1+$C$10)/($C$9-$C$10) -> 52627.5
B27: PV of Terminal Residual Income | C27: =C26/(1+$C$9)^5 -> 38957.417
B28: Equity Value (JPY mn) | C28: =C6+C25+C27 -> 325077.96
B29: Implied Value per Share (JPY) | C29: =ROUND(C28/C7*1000000,0) -> 293
B30: Upside / (Downside) vs Current Price | C30: =C29/DDM!C$11-1 -> -0.10397554
B32: Note: ROE sits close to Ke, so Residual Income per year is small and the implied value sits close to BPS_0 -- the theoretical price is structurally anchored to book value, not to growth assumptions. Whether ROE durably exceeds Ke is the entire valuation question for this stock.
B34: Justified P/B = (ROE - g) / (Ke - g)
B35: ROE \ Ke | C35: 0.052 | D35: 0.057 | E35: 0.062 | F35: 0.067 | G35: 0.072
B36: 0.045 | C36: =IF(C$35<=$C$10,"",ROUND(($B36-$C$10)/(C$35-$C$10),2)) -> 0.81 | D36: =IF(D$35<=$C$10,"",ROUND(($B36-$C$10)/(D$35-$C$10),2)) -> 0.71 | E36: =IF(E$35<=$C$10,"",ROUND(($B36-$C$10)/(E$35-$C$10),2)) -> 0.64 | F36: =IF(F$35<=$C$10,"",ROUND(($B36-$C$10)/(F$35-$C$10),2)) -> 0.58 | G36: =IF(G$35<=$C$10,"",ROUND(($B36-$C$10)/(G$35-$C$10),2)) -> 0.53
B37: 0.05 | C37: =IF(C$35<=$C$10,"",ROUND(($B37-$C$10)/(C$35-$C$10),2)) -> 0.95 | D37: =IF(D$35<=$C$10,"",ROUND(($B37-$C$10)/(D$35-$C$10),2)) -> 0.83 | E37: =IF(E$35<=$C$10,"",ROUND(($B37-$C$10)/(E$35-$C$10),2)) -> 0.74 | F37: =IF(F$35<=$C$10,"",ROUND(($B37-$C$10)/(F$35-$C$10),2)) -> 0.67 | G37: =IF(G$35<=$C$10,"",ROUND(($B37-$C$10)/(G$35-$C$10),2)) -> 0.61
B38: 0.055 | C38: =IF(C$35<=$C$10,"",ROUND(($B38-$C$10)/(C$35-$C$10),2)) -> 1.08 | D38: =IF(D$35<=$C$10,"",ROUND(($B38-$C$10)/(D$35-$C$10),2)) -> 0.95 | E38: =IF(E$35<=$C$10,"",ROUND(($B38-$C$10)/(E$35-$C$10),2)) -> 0.85 | F38: =IF(F$35<=$C$10,"",ROUND(($B38-$C$10)/(F$35-$C$10),2)) -> 0.77 | G38: =IF(G$35<=$C$10,"",ROUND(($B38-$C$10)/(G$35-$C$10),2)) -> 0.7
B39: 0.06 | C39: =IF(C$35<=$C$10,"",ROUND(($B39-$C$10)/(C$35-$C$10),2)) -> 1.22 | D39: =IF(D$35<=$C$10,"",ROUND(($B39-$C$10)/(D$35-$C$10),2)) -> 1.07 | E39: =IF(E$35<=$C$10,"",ROUND(($B39-$C$10)/(E$35-$C$10),2)) -> 0.96 | F39: =IF(F$35<=$C$10,"",ROUND(($B39-$C$10)/(F$35-$C$10),2)) -> 0.87 | G39: =IF(G$35<=$C$10,"",ROUND(($B39-$C$10)/(G$35-$C$10),2)) -> 0.79
B40: 0.065 | C40: =IF(C$35<=$C$10,"",ROUND(($B40-$C$10)/(C$35-$C$10),2)) -> 1.35 | D40: =IF(D$35<=$C$10,"",ROUND(($B40-$C$10)/(D$35-$C$10),2)) -> 1.19 | E40: =IF(E$35<=$C$10,"",ROUND(($B40-$C$10)/(E$35-$C$10),2)) -> 1.06 | F40: =IF(F$35<=$C$10,"",ROUND(($B40-$C$10)/(F$35-$C$10),2)) -> 0.96 | G40: =IF(G$35<=$C$10,"",ROUND(($B40-$C$10)/(G$35-$C$10),2)) -> 0.88
B41: 0.07 | C41: =IF(C$35<=$C$10,"",ROUND(($B41-$C$10)/(C$35-$C$10),2)) -> 1.49 | D41: =IF(D$35<=$C$10,"",ROUND(($B41-$C$10)/(D$35-$C$10),2)) -> 1.31 | E41: =IF(E$35<=$C$10,"",ROUND(($B41-$C$10)/(E$35-$C$10),2)) -> 1.17 | F41: =IF(F$35<=$C$10,"",ROUND(($B41-$C$10)/(F$35-$C$10),2)) -> 1.06 | G41: =IF(G$35<=$C$10,"",ROUND(($B41-$C$10)/(G$35-$C$10),2)) -> 0.96
B42: 0.075 | C42: =IF(C$35<=$C$10,"",ROUND(($B42-$C$10)/(C$35-$C$10),2)) -> 1.62 | D42: =IF(D$35<=$C$10,"",ROUND(($B42-$C$10)/(D$35-$C$10),2)) -> 1.43 | E42: =IF(E$35<=$C$10,"",ROUND(($B42-$C$10)/(E$35-$C$10),2)) -> 1.28 | F42: =IF(F$35<=$C$10,"",ROUND(($B42-$C$10)/(F$35-$C$10),2)) -> 1.15 | G42: =IF(G$35<=$C$10,"",ROUND(($B42-$C$10)/(G$35-$C$10),2)) -> 1.05
B43: 0.08 | C43: =IF(C$35<=$C$10,"",ROUND(($B43-$C$10)/(C$35-$C$10),2)) -> 1.76 | D43: =IF(D$35<=$C$10,"",ROUND(($B43-$C$10)/(D$35-$C$10),2)) -> 1.55 | E43: =IF(E$35<=$C$10,"",ROUND(($B43-$C$10)/(E$35-$C$10),2)) -> 1.38 | F43: =IF(F$35<=$C$10,"",ROUND(($B43-$C$10)/(F$35-$C$10),2)) -> 1.25 | G43: =IF(G$35<=$C$10,"",ROUND(($B43-$C$10)/(G$35-$C$10),2)) -> 1.14
B44: 0.085 | C44: =IF(C$35<=$C$10,"",ROUND(($B44-$C$10)/(C$35-$C$10),2)) -> 1.89 | D44: =IF(D$35<=$C$10,"",ROUND(($B44-$C$10)/(D$35-$C$10),2)) -> 1.67 | E44: =IF(E$35<=$C$10,"",ROUND(($B44-$C$10)/(E$35-$C$10),2)) -> 1.49 | F44: =IF(F$35<=$C$10,"",ROUND(($B44-$C$10)/(F$35-$C$10),2)) -> 1.35 | G44: =IF(G$35<=$C$10,"",ROUND(($B44-$C$10)/(G$35-$C$10),2)) -> 1.23
B46: Implied Share Price at each (ROE, Ke) node = BPS_0 x Justified P/B (JPY)
B47: ROE \ Ke | C47: 0.052 | D47: 0.057 | E47: 0.062 | F47: 0.067 | G47: 0.072
B48: 0.045 | C48: =IF(C36="","",ROUND(C36*$C$8,0)) -> 205 | D48: =IF(D36="","",ROUND(D36*$C$8,0)) -> 179 | E48: =IF(E36="","",ROUND(E36*$C$8,0)) -> 162 | F48: =IF(F36="","",ROUND(F36*$C$8,0)) -> 147 | G48: =IF(G36="","",ROUND(G36*$C$8,0)) -> 134
B49: 0.05 | C49: =IF(C37="","",ROUND(C37*$C$8,0)) -> 240 | D49: =IF(D37="","",ROUND(D37*$C$8,0)) -> 210 | E49: =IF(E37="","",ROUND(E37*$C$8,0)) -> 187 | F49: =IF(F37="","",ROUND(F37*$C$8,0)) -> 169 | G49: =IF(G37="","",ROUND(G37*$C$8,0)) -> 154
B50: 0.055 | C50: =IF(C38="","",ROUND(C38*$C$8,0)) -> 273 | D50: =IF(D38="","",ROUND(D38*$C$8,0)) -> 240 | E50: =IF(E38="","",ROUND(E38*$C$8,0)) -> 215 | F50: =IF(F38="","",ROUND(F38*$C$8,0)) -> 195 | G50: =IF(G38="","",ROUND(G38*$C$8,0)) -> 177
B51: 0.06 | C51: =IF(C39="","",ROUND(C39*$C$8,0)) -> 308 | D51: =IF(D39="","",ROUND(D39*$C$8,0)) -> 270 | E51: =IF(E39="","",ROUND(E39*$C$8,0)) -> 243 | F51: =IF(F39="","",ROUND(F39*$C$8,0)) -> 220 | G51: =IF(G39="","",ROUND(G39*$C$8,0)) -> 200
B52: 0.065 | C52: =IF(C40="","",ROUND(C40*$C$8,0)) -> 341 | D52: =IF(D40="","",ROUND(D40*$C$8,0)) -> 301 | E52: =IF(E40="","",ROUND(E40*$C$8,0)) -> 268 | F52: =IF(F40="","",ROUND(F40*$C$8,0)) -> 243 | G52: =IF(G40="","",ROUND(G40*$C$8,0)) -> 222
B53: 0.07 | C53: =IF(C41="","",ROUND(C41*$C$8,0)) -> 377 | D53: =IF(D41="","",ROUND(D41*$C$8,0)) -> 331 | E53: =IF(E41="","",ROUND(E41*$C$8,0)) -> 296 | F53: =IF(F41="","",ROUND(F41*$C$8,0)) -> 268 | G53: =IF(G41="","",ROUND(G41*$C$8,0)) -> 243
B54: 0.075 | C54: =IF(C42="","",ROUND(C42*$C$8,0)) -> 409 | D54: =IF(D42="","",ROUND(D42*$C$8,0)) -> 361 | E54: =IF(E42="","",ROUND(E42*$C$8,0)) -> 323 | F54: =IF(F42="","",ROUND(F42*$C$8,0)) -> 291 | G54: =IF(G42="","",ROUND(G42*$C$8,0)) -> 265
B55: 0.08 | C55: =IF(C43="","",ROUND(C43*$C$8,0)) -> 445 | D55: =IF(D43="","",ROUND(D43*$C$8,0)) -> 392 | E55: =IF(E43="","",ROUND(E43*$C$8,0)) -> 349 | F55: =IF(F43="","",ROUND(F43*$C$8,0)) -> 316 | G55: =IF(G43="","",ROUND(G43*$C$8,0)) -> 288
B56: 0.085 | C56: =IF(C44="","",ROUND(C44*$C$8,0)) -> 478 | D56: =IF(D44="","",ROUND(D44*$C$8,0)) -> 422 | E56: =IF(E44="","",ROUND(E44*$C$8,0)) -> 377 | F56: =IF(F44="","",ROUND(F44*$C$8,0)) -> 341 | G56: =IF(G44="","",ROUND(G44*$C$8,0)) -> 311
