Workbook

Sheet Executive Summary
B1: DISCLAIMER: This is a sample analysis for demonstration purposes only. It does not constitute investment advice.
B3: 株式会社セブン銀行 (8410.T)
B4: Equity Research Report
B6: Company | C6: 株式会社セブン銀行
B7: Ticker | C7: 8410.T (TSE)
B8: Sector | C8: Banking (ATM network / fee-based financial infrastructure)
B9: Current Price | C9: 340
B10: Target Price (DCF Mid) - DDM / Residual Income の平均 | C10: =IF(AND(ISNUMBER(C18),ISNUMBER(C19)),ROUND(AVERAGE(C18:C19),0),"N/A") -> 187
B11: Recommendation | C11: =IF(NOT(ISNUMBER(C12)),"N/A",IF(C12>0.15,"BUY",IF(C12>0.05,"HOLD","SELL"))) -> SELL
B12: Upside / Downside | C12: =IF(ISNUMBER(C10),(C10-C9)/C9,"N/A") -> -0.45
B14: Valuation Summary
B15: Methodology | C15: Implied Value (JPY) | D15: vs Current Price
B16: DCF - Perpetuity Growth [参考・Target不算入 — 型D: 銀行に DCF は成立しない] | C16: =IF('DCF Model'!C53<'DCF Model'!C16,"INVALID (EV < net debt)",'DCF Model'!C55) -> 327 | D16: =IF(ISNUMBER(C16),(C16-C9)/C9,"N/A") -> -0.038235294
B17: DCF - Exit Multiple [参考・Target不算入 — 型D: 銀行に DCF は成立しない] | C17: =IF('DCF Model'!C62<'DCF Model'!C16,"INVALID (EV < net debt)",'DCF Model'!C64) -> 378 | D17: =IF(ISNUMBER(C17),(C17-C9)/C9,"N/A") -> 0.11176471
B18: DDM - 2-Stage Dividend Discount (主手法) | C18: =DDM!C26 -> 174
B19: Residual Income (主手法) | C19: ='Residual Income'!C29 -> 200
B20: Comps - EV/EBITDA Median [参考・Target不算入] | C20: ='Comps Analysis'!C27 -> INVALID (n<3) | D20: =IF(ISNUMBER(C18),(C18-C9)/C9,"N/A") -> -0.48823529
B21: Comps - PER Median [参考・Target不算入] | C21: ='Comps Analysis'!C28 -> 186 | D21: =IF(ISNUMBER(C19),(C19-C9)/C9,"N/A") -> -0.41176471
B22: Note: Target Mid は DCF 2法（PGM / Exit）の平均のみ。Comps 2法は [参考] で Target 不算入（EV<ネットデットで株式価値が負になる手法は INVALID として平均から除外） ■【型D: 銀行】手順書 §2 により **DCF は成立しない**（負債が資金調達ではなく原材料であり、運転資本が定義できず、自己資本規制が配当を制約するため）。**Target は DDM と Residual Income の2手法の平均のみ**で構成し、DCF の2脚（PGM / Exit）と Comps の EV 倍率は Target に算入しない。DCF Model シートは ATM 手数料フランチャイズの採算を読むための補助として残してある。
B23: DCF Valuation Range (PGM - Exit) | C23: =IF(COUNT(C16:C17)=0,"N/A",MIN(C16:C17)&" - "&MAX(C16:C17)) -> 327 - 378
B25: Key Investment Thesis
B26: 1. The reported 26% net income decline is misleading -- ordinary profit was essentially flat at 30,165 (-0.4%). The drop came from an 8,456 impairment on the credit card business and new-ATM replacement costs, both below the ordinary line. The franchise did not deteriorate; the accounting did.
B27: 2. Cashless payment adoption is currently a TAILWIND, not a headwind. ATM transaction volume rose because consumers load cash onto cashless wallets at Seven Bank ATMs. ATM units reached 28,536 (+1.9%) with 109.2 daily transactions per unit. The bear case requires this to reverse, which it has not yet.
B28: 3. Fee-based infrastructure economics inside a banking licence. 91.3% of ordinary income is fee income (ATM fees alone 169,240, or 76.9%); interest income is only 7.2%. This is an ATM network operator, and should be valued on franchise durability and ROE, not on net interest margin.
B30: Key Risks
B31: 1. ROE sits almost exactly at the cost of equity. FY2026/3 ROE was 4.8% (6.1% on FY2027/3 guidance) against an estimated 6.2% cost of equity. When ROE equals Ke, intrinsic value collapses to book value, and the shares already trade at 1.065x book. There is little valuation cushion.
B32: 2. Capex exceeds depreciation during the ATM replacement cycle. Depreciation is roughly 30,586 while the fourth-generation ATM rollout keeps capex elevated. 28,536 units must be refreshed on a recurring cycle regardless of demand.
B33: 3. Payout ratio near 90% leaves almost no retained growth. Sustainable growth = ROE x (1 - payout) is well under 1%, so the dividend is the return. Any ROE shortfall hits both the dividend and the terminal value simultaneously.

Sheet Financial Statements
B2: 株式会社セブン銀行 - Historical Financials (JPY mn)
C4: FY2024/3 | D4: FY2025/3 | E4: FY2026/3
B5: Income Statement
B6: Revenue | C6: 197877 | D6: 214408 | E6: 220025
B7: COGS | C7: 54594 | D7: 57759 | E7: 58729
B8: Gross Profit | C8: =C6-C7 -> 143283 | D8: =D6-D7 -> 156649 | E8: =E6-E7 -> 161296
B9: Gross Margin | C9: =C8/C6 -> 0.72410134 | D9: =D8/D6 -> 0.73061173 | E9: =E8/E6 -> 0.73308033
B10: SGA | C10: 112757 | D10: 126357 | E10: 131129
B11: Operating Income | C11: 30526 | D11: 30289 | E11: 30165
B12: Net Income | C12: 31970 | D12: 18221 | E12: 13476
B13: Operating Margin | C13: =C11/C6 -> 0.15426755 | D13: =D11/D6 -> 0.14126805 | E13: =E11/E6 -> 0.13709806
B14: Net Margin | C14: =C12/C6 -> 0.16156501 | D14: =D12/D6 -> 0.084982836 | E14: =E12/E6 -> 0.061247586
B15: Revenue Growth (YoY) | C15: n/a | D15: =(D6-C6)/C6 -> 0.083541796 | E15: =(E6-D6)/D6 -> 0.026197717
B16: Operating Income Growth (YoY) | C16: n/a | D16: =(D11-C11)/C11 -> -0.0077638734 | E16: =(E11-D11)/D11 -> -0.0040938955
B18: Cash Flow Statement
B19: Operating Cash Flow | C19: 100751 | D19: -38869 | E19: 83930
B20: Capex | C20: 17739 | D20: 23206 | E20: 9947
B21: Free Cash Flow | C21: =C19-C20 -> 83012 | D21: =D19-D20 -> -62075 | E21: =E19-E20 -> 73983
B22: FCF Margin | C22: =C21/C6 -> 0.41951313 | D22: =D21/D6 -> -0.28951811 | E22: =E21/E6 -> 0.33624815
B23: Capex / Revenue | C23: =C20/C6 -> 0.089646599 | D23: =D20/D6 -> 0.1082329 | E23: =E20/E6 -> 0.045208499
B25: Balance Sheet Highlights
B26: Cash & Deposits | C26: 988721 | D26: 892626 | E26: 892764
B27: Total Interest-bearing Debt (short + long) | C27: 65000 | D27: 50000 | E27: 100000
B28: Net Debt (Cash) | C28: =C27-C26 -> -923721 | D28: =D27-D26 -> -842626 | E28: =E27-E26 -> -792764
B30: Note: OCF / Cash / Debt coverage OCF 3/3, Cash 3/3, Debt 3/3 — blank cells are years with no year-key match in the source data (verify against 決算短信 or set hist_ocf / hist_cash / hist_debt in overrides).

Sheet DCF Model
B1: ⚠ 型D（銀行）: このシートは参考表示である。銀行に UFCF ベースの DCF は成立しない（負債は資金調達ではなく原材料、運転資本が定義できない、自己資本規制が配当を制約する）。**主手法は DDM シートと Residual Income シート**であり、Target はその2手法の平均である。
B2: DCF Valuation Model - 株式会社セブン銀行
B4: Assumptions
B5: Capex / Revenue (fallback) | C5: 0.155
B6: Effective Tax Rate | C6: 0.25
B7: Risk-Free Rate | C7: 0.0297
B8: Beta | C8: 0.6264
B9: Equity Risk Premium | C9: 0.065
B10: Size Premium | C10: 0.01
B11: After-tax Cost of Debt | C11: 0.01
B12: D/E Ratio | C12: 0
B13: Terminal Growth Rate | C13: 0.01
B14: Exit Multiple (EV/EBITDA) | C14: 7
B15: Fully Diluted Shares | C15: 1167997856
B16: Net Debt (JPY mn) | C16: 0
... B20: LTM Revenue (JPY mn) | C20: 220025
B22: WACC Calculation
B23: Cost of Equity (Ke) | C23: =C7+C8*C9+C10 -> 0.080416
B24: Weight of Equity | C24: =1/(1+C12) -> 1
B25: Weight of Debt | C25: =C12/(1+C12) -> 0
B26: WACC | C26: =C23*C24+C11*C25 -> 0.080416
B27: Active Scenario | C27: Base | D27: =MATCH(C27,B69:B73,0) -> 1
B28: Projected Free Cash Flow
C29: FY2027(E) | D29: FY2028(E) | E29: FY2029(E) | F29: FY2030(E) | G29: FY2031(E)
B30: Revenue Growth (YoY) | C30: =CHOOSE($D$27,C69,C70,C71,C72,C73) -> 0.05 | D30: =CHOOSE($D$27,D69,D70,D71,D72,D73) -> 0.035 | E30: =CHOOSE($D$27,E69,E70,E71,E72,E73) -> 0.03 | F30: =CHOOSE($D$27,F69,F70,F71,F72,F73) -> 0.025 | G30: =CHOOSE($D$27,G69,G70,G71,G72,G73) -> 0.02
B31: COGS % of Revenue | C31: =CHOOSE($D$27,C76,C77,C78,C79,C80) -> 0.265 | D31: =CHOOSE($D$27,D76,D77,D78,D79,D80) -> 0.265 | E31: =CHOOSE($D$27,E76,E77,E78,E79,E80) -> 0.265 | F31: =CHOOSE($D$27,F76,F77,F78,F79,F80) -> 0.265 | G31: =CHOOSE($D$27,G76,G77,G78,G79,G80) -> 0.265
B32: SGA % of Revenue | C32: =CHOOSE($D$27,C83,C84,C85,C86,C87) -> 0.61 | D32: =CHOOSE($D$27,D83,D84,D85,D86,D87) -> 0.6 | E32: =CHOOSE($D$27,E83,E84,E85,E86,E87) -> 0.59 | F32: =CHOOSE($D$27,F83,F84,F85,F86,F87) -> 0.585 | G32: =CHOOSE($D$27,G83,G84,G85,G86,G87) -> 0.585
B33: Revenue | C33: =C17*(1+C30) -> 231026.25 | D33: =C33*(1+D30) -> 239112.17 | E33: =D33*(1+E30) -> 246285.53 | F33: =E33*(1+F30) -> 252442.67 | G33: =F33*(1+G30) -> 257491.53
B34: COGS | C34: =C33*C31 -> 61221.956 | D34: =D33*D31 -> 63364.725 | E34: =E33*E31 -> 65265.666 | F34: =F33*F31 -> 66897.308 | G34: =G33*G31 -> 68235.254
B35: Gross Profit | C35: =C33-C34 -> 169804.29 | D35: =D33-D34 -> 175747.44 | E35: =E33-E34 -> 181019.87 | F35: =F33-F34 -> 185545.36 | G35: =G33-G34 -> 189256.27
B36: Gross Margin | C36: =C35/C33 -> 0.735 | D36: =D35/D33 -> 0.735 | E36: =E35/E33 -> 0.735 | F36: =F35/F33 -> 0.735 | G36: =G35/G33 -> 0.735
B37: SGA Expense | C37: =C33*C32 -> 140926.01 | D37: =D33*D32 -> 143467.3 | E37: =E33*E32 -> 145308.46 | F37: =F33*F32 -> 147678.96 | G37: =G33*G32 -> 150632.54
B38: Implied Operating Margin | C38: =(C35-C37)/C33 -> 0.125 | D38: =(D35-D37)/D33 -> 0.135 | E38: =(E35-E37)/E33 -> 0.145 | F38: =(F35-F37)/F33 -> 0.15 | G38: =(G35-G37)/G33 -> 0.15
B39: Operating Income (EBIT) | C39: =C35-C37 -> 28878.281 | D39: =D35-D37 -> 32280.143 | E39: =E35-E37 -> 35711.402 | F39: =F35-F37 -> 37866.401 | G39: =G35-G37 -> 38623.729
B40: Less: Tax | C40: =MAX(0,C39*C6) -> 7219.5703 | D40: =MAX(0,D39*C6) -> 8070.0357 | E40: =MAX(0,E39*C6) -> 8927.8506 | F40: =MAX(0,F39*C6) -> 9466.6002 | G40: =MAX(0,G39*C6) -> 9655.9322
B41: NOPAT | C41: =C39-C40 -> 21658.711 | D41: =D39-D40 -> 24210.107 | E41: =E39-E40 -> 26783.552 | F41: =F39-F40 -> 28399.801 | G41: =G39-G40 -> 28967.797
B42: Plus: D&A | C42: 32000 | D42: 33000 | E42: 33500 | F42: 34000 | G42: 34500
B43: Less: Capex | C43: 38000 | D43: 36000 | E43: 34000 | F43: 34000 | G43: 34000
B44: Change in NWC | C44: ='NWC Schedule'!D19 -> 0 | D44: ='NWC Schedule'!E19 -> 0 | E44: ='NWC Schedule'!F19 -> 0 | F44: ='NWC Schedule'!G19 -> 0 | G44: ='NWC Schedule'!H19 -> 0
B45: Unlevered Free Cash Flow | C45: =C41+C42-C43-C44 -> 15658.711 | D45: =D41+D42-D43-D44 -> 21210.107 | E45: =E41+E42-E43-E44 -> 26283.552 | F45: =F41+F42-F43-F44 -> 28399.801 | G45: =G41+G42-G43-G44 -> 29467.797
B46: Discount Factor | C46: =1/(1+C26)^(C19+0) -> 0.92556941 | D46: =1/(1+C26)^(C19+1) -> 0.85667873 | E46: =1/(1+C26)^(C19+2) -> 0.79291563 | F46: =1/(1+C26)^(C19+3) -> 0.73389845 | G46: =1/(1+C26)^(C19+4) -> 0.67927396
B47: PV of FCF | C47: =C45*C46 -> 14493.224 | D47: =D45*D46 -> 18170.248 | E47: =E45*E46 -> 20840.639 | F47: =F45*F46 -> 20842.57 | G47: =G45*G46 -> 20016.707
B49: Valuation - Perpetuity Growth Method
B50: Sum of PV of FCFs | C50: =SUM(C47:G47) -> 94363.387
B51: Terminal Value (PGM) | C51: =G45*(1+C13)/(C26-C13) -> 422666.36
B52: PV of Terminal Value | C52: =C51*G46 -> 287106.25
B53: Enterprise Value | C53: =C50+C52 -> 381469.64
B54: Equity Value | C54: =C53-C16 -> 381469.64
B55: Implied Share Price (PGM) | C55: =ROUND(C54*1000000/C15,0) -> 327
B57: Valuation - Exit Multiple Method
B58: Sum of PV of FCFs | C58: =C50 -> 94363.387
B59: Year 5 EBITDA | C59: =G39+G42 -> 73123.729
B60: Terminal Value (Exit Multiple) | C60: =C59*C14 -> 511866.1
B61: PV of Terminal Value | C61: =C60*G46 -> 347697.31
B62: Enterprise Value | C62: =C58+C61 -> 442060.7
B63: Equity Value | C63: =C62-C16 -> 442060.7
B64: Implied Share Price (Exit Multiple) | C64: =ROUND(C63*1000000/C15,0) -> 378
B66: Scenario Input Matrix
C67: Year 1 | D67: Year 2 | E67: Year 3 | F67: Year 4 | G67: Year 5
B68: Revenue Growth (YoY)
B69: Base | C69: 0.05 | D69: 0.035 | E69: 0.03 | F69: 0.025 | G69: 0.02
B70: Upside | C70: 0.09 | D70: 0.07 | E70: 0.06 | F70: 0.05 | G70: 0.045
B71: Management | C71: 0.07 | D71: 0.04 | E71: 0.03 | F71: 0.025 | G71: 0.02
B72: Downside 1 | C72: 0.02 | D72: 0 | E72: -0.01 | F72: -0.01 | G72: -0.01
B73: Downside 2 | C73: -0.02 | D73: -0.04 | E73: -0.04 | F73: -0.03 | G73: -0.03
B75: COGS % of Revenue
B76: Base | C76: 0.265 | D76: 0.265 | E76: 0.265 | F76: 0.265 | G76: 0.265
B77: Upside | C77: 0.26 | D77: 0.26 | E77: 0.26 | F77: 0.26 | G77: 0.26
B78: Management | C78: 0.265 | D78: 0.265 | E78: 0.265 | F78: 0.265 | G78: 0.265
B79: Downside 1 | C79: 0.275 | D79: 0.275 | E79: 0.275 | F79: 0.275 | G79: 0.275
B80: Downside 2 | C80: 0.285 | D80: 0.285 | E80: 0.285 | F80: 0.285 | G80: 0.285
B82: SGA % of Revenue
B83: Base | C83: 0.61 | D83: 0.6 | E83: 0.59 | F83: 0.585 | G83: 0.585
B84: Upside | C84: 0.605 | D84: 0.59 | E84: 0.575 | F84: 0.57 | G84: 0.565
B85: Management | C85: 0.61 | D85: 0.605 | E85: 0.6 | F85: 0.595 | G85: 0.595
B86: Downside 1 | C86: 0.615 | D86: 0.625 | E86: 0.625 | F86: 0.62 | G86: 0.62
B87: Downside 2 | C87: 0.625 | D87: 0.65 | E87: 0.655 | F87: 0.65 | G87: 0.65

Sheet Reverse DCF
B2: Reverse DCF - 株式会社セブン銀行 (8410.T)
B3: What is the current share price already assuming? Every value below is a live formula off the other sheets.
B5: Block 0: Market-implied enterprise value (live)
B6: Current Share Price (JPY) | C6: ='Executive Summary'!C9 -> 340
B7: Fully Diluted Shares | C7: ='DCF Model'!C15 -> 1167997856
B8: Market Capitalisation (JPY mn) | C8: =C6*C7/1000000 -> 397119.27
B9: Net Debt (JPY mn) | C9: ='DCF Model'!C16 -> 0
B10: Enterprise Value (JPY mn) | C10: =C8+C9 -> 397119.27
B11: WACC (w) | C11: ='DCF Model'!C26 -> 0.080416
B12: Terminal Growth (g) | C12: ='DCF Model'!C13 -> 0.01
B13: Effective Tax Rate (t) | C13: ='DCF Model'!C6 -> 0.25
B14: Starting Operating Profit OP0 (FY2026/3 actual) | C14: 30165
B15: Cycle-peak Operating Profit (FY2024/3 actual) | C15: 30526
B16: Terminal-year Revenue, active scenario (JPY mn) | C16: ='DCF Model'!G33 -> 257491.53
B17: Base-case DCF Enterprise Value, PGM (JPY mn) | C17: ='DCF Model'!C53 -> 381469.64
B18: Cycle-peak Operating Margin (FY2024/3 actual) | C18: 0.15426755
B19: Gap: market EV less base-case DCF EV (JPY mn) | C19: =C10-C17 -> 15649.631
B20: Gap per share (JPY) - the part of the price the base case does not explain | C20: =IFERROR(ROUND(C19*1000000/C7,0),"N/A") -> 13
B22: Block A: Required steady-state operating profit, reached IMMEDIATELY (no ramp)
B23: The lowest bar the price can clear: today's EV read as a perpetuity of one steady-state profit, capex = D&A, no NWC build.
B24: Required steady-state NOPAT (JPY mn) | C24: =C10*(C11-C12) -> 27963.551
B25: Required steady-state Operating Profit (JPY mn) | C25: =IFERROR(C24/(1-C13),"N/A") -> 37284.734
B26: ... as a multiple of the FY2024/3 peak | C26: =IFERROR(C25/C15,"N/A") -> 1.2214091
B27: ... as a multiple of FY2026/3 actual | C27: =IFERROR(C25/C14,"N/A") -> 1.2360263
B28: ... implied OPM on terminal-year revenue | C28: =IFERROR(C25/C16,"N/A") -> 0.14479985
B29: ... revenue needed if margins only reach the cycle peak | C29: =IFERROR(C25/C18,"N/A") -> 241688.77
B32: Block B: Required steady-state operating profit by YEARS-TO-REACH (linear ramp) x WACC
B33: Operating profit ramps linearly from OP0 (C14) to OP* over N years, then grows at g for ever. Column F is the model WACC.
B34: OP* = ( EV/(1-t) - OP0*(A-B) ) / ( B + TVF ). A longer ramp needs a HIGHER steady state, because more years are spent below it.
B36: Years to steady state (N) \ WACC | C36: N | D36: ='DCF Model'!C26-0.02 -> 0.060416 | E36: ='DCF Model'!C26-0.01 -> 0.070416 | F36: ='DCF Model'!C26 -> 0.080416 | G36: ='DCF Model'!C26+0.01 -> 0.090416 | H36: ='DCF Model'!C26+0.02 -> 0.100416
B37: B-1 PV weight on the RAMP from OP0 (A - B)
B38: N = 3 years | C38: 3 | D38: =IFERROR((1-(1+D$36)^(-$C38))/D$36-(1+D$36)/(D$36^2*$C38)*(1-($C38+1)/(1+D$36)^$C38+$C38/(1+D$36)^($C38+1)),"N/A") -> 0.92511685 | E38: =IFERROR((1-(1+E$36)^(-$C38))/E$36-(1+E$36)/(E$36^2*$C38)*(1-($C38+1)/(1+E$36)^$C38+$C38/(1+E$36)^($C38+1)),"N/A") -> 0.91373081 | F38: =IFERROR((1-(1+F$36)^(-$C38))/F$36-(1+F$36)/(F$36^2*$C38)*(1-($C38+1)/(1+F$36)^$C38+$C38/(1+F$36)^($C38+1)),"N/A") -> 0.90260585 | G38: =IFERROR((1-(1+G$36)^(-$C38))/G$36-(1+G$36)/(G$36^2*$C38)*(1-($C38+1)/(1+G$36)^$C38+$C38/(1+G$36)^($C38+1)),"N/A") -> 0.89173343 | H38: =IFERROR((1-(1+H$36)^(-$C38))/H$36-(1+H$36)/(H$36^2*$C38)*(1-($C38+1)/(1+H$36)^$C38+$C38/(1+H$36)^($C38+1)),"N/A") -> 0.88110534
B39: N = 5 years | C39: 5 | D39: =IFERROR((1-(1+D$36)^(-$C39))/D$36-(1+D$36)/(D$36^2*$C39)*(1-($C39+1)/(1+D$36)^$C39+$C39/(1+D$36)^($C39+1)),"N/A") -> 1.7816228 | E39: =IFERROR((1-(1+E$36)^(-$C39))/E$36-(1+E$36)/(E$36^2*$C39)*(1-($C39+1)/(1+E$36)^$C39+$C39/(1+E$36)^($C39+1)),"N/A") -> 1.7495096 | F39: =IFERROR((1-(1+F$36)^(-$C39))/F$36-(1+F$36)/(F$36^2*$C39)*(1-($C39+1)/(1+F$36)^$C39+$C39/(1+F$36)^($C39+1)),"N/A") -> 1.7184087 | G39: =IFERROR((1-(1+G$36)^(-$C39))/G$36-(1+G$36)/(G$36^2*$C39)*(1-($C39+1)/(1+G$36)^$C39+$C39/(1+G$36)^($C39+1)),"N/A") -> 1.6882767 | H39: =IFERROR((1-(1+H$36)^(-$C39))/H$36-(1+H$36)/(H$36^2*$C39)*(1-($C39+1)/(1+H$36)^$C39+$C39/(1+H$36)^($C39+1)),"N/A") -> 1.6590722
B40: N = 7 years | C40: 7 | D40: =IFERROR((1-(1+D$36)^(-$C40))/D$36-(1+D$36)/(D$36^2*$C40)*(1-($C40+1)/(1+D$36)^$C40+$C40/(1+D$36)^($C40+1)),"N/A") -> 2.5752312 | E40: =IFERROR((1-(1+E$36)^(-$C40))/E$36-(1+E$36)/(E$36^2*$C40)*(1-($C40+1)/(1+E$36)^$C40+$C40/(1+E$36)^($C40+1)),"N/A") -> 2.514801 | F40: =IFERROR((1-(1+F$36)^(-$C40))/F$36-(1+F$36)/(F$36^2*$C40)*(1-($C40+1)/(1+F$36)^$C40+$C40/(1+F$36)^($C40+1)),"N/A") -> 2.4567759 | G40: =IFERROR((1-(1+G$36)^(-$C40))/G$36-(1+G$36)/(G$36^2*$C40)*(1-($C40+1)/(1+G$36)^$C40+$C40/(1+G$36)^($C40+1)),"N/A") -> 2.4010286 | H40: =IFERROR((1-(1+H$36)^(-$C40))/H$36-(1+H$36)/(H$36^2*$C40)*(1-($C40+1)/(1+H$36)^$C40+$C40/(1+H$36)^($C40+1)),"N/A") -> 2.3474398
B41: N = 10 years | C41: 10 | D41: =IFERROR((1-(1+D$36)^(-$C41))/D$36-(1+D$36)/(D$36^2*$C41)*(1-($C41+1)/(1+D$36)^$C41+$C41/(1+D$36)^($C41+1)),"N/A") -> 3.6589733 | E41: =IFERROR((1-(1+E$36)^(-$C41))/E$36-(1+E$36)/(E$36^2*$C41)*(1-($C41+1)/(1+E$36)^$C41+$C41/(1+E$36)^($C41+1)),"N/A") -> 3.5450491 | F41: =IFERROR((1-(1+F$36)^(-$C41))/F$36-(1+F$36)/(F$36^2*$C41)*(1-($C41+1)/(1+F$36)^$C41+$C41/(1+F$36)^($C41+1)),"N/A") -> 3.4370076 | G41: =IFERROR((1-(1+G$36)^(-$C41))/G$36-(1+G$36)/(G$36^2*$C41)*(1-($C41+1)/(1+G$36)^$C41+$C41/(1+G$36)^($C41+1)),"N/A") -> 3.3344528 | H41: =IFERROR((1-(1+H$36)^(-$C41))/H$36-(1+H$36)/(H$36^2*$C41)*(1-($C41+1)/(1+H$36)^$C41+$C41/(1+H$36)^($C41+1)),"N/A") -> 3.2370207
B42: B-2 PV weight on the STEADY STATE OP* (B + terminal factor)
B43: N = 3 years | C43: 3 | D43: =IFERROR((1+D$36)/(D$36^2*$C43)*(1-($C43+1)/(1+D$36)^$C43+$C43/(1+D$36)^($C43+1))+(1+$C$12)/((D$36-$C$12)*(1+D$36)^$C43),"N/A") -> 18.546415 | E43: =IFERROR((1+E$36)/(E$36^2*$C43)*(1-($C43+1)/(1+E$36)^$C43+$C43/(1+E$36)^($C43+1))+(1+$C$12)/((E$36-$C$12)*(1+E$36)^$C43),"N/A") -> 15.339087 | F43: =IFERROR((1+F$36)/(F$36^2*$C43)*(1-($C43+1)/(1+F$36)^$C43+$C43/(1+F$36)^($C43+1))+(1+$C$12)/((F$36-$C$12)*(1+F$36)^$C43),"N/A") -> 13.045609 | G43: =IFERROR((1+G$36)/(G$36^2*$C43)*(1-($C43+1)/(1+G$36)^$C43+$C43/(1+G$36)^($C43+1))+(1+$C$12)/((G$36-$C$12)*(1+G$36)^$C43),"N/A") -> 11.324975 | H43: =IFERROR((1+H$36)/(H$36^2*$C43)*(1-($C43+1)/(1+H$36)^$C43+$C43/(1+H$36)^($C43+1))+(1+$C$12)/((H$36-$C$12)*(1+H$36)^$C43),"N/A") -> 9.9870409
B44: N = 5 years | C44: 5 | D44: =IFERROR((1+D$36)/(D$36^2*$C44)*(1-($C44+1)/(1+D$36)^$C44+$C44/(1+D$36)^($C44+1))+(1+$C$12)/((D$36-$C$12)*(1+D$36)^$C44),"N/A") -> 17.366702 | E44: =IFERROR((1+E$36)/(E$36^2*$C44)*(1-($C44+1)/(1+E$36)^$C44+$C44/(1+E$36)^($C44+1))+(1+$C$12)/((E$36-$C$12)*(1+E$36)^$C44),"N/A") -> 14.242275 | F44: =IFERROR((1+F$36)/(F$36^2*$C44)*(1-($C44+1)/(1+F$36)^$C44+$C44/(1+F$36)^($C44+1))+(1+$C$12)/((F$36-$C$12)*(1+F$36)^$C44),"N/A") -> 12.012979 | G44: =IFERROR((1+G$36)/(G$36^2*$C44)*(1-($C44+1)/(1+G$36)^$C44+$C44/(1+G$36)^($C44+1))+(1+$C$12)/((G$36-$C$12)*(1+G$36)^$C44),"N/A") -> 10.344557 | H44: =IFERROR((1+H$36)/(H$36^2*$C44)*(1-($C44+1)/(1+H$36)^$C44+$C44/(1+H$36)^($C44+1))+(1+$C$12)/((H$36-$C$12)*(1+H$36)^$C44),"N/A") -> 9.0506459
B45: N = 7 years | C45: 7 | D45: =IFERROR((1+D$36)/(D$36^2*$C45)*(1-($C45+1)/(1+D$36)^$C45+$C45/(1+D$36)^($C45+1))+(1+$C$12)/((D$36-$C$12)*(1+D$36)^$C45),"N/A") -> 16.285665 | E45: =IFERROR((1+E$36)/(E$36^2*$C45)*(1-($C45+1)/(1+E$36)^$C45+$C45/(1+E$36)^($C45+1))+(1+$C$12)/((E$36-$C$12)*(1+E$36)^$C45),"N/A") -> 13.249165 | F45: =IFERROR((1+F$36)/(F$36^2*$C45)*(1-($C45+1)/(1+F$36)^$C45+$C45/(1+F$36)^($C45+1))+(1+$C$12)/((F$36-$C$12)*(1+F$36)^$C45),"N/A") -> 11.08886 | G45: =IFERROR((1+G$36)/(G$36^2*$C45)*(1-($C45+1)/(1+G$36)^$C45+$C45/(1+G$36)^($C45+1))+(1+$C$12)/((G$36-$C$12)*(1+G$36)^$C45),"N/A") -> 9.4771598 | H45: =IFERROR((1+H$36)/(H$36^2*$C45)*(1-($C45+1)/(1+H$36)^$C45+$C45/(1+H$36)^($C45+1))+(1+$C$12)/((H$36-$C$12)*(1+H$36)^$C45),"N/A") -> 8.2314448
B46: N = 10 years | C46: 10 | D46: =IFERROR((1+D$36)/(D$36^2*$C46)*(1-($C46+1)/(1+D$36)^$C46+$C46/(1+D$36)^($C46+1))+(1+$C$12)/((D$36-$C$12)*(1+D$36)^$C46),"N/A") -> 14.829325 | E46: =IFERROR((1+E$36)/(E$36^2*$C46)*(1-($C46+1)/(1+E$36)^$C46+$C46/(1+E$36)^($C46+1))+(1+$C$12)/((E$36-$C$12)*(1+E$36)^$C46),"N/A") -> 11.930368 | F46: =IFERROR((1+F$36)/(F$36^2*$C46)*(1-($C46+1)/(1+F$36)^$C46+$C46/(1+F$36)^($C46+1))+(1+$C$12)/((F$36-$C$12)*(1+F$36)^$C46),"N/A") -> 9.8787025 | G46: =IFERROR((1+G$36)/(G$36^2*$C46)*(1-($C46+1)/(1+G$36)^$C46+$C46/(1+G$36)^($C46+1))+(1+$C$12)/((G$36-$C$12)*(1+G$36)^$C46),"N/A") -> 8.3566135 | H46: =IFERROR((1+H$36)/(H$36^2*$C46)*(1-($C46+1)/(1+H$36)^$C46+$C46/(1+H$36)^($C46+1))+(1+$C$12)/((H$36-$C$12)*(1+H$36)^$C46),"N/A") -> 7.1870731
B47: B-3 REQUIRED steady-state Operating Profit (JPY mn)
B48: N = 3 years | C48: 3 | D48: =IFERROR(($C$10/(1-$C$13)-$C$14*D38)/D43,"N/A") -> 27044.915 | E48: =IFERROR(($C$10/(1-$C$13)-$C$14*E38)/E43,"N/A") -> 32722.265 | F48: =IFERROR(($C$10/(1-$C$13)-$C$14*F38)/F43,"N/A") -> 38500.713 | G48: =IFERROR(($C$10/(1-$C$13)-$C$14*G38)/G43,"N/A") -> 44379.191 | H48: =IFERROR(($C$10/(1-$C$13)-$C$14*H38)/H43,"N/A") -> 50356.639
B49: N = 5 years | C49: 5 | D49: =IFERROR(($C$10/(1-$C$13)-$C$14*D39)/D44,"N/A") -> 27394.362 | E49: =IFERROR(($C$10/(1-$C$13)-$C$14*E39)/E44,"N/A") -> 33472.068 | F49: =IFERROR(($C$10/(1-$C$13)-$C$14*F39)/F44,"N/A") -> 39761.709 | G49: =IFERROR(($C$10/(1-$C$13)-$C$14*G39)/G44,"N/A") -> 46262.541 | H49: =IFERROR(($C$10/(1-$C$13)-$C$14*H39)/H44,"N/A") -> 52973.727
B50: N = 7 years | C50: 7 | D50: =IFERROR(($C$10/(1-$C$13)-$C$14*D40)/D45,"N/A") -> 27742.834 | E50: =IFERROR(($C$10/(1-$C$13)-$C$14*E40)/E45,"N/A") -> 34238.64 | F50: =IFERROR(($C$10/(1-$C$13)-$C$14*F40)/F45,"N/A") -> 41066.775 | G50: =IFERROR(($C$10/(1-$C$13)-$C$14*G40)/G45,"N/A") -> 48228.092 | H50: =IFERROR(($C$10/(1-$C$13)-$C$14*H40)/H45,"N/A") -> 55723.126
B51: N = 10 years | C51: 10 | D51: =IFERROR(($C$10/(1-$C$13)-$C$14*D41)/D46,"N/A") -> 28262.88 | E51: =IFERROR(($C$10/(1-$C$13)-$C$14*E41)/E46,"N/A") -> 35418.517 | F51: =IFERROR(($C$10/(1-$C$13)-$C$14*F41)/F46,"N/A") -> 43104.348 | G51: =IFERROR(($C$10/(1-$C$13)-$C$14*G41)/G46,"N/A") -> 51325.647 | H51: =IFERROR(($C$10/(1-$C$13)-$C$14*H41)/H46,"N/A") -> 60086.717
B52: B-4 ... as a multiple of the FY2024/3 peak operating profit
B53: N = 3 years | C53: 3 | D53: =IFERROR(D48/$C$15,"N/A") -> 0.88596326 | E53: =IFERROR(E48/$C$15,"N/A") -> 1.0719474 | F53: =IFERROR(F48/$C$15,"N/A") -> 1.2612433 | G53: =IFERROR(G48/$C$15,"N/A") -> 1.4538161 | H53: =IFERROR(H48/$C$15,"N/A") -> 1.6496311
B54: N = 5 years | C54: 5 | D54: =IFERROR(D49/$C$15,"N/A") -> 0.89741079 | E54: =IFERROR(E49/$C$15,"N/A") -> 1.0965101 | F54: =IFERROR(F49/$C$15,"N/A") -> 1.3025522 | G54: =IFERROR(G49/$C$15,"N/A") -> 1.5155127 | H54: =IFERROR(H49/$C$15,"N/A") -> 1.7353642
B55: N = 7 years | C55: 7 | D55: =IFERROR(D50/$C$15,"N/A") -> 0.90882638 | E55: =IFERROR(E50/$C$15,"N/A") -> 1.1216222 | F55: =IFERROR(F50/$C$15,"N/A") -> 1.3453048 | G55: =IFERROR(G50/$C$15,"N/A") -> 1.5799021 | H55: =IFERROR(H50/$C$15,"N/A") -> 1.8254316
B56: N = 10 years | C56: 10 | D56: =IFERROR(D51/$C$15,"N/A") -> 0.92586253 | E56: =IFERROR(E51/$C$15,"N/A") -> 1.1602738 | F56: =IFERROR(F51/$C$15,"N/A") -> 1.4120536 | G56: =IFERROR(G51/$C$15,"N/A") -> 1.6813748 | H56: =IFERROR(H51/$C$15,"N/A") -> 1.9683783
B58: Block C: Decomposing the required profit into revenue x margin (N = 5 years, model WACC)
B59: The revenue the company must run at, for a given steady-state operating margin, to earn the Block B-3 profit.
B60: Required steady-state Operating Profit (N=5, model WACC) | C60: =F49 -> 39761.709
B62: Assumed steady-state OPM | C62: Required Revenue | D62: x base-year revenue
B63: 0.0771 | C63: =IFERROR($C$60/B63,"N/A") -> 515716.07 | D63: =IFERROR(C63/'DCF Model'!C17,"N/A") -> 2.3438976
B64: 0.1157 | C64: =IFERROR($C$60/B64,"N/A") -> 343662.13 | D64: =IFERROR(C64/'DCF Model'!C17,"N/A") -> 1.5619231
B65: cycle-peak OPM (FY2024/3) | C65: =IFERROR($C$60/$C$18,"N/A") -> 257745.12 | D65: =IFERROR(C65/'DCF Model'!C17,"N/A") -> 1.1714356
B66: 0.1928 | C66: =IFERROR($C$60/B66,"N/A") -> 206232.93 | D66: =IFERROR(C66/'DCF Model'!C17,"N/A") -> 0.93731589
B67: 0.2314 | C67: =IFERROR($C$60/B67,"N/A") -> 171831.07 | D67: =IFERROR(C67/'DCF Model'!C17,"N/A") -> 0.78096156
B69: Block D: The same question expressed as multiples
B70: Current EV / latest-FY EBITDA (actual) | C70: =IFERROR(C10/'Comps Analysis'!G5,"N/A") -> 6.5368351
B71: Current EV / latest-FY Revenue (actual) | C71: =IFERROR(C10/'Comps Analysis'!F5,"N/A") -> 1.8048825
B72: EV / EBITDA if the Block A profit were already earned | C72: =IFERROR(C10/(C25+'DCF Model'!G42),"N/A") -> 5.5320853
B73: EV / EBITDA if the Block B-3 (N=5) profit were already earned | C73: =IFERROR(C10/(C60+'DCF Model'!G42),"N/A") -> 5.3475644
B74: Peer median EV / EBITDA (statistics rows) | C74: =IFERROR('Comps Analysis'!D16,"N/A") -> N/A
B75: Rows 3-4 answer: what multiple would today's EV be paying IF the company already earned the profit the price requires?
B77: Block F: The one-line answer
B78: ="At "&TEXT(C6,"#,##0")&" yen the market is paying for a steady-state operating profit of "&TEXT(F49,"#,##0")&" mn JPY - "&TEXT(F54,"0.00")&"x the FY2024/3 cycle peak of "&TEXT(C15,"#,##0")&" mn - reached in 5 years and sustained for ever, against "&TEXT(C14,"#,##0")&" mn actually earned in FY2026/3." -> At 340 yen the market is paying for a steady-state operating profit of 39,762 mn JPY - 1.30x the FY2024/3 cycle peak of 30,526 mn - reached in 5 years and sustained for ever, against 30,165 mn actually earned in FY2026/3.
B79: ="Even with no ramp at all (Block A) the price needs "&TEXT(C25,"#,##0")&" mn, or "&TEXT(C26,"0.00")&"x the peak. The base case supports an EV of only "&TEXT(C17,"#,##0")&" mn, leaving "&TEXT(C20,"#,##0")&" yen per share of the current price unexplained by mid-cycle economics." -> Even with no ramp at all (Block A) the price needs 37,285 mn, or 1.22x the peak. The base case supports an EV of only 381,470 mn, leaving 13 yen per share of the current price unexplained by mid-cycle economics.

Sheet NWC Schedule
B2: NWC Schedule - 株式会社セブン銀行
B4: Working Capital Drivers (% of Revenue) | C4: Base Year | D4: FY2027(E) | E4: FY2028(E) | F4: FY2029(E) | G4: FY2030(E) | H4: FY2031(E)
B5: NWC % of Revenue | C5: =C18/C9 -> 0 | D5: =CHOOSE('DCF Model'!$D$27,D25,D26,D27,D28,D29) -> 0 | E5: =CHOOSE('DCF Model'!$D$27,E25,E26,E27,E28,E29) -> 0 | F5: =CHOOSE('DCF Model'!$D$27,F25,F26,F27,F28,F29) -> 0 | G5: =CHOOSE('DCF Model'!$D$27,G25,G26,G27,G28,G29) -> 0 | H5: =CHOOSE('DCF Model'!$D$27,H25,H26,H27,H28,H29) -> 0
B6: — | C6: — | D6: — | E6: — | F6: — | G6: — | H6: —
B7: — | C7: — | D7: — | E7: — | F7: — | G7: — | H7: —
B8: P&L Reference (JPY mn)
B9: Revenue | C9: 220025 | D9: ='DCF Model'!C33 -> 231026.25 | E9: ='DCF Model'!D33 -> 239112.17 | F9: ='DCF Model'!E33 -> 246285.53 | G9: ='DCF Model'!F33 -> 252442.67 | H9: ='DCF Model'!G33 -> 257491.53
B10: — | C10: — | D10: — | E10: — | F10: — | G10: — | H10: —
B11: Working Capital Items (JPY mn)
B12: — | C12: — | D12: — | E12: — | F12: — | G12: — | H12: —
B13: — | C13: — | D13: — | E13: — | F13: — | G13: — | H13: —
B14: — | C14: — | D14: — | E14: — | F14: — | G14: — | H14: —
B15: — | C15: — | D15: — | E15: — | F15: — | G15: — | H15: —
B16: — | C16: — | D16: — | E16: — | F16: — | G16: — | H16: —
B17: Net Working Capital (JPY mn)
B18: Net Working Capital | C18: 0 | D18: =D9*D5 -> 0 | E18: =E9*E5 -> 0 | F18: =F9*F5 -> 0 | G18: =G9*G5 -> 0 | H18: =H9*H5 -> 0
B19: Change in NWC | C19: n/a | D19: =D18-C18 -> 0 | E19: =E18-D18 -> 0 | F19: =F18-E18 -> 0 | G19: =G18-F18 -> 0 | H19: =H18-G18 -> 0
B22: Scenario Input Matrix (NWC % of Revenue)
D23: FY2027(E) | E23: FY2028(E) | F23: FY2029(E) | G23: FY2030(E) | H23: FY2031(E)
B24: NWC % of Revenue
B25: Base | D25: 0 | E25: 0 | F25: 0 | G25: 0 | H25: 0
B26: Upside | D26: 0 | E26: 0 | F26: 0 | G26: 0 | H26: 0
B27: Management | D27: 0 | E27: 0 | F27: 0 | G27: 0 | H27: 0
B28: Downside 1 | D28: 0 | E28: 0 | F28: 0 | G28: 0 | H28: 0
B29: Downside 2 | D29: 0 | E29: 0 | F29: 0 | G29: 0 | H29: 0

Sheet Comps Analysis
B2: Comparable Company Analysis
B3: Peer prices as of 2026-09-06 (Mkt Cap / EV of peer rows are static CSV values; the subject row is live-linked to Executive Summary)
B4: Company | C4: Ticker | D4: Mkt Cap (JPY mn) | E4: EV (JPY mn) | F4: Revenue (JPY mn) | G4: EBITDA (JPY mn) | H4: Op Income (JPY mn) | I4: Net Income (JPY mn) | J4: EV/EBITDA | K4: EV/Revenue | L4: ← 型D(銀行): EV 倍率は使用しない（comps は全社 Net_Debt=0 の契約であり EV は時価総額に等しくなる）。PER / PBR のみを参照すること | M4: PBR | N4: Op Margin | O4: ROE | P4: Book Value (JPY mn) | Q4: Note
B5: Seven Bank | C5: 8410.T | D5: ='Executive Summary'!C9*C23/1000000 -> 397119.27 | E5: =D5+C24 -> 397119.27 | F5: 220025 | G5: 60751 | H5: 30165 | I5: 13476 | J5: N/A | K5: N/A | L5: =IFERROR(D5/I5,"") -> 29.468631 | M5: =IFERROR(D5/P5,"") -> 1.4158004 | N5: =IFERROR(H5/F5,"") -> 0.13709806 | O5: =IFERROR(I5/P5,"") -> 0.048044322 | P5: 280491
B6: Rakuten Bank | C6: 5838.T | D6: 950497 | E6: 950497 | F6: 255579 | H6: 103091 | I6: 73072 | L6: =IFERROR(D6/I6,"") -> 13.007677 | M6: =IFERROR(D6/P6,"") -> 2.4483652 | N6: =IFERROR(H6/F6,"") -> 0.40336256 | O6: =IFERROR(I6/P6,"") -> 0.18822463 | P6: 388217 | Q6: (D&A n/a)
B7: Japan Post Bank | C7: 7182.T | D7: 11500000 | E7: 11500000 | F7: 2852200 | H7: 759100 | I7: 525500 | L7: =IFERROR(D7/I7,"") -> 21.88392 | M7: =IFERROR(D7/P7,"") -> 1.2419006 | N7: =IFERROR(H7/F7,"") -> 0.26614543 | O7: =IFERROR(I7/P7,"") -> 0.05674946 | P7: 9260000 | Q7: (D&A n/a)
B8: AEON Financial Service | C8: 8570.T | D8: 340000 | E8: 340000 | F8: 569370 | H8: 60693 | I8: 21092 | L8: =IFERROR(D8/I8,"") -> 16.119856 | M8: =IFERROR(D8/P8,"") -> 0.7328913 | N8: =IFERROR(H8/F8,"") -> 0.10659676 | O8: =IFERROR(I8/P8,"") -> 0.045465127 | P8: 463916 | Q8: (D&A n/a)
B14: Statistics
B15: 25th Percentile | D15: N/A | E15: N/A | F15: =PERCENTILE(L6:L8,0.25) -> 14.563767 | G15: =PERCENTILE(M6:M8,0.25) -> 0.98739597 | H15: =PERCENTILE(N6:N8,0.25) -> 0.1863711 | I15: =PERCENTILE(O6:O8,0.25) -> 0.051107294
B16: Median (50th) | D16: N/A | E16: N/A | F16: =MEDIAN(L6:L8) -> 16.119856 | G16: =MEDIAN(M6:M8) -> 1.2419006 | H16: =MEDIAN(N6:N8) -> 0.26614543 | I16: =MEDIAN(O6:O8) -> 0.05674946
B17: 75th Percentile | D17: N/A | E17: N/A | F17: =PERCENTILE(L6:L8,0.75) -> 19.001888 | G17: =PERCENTILE(M6:M8,0.75) -> 1.8451329 | H17: =PERCENTILE(N6:N8,0.75) -> 0.334754 | I17: =PERCENTILE(O6:O8,0.75) -> 0.12248704
B19: Implied Valuation for 株式会社セブン銀行
B20: 株式会社セブン銀行 Financials
B21: EBITDA (JPY mn) | C21: 60751
B22: Net Income (JPY mn) | C22: 13476
B23: Shares Outstanding | C23: 1167997856
B24: Net Debt (JPY mn) | C24: 0
B26: Implied Share Price (Median Multiples)
B27: Via EV/EBITDA (Median) | C27: INVALID (n<3) | D27: Only 0 peer(s) with D&A-inclusive EBITDA — EV/EBITDA excluded from Target Price
B28: Via PER (Median) | C28: =ROUND(C22*F16*1000000/C23,0) -> 186

Sheet Sensitivity Analysis
B2: Sensitivity Analysis
B3: Current WACC: | C3: ='DCF Model'!C26 -> 0.080416 | E3: Terminal g: | F3: ='DCF Model'!C13 -> 0.01 | H3: Exit Multiple: | I3: ='DCF Model'!C14 -> 7
B5: Table 1: WACC vs Terminal Growth Rate (PGM - Implied Share Price, JPY)
B6: WACC \ Terminal g | C6: =$F$3-0.0075 -> 0.0025 | D6: =$F$3-0.005 -> 0.005 | E6: =$F$3-0.0025 -> 0.0075 | F6: =$F$3 -> 0.01 | G6: =$F$3+0.0025 -> 0.0125 | H6: =$F$3+0.005 -> 0.015 | I6: =$F$3+0.0075 -> 0.0175
B7: =$C$3-0.015 -> 0.065416 | C7: =IFERROR(ROUND(('DCF Model'!C45/(1+$B7)^('DCF Model'!C19+0)+'DCF Model'!D45/(1+$B7)^('DCF Model'!C19+1)+'DCF Model'!E45/(1+$B7)^('DCF Model'!C19+2)+'DCF Model'!F45/(1+$B7)^('DCF Model'!C19+3)+'DCF Model'!G45/(1+$B7)^('DCF Model'!C19+4)+'DCF Model'!G45*(1+C$6)/($B7-C$6)/(1+$B7)^('DCF Model'!C19+4)-'DCF Model'!C16)*1000000/'DCF Model'!C15,0),"") -> 377 | D7: =IFERROR(ROUND(('DCF Model'!C45/(1+$B7)^('DCF Model'!C19+0)+'DCF Model'!D45/(1+$B7)^('DCF Model'!C19+1)+'DCF Model'!E45/(1+$B7)^('DCF Model'!C19+2)+'DCF Model'!F45/(1+$B7)^('DCF Model'!C19+3)+'DCF Model'!G45/(1+$B7)^('DCF Model'!C19+4)+'DCF Model'!G45*(1+D$6)/($B7-D$6)/(1+$B7)^('DCF Model'!C19+4)-'DCF Model'!C16)*1000000/'DCF Model'!C15,0),"") -> 390 | E7: =IFERROR(ROUND(('DCF Model'!C45/(1+$B7)^('DCF Model'!C19+0)+'DCF Model'!D45/(1+$B7)^('DCF Model'!C19+1)+'DCF Model'!E45/(1+$B7)^('DCF Model'!C19+2)+'DCF Model'!F45/(1+$B7)^('DCF Model'!C19+3)+'DCF Model'!G45/(1+$B7)^('DCF Model'!C19+4)+'DCF Model'!G45*(1+E$6)/($B7-E$6)/(1+$B7)^('DCF Model'!C19+4)-'DCF Model'!C16)*1000000/'DCF Model'!C15,0),"") -> 404 | F7: =IFERROR(ROUND(('DCF Model'!C45/(1+$B7)^('DCF Model'!C19+0)+'DCF Model'!D45/(1+$B7)^('DCF Model'!C19+1)+'DCF Model'!E45/(1+$B7)^('DCF Model'!C19+2)+'DCF Model'!F45/(1+$B7)^('DCF Model'!C19+3)+'DCF Model'!G45/(1+$B7)^('DCF Model'!C19+4)+'DCF Model'!G45*(1+F$6)/($B7-F$6)/(1+$B7)^('DCF Model'!C19+4)-'DCF Model'!C16)*1000000/'DCF Model'!C15,0),"") -> 419 | G7: =IFERROR(ROUND(('DCF Model'!C45/(1+$B7)^('DCF Model'!C19+0)+'DCF Model'!D45/(1+$B7)^('DCF Model'!C19+1)+'DCF Model'!E45/(1+$B7)^('DCF Model'!C19+2)+'DCF Model'!F45/(1+$B7)^('DCF Model'!C19+3)+'DCF Model'!G45/(1+$B7)^('DCF Model'!C19+4)+'DCF Model'!G45*(1+G$6)/($B7-G$6)/(1+$B7)^('DCF Model'!C19+4)-'DCF Model'!C16)*1000000/'DCF Model'!C15,0),"") -> 436 | H7: =IFERROR(ROUND(('DCF Model'!C45/(1+$B7)^('DCF Model'!C19+0)+'DCF Model'!D45/(1+$B7)^('DCF Model'!C19+1)+'DCF Model'!E45/(1+$B7)^('DCF Model'!C19+2)+'DCF Model'!F45/(1+$B7)^('DCF Model'!C19+3)+'DCF Model'!G45/(1+$B7)^('DCF Model'!C19+4)+'DCF Model'!G45*(1+H$6)/($B7-H$6)/(1+$B7)^('DCF Model'!C19+4)-'DCF Model'!C16)*1000000/'DCF Model'!C15,0),"") -> 454 | I7: =IFERROR(ROUND(('DCF Model'!C45/(1+$B7)^('DCF Model'!C19+0)+'DCF Model'!D45/(1+$B7)^('DCF Model'!C19+1)+'DCF Model'!E45/(1+$B7)^('DCF Model'!C19+2)+'DCF Model'!F45/(1+$B7)^('DCF Model'!C19+3)+'DCF Model'!G45/(1+$B7)^('DCF Model'!C19+4)+'DCF Model'!G45*(1+I$6)/($B7-I$6)/(1+$B7)^('DCF Model'!C19+4)-'DCF Model'!C16)*1000000/'DCF Model'!C15,0),"") -> 475
B8: =$C$3-0.01 -> 0.070416 | C8: =IFERROR(ROUND(('DCF Model'!C45/(1+$B8)^('DCF Model'!C19+0)+'DCF Model'!D45/(1+$B8)^('DCF Model'!C19+1)+'DCF Model'!E45/(1+$B8)^('DCF Model'!C19+2)+'DCF Model'!F45/(1+$B8)^('DCF Model'!C19+3)+'DCF Model'!G45/(1+$B8)^('DCF Model'!C19+4)+'DCF Model'!G45*(1+C$6)/($B8-C$6)/(1+$B8)^('DCF Model'!C19+4)-'DCF Model'!C16)*1000000/'DCF Model'!C15,0),"") -> 348 | D8: =IFERROR(ROUND(('DCF Model'!C45/(1+$B8)^('DCF Model'!C19+0)+'DCF Model'!D45/(1+$B8)^('DCF Model'!C19+1)+'DCF Model'!E45/(1+$B8)^('DCF Model'!C19+2)+'DCF Model'!F45/(1+$B8)^('DCF Model'!C19+3)+'DCF Model'!G45/(1+$B8)^('DCF Model'!C19+4)+'DCF Model'!G45*(1+D$6)/($B8-D$6)/(1+$B8)^('DCF Model'!C19+4)-'DCF Model'!C16)*1000000/'DCF Model'!C15,0),"") -> 359 | E8: =IFERROR(ROUND(('DCF Model'!C45/(1+$B8)^('DCF Model'!C19+0)+'DCF Model'!D45/(1+$B8)^('DCF Model'!C19+1)+'DCF Model'!E45/(1+$B8)^('DCF Model'!C19+2)+'DCF Model'!F45/(1+$B8)^('DCF Model'!C19+3)+'DCF Model'!G45/(1+$B8)^('DCF Model'!C19+4)+'DCF Model'!G45*(1+E$6)/($B8-E$6)/(1+$B8)^('DCF Model'!C19+4)-'DCF Model'!C16)*1000000/'DCF Model'!C15,0),"") -> 371 | F8: =IFERROR(ROUND(('DCF Model'!C45/(1+$B8)^('DCF Model'!C19+0)+'DCF Model'!D45/(1+$B8)^('DCF Model'!C19+1)+'DCF Model'!E45/(1+$B8)^('DCF Model'!C19+2)+'DCF Model'!F45/(1+$B8)^('DCF Model'!C19+3)+'DCF Model'!G45/(1+$B8)^('DCF Model'!C19+4)+'DCF Model'!G45*(1+F$6)/($B8-F$6)/(1+$B8)^('DCF Model'!C19+4)-'DCF Model'!C16)*1000000/'DCF Model'!C15,0),"") -> 383 | G8: =IFERROR(ROUND(('DCF Model'!C45/(1+$B8)^('DCF Model'!C19+0)+'DCF Model'!D45/(1+$B8)^('DCF Model'!C19+1)+'DCF Model'!E45/(1+$B8)^('DCF Model'!C19+2)+'DCF Model'!F45/(1+$B8)^('DCF Model'!C19+3)+'DCF Model'!G45/(1+$B8)^('DCF Model'!C19+4)+'DCF Model'!G45*(1+G$6)/($B8-G$6)/(1+$B8)^('DCF Model'!C19+4)-'DCF Model'!C16)*1000000/'DCF Model'!C15,0),"") -> 397 | H8: =IFERROR(ROUND(('DCF Model'!C45/(1+$B8)^('DCF Model'!C19+0)+'DCF Model'!D45/(1+$B8)^('DCF Model'!C19+1)+'DCF Model'!E45/(1+$B8)^('DCF Model'!C19+2)+'DCF Model'!F45/(1+$B8)^('DCF Model'!C19+3)+'DCF Model'!G45/(1+$B8)^('DCF Model'!C19+4)+'DCF Model'!G45*(1+H$6)/($B8-H$6)/(1+$B8)^('DCF Model'!C19+4)-'DCF Model'!C16)*1000000/'DCF Model'!C15,0),"") -> 412 | I8: =IFERROR(ROUND(('DCF Model'!C45/(1+$B8)^('DCF Model'!C19+0)+'DCF Model'!D45/(1+$B8)^('DCF Model'!C19+1)+'DCF Model'!E45/(1+$B8)^('DCF Model'!C19+2)+'DCF Model'!F45/(1+$B8)^('DCF Model'!C19+3)+'DCF Model'!G45/(1+$B8)^('DCF Model'!C19+4)+'DCF Model'!G45*(1+I$6)/($B8-I$6)/(1+$B8)^('DCF Model'!C19+4)-'DCF Model'!C16)*1000000/'DCF Model'!C15,0),"") -> 428
B9: =$C$3-0.005 -> 0.075416 | C9: =IFERROR(ROUND(('DCF Model'!C45/(1+$B9)^('DCF Model'!C19+0)+'DCF Model'!D45/(1+$B9)^('DCF Model'!C19+1)+'DCF Model'!E45/(1+$B9)^('DCF Model'!C19+2)+'DCF Model'!F45/(1+$B9)^('DCF Model'!C19+3)+'DCF Model'!G45/(1+$B9)^('DCF Model'!C19+4)+'DCF Model'!G45*(1+C$6)/($B9-C$6)/(1+$B9)^('DCF Model'!C19+4)-'DCF Model'!C16)*1000000/'DCF Model'!C15,0),"") -> 323 | D9: =IFERROR(ROUND(('DCF Model'!C45/(1+$B9)^('DCF Model'!C19+0)+'DCF Model'!D45/(1+$B9)^('DCF Model'!C19+1)+'DCF Model'!E45/(1+$B9)^('DCF Model'!C19+2)+'DCF Model'!F45/(1+$B9)^('DCF Model'!C19+3)+'DCF Model'!G45/(1+$B9)^('DCF Model'!C19+4)+'DCF Model'!G45*(1+D$6)/($B9-D$6)/(1+$B9)^('DCF Model'!C19+4)-'DCF Model'!C16)*1000000/'DCF Model'!C15,0),"") -> 332 | E9: =IFERROR(ROUND(('DCF Model'!C45/(1+$B9)^('DCF Model'!C19+0)+'DCF Model'!D45/(1+$B9)^('DCF Model'!C19+1)+'DCF Model'!E45/(1+$B9)^('DCF Model'!C19+2)+'DCF Model'!F45/(1+$B9)^('DCF Model'!C19+3)+'DCF Model'!G45/(1+$B9)^('DCF Model'!C19+4)+'DCF Model'!G45*(1+E$6)/($B9-E$6)/(1+$B9)^('DCF Model'!C19+4)-'DCF Model'!C16)*1000000/'DCF Model'!C15,0),"") -> 342 | F9: =IFERROR(ROUND(('DCF Model'!C45/(1+$B9)^('DCF Model'!C19+0)+'DCF Model'!D45/(1+$B9)^('DCF Model'!C19+1)+'DCF Model'!E45/(1+$B9)^('DCF Model'!C19+2)+'DCF Model'!F45/(1+$B9)^('DCF Model'!C19+3)+'DCF Model'!G45/(1+$B9)^('DCF Model'!C19+4)+'DCF Model'!G45*(1+F$6)/($B9-F$6)/(1+$B9)^('DCF Model'!C19+4)-'DCF Model'!C16)*1000000/'DCF Model'!C15,0),"") -> 353 | G9: =IFERROR(ROUND(('DCF Model'!C45/(1+$B9)^('DCF Model'!C19+0)+'DCF Model'!D45/(1+$B9)^('DCF Model'!C19+1)+'DCF Model'!E45/(1+$B9)^('DCF Model'!C19+2)+'DCF Model'!F45/(1+$B9)^('DCF Model'!C19+3)+'DCF Model'!G45/(1+$B9)^('DCF Model'!C19+4)+'DCF Model'!G45*(1+G$6)/($B9-G$6)/(1+$B9)^('DCF Model'!C19+4)-'DCF Model'!C16)*1000000/'DCF Model'!C15,0),"") -> 364 | H9: =IFERROR(ROUND(('DCF Model'!C45/(1+$B9)^('DCF Model'!C19+0)+'DCF Model'!D45/(1+$B9)^('DCF Model'!C19+1)+'DCF Model'!E45/(1+$B9)^('DCF Model'!C19+2)+'DCF Model'!F45/(1+$B9)^('DCF Model'!C19+3)+'DCF Model'!G45/(1+$B9)^('DCF Model'!C19+4)+'DCF Model'!G45*(1+H$6)/($B9-H$6)/(1+$B9)^('DCF Model'!C19+4)-'DCF Model'!C16)*1000000/'DCF Model'!C15,0),"") -> 377 | I9: =IFERROR(ROUND(('DCF Model'!C45/(1+$B9)^('DCF Model'!C19+0)+'DCF Model'!D45/(1+$B9)^('DCF Model'!C19+1)+'DCF Model'!E45/(1+$B9)^('DCF Model'!C19+2)+'DCF Model'!F45/(1+$B9)^('DCF Model'!C19+3)+'DCF Model'!G45/(1+$B9)^('DCF Model'!C19+4)+'DCF Model'!G45*(1+I$6)/($B9-I$6)/(1+$B9)^('DCF Model'!C19+4)-'DCF Model'!C16)*1000000/'DCF Model'!C15,0),"") -> 390
B10: =$C$3 -> 0.080416 | C10: =IFERROR(ROUND(('DCF Model'!C45/(1+$B10)^('DCF Model'!C19+0)+'DCF Model'!D45/(1+$B10)^('DCF Model'!C19+1)+'DCF Model'!E45/(1+$B10)^('DCF Model'!C19+2)+'DCF Model'!F45/(1+$B10)^('DCF Model'!C19+3)+'DCF Model'!G45/(1+$B10)^('DCF Model'!C19+4)+'DCF Model'!G45*(1+C$6)/($B10-C$6)/(1+$B10)^('DCF Model'!C19+4)-'DCF Model'!C16)*1000000/'DCF Model'!C15,0),"") -> 301 | D10: =IFERROR(ROUND(('DCF Model'!C45/(1+$B10)^('DCF Model'!C19+0)+'DCF Model'!D45/(1+$B10)^('DCF Model'!C19+1)+'DCF Model'!E45/(1+$B10)^('DCF Model'!C19+2)+'DCF Model'!F45/(1+$B10)^('DCF Model'!C19+3)+'DCF Model'!G45/(1+$B10)^('DCF Model'!C19+4)+'DCF Model'!G45*(1+D$6)/($B10-D$6)/(1+$B10)^('DCF Model'!C19+4)-'DCF Model'!C16)*1000000/'DCF Model'!C15,0),"") -> 309 | E10: =IFERROR(ROUND(('DCF Model'!C45/(1+$B10)^('DCF Model'!C19+0)+'DCF Model'!D45/(1+$B10)^('DCF Model'!C19+1)+'DCF Model'!E45/(1+$B10)^('DCF Model'!C19+2)+'DCF Model'!F45/(1+$B10)^('DCF Model'!C19+3)+'DCF Model'!G45/(1+$B10)^('DCF Model'!C19+4)+'DCF Model'!G45*(1+E$6)/($B10-E$6)/(1+$B10)^('DCF Model'!C19+4)-'DCF Model'!C16)*1000000/'DCF Model'!C15,0),"") -> 318 | F10: =IFERROR(ROUND(('DCF Model'!C45/(1+$B10)^('DCF Model'!C19+0)+'DCF Model'!D45/(1+$B10)^('DCF Model'!C19+1)+'DCF Model'!E45/(1+$B10)^('DCF Model'!C19+2)+'DCF Model'!F45/(1+$B10)^('DCF Model'!C19+3)+'DCF Model'!G45/(1+$B10)^('DCF Model'!C19+4)+'DCF Model'!G45*(1+F$6)/($B10-F$6)/(1+$B10)^('DCF Model'!C19+4)-'DCF Model'!C16)*1000000/'DCF Model'!C15,0),"") -> 327 | G10: =IFERROR(ROUND(('DCF Model'!C45/(1+$B10)^('DCF Model'!C19+0)+'DCF Model'!D45/(1+$B10)^('DCF Model'!C19+1)+'DCF Model'!E45/(1+$B10)^('DCF Model'!C19+2)+'DCF Model'!F45/(1+$B10)^('DCF Model'!C19+3)+'DCF Model'!G45/(1+$B10)^('DCF Model'!C19+4)+'DCF Model'!G45*(1+G$6)/($B10-G$6)/(1+$B10)^('DCF Model'!C19+4)-'DCF Model'!C16)*1000000/'DCF Model'!C15,0),"") -> 336 | H10: =IFERROR(ROUND(('DCF Model'!C45/(1+$B10)^('DCF Model'!C19+0)+'DCF Model'!D45/(1+$B10)^('DCF Model'!C19+1)+'DCF Model'!E45/(1+$B10)^('DCF Model'!C19+2)+'DCF Model'!F45/(1+$B10)^('DCF Model'!C19+3)+'DCF Model'!G45/(1+$B10)^('DCF Model'!C19+4)+'DCF Model'!G45*(1+H$6)/($B10-H$6)/(1+$B10)^('DCF Model'!C19+4)-'DCF Model'!C16)*1000000/'DCF Model'!C15,0),"") -> 347 | I10: =IFERROR(ROUND(('DCF Model'!C45/(1+$B10)^('DCF Model'!C19+0)+'DCF Model'!D45/(1+$B10)^('DCF Model'!C19+1)+'DCF Model'!E45/(1+$B10)^('DCF Model'!C19+2)+'DCF Model'!F45/(1+$B10)^('DCF Model'!C19+3)+'DCF Model'!G45/(1+$B10)^('DCF Model'!C19+4)+'DCF Model'!G45*(1+I$6)/($B10-I$6)/(1+$B10)^('DCF Model'!C19+4)-'DCF Model'!C16)*1000000/'DCF Model'!C15,0),"") -> 358
B11: =$C$3+0.005 -> 0.085416 | C11: =IFERROR(ROUND(('DCF Model'!C45/(1+$B11)^('DCF Model'!C19+0)+'DCF Model'!D45/(1+$B11)^('DCF Model'!C19+1)+'DCF Model'!E45/(1+$B11)^('DCF Model'!C19+2)+'DCF Model'!F45/(1+$B11)^('DCF Model'!C19+3)+'DCF Model'!G45/(1+$B11)^('DCF Model'!C19+4)+'DCF Model'!G45*(1+C$6)/($B11-C$6)/(1+$B11)^('DCF Model'!C19+4)-'DCF Model'!C16)*1000000/'DCF Model'!C15,0),"") -> 282 | D11: =IFERROR(ROUND(('DCF Model'!C45/(1+$B11)^('DCF Model'!C19+0)+'DCF Model'!D45/(1+$B11)^('DCF Model'!C19+1)+'DCF Model'!E45/(1+$B11)^('DCF Model'!C19+2)+'DCF Model'!F45/(1+$B11)^('DCF Model'!C19+3)+'DCF Model'!G45/(1+$B11)^('DCF Model'!C19+4)+'DCF Model'!G45*(1+D$6)/($B11-D$6)/(1+$B11)^('DCF Model'!C19+4)-'DCF Model'!C16)*1000000/'DCF Model'!C15,0),"") -> 289 | E11: =IFERROR(ROUND(('DCF Model'!C45/(1+$B11)^('DCF Model'!C19+0)+'DCF Model'!D45/(1+$B11)^('DCF Model'!C19+1)+'DCF Model'!E45/(1+$B11)^('DCF Model'!C19+2)+'DCF Model'!F45/(1+$B11)^('DCF Model'!C19+3)+'DCF Model'!G45/(1+$B11)^('DCF Model'!C19+4)+'DCF Model'!G45*(1+E$6)/($B11-E$6)/(1+$B11)^('DCF Model'!C19+4)-'DCF Model'!C16)*1000000/'DCF Model'!C15,0),"") -> 296 | F11: =IFERROR(ROUND(('DCF Model'!C45/(1+$B11)^('DCF Model'!C19+0)+'DCF Model'!D45/(1+$B11)^('DCF Model'!C19+1)+'DCF Model'!E45/(1+$B11)^('DCF Model'!C19+2)+'DCF Model'!F45/(1+$B11)^('DCF Model'!C19+3)+'DCF Model'!G45/(1+$B11)^('DCF Model'!C19+4)+'DCF Model'!G45*(1+F$6)/($B11-F$6)/(1+$B11)^('DCF Model'!C19+4)-'DCF Model'!C16)*1000000/'DCF Model'!C15,0),"") -> 304 | G11: =IFERROR(ROUND(('DCF Model'!C45/(1+$B11)^('DCF Model'!C19+0)+'DCF Model'!D45/(1+$B11)^('DCF Model'!C19+1)+'DCF Model'!E45/(1+$B11)^('DCF Model'!C19+2)+'DCF Model'!F45/(1+$B11)^('DCF Model'!C19+3)+'DCF Model'!G45/(1+$B11)^('DCF Model'!C19+4)+'DCF Model'!G45*(1+G$6)/($B11-G$6)/(1+$B11)^('DCF Model'!C19+4)-'DCF Model'!C16)*1000000/'DCF Model'!C15,0),"") -> 312 | H11: =IFERROR(ROUND(('DCF Model'!C45/(1+$B11)^('DCF Model'!C19+0)+'DCF Model'!D45/(1+$B11)^('DCF Model'!C19+1)+'DCF Model'!E45/(1+$B11)^('DCF Model'!C19+2)+'DCF Model'!F45/(1+$B11)^('DCF Model'!C19+3)+'DCF Model'!G45/(1+$B11)^('DCF Model'!C19+4)+'DCF Model'!G45*(1+H$6)/($B11-H$6)/(1+$B11)^('DCF Model'!C19+4)-'DCF Model'!C16)*1000000/'DCF Model'!C15,0),"") -> 321 | I11: =IFERROR(ROUND(('DCF Model'!C45/(1+$B11)^('DCF Model'!C19+0)+'DCF Model'!D45/(1+$B11)^('DCF Model'!C19+1)+'DCF Model'!E45/(1+$B11)^('DCF Model'!C19+2)+'DCF Model'!F45/(1+$B11)^('DCF Model'!C19+3)+'DCF Model'!G45/(1+$B11)^('DCF Model'!C19+4)+'DCF Model'!G45*(1+I$6)/($B11-I$6)/(1+$B11)^('DCF Model'!C19+4)-'DCF Model'!C16)*1000000/'DCF Model'!C15,0),"") -> 331
B12: =$C$3+0.01 -> 0.090416 | C12: =IFERROR(ROUND(('DCF Model'!C45/(1+$B12)^('DCF Model'!C19+0)+'DCF Model'!D45/(1+$B12)^('DCF Model'!C19+1)+'DCF Model'!E45/(1+$B12)^('DCF Model'!C19+2)+'DCF Model'!F45/(1+$B12)^('DCF Model'!C19+3)+'DCF Model'!G45/(1+$B12)^('DCF Model'!C19+4)+'DCF Model'!G45*(1+C$6)/($B12-C$6)/(1+$B12)^('DCF Model'!C19+4)-'DCF Model'!C16)*1000000/'DCF Model'!C15,0),"") -> 265 | D12: =IFERROR(ROUND(('DCF Model'!C45/(1+$B12)^('DCF Model'!C19+0)+'DCF Model'!D45/(1+$B12)^('DCF Model'!C19+1)+'DCF Model'!E45/(1+$B12)^('DCF Model'!C19+2)+'DCF Model'!F45/(1+$B12)^('DCF Model'!C19+3)+'DCF Model'!G45/(1+$B12)^('DCF Model'!C19+4)+'DCF Model'!G45*(1+D$6)/($B12-D$6)/(1+$B12)^('DCF Model'!C19+4)-'DCF Model'!C16)*1000000/'DCF Model'!C15,0),"") -> 271 | E12: =IFERROR(ROUND(('DCF Model'!C45/(1+$B12)^('DCF Model'!C19+0)+'DCF Model'!D45/(1+$B12)^('DCF Model'!C19+1)+'DCF Model'!E45/(1+$B12)^('DCF Model'!C19+2)+'DCF Model'!F45/(1+$B12)^('DCF Model'!C19+3)+'DCF Model'!G45/(1+$B12)^('DCF Model'!C19+4)+'DCF Model'!G45*(1+E$6)/($B12-E$6)/(1+$B12)^('DCF Model'!C19+4)-'DCF Model'!C16)*1000000/'DCF Model'!C15,0),"") -> 277 | F12: =IFERROR(ROUND(('DCF Model'!C45/(1+$B12)^('DCF Model'!C19+0)+'DCF Model'!D45/(1+$B12)^('DCF Model'!C19+1)+'DCF Model'!E45/(1+$B12)^('DCF Model'!C19+2)+'DCF Model'!F45/(1+$B12)^('DCF Model'!C19+3)+'DCF Model'!G45/(1+$B12)^('DCF Model'!C19+4)+'DCF Model'!G45*(1+F$6)/($B12-F$6)/(1+$B12)^('DCF Model'!C19+4)-'DCF Model'!C16)*1000000/'DCF Model'!C15,0),"") -> 284 | G12: =IFERROR(ROUND(('DCF Model'!C45/(1+$B12)^('DCF Model'!C19+0)+'DCF Model'!D45/(1+$B12)^('DCF Model'!C19+1)+'DCF Model'!E45/(1+$B12)^('DCF Model'!C19+2)+'DCF Model'!F45/(1+$B12)^('DCF Model'!C19+3)+'DCF Model'!G45/(1+$B12)^('DCF Model'!C19+4)+'DCF Model'!G45*(1+G$6)/($B12-G$6)/(1+$B12)^('DCF Model'!C19+4)-'DCF Model'!C16)*1000000/'DCF Model'!C15,0),"") -> 291 | H12: =IFERROR(ROUND(('DCF Model'!C45/(1+$B12)^('DCF Model'!C19+0)+'DCF Model'!D45/(1+$B12)^('DCF Model'!C19+1)+'DCF Model'!E45/(1+$B12)^('DCF Model'!C19+2)+'DCF Model'!F45/(1+$B12)^('DCF Model'!C19+3)+'DCF Model'!G45/(1+$B12)^('DCF Model'!C19+4)+'DCF Model'!G45*(1+H$6)/($B12-H$6)/(1+$B12)^('DCF Model'!C19+4)-'DCF Model'!C16)*1000000/'DCF Model'!C15,0),"") -> 299 | I12: =IFERROR(ROUND(('DCF Model'!C45/(1+$B12)^('DCF Model'!C19+0)+'DCF Model'!D45/(1+$B12)^('DCF Model'!C19+1)+'DCF Model'!E45/(1+$B12)^('DCF Model'!C19+2)+'DCF Model'!F45/(1+$B12)^('DCF Model'!C19+3)+'DCF Model'!G45/(1+$B12)^('DCF Model'!C19+4)+'DCF Model'!G45*(1+I$6)/($B12-I$6)/(1+$B12)^('DCF Model'!C19+4)-'DCF Model'!C16)*1000000/'DCF Model'!C15,0),"") -> 307
B13: =$C$3+0.015 -> 0.095416 | C13: =IFERROR(ROUND(('DCF Model'!C45/(1+$B13)^('DCF Model'!C19+0)+'DCF Model'!D45/(1+$B13)^('DCF Model'!C19+1)+'DCF Model'!E45/(1+$B13)^('DCF Model'!C19+2)+'DCF Model'!F45/(1+$B13)^('DCF Model'!C19+3)+'DCF Model'!G45/(1+$B13)^('DCF Model'!C19+4)+'DCF Model'!G45*(1+C$6)/($B13-C$6)/(1+$B13)^('DCF Model'!C19+4)-'DCF Model'!C16)*1000000/'DCF Model'!C15,0),"") -> 250 | D13: =IFERROR(ROUND(('DCF Model'!C45/(1+$B13)^('DCF Model'!C19+0)+'DCF Model'!D45/(1+$B13)^('DCF Model'!C19+1)+'DCF Model'!E45/(1+$B13)^('DCF Model'!C19+2)+'DCF Model'!F45/(1+$B13)^('DCF Model'!C19+3)+'DCF Model'!G45/(1+$B13)^('DCF Model'!C19+4)+'DCF Model'!G45*(1+D$6)/($B13-D$6)/(1+$B13)^('DCF Model'!C19+4)-'DCF Model'!C16)*1000000/'DCF Model'!C15,0),"") -> 255 | E13: =IFERROR(ROUND(('DCF Model'!C45/(1+$B13)^('DCF Model'!C19+0)+'DCF Model'!D45/(1+$B13)^('DCF Model'!C19+1)+'DCF Model'!E45/(1+$B13)^('DCF Model'!C19+2)+'DCF Model'!F45/(1+$B13)^('DCF Model'!C19+3)+'DCF Model'!G45/(1+$B13)^('DCF Model'!C19+4)+'DCF Model'!G45*(1+E$6)/($B13-E$6)/(1+$B13)^('DCF Model'!C19+4)-'DCF Model'!C16)*1000000/'DCF Model'!C15,0),"") -> 261 | F13: =IFERROR(ROUND(('DCF Model'!C45/(1+$B13)^('DCF Model'!C19+0)+'DCF Model'!D45/(1+$B13)^('DCF Model'!C19+1)+'DCF Model'!E45/(1+$B13)^('DCF Model'!C19+2)+'DCF Model'!F45/(1+$B13)^('DCF Model'!C19+3)+'DCF Model'!G45/(1+$B13)^('DCF Model'!C19+4)+'DCF Model'!G45*(1+F$6)/($B13-F$6)/(1+$B13)^('DCF Model'!C19+4)-'DCF Model'!C16)*1000000/'DCF Model'!C15,0),"") -> 267 | G13: =IFERROR(ROUND(('DCF Model'!C45/(1+$B13)^('DCF Model'!C19+0)+'DCF Model'!D45/(1+$B13)^('DCF Model'!C19+1)+'DCF Model'!E45/(1+$B13)^('DCF Model'!C19+2)+'DCF Model'!F45/(1+$B13)^('DCF Model'!C19+3)+'DCF Model'!G45/(1+$B13)^('DCF Model'!C19+4)+'DCF Model'!G45*(1+G$6)/($B13-G$6)/(1+$B13)^('DCF Model'!C19+4)-'DCF Model'!C16)*1000000/'DCF Model'!C15,0),"") -> 273 | H13: =IFERROR(ROUND(('DCF Model'!C45/(1+$B13)^('DCF Model'!C19+0)+'DCF Model'!D45/(1+$B13)^('DCF Model'!C19+1)+'DCF Model'!E45/(1+$B13)^('DCF Model'!C19+2)+'DCF Model'!F45/(1+$B13)^('DCF Model'!C19+3)+'DCF Model'!G45/(1+$B13)^('DCF Model'!C19+4)+'DCF Model'!G45*(1+H$6)/($B13-H$6)/(1+$B13)^('DCF Model'!C19+4)-'DCF Model'!C16)*1000000/'DCF Model'!C15,0),"") -> 279 | I13: =IFERROR(ROUND(('DCF Model'!C45/(1+$B13)^('DCF Model'!C19+0)+'DCF Model'!D45/(1+$B13)^('DCF Model'!C19+1)+'DCF Model'!E45/(1+$B13)^('DCF Model'!C19+2)+'DCF Model'!F45/(1+$B13)^('DCF Model'!C19+3)+'DCF Model'!G45/(1+$B13)^('DCF Model'!C19+4)+'DCF Model'!G45*(1+I$6)/($B13-I$6)/(1+$B13)^('DCF Model'!C19+4)-'DCF Model'!C16)*1000000/'DCF Model'!C15,0),"") -> 286
B16: Table 2: WACC vs Exit Multiple (Exit Multiple - Implied Share Price, JPY)
B17: WACC \ Exit Multiple | C17: =$I$3-3 -> 4 | D17: =$I$3-2 -> 5 | E17: =$I$3-1 -> 6 | F17: =$I$3 -> 7 | G17: =$I$3+1 -> 8 | H17: =$I$3+2 -> 9 | I17: =$I$3+3 -> 10
B18: =$C$3-0.015 -> 0.065416 | C18: =IFERROR(ROUND(('DCF Model'!C45/(1+$B18)^('DCF Model'!C19+0)+'DCF Model'!D45/(1+$B18)^('DCF Model'!C19+1)+'DCF Model'!E45/(1+$B18)^('DCF Model'!C19+2)+'DCF Model'!F45/(1+$B18)^('DCF Model'!C19+3)+'DCF Model'!G45/(1+$B18)^('DCF Model'!C19+4)+('DCF Model'!G39+'DCF Model'!G42)*C$17/(1+$B18)^('DCF Model'!C19+4)-'DCF Model'!C16)*1000000/'DCF Model'!C15,0),"") -> 267 | D18: =IFERROR(ROUND(('DCF Model'!C45/(1+$B18)^('DCF Model'!C19+0)+'DCF Model'!D45/(1+$B18)^('DCF Model'!C19+1)+'DCF Model'!E45/(1+$B18)^('DCF Model'!C19+2)+'DCF Model'!F45/(1+$B18)^('DCF Model'!C19+3)+'DCF Model'!G45/(1+$B18)^('DCF Model'!C19+4)+('DCF Model'!G39+'DCF Model'!G42)*D$17/(1+$B18)^('DCF Model'!C19+4)-'DCF Model'!C16)*1000000/'DCF Model'!C15,0),"") -> 312 | E18: =IFERROR(ROUND(('DCF Model'!C45/(1+$B18)^('DCF Model'!C19+0)+'DCF Model'!D45/(1+$B18)^('DCF Model'!C19+1)+'DCF Model'!E45/(1+$B18)^('DCF Model'!C19+2)+'DCF Model'!F45/(1+$B18)^('DCF Model'!C19+3)+'DCF Model'!G45/(1+$B18)^('DCF Model'!C19+4)+('DCF Model'!G39+'DCF Model'!G42)*E$17/(1+$B18)^('DCF Model'!C19+4)-'DCF Model'!C16)*1000000/'DCF Model'!C15,0),"") -> 358 | F18: =IFERROR(ROUND(('DCF Model'!C45/(1+$B18)^('DCF Model'!C19+0)+'DCF Model'!D45/(1+$B18)^('DCF Model'!C19+1)+'DCF Model'!E45/(1+$B18)^('DCF Model'!C19+2)+'DCF Model'!F45/(1+$B18)^('DCF Model'!C19+3)+'DCF Model'!G45/(1+$B18)^('DCF Model'!C19+4)+('DCF Model'!G39+'DCF Model'!G42)*F$17/(1+$B18)^('DCF Model'!C19+4)-'DCF Model'!C16)*1000000/'DCF Model'!C15,0),"") -> 404 | G18: =IFERROR(ROUND(('DCF Model'!C45/(1+$B18)^('DCF Model'!C19+0)+'DCF Model'!D45/(1+$B18)^('DCF Model'!C19+1)+'DCF Model'!E45/(1+$B18)^('DCF Model'!C19+2)+'DCF Model'!F45/(1+$B18)^('DCF Model'!C19+3)+'DCF Model'!G45/(1+$B18)^('DCF Model'!C19+4)+('DCF Model'!G39+'DCF Model'!G42)*G$17/(1+$B18)^('DCF Model'!C19+4)-'DCF Model'!C16)*1000000/'DCF Model'!C15,0),"") -> 449 | H18: =IFERROR(ROUND(('DCF Model'!C45/(1+$B18)^('DCF Model'!C19+0)+'DCF Model'!D45/(1+$B18)^('DCF Model'!C19+1)+'DCF Model'!E45/(1+$B18)^('DCF Model'!C19+2)+'DCF Model'!F45/(1+$B18)^('DCF Model'!C19+3)+'DCF Model'!G45/(1+$B18)^('DCF Model'!C19+4)+('DCF Model'!G39+'DCF Model'!G42)*H$17/(1+$B18)^('DCF Model'!C19+4)-'DCF Model'!C16)*1000000/'DCF Model'!C15,0),"") -> 495 | I18: =IFERROR(ROUND(('DCF Model'!C45/(1+$B18)^('DCF Model'!C19+0)+'DCF Model'!D45/(1+$B18)^('DCF Model'!C19+1)+'DCF Model'!E45/(1+$B18)^('DCF Model'!C19+2)+'DCF Model'!F45/(1+$B18)^('DCF Model'!C19+3)+'DCF Model'!G45/(1+$B18)^('DCF Model'!C19+4)+('DCF Model'!G39+'DCF Model'!G42)*I$17/(1+$B18)^('DCF Model'!C19+4)-'DCF Model'!C16)*1000000/'DCF Model'!C15,0),"") -> 540
B19: =$C$3-0.01 -> 0.070416 | C19: =IFERROR(ROUND(('DCF Model'!C45/(1+$B19)^('DCF Model'!C19+0)+'DCF Model'!D45/(1+$B19)^('DCF Model'!C19+1)+'DCF Model'!E45/(1+$B19)^('DCF Model'!C19+2)+'DCF Model'!F45/(1+$B19)^('DCF Model'!C19+3)+'DCF Model'!G45/(1+$B19)^('DCF Model'!C19+4)+('DCF Model'!G39+'DCF Model'!G42)*C$17/(1+$B19)^('DCF Model'!C19+4)-'DCF Model'!C16)*1000000/'DCF Model'!C15,0),"") -> 261 | D19: =IFERROR(ROUND(('DCF Model'!C45/(1+$B19)^('DCF Model'!C19+0)+'DCF Model'!D45/(1+$B19)^('DCF Model'!C19+1)+'DCF Model'!E45/(1+$B19)^('DCF Model'!C19+2)+'DCF Model'!F45/(1+$B19)^('DCF Model'!C19+3)+'DCF Model'!G45/(1+$B19)^('DCF Model'!C19+4)+('DCF Model'!G39+'DCF Model'!G42)*D$17/(1+$B19)^('DCF Model'!C19+4)-'DCF Model'!C16)*1000000/'DCF Model'!C15,0),"") -> 306 | E19: =IFERROR(ROUND(('DCF Model'!C45/(1+$B19)^('DCF Model'!C19+0)+'DCF Model'!D45/(1+$B19)^('DCF Model'!C19+1)+'DCF Model'!E45/(1+$B19)^('DCF Model'!C19+2)+'DCF Model'!F45/(1+$B19)^('DCF Model'!C19+3)+'DCF Model'!G45/(1+$B19)^('DCF Model'!C19+4)+('DCF Model'!G39+'DCF Model'!G42)*E$17/(1+$B19)^('DCF Model'!C19+4)-'DCF Model'!C16)*1000000/'DCF Model'!C15,0),"") -> 350 | F19: =IFERROR(ROUND(('DCF Model'!C45/(1+$B19)^('DCF Model'!C19+0)+'DCF Model'!D45/(1+$B19)^('DCF Model'!C19+1)+'DCF Model'!E45/(1+$B19)^('DCF Model'!C19+2)+'DCF Model'!F45/(1+$B19)^('DCF Model'!C19+3)+'DCF Model'!G45/(1+$B19)^('DCF Model'!C19+4)+('DCF Model'!G39+'DCF Model'!G42)*F$17/(1+$B19)^('DCF Model'!C19+4)-'DCF Model'!C16)*1000000/'DCF Model'!C15,0),"") -> 395 | G19: =IFERROR(ROUND(('DCF Model'!C45/(1+$B19)^('DCF Model'!C19+0)+'DCF Model'!D45/(1+$B19)^('DCF Model'!C19+1)+'DCF Model'!E45/(1+$B19)^('DCF Model'!C19+2)+'DCF Model'!F45/(1+$B19)^('DCF Model'!C19+3)+'DCF Model'!G45/(1+$B19)^('DCF Model'!C19+4)+('DCF Model'!G39+'DCF Model'!G42)*G$17/(1+$B19)^('DCF Model'!C19+4)-'DCF Model'!C16)*1000000/'DCF Model'!C15,0),"") -> 440 | H19: =IFERROR(ROUND(('DCF Model'!C45/(1+$B19)^('DCF Model'!C19+0)+'DCF Model'!D45/(1+$B19)^('DCF Model'!C19+1)+'DCF Model'!E45/(1+$B19)^('DCF Model'!C19+2)+'DCF Model'!F45/(1+$B19)^('DCF Model'!C19+3)+'DCF Model'!G45/(1+$B19)^('DCF Model'!C19+4)+('DCF Model'!G39+'DCF Model'!G42)*H$17/(1+$B19)^('DCF Model'!C19+4)-'DCF Model'!C16)*1000000/'DCF Model'!C15,0),"") -> 484 | I19: =IFERROR(ROUND(('DCF Model'!C45/(1+$B19)^('DCF Model'!C19+0)+'DCF Model'!D45/(1+$B19)^('DCF Model'!C19+1)+'DCF Model'!E45/(1+$B19)^('DCF Model'!C19+2)+'DCF Model'!F45/(1+$B19)^('DCF Model'!C19+3)+'DCF Model'!G45/(1+$B19)^('DCF Model'!C19+4)+('DCF Model'!G39+'DCF Model'!G42)*I$17/(1+$B19)^('DCF Model'!C19+4)-'DCF Model'!C16)*1000000/'DCF Model'!C15,0),"") -> 529
B20: =$C$3-0.005 -> 0.075416 | C20: =IFERROR(ROUND(('DCF Model'!C45/(1+$B20)^('DCF Model'!C19+0)+'DCF Model'!D45/(1+$B20)^('DCF Model'!C19+1)+'DCF Model'!E45/(1+$B20)^('DCF Model'!C19+2)+'DCF Model'!F45/(1+$B20)^('DCF Model'!C19+3)+'DCF Model'!G45/(1+$B20)^('DCF Model'!C19+4)+('DCF Model'!G39+'DCF Model'!G42)*C$17/(1+$B20)^('DCF Model'!C19+4)-'DCF Model'!C16)*1000000/'DCF Model'!C15,0),"") -> 256 | D20: =IFERROR(ROUND(('DCF Model'!C45/(1+$B20)^('DCF Model'!C19+0)+'DCF Model'!D45/(1+$B20)^('DCF Model'!C19+1)+'DCF Model'!E45/(1+$B20)^('DCF Model'!C19+2)+'DCF Model'!F45/(1+$B20)^('DCF Model'!C19+3)+'DCF Model'!G45/(1+$B20)^('DCF Model'!C19+4)+('DCF Model'!G39+'DCF Model'!G42)*D$17/(1+$B20)^('DCF Model'!C19+4)-'DCF Model'!C16)*1000000/'DCF Model'!C15,0),"") -> 300 | E20: =IFERROR(ROUND(('DCF Model'!C45/(1+$B20)^('DCF Model'!C19+0)+'DCF Model'!D45/(1+$B20)^('DCF Model'!C19+1)+'DCF Model'!E45/(1+$B20)^('DCF Model'!C19+2)+'DCF Model'!F45/(1+$B20)^('DCF Model'!C19+3)+'DCF Model'!G45/(1+$B20)^('DCF Model'!C19+4)+('DCF Model'!G39+'DCF Model'!G42)*E$17/(1+$B20)^('DCF Model'!C19+4)-'DCF Model'!C16)*1000000/'DCF Model'!C15,0),"") -> 343 | F20: =IFERROR(ROUND(('DCF Model'!C45/(1+$B20)^('DCF Model'!C19+0)+'DCF Model'!D45/(1+$B20)^('DCF Model'!C19+1)+'DCF Model'!E45/(1+$B20)^('DCF Model'!C19+2)+'DCF Model'!F45/(1+$B20)^('DCF Model'!C19+3)+'DCF Model'!G45/(1+$B20)^('DCF Model'!C19+4)+('DCF Model'!G39+'DCF Model'!G42)*F$17/(1+$B20)^('DCF Model'!C19+4)-'DCF Model'!C16)*1000000/'DCF Model'!C15,0),"") -> 387 | G20: =IFERROR(ROUND(('DCF Model'!C45/(1+$B20)^('DCF Model'!C19+0)+'DCF Model'!D45/(1+$B20)^('DCF Model'!C19+1)+'DCF Model'!E45/(1+$B20)^('DCF Model'!C19+2)+'DCF Model'!F45/(1+$B20)^('DCF Model'!C19+3)+'DCF Model'!G45/(1+$B20)^('DCF Model'!C19+4)+('DCF Model'!G39+'DCF Model'!G42)*G$17/(1+$B20)^('DCF Model'!C19+4)-'DCF Model'!C16)*1000000/'DCF Model'!C15,0),"") -> 430 | H20: =IFERROR(ROUND(('DCF Model'!C45/(1+$B20)^('DCF Model'!C19+0)+'DCF Model'!D45/(1+$B20)^('DCF Model'!C19+1)+'DCF Model'!E45/(1+$B20)^('DCF Model'!C19+2)+'DCF Model'!F45/(1+$B20)^('DCF Model'!C19+3)+'DCF Model'!G45/(1+$B20)^('DCF Model'!C19+4)+('DCF Model'!G39+'DCF Model'!G42)*H$17/(1+$B20)^('DCF Model'!C19+4)-'DCF Model'!C16)*1000000/'DCF Model'!C15,0),"") -> 474 | I20: =IFERROR(ROUND(('DCF Model'!C45/(1+$B20)^('DCF Model'!C19+0)+'DCF Model'!D45/(1+$B20)^('DCF Model'!C19+1)+'DCF Model'!E45/(1+$B20)^('DCF Model'!C19+2)+'DCF Model'!F45/(1+$B20)^('DCF Model'!C19+3)+'DCF Model'!G45/(1+$B20)^('DCF Model'!C19+4)+('DCF Model'!G39+'DCF Model'!G42)*I$17/(1+$B20)^('DCF Model'!C19+4)-'DCF Model'!C16)*1000000/'DCF Model'!C15,0),"") -> 517
B21: =$C$3 -> 0.080416 | C21: =IFERROR(ROUND(('DCF Model'!C45/(1+$B21)^('DCF Model'!C19+0)+'DCF Model'!D45/(1+$B21)^('DCF Model'!C19+1)+'DCF Model'!E45/(1+$B21)^('DCF Model'!C19+2)+'DCF Model'!F45/(1+$B21)^('DCF Model'!C19+3)+'DCF Model'!G45/(1+$B21)^('DCF Model'!C19+4)+('DCF Model'!G39+'DCF Model'!G42)*C$17/(1+$B21)^('DCF Model'!C19+4)-'DCF Model'!C16)*1000000/'DCF Model'!C15,0),"") -> 251 | D21: =IFERROR(ROUND(('DCF Model'!C45/(1+$B21)^('DCF Model'!C19+0)+'DCF Model'!D45/(1+$B21)^('DCF Model'!C19+1)+'DCF Model'!E45/(1+$B21)^('DCF Model'!C19+2)+'DCF Model'!F45/(1+$B21)^('DCF Model'!C19+3)+'DCF Model'!G45/(1+$B21)^('DCF Model'!C19+4)+('DCF Model'!G39+'DCF Model'!G42)*D$17/(1+$B21)^('DCF Model'!C19+4)-'DCF Model'!C16)*1000000/'DCF Model'!C15,0),"") -> 293 | E21: =IFERROR(ROUND(('DCF Model'!C45/(1+$B21)^('DCF Model'!C19+0)+'DCF Model'!D45/(1+$B21)^('DCF Model'!C19+1)+'DCF Model'!E45/(1+$B21)^('DCF Model'!C19+2)+'DCF Model'!F45/(1+$B21)^('DCF Model'!C19+3)+'DCF Model'!G45/(1+$B21)^('DCF Model'!C19+4)+('DCF Model'!G39+'DCF Model'!G42)*E$17/(1+$B21)^('DCF Model'!C19+4)-'DCF Model'!C16)*1000000/'DCF Model'!C15,0),"") -> 336 | F21: =IFERROR(ROUND(('DCF Model'!C45/(1+$B21)^('DCF Model'!C19+0)+'DCF Model'!D45/(1+$B21)^('DCF Model'!C19+1)+'DCF Model'!E45/(1+$B21)^('DCF Model'!C19+2)+'DCF Model'!F45/(1+$B21)^('DCF Model'!C19+3)+'DCF Model'!G45/(1+$B21)^('DCF Model'!C19+4)+('DCF Model'!G39+'DCF Model'!G42)*F$17/(1+$B21)^('DCF Model'!C19+4)-'DCF Model'!C16)*1000000/'DCF Model'!C15,0),"") -> 378 | G21: =IFERROR(ROUND(('DCF Model'!C45/(1+$B21)^('DCF Model'!C19+0)+'DCF Model'!D45/(1+$B21)^('DCF Model'!C19+1)+'DCF Model'!E45/(1+$B21)^('DCF Model'!C19+2)+'DCF Model'!F45/(1+$B21)^('DCF Model'!C19+3)+'DCF Model'!G45/(1+$B21)^('DCF Model'!C19+4)+('DCF Model'!G39+'DCF Model'!G42)*G$17/(1+$B21)^('DCF Model'!C19+4)-'DCF Model'!C16)*1000000/'DCF Model'!C15,0),"") -> 421 | H21: =IFERROR(ROUND(('DCF Model'!C45/(1+$B21)^('DCF Model'!C19+0)+'DCF Model'!D45/(1+$B21)^('DCF Model'!C19+1)+'DCF Model'!E45/(1+$B21)^('DCF Model'!C19+2)+'DCF Model'!F45/(1+$B21)^('DCF Model'!C19+3)+'DCF Model'!G45/(1+$B21)^('DCF Model'!C19+4)+('DCF Model'!G39+'DCF Model'!G42)*H$17/(1+$B21)^('DCF Model'!C19+4)-'DCF Model'!C16)*1000000/'DCF Model'!C15,0),"") -> 464 | I21: =IFERROR(ROUND(('DCF Model'!C45/(1+$B21)^('DCF Model'!C19+0)+'DCF Model'!D45/(1+$B21)^('DCF Model'!C19+1)+'DCF Model'!E45/(1+$B21)^('DCF Model'!C19+2)+'DCF Model'!F45/(1+$B21)^('DCF Model'!C19+3)+'DCF Model'!G45/(1+$B21)^('DCF Model'!C19+4)+('DCF Model'!G39+'DCF Model'!G42)*I$17/(1+$B21)^('DCF Model'!C19+4)-'DCF Model'!C16)*1000000/'DCF Model'!C15,0),"") -> 506
B22: =$C$3+0.005 -> 0.085416 | C22: =IFERROR(ROUND(('DCF Model'!C45/(1+$B22)^('DCF Model'!C19+0)+'DCF Model'!D45/(1+$B22)^('DCF Model'!C19+1)+'DCF Model'!E45/(1+$B22)^('DCF Model'!C19+2)+'DCF Model'!F45/(1+$B22)^('DCF Model'!C19+3)+'DCF Model'!G45/(1+$B22)^('DCF Model'!C19+4)+('DCF Model'!G39+'DCF Model'!G42)*C$17/(1+$B22)^('DCF Model'!C19+4)-'DCF Model'!C16)*1000000/'DCF Model'!C15,0),"") -> 246 | D22: =IFERROR(ROUND(('DCF Model'!C45/(1+$B22)^('DCF Model'!C19+0)+'DCF Model'!D45/(1+$B22)^('DCF Model'!C19+1)+'DCF Model'!E45/(1+$B22)^('DCF Model'!C19+2)+'DCF Model'!F45/(1+$B22)^('DCF Model'!C19+3)+'DCF Model'!G45/(1+$B22)^('DCF Model'!C19+4)+('DCF Model'!G39+'DCF Model'!G42)*D$17/(1+$B22)^('DCF Model'!C19+4)-'DCF Model'!C16)*1000000/'DCF Model'!C15,0),"") -> 287 | E22: =IFERROR(ROUND(('DCF Model'!C45/(1+$B22)^('DCF Model'!C19+0)+'DCF Model'!D45/(1+$B22)^('DCF Model'!C19+1)+'DCF Model'!E45/(1+$B22)^('DCF Model'!C19+2)+'DCF Model'!F45/(1+$B22)^('DCF Model'!C19+3)+'DCF Model'!G45/(1+$B22)^('DCF Model'!C19+4)+('DCF Model'!G39+'DCF Model'!G42)*E$17/(1+$B22)^('DCF Model'!C19+4)-'DCF Model'!C16)*1000000/'DCF Model'!C15,0),"") -> 329 | F22: =IFERROR(ROUND(('DCF Model'!C45/(1+$B22)^('DCF Model'!C19+0)+'DCF Model'!D45/(1+$B22)^('DCF Model'!C19+1)+'DCF Model'!E45/(1+$B22)^('DCF Model'!C19+2)+'DCF Model'!F45/(1+$B22)^('DCF Model'!C19+3)+'DCF Model'!G45/(1+$B22)^('DCF Model'!C19+4)+('DCF Model'!G39+'DCF Model'!G42)*F$17/(1+$B22)^('DCF Model'!C19+4)-'DCF Model'!C16)*1000000/'DCF Model'!C15,0),"") -> 371 | G22: =IFERROR(ROUND(('DCF Model'!C45/(1+$B22)^('DCF Model'!C19+0)+'DCF Model'!D45/(1+$B22)^('DCF Model'!C19+1)+'DCF Model'!E45/(1+$B22)^('DCF Model'!C19+2)+'DCF Model'!F45/(1+$B22)^('DCF Model'!C19+3)+'DCF Model'!G45/(1+$B22)^('DCF Model'!C19+4)+('DCF Model'!G39+'DCF Model'!G42)*G$17/(1+$B22)^('DCF Model'!C19+4)-'DCF Model'!C16)*1000000/'DCF Model'!C15,0),"") -> 412 | H22: =IFERROR(ROUND(('DCF Model'!C45/(1+$B22)^('DCF Model'!C19+0)+'DCF Model'!D45/(1+$B22)^('DCF Model'!C19+1)+'DCF Model'!E45/(1+$B22)^('DCF Model'!C19+2)+'DCF Model'!F45/(1+$B22)^('DCF Model'!C19+3)+'DCF Model'!G45/(1+$B22)^('DCF Model'!C19+4)+('DCF Model'!G39+'DCF Model'!G42)*H$17/(1+$B22)^('DCF Model'!C19+4)-'DCF Model'!C16)*1000000/'DCF Model'!C15,0),"") -> 454 | I22: =IFERROR(ROUND(('DCF Model'!C45/(1+$B22)^('DCF Model'!C19+0)+'DCF Model'!D45/(1+$B22)^('DCF Model'!C19+1)+'DCF Model'!E45/(1+$B22)^('DCF Model'!C19+2)+'DCF Model'!F45/(1+$B22)^('DCF Model'!C19+3)+'DCF Model'!G45/(1+$B22)^('DCF Model'!C19+4)+('DCF Model'!G39+'DCF Model'!G42)*I$17/(1+$B22)^('DCF Model'!C19+4)-'DCF Model'!C16)*1000000/'DCF Model'!C15,0),"") -> 495
B23: =$C$3+0.01 -> 0.090416 | C23: =IFERROR(ROUND(('DCF Model'!C45/(1+$B23)^('DCF Model'!C19+0)+'DCF Model'!D45/(1+$B23)^('DCF Model'!C19+1)+'DCF Model'!E45/(1+$B23)^('DCF Model'!C19+2)+'DCF Model'!F45/(1+$B23)^('DCF Model'!C19+3)+'DCF Model'!G45/(1+$B23)^('DCF Model'!C19+4)+('DCF Model'!G39+'DCF Model'!G42)*C$17/(1+$B23)^('DCF Model'!C19+4)-'DCF Model'!C16)*1000000/'DCF Model'!C15,0),"") -> 241 | D23: =IFERROR(ROUND(('DCF Model'!C45/(1+$B23)^('DCF Model'!C19+0)+'DCF Model'!D45/(1+$B23)^('DCF Model'!C19+1)+'DCF Model'!E45/(1+$B23)^('DCF Model'!C19+2)+'DCF Model'!F45/(1+$B23)^('DCF Model'!C19+3)+'DCF Model'!G45/(1+$B23)^('DCF Model'!C19+4)+('DCF Model'!G39+'DCF Model'!G42)*D$17/(1+$B23)^('DCF Model'!C19+4)-'DCF Model'!C16)*1000000/'DCF Model'!C15,0),"") -> 282 | E23: =IFERROR(ROUND(('DCF Model'!C45/(1+$B23)^('DCF Model'!C19+0)+'DCF Model'!D45/(1+$B23)^('DCF Model'!C19+1)+'DCF Model'!E45/(1+$B23)^('DCF Model'!C19+2)+'DCF Model'!F45/(1+$B23)^('DCF Model'!C19+3)+'DCF Model'!G45/(1+$B23)^('DCF Model'!C19+4)+('DCF Model'!G39+'DCF Model'!G42)*E$17/(1+$B23)^('DCF Model'!C19+4)-'DCF Model'!C16)*1000000/'DCF Model'!C15,0),"") -> 322 | F23: =IFERROR(ROUND(('DCF Model'!C45/(1+$B23)^('DCF Model'!C19+0)+'DCF Model'!D45/(1+$B23)^('DCF Model'!C19+1)+'DCF Model'!E45/(1+$B23)^('DCF Model'!C19+2)+'DCF Model'!F45/(1+$B23)^('DCF Model'!C19+3)+'DCF Model'!G45/(1+$B23)^('DCF Model'!C19+4)+('DCF Model'!G39+'DCF Model'!G42)*F$17/(1+$B23)^('DCF Model'!C19+4)-'DCF Model'!C16)*1000000/'DCF Model'!C15,0),"") -> 363 | G23: =IFERROR(ROUND(('DCF Model'!C45/(1+$B23)^('DCF Model'!C19+0)+'DCF Model'!D45/(1+$B23)^('DCF Model'!C19+1)+'DCF Model'!E45/(1+$B23)^('DCF Model'!C19+2)+'DCF Model'!F45/(1+$B23)^('DCF Model'!C19+3)+'DCF Model'!G45/(1+$B23)^('DCF Model'!C19+4)+('DCF Model'!G39+'DCF Model'!G42)*G$17/(1+$B23)^('DCF Model'!C19+4)-'DCF Model'!C16)*1000000/'DCF Model'!C15,0),"") -> 403 | H23: =IFERROR(ROUND(('DCF Model'!C45/(1+$B23)^('DCF Model'!C19+0)+'DCF Model'!D45/(1+$B23)^('DCF Model'!C19+1)+'DCF Model'!E45/(1+$B23)^('DCF Model'!C19+2)+'DCF Model'!F45/(1+$B23)^('DCF Model'!C19+3)+'DCF Model'!G45/(1+$B23)^('DCF Model'!C19+4)+('DCF Model'!G39+'DCF Model'!G42)*H$17/(1+$B23)^('DCF Model'!C19+4)-'DCF Model'!C16)*1000000/'DCF Model'!C15,0),"") -> 444 | I23: =IFERROR(ROUND(('DCF Model'!C45/(1+$B23)^('DCF Model'!C19+0)+'DCF Model'!D45/(1+$B23)^('DCF Model'!C19+1)+'DCF Model'!E45/(1+$B23)^('DCF Model'!C19+2)+'DCF Model'!F45/(1+$B23)^('DCF Model'!C19+3)+'DCF Model'!G45/(1+$B23)^('DCF Model'!C19+4)+('DCF Model'!G39+'DCF Model'!G42)*I$17/(1+$B23)^('DCF Model'!C19+4)-'DCF Model'!C16)*1000000/'DCF Model'!C15,0),"") -> 485
B24: =$C$3+0.015 -> 0.095416 | C24: =IFERROR(ROUND(('DCF Model'!C45/(1+$B24)^('DCF Model'!C19+0)+'DCF Model'!D45/(1+$B24)^('DCF Model'!C19+1)+'DCF Model'!E45/(1+$B24)^('DCF Model'!C19+2)+'DCF Model'!F45/(1+$B24)^('DCF Model'!C19+3)+'DCF Model'!G45/(1+$B24)^('DCF Model'!C19+4)+('DCF Model'!G39+'DCF Model'!G42)*C$17/(1+$B24)^('DCF Model'!C19+4)-'DCF Model'!C16)*1000000/'DCF Model'!C15,0),"") -> 236 | D24: =IFERROR(ROUND(('DCF Model'!C45/(1+$B24)^('DCF Model'!C19+0)+'DCF Model'!D45/(1+$B24)^('DCF Model'!C19+1)+'DCF Model'!E45/(1+$B24)^('DCF Model'!C19+2)+'DCF Model'!F45/(1+$B24)^('DCF Model'!C19+3)+'DCF Model'!G45/(1+$B24)^('DCF Model'!C19+4)+('DCF Model'!G39+'DCF Model'!G42)*D$17/(1+$B24)^('DCF Model'!C19+4)-'DCF Model'!C16)*1000000/'DCF Model'!C15,0),"") -> 276 | E24: =IFERROR(ROUND(('DCF Model'!C45/(1+$B24)^('DCF Model'!C19+0)+'DCF Model'!D45/(1+$B24)^('DCF Model'!C19+1)+'DCF Model'!E45/(1+$B24)^('DCF Model'!C19+2)+'DCF Model'!F45/(1+$B24)^('DCF Model'!C19+3)+'DCF Model'!G45/(1+$B24)^('DCF Model'!C19+4)+('DCF Model'!G39+'DCF Model'!G42)*E$17/(1+$B24)^('DCF Model'!C19+4)-'DCF Model'!C16)*1000000/'DCF Model'!C15,0),"") -> 316 | F24: =IFERROR(ROUND(('DCF Model'!C45/(1+$B24)^('DCF Model'!C19+0)+'DCF Model'!D45/(1+$B24)^('DCF Model'!C19+1)+'DCF Model'!E45/(1+$B24)^('DCF Model'!C19+2)+'DCF Model'!F45/(1+$B24)^('DCF Model'!C19+3)+'DCF Model'!G45/(1+$B24)^('DCF Model'!C19+4)+('DCF Model'!G39+'DCF Model'!G42)*F$17/(1+$B24)^('DCF Model'!C19+4)-'DCF Model'!C16)*1000000/'DCF Model'!C15,0),"") -> 355 | G24: =IFERROR(ROUND(('DCF Model'!C45/(1+$B24)^('DCF Model'!C19+0)+'DCF Model'!D45/(1+$B24)^('DCF Model'!C19+1)+'DCF Model'!E45/(1+$B24)^('DCF Model'!C19+2)+'DCF Model'!F45/(1+$B24)^('DCF Model'!C19+3)+'DCF Model'!G45/(1+$B24)^('DCF Model'!C19+4)+('DCF Model'!G39+'DCF Model'!G42)*G$17/(1+$B24)^('DCF Model'!C19+4)-'DCF Model'!C16)*1000000/'DCF Model'!C15,0),"") -> 395 | H24: =IFERROR(ROUND(('DCF Model'!C45/(1+$B24)^('DCF Model'!C19+0)+'DCF Model'!D45/(1+$B24)^('DCF Model'!C19+1)+'DCF Model'!E45/(1+$B24)^('DCF Model'!C19+2)+'DCF Model'!F45/(1+$B24)^('DCF Model'!C19+3)+'DCF Model'!G45/(1+$B24)^('DCF Model'!C19+4)+('DCF Model'!G39+'DCF Model'!G42)*H$17/(1+$B24)^('DCF Model'!C19+4)-'DCF Model'!C16)*1000000/'DCF Model'!C15,0),"") -> 435 | I24: =IFERROR(ROUND(('DCF Model'!C45/(1+$B24)^('DCF Model'!C19+0)+'DCF Model'!D45/(1+$B24)^('DCF Model'!C19+1)+'DCF Model'!E45/(1+$B24)^('DCF Model'!C19+2)+'DCF Model'!F45/(1+$B24)^('DCF Model'!C19+3)+'DCF Model'!G45/(1+$B24)^('DCF Model'!C19+4)+('DCF Model'!G39+'DCF Model'!G42)*I$17/(1+$B24)^('DCF Model'!C19+4)-'DCF Model'!C16)*1000000/'DCF Model'!C15,0),"") -> 474
B26: All values dynamically linked to DCF Model. Headers auto-center on current WACC / Terminal g / Exit Multiple.

Sheet Adjustments Log
B2: Adjustments Log - 株式会社セブン銀行
B4: 日付 | C4: セル | D4: 変更内容 | E4: 理由 | F4: 元の値 | G4: 状態
B5: 2026-09-06 | C5: - | D5: Generated by pipeline on 2026-09-06 23:13, template rev 041abe3 | E5: 初期生成（手修正なし） | F5: - | G5: generated
B6: 2026-09-06 | C6: DCF Model!C8 | D6: Beta = 0.626（採用値） | E6: 実測β(raw) = 0.442 → Blume調整 0.67×raw + 0.33×1.00 = 0.626 → 採用 0.626。クランプ域 [0.3, 2.0] の内側。置換なし。回帰βは平均回帰するため Blume 調整を既定とする（2026-09-05 バッチで85件中57件が旧下限 0.60 に張り付き、両裾の歪みが実証された）。 | F6: 実測 0.442 | G6: 確定
B12: Pipeline Metadata (do not edit — read by scripts/validate_output.py)
B13: key | C13: value
B14: annual_doc_ids | C14: 2026-03-31=S100YC1N, 2025-03-31=S100VY5C, 2024-03-31=S100TMDS, 2023-03-31=S100QYPL, 2022-03-31=S100O9ZI
B15: auto_log_entries | C15: 1
B16: beta_adopted_c8 | C16: 0.6264
B17: beta_basis | C17: Blume: 0.67 x 0.442 + 0.33 x 1.00 = 0.626
B18: beta_blume_adjusted | C18: 0.6264
B19: beta_clamped | C19: no
B20: beta_raw | C20: 0.4424
B21: capex_pct_basis | C21: explicit_override
B22: capex_pct_c5 | C22: 0.155
B23: capex_pct_hist3yr | C23: 0.081029
B24: company_name | C24: 株式会社セブン銀行
... B28: comps_ev_ebitda_invalid | C28: yes
B29: comps_ev_ebitda_rows
B30: comps_impl_mult_row | C30: 27
B31: comps_impl_per_row | C31: 28
B32: comps_peer_rows | C32: 6,7,8
B33: comps_per_excluded | C33: no
B34: comps_stale_excluded | C34: none
B35: comps_stat_median_row | C35: 16
B36: comps_subject_row | C36: 5
B37: core_ebitda | C37: 60751
B38: core_net_income | C38: 13476
B39: cost_of_debt_at_c11 | C39: 0.01
B40: cost_of_debt_basis | C40: assumption
B41: da_pct_basis | C41: explicit_override
... B62: ticker | C62: 8410.T

Sheet DDM
B2: DDM - 2-Stage Dividend Discount Model (PRIMARY METHOD - bank)
B3: Standard UFCF DCF does not apply to a bank (see 'DCF Model' sheet, used only as an auxiliary ATM-fee-franchise cross-check).
B5: Inputs
B6: Risk-Free Rate | C6: ='DCF Model'!C7 -> 0.0297
B7: Beta | C7: ='DCF Model'!C8 -> 0.6264
B8: Equity Risk Premium | C8: ='DCF Model'!C9 -> 0.065
B9: Cost of Equity (Ke) | C9: ='DCF Model'!C23 -> 0.080416
B10: Shares Outstanding | C10: ='DCF Model'!C15 -> 1167997856
B11: Current Price (JPY) | C11: ='Executive Summary'!C9 -> 340
B12: Terminal Growth (g) | C12: 0.01
B14: Guard (Ke must exceed g) | C14: =IF($C$9<=$C$12,"ERROR: Ke <= g, model invalid","OK") -> OK
B16: Dividend per Share Forecast (Base scenario)
C17: FY2027(E) | D17: FY2028(E) | E17: FY2029(E) | F17: FY2030(E) | G17: FY2031(E)
B18: DPS (JPY) | C18: 11 | D18: 11.5 | E18: 12 | F18: 12.5 | G18: 13 | H18: FY2027(E)=11.00 は会社の配当予想(FY2026/3 実績横ばい)。2026年7月版と同一の配当経路を維持している。
B19: Discount Factor | C19: =1/(1+$C$9)^1 -> 0.92556941 | D19: =1/(1+$C$9)^2 -> 0.85667873 | E19: =1/(1+$C$9)^3 -> 0.79291563 | F19: =1/(1+$C$9)^4 -> 0.73389845 | G19: =1/(1+$C$9)^5 -> 0.67927396
B20: PV of DPS | C20: =C18*C19 -> 10.181264 | D20: =D18*D19 -> 9.8518054 | E20: =E18*E19 -> 9.5149876 | F20: =F18*F19 -> 9.1737307 | G20: =G18*G19 -> 8.8305614
B22: Valuation
B23: Sum of PV of DPS (Yr 1-5) | C23: =SUM(C20:G20) -> 47.552349
B24: Terminal Value (Yr 5) | C24: =G18*(1+$C$12)/($C$9-$C$12) -> 186.4633
B25: PV of Terminal Value | C25: =C24*G19 -> 126.65967
B26: Implied Value per Share (JPY) | C26: =ROUND(C23+C25,0) -> 174
B27: Upside / (Downside) vs Current Price | C27: =C26/$C$11-1 -> -0.48823529
B29: Sensitivity: Ke (rows) x Terminal g (cols)
B30: Ke \ g | C30: 0 | D30: 0.0025 | E30: 0.005 | F30: 0.0075 | G30: 0.01 | H30: 0.0125 | I30: 0.015 | J30: 0.0175 | K30: 0.02
B31: 0.07 | C31: =IF($B31<=C$30,"",ROUND(SUMPRODUCT($C$18:$G$18,1/(1+$B31)^{1,2,3,4,5})+G18*(1+C$30)/($B31-C$30)/(1+$B31)^5,0)) -> 181 | D31: =IF($B31<=D$30,"",ROUND(SUMPRODUCT($C$18:$G$18,1/(1+$B31)^{1,2,3,4,5})+G18*(1+D$30)/($B31-D$30)/(1+$B31)^5,0)) -> 187 | E31: =IF($B31<=E$30,"",ROUND(SUMPRODUCT($C$18:$G$18,1/(1+$B31)^{1,2,3,4,5})+G18*(1+E$30)/($B31-E$30)/(1+$B31)^5,0)) -> 192 | F31: =IF($B31<=F$30,"",ROUND(SUMPRODUCT($C$18:$G$18,1/(1+$B31)^{1,2,3,4,5})+G18*(1+F$30)/($B31-F$30)/(1+$B31)^5,0)) -> 198 | G31: =IF($B31<=G$30,"",ROUND(SUMPRODUCT($C$18:$G$18,1/(1+$B31)^{1,2,3,4,5})+G18*(1+G$30)/($B31-G$30)/(1+$B31)^5,0)) -> 205 | H31: =IF($B31<=H$30,"",ROUND(SUMPRODUCT($C$18:$G$18,1/(1+$B31)^{1,2,3,4,5})+G18*(1+H$30)/($B31-H$30)/(1+$B31)^5,0)) -> 212 | I31: =IF($B31<=I$30,"",ROUND(SUMPRODUCT($C$18:$G$18,1/(1+$B31)^{1,2,3,4,5})+G18*(1+I$30)/($B31-I$30)/(1+$B31)^5,0)) -> 220 | J31: =IF($B31<=J$30,"",ROUND(SUMPRODUCT($C$18:$G$18,1/(1+$B31)^{1,2,3,4,5})+G18*(1+J$30)/($B31-J$30)/(1+$B31)^5,0)) -> 229 | K31: =IF($B31<=K$30,"",ROUND(SUMPRODUCT($C$18:$G$18,1/(1+$B31)^{1,2,3,4,5})+G18*(1+K$30)/($B31-K$30)/(1+$B31)^5,0)) -> 238
B32: 0.0725 | C32: =IF($B32<=C$30,"",ROUND(SUMPRODUCT($C$18:$G$18,1/(1+$B32)^{1,2,3,4,5})+G18*(1+C$30)/($B32-C$30)/(1+$B32)^5,0)) -> 175 | D32: =IF($B32<=D$30,"",ROUND(SUMPRODUCT($C$18:$G$18,1/(1+$B32)^{1,2,3,4,5})+G18*(1+D$30)/($B32-D$30)/(1+$B32)^5,0)) -> 180 | E32: =IF($B32<=E$30,"",ROUND(SUMPRODUCT($C$18:$G$18,1/(1+$B32)^{1,2,3,4,5})+G18*(1+E$30)/($B32-E$30)/(1+$B32)^5,0)) -> 185 | F32: =IF($B32<=F$30,"",ROUND(SUMPRODUCT($C$18:$G$18,1/(1+$B32)^{1,2,3,4,5})+G18*(1+F$30)/($B32-F$30)/(1+$B32)^5,0)) -> 191 | G32: =IF($B32<=G$30,"",ROUND(SUMPRODUCT($C$18:$G$18,1/(1+$B32)^{1,2,3,4,5})+G18*(1+G$30)/($B32-G$30)/(1+$B32)^5,0)) -> 197 | H32: =IF($B32<=H$30,"",ROUND(SUMPRODUCT($C$18:$G$18,1/(1+$B32)^{1,2,3,4,5})+G18*(1+H$30)/($B32-H$30)/(1+$B32)^5,0)) -> 203 | I32: =IF($B32<=I$30,"",ROUND(SUMPRODUCT($C$18:$G$18,1/(1+$B32)^{1,2,3,4,5})+G18*(1+I$30)/($B32-I$30)/(1+$B32)^5,0)) -> 210 | J32: =IF($B32<=J$30,"",ROUND(SUMPRODUCT($C$18:$G$18,1/(1+$B32)^{1,2,3,4,5})+G18*(1+J$30)/($B32-J$30)/(1+$B32)^5,0)) -> 218 | K32: =IF($B32<=K$30,"",ROUND(SUMPRODUCT($C$18:$G$18,1/(1+$B32)^{1,2,3,4,5})+G18*(1+K$30)/($B32-K$30)/(1+$B32)^5,0)) -> 227
B33: 0.075 | C33: =IF($B33<=C$30,"",ROUND(SUMPRODUCT($C$18:$G$18,1/(1+$B33)^{1,2,3,4,5})+G18*(1+C$30)/($B33-C$30)/(1+$B33)^5,0)) -> 169 | D33: =IF($B33<=D$30,"",ROUND(SUMPRODUCT($C$18:$G$18,1/(1+$B33)^{1,2,3,4,5})+G18*(1+D$30)/($B33-D$30)/(1+$B33)^5,0)) -> 173 | E33: =IF($B33<=E$30,"",ROUND(SUMPRODUCT($C$18:$G$18,1/(1+$B33)^{1,2,3,4,5})+G18*(1+E$30)/($B33-E$30)/(1+$B33)^5,0)) -> 178 | F33: =IF($B33<=F$30,"",ROUND(SUMPRODUCT($C$18:$G$18,1/(1+$B33)^{1,2,3,4,5})+G18*(1+F$30)/($B33-F$30)/(1+$B33)^5,0)) -> 183 | G33: =IF($B33<=G$30,"",ROUND(SUMPRODUCT($C$18:$G$18,1/(1+$B33)^{1,2,3,4,5})+G18*(1+G$30)/($B33-G$30)/(1+$B33)^5,0)) -> 189 | H33: =IF($B33<=H$30,"",ROUND(SUMPRODUCT($C$18:$G$18,1/(1+$B33)^{1,2,3,4,5})+G18*(1+H$30)/($B33-H$30)/(1+$B33)^5,0)) -> 195 | I33: =IF($B33<=I$30,"",ROUND(SUMPRODUCT($C$18:$G$18,1/(1+$B33)^{1,2,3,4,5})+G18*(1+I$30)/($B33-I$30)/(1+$B33)^5,0)) -> 201 | J33: =IF($B33<=J$30,"",ROUND(SUMPRODUCT($C$18:$G$18,1/(1+$B33)^{1,2,3,4,5})+G18*(1+J$30)/($B33-J$30)/(1+$B33)^5,0)) -> 208 | K33: =IF($B33<=K$30,"",ROUND(SUMPRODUCT($C$18:$G$18,1/(1+$B33)^{1,2,3,4,5})+G18*(1+K$30)/($B33-K$30)/(1+$B33)^5,0)) -> 216
B34: 0.0775 | C34: =IF($B34<=C$30,"",ROUND(SUMPRODUCT($C$18:$G$18,1/(1+$B34)^{1,2,3,4,5})+G18*(1+C$30)/($B34-C$30)/(1+$B34)^5,0)) -> 163 | D34: =IF($B34<=D$30,"",ROUND(SUMPRODUCT($C$18:$G$18,1/(1+$B34)^{1,2,3,4,5})+G18*(1+D$30)/($B34-D$30)/(1+$B34)^5,0)) -> 168 | E34: =IF($B34<=E$30,"",ROUND(SUMPRODUCT($C$18:$G$18,1/(1+$B34)^{1,2,3,4,5})+G18*(1+E$30)/($B34-E$30)/(1+$B34)^5,0)) -> 172 | F34: =IF($B34<=F$30,"",ROUND(SUMPRODUCT($C$18:$G$18,1/(1+$B34)^{1,2,3,4,5})+G18*(1+F$30)/($B34-F$30)/(1+$B34)^5,0)) -> 177 | G34: =IF($B34<=G$30,"",ROUND(SUMPRODUCT($C$18:$G$18,1/(1+$B34)^{1,2,3,4,5})+G18*(1+G$30)/($B34-G$30)/(1+$B34)^5,0)) -> 182 | H34: =IF($B34<=H$30,"",ROUND(SUMPRODUCT($C$18:$G$18,1/(1+$B34)^{1,2,3,4,5})+G18*(1+H$30)/($B34-H$30)/(1+$B34)^5,0)) -> 187 | I34: =IF($B34<=I$30,"",ROUND(SUMPRODUCT($C$18:$G$18,1/(1+$B34)^{1,2,3,4,5})+G18*(1+I$30)/($B34-I$30)/(1+$B34)^5,0)) -> 193 | J34: =IF($B34<=J$30,"",ROUND(SUMPRODUCT($C$18:$G$18,1/(1+$B34)^{1,2,3,4,5})+G18*(1+J$30)/($B34-J$30)/(1+$B34)^5,0)) -> 200 | K34: =IF($B34<=K$30,"",ROUND(SUMPRODUCT($C$18:$G$18,1/(1+$B34)^{1,2,3,4,5})+G18*(1+K$30)/($B34-K$30)/(1+$B34)^5,0)) -> 207
B35: 0.08 | C35: =IF($B35<=C$30,"",ROUND(SUMPRODUCT($C$18:$G$18,1/(1+$B35)^{1,2,3,4,5})+G18*(1+C$30)/($B35-C$30)/(1+$B35)^5,0)) -> 158 | D35: =IF($B35<=D$30,"",ROUND(SUMPRODUCT($C$18:$G$18,1/(1+$B35)^{1,2,3,4,5})+G18*(1+D$30)/($B35-D$30)/(1+$B35)^5,0)) -> 162 | E35: =IF($B35<=E$30,"",ROUND(SUMPRODUCT($C$18:$G$18,1/(1+$B35)^{1,2,3,4,5})+G18*(1+E$30)/($B35-E$30)/(1+$B35)^5,0)) -> 166 | F35: =IF($B35<=F$30,"",ROUND(SUMPRODUCT($C$18:$G$18,1/(1+$B35)^{1,2,3,4,5})+G18*(1+F$30)/($B35-F$30)/(1+$B35)^5,0)) -> 171 | G35: =IF($B35<=G$30,"",ROUND(SUMPRODUCT($C$18:$G$18,1/(1+$B35)^{1,2,3,4,5})+G18*(1+G$30)/($B35-G$30)/(1+$B35)^5,0)) -> 175 | H35: =IF($B35<=H$30,"",ROUND(SUMPRODUCT($C$18:$G$18,1/(1+$B35)^{1,2,3,4,5})+G18*(1+H$30)/($B35-H$30)/(1+$B35)^5,0)) -> 180 | I35: =IF($B35<=I$30,"",ROUND(SUMPRODUCT($C$18:$G$18,1/(1+$B35)^{1,2,3,4,5})+G18*(1+I$30)/($B35-I$30)/(1+$B35)^5,0)) -> 186 | J35: =IF($B35<=J$30,"",ROUND(SUMPRODUCT($C$18:$G$18,1/(1+$B35)^{1,2,3,4,5})+G18*(1+J$30)/($B35-J$30)/(1+$B35)^5,0)) -> 192 | K35: =IF($B35<=K$30,"",ROUND(SUMPRODUCT($C$18:$G$18,1/(1+$B35)^{1,2,3,4,5})+G18*(1+K$30)/($B35-K$30)/(1+$B35)^5,0)) -> 198
B36: 0.0825 | C36: =IF($B36<=C$30,"",ROUND(SUMPRODUCT($C$18:$G$18,1/(1+$B36)^{1,2,3,4,5})+G18*(1+C$30)/($B36-C$30)/(1+$B36)^5,0)) -> 153 | D36: =IF($B36<=D$30,"",ROUND(SUMPRODUCT($C$18:$G$18,1/(1+$B36)^{1,2,3,4,5})+G18*(1+D$30)/($B36-D$30)/(1+$B36)^5,0)) -> 157 | E36: =IF($B36<=E$30,"",ROUND(SUMPRODUCT($C$18:$G$18,1/(1+$B36)^{1,2,3,4,5})+G18*(1+E$30)/($B36-E$30)/(1+$B36)^5,0)) -> 161 | F36: =IF($B36<=F$30,"",ROUND(SUMPRODUCT($C$18:$G$18,1/(1+$B36)^{1,2,3,4,5})+G18*(1+F$30)/($B36-F$30)/(1+$B36)^5,0)) -> 165 | G36: =IF($B36<=G$30,"",ROUND(SUMPRODUCT($C$18:$G$18,1/(1+$B36)^{1,2,3,4,5})+G18*(1+G$30)/($B36-G$30)/(1+$B36)^5,0)) -> 169 | H36: =IF($B36<=H$30,"",ROUND(SUMPRODUCT($C$18:$G$18,1/(1+$B36)^{1,2,3,4,5})+G18*(1+H$30)/($B36-H$30)/(1+$B36)^5,0)) -> 174 | I36: =IF($B36<=I$30,"",ROUND(SUMPRODUCT($C$18:$G$18,1/(1+$B36)^{1,2,3,4,5})+G18*(1+I$30)/($B36-I$30)/(1+$B36)^5,0)) -> 179 | J36: =IF($B36<=J$30,"",ROUND(SUMPRODUCT($C$18:$G$18,1/(1+$B36)^{1,2,3,4,5})+G18*(1+J$30)/($B36-J$30)/(1+$B36)^5,0)) -> 184 | K36: =IF($B36<=K$30,"",ROUND(SUMPRODUCT($C$18:$G$18,1/(1+$B36)^{1,2,3,4,5})+G18*(1+K$30)/($B36-K$30)/(1+$B36)^5,0)) -> 190
B37: 0.085 | C37: =IF($B37<=C$30,"",ROUND(SUMPRODUCT($C$18:$G$18,1/(1+$B37)^{1,2,3,4,5})+G18*(1+C$30)/($B37-C$30)/(1+$B37)^5,0)) -> 149 | D37: =IF($B37<=D$30,"",ROUND(SUMPRODUCT($C$18:$G$18,1/(1+$B37)^{1,2,3,4,5})+G18*(1+D$30)/($B37-D$30)/(1+$B37)^5,0)) -> 152 | E37: =IF($B37<=E$30,"",ROUND(SUMPRODUCT($C$18:$G$18,1/(1+$B37)^{1,2,3,4,5})+G18*(1+E$30)/($B37-E$30)/(1+$B37)^5,0)) -> 156 | F37: =IF($B37<=F$30,"",ROUND(SUMPRODUCT($C$18:$G$18,1/(1+$B37)^{1,2,3,4,5})+G18*(1+F$30)/($B37-F$30)/(1+$B37)^5,0)) -> 159 | G37: =IF($B37<=G$30,"",ROUND(SUMPRODUCT($C$18:$G$18,1/(1+$B37)^{1,2,3,4,5})+G18*(1+G$30)/($B37-G$30)/(1+$B37)^5,0)) -> 163 | H37: =IF($B37<=H$30,"",ROUND(SUMPRODUCT($C$18:$G$18,1/(1+$B37)^{1,2,3,4,5})+G18*(1+H$30)/($B37-H$30)/(1+$B37)^5,0)) -> 168 | I37: =IF($B37<=I$30,"",ROUND(SUMPRODUCT($C$18:$G$18,1/(1+$B37)^{1,2,3,4,5})+G18*(1+I$30)/($B37-I$30)/(1+$B37)^5,0)) -> 172 | J37: =IF($B37<=J$30,"",ROUND(SUMPRODUCT($C$18:$G$18,1/(1+$B37)^{1,2,3,4,5})+G18*(1+J$30)/($B37-J$30)/(1+$B37)^5,0)) -> 177 | K37: =IF($B37<=K$30,"",ROUND(SUMPRODUCT($C$18:$G$18,1/(1+$B37)^{1,2,3,4,5})+G18*(1+K$30)/($B37-K$30)/(1+$B37)^5,0)) -> 183
B38: 0.0875 | C38: =IF($B38<=C$30,"",ROUND(SUMPRODUCT($C$18:$G$18,1/(1+$B38)^{1,2,3,4,5})+G18*(1+C$30)/($B38-C$30)/(1+$B38)^5,0)) -> 144 | D38: =IF($B38<=D$30,"",ROUND(SUMPRODUCT($C$18:$G$18,1/(1+$B38)^{1,2,3,4,5})+G18*(1+D$30)/($B38-D$30)/(1+$B38)^5,0)) -> 147 | E38: =IF($B38<=E$30,"",ROUND(SUMPRODUCT($C$18:$G$18,1/(1+$B38)^{1,2,3,4,5})+G18*(1+E$30)/($B38-E$30)/(1+$B38)^5,0)) -> 151 | F38: =IF($B38<=F$30,"",ROUND(SUMPRODUCT($C$18:$G$18,1/(1+$B38)^{1,2,3,4,5})+G18*(1+F$30)/($B38-F$30)/(1+$B38)^5,0)) -> 154 | G38: =IF($B38<=G$30,"",ROUND(SUMPRODUCT($C$18:$G$18,1/(1+$B38)^{1,2,3,4,5})+G18*(1+G$30)/($B38-G$30)/(1+$B38)^5,0)) -> 158 | H38: =IF($B38<=H$30,"",ROUND(SUMPRODUCT($C$18:$G$18,1/(1+$B38)^{1,2,3,4,5})+G18*(1+H$30)/($B38-H$30)/(1+$B38)^5,0)) -> 162 | I38: =IF($B38<=I$30,"",ROUND(SUMPRODUCT($C$18:$G$18,1/(1+$B38)^{1,2,3,4,5})+G18*(1+I$30)/($B38-I$30)/(1+$B38)^5,0)) -> 166 | J38: =IF($B38<=J$30,"",ROUND(SUMPRODUCT($C$18:$G$18,1/(1+$B38)^{1,2,3,4,5})+G18*(1+J$30)/($B38-J$30)/(1+$B38)^5,0)) -> 171 | K38: =IF($B38<=K$30,"",ROUND(SUMPRODUCT($C$18:$G$18,1/(1+$B38)^{1,2,3,4,5})+G18*(1+K$30)/($B38-K$30)/(1+$B38)^5,0)) -> 176
B39: 0.09 | C39: =IF($B39<=C$30,"",ROUND(SUMPRODUCT($C$18:$G$18,1/(1+$B39)^{1,2,3,4,5})+G18*(1+C$30)/($B39-C$30)/(1+$B39)^5,0)) -> 140 | D39: =IF($B39<=D$30,"",ROUND(SUMPRODUCT($C$18:$G$18,1/(1+$B39)^{1,2,3,4,5})+G18*(1+D$30)/($B39-D$30)/(1+$B39)^5,0)) -> 143 | E39: =IF($B39<=E$30,"",ROUND(SUMPRODUCT($C$18:$G$18,1/(1+$B39)^{1,2,3,4,5})+G18*(1+E$30)/($B39-E$30)/(1+$B39)^5,0)) -> 146 | F39: =IF($B39<=F$30,"",ROUND(SUMPRODUCT($C$18:$G$18,1/(1+$B39)^{1,2,3,4,5})+G18*(1+F$30)/($B39-F$30)/(1+$B39)^5,0)) -> 150 | G39: =IF($B39<=G$30,"",ROUND(SUMPRODUCT($C$18:$G$18,1/(1+$B39)^{1,2,3,4,5})+G18*(1+G$30)/($B39-G$30)/(1+$B39)^5,0)) -> 153 | H39: =IF($B39<=H$30,"",ROUND(SUMPRODUCT($C$18:$G$18,1/(1+$B39)^{1,2,3,4,5})+G18*(1+H$30)/($B39-H$30)/(1+$B39)^5,0)) -> 157 | I39: =IF($B39<=I$30,"",ROUND(SUMPRODUCT($C$18:$G$18,1/(1+$B39)^{1,2,3,4,5})+G18*(1+I$30)/($B39-I$30)/(1+$B39)^5,0)) -> 161 | J39: =IF($B39<=J$30,"",ROUND(SUMPRODUCT($C$18:$G$18,1/(1+$B39)^{1,2,3,4,5})+G18*(1+J$30)/($B39-J$30)/(1+$B39)^5,0)) -> 165 | K39: =IF($B39<=K$30,"",ROUND(SUMPRODUCT($C$18:$G$18,1/(1+$B39)^{1,2,3,4,5})+G18*(1+K$30)/($B39-K$30)/(1+$B39)^5,0)) -> 169

Sheet Residual Income
B2: Residual Income Model (PRIMARY METHOD - bank)
B3: Value = Book Value + PV(Residual Income). When ROE approaches Ke, value converges to book value.
B5: Inputs
B6: Beginning Book Value (JPY mn) | C6: 280498
B7: Shares Outstanding | C7: =DDM!C$10 -> 1167997856
B8: BPS_0 (JPY) | C8: =C6/C7*1000000 -> 240.15284
B9: Cost of Equity (Ke) | C9: =DDM!C$9 -> 0.080416
B10: Terminal Growth (g) | C10: =DDM!C$12 -> 0.01
B12: ROE Forecast (Base scenario)
C13: FY2027(E) | D13: FY2028(E) | E13: FY2029(E) | F13: FY2030(E) | G13: FY2031(E)
B14: ROE | C14: 0.061 | D14: 0.065 | E14: 0.068 | F14: 0.07 | G14: 0.07 | H14: FY2027(E)=6.1% = 会社の純利益予想 17,000 ÷ 期首自己資本 280,498。2026年7月版と同一の ROE 経路。
B16: Book Value Rollforward (JPY mn)
C17: FY2027(E) | D17: FY2028(E) | E17: FY2029(E) | F17: FY2030(E) | G17: FY2031(E)
B18: Net Income_t = ROE_t x BV_(t-1) | C18: =C14*$C$6 -> 17110.378 | D18: =D14*C20 -> 18509.426 | E18: =E14*D20 -> 19708.974 | F18: =F14*E20 -> 20687.16 | G18: =G14*F20 -> 21113.263
B19: Dividends_t (from DDM) | C19: =DDM!C18*C7/1000000 -> 12847.976 | D19: =DDM!D18*C7/1000000 -> 13431.975 | E19: =DDM!E18*C7/1000000 -> 14015.974 | F19: =DDM!F18*C7/1000000 -> 14599.973 | G19: =DDM!G18*C7/1000000 -> 15183.972
B20: Ending Book Value | C20: =$C$6+C18-C19 -> 284760.4 | D20: =C20+D18-D19 -> 289837.85 | E20: =D20+E18-E19 -> 295530.85 | F20: =E20+F18-F19 -> 301618.04 | G20: =F20+G18-G19 -> 307547.33
B21: Residual Income_t = (ROE_t - Ke) x BV_(t-1) | C21: =(C14-$C$9)*$C$6 -> -5446.1492 | D21: =(D14-$C$9)*C20 -> -4389.8664 | E21: =(E14-$C$9)*D20 -> -3598.6268 | F21: =(F14-$C$9)*E20 -> -3078.2494 | G21: =(G14-$C$9)*F20 -> -3141.6535
B22: PV of Residual Income | C22: =C21/(1+$C$9)^1 -> -5040.7891 | D22: =D21/(1+$C$9)^2 -> -3760.7051 | E22: =E21/(1+$C$9)^3 -> -2853.4074 | F22: =F21/(1+$C$9)^4 -> -2259.1224 | G22: =G21/(1+$C$9)^5 -> -2134.0434
B24: Valuation
B25: Sum of PV of Residual Income | C25: =SUM(C22:G22) -> -16048.067
B26: Terminal Residual Income | C26: =G21*(1+$C$10)/($C$9-$C$10) -> -45061.776
B27: PV of Terminal Residual Income | C27: =C26/(1+$C$9)^5 -> -30609.291
B28: Equity Value (JPY mn) | C28: =C6+C25+C27 -> 233840.64
B29: Implied Value per Share (JPY) | C29: =ROUND(C28/C7*1000000,0) -> 200
B30: Upside / (Downside) vs Current Price | C30: =C29/DDM!C$11-1 -> -0.41176471
B32: Note: ROE sits close to Ke, so Residual Income per year is small and the implied value sits close to BPS_0 -- the theoretical price is structurally anchored to book value, not to growth assumptions. Whether ROE durably exceeds Ke is the entire valuation question for this stock.
B34: Justified P/B = (ROE - g) / (Ke - g)
B35: ROE \ Ke | C35: 0.07 | D35: 0.075 | E35: 0.08 | F35: 0.085 | G35: 0.09
B36: 0.045 | C36: =IF(C$35<=$C$10,"",ROUND(($B36-$C$10)/(C$35-$C$10),2)) -> 0.58 | D36: =IF(D$35<=$C$10,"",ROUND(($B36-$C$10)/(D$35-$C$10),2)) -> 0.54 | E36: =IF(E$35<=$C$10,"",ROUND(($B36-$C$10)/(E$35-$C$10),2)) -> 0.5 | F36: =IF(F$35<=$C$10,"",ROUND(($B36-$C$10)/(F$35-$C$10),2)) -> 0.47 | G36: =IF(G$35<=$C$10,"",ROUND(($B36-$C$10)/(G$35-$C$10),2)) -> 0.44
B37: 0.05 | C37: =IF(C$35<=$C$10,"",ROUND(($B37-$C$10)/(C$35-$C$10),2)) -> 0.67 | D37: =IF(D$35<=$C$10,"",ROUND(($B37-$C$10)/(D$35-$C$10),2)) -> 0.62 | E37: =IF(E$35<=$C$10,"",ROUND(($B37-$C$10)/(E$35-$C$10),2)) -> 0.57 | F37: =IF(F$35<=$C$10,"",ROUND(($B37-$C$10)/(F$35-$C$10),2)) -> 0.53 | G37: =IF(G$35<=$C$10,"",ROUND(($B37-$C$10)/(G$35-$C$10),2)) -> 0.5
B38: 0.055 | C38: =IF(C$35<=$C$10,"",ROUND(($B38-$C$10)/(C$35-$C$10),2)) -> 0.75 | D38: =IF(D$35<=$C$10,"",ROUND(($B38-$C$10)/(D$35-$C$10),2)) -> 0.69 | E38: =IF(E$35<=$C$10,"",ROUND(($B38-$C$10)/(E$35-$C$10),2)) -> 0.64 | F38: =IF(F$35<=$C$10,"",ROUND(($B38-$C$10)/(F$35-$C$10),2)) -> 0.6 | G38: =IF(G$35<=$C$10,"",ROUND(($B38-$C$10)/(G$35-$C$10),2)) -> 0.56
B39: 0.06 | C39: =IF(C$35<=$C$10,"",ROUND(($B39-$C$10)/(C$35-$C$10),2)) -> 0.83 | D39: =IF(D$35<=$C$10,"",ROUND(($B39-$C$10)/(D$35-$C$10),2)) -> 0.77 | E39: =IF(E$35<=$C$10,"",ROUND(($B39-$C$10)/(E$35-$C$10),2)) -> 0.71 | F39: =IF(F$35<=$C$10,"",ROUND(($B39-$C$10)/(F$35-$C$10),2)) -> 0.67 | G39: =IF(G$35<=$C$10,"",ROUND(($B39-$C$10)/(G$35-$C$10),2)) -> 0.63
B40: 0.065 | C40: =IF(C$35<=$C$10,"",ROUND(($B40-$C$10)/(C$35-$C$10),2)) -> 0.92 | D40: =IF(D$35<=$C$10,"",ROUND(($B40-$C$10)/(D$35-$C$10),2)) -> 0.85 | E40: =IF(E$35<=$C$10,"",ROUND(($B40-$C$10)/(E$35-$C$10),2)) -> 0.79 | F40: =IF(F$35<=$C$10,"",ROUND(($B40-$C$10)/(F$35-$C$10),2)) -> 0.73 | G40: =IF(G$35<=$C$10,"",ROUND(($B40-$C$10)/(G$35-$C$10),2)) -> 0.69
B41: 0.07 | C41: =IF(C$35<=$C$10,"",ROUND(($B41-$C$10)/(C$35-$C$10),2)) -> 1 | D41: =IF(D$35<=$C$10,"",ROUND(($B41-$C$10)/(D$35-$C$10),2)) -> 0.92 | E41: =IF(E$35<=$C$10,"",ROUND(($B41-$C$10)/(E$35-$C$10),2)) -> 0.86 | F41: =IF(F$35<=$C$10,"",ROUND(($B41-$C$10)/(F$35-$C$10),2)) -> 0.8 | G41: =IF(G$35<=$C$10,"",ROUND(($B41-$C$10)/(G$35-$C$10),2)) -> 0.75
B42: 0.075 | C42: =IF(C$35<=$C$10,"",ROUND(($B42-$C$10)/(C$35-$C$10),2)) -> 1.08 | D42: =IF(D$35<=$C$10,"",ROUND(($B42-$C$10)/(D$35-$C$10),2)) -> 1 | E42: =IF(E$35<=$C$10,"",ROUND(($B42-$C$10)/(E$35-$C$10),2)) -> 0.93 | F42: =IF(F$35<=$C$10,"",ROUND(($B42-$C$10)/(F$35-$C$10),2)) -> 0.87 | G42: =IF(G$35<=$C$10,"",ROUND(($B42-$C$10)/(G$35-$C$10),2)) -> 0.81
B43: 0.08 | C43: =IF(C$35<=$C$10,"",ROUND(($B43-$C$10)/(C$35-$C$10),2)) -> 1.17 | D43: =IF(D$35<=$C$10,"",ROUND(($B43-$C$10)/(D$35-$C$10),2)) -> 1.08 | E43: =IF(E$35<=$C$10,"",ROUND(($B43-$C$10)/(E$35-$C$10),2)) -> 1 | F43: =IF(F$35<=$C$10,"",ROUND(($B43-$C$10)/(F$35-$C$10),2)) -> 0.93 | G43: =IF(G$35<=$C$10,"",ROUND(($B43-$C$10)/(G$35-$C$10),2)) -> 0.88
B44: 0.085 | C44: =IF(C$35<=$C$10,"",ROUND(($B44-$C$10)/(C$35-$C$10),2)) -> 1.25 | D44: =IF(D$35<=$C$10,"",ROUND(($B44-$C$10)/(D$35-$C$10),2)) -> 1.15 | E44: =IF(E$35<=$C$10,"",ROUND(($B44-$C$10)/(E$35-$C$10),2)) -> 1.07 | F44: =IF(F$35<=$C$10,"",ROUND(($B44-$C$10)/(F$35-$C$10),2)) -> 1 | G44: =IF(G$35<=$C$10,"",ROUND(($B44-$C$10)/(G$35-$C$10),2)) -> 0.94
B46: Implied Share Price at each (ROE, Ke) node = BPS_0 x Justified P/B (JPY)
B47: ROE \ Ke | C47: 0.07 | D47: 0.075 | E47: 0.08 | F47: 0.085 | G47: 0.09
B48: 0.045 | C48: =IF(C36="","",ROUND(C36*$C$8,0)) -> 139 | D48: =IF(D36="","",ROUND(D36*$C$8,0)) -> 130 | E48: =IF(E36="","",ROUND(E36*$C$8,0)) -> 120 | F48: =IF(F36="","",ROUND(F36*$C$8,0)) -> 113 | G48: =IF(G36="","",ROUND(G36*$C$8,0)) -> 106
B49: 0.05 | C49: =IF(C37="","",ROUND(C37*$C$8,0)) -> 161 | D49: =IF(D37="","",ROUND(D37*$C$8,0)) -> 149 | E49: =IF(E37="","",ROUND(E37*$C$8,0)) -> 137 | F49: =IF(F37="","",ROUND(F37*$C$8,0)) -> 127 | G49: =IF(G37="","",ROUND(G37*$C$8,0)) -> 120
B50: 0.055 | C50: =IF(C38="","",ROUND(C38*$C$8,0)) -> 180 | D50: =IF(D38="","",ROUND(D38*$C$8,0)) -> 166 | E50: =IF(E38="","",ROUND(E38*$C$8,0)) -> 154 | F50: =IF(F38="","",ROUND(F38*$C$8,0)) -> 144 | G50: =IF(G38="","",ROUND(G38*$C$8,0)) -> 134
B51: 0.06 | C51: =IF(C39="","",ROUND(C39*$C$8,0)) -> 199 | D51: =IF(D39="","",ROUND(D39*$C$8,0)) -> 185 | E51: =IF(E39="","",ROUND(E39*$C$8,0)) -> 171 | F51: =IF(F39="","",ROUND(F39*$C$8,0)) -> 161 | G51: =IF(G39="","",ROUND(G39*$C$8,0)) -> 151
B52: 0.065 | C52: =IF(C40="","",ROUND(C40*$C$8,0)) -> 221 | D52: =IF(D40="","",ROUND(D40*$C$8,0)) -> 204 | E52: =IF(E40="","",ROUND(E40*$C$8,0)) -> 190 | F52: =IF(F40="","",ROUND(F40*$C$8,0)) -> 175 | G52: =IF(G40="","",ROUND(G40*$C$8,0)) -> 166
B53: 0.07 | C53: =IF(C41="","",ROUND(C41*$C$8,0)) -> 240 | D53: =IF(D41="","",ROUND(D41*$C$8,0)) -> 221 | E53: =IF(E41="","",ROUND(E41*$C$8,0)) -> 207 | F53: =IF(F41="","",ROUND(F41*$C$8,0)) -> 192 | G53: =IF(G41="","",ROUND(G41*$C$8,0)) -> 180
B54: 0.075 | C54: =IF(C42="","",ROUND(C42*$C$8,0)) -> 259 | D54: =IF(D42="","",ROUND(D42*$C$8,0)) -> 240 | E54: =IF(E42="","",ROUND(E42*$C$8,0)) -> 223 | F54: =IF(F42="","",ROUND(F42*$C$8,0)) -> 209 | G54: =IF(G42="","",ROUND(G42*$C$8,0)) -> 195
B55: 0.08 | C55: =IF(C43="","",ROUND(C43*$C$8,0)) -> 281 | D55: =IF(D43="","",ROUND(D43*$C$8,0)) -> 259 | E55: =IF(E43="","",ROUND(E43*$C$8,0)) -> 240 | F55: =IF(F43="","",ROUND(F43*$C$8,0)) -> 223 | G55: =IF(G43="","",ROUND(G43*$C$8,0)) -> 211
B56: 0.085 | C56: =IF(C44="","",ROUND(C44*$C$8,0)) -> 300 | D56: =IF(D44="","",ROUND(D44*$C$8,0)) -> 276 | E56: =IF(E44="","",ROUND(E44*$C$8,0)) -> 257 | F56: =IF(F44="","",ROUND(F44*$C$8,0)) -> 240 | G56: =IF(G44="","",ROUND(G44*$C$8,0)) -> 226
