Workbook

Sheet Cover & Thesis
B2: SOTP Valuation Model
B3: Valuation Date: September 2026
B5: Investment Thesis
B6: KDDI の連結BS は総資産の 37.5% が金融事業の貸出金・有価証券、負債の 29.7% が金融事業の預金である。連結 DCF は預金を有利子負債として扱ってしまうため成立しない。非金融(通信)を EV/EBITDA、金融(auフィナンシャルホールディングス、議決権100.0%)を PBR×純資産で評価し、SOTP で合算する。
B10: Valuation Cross-Check
B11: Method | C11: Fair Value (¥) | D11: vs SOTP Base
B12: SOTP (Base Case) | C12: ='SOTP Valuation'!C28 -> 2657.3462 | D12: —
B13: DCF - Perpetuity Growth | C13: 4628 | D13: =(C13-$C$12)/$C$12 -> 0.74158713
B14: DCF - Exit Multiple | C14: 3812 | D14: =(C14-$C$12)/$C$12 -> 0.43451386
B15: Comps - EV/EBITDA Median [参考・Target不算入] | C15: 3356 | D15: =(C15-$C$12)/$C$12 -> 0.26291409
B16: Comps - PER Median [参考・Target不算入] | C16: 3975 | D16: =(C16-$C$12)/$C$12 -> 0.49585325
B18: DCF cross-check as of 2026-09-07 01:32 from 9433_DCF_Model_20260906.xlsx (static snapshot — regenerate after re-running the DCF)

Sheet Segment Data
B1: Segment Financial Data
B2: (¥ millions)
B4: Segment | C4: FY2025.3 | D4: FY2026.3
B5: Telecom & Non-Financial (ex-au FH) (通信・非金融(auフィナンシャルHDを除く連結))
B6: Revenue | C6: 5567839 | D6: 5733007
B7: Operating Profit | C7: 1046821 | D7: 1055926
B8: OPM % | C8: =IF(C6=0,0,C7/C6) -> 0.18801208 | D8: =IF(D6=0,0,D7/D6) -> 0.18418362
B10: au Financial Holdings (100% owned) (auフィナンシャルホールディングス(議決権100.0%))
B11: Revenue | C11: 267686 | D11: 338907
B12: Operating Profit | C12: 40647 | D12: 43199
B13: OPM % | C13: =IF(C11=0,0,C12/C11) -> 0.15184582 | D13: =IF(D11=0,0,D12/D11) -> 0.12746565
B15: Consolidated Total
B16: Total Revenue | C16: =C6+C11 -> 5835525 | D16: =D6+D11 -> 6071914
B17: Total Operating Profit | C17: =C7+C12 -> 1087468 | D17: =D7+D12 -> 1099125
B18: Total OPM % | C18: =IF(C16=0,0,C17/C16) -> 0.18635307 | D18: =IF(D16=0,0,D17/D16) -> 0.18101788

Sheet Peer Comps
B1: Peer Comparable Analysis
B3: Telecom & Non-Financial (ex-au FH)
B4: Company | C4: Ticker | D4: EV/EBITDA | E4: OPM % | F4: Mkt Cap ($B) | G4: Note
B5: NTT, Inc. | C5: 9432.T | D5: 8.1 | E5: 0.124 | F5: 95 | G5: 自社パイプラインの 9432 モデル(20260906)の Comps Analysis 自社行より。
B6: SoftBank Corp. | C6: 9434.T | D6: 0 | E6: 0.1481 | F6: 78 | G6: PayPay銀行・PayPayカードを連結。本モデルが分離した金融事業が EV と EBITDA の双方に入るため統計から除外。加えて yfinance の EBITDA(1,039,656)が営業利益(1,042,576)を下回っており値自体が使えない。
B7: Okinawa Cellular | C7: 9436.T | D7: 15.13 | E7: 0.2165 | F7: 2.6 | G7: KDDI の 80.9% 子会社であり連結内。ピアとして独立していないため除外。
B8: Median | D8: =MEDIAN(D5) -> 8.1
B9: Selected Multiple | C9: 9432 NTT の EV/EBITDA 8.10x。9434 ソフトバンクは金融事業を連結しており倍率が汚染されるため除外。9436 沖縄セルラーは KDDI の 80.9% 子会社で連結内のためピアとして独立していない。 | D9: 8.1
B11: au Financial Holdings (100% owned)
B12: Company | C12: Ticker | D12: PBR (x) | E12: ROE % | F12: Mkt Cap ($B) | G12: Note
B13: Rakuten Bank | C13: 5838.T | D13: 2.952 | E13: 0.188 | F13: 7.9 | G13: デジタル銀行。グループ経済圏型で au じぶん銀行に最も近い。
B14: Seven Bank | C14: 8410.T | D14: 1.416 | E14: 0.048 | F14: 2.7 | G14: 流通系銀行。自社パイプラインの型D モデルあり。
B15: Japan Post Bank | C15: 7182.T | D15: 1.302 | E15: 0.057 | F15: 82 | G15: 規模は大きく異なるが国内リテール銀行の水準参照。
B16: AEON Financial Service | C16: 8570.T | D16: 0.737 | E16: 0.045 | F16: 2.4 | G16: 流通系金融持株会社。カード+銀行の複合という点で au FH に近い。
B17: Median | D17: =MEDIAN(D13,D14,D15,D16) -> 1.359
B18: Selected Multiple | C18: 上場デジタル/流通系銀行4社の PBR 中央値(2026-09-06 yfinance): 5838 楽天銀行 2.952 / 8410 セブン銀行 1.416 / 7182 ゆうちょ銀行 1.302 / 8570 イオンフィナンシャル 0.737 → 中央値 1.359。 | D18: 1.359

Sheet SOTP Valuation
B1: SOTP Valuation
B2: (¥ millions unless noted)
B4: Segment | C4: OP (FY25E) | D4: D&A Alloc % | E4: D&A | F4: EBITDA | G4: Multiple (x) | H4: Segment EV | I4: 金融セグメントは PBR × 純資産の【株主価値】。EV 列には合算せず、下の Equity Bridge で純有利子負債の控除後に加算する
B5: Telecom & Non-Financial (ex-au FH) | C5: ='Segment Data'!D7 -> 1055926 | D5: 1 | E5: =B10*D5 -> 679483 | F5: =C5+E5 -> 1735409 | G5: ='Peer Comps'!D9 -> 8.1 | H5: =F5*G5 -> 14056813
B6: au Financial Holdings (100% owned) | C6: 360081 | F6: =C6 -> 360081 | G6: ='Peer Comps'!D18 -> 1.359 | H6: =F6*G6 -> 489350.08 | I6: 純資産 × PBR = 株主価値 (EV ではない)
B7: Equity Method Investments | C7: 0 | F7: =C7 -> 0 | G7: 10 | H7: =F7*G7 -> 0
B8: Total Segment EV (非金融) | H8: =H5+H7 -> 14056813
B10: 679483 | C10: ← Consolidated D&A (input)
B12: EV Composition %
B13: Telecom & Non-Financial (ex-au FH) | C13: =H5/H8 -> 1
B14: (金融セグメントは EV に含まれないため構成比の対象外)
B16: Equity Bridge
B17: Total Enterprise Value | C17: =H8 -> 14056813
B18: Less: Net Debt (非金融、預金・貸出金 除外) | C18: 3060157
B19: 非金融の株主価値 | C19: =C17-C18 -> 10996656
B20: Add: 金融セグメント株主価値 (PBR × 純資産) | C20: =H6 -> 489350.08
B21: SOTP 株主価値 (割引前) | C21: =C19+C20 -> 11486006
B22: Conglomerate Discount | C22: 0.1
B23: Adjusted SOTP 株主価値 (割引後) | C23: =C21*(1-C22) -> 10337405
B24: Less: Minority Interest | C24: 515952
B25: Equity Value (親会社株主帰属) | C25: =C23-C24 -> 9821453.4
B26: Shares Outstanding (thousands) | C26: 3695963
B27: Stock Split Ratio | C27: 1
B28: Fair Value Per Share (post-split) | C28: =C25*1000/C26/C27 -> 2657.3462 | D28: Fair Value = Equity Value (¥M) × 1,000 ÷ Shares (千株) ÷ split. 株数は【千株】単位（dcf_comps_template は【株】単位: 桁が3つ違う）

Sheet Sensitivity
B1: Sensitivity Analysis
B3: Table 1: Telecom & Non-Financial (ex-au FH) Multiple × Conglomerate Discount
B4: Fair Value (¥/share, post-split)
B5: Base Assumptions (do not edit)
B6: Telecom & Non-Financial (ex-au FH) OP | C6: ='SOTP Valuation'!C5 -> 1055926 | D6: ='SOTP Valuation'!E5 -> 679483 | E6: =C6+D6 -> 1735409 | F6: ='SOTP Valuation'!G5 -> 8.1
B7: au Financial Holdings (100% owned) 純資産 | C7: ='SOTP Valuation'!C6 -> 360081 | D7: 0 | E7: =C7+D7 -> 360081 | F7: ='SOTP Valuation'!G6 -> 1.359
B8: Equity Method EV | C8: ='SOTP Valuation'!H7 -> 0
B9: Net Debt | C9: ='SOTP Valuation'!C18 -> 3060157
B10: Minority Interest | C10: ='SOTP Valuation'!C24 -> 515952
B11: Shares (thousands) | C11: ='SOTP Valuation'!C26 -> 3695963
B12: Split Ratio | C12: ='SOTP Valuation'!C27 -> 1
B14: Telecom & Non-Financial (ex-au FH) EV/EBITDA → | C14: 6 | D14: 7 | E14: 8.1 | F14: 9 | G14: 10
B15: 0 | C15: =((($E$6*6+C8)-$C$9+(E7*F7))*(1-$B15)-$C$10)*1000/$C$11/$C$12 -> 1982.0802 | D15: =((($E$6*7+C8)-$C$9+(E7*F7))*(1-$B15)-$C$10)*1000/$C$11/$C$12 -> 2451.622 | E15: =((($E$6*8.1+C8)-$C$9+(E7*F7))*(1-$B15)-$C$10)*1000/$C$11/$C$12 -> 2968.1179 | F15: =((($E$6*9+C8)-$C$9+(E7*F7))*(1-$B15)-$C$10)*1000/$C$11/$C$12 -> 3390.7055 | G15: =((($E$6*10+C8)-$C$9+(E7*F7))*(1-$B15)-$C$10)*1000/$C$11/$C$12 -> 3860.2473
B16: 0.05 | C16: =((($E$6*6+C8)-$C$9+(E7*F7))*(1-$B16)-$C$10)*1000/$C$11/$C$12 -> 1875.9962 | D16: =((($E$6*7+C8)-$C$9+(E7*F7))*(1-$B16)-$C$10)*1000/$C$11/$C$12 -> 2322.0609 | E16: =((($E$6*8.1+C8)-$C$9+(E7*F7))*(1-$B16)-$C$10)*1000/$C$11/$C$12 -> 2812.7321 | F16: =((($E$6*9+C8)-$C$9+(E7*F7))*(1-$B16)-$C$10)*1000/$C$11/$C$12 -> 3214.1903 | G16: =((($E$6*10+C8)-$C$9+(E7*F7))*(1-$B16)-$C$10)*1000/$C$11/$C$12 -> 3660.255
B17: 0.1 | C17: =((($E$6*6+C8)-$C$9+(E7*F7))*(1-$B17)-$C$10)*1000/$C$11/$C$12 -> 1769.9123 | D17: =((($E$6*7+C8)-$C$9+(E7*F7))*(1-$B17)-$C$10)*1000/$C$11/$C$12 -> 2192.4999 | E17: =((($E$6*8.1+C8)-$C$9+(E7*F7))*(1-$B17)-$C$10)*1000/$C$11/$C$12 -> 2657.3462 | F17: =((($E$6*9+C8)-$C$9+(E7*F7))*(1-$B17)-$C$10)*1000/$C$11/$C$12 -> 3037.6751 | G17: =((($E$6*10+C8)-$C$9+(E7*F7))*(1-$B17)-$C$10)*1000/$C$11/$C$12 -> 3460.2627
B18: 0.15 | C18: =((($E$6*6+C8)-$C$9+(E7*F7))*(1-$B18)-$C$10)*1000/$C$11/$C$12 -> 1663.8283 | D18: =((($E$6*7+C8)-$C$9+(E7*F7))*(1-$B18)-$C$10)*1000/$C$11/$C$12 -> 2062.9389 | E18: =((($E$6*8.1+C8)-$C$9+(E7*F7))*(1-$B18)-$C$10)*1000/$C$11/$C$12 -> 2501.9604 | F18: =((($E$6*9+C8)-$C$9+(E7*F7))*(1-$B18)-$C$10)*1000/$C$11/$C$12 -> 2861.1599 | G18: =((($E$6*10+C8)-$C$9+(E7*F7))*(1-$B18)-$C$10)*1000/$C$11/$C$12 -> 3260.2704
B19: 0.2 | C19: =((($E$6*6+C8)-$C$9+(E7*F7))*(1-$B19)-$C$10)*1000/$C$11/$C$12 -> 1557.7444 | D19: =((($E$6*7+C8)-$C$9+(E7*F7))*(1-$B19)-$C$10)*1000/$C$11/$C$12 -> 1933.3778 | E19: =((($E$6*8.1+C8)-$C$9+(E7*F7))*(1-$B19)-$C$10)*1000/$C$11/$C$12 -> 2346.5746 | F19: =((($E$6*9+C8)-$C$9+(E7*F7))*(1-$B19)-$C$10)*1000/$C$11/$C$12 -> 2684.6446 | G19: =((($E$6*10+C8)-$C$9+(E7*F7))*(1-$B19)-$C$10)*1000/$C$11/$C$12 -> 3060.2781
B22: Table 2: Telecom & Non-Financial (ex-au FH) × au Financial Holdings (100% owned) Multiple Sensitivity
B23: Fair Value (¥/share, post-split) — Base discount, base Telecom & Non-Financial (ex-au FH) multiple
B24: Telecom & Non-Financial (ex-au FH) ↓ / au Financial Holdings (100% owned) → | C24: 0.8 | D24: 1 | E24: 1.359 | F24: 1.6 | G24: 2
B25: 6 | C25: =((($E$6*$B25+$C$8)-$C$9+($E$7*C$24))*(1-'SOTP Valuation'!$C$22)-$C$10)*1000/$C$11/$C$12 -> 1720.8975 | D25: =((($E$6*$B25+$C$8)-$C$9+($E$7*D$24))*(1-'SOTP Valuation'!$C$22)-$C$10)*1000/$C$11/$C$12 -> 1738.4341 | E25: =((($E$6*$B25+$C$8)-$C$9+($E$7*E$24))*(1-'SOTP Valuation'!$C$22)-$C$10)*1000/$C$11/$C$12 -> 1769.9123 | F25: =((($E$6*$B25+$C$8)-$C$9+($E$7*F$24))*(1-'SOTP Valuation'!$C$22)-$C$10)*1000/$C$11/$C$12 -> 1791.0439 | G25: =((($E$6*$B25+$C$8)-$C$9+($E$7*G$24))*(1-'SOTP Valuation'!$C$22)-$C$10)*1000/$C$11/$C$12 -> 1826.1171
B26: 7 | C26: =((($E$6*$B26+$C$8)-$C$9+($E$7*C$24))*(1-'SOTP Valuation'!$C$22)-$C$10)*1000/$C$11/$C$12 -> 2143.4851 | D26: =((($E$6*$B26+$C$8)-$C$9+($E$7*D$24))*(1-'SOTP Valuation'!$C$22)-$C$10)*1000/$C$11/$C$12 -> 2161.0217 | E26: =((($E$6*$B26+$C$8)-$C$9+($E$7*E$24))*(1-'SOTP Valuation'!$C$22)-$C$10)*1000/$C$11/$C$12 -> 2192.4999 | F26: =((($E$6*$B26+$C$8)-$C$9+($E$7*F$24))*(1-'SOTP Valuation'!$C$22)-$C$10)*1000/$C$11/$C$12 -> 2213.6315 | G26: =((($E$6*$B26+$C$8)-$C$9+($E$7*G$24))*(1-'SOTP Valuation'!$C$22)-$C$10)*1000/$C$11/$C$12 -> 2248.7047
B27: 8.1 | C27: =((($E$6*$B27+$C$8)-$C$9+($E$7*C$24))*(1-'SOTP Valuation'!$C$22)-$C$10)*1000/$C$11/$C$12 -> 2608.3315 | D27: =((($E$6*$B27+$C$8)-$C$9+($E$7*D$24))*(1-'SOTP Valuation'!$C$22)-$C$10)*1000/$C$11/$C$12 -> 2625.8681 | E27: =((($E$6*$B27+$C$8)-$C$9+($E$7*E$24))*(1-'SOTP Valuation'!$C$22)-$C$10)*1000/$C$11/$C$12 -> 2657.3462 | F27: =((($E$6*$B27+$C$8)-$C$9+($E$7*F$24))*(1-'SOTP Valuation'!$C$22)-$C$10)*1000/$C$11/$C$12 -> 2678.4778 | G27: =((($E$6*$B27+$C$8)-$C$9+($E$7*G$24))*(1-'SOTP Valuation'!$C$22)-$C$10)*1000/$C$11/$C$12 -> 2713.551
B28: 9 | C28: =((($E$6*$B28+$C$8)-$C$9+($E$7*C$24))*(1-'SOTP Valuation'!$C$22)-$C$10)*1000/$C$11/$C$12 -> 2988.6603 | D28: =((($E$6*$B28+$C$8)-$C$9+($E$7*D$24))*(1-'SOTP Valuation'!$C$22)-$C$10)*1000/$C$11/$C$12 -> 3006.1969 | E28: =((($E$6*$B28+$C$8)-$C$9+($E$7*E$24))*(1-'SOTP Valuation'!$C$22)-$C$10)*1000/$C$11/$C$12 -> 3037.6751 | F28: =((($E$6*$B28+$C$8)-$C$9+($E$7*F$24))*(1-'SOTP Valuation'!$C$22)-$C$10)*1000/$C$11/$C$12 -> 3058.8067 | G28: =((($E$6*$B28+$C$8)-$C$9+($E$7*G$24))*(1-'SOTP Valuation'!$C$22)-$C$10)*1000/$C$11/$C$12 -> 3093.8798
B29: 10 | C29: =((($E$6*$B29+$C$8)-$C$9+($E$7*C$24))*(1-'SOTP Valuation'!$C$22)-$C$10)*1000/$C$11/$C$12 -> 3411.2479 | D29: =((($E$6*$B29+$C$8)-$C$9+($E$7*D$24))*(1-'SOTP Valuation'!$C$22)-$C$10)*1000/$C$11/$C$12 -> 3428.7845 | E29: =((($E$6*$B29+$C$8)-$C$9+($E$7*E$24))*(1-'SOTP Valuation'!$C$22)-$C$10)*1000/$C$11/$C$12 -> 3460.2627 | F29: =((($E$6*$B29+$C$8)-$C$9+($E$7*F$24))*(1-'SOTP Valuation'!$C$22)-$C$10)*1000/$C$11/$C$12 -> 3481.3943 | G29: =((($E$6*$B29+$C$8)-$C$9+($E$7*G$24))*(1-'SOTP Valuation'!$C$22)-$C$10)*1000/$C$11/$C$12 -> 3516.4674

Sheet D&A Allocation
B1: D&A Allocation Methodology
B3: セグメント別D&Aは非開示のため、固定資産集約度をもとに按分している。
B4: Segment-level D&A is not disclosed; allocation is estimated from fixed-asset intensity by segment.
B6: Consolidated D&A (FY25E) | C6: 679483 | D6: ¥M (input)
B8: Segment | C8: Allocation % | D8: D&A (¥M) | E8: Check
B9: Telecom & Non-Financial (ex-au FH) | C9: 1 | D9: =$C$6*C9 -> 679483
B10: au Financial Holdings (100% owned) | C10: 0 | D10: =$C$6*C10 -> 0
B11: Total | C11: =C9+C10 -> 1 | D11: =D9+D10 -> 679483 | E11: =IF(ABS(C11-1)<0.001,"OK","CHECK") -> OK
B13: Notes:
B14: • Allocation sums to 100% — residual is implicitly in corporate/eliminations
